Workbook

Sheet base global
A1: 2 | B1: 3 | C1: 4 | D1: 7 | E1: 8 | F1: 9 | G1: 10 | H1: 11 | I1: 12 | J1: 13 | K1: 14 | L1: 15 | M1: 16 | N1: 17 | O1: 18 | P1: 19 | Q1: Unnamed: 16 | R1: 20 | S1: 21 | T1: 22 | U1: Unnamed: 20 | V1: 23 | W1: 24 | X1: 25 | Y1: 26 | Z1: 27 | AA1: 28 | AB1: 29 | AC1: 30 | AD1: 31 | AE1: 32 | AF1: 33 | AG1: 34 | AH1: 35 | AI1: 36 | AJ1: 37 | AK1: 38 | AL1: 39 | AM1: 40 | AN1: 41 | AO1: 42 | AP1: 43 | AQ1: 44 | AR1: 45 | AS1: 46 | AT1: 47 | AU1: 48 | AV1: 49 | AW1: 50 | AX1: 51 | AY1: 52 | AZ1: 53 | BA1: 54 | BB1: 55 | BC1: 56 | BD1: 57 | BE1: 58 | BF1: 59 | BG1: 60 | BH1: 61 | BI1: 62 | BJ1: 63 | BK1: 64 | BL1: 65 | BM1: 66 | BN1: 67 | BO1: 68 | BP1: 69 | BQ1: 70 | BR1: 71 | BS1: 72 | BT1: 73 | BU1: 74 | BV1: 75 | BW1: 76 | BX1: 77 | BY1: 78 | BZ1: 79 | CA1: 80 | CB1: 81 | CC1: 82 | CD1: 83 | CE1: 84 | CF1: 85 | CG1: 86 | CH1: 87 | CI1: 88 | CJ1: 89 | CK1: 90 | CL1: 91 | CM1: 92 | CN1: 93 | CO1: 94 | CP1: 95 | CQ1: 96 | CR1: 97 | CS1: 98 | CT1: 99 | CU1: 100 | CV1: 101 | CW1: 102 | CX1: 103 | CY1: 104 | CZ1: 105 | DA1: 106 | DB1: 107 | DC1: Unnamed: 106 | DD1: Unnamed: 107 | DE1: Unnamed: 108 | DF1: Unnamed: 109 | DG1: Unnamed: 110 | DH1: Unnamed: 111 | DI1: 122 | DJ1: 123 | DK1: 124
I2: AÑOS INTERVENCIÓN | V2: BENEFICIARIOS | BE2: VENTAS HISTORIAL | CP2: VENTAS PORTIPO DE COMPROMABNTE (OBTENIDO SISPAC 2023 DEL REPORTE MATRIZ GENERAL DE VENTAS) | CW2: VENTAS POR TIPO DE COMPROMABNTE año 2024 | DC2: VENTAS POR TIPO DE COMPROMABNTE año 2025 -12.01.26)
V3: 2018 | W3: 2019 | Z3: 2020 | AC3: 2021 | AF3: 2022 | AI3: 2023 | AL3: 2024 | AO3: 2025 (Ciierre de Agosto 2025) | AS3: 2020 | AU3: 2021 | AW3: 2022 | AY3: 2023 | BA3: 2024 | BC3: 2025 (cierre agosto 2025) | BE3: 2018 | BF3: 2019 | BK3: 2020 | BP3: 2021 | BU3: 2022 | BZ3: 2023 | CE3: 2024 | CK3: 2025 (Cierre de 12.01.26) | CP3: 2023 detallado por tipo comprobante
A4: Nombre de la Organización | B4: PRODUCTO DOM | C4: PRODUCTO 1 | D4: SEDE | E4: Ubigeo | F4: DEPARTAMENTO | G4: Provincia | H4: Distrito | I4: 2018 | J4: 2019 | K4: 2020 | L4: 2021 | M4: 2022 | N4: 2023 | O4: 2024 | P4: 2025 | Q4: SERVICIO | R4: AÑOS DE INTERVENCION | S4: AÑOS DE INTERVENCIÓN DESDE 2018 AL 2024 | T4: INTERVENCIÓN 2019 al 2025 | U4: INTERVENCIÓN 2020 al 2026 | V4: TOTAL BENF 2018 | W4: BENF MASC 2019 | X4: BENF FEM 2019 | Y4: TOTAL BENF 2019 | Z4: BENF MASC 2020 | AA4: BENF FEM 2020 | AB4: TOTAL BENF 2020 | AC4: BENF MASC 2021 | AD4: BENF FEM 2021 | AE4: TOTAL BENF 2021 | AF4: BENF MASC 2022 | AG4: BENF FEM 2022 | AH4: TOTAL BENF 2022 | AI4: BENF MASC 2023 | AJ4: BENF FEM 2023 | AK4: TOTAL BENF 2023 | AL4: BENF MASC 2024 | AM4: BENF FEM 2024 | AN4: TOTAL BENF 2024 | AO4: BENF MASC 2025 | AP4: BENF FEM 2025 | AQ4: TOTAL BENF 2025 | AR4: BENEFICIADOS ULTIMO AÑO | AS4: ASISTENCIA TÉCNICA 2020 | AT4: TALLERES 2020 | AU4: ASISTENCIA TÉCNICA 2021 | AV4: TALLERES 2021 | AW4: ASISTENCIA TÉCNICA 2022 | AX4: TALLERES 2022 | AY4: ASISTENCIA TÉCNICA 2023 | AZ4: TALLERES 2023 | BA4: ASISTENCIA TÉCNICA 2024 | BB4: TALLERES 2024 | BC4: ASISTENCIA TÉCNICA 2025 | BD4: TALLERES 2025 | BE4: VENTAS TOTALES 2018 | BF4: VENTAS NACIONALES 2019 | BG4: VENTAS INTERNACIONALES 2019 | BH4: VENTAS TOTALES 2019 | BI4: INCREMENTOS VENTAS EN 2019 | BJ4: INCREMENTOS VENTAS EN 20192 | BK4: VENTAS NACIONALES 2020 | BL4: VENTAS INTERNACIONALES 2020 | BM4: VENTAS TOTALES 2020 | BN4: INCREMENTOS VENTAS EN 2020 | BO4: DIFERENCIA VENTA 2020-2019 | BP4: VENTAS NACIONALES 2021 | BQ4: VENTAS INTERNACIONALES 2021 | BR4: VENTAS TOTALES 2021 | BS4: INCREMENTOS VENTAS EN 20201 | BT4: DIFERENCIA VENTA 2021-2020 | BU4: V. EJEC NACIONALES 2022 | BV4: V. EJEC EXPORTACION 2022 | BW4: VENTAS TOTALES 2022 | BX4: INCREMENTOS VENTAS EN 22022 | BY4: DIFERENCIA VENTAS 2022-2021 | BZ4: V. EJEC NACIONALES 2023 | CA4: V. EJEC EXPORTACION 2023 | CB4: VENTAS TOTALES 2023 | CC4: INCREMENTOS VENTAS EN 2023 | CD4: DIFERENCIA VENTAS 2023-2022 | CE4: V. EJEC NACIONALES 2024 | CF4: V. EJEC EXPORTACION 2024 | CG4: VENTAS TOTALES 2024 | CH4: INCREMENTOS VENTAS EN 2024 | CI4: DIFERENCIA VENTAS 2024-2023 | CJ4: TOTAL VENTAS 2018 AL 2025 | CK4: V. EJEC NACIONALES 2025 | CL4: V. EJEC EXPORTACION 2025 | CM4: VENTAS TOTALES 2025 | CN4: INCREMENTOS VENTAS EN 2025 | CO4: DIFERENCIA VENTAS 2025-2024 | CP4: Boleta de Venta 2023 | CQ4: Declaracion Jurada 2023 | CR4: Documento de Entrega Cooperativo (DEC) 2023 | CS4: Factura 2023 | CT4: Guia de Remision 2023 | CU4: Liquidacion de Compra 2023 | CV4: Total Ventas 2023 (De comprobantes) (*) | CW4: Boleta de Venta 2024 | CX4: Declaración Jurada 2024 | CY4: Factura 2024 | CZ4: Guía de Remisión 2024 | DA4: Liquidación de Compra 2024 | DB4: Total general 2024 | DC4: Boleta de Venta 2025 | DD4: Declaración Jurada 2025 | DE4: Factura 2025 | DF4: Guía de Remisión 2025 | DG4: Liquidación de Compra 2025 | DH4: Total general 2025 | DI4: RUC | DJ4: NOMBRE SUNAT | DK4: Tipo de Organización* (Asociación/Cooperativa/CCNN, Comunidad Campesina y otros.)
A5: Cooperativa Agraria Cafetalera Montaña Azul LTDA. - Coopacma | B5: CAFÉ | C5: CAFÉ | D5: Amazonas | E5: 010706 | F5: Amazonas | G5: Utcubamba | H5: Lonya Grande | I5: 1 | J5: 1 | K5: 1 | Q5: PAC | R5: 2018-2019-2020 | S5: 3 | T5: SI | U5: SI | V5: 106 | W5: 72 | X5: 34 | Y5: 106 | Z5: 68 | AA5: 31 | AB5: 99 | AC5: 0 | AD5: 0 | AE5: 0 | AF5: 0 | AG5: 0 | AH5: 0 | AI5: 0 | AJ5: 0 | AK5: 0 | AL5: 0 | AM5: 0 | AN5: 0 | AO5: 0 | AP5: 0 | AQ5: 0 | AR5: 99 | AS5: 0 | AT5: 9 | AU5: 0 | AV5: 0 | AW5: 0 | AX5: 0 | AY5: 0 | AZ5: 0 | BA5: 0 | BB5: 0 | BC5: 0 | BD5: 0 | BE5: 0 | BF5: 0 | BG5: 83583.84 | BH5: 83583.84 | BI5: #REF! | BJ5: #REF! | BK5: 3460.24 | BL5: 0 | BM5: 3460.24 | BN5: #REF! | BO5: #REF! | BP5: 0 | BQ5: 0 | BR5: 0 | BS5: #REF! | BU5: 0 | BV5: 0 | BW5: 0 | BX5: #REF! | BY5: #REF! | BZ5: 0 | CA5: 0 | CB5: 0 | CC5: #REF! | CD5: 0 | CE5: 0 | CF5: 0 | CG5: 0 | CH5: #REF! | CI5: 0 | CJ5: #REF! | CK5: 0 | CL5: 0 | CM5: 0 | CN5: #REF! | CO5: 0 | CP5: 0 | CQ5: 0 | CR5: 0 | CS5: 0 | CT5: 0 | CU5: 0 | CV5: 0 | CW5: 0 | CX5: 0 | CY5: 0 | CZ5: 0 | DA5: 0 | DB5: 0 | DC5: 0 | DD5: 0 | DE5: 0 | DF5: 0 | DG5: 0 | DH5: 0 | DI5: 20600200756 | DJ5: COOPERATIVA AGRARIA CAFETALERA MONTAÑA AZUL LTDA. - COOPACMA | DK5: 02 Cooperativa
A6: Asociación de Productores de Café Organico y Cafes Especiales -Aprocoyce Amazonas | B6: CAFÉ | C6: CAFÉ | D6: Amazonas | E6: 010601 | F6: Amazonas | G6: Rodriguez de Mendoza | H6: San Nicolas | J6: 1 | K6: 1 | L6: 1 | M6: 1 | N6: 1 | Q6: PAC | R6: 2019-2020-2021-2022-2023 | S6: 5 | T6: SI | U6: SI | V6: 0 | W6: 50 | X6: 33 | Y6: 83 | Z6: 222 | AA6: 135 | AB6: 357 | AC6: 208 | AD6: 150 | AE6: 358 | AF6: 208 | AG6: 150 | AH6: 358 | AI6: 208 | AJ6: 150 | AK6: 358 | AL6: 0 | AM6: 0 | AN6: 0 | AO6: 0 | AP6: 0 | AQ6: 0 | AR6: 358 | AS6: 0 | AT6: 0 | AU6: 27 | AV6: 8 | AW6: 41 | AX6: 7 | AY6: 32 | AZ6: 6 | BA6: 0 | BB6: 0 | BC6: 0 | BD6: 0 | BE6: 0 | BF6: 4171009.2 | BG6: 0 | BH6: 4171009.2 | BI6: #REF! | BJ6: #REF! | BK6: 741888.91 | BL6: 0 | BM6: 741888.91 | BN6: #REF! | BO6: #REF! | BP6: 4099294.7 | BQ6: 0 | BR6: 4099294.7 | BS6: #REF! | BU6: 1820885 | BV6: 0 | BW6: 1820885 | BX6: #REF! | BY6: #REF! | BZ6: 4179472.3 | CA6: 0 | CB6: 4179472.3 | CC6: #REF! | CD6: -1820885 | CE6: 0 | CF6: 0 | CG6: 0 | CH6: #REF! | CI6: -4179472.3 | CJ6: #REF! | CK6: 0 | CL6: 0 | CM6: 0 | CN6: #REF! | CO6: 0 | CP6: 0 | CQ6: 0 | CR6: 0 | CS6: 4179472.3 | CT6: 0 | CU6: 0 | CV6: 4179472.3 | CW6: 0 | CX6: 0 | CY6: 0 | CZ6: 0 | DA6: 0 | DB6: 0 | DC6: 0 | DD6: 0 | DE6: 0 | DF6: 0 | DG6: 0 | DH6: 0 | DI6: 20539241665 | DJ6: ASOCIACION DE PRODUCTORES DE CAFES ORGANICOS Y CAFES ESPECIALES DE AMAZONAS | DK6: 01 Asociación
A7: Asociación de Productores y Exportadores de Café Rodriguez de Mendoza-Aproexport | B7: CAFÉ | C7: CAFÉ | D7: Amazonas | E7: 010601 | F7: Amazonas | G7: Rodriguez de Mendoza | H7: San Nicolas | J7: 1 | Q7: PAC | R7: 2019 | S7: 1 | T7: SI | U7: NO | V7: 0 | W7: 231 | X7: 149 | Y7: 380 | Z7: 0 | AA7: 0 | AB7: 0 | AC7: 0 | AD7: 0 | AE7: 0 | AF7: 0 | AG7: 0 | AH7: 0 | AI7: 0 | AJ7: 0 | AK7: 0 | AL7: 0 | AM7: 0 | AN7: 0 | AO7: 0 | AP7: 0 | AQ7: 0 | AR7: 380 | AS7: 0 | AT7: 0 | AU7: 0 | AV7: 0 | AW7: 0 | AX7: 0 | AY7: 0 | AZ7: 0 | BA7: 0 | BB7: 0 | BC7: 0 | BD7: 0 | BE7: 0 | BF7: 0 | BG7: 0 | BH7: 0 | BI7: #REF! | BJ7: #REF! | BK7: 0 | BL7: 0 | BM7: 0 | BN7: #REF! | BO7: #REF! | BP7: 0 | BQ7: 0 | BR7: 0 | BS7: #REF! | BU7: 0 | BV7: 0 | BW7: 0 | BX7: #REF! | BY7: #REF! | BZ7: 0 | CA7: 0 | CB7: 0 | CC7: #REF! | CD7: 0 | CE7: 0 | CF7: 0 | CG7: 0 | CH7: #REF! | CI7: 0 | CJ7: #REF! | CK7: 0 | CL7: 0 | CM7: 0 | CN7: #REF! | CO7: 0 | CP7: 0 | CQ7: 0 | CR7: 0 | CS7: 0 | CT7: 0 | CU7: 0 | CV7: 0 | CW7: 0 | CX7: 0 | CY7: 0 | CZ7: 0 | DA7: 0 | DB7: 0 | DC7: 0 | DD7: 0 | DE7: 0 | DF7: 0 | DG7: 0 | DH7: 0 | DI7: 20539205600 | DJ7: ASOCIACION DE PRODUCTORES Y EXPORTADORES DE CAFE RODRIGUEZ DE MENDOZA | DK7: 01 Asociación
A8: Cooperativa Agraria Cafetalera Alta Montaña | B8: CAFÉ | C8: CAFÉ | D8: Amazonas | E8: 010604 | F8: Amazonas | G8: Rodriguez de Mendoza | H8: Huambo | I8: 1 | J8: 1 | K8: 1 | L8: 1 | M8: 1 | N8: 1 | Q8: PAC | R8: 2018-2019-2020-2021-2022-2023 | S8: 6 | T8: SI | U8: SI | V8: 150 | W8: 0 | X8: 0 | Y8: 0 | Z8: 108 | AA8: 42 | AB8: 150 | AC8: 205 | AD8: 119 | AE8: 324 | AF8: 205 | AG8: 119 | AH8: 324 | AI8: 205 | AJ8: 119 | AK8: 324 | AL8: 0 | AM8: 0 | AN8: 0 | AO8: 0 | AP8: 0 | AQ8: 0 | AR8: 324 | AS8: 0 | AT8: 0 | AU8: 25 | AV8: 9 | AW8: 41 | AX8: 7 | AY8: 32 | AZ8: 6 | BA8: 0 | BB8: 0 | BC8: 0 | BD8: 0 | BE8: 0 | BF8: 409100 | BG8: 0 | BH8: 409100 | BI8: #REF! | BJ8: #REF! | BK8: 325000 | BL8: 0 | BM8: 325000 | BN8: #REF! | BO8: #REF! | BP8: 1224192.5 | BQ8: 398235.92 | BR8: 1622428.4 | BS8: #REF! | BU8: 820950 | BV8: 0 | BW8: 820950 | BX8: #REF! | BY8: #REF! | BZ8: 165821.2 | CA8: 0 | CB8: 165821.2 | CC8: #REF! | CD8: -820950 | CE8: 0 | CF8: 0 | CG8: 0 | CH8: #REF! | CI8: -165821.2 | CJ8: #REF! | CK8: 0 | CL8: 0 | CM8: 0 | CN8: #REF! | CO8: 0 | CP8: 9793.4 | CQ8: 0 | CR8: 0 | CS8: 156027.8 | CT8: 0 | CU8: 0 | CV8: 165821.2 | CW8: 0 | CX8: 0 | CY8: 0 | CZ8: 0 | DA8: 0 | DB8: 0 | DC8: 0 | DD8: 0 | DE8: 0 | DF8: 0 | DG8: 0 | DH8: 0 | DI8: 20603320621 | DJ8: COOPERATIVA AGRARIA CAFETALERA ALTA MONTAÑA | DK8: 02 Cooperativa
A9: Asociacion de Productores Agropecuarios la Flor de Café | B9: CAFÉ | C9: CAFÉ | D9: Amazonas | E9: 010601 | F9: Amazonas | G9: Rodriguez de Mendoza | H9: San Nicolas | J9: 1 | K9: 1 | L9: 1 | M9: 1 | N9: 1 | Q9: PAC | R9: 2019-2020-2021-2022-2023 | S9: 5 | T9: SI | U9: SI | V9: 0 | W9: 210 | X9: 113 | Y9: 323 | Z9: 210 | AA9: 113 | AB9: 323 | AC9: 274 | AD9: 137 | AE9: 411 | AF9: 274 | AG9: 137 | AH9: 411 | AI9: 274 | AJ9: 137 | AK9: 411 | AL9: 0 | AM9: 0 | AN9: 0 | AO9: 0 | AP9: 0 | AQ9: 0 | AR9: 411 | AS9: 0 | AT9: 0 | AU9: 26 | AV9: 8 | AW9: 43 | AX9: 7 | AY9: 32 | AZ9: 6 | BA9: 0 | BB9: 0 | BC9: 0 | BD9: 0 | BE9: 0 | BF9: 6041471.5 | BG9: 0 | BH9: 6041471.5 | BI9: #REF! | BJ9: #REF! | BK9: 523737.39 | BL9: 0 | BM9: 523737.39 | BN9: #REF! | BO9: #REF! | BP9: 3394807.7 | BQ9: 0 | BR9: 3394807.7 | BS9: #REF! | BU9: 4076542 | BV9: 446118 | BW9: 4522660 | BX9: #REF! | BY9: #REF! | BZ9: 5733612.8 | CA9: 984023.42 | CB9: 6717636.2 | CC9: #REF! | CD9: -4522660 | CE9: 0 | CF9: 0 | CG9: 0 | CH9: #REF! | CI9: -6717636.2 | CJ9: #REF! | CK9: 0 | CL9: 0 | CM9: 0 | CN9: #REF! | CO9: 0 | CP9: 0 | CQ9: 0 | CR9: 0 | CS9: 6717636.2 | CT9: 0 | CU9: 0 | CV9: 6717636.2 | CW9: 0 | CX9: 0 | CY9: 0 | CZ9: 0 | DA9: 0 | DB9: 0 | DC9: 0 | DD9: 0 | DE9: 0 | DF9: 0 | DG9: 0 | DH9: 0 | DI9: 20480762895 | DJ9: ASOCIACION DE PRODUCTORES AGROPECUARIOS LA FLOR DE CAFÉ | DK9: 01 Asociación
A10: Cooperativa de Servicios Multiples - APROCAM | B10: CACAO | C10: CACAO | D10: Amazonas | E10: 010201 | F10: Amazonas | G10: Bagua | H10: Bagua | I10: 1 | J10: 1 | K10: 1 | L10: 1 | M10: 1 | N10: 1 | Q10: PAC | R10: 2018-2019-2020-2021-2022-2023 | S10: 6 | T10: SI | U10: SI | V10: 418 | W10: 353 | X10: 65 | Y10: 418 | Z10: 357 | AA10: 66 | AB10: 423 | AC10: 201 | AD10: 43 | AE10: 244 | AF10: 201 | AG10: 43 | AH10: 244 | AI10: 201 | AJ10: 43 | AK10: 244 | AL10: 0 | AM10: 0 | AN10: 0 | AO10: 0 | AP10: 0 | AQ10: 0 | AR10: 244 | AS10: 0 | AT10: 0 | AU10: 35 | AV10: 7 | AW10: 32 | AX10: 5 | AY10: 39 | AZ10: 7 | BA10: 0 | BB10: 0 | BC10: 0 | BD10: 0 | BE10: 279033.24 | BF10: 0 | BG10: 1026216.8 | BH10: 1026216.8 | BI10: #REF! | BJ10: #REF! | BK10: 101917.7 | BL10: 284025.07 | BM10: 385942.77 | BN10: #REF! | BO10: #REF! | BP10: 78859.15 | BQ10: 2033180.4 | BR10: 2112039.5 | BS10: #REF! | BU10: 65644.73 | BV10: 1189543.9 | BW10: 1255188.6 | BX10: #REF! | BY10: #REF! | BZ10: 114467.98 | CA10: 1092156.7 | CB10: 1206624.7 | CC10: #REF! | CD10: -1255188.6 | CE10: 0 | CF10: 0 | CG10: 0 | CH10: #REF! | CI10: -1206624.7 | CJ10: #REF! | CK10: 0 | CL10: 0 | CM10: 0 | CN10: #REF! | CO10: 0 | CP10: 34067.084 | CQ10: 0 | CR10: 0 | CS10: 1172557.6 | CT10: 0 | CU10: 0 | CV10: 1206624.7 | CW10: 0 | CX10: 0 | CY10: 0 | CZ10: 0 | DA10: 0 | DB10: 0 | DC10: 0 | DD10: 0 | DE10: 0 | DF10: 0 | DG10: 0 | DH10: 0 | DI10: 20480458550 | DJ10: COOPERATIVA AGRARIA APROCAM | DK10: 02 Cooperativa
A11: Cooperativa Central de Productores Agropecuarios de Amazonas - CEPROAA | B11: CACAO | C11: CACAO | D11: Amazonas | E11: 010702 | F11: Amazonas | G11: Utcubamba | H11: Cajaruro | I11: 1 | J11: 1 | K11: 1 | L11: 1 | M11: 1 | N11: 1 | Q11: PAC | R11: 2018-2019-2020-2021-2022-2023 | S11: 6 | T11: SI | U11: SI | V11: 344 | W11: 272 | X11: 71 | Y11: 343 | Z11: 266 | AA11: 71 | AB11: 337 | AC11: 271 | AD11: 71 | AE11: 342 | AF11: 271 | AG11: 71 | AH11: 342 | AI11: 271 | AJ11: 71 | AK11: 342 | AL11: 0 | AM11: 0 | AN11: 0 | AO11: 0 | AP11: 0 | AQ11: 0 | AR11: 342 | AS11: 0 | AT11: 0 | AU11: 24 | AV11: 7 | AW11: 28 | AX11: 7 | AY11: 39 | AZ11: 6 | BA11: 0 | BB11: 0 | BC11: 0 | BD11: 0 | BE11: 0 | BF11: 0 | BG11: 1072102.3 | BH11: 1072102.3 | BI11: #REF! | BJ11: #REF! | BK11: 454472.63 | BL11: 0 | BM11: 454472.63 | BN11: #REF! | BO11: #REF! | BP11: 1609560.4 | BQ11: 0 | BR11: 1609560.4 | BS11: #REF! | BU11: 1731876.8 | BV11: 0 | BW11: 1731876.8 | BX11: #REF! | BY11: #REF! | BZ11: 1545263.1 | CA11: 0 | CB11: 1545263.1 | CC11: #REF! | CD11: -1731876.8 | CE11: 0 | CF11: 0 | CG11: 0 | CH11: #REF! | CI11: -1545263.1 | CJ11: #REF! | CK11: 0 | CL11: 0 | CM11: 0 | CN11: #REF! | CO11: 0 | CP11: 9912.9964 | CQ11: 0 | CR11: 820166.58 | CS11: 715183.52 | CT11: 0 | CU11: 0 | CV11: 1545263.1 | CW11: 0 | CX11: 0 | CY11: 0 | CZ11: 0 | DA11: 0 | DB11: 0 | DC11: 0 | DD11: 0 | DE11: 0 | DF11: 0 | DG11: 0 | DH11: 0 | DI11: 20479917141 | DJ11: COOPERATIVA AGRARIA CENTRAL DE PRODUCTORES DE AMAZONAS | DK11: 02 Cooperativa
A12: Asociacion de Productores Agropecuarios Luis Solibarria | B12: CACAO | C12: CACAO | D12: Amazonas | E12: 010701 | F12: Amazonas | G12: Utcubamba | H12: Bagua Grande | I12: 1 | J12: 1 | Q12: PAC | R12: 2018-2019 | S12: 2 | T12: SI | U12: NO | V12: 147 | W12: 120 | X12: 25 | Y12: 145 | Z12: 0 | AA12: 0 | AB12: 0 | AC12: 0 | AD12: 0 | AE12: 0 | AF12: 0 | AG12: 0 | AH12: 0 | AI12: 0 | AJ12: 0 | AK12: 0 | AL12: 0 | AM12: 0 | AN12: 0 | AO12: 0 | AP12: 0 | AQ12: 0 | AR12: 145 | AS12: 0 | AT12: 0 | AU12: 0 | AV12: 0 | AW12: 0 | AX12: 0 | AY12: 0 | AZ12: 0 | BA12: 0 | BB12: 0 | BC12: 0 | BD12: 0 | BE12: 0 | BF12: 0 | BG12: 0 | BH12: 0 | BI12: #REF! | BJ12: #REF! | BK12: 0 | BL12: 0 | BM12: 0 | BN12: #REF! | BO12: #REF! | BP12: 0 | BQ12: 0 | BR12: 0 | BS12: #REF! | BU12: 0 | BV12: 0 | BW12: 0 | BX12: #REF! | BY12: #REF! | BZ12: 0 | CA12: 0 | CB12: 0 | CC12: #REF! | CD12: 0 | CE12: 0 | CF12: 0 | CG12: 0 | CH12: #REF! | CI12: 0 | CJ12: #REF! | CK12: 0 | CL12: 0 | CM12: 0 | CN12: #REF! | CO12: 0 | CP12: 0 | CQ12: 0 | CR12: 0 | CS12: 0 | CT12: 0 | CU12: 0 | CV12: 0 | CW12: 0 | CX12: 0 | CY12: 0 | CZ12: 0 | DA12: 0 | DB12: 0 | DC12: 0 | DD12: 0 | DE12: 0 | DF12: 0 | DG12: 0 | DH12: 0 | DI12: 20479856258 | DJ12: ASOCIACION DE PRODUCTORES AGROPECUARIOS LUIS SOLIBARRIA | DK12: 01 Asociación
A13: Cooperativa Agraria Cafetalera Bagua Grande LTDA | B13: CAFÉ | C13: CAFÉ | D13: Amazonas | E13: 010701 | F13: Amazonas | G13: Utcubamba | H13: Bagua Grande | I13: 1 | J13: 1 | K13: 1 | N13: 1 | O13: 1 | Q13: PAC | R13: 2018-2019-2020-2023-2024 | S13: 5 | T13: SI | U13: SI | V13: 592 | W13: 498 | X13: 91 | Y13: 589 | Z13: 296 | AA13: 58 | AB13: 354 | AC13: 0 | AD13: 0 | AE13: 0 | AF13: 0 | AG13: 0 | AH13: 0 | AI13: 596 | AJ13: 94 | AK13: 690 | AL13: 263 | AM13: 46 | AN13: 309 | AO13: 0 | AP13: 0 | AQ13: 0 | AR13: 309 | AS13: 0 | AT13: 9 | AU13: 0 | AV13: 0 | AW13: 0 | AX13: 0 | AY13: 45 | AZ13: 6 | BA13: 30 | BB13: 5 | BC13: 0 | BD13: 0 | BE13: 448800 | BF13: 0 | BG13: 1768356.9 | BH13: 1768356.9 | BI13: #REF! | BJ13: #REF! | BK13: 443003.7 | BL13: 1384395.9 | BM13: 1827399.6 | BN13: #REF! | BO13: #REF! | BP13: 0 | BQ13: 0 | BR13: 0 | BS13: #REF! | BU13: 0 | BV13: 0 | BW13: 0 | BX13: #REF! | BY13: #REF! | BZ13: 0 | CA13: 5910875.3 | CB13: 5910875.3 | CC13: #REF! | CD13: 0 | CE13: 264948.69 | CF13: 8889133.3 | CG13: 9154082 | CH13: #REF! | CI13: -5910875.3 | CJ13: #REF! | CK13: 0 | CL13: 0 | CM13: 0 | CN13: #REF! | CO13: -9154082 | CP13: 0 | CQ13: 0 | CR13: 0 | CS13: 5910875.3 | CT13: 0 | CU13: 0 | CV13: 5910875.3 | CW13: 0 | CX13: 0 | CY13: 9154082 | CZ13: 0 | DA13: 0 | DB13: 9154082 | DC13: 0 | DD13: 0 | DE13: 0 | DF13: 0 | DG13: 0 | DH13: 0 | DI13: 20170142773 | DJ13: COOPERATIVA AGRARIA CAFETALERA BAGUA GRANDE LIMITADA | DK13: 02 Cooperativa
A14: Asociacion de Productores Agropecuarios Valle Verde de Rodriguez de Mendoza | B14: CAFÉ | C14: CAFÉ | D14: Amazonas | E14: 010601 | F14: Amazonas | G14: Rodriguez de Mendoza | H14: San Nicolas | I14: 1 | J14: 1 | Q14: PAC | R14: 2018-2019 | S14: 2 | T14: SI | U14: NO | V14: 427 | W14: 0 | X14: 0 | Y14: 0 | Z14: 0 | AA14: 0 | AB14: 0 | AC14: 0 | AD14: 0 | AE14: 0 | AF14: 0 | AG14: 0 | AH14: 0 | AI14: 0 | AJ14: 0 | AK14: 0 | AL14: 0 | AM14: 0 | AN14: 0 | AO14: 0 | AP14: 0 | AQ14: 0 | AR14: 427 | AS14: 0 | AT14: 0 | AU14: 0 | AV14: 0 | AW14: 0 | AX14: 0 | AY14: 0 | AZ14: 0 | BA14: 0 | BB14: 0 | BC14: 0 | BD14: 0 | BE14: 0 | BF14: 0 | BG14: 0 | BH14: 0 | BI14: #REF! | BJ14: #REF! | BK14: 0 | BL14: 0 | BM14: 0 | BN14: #REF! | BO14: #REF! | BP14: 0 | BQ14: 0 | BR14: 0 | BS14: #REF! | BU14: 0 | BV14: 0 | BW14: 0 | BX14: #REF! | BY14: #REF! | BZ14: 0 | CA14: 0 | CB14: 0 | CC14: #REF! | CD14: 0 | CE14: 0 | CF14: 0 | CG14: 0 | CH14: #REF! | CI14: 0 | CJ14: #REF! | CK14: 0 | CL14: 0 | CM14: 0 | CN14: #REF! | CO14: 0 | CP14: 0 | CQ14: 0 | CR14: 0 | CS14: 0 | CT14: 0 | CU14: 0 | CV14: 0 | CW14: 0 | CX14: 0 | CY14: 0 | CZ14: 0 | DA14: 0 | DB14: 0 | DC14: 0 | DD14: 0 | DE14: 0 | DF14: 0 | DG14: 0 | DH14: 0 | DI14: 20600682386 | DJ14: ASOCIACION DE PRODUCTORES AGROPECUARIOS VALLE VERDE DE RODRIGUEZ DE MENDOZA | DK14: 01 Asociación
A15: Asociacion de Productores Agropecuarios Luis Solibarria | B15: CACAO | C15: CACAO | D15: Amazonas | E15: 010701 | F15: Amazonas | G15: Utcubamba | H15: Bagua Grande | L15: 1 | M15: 1 | Q15: PAC | R15: 2021-2022 | S15: 2 | T15: SI | U15: SI | V15: 0 | W15: 0 | X15: 0 | Y15: 0 | Z15: 0 | AA15: 0 | AB15: 0 | AC15: 121 | AD15: 25 | AE15: 146 | AF15: 121 | AG15: 25 | AH15: 146 | AI15: 0 | AJ15: 0 | AK15: 0 | AL15: 0 | AM15: 0 | AN15: 0 | AO15: 0 | AP15: 0 | AQ15: 0 | AR15: 146 | AS15: 0 | AT15: 0 | AU15: 16 | AV15: 2 | AW15: 23 | AX15: 6 | AY15: 0 | AZ15: 0 | BA15: 0 | BB15: 0 | BC15: 0 | BD15: 0 | BE15: 0 | BF15: 0 | BG15: 0 | BH15: 0 | BI15: #REF! | BJ15: #REF! | BK15: 0 | BL15: 0 | BM15: 0 | BN15: #REF! | BO15: #REF! | BP15: 0 | BQ15: 0 | BR15: 0 | BS15: #REF! | BU15: 0 | BV15: 0 | BW15: 0 | BX15: #REF! | BY15: #REF! | BZ15: 0 | CA15: 0 | CB15: 0 | CC15: #REF! | CD15: 0 | CE15: 0 | CF15: 0 | CG15: 0 | CH15: #REF! | CI15: 0 | CJ15: #REF! | CK15: 0 | CL15: 0 | CM15: 0 | CN15: #REF! | CO15: 0 | CP15: 0 | CQ15: 0 | CR15: 0 | CS15: 0 | CT15: 0 | CU15: 0 | CV15: 0 | CW15: 0 | CX15: 0 | CY15: 0 | CZ15: 0 | DA15: 0 | DB15: 0 | DC15: 0 | DD15: 0 | DE15: 0 | DF15: 0 | DG15: 0 | DH15: 0 | DI15: 20479856258 | DJ15: ASOCIACION DE PRODUCTORES AGROPECUARIOS LUIS SOLIBARRIA | DK15: 01 Asociación
A16: Cooperativa Agraria Cafetalera Productora Comercial Exportadora Cafe Andes Amazonicos LTDA | B16: CAFÉ | C16: CAFÉ | D16: Amazonas | E16: 010706 | F16: Amazonas | G16: Utcubamba | H16: Lonya Grande | L16: 1 | M16: 1 | Q16: PAC | R16: 2021-2022 | S16: 2 | T16: SI | U16: SI | V16: 0 | W16: 0 | X16: 0 | Y16: 0 | Z16: 0 | AA16: 0 | AB16: 0 | AC16: 179 | AD16: 45 | AE16: 224 | AF16: 179 | AG16: 45 | AH16: 224 | AI16: 0 | AJ16: 0 | AK16: 0 | AL16: 0 | AM16: 0 | AN16: 0 | AO16: 0 | AP16: 0 | AQ16: 0 | AR16: 224 | AS16: 0 | AT16: 0 | AU16: 12 | AV16: 8 | AW16: 54 | AX16: 8 | AY16: 0 | AZ16: 0 | BA16: 0 | BB16: 0 | BC16: 0 | BD16: 0 | BE16: 0 | BF16: 0 | BG16: 0 | BH16: 0 | BI16: #REF! | BJ16: #REF! | BK16: 0 | BL16: 0 | BM16: 0 | BN16: #REF! | BO16: #REF! | BP16: 250823.36 | BQ16: 0 | BR16: 250823.36 | BS16: #REF! | BU16: 0 | BV16: 0 | BW16: 0 | BX16: #REF! | BY16: #REF! | BZ16: 0 | CA16: 0 | CB16: 0 | CC16: #REF! | CD16: 0 | CE16: 0 | CF16: 0 | CG16: 0 | CH16: #REF! | CI16: 0 | CJ16: #REF! | CK16: 0 | CL16: 0 | CM16: 0 | CN16: #REF! | CO16: 0 | CP16: 0 | CQ16: 0 | CR16: 0 | CS16: 0 | CT16: 0 | CU16: 0 | CV16: 0 | CW16: 0 | CX16: 0 | CY16: 0 | CZ16: 0 | DA16: 0 | DB16: 0 | DC16: 0 | DD16: 0 | DE16: 0 | DF16: 0 | DG16: 0 | DH16: 0 | DI16: 20600001109 | DJ16: COOPERATIVA AGRARIA CAFETALERA PRODUCTORA COMERCIAL EXPORTADORA CAFE ANDES AMAZONICOS LTDA | DK16: 02 Cooperativa
A17: Cooperativa de Servicios Multiples Juan Marco el Palto | B17: CAFÉ | C17: CAFÉ | D17: Amazonas | E17: 010706 | F17: Amazonas | G17: Utcubamba | H17: Lonya Grande | L17: 1 | M17: 1 | N17: 1 | Q17: PAC | R17: 2021-2022-2023 | S17: 3 | T17: SI | U17: SI | V17: 0 | W17: 0 | X17: 0 | Y17: 0 | Z17: 0 | AA17: 0 | AB17: 0 | AC17: 224 | AD17: 68 | AE17: 292 | AF17: 224 | AG17: 68 | AH17: 292 | AI17: 224 | AJ17: 68 | AK17: 292 | AL17: 0 | AM17: 0 | AN17: 0 | AO17: 0 | AP17: 0 | AQ17: 0 | AR17: 292 | AS17: 0 | AT17: 0 | AU17: 10 | AV17: 8 | AW17: 60 | AX17: 8 | AY17: 44 | AZ17: 6 | BA17: 0 | BB17: 0 | BC17: 0 | BD17: 0 | BE17: 0 | BF17: 0 | BG17: 0 | BH17: 0 | BI17: #REF! | BJ17: #REF! | BK17: 0 | BL17: 0 | BM17: 0 | BN17: #REF! | BO17: #REF! | BP17: 0 | BQ17: 1177220.5 | BR17: 1177220.5 | BS17: #REF! | BU17: 117797.43 | BV17: 3107691.5 | BW17: 3225488.9 | BX17: #REF! | BY17: #REF! | BZ17: 45403.05 | CA17: 3044784.1 | CB17: 3090187.2 | CC17: #REF! | CD17: -3225488.9 | CE17: 0 | CF17: 0 | CG17: 0 | CH17: #REF! | CI17: -3090187.2 | CJ17: #REF! | CK17: 0 | CL17: 0 | CM17: 0 | CN17: #REF! | CO17: 0 | CP17: 0 | CQ17: 0 | CR17: 0 | CS17: 3090187.2 | CT17: 0 | CU17: 0 | CV17: 3090187.2 | CW17: 0 | CX17: 0 | CY17: 0 | CZ17: 0 | DA17: 0 | DB17: 0 | DC17: 0 | DD17: 0 | DE17: 0 | DF17: 0 | DG17: 0 | DH17: 0 | DI17: 20479622699 | DJ17: COOPERATIVA AGRARIA JUAN MARCO EL PALTO | DK17: 02 Cooperativa
A18: Sedir-Servicio para el Desarrollo Integral Rural | B18: PALTA | C18: PALTA | D18: Ancash | E18: 021805 | F18: Ancash | G18: Santa | H18: Moro | I18: 1 | Q18: PAC | R18: 2018 | S18: 1 | T18: NO | U18: NO | V18: 34 | W18: 0 | X18: 0 | Y18: 0 | Z18: 0 | AA18: 0 | AB18: 0 | AC18: 0 | AD18: 0 | AE18: 0 | AF18: 0 | AG18: 0 | AH18: 0 | AI18: 0 | AJ18: 0 | AK18: 0 | AL18: 0 | AM18: 0 | AN18: 0 | AO18: 0 | AP18: 0 | AQ18: 0 | AR18: 34 | AS18: 0 | AT18: 0 | AU18: 0 | AV18: 0 | AW18: 0 | AX18: 0 | AY18: 0 | AZ18: 0 | BA18: 0 | BB18: 0 | BC18: 0 | BD18: 0 | BE18: 0 | BF18: 0 | BG18: 0 | BH18: 0 | BI18: #REF! | BJ18: #REF! | BK18: 0 | BL18: 0 | BM18: 0 | BN18: #REF! | BO18: #REF! | BP18: 0 | BQ18: 0 | BR18: 0 | BS18: #REF! | BU18: 0 | BV18: 0 | BW18: 0 | BX18: #REF! | BY18: #REF! | BZ18: 0 | CA18: 0 | CB18: 0 | CC18: #REF! | CD18: 0 | CE18: 0 | CF18: 0 | CG18: 0 | CH18: #REF! | CI18: 0 | CJ18: #REF! | CK18: 0 | CL18: 0 | CM18: 0 | CN18: #REF! | CO18: 0 | CP18: 0 | CQ18: 0 | CR18: 0 | CS18: 0 | CT18: 0 | CU18: 0 | CV18: 0 | CW18: 0 | CX18: 0 | CY18: 0 | CZ18: 0 | DA18: 0 | DB18: 0 | DC18: 0 | DD18: 0 | DE18: 0 | DF18: 0 | DG18: 0 | DH18: 0 | DI18: 20541732706 | DJ18: SERVICIO PARA EL DESARROLLO INTEGRAL RURAL | DK18: 01 Asociación
A19: Asociacion de Productores de Manzano Organico de Pariacoto | B19: MANZANA | C19: MANZANA | D19: Ancash | E19: 020110 | F19: Ancash | G19: Huaraz | H19: Pariacoto | I19: 1 | Q19: PAC | R19: 2018 | S19: 1 | T19: NO | U19: NO | V19: 15 | W19: 0 | X19: 0 | Y19: 0 | Z19: 0 | AA19: 0 | AB19: 0 | AC19: 0 | AD19: 0 | AE19: 0 | AF19: 0 | AG19: 0 | AH19: 0 | AI19: 0 | AJ19: 0 | AK19: 0 | AL19: 0 | AM19: 0 | AN19: 0 | AO19: 0 | AP19: 0 | AQ19: 0 | AR19: 15 | AS19: 0 | AT19: 0 | AU19: 0 | AV19: 0 | AW19: 0 | AX19: 0 | AY19: 0 | AZ19: 0 | BA19: 0 | BB19: 0 | BC19: 0 | BD19: 0 | BE19: 0 | BF19: 0 | BG19: 0 | BH19: 0 | BI19: #REF! | BJ19: #REF! | BK19: 0 | BL19: 0 | BM19: 0 | BN19: #REF! | BO19: #REF! | BP19: 0 | BQ19: 0 | BR19: 0 | BS19: #REF! | BU19: 0 | BV19: 0 | BW19: 0 | BX19: #REF! | BY19: #REF! | BZ19: 0 | CA19: 0 | CB19: 0 | CC19: #REF! | CD19: 0 | CE19: 0 | CF19: 0 | CG19: 0 | CH19: #REF! | CI19: 0 | CJ19: #REF! | CK19: 0 | CL19: 0 | CM19: 0 | CN19: #REF! | CO19: 0 | CP19: 0 | CQ19: 0 | CR19: 0 | CS19: 0 | CT19: 0 | CU19: 0 | CV19: 0 | CW19: 0 | CX19: 0 | CY19: 0 | CZ19: 0 | DA19: 0 | DB19: 0 | DC19: 0 | DD19: 0 | DE19: 0 | DF19: 0 | DG19: 0 | DH19: 0 | DI19: 20600862074 | DJ19: ASOCIACIÓN DE PRODUCTORES DE MANZANO ORGANICO DEL DISTRITO DE PARIACOTO | DK19: 01 Asociación
A20: Asociacion de Productores Ecologicos Agrarios del Distrito de Quiches | B20: ROMERO | C20: ROMERO | D20: Ancash | E20: 021901 | F20: Ancash | G20: Sihuas | H20: Sihuas | I20: 1 | Q20: PAC | R20: 2018 | S20: 1 | T20: NO | U20: NO | V20: 82 | W20: 0 | X20: 0 | Y20: 0 | Z20: 0 | AA20: 0 | AB20: 0 | AC20: 0 | AD20: 0 | AE20: 0 | AF20: 0 | AG20: 0 | AH20: 0 | AI20: 0 | AJ20: 0 | AK20: 0 | AL20: 0 | AM20: 0 | AN20: 0 | AO20: 0 | AP20: 0 | AQ20: 0 | AR20: 82 | AS20: 0 | AT20: 0 | AU20: 0 | AV20: 0 | AW20: 0 | AX20: 0 | AY20: 0 | AZ20: 0 | BA20: 0 | BB20: 0 | BC20: 0 | BD20: 0 | BE20: 0 | BF20: 0 | BG20: 0 | BH20: 0 | BI20: #REF! | BJ20: #REF! | BK20: 0 | BL20: 0 | BM20: 0 | BN20: #REF! | BO20: #REF! | BP20: 0 | BQ20: 0 | BR20: 0 | BS20: #REF! | BU20: 0 | BV20: 0 | BW20: 0 | BX20: #REF! | BY20: #REF! | BZ20: 0 | CA20: 0 | CB20: 0 | CC20: #REF! | CD20: 0 | CE20: 0 | CF20: 0 | CG20: 0 | CH20: #REF! | CI20: 0 | CJ20: #REF! | CK20: 0 | CL20: 0 | CM20: 0 | CN20: #REF! | CO20: 0 | CP20: 0 | CQ20: 0 | CR20: 0 | CS20: 0 | CT20: 0 | CU20: 0 | CV20: 0 | CW20: 0 | CX20: 0 | CY20: 0 | CZ20: 0 | DA20: 0 | DB20: 0 | DC20: 0 | DD20: 0 | DE20: 0 | DF20: 0 | DG20: 0 | DH20: 0 | DI20: 20602544495 | DJ20: ASOCIACION DE PRODUCTORES ECOLOGICOS AGRARIOS DEL DISTRITO DE QUICHES PROVINCIA DE SIHUAS-ANCASH | DK20: 01 Asociación
A21: Asociacion de Productores y Comerciantes de Tara de Puchka | B21: TARA | C21: TARA | D21: Ancash | E21: 021016 | F21: Ancash | G21: Huari | H21: Uco | I21: 1 | Q21: PAC | R21: 2018 | S21: 1 | T21: NO | U21: NO | V21: 39 | W21: 0 | X21: 0 | Y21: 0 | Z21: 0 | AA21: 0 | AB21: 0 | AC21: 0 | AD21: 0 | AE21: 0 | AF21: 0 | AG21: 0 | AH21: 0 | AI21: 0 | AJ21: 0 | AK21: 0 | AL21: 0 | AM21: 0 | AN21: 0 | AO21: 0 | AP21: 0 | AQ21: 0 | AR21: 39 | AS21: 0 | AT21: 0 | AU21: 0 | AV21: 0 | AW21: 0 | AX21: 0 | AY21: 0 | AZ21: 0 | BA21: 0 | BB21: 0 | BC21: 0 | BD21: 0 | BE21: 0 | BF21: 0 | BG21: 0 | BH21: 0 | BI21: #REF! | BJ21: #REF! | BK21: 0 | BL21: 0 | BM21: 0 | BN21: #REF! | BO21: #REF! | BP21: 0 | BQ21: 0 | BR21: 0 | BS21: #REF! | BU21: 0 | BV21: 0 | BW21: 0 | BX21: #REF! | BY21: #REF! | BZ21: 0 | CA21: 0 | CB21: 0 | CC21: #REF! | CD21: 0 | CE21: 0 | CF21: 0 | CG21: 0 | CH21: #REF! | CI21: 0 | CJ21: #REF! | CK21: 0 | CL21: 0 | CM21: 0 | CN21: #REF! | CO21: 0 | CP21: 0 | CQ21: 0 | CR21: 0 | CS21: 0 | CT21: 0 | CU21: 0 | CV21: 0 | CW21: 0 | CX21: 0 | CY21: 0 | CZ21: 0 | DA21: 0 | DB21: 0 | DC21: 0 | DD21: 0 | DE21: 0 | DF21: 0 | DG21: 0 | DH21: 0 | DI21: 20534142146 | DJ21: ASOCIACION DE PRODUCTORES Y COMERCIANTES DE TARA DE PUCHKA | DK21: 01 Asociación
A22: Grupo Asociado Productores de Caraz | B22: FLORES | C22: FLORES | D22: Ancash | E22: 021201 | F22: Ancash | G22: Huaylas | H22: Caraz | I22: 1 | Q22: PAC | R22: 2018 | S22: 1 | T22: NO | U22: NO | V22: 4 | W22: 0 | X22: 0 | Y22: 0 | Z22: 0 | AA22: 0 | AB22: 0 | AC22: 0 | AD22: 0 | AE22: 0 | AF22: 0 | AG22: 0 | AH22: 0 | AI22: 0 | AJ22: 0 | AK22: 0 | AL22: 0 | AM22: 0 | AN22: 0 | AO22: 0 | AP22: 0 | AQ22: 0 | AR22: 4 | AS22: 0 | AT22: 0 | AU22: 0 | AV22: 0 | AW22: 0 | AX22: 0 | AY22: 0 | AZ22: 0 | BA22: 0 | BB22: 0 | BC22: 0 | BD22: 0 | BE22: 0 | BF22: 0 | BG22: 0 | BH22: 0 | BI22: #REF! | BJ22: #REF! | BK22: 0 | BL22: 0 | BM22: 0 | BN22: #REF! | BO22: #REF! | BP22: 0 | BQ22: 0 | BR22: 0 | BS22: #REF! | BU22: 0 | BV22: 0 | BW22: 0 | BX22: #REF! | BY22: #REF! | BZ22: 0 | CA22: 0 | CB22: 0 | CC22: #REF! | CD22: 0 | CE22: 0 | CF22: 0 | CG22: 0 | CH22: #REF! | CI22: 0 | CJ22: #REF! | CK22: 0 | CL22: 0 | CM22: 0 | CN22: #REF! | CO22: 0 | CP22: 0 | CQ22: 0 | CR22: 0 | CS22: 0 | CT22: 0 | CU22: 0 | CV22: 0 | CW22: 0 | CX22: 0 | CY22: 0 | CZ22: 0 | DA22: 0 | DB22: 0 | DC22: 0 | DD22: 0 | DE22: 0 | DF22: 0 | DG22: 0 | DH22: 0 | DI22: SIN RUC | DJ22: ND | DK22: 01 Asociación
A23: Cooperativa de Productores Agroecologicos la Perla de los Andes-Callejon de Huaylas Ancash | B23: TARWI | C23: TARWI | D23: Ancash | E23: 021201 | F23: Ancash | G23: Huaylas | H23: Caraz | I23: 1 | J23: 1 | K23: 1 | L23: 1 | M23: 1 | N23: 1 | Q23: PAC | R23: 2018-2019-2020-2021-2022-2023 | S23: 6 | T23: SI | U23: SI | V23: 521 | W23: 79 | X23: 17 | Y23: 96 | Z23: 213 | AA23: 60 | AB23: 273 | AC23: 215 | AD23: 58 | AE23: 273 | AF23: 59 | AG23: 18 | AH23: 77 | AI23: 59 | AJ23: 18 | AK23: 77 | AL23: 0 | AM23: 0 | AN23: 0 | AO23: 0 | AP23: 0 | AQ23: 0 | AR23: 77 | AS23: 18 | AT23: 6 | AU23: 36 | AV23: 7 | AW23: 25 | AX23: 6 | AY23: 36 | AZ23: 2 | BA23: 0 | BB23: 0 | BC23: 0 | BD23: 0 | BE23: 0 | BF23: 11802.35 | BG23: 0 | BH23: 11802.35 | BI23: #REF! | BJ23: #REF! | BK23: 109219.27 | BL23: 0 | BM23: 109219.27 | BN23: #REF! | BO23: #REF! | BP23: 131381.75 | BQ23: 0 | BR23: 131381.75 | BS23: #REF! | BU23: 129764.41 | BV23: 0 | BW23: 129764.41 | BX23: #REF! | BY23: #REF! | BZ23: 141145.57 | CA23: 0 | CB23: 141145.57 | CC23: #REF! | CD23: -129764.41 | CE23: 0 | CF23: 0 | CG23: 0 | CH23: #REF! | CI23: -141145.57 | CJ23: #REF! | CK23: 0 | CL23: 0 | CM23: 0 | CN23: #REF! | CO23: 0 | CP23: 0 | CQ23: 0 | CR23: 0 | CS23: 141147 | CT23: 0 | CU23: 0 | CV23: 141147 | CW23: 0 | CX23: 0 | CY23: 0 | CZ23: 0 | DA23: 0 | DB23: 0 | DC23: 0 | DD23: 0 | DE23: 0 | DF23: 0 | DG23: 0 | DH23: 0 | DI23: 20603223421 | DJ23: COOPERATIVA DE PRODUCTORES AGROECOLOGICOS LA PERLA DE LOS ANDES-CALLEJON DE HUAYLAS ANCASH | DK23: 02 Cooperativa
A24: Asociación de Semillaristas de Maiz Choclo Virgen de las Mercedes del Distrito de Chingas | B24: MAÍZ | C24: MAÍZ BLANCO GIGANTE | D24: Ancash | E24: 020304 | F24: Ancash | G24: Antonio Raymondi | H24: Chingas | I24: 1 | J24: 1 | K24: 1 | L24: 1 | M24: 1 | N24: 1 | Q24: PAC | R24: 2018-2019-2020-2021-2022-2023 | S24: 6 | T24: SI | U24: SI | V24: 28 | W24: 23 | X24: 3 | Y24: 26 | Z24: 23 | AA24: 3 | AB24: 26 | AC24: 20 | AD24: 3 | AE24: 23 | AF24: 20 | AG24: 3 | AH24: 23 | AI24: 20 | AJ24: 3 | AK24: 23 | AL24: 0 | AM24: 0 | AN24: 0 | AO24: 0 | AP24: 0 | AQ24: 0 | AR24: 23 | AS24: 3 | AT24: 0 | AU24: 44 | AV24: 8 | AW24: 25 | AX24: 5 | AY24: 34 | AZ24: 4 | BA24: 0 | BB24: 0 | BC24: 0 | BD24: 0 | BE24: 0 | BF24: 0 | BG24: 0 | BH24: 0 | BI24: #REF! | BJ24: #REF! | BK24: 13830 | BL24: 0 | BM24: 13830 | BN24: #REF! | BO24: #REF! | BP24: 378700 | BQ24: 0 | BR24: 378700 | BS24: #REF! | BU24: 452800 | BV24: 0 | BW24: 452800 | BX24: #REF! | BY24: #REF! | BZ24: 564965 | CA24: 0 | CB24: 564965 | CC24: #REF! | CD24: -452800 | CE24: 0 | CF24: 0 | CG24: 0 | CH24: #REF! | CI24: -564965 | CJ24: #REF! | CK24: 0 | CL24: 0 | CM24: 0 | CN24: #REF! | CO24: 0 | CP24: 0 | CQ24: 564965 | CR24: 0 | CS24: 0 | CT24: 0 | CU24: 0 | CV24: 564965 | CW24: 0 | CX24: 0 | CY24: 0 | CZ24: 0 | DA24: 0 | DB24: 0 | DC24: 0 | DD24: 0 | DE24: 0 | DF24: 0 | DG24: 0 | DH24: 0 | DI24: 20601547458 | DJ24: ASOCIACION DE SEMILLARISTAS DE MAIZ CHOCLO VIRGEN DE LA MERCEDES DEL DISTRITO DE CHINGAS | DK24: 01 Asociación
A25: Asociacion de Productores de Paltos Moro | B25: PALTA | C25: PALTA | D25: Ancash | E25: 021805 | F25: Ancash | G25: Santa | H25: Moro | J25: 1 | Q25: PAC | R25: 2019 | S25: 1 | T25: SI | U25: NO | V25: 0 | W25: 33 | X25: 2 | Y25: 35 | Z25: 0 | AA25: 0 | AB25: 0 | AC25: 0 | AD25: 0 | AE25: 0 | AF25: 0 | AG25: 0 | AH25: 0 | AI25: 0 | AJ25: 0 | AK25: 0 | AL25: 0 | AM25: 0 | AN25: 0 | AO25: 0 | AP25: 0 | AQ25: 0 | AR25: 35 | AS25: 0 | AT25: 0 | AU25: 0 | AV25: 0 | AW25: 0 | AX25: 0 | AY25: 0 | AZ25: 0 | BA25: 0 | BB25: 0 | BC25: 0 | BD25: 0 | BE25: 0 | BF25: 260411.15 | BG25: 0 | BH25: 260411.15 | BI25: #REF! | BJ25: #REF! | BK25: 0 | BL25: 0 | BM25: 0 | BN25: #REF! | BO25: #REF! | BP25: 0 | BQ25: 0 | BR25: 0 | BS25: #REF! | BU25: 0 | BV25: 0 | BW25: 0 | BX25: #REF! | BY25: #REF! | BZ25: 0 | CA25: 0 | CB25: 0 | CC25: #REF! | CD25: 0 | CE25: 0 | CF25: 0 | CG25: 0 | CH25: #REF! | CI25: 0 | CJ25: #REF! | CK25: 0 | CL25: 0 | CM25: 0 | CN25: #REF! | CO25: 0 | CP25: 0 | CQ25: 0 | CR25: 0 | CS25: 0 | CT25: 0 | CU25: 0 | CV25: 0 | CW25: 0 | CX25: 0 | CY25: 0 | CZ25: 0 | DA25: 0 | DB25: 0 | DC25: 0 | DD25: 0 | DE25: 0 | DF25: 0 | DG25: 0 | DH25: 0 | DI25: 20603736703 | DJ25: ASOCIACION DE PRODUCTORES DE PALTOS MORO - APROPALMO | DK25: 01 Asociación
A26: Cooperativa Agraria Valle Fortaleza-Coavaf | B26: DURAZNO | C26: DURAZNO | D26: Ancash | E26: 020503 | F26: Ancash | G26: Bolognesi | H26: Antonio Raymondi | L26: 1 | Q26: PAC | R26: 2021 | S26: 1 | T26: SI | U26: SI | V26: 0 | W26: 0 | X26: 0 | Y26: 0 | Z26: 0 | AA26: 0 | AB26: 0 | AC26: 64 | AD26: 10 | AE26: 74 | AF26: 0 | AG26: 0 | AH26: 0 | AI26: 0 | AJ26: 0 | AK26: 0 | AL26: 0 | AM26: 0 | AN26: 0 | AO26: 0 | AP26: 0 | AQ26: 0 | AR26: 74 | AS26: 0 | AT26: 0 | AU26: 52 | AV26: 8 | AW26: 0 | AX26: 0 | AY26: 0 | AZ26: 0 | BA26: 0 | BB26: 0 | BC26: 0 | BD26: 0 | BE26: 0 | BF26: 0 | BG26: 0 | BH26: 0 | BI26: #REF! | BJ26: #REF! | BK26: 0 | BL26: 0 | BM26: 0 | BN26: #REF! | BO26: #REF! | BP26: 183225 | BQ26: 0 | BR26: 183225 | BS26: #REF! | BU26: 0 | BV26: 0 | BW26: 0 | BX26: #REF! | BY26: #REF! | BZ26: 0 | CA26: 0 | CB26: 0 | CC26: #REF! | CD26: 0 | CE26: 0 | CF26: 0 | CG26: 0 | CH26: #REF! | CI26: 0 | CJ26: #REF! | CK26: 0 | CL26: 0 | CM26: 0 | CN26: #REF! | CO26: 0 | CP26: 0 | CQ26: 0 | CR26: 0 | CS26: 0 | CT26: 0 | CU26: 0 | CV26: 0 | CW26: 0 | CX26: 0 | CY26: 0 | CZ26: 0 | DA26: 0 | DB26: 0 | DC26: 0 | DD26: 0 | DE26: 0 | DF26: 0 | DG26: 0 | DH26: 0 | DI26: 20600276221 | DJ26: COOPERATIVA AGRARIA VALLE FORTALEZA - COAVAFF | DK26: 02 Cooperativa
A27: Asociacion de Productores Agroecologicos de Pariacoto Promoviendo Vida Saludable - Apaprovis | B27: PALTA | C27: PALTA | D27: Ancash | E27: 020110 | F27: Ancash | G27: Huaraz | H27: Pariacoto | L27: 1 | M27: 1 | N27: 1 | O27: 1 | Q27: PAC | R27: 2021-2022-2023-2024 | S27: 4 | T27: SI | U27: SI | V27: 0 | W27: 0 | X27: 0 | Y27: 0 | Z27: 0 | AA27: 0 | AB27: 0 | AC27: 20 | AD27: 6 | AE27: 26 | AF27: 20 | AG27: 6 | AH27: 26 | AI27: 20 | AJ27: 6 | AK27: 26 | AL27: 20 | AM27: 6 | AN27: 26 | AO27: 0 | AP27: 0 | AQ27: 0 | AR27: 26 | AS27: 0 | AT27: 0 | AU27: 67 | AV27: 10 | AW27: 16 | AX27: 5 | AY27: 38 | AZ27: 1 | BA27: 30 | BB27: 0 | BC27: 0 | BD27: 0 | BE27: 0 | BF27: 0 | BG27: 0 | BH27: 0 | BI27: #REF! | BJ27: #REF! | BK27: 0 | BL27: 0 | BM27: 0 | BN27: #REF! | BO27: #REF! | BP27: 211492.7 | BQ27: 0 | BR27: 211492.7 | BS27: #REF! | BU27: 52556.7 | BV27: 0 | BW27: 52556.7 | BX27: #REF! | BY27: #REF! | BZ27: 77420.7 | CA27: 0 | CB27: 77420.7 | CC27: #REF! | CD27: -52556.7 | CE27: 48724 | CF27: 0 | CG27: 48724 | CH27: #REF! | CI27: -77420.7 | CJ27: #REF! | CK27: 0 | CL27: 0 | CM27: 0 | CN27: #REF! | CO27: -48724 | CP27: 0 | CQ27: 77420.7 | CR27: 0 | CS27: 0 | CT27: 0 | CU27: 0 | CV27: 77420.7 | CW27: 0 | CX27: 48724 | CY27: 0 | CZ27: 0 | DA27: 0 | DB27: 48724 | DC27: 0 | DD27: 0 | DE27: 0 | DF27: 0 | DG27: 0 | DH27: 0 | DI27: 20605197583 | DJ27: ASOCIACION DE PRODUCTORES AGROECOLOGICOS DE PARIACOTO PROMOVIENDO VIDA SALUDABLE - APAPROVIS | DK27: 01 Asociación
A28: Cooperativa Agraria Purifor | B28: PALTA | C28: PALTA | D28: Ancash | E28: 020507 | F28: Ancash | G28: Bolognesi | H28: Colquioc | M28: 1 | N28: 1 | O28: 1 | P28: 1 | Q28: PAC | R28: 2022-2023-2024 - 2025 | S28: 4 | T28: SI | U28: SI | V28: 0 | W28: 0 | X28: 0 | Y28: 0 | Z28: 0 | AA28: 0 | AB28: 0 | AC28: 0 | AD28: 0 | AE28: 0 | AF28: 57 | AG28: 29 | AH28: 86 | AI28: 57 | AJ28: 29 | AK28: 86 | AL28: 61 | AM28: 25 | AN28: 86 | AO28: 59 | AP28: 25 | AQ28: 84 | AR28: 84 | AS28: 0 | AT28: 0 | AU28: 0 | AV28: 0 | AW28: 19 | AX28: 5 | AY28: 38 | AZ28: 0 | BA28: 31 | BB28: 3 | BC28: 12 | BD28: 0 | BE28: 0 | BF28: 0 | BG28: 0 | BH28: 0 | BI28: #REF! | BJ28: #REF! | BK28: 0 | BL28: 0 | BM28: 0 | BN28: #REF! | BO28: #REF! | BP28: 0 | BQ28: 0 | BR28: 0 | BS28: #REF! | BU28: 351529.15 | BV28: 0 | BW28: 351529.15 | BX28: #REF! | BY28: #REF! | BZ28: 100445.5 | CA28: 0 | CB28: 100445.5 | CC28: #REF! | CD28: -351529.15 | CE28: 362155.2 | CF28: 0 | CG28: 362155.2 | CH28: #REF! | CI28: -100445.5 | CJ28: #REF! | CK28: 488080 | CL28: 0 | CM28: 488080 | CN28: #REF! | CO28: -362155.2 | CP28: 0 | CQ28: 100445.5 | CR28: 0 | CS28: 0 | CT28: 0 | CU28: 0 | CV28: 100445.5 | CW28: 0 | CX28: 362155.2 | CY28: 0 | CZ28: 0 | DA28: 0 | DB28: 362155.2 | DC28: 0 | DD28: 470180 | DE28: 0 | DF28: 17900 | DG28: 0 | DH28: 488080 | DI28: 20407808666 | DJ28: COOPERATIVA AGRARIA PURIFOR - COOP PURIFOR | DK28: 02 Cooperativa
A29: Cooperativa Agraria Andina de Santa Cruz LTDA. | B29: KIWICHA | C29: KIWICHA | D29: Ancash | E29: 021208 | F29: Ancash | G29: Huaylas | H29: Santa Cruz | M29: 1 | O29: 1 | P29: 1 | Q29: PAC | R29: 2022-2024 - 2025 | S29: 3 | T29: SI | U29: SI | V29: 0 | W29: 0 | X29: 0 | Y29: 0 | Z29: 0 | AA29: 0 | AB29: 0 | AC29: 0 | AD29: 0 | AE29: 0 | AF29: 9 | AG29: 10 | AH29: 19 | AI29: 0 | AJ29: 0 | AK29: 0 | AL29: 8 | AM29: 10 | AN29: 18 | AO29: 10 | AP29: 17 | AQ29: 27 | AR29: 27 | AS29: 0 | AT29: 0 | AU29: 0 | AV29: 0 | AW29: 22 | AX29: 6 | AY29: 0 | AZ29: 0 | BA29: 28 | BB29: 0 | BC29: 31 | BD29: 0 | BE29: 0 | BF29: 0 | BG29: 0 | BH29: 0 | BI29: #REF! | BJ29: #REF! | BK29: 0 | BL29: 0 | BM29: 0 | BN29: #REF! | BO29: #REF! | BP29: 0 | BQ29: 0 | BR29: 0 | BS29: #REF! | BU29: 29700 | BV29: 0 | BW29: 29700 | BX29: #REF! | BY29: #REF! | BZ29: 0 | CA29: 0 | CB29: 0 | CC29: #REF! | CD29: -29700 | CE29: 65663.1 | CF29: 0 | CG29: 65663.1 | CH29: #REF! | CI29: 0 | CJ29: #REF! | CK29: 28801.99 | CL29: 0 | CM29: 28801.99 | CN29: #REF! | CO29: -65663.1 | CP29: 0 | CQ29: 0 | CR29: 0 | CS29: 0 | CT29: 0 | CU29: 0 | CV29: 0 | CW29: 0 | CX29: 65663.1 | CY29: 0 | CZ29: 0 | DA29: 0 | DB29: 65663.1 | DC29: 1143.9897 | DD29: 27658 | DE29: 0 | DF29: 0 | DG29: 0 | DH29: 28801.99 | DI29: 20604755230 | DJ29: COOPERATIVA AGRARIA ANDINA DE SANTA CRUZ LTDA. | DK29: 02 Cooperativa
A30: Cooperativa Agraria Kiwicha Wayi LTDA | B30: KIWICHA | C30: KIWICHA | D30: Ancash | E30: 021201 | F30: Ancash | G30: Huaylas | H30: Caraz | M30: 1 | N30: 1 | O30: 1 | P30: 1 | Q30: PAC | R30: 2022-2023-2024 - 2025 | S30: 4 | T30: SI | U30: SI | V30: 0 | W30: 0 | X30: 0 | Y30: 0 | Z30: 0 | AA30: 0 | AB30: 0 | AC30: 0 | AD30: 0 | AE30: 0 | AF30: 12 | AG30: 14 | AH30: 26 | AI30: 12 | AJ30: 14 | AK30: 26 | AL30: 11 | AM30: 14 | AN30: 25 | AO30: 11 | AP30: 14 | AQ30: 25 | AR30: 25 | AS30: 0 | AT30: 0 | AU30: 0 | AV30: 0 | AW30: 23 | AX30: 6 | AY30: 37 | AZ30: 3 | BA30: 25 | BB30: 3 | BC30: 29 | BD30: 2 | BE30: 0 | BF30: 0 | BG30: 0 | BH30: 0 | BI30: #REF! | BJ30: #REF! | BK30: 0 | BL30: 0 | BM30: 0 | BN30: #REF! | BO30: #REF! | BP30: 0 | BQ30: 0 | BR30: 0 | BS30: #REF! | BU30: 88340 | BV30: 0 | BW30: 88340 | BX30: #REF! | BY30: #REF! | BZ30: 132750.28 | CA30: 0 | CB30: 132750.28 | CC30: #REF! | CD30: -88340 | CE30: 197902 | CF30: 0 | CG30: 197902 | CH30: #REF! | CI30: -132750.28 | CJ30: #REF! | CK30: 102372.15 | CL30: 0 | CM30: 102372.15 | CN30: #REF! | CO30: -197902 | CP30: 0 | CQ30: 59729 | CR30: 0 | CS30: 73021.284 | CT30: 0 | CU30: 0 | CV30: 132750.28 | CW30: 0 | CX30: 197902 | CY30: 0 | CZ30: 0 | DA30: 0 | DB30: 197902 | DC30: 0 | DD30: 77932.1 | DE30: 24440.055 | DF30: 0 | DG30: 0 | DH30: 102372.15 | DI30: 20600558715 | DJ30: COOPERATIVA AGRARIA KIWICHA WAYI LTDA | DK30: 02 Cooperativa
A31: Asociacion Productores Agropecuarios Santa Rosa de Kiman Ayllu | B31: PALTA | C31: PALTA | D31: Ancash | E31: 021210 | F31: Ancash | G31: Huaylas | H31: Yuracmarca | M31: 1 | N31: 1 | O31: 1 | P31: 1 | Q31: PAC | R31: 2022-2023-2024 - 2025 | S31: 4 | T31: SI | U31: SI | V31: 0 | W31: 0 | X31: 0 | Y31: 0 | Z31: 0 | AA31: 0 | AB31: 0 | AC31: 0 | AD31: 0 | AE31: 0 | AF31: 13 | AG31: 7 | AH31: 20 | AI31: 13 | AJ31: 7 | AK31: 20 | AL31: 11 | AM31: 7 | AN31: 18 | AO31: 11 | AP31: 5 | AQ31: 16 | AR31: 16 | AS31: 0 | AT31: 0 | AU31: 0 | AV31: 0 | AW31: 19 | AX31: 5 | AY31: 44 | AZ31: 3 | BA31: 32 | BB31: 4 | BC31: 35 | BD31: 0 | BE31: 0 | BF31: 0 | BG31: 0 | BH31: 0 | BI31: #REF! | BJ31: #REF! | BK31: 0 | BL31: 0 | BM31: 0 | BN31: #REF! | BO31: #REF! | BP31: 0 | BQ31: 0 | BR31: 0 | BS31: #REF! | BU31: 180390 | BV31: 0 | BW31: 180390 | BX31: #REF! | BY31: #REF! | BZ31: 208400 | CA31: 0 | CB31: 208400 | CC31: #REF! | CD31: -180390 | CE31: 241803.66 | CF31: 0 | CG31: 241803.66 | CH31: #REF! | CI31: -208400 | CJ31: #REF! | CK31: 189229.51 | CL31: 0 | CM31: 189229.51 | CN31: #REF! | CO31: -241803.66 | CP31: 0 | CQ31: 208400 | CR31: 0 | CS31: 0 | CT31: 0 | CU31: 0 | CV31: 208400 | CW31: 0 | CX31: 241803.66 | CY31: 0 | CZ31: 0 | DA31: 0 | DB31: 241803.66 | DC31: 0 | DD31: 152584.41 | DE31: 0 | DF31: 0 | DG31: 36645.095 | DH31: 189229.51 | DI31: 20533718176 | DJ31: ASOCIACION PRODUCTORES AGROPECUARIOS SANTA ROSA DE KIMAN AYLLU | DK31: 01 Asociación
A32: Cooperativa Agraria Coyapapi | B32: PALTA | C32: PALTA | D32: Ancash | E32: 020110 | F32: Ancash | G32: Huaraz | H32: Pariacoto | M32: 1 | N32: 1 | O32: 1 | Q32: PAC | R32: 2022-2023-2024 | S32: 3 | T32: SI | U32: SI | V32: 0 | W32: 0 | X32: 0 | Y32: 0 | Z32: 0 | AA32: 0 | AB32: 0 | AC32: 0 | AD32: 0 | AE32: 0 | AF32: 132 | AG32: 19 | AH32: 151 | AI32: 132 | AJ32: 19 | AK32: 151 | AL32: 135 | AM32: 14 | AN32: 149 | AO32: 0 | AP32: 0 | AQ32: 0 | AR32: 149 | AS32: 0 | AT32: 0 | AU32: 0 | AV32: 0 | AW32: 17 | AX32: 5 | AY32: 37 | AZ32: 1 | BA32: 27 | BB32: 3 | BC32: 0 | BD32: 0 | BE32: 0 | BF32: 0 | BG32: 0 | BH32: 0 | BI32: #REF! | BJ32: #REF! | BK32: 0 | BL32: 0 | BM32: 0 | BN32: #REF! | BO32: #REF! | BP32: 0 | BQ32: 0 | BR32: 0 | BS32: #REF! | BU32: 363932.5 | BV32: 0 | BW32: 363932.5 | BX32: #REF! | BY32: #REF! | BZ32: 664665.6 | CA32: 0 | CB32: 664665.6 | CC32: #REF! | CD32: -363932.5 | CE32: 1376040 | CF32: 0 | CG32: 1376040 | CH32: #REF! | CI32: -664665.6 | CJ32: #REF! | CK32: 0 | CL32: 0 | CM32: 0 | CN32: #REF! | CO32: -1376040 | CP32: 0 | CQ32: 664665.6 | CR32: 0 | CS32: 0 | CT32: 0 | CU32: 0 | CV32: 664665.6 | CW32: 0 | CX32: 1376040 | CY32: 0 | CZ32: 0 | DA32: 0 | DB32: 1376040 | DC32: 0 | DD32: 0 | DE32: 0 | DF32: 0 | DG32: 0 | DH32: 0 | DI32: 20604218358 | DJ32: COOPERATIVA AGRARIA COYAPAPI | DK32: 02 Cooperativa
A33: Asociación de Fruticultores del Valle Pampas- Afruvap | B33: PALTA | C33: PALTA | D33: Apurimac | E33: 030601 | F33: Apurimac | G33: Chincheros | H33: Chincheros | J33: 1 | K33: 1 | Q33: PAC | R33: 2019-2020 | S33: 2 | T33: SI | U33: SI | V33: 0 | W33: 15 | X33: 12 | Y33: 27 | Z33: 20 | AA33: 4 | AB33: 24 | AC33: 0 | AD33: 0 | AE33: 0 | AF33: 0 | AG33: 0 | AH33: 0 | AI33: 0 | AJ33: 0 | AK33: 0 | AL33: 0 | AM33: 0 | AN33: 0 | AO33: 0 | AP33: 0 | AQ33: 0 | AR33: 24 | AS33: 0 | AT33: 2 | AU33: 0 | AV33: 0 | AW33: 0 | AX33: 0 | AY33: 0 | AZ33: 0 | BA33: 0 | BB33: 0 | BC33: 0 | BD33: 0 | BE33: 0 | BF33: 0 | BG33: 0 | BH33: 0 | BI33: #REF! | BJ33: #REF! | BK33: 324995 | BL33: 0 | BM33: 324995 | BN33: #REF! | BO33: #REF! | BP33: 0 | BQ33: 0 | BR33: 0 | BS33: #REF! | BU33: 0 | BV33: 0 | BW33: 0 | BX33: #REF! | BY33: #REF! | BZ33: 0 | CA33: 0 | CB33: 0 | CC33: #REF! | CD33: 0 | CE33: 0 | CF33: 0 | CG33: 0 | CH33: #REF! | CI33: 0 | CJ33: #REF! | CK33: 0 | CL33: 0 | CM33: 0 | CN33: #REF! | CO33: 0 | CP33: 0 | CQ33: 0 | CR33: 0 | CS33: 0 | CT33: 0 | CU33: 0 | CV33: 0 | CW33: 0 | CX33: 0 | CY33: 0 | CZ33: 0 | DA33: 0 | DB33: 0 | DC33: 0 | DD33: 0 | DE33: 0 | DF33: 0 | DG33: 0 | DH33: 0 | DI33: 20527890285 | DJ33: ASOCIACION DE FRUTICULTORES DEL VALLE PAMPAS- AFRUVAP | DK33: 01 Asociación
A34: Asociación de Productores Agropecuarios Organicos Valle Pampas - Apaovap | B34: PALTA | C34: PALTA | D34: Apurimac | E34: 030604 | F34: Apurimac | G34: Chincheros | H34: Huaccana | I34: 1 | J34: 1 | K34: 1 | Q34: PAC | R34: 2018-2019-2020 | S34: 3 | T34: SI | U34: SI | V34: 37 | W34: 13 | X34: 15 | Y34: 28 | Z34: 11 | AA34: 8 | AB34: 19 | AC34: 0 | AD34: 0 | AE34: 0 | AF34: 0 | AG34: 0 | AH34: 0 | AI34: 0 | AJ34: 0 | AK34: 0 | AL34: 0 | AM34: 0 | AN34: 0 | AO34: 0 | AP34: 0 | AQ34: 0 | AR34: 19 | AS34: 0 | AT34: 2 | AU34: 0 | AV34: 0 | AW34: 0 | AX34: 0 | AY34: 0 | AZ34: 0 | BA34: 0 | BB34: 0 | BC34: 0 | BD34: 0 | BE34: 0 | BF34: 1974706.2 | BG34: 0 | BH34: 1974706.2 | BI34: #REF! | BJ34: #REF! | BK34: 58325 | BL34: 0 | BM34: 58325 | BN34: #REF! | BO34: #REF! | BP34: 0 | BQ34: 0 | BR34: 0 | BS34: #REF! | BU34: 0 | BV34: 0 | BW34: 0 | BX34: #REF! | BY34: #REF! | BZ34: 0 | CA34: 0 | CB34: 0 | CC34: #REF! | CD34: 0 | CE34: 0 | CF34: 0 | CG34: 0 | CH34: #REF! | CI34: 0 | CJ34: #REF! | CK34: 0 | CL34: 0 | CM34: 0 | CN34: #REF! | CO34: 0 | CP34: 0 | CQ34: 0 | CR34: 0 | CS34: 0 | CT34: 0 | CU34: 0 | CV34: 0 | CW34: 0 | CX34: 0 | CY34: 0 | CZ34: 0 | DA34: 0 | DB34: 0 | DC34: 0 | DD34: 0 | DE34: 0 | DF34: 0 | DG34: 0 | DH34: 0 | DI34: 20490594265 | DJ34: ASOCIACION DE PRODUCTORES AGROPECUARIOS ORGANICOS VALLE PAMPAS - APAOVAP | DK34: 01 Asociación
A35: Cooperativa Agroindustrial Machupicchu LTDA | B35: QUINUA Y OTROS GRANOS | C35: QUINUA | D35: Apurimac | E35: 030213 | F35: Apurimac | G35: Andahuaylas | H35: San Jeronimo | I35: 1 | J35: 1 | K35: 1 | L35: 1 | N35: 1 | P35: 1 | Q35: PAC | R35: 2018-2019-2020-2021-2023 - 2025 | S35: 6 | T35: SI | U35: SI | V35: 463 | W35: 217 | X35: 44 | Y35: 261 | Z35: 210 | AA35: 43 | AB35: 253 | AC35: 190 | AD35: 50 | AE35: 240 | AF35: 0 | AG35: 0 | AH35: 0 | AI35: 120 | AJ35: 80 | AK35: 200 | AL35: 0 | AM35: 0 | AN35: 0 | AO35: 92 | AP35: 15 | AQ35: 107 | AR35: 107 | AS35: 0 | AT35: 7 | AU35: 22 | AV35: 4 | AW35: 0 | AX35: 0 | AY35: 25 | AZ35: 7 | BA35: 0 | BB35: 0 | BC35: 24 | BD35: 0 | BE35: 2120163.2 | BF35: 2632717.2 | BG35: 0 | BH35: 2632717.2 | BI35: #REF! | BJ35: #REF! | BK35: 1413126.6 | BL35: 951293.2 | BM35: 2364419.8 | BN35: #REF! | BO35: #REF! | BP35: 671996.57 | BQ35: 364049.58 | BR35: 1036046.2 | BS35: #REF! | BU35: 0 | BV35: 0 | BW35: 0 | BX35: #REF! | BY35: #REF! | BZ35: 2082623.3 | CA35: 0 | CB35: 2082623.3 | CC35: #REF! | CD35: 0 | CE35: 0 | CF35: 0 | CG35: 0 | CH35: #REF! | CI35: -2082623.3 | CJ35: #REF! | CK35: 108583.6 | CL35: 0 | CM35: 108583.6 | CN35: #REF! | CO35: 0 | CP35: 0 | CQ35: 0 | CR35: 0 | CS35: 2082623.3 | CT35: 0 | CU35: 0 | CV35: 2082623.3 | CW35: 0 | CX35: 0 | CY35: 0 | CZ35: 0 | DA35: 0 | DB35: 0 | DC35: 0 | DD35: 0 | DE35: 108583.6 | DF35: 0 | DG35: 0 | DH35: 108583.6 | DI35: 20490810146 | DJ35: COOPERATIVA AGRARIA MACHUPICCHU LTDA - CAGMA LTDA | DK35: 02 Cooperativa
A36: Cooperativa Agroindustrial Tierra Andina LTDA | B36: QUINUA Y OTROS GRANOS | C36: QUINUA | D36: Apurimac | E36: 030201 | F36: Apurimac | G36: Andahuaylas | H36: Andahuaylas | I36: 1 | J36: 1 | K36: 1 | L36: 1 | M36: 1 | N36: 1 | Q36: PAC | R36: 2018-2019-2020-2021-2022-2023 | S36: 6 | T36: SI | U36: SI | V36: 168 | W36: 93 | X36: 42 | Y36: 135 | Z36: 82 | AA36: 41 | AB36: 123 | AC36: 103 | AD36: 47 | AE36: 150 | AF36: 103 | AG36: 47 | AH36: 150 | AI36: 103 | AJ36: 47 | AK36: 150 | AL36: 0 | AM36: 0 | AN36: 0 | AO36: 0 | AP36: 0 | AQ36: 0 | AR36: 150 | AS36: 0 | AT36: 6 | AU36: 59 | AV36: 4 | AW36: 24 | AX36: 3 | AY36: 5 | AZ36: 0 | BA36: 0 | BB36: 0 | BC36: 0 | BD36: 0 | BE36: 0 | BF36: 471229 | BG36: 0 | BH36: 471229 | BI36: #REF! | BJ36: #REF! | BK36: 1076214.4 | BL36: 0 | BM36: 1076214.4 | BN36: #REF! | BO36: #REF! | BP36: 748371.58 | BQ36: 0 | BR36: 748371.58 | BS36: #REF! | BU36: 0 | BV36: 0 | BW36: 0 | BX36: #REF! | BY36: #REF! | BZ36: 200004 | CA36: 0 | CB36: 200004 | CC36: #REF! | CD36: 0 | CE36: 0 | CF36: 0 | CG36: 0 | CH36: #REF! | CI36: -200004 | CJ36: #REF! | CK36: 0 | CL36: 0 | CM36: 0 | CN36: #REF! | CO36: 0 | CP36: 0 | CQ36: 200004 | CR36: 0 | CS36: 0 | CT36: 0 | CU36: 0 | CV36: 200004 | CW36: 0 | CX36: 0 | CY36: 0 | CZ36: 0 | DA36: 0 | DB36: 0 | DC36: 0 | DD36: 0 | DE36: 0 | DF36: 0 | DG36: 0 | DH36: 0 | DI36: 20600998847 | DJ36: COOPERATIVA AGROINDUSTRIAL TIERRA ANDINA APURIMAC LTDA - CATAA LTDA | DK36: 02 Cooperativa
A37: Asociación de Mujeres Productoras de Tallarines de Casa Santo Domingo | B37: QUINUA Y OTROS GRANOS | C37: QUINUA | D37: Apurimac | E37: 030101 | F37: Apurimac | G37: Abancay | H37: Abancay | J37: 1 | K37: 1 | L37: 1 | Q37: PAC | R37: 2019-2020-2021 | S37: 3 | T37: SI | U37: SI | V37: 0 | W37: 4 | X37: 6 | Y37: 10 | Z37: 8 | AA37: 17 | AB37: 25 | AC37: 8 | AD37: 17 | AE37: 25 | AF37: 0 | AG37: 0 | AH37: 0 | AI37: 0 | AJ37: 0 | AK37: 0 | AL37: 0 | AM37: 0 | AN37: 0 | AO37: 0 | AP37: 0 | AQ37: 0 | AR37: 25 | AS37: 0 | AT37: 0 | AU37: 3 | AV37: 0 | AW37: 0 | AX37: 0 | AY37: 0 | AZ37: 0 | BA37: 0 | BB37: 0 | BC37: 0 | BD37: 0 | BE37: 0 | BF37: 48276 | BG37: 0 | BH37: 48276 | BI37: #REF! | BJ37: #REF! | BK37: 37127 | BL37: 0 | BM37: 37127 | BN37: #REF! | BO37: #REF! | BP37: 50168 | BQ37: 0 | BR37: 50168 | BS37: #REF! | BU37: 0 | BV37: 0 | BW37: 0 | BX37: #REF! | BY37: #REF! | BZ37: 0 | CA37: 0 | CB37: 0 | CC37: #REF! | CD37: 0 | CE37: 0 | CF37: 0 | CG37: 0 | CH37: #REF! | CI37: 0 | CJ37: #REF! | CK37: 0 | CL37: 0 | CM37: 0 | CN37: #REF! | CO37: 0 | CP37: 0 | CQ37: 0 | CR37: 0 | CS37: 0 | CT37: 0 | CU37: 0 | CV37: 0 | CW37: 0 | CX37: 0 | CY37: 0 | CZ37: 0 | DA37: 0 | DB37: 0 | DC37: 0 | DD37: 0 | DE37: 0 | DF37: 0 | DG37: 0 | DH37: 0 | DI37: 20490195301 | DJ37: ASOCIACION DE MUJERES PRODUCTORAS SANTO DOMINGO TALLARIN DE CASA | DK37: 01 Asociación
A38: Asociación de Productores Tambo Inca | B38: FIBRA DE ALPACA | C38: FIBRA DE ALPACA | D38: Apurimac | E38: 030406 | F38: Apurimac | G38: Aymaraes | H38: Cotaruse | I38: 1 | J38: 1 | Q38: PAC | R38: 2018-2019 | S38: 2 | T38: SI | U38: NO | V38: 46 | W38: 15 | X38: 2 | Y38: 17 | Z38: 0 | AA38: 0 | AB38: 0 | AC38: 0 | AD38: 0 | AE38: 0 | AF38: 0 | AG38: 0 | AH38: 0 | AI38: 0 | AJ38: 0 | AK38: 0 | AL38: 0 | AM38: 0 | AN38: 0 | AO38: 0 | AP38: 0 | AQ38: 0 | AR38: 17 | AS38: 0 | AT38: 0 | AU38: 0 | AV38: 0 | AW38: 0 | AX38: 0 | AY38: 0 | AZ38: 0 | BA38: 0 | BB38: 0 | BC38: 0 | BD38: 0 | BE38: 0 | BF38: 59829.9 | BG38: 0 | BH38: 59829.9 | BI38: #REF! | BJ38: #REF! | BK38: 0 | BL38: 0 | BM38: 0 | BN38: #REF! | BO38: #REF! | BP38: 0 | BQ38: 0 | BR38: 0 | BS38: #REF! | BU38: 0 | BV38: 0 | BW38: 0 | BX38: #REF! | BY38: #REF! | BZ38: 0 | CA38: 0 | CB38: 0 | CC38: #REF! | CD38: 0 | CE38: 0 | CF38: 0 | CG38: 0 | CH38: #REF! | CI38: 0 | CJ38: #REF! | CK38: 0 | CL38: 0 | CM38: 0 | CN38: #REF! | CO38: 0 | CP38: 0 | CQ38: 0 | CR38: 0 | CS38: 0 | CT38: 0 | CU38: 0 | CV38: 0 | CW38: 0 | CX38: 0 | CY38: 0 | CZ38: 0 | DA38: 0 | DB38: 0 | DC38: 0 | DD38: 0 | DE38: 0 | DF38: 0 | DG38: 0 | DH38: 0 | DI38: 20491172135 | DJ38: ASOCIACION DE PRODUCTORES DE ALPACAS TAMBOINCA | DK38: 01 Asociación
A39: Cooperativa Agraria de Servicios Múltiples Tesoro Chanka de Kishuara - Coopagros - Kishuara | B39: PAPA | C39: PAPA | D39: Apurimac | E39: 030207 | F39: Apurimac | G39: Andahuaylas | H39: Kishuara | I39: 1 | J39: 1 | K39: 1 | L39: 1 | Q39: PAC | R39: 2018-2019-2020-2021 | S39: 4 | T39: SI | U39: SI | V39: 40 | W39: 46 | X39: 6 | Y39: 52 | Z39: 24 | AA39: 5 | AB39: 29 | AC39: 24 | AD39: 5 | AE39: 29 | AF39: 0 | AG39: 0 | AH39: 0 | AI39: 0 | AJ39: 0 | AK39: 0 | AL39: 0 | AM39: 0 | AN39: 0 | AO39: 0 | AP39: 0 | AQ39: 0 | AR39: 29 | AS39: 0 | AT39: 2 | AU39: 45 | AV39: 6 | AW39: 0 | AX39: 0 | AY39: 0 | AZ39: 0 | BA39: 0 | BB39: 0 | BC39: 0 | BD39: 0 | BE39: 25160 | BF39: 540383.69 | BG39: 0 | BH39: 540383.69 | BI39: #REF! | BJ39: #REF! | BK39: 236000 | BL39: 0 | BM39: 236000 | BN39: #REF! | BO39: #REF! | BP39: 300149 | BQ39: 0 | BR39: 300149 | BS39: #REF! | BU39: 0 | BV39: 0 | BW39: 0 | BX39: #REF! | BY39: #REF! | BZ39: 0 | CA39: 0 | CB39: 0 | CC39: #REF! | CD39: 0 | CE39: 0 | CF39: 0 | CG39: 0 | CH39: #REF! | CI39: 0 | CJ39: #REF! | CK39: 0 | CL39: 0 | CM39: 0 | CN39: #REF! | CO39: 0 | CP39: 0 | CQ39: 0 | CR39: 0 | CS39: 0 | CT39: 0 | CU39: 0 | CV39: 0 | CW39: 0 | CX39: 0 | CY39: 0 | CZ39: 0 | DA39: 0 | DB39: 0 | DC39: 0 | DD39: 0 | DE39: 0 | DF39: 0 | DG39: 0 | DH39: 0 | DI39: 20491204436 | DJ39: COOPERATIVA AGRARIA DE SERVICIOS MULTIPLES TESORO CHANKA DE KISHUARA - COOPAGROS - KISHUARA | DK39: 02 Cooperativa
A40: Cooperativa Agraria Cafetalera Valle de Incahuasi | B40: CAFÉ | C40: CAFÉ | D40: Apurimac | E40: 030201 | F40: Apurimac | G40: Andahuaylas | H40: Andahuaylas | I40: 1 | J40: 1 | K40: 1 | L40: 1 | M40: 1 | N40: 1 | Q40: PAC | R40: 2018-2019-2020-2021-2022-2023 | S40: 6 | T40: SI | U40: SI | V40: 473 | W40: 374 | X40: 82 | Y40: 456 | Z40: 405 | AA40: 80 | AB40: 485 | AC40: 386 | AD40: 86 | AE40: 472 | AF40: 401 | AG40: 92 | AH40: 493 | AI40: 401 | AJ40: 92 | AK40: 493 | AL40: 0 | AM40: 0 | AN40: 0 | AO40: 0 | AP40: 0 | AQ40: 0 | AR40: 493 | AS40: 0 | AT40: 4 | AU40: 72 | AV40: 6 | AW40: 57 | AX40: 8 | AY40: 7 | AZ40: 18 | BA40: 0 | BB40: 0 | BC40: 0 | BD40: 0 | BE40: 0 | BF40: 22490.34 | BG40: 3082078.1 | BH40: 3104568.5 | BI40: #REF! | BJ40: #REF! | BK40: 0 | BL40: 8063872.3 | BM40: 8063872.3 | BN40: #REF! | BO40: #REF! | BP40: 0 | BQ40: 9080188.9 | BR40: 9080188.9 | BS40: #REF! | BU40: 1723946.9 | BV40: 12670661 | BW40: 14394608 | BX40: #REF! | BY40: #REF! | BZ40: 227111.23 | CA40: 7340280 | CB40: 7567391.3 | CC40: #REF! | CD40: -14394608 | CE40: 0 | CF40: 0 | CG40: 0 | CH40: #REF! | CI40: -7567391.3 | CJ40: #REF! | CK40: 0 | CL40: 0 | CM40: 0 | CN40: #REF! | CO40: 0 | CP40: 0 | CQ40: 0 | CR40: 0 | CS40: 7567391.3 | CT40: 0 | CU40: 0 | CV40: 7567391.3 | CW40: 0 | CX40: 0 | CY40: 0 | CZ40: 0 | DA40: 0 | DB40: 0 | DC40: 0 | DD40: 0 | DE40: 0 | DF40: 0 | DG40: 0 | DH40: 0 | DI40: 20527565376 | DJ40: COOPERATIVA AGRARIA CAFETALERA VALLE DE INCAHUASI | DK40: 02 Cooperativa
A41: Asociacion de Productores Agropecuarios Pampas Callebamba | B41: PALTA | C41: PALTA | D41: Apurimac | E41: 030601 | F41: Apurimac | G41: Chincheros | H41: Chincheros | M41: 1 | N41: 1 | O41: 1 | Q41: PAC | R41: 2022-2023-2024 | S41: 3 | T41: SI | U41: SI | V41: 0 | W41: 0 | X41: 0 | Y41: 0 | Z41: 0 | AA41: 0 | AB41: 0 | AC41: 0 | AD41: 0 | AE41: 0 | AF41: 17 | AG41: 9 | AH41: 26 | AI41: 17 | AJ41: 9 | AK41: 26 | AL41: 15 | AM41: 10 | AN41: 25 | AO41: 0 | AP41: 0 | AQ41: 0 | AR41: 25 | AS41: 0 | AT41: 0 | AU41: 0 | AV41: 0 | AW41: 30 | AX41: 4 | AY41: 26 | AZ41: 2 | BA41: 22 | BB41: 7 | BC41: 0 | BD41: 0 | BE41: 0 | BF41: 0 | BG41: 0 | BH41: 0 | BI41: #REF! | BJ41: #REF! | BK41: 0 | BL41: 0 | BM41: 0 | BN41: #REF! | BO41: #REF! | BP41: 0 | BQ41: 0 | BR41: 0 | BS41: #REF! | BU41: 525700 | BV41: 0 | BW41: 525700 | BX41: #REF! | BY41: #REF! | BZ41: 320000 | CA41: 0 | CB41: 320000 | CC41: #REF! | CD41: -525700 | CE41: 0 | CF41: 0 | CG41: 0 | CH41: #REF! | CI41: -320000 | CJ41: #REF! | CK41: 0 | CL41: 0 | CM41: 0 | CN41: #REF! | CO41: 0 | CP41: 0 | CQ41: 320000 | CR41: 0 | CS41: 0 | CT41: 0 | CU41: 0 | CV41: 320000 | CW41: 0 | CX41: 0 | CY41: 0 | CZ41: 0 | DA41: 0 | DB41: 0 | DC41: 0 | DD41: 0 | DE41: 0 | DF41: 0 | DG41: 0 | DH41: 0 | DI41: 20605216812 | DJ41: ASOCIACION DE PRODUCTORES AGROPECUARIOS PAMPAS-CALLEBAMBA | DK41: 01 Asociación
A42: Asociación de Productores Agropecuarios Quisagui - Rio Blanco | B42: PALTA | C42: PALTA | D42: Apurimac | E42: 030604 | F42: Apurimac | G42: Chincheros | H42: Huaccana | K42: 1 | L42: 1 | M42: 1 | N42: 1 | Q42: PAC | R42: 2020-2021-2022-2023 | S42: 4 | T42: SI | U42: SI | V42: 0 | W42: 0 | X42: 0 | Y42: 0 | Z42: 17 | AA42: 11 | AB42: 28 | AC42: 19 | AD42: 10 | AE42: 29 | AF42: 19 | AG42: 10 | AH42: 29 | AI42: 19 | AJ42: 10 | AK42: 29 | AL42: 0 | AM42: 0 | AN42: 0 | AO42: 0 | AP42: 0 | AQ42: 0 | AR42: 29 | AS42: 0 | AT42: 1 | AU42: 79 | AV42: 2 | AW42: 31 | AX42: 4 | AY42: 28 | AZ42: 2 | BA42: 0 | BB42: 0 | BC42: 0 | BD42: 0 | BE42: 0 | BF42: 0 | BG42: 0 | BH42: 0 | BI42: #REF! | BJ42: #REF! | BK42: 0 | BL42: 0 | BM42: 0 | BN42: #REF! | BO42: #REF! | BP42: 454126.2 | BQ42: 0 | BR42: 454126.2 | BS42: #REF! | BU42: 276300 | BV42: 0 | BW42: 276300 | BX42: #REF! | BY42: #REF! | BZ42: 377500 | CA42: 0 | CB42: 377500 | CC42: #REF! | CD42: -276300 | CE42: 0 | CF42: 0 | CG42: 0 | CH42: #REF! | CI42: -377500 | CJ42: #REF! | CK42: 0 | CL42: 0 | CM42: 0 | CN42: #REF! | CO42: 0 | CP42: 0 | CQ42: 377500 | CR42: 0 | CS42: 0 | CT42: 0 | CU42: 0 | CV42: 377500 | CW42: 0 | CX42: 0 | CY42: 0 | CZ42: 0 | DA42: 0 | DB42: 0 | DC42: 0 | DD42: 0 | DE42: 0 | DF42: 0 | DG42: 0 | DH42: 0 | DI42: 20491248646 | DJ42: ASOCIACION DE PRODUCTORES AGROPECUARIOS QUISAGUI - RIO BLANCO | DK42: 01 Asociación
A43: Asociación de Fruticultores de la Microcuenca de Ongoy los Aynis-Afrumco | B43: PALTA | C43: PALTA | D43: Apurimac | E43: 030606 | F43: Apurimac | G43: Chincheros | H43: Ongoy | L43: 1 | M43: 1 | N43: 1 | O43: 1 | P43: 1 | Q43: PAC | R43: 2021-2022-2023-2024 - 2025 | S43: 5 | T43: SI | U43: SI | V43: 0 | W43: 0 | X43: 0 | Y43: 0 | Z43: 0 | AA43: 0 | AB43: 0 | AC43: 47 | AD43: 10 | AE43: 57 | AF43: 47 | AG43: 10 | AH43: 57 | AI43: 47 | AJ43: 10 | AK43: 57 | AL43: 47 | AM43: 10 | AN43: 57 | AO43: 48 | AP43: 11 | AQ43: 59 | AR43: 59 | AS43: 0 | AT43: 0 | AU43: 55 | AV43: 1 | AW43: 23 | AX43: 5 | AY43: 27 | AZ43: 3 | BA43: 20 | BB43: 7 | BC43: 31 | BD43: 3 | BE43: 0 | BF43: 0 | BG43: 0 | BH43: 0 | BI43: #REF! | BJ43: #REF! | BK43: 0 | BL43: 0 | BM43: 0 | BN43: #REF! | BO43: #REF! | BP43: 250061 | BQ43: 0 | BR43: 250061 | BS43: #REF! | BU43: 1060730 | BV43: 0 | BW43: 1060730 | BX43: #REF! | BY43: #REF! | BZ43: 630000 | CA43: 0 | CB43: 630000 | CC43: #REF! | CD43: -1060730 | CE43: 0 | CF43: 0 | CG43: 0 | CH43: #REF! | CI43: -630000 | CJ43: #REF! | CK43: 435513.01 | CL43: 0 | CM43: 435513.01 | CN43: #REF! | CO43: 0 | CP43: 0 | CQ43: 630000 | CR43: 0 | CS43: 0 | CT43: 0 | CU43: 0 | CV43: 630000 | CW43: 0 | CX43: 0 | CY43: 0 | CZ43: 0 | DA43: 0 | DB43: 0 | DC43: 0 | DD43: 435513.01 | DE43: 0 | DF43: 0 | DG43: 0 | DH43: 435513.01 | DI43: 20491199769 | DJ43: ASOCIACION DE FRUTICULTORES DE LA MICROCUENCA DE ONGOY LOS AYNIS - AFRUMCO | DK43: 01 Asociación
A44: Cooperativa de Servicios Multiples Sur Andinos-Coopsur | B44: QUINUA Y OTROS GRANOS | C44: QUINUA | D44: Apurimac | E44: 030213 | F44: Apurimac | G44: Andahuaylas | H44: San Jeronimo | L44: 1 | M44: 1 | N44: 1 | O44: 1 | P44: 1 | Q44: PAC | R44: 2021-2022-2023-2024 - 2025 | S44: 5 | T44: SI | U44: SI | V44: 0 | W44: 0 | X44: 0 | Y44: 0 | Z44: 0 | AA44: 0 | AB44: 0 | AC44: 72 | AD44: 23 | AE44: 95 | AF44: 72 | AG44: 23 | AH44: 95 | AI44: 72 | AJ44: 23 | AK44: 95 | AL44: 60 | AM44: 25 | AN44: 85 | AO44: 76 | AP44: 26 | AQ44: 102 | AR44: 102 | AS44: 0 | AT44: 0 | AU44: 60 | AV44: 8 | AW44: 21 | AX44: 2 | AY44: 26 | AZ44: 4 | BA44: 12 | BB44: 4 | BC44: 58 | BD44: 8 | BE44: 0 | BF44: 0 | BG44: 0 | BH44: 0 | BI44: #REF! | BJ44: #REF! | BK44: 0 | BL44: 0 | BM44: 0 | BN44: #REF! | BO44: #REF! | BP44: 216103.95 | BQ44: 0 | BR44: 216103.95 | BS44: #REF! | BU44: 377066.8 | BV44: 0 | BW44: 377066.8 | BX44: #REF! | BY44: #REF! | BZ44: 568018.75 | CA44: 0 | CB44: 568018.75 | CC44: #REF! | CD44: -377066.8 | CE44: 1274243.5 | CF44: 0 | CG44: 1274243.5 | CH44: #REF! | CI44: -568018.75 | CJ44: #REF! | CK44: 3685880.6 | CL44: 0 | CM44: 3685880.6 | CN44: #REF! | CO44: -1274243.5 | CP44: 0 | CQ44: 0 | CR44: 0 | CS44: 568018.75 | CT44: 0 | CU44: 0 | CV44: 568018.75 | CW44: 0 | CX44: 0 | CY44: 1274243.5 | CZ44: 0 | DA44: 0 | DB44: 1274243.5 | DC44: 0 | DD44: 3673784.6 | DE44: 12096 | DF44: 0 | DG44: 0 | DH44: 3685880.6 | DI44: 20601006368 | DJ44: COOPERATIVA AGRARIA DE SERVICIOS MULTIPLES SUR ANDINO - COOPSUR | DK44: 02 Cooperativa
A45: Asociacion de Productores Flor de Papa de Chullcusa Alta | B45: PAPA | C45: PAPA NATIVA | D45: Apurimac | E45: 030213 | F45: Apurimac | G45: Andahuaylas | H45: San Jeronimo | K45: 1 | L45: 1 | M45: 1 | N45: 1 | Q45: PAC | R45: 2020-2021-2022-2023 | S45: 4 | T45: SI | U45: SI | V45: 0 | W45: 0 | X45: 0 | Y45: 0 | Z45: 19 | AA45: 3 | AB45: 22 | AC45: 15 | AD45: 4 | AE45: 19 | AF45: 15 | AG45: 4 | AH45: 19 | AI45: 15 | AJ45: 4 | AK45: 19 | AL45: 0 | AM45: 0 | AN45: 0 | AO45: 0 | AP45: 0 | AQ45: 0 | AR45: 19 | AS45: 0 | AT45: 2 | AU45: 50 | AV45: 7 | AW45: 14 | AX45: 2 | AY45: 14 | AZ45: 3 | BA45: 0 | BB45: 0 | BC45: 0 | BD45: 0 | BE45: 0 | BF45: 0 | BG45: 0 | BH45: 0 | BI45: #REF! | BJ45: #REF! | BK45: 0 | BL45: 0 | BM45: 0 | BN45: #REF! | BO45: #REF! | BP45: 267925 | BQ45: 0 | BR45: 267925 | BS45: #REF! | BU45: 157500 | BV45: 0 | BW45: 157500 | BX45: #REF! | BY45: #REF! | BZ45: 215680 | CA45: 0 | CB45: 215680 | CC45: #REF! | CD45: -157500 | CE45: 0 | CF45: 0 | CG45: 0 | CH45: #REF! | CI45: -215680 | CJ45: #REF! | CK45: 0 | CL45: 0 | CM45: 0 | CN45: #REF! | CO45: 0 | CP45: 0 | CQ45: 215680 | CR45: 0 | CS45: 0 | CT45: 0 | CU45: 0 | CV45: 215680 | CW45: 0 | CX45: 0 | CY45: 0 | CZ45: 0 | DA45: 0 | DB45: 0 | DC45: 0 | DD45: 0 | DE45: 0 | DF45: 0 | DG45: 0 | DH45: 0 | DI45: 20490672835 | DJ45: ASOCIACION DE PRODUCTORES FLOR DE PAPA DE CHULLCUISA ALTA - ASOCIACION FLOR DE PAPA | DK45: 01 Asociación
A46: Asociacion Productores Agropecuarios Marco Vilca Argama Alta | B46: PAPA | C46: PAPA NATIVA | D46: Apurimac | E46: 030209 | F46: Apurimac | G46: Andahuaylas | H46: Pacucha | M46: 1 | N46: 1 | Q46: PAC | R46: 2022-2023 | S46: 2 | T46: SI | U46: SI | V46: 0 | W46: 0 | X46: 0 | Y46: 0 | Z46: 0 | AA46: 0 | AB46: 0 | AC46: 0 | AD46: 0 | AE46: 0 | AF46: 17 | AG46: 10 | AH46: 27 | AI46: 17 | AJ46: 10 | AK46: 27 | AL46: 0 | AM46: 0 | AN46: 0 | AO46: 0 | AP46: 0 | AQ46: 0 | AR46: 27 | AS46: 0 | AT46: 0 | AU46: 0 | AV46: 0 | AW46: 13 | AX46: 3 | AY46: 12 | AZ46: 2 | BA46: 0 | BB46: 0 | BC46: 0 | BD46: 0 | BE46: 0 | BF46: 0 | BG46: 0 | BH46: 0 | BI46: #REF! | BJ46: #REF! | BK46: 0 | BL46: 0 | BM46: 0 | BN46: #REF! | BO46: #REF! | BP46: 0 | BQ46: 0 | BR46: 0 | BS46: #REF! | BU46: 106710 | BV46: 0 | BW46: 106710 | BX46: #REF! | BY46: #REF! | BZ46: 148900 | CA46: 0 | CB46: 148900 | CC46: #REF! | CD46: -106710 | CE46: 0 | CF46: 0 | CG46: 0 | CH46: #REF! | CI46: -148900 | CJ46: #REF! | CK46: 0 | CL46: 0 | CM46: 0 | CN46: #REF! | CO46: 0 | CP46: 38700 | CQ46: 110200 | CR46: 0 | CS46: 0 | CT46: 0 | CU46: 0 | CV46: 148900 | CW46: 0 | CX46: 0 | CY46: 0 | CZ46: 0 | DA46: 0 | DB46: 0 | DC46: 0 | DD46: 0 | DE46: 0 | DF46: 0 | DG46: 0 | DH46: 0 | DI46: 20602684335 | DJ46: ASOCIACION PRODUCTORES AGROPECUARIOS MARCO VILCA ARGAMA ALTA | DK46: 01 Asociación
A47: Cooperativa de Servicio Multiples Campo Verde de Jose Maria Arguedas | B47: QUINUA Y OTROS GRANOS | C47: QUINUA | D47: Apurimac | E47: 030220 | F47: Apurimac | G47: Andahuaylas | H47: Jose Maria Arguedas | M47: 1 | N47: 1 | Q47: PAC | R47: 2022-2023 | S47: 2 | T47: SI | U47: SI | V47: 0 | W47: 0 | X47: 0 | Y47: 0 | Z47: 0 | AA47: 0 | AB47: 0 | AC47: 0 | AD47: 0 | AE47: 0 | AF47: 42 | AG47: 34 | AH47: 76 | AI47: 42 | AJ47: 34 | AK47: 76 | AL47: 0 | AM47: 0 | AN47: 0 | AO47: 0 | AP47: 0 | AQ47: 0 | AR47: 76 | AS47: 0 | AT47: 0 | AU47: 0 | AV47: 0 | AW47: 19 | AX47: 2 | AY47: 16 | AZ47: 3 | BA47: 0 | BB47: 0 | BC47: 0 | BD47: 0 | BE47: 0 | BF47: 0 | BG47: 0 | BH47: 0 | BI47: #REF! | BJ47: #REF! | BK47: 0 | BL47: 0 | BM47: 0 | BN47: #REF! | BO47: #REF! | BP47: 0 | BQ47: 0 | BR47: 0 | BS47: #REF! | BU47: 0 | BV47: 0 | BW47: 0 | BX47: #REF! | BY47: #REF! | BZ47: 216575.5 | CA47: 0 | CB47: 216575.5 | CC47: #REF! | CD47: 0 | CE47: 0 | CF47: 0 | CG47: 0 | CH47: #REF! | CI47: -216575.5 | CJ47: #REF! | CK47: 0 | CL47: 0 | CM47: 0 | CN47: #REF! | CO47: 0 | CP47: 0 | CQ47: 216575.5 | CR47: 0 | CS47: 0 | CT47: 0 | CU47: 0 | CV47: 216575.5 | CW47: 0 | CX47: 0 | CY47: 0 | CZ47: 0 | DA47: 0 | DB47: 0 | DC47: 0 | DD47: 0 | DE47: 0 | DF47: 0 | DG47: 0 | DH47: 0 | DI47: 20606396849 | DJ47: COOPERATIVA AGRARIA DE SERVICIOS MULTIPLES CAMPO VERDE DE JOSE MARIA ARGUEDAS - CASMUCAV | DK47: 02 Cooperativa
A48: Asociacion de Productores Agropecuarios Sumacc Inti de Huancabamba - Apasiha | B48: PAPA | C48: PAPA NATIVA | D48: Apurimac | E48: 030220 | F48: Apurimac | G48: Andahuaylas | H48: Jose Maria Arguedas | M48: 1 | N48: 1 | Q48: PAC | R48: 2022-2023 | S48: 2 | T48: SI | U48: SI | V48: 0 | W48: 0 | X48: 0 | Y48: 0 | Z48: 0 | AA48: 0 | AB48: 0 | AC48: 0 | AD48: 0 | AE48: 0 | AF48: 17 | AG48: 8 | AH48: 25 | AI48: 17 | AJ48: 8 | AK48: 25 | AL48: 0 | AM48: 0 | AN48: 0 | AO48: 0 | AP48: 0 | AQ48: 0 | AR48: 25 | AS48: 0 | AT48: 0 | AU48: 0 | AV48: 0 | AW48: 18 | AX48: 3 | AY48: 14 | AZ48: 3 | BA48: 0 | BB48: 0 | BC48: 0 | BD48: 0 | BE48: 0 | BF48: 0 | BG48: 0 | BH48: 0 | BI48: #REF! | BJ48: #REF! | BK48: 0 | BL48: 0 | BM48: 0 | BN48: #REF! | BO48: #REF! | BP48: 0 | BQ48: 0 | BR48: 0 | BS48: #REF! | BU48: 73000 | BV48: 0 | BW48: 73000 | BX48: #REF! | BY48: #REF! | BZ48: 216700 | CA48: 0 | CB48: 216700 | CC48: #REF! | CD48: -73000 | CE48: 0 | CF48: 0 | CG48: 0 | CH48: #REF! | CI48: -216700 | CJ48: #REF! | CK48: 0 | CL48: 0 | CM48: 0 | CN48: #REF! | CO48: 0 | CP48: 0 | CQ48: 216700 | CR48: 0 | CS48: 0 | CT48: 0 | CU48: 0 | CV48: 216700 | CW48: 0 | CX48: 0 | CY48: 0 | CZ48: 0 | DA48: 0 | DB48: 0 | DC48: 0 | DD48: 0 | DE48: 0 | DF48: 0 | DG48: 0 | DH48: 0 | DI48: 20491164469 | DJ48: ASOCIACION DE PRODUCTORES AGROPECUARIOS SUMACC INTI DE HUANCABAMBA - APASIHA | DK48: 01 Asociación
A49: Central de Comunidades Campesinas de Ranracancha | B49: QUINUA Y OTROS GRANOS | C49: QUINUA | D49: Apurimac | E49: 030608 | F49: Apurimac | G49: Chincheros | H49: Ranracancha | M49: 1 | N49: 1 | O49: 1 | Q49: PAC | R49: 2022-2023-2024 | S49: 3 | T49: SI | U49: SI | V49: 0 | W49: 0 | X49: 0 | Y49: 0 | Z49: 0 | AA49: 0 | AB49: 0 | AC49: 0 | AD49: 0 | AE49: 0 | AF49: 474 | AG49: 129 | AH49: 603 | AI49: 474 | AJ49: 129 | AK49: 603 | AL49: 475 | AM49: 131 | AN49: 606 | AO49: 0 | AP49: 0 | AQ49: 0 | AR49: 606 | AS49: 0 | AT49: 0 | AU49: 0 | AV49: 0 | AW49: 22 | AX49: 3 | AY49: 25 | AZ49: 12 | BA49: 12 | BB49: 0 | BC49: 0 | BD49: 0 | BE49: 0 | BF49: 0 | BG49: 0 | BH49: 0 | BI49: #REF! | BJ49: #REF! | BK49: 0 | BL49: 0 | BM49: 0 | BN49: #REF! | BO49: #REF! | BP49: 0 | BQ49: 0 | BR49: 0 | BS49: #REF! | BU49: 337573.42 | BV49: 0 | BW49: 337573.42 | BX49: #REF! | BY49: #REF! | BZ49: 269924.79 | CA49: 0 | CB49: 269924.79 | CC49: #REF! | CD49: -337573.42 | CE49: 0 | CF49: 0 | CG49: 0 | CH49: #REF! | CI49: -269924.79 | CJ49: #REF! | CK49: 0 | CL49: 0 | CM49: 0 | CN49: #REF! | CO49: 0 | CP49: 0 | CQ49: 0 | CR49: 0 | CS49: 269924.83 | CT49: 0 | CU49: 0 | CV49: 269924.83 | CW49: 0 | CX49: 0 | CY49: 0 | CZ49: 0 | DA49: 0 | DB49: 0 | DC49: 0 | DD49: 0 | DE49: 0 | DF49: 0 | DG49: 0 | DH49: 0 | DI49: 20526888686 | DJ49: CENTRAL DE COMUNIDADES CAMPESINAS DE RANRACANCHA | DK49: 01 Asociación
A50: Cooperativa Agraria Bio-Orgánica Condesuyos - Coopabic | B50: DERIVADOS LACTEOS | C50: QUESOS MADURADOS | D50: Arequipa | E50: 040605 | F50: Arequipa | G50: Condesuyos | H50: Iray | I50: 1 | Q50: PAC | R50: 2018 | S50: 1 | T50: NO | U50: NO | V50: 84 | W50: 0 | X50: 0 | Y50: 0 | Z50: 0 | AA50: 0 | AB50: 0 | AC50: 0 | AD50: 0 | AE50: 0 | AF50: 0 | AG50: 0 | AH50: 0 | AI50: 0 | AJ50: 0 | AK50: 0 | AL50: 0 | AM50: 0 | AN50: 0 | AO50: 0 | AP50: 0 | AQ50: 0 | AR50: 84 | AS50: 0 | AT50: 0 | AU50: 0 | AV50: 0 | AW50: 0 | AX50: 0 | AY50: 0 | AZ50: 0 | BA50: 0 | BB50: 0 | BC50: 0 | BD50: 0 | BE50: 0 | BF50: 0 | BG50: 0 | BH50: 0 | BI50: #REF! | BJ50: #REF! | BK50: 0 | BL50: 0 | BM50: 0 | BN50: #REF! | BO50: #REF! | BP50: 0 | BQ50: 0 | BR50: 0 | BS50: #REF! | BU50: 0 | BV50: 0 | BW50: 0 | BX50: #REF! | BY50: #REF! | BZ50: 0 | CA50: 0 | CB50: 0 | CC50: #REF! | CD50: 0 | CE50: 0 | CF50: 0 | CG50: 0 | CH50: #REF! | CI50: 0 | CJ50: #REF! | CK50: 0 | CL50: 0 | CM50: 0 | CN50: #REF! | CO50: 0 | CP50: 0 | CQ50: 0 | CR50: 0 | CS50: 0 | CT50: 0 | CU50: 0 | CV50: 0 | CW50: 0 | CX50: 0 | CY50: 0 | CZ50: 0 | DA50: 0 | DB50: 0 | DC50: 0 | DD50: 0 | DE50: 0 | DF50: 0 | DG50: 0 | DH50: 0 | DI50: 20600122330 | DJ50: COOPERATIVA AGRARIA BIO-ORGANICA CONDESUYOS - COOPABIC | DK50: 02 Cooperativa
A51: Cooperativa Agraria de Productos Bio Orgánicos y Granos Andinos de Viraco - Cooprorganic | B51: QUINUA Y OTROS GRANOS | C51: QUINUA | D51: Arequipa | E51: 040414 | F51: Arequipa | G51: Castilla | H51: Viraco | I51: 1 | J51: 1 | K51: 1 | L51: 1 | M51: 1 | Q51: PAC | R51: 2018-2019-2020-2021-2022 | S51: 5 | T51: SI | U51: SI | V51: 14 | W51: 23 | X51: 3 | Y51: 26 | Z51: 22 | AA51: 1 | AB51: 23 | AC51: 22 | AD51: 1 | AE51: 23 | AF51: 22 | AG51: 1 | AH51: 23 | AI51: 0 | AJ51: 0 | AK51: 0 | AL51: 0 | AM51: 0 | AN51: 0 | AO51: 0 | AP51: 0 | AQ51: 0 | AR51: 23 | AS51: 4 | AT51: 7 | AU51: 18 | AV51: 8 | AW51: 24 | AX51: 4 | AY51: 0 | AZ51: 0 | BA51: 0 | BB51: 0 | BC51: 0 | BD51: 0 | BE51: 0 | BF51: 245900.2 | BG51: 0 | BH51: 245900.2 | BI51: #REF! | BJ51: #REF! | BK51: 174050 | BL51: 0 | BM51: 174050 | BN51: #REF! | BO51: #REF! | BP51: 0 | BQ51: 0 | BR51: 0 | BS51: #REF! | BU51: 0 | BV51: 0 | BW51: 0 | BX51: #REF! | BY51: #REF! | BZ51: 0 | CA51: 0 | CB51: 0 | CC51: #REF! | CD51: 0 | CE51: 0 | CF51: 0 | CG51: 0 | CH51: #REF! | CI51: 0 | CJ51: #REF! | CK51: 0 | CL51: 0 | CM51: 0 | CN51: #REF! | CO51: 0 | CP51: 0 | CQ51: 0 | CR51: 0 | CS51: 0 | CT51: 0 | CU51: 0 | CV51: 0 | CW51: 0 | CX51: 0 | CY51: 0 | CZ51: 0 | DA51: 0 | DB51: 0 | DC51: 0 | DD51: 0 | DE51: 0 | DF51: 0 | DG51: 0 | DH51: 0 | DI51: 20601106699 | DJ51: COOPERATIVA AGRARIA DE PRODUCTOS BIO ORGANICOS Y GRANOS ANDINOS DE VIRACO - COOPRORGANIC | DK51: 02 Cooperativa
A52: Cooperativa Agraria Bio-Organica Condesuyos - Coopabic | B52: QUINUA Y OTROS GRANOS | C52: QUINUA | D52: Arequipa | E52: 040601 | F52: Arequipa | G52: Condesuyos | H52: Chuquibamba | I52: 1 | J52: 1 | K52: 1 | L52: 1 | M52: 1 | Q52: PAC | R52: 2018-2019-2020-2021-2022 | S52: 5 | T52: SI | U52: SI | V52: 100 | W52: 94 | X52: 23 | Y52: 117 | Z52: 68 | AA52: 23 | AB52: 91 | AC52: 28 | AD52: 3 | AE52: 31 | AF52: 28 | AG52: 3 | AH52: 31 | AI52: 0 | AJ52: 0 | AK52: 0 | AL52: 0 | AM52: 0 | AN52: 0 | AO52: 0 | AP52: 0 | AQ52: 0 | AR52: 31 | AS52: 4 | AT52: 7 | AU52: 19 | AV52: 8 | AW52: 23 | AX52: 4 | AY52: 0 | AZ52: 0 | BA52: 0 | BB52: 0 | BC52: 0 | BD52: 0 | BE52: 0 | BF52: 264992 | BG52: 0 | BH52: 264992 | BI52: #REF! | BJ52: #REF! | BK52: 190334 | BL52: 0 | BM52: 190334 | BN52: #REF! | BO52: #REF! | BP52: 0 | BQ52: 0 | BR52: 0 | BS52: #REF! | BU52: 0 | BV52: 0 | BW52: 0 | BX52: #REF! | BY52: #REF! | BZ52: 0 | CA52: 0 | CB52: 0 | CC52: #REF! | CD52: 0 | CE52: 0 | CF52: 0 | CG52: 0 | CH52: #REF! | CI52: 0 | CJ52: #REF! | CK52: 0 | CL52: 0 | CM52: 0 | CN52: #REF! | CO52: 0 | CP52: 0 | CQ52: 0 | CR52: 0 | CS52: 0 | CT52: 0 | CU52: 0 | CV52: 0 | CW52: 0 | CX52: 0 | CY52: 0 | CZ52: 0 | DA52: 0 | DB52: 0 | DC52: 0 | DD52: 0 | DE52: 0 | DF52: 0 | DG52: 0 | DH52: 0 | DI52: 20600122330 | DJ52: COOPERATIVA AGRARIA BIO-ORGANICA CONDESUYOS - COOPABIC | DK52: 02 Cooperativa
A53: Empresa Agroindustrial y Servicios Generales | B53: DERIVADOS LACTEOS | C53: DERIVADOS LACTEOS | D53: Arequipa | E53: 040520 | F53: Arequipa | G53: Caylloma | H53: Majes | I53: 1 | J53: 1 | K53: 1 | L53: 1 | M53: 1 | Q53: PAC | R53: 2018-2019-2020-2021-2022 | S53: 5 | T53: SI | U53: SI | V53: 62 | W53: 47 | X53: 15 | Y53: 62 | Z53: 49 | AA53: 13 | AB53: 62 | AC53: 47 | AD53: 15 | AE53: 62 | AF53: 47 | AG53: 15 | AH53: 62 | AI53: 0 | AJ53: 0 | AK53: 0 | AL53: 0 | AM53: 0 | AN53: 0 | AO53: 0 | AP53: 0 | AQ53: 0 | AR53: 62 | AS53: 4 | AT53: 3 | AU53: 53 | AV53: 10 | AW53: 31 | AX53: 5 | AY53: 0 | AZ53: 0 | BA53: 0 | BB53: 0 | BC53: 0 | BD53: 0 | BE53: 0 | BF53: 39645.34 | BG53: 0 | BH53: 39645.34 | BI53: #REF! | BJ53: #REF! | BK53: 37660.8 | BL53: 0 | BM53: 37660.8 | BN53: #REF! | BO53: #REF! | BP53: 74362.4 | BQ53: 0 | BR53: 74362.4 | BS53: #REF! | BU53: 72365.99 | BV53: 0 | BW53: 72365.99 | BX53: #REF! | BY53: #REF! | BZ53: 0 | CA53: 0 | CB53: 0 | CC53: #REF! | CD53: -72365.99 | CE53: 0 | CF53: 0 | CG53: 0 | CH53: #REF! | CI53: 0 | CJ53: #REF! | CK53: 0 | CL53: 0 | CM53: 0 | CN53: #REF! | CO53: 0 | CP53: 0 | CQ53: 0 | CR53: 0 | CS53: 0 | CT53: 0 | CU53: 0 | CV53: 0 | CW53: 0 | CX53: 0 | CY53: 0 | CZ53: 0 | DA53: 0 | DB53: 0 | DC53: 0 | DD53: 0 | DE53: 0 | DF53: 0 | DG53: 0 | DH53: 0 | DI53: 20600690184 | DJ53: EMPRESA AGROINDUSTRIAL Y SERVICIOS GENERALES EL PARAISO S.A. | DK53: 07 Otros
A54: Productos Lacteos Arequipa S.a. | B54: DERIVADOS LACTEOS | C54: DERIVADOS LACTEOS | D54: Arequipa | E54: 040520 | F54: Arequipa | G54: Caylloma | H54: Majes | I54: 1 | J54: 1 | Q54: PAC | R54: 2018-2019 | S54: 2 | T54: SI | U54: NO | V54: 52 | W54: 43 | X54: 9 | Y54: 52 | Z54: 0 | AA54: 0 | AB54: 0 | AC54: 0 | AD54: 0 | AE54: 0 | AF54: 0 | AG54: 0 | AH54: 0 | AI54: 0 | AJ54: 0 | AK54: 0 | AL54: 0 | AM54: 0 | AN54: 0 | AO54: 0 | AP54: 0 | AQ54: 0 | AR54: 52 | AS54: 0 | AT54: 0 | AU54: 0 | AV54: 0 | AW54: 0 | AX54: 0 | AY54: 0 | AZ54: 0 | BA54: 0 | BB54: 0 | BC54: 0 | BD54: 0 | BE54: 0 | BF54: 0 | BG54: 0 | BH54: 0 | BI54: #REF! | BJ54: #REF! | BK54: 0 | BL54: 0 | BM54: 0 | BN54: #REF! | BO54: #REF! | BP54: 0 | BQ54: 0 | BR54: 0 | BS54: #REF! | BU54: 0 | BV54: 0 | BW54: 0 | BX54: #REF! | BY54: #REF! | BZ54: 0 | CA54: 0 | CB54: 0 | CC54: #REF! | CD54: 0 | CE54: 0 | CF54: 0 | CG54: 0 | CH54: #REF! | CI54: 0 | CJ54: #REF! | CK54: 0 | CL54: 0 | CM54: 0 | CN54: #REF! | CO54: 0 | CP54: 0 | CQ54: 0 | CR54: 0 | CS54: 0 | CT54: 0 | CU54: 0 | CV54: 0 | CW54: 0 | CX54: 0 | CY54: 0 | CZ54: 0 | DA54: 0 | DB54: 0 | DC54: 0 | DD54: 0 | DE54: 0 | DF54: 0 | DG54: 0 | DH54: 0 | DI54: 20600838947 | DJ54: PRODUCTOS LACTEOS AREQUIPA S.A. | DK54: 07 Otros
A55: Asociacion de Criadores de Alpacas del Distrito de Sibayo - Ascadis | B55: FIBRA DE ALPACA | C55: FIBRA DE ALPACA | D55: Arequipa | E55: 040515 | F55: Arequipa | G55: Caylloma | H55: Sibayo | J55: 1 | K55: 1 | L55: 1 | Q55: PAC | R55: 2019-2020-2021 | S55: 3 | T55: SI | U55: SI | V55: 0 | W55: 25 | X55: 20 | Y55: 45 | Z55: 26 | AA55: 20 | AB55: 46 | AC55: 36 | AD55: 23 | AE55: 59 | AF55: 0 | AG55: 0 | AH55: 0 | AI55: 0 | AJ55: 0 | AK55: 0 | AL55: 0 | AM55: 0 | AN55: 0 | AO55: 0 | AP55: 0 | AQ55: 0 | AR55: 59 | AS55: 10 | AT55: 4 | AU55: 22 | AV55: 2 | AW55: 0 | AX55: 0 | AY55: 0 | AZ55: 0 | BA55: 0 | BB55: 0 | BC55: 0 | BD55: 0 | BE55: 0 | BF55: 11063.04 | BG55: 0 | BH55: 11063.04 | BI55: #REF! | BJ55: #REF! | BK55: 88203.65 | BL55: 0 | BM55: 88203.65 | BN55: #REF! | BO55: #REF! | BP55: 0 | BQ55: 0 | BR55: 0 | BS55: #REF! | BU55: 0 | BV55: 0 | BW55: 0 | BX55: #REF! | BY55: #REF! | BZ55: 0 | CA55: 0 | CB55: 0 | CC55: #REF! | CD55: 0 | CE55: 0 | CF55: 0 | CG55: 0 | CH55: #REF! | CI55: 0 | CJ55: #REF! | CK55: 0 | CL55: 0 | CM55: 0 | CN55: #REF! | CO55: 0 | CP55: 0 | CQ55: 0 | CR55: 0 | CS55: 0 | CT55: 0 | CU55: 0 | CV55: 0 | CW55: 0 | CX55: 0 | CY55: 0 | CZ55: 0 | DA55: 0 | DB55: 0 | DC55: 0 | DD55: 0 | DE55: 0 | DF55: 0 | DG55: 0 | DH55: 0 | DI55: 20455129321 | DJ55: ASOCIACIÓN DE CRIADORES DE ALPACAS DEL DISTRITO DE SIBAYO ASCADIS | DK55: 01 Asociación
A56: Asociacion de Productores de Leche - Asproleche | B56: DERIVADOS LACTEOS | C56: DERIVADOS LACTEOS | D56: Arequipa | E56: 040601 | F56: Arequipa | G56: Condesuyos | H56: Chuquibamba | J56: 1 | K56: 1 | L56: 1 | Q56: PAC | R56: 2019-2020-2021 | S56: 3 | T56: SI | U56: SI | V56: 0 | W56: 18 | X56: 5 | Y56: 23 | Z56: 16 | AA56: 6 | AB56: 22 | AC56: 16 | AD56: 6 | AE56: 22 | AF56: 0 | AG56: 0 | AH56: 0 | AI56: 0 | AJ56: 0 | AK56: 0 | AL56: 0 | AM56: 0 | AN56: 0 | AO56: 0 | AP56: 0 | AQ56: 0 | AR56: 22 | AS56: 13 | AT56: 9 | AU56: 54 | AV56: 8 | AW56: 0 | AX56: 0 | AY56: 0 | AZ56: 0 | BA56: 0 | BB56: 0 | BC56: 0 | BD56: 0 | BE56: 0 | BF56: 273451.44 | BG56: 0 | BH56: 273451.44 | BI56: #REF! | BJ56: #REF! | BK56: 311900.96 | BL56: 0 | BM56: 311900.96 | BN56: #REF! | BO56: #REF! | BP56: 323919.98 | BQ56: 0 | BR56: 323919.98 | BS56: #REF! | BU56: 0 | BV56: 0 | BW56: 0 | BX56: #REF! | BY56: #REF! | BZ56: 0 | CA56: 0 | CB56: 0 | CC56: #REF! | CD56: 0 | CE56: 0 | CF56: 0 | CG56: 0 | CH56: #REF! | CI56: 0 | CJ56: #REF! | CK56: 0 | CL56: 0 | CM56: 0 | CN56: #REF! | CO56: 0 | CP56: 0 | CQ56: 0 | CR56: 0 | CS56: 0 | CT56: 0 | CU56: 0 | CV56: 0 | CW56: 0 | CX56: 0 | CY56: 0 | CZ56: 0 | DA56: 0 | DB56: 0 | DC56: 0 | DD56: 0 | DE56: 0 | DF56: 0 | DG56: 0 | DH56: 0 | DI56: 20604817146 | DJ56: ASOCIACION DE PRODUCTORES GANADEROS, LECHEROS Y AGRICULTORA ECOLOGICA DE CUYAY - CHUQUIBAMBA | DK56: 01 Asociación
A57: Cooperativa de Servicios Especiales Alpaqueros los Watayponchos de Caylloma Cosecay | B57: FIBRA DE ALPACA | C57: FIBRA DE ALPACA | D57: Arequipa | E57: 040505 | F57: Arequipa | G57: Caylloma | H57: Caylloma | I57: 1 | J57: 1 | K57: 1 | L57: 1 | Q57: PAC | R57: 2018-2019-2020-2021 | S57: 4 | T57: SI | U57: SI | V57: 125 | W57: 107 | X57: 18 | Y57: 125 | Z57: 108 | AA57: 16 | AB57: 124 | AC57: 59 | AD57: 19 | AE57: 78 | AF57: 0 | AG57: 0 | AH57: 0 | AI57: 0 | AJ57: 0 | AK57: 0 | AL57: 0 | AM57: 0 | AN57: 0 | AO57: 0 | AP57: 0 | AQ57: 0 | AR57: 78 | AS57: 5 | AT57: 3 | AU57: 52 | AV57: 1 | AW57: 0 | AX57: 0 | AY57: 0 | AZ57: 0 | BA57: 0 | BB57: 0 | BC57: 0 | BD57: 0 | BE57: 0 | BF57: 172935.79 | BG57: 0 | BH57: 172935.79 | BI57: #REF! | BJ57: #REF! | BK57: 37409.42 | BL57: 0 | BM57: 37409.42 | BN57: #REF! | BO57: #REF! | BP57: 211780.74 | BQ57: 0 | BR57: 211780.74 | BS57: #REF! | BU57: 0 | BV57: 0 | BW57: 0 | BX57: #REF! | BY57: #REF! | BZ57: 0 | CA57: 0 | CB57: 0 | CC57: #REF! | CD57: 0 | CE57: 0 | CF57: 0 | CG57: 0 | CH57: #REF! | CI57: 0 | CJ57: #REF! | CK57: 0 | CL57: 0 | CM57: 0 | CN57: #REF! | CO57: 0 | CP57: 0 | CQ57: 0 | CR57: 0 | CS57: 0 | CT57: 0 | CU57: 0 | CV57: 0 | CW57: 0 | CX57: 0 | CY57: 0 | CZ57: 0 | DA57: 0 | DB57: 0 | DC57: 0 | DD57: 0 | DE57: 0 | DF57: 0 | DG57: 0 | DH57: 0 | DI57: 20539422881 | DJ57: COOPERATIVA DE SERVICIOS ESPECIALES ALPAQUEROS LOS WATAY PONCHOS DE CAYLLOMA - COSECAY | DK57: 02 Cooperativa
A58: Cooperativa de Servicios Especiales Yurac Qori | B58: FIBRA DE ALPACA | C58: FIBRA DE ALPACA | D58: Arequipa | E58: 040517 | F58: Arequipa | G58: Caylloma | H58: Tisco | I58: 1 | J58: 1 | K58: 1 | L58: 1 | Q58: PAC | R58: 2018-2019-2020-2021 | S58: 4 | T58: SI | U58: SI | V58: 74 | W58: 17 | X58: 10 | Y58: 27 | Z58: 19 | AA58: 8 | AB58: 27 | AC58: 20 | AD58: 10 | AE58: 30 | AF58: 0 | AG58: 0 | AH58: 0 | AI58: 0 | AJ58: 0 | AK58: 0 | AL58: 0 | AM58: 0 | AN58: 0 | AO58: 0 | AP58: 0 | AQ58: 0 | AR58: 30 | AS58: 3 | AT58: 2 | AU58: 23 | AV58: 1 | AW58: 0 | AX58: 0 | AY58: 0 | AZ58: 0 | BA58: 0 | BB58: 0 | BC58: 0 | BD58: 0 | BE58: 0 | BF58: 25951.38 | BG58: 0 | BH58: 25951.38 | BI58: #REF! | BJ58: #REF! | BK58: 86614.81 | BL58: 0 | BM58: 86614.81 | BN58: #REF! | BO58: #REF! | BP58: 33169.38 | BQ58: 0 | BR58: 33169.38 | BS58: #REF! | BU58: 0 | BV58: 0 | BW58: 0 | BX58: #REF! | BY58: #REF! | BZ58: 0 | CA58: 0 | CB58: 0 | CC58: #REF! | CD58: 0 | CE58: 0 | CF58: 0 | CG58: 0 | CH58: #REF! | CI58: 0 | CJ58: #REF! | CK58: 0 | CL58: 0 | CM58: 0 | CN58: #REF! | CO58: 0 | CP58: 0 | CQ58: 0 | CR58: 0 | CS58: 0 | CT58: 0 | CU58: 0 | CV58: 0 | CW58: 0 | CX58: 0 | CY58: 0 | CZ58: 0 | DA58: 0 | DB58: 0 | DC58: 0 | DD58: 0 | DE58: 0 | DF58: 0 | DG58: 0 | DH58: 0 | DI58: 20558183552 | DJ58: COOPERATIVA DE SERVICIOS ESPECIALES YURAC QORI TISCO | DK58: 02 Cooperativa
A59: Corporación Asociativa la Joya | B59: PALTA | C59: PALTA | D59: Arequipa | E59: 040108 | F59: Arequipa | G59: Arequipa | H59: La Joya | I59: 1 | J59: 1 | K59: 1 | L59: 1 | M59: 1 | Q59: PAC | R59: 2018-2019-2020-2021-2022 | S59: 5 | T59: SI | U59: SI | V59: 120 | W59: 54 | X59: 24 | Y59: 78 | Z59: 53 | AA59: 20 | AB59: 73 | AC59: 48 | AD59: 21 | AE59: 69 | AF59: 48 | AG59: 21 | AH59: 69 | AI59: 0 | AJ59: 0 | AK59: 0 | AL59: 0 | AM59: 0 | AN59: 0 | AO59: 0 | AP59: 0 | AQ59: 0 | AR59: 69 | AS59: 11 | AT59: 8 | AU59: 90 | AV59: 6 | AW59: 27 | AX59: 4 | AY59: 0 | AZ59: 0 | BA59: 0 | BB59: 0 | BC59: 0 | BD59: 0 | BE59: 307898.13 | BF59: 390389.84 | BG59: 0 | BH59: 390389.84 | BI59: #REF! | BJ59: #REF! | BK59: 290025.49 | BL59: 0 | BM59: 290025.49 | BN59: #REF! | BO59: #REF! | BP59: 1287636 | BQ59: 0 | BR59: 1287636 | BS59: #REF! | BU59: 706410.4 | BV59: 0 | BW59: 706410.4 | BX59: #REF! | BY59: #REF! | BZ59: 0 | CA59: 0 | CB59: 0 | CC59: #REF! | CD59: -706410.4 | CE59: 0 | CF59: 0 | CG59: 0 | CH59: #REF! | CI59: 0 | CJ59: #REF! | CK59: 0 | CL59: 0 | CM59: 0 | CN59: #REF! | CO59: 0 | CP59: 0 | CQ59: 0 | CR59: 0 | CS59: 0 | CT59: 0 | CU59: 0 | CV59: 0 | CW59: 0 | CX59: 0 | CY59: 0 | CZ59: 0 | DA59: 0 | DB59: 0 | DC59: 0 | DD59: 0 | DE59: 0 | DF59: 0 | DG59: 0 | DH59: 0 | DI59: 20559290336 | DJ59: CORPORACION ASOCIATIVA LA JOYA | DK59: 01 Asociación
A60: Asociacion de Productores de Agro Industrial Siguas Majes - Prasimex | B60: PALTA | C60: PALTA | D60: Arequipa | E60: 040520 | F60: Arequipa | G60: Caylloma | H60: Majes | J60: 1 | K60: 1 | L60: 1 | M60: 1 | Q60: PAC | R60: 2019-2020-2021-2022 | S60: 4 | T60: SI | U60: SI | V60: 0 | W60: 12 | X60: 8 | Y60: 20 | Z60: 12 | AA60: 8 | AB60: 20 | AC60: 9 | AD60: 3 | AE60: 12 | AF60: 9 | AG60: 3 | AH60: 12 | AI60: 0 | AJ60: 0 | AK60: 0 | AL60: 0 | AM60: 0 | AN60: 0 | AO60: 0 | AP60: 0 | AQ60: 0 | AR60: 12 | AS60: 2 | AT60: 1 | AU60: 59 | AV60: 5 | AW60: 27 | AX60: 4 | AY60: 0 | AZ60: 0 | BA60: 0 | BB60: 0 | BC60: 0 | BD60: 0 | BE60: 0 | BF60: 148371.5 | BG60: 0 | BH60: 148371.5 | BI60: #REF! | BJ60: #REF! | BK60: 0 | BL60: 0 | BM60: 0 | BN60: #REF! | BO60: #REF! | BP60: 19137.93 | BQ60: 0 | BR60: 19137.93 | BS60: #REF! | BU60: 73796.83 | BV60: 0 | BW60: 73796.83 | BX60: #REF! | BY60: #REF! | BZ60: 0 | CA60: 0 | CB60: 0 | CC60: #REF! | CD60: -73796.83 | CE60: 0 | CF60: 0 | CG60: 0 | CH60: #REF! | CI60: 0 | CJ60: #REF! | CK60: 0 | CL60: 0 | CM60: 0 | CN60: #REF! | CO60: 0 | CP60: 0 | CQ60: 0 | CR60: 0 | CS60: 0 | CT60: 0 | CU60: 0 | CV60: 0 | CW60: 0 | CX60: 0 | CY60: 0 | CZ60: 0 | DA60: 0 | DB60: 0 | DC60: 0 | DD60: 0 | DE60: 0 | DF60: 0 | DG60: 0 | DH60: 0 | DI60: 20454864604 | DJ60: ASOCIACION DE PRODUCTORES AGROINDUSTRIALES SIGUAS MAJES - PRASIMEX | DK60: 01 Asociación
A61: Asociacion de Productores Agropecuarios de Agroexportacion e-4 Irrigacion Majes-Arequipa | B61: PALTA | C61: PALTA | D61: Arequipa | E61: 040520 | F61: Arequipa | G61: Caylloma | H61: Majes | J61: 1 | K61: 1 | L61: 1 | M61: 1 | Q61: PAC | R61: 2019-2020-2021-2022 | S61: 4 | T61: SI | U61: SI | V61: 0 | W61: 15 | X61: 2 | Y61: 17 | Z61: 13 | AA61: 2 | AB61: 15 | AC61: 15 | AD61: 2 | AE61: 17 | AF61: 15 | AG61: 2 | AH61: 17 | AI61: 0 | AJ61: 0 | AK61: 0 | AL61: 0 | AM61: 0 | AN61: 0 | AO61: 0 | AP61: 0 | AQ61: 0 | AR61: 17 | AS61: 0 | AT61: 1 | AU61: 61 | AV61: 5 | AW61: 27 | AX61: 4 | AY61: 0 | AZ61: 0 | BA61: 0 | BB61: 0 | BC61: 0 | BD61: 0 | BE61: 0 | BF61: 907143.59 | BG61: 0 | BH61: 907143.59 | BI61: #REF! | BJ61: #REF! | BK61: 0 | BL61: 0 | BM61: 0 | BN61: #REF! | BO61: #REF! | BP61: 380303.5 | BQ61: 0 | BR61: 380303.5 | BS61: #REF! | BU61: 239803.31 | BV61: 0 | BW61: 239803.31 | BX61: #REF! | BY61: #REF! | BZ61: 0 | CA61: 0 | CB61: 0 | CC61: #REF! | CD61: -239803.31 | CE61: 0 | CF61: 0 | CG61: 0 | CH61: #REF! | CI61: 0 | CJ61: #REF! | CK61: 0 | CL61: 0 | CM61: 0 | CN61: #REF! | CO61: 0 | CP61: 0 | CQ61: 0 | CR61: 0 | CS61: 0 | CT61: 0 | CU61: 0 | CV61: 0 | CW61: 0 | CX61: 0 | CY61: 0 | CZ61: 0 | DA61: 0 | DB61: 0 | DC61: 0 | DD61: 0 | DE61: 0 | DF61: 0 | DG61: 0 | DH61: 0 | DI61: 20455429120 | DJ61: ASOCIACION DE PRODUCTORES AGROPECUARIOS DE AGROEXPORTACION E-4 IRRIGACION MAJES-AREQUIPA | DK61: 01 Asociación
A62: Asociacion de Productores Agropecuarios y Derivados Lacteos de Orcopampa - Orcolac | B62: DERIVADOS LACTEOS | C62: DERIVADOS LACTEOS | D62: Arequipa | E62: 040409 | F62: Arequipa | G62: Castilla | H62: Orcopampa | L62: 1 | M62: 1 | N62: 1 | Q62: PAC | R62: 2021-2022-2023 | S62: 3 | T62: SI | U62: SI | V62: 0 | W62: 0 | X62: 0 | Y62: 0 | Z62: 0 | AA62: 0 | AB62: 0 | AC62: 13 | AD62: 13 | AE62: 26 | AF62: 13 | AG62: 13 | AH62: 26 | AI62: 13 | AJ62: 13 | AK62: 26 | AL62: 0 | AM62: 0 | AN62: 0 | AO62: 0 | AP62: 0 | AQ62: 0 | AR62: 26 | AS62: 0 | AT62: 0 | AU62: 37 | AV62: 8 | AW62: 33 | AX62: 5 | AY62: 54 | AZ62: 3 | BA62: 0 | BB62: 0 | BC62: 0 | BD62: 0 | BE62: 0 | BF62: 0 | BG62: 0 | BH62: 0 | BI62: #REF! | BJ62: #REF! | BK62: 0 | BL62: 0 | BM62: 0 | BN62: #REF! | BO62: #REF! | BP62: 27212.23 | BQ62: 0 | BR62: 27212.23 | BS62: #REF! | BU62: 163160.02 | BV62: 0 | BW62: 163160.02 | BX62: #REF! | BY62: #REF! | BZ62: 343399 | CA62: 0 | CB62: 343399 | CC62: #REF! | CD62: -163160.02 | CE62: 0 | CF62: 0 | CG62: 0 | CH62: #REF! | CI62: -343399 | CJ62: #REF! | CK62: 0 | CL62: 0 | CM62: 0 | CN62: #REF! | CO62: 0 | CP62: 0 | CQ62: 342889 | CR62: 0 | CS62: 510.00025 | CT62: 0 | CU62: 0 | CV62: 343399 | CW62: 0 | CX62: 0 | CY62: 0 | CZ62: 0 | DA62: 0 | DB62: 0 | DC62: 0 | DD62: 0 | DE62: 0 | DF62: 0 | DG62: 0 | DH62: 0 | DI62: 20603296576 | DJ62: ASOCIACION DE PRODUCTORES AGROPECUARIOS Y DERIVADOS LACTEOS DE ORCOPAMPA - ORCOLAC | DK62: 01 Asociación
A63: Asociacion Alpacas y Llamas Registradas de Paquenta | B63: FIBRA DE ALPACA | C63: FIBRA DE ALPACA | D63: Arequipa | E63: 040517 | F63: Arequipa | G63: Caylloma | H63: Tisco | L63: 1 | M63: 1 | N63: 1 | Q63: PAC | R63: 2021-2022-2023 | S63: 3 | T63: SI | U63: SI | V63: 0 | W63: 0 | X63: 0 | Y63: 0 | Z63: 0 | AA63: 0 | AB63: 0 | AC63: 23 | AD63: 4 | AE63: 27 | AF63: 23 | AG63: 4 | AH63: 27 | AI63: 23 | AJ63: 4 | AK63: 27 | AL63: 0 | AM63: 0 | AN63: 0 | AO63: 0 | AP63: 0 | AQ63: 0 | AR63: 27 | AS63: 0 | AT63: 0 | AU63: 36 | AV63: 2 | AW63: 37 | AX63: 0 | AY63: 28 | AZ63: 0 | BA63: 0 | BB63: 0 | BC63: 0 | BD63: 0 | BE63: 0 | BF63: 0 | BG63: 0 | BH63: 0 | BI63: #REF! | BJ63: #REF! | BK63: 0 | BL63: 0 | BM63: 0 | BN63: #REF! | BO63: #REF! | BP63: 34432.32 | BQ63: 0 | BR63: 34432.32 | BS63: #REF! | BU63: 73097.25 | BV63: 0 | BW63: 73097.25 | BX63: #REF! | BY63: #REF! | BZ63: 145431.44 | CA63: 0 | CB63: 145431.44 | CC63: #REF! | CD63: -73097.25 | CE63: 0 | CF63: 0 | CG63: 0 | CH63: #REF! | CI63: -145431.44 | CJ63: #REF! | CK63: 0 | CL63: 0 | CM63: 0 | CN63: #REF! | CO63: 0 | CP63: 0 | CQ63: 145431.44 | CR63: 0 | CS63: 0 | CT63: 0 | CU63: 0 | CV63: 145431.44 | CW63: 0 | CX63: 0 | CY63: 0 | CZ63: 0 | DA63: 0 | DB63: 0 | DC63: 0 | DD63: 0 | DE63: 0 | DF63: 0 | DG63: 0 | DH63: 0 | DI63: 20606701846 | DJ63: ASOCIACION ALPACAS Y LLAMAS REGISTRADAS DE PAQUENTA | DK63: 01 Asociación
A64: Cooperativa Agraria de Productos Ecologicos de Pampacolca - Coapep | B64: QUINUA Y OTROS GRANOS | C64: QUINUA | D64: Arequipa | E64: 040410 | F64: Arequipa | G64: Castilla | H64: Pampacolca | L64: 1 | M64: 1 | N64: 1 | O64: 1 | Q64: PAC | R64: 2021-2022-2023-2024 | S64: 4 | T64: SI | U64: SI | V64: 0 | W64: 0 | X64: 0 | Y64: 0 | Z64: 0 | AA64: 0 | AB64: 0 | AC64: 24 | AD64: 9 | AE64: 33 | AF64: 24 | AG64: 9 | AH64: 33 | AI64: 24 | AJ64: 9 | AK64: 33 | AL64: 24 | AM64: 9 | AN64: 33 | AO64: 0 | AP64: 0 | AQ64: 0 | AR64: 33 | AS64: 0 | AT64: 0 | AU64: 17 | AV64: 7 | AW64: 23 | AX64: 2 | AY64: 26 | AZ64: 4 | BA64: 37 | BB64: 1 | BC64: 0 | BD64: 0 | BE64: 0 | BF64: 0 | BG64: 0 | BH64: 0 | BI64: #REF! | BJ64: #REF! | BK64: 0 | BL64: 0 | BM64: 0 | BN64: #REF! | BO64: #REF! | BP64: 0 | BQ64: 0 | BR64: 0 | BS64: #REF! | BU64: 0 | BV64: 0 | BW64: 0 | BX64: #REF! | BY64: #REF! | BZ64: 0 | CA64: 0 | CB64: 0 | CC64: #REF! | CD64: 0 | CE64: 476733.95 | CF64: 0 | CG64: 476733.95 | CH64: #REF! | CI64: 0 | CJ64: #REF! | CK64: 0 | CL64: 0 | CM64: 0 | CN64: #REF! | CO64: -476733.95 | CP64: 0 | CQ64: 0 | CR64: 0 | CS64: 0 | CT64: 0 | CU64: 0 | CV64: 0 | CW64: 0 | CX64: 476733.95 | CY64: 0 | CZ64: 0 | DA64: 0 | DB64: 476733.95 | DC64: 0 | DD64: 0 | DE64: 0 | DF64: 0 | DG64: 0 | DH64: 0 | DI64: 20605161678 | DJ64: COOPERATIVA AGRARIA DE PRODUCTOS ECOLOGICOS DE PAMPACOLCA - COAPEP | DK64: 02 Cooperativa
A65: Asociacion Centro de Acopio de Leche Señor de los Milagros | B65: DERIVADOS LACTEOS | C65: DERIVADOS LACTEOS | D65: Arequipa | E65: 040520 | F65: Arequipa | G65: Caylloma | H65: Majes | M65: 1 | N65: 1 | O65: 1 | P65: 1 | Q65: PAC | R65: 2022-2023-2024 - 2025 | S65: 4 | T65: SI | U65: SI | V65: 0 | W65: 0 | X65: 0 | Y65: 0 | Z65: 0 | AA65: 0 | AB65: 0 | AC65: 0 | AD65: 0 | AE65: 0 | AF65: 49 | AG65: 19 | AH65: 68 | AI65: 49 | AJ65: 19 | AK65: 68 | AL65: 48 | AM65: 21 | AN65: 69 | AO65: 48 | AP65: 21 | AQ65: 69 | AR65: 69 | AS65: 0 | AT65: 0 | AU65: 0 | AV65: 0 | AW65: 30 | AX65: 5 | AY65: 49 | AZ65: 4 | BA65: 51 | BB65: 3 | BC65: 42 | BD65: 2 | BE65: 0 | BF65: 0 | BG65: 0 | BH65: 0 | BI65: #REF! | BJ65: #REF! | BK65: 0 | BL65: 0 | BM65: 0 | BN65: #REF! | BO65: #REF! | BP65: 0 | BQ65: 0 | BR65: 0 | BS65: #REF! | BU65: 58403.51 | BV65: 0 | BW65: 58403.51 | BX65: #REF! | BY65: #REF! | BZ65: 219073.56 | CA65: 0 | CB65: 219073.56 | CC65: #REF! | CD65: -58403.51 | CE65: 394769.86 | CF65: 0 | CG65: 394769.86 | CH65: #REF! | CI65: -219073.56 | CJ65: #REF! | CK65: 338125.16 | CL65: 0 | CM65: 338125.16 | CN65: #REF! | CO65: -394769.86 | CP65: 0 | CQ65: 0 | CR65: 0 | CS65: 219073.55 | CT65: 0 | CU65: 0 | CV65: 219073.55 | CW65: 0 | CX65: 0 | CY65: 394769.86 | CZ65: 0 | DA65: 0 | DB65: 394769.86 | DC65: 0 | DD65: 0 | DE65: 338125.16 | DF65: 0 | DG65: 0 | DH65: 338125.16 | DI65: 20326767400 | DJ65: ASOC.C.DE ACOPIO D.LECHE SR.D.L.MILAGROS | DK65: 01 Asociación
A66: Coordinadora Nacional de Productores de Papa del PERU- Corpapa | B66: PAPA | C66: PAPA | D66: Ayacucho | E66: 050105 | F66: Ayacucho | G66: Huamanga | H66: Chiara | I66: 1 | Q66: PAC | R66: 2018 | S66: 1 | T66: NO | U66: NO | V66: 54 | W66: 0 | X66: 0 | Y66: 0 | Z66: 0 | AA66: 0 | AB66: 0 | AC66: 0 | AD66: 0 | AE66: 0 | AF66: 0 | AG66: 0 | AH66: 0 | AI66: 0 | AJ66: 0 | AK66: 0 | AL66: 0 | AM66: 0 | AN66: 0 | AO66: 0 | AP66: 0 | AQ66: 0 | AR66: 54 | AS66: 0 | AT66: 0 | AU66: 0 | AV66: 0 | AW66: 0 | AX66: 0 | AY66: 0 | AZ66: 0 | BA66: 0 | BB66: 0 | BC66: 0 | BD66: 0 | BE66: 0 | BF66: 0 | BG66: 0 | BH66: 0 | BI66: #REF! | BJ66: #REF! | BK66: 0 | BL66: 0 | BM66: 0 | BN66: #REF! | BO66: #REF! | BP66: 0 | BQ66: 0 | BR66: 0 | BS66: #REF! | BU66: 0 | BV66: 0 | BW66: 0 | BX66: #REF! | BY66: #REF! | BZ66: 0 | CA66: 0 | CB66: 0 | CC66: #REF! | CD66: 0 | CE66: 0 | CF66: 0 | CG66: 0 | CH66: #REF! | CI66: 0 | CJ66: #REF! | CK66: 0 | CL66: 0 | CM66: 0 | CN66: #REF! | CO66: 0 | CP66: 0 | CQ66: 0 | CR66: 0 | CS66: 0 | CT66: 0 | CU66: 0 | CV66: 0 | CW66: 0 | CX66: 0 | CY66: 0 | CZ66: 0 | DA66: 0 | DB66: 0 | DC66: 0 | DD66: 0 | DE66: 0 | DF66: 0 | DG66: 0 | DH66: 0 | DI66: 20517247805 | DJ66: COORDINADORA NACIONAL DE PRODUCTORES DE PAPA DEL PERU- CORPAPA | DK66: 01 Asociación
A67: Asociación de Productores Agro Industriales Emprendedores de Puyusca - Incuyo ( Apaepi ) | B67: DERIVADOS LACTEOS | C67: DERIVADOS LACTEOS | D67: Ayacucho | E67: 050706 | F67: Ayacucho | G67: Parinacochas | H67: Puyusca | I67: 1 | J67: 1 | Q67: PAC | R67: 2018-2019 | S67: 2 | T67: SI | U67: NO | V67: 41 | W67: 11 | X67: 20 | Y67: 31 | Z67: 0 | AA67: 0 | AB67: 0 | AC67: 0 | AD67: 0 | AE67: 0 | AF67: 0 | AG67: 0 | AH67: 0 | AI67: 0 | AJ67: 0 | AK67: 0 | AL67: 0 | AM67: 0 | AN67: 0 | AO67: 0 | AP67: 0 | AQ67: 0 | AR67: 31 | AS67: 0 | AT67: 0 | AU67: 0 | AV67: 0 | AW67: 0 | AX67: 0 | AY67: 0 | AZ67: 0 | BA67: 0 | BB67: 0 | BC67: 0 | BD67: 0 | BE67: 25955.6 | BF67: 23741.88 | BG67: 0 | BH67: 23741.88 | BI67: #REF! | BJ67: #REF! | BK67: 0 | BL67: 0 | BM67: 0 | BN67: #REF! | BO67: #REF! | BP67: 0 | BQ67: 0 | BR67: 0 | BS67: #REF! | BU67: 0 | BV67: 0 | BW67: 0 | BX67: #REF! | BY67: #REF! | BZ67: 0 | CA67: 0 | CB67: 0 | CC67: #REF! | CD67: 0 | CE67: 0 | CF67: 0 | CG67: 0 | CH67: #REF! | CI67: 0 | CJ67: #REF! | CK67: 0 | CL67: 0 | CM67: 0 | CN67: #REF! | CO67: 0 | CP67: 0 | CQ67: 0 | CR67: 0 | CS67: 0 | CT67: 0 | CU67: 0 | CV67: 0 | CW67: 0 | CX67: 0 | CY67: 0 | CZ67: 0 | DA67: 0 | DB67: 0 | DC67: 0 | DD67: 0 | DE67: 0 | DF67: 0 | DG67: 0 | DH67: 0 | DI67: 20534487801 | DJ67: ASOCIACION DE PRODUCTORES AGROINDUSTRIALES EMPRENDEDORES DE PUYUSCA - INCUYO | DK67: 01 Asociación
A68: Asociacion de Productores de Quinua y Granos Andinos de la Region Ayacucho - Apoqua | B68: QUINUA Y OTROS GRANOS | C68: QUINUA | D68: Ayacucho | E68: 050113 | F68: Ayacucho | G68: Huamanga | H68: Tambillo | J68: 1 | K68: 1 | Q68: PAC | R68: 2019-2020 | S68: 2 | T68: SI | U68: SI | V68: 0 | W68: 80 | X68: 6 | Y68: 86 | Z68: 73 | AA68: 12 | AB68: 85 | AC68: 0 | AD68: 0 | AE68: 0 | AF68: 0 | AG68: 0 | AH68: 0 | AI68: 0 | AJ68: 0 | AK68: 0 | AL68: 0 | AM68: 0 | AN68: 0 | AO68: 0 | AP68: 0 | AQ68: 0 | AR68: 85 | AS68: 0 | AT68: 4 | AU68: 0 | AV68: 0 | AW68: 0 | AX68: 0 | AY68: 0 | AZ68: 0 | BA68: 0 | BB68: 0 | BC68: 0 | BD68: 0 | BE68: 0 | BF68: 304383.65 | BG68: 0 | BH68: 304383.65 | BI68: #REF! | BJ68: #REF! | BK68: 0 | BL68: 0 | BM68: 0 | BN68: #REF! | BO68: #REF! | BP68: 0 | BQ68: 0 | BR68: 0 | BS68: #REF! | BU68: 0 | BV68: 0 | BW68: 0 | BX68: #REF! | BY68: #REF! | BZ68: 0 | CA68: 0 | CB68: 0 | CC68: #REF! | CD68: 0 | CE68: 0 | CF68: 0 | CG68: 0 | CH68: #REF! | CI68: 0 | CJ68: #REF! | CK68: 0 | CL68: 0 | CM68: 0 | CN68: #REF! | CO68: 0 | CP68: 0 | CQ68: 0 | CR68: 0 | CS68: 0 | CT68: 0 | CU68: 0 | CV68: 0 | CW68: 0 | CX68: 0 | CY68: 0 | CZ68: 0 | DA68: 0 | DB68: 0 | DC68: 0 | DD68: 0 | DE68: 0 | DF68: 0 | DG68: 0 | DH68: 0 | DI68: 20574629226 | DJ68: ASOCIACION DE PRODUCTORES DE QUINUA Y GRANOS ANDINOS DE LA REGION AYACUCHO | DK68: 01 Asociación
A69: Asociacion de Productores Agroindustriales Organicos de PERU | B69: QUINUA Y OTROS GRANOS | C69: QUINUA | D69: Ayacucho | E69: 051001 | F69: Ayacucho | G69: Victor Fajardo | H69: Huancapi | I69: 1 | J69: 1 | K69: 1 | Q69: PAC | R69: 2018-2019-2020 | S69: 3 | T69: SI | U69: SI | V69: 103 | W69: 72 | X69: 30 | Y69: 102 | Z69: 93 | AA69: 23 | AB69: 116 | AC69: 0 | AD69: 0 | AE69: 0 | AF69: 0 | AG69: 0 | AH69: 0 | AI69: 0 | AJ69: 0 | AK69: 0 | AL69: 0 | AM69: 0 | AN69: 0 | AO69: 0 | AP69: 0 | AQ69: 0 | AR69: 116 | AS69: 0 | AT69: 4 | AU69: 0 | AV69: 0 | AW69: 0 | AX69: 0 | AY69: 0 | AZ69: 0 | BA69: 0 | BB69: 0 | BC69: 0 | BD69: 0 | BE69: 0 | BF69: 3451951.3 | BG69: 0 | BH69: 3451951.3 | BI69: #REF! | BJ69: #REF! | BK69: 0 | BL69: 0 | BM69: 0 | BN69: #REF! | BO69: #REF! | BP69: 0 | BQ69: 0 | BR69: 0 | BS69: #REF! | BU69: 0 | BV69: 0 | BW69: 0 | BX69: #REF! | BY69: #REF! | BZ69: 0 | CA69: 0 | CB69: 0 | CC69: #REF! | CD69: 0 | CE69: 0 | CF69: 0 | CG69: 0 | CH69: #REF! | CI69: 0 | CJ69: #REF! | CK69: 0 | CL69: 0 | CM69: 0 | CN69: #REF! | CO69: 0 | CP69: 0 | CQ69: 0 | CR69: 0 | CS69: 0 | CT69: 0 | CU69: 0 | CV69: 0 | CW69: 0 | CX69: 0 | CY69: 0 | CZ69: 0 | DA69: 0 | DB69: 0 | DC69: 0 | DD69: 0 | DE69: 0 | DF69: 0 | DG69: 0 | DH69: 0 | DI69: 20602545025 | DJ69: ASOCIACION DE PRODUCTORES AGROINDUSTRIALES ORGANICOS DE PERU ASPAGRO | DK69: 01 Asociación
A70: Asociacion de Productores Agropecuarios y Forestales Nueva Urbanización de Huallata | B70: QUINUA Y OTROS GRANOS | C70: QUINUA | D70: Ayacucho | E70: 050201 | F70: Ayacucho | G70: Cangallo | H70: Cangallo | I70: 1 | J70: 1 | K70: 1 | L70: 1 | M70: 1 | N70: 1 | P70: 1 | Q70: PAC | R70: 2018-2019-2020-2021-2022-2023 - 2025 | S70: 7 | T70: SI | U70: SI | V70: 20 | W70: 12 | X70: 8 | Y70: 20 | Z70: 36 | AA70: 16 | AB70: 52 | AC70: 36 | AD70: 16 | AE70: 52 | AF70: 36 | AG70: 16 | AH70: 52 | AI70: 36 | AJ70: 16 | AK70: 52 | AL70: 0 | AM70: 0 | AN70: 0 | AO70: 0 | AP70: 0 | AQ70: 0 | AR70: 52 | AS70: 0 | AT70: 0 | AU70: 5 | AV70: 0 | AW70: 25 | AX70: 2 | AY70: 27 | AZ70: 3 | BA70: 0 | BB70: 0 | BC70: 0 | BD70: 0 | BE70: 0 | BF70: 45876.16 | BG70: 0 | BH70: 45876.16 | BI70: #REF! | BJ70: #REF! | BK70: 42161 | BL70: 0 | BM70: 42161 | BN70: #REF! | BO70: #REF! | BP70: 65962.72 | BQ70: 0 | BR70: 65962.72 | BS70: #REF! | BU70: 141305.43 | BV70: 0 | BW70: 141305.43 | BX70: #REF! | BY70: #REF! | BZ70: 63999 | CA70: 0 | CB70: 63999 | CC70: #REF! | CD70: -141305.43 | CE70: 0 | CF70: 0 | CG70: 0 | CH70: #REF! | CI70: -63999 | CJ70: #REF! | CK70: 161187 | CL70: 0 | CM70: 161187 | CN70: #REF! | CO70: 0 | CP70: 0 | CQ70: 0 | CR70: 0 | CS70: 63999 | CT70: 0 | CU70: 0 | CV70: 63999 | CW70: 0 | CX70: 0 | CY70: 0 | CZ70: 0 | DA70: 0 | DB70: 0 | DC70: 0 | DD70: 0 | DE70: 161187 | DF70: 0 | DG70: 0 | DH70: 161187 | DI70: 20600675487 | DJ70: ASOCIACION DE PRODUCTORES AGROPECUARIOS Y FORESTALES NUEVA URBANIZACION DE HUALLATA | DK70: 01 Asociación
A71: Asociacion de Productores Agropecuarios Inti Raymi | B71: QUINUA Y OTROS GRANOS | C71: QUINUA | D71: Ayacucho | E71: 051101 | F71: Ayacucho | G71: Vilcas Huaman | H71: Vilcas Huaman | J71: 1 | K71: 1 | Q71: PAC | R71: 2019-2020 | S71: 2 | T71: SI | U71: SI | V71: 0 | W71: 96 | X71: 24 | Y71: 120 | Z71: 95 | AA71: 25 | AB71: 120 | AC71: 0 | AD71: 0 | AE71: 0 | AF71: 0 | AG71: 0 | AH71: 0 | AI71: 0 | AJ71: 0 | AK71: 0 | AL71: 0 | AM71: 0 | AN71: 0 | AO71: 0 | AP71: 0 | AQ71: 0 | AR71: 120 | AS71: 0 | AT71: 4 | AU71: 0 | AV71: 0 | AW71: 0 | AX71: 0 | AY71: 0 | AZ71: 0 | BA71: 0 | BB71: 0 | BC71: 0 | BD71: 0 | BE71: 0 | BF71: 443932 | BG71: 0 | BH71: 443932 | BI71: #REF! | BJ71: #REF! | BK71: 562200 | BL71: 0 | BM71: 562200 | BN71: #REF! | BO71: #REF! | BP71: 0 | BQ71: 0 | BR71: 0 | BS71: #REF! | BU71: 0 | BV71: 0 | BW71: 0 | BX71: #REF! | BY71: #REF! | BZ71: 0 | CA71: 0 | CB71: 0 | CC71: #REF! | CD71: 0 | CE71: 0 | CF71: 0 | CG71: 0 | CH71: #REF! | CI71: 0 | CJ71: #REF! | CK71: 0 | CL71: 0 | CM71: 0 | CN71: #REF! | CO71: 0 | CP71: 0 | CQ71: 0 | CR71: 0 | CS71: 0 | CT71: 0 | CU71: 0 | CV71: 0 | CW71: 0 | CX71: 0 | CY71: 0 | CZ71: 0 | DA71: 0 | DB71: 0 | DC71: 0 | DD71: 0 | DE71: 0 | DF71: 0 | DG71: 0 | DH71: 0 | DI71: 20494939160 | DJ71: ASOCIACION DE PRODUCTORES AGRICOLAS Y GANADEROS INTI RAYMI | DK71: 01 Asociación
A72: Cooperativa Agraria los Productores los Morochucos - Cangallo | B72: DERIVADOS LACTEOS | C72: DERIVADOS LACTEOS | D72: Ayacucho | E72: 050203 | F72: Ayacucho | G72: Cangallo | H72: Los Morochucos | I72: 1 | J72: 1 | K72: 1 | L72: 1 | Q72: PAC | R72: 2018-2019-2020-2021 | S72: 4 | T72: SI | U72: SI | V72: 23 | W72: 20 | X72: 3 | Y72: 23 | Z72: 20 | AA72: 3 | AB72: 23 | AC72: 20 | AD72: 3 | AE72: 23 | AF72: 0 | AG72: 0 | AH72: 0 | AI72: 0 | AJ72: 0 | AK72: 0 | AL72: 0 | AM72: 0 | AN72: 0 | AO72: 0 | AP72: 0 | AQ72: 0 | AR72: 23 | AS72: 0 | AT72: 0 | AU72: 31 | AV72: 9 | AW72: 0 | AX72: 0 | AY72: 0 | AZ72: 0 | BA72: 0 | BB72: 0 | BC72: 0 | BD72: 0 | BE72: 0 | BF72: 5125.39 | BG72: 0 | BH72: 5125.39 | BI72: #REF! | BJ72: #REF! | BK72: 0 | BL72: 0 | BM72: 0 | BN72: #REF! | BO72: #REF! | BP72: 9517.8 | BQ72: 0 | BR72: 9517.8 | BS72: #REF! | BU72: 0 | BV72: 0 | BW72: 0 | BX72: #REF! | BY72: #REF! | BZ72: 0 | CA72: 0 | CB72: 0 | CC72: #REF! | CD72: 0 | CE72: 0 | CF72: 0 | CG72: 0 | CH72: #REF! | CI72: 0 | CJ72: #REF! | CK72: 0 | CL72: 0 | CM72: 0 | CN72: #REF! | CO72: 0 | CP72: 0 | CQ72: 0 | CR72: 0 | CS72: 0 | CT72: 0 | CU72: 0 | CV72: 0 | CW72: 0 | CX72: 0 | CY72: 0 | CZ72: 0 | DA72: 0 | DB72: 0 | DC72: 0 | DD72: 0 | DE72: 0 | DF72: 0 | DG72: 0 | DH72: 0 | DI72: 20601590621 | DJ72: COOPERATIVA AGRARIA DE PRODUCTORES LOS MOROCHUCOS - CANGALLO | DK72: 02 Cooperativa
A73: Cooperativa Agraria de Productores Organicos de la Sierra | B73: PALTA | C73: PALTA | D73: Ayacucho | E73: 050106 | F73: Ayacucho | G73: Huamanga | H73: Ocros | I73: 1 | J73: 1 | K73: 1 | L73: 1 | M73: 1 | Q73: PAC | R73: 2018-2019-2020-2021-2022 | S73: 5 | T73: SI | U73: SI | V73: 76 | W73: 67 | X73: 9 | Y73: 76 | Z73: 48 | AA73: 7 | AB73: 55 | AC73: 64 | AD73: 10 | AE73: 74 | AF73: 64 | AG73: 10 | AH73: 74 | AI73: 0 | AJ73: 0 | AK73: 0 | AL73: 0 | AM73: 0 | AN73: 0 | AO73: 0 | AP73: 0 | AQ73: 0 | AR73: 74 | AS73: 0 | AT73: 3 | AU73: 23 | AV73: 7 | AW73: 17 | AX73: 2 | AY73: 0 | AZ73: 0 | BA73: 0 | BB73: 0 | BC73: 0 | BD73: 0 | BE73: 0 | BF73: 0 | BG73: 0 | BH73: 0 | BI73: #REF! | BJ73: #REF! | BK73: 201381.5 | BL73: 0 | BM73: 201381.5 | BN73: #REF! | BO73: #REF! | BP73: 473731.18 | BQ73: 0 | BR73: 473731.18 | BS73: #REF! | BU73: 688066.53 | BV73: 0 | BW73: 688066.53 | BX73: #REF! | BY73: #REF! | BZ73: 0 | CA73: 0 | CB73: 0 | CC73: #REF! | CD73: -688066.53 | CE73: 0 | CF73: 0 | CG73: 0 | CH73: #REF! | CI73: 0 | CJ73: #REF! | CK73: 0 | CL73: 0 | CM73: 0 | CN73: #REF! | CO73: 0 | CP73: 0 | CQ73: 0 | CR73: 0 | CS73: 0 | CT73: 0 | CU73: 0 | CV73: 0 | CW73: 0 | CX73: 0 | CY73: 0 | CZ73: 0 | DA73: 0 | DB73: 0 | DC73: 0 | DD73: 0 | DE73: 0 | DF73: 0 | DG73: 0 | DH73: 0 | DI73: 20534847352 | DJ73: COOPERATIVA AGRARIA DE PRODUCTORES ORGANICOS DE LA SIERRA | DK73: 02 Cooperativa
A74: Asociacion de Productores de Palta Valle Torobamba | B74: PALTA | C74: PALTA | D74: Ayacucho | E74: 050501 | F74: Ayacucho | G74: La Mar | H74: San Miguel | J74: 1 | K74: 1 | L74: 1 | M74: 1 | Q74: PAC | R74: 2019-2020-2021-2022 | S74: 4 | T74: SI | U74: SI | V74: 0 | W74: 30 | X74: 11 | Y74: 41 | Z74: 23 | AA74: 4 | AB74: 27 | AC74: 23 | AD74: 5 | AE74: 28 | AF74: 23 | AG74: 5 | AH74: 28 | AI74: 0 | AJ74: 0 | AK74: 0 | AL74: 0 | AM74: 0 | AN74: 0 | AO74: 0 | AP74: 0 | AQ74: 0 | AR74: 28 | AS74: 0 | AT74: 3 | AU74: 23 | AV74: 6 | AW74: 17 | AX74: 2 | AY74: 0 | AZ74: 0 | BA74: 0 | BB74: 0 | BC74: 0 | BD74: 0 | BE74: 0 | BF74: 137850.31 | BG74: 0 | BH74: 137850.31 | BI74: #REF! | BJ74: #REF! | BK74: 437011.87 | BL74: 0 | BM74: 437011.87 | BN74: #REF! | BO74: #REF! | BP74: 712710.03 | BQ74: 0 | BR74: 712710.03 | BS74: #REF! | BU74: 275523.33 | BV74: 0 | BW74: 275523.33 | BX74: #REF! | BY74: #REF! | BZ74: 0 | CA74: 0 | CB74: 0 | CC74: #REF! | CD74: -275523.33 | CE74: 0 | CF74: 0 | CG74: 0 | CH74: #REF! | CI74: 0 | CJ74: #REF! | CK74: 0 | CL74: 0 | CM74: 0 | CN74: #REF! | CO74: 0 | CP74: 0 | CQ74: 0 | CR74: 0 | CS74: 0 | CT74: 0 | CU74: 0 | CV74: 0 | CW74: 0 | CX74: 0 | CY74: 0 | CZ74: 0 | DA74: 0 | DB74: 0 | DC74: 0 | DD74: 0 | DE74: 0 | DF74: 0 | DG74: 0 | DH74: 0 | DI74: 20574683867 | DJ74: ASOCIACION DE PRODUCTORES DE PALTA VALLE TOROBAMBA | DK74: 01 Asociación
A75: Asociacion Civil de Mantenimiento Vial y Desarrollo Agropecuario Calvario | B75: PALTA | C75: PALTA | D75: Ayacucho | E75: 050501 | F75: Ayacucho | G75: La Mar | H75: San Miguel | J75: 1 | K75: 1 | L75: 1 | M75: 1 | Q75: PAC | R75: 2019-2020-2021-2022 | S75: 4 | T75: SI | U75: SI | V75: 0 | W75: 47 | X75: 20 | Y75: 67 | Z75: 33 | AA75: 15 | AB75: 48 | AC75: 30 | AD75: 20 | AE75: 50 | AF75: 30 | AG75: 20 | AH75: 50 | AI75: 0 | AJ75: 0 | AK75: 0 | AL75: 0 | AM75: 0 | AN75: 0 | AO75: 0 | AP75: 0 | AQ75: 0 | AR75: 50 | AS75: 0 | AT75: 3 | AU75: 26 | AV75: 7 | AW75: 17 | AX75: 3 | AY75: 0 | AZ75: 0 | BA75: 0 | BB75: 0 | BC75: 0 | BD75: 0 | BE75: 0 | BF75: 1045488.3 | BG75: 0 | BH75: 1045488.3 | BI75: #REF! | BJ75: #REF! | BK75: 1322966.5 | BL75: 0 | BM75: 1322966.5 | BN75: #REF! | BO75: #REF! | BP75: 2174933.4 | BQ75: 0 | BR75: 2174933.4 | BS75: #REF! | BU75: 551925.99 | BV75: 0 | BW75: 551925.99 | BX75: #REF! | BY75: #REF! | BZ75: 0 | CA75: 0 | CB75: 0 | CC75: #REF! | CD75: -551925.99 | CE75: 0 | CF75: 0 | CG75: 0 | CH75: #REF! | CI75: 0 | CJ75: #REF! | CK75: 0 | CL75: 0 | CM75: 0 | CN75: #REF! | CO75: 0 | CP75: 0 | CQ75: 0 | CR75: 0 | CS75: 0 | CT75: 0 | CU75: 0 | CV75: 0 | CW75: 0 | CX75: 0 | CY75: 0 | CZ75: 0 | DA75: 0 | DB75: 0 | DC75: 0 | DD75: 0 | DE75: 0 | DF75: 0 | DG75: 0 | DH75: 0 | DI75: 20449558902 | DJ75: ASOCIACION CIVIL DE MANTENIMIENTO VIAL Y DESARROLLO AGROPECUARIO CALVARIO | DK75: 01 Asociación
A76: Agro Asociación y Servicios Tinkuy | B76: CACAO | C76: CACAO | D76: Ayacucho | E76: 050408 | F76: Ayacucho | G76: Huanta | H76: Llochegua | I76: 1 | J76: 1 | Q76: PAC | R76: 2018-2019 | S76: 2 | T76: SI | U76: NO | V76: 33 | W76: 21 | X76: 12 | Y76: 33 | Z76: 0 | AA76: 0 | AB76: 0 | AC76: 0 | AD76: 0 | AE76: 0 | AF76: 0 | AG76: 0 | AH76: 0 | AI76: 0 | AJ76: 0 | AK76: 0 | AL76: 0 | AM76: 0 | AN76: 0 | AO76: 0 | AP76: 0 | AQ76: 0 | AR76: 33 | AS76: 0 | AT76: 0 | AU76: 0 | AV76: 0 | AW76: 0 | AX76: 0 | AY76: 0 | AZ76: 0 | BA76: 0 | BB76: 0 | BC76: 0 | BD76: 0 | BE76: 0 | BF76: 59766 | BG76: 0 | BH76: 59766 | BI76: #REF! | BJ76: #REF! | BK76: 0 | BL76: 0 | BM76: 0 | BN76: #REF! | BO76: #REF! | BP76: 0 | BQ76: 0 | BR76: 0 | BS76: #REF! | BU76: 0 | BV76: 0 | BW76: 0 | BX76: #REF! | BY76: #REF! | BZ76: 0 | CA76: 0 | CB76: 0 | CC76: #REF! | CD76: 0 | CE76: 0 | CF76: 0 | CG76: 0 | CH76: #REF! | CI76: 0 | CJ76: #REF! | CK76: 0 | CL76: 0 | CM76: 0 | CN76: #REF! | CO76: 0 | CP76: 0 | CQ76: 0 | CR76: 0 | CS76: 0 | CT76: 0 | CU76: 0 | CV76: 0 | CW76: 0 | CX76: 0 | CY76: 0 | CZ76: 0 | DA76: 0 | DB76: 0 | DC76: 0 | DD76: 0 | DE76: 0 | DF76: 0 | DG76: 0 | DH76: 0 | DI76: 20600529693 | DJ76: AGRO ASOCIACION Y SERVICIOS TINKUY | DK76: 01 Asociación
A77: Cooperativa Agraria Cafetalera Valle Rio Apurimac -Cacvra | B77: CACAO | C77: CACAO | D77: Ayacucho | E77: 050503 | F77: Ayacucho | G77: La Mar | H77: Ayna | I77: 1 | J77: 1 | K77: 1 | L77: 1 | N77: 1 | Q77: PAC | R77: 2018-2019-2020-2021-2023 | S77: 5 | T77: SI | U77: SI | V77: 153 | W77: 139 | X77: 11 | Y77: 150 | Z77: 133 | AA77: 11 | AB77: 144 | AC77: 174 | AD77: 19 | AE77: 193 | AF77: 0 | AG77: 0 | AH77: 0 | AI77: 20 | AJ77: 5 | AK77: 25 | AL77: 0 | AM77: 0 | AN77: 0 | AO77: 0 | AP77: 0 | AQ77: 0 | AR77: 25 | AS77: 0 | AT77: 0 | AU77: 65 | AV77: 9 | AW77: 0 | AX77: 0 | AY77: 16 | AZ77: 0 | BA77: 0 | BB77: 0 | BC77: 0 | BD77: 0 | BE77: 0 | BF77: 227811.39 | BG77: 489143.26 | BH77: 716954.65 | BI77: #REF! | BJ77: #REF! | BK77: 230338 | BL77: 0 | BM77: 230338 | BN77: #REF! | BO77: #REF! | BP77: 1300 | BQ77: 0 | BR77: 1300 | BS77: #REF! | BU77: 0 | BV77: 0 | BW77: 0 | BX77: #REF! | BY77: #REF! | BZ77: 112621.8 | CA77: 0 | CB77: 112621.8 | CC77: #REF! | CD77: 0 | CE77: 0 | CF77: 0 | CG77: 0 | CH77: #REF! | CI77: -112621.8 | CJ77: #REF! | CK77: 0 | CL77: 0 | CM77: 0 | CN77: #REF! | CO77: 0 | CP77: 2390 | CQ77: 0 | CR77: 0 | CS77: 110231.8 | CT77: 0 | CU77: 0 | CV77: 112621.8 | CW77: 0 | CX77: 0 | CY77: 0 | CZ77: 0 | DA77: 0 | DB77: 0 | DC77: 0 | DD77: 0 | DE77: 0 | DF77: 0 | DG77: 0 | DH77: 0 | DI77: 20129156083 | DJ77: COOP AGRARIA CAFET VALLE RIO APURIMAC | DK77: 02 Cooperativa
A78: Asociacion de Productores Agropecuarios Unidos al Desarrollo de Santa Rosa | B78: añad | C78: CACAO | D78: Ayacucho | E78: 050507 | F78: Ayacucho | G78: La Mar | H78: Santa Rosa | I78: 1 | J78: 1 | K78: 1 | Q78: PAC | R78: 2018-2019-2020 | S78: 3 | T78: SI | U78: SI | V78: 17 | W78: 12 | X78: 5 | Y78: 17 | Z78: 36 | AA78: 20 | AB78: 56 | AC78: 0 | AD78: 0 | AE78: 0 | AF78: 0 | AG78: 0 | AH78: 0 | AI78: 0 | AJ78: 0 | AK78: 0 | AL78: 0 | AM78: 0 | AN78: 0 | AO78: 0 | AP78: 0 | AQ78: 0 | AR78: 56 | AS78: 0 | AT78: 0 | AU78: 0 | AV78: 0 | AW78: 0 | AX78: 0 | AY78: 0 | AZ78: 0 | BA78: 0 | BB78: 0 | BC78: 0 | BD78: 0 | BE78: 0 | BF78: 69404 | BG78: 0 | BH78: 69404 | BI78: #REF! | BJ78: #REF! | BK78: 0 | BL78: 0 | BM78: 0 | BN78: #REF! | BO78: #REF! | BP78: 0 | BQ78: 0 | BR78: 0 | BS78: #REF! | BU78: 0 | BV78: 0 | BW78: 0 | BX78: #REF! | BY78: #REF! | BZ78: 0 | CA78: 0 | CB78: 0 | CC78: #REF! | CD78: 0 | CE78: 0 | CF78: 0 | CG78: 0 | CH78: #REF! | CI78: 0 | CJ78: #REF! | CK78: 0 | CL78: 0 | CM78: 0 | CN78: #REF! | CO78: 0 | CP78: 0 | CQ78: 0 | CR78: 0 | CS78: 0 | CT78: 0 | CU78: 0 | CV78: 0 | CW78: 0 | CX78: 0 | CY78: 0 | CZ78: 0 | DA78: 0 | DB78: 0 | DC78: 0 | DD78: 0 | DE78: 0 | DF78: 0 | DG78: 0 | DH78: 0 | DI78: 20574734011 | DJ78: ASOCIACION DE PRODUCTORES AGROPECUARIOS UNIDOS AL DESARROLLO DE SANTA ROSA | DK78: 01 Asociación
A79: Cooperativa Agraria Cafetalera el Quinacho LTDA N° 78 | B79: CACAO | C79: CACAO | D79: Ayacucho | E79: 050407 | F79: Ayacucho | G79: Huanta | H79: Sivia | K79: 1 | L79: 1 | M79: 1 | N79: 1 | P79: 1 | Q79: CALIDAD | R79: 2020-2021-2022-2023 - 2025 | S79: 5 | T79: SI | U79: SI | V79: 0 | W79: 0 | X79: 0 | Y79: 0 | Z79: 93 | AA79: 52 | AB79: 145 | AC79: 108 | AD79: 46 | AE79: 154 | AF79: 104 | AG79: 50 | AH79: 154 | AI79: 104 | AJ79: 50 | AK79: 154 | AL79: 0 | AM79: 0 | AN79: 0 | AO79: 0 | AP79: 0 | AQ79: 0 | AR79: 154 | AS79: 0 | AT79: 0 | AU79: 62 | AV79: 9 | AW79: 31 | AX79: 10 | AY79: 11 | AZ79: 0 | BA79: 0 | BB79: 0 | BC79: 0 | BD79: 0 | BE79: 0 | BF79: 0 | BG79: 0 | BH79: 0 | BI79: #REF! | BJ79: #REF! | BK79: 0 | BL79: 3459563.9 | BM79: 3459563.9 | BN79: #REF! | BO79: #REF! | BP79: 0 | BQ79: 2752409.1 | BR79: 2752409.1 | BS79: #REF! | BU79: 508928.25 | BV79: 2876295.9 | BW79: 3385224.1 | BX79: #REF! | BY79: #REF! | BZ79: 0 | CA79: 3313766.3 | CB79: 3313766.3 | CC79: #REF! | CD79: -3385224.1 | CE79: 0 | CF79: 0 | CG79: 0 | CH79: #REF! | CI79: -3313766.3 | CJ79: #REF! | CK79: 0 | CL79: 3073770.7 | CM79: 3073770.7 | CN79: #REF! | CO79: 0 | CP79: 0 | CQ79: 0 | CR79: 0 | CS79: 3313766.3 | CT79: 0 | CU79: 0 | CV79: 3313766.3 | CW79: 0 | CX79: 0 | CY79: 0 | CZ79: 0 | DA79: 0 | DB79: 0 | DC79: 0 | DD79: 0 | DE79: 3073770.7 | DF79: 0 | DG79: 0 | DH79: 3073770.7 | DI79: 20143692010 | DJ79: COOPERATIVA AGRARIA EL QUINACHO LTDA. N° 078 | DK79: 02 Cooperativa
A80: Asociación de Productores y Servicios Múltiples San Nicolas - Apasmu - Ninabamba - San Miguel | B80: PALTA | C80: PALTA | D80: Ayacucho | E80: 050501 | F80: Ayacucho | G80: La Mar | H80: San Miguel | L80: 1 | M80: 1 | Q80: PAC | R80: 2021-2022 | S80: 2 | T80: SI | U80: SI | V80: 0 | W80: 0 | X80: 0 | Y80: 0 | Z80: 0 | AA80: 0 | AB80: 0 | AC80: 6 | AD80: 3 | AE80: 9 | AF80: 6 | AG80: 3 | AH80: 9 | AI80: 0 | AJ80: 0 | AK80: 0 | AL80: 0 | AM80: 0 | AN80: 0 | AO80: 0 | AP80: 0 | AQ80: 0 | AR80: 9 | AS80: 0 | AT80: 0 | AU80: 28 | AV80: 5 | AW80: 17 | AX80: 2 | AY80: 0 | AZ80: 0 | BA80: 0 | BB80: 0 | BC80: 0 | BD80: 0 | BE80: 0 | BF80: 0 | BG80: 0 | BH80: 0 | BI80: #REF! | BJ80: #REF! | BK80: 0 | BL80: 0 | BM80: 0 | BN80: #REF! | BO80: #REF! | BP80: 197469 | BQ80: 0 | BR80: 197469 | BS80: #REF! | BU80: 128116.8 | BV80: 0 | BW80: 128116.8 | BX80: #REF! | BY80: #REF! | BZ80: 0 | CA80: 0 | CB80: 0 | CC80: #REF! | CD80: -128116.8 | CE80: 0 | CF80: 0 | CG80: 0 | CH80: #REF! | CI80: 0 | CJ80: #REF! | CK80: 0 | CL80: 0 | CM80: 0 | CN80: #REF! | CO80: 0 | CP80: 0 | CQ80: 0 | CR80: 0 | CS80: 0 | CT80: 0 | CU80: 0 | CV80: 0 | CW80: 0 | CX80: 0 | CY80: 0 | CZ80: 0 | DA80: 0 | DB80: 0 | DC80: 0 | DD80: 0 | DE80: 0 | DF80: 0 | DG80: 0 | DH80: 0 | DI80: 20601643023 | DJ80: ASOC DE PRODUCTORES AGROPECUARIOS Y SERVICIOS MÚLTIPLES SAN NICOLÁS-APASMU NINABAMBA-SAN MIGUEL | DK80: 01 Asociación
A81: Cooperativa Agraria Frutos del Ande | B81: QUINUA Y OTROS GRANOS | C81: QUINUA | D81: Ayacucho | E81: 050101 | F81: Ayacucho | G81: Huamanga | H81: Ayacucho | L81: 1 | M81: 1 | N81: 1 | O81: 1 | P81: 1 | Q81: CALIDAD | R81: 2021-2022-2023-2024 - 2025 | S81: 5 | T81: SI | U81: SI | V81: 0 | W81: 0 | X81: 0 | Y81: 0 | Z81: 0 | AA81: 0 | AB81: 0 | AC81: 80 | AD81: 37 | AE81: 117 | AF81: 80 | AG81: 37 | AH81: 117 | AI81: 80 | AJ81: 37 | AK81: 117 | AL81: 40 | AM81: 18 | AN81: 58 | AO81: 0 | AP81: 0 | AQ81: 0 | AR81: 58 | AS81: 0 | AT81: 0 | AU81: 36 | AV81: 9 | AW81: 15 | AX81: 2 | AY81: 55 | AZ81: 8 | BA81: 16 | BB81: 2 | BC81: 0 | BD81: 0 | BE81: 0 | BF81: 0 | BG81: 0 | BH81: 0 | BI81: #REF! | BJ81: #REF! | BK81: 0 | BL81: 0 | BM81: 0 | BN81: #REF! | BO81: #REF! | BP81: 195944.1 | BQ81: 0 | BR81: 195944.1 | BS81: #REF! | BU81: 0 | BV81: 115372.86 | BW81: 115372.86 | BX81: #REF! | BY81: #REF! | BZ81: 624324.13 | CA81: 299314.59 | CB81: 923638.72 | CC81: #REF! | CD81: -115372.86 | CE81: 726147.2 | CF81: 0 | CG81: 726147.2 | CH81: #REF! | CI81: -923638.72 | CJ81: #REF! | CK81: 155461.4 | CL81: 0 | CM81: 155461.4 | CN81: #REF! | CO81: -726147.2 | CP81: 0 | CQ81: 0 | CR81: 0 | CS81: 923638.72 | CT81: 0 | CU81: 0 | CV81: 923638.72 | CW81: 0 | CX81: 0 | CY81: 726147.2 | CZ81: 0 | DA81: 0 | DB81: 726147.2 | DC81: 327 | DD81: 0 | DE81: 155134.4 | DF81: 0 | DG81: 0 | DH81: 155461.4 | DI81: 20574602450 | DJ81: COOPERATIVA AGRARIA FRUTOS DEL ANDE | DK81: 02 Cooperativa
A82: Cooperativa Agraria de Productores del Distrito de Tambillo | B82: QUINUA Y OTROS GRANOS | C82: QUINUA | D82: Ayacucho | E82: 050113 | F82: Ayacucho | G82: Huamanga | H82: Tambillo | L82: 1 | M82: 1 | N82: 1 | O82: 1 | P82: 1 | Q82: CALIDAD | R82: 2021-2022-2023-2024 - 2025 | S82: 5 | T82: SI | U82: SI | V82: 0 | W82: 0 | X82: 0 | Y82: 0 | Z82: 0 | AA82: 0 | AB82: 0 | AC82: 58 | AD82: 18 | AE82: 76 | AF82: 58 | AG82: 18 | AH82: 76 | AI82: 58 | AJ82: 18 | AK82: 76 | AL82: 56 | AM82: 14 | AN82: 70 | AO82: 0 | AP82: 0 | AQ82: 0 | AR82: 70 | AS82: 0 | AT82: 0 | AU82: 39 | AV82: 9 | AW82: 21 | AX82: 2 | AY82: 63 | AZ82: 5 | BA82: 28 | BB82: 2 | BC82: 0 | BD82: 0 | BE82: 0 | BF82: 0 | BG82: 0 | BH82: 0 | BI82: #REF! | BJ82: #REF! | BK82: 0 | BL82: 0 | BM82: 0 | BN82: #REF! | BO82: #REF! | BP82: 96273.65 | BQ82: 0 | BR82: 96273.65 | BS82: #REF! | BU82: 118400 | BV82: 0 | BW82: 118400 | BX82: #REF! | BY82: #REF! | BZ82: 473161 | CA82: 0 | CB82: 473161 | CC82: #REF! | CD82: -118400 | CE82: 612531 | CF82: 0 | CG82: 612531 | CH82: #REF! | CI82: -473161 | CJ82: #REF! | CK82: 182500 | CL82: 0 | CM82: 182500 | CN82: #REF! | CO82: -612531 | CP82: 0 | CQ82: 207150 | CR82: 0 | CS82: 266011 | CT82: 0 | CU82: 0 | CV82: 473161 | CW82: 0 | CX82: 595200 | CY82: 17331 | CZ82: 0 | DA82: 0 | DB82: 612531 | DC82: 0 | DD82: 182500 | DE82: 0 | DF82: 0 | DG82: 0 | DH82: 182500 | DI82: 20601377781 | DJ82: COOPERATIVA AGRARIA DE PRODUCTORES DEL DISTRITO DE TAMBILLO | DK82: 02 Cooperativa
A83: Cooperativa Agraria de Productores Tikanka Chiara-Ayacucho | B83: QUINUA Y OTROS GRANOS | C83: QUINUA | D83: Ayacucho | E83: 050105 | F83: Ayacucho | G83: Huamanga | H83: Chiara | L83: 1 | M83: 1 | N83: 1 | O83: 1 | Q83: PAC | R83: 2021-2022-2023-2024 | S83: 4 | T83: SI | U83: SI | V83: 0 | W83: 0 | X83: 0 | Y83: 0 | Z83: 0 | AA83: 0 | AB83: 0 | AC83: 17 | AD83: 12 | AE83: 29 | AF83: 17 | AG83: 12 | AH83: 29 | AI83: 17 | AJ83: 12 | AK83: 29 | AL83: 17 | AM83: 12 | AN83: 29 | AO83: 0 | AP83: 0 | AQ83: 0 | AR83: 29 | AS83: 0 | AT83: 0 | AU83: 38 | AV83: 9 | AW83: 21 | AX83: 3 | AY83: 62 | AZ83: 5 | BA83: 28 | BB83: 2 | BC83: 0 | BD83: 0 | BE83: 0 | BF83: 0 | BG83: 0 | BH83: 0 | BI83: #REF! | BJ83: #REF! | BK83: 0 | BL83: 0 | BM83: 0 | BN83: #REF! | BO83: #REF! | BP83: 84480 | BQ83: 0 | BR83: 84480 | BS83: #REF! | BU83: 106900 | BV83: 0 | BW83: 106900 | BX83: #REF! | BY83: #REF! | BZ83: 266550 | CA83: 0 | CB83: 266550 | CC83: #REF! | CD83: -106900 | CE83: 302050 | CF83: 0 | CG83: 302050 | CH83: #REF! | CI83: -266550 | CJ83: #REF! | CK83: 0 | CL83: 0 | CM83: 0 | CN83: #REF! | CO83: -302050 | CP83: 0 | CQ83: 266550 | CR83: 0 | CS83: 0 | CT83: 0 | CU83: 0 | CV83: 266550 | CW83: 0 | CX83: 302050 | CY83: 0 | CZ83: 0 | DA83: 0 | DB83: 302050 | DC83: 0 | DD83: 0 | DE83: 0 | DF83: 0 | DG83: 0 | DH83: 0 | DI83: 20603942028 | DJ83: COOPERATIVA AGRARIA DE PRODUCTORES TIKANKA CHIARA-AYACUCHO | DK83: 02 Cooperativa
A84: Cooperativa de Usuarios Agroindustrial de Productores Inti Raymi | B84: QUINUA Y OTROS GRANOS | C84: QUINUA | D84: Ayacucho | E84: 051101 | F84: Ayacucho | G84: Vilcas Huaman | H84: Vilcas Huaman | L84: 1 | M84: 1 | N84: 1 | Q84: PAC | R84: 2021-2022-2023 | S84: 3 | T84: SI | U84: SI | V84: 0 | W84: 0 | X84: 0 | Y84: 0 | Z84: 0 | AA84: 0 | AB84: 0 | AC84: 20 | AD84: 22 | AE84: 42 | AF84: 20 | AG84: 22 | AH84: 42 | AI84: 20 | AJ84: 22 | AK84: 42 | AL84: 0 | AM84: 0 | AN84: 0 | AO84: 0 | AP84: 0 | AQ84: 0 | AR84: 42 | AS84: 0 | AT84: 0 | AU84: 37 | AV84: 9 | AW84: 21 | AX84: 3 | AY84: 55 | AZ84: 5 | BA84: 0 | BB84: 0 | BC84: 0 | BD84: 0 | BE84: 0 | BF84: 0 | BG84: 0 | BH84: 0 | BI84: #REF! | BJ84: #REF! | BK84: 0 | BL84: 0 | BM84: 0 | BN84: #REF! | BO84: #REF! | BP84: 0 | BQ84: 0 | BR84: 0 | BS84: #REF! | BU84: 107000 | BV84: 0 | BW84: 107000 | BX84: #REF! | BY84: #REF! | BZ84: 310000 | CA84: 0 | CB84: 310000 | CC84: #REF! | CD84: -107000 | CE84: 0 | CF84: 0 | CG84: 0 | CH84: #REF! | CI84: -310000 | CJ84: #REF! | CK84: 0 | CL84: 0 | CM84: 0 | CN84: #REF! | CO84: 0 | CP84: 0 | CQ84: 245000 | CR84: 0 | CS84: 65000 | CT84: 0 | CU84: 0 | CV84: 310000 | CW84: 0 | CX84: 0 | CY84: 0 | CZ84: 0 | DA84: 0 | DB84: 0 | DC84: 0 | DD84: 0 | DE84: 0 | DF84: 0 | DG84: 0 | DH84: 0 | DI84: 20604495483 | DJ84: COOPERATIVA DE USUARIOS AGROINDUSTRIAL DE PRODUCTORES INTI RAYMI | DK84: 02 Cooperativa
A85: Asociacion Nueva Esperanza de Allpachaca | B85: DERIVADOS LACTEOS | C85: DERIVADOS LACTEOS | D85: Ayacucho | E85: 050105 | F85: Ayacucho | G85: Huamanga | H85: Chiara | L85: 1 | M85: 1 | Q85: PAC | R85: 2021-2022 | S85: 2 | T85: SI | U85: SI | V85: 0 | W85: 0 | X85: 0 | Y85: 0 | Z85: 0 | AA85: 0 | AB85: 0 | AC85: 9 | AD85: 5 | AE85: 14 | AF85: 9 | AG85: 5 | AH85: 14 | AI85: 0 | AJ85: 0 | AK85: 0 | AL85: 0 | AM85: 0 | AN85: 0 | AO85: 0 | AP85: 0 | AQ85: 0 | AR85: 14 | AS85: 0 | AT85: 0 | AU85: 30 | AV85: 9 | AW85: 32 | AX85: 4 | AY85: 0 | AZ85: 0 | BA85: 0 | BB85: 0 | BC85: 0 | BD85: 0 | BE85: 0 | BF85: 0 | BG85: 0 | BH85: 0 | BI85: #REF! | BJ85: #REF! | BK85: 0 | BL85: 0 | BM85: 0 | BN85: #REF! | BO85: #REF! | BP85: 9965 | BQ85: 0 | BR85: 9965 | BS85: #REF! | BU85: 13235 | BV85: 0 | BW85: 13235 | BX85: #REF! | BY85: #REF! | BZ85: 0 | CA85: 0 | CB85: 0 | CC85: #REF! | CD85: -13235 | CE85: 0 | CF85: 0 | CG85: 0 | CH85: #REF! | CI85: 0 | CJ85: #REF! | CK85: 0 | CL85: 0 | CM85: 0 | CN85: #REF! | CO85: 0 | CP85: 0 | CQ85: 0 | CR85: 0 | CS85: 0 | CT85: 0 | CU85: 0 | CV85: 0 | CW85: 0 | CX85: 0 | CY85: 0 | CZ85: 0 | DA85: 0 | DB85: 0 | DC85: 0 | DD85: 0 | DE85: 0 | DF85: 0 | DG85: 0 | DH85: 0 | DI85: 20494923832 | DJ85: ASOCIACION NUEVA ESPERANZA ALLPACHACA | DK85: 01 Asociación
A86: Asociacion de Ganaderos y Productores Lacteos Musuq Allpachaka | B86: DERIVADOS LACTEOS | C86: DERIVADOS LACTEOS | D86: Ayacucho | E86: 050105 | F86: Ayacucho | G86: Huamanga | H86: Chiara | L86: 1 | M86: 1 | Q86: PAC | R86: 2021-2022 | S86: 2 | T86: SI | U86: SI | V86: 0 | W86: 0 | X86: 0 | Y86: 0 | Z86: 0 | AA86: 0 | AB86: 0 | AC86: 6 | AD86: 6 | AE86: 12 | AF86: 6 | AG86: 6 | AH86: 12 | AI86: 0 | AJ86: 0 | AK86: 0 | AL86: 0 | AM86: 0 | AN86: 0 | AO86: 0 | AP86: 0 | AQ86: 0 | AR86: 12 | AS86: 0 | AT86: 0 | AU86: 31 | AV86: 8 | AW86: 26 | AX86: 6 | AY86: 0 | AZ86: 0 | BA86: 0 | BB86: 0 | BC86: 0 | BD86: 0 | BE86: 0 | BF86: 0 | BG86: 0 | BH86: 0 | BI86: #REF! | BJ86: #REF! | BK86: 0 | BL86: 0 | BM86: 0 | BN86: #REF! | BO86: #REF! | BP86: 12142 | BQ86: 0 | BR86: 12142 | BS86: #REF! | BU86: 10170 | BV86: 0 | BW86: 10170 | BX86: #REF! | BY86: #REF! | BZ86: 0 | CA86: 0 | CB86: 0 | CC86: #REF! | CD86: -10170 | CE86: 0 | CF86: 0 | CG86: 0 | CH86: #REF! | CI86: 0 | CJ86: #REF! | CK86: 0 | CL86: 0 | CM86: 0 | CN86: #REF! | CO86: 0 | CP86: 0 | CQ86: 0 | CR86: 0 | CS86: 0 | CT86: 0 | CU86: 0 | CV86: 0 | CW86: 0 | CX86: 0 | CY86: 0 | CZ86: 0 | DA86: 0 | DB86: 0 | DC86: 0 | DD86: 0 | DE86: 0 | DF86: 0 | DG86: 0 | DH86: 0 | DI86: 20534200952 | DJ86: ASOCIACION DE GANADEROS Y PRODUCTORES LACTEOS MUSUQ ALLPACHAKA | DK86: 01 Asociación
A87: Cooperativa Agraria Querohuambos | B87: DERIVADOS LACTEOS | C87: QUESOS MADURADOS | D87: Cajamarca | E87: 060409 | F87: Cajamarca | G87: Chota | H87: Huambos | I87: 1 | Q87: PAC | R87: 2018 | S87: 1 | T87: NO | U87: NO | V87: 149 | W87: 0 | X87: 0 | Y87: 0 | Z87: 0 | AA87: 0 | AB87: 0 | AC87: 0 | AD87: 0 | AE87: 0 | AF87: 0 | AG87: 0 | AH87: 0 | AI87: 0 | AJ87: 0 | AK87: 0 | AL87: 0 | AM87: 0 | AN87: 0 | AO87: 0 | AP87: 0 | AQ87: 0 | AR87: 149 | AS87: 0 | AT87: 0 | AU87: 0 | AV87: 0 | AW87: 0 | AX87: 0 | AY87: 0 | AZ87: 0 | BA87: 0 | BB87: 0 | BC87: 0 | BD87: 0 | BE87: 0 | BF87: 0 | BG87: 0 | BH87: 0 | BI87: #REF! | BJ87: #REF! | BK87: 0 | BL87: 0 | BM87: 0 | BN87: #REF! | BO87: #REF! | BP87: 0 | BQ87: 0 | BR87: 0 | BS87: #REF! | BU87: 0 | BV87: 0 | BW87: 0 | BX87: #REF! | BY87: #REF! | BZ87: 0 | CA87: 0 | CB87: 0 | CC87: #REF! | CD87: 0 | CE87: 0 | CF87: 0 | CG87: 0 | CH87: #REF! | CI87: 0 | CJ87: #REF! | CK87: 0 | CL87: 0 | CM87: 0 | CN87: #REF! | CO87: 0 | CP87: 0 | CQ87: 0 | CR87: 0 | CS87: 0 | CT87: 0 | CU87: 0 | CV87: 0 | CW87: 0 | CX87: 0 | CY87: 0 | CZ87: 0 | DA87: 0 | DB87: 0 | DC87: 0 | DD87: 0 | DE87: 0 | DF87: 0 | DG87: 0 | DH87: 0 | DI87: 20600235444 | DJ87: COOPERATIVA AGRARIA QUEROHUAMBOS | DK87: 02 Cooperativa
A88: Derivados Lácteos Barreto SRL | B88: DERIVADOS LACTEOS | C88: QUESOS MADURADOS | D88: Cajamarca | E88: 060401 | F88: Cajamarca | G88: Chota | H88: Chota | I88: 1 | Q88: PAC | R88: 2018 | S88: 1 | T88: NO | U88: NO | V88: 3 | W88: 0 | X88: 0 | Y88: 0 | Z88: 0 | AA88: 0 | AB88: 0 | AC88: 0 | AD88: 0 | AE88: 0 | AF88: 0 | AG88: 0 | AH88: 0 | AI88: 0 | AJ88: 0 | AK88: 0 | AL88: 0 | AM88: 0 | AN88: 0 | AO88: 0 | AP88: 0 | AQ88: 0 | AR88: 3 | AS88: 0 | AT88: 0 | AU88: 0 | AV88: 0 | AW88: 0 | AX88: 0 | AY88: 0 | AZ88: 0 | BA88: 0 | BB88: 0 | BC88: 0 | BD88: 0 | BE88: 0 | BF88: 0 | BG88: 0 | BH88: 0 | BI88: #REF! | BJ88: #REF! | BK88: 0 | BL88: 0 | BM88: 0 | BN88: #REF! | BO88: #REF! | BP88: 0 | BQ88: 0 | BR88: 0 | BS88: #REF! | BU88: 0 | BV88: 0 | BW88: 0 | BX88: #REF! | BY88: #REF! | BZ88: 0 | CA88: 0 | CB88: 0 | CC88: #REF! | CD88: 0 | CE88: 0 | CF88: 0 | CG88: 0 | CH88: #REF! | CI88: 0 | CJ88: #REF! | CK88: 0 | CL88: 0 | CM88: 0 | CN88: #REF! | CO88: 0 | CP88: 0 | CQ88: 0 | CR88: 0 | CS88: 0 | CT88: 0 | CU88: 0 | CV88: 0 | CW88: 0 | CX88: 0 | CY88: 0 | CZ88: 0 | DA88: 0 | DB88: 0 | DC88: 0 | DD88: 0 | DE88: 0 | DF88: 0 | DG88: 0 | DH88: 0 | DI88: 20491717221 | DJ88: DERIVADOS LACTEOS BARRETO S.R.L. | DK88: 07 Otros
A89: Cooperativa Agraria Renacer Andino | B89: DERIVADOS LACTEOS | C89: DERIVADOS LACTEOS | D89: Cajamarca | E89: 061307 | F89: Cajamarca | G89: Santa Cruz | H89: Pulan | I89: 1 | J89: 1 | K89: 1 | L89: 1 | Q89: PAC | R89: 2018-2019-2020-2021 | S89: 4 | T89: SI | U89: SI | V89: 135 | W89: 114 | X89: 22 | Y89: 136 | Z89: 111 | AA89: 23 | AB89: 134 | AC89: 27 | AD89: 3 | AE89: 30 | AF89: 0 | AG89: 0 | AH89: 0 | AI89: 0 | AJ89: 0 | AK89: 0 | AL89: 0 | AM89: 0 | AN89: 0 | AO89: 0 | AP89: 0 | AQ89: 0 | AR89: 30 | AS89: 20 | AT89: 4 | AU89: 29 | AV89: 8 | AW89: 0 | AX89: 0 | AY89: 0 | AZ89: 0 | BA89: 0 | BB89: 0 | BC89: 0 | BD89: 0 | BE89: 0 | BF89: 36558 | BG89: 0 | BH89: 36558 | BI89: #REF! | BJ89: #REF! | BK89: 197370 | BL89: 0 | BM89: 197370 | BN89: #REF! | BO89: #REF! | BP89: 137700 | BQ89: 0 | BR89: 137700 | BS89: #REF! | BU89: 0 | BV89: 0 | BW89: 0 | BX89: #REF! | BY89: #REF! | BZ89: 0 | CA89: 0 | CB89: 0 | CC89: #REF! | CD89: 0 | CE89: 0 | CF89: 0 | CG89: 0 | CH89: #REF! | CI89: 0 | CJ89: #REF! | CK89: 0 | CL89: 0 | CM89: 0 | CN89: #REF! | CO89: 0 | CP89: 0 | CQ89: 0 | CR89: 0 | CS89: 0 | CT89: 0 | CU89: 0 | CV89: 0 | CW89: 0 | CX89: 0 | CY89: 0 | CZ89: 0 | DA89: 0 | DB89: 0 | DC89: 0 | DD89: 0 | DE89: 0 | DF89: 0 | DG89: 0 | DH89: 0 | DI89: 20600717244 | DJ89: COOPERATIVA AGRARIA RENACER ANDINO | DK89: 02 Cooperativa
A90: Cooperativa Agraria Rutas del Inca | B90: CAFÉ | C90: CAFÉ | D90: Cajamarca | E90: 060415 | F90: Cajamarca | G90: Chota | H90: Querocoto | I90: 1 | J90: 1 | K90: 1 | L90: 1 | M90: 1 | N90: 1 | Q90: PAC | R90: 2018-2019-2020-2021-2022-2023 | S90: 6 | T90: SI | U90: SI | V90: 298 | W90: 267 | X90: 31 | Y90: 298 | Z90: 267 | AA90: 31 | AB90: 298 | AC90: 267 | AD90: 29 | AE90: 296 | AF90: 267 | AG90: 29 | AH90: 296 | AI90: 267 | AJ90: 29 | AK90: 296 | AL90: 0 | AM90: 0 | AN90: 0 | AO90: 0 | AP90: 0 | AQ90: 0 | AR90: 296 | AS90: 0 | AT90: 6 | AU90: 27 | AV90: 10 | AW90: 20 | AX90: 6 | AY90: 14 | AZ90: 4 | BA90: 0 | BB90: 0 | BC90: 0 | BD90: 0 | BE90: 0 | BF90: 0 | BG90: 602600.19 | BH90: 602600.19 | BI90: #REF! | BJ90: #REF! | BK90: 1927.98 | BL90: 1328260.2 | BM90: 1330188.1 | BN90: #REF! | BO90: #REF! | BP90: 0 | BQ90: 2804492.1 | BR90: 2804492.1 | BS90: #REF! | BU90: 0 | BV90: 3857237.5 | BW90: 3857237.5 | BX90: #REF! | BY90: #REF! | BZ90: 0 | CA90: 1684839.9 | CB90: 1684839.9 | CC90: #REF! | CD90: -3857237.5 | CE90: 0 | CF90: 0 | CG90: 0 | CH90: #REF! | CI90: -1684839.9 | CJ90: #REF! | CK90: 0 | CL90: 0 | CM90: 0 | CN90: #REF! | CO90: 0 | CP90: 0 | CQ90: 0 | CR90: 0 | CS90: 1684839.9 | CT90: 0 | CU90: 0 | CV90: 1684839.9 | CW90: 0 | CX90: 0 | CY90: 0 | CZ90: 0 | DA90: 0 | DB90: 0 | DC90: 0 | DD90: 0 | DE90: 0 | DF90: 0 | DG90: 0 | DH90: 0 | DI90: 20570706927 | DJ90: COOPERATIVA AGRARIA RUTAS DEL INCA | DK90: 02 Cooperativa
A91: Cooperativa de Servicios Múltiples Ecoforest | B91: CAFÉ | C91: CAFÉ | D91: Cajamarca | E91: 060801 | F91: Cajamarca | G91: Jaen | H91: Jaen | I91: 1 | J91: 1 | Q91: PAC | R91: 2018-2019 | S91: 2 | T91: SI | U91: NO | V91: 310 | W91: 257 | X91: 53 | Y91: 310 | Z91: 0 | AA91: 0 | AB91: 0 | AC91: 0 | AD91: 0 | AE91: 0 | AF91: 0 | AG91: 0 | AH91: 0 | AI91: 0 | AJ91: 0 | AK91: 0 | AL91: 0 | AM91: 0 | AN91: 0 | AO91: 0 | AP91: 0 | AQ91: 0 | AR91: 310 | AS91: 0 | AT91: 0 | AU91: 0 | AV91: 0 | AW91: 0 | AX91: 0 | AY91: 0 | AZ91: 0 | BA91: 0 | BB91: 0 | BC91: 0 | BD91: 0 | BE91: 0 | BF91: 992420.62 | BG91: 0 | BH91: 992420.62 | BI91: #REF! | BJ91: #REF! | BK91: 0 | BL91: 0 | BM91: 0 | BN91: #REF! | BO91: #REF! | BP91: 0 | BQ91: 0 | BR91: 0 | BS91: #REF! | BU91: 0 | BV91: 0 | BW91: 0 | BX91: #REF! | BY91: #REF! | BZ91: 0 | CA91: 0 | CB91: 0 | CC91: #REF! | CD91: 0 | CE91: 0 | CF91: 0 | CG91: 0 | CH91: #REF! | CI91: 0 | CJ91: #REF! | CK91: 0 | CL91: 0 | CM91: 0 | CN91: #REF! | CO91: 0 | CP91: 0 | CQ91: 0 | CR91: 0 | CS91: 0 | CT91: 0 | CU91: 0 | CV91: 0 | CW91: 0 | CX91: 0 | CY91: 0 | CZ91: 0 | DA91: 0 | DB91: 0 | DC91: 0 | DD91: 0 | DE91: 0 | DF91: 0 | DG91: 0 | DH91: 0 | DI91: 20542380455 | DJ91: COOPERATIVA AGRARIA ECOFOREST | DK91: 02 Cooperativa
A92: Cooperativa Agraria los Ambientalistas LTDA | B92: CAFÉ | C92: CAFÉ | D92: Cajamarca | E92: 060613 | F92: Cajamarca | G92: Cutervo | H92: Santo Tomas | I92: 1 | J92: 1 | Q92: PAC | R92: 2018-2019 | S92: 2 | T92: SI | U92: NO | V92: 122 | W92: 91 | X92: 28 | Y92: 119 | Z92: 0 | AA92: 0 | AB92: 0 | AC92: 0 | AD92: 0 | AE92: 0 | AF92: 0 | AG92: 0 | AH92: 0 | AI92: 0 | AJ92: 0 | AK92: 0 | AL92: 0 | AM92: 0 | AN92: 0 | AO92: 0 | AP92: 0 | AQ92: 0 | AR92: 119 | AS92: 0 | AT92: 0 | AU92: 0 | AV92: 0 | AW92: 0 | AX92: 0 | AY92: 0 | AZ92: 0 | BA92: 0 | BB92: 0 | BC92: 0 | BD92: 0 | BE92: 0 | BF92: 0 | BG92: 0 | BH92: 0 | BI92: #REF! | BJ92: #REF! | BK92: 0 | BL92: 0 | BM92: 0 | BN92: #REF! | BO92: #REF! | BP92: 0 | BQ92: 0 | BR92: 0 | BS92: #REF! | BU92: 0 | BV92: 0 | BW92: 0 | BX92: #REF! | BY92: #REF! | BZ92: 0 | CA92: 0 | CB92: 0 | CC92: #REF! | CD92: 0 | CE92: 0 | CF92: 0 | CG92: 0 | CH92: #REF! | CI92: 0 | CJ92: #REF! | CK92: 0 | CL92: 0 | CM92: 0 | CN92: #REF! | CO92: 0 | CP92: 0 | CQ92: 0 | CR92: 0 | CS92: 0 | CT92: 0 | CU92: 0 | CV92: 0 | CW92: 0 | CX92: 0 | CY92: 0 | CZ92: 0 | DA92: 0 | DB92: 0 | DC92: 0 | DD92: 0 | DE92: 0 | DF92: 0 | DG92: 0 | DH92: 0 | DI92: 20601186986 | DJ92: COOPERATIVA AGRARIA LOS AMBIENTALISTAS LTDA | DK92: 02 Cooperativa
A93: Asociacion de Productores Cafetaleros Andinos Sierra Verde | B93: CAFÉ | C93: CAFÉ | D93: Cajamarca | E93: 060801 | F93: Cajamarca | G93: Jaen | H93: Jaen | I93: 1 | J93: 1 | K93: 1 | L93: 1 | M93: 1 | N93: 1 | Q93: PAC | R93: 2018-2019-2020-2021-2022-2023 | S93: 6 | T93: SI | U93: SI | V93: 217 | W93: 160 | X93: 57 | Y93: 217 | Z93: 160 | AA93: 57 | AB93: 217 | AC93: 161 | AD93: 54 | AE93: 215 | AF93: 161 | AG93: 54 | AH93: 215 | AI93: 161 | AJ93: 54 | AK93: 215 | AL93: 0 | AM93: 0 | AN93: 0 | AO93: 0 | AP93: 0 | AQ93: 0 | AR93: 215 | AS93: 0 | AT93: 6 | AU93: 27 | AV93: 10 | AW93: 18 | AX93: 6 | AY93: 13 | AZ93: 4 | BA93: 0 | BB93: 0 | BC93: 0 | BD93: 0 | BE93: 0 | BF93: 838619.83 | BG93: 0 | BH93: 838619.83 | BI93: #REF! | BJ93: #REF! | BK93: 2149542.9 | BL93: 0 | BM93: 2149542.9 | BN93: #REF! | BO93: #REF! | BP93: 3595209.1 | BQ93: 0 | BR93: 3595209.1 | BS93: #REF! | BU93: 4081192.3 | BV93: 0 | BW93: 4081192.3 | BX93: #REF! | BY93: #REF! | BZ93: 3614510 | CA93: 0 | CB93: 3614510 | CC93: #REF! | CD93: -4081192.3 | CE93: 0 | CF93: 0 | CG93: 0 | CH93: #REF! | CI93: -3614510 | CJ93: #REF! | CK93: 0 | CL93: 0 | CM93: 0 | CN93: #REF! | CO93: 0 | CP93: 0 | CQ93: 0 | CR93: 0 | CS93: 3614510 | CT93: 0 | CU93: 0 | CV93: 3614510 | CW93: 0 | CX93: 0 | CY93: 0 | CZ93: 0 | DA93: 0 | DB93: 0 | DC93: 0 | DD93: 0 | DE93: 0 | DF93: 0 | DG93: 0 | DH93: 0 | DI93: 20600785541 | DJ93: ASOCIACION DE PRODUCTORES CAFETALEROS ANDINOS SIERRA VERDE | DK93: 01 Asociación
A94: Asociación Agroindustrial de Mujeres Productoras de Cacao y Café del VRAEM-Otari´s | B94: CACAO | C94: CACAO EN GRANO | D94: Ayacucho | E94: 080910 | F94: Cusco | G94: La Convencion | H94: Pichari | P94: 1 | Q94: PAC | R94: 2025 | S94: 1 | T94: SI | U94: SI | V94: 0 | W94: 0 | X94: 0 | Y94: 0 | Z94: 0 | AA94: 0 | AB94: 0 | AC94: 0 | AD94: 0 | AE94: 0 | AF94: 0 | AG94: 0 | AH94: 0 | AI94: 0 | AJ94: 0 | AK94: 0 | AL94: 0 | AM94: 0 | AN94: 0 | AO94: 0 | AP94: 77 | AQ94: 77 | AR94: 77 | BC94: 29 | BD94: 0 | BI94: Sin incremento | BJ94: 0 | BN94: Sin incremento | BO94: 0 | BS94: Sin incremento | BT94: 0 | BX94: Sin incremento | BY94: 0 | CC94: Sin incremento | CD94: 0 | CH94: Sin incremento | CI94: 0 | CJ94: #REF! | CK94: 313500 | CL94: 0 | CM94: 313500 | CN94: #REF! | CO94: 0 | DC94: 0 | DD94: 0 | DE94: 313500 | DF94: 0 | DG94: 0 | DH94: 313500 | DI94: 20605228489 | DJ94: ASOCIACION AGROINDUSTRIAL DE MUJERES PRODUCTORAS DE CACAO Y CAFE DEL VRAEM-OTARI´S | DK94: 01 Asociación
A95: Asoc. de Produc. Agrop. Agroind. Forestales y Serv. Mult. la Flor de la Granadilla - Alto Pere | B95: GRANADILLA | C95: GRANADILLA | D95: Cajamarca | E95: 060801 | F95: Cajamarca | G95: Jaen | H95: Jaen | J95: 1 | Q95: PAC | R95: 2019 | S95: 1 | T95: SI | U95: NO | V95: 0 | W95: 0 | X95: 0 | Y95: 0 | Z95: 0 | AA95: 0 | AB95: 0 | AC95: 0 | AD95: 0 | AE95: 0 | AF95: 0 | AG95: 0 | AH95: 0 | AI95: 0 | AJ95: 0 | AK95: 0 | AL95: 0 | AM95: 0 | AN95: 0 | AO95: 0 | AP95: 0 | AQ95: 0 | AR95: --- | AS95: 0 | AT95: 0 | AU95: 0 | AV95: 0 | AW95: 0 | AX95: 0 | AY95: 0 | AZ95: 0 | BA95: 0 | BB95: 0 | BC95: 0 | BD95: 0 | BE95: 0 | BF95: 0 | BG95: 0 | BH95: 0 | BI95: #REF! | BJ95: #REF! | BK95: 0 | BL95: 0 | BM95: 0 | BN95: #REF! | BO95: #REF! | BP95: 0 | BQ95: 0 | BR95: 0 | BS95: #REF! | BU95: 0 | BV95: 0 | BW95: 0 | BX95: #REF! | BY95: #REF! | BZ95: 0 | CA95: 0 | CB95: 0 | CC95: #REF! | CD95: 0 | CE95: 0 | CF95: 0 | CG95: 0 | CH95: #REF! | CI95: 0 | CJ95: #REF! | CK95: 0 | CL95: 0 | CM95: 0 | CN95: #REF! | CO95: 0 | CP95: 0 | CQ95: 0 | CR95: 0 | CS95: 0 | CT95: 0 | CU95: 0 | CV95: 0 | CW95: 0 | CX95: 0 | CY95: 0 | CZ95: 0 | DA95: 0 | DB95: 0 | DC95: 0 | DD95: 0 | DE95: 0 | DF95: 0 | DG95: 0 | DH95: 0 | DI95: SIN RUC | DJ95: ASOC DE PRODUC AGROP, AGROIN, FORESTALES Y SERV MULT LA FLOR DE LA GRANADILLA- ALTO PERU | DK95: 01 Asociación
A96: Asociación de Productores de Granadilla Pacharumi | B96: GRANADILLA | C96: GRANADILLA | D96: Cajamarca | E96: 060803 | F96: Cajamarca | G96: Jaen | H96: Chontali | J96: 1 | Q96: PAC | R96: 2019 | S96: 1 | T96: SI | U96: NO | V96: 0 | W96: 0 | X96: 0 | Y96: 0 | Z96: 0 | AA96: 0 | AB96: 0 | AC96: 0 | AD96: 0 | AE96: 0 | AF96: 0 | AG96: 0 | AH96: 0 | AI96: 0 | AJ96: 0 | AK96: 0 | AL96: 0 | AM96: 0 | AN96: 0 | AO96: 0 | AP96: 0 | AQ96: 0 | AR96: --- | AS96: 0 | AT96: 0 | AU96: 0 | AV96: 0 | AW96: 0 | AX96: 0 | AY96: 0 | AZ96: 0 | BA96: 0 | BB96: 0 | BC96: 0 | BD96: 0 | BE96: 0 | BF96: 0 | BG96: 0 | BH96: 0 | BI96: #REF! | BJ96: #REF! | BK96: 0 | BL96: 0 | BM96: 0 | BN96: #REF! | BO96: #REF! | BP96: 0 | BQ96: 0 | BR96: 0 | BS96: #REF! | BU96: 0 | BV96: 0 | BW96: 0 | BX96: #REF! | BY96: #REF! | BZ96: 0 | CA96: 0 | CB96: 0 | CC96: #REF! | CD96: 0 | CE96: 0 | CF96: 0 | CG96: 0 | CH96: #REF! | CI96: 0 | CJ96: #REF! | CK96: 0 | CL96: 0 | CM96: 0 | CN96: #REF! | CO96: 0 | CP96: 0 | CQ96: 0 | CR96: 0 | CS96: 0 | CT96: 0 | CU96: 0 | CV96: 0 | CW96: 0 | CX96: 0 | CY96: 0 | CZ96: 0 | DA96: 0 | DB96: 0 | DC96: 0 | DD96: 0 | DE96: 0 | DF96: 0 | DG96: 0 | DH96: 0 | DI96: 20570699700 | DJ96: ASOCIACION DE PRODUCTORES AGROPECUARIOS PACHARUMII | DK96: 01 Asociación
A97: Cooperativa de Productores Agropecuarios Hualgayoc | B97: DERIVADOS LACTEOS | C97: DERIVADOS LACTEOS | D97: Cajamarca | E97: 060703 | F97: Cajamarca | G97: Hualgayoc | H97: Hualgayoc | J97: 1 | L97: 1 | M97: 1 | N97: 1 | Q97: PAC | R97: 2019-2021-2022-2023 | S97: 4 | T97: SI | U97: SI | V97: 0 | W97: 41 | X97: 14 | Y97: 55 | Z97: 0 | AA97: 0 | AB97: 0 | AC97: 29 | AD97: 27 | AE97: 56 | AF97: 29 | AG97: 27 | AH97: 56 | AI97: 29 | AJ97: 27 | AK97: 56 | AL97: 0 | AM97: 0 | AN97: 0 | AO97: 0 | AP97: 0 | AQ97: 0 | AR97: 56 | AS97: 0 | AT97: 0 | AU97: 33 | AV97: 6 | AW97: 10 | AX97: 2 | AY97: 47 | AZ97: 5 | BA97: 0 | BB97: 0 | BC97: 0 | BD97: 0 | BE97: 0 | BF97: 0 | BG97: 0 | BH97: 0 | BI97: #REF! | BJ97: #REF! | BK97: 0 | BL97: 0 | BM97: 0 | BN97: #REF! | BO97: #REF! | BP97: 950270 | BQ97: 0 | BR97: 950270 | BS97: #REF! | BU97: 486350 | BV97: 0 | BW97: 486350 | BX97: #REF! | BY97: #REF! | BZ97: 1611989.7 | CA97: 0 | CB97: 1611989.7 | CC97: #REF! | CD97: -486350 | CE97: 0 | CF97: 0 | CG97: 0 | CH97: #REF! | CI97: -1611989.7 | CJ97: #REF! | CK97: 0 | CL97: 0 | CM97: 0 | CN97: #REF! | CO97: 0 | CP97: 0 | CQ97: 1611989.7 | CR97: 0 | CS97: 0 | CT97: 0 | CU97: 0 | CV97: 1611989.7 | CW97: 0 | CX97: 0 | CY97: 0 | CZ97: 0 | DA97: 0 | DB97: 0 | DC97: 0 | DD97: 0 | DE97: 0 | DF97: 0 | DG97: 0 | DH97: 0 | DI97: 20602902235 | DJ97: COOPERATIVA DE PRODUCTORES AGROPECUARIOS HUALGAYOC | DK97: 02 Cooperativa
A98: Cooperativa Agraria Jalca Verde | B98: HONGO COMESTIBLE | C98: HONGOS COMESTIBLES | D98: Cajamarca | E98: 060105 | F98: Cajamarca | G98: Cajamarca | H98: Encañada | J98: 1 | K98: 1 | L98: 1 | Q98: PAC | R98: 2019-2020-2021 | S98: 3 | T98: SI | U98: SI | V98: 0 | W98: 41 | X98: 12 | Y98: 53 | Z98: 40 | AA98: 13 | AB98: 53 | AC98: 23 | AD98: 12 | AE98: 35 | AF98: 0 | AG98: 0 | AH98: 0 | AI98: 0 | AJ98: 0 | AK98: 0 | AL98: 0 | AM98: 0 | AN98: 0 | AO98: 0 | AP98: 0 | AQ98: 0 | AR98: 35 | AS98: 34 | AT98: 6 | AU98: 73 | AV98: 7 | AW98: 0 | AX98: 0 | AY98: 0 | AZ98: 0 | BA98: 0 | BB98: 0 | BC98: 0 | BD98: 0 | BE98: 0 | BF98: 33189.75 | BG98: 0 | BH98: 33189.75 | BI98: #REF! | BJ98: #REF! | BK98: 9510 | BL98: 0 | BM98: 9510 | BN98: #REF! | BO98: #REF! | BP98: 2350 | BQ98: 0 | BR98: 2350 | BS98: #REF! | BU98: 0 | BV98: 0 | BW98: 0 | BX98: #REF! | BY98: #REF! | BZ98: 0 | CA98: 0 | CB98: 0 | CC98: #REF! | CD98: 0 | CE98: 0 | CF98: 0 | CG98: 0 | CH98: #REF! | CI98: 0 | CJ98: #REF! | CK98: 0 | CL98: 0 | CM98: 0 | CN98: #REF! | CO98: 0 | CP98: 0 | CQ98: 0 | CR98: 0 | CS98: 0 | CT98: 0 | CU98: 0 | CV98: 0 | CW98: 0 | CX98: 0 | CY98: 0 | CZ98: 0 | DA98: 0 | DB98: 0 | DC98: 0 | DD98: 0 | DE98: 0 | DF98: 0 | DG98: 0 | DH98: 0 | DI98: 20600325478 | DJ98: COOPERATIVA AGRARIA JALCA VERDE | DK98: 02 Cooperativa
A99: Cooperativa Agraria Coopagro LTDA - Cooperativa Coopagro | B99: CAFÉ | C99: CAFÉ | D99: Cajamarca | E99: 060801 | F99: Cajamarca | G99: Jaen | H99: Jaen | L99: 1 | M99: 1 | N99: 1 | O99: 1 | Q99: PAC | R99: 2021-2022-2023-2024 | S99: 4 | T99: SI | U99: SI | V99: 0 | W99: 0 | X99: 0 | Y99: 0 | Z99: 0 | AA99: 0 | AB99: 0 | AC99: 311 | AD99: 96 | AE99: 407 | AF99: 311 | AG99: 96 | AH99: 407 | AI99: 311 | AJ99: 96 | AK99: 407 | AL99: 311 | AM99: 97 | AN99: 408 | AO99: 0 | AP99: 0 | AQ99: 0 | AR99: 408 | AS99: 0 | AT99: 0 | AU99: 21 | AV99: 9 | AW99: 21 | AX99: 6 | AY99: 13 | AZ99: 4 | BA99: 11 | BB99: 4 | BC99: 0 | BD99: 0 | BE99: 0 | BF99: 0 | BG99: 0 | BH99: 0 | BI99: #REF! | BJ99: #REF! | BK99: 0 | BL99: 0 | BM99: 0 | BN99: #REF! | BO99: #REF! | BP99: 579309.04 | BQ99: 741934.76 | BR99: 1321243.8 | BS99: #REF! | BU99: 0 | BV99: 1959097.1 | BW99: 1959097.1 | BX99: #REF! | BY99: #REF! | BZ99: 0 | CA99: 1515083.8 | CB99: 1515083.8 | CC99: #REF! | CD99: -1959097.1 | CE99: 0 | CF99: 841453.19 | CG99: 841453.19 | CH99: #REF! | CI99: -1515083.8 | CJ99: #REF! | CK99: 0 | CL99: 0 | CM99: 0 | CN99: #REF! | CO99: -841453.19 | CP99: 0 | CQ99: 0 | CR99: 0 | CS99: 1515083.8 | CT99: 0 | CU99: 0 | CV99: 1515083.8 | CW99: 0 | CX99: 0 | CY99: 841453.19 | CZ99: 0 | DA99: 0 | DB99: 841453.19 | DC99: 0 | DD99: 0 | DE99: 0 | DF99: 0 | DG99: 0 | DH99: 0 | DI99: 20607536016 | DJ99: COOPERATIVA AGRARIA COOPAGRO LTDA - COOPERATIVA COOPAGRO | DK99: 02 Cooperativa
A100: Cooperativa de Servicios Especiales Redes de Productores de Cuyes del Crisnejas - Coopredescuy | B100: CUY | C100: CUY | D100: Cajamarca | E100: 060203 | F100: Cajamarca | G100: Cajabamba | H100: Condebamba | M100: 1 | N100: 1 | O100: 1 | Q100: PAC | R100: 2022-2023-2024 | S100: 3 | T100: SI | U100: SI | V100: 0 | W100: 0 | X100: 0 | Y100: 0 | Z100: 0 | AA100: 0 | AB100: 0 | AC100: 0 | AD100: 0 | AE100: 0 | AF100: 41 | AG100: 42 | AH100: 83 | AI100: 41 | AJ100: 42 | AK100: 83 | AL100: 40 | AM100: 42 | AN100: 82 | AO100: 0 | AP100: 0 | AQ100: 0 | AR100: 82 | AS100: 0 | AT100: 0 | AU100: 0 | AV100: 0 | AW100: 56 | AX100: 5 | AY100: 10 | AZ100: 5 | BA100: 58 | BB100: 4 | BC100: 0 | BD100: 0 | BE100: 0 | BF100: 0 | BG100: 0 | BH100: 0 | BI100: #REF! | BJ100: #REF! | BK100: 0 | BL100: 0 | BM100: 0 | BN100: #REF! | BO100: #REF! | BP100: 0 | BQ100: 0 | BR100: 0 | BS100: #REF! | BU100: 226595 | BV100: 0 | BW100: 226595 | BX100: #REF! | BY100: #REF! | BZ100: 881820 | CA100: 0 | CB100: 881820 | CC100: #REF! | CD100: -226595 | CE100: 1797516 | CF100: 0 | CG100: 1797516 | CH100: #REF! | CI100: -881820 | CJ100: 0 | CK100: 0 | CL100: 0 | CM100: 0 | CN100: #REF! | CO100: -1797516 | CP100: 0 | CQ100: 881820 | CR100: 0 | CS100: 0 | CT100: 0 | CU100: 0 | CV100: 881820 | CW100: 0 | CX100: 1797516 | CY100: 0 | CZ100: 0 | DA100: 0 | DB100: 1797516 | DC100: 0 | DD100: 0 | DE100: 0 | DF100: 0 | DG100: 0 | DH100: 0 | DI100: 20529538988 | DJ100: COOPERATIVA DE SERVICIOS ESPECIALES REDES DE PRODUCTORES DE CUYES DEL CRISNEJAS | DK100: 02 Cooperativa
...

Sheet base 7
A1: Unnamed: 0 | B1: Unnamed: 1 | C1: Unnamed: 2 | D1: Unnamed: 3 | E1: Unnamed: 4 | F1: Unnamed: 5 | G1: Unnamed: 6 | H1: Unnamed: 7 | I1: Unnamed: 8 | J1: Unnamed: 9 | K1: Unnamed: 10 | L1: Unnamed: 11 | M1: Unnamed: 12 | N1: Unnamed: 13 | O1: Unnamed: 14 | P1: Unnamed: 15 | Q1: Unnamed: 16 | R1: Unnamed: 17 | S1: Unnamed: 18 | T1: Unnamed: 19 | U1: Unnamed: 20 | V1: Unnamed: 21 | W1: Unnamed: 22 | X1: VENTAS POR TIPO DE COMPROMABNTE año 2025 -12.01.26) | Y1: Unnamed: 24 | Z1: Unnamed: 25 | AA1: Unnamed: 26 | AB1: Unnamed: 27 | AC1: Unnamed: 28 | AD1: Unnamed: 29 | AE1: Unnamed: 30
O2: 2025 (Ciierre de Agosto 2025) | S2: 2025 (Cierre de 12.01.26)
A3: Nombre de la Organización | B3: PRODUCTO DOM | C3: PRODUCTO 1 | D3: SEDE | E3: Ubigeo | F3: DEPARTAMENTO | G3: Provincia | H3: Distrito | I3: TIPO DE CERTIFICADO | J3: 2025 | K3: SERVICIO | L3: AÑOS DE INTERVENCION | M3: AÑOS DE INTERVENCIÓN DESDE 2018 AL 2024 | N3: INTERVENCIÓN 2019 al 2025 | O3: BENF MASC 2025 | P3: BENF FEM 2025 | Q3: TOTAL BENF 2025 | R3: TOTAL VENTAS 2018 AL 2025 | S3: V. EJEC NACIONALES 2025 | T3: V. EJEC EXPORTACION 2025 | U3: VENTAS TOTALES 2025 | V3: INCREMENTOS VENTAS EN 2025 | W3: DIFERENCIA VENTAS 2025-2024 | X3: Boleta de Venta 2025 | Y3: Declaración Jurada 2025 | Z3: Factura 2025 | AA3: Guía de Remisión 2025 | AB3: Liquidación de Compra 2025 | AC3: Total general 2025 | AD3: RUC | AE3: Tipo de Organización* (Asociación/Cooperativa/CCNN, Comunidad Campesina y otros.)
A4: Cooperativa Agraria de Usuarios de Pequeños Productores del PERU | B4: MANGO | C4: MANGO | D4: Ancash | E4: 020801 | F4: Ancash | G4: Casma | H4: Casma | I4: FAIR TRADE | J4: 1 | K4: PAC | L4: 2025 | M4: 1 | N4: SI | O4: 15 | P4: 9 | Q4: 24 | X4: 0 | Y4: 399056.4 | Z4: 866144.87 | AA4: 0 | AB4: 0 | AC4: 1265201.3 | AD4: 20601575184 | AE4: Cooperativa
A5: Cooperativa Agraria Agrofrutos Organicos | B5: MANGO | C5: MANGO | D5: Lambayeque | E5: 140307 | F5: Lambayeque | G5: Lambayeque | H5: Motupe | I5: ORGANICO | J5: 1 | K5: PAC | L5: 2025 | M5: 1 | O5: 62 | P5: 10 | Q5: 72 | R5: #REF! | S5: 22435.002 | T5: 0 | U5: 22435.002 | V5: #REF! | X5: 0 | Y5: 0 | Z5: 22435.002 | AA5: 0 | AB5: 0 | AC5: 22435.002 | AD5: 20613899287 | AE5: Cooperativa
A6: Cooperativa Agraria de Usuarios Aspraosra LTDA | B6: BANANO | C6: BANANO | D6: Piura | F6: Piura | G6: Morropon | H6: Buenos Aires | I6: ORGANICO/GLOBAL GAP | J6: 1 | K6: PAC | L6: 2025 | M6: 1 | O6: 22 | P6: 14 | Q6: 36 | R6: #REF! | S6: 0 | T6: 781855.2 | U6: 781855.2 | V6: #REF! | X6: 0 | Y6: 0 | Z6: 781855.2 | AA6: 0 | AB6: 0 | AC6: 781855.2 | AD6: 20526179367 | AE6: Cooperativa
A7: Asociacion de Agricultores Innovadores de Ancash, Ediflor | B7: PALTA | C7: PALTA | D7: Ancash | F7: Ancash | G7: Santa | H7: Chimbote | I7: GLOBAL GAP | J7: 1 | K7: PAC | L7: 2025 | O7: 4 | P7: 7 | Q7: 11 | R7: #REF! | S7: 120000 | T7: 0 | U7: 120000 | V7: #REF! | X7: 0 | Y7: 120000 | Z7: 0 | AA7: 0 | AB7: 0 | AC7: 120000 | AD7: 20611531088 | AE7: Asociacion
A8: Asociación de Productores Agropecuarios Chaskas de Huancallama-Apachahua | B8: PALTA | C8: PALTA | D8: Huancavelica | E8: 090409 | F8: Huancavelica | G8: Castrovirreyna | H8: Mollepampa | I8: GLOBAL GAP | J8: 1 | K8: PAC | L8: 2025 | M8: 1 | O8: 20 | P8: 4 | Q8: 24 | R8: #REF! | S8: 0 | T8: 0 | U8: 0 | V8: #REF! | X8: 0 | Y8: 0 | Z8: 0 | AA8: 0 | AB8: 0 | AC8: 0 | AD8: 20607063576 | AE8: Asociación
A9: Asociacion de Agricultores de Paltos en Huamampali - Alto Laran | B9: PALTA | C9: PALTA | D9: Ica | F9: Ica | G9: Chincha | H9: Huamanpali | I9: GLOBAL GAP | J9: 1 | K9: PAC | L9: 2025 | M9: 1 | O9: 19 | P9: 2 | Q9: 21 | R9: 0 | S9: 0 | T9: 0 | U9: 0 | V9: 0 | W9: 0 | X9: 0 | Y9: 0 | Z9: 0 | AA9: 0 | AB9: 0 | AC9: 0 | AD9: 20605371869 | AE9: Asociación

Sheet base consolidad MIDAGRI
A1: RUC | B1: Nombre de la Organización | C1: PRODUCTO DOM | D1: PRODUCTO 1 | E1: SEDE | F1: Ubigeo | G1: DEPARTAMENTO | H1: Provincia | I1: Distrito | J1: 2018 | K1: 2019 | L1: 2020 | M1: 2021 | N1: 2022 | O1: 2023 | P1: 2024 | Q1: 2025 | R1: SERVICIO | S1: AÑOS DE INTERVENCION | T1: AÑOS DE INTERVENCIÓN DESDE 2018 AL 2024 | U1: INTERVENCIÓN 2019 al 2025 | V1: INTERVENCIÓN 2020 al 2026 | W1: TOTAL BENF 2018 | X1: BENF MASC 2019 | Y1: BENF FEM 2019 | Z1: TOTAL BENF 2019 | AA1: BENF MASC 2020 | AB1: BENF FEM 2020 | AC1: TOTAL BENF 2020 | AD1: BENF MASC 2021 | AE1: BENF FEM 2021 | AF1: TOTAL BENF 2021 | AG1: BENF MASC 2022 | AH1: BENF FEM 2022 | AI1: TOTAL BENF 2022 | AJ1: BENF MASC 2023 | AK1: BENF FEM 2023 | AL1: TOTAL BENF 2023 | AM1: BENF MASC 2024 | AN1: BENF FEM 2024 | AO1: TOTAL BENF 2024 | AP1: BENF MASC 2025 | AQ1: BENF FEM 2025 | AR1: TOTAL BENF 2025 | AS1: BENEFICIADOS ULTIMO AÑO | AT1: ASISTENCIA TÉCNICA 2020 | AU1: TALLERES 2020 | AV1: ASISTENCIA TÉCNICA 2021 | AW1: TALLERES 2021 | AX1: ASISTENCIA TÉCNICA 2022 | AY1: TALLERES 2022 | AZ1: ASISTENCIA TÉCNICA 2023 | BA1: TALLERES 2023 | BB1: ASISTENCIA TÉCNICA 2024 | BC1: TALLERES 2024 | BD1: ASISTENCIA TÉCNICA 2025 | BE1: TALLERES 2025 | BF1: VENTAS TOTALES 2018 | BG1: VENTAS NACIONALES 2019 | BH1: VENTAS INTERNACIONALES 2019 | BI1: VENTAS TOTALES 2019 | BJ1: INCREMENTOS VENTAS EN 2019 | BK1: INCREMENTOS VENTAS EN 20192 | BL1: VENTAS NACIONALES 2020 | BM1: VENTAS INTERNACIONALES 2020 | BN1: VENTAS TOTALES 2020 | BO1: INCREMENTOS VENTAS EN 2020 | BP1: DIFERENCIA VENTA 2020-2019 | BQ1: VENTAS NACIONALES 2021 | BR1: VENTAS INTERNACIONALES 2021 | BS1: VENTAS TOTALES 2021 | BT1: INCREMENTOS VENTAS EN 20201 | BU1: DIFERENCIA VENTA 2021-2020 | BV1: V. EJEC NACIONALES 2022 | BW1: V. EJEC EXPORTACION 2022 | BX1: VENTAS TOTALES 2022 | BY1: INCREMENTOS VENTAS EN 22022 | BZ1: DIFERENCIA VENTAS 2022-2021 | CA1: V. EJEC NACIONALES 2023 | CB1: V. EJEC EXPORTACION 2023 | CC1: VENTAS TOTALES 2023 | CD1: INCREMENTOS VENTAS EN 2023 | CE1: DIFERENCIA VENTAS 2023-2022 | CF1: V. EJEC NACIONALES 2024 | CG1: V. EJEC EXPORTACION 2024 | CH1: VENTAS TOTALES 20224 | CI1: INCREMENTOS VENTAS EN 2024 | CJ1: DIFERENCIA VENTAS 2024-2023 | CK1: TOTAL VENTAS 2018 AL 2025 | CL1: V. EJEC NACIONALES 2025 | CM1: V. EJEC EXPORTACION 2025 | CN1: VENTAS TOTALES 2025 | CO1: INCREMENTOS VENTAS EN 2025 | CP1: DIFERENCIA VENTAS 2025-2024 | CQ1: Boleta de Venta 2023 | CR1: Declaracion Jurada 2023 | CS1: Documento de Entrega Cooperativo (DEC) 2023 | CT1: Factura 2023 | CU1: Guia de Remision 2023 | CV1: Liquidacion de Compra 2023 | CW1: Total Ventas 2023 (De comprobantes) (*) | CX1: Boleta de Venta 2024 | CY1: Declaración Jurada 2024 | CZ1: Factura 2024 | DA1: Guía de Remisión 2024 | DB1: Liquidación de Compra 2024 | DC1: Total general 2024 | DD1: Boleta de Venta 2025 | DE1: Declaración Jurada 2025 | DF1: Factura 2025 | DG1: Guía de Remisión 2025 | DH1: Liquidación de Compra 2025 | DI1: Total general 2025 | DJ1: NOMBRE SUNAT | DK1: Tipo de Organización* (Asociación/Cooperativa/CCNN, Comunidad Campesina y otros.) | DL1: TIPO DE CERTIFICADO | DM1: N° | DN1: Región | DO1: Provincia | DP1: Distrito | DQ1: Activo/ Habido SUNAT (Status al 24/02/2026) | DR1: Fecha de inicio de actividades | DS1: AÑO DE INTERVENCION | DT1: Colocar la Etapa en la que se encuentra el PAC: Formulación Ejecución Finalizado | DU1: Breve descripcion de la organización | DV1: Resumen del avance del PAC | DW1: Organización | DX1: Número de socios ( varones) | DY1: Numero de socias ( Mujeres) | DZ1: Numero de hectareas totales de la organización | EA1: Volumen de producción total estimado para la cosecha 2026 en quintales de cafe verde | EB1: Meses de cosecha 2026 | EC1: Meses: Disponibilidad para embarque o Entrega al mercado nacional | ED1: Altitud de las unidades productivas : sobre el nivel del mar | EE1: Mencionar con que variedades del cafe arábica cuentan los socios de la organización. Colocar en % estimado por cada variedad | EF1: Certificación Organica vigente (colocar el numero de certificado y la fecha de la vigencia) | EG1: Certificación Comercio Justo colocar el numero de certificado y la fecha de la vigencia) | EH1: Con que otras certificaciones vigentes cuentan (tambien incluir la vigencia de cada uno) | EI1: Colocar la calidad con que contarán para la cosecha 2026: Grado 1: Se admite un máximo de 15 defectos o imperfecciones Grado 2: Se admite un máximo de 23 defectos o imperfecciones Grado 3: Se admite un máximo de 30 defectos o imperfecciones Grado 4: Se admite un máximo de 31 a 60 defectos y/o imperfecciones ( Grado 4 según NTP 209.027:2024 CAFÉ. Café verde. Requisitos. 6a Edición) Café Especial incluir : el puntaje y el perfil referencial del café ** Si hay otras calidades de volumen, especificar. En el siguiente link, https://cloud.agromercado.gob.pe/index.php/s/PRVXHpA3V2GA2TC , encontrarán las guias para cafe verde, cafe especial, manual de defectos para el café arabica lavado de especialidad. | EJ1: Indicar el avance con el reglamento de la EUDR | EK1: Dirección | EL1: Correo | EM1: celular | EN1: Página Web | EO1: Redes sociales | EP1: nombre Gerente General | EQ1: celular.1 | ER1: correo | ES1: nombre representante legal | ET1: celular.2 | EU1: correo.1 | EV1: Registro Sanitario | EW1: Vencimiento Registro Sanitario | EX1: Marca de Café Tostado en grano | EY1: Tipo de presentación del Café Tostado en grano | EZ1: Marca de Café Tostado Molido | FA1: Tipo de presentación del Café Tostado en Molido | FB1: Comentarios ( si desea aclarar o comentar algún aspecto) | FC1: EXPORTA SI / NO | FD1: EXPORTACIONES 2025 FOB DOLARES | FE1: Q EN KILOS | FF1: Sacos de 69 kilos | FG1: Q de contenedores | FH1: Destinos | FI1: _ORIGEN
A2: 20600529693 | B2: Agro Asociación y Servicios Tinkuy | C2: CACAO | D2: CACAO | E2: Ayacucho | F2: 50408 | G2: Ayacucho | H2: Huanta | I2: Llochegua | J2: 1 | K2: 1 | R2: PAC | S2: 2018-2019 | T2: 2 | U2: SI | V2: NO | W2: 33 | X2: 21 | Y2: 12 | Z2: 33 | AA2: 0 | AB2: 0 | AC2: 0 | AD2: 0 | AE2: 0 | AF2: 0 | AG2: 0 | AH2: 0 | AI2: 0 | AJ2: 0 | AK2: 0 | AL2: 0 | AM2: 0 | AN2: 0 | AO2: 0 | AP2: 0 | AQ2: 0 | AR2: 0 | AS2: 33 | AT2: 0 | AU2: 0 | AV2: 0 | AW2: 0 | AX2: 0 | AY2: 0 | AZ2: 0 | BA2: 0 | BB2: 0 | BC2: 0 | BD2: 0 | BE2: 0 | BF2: 0 | BG2: 59766 | BH2: 0 | BI2: 59766 | BJ2: 59766 | BK2: 59766 | BL2: 0 | BM2: 0 | BN2: 0 | BO2: -59766 | BP2: -59766 | BQ2: 0 | BR2: 0 | BS2: 0 | BT2: 0 | BU2: 0 | BV2: 0 | BW2: 0 | BX2: 0 | BY2: 0 | BZ2: 0 | CA2: 0 | CB2: 0 | CC2: 0 | CD2: 0 | CE2: 0 | CF2: 0 | CG2: 0 | CH2: 0 | CI2: 0 | CJ2: 0 | CK2: 59766 | CL2: 0 | CM2: 0 | CN2: 0 | CO2: 0 | CP2: 0 | CQ2: 0 | CR2: 0 | CS2: 0 | CT2: 0 | CU2: 0 | CV2: 0 | CW2: 0 | CX2: 0 | CY2: 0 | CZ2: 0 | DA2: 0 | DB2: 0 | DC2: 0 | DD2: 0 | DE2: 0 | DF2: 0 | DG2: 0 | DH2: 0 | DI2: 0 | DJ2: AGRO ASOCIACION Y SERVICIOS TINKUY | DK2: 01 Asociación | FI2: pacMAYOR
A3: 20118588135 | B3: Cooperativa de Servicios Especiales Alpaqueras - Puno (Cecoalp) | C3: FIBRA DE ALPACA | D3: FIBRA DE ALPACA | E3: Puno | F3: 211101 | G3: Puno | H3: San Roman | I3: Juliaca | J3: 1 | K3: 1 | L3: 1 | M3: 1 | O3: 1 | R3: PAC | S3: 2018-2019-2020-2021-2023 | T3: 5 | U3: SI | V3: SI | W3: 284 | X3: 42 | Y3: 33 | Z3: 75 | AA3: 42 | AB3: 33 | AC3: 75 | AD3: 42 | AE3: 33 | AF3: 75 | AG3: 0 | AH3: 0 | AI3: 0 | AJ3: 60 | AK3: 30 | AL3: 90 | AM3: 0 | AN3: 0 | AO3: 0 | AP3: 0 | AQ3: 0 | AR3: 0 | AS3: 90 | AT3: 5 | AU3: 4 | AV3: 60 | AW3: 5 | AX3: 0 | AY3: 0 | AZ3: 24 | BA3: 3 | BB3: 0 | BC3: 0 | BD3: 0 | BE3: 0 | BF3: 0 | BG3: 850000 | BH3: 0 | BI3: 850000 | BJ3: 850000 | BK3: 850000 | BL3: 850000 | BM3: 0 | BN3: 850000 | BO3: 0 | BP3: 0 | BQ3: 436600 | BR3: 0 | BS3: 436600 | BT3: -413400 | BU3: -413400 | BV3: 0 | BW3: 0 | BX3: 0 | BY3: -436600 | BZ3: -436600 | CA3: 85185.8 | CB3: 0 | CC3: 85185.8 | CD3: 85185.8 | CE3: 85185.8 | CF3: 0 | CG3: 0 | CH3: 0 | CI3: -85185.8 | CJ3: -85185.8 | CK3: 2221785.8 | CL3: 0 | CM3: 0 | CN3: 0 | CO3: 0 | CP3: 0 | CQ3: 0 | CR3: 85185.8 | CS3: 0 | CT3: 0 | CU3: 0 | CV3: 0 | CW3: 85185.8 | CX3: 0 | CY3: 0 | CZ3: 0 | DA3: 0 | DB3: 0 | DC3: 0 | DD3: 0 | DE3: 0 | DF3: 0 | DG3: 0 | DH3: 0 | DI3: 0 | DJ3: CENTRAL DE COOPERATIVAS DE SERVICIOS ESPECIALES ALPAQUERAS DE PUNO LTDA. - CECOALP | DK3: 07 Otros | FI3: pacMAYOR
A4: 20119208026 | B4: Fongal Tacna | C4: DERIVADOS LACTEOS | D4: QUESOS MADURADOS | E4: Moquegua-Tacna | F4: 230101 | G4: Tacna | H4: Tacna | I4: Tacna | J4: 1 | R4: PAC | S4: 2018 | T4: 1 | U4: NO | V4: NO | W4: 42 | X4: 0 | Y4: 0 | Z4: 0 | AA4: 0 | AB4: 0 | AC4: 0 | AD4: 0 | AE4: 0 | AF4: 0 | AG4: 0 | AH4: 0 | AI4: 0 | AJ4: 0 | AK4: 0 | AL4: 0 | AM4: 0 | AN4: 0 | AO4: 0 | AP4: 0 | AQ4: 0 | AR4: 0 | AS4: 42 | AT4: 0 | AU4: 0 | AV4: 0 | AW4: 0 | AX4: 0 | AY4: 0 | AZ4: 0 | BA4: 0 | BB4: 0 | BC4: 0 | BD4: 0 | BE4: 0 | BF4: 0 | BG4: 0 | BH4: 0 | BI4: 0 | BJ4: 0 | BK4: 0 | BL4: 0 | BM4: 0 | BN4: 0 | BO4: 0 | BP4: 0 | BQ4: 0 | BR4: 0 | BS4: 0 | BT4: 0 | BU4: 0 | BV4: 0 | BW4: 0 | BX4: 0 | BY4: 0 | BZ4: 0 | CA4: 0 | CB4: 0 | CC4: 0 | CD4: 0 | CE4: 0 | CF4: 0 | CG4: 0 | CH4: 0 | CI4: 0 | CJ4: 0 | CK4: 0 | CL4: 0 | CM4: 0 | CN4: 0 | CO4: 0 | CP4: 0 | CQ4: 0 | CR4: 0 | CS4: 0 | CT4: 0 | CU4: 0 | CV4: 0 | CW4: 0 | CX4: 0 | CY4: 0 | CZ4: 0 | DA4: 0 | DB4: 0 | DC4: 0 | DD4: 0 | DE4: 0 | DF4: 0 | DG4: 0 | DH4: 0 | DI4: 0 | DJ4: FONGAL TACNA | DK4: 01 Asociación | FI4: pacMAYOR
A5: 20606556331 | B5: Asociación Abiseo San Martin - Asabisam | C5: CACAO | D5: CACAO | E5: San Martin | F5: 220601 | G5: San Martin | H5: Mariscal Caceres | I5: Juanjui | P5: 1 | Q5: 1 | R5: PAC | S5: 2024 - 2025 | T5: 2 | U5: SI | V5: SI | W5: 0 | X5: 0 | Y5: 0 | Z5: 0 | AA5: 0 | AB5: 0 | AC5: 0 | AD5: 0 | AE5: 0 | AF5: 0 | AG5: 0 | AH5: 0 | AI5: 0 | AJ5: 0 | AK5: 0 | AL5: 0 | AM5: 22 | AN5: 8 | AO5: 30 | AP5: 33 | AQ5: 25 | AR5: 58 | AS5: 58 | AT5: 0 | AU5: 0 | AV5: 0 | AW5: 0 | AX5: 0 | AY5: 0 | AZ5: 0 | BA5: 0 | BB5: 3 | BC5: 0 | BD5: 12 | BE5: 0 | BF5: 0 | BG5: 0 | BH5: 0 | BI5: 0 | BJ5: 0 | BK5: 0 | BL5: 0 | BM5: 0 | BN5: 0 | BO5: 0 | BP5: 0 | BQ5: 0 | BR5: 0 | BS5: 0 | BT5: 0 | BU5: 0 | BV5: 0 | BW5: 0 | BX5: 0 | BY5: 0 | BZ5: 0 | CA5: 0 | CB5: 0 | CC5: 0 | CD5: 0 | CE5: 0 | CF5: 0 | CG5: 0 | CH5: 0 | CI5: 0 | CJ5: 0 | CK5: 0 | CL5: 0 | CM5: 0 | CN5: 0 | CO5: 0 | CP5: 0 | CQ5: 0 | CR5: 0 | CS5: 0 | CT5: 0 | CU5: 0 | CV5: 0 | CW5: 0 | CX5: 0 | CY5: 0 | CZ5: 0 | DA5: 0 | DB5: 0 | DC5: 0 | DD5: 0 | DE5: 0 | DF5: 0 | DG5: 0 | DH5: 0 | DI5: 0 | DJ5: ASOCIACIÓN ABISEO SAN MARTIN - ASABISAM | DK5: 01 Asociación | FI5: pacMAYOR
A6: 20602650643 | B6: Asociación Agroexportadora de la Región San Martín | C6: CAFÉ | D6: CAFE VERDE | E6: San Martin | F6: 220101 | G6: San Martin | H6: Moyobamba | I6: Moyobamba | Q6: 1 | R6: PAC | S6: 2025 | T6: 1 | U6: SI | V6: SI | W6: 0 | X6: 0 | Y6: 0 | Z6: 0 | AA6: 0 | AB6: 0 | AC6: 0 | AD6: 0 | AE6: 0 | AF6: 0 | AG6: 0 | AH6: 0 | AI6: 0 | AJ6: 0 | AK6: 0 | AL6: 0 | AM6: 0 | AN6: 0 | AO6: 0 | AP6: 407 | AQ6: 200 | AR6: 607 | AS6: 607 | BD6: 6 | BE6: 0 | CK6: 26019551 | CL6: 374967.7 | CM6: 25644583 | CN6: 26019551 | CO6: 26019551 | CP6: 26019551 | DD6: 0 | DE6: 0 | DF6: 26019551 | DG6: 0 | DH6: 0 | DI6: 26019551 | DJ6: ASOCIACIÓN AGROEXPORTADORA DE LA REGIÓN SAN MARTÍN | DK6: 01 Asociación | DM6: 7 | DN6: San Martín | DO6: Moyobamba | DP6: Moyobamba | DQ6: SI | DR6: 43062 | DS6: 2025 | DT6: Ejecución | DU6: Organización agraria dedicada a la producción de café, que cuenta con diversas certificaciones, como orgánico y comercio justo, además de la marca de Agricultura Familiar. Está conformada por 607 socios. | DV6: Dio inicio el PAC 2025, dando comienzo al proceso de articulación comercial en función de las necesidades identificadas en el diagnóstico. Asimismo, se ha brindado apoyo mediante un Especialista en EUDR, a través del cual se logró registrar a los socios en el PPA. De igual manera, se gestionó un memorando de entendimiento con el MIDAGRI, el cual actualmente se encuentra en proceso. | DW6: Asociación Agroexportadora de la Región San Martín | DX6: 607 | DY6: 155 | DZ6: 1500 | EA6: 22000 qq | EB6: Marzo - Noviembre | EC6: Marzo - Diciembre | ED6: 1100 - 1700 m s. n. m. | EE6: Catimor, Costa Rica, Castilla, Típica, Pache | EF6: Si (vigencia hasta el 23/10/2026) certificación de OCI Internacionla N° LPO -00750 | EG6: Si (vigencia hasta junio del 2028) | EH6: Certificación Orgánica Certificación Comercio Justo (Fairtrade) | EI6: Grado 1: 40 contenedores Grado 2: 15 contenedores Café Especial incluir : Cafes taza limpia de 82 a 83 puntos SCA | EJ6: 0.8 | EK6: Car.Marginal Nro. S/N (Al Costado de Perhusac) | EL6: agroexportadorsanmartin@hotmail.com | EM6: 981234888 | EN6: https://agrosanmartin.com/ | EP6: Zamora Malca Gerardo | EQ6: 981234888 | ER6: agroexportadorsanmartin@hotmail.com | ES6: Zamora Malca Gerardo | ET6: 981234888 | EU6: agroexportadorsanmartin@hotmail.com | EV6: No cuenta con Registro | EX6: NO | EY6: NO | EZ6: NO | FC6: SI | FD6: 6402453 | FE6: 864660 | FF6: 12531.304 | FG6: 45.568379 | FH6: Alemania, Suecia,Mexico, Belgica, Reino Unido | FI6: pacMAYOR|san martin
A7: 20129772043 | B7: Cooperativa Comunal de Vicco LTDA | C7: FIBRA DE ALPACA | D7: FIBRA DE ALPACA | E7: Pasco | F7: 190112 | G7: Pasco | H7: Pasco | I7: Vicco | M7: 1 | N7: 1 | R7: PAC | S7: 2021-2022 | T7: 2 | U7: SI | V7: SI | W7: 0 | X7: 0 | Y7: 0 | Z7: 0 | AA7: 0 | AB7: 0 | AC7: 0 | AD7: 398 | AE7: 240 | AF7: 638 | AG7: 398 | AH7: 240 | AI7: 638 | AJ7: 0 | AK7: 0 | AL7: 0 | AM7: 0 | AN7: 0 | AO7: 0 | AP7: 0 | AQ7: 0 | AR7: 0 | AS7: 638 | AT7: 0 | AU7: 0 | AV7: 34 | AW7: 1 | AX7: 42 | AY7: 0 | AZ7: 0 | BA7: 0 | BB7: 0 | BC7: 0 | BD7: 0 | BE7: 0 | BF7: 0 | BG7: 0 | BH7: 0 | BI7: 0 | BJ7: 0 | BK7: 0 | BL7: 0 | BM7: 0 | BN7: 0 | BO7: 0 | BP7: 0 | BQ7: 28852.7 | BR7: 0 | BS7: 28852.7 | BT7: 28852.7 | BU7: 28852.7 | BV7: 0 | BW7: 0 | BX7: 0 | BY7: -28852.7 | BZ7: -28852.7 | CA7: 0 | CB7: 0 | CC7: 0 | CD7: 0 | CE7: 0 | CF7: 0 | CG7: 0 | CH7: 0 | CI7: 0 | CJ7: 0 | CK7: 28852.7 | CL7: 0 | CM7: 0 | CN7: 0 | CO7: 0 | CP7: 0 | CQ7: 0 | CR7: 0 | CS7: 0 | CT7: 0 | CU7: 0 | CV7: 0 | CW7: 0 | CX7: 0 | CY7: 0 | CZ7: 0 | DA7: 0 | DB7: 0 | DC7: 0 | DD7: 0 | DE7: 0 | DF7: 0 | DG7: 0 | DH7: 0 | DI7: 0 | DJ7: COOPERATIVA COMUNAL VICCO LTDA | DK7: 02 Cooperativa | FI7: pacMAYOR
A8: 20129830426 | B8: Cooperativa Comunal de Huayllay LTDA 16 | C8: FIBRA DE ALPACA | D8: FIBRA DE ALPACA | E8: Pasco | F8: 190104 | G8: Pasco | H8: Pasco | I8: Huayllay | M8: 1 | N8: 1 | P8: 1 | Q8: 1 | R8: PAC | S8: 2021-2022-2024 - 2025 | T8: 4 | U8: SI | V8: SI | W8: 0 | X8: 0 | Y8: 0 | Z8: 0 | AA8: 0 | AB8: 0 | AC8: 0 | AD8: 272 | AE8: 215 | AF8: 487 | AG8: 272 | AH8: 215 | AI8: 487 | AJ8: 0 | AK8: 0 | AL8: 0 | AM8: 272 | AN8: 215 | AO8: 487 | AP8: 235 | AQ8: 254 | AR8: 489 | AS8: 489 | AT8: 0 | AU8: 0 | AV8: 38 | AW8: 1 | AX8: 42 | AY8: 0 | AZ8: 0 | BA8: 0 | BB8: 33 | BC8: 0 | BD8: 20 | BE8: 4 | BF8: 0 | BG8: 0 | BH8: 0 | BI8: 0 | BJ8: 0 | BK8: 0 | BL8: 0 | BM8: 0 | BN8: 0 | BO8: 0 | BP8: 0 | BQ8: 254137.96 | BR8: 0 | BS8: 254137.96 | BT8: 254137.96 | BU8: 254137.96 | BV8: 384239.16 | BW8: 0 | BX8: 384239.16 | BY8: 130101.2 | BZ8: 130101.2 | CA8: 0 | CB8: 0 | CC8: 0 | CD8: -384239.16 | CE8: -384239.16 | CF8: 0 | CG8: 0 | CH8: 0 | CI8: 0 | CJ8: 0 | CK8: 638377.12 | CL8: 0 | CM8: 0 | CN8: 0 | CO8: 0 | CP8: 0 | CQ8: 0 | CR8: 0 | CS8: 0 | CT8: 0 | CU8: 0 | CV8: 0 | CW8: 0 | CX8: 0 | CY8: 0 | CZ8: 0 | DA8: 0 | DB8: 0 | DC8: 0 | DD8: 0 | DE8: 0 | DF8: 0 | DG8: 0 | DH8: 0 | DI8: 0 | DJ8: COOPERATIVA COMUNAL HUAYLLAY LTDA 16 | DK8: 02 Cooperativa | FI8: pacMAYOR
A9: 20129842351 | B9: Cooperativa Comunal San Antonio de Rancas LTDA. | C9: FIBRA DE ALPACA | D9: FIBRA DE ALPACA | E9: Pasco | F9: 190109 | G9: Pasco | H9: Pasco | I9: Simon Bolivar | K9: 1 | L9: 1 | M9: 1 | N9: 1 | R9: PAC | S9: 2019-2020-2021-2022 | T9: 4 | U9: SI | V9: SI | W9: 0 | X9: 6 | Y9: 2 | Z9: 8 | AA9: 87 | AB9: 76 | AC9: 163 | AD9: 85 | AE9: 79 | AF9: 164 | AG9: 85 | AH9: 79 | AI9: 164 | AJ9: 0 | AK9: 0 | AL9: 0 | AM9: 0 | AN9: 0 | AO9: 0 | AP9: 0 | AQ9: 0 | AR9: 0 | AS9: 164 | AT9: 0 | AU9: 0 | AV9: 33 | AW9: 2 | AX9: 42 | AY9: 0 | AZ9: 0 | BA9: 0 | BB9: 0 | BC9: 0 | BD9: 0 | BE9: 0 | BF9: 0 | BG9: 0 | BH9: 0 | BI9: 0 | BJ9: 0 | BK9: 0 | BL9: 37140 | BM9: 0 | BN9: 37140 | BO9: 37140 | BP9: 37140 | BQ9: 0 | BR9: 0 | BS9: 0 | BT9: -37140 | BU9: -37140 | BV9: 25752 | BW9: 0 | BX9: 25752 | BY9: 25752 | BZ9: 25752 | CA9: 0 | CB9: 0 | CC9: 0 | CD9: -25752 | CE9: -25752 | CF9: 0 | CG9: 0 | CH9: 0 | CI9: 0 | CJ9: 0 | CK9: 62892 | CL9: 0 | CM9: 0 | CN9: 0 | CO9: 0 | CP9: 0 | CQ9: 0 | CR9: 0 | CS9: 0 | CT9: 0 | CU9: 0 | CV9: 0 | CW9: 0 | CX9: 0 | CY9: 0 | CZ9: 0 | DA9: 0 | DB9: 0 | DC9: 0 | DD9: 0 | DE9: 0 | DF9: 0 | DG9: 0 | DH9: 0 | DI9: 0 | DJ9: COOPERATIVA COMUNAL SAN ANTONIO DE RANCAS LTDA. 289 | DK9: 02 Cooperativa | FI9: pacMAYOR
A10: 20131453427 | B10: Cooperativa Comunal San Pedro de Racco LTDA | C10: FIBRA DE ALPACA | D10: FIBRA DE ALPACA | E10: Pasco | F10: 190109 | G10: Pasco | H10: Pasco | I10: Simon Bolivar | M10: 1 | N10: 1 | P10: 1 | Q10: 1 | R10: PAC | S10: 2021-2022-2024 - 2025 | T10: 4 | U10: SI | V10: SI | W10: 0 | X10: 0 | Y10: 0 | Z10: 0 | AA10: 0 | AB10: 0 | AC10: 0 | AD10: 110 | AE10: 78 | AF10: 188 | AG10: 109 | AH10: 78 | AI10: 187 | AJ10: 0 | AK10: 0 | AL10: 0 | AM10: 111 | AN10: 80 | AO10: 191 | AP10: 117 | AQ10: 95 | AR10: 212 | AS10: 212 | AT10: 0 | AU10: 0 | AV10: 33 | AW10: 1 | AX10: 42 | AY10: 0 | AZ10: 0 | BA10: 0 | BB10: 40 | BC10: 0 | BD10: 21 | BE10: 4 | BF10: 0 | BG10: 0 | BH10: 0 | BI10: 0 | BJ10: 0 | BK10: 0 | BL10: 0 | BM10: 0 | BN10: 0 | BO10: 0 | BP10: 0 | BQ10: 130050.3 | BR10: 0 | BS10: 130050.3 | BT10: 130050.3 | BU10: 130050.3 | BV10: 83938 | BW10: 0 | BX10: 83938 | BY10: -46112.3 | BZ10: -46112.3 | CA10: 0 | CB10: 0 | CC10: 0 | CD10: -83938 | CE10: -83938 | CF10: 0 | CG10: 0 | CH10: 0 | CI10: 0 | CJ10: 0 | CK10: 213988.3 | CL10: 0 | CM10: 0 | CN10: 0 | CO10: 0 | CP10: 0 | CQ10: 0 | CR10: 0 | CS10: 0 | CT10: 0 | CU10: 0 | CV10: 0 | CW10: 0 | CX10: 0 | CY10: 0 | CZ10: 0 | DA10: 0 | DB10: 0 | DC10: 0 | DD10: 0 | DE10: 0 | DF10: 0 | DG10: 0 | DH10: 0 | DI10: 0 | DJ10: COOPERATIVA COMUNAL SAN PEDRO DE RACCO | DK10: 02 Cooperativa | FI10: pacMAYOR
A11: 20132489824 | B11: Cooperativa Agraria Cafetalera Chancamayo LTDA. N° 008-B-Vii | C11: CAFÉ | D11: CAFÉ | E11: Cusco | F11: 80408 | G11: Cusco | H11: Calca | I11: Yanatile | DJ11: COOPERATIVA AGRARIA CAFETALERA CHANCAMAYO LTDA. N° 008-B-VII | DK11: 02 Cooperativa | DM11: 19 | DN11: Cusco | DO11: Calca | DP11: Yanatile | DQ11: SI | DR11: 27075 | DS11: 2025 | DT11: Ejecucion | DU11: La Cooperativa agraria cafetalera Chancamayo ltda 008*B-VII es una organización sólida y debidamente formalizada que inició sus actividades económicas el 15/02/1974, se ha consolidado como un referente en la producción y comercialización de café de calidad de la region Cusco. | DV11: En el marco de las estrategias de apoyo al productor, AGROMERCADO se encuentra ejecutando un Plan de Articulación Comercial en beneficio de esta cooperativa. Esta intervención se realiza en estricto cumplimiento de lo priorizado en el Anexo 5A | DW11: Cooperativa Agraria Cafetalera Chancamayo Ltda N° 008-B-VII, | DX11: 30 | DY11: 14 | DZ11: 44 | EA11: 20TM | EB11: Mayo - Agosto | EC11: Junio - Noviembre | ED11: 1400 - 2150 m s. n. m. | EE11: Catimor 70%, Caturra 10%, Bourbon 5%, Otros 15% | EF11: Certificacion Organica, vigencia hasta 14/08/2026 | EG11: Vigencia organica hasta 26/03/2027 | EI11: Grado 1: 65 %, Grado 2: 60% | EK11: Centro Poblado de Chancamayo Yanatile - Provincia de Calca | EL11: walticomt@hotmail.com | EM11: 976065194 | EP11: Fredy Castillo Herrera | EQ11: 976065194 | ER11: walticomt@hotmail.com | ES11: Fredy Castillo Herrera | ET11: 976065194 | EU11: walticomt@hotmail.com | EV11: no cuenta con registro | FC11: NO | FI11: san martin
A12: 20605228489 | B12: Asociación Agroindustrial de Mujeres Productoras de Cacao y Café del VRAEM-Otari´s | C12: CACAO | D12: CACAO EN GRANO | E12: Ayacucho | F12: 80910 | G12: Cusco | H12: La Convencion | I12: Pichari | Q12: 1 | R12: PAC | S12: 2025 | T12: 1 | U12: SI | V12: SI | W12: 0 | X12: 0 | Y12: 0 | Z12: 0 | AA12: 0 | AB12: 0 | AC12: 0 | AD12: 0 | AE12: 0 | AF12: 0 | AG12: 0 | AH12: 0 | AI12: 0 | AJ12: 0 | AK12: 0 | AL12: 0 | AM12: 0 | AN12: 0 | AO12: 0 | AP12: 0 | AQ12: 77 | AR12: 77 | AS12: 77 | BD12: 29 | BE12: 0 | CK12: 313500 | CL12: 313500 | CM12: 0 | CN12: 313500 | CO12: 313500 | CP12: 313500 | DD12: 0 | DE12: 0 | DF12: 313500 | DG12: 0 | DH12: 0 | DI12: 313500 | DJ12: ASOCIACIÓN AGROINDUSTRIAL DE MUJERES PRODUCTORAS DE CACAO Y CAFÉ DEL VRAEM-OTARI´S | DK12: 01 Asociación | FI12: pacMAYOR
A13: 20606041382 | B13: Asociacion Aroma de Mujer Llaque | C13: CAFÉ | D13: CAFÉ | E13: Lambayeque | F13: 140310 | G13: Lambayeque | H13: Lambayeque | I13: Salas | P13: 1 | Q13: 1 | R13: PAC | S13: 2024 - 2025 | T13: 2 | U13: SI | V13: SI | W13: 0 | X13: 0 | Y13: 0 | Z13: 0 | AA13: 0 | AB13: 0 | AC13: 0 | AD13: 0 | AE13: 0 | AF13: 0 | AG13: 0 | AH13: 0 | AI13: 0 | AJ13: 0 | AK13: 0 | AL13: 0 | AM13: 20 | AN13: 14 | AO13: 34 | AP13: 13 | AQ13: 11 | AR13: 24 | AS13: 24 | AT13: 0 | AU13: 0 | AV13: 0 | AW13: 0 | AX13: 0 | AY13: 0 | AZ13: 0 | BA13: 0 | BB13: 48 | BC13: 4 | BD13: 45 | BE13: 4 | BF13: 0 | BG13: 0 | BH13: 0 | BI13: 0 | BJ13: 0 | BK13: 0 | BL13: 0 | BM13: 0 | BN13: 0 | BO13: 0 | BP13: 0 | BQ13: 0 | BR13: 0 | BS13: 0 | BT13: 0 | BU13: 0 | BV13: 0 | BW13: 0 | BX13: 0 | BY13: 0 | BZ13: 0 | CA13: 0 | CB13: 0 | CC13: 0 | CD13: 0 | CE13: 0 | CF13: 0 | CG13: 0 | CH13: 0 | CI13: 0 | CJ13: 0 | CK13: 0 | CL13: 0 | CM13: 0 | CN13: 0 | CO13: 0 | CP13: 0 | CQ13: 0 | CR13: 0 | CS13: 0 | CT13: 0 | CU13: 0 | CV13: 0 | CW13: 0 | CX13: 0 | CY13: 0 | CZ13: 0 | DA13: 0 | DB13: 0 | DC13: 0 | DD13: 0 | DE13: 0 | DF13: 0 | DG13: 0 | DH13: 0 | DI13: 0 | DJ13: ASOCIACION AROMA DE MUJER LLAQUE | DK13: 01 Asociación | FI13: pacMAYOR
A14: 20600964080 | B14: Asociación de Agricultores Kergueranos | C14: CAFÉ | D14: CAFÉ | E14: Lambayeque | F14: 140310 | G14: Lambayeque | H14: Lambayeque | I14: Salas | K14: 1 | L14: 1 | O14: 1 | R14: PAC | S14: 2019-2020-2023 | T14: 3 | U14: SI | V14: SI | W14: 0 | X14: 22 | Y14: 28 | Z14: 50 | AA14: 24 | AB14: 26 | AC14: 50 | AD14: 0 | AE14: 0 | AF14: 0 | AG14: 0 | AH14: 0 | AI14: 0 | AJ14: 89 | AK14: 27 | AL14: 116 | AM14: 0 | AN14: 0 | AO14: 0 | AP14: 0 | AQ14: 0 | AR14: 0 | AS14: 116 | AT14: 0 | AU14: 0 | AV14: 0 | AW14: 0 | AX14: 0 | AY14: 0 | AZ14: 22 | BA14: 4 | BB14: 0 | BC14: 0 | BD14: 0 | BE14: 0 | BF14: 0 | BG14: 0 | BH14: 0 | BI14: 0 | BJ14: 0 | BK14: 0 | BL14: 24668.25 | BM14: 0 | BN14: 24668.25 | BO14: 24668.25 | BP14: 24668.25 | BQ14: 0 | BR14: 0 | BS14: 0 | BT14: -24668.25 | BU14: -24668.25 | BV14: 0 | BW14: 0 | BX14: 0 | BY14: 0 | BZ14: 0 | CA14: 28500 | CB14: 0 | CC14: 28500 | CD14: 28500 | CE14: 28500 | CF14: 0 | CG14: 0 | CH14: 0 | CI14: -28500 | CJ14: -28500 | CK14: 53168.25 | CL14: 0 | CM14: 0 | CN14: 0 | CO14: 0 | CP14: 0 | CQ14: 0 | CR14: 0 | CS14: 0 | CT14: 0 | CU14: 28500 | CV14: 0 | CW14: 28500 | CX14: 0 | CY14: 0 | CZ14: 0 | DA14: 0 | DB14: 0 | DC14: 0 | DD14: 0 | DE14: 0 | DF14: 0 | DG14: 0 | DH14: 0 | DI14: 0 | DJ14: ASOCIACIÓN DE AGRICULTORES KERGUERANOS | DK14: 01 Asociación | FI14: pacMAYOR
A15: 20610772553 | B15: Asociación de Mujeres Caficultoras de Chinyama Cañaris | C15: CAFÉ | D15: CAFÉ | E15: Lambayeque | F15: 140202 | G15: Lambayeque | H15: Ferreñafe | I15: Cañaris | P15: 1 | Q15: 1 | R15: PAC | S15: 2024 - 2025 | T15: 2 | U15: SI | V15: SI | W15: 0 | X15: 0 | Y15: 0 | Z15: 0 | AA15: 0 | AB15: 0 | AC15: 0 | AD15: 0 | AE15: 0 | AF15: 0 | AG15: 0 | AH15: 0 | AI15: 0 | AJ15: 0 | AK15: 0 | AL15: 0 | AM15: 8 | AN15: 27 | AO15: 35 | AP15: 1 | AQ15: 14 | AR15: 15 | AS15: 15 | AT15: 0 | AU15: 0 | AV15: 0 | AW15: 0 | AX15: 0 | AY15: 0 | AZ15: 0 | BA15: 0 | BB15: 50 | BC15: 7 | BD15: 166 | BE15: 3 | BF15: 0 | BG15: 0 | BH15: 0 | BI15: 0 | BJ15: 0 | BK15: 0 | BL15: 0 | BM15: 0 | BN15: 0 | BO15: 0 | BP15: 0 | BQ15: 0 | BR15: 0 | BS15: 0 | BT15: 0 | BU15: 0 | BV15: 0 | BW15: 0 | BX15: 0 | BY15: 0 | BZ15: 0 | CA15: 0 | CB15: 0 | CC15: 0 | CD15: 0 | CE15: 0 | CF15: 0 | CG15: 0 | CH15: 0 | CI15: 0 | CJ15: 0 | CK15: 168424.62 | CL15: 168424.62 | CM15: 0 | CN15: 168424.62 | CO15: 168424.62 | CP15: 168424.62 | CQ15: 0 | CR15: 0 | CS15: 0 | CT15: 0 | CU15: 0 | CV15: 0 | CW15: 0 | CX15: 0 | CY15: 0 | CZ15: 0 | DA15: 0 | DB15: 0 | DC15: 0 | DD15: 0 | DE15: 168424.62 | DF15: 0 | DG15: 0 | DH15: 0 | DI15: 168424.62 | DJ15: ASOCIACIÓN DE MUJERES CAFICULTORAS DE CHINYAMA CAÑARIS | DK15: 01 Asociación | FI15: pacMAYOR
A16: 20602047025 | B16: Asociacion de Mujeres Chocolateras Chocolate Corazon de Nolberth Alto Uruya | C16: CACAO | D16: CACAO | E16: Ucayali | F16: 250304 | G16: Ucayali | H16: Padre Abad | I16: Neshuya | N16: 1 | R16: PAC | S16: 2022 | T16: 1 | U16: SI | V16: SI | W16: 0 | X16: 0 | Y16: 0 | Z16: 0 | AA16: 0 | AB16: 0 | AC16: 0 | AD16: 0 | AE16: 0 | AF16: 0 | AG16: 10 | AH16: 7 | AI16: 17 | AJ16: 0 | AK16: 0 | AL16: 0 | AM16: 0 | AN16: 0 | AO16: 0 | AP16: 0 | AQ16: 0 | AR16: 0 | AS16: 17 | AT16: 0 | AU16: 0 | AV16: 0 | AW16: 0 | AX16: 47 | AY16: 0 | AZ16: 0 | BA16: 0 | BB16: 0 | BC16: 0 | BD16: 0 | BE16: 0 | BF16: 0 | BG16: 0 | BH16: 0 | BI16: 0 | BJ16: 0 | BK16: 0 | BL16: 0 | BM16: 0 | BN16: 0 | BO16: 0 | BP16: 0 | BQ16: 0 | BR16: 0 | BS16: 0 | BT16: 0 | BU16: 0 | BV16: 12244 | BW16: 0 | BX16: 12244 | BY16: 12244 | BZ16: 12244 | CA16: 0 | CB16: 0 | CC16: 0 | CD16: -12244 | CE16: -12244 | CF16: 0 | CG16: 0 | CH16: 0 | CI16: 0 | CJ16: 0 | CK16: 12244 | CL16: 0 | CM16: 0 | CN16: 0 | CO16: 0 | CP16: 0 | CQ16: 0 | CR16: 0 | CS16: 0 | CT16: 0 | CU16: 0 | CV16: 0 | CW16: 0 | CX16: 0 | CY16: 0 | CZ16: 0 | DA16: 0 | DB16: 0 | DC16: 0 | DD16: 0 | DE16: 0 | DF16: 0 | DG16: 0 | DH16: 0 | DI16: 0 | DJ16: ASOCIACION DE MUJERES CHOCOLATERAS CHOCOLATE CORAZON DE NOLBERTH ALTO URUYA | DK16: 01 Asociación | FI16: pacMAYOR
A17: 20542251990 | B17: Asociacion de Mujeres Emprendedoras de Nuevo Progreso | C17: CACAO | D17: CACAO | E17: San Martin | F17: 221002 | G17: San Martin | H17: Tocache | I17: Nuevo Progreso | J17: 1 | K17: 1 | L17: 1 | R17: PAC | S17: 2018-2019-2020 | T17: 3 | U17: SI | V17: SI | W17: 29 | X17: 0 | Y17: 29 | Z17: 29 | AA17: 0 | AB17: 29 | AC17: 29 | AD17: 0 | AE17: 0 | AF17: 0 | AG17: 0 | AH17: 0 | AI17: 0 | AJ17: 0 | AK17: 0 | AL17: 0 | AM17: 0 | AN17: 0 | AO17: 0 | AP17: 0 | AQ17: 0 | AR17: 0 | AS17: 29 | AT17: 0 | AU17: 1 | AV17: 0 | AW17: 0 | AX17: 0 | AY17: 0 | AZ17: 0 | BA17: 0 | BB17: 0 | BC17: 0 | BD17: 0 | BE17: 0 | BF17: 0 | BG17: 9089.28 | BH17: 0 | BI17: 9089.28 | BJ17: 9089.28 | BK17: 9089.28 | BL17: 19627.8 | BM17: 0 | BN17: 19627.8 | BO17: 10538.52 | BP17: 10538.52 | BQ17: 0 | BR17: 0 | BS17: 0 | BT17: -19627.8 | BU17: -19627.8 | BV17: 0 | BW17: 0 | BX17: 0 | BY17: 0 | BZ17: 0 | CA17: 0 | CB17: 0 | CC17: 0 | CD17: 0 | CE17: 0 | CF17: 0 | CG17: 0 | CH17: 0 | CI17: 0 | CJ17: 0 | CK17: 28717.08 | CL17: 0 | CM17: 0 | CN17: 0 | CO17: 0 | CP17: 0 | CQ17: 0 | CR17: 0 | CS17: 0 | CT17: 0 | CU17: 0 | CV17: 0 | CW17: 0 | CX17: 0 | CY17: 0 | CZ17: 0 | DA17: 0 | DB17: 0 | DC17: 0 | DD17: 0 | DE17: 0 | DF17: 0 | DG17: 0 | DH17: 0 | DI17: 0 | DJ17: ASOCIACION DE MUJERES EMPRENDEDORAS DE NUEVO PROGRESO | DK17: 01 Asociación | FI17: pacMAYOR
A18: 20140181405 | B18: Cooperativa Agraria Cafetalera la Florida | C18: CAFÉ | E18: Junín | F18: 120302 | G18: Junín | H18: Chanchamayo | I18: Perene | DJ18: COOPERATIVA AGRARIA CAFETALERA LA FLORIDA | DK18: 02 Cooperativa | DM18: 27 | DN18: Junín | DO18: Chanchamayo | DP18: Perene | DQ18: SI | DR18: 25849 | DS18: 2026 | DT18: Ejecución | DU18: Organización agraria dedicada a la producción de café, que cuenta con diversas certificaciones, como orgánico y comercio justo | DV18: Se realizo el primer embarque de café verde para el mercado de Francia a fines de abril del presente año | DW18: Cooperativa Agraria Cafetalera la Florida | DX18: 339 | DY18: 111 | DZ18: 1605.8 | EA18: 13700 | EB18: Abril - Octubre | EC18: Mayo - Diciembre | ED18: Mayor a 1200 m s. n. m. | EE18: Catimor, Costa Rica, Catuaí, Castilla, Marsellesa | EF18: 1780867353, VIGENCIA HASTA 06 FEB 2028 | EG18: FLO ID 796, VIGENCIA HASTA 24 DIC 2028 | EH18: BIRD FRIENDEY y Fairtrade | EI18: Grado 1: Se admite un máximo de 15 defectos o imperfecciones, Grado 2: Se admite un máximo de 23 defectos o imperfecciones, Grado 3: Se admite un máximo de 30 defectos o imperfecciones | EJ18: 0.75 | EK18: C.P. Yurinaki S/N Perene Chanchamayo | EL18: gerente@laflorida.org.pe | EM18: 993234718 | EN18: https://laflorida.org.pe/es/la_florida | EO18: https://www.facebook.com/profile.php?id=61581161727085&sk=about | EP18: Edwin Villacorta Reategui | EQ18: 993234718 | ER18: gerencia@laflorida.org.pe | ES18: Edwin Villacorta Reategui | ET18: 993234718 | EU18: gerencia@laflorida.org.pe | EV18: Q0244724N/KCCAR; Q0041224N/KCCOAR | EW18: 46635 | EX18: Aroma Mujer, Monte Inkareado, Maestro | EY18: 250 gr | EZ18: Aroma Munjer, Monte Inkareado, Maestro | FA18: empaque trilaminados | FC18: SI | FD18: 2877331.6 | FE18: 355410 | FF18: 5150.8696 | FG18: 18.730435 | FH18: Guadalupe, Canadá, Mexico, Estados Unidos, Japón. | FI18: san martin
A19: 20393972000 | B19: Asociación de Mujeres Emprendedoras Flor de Boqueron | C19: CACAO | D19: CACAO | E19: Ucayali | F19: 250303 | G19: Ucayali | H19: Padre Abad | I19: Curimana | M19: 1 | R19: PAC | S19: 2021 | T19: 1 | U19: SI | V19: SI | W19: 0 | X19: 0 | Y19: 0 | Z19: 0 | AA19: 0 | AB19: 0 | AC19: 0 | AD19: 1 | AE19: 19 | AF19: 20 | AG19: 0 | AH19: 0 | AI19: 0 | AJ19: 0 | AK19: 0 | AL19: 0 | AM19: 0 | AN19: 0 | AO19: 0 | AP19: 0 | AQ19: 0 | AR19: 0 | AS19: 20 | AT19: 0 | AU19: 0 | AV19: 21 | AW19: 0 | AX19: 0 | AY19: 0 | AZ19: 0 | BA19: 0 | BB19: 0 | BC19: 0 | BD19: 0 | BE19: 0 | BF19: 0 | BG19: 0 | BH19: 0 | BI19: 0 | BJ19: 0 | BK19: 0 | BL19: 0 | BM19: 0 | BN19: 0 | BO19: 0 | BP19: 0 | BQ19: 823 | BR19: 0 | BS19: 823 | BT19: 823 | BU19: 823 | BV19: 0 | BW19: 0 | BX19: 0 | BY19: -823 | BZ19: -823 | CA19: 0 | CB19: 0 | CC19: 0 | CD19: 0 | CE19: 0 | CF19: 0 | CG19: 0 | CH19: 0 | CI19: 0 | CJ19: 0 | CK19: 823 | CL19: 0 | CM19: 0 | CN19: 0 | CO19: 0 | CP19: 0 | CQ19: 0 | CR19: 0 | CS19: 0 | CT19: 0 | CU19: 0 | CV19: 0 | CW19: 0 | CX19: 0 | CY19: 0 | CZ19: 0 | DA19: 0 | DB19: 0 | DC19: 0 | DD19: 0 | DE19: 0 | DF19: 0 | DG19: 0 | DH19: 0 | DI19: 0 | DJ19: ASOCIACIÓN DE MUJERES EMPRENDEDORAS FLOR DE BOQUERON | DK19: 01 Asociación | FI19: pacMAYOR
A20: 20143224857 | B20: Cooperativa Agraria Amaybamba Pistipata | C20: TE | D20: TE | E20: Cusco | F20: 80903 | G20: Cusco | H20: La Convencion | I20: Huayopata | M20: 1 | N20: 1 | O20: 1 | P20: 1 | Q20: 1 | R20: PAC | S20: 2021-2022-2023-2024 - 2025 | T20: 5 | U20: SI | V20: SI | W20: 0 | X20: 0 | Y20: 0 | Z20: 0 | AA20: 0 | AB20: 0 | AC20: 0 | AD20: 17 | AE20: 7 | AF20: 24 | AG20: 17 | AH20: 7 | AI20: 24 | AJ20: 17 | AK20: 7 | AL20: 24 | AM20: 21 | AN20: 10 | AO20: 31 | AP20: 22 | AQ20: 9 | AR20: 31 | AS20: 31 | AT20: 0 | AU20: 0 | AV20: 23 | AW20: 4 | AX20: 33 | AY20: 6 | AZ20: 38 | BA20: 5 | BB20: 34 | BC20: 7 | BD20: 25 | BE20: 5 | BF20: 0 | BG20: 0 | BH20: 0 | BI20: 0 | BJ20: 0 | BK20: 0 | BL20: 0 | BM20: 0 | BN20: 0 | BO20: 0 | BP20: 0 | BQ20: 11267.5 | BR20: 0 | BS20: 11267.5 | BT20: 11267.5 | BU20: 11267.5 | BV20: 75014 | BW20: 0 | BX20: 75014 | BY20: 63746.5 | BZ20: 63746.5 | CA20: 110208 | CB20: 0 | CC20: 110208 | CD20: 35194 | CE20: 35194 | CF20: 45825.402 | CG20: 0 | CH20: 45825.402 | CI20: -64382.598 | CJ20: -64382.598 | CK20: 409343.9 | CL20: 167029 | CM20: 0 | CN20: 167029 | CO20: 121203.6 | CP20: 121203.6 | CQ20: 65795.5 | CR20: 0 | CS20: 0 | CT20: 44412.5 | CU20: 0 | CV20: 0 | CW20: 110208 | CX20: 0 | CY20: 0 | CZ20: 45825.402 | DA20: 0 | DB20: 0 | DC20: 45825.402 | DD20: 29041.5 | DE20: 0 | DF20: 137987.5 | DG20: 0 | DH20: 0 | DI20: 167029 | DJ20: COOPERATIVA AGRARIA AMAYBAMBA PISTIPATA | DK20: 02 Cooperativa | FI20: pacMAYOR
A21: 20612331821 | B21: Asociación de Mujeres las 0s de Luya | C21: CAFÉ | D21: CAFE VERDE | E21: Amazonas | F21: 10514 | G21: Amazonas | H21: Luya | I21: Pisuquia | Q21: 1 | R21: PAC | S21: 2025 | T21: 1 | U21: SI | V21: SI | W21: 0 | X21: 0 | Y21: 0 | Z21: 0 | AA21: 0 | AB21: 0 | AC21: 0 | AD21: 0 | AE21: 0 | AF21: 0 | AG21: 0 | AH21: 0 | AI21: 0 | AJ21: 0 | AK21: 0 | AL21: 0 | AM21: 0 | AN21: 0 | AO21: 0 | AP21: 0 | AQ21: 174 | AR21: 174 | AS21: 174 | BD21: 21 | BE21: 6 | CK21: 1032801.8 | CL21: 0 | CM21: 1032801.8 | CN21: 1032801.8 | CO21: 1032801.8 | CP21: 1032801.8 | DD21: 0 | DE21: 0 | DF21: 1032801.8 | DG21: 0 | DH21: 0 | DI21: 1032801.8 | DJ21: ASOCIACIÓN DE MUJERES LAS 0S DE LUYA | DK21: 01 Asociación | FI21: pacMAYOR
A22: 20572111131 | B22: Asociacion de Mujeres Organizadas Choco Warmis | C22: CACAO | D22: CACAO | E22: San Martin | F22: 220301 | G22: San Martin | H22: El Dorado | I22: San Jose de Sisa | M22: 1 | R22: PAC | S22: 2021 | T22: 1 | U22: SI | V22: SI | W22: 0 | X22: 0 | Y22: 0 | Z22: 0 | AA22: 0 | AB22: 0 | AC22: 0 | AD22: 0 | AE22: 20 | AF22: 20 | AG22: 0 | AH22: 0 | AI22: 0 | AJ22: 0 | AK22: 0 | AL22: 0 | AM22: 0 | AN22: 0 | AO22: 0 | AP22: 0 | AQ22: 0 | AR22: 0 | AS22: 20 | AT22: 0 | AU22: 0 | AV22: 27 | AW22: 9 | AX22: 0 | AY22: 0 | AZ22: 0 | BA22: 0 | BB22: 0 | BC22: 0 | BD22: 0 | BE22: 0 | BF22: 0 | BG22: 0 | BH22: 0 | BI22: 0 | BJ22: 0 | BK22: 0 | BL22: 0 | BM22: 0 | BN22: 0 | BO22: 0 | BP22: 0 | BQ22: 0 | BR22: 0 | BS22: 0 | BT22: 0 | BU22: 0 | BV22: 0 | BW22: 0 | BX22: 0 | BY22: 0 | BZ22: 0 | CA22: 0 | CB22: 0 | CC22: 0 | CD22: 0 | CE22: 0 | CF22: 0 | CG22: 0 | CH22: 0 | CI22: 0 | CJ22: 0 | CK22: 0 | CL22: 0 | CM22: 0 | CN22: 0 | CO22: 0 | CP22: 0 | CQ22: 0 | CR22: 0 | CS22: 0 | CT22: 0 | CU22: 0 | CV22: 0 | CW22: 0 | CX22: 0 | CY22: 0 | CZ22: 0 | DA22: 0 | DB22: 0 | DC22: 0 | DD22: 0 | DE22: 0 | DF22: 0 | DG22: 0 | DH22: 0 | DI22: 0 | DJ22: ASOCIACION DE MUJERES ORGANIZADAS CHOCO WARMIS | DK22: 01 Asociación | FI22: pacMAYOR
A23: 20568609833 | B23: Asociación de Mujeres Productoras Artesanas Cacao Jentari - Amproa Cacao Jentari | C23: CACAO | D23: CACAO | E23: Junin | F23: 120607 | G23: Junin | H23: Satipo | I23: Rio Negro | J23: 1 | R23: PAC | S23: 2018 | T23: 1 | U23: NO | V23: NO | W23: 14 | X23: 0 | Y23: 0 | Z23: 0 | AA23: 0 | AB23: 0 | AC23: 0 | AD23: 0 | AE23: 0 | AF23: 0 | AG23: 0 | AH23: 0 | AI23: 0 | AJ23: 0 | AK23: 0 | AL23: 0 | AM23: 0 | AN23: 0 | AO23: 0 | AP23: 0 | AQ23: 0 | AR23: 0 | AS23: 14 | AT23: 0 | AU23: 0 | AV23: 0 | AW23: 0 | AX23: 0 | AY23: 0 | AZ23: 0 | BA23: 0 | BB23: 0 | BC23: 0 | BD23: 0 | BE23: 0 | BF23: 0 | BG23: 0 | BH23: 0 | BI23: 0 | BJ23: 0 | BK23: 0 | BL23: 0 | BM23: 0 | BN23: 0 | BO23: 0 | BP23: 0 | BQ23: 0 | BR23: 0 | BS23: 0 | BT23: 0 | BU23: 0 | BV23: 0 | BW23: 0 | BX23: 0 | BY23: 0 | BZ23: 0 | CA23: 0 | CB23: 0 | CC23: 0 | CD23: 0 | CE23: 0 | CF23: 0 | CG23: 0 | CH23: 0 | CI23: 0 | CJ23: 0 | CK23: 0 | CL23: 0 | CM23: 0 | CN23: 0 | CO23: 0 | CP23: 0 | CQ23: 0 | CR23: 0 | CS23: 0 | CT23: 0 | CU23: 0 | CV23: 0 | CW23: 0 | CX23: 0 | CY23: 0 | CZ23: 0 | DA23: 0 | DB23: 0 | DC23: 0 | DD23: 0 | DE23: 0 | DF23: 0 | DG23: 0 | DH23: 0 | DI23: 0 | DJ23: ASOCIACIÓN DE MUJERES PRODUCTORAS ARTESANAS CACAO JENTARI - AMPROA CACAO JENTARI | DK23: 01 Asociación | FI23: pacMAYOR
A24: 20147443120 | B24: Cooperativa Agraria Cafetalera Tirijuay Pavayoc LTDA 013-B-Vii | C24: CAFÉ | E24: Cusco | F24: 80905 | G24: Cusco | H24: La Convención | I24: Ocobamba | DJ24: COOPERATIVA AGRARIA CAFETALERA TIRIJUAY PAVAYOC LTDA 013-B-VII | DK24: 02 Cooperativa | DM24: 20 | DN24: Cusco | DO24: La Convencion | DP24: Ocobamba | DQ24: SUSPENSION TEMPORAL / NO HABIDO Deberá declarar el nuevo domicilio fiscal o confirmar el señalado en el RUC. Para ello, deberá acercarse a los Centros de Servicios al Contribuyente con los documentos que sustenten el nuevo domicilio. | DR24: 27668 | DS24: 2025 | DT24: Ejecucion | DU24: La Cooperativa agraria cafetalera Tirijuay Pavayoc es una organización sólida y debidamente formalizada que inició sus actividades económicas el 01/10/1975, se ha consolidado como un referente en la producción y comercialización de café de calidad de la region Cusco. | DV24: En el marco de las estrategias de apoyo al productor, AGROMERCADO se encuentra ejecutando un Plan de Articulación Comercial en beneficio de esta cooperativa. Esta intervención se realiza en estricto cumplimiento de lo priorizado en el Anexo 5A | DW24: Cooperativa Agraria Cafetalera Tirijuay Pavayoc Ltda 13-B-VII | DX24: 44 | DY24: 30 | DZ24: 150 | EA24: 20TM | EB24: Mayo - Agosto | EC24: Junio - Noviembre | ED24: 1400 - 2100 m s. n. m. | EE24: Catimor 70%, Caturra 10%, Bourbon 5%, Otros 15% | EF24: Certificacion Organica, vigencia hasta 14/08/2026 | EG24: Vigencia organica hasta 26/03/2027 | EI24: Grado 1: 65 %, Grado 2: 60% | EK24: Centro Poblado de Versalles Distrito de Ocobamba, La Convencion | EL24: cactirijuaypavayoc@gmail.com | EM24: 974776817 | EP24: Carlos Velasquez Champi | EQ24: 974776817 | ER24: cactirijuaypavayoc@gmail.com | ES24: Carlos Velasquez Champi | ET24: 974776817 | EU24: cactirijuaypavayoc@gmail.com | EV24: no cuenta con registro | FB24: SU COMPRADOR PRINCIPAL ES COCLA | FC24: NO | FI24: san martin
A25: 20539280644 | B25: Asociación de Pequeños Agricultores para la Producción Ecológica San Mateo de Penachi | C25: CAFÉ | D25: CAFÉ | E25: Lambayeque | F25: 140310 | G25: Lambayeque | H25: Lambayeque | I25: Salas | K25: 1 | L25: 1 | M25: 1 | O25: 1 | R25: PAC | S25: 2019-2020-2021-2023 | T25: 4 | U25: SI | V25: SI | W25: 0 | X25: 103 | Y25: 92 | Z25: 195 | AA25: 89 | AB25: 91 | AC25: 180 | AD25: 82 | AE25: 81 | AF25: 163 | AG25: 0 | AH25: 0 | AI25: 0 | AJ25: 8 | AK25: 12 | AL25: 20 | AM25: 0 | AN25: 0 | AO25: 0 | AP25: 0 | AQ25: 0 | AR25: 0 | AS25: 20 | AT25: 0 | AU25: 1 | AV25: 62 | AW25: 26 | AX25: 0 | AY25: 0 | AZ25: 32 | BA25: 16 | BB25: 0 | BC25: 0 | BD25: 0 | BE25: 0 | BF25: 0 | BG25: 0 | BH25: 0 | BI25: 0 | BJ25: 0 | BK25: 0 | BL25: 399924.47 | BM25: 0 | BN25: 399924.47 | BO25: 399924.47 | BP25: 399924.47 | BQ25: 597668.98 | BR25: 0 | BS25: 597668.98 | BT25: 197744.51 | BU25: 197744.51 | BV25: 0 | BW25: 0 | BX25: 0 | BY25: -597668.98 | BZ25: -597668.98 | CA25: 526288.09 | CB25: 0 | CC25: 526288.09 | CD25: 526288.09 | CE25: 526288.09 | CF25: 0 | CG25: 0 | CH25: 0 | CI25: -526288.09 | CJ25: -526288.09 | CK25: 1523881.5 | CL25: 0 | CM25: 0 | CN25: 0 | CO25: 0 | CP25: 0 | CQ25: 0 | CR25: 0 | CS25: 0 | CT25: 4034.81 | CU25: 0 | CV25: 522253.47 | CW25: 526288.28 | CX25: 0 | CY25: 0 | CZ25: 0 | DA25: 0 | DB25: 0 | DC25: 0 | DD25: 0 | DE25: 0 | DF25: 0 | DG25: 0 | DH25: 0 | DI25: 0 | DJ25: ASOCIACION DE PEQUEÑOS AGRICULTORES PARA LA PRODUCCION ECOLOGICA SAN MATEO DE PENACHI | DK25: 01 Asociación | FI25: pacMAYOR
A26: 20568560133 | B26: Asociacion de Pequeños Productores Agroecologicos Laguna Raya (Appalar) | C26: CACAO | D26: CACAO | E26: Pasco | F26: 190304 | G26: Pasco | H26: Oxapampa | I26: Palcazu | K26: 1 | L26: 1 | O26: 1 | P26: 1 | R26: PAC | S26: 2019-2020-2023-2024 | T26: 4 | U26: SI | V26: SI | W26: 0 | X26: 24 | Y26: 16 | Z26: 40 | AA26: 24 | AB26: 16 | AC26: 40 | AD26: 0 | AE26: 0 | AF26: 0 | AG26: 0 | AH26: 0 | AI26: 0 | AJ26: 30 | AK26: 10 | AL26: 40 | AM26: 30 | AN26: 10 | AO26: 40 | AP26: 0 | AQ26: 0 | AR26: 0 | AS26: 40 | AT26: 0 | AU26: 0 | AV26: 0 | AW26: 0 | AX26: 0 | AY26: 0 | AZ26: 27 | BA26: 3 | BB26: 28 | BC26: 1 | BD26: 0 | BE26: 0 | BF26: 0 | BG26: 0 | BH26: 0 | BI26: 0 | BJ26: 0 | BK26: 0 | BL26: 0 | BM26: 0 | BN26: 0 | BO26: 0 | BP26: 0 | BQ26: 0 | BR26: 0 | BS26: 0 | BT26: 0 | BU26: 0 | BV26: 0 | BW26: 0 | BX26: 0 | BY26: 0 | BZ26: 0 | CA26: 21799.2 | CB26: 0 | CC26: 21799.2 | CD26: 21799.2 | CE26: 21799.2 | CF26: 0 | CG26: 0 | CH26: 0 | CI26: -21799.2 | CJ26: -21799.2 | CK26: 21799.2 | CL26: 0 | CM26: 0 | CN26: 0 | CO26: 0 | CP26: 0 | CQ26: 5808 | CR26: 10899.6 | CS26: 0 | CT26: 0 | CU26: 5091.6 | CV26: 0 | CW26: 21799.2 | CX26: 0 | CY26: 0 | CZ26: 0 | DA26: 0 | DB26: 0 | DC26: 0 | DD26: 0 | DE26: 0 | DF26: 0 | DG26: 0 | DH26: 0 | DI26: 0 | DJ26: ASOCIACION DE PEQUEÑOS PRODUCTORES AGROECOLOGICOS LAGUNA RAYA | DK26: 01 Asociación | FI26: pacMAYOR
A27: 20175089111 | B27: COOP. Ag. Sociedad Agricola de Interes Social Jose Carlos Mariategui Ltda.n°16 Sunchubamba y Anexos | C27: DERIVADOS LACTEOS | D27: DERIVADOS LACTEOS | E27: Cajamarca | F27: 60104 | G27: Cajamarca | H27: Cajamarca | I27: Cospan | O27: 1 | P27: 1 | Q27: 1 | R27: PAC | S27: 2023-2024 - 2025 | T27: 3 | U27: SI | V27: SI | W27: 0 | X27: 0 | Y27: 0 | Z27: 0 | AA27: 0 | AB27: 0 | AC27: 0 | AD27: 0 | AE27: 0 | AF27: 0 | AG27: 0 | AH27: 0 | AI27: 0 | AJ27: 250 | AK27: 42 | AL27: 292 | AM27: 199 | AN27: 93 | AO27: 292 | AP27: 24 | AQ27: 5 | AR27: 29 | AS27: 29 | AT27: 0 | AU27: 0 | AV27: 0 | AW27: 0 | AX27: 0 | AY27: 0 | AZ27: 47 | BA27: 5 | BB27: 30 | BC27: 5 | BD27: 30 | BE27: 4 | BF27: 0 | BG27: 0 | BH27: 0 | BI27: 0 | BJ27: 0 | BK27: 0 | BL27: 0 | BM27: 0 | BN27: 0 | BO27: 0 | BP27: 0 | BQ27: 0 | BR27: 0 | BS27: 0 | BT27: 0 | BU27: 0 | BV27: 0 | BW27: 0 | BX27: 0 | BY27: 0 | BZ27: 0 | CA27: 15015.6 | CB27: 0 | CC27: 15015.6 | CD27: 15015.6 | CE27: 15015.6 | CF27: 17323 | CG27: 0 | CH27: 17323 | CI27: 2307.4 | CJ27: 2307.4 | CK27: 48138.6 | CL27: 15800 | CM27: 0 | CN27: 15800 | CO27: -1523 | CP27: -1523 | CQ27: 0 | CR27: 15015.6 | CS27: 0 | CT27: 0 | CU27: 0 | CV27: 0 | CW27: 15015.6 | CX27: 0 | CY27: 17323 | CZ27: 0 | DA27: 0 | DB27: 0 | DC27: 17323 | DD27: 0 | DE27: 15800 | DF27: 0 | DG27: 0 | DH27: 0 | DI27: 15800 | DJ27: COOP. AG. SOCIEDAD AGRICOLA DE INTERES SOCIAL JOSE CARLOS MARIATEGUI LTDA.N°16 SUNCHUBAMBA Y ANEXOS | DK27: 02 Cooperativa | FI27: pacMAYOR
A28: 20183732031 | B28: Asociación de Productores de Rocoto y Productos Agricolas de Oxapampa "aprpao" | C28: CAPSICUMS | D28: CAPSICUMS | E28: Pasco | F28: 190301 | G28: Pasco | H28: Oxapampa | I28: Oxapampa | K28: 1 | R28: PAC | S28: 2019 | T28: 1 | U28: SI | V28: NO | W28: 0 | X28: 26 | Y28: 0 | Z28: 26 | AA28: 0 | AB28: 0 | AC28: 0 | AD28: 0 | AE28: 0 | AF28: 0 | AG28: 0 | AH28: 0 | AI28: 0 | AJ28: 0 | AK28: 0 | AL28: 0 | AM28: 0 | AN28: 0 | AO28: 0 | AP28: 0 | AQ28: 0 | AR28: 0 | AS28: 26 | AT28: 0 | AU28: 0 | AV28: 0 | AW28: 0 | AX28: 0 | AY28: 0 | AZ28: 0 | BA28: 0 | BB28: 0 | BC28: 0 | BD28: 0 | BE28: 0 | BF28: 0 | BG28: 0 | BH28: 0 | BI28: 0 | BJ28: 0 | BK28: 0 | BL28: 0 | BM28: 0 | BN28: 0 | BO28: 0 | BP28: 0 | BQ28: 0 | BR28: 0 | BS28: 0 | BT28: 0 | BU28: 0 | BV28: 0 | BW28: 0 | BX28: 0 | BY28: 0 | BZ28: 0 | CA28: 0 | CB28: 0 | CC28: 0 | CD28: 0 | CE28: 0 | CF28: 0 | CG28: 0 | CH28: 0 | CI28: 0 | CJ28: 0 | CK28: 0 | CL28: 0 | CM28: 0 | CN28: 0 | CO28: 0 | CP28: 0 | CQ28: 0 | CR28: 0 | CS28: 0 | CT28: 0 | CU28: 0 | CV28: 0 | CW28: 0 | CX28: 0 | CY28: 0 | CZ28: 0 | DA28: 0 | DB28: 0 | DC28: 0 | DD28: 0 | DE28: 0 | DF28: 0 | DG28: 0 | DH28: 0 | DI28: 0 | DJ28: ASOCIACION DE PRODUCTORES DE ROCOTO Y PRODUCTOS AGRICOLAS DE OXAPAMPA | DK28: 01 Asociación | FI28: pacMAYOR
A29: 20200880448 | B29: Cooperativa Agraria Cafetalera Jorge Chavez LTDA | C29: CAFÉ | D29: CAFÉ | E29: Cusco | F29: 80408 | G29: Cusco | H29: Calca | I29: Yanatile | DJ29: COOPERATIVA AGRARIA CAFETALERA JORGE CHAVEZ LTDA | DK29: 02 Cooperativa | DM29: 21 | DN29: Cusco | DO29: Calca | DP29: Yanatile | DQ29: SI | DR29: 30231 | DS29: 2025 | DT29: Ejecucion | DU29: La Cooperativa agraria cafetalera Aguilayoc es una organización sólida y debidamente formalizada que inició sus actividades económicas el 07/10/1982, se ha consolidado como un referente en la producción y comercialización de café de calidad de la region Cusco. | DV29: En el marco de las estrategias de apoyo al productor, AGROMERCADO se encuentra ejecutando un Plan de Articulación Comercial en beneficio de esta cooperativa. Esta intervención se realiza en estricto cumplimiento de lo priorizado en el Anexo 5A | DW29: Cooperativa Agraria Cafetalera Jorge Chavez Ltda | DX29: 29 | DY29: 7 | DZ29: 38 | EA29: 20TM | EB29: Mayo - Agosto | EC29: Junio - Noviembre | ED29: 1600 - 2200 m s. n. m. | EE29: Catimor 70%, Caturra 10%, Bourbon 5%, Otros 15% | EF29: Certificacion Organica, vigencia hasta 14/08/2026 | EG29: Vigencia organica hasta 26/03/2027 | EI29: Grado 1: 65 %, Grado 2: 60% | EK29: NRO. S/N INT. S/N C.C.CUQUIPATA (CARRETERA KM.117) CUSCO - CALCA - YANATILE | EL29: josecarloshanccotorres144@gmail.com | EM29: 954004223 | ES29: Raul Castro Farfan | ET29: 954004223 | EU29: josecarloshanccotorres144@gmail.com | EV29: no cuenta con registro | FB29: SU COMPRADOR PRINCIPAL ES COCLA | FC29: NO | FI29: san martin
A30: 20204028061 | B30: Cooperativa Comunal San Pedro de Cajas | C30: FIBRA DE ALPACA | D30: FIBRA DE ALPACA | E30: Junin | F30: 120708 | G30: Junin | H30: Tarma | I30: San Pedro de Cajas | K30: 1 | L30: 1 | R30: PAC | S30: 2019-2020 | T30: 2 | U30: SI | V30: SI | W30: 0 | X30: 54 | Y30: 26 | Z30: 80 | AA30: 54 | AB30: 26 | AC30: 80 | AD30: 0 | AE30: 0 | AF30: 0 | AG30: 0 | AH30: 0 | AI30: 0 | AJ30: 0 | AK30: 0 | AL30: 0 | AM30: 0 | AN30: 0 | AO30: 0 | AP30: 0 | AQ30: 0 | AR30: 0 | AS30: 80 | AT30: 0 | AU30: 0 | AV30: 0 | AW30: 0 | AX30: 0 | AY30: 0 | AZ30: 0 | BA30: 0 | BB30: 0 | BC30: 0 | BD30: 0 | BE30: 0 | BF30: 0 | BG30: 0 | BH30: 0 | BI30: 0 | BJ30: 0 | BK30: 0 | BL30: 0 | BM30: 0 | BN30: 0 | BO30: 0 | BP30: 0 | BQ30: 0 | BR30: 0 | BS30: 0 | BT30: 0 | BU30: 0 | BV30: 0 | BW30: 0 | BX30: 0 | BY30: 0 | BZ30: 0 | CA30: 0 | CB30: 0 | CC30: 0 | CD30: 0 | CE30: 0 | CF30: 0 | CG30: 0 | CH30: 0 | CI30: 0 | CJ30: 0 | CK30: 0 | CL30: 0 | CM30: 0 | CN30: 0 | CO30: 0 | CP30: 0 | CQ30: 0 | CR30: 0 | CS30: 0 | CT30: 0 | CU30: 0 | CV30: 0 | CW30: 0 | CX30: 0 | CY30: 0 | CZ30: 0 | DA30: 0 | DB30: 0 | DC30: 0 | DD30: 0 | DE30: 0 | DF30: 0 | DG30: 0 | DH30: 0 | DI30: 0 | DJ30: COOPERATIVA COMUNAL SAN PEDRO DE CAJAS | DK30: 02 Cooperativa | FI30: pacMAYOR
A31: 20287980672 | B31: Comunidad Nativa Tres Islas | C31: AGUAJE | D31: AGUAJE | E31: Madre de Dios | F31: 170101 | G31: Madre de Dios | H31: Tambopata | I31: Tambopata | K31: 1 | M31: 1 | N31: 1 | O31: 1 | P31: 1 | Q31: 1 | R31: PAC | S31: 2019 | T31: 1 | U31: SI | V31: NO | W31: 0 | X31: 0 | Y31: 0 | Z31: 0 | AA31: 0 | AB31: 0 | AC31: 0 | AD31: 0 | AE31: 0 | AF31: 0 | AG31: 0 | AH31: 0 | AI31: 0 | AJ31: 0 | AK31: 0 | AL31: 0 | AM31: 0 | AN31: 0 | AO31: 0 | AP31: 0 | AQ31: 0 | AR31: 0 | AS31: --- | AT31: 0 | AU31: 0 | AV31: 0 | AW31: 0 | AX31: 0 | AY31: 0 | AZ31: 0 | BA31: 0 | BB31: 0 | BC31: 0 | BD31: 0 | BE31: 0 | BF31: 0 | BG31: 0 | BH31: 0 | BI31: 0 | BJ31: 0 | BK31: 0 | BL31: 0 | BM31: 0 | BN31: 0 | BO31: 0 | BP31: 0 | BQ31: 0 | BR31: 0 | BS31: 0 | BT31: 0 | BU31: 0 | BV31: 0 | BW31: 0 | BX31: 0 | BY31: 0 | BZ31: 0 | CA31: 0 | CB31: 0 | CC31: 0 | CD31: 0 | CE31: 0 | CF31: 0 | CG31: 0 | CH31: 0 | CI31: 0 | CJ31: 0 | CK31: 0 | CL31: 0 | CM31: 0 | CN31: 0 | CO31: 0 | CP31: 0 | CQ31: 0 | CR31: 0 | CS31: 0 | CT31: 0 | CU31: 0 | CV31: 0 | CW31: 0 | CX31: 0 | CY31: 0 | CZ31: 0 | DA31: 0 | DB31: 0 | DC31: 0 | DD31: 0 | DE31: 0 | DF31: 0 | DG31: 0 | DH31: 0 | DI31: 0 | DJ31: COMUNIDAD NATIVA TRES ISLAS | DK31: 05 Comunidades Campesinas | FI31: pacMAYOR
A32: 20323699365 | B32: Inversiones Perualp S.a | C32: DERIVADOS LACTEOS | D32: QUESOS MADURADOS | E32: Pasco | F32: 190301 | G32: Pasco | H32: Oxapampa | I32: Oxapampa | J32: 1 | R32: PAC | S32: 2018 | T32: 1 | U32: NO | V32: NO | W32: 48 | X32: 0 | Y32: 0 | Z32: 0 | AA32: 0 | AB32: 0 | AC32: 0 | AD32: 0 | AE32: 0 | AF32: 0 | AG32: 0 | AH32: 0 | AI32: 0 | AJ32: 0 | AK32: 0 | AL32: 0 | AM32: 0 | AN32: 0 | AO32: 0 | AP32: 0 | AQ32: 0 | AR32: 0 | AS32: 48 | AT32: 0 | AU32: 0 | AV32: 0 | AW32: 0 | AX32: 0 | AY32: 0 | AZ32: 0 | BA32: 0 | BB32: 0 | BC32: 0 | BD32: 0 | BE32: 0 | BF32: 0 | BG32: 0 | BH32: 0 | BI32: 0 | BJ32: 0 | BK32: 0 | BL32: 0 | BM32: 0 | BN32: 0 | BO32: 0 | BP32: 0 | BQ32: 0 | BR32: 0 | BS32: 0 | BT32: 0 | BU32: 0 | BV32: 0 | BW32: 0 | BX32: 0 | BY32: 0 | BZ32: 0 | CA32: 0 | CB32: 0 | CC32: 0 | CD32: 0 | CE32: 0 | CF32: 0 | CG32: 0 | CH32: 0 | CI32: 0 | CJ32: 0 | CK32: 0 | CL32: 0 | CM32: 0 | CN32: 0 | CO32: 0 | CP32: 0 | CQ32: 0 | CR32: 0 | CS32: 0 | CT32: 0 | CU32: 0 | CV32: 0 | CW32: 0 | CX32: 0 | CY32: 0 | CZ32: 0 | DA32: 0 | DB32: 0 | DC32: 0 | DD32: 0 | DE32: 0 | DF32: 0 | DG32: 0 | DH32: 0 | DI32: 0 | DJ32: INVERSIONES PERUALP S.A. | DK32: 07 Otros | FI32: pacMAYOR
A33: 20326767400 | B33: Asociacion Centro de Acopio de Leche Señor de los Milagros | C33: DERIVADOS LACTEOS | D33: DERIVADOS LACTEOS | E33: Arequipa | F33: 40520 | G33: Arequipa | H33: Caylloma | I33: Majes | N33: 1 | O33: 1 | P33: 1 | Q33: 1 | R33: PAC | S33: 2022-2023-2024 - 2025 | T33: 4 | U33: SI | V33: SI | W33: 0 | X33: 0 | Y33: 0 | Z33: 0 | AA33: 0 | AB33: 0 | AC33: 0 | AD33: 0 | AE33: 0 | AF33: 0 | AG33: 49 | AH33: 19 | AI33: 68 | AJ33: 49 | AK33: 19 | AL33: 68 | AM33: 48 | AN33: 21 | AO33: 69 | AP33: 48 | AQ33: 21 | AR33: 69 | AS33: 69 | AT33: 0 | AU33: 0 | AV33: 0 | AW33: 0 | AX33: 30 | AY33: 5 | AZ33: 49 | BA33: 4 | BB33: 51 | BC33: 3 | BD33: 42 | BE33: 2 | BF33: 0 | BG33: 0 | BH33: 0 | BI33: 0 | BJ33: 0 | BK33: 0 | BL33: 0 | BM33: 0 | BN33: 0 | BO33: 0 | BP33: 0 | BQ33: 0 | BR33: 0 | BS33: 0 | BT33: 0 | BU33: 0 | BV33: 58403.51 | BW33: 0 | BX33: 58403.51 | BY33: 58403.51 | BZ33: 58403.51 | CA33: 219073.56 | CB33: 0 | CC33: 219073.56 | CD33: 160670.05 | CE33: 160670.05 | CF33: 394769.86 | CG33: 0 | CH33: 394769.86 | CI33: 175696.3 | CJ33: 175696.3 | CK33: 1010372.1 | CL33: 338125.16 | CM33: 0 | CN33: 338125.16 | CO33: -56644.696 | CP33: -56644.696 | CQ33: 0 | CR33: 0 | CS33: 0 | CT33: 219073.55 | CU33: 0 | CV33: 0 | CW33: 219073.55 | CX33: 0 | CY33: 0 | CZ33: 394769.86 | DA33: 0 | DB33: 0 | DC33: 394769.86 | DD33: 0 | DE33: 0 | DF33: 338125.16 | DG33: 0 | DH33: 0 | DI33: 338125.16 | DJ33: ASOC.C.DE ACOPIO D.LECHE SR.D.L.MILAGROS | DK33: 01 Asociación | FI33: pacMAYOR
A34: 20327993705 | B34: Asociacion Centro de Acopio de Leche Luis Pasteur | C34: DERIVADOS LACTEOS | D34: YOGURT | E34: Arequipa | F34: 40520 | G34: Arequipa | H34: Caylloma | I34: Majes | Q34: 1 | R34: PAC | S34: 2025 | T34: 1 | U34: SI | V34: SI | W34: 0 | X34: 0 | Y34: 0 | Z34: 0 | AA34: 0 | AB34: 0 | AC34: 0 | AD34: 0 | AE34: 0 | AF34: 0 | AG34: 0 | AH34: 0 | AI34: 0 | AJ34: 0 | AK34: 0 | AL34: 0 | AM34: 0 | AN34: 0 | AO34: 0 | AP34: 20 | AQ34: 4 | AR34: 24 | AS34: 24 | BD34: 42 | BE34: 2 | CK34: 246100 | CL34: 246100 | CM34: 0 | CN34: 246100 | CO34: 246100 | CP34: 246100 | DD34: 0 | DE34: 246100 | DF34: 0 | DG34: 0 | DH34: 0 | DI34: 246100 | DJ34: CENTRO DE ACOPIO DE LECHE LUIS PASTEUR | DK34: 01 Asociación | FI34: pacMAYOR
A35: 20352266052 | B35: Asociacion de Productores de Palmito de Aguaytia | C35: PALMITO | D35: PALMITO | E35: Ucayali | F35: 250301 | G35: Ucayali | H35: Padre Abad | I35: Padre Abad | J35: 1 | K35: 1 | R35: PAC | S35: 2018-2019 | T35: 2 | U35: SI | V35: NO | W35: 27 | X35: 16 | Y35: 10 | Z35: 26 | AA35: 0 | AB35: 0 | AC35: 0 | AD35: 0 | AE35: 0 | AF35: 0 | AG35: 0 | AH35: 0 | AI35: 0 | AJ35: 0 | AK35: 0 | AL35: 0 | AM35: 0 | AN35: 0 | AO35: 0 | AP35: 0 | AQ35: 0 | AR35: 0 | AS35: 26 | AT35: 0 | AU35: 0 | AV35: 0 | AW35: 0 | AX35: 0 | AY35: 0 | AZ35: 0 | BA35: 0 | BB35: 0 | BC35: 0 | BD35: 0 | BE35: 0 | BF35: 0 | BG35: 0 | BH35: 0 | BI35: 0 | BJ35: 0 | BK35: 0 | BL35: 0 | BM35: 0 | BN35: 0 | BO35: 0 | BP35: 0 | BQ35: 0 | BR35: 0 | BS35: 0 | BT35: 0 | BU35: 0 | BV35: 0 | BW35: 0 | BX35: 0 | BY35: 0 | BZ35: 0 | CA35: 0 | CB35: 0 | CC35: 0 | CD35: 0 | CE35: 0 | CF35: 0 | CG35: 0 | CH35: 0 | CI35: 0 | CJ35: 0 | CK35: 0 | CL35: 0 | CM35: 0 | CN35: 0 | CO35: 0 | CP35: 0 | CQ35: 0 | CR35: 0 | CS35: 0 | CT35: 0 | CU35: 0 | CV35: 0 | CW35: 0 | CX35: 0 | CY35: 0 | CZ35: 0 | DA35: 0 | DB35: 0 | DC35: 0 | DD35: 0 | DE35: 0 | DF35: 0 | DG35: 0 | DH35: 0 | DI35: 0 | DJ35: ASOCIACION DE PRODUCTORES DE PALMITO DE AGUAYTIA | DK35: 01 Asociación | FI35: pacMAYOR
A36: 20607265624 | B36: Asociacion de Pequeños Productores Agropecuarios Penachi Kerguer | C36: CAFÉ | D36: CAFÉ | E36: Lambayeque | F36: 140310 | G36: Lambayeque | H36: Lambayeque | I36: Salas | P36: 1 | Q36: 1 | R36: PAC | S36: 2024 - 2025 | T36: 2 | U36: SI | V36: SI | W36: 0 | X36: 0 | Y36: 0 | Z36: 0 | AA36: 0 | AB36: 0 | AC36: 0 | AD36: 0 | AE36: 0 | AF36: 0 | AG36: 0 | AH36: 0 | AI36: 0 | AJ36: 0 | AK36: 0 | AL36: 0 | AM36: 32 | AN36: 18 | AO36: 50 | AP36: 33 | AQ36: 17 | AR36: 50 | AS36: 50 | AT36: 0 | AU36: 0 | AV36: 0 | AW36: 0 | AX36: 0 | AY36: 0 | AZ36: 0 | BA36: 0 | BB36: 49 | BC36: 4 | BD36: 43 | BE36: 4 | BF36: 0 | BG36: 0 | BH36: 0 | BI36: 0 | BJ36: 0 | BK36: 0 | BL36: 0 | BM36: 0 | BN36: 0 | BO36: 0 | BP36: 0 | BQ36: 0 | BR36: 0 | BS36: 0 | BT36: 0 | BU36: 0 | BV36: 0 | BW36: 0 | BX36: 0 | BY36: 0 | BZ36: 0 | CA36: 0 | CB36: 0 | CC36: 0 | CD36: 0 | CE36: 0 | CF36: 0 | CG36: 0 | CH36: 0 | CI36: 0 | CJ36: 0 | CK36: 258802.86 | CL36: 258802.86 | CM36: 0 | CN36: 258802.86 | CO36: 258802.86 | CP36: 258802.86 | CQ36: 0 | CR36: 0 | CS36: 0 | CT36: 0 | CU36: 0 | CV36: 0 | CW36: 0 | CX36: 0 | CY36: 0 | CZ36: 0 | DA36: 0 | DB36: 0 | DC36: 0 | DD36: 0 | DE36: 258802.86 | DF36: 0 | DG36: 0 | DH36: 0 | DI36: 258802.86 | DJ36: ASOCIACION DE PEQUEÑOS PRODUCTORES AGROPECUARIOS PENACHI-KERGUER | DK36: 01 Asociación | FI36: pacMAYOR
A37: 20607382604 | B37: Asociacion de Pequeños Productores Agropecuarios San Lorenzo de Lalaquiz | C37: CAFÉ | D37: CAFÉ | E37: Piura | F37: 200101 | G37: Piura | H37: Piura | I37: Piura | P37: 1 | Q37: 1 | R37: PAC | S37: 2024 - 2025 | T37: 2 | U37: SI | V37: SI | W37: 0 | X37: 0 | Y37: 0 | Z37: 0 | AA37: 0 | AB37: 0 | AC37: 0 | AD37: 0 | AE37: 0 | AF37: 0 | AG37: 0 | AH37: 0 | AI37: 0 | AJ37: 0 | AK37: 0 | AL37: 0 | AM37: 25 | AN37: 20 | AO37: 45 | AP37: 0 | AQ37: 0 | AR37: 0 | AS37: 45 | AT37: 0 | AU37: 0 | AV37: 0 | AW37: 0 | AX37: 0 | AY37: 0 | AZ37: 0 | BA37: 0 | BB37: 46 | BC37: 3 | BD37: 0 | BE37: 0 | BF37: 0 | BG37: 0 | BH37: 0 | BI37: 0 | BJ37: 0 | BK37: 0 | BL37: 0 | BM37: 0 | BN37: 0 | BO37: 0 | BP37: 0 | BQ37: 0 | BR37: 0 | BS37: 0 | BT37: 0 | BU37: 0 | BV37: 0 | BW37: 0 | BX37: 0 | BY37: 0 | BZ37: 0 | CA37: 0 | CB37: 0 | CC37: 0 | CD37: 0 | CE37: 0 | CF37: 0 | CG37: 0 | CH37: 0 | CI37: 0 | CJ37: 0 | CK37: 0 | CL37: 0 | CM37: 0 | CN37: 0 | CO37: 0 | CP37: 0 | CQ37: 0 | CR37: 0 | CS37: 0 | CT37: 0 | CU37: 0 | CV37: 0 | CW37: 0 | CX37: 0 | CY37: 0 | CZ37: 0 | DA37: 0 | DB37: 0 | DC37: 0 | DD37: 0 | DE37: 0 | DF37: 0 | DG37: 0 | DH37: 0 | DI37: 0 | DJ37: ASOCIACION DE PEQUEÑOS PRODUCTORES AGROPECUARIOS SAN LORENZO DE LALAQUIZ | DK37: 01 Asociación | FI37: pacMAYOR
A38: 20365575674 | B38: Comunidad Campesina San Antonio de Rancas | C38: DERIVADOS LACTEOS | D38: QUESOS | E38: Pasco | F38: 190109 | G38: Pasco | H38: Pasco | I38: Simon Bolivar | P38: 1 | Q38: 1 | R38: PAC | S38: 2024 - 2025 | T38: 2 | U38: SI | V38: SI | W38: 0 | X38: 0 | Y38: 0 | Z38: 0 | AA38: 0 | AB38: 0 | AC38: 0 | AD38: 0 | AE38: 0 | AF38: 0 | AG38: 0 | AH38: 0 | AI38: 0 | AJ38: 0 | AK38: 0 | AL38: 0 | AM38: 570 | AN38: 230 | AO38: 800 | AP38: 447 | AQ38: 246 | AR38: 693 | AS38: 693 | AT38: 0 | AU38: 0 | AV38: 0 | AW38: 0 | AX38: 0 | AY38: 0 | AZ38: 0 | BA38: 0 | BB38: 16 | BC38: 0 | BD38: 20 | BE38: 4 | BF38: 0 | BG38: 0 | BH38: 0 | BI38: 0 | BJ38: 0 | BK38: 0 | BL38: 0 | BM38: 0 | BN38: 0 | BO38: 0 | BP38: 0 | BQ38: 0 | BR38: 0 | BS38: 0 | BT38: 0 | BU38: 0 | BV38: 0 | BW38: 0 | BX38: 0 | BY38: 0 | BZ38: 0 | CA38: 0 | CB38: 0 | CC38: 0 | CD38: 0 | CE38: 0 | CF38: 156032 | CG38: 0 | CH38: 156032 | CI38: 156032 | CJ38: 156032 | CK38: 447151.08 | CL38: 291119.08 | CM38: 0 | CN38: 291119.08 | CO38: 135087.08 | CP38: 135087.08 | CQ38: 0 | CR38: 0 | CS38: 0 | CT38: 0 | CU38: 0 | CV38: 0 | CW38: 0 | CX38: 0 | CY38: 156032 | CZ38: 0 | DA38: 0 | DB38: 0 | DC38: 156032 | DD38: 2155 | DE38: 285505.5 | DF38: 3458.58 | DG38: 0 | DH38: 0 | DI38: 291119.08 | DJ38: COMUNIDAD CAMPESINA SAN ANTONIO DE RANCAS | DK38: 05 Comunidades Campesinas | FI38: pacMAYOR
A39: 20606717475 | B39: Asociacion de Pequeños Productores Agropecuarios Ullma | C39: CAFÉ | D39: CAFÉ | E39: Piura | F39: 200301 | G39: Piura | H39: Huancabamba | I39: Huancabamba | O39: 1 | P39: 1 | Q39: 1 | R39: PAC | S39: 2023-2024 - 2025 | T39: 3 | U39: SI | V39: SI | W39: 0 | X39: 0 | Y39: 0 | Z39: 0 | AA39: 0 | AB39: 0 | AC39: 0 | AD39: 0 | AE39: 0 | AF39: 0 | AG39: 0 | AH39: 0 | AI39: 0 | AJ39: 50 | AK39: 25 | AL39: 75 | AM39: 50 | AN39: 25 | AO39: 75 | AP39: 0 | AQ39: 0 | AR39: 0 | AS39: 75 | AT39: 0 | AU39: 0 | AV39: 0 | AW39: 0 | AX39: 0 | AY39: 0 | AZ39: 35 | BA39: 4 | BB39: 47 | BC39: 4 | BD39: 0 | BE39: 0 | BF39: 0 | BG39: 0 | BH39: 0 | BI39: 0 | BJ39: 0 | BK39: 0 | BL39: 0 | BM39: 0 | BN39: 0 | BO39: 0 | BP39: 0 | BQ39: 0 | BR39: 0 | BS39: 0 | BT39: 0 | BU39: 0 | BV39: 0 | BW39: 0 | BX39: 0 | BY39: 0 | BZ39: 0 | CA39: 0 | CB39: 0 | CC39: 0 | CD39: 0 | CE39: 0 | CF39: 0 | CG39: 0 | CH39: 0 | CI39: 0 | CJ39: 0 | CK39: 0 | CL39: 0 | CM39: 0 | CN39: 0 | CO39: 0 | CP39: 0 | CQ39: 0 | CR39: 0 | CS39: 0 | CT39: 0 | CU39: 0 | CV39: 0 | CW39: 0 | CX39: 0 | CY39: 0 | CZ39: 0 | DA39: 0 | DB39: 0 | DC39: 0 | DD39: 0 | DE39: 0 | DF39: 0 | DG39: 0 | DH39: 0 | DI39: 0 | DJ39: ASOCIACION DE PEQUEÑOS PRODUCTORES AGROPECUARIOS ULLMA | DK39: 01 Asociación | FI39: pacMAYOR
A40: 20393335620 | B40: Asociación de Productores Ecológicos del Caserío San Cristóbal de Agua Blanca (Apecab) | C40: PANELA | D40: PANELA | E40: Ucayali | F40: 250102 | G40: Ucayali | H40: Coronel Portillo | I40: Campoverde | J40: 1 | R40: PAC | S40: 2018 | T40: 1 | U40: NO | V40: NO | W40: 19 | X40: 0 | Y40: 0 | Z40: 0 | AA40: 0 | AB40: 0 | AC40: 0 | AD40: 0 | AE40: 0 | AF40: 0 | AG40: 0 | AH40: 0 | AI40: 0 | AJ40: 0 | AK40: 0 | AL40: 0 | AM40: 0 | AN40: 0 | AO40: 0 | AP40: 0 | AQ40: 0 | AR40: 0 | AS40: 19 | AT40: 0 | AU40: 0 | AV40: 0 | AW40: 0 | AX40: 0 | AY40: 0 | AZ40: 0 | BA40: 0 | BB40: 0 | BC40: 0 | BD40: 0 | BE40: 0 | BF40: 0 | BG40: 0 | BH40: 0 | BI40: 0 | BJ40: 0 | BK40: 0 | BL40: 0 | BM40: 0 | BN40: 0 | BO40: 0 | BP40: 0 | BQ40: 0 | BR40: 0 | BS40: 0 | BT40: 0 | BU40: 0 | BV40: 0 | BW40: 0 | BX40: 0 | BY40: 0 | BZ40: 0 | CA40: 0 | CB40: 0 | CC40: 0 | CD40: 0 | CE40: 0 | CF40: 0 | CG40: 0 | CH40: 0 | CI40: 0 | CJ40: 0 | CK40: 0 | CL40: 0 | CM40: 0 | CN40: 0 | CO40: 0 | CP40: 0 | CQ40: 0 | CR40: 0 | CS40: 0 | CT40: 0 | CU40: 0 | CV40: 0 | CW40: 0 | CX40: 0 | CY40: 0 | CZ40: 0 | DA40: 0 | DB40: 0 | DC40: 0 | DD40: 0 | DE40: 0 | DF40: 0 | DG40: 0 | DH40: 0 | DI40: 0 | DJ40: ASOCIACIÓN DE PRODUCTORES ECOLÓGICOS DEL CASERÍO SAN CRISTÓBAL DE AGUA BLANCA | DK40: 01 Asociación | FI40: pacMAYOR
