Workbook

Sheet INSTRUCCIONES
A1: PLANTILLA ÍNDICE PVE — PACTO VERDE EUROPEO
A2: Clasificación de preparación y vulnerabilidad de cooperativas café y cacao ante el EUDR / Pacto Verde Europeo
A4: PROPÓSITO
A7: CÓMO FUNCIONA
A10: FLUJO DE USO
A11: Paso 1 | B11: Revisar PONDERADORES — los pesos son editables en celdas amarillas
A12: Paso 2 | B12: Ir a MATRIZ_174 — verificar/actualizar FOB, país destino, certificaciones
A13: Paso 3 | B13: Para cada organización con FOB UE > 0, completar PREGUNTAS_PROXY usando llamada telefónica o visita de 30 min
A14: Paso 4 | B14: Revisar SCORECARDS — el semáforo se actualiza automáticamente
A15: Paso 5 | B15: Usar RADAR_BRECHAS para comparación por departamento
A17: SEMÁFORO
A18: 🔴 Crítico (0–33) | B18: La cooperativa no puede generar la declaración EUDR. Riesgo de rechazo en frontera UE desde dic 2026.
A19: 🟡 Vulnerable (34–66) | B19: Tiene infraestructura parcial pero incompleta. Necesita inversión en geolocalización y proceso.
A20: 🟢 Preparado (67–100) | B20: Cumple los requisitos mínimos. Requiere monitoreo de actualización.
A22: NOTAS IMPORTANTES

Sheet PONDERADORES
A1: BLOQUE DE SUPUESTOS — PONDERACIONES DEL ÍNDICE PVE
A2: LEYENDA DE COLORES
A3: 🔵 Azul | B3: Input hardcoded — valor primario, editable
A4: ⚫ Negro | B4: Fórmula calculada — no editar manualmente
A5: 🟡 Amarillo | B5: Input editable — cambiar ponderación aquí
A6: 🟢 Verde | B6: Resultado positivo (cumple)
A7: 🔴 Rojo | B7: Resultado negativo (no cumple)
A8: ⬜ Gris | B8: Dato pendiente de capturar
A10: PONDERACIONES — MODIFICAR SOLO LAS CELDAS AMARILLAS
A11: Componente | B11: Dimensión EUDR | C11: Variable | D11: Ponderación (%)
A12: EXP_UE | B12: D7 / Exposición UE | C12: % FOB exportado a UE sobre FOB total | D12: 25
A13: TRAZA | B13: D2 / Trazabilidad | C13: ¿Existe vínculo lote → parcela con coords? | D13: 20
A14: DILIG | B14: D5 / Debida diligencia | C14: ¿Existe proceso de evaluación de riesgo? | D14: 15
A15: CAPAC | B15: D6 / Capacidad digital | C15: ¿Tiene personal dedicado a datos? | D15: 10
A16: PRESION | B16: D7 / Presión comprador | C16: ¿Comprador UE exige EUDR? | D16: 15
A17: CERTIF | B17: D8 / Certificaciones | C17: Score de certificaciones vigentes (Org + Ftrade) | D17: 10
A18: PPWR | B18: D14 / Envases | C18: ¿Usa sacos reutilizables o certificados? | D18: 5
A19: TOTAL | D19: =SUM(D12:D18)
A21: ⚠ El TOTAL debe sumar 100. Si lo ajustas, el Índice PVE en SCORECARDS se recalcula automáticamente.

Sheet MATRIZ_174
A1: MATRIZ 174 — Datos existentes de organizaciones | W1: D12 | X1: D13 | Y1: D14 | Z1: D15 | AA1: P1 | AB1: P2 | AC1: P3 | AD1: P4 | AE1: P5 | AF1: P6 | AG1: P7 | AH1: P8 | AI1: P9 | AJ1: P10 | AK1: P11 | AL1: P12 | AM1: P13 | AN1: P14 | AO1: Bloque P Score (0-1) | AP1: ISA-PactoVerde (0-1)
A2: RUC | B2: Razón Social (SUNAT) | C2: Depto | D2: Producto | E2: FOB Total USD | F2: N° DUAs | G2: Exporta | H2: Cert. Orgánica | I2: Cert. Fairtrade | J2: Estado SUNAT | K2: Avance EUDR | L2: FOB UE USD | M2: % UE/FOB | N2: HS Code principal | O2: Score Cert (0-1) | P2: Tipo org. | Q2: N° aprox. socios | R2: Hectáreas aprox. | S2: PVE Score (0-100) | T2: Clasificación | U2: D3 Score (OSCE) | V2: D3 Observación | W2: D12 — Huella Carbono 0=Sin medición 1=En curso (ha conocidas) 2=Certificado ───────────────────── NOTA: Valor actual = proxy FAO/IPCC (ha × factor IPCC/FAO por cultivo). Reemplazar tras Instrumento 2 Q40-Q44. | X2: Reporte Sostenibilidad (D13) 0=No, 1=En curso, 2=Publicado | Y2: Economía Circular (D14) 0=No, 1=En transición, 2=Avanzado | Z2: Fitosanitario/LMR (D15) 0=No verificado, 1=En monitoreo, 2=Cumple UE | AA2: P1 — Productividad (USD/ha/año) | AB2: P2 — Ingreso neto (USD/ha) | AC2: P3 — % socios con acceso crédito | AD2: P4 — Gender score (% muj. en org.) | AE2: P5 — Formalización laboral (%) | AF2: P6 — Capacitación/año/persona | AG2: P7 — Tasa retención socios (%) | AH2: P8 — Diversificación ingresos (%) | AI2: P9 — Acceso mercados premium (%) | AJ2: P10 — Inversión EUDR (USD/año) | AK2: P11 — Score trazabilidad (%) | AL2: P12 — Quejas resueltas (%) | AM2: P13 — Energía renovable (%) | AN2: P14 — Residuos gestionados (%) | AO2: P_Global — Promedio P1:P14 (0=None, 1=满分) | AP2: ISA-PactoVerde = AVG(D12:D15)/2 0=Nada, 2=Certificado
A3: 20118578415 | B3: CENT.DE COOP.AGR. CAF.VALLES SANDIA LTDA | C3: PUNO | D3: CAFÉ | E3: 5107246.6 | F3: 38 | G3: SI | H3: nan | I3: nan | J3: ACTIVO | K3: nan | L3: 2553623.3 | M3: =IF(E3>0,ROUND(L3/E3*100,1),0) | N3: PENDIENTE | O3: =IF(H3="SI",1,0)*0.6+IF(I3="SI",1,0)*0.4 | P3: PENDIENTE | S3: =IFERROR(SCORECARDS!C1,"—") | T3: =IF(ISTEXT(S3),S3,IF(S3<34,"🔴 Crítico",IF(S3<67,"🟡 Vulnerable","🟢 Preparado"))) | U3: 1 | V3: Sin hallazgos OSCE / OEFA | W3: 1 | X3: 0 | Y3: 0 | Z3: 0 | AA3: 0 | AB3: 0 | AC3: 0 | AD3: 0 | AE3: 0 | AF3: 0 | AG3: 0 | AH3: 0 | AI3: 0 | AJ3: 0 | AK3: 0 | AL3: 0 | AM3: 0 | AN3: 0 | AO3: =IFERROR(AVERAGE(AA3,AB3,AC3,AD3,AE3,AF3,AG3,AH3,AI3,AJ3,AK3,AL3,AM3,AN3),"N/A") | AP3: =IFERROR(AVERAGE(W3,X3,Y3,Z3)/2,"N/A")
A4: 20129156083 | B4: COOP AGRARIA CAFET VALLE RIO APURIMAC | C4: AYACUCHO | D4: CACAO | E4: 0 | G4: NO | H4: nan | I4: nan | J4: ACTIVO | K4: nan | L4: 0 | M4: =IF(E4>0,ROUND(L4/E4*100,1),0) | N4: PENDIENTE | O4: =IF(H4="SI",1,0)*0.6+IF(I4="SI",1,0)*0.4 | P4: PENDIENTE | S4: =IFERROR(SCORECARDS!C2,"—") | T4: =IF(ISTEXT(S4),S4,IF(S4<34,"🔴 Crítico",IF(S4<67,"🟡 Vulnerable","🟢 Preparado"))) | W4: 0 | X4: 0 | Y4: 0 | Z4: 0 | AA4: 0 | AB4: 0 | AC4: 0 | AD4: 0 | AE4: 0 | AF4: 0 | AG4: 0 | AH4: 0 | AI4: 0 | AJ4: 0 | AK4: 0 | AL4: 0 | AM4: 0 | AN4: 0 | AO4: =IFERROR(AVERAGE(AA4,AB4,AC4,AD4,AE4,AF4,AG4,AH4,AI4,AJ4,AK4,AL4,AM4,AN4),"N/A") | AP4: =IFERROR(AVERAGE(W4,X4,Y4,Z4)/2,"N/A")
A5: 20129529530 | B5: COOP AGRARIA CAFETALERA SATIPO LTDA | C5: JUNIN | D5: nan | E5: 9603968.1 | F5: 41 | G5: SI | H5: nan | I5: nan | J5: ACTIVO | K5: nan | L5: 4801984.1 | M5: =IF(E5>0,ROUND(L5/E5*100,1),0) | N5: PENDIENTE | O5: =IF(H5="SI",1,0)*0.6+IF(I5="SI",1,0)*0.4 | P5: PENDIENTE | S5: =IFERROR(SCORECARDS!C3,"—") | T5: =IF(ISTEXT(S5),S5,IF(S5<34,"🔴 Crítico",IF(S5<67,"🟡 Vulnerable","🟢 Preparado"))) | U5: 1 | V5: Sin hallazgos OSCE / OEFA | W5: 1 | X5: 0 | Y5: 0 | Z5: 0 | AA5: 0 | AB5: 0 | AC5: 0 | AD5: 0 | AE5: 0 | AF5: 0 | AG5: 0 | AH5: 0 | AI5: 0 | AJ5: 0 | AK5: 0 | AL5: 0 | AM5: 0 | AN5: 0 | AO5: =IFERROR(AVERAGE(AA5,AB5,AC5,AD5,AE5,AF5,AG5,AH5,AI5,AJ5,AK5,AL5,AM5,AN5),"N/A") | AP5: =IFERROR(AVERAGE(W5,X5,Y5,Z5)/2,"N/A")
A6: 20132489824 | B6: COOPERATIVA AGRARIA CAFETALERA CHANCAMAYO LTDA. N° 008-B-VII | C6: CUSCO | D6: nan | G6: NO | H6: Cer | I6: Vig | J6: ACTIVO | K6: nan | L6: 0 | M6: =IF(E6>0,ROUND(L6/E6*100,1),0) | N6: PENDIENTE | O6: =IF(H6="SI",1,0)*0.6+IF(I6="SI",1,0)*0.4 | P6: PENDIENTE | Q6: 44 | R6: 44 | S6: =IFERROR(SCORECARDS!C4,"—") | T6: =IF(ISTEXT(S6),S6,IF(S6<34,"🔴 Crítico",IF(S6<67,"🟡 Vulnerable","🟢 Preparado"))) | W6: 1 | X6: 0 | Y6: 0 | Z6: 0 | AA6: 0 | AB6: 0 | AC6: 0 | AD6: 0 | AE6: 0 | AF6: 0 | AG6: 0 | AH6: 0 | AI6: 0 | AJ6: 0 | AK6: 0 | AL6: 0 | AM6: 0 | AN6: 0 | AO6: =IFERROR(AVERAGE(AA6,AB6,AC6,AD6,AE6,AF6,AG6,AH6,AI6,AJ6,AK6,AL6,AM6,AN6),"N/A") | AP6: =IFERROR(AVERAGE(W6,X6,Y6,Z6)/2,"N/A")
A7: 20132505455 | B7: COOPERATIVA AGRARIA CAFETALERA AGUILAYOC LTDA. 084 | C7: CUSCO | D7: CAFÉ | G7: NO | H7: Cer | I7: nan | J7: ACTIVO | K7: 0.75 | L7: 0 | M7: =IF(E7>0,ROUND(L7/E7*100,1),0) | N7: PENDIENTE | O7: =IF(H7="SI",1,0)*0.6+IF(I7="SI",1,0)*0.4 | P7: PENDIENTE | Q7: 100 | R7: 218 | S7: =IFERROR(SCORECARDS!C5,"—") | T7: =IF(ISTEXT(S7),S7,IF(S7<34,"🔴 Crítico",IF(S7<67,"🟡 Vulnerable","🟢 Preparado"))) | W7: 1 | X7: 0 | Y7: 0 | Z7: 0 | AA7: 0 | AB7: 0 | AC7: 0 | AD7: 0 | AE7: 0 | AF7: 0 | AG7: 0 | AH7: 0 | AI7: 0 | AJ7: 0 | AK7: 0 | AL7: 0 | AM7: 0 | AN7: 0 | AO7: =IFERROR(AVERAGE(AA7,AB7,AC7,AD7,AE7,AF7,AG7,AH7,AI7,AJ7,AK7,AL7,AM7,AN7),"N/A") | AP7: =IFERROR(AVERAGE(W7,X7,Y7,Z7)/2,"N/A")
A8: 20132509795 | B8: COOPERATIVA AGRARIA CAFETALERA JOSE OLAYA LTDA N° 252 | C8: CUSCO | D8: CAFÉ | E8: 2477083.5 | F8: 14 | G8: SI | H8: nan | I8: nan | J8: ACTIVO | K8: nan | L8: 1238541.8 | M8: =IF(E8>0,ROUND(L8/E8*100,1),0) | N8: PENDIENTE | O8: =IF(H8="SI",1,0)*0.6+IF(I8="SI",1,0)*0.4 | P8: PENDIENTE | S8: =IFERROR(SCORECARDS!C6,"—") | T8: =IF(ISTEXT(S8),S8,IF(S8<34,"🔴 Crítico",IF(S8<67,"🟡 Vulnerable","🟢 Preparado"))) | U8: 1 | V8: Sin hallazgos OSCE / OEFA | W8: 1 | X8: 0 | Y8: 0 | Z8: 0 | AA8: 0 | AB8: 0 | AC8: 0 | AD8: 0 | AE8: 0 | AF8: 0 | AG8: 0 | AH8: 0 | AI8: 0 | AJ8: 0 | AK8: 0 | AL8: 0 | AM8: 0 | AN8: 0 | AO8: =IFERROR(AVERAGE(AA8,AB8,AC8,AD8,AE8,AF8,AG8,AH8,AI8,AJ8,AK8,AL8,AM8,AN8),"N/A") | AP8: =IFERROR(AVERAGE(W8,X8,Y8,Z8)/2,"N/A")
A9: 20132509876 | B9: COOPERATIVA AGRARIA CAFETALERA MARANURA LTDA. 129 | C9: CUSCO | D9: CAFÉ | E9: 1689820.3 | F9: 5 | G9: SI | H9: nan | I9: nan | J9: ACTIVO | K9: nan | L9: 0 | M9: =IF(E9>0,ROUND(L9/E9*100,1),0) | N9: PENDIENTE | O9: =IF(H9="SI",1,0)*0.6+IF(I9="SI",1,0)*0.4 | P9: PENDIENTE | S9: =IFERROR(SCORECARDS!C7,"—") | T9: =IF(ISTEXT(S9),S9,IF(S9<34,"🔴 Crítico",IF(S9<67,"🟡 Vulnerable","🟢 Preparado"))) | W9: 0 | X9: 0 | Y9: 0 | Z9: 0 | AA9: 0 | AB9: 0 | AC9: 0 | AD9: 0 | AE9: 0 | AF9: 0 | AG9: 0 | AH9: 0 | AI9: 0 | AJ9: 0 | AK9: 0 | AL9: 0 | AM9: 0 | AN9: 0 | AO9: =IFERROR(AVERAGE(AA9,AB9,AC9,AD9,AE9,AF9,AG9,AH9,AI9,AJ9,AK9,AL9,AM9,AN9),"N/A") | AP9: =IFERROR(AVERAGE(W9,X9,Y9,Z9)/2,"N/A")
A10: 20132517119 | B10: COOPERATIVA AGRARIA CAFETALERA MATEO PUMACAHUA LTDA N° 185 | C10: CUSCO | D10: CAFÉ | E10: 0 | G10: NO | H10: Cer | I10: Fai | J10: ACTIVO | K10: 0.75 | L10: 0 | M10: =IF(E10>0,ROUND(L10/E10*100,1),0) | N10: PENDIENTE | O10: =IF(H10="SI",1,0)*0.6+IF(I10="SI",1,0)*0.4 | P10: PENDIENTE | Q10: 177 | R10: 469 | S10: =IFERROR(SCORECARDS!C8,"—") | T10: =IF(ISTEXT(S10),S10,IF(S10<34,"🔴 Crítico",IF(S10<67,"🟡 Vulnerable","🟢 Preparado"))) | W10: 1 | X10: 0 | Y10: 0 | Z10: 0 | AA10: 0 | AB10: 0 | AC10: 0 | AD10: 0 | AE10: 0 | AF10: 0 | AG10: 0 | AH10: 0 | AI10: 0 | AJ10: 0 | AK10: 0 | AL10: 0 | AM10: 0 | AN10: 0 | AO10: =IFERROR(AVERAGE(AA10,AB10,AC10,AD10,AE10,AF10,AG10,AH10,AI10,AJ10,AK10,AL10,AM10,AN10),"N/A") | AP10: =IFERROR(AVERAGE(W10,X10,Y10,Z10)/2,"N/A")
A11: 20136201132 | B11: COOPERATIVA AGRARIA CAFETALERA ALTO URUBAMBA LTDA N° 239 | C11: CUSCO | D11: CAFÉ | E11: 681394.36 | F11: 6 | G11: SI | H11: nan | I11: nan | J11: ACTIVO | K11: nan | L11: 0 | M11: =IF(E11>0,ROUND(L11/E11*100,1),0) | N11: PENDIENTE | O11: =IF(H11="SI",1,0)*0.6+IF(I11="SI",1,0)*0.4 | P11: PENDIENTE | S11: =IFERROR(SCORECARDS!C9,"—") | T11: =IF(ISTEXT(S11),S11,IF(S11<34,"🔴 Crítico",IF(S11<67,"🟡 Vulnerable","🟢 Preparado"))) | W11: 0 | X11: 0 | Y11: 0 | Z11: 0 | AA11: 0 | AB11: 0 | AC11: 0 | AD11: 0 | AE11: 0 | AF11: 0 | AG11: 0 | AH11: 0 | AI11: 0 | AJ11: 0 | AK11: 0 | AL11: 0 | AM11: 0 | AN11: 0 | AO11: =IFERROR(AVERAGE(AA11,AB11,AC11,AD11,AE11,AF11,AG11,AH11,AI11,AJ11,AK11,AL11,AM11,AN11),"N/A") | AP11: =IFERROR(AVERAGE(W11,X11,Y11,Z11)/2,"N/A")
A12: 20136201213 | B12: CENTRAL DE COOPERATIVAS AGRARIAS CAFETALERAS COCLA LTDA. N° | C12: CUSCO | D12: CAFÉ | E12: 4445611.6 | F12: 33 | G12: SI | H12: Cer | I12: Fai | J12: ACTIVO | K12: 0.75 | L12: 894391.27 | M12: =IF(E12>0,ROUND(L12/E12*100,1),0) | N12: PENDIENTE | O12: =IF(H12="SI",1,0)*0.6+IF(I12="SI",1,0)*0.4 | P12: PENDIENTE | Q12: 660 | R12: 1670 | S12: =IFERROR(SCORECARDS!C10,"—") | T12: =IF(ISTEXT(S12),S12,IF(S12<34,"🔴 Crítico",IF(S12<67,"🟡 Vulnerable","🟢 Preparado"))) | U12: 0.75 | V12: ⚠ 1 infracc. ambiental (OEFA) | W12: 1 | X12: 0 | Y12: 0 | Z12: 0 | AA12: 0 | AB12: 0 | AC12: 0 | AD12: 0 | AE12: 0 | AF12: 0 | AG12: 0 | AH12: 0 | AI12: 0 | AJ12: 0 | AK12: 0 | AL12: 0 | AM12: 0 | AN12: 0 | AO12: =IFERROR(AVERAGE(AA12,AB12,AC12,AD12,AE12,AF12,AG12,AH12,AI12,AJ12,AK12,AL12,AM12,AN12),"N/A") | AP12: =IFERROR(AVERAGE(W12,X12,Y12,Z12)/2,"N/A")
A13: 20140292657 | B13: COOPERATIVA AGRARIA CAFETALERA CCOCHAPAMPA LTDA. | C13: CUSCO | D13: CAFÉ | E13: 0 | G13: NO | H13: Cer | I13: Fa | J13: ACTIVO | K13: 0.75 | L13: 0 | M13: =IF(E13>0,ROUND(L13/E13*100,1),0) | N13: PENDIENTE | O13: =IF(H13="SI",1,0)*0.6+IF(I13="SI",1,0)*0.4 | P13: PENDIENTE | Q13: 49 | R13: 136.9 | S13: =IFERROR(SCORECARDS!C11,"—") | T13: =IF(ISTEXT(S13),S13,IF(S13<34,"🔴 Crítico",IF(S13<67,"🟡 Vulnerable","🟢 Preparado"))) | W13: 1 | X13: 0 | Y13: 0 | Z13: 0 | AA13: 0 | AB13: 0 | AC13: 0 | AD13: 0 | AE13: 0 | AF13: 0 | AG13: 0 | AH13: 0 | AI13: 0 | AJ13: 0 | AK13: 0 | AL13: 0 | AM13: 0 | AN13: 0 | AO13: =IFERROR(AVERAGE(AA13,AB13,AC13,AD13,AE13,AF13,AG13,AH13,AI13,AJ13,AK13,AL13,AM13,AN13),"N/A") | AP13: =IFERROR(AVERAGE(W13,X13,Y13,Z13)/2,"N/A")
A14: 20143692010 | B14: COOPERATIVA AGRARIA EL QUINACHO LTDA. N° 078 | C14: AYACUCHO | D14: CACAO | E14: 4030694.7 | F14: 14 | G14: SI | H14: nan | I14: nan | J14: ACTIVO | K14: nan | L14: 2015347.3 | M14: =IF(E14>0,ROUND(L14/E14*100,1),0) | N14: PENDIENTE | O14: =IF(H14="SI",1,0)*0.6+IF(I14="SI",1,0)*0.4 | P14: PENDIENTE | S14: =IFERROR(SCORECARDS!C12,"—") | T14: =IF(ISTEXT(S14),S14,IF(S14<34,"🔴 Crítico",IF(S14<67,"🟡 Vulnerable","🟢 Preparado"))) | U14: 1 | V14: Sin hallazgos OSCE / OEFA | W14: 1 | X14: 0 | Y14: 0 | Z14: 0 | AA14: 0 | AB14: 0 | AC14: 0 | AD14: 0 | AE14: 0 | AF14: 0 | AG14: 0 | AH14: 0 | AI14: 0 | AJ14: 0 | AK14: 0 | AL14: 0 | AM14: 0 | AN14: 0 | AO14: =IFERROR(AVERAGE(AA14,AB14,AC14,AD14,AE14,AF14,AG14,AH14,AI14,AJ14,AK14,AL14,AM14,AN14),"N/A") | AP14: =IFERROR(AVERAGE(W14,X14,Y14,Z14)/2,"N/A")
A15: 20145484597 | B15: COOPERATIVA AGRARIA CAFETALERA SAN IGNACIO LTDA. | C15: PUNO | D15: CAFÉ | G15: NO | H15: nan | I15: nan | J15: ACTIVO | K15: nan | L15: 0 | M15: =IF(E15>0,ROUND(L15/E15*100,1),0) | N15: PENDIENTE | O15: =IF(H15="SI",1,0)*0.6+IF(I15="SI",1,0)*0.4 | P15: PENDIENTE | S15: =IFERROR(SCORECARDS!C13,"—") | T15: =IF(ISTEXT(S15),S15,IF(S15<34,"🔴 Crítico",IF(S15<67,"🟡 Vulnerable","🟢 Preparado"))) | W15: 0 | X15: 0 | Y15: 0 | Z15: 0 | AA15: 0 | AB15: 0 | AC15: 0 | AD15: 0 | AE15: 0 | AF15: 0 | AG15: 0 | AH15: 0 | AI15: 0 | AJ15: 0 | AK15: 0 | AL15: 0 | AM15: 0 | AN15: 0 | AO15: =IFERROR(AVERAGE(AA15,AB15,AC15,AD15,AE15,AF15,AG15,AH15,AI15,AJ15,AK15,AL15,AM15,AN15),"N/A") | AP15: =IFERROR(AVERAGE(W15,X15,Y15,Z15)/2,"N/A")
A16: 20146696041 | B16: COOP AGRARIA CAFET JOSE GABRIEL CONDORCA | C16: PIURA | D16: CAFÉ | G16: NO | H16: nan | I16: nan | J16: ACTIVO | K16: nan | L16: 0 | M16: =IF(E16>0,ROUND(L16/E16*100,1),0) | N16: PENDIENTE | O16: =IF(H16="SI",1,0)*0.6+IF(I16="SI",1,0)*0.4 | P16: PENDIENTE | S16: =IFERROR(SCORECARDS!C14,"—") | T16: =IF(ISTEXT(S16),S16,IF(S16<34,"🔴 Crítico",IF(S16<67,"🟡 Vulnerable","🟢 Preparado"))) | W16: 0 | X16: 0 | Y16: 0 | Z16: 0 | AA16: 0 | AB16: 0 | AC16: 0 | AD16: 0 | AE16: 0 | AF16: 0 | AG16: 0 | AH16: 0 | AI16: 0 | AJ16: 0 | AK16: 0 | AL16: 0 | AM16: 0 | AN16: 0 | AO16: =IFERROR(AVERAGE(AA16,AB16,AC16,AD16,AE16,AF16,AG16,AH16,AI16,AJ16,AK16,AL16,AM16,AN16),"N/A") | AP16: =IFERROR(AVERAGE(W16,X16,Y16,Z16)/2,"N/A")
A17: 20147443120 | B17: COOPERATIVA AGRARIA CAFETALERA TIRIJUAY PAVAYOC LTDA 013-B-V | C17: CUSCO | D17: nan | G17: NO | H17: Cer | I17: Vig | J17: SUSPENSION TEMPORAL | K17: nan | L17: 0 | M17: =IF(E17>0,ROUND(L17/E17*100,1),0) | N17: PENDIENTE | O17: =IF(H17="SI",1,0)*0.6+IF(I17="SI",1,0)*0.4 | P17: PENDIENTE | Q17: 74 | R17: 150 | S17: =IFERROR(SCORECARDS!C15,"—") | T17: =IF(ISTEXT(S17),S17,IF(S17<34,"🔴 Crítico",IF(S17<67,"🟡 Vulnerable","🟢 Preparado"))) | W17: 1 | X17: 0 | Y17: 0 | Z17: 0 | AA17: 0 | AB17: 0 | AC17: 0 | AD17: 0 | AE17: 0 | AF17: 0 | AG17: 0 | AH17: 0 | AI17: 0 | AJ17: 0 | AK17: 0 | AL17: 0 | AM17: 0 | AN17: 0 | AO17: =IFERROR(AVERAGE(AA17,AB17,AC17,AD17,AE17,AF17,AG17,AH17,AI17,AJ17,AK17,AL17,AM17,AN17),"N/A") | AP17: =IFERROR(AVERAGE(W17,X17,Y17,Z17)/2,"N/A")
A18: 20166786861 | B18: COMITE CENTRAL DE PRODUCTORES AGROPECUARIOS DE SAN ALEJANDRO | C18: UCAYALI | D18: CACAO | G18: NO | H18: nan | I18: nan | J18: ACTIVO | K18: nan | L18: 0 | M18: =IF(E18>0,ROUND(L18/E18*100,1),0) | N18: PENDIENTE | O18: =IF(H18="SI",1,0)*0.6+IF(I18="SI",1,0)*0.4 | P18: PENDIENTE | S18: =IFERROR(SCORECARDS!C16,"—") | T18: =IF(ISTEXT(S18),S18,IF(S18<34,"🔴 Crítico",IF(S18<67,"🟡 Vulnerable","🟢 Preparado"))) | W18: 0 | X18: 0 | Y18: 0 | Z18: 0 | AA18: 0 | AB18: 0 | AC18: 0 | AD18: 0 | AE18: 0 | AF18: 0 | AG18: 0 | AH18: 0 | AI18: 0 | AJ18: 0 | AK18: 0 | AL18: 0 | AM18: 0 | AN18: 0 | AO18: =IFERROR(AVERAGE(AA18,AB18,AC18,AD18,AE18,AF18,AG18,AH18,AI18,AJ18,AK18,AL18,AM18,AN18),"N/A") | AP18: =IFERROR(AVERAGE(W18,X18,Y18,Z18)/2,"N/A")
A19: 20170142773 | B19: COOPERATIVA AGRARIA CAFETALERA BAGUA GRANDE LIMITADA | C19: AMAZONAS | D19: CAFÉ | E19: 9070756.9 | F19: 41 | G19: SI | H19: nan | I19: nan | J19: ACTIVO | K19: nan | L19: 4535378.4 | M19: =IF(E19>0,ROUND(L19/E19*100,1),0) | N19: PENDIENTE | O19: =IF(H19="SI",1,0)*0.6+IF(I19="SI",1,0)*0.4 | P19: PENDIENTE | S19: =IFERROR(SCORECARDS!C17,"—") | T19: =IF(ISTEXT(S19),S19,IF(S19<34,"🔴 Crítico",IF(S19<67,"🟡 Vulnerable","🟢 Preparado"))) | U19: 1 | V19: Sin hallazgos OSCE / OEFA | W19: 1 | X19: 0 | Y19: 0 | Z19: 0 | AA19: 0 | AB19: 0 | AC19: 0 | AD19: 0 | AE19: 0 | AF19: 0 | AG19: 0 | AH19: 0 | AI19: 0 | AJ19: 0 | AK19: 0 | AL19: 0 | AM19: 0 | AN19: 0 | AO19: =IFERROR(AVERAGE(AA19,AB19,AC19,AD19,AE19,AF19,AG19,AH19,AI19,AJ19,AK19,AL19,AM19,AN19),"N/A") | AP19: =IFERROR(AVERAGE(W19,X19,Y19,Z19)/2,"N/A")
A20: 20200880448 | B20: COOPERATIVA AGRARIA CAFETALERA JORGE CHAVEZ LTDA | C20: CUSCO | D20: nan | G20: NO | H20: Cer | I20: Vig | J20: ACTIVO | K20: nan | L20: 0 | M20: =IF(E20>0,ROUND(L20/E20*100,1),0) | N20: PENDIENTE | O20: =IF(H20="SI",1,0)*0.6+IF(I20="SI",1,0)*0.4 | P20: PENDIENTE | Q20: 36 | R20: 38 | S20: =IFERROR(SCORECARDS!C18,"—") | T20: =IF(ISTEXT(S20),S20,IF(S20<34,"🔴 Crítico",IF(S20<67,"🟡 Vulnerable","🟢 Preparado"))) | W20: 1 | X20: 0 | Y20: 0 | Z20: 0 | AA20: 0 | AB20: 0 | AC20: 0 | AD20: 0 | AE20: 0 | AF20: 0 | AG20: 0 | AH20: 0 | AI20: 0 | AJ20: 0 | AK20: 0 | AL20: 0 | AM20: 0 | AN20: 0 | AO20: =IFERROR(AVERAGE(AA20,AB20,AC20,AD20,AE20,AF20,AG20,AH20,AI20,AJ20,AK20,AL20,AM20,AN20),"N/A") | AP20: =IFERROR(AVERAGE(W20,X20,Y20,Z20)/2,"N/A")
A21: 20352417018 | B21: COOPERATIVA AGRARIA DE CACAOTEROS TECNIFICADOS DE PADRE ABAD | C21: UCAYALI | D21: CACAO | E21: 0 | G21: NO | H21: nan | I21: nan | J21: SUSPENSION TEMPORAL | K21: nan | L21: 0 | M21: =IF(E21>0,ROUND(L21/E21*100,1),0) | N21: PENDIENTE | O21: =IF(H21="SI",1,0)*0.6+IF(I21="SI",1,0)*0.4 | P21: PENDIENTE | S21: =IFERROR(SCORECARDS!C19,"—") | T21: =IF(ISTEXT(S21),S21,IF(S21<34,"🔴 Crítico",IF(S21<67,"🟡 Vulnerable","🟢 Preparado"))) | W21: 0 | X21: 0 | Y21: 0 | Z21: 0 | AA21: 0 | AB21: 0 | AC21: 0 | AD21: 0 | AE21: 0 | AF21: 0 | AG21: 0 | AH21: 0 | AI21: 0 | AJ21: 0 | AK21: 0 | AL21: 0 | AM21: 0 | AN21: 0 | AO21: =IFERROR(AVERAGE(AA21,AB21,AC21,AD21,AE21,AF21,AG21,AH21,AI21,AJ21,AK21,AL21,AM21,AN21),"N/A") | AP21: =IFERROR(AVERAGE(W21,X21,Y21,Z21)/2,"N/A")
A22: 20352423921 | B22: COOPERATIVA AGRARIA CAFETALERA DIVISORIA LTDA | C22: HUANUCO | D22: CAFÉ | E22: 0 | G22: NO | H22: nan | I22: nan | J22: ACTIVO | K22: nan | L22: 0 | M22: =IF(E22>0,ROUND(L22/E22*100,1),0) | N22: PENDIENTE | O22: =IF(H22="SI",1,0)*0.6+IF(I22="SI",1,0)*0.4 | P22: PENDIENTE | S22: =IFERROR(SCORECARDS!C20,"—") | T22: =IF(ISTEXT(S22),S22,IF(S22<34,"🔴 Crítico",IF(S22<67,"🟡 Vulnerable","🟢 Preparado"))) | W22: 0 | X22: 0 | Y22: 0 | Z22: 0 | AA22: 0 | AB22: 0 | AC22: 0 | AD22: 0 | AE22: 0 | AF22: 0 | AG22: 0 | AH22: 0 | AI22: 0 | AJ22: 0 | AK22: 0 | AL22: 0 | AM22: 0 | AN22: 0 | AO22: =IFERROR(AVERAGE(AA22,AB22,AC22,AD22,AE22,AF22,AG22,AH22,AI22,AJ22,AK22,AL22,AM22,AN22),"N/A") | AP22: =IFERROR(AVERAGE(W22,X22,Y22,Z22)/2,"N/A")
A23: 20393152207 | B23: COOPERATIVA AGRO INDUSTRIAL APCTVASH | C23: UCAYALI | D23: CACAO | G23: NO | H23: nan | I23: nan | J23: ACTIVO | K23: nan | L23: 0 | M23: =IF(E23>0,ROUND(L23/E23*100,1),0) | N23: PENDIENTE | O23: =IF(H23="SI",1,0)*0.6+IF(I23="SI",1,0)*0.4 | P23: PENDIENTE | S23: =IFERROR(SCORECARDS!C21,"—") | T23: =IF(ISTEXT(S23),S23,IF(S23<34,"🔴 Crítico",IF(S23<67,"🟡 Vulnerable","🟢 Preparado"))) | W23: 0 | X23: 0 | Y23: 0 | Z23: 0 | AA23: 0 | AB23: 0 | AC23: 0 | AD23: 0 | AE23: 0 | AF23: 0 | AG23: 0 | AH23: 0 | AI23: 0 | AJ23: 0 | AK23: 0 | AL23: 0 | AM23: 0 | AN23: 0 | AO23: =IFERROR(AVERAGE(AA23,AB23,AC23,AD23,AE23,AF23,AG23,AH23,AI23,AJ23,AK23,AL23,AM23,AN23),"N/A") | AP23: =IFERROR(AVERAGE(W23,X23,Y23,Z23)/2,"N/A")
A24: 20393593670 | B24: COMITE CENTRAL CON DESARROLLO AL FUTURO DE CURIMANA | C24: UCAYALI | D24: CACAO | E24: 0 | G24: NO | H24: nan | I24: nan | J24: BAJA DE OFICIO | K24: nan | L24: 0 | M24: =IF(E24>0,ROUND(L24/E24*100,1),0) | N24: PENDIENTE | O24: =IF(H24="SI",1,0)*0.6+IF(I24="SI",1,0)*0.4 | P24: PENDIENTE | S24: =IFERROR(SCORECARDS!C22,"—") | T24: =IF(ISTEXT(S24),S24,IF(S24<34,"🔴 Crítico",IF(S24<67,"🟡 Vulnerable","🟢 Preparado"))) | W24: 0 | X24: 0 | Y24: 0 | Z24: 0 | AA24: 0 | AB24: 0 | AC24: 0 | AD24: 0 | AE24: 0 | AF24: 0 | AG24: 0 | AH24: 0 | AI24: 0 | AJ24: 0 | AK24: 0 | AL24: 0 | AM24: 0 | AN24: 0 | AO24: =IFERROR(AVERAGE(AA24,AB24,AC24,AD24,AE24,AF24,AG24,AH24,AI24,AJ24,AK24,AL24,AM24,AN24),"N/A") | AP24: =IFERROR(AVERAGE(W24,X24,Y24,Z24)/2,"N/A")
A25: 20393692228 | B25: COOPERATIVA AGRARIA CACAOTERA SAN ALEJANDRO LTDA | C25: UCAYALI | D25: CACAO | E25: 0 | G25: NO | H25: nan | I25: nan | J25: ACTIVO | K25: nan | L25: 0 | M25: =IF(E25>0,ROUND(L25/E25*100,1),0) | N25: PENDIENTE | O25: =IF(H25="SI",1,0)*0.6+IF(I25="SI",1,0)*0.4 | P25: PENDIENTE | S25: =IFERROR(SCORECARDS!C23,"—") | T25: =IF(ISTEXT(S25),S25,IF(S25<34,"🔴 Crítico",IF(S25<67,"🟡 Vulnerable","🟢 Preparado"))) | W25: 0 | X25: 0 | Y25: 0 | Z25: 0 | AA25: 0 | AB25: 0 | AC25: 0 | AD25: 0 | AE25: 0 | AF25: 0 | AG25: 0 | AH25: 0 | AI25: 0 | AJ25: 0 | AK25: 0 | AL25: 0 | AM25: 0 | AN25: 0 | AO25: =IFERROR(AVERAGE(AA25,AB25,AC25,AD25,AE25,AF25,AG25,AH25,AI25,AJ25,AK25,AL25,AM25,AN25),"N/A") | AP25: =IFERROR(AVERAGE(W25,X25,Y25,Z25)/2,"N/A")
A26: 20393786044 | B26: COOPERATIVA AGRARIA CAFETALERA COORDILLERA AZUL DE UCAYALI L | C26: UCAYALI | D26: CAFÉ | G26: NO | H26: nan | I26: nan | J26: ACTIVO | K26: nan | L26: 0 | M26: =IF(E26>0,ROUND(L26/E26*100,1),0) | N26: PENDIENTE | O26: =IF(H26="SI",1,0)*0.6+IF(I26="SI",1,0)*0.4 | P26: PENDIENTE | S26: =IFERROR(SCORECARDS!C24,"—") | T26: =IF(ISTEXT(S26),S26,IF(S26<34,"🔴 Crítico",IF(S26<67,"🟡 Vulnerable","🟢 Preparado"))) | W26: 0 | X26: 0 | Y26: 0 | Z26: 0 | AA26: 0 | AB26: 0 | AC26: 0 | AD26: 0 | AE26: 0 | AF26: 0 | AG26: 0 | AH26: 0 | AI26: 0 | AJ26: 0 | AK26: 0 | AL26: 0 | AM26: 0 | AN26: 0 | AO26: =IFERROR(AVERAGE(AA26,AB26,AC26,AD26,AE26,AF26,AG26,AH26,AI26,AJ26,AK26,AL26,AM26,AN26),"N/A") | AP26: =IFERROR(AVERAGE(W26,X26,Y26,Z26)/2,"N/A")
A27: 20393816211 | B27: COOPERATIVA AGRARIA SAN JUAN BAUTISTA | C27: UCAYALI | D27: CACAO | E27: 0 | G27: NO | H27: nan | I27: nan | J27: ACTIVO | K27: nan | L27: 0 | M27: =IF(E27>0,ROUND(L27/E27*100,1),0) | N27: PENDIENTE | O27: =IF(H27="SI",1,0)*0.6+IF(I27="SI",1,0)*0.4 | P27: PENDIENTE | S27: =IFERROR(SCORECARDS!C25,"—") | T27: =IF(ISTEXT(S27),S27,IF(S27<34,"🔴 Crítico",IF(S27<67,"🟡 Vulnerable","🟢 Preparado"))) | W27: 0 | X27: 0 | Y27: 0 | Z27: 0 | AA27: 0 | AB27: 0 | AC27: 0 | AD27: 0 | AE27: 0 | AF27: 0 | AG27: 0 | AH27: 0 | AI27: 0 | AJ27: 0 | AK27: 0 | AL27: 0 | AM27: 0 | AN27: 0 | AO27: =IFERROR(AVERAGE(AA27,AB27,AC27,AD27,AE27,AF27,AG27,AH27,AI27,AJ27,AK27,AL27,AM27,AN27),"N/A") | AP27: =IFERROR(AVERAGE(W27,X27,Y27,Z27)/2,"N/A")
A28: 20393882868 | B28: COOPERATIVA AGRARIA ASCAH | C28: UCAYALI | D28: CACAO | G28: NO | H28: nan | I28: nan | J28: ACTIVO | K28: nan | L28: 0 | M28: =IF(E28>0,ROUND(L28/E28*100,1),0) | N28: PENDIENTE | O28: =IF(H28="SI",1,0)*0.6+IF(I28="SI",1,0)*0.4 | P28: PENDIENTE | S28: =IFERROR(SCORECARDS!C26,"—") | T28: =IF(ISTEXT(S28),S28,IF(S28<34,"🔴 Crítico",IF(S28<67,"🟡 Vulnerable","🟢 Preparado"))) | W28: 0 | X28: 0 | Y28: 0 | Z28: 0 | AA28: 0 | AB28: 0 | AC28: 0 | AD28: 0 | AE28: 0 | AF28: 0 | AG28: 0 | AH28: 0 | AI28: 0 | AJ28: 0 | AK28: 0 | AL28: 0 | AM28: 0 | AN28: 0 | AO28: =IFERROR(AVERAGE(AA28,AB28,AC28,AD28,AE28,AF28,AG28,AH28,AI28,AJ28,AK28,AL28,AM28,AN28),"N/A") | AP28: =IFERROR(AVERAGE(W28,X28,Y28,Z28)/2,"N/A")
A29: 20393972000 | B29: ASOCIACION DE MUJERES EMPRENDEDORAS FLOR DE BOQUERON | C29: UCAYALI | D29: CACAO | G29: NO | H29: nan | I29: nan | J29: ACTIVO | K29: nan | L29: 0 | M29: =IF(E29>0,ROUND(L29/E29*100,1),0) | N29: PENDIENTE | O29: =IF(H29="SI",1,0)*0.6+IF(I29="SI",1,0)*0.4 | P29: PENDIENTE | S29: =IFERROR(SCORECARDS!C27,"—") | T29: =IF(ISTEXT(S29),S29,IF(S29<34,"🔴 Crítico",IF(S29<67,"🟡 Vulnerable","🟢 Preparado"))) | W29: 0 | X29: 0 | Y29: 0 | Z29: 0 | AA29: 0 | AB29: 0 | AC29: 0 | AD29: 0 | AE29: 0 | AF29: 0 | AG29: 0 | AH29: 0 | AI29: 0 | AJ29: 0 | AK29: 0 | AL29: 0 | AM29: 0 | AN29: 0 | AO29: =IFERROR(AVERAGE(AA29,AB29,AC29,AD29,AE29,AF29,AG29,AH29,AI29,AJ29,AK29,AL29,AM29,AN29),"N/A") | AP29: =IFERROR(AVERAGE(W29,X29,Y29,Z29)/2,"N/A")
A30: 20447888701 | B30: COOPERATIVA AGRARIA INDUSTRIAL SAN GABAN LTDA. | C30: PUNO | D30: CACAO | G30: NO | H30: nan | I30: nan | J30: ACTIVO | K30: nan | L30: 0 | M30: =IF(E30>0,ROUND(L30/E30*100,1),0) | N30: PENDIENTE | O30: =IF(H30="SI",1,0)*0.6+IF(I30="SI",1,0)*0.4 | P30: PENDIENTE | S30: =IFERROR(SCORECARDS!C28,"—") | T30: =IF(ISTEXT(S30),S30,IF(S30<34,"🔴 Crítico",IF(S30<67,"🟡 Vulnerable","🟢 Preparado"))) | W30: 0 | X30: 0 | Y30: 0 | Z30: 0 | AA30: 0 | AB30: 0 | AC30: 0 | AD30: 0 | AE30: 0 | AF30: 0 | AG30: 0 | AH30: 0 | AI30: 0 | AJ30: 0 | AK30: 0 | AL30: 0 | AM30: 0 | AN30: 0 | AO30: =IFERROR(AVERAGE(AA30,AB30,AC30,AD30,AE30,AF30,AG30,AH30,AI30,AJ30,AK30,AL30,AM30,AN30),"N/A") | AP30: =IFERROR(AVERAGE(W30,X30,Y30,Z30)/2,"N/A")
A31: 20450189201 | B31: COOPERATIVA DE SERVICIOS MULTIPLES FRUTOS DE SELVA | C31: SAN MARTIN | D31: CAFÉ | E31: 0 | G31: NO | H31: nan | I31: nan | J31: ACTIVO | K31: nan | L31: 0 | M31: =IF(E31>0,ROUND(L31/E31*100,1),0) | N31: PENDIENTE | O31: =IF(H31="SI",1,0)*0.6+IF(I31="SI",1,0)*0.4 | P31: PENDIENTE | S31: =IFERROR(SCORECARDS!C29,"—") | T31: =IF(ISTEXT(S31),S31,IF(S31<34,"🔴 Crítico",IF(S31<67,"🟡 Vulnerable","🟢 Preparado"))) | W31: 0 | X31: 0 | Y31: 0 | Z31: 0 | AA31: 0 | AB31: 0 | AC31: 0 | AD31: 0 | AE31: 0 | AF31: 0 | AG31: 0 | AH31: 0 | AI31: 0 | AJ31: 0 | AK31: 0 | AL31: 0 | AM31: 0 | AN31: 0 | AO31: =IFERROR(AVERAGE(AA31,AB31,AC31,AD31,AE31,AF31,AG31,AH31,AI31,AJ31,AK31,AL31,AM31,AN31),"N/A") | AP31: =IFERROR(AVERAGE(W31,X31,Y31,Z31)/2,"N/A")
A32: 20450207544 | B32: COOPERATIVA AGRARIA UCHIZA LTDA | C32: SAN MARTIN | D32: CACAO | E32: 0 | G32: NO | H32: nan | I32: nan | J32: ACTIVO | K32: nan | L32: 0 | M32: =IF(E32>0,ROUND(L32/E32*100,1),0) | N32: PENDIENTE | O32: =IF(H32="SI",1,0)*0.6+IF(I32="SI",1,0)*0.4 | P32: PENDIENTE | S32: =IFERROR(SCORECARDS!C30,"—") | T32: =IF(ISTEXT(S32),S32,IF(S32<34,"🔴 Crítico",IF(S32<67,"🟡 Vulnerable","🟢 Preparado"))) | W32: 0 | X32: 0 | Y32: 0 | Z32: 0 | AA32: 0 | AB32: 0 | AC32: 0 | AD32: 0 | AE32: 0 | AF32: 0 | AG32: 0 | AH32: 0 | AI32: 0 | AJ32: 0 | AK32: 0 | AL32: 0 | AM32: 0 | AN32: 0 | AO32: =IFERROR(AVERAGE(AA32,AB32,AC32,AD32,AE32,AF32,AG32,AH32,AI32,AJ32,AK32,AL32,AM32,AN32),"N/A") | AP32: =IFERROR(AVERAGE(W32,X32,Y32,Z32)/2,"N/A")
A33: 20450242021 | B33: COOPERATIVA DE SERVICIOS MULTIPLES CAPEMA | C33: SAN MARTIN | D33: CAFÉ | E33: 0 | G33: NO | H33: nan | I33: nan | J33: ACTIVO | K33: nan | L33: 0 | M33: =IF(E33>0,ROUND(L33/E33*100,1),0) | N33: PENDIENTE | O33: =IF(H33="SI",1,0)*0.6+IF(I33="SI",1,0)*0.4 | P33: PENDIENTE | S33: =IFERROR(SCORECARDS!C31,"—") | T33: =IF(ISTEXT(S33),S33,IF(S33<34,"🔴 Crítico",IF(S33<67,"🟡 Vulnerable","🟢 Preparado"))) | W33: 0 | X33: 0 | Y33: 0 | Z33: 0 | AA33: 0 | AB33: 0 | AC33: 0 | AD33: 0 | AE33: 0 | AF33: 0 | AG33: 0 | AH33: 0 | AI33: 0 | AJ33: 0 | AK33: 0 | AL33: 0 | AM33: 0 | AN33: 0 | AO33: =IFERROR(AVERAGE(AA33,AB33,AC33,AD33,AE33,AF33,AG33,AH33,AI33,AJ33,AK33,AL33,AM33,AN33),"N/A") | AP33: =IFERROR(AVERAGE(W33,X33,Y33,Z33)/2,"N/A")
A34: 20450319423 | B34: COOPERATIVA AGRARIA DE SERVICIOS MULTIPLES CAFE DONCEL | C34: SAN MARTIN | D34: CAFÉ | G34: NO | H34: nan | I34: nan | J34: ACTIVO | K34: nan | L34: 0 | M34: =IF(E34>0,ROUND(L34/E34*100,1),0) | N34: PENDIENTE | O34: =IF(H34="SI",1,0)*0.6+IF(I34="SI",1,0)*0.4 | P34: PENDIENTE | S34: =IFERROR(SCORECARDS!C32,"—") | T34: =IF(ISTEXT(S34),S34,IF(S34<34,"🔴 Crítico",IF(S34<67,"🟡 Vulnerable","🟢 Preparado"))) | W34: 0 | X34: 0 | Y34: 0 | Z34: 0 | AA34: 0 | AB34: 0 | AC34: 0 | AD34: 0 | AE34: 0 | AF34: 0 | AG34: 0 | AH34: 0 | AI34: 0 | AJ34: 0 | AK34: 0 | AL34: 0 | AM34: 0 | AN34: 0 | AO34: =IFERROR(AVERAGE(AA34,AB34,AC34,AD34,AE34,AF34,AG34,AH34,AI34,AJ34,AK34,AL34,AM34,AN34),"N/A") | AP34: =IFERROR(AVERAGE(W34,X34,Y34,Z34)/2,"N/A")
A35: 20452774705 | B35: COOPERATIVA AGRARIA CACAO VRAE | C35: CUSCO | D35: CACAO | E35: 1931452.7 | F35: 7 | G35: SI | H35: nan | I35: nan | J35: ACTIVO | K35: nan | L35: 965726.35 | M35: =IF(E35>0,ROUND(L35/E35*100,1),0) | N35: PENDIENTE | O35: =IF(H35="SI",1,0)*0.6+IF(I35="SI",1,0)*0.4 | P35: PENDIENTE | S35: =IFERROR(SCORECARDS!C33,"—") | T35: =IF(ISTEXT(S35),S35,IF(S35<34,"🔴 Crítico",IF(S35<67,"🟡 Vulnerable","🟢 Preparado"))) | U35: 1 | V35: Sin hallazgos OSCE / OEFA | W35: 1 | X35: 0 | Y35: 0 | Z35: 0 | AA35: 0 | AB35: 0 | AC35: 0 | AD35: 0 | AE35: 0 | AF35: 0 | AG35: 0 | AH35: 0 | AI35: 0 | AJ35: 0 | AK35: 0 | AL35: 0 | AM35: 0 | AN35: 0 | AO35: =IFERROR(AVERAGE(AA35,AB35,AC35,AD35,AE35,AF35,AG35,AH35,AI35,AJ35,AK35,AL35,AM35,AN35),"N/A") | AP35: =IFERROR(AVERAGE(W35,X35,Y35,Z35)/2,"N/A")
A36: 20479595276 | B36: COOPERATIVA AGRARIA CAFETALERA CASIL LTDA. | C36: CAJAMARCA | D36: CAFÉ | E36: 4538578.9 | F36: 24 | G36: SI | H36: SI | I36: SI | J36: ACTIVO | K36: nan | L36: 965167.45 | M36: =IF(E36>0,ROUND(L36/E36*100,1),0) | N36: PENDIENTE | O36: =IF(H36="SI",1,0)*0.6+IF(I36="SI",1,0)*0.4 | P36: PENDIENTE | Q36: 178 | R36: 437 | S36: =IFERROR(SCORECARDS!C34,"—") | T36: =IF(ISTEXT(S36),S36,IF(S36<34,"🔴 Crítico",IF(S36<67,"🟡 Vulnerable","🟢 Preparado"))) | U36: 1 | V36: Sin hallazgos OSCE / OEFA | W36: 1 | X36: 0 | Y36: 0 | Z36: 0 | AA36: 0 | AB36: 0 | AC36: 0 | AD36: 0 | AE36: 0 | AF36: 0 | AG36: 0 | AH36: 0 | AI36: 0 | AJ36: 0 | AK36: 0 | AL36: 0 | AM36: 0 | AN36: 0 | AO36: =IFERROR(AVERAGE(AA36,AB36,AC36,AD36,AE36,AF36,AG36,AH36,AI36,AJ36,AK36,AL36,AM36,AN36),"N/A") | AP36: =IFERROR(AVERAGE(W36,X36,Y36,Z36)/2,"N/A")
A37: 20479622699 | B37: COOPERATIVA AGRARIA JUAN MARCO EL PALTO | C37: AMAZONAS | D37: CAFÉ | E37: 0 | G37: NO | H37: nan | I37: nan | J37: ACTIVO | K37: nan | L37: 0 | M37: =IF(E37>0,ROUND(L37/E37*100,1),0) | N37: PENDIENTE | O37: =IF(H37="SI",1,0)*0.6+IF(I37="SI",1,0)*0.4 | P37: PENDIENTE | S37: =IFERROR(SCORECARDS!C35,"—") | T37: =IF(ISTEXT(S37),S37,IF(S37<34,"🔴 Crítico",IF(S37<67,"🟡 Vulnerable","🟢 Preparado"))) | W37: 0 | X37: 0 | Y37: 0 | Z37: 0 | AA37: 0 | AB37: 0 | AC37: 0 | AD37: 0 | AE37: 0 | AF37: 0 | AG37: 0 | AH37: 0 | AI37: 0 | AJ37: 0 | AK37: 0 | AL37: 0 | AM37: 0 | AN37: 0 | AO37: =IFERROR(AVERAGE(AA37,AB37,AC37,AD37,AE37,AF37,AG37,AH37,AI37,AJ37,AK37,AL37,AM37,AN37),"N/A") | AP37: =IFERROR(AVERAGE(W37,X37,Y37,Z37)/2,"N/A")
A38: 20479856258 | B38: ASOCIACION DE PRODUCTORES AGROPECUARIOS LUIS SOLIBARRIA | C38: AMAZONAS | D38: nan | G38: NO | H38: nan | I38: nan | J38: BAJA DE OFICIO | K38: nan | L38: 0 | M38: =IF(E38>0,ROUND(L38/E38*100,1),0) | N38: PENDIENTE | O38: =IF(H38="SI",1,0)*0.6+IF(I38="SI",1,0)*0.4 | P38: PENDIENTE | S38: =IFERROR(SCORECARDS!C36,"—") | T38: =IF(ISTEXT(S38),S38,IF(S38<34,"🔴 Crítico",IF(S38<67,"🟡 Vulnerable","🟢 Preparado"))) | W38: 0 | X38: 0 | Y38: 0 | Z38: 0 | AA38: 0 | AB38: 0 | AC38: 0 | AD38: 0 | AE38: 0 | AF38: 0 | AG38: 0 | AH38: 0 | AI38: 0 | AJ38: 0 | AK38: 0 | AL38: 0 | AM38: 0 | AN38: 0 | AO38: =IFERROR(AVERAGE(AA38,AB38,AC38,AD38,AE38,AF38,AG38,AH38,AI38,AJ38,AK38,AL38,AM38,AN38),"N/A") | AP38: =IFERROR(AVERAGE(W38,X38,Y38,Z38)/2,"N/A")
A39: 20479917141 | B39: COOPERATIVA AGRARIA CENTRAL DE PRODUCTORES DE AMAZONAS | C39: AMAZONAS | D39: CACAO | E39: 1175215.3 | F39: 7 | G39: SI | H39: nan | I39: nan | J39: ACTIVO | K39: nan | L39: 587607.64 | M39: =IF(E39>0,ROUND(L39/E39*100,1),0) | N39: PENDIENTE | O39: =IF(H39="SI",1,0)*0.6+IF(I39="SI",1,0)*0.4 | P39: PENDIENTE | S39: =IFERROR(SCORECARDS!C37,"—") | T39: =IF(ISTEXT(S39),S39,IF(S39<34,"🔴 Crítico",IF(S39<67,"🟡 Vulnerable","🟢 Preparado"))) | U39: 1 | V39: Sin hallazgos OSCE / OEFA | W39: 1 | X39: 0 | Y39: 0 | Z39: 0 | AA39: 0 | AB39: 0 | AC39: 0 | AD39: 0 | AE39: 0 | AF39: 0 | AG39: 0 | AH39: 0 | AI39: 0 | AJ39: 0 | AK39: 0 | AL39: 0 | AM39: 0 | AN39: 0 | AO39: =IFERROR(AVERAGE(AA39,AB39,AC39,AD39,AE39,AF39,AG39,AH39,AI39,AJ39,AK39,AL39,AM39,AN39),"N/A") | AP39: =IFERROR(AVERAGE(W39,X39,Y39,Z39)/2,"N/A")
A40: 20480458550 | B40: COOPERATIVA AGRARIA APROCAM | C40: AMAZONAS | D40: CACAO | E40: 1684430 | F40: 14 | G40: SI | H40: nan | I40: nan | J40: ACTIVO | K40: nan | L40: 842214.99 | M40: =IF(E40>0,ROUND(L40/E40*100,1),0) | N40: PENDIENTE | O40: =IF(H40="SI",1,0)*0.6+IF(I40="SI",1,0)*0.4 | P40: PENDIENTE | S40: =IFERROR(SCORECARDS!C38,"—") | T40: =IF(ISTEXT(S40),S40,IF(S40<34,"🔴 Crítico",IF(S40<67,"🟡 Vulnerable","🟢 Preparado"))) | U40: 1 | V40: Sin hallazgos OSCE / OEFA | W40: 1 | X40: 0 | Y40: 0 | Z40: 0 | AA40: 0 | AB40: 0 | AC40: 0 | AD40: 0 | AE40: 0 | AF40: 0 | AG40: 0 | AH40: 0 | AI40: 0 | AJ40: 0 | AK40: 0 | AL40: 0 | AM40: 0 | AN40: 0 | AO40: =IFERROR(AVERAGE(AA40,AB40,AC40,AD40,AE40,AF40,AG40,AH40,AI40,AJ40,AK40,AL40,AM40,AN40),"N/A") | AP40: =IFERROR(AVERAGE(W40,X40,Y40,Z40)/2,"N/A")
A41: 20480762895 | B41: ASOCIACION DE PRODUCTORES AGROPECUARIOS LA FLOR DE CAFE | C41: AMAZONAS | D41: CAFÉ | E41: 0 | G41: NO | H41: nan | I41: nan | J41: BAJA DE OFICIO | K41: nan | L41: 0 | M41: =IF(E41>0,ROUND(L41/E41*100,1),0) | N41: PENDIENTE | O41: =IF(H41="SI",1,0)*0.6+IF(I41="SI",1,0)*0.4 | P41: PENDIENTE | S41: =IFERROR(SCORECARDS!C39,"—") | T41: =IF(ISTEXT(S41),S41,IF(S41<34,"🔴 Crítico",IF(S41<67,"🟡 Vulnerable","🟢 Preparado"))) | W41: 0 | X41: 0 | Y41: 0 | Z41: 0 | AA41: 0 | AB41: 0 | AC41: 0 | AD41: 0 | AE41: 0 | AF41: 0 | AG41: 0 | AH41: 0 | AI41: 0 | AJ41: 0 | AK41: 0 | AL41: 0 | AM41: 0 | AN41: 0 | AO41: =IFERROR(AVERAGE(AA41,AB41,AC41,AD41,AE41,AF41,AG41,AH41,AI41,AJ41,AK41,AL41,AM41,AN41),"N/A") | AP41: =IFERROR(AVERAGE(W41,X41,Y41,Z41)/2,"N/A")
A42: 20484163902 | B42: COOPERATIVA AGRARIA APPROCAP LTDA | C42: PIURA | D42: CACAO | E42: 817000 | F42: 6 | G42: SI | H42: nan | I42: nan | J42: ACTIVO | K42: nan | L42: 408500 | M42: =IF(E42>0,ROUND(L42/E42*100,1),0) | N42: PENDIENTE | O42: =IF(H42="SI",1,0)*0.6+IF(I42="SI",1,0)*0.4 | P42: PENDIENTE | S42: =IFERROR(SCORECARDS!C40,"—") | T42: =IF(ISTEXT(S42),S42,IF(S42<34,"🔴 Crítico",IF(S42<67,"🟡 Vulnerable","🟢 Preparado"))) | U42: 1 | V42: Sin hallazgos OSCE / OEFA | W42: 0 | X42: 0 | Y42: 0 | Z42: 0 | AA42: 0 | AB42: 0 | AC42: 0 | AD42: 0 | AE42: 0 | AF42: 0 | AG42: 0 | AH42: 0 | AI42: 0 | AJ42: 0 | AK42: 0 | AL42: 0 | AM42: 0 | AN42: 0 | AO42: =IFERROR(AVERAGE(AA42,AB42,AC42,AD42,AE42,AF42,AG42,AH42,AI42,AJ42,AK42,AL42,AM42,AN42),"N/A") | AP42: =IFERROR(AVERAGE(W42,X42,Y42,Z42)/2,"N/A")
A43: 20485945815 | B43: COOPERATIVA AGRARIA CAFETALERA ECOLOGICO ALTO PALOMAR | C43: JUNIN | D43: CAFÉ | E43: 0 | G43: NO | H43: nan | I43: nan | J43: SUSPENSION TEMPORAL | K43: nan | L43: 0 | M43: =IF(E43>0,ROUND(L43/E43*100,1),0) | N43: PENDIENTE | O43: =IF(H43="SI",1,0)*0.6+IF(I43="SI",1,0)*0.4 | P43: PENDIENTE | S43: =IFERROR(SCORECARDS!C41,"—") | T43: =IF(ISTEXT(S43),S43,IF(S43<34,"🔴 Crítico",IF(S43<67,"🟡 Vulnerable","🟢 Preparado"))) | W43: 0 | X43: 0 | Y43: 0 | Z43: 0 | AA43: 0 | AB43: 0 | AC43: 0 | AD43: 0 | AE43: 0 | AF43: 0 | AG43: 0 | AH43: 0 | AI43: 0 | AJ43: 0 | AK43: 0 | AL43: 0 | AM43: 0 | AN43: 0 | AO43: =IFERROR(AVERAGE(AA43,AB43,AC43,AD43,AE43,AF43,AG43,AH43,AI43,AJ43,AK43,AL43,AM43,AN43),"N/A") | AP43: =IFERROR(AVERAGE(W43,X43,Y43,Z43)/2,"N/A")
A44: 20486094657 | B44: ASOCIACION DE PRODUCTORES DE CAFES ESPECIALES MOUNTAIN COFFE | C44: JUNIN | D44: CAFÉ | E44: 0 | G44: NO | H44: nan | I44: nan | J44: ACTIVO | K44: nan | L44: 0 | M44: =IF(E44>0,ROUND(L44/E44*100,1),0) | N44: PENDIENTE | O44: =IF(H44="SI",1,0)*0.6+IF(I44="SI",1,0)*0.4 | P44: PENDIENTE | S44: =IFERROR(SCORECARDS!C42,"—") | T44: =IF(ISTEXT(S44),S44,IF(S44<34,"🔴 Crítico",IF(S44<67,"🟡 Vulnerable","🟢 Preparado"))) | W44: 0 | X44: 0 | Y44: 0 | Z44: 0 | AA44: 0 | AB44: 0 | AC44: 0 | AD44: 0 | AE44: 0 | AF44: 0 | AG44: 0 | AH44: 0 | AI44: 0 | AJ44: 0 | AK44: 0 | AL44: 0 | AM44: 0 | AN44: 0 | AO44: =IFERROR(AVERAGE(AA44,AB44,AC44,AD44,AE44,AF44,AG44,AH44,AI44,AJ44,AK44,AL44,AM44,AN44),"N/A") | AP44: =IFERROR(AVERAGE(W44,X44,Y44,Z44)/2,"N/A")
A45: 20486255090 | B45: COOPERATIVA AGRARIA SANGARENI | C45: JUNIN | D45: CAFÉ | E45: 13207692 | F45: 41 | G45: SI | H45: nan | I45: nan | J45: ACTIVO | K45: nan | L45: 6603846 | M45: =IF(E45>0,ROUND(L45/E45*100,1),0) | N45: PENDIENTE | O45: =IF(H45="SI",1,0)*0.6+IF(I45="SI",1,0)*0.4 | P45: PENDIENTE | S45: =IFERROR(SCORECARDS!C43,"—") | T45: =IF(ISTEXT(S45),S45,IF(S45<34,"🔴 Crítico",IF(S45<67,"🟡 Vulnerable","🟢 Preparado"))) | U45: 1 | V45: Sin hallazgos OSCE / OEFA | W45: 1 | X45: 0 | Y45: 0 | Z45: 0 | AA45: 0 | AB45: 0 | AC45: 0 | AD45: 0 | AE45: 0 | AF45: 0 | AG45: 0 | AH45: 0 | AI45: 0 | AJ45: 0 | AK45: 0 | AL45: 0 | AM45: 0 | AN45: 0 | AO45: =IFERROR(AVERAGE(AA45,AB45,AC45,AD45,AE45,AF45,AG45,AH45,AI45,AJ45,AK45,AL45,AM45,AN45),"N/A") | AP45: =IFERROR(AVERAGE(W45,X45,Y45,Z45)/2,"N/A")
A46: 20486668335 | B46: COOPERATIVA AGROINDUSTRIAL SONOMORO LTDA | C46: JUNIN | D46: nan | E46: 0 | G46: NO | H46: nan | I46: nan | J46: SUSPENSION TEMPORAL | K46: nan | L46: 0 | M46: =IF(E46>0,ROUND(L46/E46*100,1),0) | N46: PENDIENTE | O46: =IF(H46="SI",1,0)*0.6+IF(I46="SI",1,0)*0.4 | P46: PENDIENTE | S46: =IFERROR(SCORECARDS!C44,"—") | T46: =IF(ISTEXT(S46),S46,IF(S46<34,"🔴 Crítico",IF(S46<67,"🟡 Vulnerable","🟢 Preparado"))) | W46: 0 | X46: 0 | Y46: 0 | Z46: 0 | AA46: 0 | AB46: 0 | AC46: 0 | AD46: 0 | AE46: 0 | AF46: 0 | AG46: 0 | AH46: 0 | AI46: 0 | AJ46: 0 | AK46: 0 | AL46: 0 | AM46: 0 | AN46: 0 | AO46: =IFERROR(AVERAGE(AA46,AB46,AC46,AD46,AE46,AF46,AG46,AH46,AI46,AJ46,AK46,AL46,AM46,AN46),"N/A") | AP46: =IFERROR(AVERAGE(W46,X46,Y46,Z46)/2,"N/A")
A47: 20486876019 | B47: COOPERATIVA AGROECOLOGICO INDUSTRIAL MAZAMARI LTDA | C47: JUNIN | D47: CACAO | G47: NO | H47: nan | I47: nan | J47: ACTIVO | K47: nan | L47: 0 | M47: =IF(E47>0,ROUND(L47/E47*100,1),0) | N47: PENDIENTE | O47: =IF(H47="SI",1,0)*0.6+IF(I47="SI",1,0)*0.4 | P47: PENDIENTE | S47: =IFERROR(SCORECARDS!C45,"—") | T47: =IF(ISTEXT(S47),S47,IF(S47<34,"🔴 Crítico",IF(S47<67,"🟡 Vulnerable","🟢 Preparado"))) | W47: 0 | X47: 0 | Y47: 0 | Z47: 0 | AA47: 0 | AB47: 0 | AC47: 0 | AD47: 0 | AE47: 0 | AF47: 0 | AG47: 0 | AH47: 0 | AI47: 0 | AJ47: 0 | AK47: 0 | AL47: 0 | AM47: 0 | AN47: 0 | AO47: =IFERROR(AVERAGE(AA47,AB47,AC47,AD47,AE47,AF47,AG47,AH47,AI47,AJ47,AK47,AL47,AM47,AN47),"N/A") | AP47: =IFERROR(AVERAGE(W47,X47,Y47,Z47)/2,"N/A")
A48: 20486973219 | B48: COOPERATIVA AGRARIA SONOMORO DEL VRAEM LTDA | C48: JUNIN | D48: CACAO | E48: 30342293 | F48: 108 | G48: SI | H48: nan | I48: nan | J48: ACTIVO | K48: nan | L48: 15171147 | M48: =IF(E48>0,ROUND(L48/E48*100,1),0) | N48: PENDIENTE | O48: =IF(H48="SI",1,0)*0.6+IF(I48="SI",1,0)*0.4 | P48: PENDIENTE | S48: =IFERROR(SCORECARDS!C46,"—") | T48: =IF(ISTEXT(S48),S48,IF(S48<34,"🔴 Crítico",IF(S48<67,"🟡 Vulnerable","🟢 Preparado"))) | U48: 1 | V48: Sin hallazgos OSCE / OEFA | W48: 1 | X48: 0 | Y48: 0 | Z48: 0 | AA48: 0 | AB48: 0 | AC48: 0 | AD48: 0 | AE48: 0 | AF48: 0 | AG48: 0 | AH48: 0 | AI48: 0 | AJ48: 0 | AK48: 0 | AL48: 0 | AM48: 0 | AN48: 0 | AO48: =IFERROR(AVERAGE(AA48,AB48,AC48,AD48,AE48,AF48,AG48,AH48,AI48,AJ48,AK48,AL48,AM48,AN48),"N/A") | AP48: =IFERROR(AVERAGE(W48,X48,Y48,Z48)/2,"N/A")
A49: 20487242994 | B49: COOPERATIVA AGRARIA ECOLOGICA CACAOTERA VALLE RIO ENE - COOP | C49: JUNIN | D49: CACAO | E49: 2290978.7 | F49: 10 | G49: SI | H49: nan | I49: nan | J49: ACTIVO | K49: nan | L49: 1145489.4 | M49: =IF(E49>0,ROUND(L49/E49*100,1),0) | N49: PENDIENTE | O49: =IF(H49="SI",1,0)*0.6+IF(I49="SI",1,0)*0.4 | P49: PENDIENTE | S49: =IFERROR(SCORECARDS!C47,"—") | T49: =IF(ISTEXT(S49),S49,IF(S49<34,"🔴 Crítico",IF(S49<67,"🟡 Vulnerable","🟢 Preparado"))) | U49: 1 | V49: Sin hallazgos OSCE / OEFA | W49: 1 | X49: 0 | Y49: 0 | Z49: 0 | AA49: 0 | AB49: 0 | AC49: 0 | AD49: 0 | AE49: 0 | AF49: 0 | AG49: 0 | AH49: 0 | AI49: 0 | AJ49: 0 | AK49: 0 | AL49: 0 | AM49: 0 | AN49: 0 | AO49: =IFERROR(AVERAGE(AA49,AB49,AC49,AD49,AE49,AF49,AG49,AH49,AI49,AJ49,AK49,AL49,AM49,AN49),"N/A") | AP49: =IFERROR(AVERAGE(W49,X49,Y49,Z49)/2,"N/A")
A50: 20487351343 | B50: ASOCIACION DE PRODUCTORES AGROPECUARIOS TUPAC AMARU DE CHIÑA | C50: LAMBAYEQUE | D50: CAFÉ | G50: NO | H50: nan | I50: nan | J50: BAJA DE OFICIO | K50: nan | L50: 0 | M50: =IF(E50>0,ROUND(L50/E50*100,1),0) | N50: PENDIENTE | O50: =IF(H50="SI",1,0)*0.6+IF(I50="SI",1,0)*0.4 | P50: PENDIENTE | S50: =IFERROR(SCORECARDS!C48,"—") | T50: =IF(ISTEXT(S50),S50,IF(S50<34,"🔴 Crítico",IF(S50<67,"🟡 Vulnerable","🟢 Preparado"))) | W50: 0 | X50: 0 | Y50: 0 | Z50: 0 | AA50: 0 | AB50: 0 | AC50: 0 | AD50: 0 | AE50: 0 | AF50: 0 | AG50: 0 | AH50: 0 | AI50: 0 | AJ50: 0 | AK50: 0 | AL50: 0 | AM50: 0 | AN50: 0 | AO50: =IFERROR(AVERAGE(AA50,AB50,AC50,AD50,AE50,AF50,AG50,AH50,AI50,AJ50,AK50,AL50,AM50,AN50),"N/A") | AP50: =IFERROR(AVERAGE(W50,X50,Y50,Z50)/2,"N/A")
A51: 20487661539 | B51: ASOCIACION DE PRODUCTORES CACAOTEROS DEL DISTRITO DE HUARANG | C51: CAJAMARCA | D51: CACAO | G51: NO | H51: nan | I51: nan | J51: ACTIVO | K51: nan | L51: 0 | M51: =IF(E51>0,ROUND(L51/E51*100,1),0) | N51: PENDIENTE | O51: =IF(H51="SI",1,0)*0.6+IF(I51="SI",1,0)*0.4 | P51: PENDIENTE | S51: =IFERROR(SCORECARDS!C49,"—") | T51: =IF(ISTEXT(S51),S51,IF(S51<34,"🔴 Crítico",IF(S51<67,"🟡 Vulnerable","🟢 Preparado"))) | W51: 0 | X51: 0 | Y51: 0 | Z51: 0 | AA51: 0 | AB51: 0 | AC51: 0 | AD51: 0 | AE51: 0 | AF51: 0 | AG51: 0 | AH51: 0 | AI51: 0 | AJ51: 0 | AK51: 0 | AL51: 0 | AM51: 0 | AN51: 0 | AO51: =IFERROR(AVERAGE(AA51,AB51,AC51,AD51,AE51,AF51,AG51,AH51,AI51,AJ51,AK51,AL51,AM51,AN51),"N/A") | AP51: =IFERROR(AVERAGE(W51,X51,Y51,Z51)/2,"N/A")
A52: 20490726196 | B52: ASOCIACIÓN DE PRODUCTORES AGROPECUARIOS VALLESITO - CHAHUARE | C52: CUSCO | D52: CACAO | G52: NO | H52: nan | I52: nan | J52: ACTIVO | K52: nan | L52: 0 | M52: =IF(E52>0,ROUND(L52/E52*100,1),0) | N52: PENDIENTE | O52: =IF(H52="SI",1,0)*0.6+IF(I52="SI",1,0)*0.4 | P52: PENDIENTE | S52: =IFERROR(SCORECARDS!C50,"—") | T52: =IF(ISTEXT(S52),S52,IF(S52<34,"🔴 Crítico",IF(S52<67,"🟡 Vulnerable","🟢 Preparado"))) | W52: 0 | X52: 0 | Y52: 0 | Z52: 0 | AA52: 0 | AB52: 0 | AC52: 0 | AD52: 0 | AE52: 0 | AF52: 0 | AG52: 0 | AH52: 0 | AI52: 0 | AJ52: 0 | AK52: 0 | AL52: 0 | AM52: 0 | AN52: 0 | AO52: =IFERROR(AVERAGE(AA52,AB52,AC52,AD52,AE52,AF52,AG52,AH52,AI52,AJ52,AK52,AL52,AM52,AN52),"N/A") | AP52: =IFERROR(AVERAGE(W52,X52,Y52,Z52)/2,"N/A")
A53: 20493934822 | B53: COOPERATIVA AGRARIA NUEVO AMANECER LTDA. | C53: SAN MARTIN | D53: CACAO | E53: 0 | G53: NO | H53: nan | I53: nan | J53: ACTIVO | K53: nan | L53: 0 | M53: =IF(E53>0,ROUND(L53/E53*100,1),0) | N53: PENDIENTE | O53: =IF(H53="SI",1,0)*0.6+IF(I53="SI",1,0)*0.4 | P53: PENDIENTE | S53: =IFERROR(SCORECARDS!C51,"—") | T53: =IF(ISTEXT(S53),S53,IF(S53<34,"🔴 Crítico",IF(S53<67,"🟡 Vulnerable","🟢 Preparado"))) | W53: 0 | X53: 0 | Y53: 0 | Z53: 0 | AA53: 0 | AB53: 0 | AC53: 0 | AD53: 0 | AE53: 0 | AF53: 0 | AG53: 0 | AH53: 0 | AI53: 0 | AJ53: 0 | AK53: 0 | AL53: 0 | AM53: 0 | AN53: 0 | AO53: =IFERROR(AVERAGE(AA53,AB53,AC53,AD53,AE53,AF53,AG53,AH53,AI53,AJ53,AK53,AL53,AM53,AN53),"N/A") | AP53: =IFERROR(AVERAGE(W53,X53,Y53,Z53)/2,"N/A")
A54: 20493959574 | B54: COOPERATIVA AGRARIA DE SERVICIOS MUJERES TECNOLOGAS CACAOTER | C54: SAN MARTIN | D54: CACAO | G54: NO | H54: nan | I54: nan | J54: SUSPENSION TEMPORAL | K54: nan | L54: 0 | M54: =IF(E54>0,ROUND(L54/E54*100,1),0) | N54: PENDIENTE | O54: =IF(H54="SI",1,0)*0.6+IF(I54="SI",1,0)*0.4 | P54: PENDIENTE | S54: =IFERROR(SCORECARDS!C52,"—") | T54: =IF(ISTEXT(S54),S54,IF(S54<34,"🔴 Crítico",IF(S54<67,"🟡 Vulnerable","🟢 Preparado"))) | W54: 0 | X54: 0 | Y54: 0 | Z54: 0 | AA54: 0 | AB54: 0 | AC54: 0 | AD54: 0 | AE54: 0 | AF54: 0 | AG54: 0 | AH54: 0 | AI54: 0 | AJ54: 0 | AK54: 0 | AL54: 0 | AM54: 0 | AN54: 0 | AO54: =IFERROR(AVERAGE(AA54,AB54,AC54,AD54,AE54,AF54,AG54,AH54,AI54,AJ54,AK54,AL54,AM54,AN54),"N/A") | AP54: =IFERROR(AVERAGE(W54,X54,Y54,Z54)/2,"N/A")
A55: 20494126819 | B55: ASOCIACION DE PRODUCTORES AGROPECUARIOS RIO MAYO SHANAO | C55: SAN MARTIN | D55: CACAO | G55: NO | H55: nan | I55: nan | J55: ACTIVO | K55: nan | L55: 0 | M55: =IF(E55>0,ROUND(L55/E55*100,1),0) | N55: PENDIENTE | O55: =IF(H55="SI",1,0)*0.6+IF(I55="SI",1,0)*0.4 | P55: PENDIENTE | S55: =IFERROR(SCORECARDS!C53,"—") | T55: =IF(ISTEXT(S55),S55,IF(S55<34,"🔴 Crítico",IF(S55<67,"🟡 Vulnerable","🟢 Preparado"))) | W55: 0 | X55: 0 | Y55: 0 | Z55: 0 | AA55: 0 | AB55: 0 | AC55: 0 | AD55: 0 | AE55: 0 | AF55: 0 | AG55: 0 | AH55: 0 | AI55: 0 | AJ55: 0 | AK55: 0 | AL55: 0 | AM55: 0 | AN55: 0 | AO55: =IFERROR(AVERAGE(AA55,AB55,AC55,AD55,AE55,AF55,AG55,AH55,AI55,AJ55,AK55,AL55,AM55,AN55),"N/A") | AP55: =IFERROR(AVERAGE(W55,X55,Y55,Z55)/2,"N/A")
A56: 20494145791 | B56: ASOCIACION ECOLOGICA Y DE PRODUCTORES AGROPECUARIOS SAN JOSE | C56: LORETO | D56: CACAO | G56: NO | H56: nan | I56: nan | J56: ACTIVO | K56: nan | L56: 0 | M56: =IF(E56>0,ROUND(L56/E56*100,1),0) | N56: PENDIENTE | O56: =IF(H56="SI",1,0)*0.6+IF(I56="SI",1,0)*0.4 | P56: PENDIENTE | S56: =IFERROR(SCORECARDS!C54,"—") | T56: =IF(ISTEXT(S56),S56,IF(S56<34,"🔴 Crítico",IF(S56<67,"🟡 Vulnerable","🟢 Preparado"))) | W56: 0 | X56: 0 | Y56: 0 | Z56: 0 | AA56: 0 | AB56: 0 | AC56: 0 | AD56: 0 | AE56: 0 | AF56: 0 | AG56: 0 | AH56: 0 | AI56: 0 | AJ56: 0 | AK56: 0 | AL56: 0 | AM56: 0 | AN56: 0 | AO56: =IFERROR(AVERAGE(AA56,AB56,AC56,AD56,AE56,AF56,AG56,AH56,AI56,AJ56,AK56,AL56,AM56,AN56),"N/A") | AP56: =IFERROR(AVERAGE(W56,X56,Y56,Z56)/2,"N/A")
A57: 20494699690 | B57: ASOCIACION DE PRODUCTORES DE CACAO ECOLOGICO DE KIMBIRI - AP | C57: CUSCO | D57: CACAO | G57: NO | H57: nan | I57: nan | J57: ACTIVO | K57: nan | L57: 0 | M57: =IF(E57>0,ROUND(L57/E57*100,1),0) | N57: PENDIENTE | O57: =IF(H57="SI",1,0)*0.6+IF(I57="SI",1,0)*0.4 | P57: PENDIENTE | S57: =IFERROR(SCORECARDS!C55,"—") | T57: =IF(ISTEXT(S57),S57,IF(S57<34,"🔴 Crítico",IF(S57<67,"🟡 Vulnerable","🟢 Preparado"))) | W57: 0 | X57: 0 | Y57: 0 | Z57: 0 | AA57: 0 | AB57: 0 | AC57: 0 | AD57: 0 | AE57: 0 | AF57: 0 | AG57: 0 | AH57: 0 | AI57: 0 | AJ57: 0 | AK57: 0 | AL57: 0 | AM57: 0 | AN57: 0 | AO57: =IFERROR(AVERAGE(AA57,AB57,AC57,AD57,AE57,AF57,AG57,AH57,AI57,AJ57,AK57,AL57,AM57,AN57),"N/A") | AP57: =IFERROR(AVERAGE(W57,X57,Y57,Z57)/2,"N/A")
A58: 20525969551 | B58: COOPERATIVA AGRARIA DE PRODUCTORES DE BANANO, CACAO ORGANICO | C58: PIURA | D58: CACAO | E58: 105840 | F58: 7 | G58: SI | H58: nan | I58: nan | J58: ACTIVO | K58: nan | L58: 52920 | M58: =IF(E58>0,ROUND(L58/E58*100,1),0) | N58: PENDIENTE | O58: =IF(H58="SI",1,0)*0.6+IF(I58="SI",1,0)*0.4 | P58: PENDIENTE | S58: =IFERROR(SCORECARDS!C56,"—") | T58: =IF(ISTEXT(S58),S58,IF(S58<34,"🔴 Crítico",IF(S58<67,"🟡 Vulnerable","🟢 Preparado"))) | U58: 1 | V58: Sin hallazgos OSCE / OEFA | W58: 0 | X58: 0 | Y58: 0 | Z58: 0 | AA58: 0 | AB58: 0 | AC58: 0 | AD58: 0 | AE58: 0 | AF58: 0 | AG58: 0 | AH58: 0 | AI58: 0 | AJ58: 0 | AK58: 0 | AL58: 0 | AM58: 0 | AN58: 0 | AO58: =IFERROR(AVERAGE(AA58,AB58,AC58,AD58,AE58,AF58,AG58,AH58,AI58,AJ58,AK58,AL58,AM58,AN58),"N/A") | AP58: =IFERROR(AVERAGE(W58,X58,Y58,Z58)/2,"N/A")
A59: 20526514689 | B59: ASOCIACION DE PRODUCTORES AGROPECUARIOS ARTESANALES E INDUST | C59: PIURA | D59: CACAO | G59: NO | H59: nan | I59: nan | J59: BAJA DE OFICIO | K59: nan | L59: 0 | M59: =IF(E59>0,ROUND(L59/E59*100,1),0) | N59: PENDIENTE | O59: =IF(H59="SI",1,0)*0.6+IF(I59="SI",1,0)*0.4 | P59: PENDIENTE | S59: =IFERROR(SCORECARDS!C57,"—") | T59: =IF(ISTEXT(S59),S59,IF(S59<34,"🔴 Crítico",IF(S59<67,"🟡 Vulnerable","🟢 Preparado"))) | W59: 0 | X59: 0 | Y59: 0 | Z59: 0 | AA59: 0 | AB59: 0 | AC59: 0 | AD59: 0 | AE59: 0 | AF59: 0 | AG59: 0 | AH59: 0 | AI59: 0 | AJ59: 0 | AK59: 0 | AL59: 0 | AM59: 0 | AN59: 0 | AO59: =IFERROR(AVERAGE(AA59,AB59,AC59,AD59,AE59,AF59,AG59,AH59,AI59,AJ59,AK59,AL59,AM59,AN59),"N/A") | AP59: =IFERROR(AVERAGE(W59,X59,Y59,Z59)/2,"N/A")
A60: 20527565376 | B60: COOPERATIVA AGRARIA CAFETALERA VALLE DE INCAHUASI | C60: APURIMAC | D60: CAFÉ | E60: 10746931 | F60: 59 | G60: SI | H60: nan | I60: nan | J60: ACTIVO | K60: nan | L60: 5373465.5 | M60: =IF(E60>0,ROUND(L60/E60*100,1),0) | N60: PENDIENTE | O60: =IF(H60="SI",1,0)*0.6+IF(I60="SI",1,0)*0.4 | P60: PENDIENTE | S60: =IFERROR(SCORECARDS!C58,"—") | T60: =IF(ISTEXT(S60),S60,IF(S60<34,"🔴 Crítico",IF(S60<67,"🟡 Vulnerable","🟢 Preparado"))) | U60: 1 | V60: Sin hallazgos OSCE / OEFA | W60: 1 | X60: 0 | Y60: 0 | Z60: 0 | AA60: 0 | AB60: 0 | AC60: 0 | AD60: 0 | AE60: 0 | AF60: 0 | AG60: 0 | AH60: 0 | AI60: 0 | AJ60: 0 | AK60: 0 | AL60: 0 | AM60: 0 | AN60: 0 | AO60: =IFERROR(AVERAGE(AA60,AB60,AC60,AD60,AE60,AF60,AG60,AH60,AI60,AJ60,AK60,AL60,AM60,AN60),"N/A") | AP60: =IFERROR(AVERAGE(W60,X60,Y60,Z60)/2,"N/A")
A61: 20528996214 | B61: COOPERATIVA AGRARIA CAFETALERA MILAGROS - MONZON | C61: HUANUCO | D61: CAFÉ | G61: NO | H61: nan | I61: nan | J61: ACTIVO | K61: nan | L61: 0 | M61: =IF(E61>0,ROUND(L61/E61*100,1),0) | N61: PENDIENTE | O61: =IF(H61="SI",1,0)*0.6+IF(I61="SI",1,0)*0.4 | P61: PENDIENTE | S61: =IFERROR(SCORECARDS!C59,"—") | T61: =IF(ISTEXT(S61),S61,IF(S61<34,"🔴 Crítico",IF(S61<67,"🟡 Vulnerable","🟢 Preparado"))) | W61: 0 | X61: 0 | Y61: 0 | Z61: 0 | AA61: 0 | AB61: 0 | AC61: 0 | AD61: 0 | AE61: 0 | AF61: 0 | AG61: 0 | AH61: 0 | AI61: 0 | AJ61: 0 | AK61: 0 | AL61: 0 | AM61: 0 | AN61: 0 | AO61: =IFERROR(AVERAGE(AA61,AB61,AC61,AD61,AE61,AF61,AG61,AH61,AI61,AJ61,AK61,AL61,AM61,AN61),"N/A") | AP61: =IFERROR(AVERAGE(W61,X61,Y61,Z61)/2,"N/A")
A62: 20529801433 | B62: OPA MARAY-ULLMA SAN LORENZO | C62: PIURA | D62: CAFÉ | G62: NO | H62: nan | I62: nan | J62: BAJA DE OFICIO | K62: nan | L62: 0 | M62: =IF(E62>0,ROUND(L62/E62*100,1),0) | N62: PENDIENTE | O62: =IF(H62="SI",1,0)*0.6+IF(I62="SI",1,0)*0.4 | P62: PENDIENTE | S62: =IFERROR(SCORECARDS!C60,"—") | T62: =IF(ISTEXT(S62),S62,IF(S62<34,"🔴 Crítico",IF(S62<67,"🟡 Vulnerable","🟢 Preparado"))) | W62: 0 | X62: 0 | Y62: 0 | Z62: 0 | AA62: 0 | AB62: 0 | AC62: 0 | AD62: 0 | AE62: 0 | AF62: 0 | AG62: 0 | AH62: 0 | AI62: 0 | AJ62: 0 | AK62: 0 | AL62: 0 | AM62: 0 | AN62: 0 | AO62: =IFERROR(AVERAGE(AA62,AB62,AC62,AD62,AE62,AF62,AG62,AH62,AI62,AJ62,AK62,AL62,AM62,AN62),"N/A") | AP62: =IFERROR(AVERAGE(W62,X62,Y62,Z62)/2,"N/A")
A63: 20529822350 | B63: OPA PAPAYO - LA LAGUNA | C63: PIURA | D63: CAFÉ | G63: NO | H63: nan | I63: nan | J63: BAJA DE OFICIO | K63: nan | L63: 0 | M63: =IF(E63>0,ROUND(L63/E63*100,1),0) | N63: PENDIENTE | O63: =IF(H63="SI",1,0)*0.6+IF(I63="SI",1,0)*0.4 | P63: PENDIENTE | S63: =IFERROR(SCORECARDS!C61,"—") | T63: =IF(ISTEXT(S63),S63,IF(S63<34,"🔴 Crítico",IF(S63<67,"🟡 Vulnerable","🟢 Preparado"))) | W63: 0 | X63: 0 | Y63: 0 | Z63: 0 | AA63: 0 | AB63: 0 | AC63: 0 | AD63: 0 | AE63: 0 | AF63: 0 | AG63: 0 | AH63: 0 | AI63: 0 | AJ63: 0 | AK63: 0 | AL63: 0 | AM63: 0 | AN63: 0 | AO63: =IFERROR(AVERAGE(AA63,AB63,AC63,AD63,AE63,AF63,AG63,AH63,AI63,AJ63,AK63,AL63,AM63,AN63),"N/A") | AP63: =IFERROR(AVERAGE(W63,X63,Y63,Z63)/2,"N/A")
A64: 20531405723 | B64: COOPERATIVA DE SERVICIOS MULTIPLES ADISA NARANJOS | C64: SAN MARTIN | D64: CAFÉ | E64: 0 | G64: NO | H64: nan | I64: nan | J64: ACTIVO | K64: nan | L64: 0 | M64: =IF(E64>0,ROUND(L64/E64*100,1),0) | N64: PENDIENTE | O64: =IF(H64="SI",1,0)*0.6+IF(I64="SI",1,0)*0.4 | P64: PENDIENTE | S64: =IFERROR(SCORECARDS!C62,"—") | T64: =IF(ISTEXT(S64),S64,IF(S64<34,"🔴 Crítico",IF(S64<67,"🟡 Vulnerable","🟢 Preparado"))) | W64: 0 | X64: 0 | Y64: 0 | Z64: 0 | AA64: 0 | AB64: 0 | AC64: 0 | AD64: 0 | AE64: 0 | AF64: 0 | AG64: 0 | AH64: 0 | AI64: 0 | AJ64: 0 | AK64: 0 | AL64: 0 | AM64: 0 | AN64: 0 | AO64: =IFERROR(AVERAGE(AA64,AB64,AC64,AD64,AE64,AF64,AG64,AH64,AI64,AJ64,AK64,AL64,AM64,AN64),"N/A") | AP64: =IFERROR(AVERAGE(W64,X64,Y64,Z64)/2,"N/A")
A65: 20531441797 | B65: COOPERATIVA AGRARIA ALLIMA CACAO LTDA. | C65: SAN MARTIN | D65: CACAO | E65: 1984.05 | F65: 1 | G65: SI | H65: nan | I65: nan | J65: ACTIVO | K65: nan | L65: 0 | M65: =IF(E65>0,ROUND(L65/E65*100,1),0) | N65: PENDIENTE | O65: =IF(H65="SI",1,0)*0.6+IF(I65="SI",1,0)*0.4 | P65: PENDIENTE | S65: =IFERROR(SCORECARDS!C63,"—") | T65: =IF(ISTEXT(S65),S65,IF(S65<34,"🔴 Crítico",IF(S65<67,"🟡 Vulnerable","🟢 Preparado"))) | W65: 0 | X65: 0 | Y65: 0 | Z65: 0 | AA65: 0 | AB65: 0 | AC65: 0 | AD65: 0 | AE65: 0 | AF65: 0 | AG65: 0 | AH65: 0 | AI65: 0 | AJ65: 0 | AK65: 0 | AL65: 0 | AM65: 0 | AN65: 0 | AO65: =IFERROR(AVERAGE(AA65,AB65,AC65,AD65,AE65,AF65,AG65,AH65,AI65,AJ65,AK65,AL65,AM65,AN65),"N/A") | AP65: =IFERROR(AVERAGE(W65,X65,Y65,Z65)/2,"N/A")
A66: 20534524774 | B66: COOPERATIVA AGRARIA TROPICAL ECOLOGICA DE KIMBIRI | C66: CUSCO | D66: CAFÉ | G66: NO | H66: nan | I66: nan | J66: ACTIVO | K66: nan | L66: 0 | M66: =IF(E66>0,ROUND(L66/E66*100,1),0) | N66: PENDIENTE | O66: =IF(H66="SI",1,0)*0.6+IF(I66="SI",1,0)*0.4 | P66: PENDIENTE | S66: =IFERROR(SCORECARDS!C64,"—") | T66: =IF(ISTEXT(S66),S66,IF(S66<34,"🔴 Crítico",IF(S66<67,"🟡 Vulnerable","🟢 Preparado"))) | W66: 0 | X66: 0 | Y66: 0 | Z66: 0 | AA66: 0 | AB66: 0 | AC66: 0 | AD66: 0 | AE66: 0 | AF66: 0 | AG66: 0 | AH66: 0 | AI66: 0 | AJ66: 0 | AK66: 0 | AL66: 0 | AM66: 0 | AN66: 0 | AO66: =IFERROR(AVERAGE(AA66,AB66,AC66,AD66,AE66,AF66,AG66,AH66,AI66,AJ66,AK66,AL66,AM66,AN66),"N/A") | AP66: =IFERROR(AVERAGE(W66,X66,Y66,Z66)/2,"N/A")
A67: 20539205600 | B67: ASOCIACION DE PRODUCTORES Y EXPORTADORES DE CAFE RODRIGUEZ D | C67: AMAZONAS | D67: CAFÉ | G67: NO | H67: nan | I67: nan | J67: ACTIVO | K67: nan | L67: 0 | M67: =IF(E67>0,ROUND(L67/E67*100,1),0) | N67: PENDIENTE | O67: =IF(H67="SI",1,0)*0.6+IF(I67="SI",1,0)*0.4 | P67: PENDIENTE | S67: =IFERROR(SCORECARDS!C65,"—") | T67: =IF(ISTEXT(S67),S67,IF(S67<34,"🔴 Crítico",IF(S67<67,"🟡 Vulnerable","🟢 Preparado"))) | W67: 0 | X67: 0 | Y67: 0 | Z67: 0 | AA67: 0 | AB67: 0 | AC67: 0 | AD67: 0 | AE67: 0 | AF67: 0 | AG67: 0 | AH67: 0 | AI67: 0 | AJ67: 0 | AK67: 0 | AL67: 0 | AM67: 0 | AN67: 0 | AO67: =IFERROR(AVERAGE(AA67,AB67,AC67,AD67,AE67,AF67,AG67,AH67,AI67,AJ67,AK67,AL67,AM67,AN67),"N/A") | AP67: =IFERROR(AVERAGE(W67,X67,Y67,Z67)/2,"N/A")
A68: 20539241665 | B68: ASOCIACION DE PRODUCTORES DE CAFES ORGANICOS Y CAFES ESPECIA | C68: AMAZONAS | D68: CAFÉ | G68: NO | H68: nan | I68: nan | J68: ACTIVO | K68: nan | L68: 0 | M68: =IF(E68>0,ROUND(L68/E68*100,1),0) | N68: PENDIENTE | O68: =IF(H68="SI",1,0)*0.6+IF(I68="SI",1,0)*0.4 | P68: PENDIENTE | S68: =IFERROR(SCORECARDS!C66,"—") | T68: =IF(ISTEXT(S68),S68,IF(S68<34,"🔴 Crítico",IF(S68<67,"🟡 Vulnerable","🟢 Preparado"))) | W68: 0 | X68: 0 | Y68: 0 | Z68: 0 | AA68: 0 | AB68: 0 | AC68: 0 | AD68: 0 | AE68: 0 | AF68: 0 | AG68: 0 | AH68: 0 | AI68: 0 | AJ68: 0 | AK68: 0 | AL68: 0 | AM68: 0 | AN68: 0 | AO68: =IFERROR(AVERAGE(AA68,AB68,AC68,AD68,AE68,AF68,AG68,AH68,AI68,AJ68,AK68,AL68,AM68,AN68),"N/A") | AP68: =IFERROR(AVERAGE(W68,X68,Y68,Z68)/2,"N/A")
A69: 20539280644 | B69: ASOCIACION DE PEQUEÑOS AGRICULTORES PARA LA PRODUCCION ECOLO | C69: LAMBAYEQUE | D69: CAFÉ | G69: NO | H69: nan | I69: nan | J69: BAJA DE OFICIO | K69: nan | L69: 0 | M69: =IF(E69>0,ROUND(L69/E69*100,1),0) | N69: PENDIENTE | O69: =IF(H69="SI",1,0)*0.6+IF(I69="SI",1,0)*0.4 | P69: PENDIENTE | S69: =IFERROR(SCORECARDS!C67,"—") | T69: =IF(ISTEXT(S69),S69,IF(S69<34,"🔴 Crítico",IF(S69<67,"🟡 Vulnerable","🟢 Preparado"))) | W69: 0 | X69: 0 | Y69: 0 | Z69: 0 | AA69: 0 | AB69: 0 | AC69: 0 | AD69: 0 | AE69: 0 | AF69: 0 | AG69: 0 | AH69: 0 | AI69: 0 | AJ69: 0 | AK69: 0 | AL69: 0 | AM69: 0 | AN69: 0 | AO69: =IFERROR(AVERAGE(AA69,AB69,AC69,AD69,AE69,AF69,AG69,AH69,AI69,AJ69,AK69,AL69,AM69,AN69),"N/A") | AP69: =IFERROR(AVERAGE(W69,X69,Y69,Z69)/2,"N/A")
A70: 20542209951 | B70: COOPERATIVA AGRARIA VALLE GRANDE | C70: SAN MARTIN | D70: CAFÉ | E70: 13246409 | F70: 46 | G70: SI | H70: Si | I70: Si | J70: ACTIVO | K70: 1 | L70: 7878141.7 | M70: =IF(E70>0,ROUND(L70/E70*100,1),0) | N70: PENDIENTE | O70: =IF(H70="SI",1,0)*0.6+IF(I70="SI",1,0)*0.4 | P70: PENDIENTE | Q70: 622 | R70: 4031 | S70: =IFERROR(SCORECARDS!C68,"—") | T70: =IF(ISTEXT(S70),S70,IF(S70<34,"🔴 Crítico",IF(S70<67,"🟡 Vulnerable","🟢 Preparado"))) | U70: 1 | V70: Sin hallazgos OSCE / OEFA | W70: 1 | X70: 0 | Y70: 0 | Z70: 0 | AA70: 0 | AB70: 0 | AC70: 0 | AD70: 0 | AE70: 0 | AF70: 0 | AG70: 0 | AH70: 0 | AI70: 0 | AJ70: 0 | AK70: 0 | AL70: 0 | AM70: 0 | AN70: 0 | AO70: =IFERROR(AVERAGE(AA70,AB70,AC70,AD70,AE70,AF70,AG70,AH70,AI70,AJ70,AK70,AL70,AM70,AN70),"N/A") | AP70: =IFERROR(AVERAGE(W70,X70,Y70,Z70)/2,"N/A")
A71: 20542251990 | B71: ASOCIACION DE MUJERES EMPRENDEDORAS DE NUEVO PROGRESO | C71: SAN MARTIN | D71: CACAO | G71: NO | H71: nan | I71: nan | J71: ACTIVO | K71: nan | L71: 0 | M71: =IF(E71>0,ROUND(L71/E71*100,1),0) | N71: PENDIENTE | O71: =IF(H71="SI",1,0)*0.6+IF(I71="SI",1,0)*0.4 | P71: PENDIENTE | S71: =IFERROR(SCORECARDS!C69,"—") | T71: =IF(ISTEXT(S71),S71,IF(S71<34,"🔴 Crítico",IF(S71<67,"🟡 Vulnerable","🟢 Preparado"))) | W71: 0 | X71: 0 | Y71: 0 | Z71: 0 | AA71: 0 | AB71: 0 | AC71: 0 | AD71: 0 | AE71: 0 | AF71: 0 | AG71: 0 | AH71: 0 | AI71: 0 | AJ71: 0 | AK71: 0 | AL71: 0 | AM71: 0 | AN71: 0 | AO71: =IFERROR(AVERAGE(AA71,AB71,AC71,AD71,AE71,AF71,AG71,AH71,AI71,AJ71,AK71,AL71,AM71,AN71),"N/A") | AP71: =IFERROR(AVERAGE(W71,X71,Y71,Z71)/2,"N/A")
A72: 20542257416 | B72: EMPRESA INDUSTRIAL ORO VERDE SOCIEDAD ANONIMA CERRADA | C72: SAN MARTIN | D72: CACAO | E72: 2826075 | F72: 12 | G72: SI | H72: nan | I72: nan | J72: ACTIVO | K72: nan | L72: 1413037.5 | M72: =IF(E72>0,ROUND(L72/E72*100,1),0) | N72: PENDIENTE | O72: =IF(H72="SI",1,0)*0.6+IF(I72="SI",1,0)*0.4 | P72: PENDIENTE | S72: =IFERROR(SCORECARDS!C70,"—") | T72: =IF(ISTEXT(S72),S72,IF(S72<34,"🔴 Crítico",IF(S72<67,"🟡 Vulnerable","🟢 Preparado"))) | U72: 1 | V72: Sin hallazgos OSCE / OEFA | W72: 1 | X72: 0 | Y72: 0 | Z72: 0 | AA72: 0 | AB72: 0 | AC72: 0 | AD72: 0 | AE72: 0 | AF72: 0 | AG72: 0 | AH72: 0 | AI72: 0 | AJ72: 0 | AK72: 0 | AL72: 0 | AM72: 0 | AN72: 0 | AO72: =IFERROR(AVERAGE(AA72,AB72,AC72,AD72,AE72,AF72,AG72,AH72,AI72,AJ72,AK72,AL72,AM72,AN72),"N/A") | AP72: =IFERROR(AVERAGE(W72,X72,Y72,Z72)/2,"N/A")
A73: 20542264544 | B73: COOPERATIVA AGRARIA VALLE DEL BIAVO LTDA | C73: SAN MARTIN | D73: CAFÉ | E73: 1187600.5 | F73: 6 | G73: SI | H73: PE- | I73: FLO | J73: ACTIVO | K73: 1 | L73: 1187600.5 | M73: =IF(E73>0,ROUND(L73/E73*100,1),0) | N73: PENDIENTE | O73: =IF(H73="SI",1,0)*0.6+IF(I73="SI",1,0)*0.4 | P73: PENDIENTE | Q73: 416 | R73: 1248 | S73: =IFERROR(SCORECARDS!C71,"—") | T73: =IF(ISTEXT(S73),S73,IF(S73<34,"🔴 Crítico",IF(S73<67,"🟡 Vulnerable","🟢 Preparado"))) | U73: 1 | V73: Sin hallazgos OSCE / OEFA | W73: 1 | X73: 0 | Y73: 0 | Z73: 0 | AA73: 0 | AB73: 0 | AC73: 0 | AD73: 0 | AE73: 0 | AF73: 0 | AG73: 0 | AH73: 0 | AI73: 0 | AJ73: 0 | AK73: 0 | AL73: 0 | AM73: 0 | AN73: 0 | AO73: =IFERROR(AVERAGE(AA73,AB73,AC73,AD73,AE73,AF73,AG73,AH73,AI73,AJ73,AK73,AL73,AM73,AN73),"N/A") | AP73: =IFERROR(AVERAGE(W73,X73,Y73,Z73)/2,"N/A")
A74: 20542289024 | B74: CUENCAS DEL HUALLAGA ASOCIACION DE PRODUCTORES AGROPECUARIOS | C74: SAN MARTIN | D74: CACAO | E74: 24285432 | F74: 111 | G74: SI | H74: nan | I74: nan | J74: ACTIVO | K74: nan | L74: 12142716 | M74: =IF(E74>0,ROUND(L74/E74*100,1),0) | N74: PENDIENTE | O74: =IF(H74="SI",1,0)*0.6+IF(I74="SI",1,0)*0.4 | P74: PENDIENTE | S74: =IFERROR(SCORECARDS!C72,"—") | T74: =IF(ISTEXT(S74),S74,IF(S74<34,"🔴 Crítico",IF(S74<67,"🟡 Vulnerable","🟢 Preparado"))) | U74: 1 | V74: Sin hallazgos OSCE / OEFA | W74: 1 | X74: 0 | Y74: 0 | Z74: 0 | AA74: 0 | AB74: 0 | AC74: 0 | AD74: 0 | AE74: 0 | AF74: 0 | AG74: 0 | AH74: 0 | AI74: 0 | AJ74: 0 | AK74: 0 | AL74: 0 | AM74: 0 | AN74: 0 | AO74: =IFERROR(AVERAGE(AA74,AB74,AC74,AD74,AE74,AF74,AG74,AH74,AI74,AJ74,AK74,AL74,AM74,AN74),"N/A") | AP74: =IFERROR(AVERAGE(W74,X74,Y74,Z74)/2,"N/A")
A75: 20542299330 | B75: ASOCIACION DE PRODUCTORES AGROPECUARIOS DE SHUCUSHYACU FLOR | C75: LORETO | D75: CACAO | G75: NO | H75: nan | I75: nan | J75: ACTIVO | K75: nan | L75: 0 | M75: =IF(E75>0,ROUND(L75/E75*100,1),0) | N75: PENDIENTE | O75: =IF(H75="SI",1,0)*0.6+IF(I75="SI",1,0)*0.4 | P75: PENDIENTE | S75: =IFERROR(SCORECARDS!C73,"—") | T75: =IF(ISTEXT(S75),S75,IF(S75<34,"🔴 Crítico",IF(S75<67,"🟡 Vulnerable","🟢 Preparado"))) | W75: 0 | X75: 0 | Y75: 0 | Z75: 0 | AA75: 0 | AB75: 0 | AC75: 0 | AD75: 0 | AE75: 0 | AF75: 0 | AG75: 0 | AH75: 0 | AI75: 0 | AJ75: 0 | AK75: 0 | AL75: 0 | AM75: 0 | AN75: 0 | AO75: =IFERROR(AVERAGE(AA75,AB75,AC75,AD75,AE75,AF75,AG75,AH75,AI75,AJ75,AK75,AL75,AM75,AN75),"N/A") | AP75: =IFERROR(AVERAGE(W75,X75,Y75,Z75)/2,"N/A")
A76: 20542311569 | B76: COOPERATIVA AGRARIA ACHUAR SHAKAIM LTDA | C76: LORETO | D76: CACAO | G76: NO | H76: nan | I76: nan | J76: ACTIVO | K76: nan | L76: 0 | M76: =IF(E76>0,ROUND(L76/E76*100,1),0) | N76: PENDIENTE | O76: =IF(H76="SI",1,0)*0.6+IF(I76="SI",1,0)*0.4 | P76: PENDIENTE | S76: =IFERROR(SCORECARDS!C74,"—") | T76: =IF(ISTEXT(S76),S76,IF(S76<34,"🔴 Crítico",IF(S76<67,"🟡 Vulnerable","🟢 Preparado"))) | W76: 0 | X76: 0 | Y76: 0 | Z76: 0 | AA76: 0 | AB76: 0 | AC76: 0 | AD76: 0 | AE76: 0 | AF76: 0 | AG76: 0 | AH76: 0 | AI76: 0 | AJ76: 0 | AK76: 0 | AL76: 0 | AM76: 0 | AN76: 0 | AO76: =IFERROR(AVERAGE(AA76,AB76,AC76,AD76,AE76,AF76,AG76,AH76,AI76,AJ76,AK76,AL76,AM76,AN76),"N/A") | AP76: =IFERROR(AVERAGE(W76,X76,Y76,Z76)/2,"N/A")
A77: 20542380455 | B77: COOPERATIVA AGRARIA ECOFOREST | C77: CAJAMARCA | D77: CAFÉ | E77: 16891006 | F77: 81 | G77: SI | H77: nan | I77: nan | J77: ACTIVO | K77: nan | L77: 8445503.2 | M77: =IF(E77>0,ROUND(L77/E77*100,1),0) | N77: PENDIENTE | O77: =IF(H77="SI",1,0)*0.6+IF(I77="SI",1,0)*0.4 | P77: PENDIENTE | S77: =IFERROR(SCORECARDS!C75,"—") | T77: =IF(ISTEXT(S77),S77,IF(S77<34,"🔴 Crítico",IF(S77<67,"🟡 Vulnerable","🟢 Preparado"))) | U77: 1 | V77: Sin hallazgos OSCE / OEFA | W77: 1 | X77: 0 | Y77: 0 | Z77: 0 | AA77: 0 | AB77: 0 | AC77: 0 | AD77: 0 | AE77: 0 | AF77: 0 | AG77: 0 | AH77: 0 | AI77: 0 | AJ77: 0 | AK77: 0 | AL77: 0 | AM77: 0 | AN77: 0 | AO77: =IFERROR(AVERAGE(AA77,AB77,AC77,AD77,AE77,AF77,AG77,AH77,AI77,AJ77,AK77,AL77,AM77,AN77),"N/A") | AP77: =IFERROR(AVERAGE(W77,X77,Y77,Z77)/2,"N/A")
A78: 20542482886 | B78: COOPERATIVA AGROINDUSTRIAL APCCA | C78: HUANUCO | D78: CACAO | G78: NO | H78: nan | I78: nan | J78: SUSPENSION TEMPORAL | K78: nan | L78: 0 | M78: =IF(E78>0,ROUND(L78/E78*100,1),0) | N78: PENDIENTE | O78: =IF(H78="SI",1,0)*0.6+IF(I78="SI",1,0)*0.4 | P78: PENDIENTE | S78: =IFERROR(SCORECARDS!C76,"—") | T78: =IF(ISTEXT(S78),S78,IF(S78<34,"🔴 Crítico",IF(S78<67,"🟡 Vulnerable","🟢 Preparado"))) | W78: 0 | X78: 0 | Y78: 0 | Z78: 0 | AA78: 0 | AB78: 0 | AC78: 0 | AD78: 0 | AE78: 0 | AF78: 0 | AG78: 0 | AH78: 0 | AI78: 0 | AJ78: 0 | AK78: 0 | AL78: 0 | AM78: 0 | AN78: 0 | AO78: =IFERROR(AVERAGE(AA78,AB78,AC78,AD78,AE78,AF78,AG78,AH78,AI78,AJ78,AK78,AL78,AM78,AN78),"N/A") | AP78: =IFERROR(AVERAGE(W78,X78,Y78,Z78)/2,"N/A")
A79: 20542825163 | B79: COOPERATIVA AGRARIA CACAO FINO AGROBOSQUE | C79: MADRE DE DIOS | D79: CACAO | E79: 0 | G79: NO | H79: nan | I79: nan | J79: ACTIVO | K79: nan | L79: 0 | M79: =IF(E79>0,ROUND(L79/E79*100,1),0) | N79: PENDIENTE | O79: =IF(H79="SI",1,0)*0.6+IF(I79="SI",1,0)*0.4 | P79: PENDIENTE | S79: =IFERROR(SCORECARDS!C77,"—") | T79: =IF(ISTEXT(S79),S79,IF(S79<34,"🔴 Crítico",IF(S79<67,"🟡 Vulnerable","🟢 Preparado"))) | W79: 0 | X79: 0 | Y79: 0 | Z79: 0 | AA79: 0 | AB79: 0 | AC79: 0 | AD79: 0 | AE79: 0 | AF79: 0 | AG79: 0 | AH79: 0 | AI79: 0 | AJ79: 0 | AK79: 0 | AL79: 0 | AM79: 0 | AN79: 0 | AO79: =IFERROR(AVERAGE(AA79,AB79,AC79,AD79,AE79,AF79,AG79,AH79,AI79,AJ79,AK79,AL79,AM79,AN79),"N/A") | AP79: =IFERROR(AVERAGE(W79,X79,Y79,Z79)/2,"N/A")
A80: 20561140091 | B80: COOPERATIVA AGRARIA ECOLOGICA CAFETALERA DE LONYA GRANDE | C80: AMAZONAS | D80: CAFÉ | E80: 0 | G80: NO | H80: SI( | I80: NO | J80: SUSPENSION TEMPORAL | K80: 0.5 | L80: 0 | M80: =IF(E80>0,ROUND(L80/E80*100,1),0) | N80: PENDIENTE | O80: =IF(H80="SI",1,0)*0.6+IF(I80="SI",1,0)*0.4 | P80: PENDIENTE | Q80: 351 | R80: 1045.6 | S80: =IFERROR(SCORECARDS!C78,"—") | T80: =IF(ISTEXT(S80),S80,IF(S80<34,"🔴 Crítico",IF(S80<67,"🟡 Vulnerable","🟢 Preparado"))) | W80: 1 | X80: 0 | Y80: 0 | Z80: 0 | AA80: 0 | AB80: 0 | AC80: 0 | AD80: 0 | AE80: 0 | AF80: 0 | AG80: 0 | AH80: 0 | AI80: 0 | AJ80: 0 | AK80: 0 | AL80: 0 | AM80: 0 | AN80: 0 | AO80: =IFERROR(AVERAGE(AA80,AB80,AC80,AD80,AE80,AF80,AG80,AH80,AI80,AJ80,AK80,AL80,AM80,AN80),"N/A") | AP80: =IFERROR(AVERAGE(W80,X80,Y80,Z80)/2,"N/A")
A81: 20564032485 | B81: ASOCIACION DE PRODUCTORES ECOLOGICOS DE CACAO MEDIO URUBAMBA | C81: CUSCO | D81: CACAO | E81: 0 | G81: NO | H81: nan | I81: nan | J81: ACTIVO | K81: nan | L81: 0 | M81: =IF(E81>0,ROUND(L81/E81*100,1),0) | N81: PENDIENTE | O81: =IF(H81="SI",1,0)*0.6+IF(I81="SI",1,0)*0.4 | P81: PENDIENTE | S81: =IFERROR(SCORECARDS!C79,"—") | T81: =IF(ISTEXT(S81),S81,IF(S81<34,"🔴 Crítico",IF(S81<67,"🟡 Vulnerable","🟢 Preparado"))) | W81: 0 | X81: 0 | Y81: 0 | Z81: 0 | AA81: 0 | AB81: 0 | AC81: 0 | AD81: 0 | AE81: 0 | AF81: 0 | AG81: 0 | AH81: 0 | AI81: 0 | AJ81: 0 | AK81: 0 | AL81: 0 | AM81: 0 | AN81: 0 | AO81: =IFERROR(AVERAGE(AA81,AB81,AC81,AD81,AE81,AF81,AG81,AH81,AI81,AJ81,AK81,AL81,AM81,AN81),"N/A") | AP81: =IFERROR(AVERAGE(W81,X81,Y81,Z81)/2,"N/A")
A82: 20568071281 | B82: COOPERATIVA AGRARIA CAFETALERA CEPRO YANESHA | C82: PASCO | D82: CAFÉ | E82: 1435723.7 | F82: 10 | G82: SI | H82: nan | I82: nan | J82: ACTIVO | K82: nan | L82: 717861.85 | M82: =IF(E82>0,ROUND(L82/E82*100,1),0) | N82: PENDIENTE | O82: =IF(H82="SI",1,0)*0.6+IF(I82="SI",1,0)*0.4 | P82: PENDIENTE | S82: =IFERROR(SCORECARDS!C80,"—") | T82: =IF(ISTEXT(S82),S82,IF(S82<34,"🔴 Crítico",IF(S82<67,"🟡 Vulnerable","🟢 Preparado"))) | U82: 1 | V82: Sin hallazgos OSCE / OEFA | W82: 1 | X82: 0 | Y82: 0 | Z82: 0 | AA82: 0 | AB82: 0 | AC82: 0 | AD82: 0 | AE82: 0 | AF82: 0 | AG82: 0 | AH82: 0 | AI82: 0 | AJ82: 0 | AK82: 0 | AL82: 0 | AM82: 0 | AN82: 0 | AO82: =IFERROR(AVERAGE(AA82,AB82,AC82,AD82,AE82,AF82,AG82,AH82,AI82,AJ82,AK82,AL82,AM82,AN82),"N/A") | AP82: =IFERROR(AVERAGE(W82,X82,Y82,Z82)/2,"N/A")
A83: 20568080948 | B83: CONSEJO REGULADOR DE LA DENOMINACION DE ORIGEN CAFE VILLA RI | C83: PASCO | D83: CAFÉ | G83: NO | H83: nan | I83: nan | J83: ACTIVO | K83: nan | L83: 0 | M83: =IF(E83>0,ROUND(L83/E83*100,1),0) | N83: PENDIENTE | O83: =IF(H83="SI",1,0)*0.6+IF(I83="SI",1,0)*0.4 | P83: PENDIENTE | S83: =IFERROR(SCORECARDS!C81,"—") | T83: =IF(ISTEXT(S83),S83,IF(S83<34,"🔴 Crítico",IF(S83<67,"🟡 Vulnerable","🟢 Preparado"))) | W83: 0 | X83: 0 | Y83: 0 | Z83: 0 | AA83: 0 | AB83: 0 | AC83: 0 | AD83: 0 | AE83: 0 | AF83: 0 | AG83: 0 | AH83: 0 | AI83: 0 | AJ83: 0 | AK83: 0 | AL83: 0 | AM83: 0 | AN83: 0 | AO83: =IFERROR(AVERAGE(AA83,AB83,AC83,AD83,AE83,AF83,AG83,AH83,AI83,AJ83,AK83,AL83,AM83,AN83),"N/A") | AP83: =IFERROR(AVERAGE(W83,X83,Y83,Z83)/2,"N/A")
A84: 20568190450 | B84: COOPERATIVA AGRARIA KEMITO ENE LTDA. - KEMITO ENE | C84: JUNIN | D84: CACAO | E84: 113466.98 | F84: 10 | G84: SI | H84: nan | I84: nan | J84: ACTIVO | K84: nan | L84: 0 | M84: =IF(E84>0,ROUND(L84/E84*100,1),0) | N84: PENDIENTE | O84: =IF(H84="SI",1,0)*0.6+IF(I84="SI",1,0)*0.4 | P84: PENDIENTE | S84: =IFERROR(SCORECARDS!C82,"—") | T84: =IF(ISTEXT(S84),S84,IF(S84<34,"🔴 Crítico",IF(S84<67,"🟡 Vulnerable","🟢 Preparado"))) | W84: 0 | X84: 0 | Y84: 0 | Z84: 0 | AA84: 0 | AB84: 0 | AC84: 0 | AD84: 0 | AE84: 0 | AF84: 0 | AG84: 0 | AH84: 0 | AI84: 0 | AJ84: 0 | AK84: 0 | AL84: 0 | AM84: 0 | AN84: 0 | AO84: =IFERROR(AVERAGE(AA84,AB84,AC84,AD84,AE84,AF84,AG84,AH84,AI84,AJ84,AK84,AL84,AM84,AN84),"N/A") | AP84: =IFERROR(AVERAGE(W84,X84,Y84,Z84)/2,"N/A")
A85: 20568194951 | B85: ASOCIACION DE PRODUCTORES AGROSOSTENIBLES VILLA ECOLOGICA PE | C85: JUNIN | D85: CAFÉ | E85: 5355025.2 | F85: 27 | G85: SI | H85: nan | I85: nan | J85: ACTIVO | K85: nan | L85: 2677512.6 | M85: =IF(E85>0,ROUND(L85/E85*100,1),0) | N85: PENDIENTE | O85: =IF(H85="SI",1,0)*0.6+IF(I85="SI",1,0)*0.4 | P85: PENDIENTE | S85: =IFERROR(SCORECARDS!C83,"—") | T85: =IF(ISTEXT(S85),S85,IF(S85<34,"🔴 Crítico",IF(S85<67,"🟡 Vulnerable","🟢 Preparado"))) | U85: 1 | V85: Sin hallazgos OSCE / OEFA | W85: 1 | X85: 0 | Y85: 0 | Z85: 0 | AA85: 0 | AB85: 0 | AC85: 0 | AD85: 0 | AE85: 0 | AF85: 0 | AG85: 0 | AH85: 0 | AI85: 0 | AJ85: 0 | AK85: 0 | AL85: 0 | AM85: 0 | AN85: 0 | AO85: =IFERROR(AVERAGE(AA85,AB85,AC85,AD85,AE85,AF85,AG85,AH85,AI85,AJ85,AK85,AL85,AM85,AN85),"N/A") | AP85: =IFERROR(AVERAGE(W85,X85,Y85,Z85)/2,"N/A")
A86: 20568428375 | B86: COOPERATIVA AGRARIA ASHANINKA DEL VALLE PICHIS | C86: PASCO | D86: CACAO | G86: NO | H86: nan | I86: nan | J86: ACTIVO | K86: nan | L86: 0 | M86: =IF(E86>0,ROUND(L86/E86*100,1),0) | N86: PENDIENTE | O86: =IF(H86="SI",1,0)*0.6+IF(I86="SI",1,0)*0.4 | P86: PENDIENTE | S86: =IFERROR(SCORECARDS!C84,"—") | T86: =IF(ISTEXT(S86),S86,IF(S86<34,"🔴 Crítico",IF(S86<67,"🟡 Vulnerable","🟢 Preparado"))) | W86: 0 | X86: 0 | Y86: 0 | Z86: 0 | AA86: 0 | AB86: 0 | AC86: 0 | AD86: 0 | AE86: 0 | AF86: 0 | AG86: 0 | AH86: 0 | AI86: 0 | AJ86: 0 | AK86: 0 | AL86: 0 | AM86: 0 | AN86: 0 | AO86: =IFERROR(AVERAGE(AA86,AB86,AC86,AD86,AE86,AF86,AG86,AH86,AI86,AJ86,AK86,AL86,AM86,AN86),"N/A") | AP86: =IFERROR(AVERAGE(W86,X86,Y86,Z86)/2,"N/A")
A87: 20568549083 | B87: COOPERATIVA AGRARIA INDUSTRIAL APASC SANCORE-PALCAZU LTDA | C87: PASCO | D87: CACAO | G87: NO | H87: nan | I87: nan | J87: ACTIVO | K87: nan | L87: 0 | M87: =IF(E87>0,ROUND(L87/E87*100,1),0) | N87: PENDIENTE | O87: =IF(H87="SI",1,0)*0.6+IF(I87="SI",1,0)*0.4 | P87: PENDIENTE | S87: =IFERROR(SCORECARDS!C85,"—") | T87: =IF(ISTEXT(S87),S87,IF(S87<34,"🔴 Crítico",IF(S87<67,"🟡 Vulnerable","🟢 Preparado"))) | W87: 0 | X87: 0 | Y87: 0 | Z87: 0 | AA87: 0 | AB87: 0 | AC87: 0 | AD87: 0 | AE87: 0 | AF87: 0 | AG87: 0 | AH87: 0 | AI87: 0 | AJ87: 0 | AK87: 0 | AL87: 0 | AM87: 0 | AN87: 0 | AO87: =IFERROR(AVERAGE(AA87,AB87,AC87,AD87,AE87,AF87,AG87,AH87,AI87,AJ87,AK87,AL87,AM87,AN87),"N/A") | AP87: =IFERROR(AVERAGE(W87,X87,Y87,Z87)/2,"N/A")
A88: 20568560133 | B88: COOPERATIVA AGRARIA ECOLOGICO ALTO PALCAZU LAGUNA RAYA | C88: PASCO | D88: CACAO | G88: NO | H88: nan | I88: nan | J88: ACTIVO | K88: nan | L88: 0 | M88: =IF(E88>0,ROUND(L88/E88*100,1),0) | N88: PENDIENTE | O88: =IF(H88="SI",1,0)*0.6+IF(I88="SI",1,0)*0.4 | P88: PENDIENTE | S88: =IFERROR(SCORECARDS!C86,"—") | T88: =IF(ISTEXT(S88),S88,IF(S88<34,"🔴 Crítico",IF(S88<67,"🟡 Vulnerable","🟢 Preparado"))) | W88: 0 | X88: 0 | Y88: 0 | Z88: 0 | AA88: 0 | AB88: 0 | AC88: 0 | AD88: 0 | AE88: 0 | AF88: 0 | AG88: 0 | AH88: 0 | AI88: 0 | AJ88: 0 | AK88: 0 | AL88: 0 | AM88: 0 | AN88: 0 | AO88: =IFERROR(AVERAGE(AA88,AB88,AC88,AD88,AE88,AF88,AG88,AH88,AI88,AJ88,AK88,AL88,AM88,AN88),"N/A") | AP88: =IFERROR(AVERAGE(W88,X88,Y88,Z88)/2,"N/A")
A89: 20568567731 | B89: COOPERATIVA AGRARIA VILLA RICA GOLDEN COFFEE LTDA. | C89: PASCO | D89: CAFÉ | E89: 0 | G89: NO | H89: nan | I89: nan | J89: ACTIVO | K89: nan | L89: 0 | M89: =IF(E89>0,ROUND(L89/E89*100,1),0) | N89: PENDIENTE | O89: =IF(H89="SI",1,0)*0.6+IF(I89="SI",1,0)*0.4 | P89: PENDIENTE | S89: =IFERROR(SCORECARDS!C87,"—") | T89: =IF(ISTEXT(S89),S89,IF(S89<34,"🔴 Crítico",IF(S89<67,"🟡 Vulnerable","🟢 Preparado"))) | W89: 0 | X89: 0 | Y89: 0 | Z89: 0 | AA89: 0 | AB89: 0 | AC89: 0 | AD89: 0 | AE89: 0 | AF89: 0 | AG89: 0 | AH89: 0 | AI89: 0 | AJ89: 0 | AK89: 0 | AL89: 0 | AM89: 0 | AN89: 0 | AO89: =IFERROR(AVERAGE(AA89,AB89,AC89,AD89,AE89,AF89,AG89,AH89,AI89,AJ89,AK89,AL89,AM89,AN89),"N/A") | AP89: =IFERROR(AVERAGE(W89,X89,Y89,Z89)/2,"N/A")
A90: 20568609833 | B90: ASOCIACION DE MUJERES PRODUCTORAS ARTESANAS CACAO JENTARI - | C90: JUNIN | D90: CACAO | G90: NO | H90: nan | I90: nan | J90: BAJA DE OFICIO | K90: nan | L90: 0 | M90: =IF(E90>0,ROUND(L90/E90*100,1),0) | N90: PENDIENTE | O90: =IF(H90="SI",1,0)*0.6+IF(I90="SI",1,0)*0.4 | P90: PENDIENTE | S90: =IFERROR(SCORECARDS!C88,"—") | T90: =IF(ISTEXT(S90),S90,IF(S90<34,"🔴 Crítico",IF(S90<67,"🟡 Vulnerable","🟢 Preparado"))) | W90: 0 | X90: 0 | Y90: 0 | Z90: 0 | AA90: 0 | AB90: 0 | AC90: 0 | AD90: 0 | AE90: 0 | AF90: 0 | AG90: 0 | AH90: 0 | AI90: 0 | AJ90: 0 | AK90: 0 | AL90: 0 | AM90: 0 | AN90: 0 | AO90: =IFERROR(AVERAGE(AA90,AB90,AC90,AD90,AE90,AF90,AG90,AH90,AI90,AJ90,AK90,AL90,AM90,AN90),"N/A") | AP90: =IFERROR(AVERAGE(W90,X90,Y90,Z90)/2,"N/A")
A91: 20568962282 | B91: ASOCIACIÓN DE PRODUCTORES CENTRO COFFEE | C91: JUNIN | D91: CAFÉ | E91: 0 | G91: NO | H91: nan | I91: nan | J91: SUSPENSION TEMPORAL | K91: nan | L91: 0 | M91: =IF(E91>0,ROUND(L91/E91*100,1),0) | N91: PENDIENTE | O91: =IF(H91="SI",1,0)*0.6+IF(I91="SI",1,0)*0.4 | P91: PENDIENTE | S91: =IFERROR(SCORECARDS!C89,"—") | T91: =IF(ISTEXT(S91),S91,IF(S91<34,"🔴 Crítico",IF(S91<67,"🟡 Vulnerable","🟢 Preparado"))) | W91: 0 | X91: 0 | Y91: 0 | Z91: 0 | AA91: 0 | AB91: 0 | AC91: 0 | AD91: 0 | AE91: 0 | AF91: 0 | AG91: 0 | AH91: 0 | AI91: 0 | AJ91: 0 | AK91: 0 | AL91: 0 | AM91: 0 | AN91: 0 | AO91: =IFERROR(AVERAGE(AA91,AB91,AC91,AD91,AE91,AF91,AG91,AH91,AI91,AJ91,AK91,AL91,AM91,AN91),"N/A") | AP91: =IFERROR(AVERAGE(W91,X91,Y91,Z91)/2,"N/A")
A92: 20570706927 | B92: COOPERATIVA AGRARIA RUTAS DEL INCA | C92: CAJAMARCA | D92: CAFÉ | E92: 9585341.8 | F92: 58 | G92: SI | H92: nan | I92: nan | J92: ACTIVO | K92: nan | L92: 4792670.9 | M92: =IF(E92>0,ROUND(L92/E92*100,1),0) | N92: PENDIENTE | O92: =IF(H92="SI",1,0)*0.6+IF(I92="SI",1,0)*0.4 | P92: PENDIENTE | S92: =IFERROR(SCORECARDS!C90,"—") | T92: =IF(ISTEXT(S92),S92,IF(S92<34,"🔴 Crítico",IF(S92<67,"🟡 Vulnerable","🟢 Preparado"))) | U92: 1 | V92: Sin hallazgos OSCE / OEFA | W92: 1 | X92: 0 | Y92: 0 | Z92: 0 | AA92: 0 | AB92: 0 | AC92: 0 | AD92: 0 | AE92: 0 | AF92: 0 | AG92: 0 | AH92: 0 | AI92: 0 | AJ92: 0 | AK92: 0 | AL92: 0 | AM92: 0 | AN92: 0 | AO92: =IFERROR(AVERAGE(AA92,AB92,AC92,AD92,AE92,AF92,AG92,AH92,AI92,AJ92,AK92,AL92,AM92,AN92),"N/A") | AP92: =IFERROR(AVERAGE(W92,X92,Y92,Z92)/2,"N/A")
A93: 20572111131 | B93: ASOCIACION DE MUJERES ORGANIZADAS CHOCO WARMIS | C93: SAN MARTIN | D93: nan | G93: NO | H93: nan | I93: nan | J93: ACTIVO | K93: nan | L93: 0 | M93: =IF(E93>0,ROUND(L93/E93*100,1),0) | N93: PENDIENTE | O93: =IF(H93="SI",1,0)*0.6+IF(I93="SI",1,0)*0.4 | P93: PENDIENTE | S93: =IFERROR(SCORECARDS!C91,"—") | T93: =IF(ISTEXT(S93),S93,IF(S93<34,"🔴 Crítico",IF(S93<67,"🟡 Vulnerable","🟢 Preparado"))) | W93: 0 | X93: 0 | Y93: 0 | Z93: 0 | AA93: 0 | AB93: 0 | AC93: 0 | AD93: 0 | AE93: 0 | AF93: 0 | AG93: 0 | AH93: 0 | AI93: 0 | AJ93: 0 | AK93: 0 | AL93: 0 | AM93: 0 | AN93: 0 | AO93: =IFERROR(AVERAGE(AA93,AB93,AC93,AD93,AE93,AF93,AG93,AH93,AI93,AJ93,AK93,AL93,AM93,AN93),"N/A") | AP93: =IFERROR(AVERAGE(W93,X93,Y93,Z93)/2,"N/A")
A94: 20572190251 | B94: CENTRAL DE COOPERATIVAS AGRARIAS CACAO AROMA DE TOCACHE LTDA | C94: SAN MARTIN | D94: nan | E94: 3777944.8 | F94: 14 | G94: SI | H94: nan | I94: nan | J94: ACTIVO | K94: nan | L94: 1888972.4 | M94: =IF(E94>0,ROUND(L94/E94*100,1),0) | N94: PENDIENTE | O94: =IF(H94="SI",1,0)*0.6+IF(I94="SI",1,0)*0.4 | P94: PENDIENTE | S94: =IFERROR(SCORECARDS!C92,"—") | T94: =IF(ISTEXT(S94),S94,IF(S94<34,"🔴 Crítico",IF(S94<67,"🟡 Vulnerable","🟢 Preparado"))) | U94: 1 | V94: Sin hallazgos OSCE / OEFA | W94: 1 | X94: 0 | Y94: 0 | Z94: 0 | AA94: 0 | AB94: 0 | AC94: 0 | AD94: 0 | AE94: 0 | AF94: 0 | AG94: 0 | AH94: 0 | AI94: 0 | AJ94: 0 | AK94: 0 | AL94: 0 | AM94: 0 | AN94: 0 | AO94: =IFERROR(AVERAGE(AA94,AB94,AC94,AD94,AE94,AF94,AG94,AH94,AI94,AJ94,AK94,AL94,AM94,AN94),"N/A") | AP94: =IFERROR(AVERAGE(W94,X94,Y94,Z94)/2,"N/A")
A95: 20573049102 | B95: COOPERATIVA AGRARIA CACAOTERA PUERTO INCA | C95: HUANUCO | D95: CACAO | G95: NO | H95: nan | I95: nan | J95: ACTIVO | K95: nan | L95: 0 | M95: =IF(E95>0,ROUND(L95/E95*100,1),0) | N95: PENDIENTE | O95: =IF(H95="SI",1,0)*0.6+IF(I95="SI",1,0)*0.4 | P95: PENDIENTE | S95: =IFERROR(SCORECARDS!C93,"—") | T95: =IF(ISTEXT(S95),S95,IF(S95<34,"🔴 Crítico",IF(S95<67,"🟡 Vulnerable","🟢 Preparado"))) | W95: 0 | X95: 0 | Y95: 0 | Z95: 0 | AA95: 0 | AB95: 0 | AC95: 0 | AD95: 0 | AE95: 0 | AF95: 0 | AG95: 0 | AH95: 0 | AI95: 0 | AJ95: 0 | AK95: 0 | AL95: 0 | AM95: 0 | AN95: 0 | AO95: =IFERROR(AVERAGE(AA95,AB95,AC95,AD95,AE95,AF95,AG95,AH95,AI95,AJ95,AK95,AL95,AM95,AN95),"N/A") | AP95: =IFERROR(AVERAGE(W95,X95,Y95,Z95)/2,"N/A")
A96: 20573057385 | B96: COOPERATIVA AGRARIA PARAISO | C96: HUANUCO | D96: CACAO | E96: 0 | G96: NO | H96: nan | I96: nan | J96: ACTIVO | K96: nan | L96: 0 | M96: =IF(E96>0,ROUND(L96/E96*100,1),0) | N96: PENDIENTE | O96: =IF(H96="SI",1,0)*0.6+IF(I96="SI",1,0)*0.4 | P96: PENDIENTE | S96: =IFERROR(SCORECARDS!C94,"—") | T96: =IF(ISTEXT(S96),S96,IF(S96<34,"🔴 Crítico",IF(S96<67,"🟡 Vulnerable","🟢 Preparado"))) | W96: 0 | X96: 0 | Y96: 0 | Z96: 0 | AA96: 0 | AB96: 0 | AC96: 0 | AD96: 0 | AE96: 0 | AF96: 0 | AG96: 0 | AH96: 0 | AI96: 0 | AJ96: 0 | AK96: 0 | AL96: 0 | AM96: 0 | AN96: 0 | AO96: =IFERROR(AVERAGE(AA96,AB96,AC96,AD96,AE96,AF96,AG96,AH96,AI96,AJ96,AK96,AL96,AM96,AN96),"N/A") | AP96: =IFERROR(AVERAGE(W96,X96,Y96,Z96)/2,"N/A")
A97: 20573138202 | B97: ASOCIACION DE PRODUCTORES AGROPECUARIOS Y FORESTALES EL ALVA | C97: HUANUCO | D97: CACAO | G97: NO | H97: nan | I97: nan | J97: BAJA DE OFICIO | K97: nan | L97: 0 | M97: =IF(E97>0,ROUND(L97/E97*100,1),0) | N97: PENDIENTE | O97: =IF(H97="SI",1,0)*0.6+IF(I97="SI",1,0)*0.4 | P97: PENDIENTE | S97: =IFERROR(SCORECARDS!C95,"—") | T97: =IF(ISTEXT(S97),S97,IF(S97<34,"🔴 Crítico",IF(S97<67,"🟡 Vulnerable","🟢 Preparado"))) | W97: 0 | X97: 0 | Y97: 0 | Z97: 0 | AA97: 0 | AB97: 0 | AC97: 0 | AD97: 0 | AE97: 0 | AF97: 0 | AG97: 0 | AH97: 0 | AI97: 0 | AJ97: 0 | AK97: 0 | AL97: 0 | AM97: 0 | AN97: 0 | AO97: =IFERROR(AVERAGE(AA97,AB97,AC97,AD97,AE97,AF97,AG97,AH97,AI97,AJ97,AK97,AL97,AM97,AN97),"N/A") | AP97: =IFERROR(AVERAGE(W97,X97,Y97,Z97)/2,"N/A")
A98: 20573260008 | B98: COOPERATIVA AGRARIA AUCAYACU | C98: HUANUCO | D98: CACAO | G98: NO | H98: nan | I98: nan | J98: ACTIVO | K98: nan | L98: 0 | M98: =IF(E98>0,ROUND(L98/E98*100,1),0) | N98: PENDIENTE | O98: =IF(H98="SI",1,0)*0.6+IF(I98="SI",1,0)*0.4 | P98: PENDIENTE | S98: =IFERROR(SCORECARDS!C96,"—") | T98: =IF(ISTEXT(S98),S98,IF(S98<34,"🔴 Crítico",IF(S98<67,"🟡 Vulnerable","🟢 Preparado"))) | W98: 0 | X98: 0 | Y98: 0 | Z98: 0 | AA98: 0 | AB98: 0 | AC98: 0 | AD98: 0 | AE98: 0 | AF98: 0 | AG98: 0 | AH98: 0 | AI98: 0 | AJ98: 0 | AK98: 0 | AL98: 0 | AM98: 0 | AN98: 0 | AO98: =IFERROR(AVERAGE(AA98,AB98,AC98,AD98,AE98,AF98,AG98,AH98,AI98,AJ98,AK98,AL98,AM98,AN98),"N/A") | AP98: =IFERROR(AVERAGE(W98,X98,Y98,Z98)/2,"N/A")
A99: 20573344791 | B99: ASOCIACION AGROECOLOGICO HUANGANAPAMPA | C99: HUANUCO | D99: PLÁTANO | G99: NO | H99: nan | I99: nan | J99: BAJA DE OFICIO | K99: nan | L99: 0 | M99: =IF(E99>0,ROUND(L99/E99*100,1),0) | N99: PENDIENTE | O99: =IF(H99="SI",1,0)*0.6+IF(I99="SI",1,0)*0.4 | P99: PENDIENTE | S99: =IFERROR(SCORECARDS!C97,"—") | T99: =IF(ISTEXT(S99),S99,IF(S99<34,"🔴 Crítico",IF(S99<67,"🟡 Vulnerable","🟢 Preparado"))) | W99: 0 | X99: 0 | Y99: 0 | Z99: 0 | AA99: 0 | AB99: 0 | AC99: 0 | AD99: 0 | AE99: 0 | AF99: 0 | AG99: 0 | AH99: 0 | AI99: 0 | AJ99: 0 | AK99: 0 | AL99: 0 | AM99: 0 | AN99: 0 | AO99: =IFERROR(AVERAGE(AA99,AB99,AC99,AD99,AE99,AF99,AG99,AH99,AI99,AJ99,AK99,AL99,AM99,AN99),"N/A") | AP99: =IFERROR(AVERAGE(W99,X99,Y99,Z99)/2,"N/A")
A100: 20574797013 | B100: ASOCIACION DE PRODUCTORES AGROPECUARIOS DE PARAISO CENTRAL | C100: CUSCO | D100: CACAO | G100: NO | H100: nan | I100: nan | J100: ACTIVO | K100: nan | L100: 0 | M100: =IF(E100>0,ROUND(L100/E100*100,1),0) | N100: PENDIENTE | O100: =IF(H100="SI",1,0)*0.6+IF(I100="SI",1,0)*0.4 | P100: PENDIENTE | S100: =IFERROR(SCORECARDS!C98,"—") | T100: =IF(ISTEXT(S100),S100,IF(S100<34,"🔴 Crítico",IF(S100<67,"🟡 Vulnerable","🟢 Preparado"))) | W100: 0 | X100: 0 | Y100: 0 | Z100: 0 | AA100: 0 | AB100: 0 | AC100: 0 | AD100: 0 | AE100: 0 | AF100: 0 | AG100: 0 | AH100: 0 | AI100: 0 | AJ100: 0 | AK100: 0 | AL100: 0 | AM100: 0 | AN100: 0 | AO100: =IFERROR(AVERAGE(AA100,AB100,AC100,AD100,AE100,AF100,AG100,AH100,AI100,AJ100,AK100,AL100,AM100,AN100),"N/A") | AP100: =IFERROR(AVERAGE(W100,X100,Y100,Z100)/2,"N/A")
...

Sheet PREGUNTAS_PROXY
A1: PREGUNTAS PROXY — Verificación rápida por dimensión EUDR
A2: Dim. | B2: # | C2: Pregunta | D2: Respuesta | E2: Score (0-1) | F2: Variable | G2: Fuente | H2: Obs.
A3: DIMENSIÓN D1 — Clasificación regulatoria
A4: D1 | B4: 1 | C4: ¿Cuál es el rol principal de la organización? | E4: =IF(D4="Sí",1,IF(D4="Sí, todas",1,IF(D4="Sí, FT",1,IF(D4="Sí, PT",0.6,IF(D4="Sí, formalmente",1,IF(D4="Sí, informalmente",0.5,IF(D4="Sí, con indicadores",1,IF(D4="Sí, básico",0.5,IF(D4="Sí, los usa",1,IF(D4="Sí, los conoce",0.5,IF(D4="Parcialmente",0.5,IF(D4="Sí, algunas",0.5,IF(D4="Europa",1,IF(D4="EE.UU.",0.3,IF(D4="Asia",0.1,IF(D4="Mercado interno",0,IF(D4="No exporta",0,IF(D4="App propia",1,IF(D4="App de comprador o proyecto",0.7,IF(D4="Excel",0.4,IF(D4="Ninguno",0,IF(D4="Yute reutilizable",1,IF(D4="Big bags reciclables",0.8,IF(D4="Yute nuevo",0.3,IF(D4="Bolsas papel",0.2,IF(D4="Otro",0.1,IF(D4="En proceso",0.5,IF(D4="En gestión",0.5,IF(D4="No sabe",0.3,IF(D4="No aplica",0.5,IF(D4="No",0,IF(D4="",0,IF(ISTEXT(D4),0.5,0)))))))))))))))))))))))))) | F4: tipo_rol | G4: Entrevista directiva / SUNAT
A5: D1 | B5: 2 | C5: ¿La organización está inscrita en el RNCA (Registro Nacional de Cooperativas Agrarias)? | E5: =IF(D5="Sí",1,IF(D5="Sí, todas",1,IF(D5="Sí, FT",1,IF(D5="Sí, PT",0.6,IF(D5="Sí, formalmente",1,IF(D5="Sí, informalmente",0.5,IF(D5="Sí, con indicadores",1,IF(D5="Sí, básico",0.5,IF(D5="Sí, los usa",1,IF(D5="Sí, los conoce",0.5,IF(D5="Parcialmente",0.5,IF(D5="Sí, algunas",0.5,IF(D5="Europa",1,IF(D5="EE.UU.",0.3,IF(D5="Asia",0.1,IF(D5="Mercado interno",0,IF(D5="No exporta",0,IF(D5="App propia",1,IF(D5="App de comprador o proyecto",0.7,IF(D5="Excel",0.4,IF(D5="Ninguno",0,IF(D5="Yute reutilizable",1,IF(D5="Big bags reciclables",0.8,IF(D5="Yute nuevo",0.3,IF(D5="Bolsas papel",0.2,IF(D5="Otro",0.1,IF(D5="En proceso",0.5,IF(D5="En gestión",0.5,IF(D5="No sabe",0.3,IF(D5="No aplica",0.5,IF(D5="No",0,IF(D5="",0,IF(ISTEXT(D5),0.5,0)))))))))))))))))))))))))) | F5: rnca | G5: SUNAT / MIDAGRI RNCA
A6: D1 | B6: 3 | C6: ¿Exporta directamente bajo su propio RUC (no a través de un agente)? | E6: =IF(D6="Sí",1,IF(D6="Sí, todas",1,IF(D6="Sí, FT",1,IF(D6="Sí, PT",0.6,IF(D6="Sí, formalmente",1,IF(D6="Sí, informalmente",0.5,IF(D6="Sí, con indicadores",1,IF(D6="Sí, básico",0.5,IF(D6="Sí, los usa",1,IF(D6="Sí, los conoce",0.5,IF(D6="Parcialmente",0.5,IF(D6="Sí, algunas",0.5,IF(D6="Europa",1,IF(D6="EE.UU.",0.3,IF(D6="Asia",0.1,IF(D6="Mercado interno",0,IF(D6="No exporta",0,IF(D6="App propia",1,IF(D6="App de comprador o proyecto",0.7,IF(D6="Excel",0.4,IF(D6="Ninguno",0,IF(D6="Yute reutilizable",1,IF(D6="Big bags reciclables",0.8,IF(D6="Yute nuevo",0.3,IF(D6="Bolsas papel",0.2,IF(D6="Otro",0.1,IF(D6="En proceso",0.5,IF(D6="En gestión",0.5,IF(D6="No sabe",0.3,IF(D6="No aplica",0.5,IF(D6="No",0,IF(D6="",0,IF(ISTEXT(D6),0.5,0)))))))))))))))))))))))))) | F6: exporta_directo | G6: ADUANET / DUAs
A7: DIMENSIÓN D2 — Trazabilidad y geolocalización
A8: D2 | B8: 1 | C8: ¿Existe al menos un registro donde cada lote exportado esté vinculado a la parcela de origen? | E8: =IF(D8="Sí",1,IF(D8="Sí, todas",1,IF(D8="Sí, FT",1,IF(D8="Sí, PT",0.6,IF(D8="Sí, formalmente",1,IF(D8="Sí, informalmente",0.5,IF(D8="Sí, con indicadores",1,IF(D8="Sí, básico",0.5,IF(D8="Sí, los usa",1,IF(D8="Sí, los conoce",0.5,IF(D8="Parcialmente",0.5,IF(D8="Sí, algunas",0.5,IF(D8="Europa",1,IF(D8="EE.UU.",0.3,IF(D8="Asia",0.1,IF(D8="Mercado interno",0,IF(D8="No exporta",0,IF(D8="App propia",1,IF(D8="App de comprador o proyecto",0.7,IF(D8="Excel",0.4,IF(D8="Ninguno",0,IF(D8="Yute reutilizable",1,IF(D8="Big bags reciclables",0.8,IF(D8="Yute nuevo",0.3,IF(D8="Bolsas papel",0.2,IF(D8="Otro",0.1,IF(D8="En proceso",0.5,IF(D8="En gestión",0.5,IF(D8="No sabe",0.3,IF(D8="No aplica",0.5,IF(D8="No",0,IF(D8="",0,IF(ISTEXT(D8),0.5,0)))))))))))))))))))))))))) | F8: lote_parcela | G8: Entrevista + revisión documentos
A9: D2 | B9: 2 | C9: ¿Se registran las coordenadas geográficas de las parcelas de los socios? | E9: =IF(D9="Sí",1,IF(D9="Sí, todas",1,IF(D9="Sí, FT",1,IF(D9="Sí, PT",0.6,IF(D9="Sí, formalmente",1,IF(D9="Sí, informalmente",0.5,IF(D9="Sí, con indicadores",1,IF(D9="Sí, básico",0.5,IF(D9="Sí, los usa",1,IF(D9="Sí, los conoce",0.5,IF(D9="Parcialmente",0.5,IF(D9="Sí, algunas",0.5,IF(D9="Europa",1,IF(D9="EE.UU.",0.3,IF(D9="Asia",0.1,IF(D9="Mercado interno",0,IF(D9="No exporta",0,IF(D9="App propia",1,IF(D9="App de comprador o proyecto",0.7,IF(D9="Excel",0.4,IF(D9="Ninguno",0,IF(D9="Yute reutilizable",1,IF(D9="Big bags reciclables",0.8,IF(D9="Yute nuevo",0.3,IF(D9="Bolsas papel",0.2,IF(D9="Otro",0.1,IF(D9="En proceso",0.5,IF(D9="En gestión",0.5,IF(D9="No sabe",0.3,IF(D9="No aplica",0.5,IF(D9="No",0,IF(D9="",0,IF(ISTEXT(D9),0.5,0)))))))))))))))))))))))))) | F9: coords | G9: Entrevista + evidencia
A10: D2 | B10: 3 | C10: ¿Con qué frecuencia se actualizan las coordenadas de parcelas? | E10: =IF(D10="Sí",1,IF(D10="Sí, todas",1,IF(D10="Sí, FT",1,IF(D10="Sí, PT",0.6,IF(D10="Sí, formalmente",1,IF(D10="Sí, informalmente",0.5,IF(D10="Sí, con indicadores",1,IF(D10="Sí, básico",0.5,IF(D10="Sí, los usa",1,IF(D10="Sí, los conoce",0.5,IF(D10="Parcialmente",0.5,IF(D10="Sí, algunas",0.5,IF(D10="Europa",1,IF(D10="EE.UU.",0.3,IF(D10="Asia",0.1,IF(D10="Mercado interno",0,IF(D10="No exporta",0,IF(D10="App propia",1,IF(D10="App de comprador o proyecto",0.7,IF(D10="Excel",0.4,IF(D10="Ninguno",0,IF(D10="Yute reutilizable",1,IF(D10="Big bags reciclables",0.8,IF(D10="Yute nuevo",0.3,IF(D10="Bolsas papel",0.2,IF(D10="Otro",0.1,IF(D10="En proceso",0.5,IF(D10="En gestión",0.5,IF(D10="No sabe",0.3,IF(D10="No aplica",0.5,IF(D10="No",0,IF(D10="",0,IF(ISTEXT(D10),0.5,0)))))))))))))))))))))))))) | F10: frec_coords | G10: Entrevista
A11: D2 | B11: 4 | C11: ¿Se usa balance de masas (mezcla de lotes sin segregación física)? | E11: =IF(D11="Sí",1,IF(D11="Sí, todas",1,IF(D11="Sí, FT",1,IF(D11="Sí, PT",0.6,IF(D11="Sí, formalmente",1,IF(D11="Sí, informalmente",0.5,IF(D11="Sí, con indicadores",1,IF(D11="Sí, básico",0.5,IF(D11="Sí, los usa",1,IF(D11="Sí, los conoce",0.5,IF(D11="Parcialmente",0.5,IF(D11="Sí, algunas",0.5,IF(D11="Europa",1,IF(D11="EE.UU.",0.3,IF(D11="Asia",0.1,IF(D11="Mercado interno",0,IF(D11="No exporta",0,IF(D11="App propia",1,IF(D11="App de comprador o proyecto",0.7,IF(D11="Excel",0.4,IF(D11="Ninguno",0,IF(D11="Yute reutilizable",1,IF(D11="Big bags reciclables",0.8,IF(D11="Yute nuevo",0.3,IF(D11="Bolsas papel",0.2,IF(D11="Otro",0.1,IF(D11="En proceso",0.5,IF(D11="En gestión",0.5,IF(D11="No sabe",0.3,IF(D11="No aplica",0.5,IF(D11="No",0,IF(D11="",0,IF(ISTEXT(D11),0.5,0)))))))))))))))))))))))))) | F11: bal_masas | G11: Entrevista — ROJO si dice Sí | H11: ⚠ Bal. de masas prohibido bajo EUDR
A12: D2 | B12: 5 | C12: ¿Los proveedores externos (no socios) representan volumen significativo? | E12: =IF(D12="Sí",1,IF(D12="Sí, todas",1,IF(D12="Sí, FT",1,IF(D12="Sí, PT",0.6,IF(D12="Sí, formalmente",1,IF(D12="Sí, informalmente",0.5,IF(D12="Sí, con indicadores",1,IF(D12="Sí, básico",0.5,IF(D12="Sí, los usa",1,IF(D12="Sí, los conoce",0.5,IF(D12="Parcialmente",0.5,IF(D12="Sí, algunas",0.5,IF(D12="Europa",1,IF(D12="EE.UU.",0.3,IF(D12="Asia",0.1,IF(D12="Mercado interno",0,IF(D12="No exporta",0,IF(D12="App propia",1,IF(D12="App de comprador o proyecto",0.7,IF(D12="Excel",0.4,IF(D12="Ninguno",0,IF(D12="Yute reutilizable",1,IF(D12="Big bags reciclables",0.8,IF(D12="Yute nuevo",0.3,IF(D12="Bolsas papel",0.2,IF(D12="Otro",0.1,IF(D12="En proceso",0.5,IF(D12="En gestión",0.5,IF(D12="No sabe",0.3,IF(D12="No aplica",0.5,IF(D12="No",0,IF(D12="",0,IF(ISTEXT(D12),0.5,0)))))))))))))))))))))))))) | F12: pct_ext | G12: Entrevista
A13: D2 | B13: 6 | C13: ¿Se registra la trazabilidad de proveedores externos (nombre, cantidad, origen)? | E13: =IF(D13="Sí",1,IF(D13="Sí, todas",1,IF(D13="Sí, FT",1,IF(D13="Sí, PT",0.6,IF(D13="Sí, formalmente",1,IF(D13="Sí, informalmente",0.5,IF(D13="Sí, con indicadores",1,IF(D13="Sí, básico",0.5,IF(D13="Sí, los usa",1,IF(D13="Sí, los conoce",0.5,IF(D13="Parcialmente",0.5,IF(D13="Sí, algunas",0.5,IF(D13="Europa",1,IF(D13="EE.UU.",0.3,IF(D13="Asia",0.1,IF(D13="Mercado interno",0,IF(D13="No exporta",0,IF(D13="App propia",1,IF(D13="App de comprador o proyecto",0.7,IF(D13="Excel",0.4,IF(D13="Ninguno",0,IF(D13="Yute reutilizable",1,IF(D13="Big bags reciclables",0.8,IF(D13="Yute nuevo",0.3,IF(D13="Bolsas papel",0.2,IF(D13="Otro",0.1,IF(D13="En proceso",0.5,IF(D13="En gestión",0.5,IF(D13="No sabe",0.3,IF(D13="No aplica",0.5,IF(D13="No",0,IF(D13="",0,IF(ISTEXT(D13),0.5,0)))))))))))))))))))))))))) | F13: traza_ext | G13: Entrevista
A14: DIMENSIÓN D3 — Legalidad de la producción
A15: D3 | B15: 1 | C15: ¿Qué porcentaje aproximado de los socios tiene título de propiedad o constancia de posesión inscrita en SUNARP? | E15: =IF(D15="Sí",1,IF(D15="Sí, todas",1,IF(D15="Sí, FT",1,IF(D15="Sí, PT",0.6,IF(D15="Sí, formalmente",1,IF(D15="Sí, informalmente",0.5,IF(D15="Sí, con indicadores",1,IF(D15="Sí, básico",0.5,IF(D15="Sí, los usa",1,IF(D15="Sí, los conoce",0.5,IF(D15="Parcialmente",0.5,IF(D15="Sí, algunas",0.5,IF(D15="Europa",1,IF(D15="EE.UU.",0.3,IF(D15="Asia",0.1,IF(D15="Mercado interno",0,IF(D15="No exporta",0,IF(D15="App propia",1,IF(D15="App de comprador o proyecto",0.7,IF(D15="Excel",0.4,IF(D15="Ninguno",0,IF(D15="Yute reutilizable",1,IF(D15="Big bags reciclables",0.8,IF(D15="Yute nuevo",0.3,IF(D15="Bolsas papel",0.2,IF(D15="Otro",0.1,IF(D15="En proceso",0.5,IF(D15="En gestión",0.5,IF(D15="No sabe",0.3,IF(D15="No aplica",0.5,IF(D15="No",0,IF(D15="",0,IF(ISTEXT(D15),0.5,0)))))))))))))))))))))))))) | F15: pct_titulo | G15: Entrevista / MIDAGRI
A16: D3 | B16: 2 | C16: ¿La zona de producción está en un área natural protegida o zona de amortiguamiento? | E16: =IF(D16="Sí",1,IF(D16="Sí, todas",1,IF(D16="Sí, FT",1,IF(D16="Sí, PT",0.6,IF(D16="Sí, formalmente",1,IF(D16="Sí, informalmente",0.5,IF(D16="Sí, con indicadores",1,IF(D16="Sí, básico",0.5,IF(D16="Sí, los usa",1,IF(D16="Sí, los conoce",0.5,IF(D16="Parcialmente",0.5,IF(D16="Sí, algunas",0.5,IF(D16="Europa",1,IF(D16="EE.UU.",0.3,IF(D16="Asia",0.1,IF(D16="Mercado interno",0,IF(D16="No exporta",0,IF(D16="App propia",1,IF(D16="App de comprador o proyecto",0.7,IF(D16="Excel",0.4,IF(D16="Ninguno",0,IF(D16="Yute reutilizable",1,IF(D16="Big bags reciclables",0.8,IF(D16="Yute nuevo",0.3,IF(D16="Bolsas papel",0.2,IF(D16="Otro",0.1,IF(D16="En proceso",0.5,IF(D16="En gestión",0.5,IF(D16="No sabe",0.3,IF(D16="No aplica",0.5,IF(D16="No",0,IF(D16="",0,IF(ISTEXT(D16),0.5,0)))))))))))))))))))))))))) | F16: anp | G16: GEOSERFOR / SINIA
A17: D3 | B17: 3 | C17: ¿La organización cuenta con autorizaciones ambientales vigentes (EIA, DIA, certificación forestal)? | E17: =IF(D17="Sí",1,IF(D17="Sí, todas",1,IF(D17="Sí, FT",1,IF(D17="Sí, PT",0.6,IF(D17="Sí, formalmente",1,IF(D17="Sí, informalmente",0.5,IF(D17="Sí, con indicadores",1,IF(D17="Sí, básico",0.5,IF(D17="Sí, los usa",1,IF(D17="Sí, los conoce",0.5,IF(D17="Parcialmente",0.5,IF(D17="Sí, algunas",0.5,IF(D17="Europa",1,IF(D17="EE.UU.",0.3,IF(D17="Asia",0.1,IF(D17="Mercado interno",0,IF(D17="No exporta",0,IF(D17="App propia",1,IF(D17="App de comprador o proyecto",0.7,IF(D17="Excel",0.4,IF(D17="Ninguno",0,IF(D17="Yute reutilizable",1,IF(D17="Big bags reciclables",0.8,IF(D17="Yute nuevo",0.3,IF(D17="Bolsas papel",0.2,IF(D17="Otro",0.1,IF(D17="En proceso",0.5,IF(D17="En gestión",0.5,IF(D17="No sabe",0.3,IF(D17="No aplica",0.5,IF(D17="No",0,IF(D17="",0,IF(ISTEXT(D17),0.5,0)))))))))))))))))))))))))) | F17: aut_ambiental | G17: Entrevista / OEFA
A18: D3 | B18: 4 | C18: ¿Hay algún proceso sancionador vigente de OEFA o SINEFA contra la organización? | E18: =IF(D18="Sí",1,IF(D18="Sí, todas",1,IF(D18="Sí, FT",1,IF(D18="Sí, PT",0.6,IF(D18="Sí, formalmente",1,IF(D18="Sí, informalmente",0.5,IF(D18="Sí, con indicadores",1,IF(D18="Sí, básico",0.5,IF(D18="Sí, los usa",1,IF(D18="Sí, los conoce",0.5,IF(D18="Parcialmente",0.5,IF(D18="Sí, algunas",0.5,IF(D18="Europa",1,IF(D18="EE.UU.",0.3,IF(D18="Asia",0.1,IF(D18="Mercado interno",0,IF(D18="No exporta",0,IF(D18="App propia",1,IF(D18="App de comprador o proyecto",0.7,IF(D18="Excel",0.4,IF(D18="Ninguno",0,IF(D18="Yute reutilizable",1,IF(D18="Big bags reciclables",0.8,IF(D18="Yute nuevo",0.3,IF(D18="Bolsas papel",0.2,IF(D18="Otro",0.1,IF(D18="En proceso",0.5,IF(D18="En gestión",0.5,IF(D18="No sabe",0.3,IF(D18="No aplica",0.5,IF(D18="No",0,IF(D18="",0,IF(ISTEXT(D18),0.5,0)))))))))))))))))))))))))) | F18: sancion_oea | G18: OEFA / SINEFA
A19: DIMENSIÓN D4 — Riesgo de deforestación
A20: D4 | B20: 1 | C20: ¿La organización ha realizado cruces de sus parcelas contra mapas de deforestación (GEOSERFOR / PNCB)? | E20: =IF(D20="Sí",1,IF(D20="Sí, todas",1,IF(D20="Sí, FT",1,IF(D20="Sí, PT",0.6,IF(D20="Sí, formalmente",1,IF(D20="Sí, informalmente",0.5,IF(D20="Sí, con indicadores",1,IF(D20="Sí, básico",0.5,IF(D20="Sí, los usa",1,IF(D20="Sí, los conoce",0.5,IF(D20="Parcialmente",0.5,IF(D20="Sí, algunas",0.5,IF(D20="Europa",1,IF(D20="EE.UU.",0.3,IF(D20="Asia",0.1,IF(D20="Mercado interno",0,IF(D20="No exporta",0,IF(D20="App propia",1,IF(D20="App de comprador o proyecto",0.7,IF(D20="Excel",0.4,IF(D20="Ninguno",0,IF(D20="Yute reutilizable",1,IF(D20="Big bags reciclables",0.8,IF(D20="Yute nuevo",0.3,IF(D20="Bolsas papel",0.2,IF(D20="Otro",0.1,IF(D20="En proceso",0.5,IF(D20="En gestión",0.5,IF(D20="No sabe",0.3,IF(D20="No aplica",0.5,IF(D20="No",0,IF(D20="",0,IF(ISTEXT(D20),0.5,0)))))))))))))))))))))))))) | F20: cruce_deforest | G20: Entrevista / verificación web
A21: D4 | B21: 2 | C21: ¿Se han detectado alertas de deforestación en parcelas de la organización? | E21: =IF(D21="Sí",1,IF(D21="Sí, todas",1,IF(D21="Sí, FT",1,IF(D21="Sí, PT",0.6,IF(D21="Sí, formalmente",1,IF(D21="Sí, informalmente",0.5,IF(D21="Sí, con indicadores",1,IF(D21="Sí, básico",0.5,IF(D21="Sí, los usa",1,IF(D21="Sí, los conoce",0.5,IF(D21="Parcialmente",0.5,IF(D21="Sí, algunas",0.5,IF(D21="Europa",1,IF(D21="EE.UU.",0.3,IF(D21="Asia",0.1,IF(D21="Mercado interno",0,IF(D21="No exporta",0,IF(D21="App propia",1,IF(D21="App de comprador o proyecto",0.7,IF(D21="Excel",0.4,IF(D21="Ninguno",0,IF(D21="Yute reutilizable",1,IF(D21="Big bags reciclables",0.8,IF(D21="Yute nuevo",0.3,IF(D21="Bolsas papel",0.2,IF(D21="Otro",0.1,IF(D21="En proceso",0.5,IF(D21="En gestión",0.5,IF(D21="No sabe",0.3,IF(D21="No aplica",0.5,IF(D21="No",0,IF(D21="",0,IF(ISTEXT(D21),0.5,0)))))))))))))))))))))))))) | F21: alerta_deforest | G21: GEOSERFOR / GFW
A22: DIMENSIÓN D5 — Sistema de debida diligencia
A23: D5 | B23: 1 | C23: ¿Existe un proceso documentado para evaluar riesgo de deforestación antes de exportar? | E23: =IF(D23="Sí",1,IF(D23="Sí, todas",1,IF(D23="Sí, FT",1,IF(D23="Sí, PT",0.6,IF(D23="Sí, formalmente",1,IF(D23="Sí, informalmente",0.5,IF(D23="Sí, con indicadores",1,IF(D23="Sí, básico",0.5,IF(D23="Sí, los usa",1,IF(D23="Sí, los conoce",0.5,IF(D23="Parcialmente",0.5,IF(D23="Sí, algunas",0.5,IF(D23="Europa",1,IF(D23="EE.UU.",0.3,IF(D23="Asia",0.1,IF(D23="Mercado interno",0,IF(D23="No exporta",0,IF(D23="App propia",1,IF(D23="App de comprador o proyecto",0.7,IF(D23="Excel",0.4,IF(D23="Ninguno",0,IF(D23="Yute reutilizable",1,IF(D23="Big bags reciclables",0.8,IF(D23="Yute nuevo",0.3,IF(D23="Bolsas papel",0.2,IF(D23="Otro",0.1,IF(D23="En proceso",0.5,IF(D23="En gestión",0.5,IF(D23="No sabe",0.3,IF(D23="No aplica",0.5,IF(D23="No",0,IF(D23="",0,IF(ISTEXT(D23),0.5,0)))))))))))))))))))))))))) | F23: proc_dd | G23: Entrevista + revisión docs
A24: D5 | B24: 2 | C24: ¿Se registran las alertas o rechazos de compradores europeos en los últimos 2 años? | E24: =IF(D24="Sí",1,IF(D24="Sí, todas",1,IF(D24="Sí, FT",1,IF(D24="Sí, PT",0.6,IF(D24="Sí, formalmente",1,IF(D24="Sí, informalmente",0.5,IF(D24="Sí, con indicadores",1,IF(D24="Sí, básico",0.5,IF(D24="Sí, los usa",1,IF(D24="Sí, los conoce",0.5,IF(D24="Parcialmente",0.5,IF(D24="Sí, algunas",0.5,IF(D24="Europa",1,IF(D24="EE.UU.",0.3,IF(D24="Asia",0.1,IF(D24="Mercado interno",0,IF(D24="No exporta",0,IF(D24="App propia",1,IF(D24="App de comprador o proyecto",0.7,IF(D24="Excel",0.4,IF(D24="Ninguno",0,IF(D24="Yute reutilizable",1,IF(D24="Big bags reciclables",0.8,IF(D24="Yute nuevo",0.3,IF(D24="Bolsas papel",0.2,IF(D24="Otro",0.1,IF(D24="En proceso",0.5,IF(D24="En gestión",0.5,IF(D24="No sabe",0.3,IF(D24="No aplica",0.5,IF(D24="No",0,IF(D24="",0,IF(ISTEXT(D24),0.5,0)))))))))))))))))))))))))) | F24: reg_rechazos | G24: Entrevista
A25: D5 | B25: 3 | C25: ¿La organización elabora un reporte periódico de debida diligencia? | E25: =IF(D25="Sí",1,IF(D25="Sí, todas",1,IF(D25="Sí, FT",1,IF(D25="Sí, PT",0.6,IF(D25="Sí, formalmente",1,IF(D25="Sí, informalmente",0.5,IF(D25="Sí, con indicadores",1,IF(D25="Sí, básico",0.5,IF(D25="Sí, los usa",1,IF(D25="Sí, los conoce",0.5,IF(D25="Parcialmente",0.5,IF(D25="Sí, algunas",0.5,IF(D25="Europa",1,IF(D25="EE.UU.",0.3,IF(D25="Asia",0.1,IF(D25="Mercado interno",0,IF(D25="No exporta",0,IF(D25="App propia",1,IF(D25="App de comprador o proyecto",0.7,IF(D25="Excel",0.4,IF(D25="Ninguno",0,IF(D25="Yute reutilizable",1,IF(D25="Big bags reciclables",0.8,IF(D25="Yute nuevo",0.3,IF(D25="Bolsas papel",0.2,IF(D25="Otro",0.1,IF(D25="En proceso",0.5,IF(D25="En gestión",0.5,IF(D25="No sabe",0.3,IF(D25="No aplica",0.5,IF(D25="No",0,IF(D25="",0,IF(ISTEXT(D25),0.5,0)))))))))))))))))))))))))) | F25: reporte_dd | G25: Entrevista
A26: DIMENSIÓN D6 — Capacidad organizacional y digital
A27: D6 | B27: 1 | C27: ¿Hay personal dedicado (tiempo completo o parcial) a tareas de gestión de datos o sistemas? | E27: =IF(D27="Sí",1,IF(D27="Sí, todas",1,IF(D27="Sí, FT",1,IF(D27="Sí, PT",0.6,IF(D27="Sí, formalmente",1,IF(D27="Sí, informalmente",0.5,IF(D27="Sí, con indicadores",1,IF(D27="Sí, básico",0.5,IF(D27="Sí, los usa",1,IF(D27="Sí, los conoce",0.5,IF(D27="Parcialmente",0.5,IF(D27="Sí, algunas",0.5,IF(D27="Europa",1,IF(D27="EE.UU.",0.3,IF(D27="Asia",0.1,IF(D27="Mercado interno",0,IF(D27="No exporta",0,IF(D27="App propia",1,IF(D27="App de comprador o proyecto",0.7,IF(D27="Excel",0.4,IF(D27="Ninguno",0,IF(D27="Yute reutilizable",1,IF(D27="Big bags reciclables",0.8,IF(D27="Yute nuevo",0.3,IF(D27="Bolsas papel",0.2,IF(D27="Otro",0.1,IF(D27="En proceso",0.5,IF(D27="En gestión",0.5,IF(D27="No sabe",0.3,IF(D27="No aplica",0.5,IF(D27="No",0,IF(D27="",0,IF(ISTEXT(D27),0.5,0)))))))))))))))))))))))))) | F27: personal_datos | G27: Entrevista
A28: D6 | B28: 2 | C28: ¿La organización tiene acceso a internet estable en su sede? | E28: =IF(D28="Sí",1,IF(D28="Sí, todas",1,IF(D28="Sí, FT",1,IF(D28="Sí, PT",0.6,IF(D28="Sí, formalmente",1,IF(D28="Sí, informalmente",0.5,IF(D28="Sí, con indicadores",1,IF(D28="Sí, básico",0.5,IF(D28="Sí, los usa",1,IF(D28="Sí, los conoce",0.5,IF(D28="Parcialmente",0.5,IF(D28="Sí, algunas",0.5,IF(D28="Europa",1,IF(D28="EE.UU.",0.3,IF(D28="Asia",0.1,IF(D28="Mercado interno",0,IF(D28="No exporta",0,IF(D28="App propia",1,IF(D28="App de comprador o proyecto",0.7,IF(D28="Excel",0.4,IF(D28="Ninguno",0,IF(D28="Yute reutilizable",1,IF(D28="Big bags reciclables",0.8,IF(D28="Yute nuevo",0.3,IF(D28="Bolsas papel",0.2,IF(D28="Otro",0.1,IF(D28="En proceso",0.5,IF(D28="En gestión",0.5,IF(D28="No sabe",0.3,IF(D28="No aplica",0.5,IF(D28="No",0,IF(D28="",0,IF(ISTEXT(D28),0.5,0)))))))))))))))))))))))))) | F28: internet | G28: Entrevista
A29: D6 | B29: 3 | C29: ¿Usa algún software o herramienta digital para gestionar trazabilidad? | E29: =IF(D29="Sí",1,IF(D29="Sí, todas",1,IF(D29="Sí, FT",1,IF(D29="Sí, PT",0.6,IF(D29="Sí, formalmente",1,IF(D29="Sí, informalmente",0.5,IF(D29="Sí, con indicadores",1,IF(D29="Sí, básico",0.5,IF(D29="Sí, los usa",1,IF(D29="Sí, los conoce",0.5,IF(D29="Parcialmente",0.5,IF(D29="Sí, algunas",0.5,IF(D29="Europa",1,IF(D29="EE.UU.",0.3,IF(D29="Asia",0.1,IF(D29="Mercado interno",0,IF(D29="No exporta",0,IF(D29="App propia",1,IF(D29="App de comprador o proyecto",0.7,IF(D29="Excel",0.4,IF(D29="Ninguno",0,IF(D29="Yute reutilizable",1,IF(D29="Big bags reciclables",0.8,IF(D29="Yute nuevo",0.3,IF(D29="Bolsas papel",0.2,IF(D29="Otro",0.1,IF(D29="En proceso",0.5,IF(D29="En gestión",0.5,IF(D29="No sabe",0.3,IF(D29="No aplica",0.5,IF(D29="No",0,IF(D29="",0,IF(ISTEXT(D29),0.5,0)))))))))))))))))))))))))) | F29: sw_trazabilidad | G29: Entrevista
A30: D6 | B30: 4 | C30: ¿El presupuesto anual incluye una partida para tecnología o datos? | E30: =IF(D30="Sí",1,IF(D30="Sí, todas",1,IF(D30="Sí, FT",1,IF(D30="Sí, PT",0.6,IF(D30="Sí, formalmente",1,IF(D30="Sí, informalmente",0.5,IF(D30="Sí, con indicadores",1,IF(D30="Sí, básico",0.5,IF(D30="Sí, los usa",1,IF(D30="Sí, los conoce",0.5,IF(D30="Parcialmente",0.5,IF(D30="Sí, algunas",0.5,IF(D30="Europa",1,IF(D30="EE.UU.",0.3,IF(D30="Asia",0.1,IF(D30="Mercado interno",0,IF(D30="No exporta",0,IF(D30="App propia",1,IF(D30="App de comprador o proyecto",0.7,IF(D30="Excel",0.4,IF(D30="Ninguno",0,IF(D30="Yute reutilizable",1,IF(D30="Big bags reciclables",0.8,IF(D30="Yute nuevo",0.3,IF(D30="Bolsas papel",0.2,IF(D30="Otro",0.1,IF(D30="En proceso",0.5,IF(D30="En gestión",0.5,IF(D30="No sabe",0.3,IF(D30="No aplica",0.5,IF(D30="No",0,IF(D30="",0,IF(ISTEXT(D30),0.5,0)))))))))))))))))))))))))) | F30: presupuesto_tech | G30: Entrevista directiva
A31: DIMENSIÓN D7 — Posición en la cadena de valor
A32: D7 | B32: 1 | C32: ¿Cuál es el destino principal de las exportaciones? | E32: =IF(D32="Sí",1,IF(D32="Sí, todas",1,IF(D32="Sí, FT",1,IF(D32="Sí, PT",0.6,IF(D32="Sí, formalmente",1,IF(D32="Sí, informalmente",0.5,IF(D32="Sí, con indicadores",1,IF(D32="Sí, básico",0.5,IF(D32="Sí, los usa",1,IF(D32="Sí, los conoce",0.5,IF(D32="Parcialmente",0.5,IF(D32="Sí, algunas",0.5,IF(D32="Europa",1,IF(D32="EE.UU.",0.3,IF(D32="Asia",0.1,IF(D32="Mercado interno",0,IF(D32="No exporta",0,IF(D32="App propia",1,IF(D32="App de comprador o proyecto",0.7,IF(D32="Excel",0.4,IF(D32="Ninguno",0,IF(D32="Yute reutilizable",1,IF(D32="Big bags reciclables",0.8,IF(D32="Yute nuevo",0.3,IF(D32="Bolsas papel",0.2,IF(D32="Otro",0.1,IF(D32="En proceso",0.5,IF(D32="En gestión",0.5,IF(D32="No sabe",0.3,IF(D32="No aplica",0.5,IF(D32="No",0,IF(D32="",0,IF(ISTEXT(D32),0.5,0)))))))))))))))))))))))))) | F32: destino_principal | G32: DUAs / Entrevista
A33: D7 | B33: 2 | C33: ¿El comprador principal (primera mano) es una empresa europea o está sujeta a CS3D? | E33: =IF(D33="Sí",1,IF(D33="Sí, todas",1,IF(D33="Sí, FT",1,IF(D33="Sí, PT",0.6,IF(D33="Sí, formalmente",1,IF(D33="Sí, informalmente",0.5,IF(D33="Sí, con indicadores",1,IF(D33="Sí, básico",0.5,IF(D33="Sí, los usa",1,IF(D33="Sí, los conoce",0.5,IF(D33="Parcialmente",0.5,IF(D33="Sí, algunas",0.5,IF(D33="Europa",1,IF(D33="EE.UU.",0.3,IF(D33="Asia",0.1,IF(D33="Mercado interno",0,IF(D33="No exporta",0,IF(D33="App propia",1,IF(D33="App de comprador o proyecto",0.7,IF(D33="Excel",0.4,IF(D33="Ninguno",0,IF(D33="Yute reutilizable",1,IF(D33="Big bags reciclables",0.8,IF(D33="Yute nuevo",0.3,IF(D33="Bolsas papel",0.2,IF(D33="Otro",0.1,IF(D33="En proceso",0.5,IF(D33="En gestión",0.5,IF(D33="No sabe",0.3,IF(D33="No aplica",0.5,IF(D33="No",0,IF(D33="",0,IF(ISTEXT(D33),0.5,0)))))))))))))))))))))))))) | F33: comprador_ue | G33: Entrevista / web
A34: D7 | B34: 3 | C34: ¿El comprador ha solicitado evidencia de trazabilidad o geolocalización? | E34: =IF(D34="Sí",1,IF(D34="Sí, todas",1,IF(D34="Sí, FT",1,IF(D34="Sí, PT",0.6,IF(D34="Sí, formalmente",1,IF(D34="Sí, informalmente",0.5,IF(D34="Sí, con indicadores",1,IF(D34="Sí, básico",0.5,IF(D34="Sí, los usa",1,IF(D34="Sí, los conoce",0.5,IF(D34="Parcialmente",0.5,IF(D34="Sí, algunas",0.5,IF(D34="Europa",1,IF(D34="EE.UU.",0.3,IF(D34="Asia",0.1,IF(D34="Mercado interno",0,IF(D34="No exporta",0,IF(D34="App propia",1,IF(D34="App de comprador o proyecto",0.7,IF(D34="Excel",0.4,IF(D34="Ninguno",0,IF(D34="Yute reutilizable",1,IF(D34="Big bags reciclables",0.8,IF(D34="Yute nuevo",0.3,IF(D34="Bolsas papel",0.2,IF(D34="Otro",0.1,IF(D34="En proceso",0.5,IF(D34="En gestión",0.5,IF(D34="No sabe",0.3,IF(D34="No aplica",0.5,IF(D34="No",0,IF(D34="",0,IF(ISTEXT(D34),0.5,0)))))))))))))))))))))))))) | F34: exige_evidencia | G34: Entrevista
A35: D7 | B35: 4 | C35: ¿Hay contrato escrito con cláusula EUDR o debida diligencia? | E35: =IF(D35="Sí",1,IF(D35="Sí, todas",1,IF(D35="Sí, FT",1,IF(D35="Sí, PT",0.6,IF(D35="Sí, formalmente",1,IF(D35="Sí, informalmente",0.5,IF(D35="Sí, con indicadores",1,IF(D35="Sí, básico",0.5,IF(D35="Sí, los usa",1,IF(D35="Sí, los conoce",0.5,IF(D35="Parcialmente",0.5,IF(D35="Sí, algunas",0.5,IF(D35="Europa",1,IF(D35="EE.UU.",0.3,IF(D35="Asia",0.1,IF(D35="Mercado interno",0,IF(D35="No exporta",0,IF(D35="App propia",1,IF(D35="App de comprador o proyecto",0.7,IF(D35="Excel",0.4,IF(D35="Ninguno",0,IF(D35="Yute reutilizable",1,IF(D35="Big bags reciclables",0.8,IF(D35="Yute nuevo",0.3,IF(D35="Bolsas papel",0.2,IF(D35="Otro",0.1,IF(D35="En proceso",0.5,IF(D35="En gestión",0.5,IF(D35="No sabe",0.3,IF(D35="No aplica",0.5,IF(D35="No",0,IF(D35="",0,IF(ISTEXT(D35),0.5,0)))))))))))))))))))))))))) | F35: contrato_eudr | G35: Entrevista / docs legales
A36: DIMENSIÓN D8 — Gobernanza y participación de socios
A37: D8 | B37: 1 | C37: ¿Los socios conocen los requisitos EUDR y sus implicancias? | E37: =IF(D37="Sí",1,IF(D37="Sí, todas",1,IF(D37="Sí, FT",1,IF(D37="Sí, PT",0.6,IF(D37="Sí, formalmente",1,IF(D37="Sí, informalmente",0.5,IF(D37="Sí, con indicadores",1,IF(D37="Sí, básico",0.5,IF(D37="Sí, los usa",1,IF(D37="Sí, los conoce",0.5,IF(D37="Parcialmente",0.5,IF(D37="Sí, algunas",0.5,IF(D37="Europa",1,IF(D37="EE.UU.",0.3,IF(D37="Asia",0.1,IF(D37="Mercado interno",0,IF(D37="No exporta",0,IF(D37="App propia",1,IF(D37="App de comprador o proyecto",0.7,IF(D37="Excel",0.4,IF(D37="Ninguno",0,IF(D37="Yute reutilizable",1,IF(D37="Big bags reciclables",0.8,IF(D37="Yute nuevo",0.3,IF(D37="Bolsas papel",0.2,IF(D37="Otro",0.1,IF(D37="En proceso",0.5,IF(D37="En gestión",0.5,IF(D37="No sabe",0.3,IF(D37="No aplica",0.5,IF(D37="No",0,IF(D37="",0,IF(ISTEXT(D37),0.5,0)))))))))))))))))))))))))) | F37: socios_conocen | G37: Entrevista + observación
A38: D8 | B38: 2 | C38: ¿Existe un mecanismo formal para que los socios entreguen datos de parcelas? | E38: =IF(D38="Sí",1,IF(D38="Sí, todas",1,IF(D38="Sí, FT",1,IF(D38="Sí, PT",0.6,IF(D38="Sí, formalmente",1,IF(D38="Sí, informalmente",0.5,IF(D38="Sí, con indicadores",1,IF(D38="Sí, básico",0.5,IF(D38="Sí, los usa",1,IF(D38="Sí, los conoce",0.5,IF(D38="Parcialmente",0.5,IF(D38="Sí, algunas",0.5,IF(D38="Europa",1,IF(D38="EE.UU.",0.3,IF(D38="Asia",0.1,IF(D38="Mercado interno",0,IF(D38="No exporta",0,IF(D38="App propia",1,IF(D38="App de comprador o proyecto",0.7,IF(D38="Excel",0.4,IF(D38="Ninguno",0,IF(D38="Yute reutilizable",1,IF(D38="Big bags reciclables",0.8,IF(D38="Yute nuevo",0.3,IF(D38="Bolsas papel",0.2,IF(D38="Otro",0.1,IF(D38="En proceso",0.5,IF(D38="En gestión",0.5,IF(D38="No sabe",0.3,IF(D38="No aplica",0.5,IF(D38="No",0,IF(D38="",0,IF(ISTEXT(D38),0.5,0)))))))))))))))))))))))))) | F38: mec_entrega | G38: Entrevista
A39: DIMENSIÓN D9 — Sostenibilidad económica del cumplimiento
A40: D9 | B40: 1 | C40: ¿La organización ha estimado el costo de adecuación al EUDR? | E40: =IF(D40="Sí",1,IF(D40="Sí, todas",1,IF(D40="Sí, FT",1,IF(D40="Sí, PT",0.6,IF(D40="Sí, formalmente",1,IF(D40="Sí, informalmente",0.5,IF(D40="Sí, con indicadores",1,IF(D40="Sí, básico",0.5,IF(D40="Sí, los usa",1,IF(D40="Sí, los conoce",0.5,IF(D40="Parcialmente",0.5,IF(D40="Sí, algunas",0.5,IF(D40="Europa",1,IF(D40="EE.UU.",0.3,IF(D40="Asia",0.1,IF(D40="Mercado interno",0,IF(D40="No exporta",0,IF(D40="App propia",1,IF(D40="App de comprador o proyecto",0.7,IF(D40="Excel",0.4,IF(D40="Ninguno",0,IF(D40="Yute reutilizable",1,IF(D40="Big bags reciclables",0.8,IF(D40="Yute nuevo",0.3,IF(D40="Bolsas papel",0.2,IF(D40="Otro",0.1,IF(D40="En proceso",0.5,IF(D40="En gestión",0.5,IF(D40="No sabe",0.3,IF(D40="No aplica",0.5,IF(D40="No",0,IF(D40="",0,IF(ISTEXT(D40),0.5,0)))))))))))))))))))))))))) | F40: costo_estimado | G40: Entrevista directiva
A41: D9 | B41: 2 | C41: ¿Existe una fuente de financiamiento identificada para la adecuación? | E41: =IF(D41="Sí",1,IF(D41="Sí, todas",1,IF(D41="Sí, FT",1,IF(D41="Sí, PT",0.6,IF(D41="Sí, formalmente",1,IF(D41="Sí, informalmente",0.5,IF(D41="Sí, con indicadores",1,IF(D41="Sí, básico",0.5,IF(D41="Sí, los usa",1,IF(D41="Sí, los conoce",0.5,IF(D41="Parcialmente",0.5,IF(D41="Sí, algunas",0.5,IF(D41="Europa",1,IF(D41="EE.UU.",0.3,IF(D41="Asia",0.1,IF(D41="Mercado interno",0,IF(D41="No exporta",0,IF(D41="App propia",1,IF(D41="App de comprador o proyecto",0.7,IF(D41="Excel",0.4,IF(D41="Ninguno",0,IF(D41="Yute reutilizable",1,IF(D41="Big bags reciclables",0.8,IF(D41="Yute nuevo",0.3,IF(D41="Bolsas papel",0.2,IF(D41="Otro",0.1,IF(D41="En proceso",0.5,IF(D41="En gestión",0.5,IF(D41="No sabe",0.3,IF(D41="No aplica",0.5,IF(D41="No",0,IF(D41="",0,IF(ISTEXT(D41),0.5,0)))))))))))))))))))))))))) | F41: financiamiento | G41: Entrevista
A42: DIMENSIÓN D10 — Confusión certificación / EUDR
A43: D10 | B43: 1 | C43: ¿La organización cree que sus certificaciones (Orgánica, Fairtrade, Rainforest) cubren los requisitos EUDR? | E43: =IF(D43="Sí",1,IF(D43="Sí, todas",1,IF(D43="Sí, FT",1,IF(D43="Sí, PT",0.6,IF(D43="Sí, formalmente",1,IF(D43="Sí, informalmente",0.5,IF(D43="Sí, con indicadores",1,IF(D43="Sí, básico",0.5,IF(D43="Sí, los usa",1,IF(D43="Sí, los conoce",0.5,IF(D43="Parcialmente",0.5,IF(D43="Sí, algunas",0.5,IF(D43="Europa",1,IF(D43="EE.UU.",0.3,IF(D43="Asia",0.1,IF(D43="Mercado interno",0,IF(D43="No exporta",0,IF(D43="App propia",1,IF(D43="App de comprador o proyecto",0.7,IF(D43="Excel",0.4,IF(D43="Ninguno",0,IF(D43="Yute reutilizable",1,IF(D43="Big bags reciclables",0.8,IF(D43="Yute nuevo",0.3,IF(D43="Bolsas papel",0.2,IF(D43="Otro",0.1,IF(D43="En proceso",0.5,IF(D43="En gestión",0.5,IF(D43="No sabe",0.3,IF(D43="No aplica",0.5,IF(D43="No",0,IF(D43="",0,IF(ISTEXT(D43),0.5,0)))))))))))))))))))))))))) | F43: cree_cubierta | G43: Entrevista — ROJO si dice Sí sin entender EUDR
A44: D10 | B44: 2 | C44: ¿Ha recibido asesoría específica sobre EUDR (no solo genérica de sostenibilidad)? | E44: =IF(D44="Sí",1,IF(D44="Sí, todas",1,IF(D44="Sí, FT",1,IF(D44="Sí, PT",0.6,IF(D44="Sí, formalmente",1,IF(D44="Sí, informalmente",0.5,IF(D44="Sí, con indicadores",1,IF(D44="Sí, básico",0.5,IF(D44="Sí, los usa",1,IF(D44="Sí, los conoce",0.5,IF(D44="Parcialmente",0.5,IF(D44="Sí, algunas",0.5,IF(D44="Europa",1,IF(D44="EE.UU.",0.3,IF(D44="Asia",0.1,IF(D44="Mercado interno",0,IF(D44="No exporta",0,IF(D44="App propia",1,IF(D44="App de comprador o proyecto",0.7,IF(D44="Excel",0.4,IF(D44="Ninguno",0,IF(D44="Yute reutilizable",1,IF(D44="Big bags reciclables",0.8,IF(D44="Yute nuevo",0.3,IF(D44="Bolsas papel",0.2,IF(D44="Otro",0.1,IF(D44="En proceso",0.5,IF(D44="En gestión",0.5,IF(D44="No sabe",0.3,IF(D44="No aplica",0.5,IF(D44="No",0,IF(D44="",0,IF(ISTEXT(D44),0.5,0)))))))))))))))))))))))))) | F44: asesoria_eudr | G44: Entrevista
A45: DIMENSIÓN D11 — Ecosistema de apoyo externo
A46: D11 | B46: 1 | C46: ¿Conoce programas de MIDAGRI, GIZ, EFI, PROMPERÚ o cooperación para apoyo EUDR? | E46: =IF(D46="Sí",1,IF(D46="Sí, todas",1,IF(D46="Sí, FT",1,IF(D46="Sí, PT",0.6,IF(D46="Sí, formalmente",1,IF(D46="Sí, informalmente",0.5,IF(D46="Sí, con indicadores",1,IF(D46="Sí, básico",0.5,IF(D46="Sí, los usa",1,IF(D46="Sí, los conoce",0.5,IF(D46="Parcialmente",0.5,IF(D46="Sí, algunas",0.5,IF(D46="Europa",1,IF(D46="EE.UU.",0.3,IF(D46="Asia",0.1,IF(D46="Mercado interno",0,IF(D46="No exporta",0,IF(D46="App propia",1,IF(D46="App de comprador o proyecto",0.7,IF(D46="Excel",0.4,IF(D46="Ninguno",0,IF(D46="Yute reutilizable",1,IF(D46="Big bags reciclables",0.8,IF(D46="Yute nuevo",0.3,IF(D46="Bolsas papel",0.2,IF(D46="Otro",0.1,IF(D46="En proceso",0.5,IF(D46="En gestión",0.5,IF(D46="No sabe",0.3,IF(D46="No aplica",0.5,IF(D46="No",0,IF(D46="",0,IF(ISTEXT(D46),0.5,0)))))))))))))))))))))))))) | F46: prog_apoyo | G46: Entrevista
A47: D11 | B47: 2 | C47: ¿Está inscrita en la plataforma de trazabilidad de APPCACAO o JNC? | E47: =IF(D47="Sí",1,IF(D47="Sí, todas",1,IF(D47="Sí, FT",1,IF(D47="Sí, PT",0.6,IF(D47="Sí, formalmente",1,IF(D47="Sí, informalmente",0.5,IF(D47="Sí, con indicadores",1,IF(D47="Sí, básico",0.5,IF(D47="Sí, los usa",1,IF(D47="Sí, los conoce",0.5,IF(D47="Parcialmente",0.5,IF(D47="Sí, algunas",0.5,IF(D47="Europa",1,IF(D47="EE.UU.",0.3,IF(D47="Asia",0.1,IF(D47="Mercado interno",0,IF(D47="No exporta",0,IF(D47="App propia",1,IF(D47="App de comprador o proyecto",0.7,IF(D47="Excel",0.4,IF(D47="Ninguno",0,IF(D47="Yute reutilizable",1,IF(D47="Big bags reciclables",0.8,IF(D47="Yute nuevo",0.3,IF(D47="Bolsas papel",0.2,IF(D47="Otro",0.1,IF(D47="En proceso",0.5,IF(D47="En gestión",0.5,IF(D47="No sabe",0.3,IF(D47="No aplica",0.5,IF(D47="No",0,IF(D47="",0,IF(ISTEXT(D47),0.5,0)))))))))))))))))))))))))) | F47: plataforma_traz | G47: Verificación web + entrevista
A48: DIMENSIÓN PPWR — Envases y Packaging (PPWR)
A49: PPWR | B49: P1 | C49: ¿Qué tipo de sacos de exportación usa principalmente? | E49: =IF(D49="Sí",1,IF(D49="Sí, todas",1,IF(D49="Sí, FT",1,IF(D49="Sí, PT",0.6,IF(D49="Sí, formalmente",1,IF(D49="Sí, informalmente",0.5,IF(D49="Sí, con indicadores",1,IF(D49="Sí, básico",0.5,IF(D49="Sí, los usa",1,IF(D49="Sí, los conoce",0.5,IF(D49="Parcialmente",0.5,IF(D49="Sí, algunas",0.5,IF(D49="Europa",1,IF(D49="EE.UU.",0.3,IF(D49="Asia",0.1,IF(D49="Mercado interno",0,IF(D49="No exporta",0,IF(D49="App propia",1,IF(D49="App de comprador o proyecto",0.7,IF(D49="Excel",0.4,IF(D49="Ninguno",0,IF(D49="Yute reutilizable",1,IF(D49="Big bags reciclables",0.8,IF(D49="Yute nuevo",0.3,IF(D49="Bolsas papel",0.2,IF(D49="Otro",0.1,IF(D49="En proceso",0.5,IF(D49="En gestión",0.5,IF(D49="No sabe",0.3,IF(D49="No aplica",0.5,IF(D49="No",0,IF(D49="",0,IF(ISTEXT(D49),0.5,0)))))))))))))))))))))))))) | F49: tipo_saco | G49: Entrevista
A50: PPWR | B50: P2 | C50: ¿Los sacos tienen certificación FSC o equivalente? | E50: =IF(D50="Sí",1,IF(D50="Sí, todas",1,IF(D50="Sí, FT",1,IF(D50="Sí, PT",0.6,IF(D50="Sí, formalmente",1,IF(D50="Sí, informalmente",0.5,IF(D50="Sí, con indicadores",1,IF(D50="Sí, básico",0.5,IF(D50="Sí, los usa",1,IF(D50="Sí, los conoce",0.5,IF(D50="Parcialmente",0.5,IF(D50="Sí, algunas",0.5,IF(D50="Europa",1,IF(D50="EE.UU.",0.3,IF(D50="Asia",0.1,IF(D50="Mercado interno",0,IF(D50="No exporta",0,IF(D50="App propia",1,IF(D50="App de comprador o proyecto",0.7,IF(D50="Excel",0.4,IF(D50="Ninguno",0,IF(D50="Yute reutilizable",1,IF(D50="Big bags reciclables",0.8,IF(D50="Yute nuevo",0.3,IF(D50="Bolsas papel",0.2,IF(D50="Otro",0.1,IF(D50="En proceso",0.5,IF(D50="En gestión",0.5,IF(D50="No sabe",0.3,IF(D50="No aplica",0.5,IF(D50="No",0,IF(D50="",0,IF(ISTEXT(D50),0.5,0)))))))))))))))))))))))))) | F50: fsc | G50: Entrevista / proveedor
A52: RESUMEN DE SCORES POR DIMENSIÓN
A53: Dimensión | B53: Score promedio | C53: N° preguntas | D53: Nivel
A54: D1 — Clasificación regulatoria | B54: =IFERROR(AVERAGEIF(E3:E6,">0"),0) | C54: =COUNTIF(E3:E6,">0") | D54: =IF(B54>=0.67,"🟢 Verde",IF(B54>=0.34,"🟡 Amarillo","🔴 Rojo"))
A55: D2 — Trazabilidad y geolocalización | B55: =IFERROR(AVERAGEIF(E7:E13,">0"),0) | C55: =COUNTIF(E7:E13,">0") | D55: =IF(B55>=0.67,"🟢 Verde",IF(B55>=0.34,"🟡 Amarillo","🔴 Rojo"))
A56: D3 — Legalidad de la producción | B56: =IFERROR(AVERAGEIF(E14:E18,">0"),0) | C56: =COUNTIF(E14:E18,">0") | D56: =IF(B56>=0.67,"🟢 Verde",IF(B56>=0.34,"🟡 Amarillo","🔴 Rojo"))
A57: D4 — Riesgo de deforestación | B57: =IFERROR(AVERAGEIF(E19:E21,">0"),0) | C57: =COUNTIF(E19:E21,">0") | D57: =IF(B57>=0.67,"🟢 Verde",IF(B57>=0.34,"🟡 Amarillo","🔴 Rojo"))
A58: D5 — Sistema de debida diligencia | B58: =IFERROR(AVERAGEIF(E22:E25,">0"),0) | C58: =COUNTIF(E22:E25,">0") | D58: =IF(B58>=0.67,"🟢 Verde",IF(B58>=0.34,"🟡 Amarillo","🔴 Rojo"))
A59: D6 — Capacidad organizacional y digital | B59: =IFERROR(AVERAGEIF(E26:E30,">0"),0) | C59: =COUNTIF(E26:E30,">0") | D59: =IF(B59>=0.67,"🟢 Verde",IF(B59>=0.34,"🟡 Amarillo","🔴 Rojo"))
A60: D7 — Posición en la cadena de valor | B60: =IFERROR(AVERAGEIF(E31:E35,">0"),0) | C60: =COUNTIF(E31:E35,">0") | D60: =IF(B60>=0.67,"🟢 Verde",IF(B60>=0.34,"🟡 Amarillo","🔴 Rojo"))
A61: D8 — Gobernanza y participación de socios | B61: =IFERROR(AVERAGEIF(E36:E38,">0"),0) | C61: =COUNTIF(E36:E38,">0") | D61: =IF(B61>=0.67,"🟢 Verde",IF(B61>=0.34,"🟡 Amarillo","🔴 Rojo"))
A62: D9 — Sostenibilidad económica del cumplimiento | B62: =IFERROR(AVERAGEIF(E39:E41,">0"),0) | C62: =COUNTIF(E39:E41,">0") | D62: =IF(B62>=0.67,"🟢 Verde",IF(B62>=0.34,"🟡 Amarillo","🔴 Rojo"))
A63: D10 — Confusión certificación / EUDR | B63: =IFERROR(AVERAGEIF(E42:E44,">0"),0) | C63: =COUNTIF(E42:E44,">0") | D63: =IF(B63>=0.67,"🟢 Verde",IF(B63>=0.34,"🟡 Amarillo","🔴 Rojo"))
A64: D11 — Ecosistema de apoyo externo | B64: =IFERROR(AVERAGEIF(E45:E47,">0"),0) | C64: =COUNTIF(E45:E47,">0") | D64: =IF(B64>=0.67,"🟢 Verde",IF(B64>=0.34,"🟡 Amarillo","🔴 Rojo"))
A65: PPWR — Envases y Packaging (PPWR) | B65: =IFERROR(AVERAGEIF(E48:E50,">0"),0) | C65: =COUNTIF(E48:E50,">0") | D65: =IF(B65>=0.67,"🟢 Verde",IF(B65>=0.34,"🟡 Amarillo","🔴 Rojo"))

Sheet SCORECARDS
A1: SCORECARDS — Índice PVE por organización (0-100)
A2: RUC | B2: Razón Social | C2: PVE Score | D2: Semáforo | E2: Ranking | F2: FOB UE USD | G2: % UE/FOB | H2: Trazab. (D2) | I2: Dilig. (D5) | J2: Capacidad (D6) | K2: Legalidad D3 (OSCE) | L2: Cert (0-1) | M2: PPWR | N2: Depto | O2: Segmento
A3: 20118578415 | B3: CENT.DE COOP.AGR. CAF.VALLES SANDIA LTDA | C3: =ROUND(PONDERADORES!$D$12*G3+PONDERADORES!$D$13*H3+PONDERADORES!$D$14*I3+PONDERADORES!$D$15*J3+PONDERADORES!$D$16*K3+PONDERADORES!$D$17*L3+PONDERADORES!$D$18*M3,1) | D3: =IF(C3<34,"🔴 Critico",IF(C3<67,"🟡 Vulnerable","🟢 Preparado")) | E3: =IFERROR(RANK(C3,C:C,-1),"") | F3: 2553623.3 | G3: =IFERROR(MATRIZ_174!M3,0) | H3: 0 | I3: 0 | J3: 0 | K3: =IFERROR(INDEX(MATRIZ_174!$U:$U,MATCH(A3,MATRIZ_174!$A:$A,0)),"") | L3: =IFERROR(MATRIZ_174!O3,0) | M3: 0 | N3: =IF(AND(F3>0,C3<34),"🔴 UE + Critico",IF(AND(F3>0,C3<67),"🟡 UE + Vulnerable",IF(AND(F3>0,C3>=67),"🟢 UE + Preparado",IF(C3=0,"— Sin dato","Sin exposición UE")))) | O3: PUNO
A4: 20129156083 | B4: COOP AGRARIA CAFET VALLE RIO APURIMAC | C4: =ROUND(PONDERADORES!$D$12*G4+PONDERADORES!$D$13*H4+PONDERADORES!$D$14*I4+PONDERADORES!$D$15*J4+PONDERADORES!$D$16*K4+PONDERADORES!$D$17*L4+PONDERADORES!$D$18*M4,1) | D4: =IF(C4<34,"🔴 Critico",IF(C4<67,"🟡 Vulnerable","🟢 Preparado")) | E4: =IFERROR(RANK(C4,C:C,-1),"") | F4: 0 | G4: =IFERROR(MATRIZ_174!M4,0) | H4: 0 | I4: 0 | J4: 0 | K4: =IFERROR(INDEX(MATRIZ_174!$U:$U,MATCH(A4,MATRIZ_174!$A:$A,0)),"") | L4: =IFERROR(MATRIZ_174!O4,0) | M4: 0 | N4: =IF(AND(F4>0,C4<34),"🔴 UE + Critico",IF(AND(F4>0,C4<67),"🟡 UE + Vulnerable",IF(AND(F4>0,C4>=67),"🟢 UE + Preparado",IF(C4=0,"— Sin dato","Sin exposición UE")))) | O4: AYACUCHO
A5: 20129529530 | B5: COOP AGRARIA CAFETALERA SATIPO LTDA | C5: =ROUND(PONDERADORES!$D$12*G5+PONDERADORES!$D$13*H5+PONDERADORES!$D$14*I5+PONDERADORES!$D$15*J5+PONDERADORES!$D$16*K5+PONDERADORES!$D$17*L5+PONDERADORES!$D$18*M5,1) | D5: =IF(C5<34,"🔴 Critico",IF(C5<67,"🟡 Vulnerable","🟢 Preparado")) | E5: =IFERROR(RANK(C5,C:C,-1),"") | F5: 4801984.1 | G5: =IFERROR(MATRIZ_174!M5,0) | H5: 0 | I5: 0 | J5: 0 | K5: =IFERROR(INDEX(MATRIZ_174!$U:$U,MATCH(A5,MATRIZ_174!$A:$A,0)),"") | L5: =IFERROR(MATRIZ_174!O5,0) | M5: 0 | N5: =IF(AND(F5>0,C5<34),"🔴 UE + Critico",IF(AND(F5>0,C5<67),"🟡 UE + Vulnerable",IF(AND(F5>0,C5>=67),"🟢 UE + Preparado",IF(C5=0,"— Sin dato","Sin exposición UE")))) | O5: JUNIN
A6: 20132489824 | B6: COOPERATIVA AGRARIA CAFETALERA CHANCAMAYO LTDA. N° 008-B-VII | C6: =ROUND(PONDERADORES!$D$12*G6+PONDERADORES!$D$13*H6+PONDERADORES!$D$14*I6+PONDERADORES!$D$15*J6+PONDERADORES!$D$16*K6+PONDERADORES!$D$17*L6+PONDERADORES!$D$18*M6,1) | D6: =IF(C6<34,"🔴 Critico",IF(C6<67,"🟡 Vulnerable","🟢 Preparado")) | E6: =IFERROR(RANK(C6,C:C,-1),"") | F6: =IFERROR(MATRIZ_174!L6,0) | G6: =IFERROR(MATRIZ_174!M6,0) | H6: 0 | I6: 0 | J6: 0 | K6: =IFERROR(INDEX(MATRIZ_174!$U:$U,MATCH(A6,MATRIZ_174!$A:$A,0)),"") | L6: =IFERROR(MATRIZ_174!O6,0) | M6: 0 | N6: =IF(AND(F6>0,C6<34),"🔴 UE + Critico",IF(AND(F6>0,C6<67),"🟡 UE + Vulnerable",IF(AND(F6>0,C6>=67),"🟢 UE + Preparado",IF(C6=0,"— Sin dato","Sin exposición UE")))) | O6: CUSCO
A7: 20132505455 | B7: COOPERATIVA AGRARIA CAFETALERA AGUILAYOC LTDA. 084 | C7: =ROUND(PONDERADORES!$D$12*G7+PONDERADORES!$D$13*H7+PONDERADORES!$D$14*I7+PONDERADORES!$D$15*J7+PONDERADORES!$D$16*K7+PONDERADORES!$D$17*L7+PONDERADORES!$D$18*M7,1) | D7: =IF(C7<34,"🔴 Critico",IF(C7<67,"🟡 Vulnerable","🟢 Preparado")) | E7: =IFERROR(RANK(C7,C:C,-1),"") | F7: =IFERROR(MATRIZ_174!L7,0) | G7: =IFERROR(MATRIZ_174!M7,0) | H7: 0 | I7: 0 | J7: 0 | K7: =IFERROR(INDEX(MATRIZ_174!$U:$U,MATCH(A7,MATRIZ_174!$A:$A,0)),"") | L7: =IFERROR(MATRIZ_174!O7,0) | M7: 0 | N7: =IF(AND(F7>0,C7<34),"🔴 UE + Critico",IF(AND(F7>0,C7<67),"🟡 UE + Vulnerable",IF(AND(F7>0,C7>=67),"🟢 UE + Preparado",IF(C7=0,"— Sin dato","Sin exposición UE")))) | O7: CUSCO
A8: 20132509795 | B8: COOPERATIVA AGRARIA CAFETALERA JOSE OLAYA LTDA N° 252 | C8: =ROUND(PONDERADORES!$D$12*G8+PONDERADORES!$D$13*H8+PONDERADORES!$D$14*I8+PONDERADORES!$D$15*J8+PONDERADORES!$D$16*K8+PONDERADORES!$D$17*L8+PONDERADORES!$D$18*M8,1) | D8: =IF(C8<34,"🔴 Critico",IF(C8<67,"🟡 Vulnerable","🟢 Preparado")) | E8: =IFERROR(RANK(C8,C:C,-1),"") | F8: 1238541.8 | G8: =IFERROR(MATRIZ_174!M8,0) | H8: 0 | I8: 0 | J8: 0 | K8: =IFERROR(INDEX(MATRIZ_174!$U:$U,MATCH(A8,MATRIZ_174!$A:$A,0)),"") | L8: =IFERROR(MATRIZ_174!O8,0) | M8: 0 | N8: =IF(AND(F8>0,C8<34),"🔴 UE + Critico",IF(AND(F8>0,C8<67),"🟡 UE + Vulnerable",IF(AND(F8>0,C8>=67),"🟢 UE + Preparado",IF(C8=0,"— Sin dato","Sin exposición UE")))) | O8: CUSCO
A9: 20132509876 | B9: COOPERATIVA AGRARIA CAFETALERA MARANURA LTDA. 129 | C9: =ROUND(PONDERADORES!$D$12*G9+PONDERADORES!$D$13*H9+PONDERADORES!$D$14*I9+PONDERADORES!$D$15*J9+PONDERADORES!$D$16*K9+PONDERADORES!$D$17*L9+PONDERADORES!$D$18*M9,1) | D9: =IF(C9<34,"🔴 Critico",IF(C9<67,"🟡 Vulnerable","🟢 Preparado")) | E9: =IFERROR(RANK(C9,C:C,-1),"") | F9: 0 | G9: =IFERROR(MATRIZ_174!M9,0) | H9: 0 | I9: 0 | J9: 0 | K9: =IFERROR(INDEX(MATRIZ_174!$U:$U,MATCH(A9,MATRIZ_174!$A:$A,0)),"") | L9: =IFERROR(MATRIZ_174!O9,0) | M9: 0 | N9: =IF(AND(F9>0,C9<34),"🔴 UE + Critico",IF(AND(F9>0,C9<67),"🟡 UE + Vulnerable",IF(AND(F9>0,C9>=67),"🟢 UE + Preparado",IF(C9=0,"— Sin dato","Sin exposición UE")))) | O9: CUSCO
A10: 20132517119 | B10: COOPERATIVA AGRARIA CAFETALERA MATEO PUMACAHUA LTDA N° 185 | C10: =ROUND(PONDERADORES!$D$12*G10+PONDERADORES!$D$13*H10+PONDERADORES!$D$14*I10+PONDERADORES!$D$15*J10+PONDERADORES!$D$16*K10+PONDERADORES!$D$17*L10+PONDERADORES!$D$18*M10,1) | D10: =IF(C10<34,"🔴 Critico",IF(C10<67,"🟡 Vulnerable","🟢 Preparado")) | E10: =IFERROR(RANK(C10,C:C,-1),"") | F10: 0 | G10: =IFERROR(MATRIZ_174!M10,0) | H10: 0 | I10: 0 | J10: 0 | K10: =IFERROR(INDEX(MATRIZ_174!$U:$U,MATCH(A10,MATRIZ_174!$A:$A,0)),"") | L10: =IFERROR(MATRIZ_174!O10,0) | M10: 0 | N10: =IF(AND(F10>0,C10<34),"🔴 UE + Critico",IF(AND(F10>0,C10<67),"🟡 UE + Vulnerable",IF(AND(F10>0,C10>=67),"🟢 UE + Preparado",IF(C10=0,"— Sin dato","Sin exposición UE")))) | O10: CUSCO
A11: 20136201132 | B11: COOPERATIVA AGRARIA CAFETALERA ALTO URUBAMBA LTDA N° 239 | C11: =ROUND(PONDERADORES!$D$12*G11+PONDERADORES!$D$13*H11+PONDERADORES!$D$14*I11+PONDERADORES!$D$15*J11+PONDERADORES!$D$16*K11+PONDERADORES!$D$17*L11+PONDERADORES!$D$18*M11,1) | D11: =IF(C11<34,"🔴 Critico",IF(C11<67,"🟡 Vulnerable","🟢 Preparado")) | E11: =IFERROR(RANK(C11,C:C,-1),"") | F11: =IFERROR(MATRIZ_174!L11,0) | G11: =IFERROR(MATRIZ_174!M11,0) | H11: 0 | I11: 0 | J11: 0 | K11: =IFERROR(INDEX(MATRIZ_174!$U:$U,MATCH(A11,MATRIZ_174!$A:$A,0)),"") | L11: =IFERROR(MATRIZ_174!O11,0) | M11: 0 | N11: =IF(AND(F11>0,C11<34),"🔴 UE + Critico",IF(AND(F11>0,C11<67),"🟡 UE + Vulnerable",IF(AND(F11>0,C11>=67),"🟢 UE + Preparado",IF(C11=0,"— Sin dato","Sin exposición UE")))) | O11: CUSCO
A12: 20136201213 | B12: CENTRAL DE COOPERATIVAS AGRARIAS CAFETALERAS COCLA LTDA. N° | C12: =ROUND(PONDERADORES!$D$12*G12+PONDERADORES!$D$13*H12+PONDERADORES!$D$14*I12+PONDERADORES!$D$15*J12+PONDERADORES!$D$16*K12+PONDERADORES!$D$17*L12+PONDERADORES!$D$18*M12,1) | D12: =IF(C12<34,"🔴 Critico",IF(C12<67,"🟡 Vulnerable","🟢 Preparado")) | E12: =IFERROR(RANK(C12,C:C,-1),"") | F12: 894391.27 | G12: =IFERROR(MATRIZ_174!M12,0) | H12: 0 | I12: 0 | J12: 0 | K12: =IFERROR(INDEX(MATRIZ_174!$U:$U,MATCH(A12,MATRIZ_174!$A:$A,0)),"") | L12: =IFERROR(MATRIZ_174!O12,0) | M12: 0 | N12: =IF(AND(F12>0,C12<34),"🔴 UE + Critico",IF(AND(F12>0,C12<67),"🟡 UE + Vulnerable",IF(AND(F12>0,C12>=67),"🟢 UE + Preparado",IF(C12=0,"— Sin dato","Sin exposición UE")))) | O12: CUSCO
A13: 20140292657 | B13: COOPERATIVA AGRARIA CAFETALERA CCOCHAPAMPA LTDA. | C13: =ROUND(PONDERADORES!$D$12*G13+PONDERADORES!$D$13*H13+PONDERADORES!$D$14*I13+PONDERADORES!$D$15*J13+PONDERADORES!$D$16*K13+PONDERADORES!$D$17*L13+PONDERADORES!$D$18*M13,1) | D13: =IF(C13<34,"🔴 Critico",IF(C13<67,"🟡 Vulnerable","🟢 Preparado")) | E13: =IFERROR(RANK(C13,C:C,-1),"") | F13: 0 | G13: =IFERROR(MATRIZ_174!M13,0) | H13: 0 | I13: 0 | J13: 0 | K13: =IFERROR(INDEX(MATRIZ_174!$U:$U,MATCH(A13,MATRIZ_174!$A:$A,0)),"") | L13: =IFERROR(MATRIZ_174!O13,0) | M13: 0 | N13: =IF(AND(F13>0,C13<34),"🔴 UE + Critico",IF(AND(F13>0,C13<67),"🟡 UE + Vulnerable",IF(AND(F13>0,C13>=67),"🟢 UE + Preparado",IF(C13=0,"— Sin dato","Sin exposición UE")))) | O13: CUSCO
A14: 20143692010 | B14: COOPERATIVA AGRARIA EL QUINACHO LTDA. N° 078 | C14: =ROUND(PONDERADORES!$D$12*G14+PONDERADORES!$D$13*H14+PONDERADORES!$D$14*I14+PONDERADORES!$D$15*J14+PONDERADORES!$D$16*K14+PONDERADORES!$D$17*L14+PONDERADORES!$D$18*M14,1) | D14: =IF(C14<34,"🔴 Critico",IF(C14<67,"🟡 Vulnerable","🟢 Preparado")) | E14: =IFERROR(RANK(C14,C:C,-1),"") | F14: 2015347.3 | G14: =IFERROR(MATRIZ_174!M14,0) | H14: 0 | I14: 0 | J14: 0 | K14: =IFERROR(INDEX(MATRIZ_174!$U:$U,MATCH(A14,MATRIZ_174!$A:$A,0)),"") | L14: =IFERROR(MATRIZ_174!O14,0) | M14: 0 | N14: =IF(AND(F14>0,C14<34),"🔴 UE + Critico",IF(AND(F14>0,C14<67),"🟡 UE + Vulnerable",IF(AND(F14>0,C14>=67),"🟢 UE + Preparado",IF(C14=0,"— Sin dato","Sin exposición UE")))) | O14: AYACUCHO
A15: 20145484597 | B15: COOPERATIVA AGRARIA CAFETALERA SAN IGNACIO LTDA. | C15: =ROUND(PONDERADORES!$D$12*G15+PONDERADORES!$D$13*H15+PONDERADORES!$D$14*I15+PONDERADORES!$D$15*J15+PONDERADORES!$D$16*K15+PONDERADORES!$D$17*L15+PONDERADORES!$D$18*M15,1) | D15: =IF(C15<34,"🔴 Critico",IF(C15<67,"🟡 Vulnerable","🟢 Preparado")) | E15: =IFERROR(RANK(C15,C:C,-1),"") | F15: =IFERROR(MATRIZ_174!L15,0) | G15: =IFERROR(MATRIZ_174!M15,0) | H15: 0 | I15: 0 | J15: 0 | K15: =IFERROR(INDEX(MATRIZ_174!$U:$U,MATCH(A15,MATRIZ_174!$A:$A,0)),"") | L15: =IFERROR(MATRIZ_174!O15,0) | M15: 0 | N15: =IF(AND(F15>0,C15<34),"🔴 UE + Critico",IF(AND(F15>0,C15<67),"🟡 UE + Vulnerable",IF(AND(F15>0,C15>=67),"🟢 UE + Preparado",IF(C15=0,"— Sin dato","Sin exposición UE")))) | O15: PUNO
A16: 20146696041 | B16: COOP AGRARIA CAFET JOSE GABRIEL CONDORCA | C16: =ROUND(PONDERADORES!$D$12*G16+PONDERADORES!$D$13*H16+PONDERADORES!$D$14*I16+PONDERADORES!$D$15*J16+PONDERADORES!$D$16*K16+PONDERADORES!$D$17*L16+PONDERADORES!$D$18*M16,1) | D16: =IF(C16<34,"🔴 Critico",IF(C16<67,"🟡 Vulnerable","🟢 Preparado")) | E16: =IFERROR(RANK(C16,C:C,-1),"") | F16: =IFERROR(MATRIZ_174!L16,0) | G16: =IFERROR(MATRIZ_174!M16,0) | H16: 0 | I16: 0 | J16: 0 | K16: =IFERROR(INDEX(MATRIZ_174!$U:$U,MATCH(A16,MATRIZ_174!$A:$A,0)),"") | L16: =IFERROR(MATRIZ_174!O16,0) | M16: 0 | N16: =IF(AND(F16>0,C16<34),"🔴 UE + Critico",IF(AND(F16>0,C16<67),"🟡 UE + Vulnerable",IF(AND(F16>0,C16>=67),"🟢 UE + Preparado",IF(C16=0,"— Sin dato","Sin exposición UE")))) | O16: PIURA
A17: 20147443120 | B17: COOPERATIVA AGRARIA CAFETALERA TIRIJUAY PAVAYOC LTDA 013-B-V | C17: =ROUND(PONDERADORES!$D$12*G17+PONDERADORES!$D$13*H17+PONDERADORES!$D$14*I17+PONDERADORES!$D$15*J17+PONDERADORES!$D$16*K17+PONDERADORES!$D$17*L17+PONDERADORES!$D$18*M17,1) | D17: =IF(C17<34,"🔴 Critico",IF(C17<67,"🟡 Vulnerable","🟢 Preparado")) | E17: =IFERROR(RANK(C17,C:C,-1),"") | F17: =IFERROR(MATRIZ_174!L17,0) | G17: =IFERROR(MATRIZ_174!M17,0) | H17: 0 | I17: 0 | J17: 0 | K17: =IFERROR(INDEX(MATRIZ_174!$U:$U,MATCH(A17,MATRIZ_174!$A:$A,0)),"") | L17: =IFERROR(MATRIZ_174!O17,0) | M17: 0 | N17: =IF(AND(F17>0,C17<34),"🔴 UE + Critico",IF(AND(F17>0,C17<67),"🟡 UE + Vulnerable",IF(AND(F17>0,C17>=67),"🟢 UE + Preparado",IF(C17=0,"— Sin dato","Sin exposición UE")))) | O17: CUSCO
A18: 20166786861 | B18: COMITE CENTRAL DE PRODUCTORES AGROPECUARIOS DE SAN ALEJANDRO | C18: =ROUND(PONDERADORES!$D$12*G18+PONDERADORES!$D$13*H18+PONDERADORES!$D$14*I18+PONDERADORES!$D$15*J18+PONDERADORES!$D$16*K18+PONDERADORES!$D$17*L18+PONDERADORES!$D$18*M18,1) | D18: =IF(C18<34,"🔴 Critico",IF(C18<67,"🟡 Vulnerable","🟢 Preparado")) | E18: =IFERROR(RANK(C18,C:C,-1),"") | F18: =IFERROR(MATRIZ_174!L18,0) | G18: =IFERROR(MATRIZ_174!M18,0) | H18: 0 | I18: 0 | J18: 0 | K18: =IFERROR(INDEX(MATRIZ_174!$U:$U,MATCH(A18,MATRIZ_174!$A:$A,0)),"") | L18: =IFERROR(MATRIZ_174!O18,0) | M18: 0 | N18: =IF(AND(F18>0,C18<34),"🔴 UE + Critico",IF(AND(F18>0,C18<67),"🟡 UE + Vulnerable",IF(AND(F18>0,C18>=67),"🟢 UE + Preparado",IF(C18=0,"— Sin dato","Sin exposición UE")))) | O18: UCAYALI
A19: 20170142773 | B19: COOPERATIVA AGRARIA CAFETALERA BAGUA GRANDE LIMITADA | C19: =ROUND(PONDERADORES!$D$12*G19+PONDERADORES!$D$13*H19+PONDERADORES!$D$14*I19+PONDERADORES!$D$15*J19+PONDERADORES!$D$16*K19+PONDERADORES!$D$17*L19+PONDERADORES!$D$18*M19,1) | D19: =IF(C19<34,"🔴 Critico",IF(C19<67,"🟡 Vulnerable","🟢 Preparado")) | E19: =IFERROR(RANK(C19,C:C,-1),"") | F19: 4535378.4 | G19: =IFERROR(MATRIZ_174!M19,0) | H19: 0 | I19: 0 | J19: 0 | K19: =IFERROR(INDEX(MATRIZ_174!$U:$U,MATCH(A19,MATRIZ_174!$A:$A,0)),"") | L19: =IFERROR(MATRIZ_174!O19,0) | M19: 0 | N19: =IF(AND(F19>0,C19<34),"🔴 UE + Critico",IF(AND(F19>0,C19<67),"🟡 UE + Vulnerable",IF(AND(F19>0,C19>=67),"🟢 UE + Preparado",IF(C19=0,"— Sin dato","Sin exposición UE")))) | O19: AMAZONAS
A20: 20200880448 | B20: COOPERATIVA AGRARIA CAFETALERA JORGE CHAVEZ LTDA | C20: =ROUND(PONDERADORES!$D$12*G20+PONDERADORES!$D$13*H20+PONDERADORES!$D$14*I20+PONDERADORES!$D$15*J20+PONDERADORES!$D$16*K20+PONDERADORES!$D$17*L20+PONDERADORES!$D$18*M20,1) | D20: =IF(C20<34,"🔴 Critico",IF(C20<67,"🟡 Vulnerable","🟢 Preparado")) | E20: =IFERROR(RANK(C20,C:C,-1),"") | F20: =IFERROR(MATRIZ_174!L20,0) | G20: =IFERROR(MATRIZ_174!M20,0) | H20: 0 | I20: 0 | J20: 0 | K20: =IFERROR(INDEX(MATRIZ_174!$U:$U,MATCH(A20,MATRIZ_174!$A:$A,0)),"") | L20: =IFERROR(MATRIZ_174!O20,0) | M20: 0 | N20: =IF(AND(F20>0,C20<34),"🔴 UE + Critico",IF(AND(F20>0,C20<67),"🟡 UE + Vulnerable",IF(AND(F20>0,C20>=67),"🟢 UE + Preparado",IF(C20=0,"— Sin dato","Sin exposición UE")))) | O20: CUSCO
A21: 20352417018 | B21: COOPERATIVA AGRARIA DE CACAOTEROS TECNIFICADOS DE PADRE ABAD | C21: =ROUND(PONDERADORES!$D$12*G21+PONDERADORES!$D$13*H21+PONDERADORES!$D$14*I21+PONDERADORES!$D$15*J21+PONDERADORES!$D$16*K21+PONDERADORES!$D$17*L21+PONDERADORES!$D$18*M21,1) | D21: =IF(C21<34,"🔴 Critico",IF(C21<67,"🟡 Vulnerable","🟢 Preparado")) | E21: =IFERROR(RANK(C21,C:C,-1),"") | F21: 0 | G21: =IFERROR(MATRIZ_174!M21,0) | H21: 0 | I21: 0 | J21: 0 | K21: =IFERROR(INDEX(MATRIZ_174!$U:$U,MATCH(A21,MATRIZ_174!$A:$A,0)),"") | L21: =IFERROR(MATRIZ_174!O21,0) | M21: 0 | N21: =IF(AND(F21>0,C21<34),"🔴 UE + Critico",IF(AND(F21>0,C21<67),"🟡 UE + Vulnerable",IF(AND(F21>0,C21>=67),"🟢 UE + Preparado",IF(C21=0,"— Sin dato","Sin exposición UE")))) | O21: UCAYALI
A22: 20352423921 | B22: COOPERATIVA AGRARIA CAFETALERA DIVISORIA LTDA | C22: =ROUND(PONDERADORES!$D$12*G22+PONDERADORES!$D$13*H22+PONDERADORES!$D$14*I22+PONDERADORES!$D$15*J22+PONDERADORES!$D$16*K22+PONDERADORES!$D$17*L22+PONDERADORES!$D$18*M22,1) | D22: =IF(C22<34,"🔴 Critico",IF(C22<67,"🟡 Vulnerable","🟢 Preparado")) | E22: =IFERROR(RANK(C22,C:C,-1),"") | F22: 0 | G22: =IFERROR(MATRIZ_174!M22,0) | H22: 0 | I22: 0 | J22: 0 | K22: =IFERROR(INDEX(MATRIZ_174!$U:$U,MATCH(A22,MATRIZ_174!$A:$A,0)),"") | L22: =IFERROR(MATRIZ_174!O22,0) | M22: 0 | N22: =IF(AND(F22>0,C22<34),"🔴 UE + Critico",IF(AND(F22>0,C22<67),"🟡 UE + Vulnerable",IF(AND(F22>0,C22>=67),"🟢 UE + Preparado",IF(C22=0,"— Sin dato","Sin exposición UE")))) | O22: HUANUCO
A23: 20393152207 | B23: COOPERATIVA AGRO INDUSTRIAL APCTVASH | C23: =ROUND(PONDERADORES!$D$12*G23+PONDERADORES!$D$13*H23+PONDERADORES!$D$14*I23+PONDERADORES!$D$15*J23+PONDERADORES!$D$16*K23+PONDERADORES!$D$17*L23+PONDERADORES!$D$18*M23,1) | D23: =IF(C23<34,"🔴 Critico",IF(C23<67,"🟡 Vulnerable","🟢 Preparado")) | E23: =IFERROR(RANK(C23,C:C,-1),"") | F23: =IFERROR(MATRIZ_174!L23,0) | G23: =IFERROR(MATRIZ_174!M23,0) | H23: 0 | I23: 0 | J23: 0 | K23: =IFERROR(INDEX(MATRIZ_174!$U:$U,MATCH(A23,MATRIZ_174!$A:$A,0)),"") | L23: =IFERROR(MATRIZ_174!O23,0) | M23: 0 | N23: =IF(AND(F23>0,C23<34),"🔴 UE + Critico",IF(AND(F23>0,C23<67),"🟡 UE + Vulnerable",IF(AND(F23>0,C23>=67),"🟢 UE + Preparado",IF(C23=0,"— Sin dato","Sin exposición UE")))) | O23: UCAYALI
A24: 20393593670 | B24: COMITE CENTRAL CON DESARROLLO AL FUTURO DE CURIMANA | C24: =ROUND(PONDERADORES!$D$12*G24+PONDERADORES!$D$13*H24+PONDERADORES!$D$14*I24+PONDERADORES!$D$15*J24+PONDERADORES!$D$16*K24+PONDERADORES!$D$17*L24+PONDERADORES!$D$18*M24,1) | D24: =IF(C24<34,"🔴 Critico",IF(C24<67,"🟡 Vulnerable","🟢 Preparado")) | E24: =IFERROR(RANK(C24,C:C,-1),"") | F24: 0 | G24: =IFERROR(MATRIZ_174!M24,0) | H24: 0 | I24: 0 | J24: 0 | K24: =IFERROR(INDEX(MATRIZ_174!$U:$U,MATCH(A24,MATRIZ_174!$A:$A,0)),"") | L24: =IFERROR(MATRIZ_174!O24,0) | M24: 0 | N24: =IF(AND(F24>0,C24<34),"🔴 UE + Critico",IF(AND(F24>0,C24<67),"🟡 UE + Vulnerable",IF(AND(F24>0,C24>=67),"🟢 UE + Preparado",IF(C24=0,"— Sin dato","Sin exposición UE")))) | O24: UCAYALI
A25: 20393692228 | B25: COOPERATIVA AGRARIA CACAOTERA SAN ALEJANDRO LTDA | C25: =ROUND(PONDERADORES!$D$12*G25+PONDERADORES!$D$13*H25+PONDERADORES!$D$14*I25+PONDERADORES!$D$15*J25+PONDERADORES!$D$16*K25+PONDERADORES!$D$17*L25+PONDERADORES!$D$18*M25,1) | D25: =IF(C25<34,"🔴 Critico",IF(C25<67,"🟡 Vulnerable","🟢 Preparado")) | E25: =IFERROR(RANK(C25,C:C,-1),"") | F25: 0 | G25: =IFERROR(MATRIZ_174!M25,0) | H25: 0 | I25: 0 | J25: 0 | K25: =IFERROR(INDEX(MATRIZ_174!$U:$U,MATCH(A25,MATRIZ_174!$A:$A,0)),"") | L25: =IFERROR(MATRIZ_174!O25,0) | M25: 0 | N25: =IF(AND(F25>0,C25<34),"🔴 UE + Critico",IF(AND(F25>0,C25<67),"🟡 UE + Vulnerable",IF(AND(F25>0,C25>=67),"🟢 UE + Preparado",IF(C25=0,"— Sin dato","Sin exposición UE")))) | O25: UCAYALI
A26: 20393786044 | B26: COOPERATIVA AGRARIA CAFETALERA COORDILLERA AZUL DE UCAYALI L | C26: =ROUND(PONDERADORES!$D$12*G26+PONDERADORES!$D$13*H26+PONDERADORES!$D$14*I26+PONDERADORES!$D$15*J26+PONDERADORES!$D$16*K26+PONDERADORES!$D$17*L26+PONDERADORES!$D$18*M26,1) | D26: =IF(C26<34,"🔴 Critico",IF(C26<67,"🟡 Vulnerable","🟢 Preparado")) | E26: =IFERROR(RANK(C26,C:C,-1),"") | F26: =IFERROR(MATRIZ_174!L26,0) | G26: =IFERROR(MATRIZ_174!M26,0) | H26: 0 | I26: 0 | J26: 0 | K26: =IFERROR(INDEX(MATRIZ_174!$U:$U,MATCH(A26,MATRIZ_174!$A:$A,0)),"") | L26: =IFERROR(MATRIZ_174!O26,0) | M26: 0 | N26: =IF(AND(F26>0,C26<34),"🔴 UE + Critico",IF(AND(F26>0,C26<67),"🟡 UE + Vulnerable",IF(AND(F26>0,C26>=67),"🟢 UE + Preparado",IF(C26=0,"— Sin dato","Sin exposición UE")))) | O26: UCAYALI
A27: 20393816211 | B27: COOPERATIVA AGRARIA SAN JUAN BAUTISTA | C27: =ROUND(PONDERADORES!$D$12*G27+PONDERADORES!$D$13*H27+PONDERADORES!$D$14*I27+PONDERADORES!$D$15*J27+PONDERADORES!$D$16*K27+PONDERADORES!$D$17*L27+PONDERADORES!$D$18*M27,1) | D27: =IF(C27<34,"🔴 Critico",IF(C27<67,"🟡 Vulnerable","🟢 Preparado")) | E27: =IFERROR(RANK(C27,C:C,-1),"") | F27: 0 | G27: =IFERROR(MATRIZ_174!M27,0) | H27: 0 | I27: 0 | J27: 0 | K27: =IFERROR(INDEX(MATRIZ_174!$U:$U,MATCH(A27,MATRIZ_174!$A:$A,0)),"") | L27: =IFERROR(MATRIZ_174!O27,0) | M27: 0 | N27: =IF(AND(F27>0,C27<34),"🔴 UE + Critico",IF(AND(F27>0,C27<67),"🟡 UE + Vulnerable",IF(AND(F27>0,C27>=67),"🟢 UE + Preparado",IF(C27=0,"— Sin dato","Sin exposición UE")))) | O27: UCAYALI
A28: 20393882868 | B28: COOPERATIVA AGRARIA ASCAH | C28: =ROUND(PONDERADORES!$D$12*G28+PONDERADORES!$D$13*H28+PONDERADORES!$D$14*I28+PONDERADORES!$D$15*J28+PONDERADORES!$D$16*K28+PONDERADORES!$D$17*L28+PONDERADORES!$D$18*M28,1) | D28: =IF(C28<34,"🔴 Critico",IF(C28<67,"🟡 Vulnerable","🟢 Preparado")) | E28: =IFERROR(RANK(C28,C:C,-1),"") | F28: =IFERROR(MATRIZ_174!L28,0) | G28: =IFERROR(MATRIZ_174!M28,0) | H28: 0 | I28: 0 | J28: 0 | K28: =IFERROR(INDEX(MATRIZ_174!$U:$U,MATCH(A28,MATRIZ_174!$A:$A,0)),"") | L28: =IFERROR(MATRIZ_174!O28,0) | M28: 0 | N28: =IF(AND(F28>0,C28<34),"🔴 UE + Critico",IF(AND(F28>0,C28<67),"🟡 UE + Vulnerable",IF(AND(F28>0,C28>=67),"🟢 UE + Preparado",IF(C28=0,"— Sin dato","Sin exposición UE")))) | O28: UCAYALI
A29: 20393972000 | B29: ASOCIACION DE MUJERES EMPRENDEDORAS FLOR DE BOQUERON | C29: =ROUND(PONDERADORES!$D$12*G29+PONDERADORES!$D$13*H29+PONDERADORES!$D$14*I29+PONDERADORES!$D$15*J29+PONDERADORES!$D$16*K29+PONDERADORES!$D$17*L29+PONDERADORES!$D$18*M29,1) | D29: =IF(C29<34,"🔴 Critico",IF(C29<67,"🟡 Vulnerable","🟢 Preparado")) | E29: =IFERROR(RANK(C29,C:C,-1),"") | F29: =IFERROR(MATRIZ_174!L29,0) | G29: =IFERROR(MATRIZ_174!M29,0) | H29: 0 | I29: 0 | J29: 0 | K29: =IFERROR(INDEX(MATRIZ_174!$U:$U,MATCH(A29,MATRIZ_174!$A:$A,0)),"") | L29: =IFERROR(MATRIZ_174!O29,0) | M29: 0 | N29: =IF(AND(F29>0,C29<34),"🔴 UE + Critico",IF(AND(F29>0,C29<67),"🟡 UE + Vulnerable",IF(AND(F29>0,C29>=67),"🟢 UE + Preparado",IF(C29=0,"— Sin dato","Sin exposición UE")))) | O29: UCAYALI
A30: 20447888701 | B30: COOPERATIVA AGRARIA INDUSTRIAL SAN GABAN LTDA. | C30: =ROUND(PONDERADORES!$D$12*G30+PONDERADORES!$D$13*H30+PONDERADORES!$D$14*I30+PONDERADORES!$D$15*J30+PONDERADORES!$D$16*K30+PONDERADORES!$D$17*L30+PONDERADORES!$D$18*M30,1) | D30: =IF(C30<34,"🔴 Critico",IF(C30<67,"🟡 Vulnerable","🟢 Preparado")) | E30: =IFERROR(RANK(C30,C:C,-1),"") | F30: =IFERROR(MATRIZ_174!L30,0) | G30: =IFERROR(MATRIZ_174!M30,0) | H30: 0 | I30: 0 | J30: 0 | K30: =IFERROR(INDEX(MATRIZ_174!$U:$U,MATCH(A30,MATRIZ_174!$A:$A,0)),"") | L30: =IFERROR(MATRIZ_174!O30,0) | M30: 0 | N30: =IF(AND(F30>0,C30<34),"🔴 UE + Critico",IF(AND(F30>0,C30<67),"🟡 UE + Vulnerable",IF(AND(F30>0,C30>=67),"🟢 UE + Preparado",IF(C30=0,"— Sin dato","Sin exposición UE")))) | O30: PUNO
A31: 20450189201 | B31: COOPERATIVA DE SERVICIOS MULTIPLES FRUTOS DE SELVA | C31: =ROUND(PONDERADORES!$D$12*G31+PONDERADORES!$D$13*H31+PONDERADORES!$D$14*I31+PONDERADORES!$D$15*J31+PONDERADORES!$D$16*K31+PONDERADORES!$D$17*L31+PONDERADORES!$D$18*M31,1) | D31: =IF(C31<34,"🔴 Critico",IF(C31<67,"🟡 Vulnerable","🟢 Preparado")) | E31: =IFERROR(RANK(C31,C:C,-1),"") | F31: 0 | G31: =IFERROR(MATRIZ_174!M31,0) | H31: 0 | I31: 0 | J31: 0 | K31: =IFERROR(INDEX(MATRIZ_174!$U:$U,MATCH(A31,MATRIZ_174!$A:$A,0)),"") | L31: =IFERROR(MATRIZ_174!O31,0) | M31: 0 | N31: =IF(AND(F31>0,C31<34),"🔴 UE + Critico",IF(AND(F31>0,C31<67),"🟡 UE + Vulnerable",IF(AND(F31>0,C31>=67),"🟢 UE + Preparado",IF(C31=0,"— Sin dato","Sin exposición UE")))) | O31: SAN MARTIN
A32: 20450207544 | B32: COOPERATIVA AGRARIA UCHIZA LTDA | C32: =ROUND(PONDERADORES!$D$12*G32+PONDERADORES!$D$13*H32+PONDERADORES!$D$14*I32+PONDERADORES!$D$15*J32+PONDERADORES!$D$16*K32+PONDERADORES!$D$17*L32+PONDERADORES!$D$18*M32,1) | D32: =IF(C32<34,"🔴 Critico",IF(C32<67,"🟡 Vulnerable","🟢 Preparado")) | E32: =IFERROR(RANK(C32,C:C,-1),"") | F32: 0 | G32: =IFERROR(MATRIZ_174!M32,0) | H32: 0 | I32: 0 | J32: 0 | K32: =IFERROR(INDEX(MATRIZ_174!$U:$U,MATCH(A32,MATRIZ_174!$A:$A,0)),"") | L32: =IFERROR(MATRIZ_174!O32,0) | M32: 0 | N32: =IF(AND(F32>0,C32<34),"🔴 UE + Critico",IF(AND(F32>0,C32<67),"🟡 UE + Vulnerable",IF(AND(F32>0,C32>=67),"🟢 UE + Preparado",IF(C32=0,"— Sin dato","Sin exposición UE")))) | O32: SAN MARTIN
A33: 20450242021 | B33: COOPERATIVA DE SERVICIOS MULTIPLES CAPEMA | C33: =ROUND(PONDERADORES!$D$12*G33+PONDERADORES!$D$13*H33+PONDERADORES!$D$14*I33+PONDERADORES!$D$15*J33+PONDERADORES!$D$16*K33+PONDERADORES!$D$17*L33+PONDERADORES!$D$18*M33,1) | D33: =IF(C33<34,"🔴 Critico",IF(C33<67,"🟡 Vulnerable","🟢 Preparado")) | E33: =IFERROR(RANK(C33,C:C,-1),"") | F33: 0 | G33: =IFERROR(MATRIZ_174!M33,0) | H33: 0 | I33: 0 | J33: 0 | K33: =IFERROR(INDEX(MATRIZ_174!$U:$U,MATCH(A33,MATRIZ_174!$A:$A,0)),"") | L33: =IFERROR(MATRIZ_174!O33,0) | M33: 0 | N33: =IF(AND(F33>0,C33<34),"🔴 UE + Critico",IF(AND(F33>0,C33<67),"🟡 UE + Vulnerable",IF(AND(F33>0,C33>=67),"🟢 UE + Preparado",IF(C33=0,"— Sin dato","Sin exposición UE")))) | O33: SAN MARTIN
A34: 20450319423 | B34: COOPERATIVA AGRARIA DE SERVICIOS MULTIPLES CAFE DONCEL | C34: =ROUND(PONDERADORES!$D$12*G34+PONDERADORES!$D$13*H34+PONDERADORES!$D$14*I34+PONDERADORES!$D$15*J34+PONDERADORES!$D$16*K34+PONDERADORES!$D$17*L34+PONDERADORES!$D$18*M34,1) | D34: =IF(C34<34,"🔴 Critico",IF(C34<67,"🟡 Vulnerable","🟢 Preparado")) | E34: =IFERROR(RANK(C34,C:C,-1),"") | F34: =IFERROR(MATRIZ_174!L34,0) | G34: =IFERROR(MATRIZ_174!M34,0) | H34: 0 | I34: 0 | J34: 0 | K34: =IFERROR(INDEX(MATRIZ_174!$U:$U,MATCH(A34,MATRIZ_174!$A:$A,0)),"") | L34: =IFERROR(MATRIZ_174!O34,0) | M34: 0 | N34: =IF(AND(F34>0,C34<34),"🔴 UE + Critico",IF(AND(F34>0,C34<67),"🟡 UE + Vulnerable",IF(AND(F34>0,C34>=67),"🟢 UE + Preparado",IF(C34=0,"— Sin dato","Sin exposición UE")))) | O34: SAN MARTIN
A35: 20452774705 | B35: COOPERATIVA AGRARIA CACAO VRAE | C35: =ROUND(PONDERADORES!$D$12*G35+PONDERADORES!$D$13*H35+PONDERADORES!$D$14*I35+PONDERADORES!$D$15*J35+PONDERADORES!$D$16*K35+PONDERADORES!$D$17*L35+PONDERADORES!$D$18*M35,1) | D35: =IF(C35<34,"🔴 Critico",IF(C35<67,"🟡 Vulnerable","🟢 Preparado")) | E35: =IFERROR(RANK(C35,C:C,-1),"") | F35: 965726.35 | G35: =IFERROR(MATRIZ_174!M35,0) | H35: 0 | I35: 0 | J35: 0 | K35: =IFERROR(INDEX(MATRIZ_174!$U:$U,MATCH(A35,MATRIZ_174!$A:$A,0)),"") | L35: =IFERROR(MATRIZ_174!O35,0) | M35: 0 | N35: =IF(AND(F35>0,C35<34),"🔴 UE + Critico",IF(AND(F35>0,C35<67),"🟡 UE + Vulnerable",IF(AND(F35>0,C35>=67),"🟢 UE + Preparado",IF(C35=0,"— Sin dato","Sin exposición UE")))) | O35: CUSCO
A36: 20479595276 | B36: COOPERATIVA AGRARIA CAFETALERA CASIL LTDA. | C36: =ROUND(PONDERADORES!$D$12*G36+PONDERADORES!$D$13*H36+PONDERADORES!$D$14*I36+PONDERADORES!$D$15*J36+PONDERADORES!$D$16*K36+PONDERADORES!$D$17*L36+PONDERADORES!$D$18*M36,1) | D36: =IF(C36<34,"🔴 Critico",IF(C36<67,"🟡 Vulnerable","🟢 Preparado")) | E36: =IFERROR(RANK(C36,C:C,-1),"") | F36: 965167.45 | G36: =IFERROR(MATRIZ_174!M36,0) | H36: 0 | I36: 0 | J36: 0 | K36: =IFERROR(INDEX(MATRIZ_174!$U:$U,MATCH(A36,MATRIZ_174!$A:$A,0)),"") | L36: =IFERROR(MATRIZ_174!O36,0) | M36: 0 | N36: =IF(AND(F36>0,C36<34),"🔴 UE + Critico",IF(AND(F36>0,C36<67),"🟡 UE + Vulnerable",IF(AND(F36>0,C36>=67),"🟢 UE + Preparado",IF(C36=0,"— Sin dato","Sin exposición UE")))) | O36: CAJAMARCA
A37: 20479622699 | B37: COOPERATIVA AGRARIA JUAN MARCO EL PALTO | C37: =ROUND(PONDERADORES!$D$12*G37+PONDERADORES!$D$13*H37+PONDERADORES!$D$14*I37+PONDERADORES!$D$15*J37+PONDERADORES!$D$16*K37+PONDERADORES!$D$17*L37+PONDERADORES!$D$18*M37,1) | D37: =IF(C37<34,"🔴 Critico",IF(C37<67,"🟡 Vulnerable","🟢 Preparado")) | E37: =IFERROR(RANK(C37,C:C,-1),"") | F37: 0 | G37: =IFERROR(MATRIZ_174!M37,0) | H37: 0 | I37: 0 | J37: 0 | K37: =IFERROR(INDEX(MATRIZ_174!$U:$U,MATCH(A37,MATRIZ_174!$A:$A,0)),"") | L37: =IFERROR(MATRIZ_174!O37,0) | M37: 0 | N37: =IF(AND(F37>0,C37<34),"🔴 UE + Critico",IF(AND(F37>0,C37<67),"🟡 UE + Vulnerable",IF(AND(F37>0,C37>=67),"🟢 UE + Preparado",IF(C37=0,"— Sin dato","Sin exposición UE")))) | O37: AMAZONAS
A38: 20479856258 | B38: ASOCIACION DE PRODUCTORES AGROPECUARIOS LUIS SOLIBARRIA | C38: =ROUND(PONDERADORES!$D$12*G38+PONDERADORES!$D$13*H38+PONDERADORES!$D$14*I38+PONDERADORES!$D$15*J38+PONDERADORES!$D$16*K38+PONDERADORES!$D$17*L38+PONDERADORES!$D$18*M38,1) | D38: =IF(C38<34,"🔴 Critico",IF(C38<67,"🟡 Vulnerable","🟢 Preparado")) | E38: =IFERROR(RANK(C38,C:C,-1),"") | F38: =IFERROR(MATRIZ_174!L38,0) | G38: =IFERROR(MATRIZ_174!M38,0) | H38: 0 | I38: 0 | J38: 0 | K38: =IFERROR(INDEX(MATRIZ_174!$U:$U,MATCH(A38,MATRIZ_174!$A:$A,0)),"") | L38: =IFERROR(MATRIZ_174!O38,0) | M38: 0 | N38: =IF(AND(F38>0,C38<34),"🔴 UE + Critico",IF(AND(F38>0,C38<67),"🟡 UE + Vulnerable",IF(AND(F38>0,C38>=67),"🟢 UE + Preparado",IF(C38=0,"— Sin dato","Sin exposición UE")))) | O38: AMAZONAS
A39: 20479917141 | B39: COOPERATIVA AGRARIA CENTRAL DE PRODUCTORES DE AMAZONAS | C39: =ROUND(PONDERADORES!$D$12*G39+PONDERADORES!$D$13*H39+PONDERADORES!$D$14*I39+PONDERADORES!$D$15*J39+PONDERADORES!$D$16*K39+PONDERADORES!$D$17*L39+PONDERADORES!$D$18*M39,1) | D39: =IF(C39<34,"🔴 Critico",IF(C39<67,"🟡 Vulnerable","🟢 Preparado")) | E39: =IFERROR(RANK(C39,C:C,-1),"") | F39: 587607.64 | G39: =IFERROR(MATRIZ_174!M39,0) | H39: 0 | I39: 0 | J39: 0 | K39: =IFERROR(INDEX(MATRIZ_174!$U:$U,MATCH(A39,MATRIZ_174!$A:$A,0)),"") | L39: =IFERROR(MATRIZ_174!O39,0) | M39: 0 | N39: =IF(AND(F39>0,C39<34),"🔴 UE + Critico",IF(AND(F39>0,C39<67),"🟡 UE + Vulnerable",IF(AND(F39>0,C39>=67),"🟢 UE + Preparado",IF(C39=0,"— Sin dato","Sin exposición UE")))) | O39: AMAZONAS
A40: 20480458550 | B40: COOPERATIVA AGRARIA APROCAM | C40: =ROUND(PONDERADORES!$D$12*G40+PONDERADORES!$D$13*H40+PONDERADORES!$D$14*I40+PONDERADORES!$D$15*J40+PONDERADORES!$D$16*K40+PONDERADORES!$D$17*L40+PONDERADORES!$D$18*M40,1) | D40: =IF(C40<34,"🔴 Critico",IF(C40<67,"🟡 Vulnerable","🟢 Preparado")) | E40: =IFERROR(RANK(C40,C:C,-1),"") | F40: 842214.99 | G40: =IFERROR(MATRIZ_174!M40,0) | H40: 0 | I40: 0 | J40: 0 | K40: =IFERROR(INDEX(MATRIZ_174!$U:$U,MATCH(A40,MATRIZ_174!$A:$A,0)),"") | L40: =IFERROR(MATRIZ_174!O40,0) | M40: 0 | N40: =IF(AND(F40>0,C40<34),"🔴 UE + Critico",IF(AND(F40>0,C40<67),"🟡 UE + Vulnerable",IF(AND(F40>0,C40>=67),"🟢 UE + Preparado",IF(C40=0,"— Sin dato","Sin exposición UE")))) | O40: AMAZONAS
A41: 20480762895 | B41: ASOCIACION DE PRODUCTORES AGROPECUARIOS LA FLOR DE CAFE | C41: =ROUND(PONDERADORES!$D$12*G41+PONDERADORES!$D$13*H41+PONDERADORES!$D$14*I41+PONDERADORES!$D$15*J41+PONDERADORES!$D$16*K41+PONDERADORES!$D$17*L41+PONDERADORES!$D$18*M41,1) | D41: =IF(C41<34,"🔴 Critico",IF(C41<67,"🟡 Vulnerable","🟢 Preparado")) | E41: =IFERROR(RANK(C41,C:C,-1),"") | F41: 0 | G41: =IFERROR(MATRIZ_174!M41,0) | H41: 0 | I41: 0 | J41: 0 | K41: =IFERROR(INDEX(MATRIZ_174!$U:$U,MATCH(A41,MATRIZ_174!$A:$A,0)),"") | L41: =IFERROR(MATRIZ_174!O41,0) | M41: 0 | N41: =IF(AND(F41>0,C41<34),"🔴 UE + Critico",IF(AND(F41>0,C41<67),"🟡 UE + Vulnerable",IF(AND(F41>0,C41>=67),"🟢 UE + Preparado",IF(C41=0,"— Sin dato","Sin exposición UE")))) | O41: AMAZONAS
A42: 20484163902 | B42: COOPERATIVA AGRARIA APPROCAP LTDA | C42: =ROUND(PONDERADORES!$D$12*G42+PONDERADORES!$D$13*H42+PONDERADORES!$D$14*I42+PONDERADORES!$D$15*J42+PONDERADORES!$D$16*K42+PONDERADORES!$D$17*L42+PONDERADORES!$D$18*M42,1) | D42: =IF(C42<34,"🔴 Critico",IF(C42<67,"🟡 Vulnerable","🟢 Preparado")) | E42: =IFERROR(RANK(C42,C:C,-1),"") | F42: 408500 | G42: =IFERROR(MATRIZ_174!M42,0) | H42: 0 | I42: 0 | J42: 0 | K42: =IFERROR(INDEX(MATRIZ_174!$U:$U,MATCH(A42,MATRIZ_174!$A:$A,0)),"") | L42: =IFERROR(MATRIZ_174!O42,0) | M42: 0 | N42: =IF(AND(F42>0,C42<34),"🔴 UE + Critico",IF(AND(F42>0,C42<67),"🟡 UE + Vulnerable",IF(AND(F42>0,C42>=67),"🟢 UE + Preparado",IF(C42=0,"— Sin dato","Sin exposición UE")))) | O42: PIURA
A43: 20485945815 | B43: COOPERATIVA AGRARIA CAFETALERA ECOLOGICO ALTO PALOMAR | C43: =ROUND(PONDERADORES!$D$12*G43+PONDERADORES!$D$13*H43+PONDERADORES!$D$14*I43+PONDERADORES!$D$15*J43+PONDERADORES!$D$16*K43+PONDERADORES!$D$17*L43+PONDERADORES!$D$18*M43,1) | D43: =IF(C43<34,"🔴 Critico",IF(C43<67,"🟡 Vulnerable","🟢 Preparado")) | E43: =IFERROR(RANK(C43,C:C,-1),"") | F43: 0 | G43: =IFERROR(MATRIZ_174!M43,0) | H43: 0 | I43: 0 | J43: 0 | K43: =IFERROR(INDEX(MATRIZ_174!$U:$U,MATCH(A43,MATRIZ_174!$A:$A,0)),"") | L43: =IFERROR(MATRIZ_174!O43,0) | M43: 0 | N43: =IF(AND(F43>0,C43<34),"🔴 UE + Critico",IF(AND(F43>0,C43<67),"🟡 UE + Vulnerable",IF(AND(F43>0,C43>=67),"🟢 UE + Preparado",IF(C43=0,"— Sin dato","Sin exposición UE")))) | O43: JUNIN
A44: 20486094657 | B44: ASOCIACION DE PRODUCTORES DE CAFES ESPECIALES MOUNTAIN COFFE | C44: =ROUND(PONDERADORES!$D$12*G44+PONDERADORES!$D$13*H44+PONDERADORES!$D$14*I44+PONDERADORES!$D$15*J44+PONDERADORES!$D$16*K44+PONDERADORES!$D$17*L44+PONDERADORES!$D$18*M44,1) | D44: =IF(C44<34,"🔴 Critico",IF(C44<67,"🟡 Vulnerable","🟢 Preparado")) | E44: =IFERROR(RANK(C44,C:C,-1),"") | F44: 0 | G44: =IFERROR(MATRIZ_174!M44,0) | H44: 0 | I44: 0 | J44: 0 | K44: =IFERROR(INDEX(MATRIZ_174!$U:$U,MATCH(A44,MATRIZ_174!$A:$A,0)),"") | L44: =IFERROR(MATRIZ_174!O44,0) | M44: 0 | N44: =IF(AND(F44>0,C44<34),"🔴 UE + Critico",IF(AND(F44>0,C44<67),"🟡 UE + Vulnerable",IF(AND(F44>0,C44>=67),"🟢 UE + Preparado",IF(C44=0,"— Sin dato","Sin exposición UE")))) | O44: JUNIN
A45: 20486255090 | B45: COOPERATIVA AGRARIA SANGARENI | C45: =ROUND(PONDERADORES!$D$12*G45+PONDERADORES!$D$13*H45+PONDERADORES!$D$14*I45+PONDERADORES!$D$15*J45+PONDERADORES!$D$16*K45+PONDERADORES!$D$17*L45+PONDERADORES!$D$18*M45,1) | D45: =IF(C45<34,"🔴 Critico",IF(C45<67,"🟡 Vulnerable","🟢 Preparado")) | E45: =IFERROR(RANK(C45,C:C,-1),"") | F45: 6603846 | G45: =IFERROR(MATRIZ_174!M45,0) | H45: 0 | I45: 0 | J45: 0 | K45: =IFERROR(INDEX(MATRIZ_174!$U:$U,MATCH(A45,MATRIZ_174!$A:$A,0)),"") | L45: =IFERROR(MATRIZ_174!O45,0) | M45: 0 | N45: =IF(AND(F45>0,C45<34),"🔴 UE + Critico",IF(AND(F45>0,C45<67),"🟡 UE + Vulnerable",IF(AND(F45>0,C45>=67),"🟢 UE + Preparado",IF(C45=0,"— Sin dato","Sin exposición UE")))) | O45: JUNIN
A46: 20486668335 | B46: COOPERATIVA AGROINDUSTRIAL SONOMORO LTDA | C46: =ROUND(PONDERADORES!$D$12*G46+PONDERADORES!$D$13*H46+PONDERADORES!$D$14*I46+PONDERADORES!$D$15*J46+PONDERADORES!$D$16*K46+PONDERADORES!$D$17*L46+PONDERADORES!$D$18*M46,1) | D46: =IF(C46<34,"🔴 Critico",IF(C46<67,"🟡 Vulnerable","🟢 Preparado")) | E46: =IFERROR(RANK(C46,C:C,-1),"") | F46: 0 | G46: =IFERROR(MATRIZ_174!M46,0) | H46: 0 | I46: 0 | J46: 0 | K46: =IFERROR(INDEX(MATRIZ_174!$U:$U,MATCH(A46,MATRIZ_174!$A:$A,0)),"") | L46: =IFERROR(MATRIZ_174!O46,0) | M46: 0 | N46: =IF(AND(F46>0,C46<34),"🔴 UE + Critico",IF(AND(F46>0,C46<67),"🟡 UE + Vulnerable",IF(AND(F46>0,C46>=67),"🟢 UE + Preparado",IF(C46=0,"— Sin dato","Sin exposición UE")))) | O46: JUNIN
A47: 20486876019 | B47: COOPERATIVA AGROECOLOGICO INDUSTRIAL MAZAMARI LTDA | C47: =ROUND(PONDERADORES!$D$12*G47+PONDERADORES!$D$13*H47+PONDERADORES!$D$14*I47+PONDERADORES!$D$15*J47+PONDERADORES!$D$16*K47+PONDERADORES!$D$17*L47+PONDERADORES!$D$18*M47,1) | D47: =IF(C47<34,"🔴 Critico",IF(C47<67,"🟡 Vulnerable","🟢 Preparado")) | E47: =IFERROR(RANK(C47,C:C,-1),"") | F47: =IFERROR(MATRIZ_174!L47,0) | G47: =IFERROR(MATRIZ_174!M47,0) | H47: 0 | I47: 0 | J47: 0 | K47: =IFERROR(INDEX(MATRIZ_174!$U:$U,MATCH(A47,MATRIZ_174!$A:$A,0)),"") | L47: =IFERROR(MATRIZ_174!O47,0) | M47: 0 | N47: =IF(AND(F47>0,C47<34),"🔴 UE + Critico",IF(AND(F47>0,C47<67),"🟡 UE + Vulnerable",IF(AND(F47>0,C47>=67),"🟢 UE + Preparado",IF(C47=0,"— Sin dato","Sin exposición UE")))) | O47: JUNIN
A48: 20486973219 | B48: COOPERATIVA AGRARIA SONOMORO DEL VRAEM LTDA | C48: =ROUND(PONDERADORES!$D$12*G48+PONDERADORES!$D$13*H48+PONDERADORES!$D$14*I48+PONDERADORES!$D$15*J48+PONDERADORES!$D$16*K48+PONDERADORES!$D$17*L48+PONDERADORES!$D$18*M48,1) | D48: =IF(C48<34,"🔴 Critico",IF(C48<67,"🟡 Vulnerable","🟢 Preparado")) | E48: =IFERROR(RANK(C48,C:C,-1),"") | F48: 15171147 | G48: =IFERROR(MATRIZ_174!M48,0) | H48: 0 | I48: 0 | J48: 0 | K48: =IFERROR(INDEX(MATRIZ_174!$U:$U,MATCH(A48,MATRIZ_174!$A:$A,0)),"") | L48: =IFERROR(MATRIZ_174!O48,0) | M48: 0 | N48: =IF(AND(F48>0,C48<34),"🔴 UE + Critico",IF(AND(F48>0,C48<67),"🟡 UE + Vulnerable",IF(AND(F48>0,C48>=67),"🟢 UE + Preparado",IF(C48=0,"— Sin dato","Sin exposición UE")))) | O48: JUNIN
A49: 20487242994 | B49: COOPERATIVA AGRARIA ECOLOGICA CACAOTERA VALLE RIO ENE - COOP | C49: =ROUND(PONDERADORES!$D$12*G49+PONDERADORES!$D$13*H49+PONDERADORES!$D$14*I49+PONDERADORES!$D$15*J49+PONDERADORES!$D$16*K49+PONDERADORES!$D$17*L49+PONDERADORES!$D$18*M49,1) | D49: =IF(C49<34,"🔴 Critico",IF(C49<67,"🟡 Vulnerable","🟢 Preparado")) | E49: =IFERROR(RANK(C49,C:C,-1),"") | F49: 1145489.4 | G49: =IFERROR(MATRIZ_174!M49,0) | H49: 0 | I49: 0 | J49: 0 | K49: =IFERROR(INDEX(MATRIZ_174!$U:$U,MATCH(A49,MATRIZ_174!$A:$A,0)),"") | L49: =IFERROR(MATRIZ_174!O49,0) | M49: 0 | N49: =IF(AND(F49>0,C49<34),"🔴 UE + Critico",IF(AND(F49>0,C49<67),"🟡 UE + Vulnerable",IF(AND(F49>0,C49>=67),"🟢 UE + Preparado",IF(C49=0,"— Sin dato","Sin exposición UE")))) | O49: JUNIN
A50: 20487351343 | B50: ASOCIACION DE PRODUCTORES AGROPECUARIOS TUPAC AMARU DE CHIÑA | C50: =ROUND(PONDERADORES!$D$12*G50+PONDERADORES!$D$13*H50+PONDERADORES!$D$14*I50+PONDERADORES!$D$15*J50+PONDERADORES!$D$16*K50+PONDERADORES!$D$17*L50+PONDERADORES!$D$18*M50,1) | D50: =IF(C50<34,"🔴 Critico",IF(C50<67,"🟡 Vulnerable","🟢 Preparado")) | E50: =IFERROR(RANK(C50,C:C,-1),"") | F50: =IFERROR(MATRIZ_174!L50,0) | G50: =IFERROR(MATRIZ_174!M50,0) | H50: 0 | I50: 0 | J50: 0 | K50: =IFERROR(INDEX(MATRIZ_174!$U:$U,MATCH(A50,MATRIZ_174!$A:$A,0)),"") | L50: =IFERROR(MATRIZ_174!O50,0) | M50: 0 | N50: =IF(AND(F50>0,C50<34),"🔴 UE + Critico",IF(AND(F50>0,C50<67),"🟡 UE + Vulnerable",IF(AND(F50>0,C50>=67),"🟢 UE + Preparado",IF(C50=0,"— Sin dato","Sin exposición UE")))) | O50: LAMBAYEQUE
A51: 20487661539 | B51: ASOCIACION DE PRODUCTORES CACAOTEROS DEL DISTRITO DE HUARANG | C51: =ROUND(PONDERADORES!$D$12*G51+PONDERADORES!$D$13*H51+PONDERADORES!$D$14*I51+PONDERADORES!$D$15*J51+PONDERADORES!$D$16*K51+PONDERADORES!$D$17*L51+PONDERADORES!$D$18*M51,1) | D51: =IF(C51<34,"🔴 Critico",IF(C51<67,"🟡 Vulnerable","🟢 Preparado")) | E51: =IFERROR(RANK(C51,C:C,-1),"") | F51: =IFERROR(MATRIZ_174!L51,0) | G51: =IFERROR(MATRIZ_174!M51,0) | H51: 0 | I51: 0 | J51: 0 | K51: =IFERROR(INDEX(MATRIZ_174!$U:$U,MATCH(A51,MATRIZ_174!$A:$A,0)),"") | L51: =IFERROR(MATRIZ_174!O51,0) | M51: 0 | N51: =IF(AND(F51>0,C51<34),"🔴 UE + Critico",IF(AND(F51>0,C51<67),"🟡 UE + Vulnerable",IF(AND(F51>0,C51>=67),"🟢 UE + Preparado",IF(C51=0,"— Sin dato","Sin exposición UE")))) | O51: CAJAMARCA
A52: 20490726196 | B52: ASOCIACIÓN DE PRODUCTORES AGROPECUARIOS VALLESITO - CHAHUARE | C52: =ROUND(PONDERADORES!$D$12*G52+PONDERADORES!$D$13*H52+PONDERADORES!$D$14*I52+PONDERADORES!$D$15*J52+PONDERADORES!$D$16*K52+PONDERADORES!$D$17*L52+PONDERADORES!$D$18*M52,1) | D52: =IF(C52<34,"🔴 Critico",IF(C52<67,"🟡 Vulnerable","🟢 Preparado")) | E52: =IFERROR(RANK(C52,C:C,-1),"") | F52: =IFERROR(MATRIZ_174!L52,0) | G52: =IFERROR(MATRIZ_174!M52,0) | H52: 0 | I52: 0 | J52: 0 | K52: =IFERROR(INDEX(MATRIZ_174!$U:$U,MATCH(A52,MATRIZ_174!$A:$A,0)),"") | L52: =IFERROR(MATRIZ_174!O52,0) | M52: 0 | N52: =IF(AND(F52>0,C52<34),"🔴 UE + Critico",IF(AND(F52>0,C52<67),"🟡 UE + Vulnerable",IF(AND(F52>0,C52>=67),"🟢 UE + Preparado",IF(C52=0,"— Sin dato","Sin exposición UE")))) | O52: CUSCO
A53: 20493934822 | B53: COOPERATIVA AGRARIA NUEVO AMANECER LTDA. | C53: =ROUND(PONDERADORES!$D$12*G53+PONDERADORES!$D$13*H53+PONDERADORES!$D$14*I53+PONDERADORES!$D$15*J53+PONDERADORES!$D$16*K53+PONDERADORES!$D$17*L53+PONDERADORES!$D$18*M53,1) | D53: =IF(C53<34,"🔴 Critico",IF(C53<67,"🟡 Vulnerable","🟢 Preparado")) | E53: =IFERROR(RANK(C53,C:C,-1),"") | F53: 0 | G53: =IFERROR(MATRIZ_174!M53,0) | H53: 0 | I53: 0 | J53: 0 | K53: =IFERROR(INDEX(MATRIZ_174!$U:$U,MATCH(A53,MATRIZ_174!$A:$A,0)),"") | L53: =IFERROR(MATRIZ_174!O53,0) | M53: 0 | N53: =IF(AND(F53>0,C53<34),"🔴 UE + Critico",IF(AND(F53>0,C53<67),"🟡 UE + Vulnerable",IF(AND(F53>0,C53>=67),"🟢 UE + Preparado",IF(C53=0,"— Sin dato","Sin exposición UE")))) | O53: SAN MARTIN
A54: 20493959574 | B54: COOPERATIVA AGRARIA DE SERVICIOS MUJERES TECNOLOGAS CACAOTER | C54: =ROUND(PONDERADORES!$D$12*G54+PONDERADORES!$D$13*H54+PONDERADORES!$D$14*I54+PONDERADORES!$D$15*J54+PONDERADORES!$D$16*K54+PONDERADORES!$D$17*L54+PONDERADORES!$D$18*M54,1) | D54: =IF(C54<34,"🔴 Critico",IF(C54<67,"🟡 Vulnerable","🟢 Preparado")) | E54: =IFERROR(RANK(C54,C:C,-1),"") | F54: =IFERROR(MATRIZ_174!L54,0) | G54: =IFERROR(MATRIZ_174!M54,0) | H54: 0 | I54: 0 | J54: 0 | K54: =IFERROR(INDEX(MATRIZ_174!$U:$U,MATCH(A54,MATRIZ_174!$A:$A,0)),"") | L54: =IFERROR(MATRIZ_174!O54,0) | M54: 0 | N54: =IF(AND(F54>0,C54<34),"🔴 UE + Critico",IF(AND(F54>0,C54<67),"🟡 UE + Vulnerable",IF(AND(F54>0,C54>=67),"🟢 UE + Preparado",IF(C54=0,"— Sin dato","Sin exposición UE")))) | O54: SAN MARTIN
A55: 20494126819 | B55: ASOCIACION DE PRODUCTORES AGROPECUARIOS RIO MAYO SHANAO | C55: =ROUND(PONDERADORES!$D$12*G55+PONDERADORES!$D$13*H55+PONDERADORES!$D$14*I55+PONDERADORES!$D$15*J55+PONDERADORES!$D$16*K55+PONDERADORES!$D$17*L55+PONDERADORES!$D$18*M55,1) | D55: =IF(C55<34,"🔴 Critico",IF(C55<67,"🟡 Vulnerable","🟢 Preparado")) | E55: =IFERROR(RANK(C55,C:C,-1),"") | F55: =IFERROR(MATRIZ_174!L55,0) | G55: =IFERROR(MATRIZ_174!M55,0) | H55: 0 | I55: 0 | J55: 0 | K55: =IFERROR(INDEX(MATRIZ_174!$U:$U,MATCH(A55,MATRIZ_174!$A:$A,0)),"") | L55: =IFERROR(MATRIZ_174!O55,0) | M55: 0 | N55: =IF(AND(F55>0,C55<34),"🔴 UE + Critico",IF(AND(F55>0,C55<67),"🟡 UE + Vulnerable",IF(AND(F55>0,C55>=67),"🟢 UE + Preparado",IF(C55=0,"— Sin dato","Sin exposición UE")))) | O55: SAN MARTIN
A56: 20494145791 | B56: ASOCIACION ECOLOGICA Y DE PRODUCTORES AGROPECUARIOS SAN JOSE | C56: =ROUND(PONDERADORES!$D$12*G56+PONDERADORES!$D$13*H56+PONDERADORES!$D$14*I56+PONDERADORES!$D$15*J56+PONDERADORES!$D$16*K56+PONDERADORES!$D$17*L56+PONDERADORES!$D$18*M56,1) | D56: =IF(C56<34,"🔴 Critico",IF(C56<67,"🟡 Vulnerable","🟢 Preparado")) | E56: =IFERROR(RANK(C56,C:C,-1),"") | F56: =IFERROR(MATRIZ_174!L56,0) | G56: =IFERROR(MATRIZ_174!M56,0) | H56: 0 | I56: 0 | J56: 0 | K56: =IFERROR(INDEX(MATRIZ_174!$U:$U,MATCH(A56,MATRIZ_174!$A:$A,0)),"") | L56: =IFERROR(MATRIZ_174!O56,0) | M56: 0 | N56: =IF(AND(F56>0,C56<34),"🔴 UE + Critico",IF(AND(F56>0,C56<67),"🟡 UE + Vulnerable",IF(AND(F56>0,C56>=67),"🟢 UE + Preparado",IF(C56=0,"— Sin dato","Sin exposición UE")))) | O56: LORETO
A57: 20494699690 | B57: ASOCIACION DE PRODUCTORES DE CACAO ECOLOGICO DE KIMBIRI - AP | C57: =ROUND(PONDERADORES!$D$12*G57+PONDERADORES!$D$13*H57+PONDERADORES!$D$14*I57+PONDERADORES!$D$15*J57+PONDERADORES!$D$16*K57+PONDERADORES!$D$17*L57+PONDERADORES!$D$18*M57,1) | D57: =IF(C57<34,"🔴 Critico",IF(C57<67,"🟡 Vulnerable","🟢 Preparado")) | E57: =IFERROR(RANK(C57,C:C,-1),"") | F57: =IFERROR(MATRIZ_174!L57,0) | G57: =IFERROR(MATRIZ_174!M57,0) | H57: 0 | I57: 0 | J57: 0 | K57: =IFERROR(INDEX(MATRIZ_174!$U:$U,MATCH(A57,MATRIZ_174!$A:$A,0)),"") | L57: =IFERROR(MATRIZ_174!O57,0) | M57: 0 | N57: =IF(AND(F57>0,C57<34),"🔴 UE + Critico",IF(AND(F57>0,C57<67),"🟡 UE + Vulnerable",IF(AND(F57>0,C57>=67),"🟢 UE + Preparado",IF(C57=0,"— Sin dato","Sin exposición UE")))) | O57: CUSCO
A58: 20525969551 | B58: COOPERATIVA AGRARIA DE PRODUCTORES DE BANANO, CACAO ORGANICO | C58: =ROUND(PONDERADORES!$D$12*G58+PONDERADORES!$D$13*H58+PONDERADORES!$D$14*I58+PONDERADORES!$D$15*J58+PONDERADORES!$D$16*K58+PONDERADORES!$D$17*L58+PONDERADORES!$D$18*M58,1) | D58: =IF(C58<34,"🔴 Critico",IF(C58<67,"🟡 Vulnerable","🟢 Preparado")) | E58: =IFERROR(RANK(C58,C:C,-1),"") | F58: 52920 | G58: =IFERROR(MATRIZ_174!M58,0) | H58: 0 | I58: 0 | J58: 0 | K58: =IFERROR(INDEX(MATRIZ_174!$U:$U,MATCH(A58,MATRIZ_174!$A:$A,0)),"") | L58: =IFERROR(MATRIZ_174!O58,0) | M58: 0 | N58: =IF(AND(F58>0,C58<34),"🔴 UE + Critico",IF(AND(F58>0,C58<67),"🟡 UE + Vulnerable",IF(AND(F58>0,C58>=67),"🟢 UE + Preparado",IF(C58=0,"— Sin dato","Sin exposición UE")))) | O58: PIURA
A59: 20526514689 | B59: ASOCIACION DE PRODUCTORES AGROPECUARIOS ARTESANALES E INDUST | C59: =ROUND(PONDERADORES!$D$12*G59+PONDERADORES!$D$13*H59+PONDERADORES!$D$14*I59+PONDERADORES!$D$15*J59+PONDERADORES!$D$16*K59+PONDERADORES!$D$17*L59+PONDERADORES!$D$18*M59,1) | D59: =IF(C59<34,"🔴 Critico",IF(C59<67,"🟡 Vulnerable","🟢 Preparado")) | E59: =IFERROR(RANK(C59,C:C,-1),"") | F59: =IFERROR(MATRIZ_174!L59,0) | G59: =IFERROR(MATRIZ_174!M59,0) | H59: 0 | I59: 0 | J59: 0 | K59: =IFERROR(INDEX(MATRIZ_174!$U:$U,MATCH(A59,MATRIZ_174!$A:$A,0)),"") | L59: =IFERROR(MATRIZ_174!O59,0) | M59: 0 | N59: =IF(AND(F59>0,C59<34),"🔴 UE + Critico",IF(AND(F59>0,C59<67),"🟡 UE + Vulnerable",IF(AND(F59>0,C59>=67),"🟢 UE + Preparado",IF(C59=0,"— Sin dato","Sin exposición UE")))) | O59: PIURA
A60: 20527565376 | B60: COOPERATIVA AGRARIA CAFETALERA VALLE DE INCAHUASI | C60: =ROUND(PONDERADORES!$D$12*G60+PONDERADORES!$D$13*H60+PONDERADORES!$D$14*I60+PONDERADORES!$D$15*J60+PONDERADORES!$D$16*K60+PONDERADORES!$D$17*L60+PONDERADORES!$D$18*M60,1) | D60: =IF(C60<34,"🔴 Critico",IF(C60<67,"🟡 Vulnerable","🟢 Preparado")) | E60: =IFERROR(RANK(C60,C:C,-1),"") | F60: 5373465.5 | G60: =IFERROR(MATRIZ_174!M60,0) | H60: 0 | I60: 0 | J60: 0 | K60: =IFERROR(INDEX(MATRIZ_174!$U:$U,MATCH(A60,MATRIZ_174!$A:$A,0)),"") | L60: =IFERROR(MATRIZ_174!O60,0) | M60: 0 | N60: =IF(AND(F60>0,C60<34),"🔴 UE + Critico",IF(AND(F60>0,C60<67),"🟡 UE + Vulnerable",IF(AND(F60>0,C60>=67),"🟢 UE + Preparado",IF(C60=0,"— Sin dato","Sin exposición UE")))) | O60: APURIMAC
A61: 20528996214 | B61: COOPERATIVA AGRARIA CAFETALERA MILAGROS - MONZON | C61: =ROUND(PONDERADORES!$D$12*G61+PONDERADORES!$D$13*H61+PONDERADORES!$D$14*I61+PONDERADORES!$D$15*J61+PONDERADORES!$D$16*K61+PONDERADORES!$D$17*L61+PONDERADORES!$D$18*M61,1) | D61: =IF(C61<34,"🔴 Critico",IF(C61<67,"🟡 Vulnerable","🟢 Preparado")) | E61: =IFERROR(RANK(C61,C:C,-1),"") | F61: =IFERROR(MATRIZ_174!L61,0) | G61: =IFERROR(MATRIZ_174!M61,0) | H61: 0 | I61: 0 | J61: 0 | K61: =IFERROR(INDEX(MATRIZ_174!$U:$U,MATCH(A61,MATRIZ_174!$A:$A,0)),"") | L61: =IFERROR(MATRIZ_174!O61,0) | M61: 0 | N61: =IF(AND(F61>0,C61<34),"🔴 UE + Critico",IF(AND(F61>0,C61<67),"🟡 UE + Vulnerable",IF(AND(F61>0,C61>=67),"🟢 UE + Preparado",IF(C61=0,"— Sin dato","Sin exposición UE")))) | O61: HUANUCO
A62: 20529801433 | B62: OPA MARAY-ULLMA SAN LORENZO | C62: =ROUND(PONDERADORES!$D$12*G62+PONDERADORES!$D$13*H62+PONDERADORES!$D$14*I62+PONDERADORES!$D$15*J62+PONDERADORES!$D$16*K62+PONDERADORES!$D$17*L62+PONDERADORES!$D$18*M62,1) | D62: =IF(C62<34,"🔴 Critico",IF(C62<67,"🟡 Vulnerable","🟢 Preparado")) | E62: =IFERROR(RANK(C62,C:C,-1),"") | F62: =IFERROR(MATRIZ_174!L62,0) | G62: =IFERROR(MATRIZ_174!M62,0) | H62: 0 | I62: 0 | J62: 0 | K62: =IFERROR(INDEX(MATRIZ_174!$U:$U,MATCH(A62,MATRIZ_174!$A:$A,0)),"") | L62: =IFERROR(MATRIZ_174!O62,0) | M62: 0 | N62: =IF(AND(F62>0,C62<34),"🔴 UE + Critico",IF(AND(F62>0,C62<67),"🟡 UE + Vulnerable",IF(AND(F62>0,C62>=67),"🟢 UE + Preparado",IF(C62=0,"— Sin dato","Sin exposición UE")))) | O62: PIURA
A63: 20529822350 | B63: OPA PAPAYO - LA LAGUNA | C63: =ROUND(PONDERADORES!$D$12*G63+PONDERADORES!$D$13*H63+PONDERADORES!$D$14*I63+PONDERADORES!$D$15*J63+PONDERADORES!$D$16*K63+PONDERADORES!$D$17*L63+PONDERADORES!$D$18*M63,1) | D63: =IF(C63<34,"🔴 Critico",IF(C63<67,"🟡 Vulnerable","🟢 Preparado")) | E63: =IFERROR(RANK(C63,C:C,-1),"") | F63: =IFERROR(MATRIZ_174!L63,0) | G63: =IFERROR(MATRIZ_174!M63,0) | H63: 0 | I63: 0 | J63: 0 | K63: =IFERROR(INDEX(MATRIZ_174!$U:$U,MATCH(A63,MATRIZ_174!$A:$A,0)),"") | L63: =IFERROR(MATRIZ_174!O63,0) | M63: 0 | N63: =IF(AND(F63>0,C63<34),"🔴 UE + Critico",IF(AND(F63>0,C63<67),"🟡 UE + Vulnerable",IF(AND(F63>0,C63>=67),"🟢 UE + Preparado",IF(C63=0,"— Sin dato","Sin exposición UE")))) | O63: PIURA
A64: 20531405723 | B64: COOPERATIVA DE SERVICIOS MULTIPLES ADISA NARANJOS | C64: =ROUND(PONDERADORES!$D$12*G64+PONDERADORES!$D$13*H64+PONDERADORES!$D$14*I64+PONDERADORES!$D$15*J64+PONDERADORES!$D$16*K64+PONDERADORES!$D$17*L64+PONDERADORES!$D$18*M64,1) | D64: =IF(C64<34,"🔴 Critico",IF(C64<67,"🟡 Vulnerable","🟢 Preparado")) | E64: =IFERROR(RANK(C64,C:C,-1),"") | F64: 0 | G64: =IFERROR(MATRIZ_174!M64,0) | H64: 0 | I64: 0 | J64: 0 | K64: =IFERROR(INDEX(MATRIZ_174!$U:$U,MATCH(A64,MATRIZ_174!$A:$A,0)),"") | L64: =IFERROR(MATRIZ_174!O64,0) | M64: 0 | N64: =IF(AND(F64>0,C64<34),"🔴 UE + Critico",IF(AND(F64>0,C64<67),"🟡 UE + Vulnerable",IF(AND(F64>0,C64>=67),"🟢 UE + Preparado",IF(C64=0,"— Sin dato","Sin exposición UE")))) | O64: SAN MARTIN
A65: 20531441797 | B65: COOPERATIVA AGRARIA ALLIMA CACAO LTDA. | C65: =ROUND(PONDERADORES!$D$12*G65+PONDERADORES!$D$13*H65+PONDERADORES!$D$14*I65+PONDERADORES!$D$15*J65+PONDERADORES!$D$16*K65+PONDERADORES!$D$17*L65+PONDERADORES!$D$18*M65,1) | D65: =IF(C65<34,"🔴 Critico",IF(C65<67,"🟡 Vulnerable","🟢 Preparado")) | E65: =IFERROR(RANK(C65,C:C,-1),"") | F65: 0 | G65: =IFERROR(MATRIZ_174!M65,0) | H65: 0 | I65: 0 | J65: 0 | K65: =IFERROR(INDEX(MATRIZ_174!$U:$U,MATCH(A65,MATRIZ_174!$A:$A,0)),"") | L65: =IFERROR(MATRIZ_174!O65,0) | M65: 0 | N65: =IF(AND(F65>0,C65<34),"🔴 UE + Critico",IF(AND(F65>0,C65<67),"🟡 UE + Vulnerable",IF(AND(F65>0,C65>=67),"🟢 UE + Preparado",IF(C65=0,"— Sin dato","Sin exposición UE")))) | O65: SAN MARTIN
A66: 20534524774 | B66: COOPERATIVA AGRARIA TROPICAL ECOLOGICA DE KIMBIRI | C66: =ROUND(PONDERADORES!$D$12*G66+PONDERADORES!$D$13*H66+PONDERADORES!$D$14*I66+PONDERADORES!$D$15*J66+PONDERADORES!$D$16*K66+PONDERADORES!$D$17*L66+PONDERADORES!$D$18*M66,1) | D66: =IF(C66<34,"🔴 Critico",IF(C66<67,"🟡 Vulnerable","🟢 Preparado")) | E66: =IFERROR(RANK(C66,C:C,-1),"") | F66: =IFERROR(MATRIZ_174!L66,0) | G66: =IFERROR(MATRIZ_174!M66,0) | H66: 0 | I66: 0 | J66: 0 | K66: =IFERROR(INDEX(MATRIZ_174!$U:$U,MATCH(A66,MATRIZ_174!$A:$A,0)),"") | L66: =IFERROR(MATRIZ_174!O66,0) | M66: 0 | N66: =IF(AND(F66>0,C66<34),"🔴 UE + Critico",IF(AND(F66>0,C66<67),"🟡 UE + Vulnerable",IF(AND(F66>0,C66>=67),"🟢 UE + Preparado",IF(C66=0,"— Sin dato","Sin exposición UE")))) | O66: CUSCO
A67: 20539205600 | B67: ASOCIACION DE PRODUCTORES Y EXPORTADORES DE CAFE RODRIGUEZ D | C67: =ROUND(PONDERADORES!$D$12*G67+PONDERADORES!$D$13*H67+PONDERADORES!$D$14*I67+PONDERADORES!$D$15*J67+PONDERADORES!$D$16*K67+PONDERADORES!$D$17*L67+PONDERADORES!$D$18*M67,1) | D67: =IF(C67<34,"🔴 Critico",IF(C67<67,"🟡 Vulnerable","🟢 Preparado")) | E67: =IFERROR(RANK(C67,C:C,-1),"") | F67: =IFERROR(MATRIZ_174!L67,0) | G67: =IFERROR(MATRIZ_174!M67,0) | H67: 0 | I67: 0 | J67: 0 | K67: =IFERROR(INDEX(MATRIZ_174!$U:$U,MATCH(A67,MATRIZ_174!$A:$A,0)),"") | L67: =IFERROR(MATRIZ_174!O67,0) | M67: 0 | N67: =IF(AND(F67>0,C67<34),"🔴 UE + Critico",IF(AND(F67>0,C67<67),"🟡 UE + Vulnerable",IF(AND(F67>0,C67>=67),"🟢 UE + Preparado",IF(C67=0,"— Sin dato","Sin exposición UE")))) | O67: AMAZONAS
A68: 20539241665 | B68: ASOCIACION DE PRODUCTORES DE CAFES ORGANICOS Y CAFES ESPECIA | C68: =ROUND(PONDERADORES!$D$12*G68+PONDERADORES!$D$13*H68+PONDERADORES!$D$14*I68+PONDERADORES!$D$15*J68+PONDERADORES!$D$16*K68+PONDERADORES!$D$17*L68+PONDERADORES!$D$18*M68,1) | D68: =IF(C68<34,"🔴 Critico",IF(C68<67,"🟡 Vulnerable","🟢 Preparado")) | E68: =IFERROR(RANK(C68,C:C,-1),"") | F68: =IFERROR(MATRIZ_174!L68,0) | G68: =IFERROR(MATRIZ_174!M68,0) | H68: 0 | I68: 0 | J68: 0 | K68: =IFERROR(INDEX(MATRIZ_174!$U:$U,MATCH(A68,MATRIZ_174!$A:$A,0)),"") | L68: =IFERROR(MATRIZ_174!O68,0) | M68: 0 | N68: =IF(AND(F68>0,C68<34),"🔴 UE + Critico",IF(AND(F68>0,C68<67),"🟡 UE + Vulnerable",IF(AND(F68>0,C68>=67),"🟢 UE + Preparado",IF(C68=0,"— Sin dato","Sin exposición UE")))) | O68: AMAZONAS
A69: 20539280644 | B69: ASOCIACION DE PEQUEÑOS AGRICULTORES PARA LA PRODUCCION ECOLO | C69: =ROUND(PONDERADORES!$D$12*G69+PONDERADORES!$D$13*H69+PONDERADORES!$D$14*I69+PONDERADORES!$D$15*J69+PONDERADORES!$D$16*K69+PONDERADORES!$D$17*L69+PONDERADORES!$D$18*M69,1) | D69: =IF(C69<34,"🔴 Critico",IF(C69<67,"🟡 Vulnerable","🟢 Preparado")) | E69: =IFERROR(RANK(C69,C:C,-1),"") | F69: =IFERROR(MATRIZ_174!L69,0) | G69: =IFERROR(MATRIZ_174!M69,0) | H69: 0 | I69: 0 | J69: 0 | K69: =IFERROR(INDEX(MATRIZ_174!$U:$U,MATCH(A69,MATRIZ_174!$A:$A,0)),"") | L69: =IFERROR(MATRIZ_174!O69,0) | M69: 0 | N69: =IF(AND(F69>0,C69<34),"🔴 UE + Critico",IF(AND(F69>0,C69<67),"🟡 UE + Vulnerable",IF(AND(F69>0,C69>=67),"🟢 UE + Preparado",IF(C69=0,"— Sin dato","Sin exposición UE")))) | O69: LAMBAYEQUE
A70: 20542209951 | B70: COOPERATIVA AGRARIA VALLE GRANDE | C70: =ROUND(PONDERADORES!$D$12*G70+PONDERADORES!$D$13*H70+PONDERADORES!$D$14*I70+PONDERADORES!$D$15*J70+PONDERADORES!$D$16*K70+PONDERADORES!$D$17*L70+PONDERADORES!$D$18*M70,1) | D70: =IF(C70<34,"🔴 Critico",IF(C70<67,"🟡 Vulnerable","🟢 Preparado")) | E70: =IFERROR(RANK(C70,C:C,-1),"") | F70: 7878141.7 | G70: =IFERROR(MATRIZ_174!M70,0) | H70: 0 | I70: 0 | J70: 0 | K70: =IFERROR(INDEX(MATRIZ_174!$U:$U,MATCH(A70,MATRIZ_174!$A:$A,0)),"") | L70: =IFERROR(MATRIZ_174!O70,0) | M70: 0 | N70: =IF(AND(F70>0,C70<34),"🔴 UE + Critico",IF(AND(F70>0,C70<67),"🟡 UE + Vulnerable",IF(AND(F70>0,C70>=67),"🟢 UE + Preparado",IF(C70=0,"— Sin dato","Sin exposición UE")))) | O70: SAN MARTIN
A71: 20542251990 | B71: ASOCIACION DE MUJERES EMPRENDEDORAS DE NUEVO PROGRESO | C71: =ROUND(PONDERADORES!$D$12*G71+PONDERADORES!$D$13*H71+PONDERADORES!$D$14*I71+PONDERADORES!$D$15*J71+PONDERADORES!$D$16*K71+PONDERADORES!$D$17*L71+PONDERADORES!$D$18*M71,1) | D71: =IF(C71<34,"🔴 Critico",IF(C71<67,"🟡 Vulnerable","🟢 Preparado")) | E71: =IFERROR(RANK(C71,C:C,-1),"") | F71: =IFERROR(MATRIZ_174!L71,0) | G71: =IFERROR(MATRIZ_174!M71,0) | H71: 0 | I71: 0 | J71: 0 | K71: =IFERROR(INDEX(MATRIZ_174!$U:$U,MATCH(A71,MATRIZ_174!$A:$A,0)),"") | L71: =IFERROR(MATRIZ_174!O71,0) | M71: 0 | N71: =IF(AND(F71>0,C71<34),"🔴 UE + Critico",IF(AND(F71>0,C71<67),"🟡 UE + Vulnerable",IF(AND(F71>0,C71>=67),"🟢 UE + Preparado",IF(C71=0,"— Sin dato","Sin exposición UE")))) | O71: SAN MARTIN
A72: 20542257416 | B72: EMPRESA INDUSTRIAL ORO VERDE SOCIEDAD ANONIMA CERRADA | C72: =ROUND(PONDERADORES!$D$12*G72+PONDERADORES!$D$13*H72+PONDERADORES!$D$14*I72+PONDERADORES!$D$15*J72+PONDERADORES!$D$16*K72+PONDERADORES!$D$17*L72+PONDERADORES!$D$18*M72,1) | D72: =IF(C72<34,"🔴 Critico",IF(C72<67,"🟡 Vulnerable","🟢 Preparado")) | E72: =IFERROR(RANK(C72,C:C,-1),"") | F72: 1413037.5 | G72: =IFERROR(MATRIZ_174!M72,0) | H72: 0 | I72: 0 | J72: 0 | K72: =IFERROR(INDEX(MATRIZ_174!$U:$U,MATCH(A72,MATRIZ_174!$A:$A,0)),"") | L72: =IFERROR(MATRIZ_174!O72,0) | M72: 0 | N72: =IF(AND(F72>0,C72<34),"🔴 UE + Critico",IF(AND(F72>0,C72<67),"🟡 UE + Vulnerable",IF(AND(F72>0,C72>=67),"🟢 UE + Preparado",IF(C72=0,"— Sin dato","Sin exposición UE")))) | O72: SAN MARTIN
A73: 20542264544 | B73: COOPERATIVA AGRARIA VALLE DEL BIAVO LTDA | C73: =ROUND(PONDERADORES!$D$12*G73+PONDERADORES!$D$13*H73+PONDERADORES!$D$14*I73+PONDERADORES!$D$15*J73+PONDERADORES!$D$16*K73+PONDERADORES!$D$17*L73+PONDERADORES!$D$18*M73,1) | D73: =IF(C73<34,"🔴 Critico",IF(C73<67,"🟡 Vulnerable","🟢 Preparado")) | E73: =IFERROR(RANK(C73,C:C,-1),"") | F73: 1187600.5 | G73: =IFERROR(MATRIZ_174!M73,0) | H73: 0 | I73: 0 | J73: 0 | K73: =IFERROR(INDEX(MATRIZ_174!$U:$U,MATCH(A73,MATRIZ_174!$A:$A,0)),"") | L73: =IFERROR(MATRIZ_174!O73,0) | M73: 0 | N73: =IF(AND(F73>0,C73<34),"🔴 UE + Critico",IF(AND(F73>0,C73<67),"🟡 UE + Vulnerable",IF(AND(F73>0,C73>=67),"🟢 UE + Preparado",IF(C73=0,"— Sin dato","Sin exposición UE")))) | O73: SAN MARTIN
A74: 20542289024 | B74: CUENCAS DEL HUALLAGA ASOCIACION DE PRODUCTORES AGROPECUARIOS | C74: =ROUND(PONDERADORES!$D$12*G74+PONDERADORES!$D$13*H74+PONDERADORES!$D$14*I74+PONDERADORES!$D$15*J74+PONDERADORES!$D$16*K74+PONDERADORES!$D$17*L74+PONDERADORES!$D$18*M74,1) | D74: =IF(C74<34,"🔴 Critico",IF(C74<67,"🟡 Vulnerable","🟢 Preparado")) | E74: =IFERROR(RANK(C74,C:C,-1),"") | F74: 12142716 | G74: =IFERROR(MATRIZ_174!M74,0) | H74: 0 | I74: 0 | J74: 0 | K74: =IFERROR(INDEX(MATRIZ_174!$U:$U,MATCH(A74,MATRIZ_174!$A:$A,0)),"") | L74: =IFERROR(MATRIZ_174!O74,0) | M74: 0 | N74: =IF(AND(F74>0,C74<34),"🔴 UE + Critico",IF(AND(F74>0,C74<67),"🟡 UE + Vulnerable",IF(AND(F74>0,C74>=67),"🟢 UE + Preparado",IF(C74=0,"— Sin dato","Sin exposición UE")))) | O74: SAN MARTIN
A75: 20542299330 | B75: ASOCIACION DE PRODUCTORES AGROPECUARIOS DE SHUCUSHYACU FLOR | C75: =ROUND(PONDERADORES!$D$12*G75+PONDERADORES!$D$13*H75+PONDERADORES!$D$14*I75+PONDERADORES!$D$15*J75+PONDERADORES!$D$16*K75+PONDERADORES!$D$17*L75+PONDERADORES!$D$18*M75,1) | D75: =IF(C75<34,"🔴 Critico",IF(C75<67,"🟡 Vulnerable","🟢 Preparado")) | E75: =IFERROR(RANK(C75,C:C,-1),"") | F75: =IFERROR(MATRIZ_174!L75,0) | G75: =IFERROR(MATRIZ_174!M75,0) | H75: 0 | I75: 0 | J75: 0 | K75: =IFERROR(INDEX(MATRIZ_174!$U:$U,MATCH(A75,MATRIZ_174!$A:$A,0)),"") | L75: =IFERROR(MATRIZ_174!O75,0) | M75: 0 | N75: =IF(AND(F75>0,C75<34),"🔴 UE + Critico",IF(AND(F75>0,C75<67),"🟡 UE + Vulnerable",IF(AND(F75>0,C75>=67),"🟢 UE + Preparado",IF(C75=0,"— Sin dato","Sin exposición UE")))) | O75: LORETO
A76: 20542311569 | B76: COOPERATIVA AGRARIA ACHUAR SHAKAIM LTDA | C76: =ROUND(PONDERADORES!$D$12*G76+PONDERADORES!$D$13*H76+PONDERADORES!$D$14*I76+PONDERADORES!$D$15*J76+PONDERADORES!$D$16*K76+PONDERADORES!$D$17*L76+PONDERADORES!$D$18*M76,1) | D76: =IF(C76<34,"🔴 Critico",IF(C76<67,"🟡 Vulnerable","🟢 Preparado")) | E76: =IFERROR(RANK(C76,C:C,-1),"") | F76: =IFERROR(MATRIZ_174!L76,0) | G76: =IFERROR(MATRIZ_174!M76,0) | H76: 0 | I76: 0 | J76: 0 | K76: =IFERROR(INDEX(MATRIZ_174!$U:$U,MATCH(A76,MATRIZ_174!$A:$A,0)),"") | L76: =IFERROR(MATRIZ_174!O76,0) | M76: 0 | N76: =IF(AND(F76>0,C76<34),"🔴 UE + Critico",IF(AND(F76>0,C76<67),"🟡 UE + Vulnerable",IF(AND(F76>0,C76>=67),"🟢 UE + Preparado",IF(C76=0,"— Sin dato","Sin exposición UE")))) | O76: LORETO
A77: 20542380455 | B77: COOPERATIVA AGRARIA ECOFOREST | C77: =ROUND(PONDERADORES!$D$12*G77+PONDERADORES!$D$13*H77+PONDERADORES!$D$14*I77+PONDERADORES!$D$15*J77+PONDERADORES!$D$16*K77+PONDERADORES!$D$17*L77+PONDERADORES!$D$18*M77,1) | D77: =IF(C77<34,"🔴 Critico",IF(C77<67,"🟡 Vulnerable","🟢 Preparado")) | E77: =IFERROR(RANK(C77,C:C,-1),"") | F77: 8445503.2 | G77: =IFERROR(MATRIZ_174!M77,0) | H77: 0 | I77: 0 | J77: 0 | K77: =IFERROR(INDEX(MATRIZ_174!$U:$U,MATCH(A77,MATRIZ_174!$A:$A,0)),"") | L77: =IFERROR(MATRIZ_174!O77,0) | M77: 0 | N77: =IF(AND(F77>0,C77<34),"🔴 UE + Critico",IF(AND(F77>0,C77<67),"🟡 UE + Vulnerable",IF(AND(F77>0,C77>=67),"🟢 UE + Preparado",IF(C77=0,"— Sin dato","Sin exposición UE")))) | O77: CAJAMARCA
A78: 20542482886 | B78: COOPERATIVA AGROINDUSTRIAL APCCA | C78: =ROUND(PONDERADORES!$D$12*G78+PONDERADORES!$D$13*H78+PONDERADORES!$D$14*I78+PONDERADORES!$D$15*J78+PONDERADORES!$D$16*K78+PONDERADORES!$D$17*L78+PONDERADORES!$D$18*M78,1) | D78: =IF(C78<34,"🔴 Critico",IF(C78<67,"🟡 Vulnerable","🟢 Preparado")) | E78: =IFERROR(RANK(C78,C:C,-1),"") | F78: =IFERROR(MATRIZ_174!L78,0) | G78: =IFERROR(MATRIZ_174!M78,0) | H78: 0 | I78: 0 | J78: 0 | K78: =IFERROR(INDEX(MATRIZ_174!$U:$U,MATCH(A78,MATRIZ_174!$A:$A,0)),"") | L78: =IFERROR(MATRIZ_174!O78,0) | M78: 0 | N78: =IF(AND(F78>0,C78<34),"🔴 UE + Critico",IF(AND(F78>0,C78<67),"🟡 UE + Vulnerable",IF(AND(F78>0,C78>=67),"🟢 UE + Preparado",IF(C78=0,"— Sin dato","Sin exposición UE")))) | O78: HUANUCO
A79: 20542825163 | B79: COOPERATIVA AGRARIA CACAO FINO AGROBOSQUE | C79: =ROUND(PONDERADORES!$D$12*G79+PONDERADORES!$D$13*H79+PONDERADORES!$D$14*I79+PONDERADORES!$D$15*J79+PONDERADORES!$D$16*K79+PONDERADORES!$D$17*L79+PONDERADORES!$D$18*M79,1) | D79: =IF(C79<34,"🔴 Critico",IF(C79<67,"🟡 Vulnerable","🟢 Preparado")) | E79: =IFERROR(RANK(C79,C:C,-1),"") | F79: 0 | G79: =IFERROR(MATRIZ_174!M79,0) | H79: 0 | I79: 0 | J79: 0 | K79: =IFERROR(INDEX(MATRIZ_174!$U:$U,MATCH(A79,MATRIZ_174!$A:$A,0)),"") | L79: =IFERROR(MATRIZ_174!O79,0) | M79: 0 | N79: =IF(AND(F79>0,C79<34),"🔴 UE + Critico",IF(AND(F79>0,C79<67),"🟡 UE + Vulnerable",IF(AND(F79>0,C79>=67),"🟢 UE + Preparado",IF(C79=0,"— Sin dato","Sin exposición UE")))) | O79: MADRE DE DIOS
A80: 20561140091 | B80: COOPERATIVA AGRARIA ECOLOGICA CAFETALERA DE LONYA GRANDE | C80: =ROUND(PONDERADORES!$D$12*G80+PONDERADORES!$D$13*H80+PONDERADORES!$D$14*I80+PONDERADORES!$D$15*J80+PONDERADORES!$D$16*K80+PONDERADORES!$D$17*L80+PONDERADORES!$D$18*M80,1) | D80: =IF(C80<34,"🔴 Critico",IF(C80<67,"🟡 Vulnerable","🟢 Preparado")) | E80: =IFERROR(RANK(C80,C:C,-1),"") | F80: 0 | G80: =IFERROR(MATRIZ_174!M80,0) | H80: 0 | I80: 0 | J80: 0 | K80: =IFERROR(INDEX(MATRIZ_174!$U:$U,MATCH(A80,MATRIZ_174!$A:$A,0)),"") | L80: =IFERROR(MATRIZ_174!O80,0) | M80: 0 | N80: =IF(AND(F80>0,C80<34),"🔴 UE + Critico",IF(AND(F80>0,C80<67),"🟡 UE + Vulnerable",IF(AND(F80>0,C80>=67),"🟢 UE + Preparado",IF(C80=0,"— Sin dato","Sin exposición UE")))) | O80: AMAZONAS
A81: 20564032485 | B81: ASOCIACION DE PRODUCTORES ECOLOGICOS DE CACAO MEDIO URUBAMBA | C81: =ROUND(PONDERADORES!$D$12*G81+PONDERADORES!$D$13*H81+PONDERADORES!$D$14*I81+PONDERADORES!$D$15*J81+PONDERADORES!$D$16*K81+PONDERADORES!$D$17*L81+PONDERADORES!$D$18*M81,1) | D81: =IF(C81<34,"🔴 Critico",IF(C81<67,"🟡 Vulnerable","🟢 Preparado")) | E81: =IFERROR(RANK(C81,C:C,-1),"") | F81: 0 | G81: =IFERROR(MATRIZ_174!M81,0) | H81: 0 | I81: 0 | J81: 0 | K81: =IFERROR(INDEX(MATRIZ_174!$U:$U,MATCH(A81,MATRIZ_174!$A:$A,0)),"") | L81: =IFERROR(MATRIZ_174!O81,0) | M81: 0 | N81: =IF(AND(F81>0,C81<34),"🔴 UE + Critico",IF(AND(F81>0,C81<67),"🟡 UE + Vulnerable",IF(AND(F81>0,C81>=67),"🟢 UE + Preparado",IF(C81=0,"— Sin dato","Sin exposición UE")))) | O81: CUSCO
A82: 20568071281 | B82: COOPERATIVA AGRARIA CAFETALERA CEPRO YANESHA | C82: =ROUND(PONDERADORES!$D$12*G82+PONDERADORES!$D$13*H82+PONDERADORES!$D$14*I82+PONDERADORES!$D$15*J82+PONDERADORES!$D$16*K82+PONDERADORES!$D$17*L82+PONDERADORES!$D$18*M82,1) | D82: =IF(C82<34,"🔴 Critico",IF(C82<67,"🟡 Vulnerable","🟢 Preparado")) | E82: =IFERROR(RANK(C82,C:C,-1),"") | F82: 717861.85 | G82: =IFERROR(MATRIZ_174!M82,0) | H82: 0 | I82: 0 | J82: 0 | K82: =IFERROR(INDEX(MATRIZ_174!$U:$U,MATCH(A82,MATRIZ_174!$A:$A,0)),"") | L82: =IFERROR(MATRIZ_174!O82,0) | M82: 0 | N82: =IF(AND(F82>0,C82<34),"🔴 UE + Critico",IF(AND(F82>0,C82<67),"🟡 UE + Vulnerable",IF(AND(F82>0,C82>=67),"🟢 UE + Preparado",IF(C82=0,"— Sin dato","Sin exposición UE")))) | O82: PASCO
A83: 20568080948 | B83: CONSEJO REGULADOR DE LA DENOMINACION DE ORIGEN CAFE VILLA RI | C83: =ROUND(PONDERADORES!$D$12*G83+PONDERADORES!$D$13*H83+PONDERADORES!$D$14*I83+PONDERADORES!$D$15*J83+PONDERADORES!$D$16*K83+PONDERADORES!$D$17*L83+PONDERADORES!$D$18*M83,1) | D83: =IF(C83<34,"🔴 Critico",IF(C83<67,"🟡 Vulnerable","🟢 Preparado")) | E83: =IFERROR(RANK(C83,C:C,-1),"") | F83: =IFERROR(MATRIZ_174!L83,0) | G83: =IFERROR(MATRIZ_174!M83,0) | H83: 0 | I83: 0 | J83: 0 | K83: =IFERROR(INDEX(MATRIZ_174!$U:$U,MATCH(A83,MATRIZ_174!$A:$A,0)),"") | L83: =IFERROR(MATRIZ_174!O83,0) | M83: 0 | N83: =IF(AND(F83>0,C83<34),"🔴 UE + Critico",IF(AND(F83>0,C83<67),"🟡 UE + Vulnerable",IF(AND(F83>0,C83>=67),"🟢 UE + Preparado",IF(C83=0,"— Sin dato","Sin exposición UE")))) | O83: PASCO
A84: 20568190450 | B84: COOPERATIVA AGRARIA KEMITO ENE LTDA. - KEMITO ENE | C84: =ROUND(PONDERADORES!$D$12*G84+PONDERADORES!$D$13*H84+PONDERADORES!$D$14*I84+PONDERADORES!$D$15*J84+PONDERADORES!$D$16*K84+PONDERADORES!$D$17*L84+PONDERADORES!$D$18*M84,1) | D84: =IF(C84<34,"🔴 Critico",IF(C84<67,"🟡 Vulnerable","🟢 Preparado")) | E84: =IFERROR(RANK(C84,C:C,-1),"") | F84: =IFERROR(MATRIZ_174!L84,0) | G84: =IFERROR(MATRIZ_174!M84,0) | H84: 0 | I84: 0 | J84: 0 | K84: =IFERROR(INDEX(MATRIZ_174!$U:$U,MATCH(A84,MATRIZ_174!$A:$A,0)),"") | L84: =IFERROR(MATRIZ_174!O84,0) | M84: 0 | N84: =IF(AND(F84>0,C84<34),"🔴 UE + Critico",IF(AND(F84>0,C84<67),"🟡 UE + Vulnerable",IF(AND(F84>0,C84>=67),"🟢 UE + Preparado",IF(C84=0,"— Sin dato","Sin exposición UE")))) | O84: JUNIN
A85: 20568194951 | B85: ASOCIACION DE PRODUCTORES AGROSOSTENIBLES VILLA ECOLOGICA PE | C85: =ROUND(PONDERADORES!$D$12*G85+PONDERADORES!$D$13*H85+PONDERADORES!$D$14*I85+PONDERADORES!$D$15*J85+PONDERADORES!$D$16*K85+PONDERADORES!$D$17*L85+PONDERADORES!$D$18*M85,1) | D85: =IF(C85<34,"🔴 Critico",IF(C85<67,"🟡 Vulnerable","🟢 Preparado")) | E85: =IFERROR(RANK(C85,C:C,-1),"") | F85: 2677512.6 | G85: =IFERROR(MATRIZ_174!M85,0) | H85: 0 | I85: 0 | J85: 0 | K85: =IFERROR(INDEX(MATRIZ_174!$U:$U,MATCH(A85,MATRIZ_174!$A:$A,0)),"") | L85: =IFERROR(MATRIZ_174!O85,0) | M85: 0 | N85: =IF(AND(F85>0,C85<34),"🔴 UE + Critico",IF(AND(F85>0,C85<67),"🟡 UE + Vulnerable",IF(AND(F85>0,C85>=67),"🟢 UE + Preparado",IF(C85=0,"— Sin dato","Sin exposición UE")))) | O85: JUNIN
A86: 20568428375 | B86: COOPERATIVA AGRARIA ASHANINKA DEL VALLE PICHIS | C86: =ROUND(PONDERADORES!$D$12*G86+PONDERADORES!$D$13*H86+PONDERADORES!$D$14*I86+PONDERADORES!$D$15*J86+PONDERADORES!$D$16*K86+PONDERADORES!$D$17*L86+PONDERADORES!$D$18*M86,1) | D86: =IF(C86<34,"🔴 Critico",IF(C86<67,"🟡 Vulnerable","🟢 Preparado")) | E86: =IFERROR(RANK(C86,C:C,-1),"") | F86: =IFERROR(MATRIZ_174!L86,0) | G86: =IFERROR(MATRIZ_174!M86,0) | H86: 0 | I86: 0 | J86: 0 | K86: =IFERROR(INDEX(MATRIZ_174!$U:$U,MATCH(A86,MATRIZ_174!$A:$A,0)),"") | L86: =IFERROR(MATRIZ_174!O86,0) | M86: 0 | N86: =IF(AND(F86>0,C86<34),"🔴 UE + Critico",IF(AND(F86>0,C86<67),"🟡 UE + Vulnerable",IF(AND(F86>0,C86>=67),"🟢 UE + Preparado",IF(C86=0,"— Sin dato","Sin exposición UE")))) | O86: PASCO
A87: 20568549083 | B87: COOPERATIVA AGRARIA INDUSTRIAL APASC SANCORE-PALCAZU LTDA | C87: =ROUND(PONDERADORES!$D$12*G87+PONDERADORES!$D$13*H87+PONDERADORES!$D$14*I87+PONDERADORES!$D$15*J87+PONDERADORES!$D$16*K87+PONDERADORES!$D$17*L87+PONDERADORES!$D$18*M87,1) | D87: =IF(C87<34,"🔴 Critico",IF(C87<67,"🟡 Vulnerable","🟢 Preparado")) | E87: =IFERROR(RANK(C87,C:C,-1),"") | F87: =IFERROR(MATRIZ_174!L87,0) | G87: =IFERROR(MATRIZ_174!M87,0) | H87: 0 | I87: 0 | J87: 0 | K87: =IFERROR(INDEX(MATRIZ_174!$U:$U,MATCH(A87,MATRIZ_174!$A:$A,0)),"") | L87: =IFERROR(MATRIZ_174!O87,0) | M87: 0 | N87: =IF(AND(F87>0,C87<34),"🔴 UE + Critico",IF(AND(F87>0,C87<67),"🟡 UE + Vulnerable",IF(AND(F87>0,C87>=67),"🟢 UE + Preparado",IF(C87=0,"— Sin dato","Sin exposición UE")))) | O87: PASCO
A88: 20568560133 | B88: COOPERATIVA AGRARIA ECOLOGICO ALTO PALCAZU LAGUNA RAYA | C88: =ROUND(PONDERADORES!$D$12*G88+PONDERADORES!$D$13*H88+PONDERADORES!$D$14*I88+PONDERADORES!$D$15*J88+PONDERADORES!$D$16*K88+PONDERADORES!$D$17*L88+PONDERADORES!$D$18*M88,1) | D88: =IF(C88<34,"🔴 Critico",IF(C88<67,"🟡 Vulnerable","🟢 Preparado")) | E88: =IFERROR(RANK(C88,C:C,-1),"") | F88: =IFERROR(MATRIZ_174!L88,0) | G88: =IFERROR(MATRIZ_174!M88,0) | H88: 0 | I88: 0 | J88: 0 | K88: =IFERROR(INDEX(MATRIZ_174!$U:$U,MATCH(A88,MATRIZ_174!$A:$A,0)),"") | L88: =IFERROR(MATRIZ_174!O88,0) | M88: 0 | N88: =IF(AND(F88>0,C88<34),"🔴 UE + Critico",IF(AND(F88>0,C88<67),"🟡 UE + Vulnerable",IF(AND(F88>0,C88>=67),"🟢 UE + Preparado",IF(C88=0,"— Sin dato","Sin exposición UE")))) | O88: PASCO
A89: 20568567731 | B89: COOPERATIVA AGRARIA VILLA RICA GOLDEN COFFEE LTDA. | C89: =ROUND(PONDERADORES!$D$12*G89+PONDERADORES!$D$13*H89+PONDERADORES!$D$14*I89+PONDERADORES!$D$15*J89+PONDERADORES!$D$16*K89+PONDERADORES!$D$17*L89+PONDERADORES!$D$18*M89,1) | D89: =IF(C89<34,"🔴 Critico",IF(C89<67,"🟡 Vulnerable","🟢 Preparado")) | E89: =IFERROR(RANK(C89,C:C,-1),"") | F89: 0 | G89: =IFERROR(MATRIZ_174!M89,0) | H89: 0 | I89: 0 | J89: 0 | K89: =IFERROR(INDEX(MATRIZ_174!$U:$U,MATCH(A89,MATRIZ_174!$A:$A,0)),"") | L89: =IFERROR(MATRIZ_174!O89,0) | M89: 0 | N89: =IF(AND(F89>0,C89<34),"🔴 UE + Critico",IF(AND(F89>0,C89<67),"🟡 UE + Vulnerable",IF(AND(F89>0,C89>=67),"🟢 UE + Preparado",IF(C89=0,"— Sin dato","Sin exposición UE")))) | O89: PASCO
A90: 20568609833 | B90: ASOCIACION DE MUJERES PRODUCTORAS ARTESANAS CACAO JENTARI - | C90: =ROUND(PONDERADORES!$D$12*G90+PONDERADORES!$D$13*H90+PONDERADORES!$D$14*I90+PONDERADORES!$D$15*J90+PONDERADORES!$D$16*K90+PONDERADORES!$D$17*L90+PONDERADORES!$D$18*M90,1) | D90: =IF(C90<34,"🔴 Critico",IF(C90<67,"🟡 Vulnerable","🟢 Preparado")) | E90: =IFERROR(RANK(C90,C:C,-1),"") | F90: =IFERROR(MATRIZ_174!L90,0) | G90: =IFERROR(MATRIZ_174!M90,0) | H90: 0 | I90: 0 | J90: 0 | K90: =IFERROR(INDEX(MATRIZ_174!$U:$U,MATCH(A90,MATRIZ_174!$A:$A,0)),"") | L90: =IFERROR(MATRIZ_174!O90,0) | M90: 0 | N90: =IF(AND(F90>0,C90<34),"🔴 UE + Critico",IF(AND(F90>0,C90<67),"🟡 UE + Vulnerable",IF(AND(F90>0,C90>=67),"🟢 UE + Preparado",IF(C90=0,"— Sin dato","Sin exposición UE")))) | O90: JUNIN
A91: 20568962282 | B91: ASOCIACIÓN DE PRODUCTORES CENTRO COFFEE | C91: =ROUND(PONDERADORES!$D$12*G91+PONDERADORES!$D$13*H91+PONDERADORES!$D$14*I91+PONDERADORES!$D$15*J91+PONDERADORES!$D$16*K91+PONDERADORES!$D$17*L91+PONDERADORES!$D$18*M91,1) | D91: =IF(C91<34,"🔴 Critico",IF(C91<67,"🟡 Vulnerable","🟢 Preparado")) | E91: =IFERROR(RANK(C91,C:C,-1),"") | F91: 0 | G91: =IFERROR(MATRIZ_174!M91,0) | H91: 0 | I91: 0 | J91: 0 | K91: =IFERROR(INDEX(MATRIZ_174!$U:$U,MATCH(A91,MATRIZ_174!$A:$A,0)),"") | L91: =IFERROR(MATRIZ_174!O91,0) | M91: 0 | N91: =IF(AND(F91>0,C91<34),"🔴 UE + Critico",IF(AND(F91>0,C91<67),"🟡 UE + Vulnerable",IF(AND(F91>0,C91>=67),"🟢 UE + Preparado",IF(C91=0,"— Sin dato","Sin exposición UE")))) | O91: JUNIN
A92: 20570706927 | B92: COOPERATIVA AGRARIA RUTAS DEL INCA | C92: =ROUND(PONDERADORES!$D$12*G92+PONDERADORES!$D$13*H92+PONDERADORES!$D$14*I92+PONDERADORES!$D$15*J92+PONDERADORES!$D$16*K92+PONDERADORES!$D$17*L92+PONDERADORES!$D$18*M92,1) | D92: =IF(C92<34,"🔴 Critico",IF(C92<67,"🟡 Vulnerable","🟢 Preparado")) | E92: =IFERROR(RANK(C92,C:C,-1),"") | F92: 4792670.9 | G92: =IFERROR(MATRIZ_174!M92,0) | H92: 0 | I92: 0 | J92: 0 | K92: =IFERROR(INDEX(MATRIZ_174!$U:$U,MATCH(A92,MATRIZ_174!$A:$A,0)),"") | L92: =IFERROR(MATRIZ_174!O92,0) | M92: 0 | N92: =IF(AND(F92>0,C92<34),"🔴 UE + Critico",IF(AND(F92>0,C92<67),"🟡 UE + Vulnerable",IF(AND(F92>0,C92>=67),"🟢 UE + Preparado",IF(C92=0,"— Sin dato","Sin exposición UE")))) | O92: CAJAMARCA
A93: 20572111131 | B93: ASOCIACION DE MUJERES ORGANIZADAS CHOCO WARMIS | C93: =ROUND(PONDERADORES!$D$12*G93+PONDERADORES!$D$13*H93+PONDERADORES!$D$14*I93+PONDERADORES!$D$15*J93+PONDERADORES!$D$16*K93+PONDERADORES!$D$17*L93+PONDERADORES!$D$18*M93,1) | D93: =IF(C93<34,"🔴 Critico",IF(C93<67,"🟡 Vulnerable","🟢 Preparado")) | E93: =IFERROR(RANK(C93,C:C,-1),"") | F93: =IFERROR(MATRIZ_174!L93,0) | G93: =IFERROR(MATRIZ_174!M93,0) | H93: 0 | I93: 0 | J93: 0 | K93: =IFERROR(INDEX(MATRIZ_174!$U:$U,MATCH(A93,MATRIZ_174!$A:$A,0)),"") | L93: =IFERROR(MATRIZ_174!O93,0) | M93: 0 | N93: =IF(AND(F93>0,C93<34),"🔴 UE + Critico",IF(AND(F93>0,C93<67),"🟡 UE + Vulnerable",IF(AND(F93>0,C93>=67),"🟢 UE + Preparado",IF(C93=0,"— Sin dato","Sin exposición UE")))) | O93: SAN MARTIN
A94: 20572190251 | B94: CENTRAL DE COOPERATIVAS AGRARIAS CACAO AROMA DE TOCACHE LTDA | C94: =ROUND(PONDERADORES!$D$12*G94+PONDERADORES!$D$13*H94+PONDERADORES!$D$14*I94+PONDERADORES!$D$15*J94+PONDERADORES!$D$16*K94+PONDERADORES!$D$17*L94+PONDERADORES!$D$18*M94,1) | D94: =IF(C94<34,"🔴 Critico",IF(C94<67,"🟡 Vulnerable","🟢 Preparado")) | E94: =IFERROR(RANK(C94,C:C,-1),"") | F94: 1888972.4 | G94: =IFERROR(MATRIZ_174!M94,0) | H94: 0 | I94: 0 | J94: 0 | K94: =IFERROR(INDEX(MATRIZ_174!$U:$U,MATCH(A94,MATRIZ_174!$A:$A,0)),"") | L94: =IFERROR(MATRIZ_174!O94,0) | M94: 0 | N94: =IF(AND(F94>0,C94<34),"🔴 UE + Critico",IF(AND(F94>0,C94<67),"🟡 UE + Vulnerable",IF(AND(F94>0,C94>=67),"🟢 UE + Preparado",IF(C94=0,"— Sin dato","Sin exposición UE")))) | O94: SAN MARTIN
A95: 20573049102 | B95: COOPERATIVA AGRARIA CACAOTERA PUERTO INCA | C95: =ROUND(PONDERADORES!$D$12*G95+PONDERADORES!$D$13*H95+PONDERADORES!$D$14*I95+PONDERADORES!$D$15*J95+PONDERADORES!$D$16*K95+PONDERADORES!$D$17*L95+PONDERADORES!$D$18*M95,1) | D95: =IF(C95<34,"🔴 Critico",IF(C95<67,"🟡 Vulnerable","🟢 Preparado")) | E95: =IFERROR(RANK(C95,C:C,-1),"") | F95: =IFERROR(MATRIZ_174!L95,0) | G95: =IFERROR(MATRIZ_174!M95,0) | H95: 0 | I95: 0 | J95: 0 | K95: =IFERROR(INDEX(MATRIZ_174!$U:$U,MATCH(A95,MATRIZ_174!$A:$A,0)),"") | L95: =IFERROR(MATRIZ_174!O95,0) | M95: 0 | N95: =IF(AND(F95>0,C95<34),"🔴 UE + Critico",IF(AND(F95>0,C95<67),"🟡 UE + Vulnerable",IF(AND(F95>0,C95>=67),"🟢 UE + Preparado",IF(C95=0,"— Sin dato","Sin exposición UE")))) | O95: HUANUCO
A96: 20573057385 | B96: COOPERATIVA AGRARIA PARAISO | C96: =ROUND(PONDERADORES!$D$12*G96+PONDERADORES!$D$13*H96+PONDERADORES!$D$14*I96+PONDERADORES!$D$15*J96+PONDERADORES!$D$16*K96+PONDERADORES!$D$17*L96+PONDERADORES!$D$18*M96,1) | D96: =IF(C96<34,"🔴 Critico",IF(C96<67,"🟡 Vulnerable","🟢 Preparado")) | E96: =IFERROR(RANK(C96,C:C,-1),"") | F96: 0 | G96: =IFERROR(MATRIZ_174!M96,0) | H96: 0 | I96: 0 | J96: 0 | K96: =IFERROR(INDEX(MATRIZ_174!$U:$U,MATCH(A96,MATRIZ_174!$A:$A,0)),"") | L96: =IFERROR(MATRIZ_174!O96,0) | M96: 0 | N96: =IF(AND(F96>0,C96<34),"🔴 UE + Critico",IF(AND(F96>0,C96<67),"🟡 UE + Vulnerable",IF(AND(F96>0,C96>=67),"🟢 UE + Preparado",IF(C96=0,"— Sin dato","Sin exposición UE")))) | O96: HUANUCO
A97: 20573138202 | B97: ASOCIACION DE PRODUCTORES AGROPECUARIOS Y FORESTALES EL ALVA | C97: =ROUND(PONDERADORES!$D$12*G97+PONDERADORES!$D$13*H97+PONDERADORES!$D$14*I97+PONDERADORES!$D$15*J97+PONDERADORES!$D$16*K97+PONDERADORES!$D$17*L97+PONDERADORES!$D$18*M97,1) | D97: =IF(C97<34,"🔴 Critico",IF(C97<67,"🟡 Vulnerable","🟢 Preparado")) | E97: =IFERROR(RANK(C97,C:C,-1),"") | F97: =IFERROR(MATRIZ_174!L97,0) | G97: =IFERROR(MATRIZ_174!M97,0) | H97: 0 | I97: 0 | J97: 0 | K97: =IFERROR(INDEX(MATRIZ_174!$U:$U,MATCH(A97,MATRIZ_174!$A:$A,0)),"") | L97: =IFERROR(MATRIZ_174!O97,0) | M97: 0 | N97: =IF(AND(F97>0,C97<34),"🔴 UE + Critico",IF(AND(F97>0,C97<67),"🟡 UE + Vulnerable",IF(AND(F97>0,C97>=67),"🟢 UE + Preparado",IF(C97=0,"— Sin dato","Sin exposición UE")))) | O97: HUANUCO
A98: 20573260008 | B98: COOPERATIVA AGRARIA AUCAYACU | C98: =ROUND(PONDERADORES!$D$12*G98+PONDERADORES!$D$13*H98+PONDERADORES!$D$14*I98+PONDERADORES!$D$15*J98+PONDERADORES!$D$16*K98+PONDERADORES!$D$17*L98+PONDERADORES!$D$18*M98,1) | D98: =IF(C98<34,"🔴 Critico",IF(C98<67,"🟡 Vulnerable","🟢 Preparado")) | E98: =IFERROR(RANK(C98,C:C,-1),"") | F98: =IFERROR(MATRIZ_174!L98,0) | G98: =IFERROR(MATRIZ_174!M98,0) | H98: 0 | I98: 0 | J98: 0 | K98: =IFERROR(INDEX(MATRIZ_174!$U:$U,MATCH(A98,MATRIZ_174!$A:$A,0)),"") | L98: =IFERROR(MATRIZ_174!O98,0) | M98: 0 | N98: =IF(AND(F98>0,C98<34),"🔴 UE + Critico",IF(AND(F98>0,C98<67),"🟡 UE + Vulnerable",IF(AND(F98>0,C98>=67),"🟢 UE + Preparado",IF(C98=0,"— Sin dato","Sin exposición UE")))) | O98: HUANUCO
A99: 20573344791 | B99: ASOCIACION AGROECOLOGICO HUANGANAPAMPA | C99: =ROUND(PONDERADORES!$D$12*G99+PONDERADORES!$D$13*H99+PONDERADORES!$D$14*I99+PONDERADORES!$D$15*J99+PONDERADORES!$D$16*K99+PONDERADORES!$D$17*L99+PONDERADORES!$D$18*M99,1) | D99: =IF(C99<34,"🔴 Critico",IF(C99<67,"🟡 Vulnerable","🟢 Preparado")) | E99: =IFERROR(RANK(C99,C:C,-1),"") | F99: =IFERROR(MATRIZ_174!L99,0) | G99: =IFERROR(MATRIZ_174!M99,0) | H99: 0 | I99: 0 | J99: 0 | K99: =IFERROR(INDEX(MATRIZ_174!$U:$U,MATCH(A99,MATRIZ_174!$A:$A,0)),"") | L99: =IFERROR(MATRIZ_174!O99,0) | M99: 0 | N99: =IF(AND(F99>0,C99<34),"🔴 UE + Critico",IF(AND(F99>0,C99<67),"🟡 UE + Vulnerable",IF(AND(F99>0,C99>=67),"🟢 UE + Preparado",IF(C99=0,"— Sin dato","Sin exposición UE")))) | O99: HUANUCO
A100: 20574797013 | B100: ASOCIACION DE PRODUCTORES AGROPECUARIOS DE PARAISO CENTRAL | C100: =ROUND(PONDERADORES!$D$12*G100+PONDERADORES!$D$13*H100+PONDERADORES!$D$14*I100+PONDERADORES!$D$15*J100+PONDERADORES!$D$16*K100+PONDERADORES!$D$17*L100+PONDERADORES!$D$18*M100,1) | D100: =IF(C100<34,"🔴 Critico",IF(C100<67,"🟡 Vulnerable","🟢 Preparado")) | E100: =IFERROR(RANK(C100,C:C,-1),"") | F100: =IFERROR(MATRIZ_174!L100,0) | G100: =IFERROR(MATRIZ_174!M100,0) | H100: 0 | I100: 0 | J100: 0 | K100: =IFERROR(INDEX(MATRIZ_174!$U:$U,MATCH(A100,MATRIZ_174!$A:$A,0)),"") | L100: =IFERROR(MATRIZ_174!O100,0) | M100: 0 | N100: =IF(AND(F100>0,C100<34),"🔴 UE + Critico",IF(AND(F100>0,C100<67),"🟡 UE + Vulnerable",IF(AND(F100>0,C100>=67),"🟢 UE + Preparado",IF(C100=0,"— Sin dato","Sin exposición UE")))) | O100: CUSCO
...

Sheet RADAR_BRECHAS
A1: RADAR DE BRECHAS — Score promedio por departamento y dimensión
A2: Departamento / Dimensión | B2: D1 | C2: D2 | D2: D3 | E2: D4 | F2: D5 | G2: D6 | H2: D7 | I2: D8 | J2: D9 | K2: D10 | L2: D11 | M2: PVE Promedio
A3: SAN MARTIN | B3: =0 | C3: =IFERROR(AVERAGEIF(MATRIZ_174!C:C,A3,SCORECARDS!H:H),0) | D3: =IFERROR(AVERAGEIF(MATRIZ_174!$C:$C,A3,SCORECARDS!$K:$K),0) | E3: =0 | F3: =IFERROR(AVERAGEIF(MATRIZ_174!C:C,A3,SCORECARDS!I:I),0) | G3: =IFERROR(AVERAGEIF(MATRIZ_174!C:C,A3,SCORECARDS!J:J),0) | H3: =IFERROR(AVERAGEIF(MATRIZ_174!C:C,A3,SCORECARDS!K:K),0) | I3: =0 | J3: =0 | K3: =0 | L3: =0 | M3: =IFERROR(AVERAGE(B3:L3),0)
A4: JUNIN | B4: =0 | C4: =IFERROR(AVERAGEIF(MATRIZ_174!C:C,A4,SCORECARDS!H:H),0) | D4: =IFERROR(AVERAGEIF(MATRIZ_174!$C:$C,A4,SCORECARDS!$K:$K),0) | E4: =0 | F4: =IFERROR(AVERAGEIF(MATRIZ_174!C:C,A4,SCORECARDS!I:I),0) | G4: =IFERROR(AVERAGEIF(MATRIZ_174!C:C,A4,SCORECARDS!J:J),0) | H4: =IFERROR(AVERAGEIF(MATRIZ_174!C:C,A4,SCORECARDS!K:K),0) | I4: =0 | J4: =0 | K4: =0 | L4: =0 | M4: =IFERROR(AVERAGE(B4:L4),0)
A5: AMAZONAS | B5: =0 | C5: =IFERROR(AVERAGEIF(MATRIZ_174!C:C,A5,SCORECARDS!H:H),0) | D5: =IFERROR(AVERAGEIF(MATRIZ_174!$C:$C,A5,SCORECARDS!$K:$K),0) | E5: =0 | F5: =IFERROR(AVERAGEIF(MATRIZ_174!C:C,A5,SCORECARDS!I:I),0) | G5: =IFERROR(AVERAGEIF(MATRIZ_174!C:C,A5,SCORECARDS!J:J),0) | H5: =IFERROR(AVERAGEIF(MATRIZ_174!C:C,A5,SCORECARDS!K:K),0) | I5: =0 | J5: =0 | K5: =0 | L5: =0 | M5: =IFERROR(AVERAGE(B5:L5),0)
A6: CAJAMARCA | B6: =0 | C6: =IFERROR(AVERAGEIF(MATRIZ_174!C:C,A6,SCORECARDS!H:H),0) | D6: =IFERROR(AVERAGEIF(MATRIZ_174!$C:$C,A6,SCORECARDS!$K:$K),0) | E6: =0 | F6: =IFERROR(AVERAGEIF(MATRIZ_174!C:C,A6,SCORECARDS!I:I),0) | G6: =IFERROR(AVERAGEIF(MATRIZ_174!C:C,A6,SCORECARDS!J:J),0) | H6: =IFERROR(AVERAGEIF(MATRIZ_174!C:C,A6,SCORECARDS!K:K),0) | I6: =0 | J6: =0 | K6: =0 | L6: =0 | M6: =IFERROR(AVERAGE(B6:L6),0)
A7: CUSCO | B7: =0 | C7: =IFERROR(AVERAGEIF(MATRIZ_174!C:C,A7,SCORECARDS!H:H),0) | D7: =IFERROR(AVERAGEIF(MATRIZ_174!$C:$C,A7,SCORECARDS!$K:$K),0) | E7: =0 | F7: =IFERROR(AVERAGEIF(MATRIZ_174!C:C,A7,SCORECARDS!I:I),0) | G7: =IFERROR(AVERAGEIF(MATRIZ_174!C:C,A7,SCORECARDS!J:J),0) | H7: =IFERROR(AVERAGEIF(MATRIZ_174!C:C,A7,SCORECARDS!K:K),0) | I7: =0 | J7: =0 | K7: =0 | L7: =0 | M7: =IFERROR(AVERAGE(B7:L7),0)
A8: UCAYALI | B8: =0 | C8: =IFERROR(AVERAGEIF(MATRIZ_174!C:C,A8,SCORECARDS!H:H),0) | D8: =IFERROR(AVERAGEIF(MATRIZ_174!$C:$C,A8,SCORECARDS!$K:$K),0) | E8: =0 | F8: =IFERROR(AVERAGEIF(MATRIZ_174!C:C,A8,SCORECARDS!I:I),0) | G8: =IFERROR(AVERAGEIF(MATRIZ_174!C:C,A8,SCORECARDS!J:J),0) | H8: =IFERROR(AVERAGEIF(MATRIZ_174!C:C,A8,SCORECARDS!K:K),0) | I8: =0 | J8: =0 | K8: =0 | L8: =0 | M8: =IFERROR(AVERAGE(B8:L8),0)
A9: PASCO | B9: =0 | C9: =IFERROR(AVERAGEIF(MATRIZ_174!C:C,A9,SCORECARDS!H:H),0) | D9: =IFERROR(AVERAGEIF(MATRIZ_174!$C:$C,A9,SCORECARDS!$K:$K),0) | E9: =0 | F9: =IFERROR(AVERAGEIF(MATRIZ_174!C:C,A9,SCORECARDS!I:I),0) | G9: =IFERROR(AVERAGEIF(MATRIZ_174!C:C,A9,SCORECARDS!J:J),0) | H9: =IFERROR(AVERAGEIF(MATRIZ_174!C:C,A9,SCORECARDS!K:K),0) | I9: =0 | J9: =0 | K9: =0 | L9: =0 | M9: =IFERROR(AVERAGE(B9:L9),0)
A10: PIURA | B10: =0 | C10: =IFERROR(AVERAGEIF(MATRIZ_174!C:C,A10,SCORECARDS!H:H),0) | D10: =IFERROR(AVERAGEIF(MATRIZ_174!$C:$C,A10,SCORECARDS!$K:$K),0) | E10: =0 | F10: =IFERROR(AVERAGEIF(MATRIZ_174!C:C,A10,SCORECARDS!I:I),0) | G10: =IFERROR(AVERAGEIF(MATRIZ_174!C:C,A10,SCORECARDS!J:J),0) | H10: =IFERROR(AVERAGEIF(MATRIZ_174!C:C,A10,SCORECARDS!K:K),0) | I10: =0 | J10: =0 | K10: =0 | L10: =0 | M10: =IFERROR(AVERAGE(B10:L10),0)
A11: AYACUCHO | B11: =0 | C11: =IFERROR(AVERAGEIF(MATRIZ_174!C:C,A11,SCORECARDS!H:H),0) | D11: =IFERROR(AVERAGEIF(MATRIZ_174!$C:$C,A11,SCORECARDS!$K:$K),0) | E11: =0 | F11: =IFERROR(AVERAGEIF(MATRIZ_174!C:C,A11,SCORECARDS!I:I),0) | G11: =IFERROR(AVERAGEIF(MATRIZ_174!C:C,A11,SCORECARDS!J:J),0) | H11: =IFERROR(AVERAGEIF(MATRIZ_174!C:C,A11,SCORECARDS!K:K),0) | I11: =0 | J11: =0 | K11: =0 | L11: =0 | M11: =IFERROR(AVERAGE(B11:L11),0)
A12: PUNO | B12: =0 | C12: =IFERROR(AVERAGEIF(MATRIZ_174!C:C,A12,SCORECARDS!H:H),0) | D12: =IFERROR(AVERAGEIF(MATRIZ_174!$C:$C,A12,SCORECARDS!$K:$K),0) | E12: =0 | F12: =IFERROR(AVERAGEIF(MATRIZ_174!C:C,A12,SCORECARDS!I:I),0) | G12: =IFERROR(AVERAGEIF(MATRIZ_174!C:C,A12,SCORECARDS!J:J),0) | H12: =IFERROR(AVERAGEIF(MATRIZ_174!C:C,A12,SCORECARDS!K:K),0) | I12: =0 | J12: =0 | K12: =0 | L12: =0 | M12: =IFERROR(AVERAGE(B12:L12),0)
A13: APURIMAC | B13: =0 | C13: =IFERROR(AVERAGEIF(MATRIZ_174!C:C,A13,SCORECARDS!H:H),0) | D13: =IFERROR(AVERAGEIF(MATRIZ_174!$C:$C,A13,SCORECARDS!$K:$K),0) | E13: =0 | F13: =IFERROR(AVERAGEIF(MATRIZ_174!C:C,A13,SCORECARDS!I:I),0) | G13: =IFERROR(AVERAGEIF(MATRIZ_174!C:C,A13,SCORECARDS!J:J),0) | H13: =IFERROR(AVERAGEIF(MATRIZ_174!C:C,A13,SCORECARDS!K:K),0) | I13: =0 | J13: =0 | K13: =0 | L13: =0 | M13: =IFERROR(AVERAGE(B13:L13),0)
A14: MADRE DE DIOS | B14: =0 | C14: =IFERROR(AVERAGEIF(MATRIZ_174!C:C,A14,SCORECARDS!H:H),0) | D14: =IFERROR(AVERAGEIF(MATRIZ_174!$C:$C,A14,SCORECARDS!$K:$K),0) | E14: =0 | F14: =IFERROR(AVERAGEIF(MATRIZ_174!C:C,A14,SCORECARDS!I:I),0) | G14: =IFERROR(AVERAGEIF(MATRIZ_174!C:C,A14,SCORECARDS!J:J),0) | H14: =IFERROR(AVERAGEIF(MATRIZ_174!C:C,A14,SCORECARDS!K:K),0) | I14: =0 | J14: =0 | K14: =0 | L14: =0 | M14: =IFERROR(AVERAGE(B14:L14),0)
... A17: OTROS | B17: =0 | C17: =IFERROR(AVERAGEIF(MATRIZ_174!C:C,A17,SCORECARDS!H:H),0) | D17: =IFERROR(AVERAGEIF(MATRIZ_174!$C:$C,A17,SCORECARDS!$K:$K),0) | E17: =0 | F17: =IFERROR(AVERAGEIF(MATRIZ_174!C:C,A17,SCORECARDS!I:I),0) | G17: =IFERROR(AVERAGEIF(MATRIZ_174!C:C,A17,SCORECARDS!J:J),0) | H17: =IFERROR(AVERAGEIF(MATRIZ_174!C:C,A17,SCORECARDS!K:K),0) | I17: =0 | J17: =0 | K17: =0 | L17: =0 | M17: =IFERROR(AVERAGE(B17:L17),0)
D18: =IFERROR(AVERAGEIF(MATRIZ_174!$C:$C,A18,SCORECARDS!$K:$K),0)
D19: =IFERROR(AVERAGEIF(MATRIZ_174!$C:$C,A19,SCORECARDS!$K:$K),0)
A20: LEYENDA — NIVELES DE CUMPLIMIENTO
A21: 🟢 Verde (0.67–1.00) — Cumplimiento adecuado
A22: 🟡 Amarillo (0.34–0.66) — Brecha moderada
A23: 🔴 Rojo (0.00–0.33) — Brecha crítica
A24: ⬜ Gris (0.00) — Sin dato capturado
D25: =IFERROR(AVERAGEIF(MATRIZ_174!$C:$C,A25,SCORECARDS!$K:$K),0)
A26: NOTA: Los scores en D2, D5, D6, D7 corresponden a los valores ingresados manualmente en SCORECARDS. Completar la hoja PREGUNTAS_PROXY y transferir los scores a SCORECARDS para actualizar este radar.
