Workbook

Sheet INSTRUCCIONES
A1: PLANTILLA ÍNDICE PVE — PACTO VERDE EUROPEO
A2: Clasificación de preparación y vulnerabilidad de cooperativas café y cacao ante el EUDR / Pacto Verde Europeo
A4: PROPÓSITO
A7: CÓMO FUNCIONA
A10: FLUJO DE USO
A11: Paso 1 | B11: Revisar PONDERADORES — los pesos son editables en celdas amarillas
A12: Paso 2 | B12: Ir a MATRIZ_174 — verificar/actualizar FOB, país destino, certificaciones
A13: Paso 3 | B13: Para cada organización con FOB UE > 0, completar PREGUNTAS_PROXY usando llamada telefónica o visita de 30 min
A14: Paso 4 | B14: Revisar SCORECARDS — el semáforo se actualiza automáticamente
A15: Paso 5 | B15: Usar RADAR_BRECHAS para comparación por departamento
A17: SEMÁFORO
A18: 🔴 Crítico (0–33) | B18: La cooperativa no puede generar la declaración EUDR. Riesgo de rechazo en frontera UE desde dic 2026.
A19: 🟡 Vulnerable (34–66) | B19: Tiene infraestructura parcial pero incompleta. Necesita inversión en geolocalización y proceso.
A20: 🟢 Preparado (67–100) | B20: Cumple los requisitos mínimos. Requiere monitoreo de actualización.
A22: NOTAS IMPORTANTES

Sheet ISCAM_Score
A1: ISCAM — ISA-Completo = 0.70×ISA-EUDR + 0.30×ISA-PV | IP × IV → RE | Café y Cacao Perú — 174 organizaciones
A2: ISA-Completo = 0.70×ISA-EUDR + 0.30×ISA-PV | ISA-EUDR = 0.875×Núcleo(D1–D7, geom.) + 0.125×Extendido(D8–D9, arit.) | ISA-PV = Promedio(D12:D15) | IP = Promedio(IP1..IP5) | IV = Promedio(IV1..IV5) | RE = IV×(1−IP/100) | Corte 2×2: 50
A3: RUC | B3: Razón Social | C3: Depto | D3: FOB UE USD | E3: D1 — Clasific. Regulatoria | F3: D2 — Trazabilidad (SCORECARDS H) | G3: D3 — Legalidad (OSCE/Neon) | H3: D4 — Deforestación Cero | I3: D5 — Diligencia Debida | J3: D6 — Capacidad Digital | K3: D7 — Presión Comprador | L3: D8 — Gobernanza | M3: D9 — Riesgo Financiero | N3: D10 — Certificac. | O3: D11 — Género e Inclusión | P3: IP1 Trazabilidad D2 | Q3: IP2 √(D3×D4) | R3: IP3 (D5+D6+D8)/3 | S3: IP4 (D6+D2)/2 | T3: IP5 (D7+D9+Cert)/3 | U3: IV1 Presión EU ISA-PV×50 | V3: IV2 D1 (base=50) | W3: IV3 ha>0? → 65:35 | X3: IV4 Cert=0? → 70:30 | Y3: IV5 Tipo Asoc → 65:40 | Z3: IP Preparación | AA3: IV Vulnerabilidad | AB3: RE Exclusión | AC3: Tipología 2×2 ISCAM | AD3: Banderas Duras | AE3: D12 Huella Carbono | AF3: D13 Reporte Sostenib. | AG3: D14 Economía Circular | AH3: D15 Fitosanitario | AI3: ISA-PV Promedio D12:D15 | AJ3: P_Global Promedio P1:P14 | AK3: ISA-EUDR Geom.D1–D7 + Arit.D8–D9 | AL3: ISA-Completo 0.70×EUDR +0.30×PV
A4: 20118578415 | B4: CENT.DE COOP.AGR. CAF.VALLES SANDIA LTDA | C4: PUNO | D4: 2553623.3 | E4: 0 | F4: =IFERROR(SCORECARDS!H3,"") -> 0 | G4: =IFERROR(MATRIZ_174!U3,0) -> 1 | H4: 0 | I4: =IFERROR(SCORECARDS!I3,"") -> 0 | J4: =IFERROR(SCORECARDS!J3,"") -> 0 | K4: 0 | L4: 0 | M4: 0 | N4: 0 | O4: 0 | P4: =IFERROR(F4,0) -> 0 | Q4: =IFERROR(SQRT(G4*H4),0) -> 0 | R4: =IFERROR((I4+J4+L4)/3,0) -> 0 | S4: =IFERROR((J4+F4)/2,0) -> 0 | T4: =IFERROR((K4+M4+MATRIZ_174!O3)/3,0) -> 0 | U4: =IFERROR(MATRIZ_174!AP3*50,0) -> 6.25 | V4: =IFERROR(IF(E4=0,50,E4),0) -> 50 | W4: =IF(MATRIZ_174!R3>0,65,35) -> 35 | X4: =IF(MATRIZ_174!O3=0,70,30) -> 70 | Y4: =IF(OR(MATRIZ_174!P3="ASOCIACION",MATRIZ_174!P3="PENDIENTE"),65,40) -> 65 | Z4: =IFERROR(ROUND(AVERAGE(P4,Q4,R4,S4,T4),1),0) -> 0 | AA4: =IFERROR(ROUND(AVERAGE(U4,V4,W4,X4,Y4),1),0) -> 45.3 | AB4: =IFERROR(ROUND(AA4*(1-Z4/100),1),0) -> 45.3 | AC4: =IF(AND(Z4>=50,AA4<50),"🟢 Resilientes",IF(AND(Z4>=50,AA4>=50),"🟠 Expuestas Adaptables",IF(AND(Z4<50,AA4<50),"⬜ Riesgo Latente","🔴 Riesgo Crítico"))) -> ⬜ Riesgo Latente | AD4: =IF(G4=0,"🚫 Inh. vigente OSCE","") | AE4: =IFERROR(MATRIZ_174!W3,0) -> 1 | AF4: =IFERROR(MATRIZ_174!X3,0) -> 0 | AG4: =IFERROR(MATRIZ_174!Y3,0) -> 0 | AH4: =IFERROR(MATRIZ_174!Z3,0) -> 0 | AI4: =IFERROR(MATRIZ_174!AP3,"N/A") -> 0.125 | AJ4: =IFERROR(MATRIZ_174!AO3,"N/A") -> 0 | AK4: =IFERROR(ROUND(POWER((E4*F4*G4*H4*I4*J4*K4),1/7)*0.875+((L4+M4)/2)*0.125,1),"N/A") -> 0 | AL4: =IFERROR(IF(AK4="N/A","N/A",ROUND(0.7*AK4+0.3*AI4,1)),"N/A") -> 0
A5: 20129156083 | B5: COOP AGRARIA CAFET VALLE RIO APURIMAC | C5: AYACUCHO | D5: 0 | E5: 0 | F5: =IFERROR(SCORECARDS!H4,"") -> 0 | G5: =IFERROR(MATRIZ_174!U4,0) -> 0 | H5: 0 | I5: =IFERROR(SCORECARDS!I4,"") -> 0 | J5: =IFERROR(SCORECARDS!J4,"") -> 0 | K5: 0 | L5: 0 | M5: 0 | N5: 0 | O5: 0 | P5: =IFERROR(F5,0) -> 0 | Q5: =IFERROR(SQRT(G5*H5),0) -> 0 | R5: =IFERROR((I5+J5+L5)/3,0) -> 0 | S5: =IFERROR((J5+F5)/2,0) -> 0 | T5: =IFERROR((K5+M5+MATRIZ_174!O4)/3,0) -> 0 | U5: =IFERROR(MATRIZ_174!AP4*50,0) -> 0 | V5: =IFERROR(IF(E5=0,50,E5),0) -> 50 | W5: =IF(MATRIZ_174!R4>0,65,35) -> 35 | X5: =IF(MATRIZ_174!O4=0,70,30) -> 70 | Y5: =IF(OR(MATRIZ_174!P4="ASOCIACION",MATRIZ_174!P4="PENDIENTE"),65,40) -> 65 | Z5: =IFERROR(ROUND(AVERAGE(P5,Q5,R5,S5,T5),1),0) -> 0 | AA5: =IFERROR(ROUND(AVERAGE(U5,V5,W5,X5,Y5),1),0) -> 44 | AB5: =IFERROR(ROUND(AA5*(1-Z5/100),1),0) -> 44 | AC5: =IF(AND(Z5>=50,AA5<50),"🟢 Resilientes",IF(AND(Z5>=50,AA5>=50),"🟠 Expuestas Adaptables",IF(AND(Z5<50,AA5<50),"⬜ Riesgo Latente","🔴 Riesgo Crítico"))) -> ⬜ Riesgo Latente | AD5: =IF(G5=0,"🚫 Inh. vigente OSCE","") -> 🚫 Inh. vigente OSCE | AE5: =IFERROR(MATRIZ_174!W4,0) -> 0 | AF5: =IFERROR(MATRIZ_174!X4,0) -> 0 | AG5: =IFERROR(MATRIZ_174!Y4,0) -> 0 | AH5: =IFERROR(MATRIZ_174!Z4,0) -> 0 | AI5: =IFERROR(MATRIZ_174!AP4,"N/A") -> 0 | AJ5: =IFERROR(MATRIZ_174!AO4,"N/A") -> 0 | AK5: =IFERROR(ROUND(POWER((E5*F5*G5*H5*I5*J5*K5),1/7)*0.875+((L5+M5)/2)*0.125,1),"N/A") -> 0 | AL5: =IFERROR(IF(AK5="N/A","N/A",ROUND(0.7*AK5+0.3*AI5,1)),"N/A") -> 0
A6: 20129529530 | B6: COOP AGRARIA CAFETALERA SATIPO LTDA | C6: JUNIN | D6: 4801984.1 | E6: 0 | F6: =IFERROR(SCORECARDS!H5,"") -> 0 | G6: =IFERROR(MATRIZ_174!U5,0) -> 1 | H6: 0 | I6: =IFERROR(SCORECARDS!I5,"") -> 0 | J6: =IFERROR(SCORECARDS!J5,"") -> 0 | K6: 0 | L6: 0 | M6: 0 | N6: 0 | O6: 0 | P6: =IFERROR(F6,0) -> 0 | Q6: =IFERROR(SQRT(G6*H6),0) -> 0 | R6: =IFERROR((I6+J6+L6)/3,0) -> 0 | S6: =IFERROR((J6+F6)/2,0) -> 0 | T6: =IFERROR((K6+M6+MATRIZ_174!O5)/3,0) -> 0 | U6: =IFERROR(MATRIZ_174!AP5*50,0) -> 6.25 | V6: =IFERROR(IF(E6=0,50,E6),0) -> 50 | W6: =IF(MATRIZ_174!R5>0,65,35) -> 35 | X6: =IF(MATRIZ_174!O5=0,70,30) -> 70 | Y6: =IF(OR(MATRIZ_174!P5="ASOCIACION",MATRIZ_174!P5="PENDIENTE"),65,40) -> 65 | Z6: =IFERROR(ROUND(AVERAGE(P6,Q6,R6,S6,T6),1),0) -> 0 | AA6: =IFERROR(ROUND(AVERAGE(U6,V6,W6,X6,Y6),1),0) -> 45.3 | AB6: =IFERROR(ROUND(AA6*(1-Z6/100),1),0) -> 45.3 | AC6: =IF(AND(Z6>=50,AA6<50),"🟢 Resilientes",IF(AND(Z6>=50,AA6>=50),"🟠 Expuestas Adaptables",IF(AND(Z6<50,AA6<50),"⬜ Riesgo Latente","🔴 Riesgo Crítico"))) -> ⬜ Riesgo Latente | AD6: =IF(G6=0,"🚫 Inh. vigente OSCE","") | AE6: =IFERROR(MATRIZ_174!W5,0) -> 1 | AF6: =IFERROR(MATRIZ_174!X5,0) -> 0 | AG6: =IFERROR(MATRIZ_174!Y5,0) -> 0 | AH6: =IFERROR(MATRIZ_174!Z5,0) -> 0 | AI6: =IFERROR(MATRIZ_174!AP5,"N/A") -> 0.125 | AJ6: =IFERROR(MATRIZ_174!AO5,"N/A") -> 0 | AK6: =IFERROR(ROUND(POWER((E6*F6*G6*H6*I6*J6*K6),1/7)*0.875+((L6+M6)/2)*0.125,1),"N/A") -> 0 | AL6: =IFERROR(IF(AK6="N/A","N/A",ROUND(0.7*AK6+0.3*AI6,1)),"N/A") -> 0
A7: 20132489824 | B7: COOPERATIVA AGRARIA CAFETALERA CHANCAMAYO LTDA. N° 008-B-VII | C7: CUSCO | D7: 0 | E7: 0 | F7: =IFERROR(SCORECARDS!H6,"") -> 0 | G7: =IFERROR(MATRIZ_174!U6,0) -> 0 | H7: 0 | I7: =IFERROR(SCORECARDS!I6,"") -> 0 | J7: =IFERROR(SCORECARDS!J6,"") -> 0 | K7: 0 | L7: 0 | M7: 0 | N7: 0 | O7: 0 | P7: =IFERROR(F7,0) -> 0 | Q7: =IFERROR(SQRT(G7*H7),0) -> 0 | R7: =IFERROR((I7+J7+L7)/3,0) -> 0 | S7: =IFERROR((J7+F7)/2,0) -> 0 | T7: =IFERROR((K7+M7+MATRIZ_174!O6)/3,0) -> 0 | U7: =IFERROR(MATRIZ_174!AP6*50,0) -> 6.25 | V7: =IFERROR(IF(E7=0,50,E7),0) -> 50 | W7: =IF(MATRIZ_174!R6>0,65,35) -> 65 | X7: =IF(MATRIZ_174!O6=0,70,30) -> 70 | Y7: =IF(OR(MATRIZ_174!P6="ASOCIACION",MATRIZ_174!P6="PENDIENTE"),65,40) -> 65 | Z7: =IFERROR(ROUND(AVERAGE(P7,Q7,R7,S7,T7),1),0) -> 0 | AA7: =IFERROR(ROUND(AVERAGE(U7,V7,W7,X7,Y7),1),0) -> 51.3 | AB7: =IFERROR(ROUND(AA7*(1-Z7/100),1),0) -> 51.3 | AC7: =IF(AND(Z7>=50,AA7<50),"🟢 Resilientes",IF(AND(Z7>=50,AA7>=50),"🟠 Expuestas Adaptables",IF(AND(Z7<50,AA7<50),"⬜ Riesgo Latente","🔴 Riesgo Crítico"))) -> 🔴 Riesgo Crítico | AD7: =IF(G7=0,"🚫 Inh. vigente OSCE","") -> 🚫 Inh. vigente OSCE | AE7: =IFERROR(MATRIZ_174!W6,0) -> 1 | AF7: =IFERROR(MATRIZ_174!X6,0) -> 0 | AG7: =IFERROR(MATRIZ_174!Y6,0) -> 0 | AH7: =IFERROR(MATRIZ_174!Z6,0) -> 0 | AI7: =IFERROR(MATRIZ_174!AP6,"N/A") -> 0.125 | AJ7: =IFERROR(MATRIZ_174!AO6,"N/A") -> 0 | AK7: =IFERROR(ROUND(POWER((E7*F7*G7*H7*I7*J7*K7),1/7)*0.875+((L7+M7)/2)*0.125,1),"N/A") -> 0 | AL7: =IFERROR(IF(AK7="N/A","N/A",ROUND(0.7*AK7+0.3*AI7,1)),"N/A") -> 0
A8: 20132505455 | B8: COOPERATIVA AGRARIA CAFETALERA AGUILAYOC LTDA. 084 | C8: CUSCO | D8: 0 | E8: 0 | F8: =IFERROR(SCORECARDS!H7,"") -> 0 | G8: =IFERROR(MATRIZ_174!U7,0) -> 0 | H8: 0 | I8: =IFERROR(SCORECARDS!I7,"") -> 0 | J8: =IFERROR(SCORECARDS!J7,"") -> 0 | K8: 0 | L8: 0 | M8: 0 | N8: 0 | O8: 0 | P8: =IFERROR(F8,0) -> 0 | Q8: =IFERROR(SQRT(G8*H8),0) -> 0 | R8: =IFERROR((I8+J8+L8)/3,0) -> 0 | S8: =IFERROR((J8+F8)/2,0) -> 0 | T8: =IFERROR((K8+M8+MATRIZ_174!O7)/3,0) -> 0 | U8: =IFERROR(MATRIZ_174!AP7*50,0) -> 6.25 | V8: =IFERROR(IF(E8=0,50,E8),0) -> 50 | W8: =IF(MATRIZ_174!R7>0,65,35) -> 65 | X8: =IF(MATRIZ_174!O7=0,70,30) -> 70 | Y8: =IF(OR(MATRIZ_174!P7="ASOCIACION",MATRIZ_174!P7="PENDIENTE"),65,40) -> 65 | Z8: =IFERROR(ROUND(AVERAGE(P8,Q8,R8,S8,T8),1),0) -> 0 | AA8: =IFERROR(ROUND(AVERAGE(U8,V8,W8,X8,Y8),1),0) -> 51.3 | AB8: =IFERROR(ROUND(AA8*(1-Z8/100),1),0) -> 51.3 | AC8: =IF(AND(Z8>=50,AA8<50),"🟢 Resilientes",IF(AND(Z8>=50,AA8>=50),"🟠 Expuestas Adaptables",IF(AND(Z8<50,AA8<50),"⬜ Riesgo Latente","🔴 Riesgo Crítico"))) -> 🔴 Riesgo Crítico | AD8: =IF(G8=0,"🚫 Inh. vigente OSCE","") -> 🚫 Inh. vigente OSCE | AE8: =IFERROR(MATRIZ_174!W7,0) -> 1 | AF8: =IFERROR(MATRIZ_174!X7,0) -> 0 | AG8: =IFERROR(MATRIZ_174!Y7,0) -> 0 | AH8: =IFERROR(MATRIZ_174!Z7,0) -> 0 | AI8: =IFERROR(MATRIZ_174!AP7,"N/A") -> 0.125 | AJ8: =IFERROR(MATRIZ_174!AO7,"N/A") -> 0 | AK8: =IFERROR(ROUND(POWER((E8*F8*G8*H8*I8*J8*K8),1/7)*0.875+((L8+M8)/2)*0.125,1),"N/A") -> 0 | AL8: =IFERROR(IF(AK8="N/A","N/A",ROUND(0.7*AK8+0.3*AI8,1)),"N/A") -> 0
A9: 20132509795 | B9: COOPERATIVA AGRARIA CAFETALERA JOSE OLAYA LTDA N° 252 | C9: CUSCO | D9: 1238541.8 | E9: 0 | F9: =IFERROR(SCORECARDS!H8,"") -> 0 | G9: =IFERROR(MATRIZ_174!U8,0) -> 1 | H9: 0 | I9: =IFERROR(SCORECARDS!I8,"") -> 0 | J9: =IFERROR(SCORECARDS!J8,"") -> 0 | K9: 0 | L9: 0 | M9: 0 | N9: 0 | O9: 0 | P9: =IFERROR(F9,0) -> 0 | Q9: =IFERROR(SQRT(G9*H9),0) -> 0 | R9: =IFERROR((I9+J9+L9)/3,0) -> 0 | S9: =IFERROR((J9+F9)/2,0) -> 0 | T9: =IFERROR((K9+M9+MATRIZ_174!O8)/3,0) -> 0 | U9: =IFERROR(MATRIZ_174!AP8*50,0) -> 6.25 | V9: =IFERROR(IF(E9=0,50,E9),0) -> 50 | W9: =IF(MATRIZ_174!R8>0,65,35) -> 35 | X9: =IF(MATRIZ_174!O8=0,70,30) -> 70 | Y9: =IF(OR(MATRIZ_174!P8="ASOCIACION",MATRIZ_174!P8="PENDIENTE"),65,40) -> 65 | Z9: =IFERROR(ROUND(AVERAGE(P9,Q9,R9,S9,T9),1),0) -> 0 | AA9: =IFERROR(ROUND(AVERAGE(U9,V9,W9,X9,Y9),1),0) -> 45.3 | AB9: =IFERROR(ROUND(AA9*(1-Z9/100),1),0) -> 45.3 | AC9: =IF(AND(Z9>=50,AA9<50),"🟢 Resilientes",IF(AND(Z9>=50,AA9>=50),"🟠 Expuestas Adaptables",IF(AND(Z9<50,AA9<50),"⬜ Riesgo Latente","🔴 Riesgo Crítico"))) -> ⬜ Riesgo Latente | AD9: =IF(G9=0,"🚫 Inh. vigente OSCE","") | AE9: =IFERROR(MATRIZ_174!W8,0) -> 1 | AF9: =IFERROR(MATRIZ_174!X8,0) -> 0 | AG9: =IFERROR(MATRIZ_174!Y8,0) -> 0 | AH9: =IFERROR(MATRIZ_174!Z8,0) -> 0 | AI9: =IFERROR(MATRIZ_174!AP8,"N/A") -> 0.125 | AJ9: =IFERROR(MATRIZ_174!AO8,"N/A") -> 0 | AK9: =IFERROR(ROUND(POWER((E9*F9*G9*H9*I9*J9*K9),1/7)*0.875+((L9+M9)/2)*0.125,1),"N/A") -> 0 | AL9: =IFERROR(IF(AK9="N/A","N/A",ROUND(0.7*AK9+0.3*AI9,1)),"N/A") -> 0
A10: 20132509876 | B10: COOPERATIVA AGRARIA CAFETALERA MARANURA LTDA. 129 | C10: CUSCO | D10: 0 | E10: 0 | F10: =IFERROR(SCORECARDS!H9,"") -> 0 | G10: =IFERROR(MATRIZ_174!U9,0) -> 0 | H10: 0 | I10: =IFERROR(SCORECARDS!I9,"") -> 0 | J10: =IFERROR(SCORECARDS!J9,"") -> 0 | K10: 0 | L10: 0 | M10: 0 | N10: 0 | O10: 0 | P10: =IFERROR(F10,0) -> 0 | Q10: =IFERROR(SQRT(G10*H10),0) -> 0 | R10: =IFERROR((I10+J10+L10)/3,0) -> 0 | S10: =IFERROR((J10+F10)/2,0) -> 0 | T10: =IFERROR((K10+M10+MATRIZ_174!O9)/3,0) -> 0 | U10: =IFERROR(MATRIZ_174!AP9*50,0) -> 0 | V10: =IFERROR(IF(E10=0,50,E10),0) -> 50 | W10: =IF(MATRIZ_174!R9>0,65,35) -> 35 | X10: =IF(MATRIZ_174!O9=0,70,30) -> 70 | Y10: =IF(OR(MATRIZ_174!P9="ASOCIACION",MATRIZ_174!P9="PENDIENTE"),65,40) -> 65 | Z10: =IFERROR(ROUND(AVERAGE(P10,Q10,R10,S10,T10),1),0) -> 0 | AA10: =IFERROR(ROUND(AVERAGE(U10,V10,W10,X10,Y10),1),0) -> 44 | AB10: =IFERROR(ROUND(AA10*(1-Z10/100),1),0) -> 44 | AC10: =IF(AND(Z10>=50,AA10<50),"🟢 Resilientes",IF(AND(Z10>=50,AA10>=50),"🟠 Expuestas Adaptables",IF(AND(Z10<50,AA10<50),"⬜ Riesgo Latente","🔴 Riesgo Crítico"))) -> ⬜ Riesgo Latente | AD10: =IF(G10=0,"🚫 Inh. vigente OSCE","") -> 🚫 Inh. vigente OSCE | AE10: =IFERROR(MATRIZ_174!W9,0) -> 0 | AF10: =IFERROR(MATRIZ_174!X9,0) -> 0 | AG10: =IFERROR(MATRIZ_174!Y9,0) -> 0 | AH10: =IFERROR(MATRIZ_174!Z9,0) -> 0 | AI10: =IFERROR(MATRIZ_174!AP9,"N/A") -> 0 | AJ10: =IFERROR(MATRIZ_174!AO9,"N/A") -> 0 | AK10: =IFERROR(ROUND(POWER((E10*F10*G10*H10*I10*J10*K10),1/7)*0.875+((L10+M10)/2)*0.125,1),"N/A") -> 0 | AL10: =IFERROR(IF(AK10="N/A","N/A",ROUND(0.7*AK10+0.3*AI10,1)),"N/A") -> 0
A11: 20132517119 | B11: COOPERATIVA AGRARIA CAFETALERA MATEO PUMACAHUA LTDA N° 185 | C11: CUSCO | D11: 0 | E11: 0 | F11: =IFERROR(SCORECARDS!H10,"") -> 0 | G11: =IFERROR(MATRIZ_174!U10,0) -> 0 | H11: 0 | I11: =IFERROR(SCORECARDS!I10,"") -> 0 | J11: =IFERROR(SCORECARDS!J10,"") -> 0 | K11: 0 | L11: 0 | M11: 0 | N11: 0 | O11: 0 | P11: =IFERROR(F11,0) -> 0 | Q11: =IFERROR(SQRT(G11*H11),0) -> 0 | R11: =IFERROR((I11+J11+L11)/3,0) -> 0 | S11: =IFERROR((J11+F11)/2,0) -> 0 | T11: =IFERROR((K11+M11+MATRIZ_174!O10)/3,0) -> 0 | U11: =IFERROR(MATRIZ_174!AP10*50,0) -> 6.25 | V11: =IFERROR(IF(E11=0,50,E11),0) -> 50 | W11: =IF(MATRIZ_174!R10>0,65,35) -> 65 | X11: =IF(MATRIZ_174!O10=0,70,30) -> 70 | Y11: =IF(OR(MATRIZ_174!P10="ASOCIACION",MATRIZ_174!P10="PENDIENTE"),65,40) -> 65 | Z11: =IFERROR(ROUND(AVERAGE(P11,Q11,R11,S11,T11),1),0) -> 0 | AA11: =IFERROR(ROUND(AVERAGE(U11,V11,W11,X11,Y11),1),0) -> 51.3 | AB11: =IFERROR(ROUND(AA11*(1-Z11/100),1),0) -> 51.3 | AC11: =IF(AND(Z11>=50,AA11<50),"🟢 Resilientes",IF(AND(Z11>=50,AA11>=50),"🟠 Expuestas Adaptables",IF(AND(Z11<50,AA11<50),"⬜ Riesgo Latente","🔴 Riesgo Crítico"))) -> 🔴 Riesgo Crítico | AD11: =IF(G11=0,"🚫 Inh. vigente OSCE","") -> 🚫 Inh. vigente OSCE | AE11: =IFERROR(MATRIZ_174!W10,0) -> 1 | AF11: =IFERROR(MATRIZ_174!X10,0) -> 0 | AG11: =IFERROR(MATRIZ_174!Y10,0) -> 0 | AH11: =IFERROR(MATRIZ_174!Z10,0) -> 0 | AI11: =IFERROR(MATRIZ_174!AP10,"N/A") -> 0.125 | AJ11: =IFERROR(MATRIZ_174!AO10,"N/A") -> 0 | AK11: =IFERROR(ROUND(POWER((E11*F11*G11*H11*I11*J11*K11),1/7)*0.875+((L11+M11)/2)*0.125,1),"N/A") -> 0 | AL11: =IFERROR(IF(AK11="N/A","N/A",ROUND(0.7*AK11+0.3*AI11,1)),"N/A") -> 0
A12: 20136201132 | B12: COOPERATIVA AGRARIA CAFETALERA ALTO URUBAMBA LTDA N° 239 | C12: CUSCO | D12: 0 | E12: 0 | F12: =IFERROR(SCORECARDS!H11,"") -> 0 | G12: =IFERROR(MATRIZ_174!U11,0) -> 0 | H12: 0 | I12: =IFERROR(SCORECARDS!I11,"") -> 0 | J12: =IFERROR(SCORECARDS!J11,"") -> 0 | K12: 0 | L12: 0 | M12: 0 | N12: 0 | O12: 0 | P12: =IFERROR(F12,0) -> 0 | Q12: =IFERROR(SQRT(G12*H12),0) -> 0 | R12: =IFERROR((I12+J12+L12)/3,0) -> 0 | S12: =IFERROR((J12+F12)/2,0) -> 0 | T12: =IFERROR((K12+M12+MATRIZ_174!O11)/3,0) -> 0 | U12: =IFERROR(MATRIZ_174!AP11*50,0) -> 0 | V12: =IFERROR(IF(E12=0,50,E12),0) -> 50 | W12: =IF(MATRIZ_174!R11>0,65,35) -> 35 | X12: =IF(MATRIZ_174!O11=0,70,30) -> 70 | Y12: =IF(OR(MATRIZ_174!P11="ASOCIACION",MATRIZ_174!P11="PENDIENTE"),65,40) -> 65 | Z12: =IFERROR(ROUND(AVERAGE(P12,Q12,R12,S12,T12),1),0) -> 0 | AA12: =IFERROR(ROUND(AVERAGE(U12,V12,W12,X12,Y12),1),0) -> 44 | AB12: =IFERROR(ROUND(AA12*(1-Z12/100),1),0) -> 44 | AC12: =IF(AND(Z12>=50,AA12<50),"🟢 Resilientes",IF(AND(Z12>=50,AA12>=50),"🟠 Expuestas Adaptables",IF(AND(Z12<50,AA12<50),"⬜ Riesgo Latente","🔴 Riesgo Crítico"))) -> ⬜ Riesgo Latente | AD12: =IF(G12=0,"🚫 Inh. vigente OSCE","") -> 🚫 Inh. vigente OSCE | AE12: =IFERROR(MATRIZ_174!W11,0) -> 0 | AF12: =IFERROR(MATRIZ_174!X11,0) -> 0 | AG12: =IFERROR(MATRIZ_174!Y11,0) -> 0 | AH12: =IFERROR(MATRIZ_174!Z11,0) -> 0 | AI12: =IFERROR(MATRIZ_174!AP11,"N/A") -> 0 | AJ12: =IFERROR(MATRIZ_174!AO11,"N/A") -> 0 | AK12: =IFERROR(ROUND(POWER((E12*F12*G12*H12*I12*J12*K12),1/7)*0.875+((L12+M12)/2)*0.125,1),"N/A") -> 0 | AL12: =IFERROR(IF(AK12="N/A","N/A",ROUND(0.7*AK12+0.3*AI12,1)),"N/A") -> 0
A13: 20136201213 | B13: CENTRAL DE COOPERATIVAS AGRARIAS CAFETALERAS COCLA LTDA. N° | C13: CUSCO | D13: 894391.27 | E13: 0 | F13: =IFERROR(SCORECARDS!H12,"") -> 0 | G13: =IFERROR(MATRIZ_174!U12,0) -> 0.75 | H13: 0 | I13: =IFERROR(SCORECARDS!I12,"") -> 0 | J13: =IFERROR(SCORECARDS!J12,"") -> 0 | K13: 0 | L13: 0 | M13: 0 | N13: 0 | O13: 0 | P13: =IFERROR(F13,0) -> 0 | Q13: =IFERROR(SQRT(G13*H13),0) -> 0 | R13: =IFERROR((I13+J13+L13)/3,0) -> 0 | S13: =IFERROR((J13+F13)/2,0) -> 0 | T13: =IFERROR((K13+M13+MATRIZ_174!O12)/3,0) -> 0 | U13: =IFERROR(MATRIZ_174!AP12*50,0) -> 6.25 | V13: =IFERROR(IF(E13=0,50,E13),0) -> 50 | W13: =IF(MATRIZ_174!R12>0,65,35) -> 65 | X13: =IF(MATRIZ_174!O12=0,70,30) -> 70 | Y13: =IF(OR(MATRIZ_174!P12="ASOCIACION",MATRIZ_174!P12="PENDIENTE"),65,40) -> 65 | Z13: =IFERROR(ROUND(AVERAGE(P13,Q13,R13,S13,T13),1),0) -> 0 | AA13: =IFERROR(ROUND(AVERAGE(U13,V13,W13,X13,Y13),1),0) -> 51.3 | AB13: =IFERROR(ROUND(AA13*(1-Z13/100),1),0) -> 51.3 | AC13: =IF(AND(Z13>=50,AA13<50),"🟢 Resilientes",IF(AND(Z13>=50,AA13>=50),"🟠 Expuestas Adaptables",IF(AND(Z13<50,AA13<50),"⬜ Riesgo Latente","🔴 Riesgo Crítico"))) -> 🔴 Riesgo Crítico | AD13: =IF(G13=0,"🚫 Inh. vigente OSCE","") | AE13: =IFERROR(MATRIZ_174!W12,0) -> 1 | AF13: =IFERROR(MATRIZ_174!X12,0) -> 0 | AG13: =IFERROR(MATRIZ_174!Y12,0) -> 0 | AH13: =IFERROR(MATRIZ_174!Z12,0) -> 0 | AI13: =IFERROR(MATRIZ_174!AP12,"N/A") -> 0.125 | AJ13: =IFERROR(MATRIZ_174!AO12,"N/A") -> 0 | AK13: =IFERROR(ROUND(POWER((E13*F13*G13*H13*I13*J13*K13),1/7)*0.875+((L13+M13)/2)*0.125,1),"N/A") -> 0 | AL13: =IFERROR(IF(AK13="N/A","N/A",ROUND(0.7*AK13+0.3*AI13,1)),"N/A") -> 0
A14: 20140292657 | B14: COOPERATIVA AGRARIA CAFETALERA CCOCHAPAMPA LTDA. | C14: CUSCO | D14: 0 | E14: 0 | F14: =IFERROR(SCORECARDS!H13,"") -> 0 | G14: =IFERROR(MATRIZ_174!U13,0) -> 0 | H14: 0 | I14: =IFERROR(SCORECARDS!I13,"") -> 0 | J14: =IFERROR(SCORECARDS!J13,"") -> 0 | K14: 0 | L14: 0 | M14: 0 | N14: 0 | O14: 0 | P14: =IFERROR(F14,0) -> 0 | Q14: =IFERROR(SQRT(G14*H14),0) -> 0 | R14: =IFERROR((I14+J14+L14)/3,0) -> 0 | S14: =IFERROR((J14+F14)/2,0) -> 0 | T14: =IFERROR((K14+M14+MATRIZ_174!O13)/3,0) -> 0 | U14: =IFERROR(MATRIZ_174!AP13*50,0) -> 6.25 | V14: =IFERROR(IF(E14=0,50,E14),0) -> 50 | W14: =IF(MATRIZ_174!R13>0,65,35) -> 65 | X14: =IF(MATRIZ_174!O13=0,70,30) -> 70 | Y14: =IF(OR(MATRIZ_174!P13="ASOCIACION",MATRIZ_174!P13="PENDIENTE"),65,40) -> 65 | Z14: =IFERROR(ROUND(AVERAGE(P14,Q14,R14,S14,T14),1),0) -> 0 | AA14: =IFERROR(ROUND(AVERAGE(U14,V14,W14,X14,Y14),1),0) -> 51.3 | AB14: =IFERROR(ROUND(AA14*(1-Z14/100),1),0) -> 51.3 | AC14: =IF(AND(Z14>=50,AA14<50),"🟢 Resilientes",IF(AND(Z14>=50,AA14>=50),"🟠 Expuestas Adaptables",IF(AND(Z14<50,AA14<50),"⬜ Riesgo Latente","🔴 Riesgo Crítico"))) -> 🔴 Riesgo Crítico | AD14: =IF(G14=0,"🚫 Inh. vigente OSCE","") -> 🚫 Inh. vigente OSCE | AE14: =IFERROR(MATRIZ_174!W13,0) -> 1 | AF14: =IFERROR(MATRIZ_174!X13,0) -> 0 | AG14: =IFERROR(MATRIZ_174!Y13,0) -> 0 | AH14: =IFERROR(MATRIZ_174!Z13,0) -> 0 | AI14: =IFERROR(MATRIZ_174!AP13,"N/A") -> 0.125 | AJ14: =IFERROR(MATRIZ_174!AO13,"N/A") -> 0 | AK14: =IFERROR(ROUND(POWER((E14*F14*G14*H14*I14*J14*K14),1/7)*0.875+((L14+M14)/2)*0.125,1),"N/A") -> 0 | AL14: =IFERROR(IF(AK14="N/A","N/A",ROUND(0.7*AK14+0.3*AI14,1)),"N/A") -> 0
A15: 20143692010 | B15: COOPERATIVA AGRARIA EL QUINACHO LTDA. N° 078 | C15: AYACUCHO | D15: 2015347.3 | E15: 0 | F15: =IFERROR(SCORECARDS!H14,"") -> 0 | G15: =IFERROR(MATRIZ_174!U14,0) -> 1 | H15: 0 | I15: =IFERROR(SCORECARDS!I14,"") -> 0 | J15: =IFERROR(SCORECARDS!J14,"") -> 0 | K15: 0 | L15: 0 | M15: 0 | N15: 0 | O15: 0 | P15: =IFERROR(F15,0) -> 0 | Q15: =IFERROR(SQRT(G15*H15),0) -> 0 | R15: =IFERROR((I15+J15+L15)/3,0) -> 0 | S15: =IFERROR((J15+F15)/2,0) -> 0 | T15: =IFERROR((K15+M15+MATRIZ_174!O14)/3,0) -> 0 | U15: =IFERROR(MATRIZ_174!AP14*50,0) -> 6.25 | V15: =IFERROR(IF(E15=0,50,E15),0) -> 50 | W15: =IF(MATRIZ_174!R14>0,65,35) -> 35 | X15: =IF(MATRIZ_174!O14=0,70,30) -> 70 | Y15: =IF(OR(MATRIZ_174!P14="ASOCIACION",MATRIZ_174!P14="PENDIENTE"),65,40) -> 65 | Z15: =IFERROR(ROUND(AVERAGE(P15,Q15,R15,S15,T15),1),0) -> 0 | AA15: =IFERROR(ROUND(AVERAGE(U15,V15,W15,X15,Y15),1),0) -> 45.3 | AB15: =IFERROR(ROUND(AA15*(1-Z15/100),1),0) -> 45.3 | AC15: =IF(AND(Z15>=50,AA15<50),"🟢 Resilientes",IF(AND(Z15>=50,AA15>=50),"🟠 Expuestas Adaptables",IF(AND(Z15<50,AA15<50),"⬜ Riesgo Latente","🔴 Riesgo Crítico"))) -> ⬜ Riesgo Latente | AD15: =IF(G15=0,"🚫 Inh. vigente OSCE","") | AE15: =IFERROR(MATRIZ_174!W14,0) -> 1 | AF15: =IFERROR(MATRIZ_174!X14,0) -> 0 | AG15: =IFERROR(MATRIZ_174!Y14,0) -> 0 | AH15: =IFERROR(MATRIZ_174!Z14,0) -> 0 | AI15: =IFERROR(MATRIZ_174!AP14,"N/A") -> 0.125 | AJ15: =IFERROR(MATRIZ_174!AO14,"N/A") -> 0 | AK15: =IFERROR(ROUND(POWER((E15*F15*G15*H15*I15*J15*K15),1/7)*0.875+((L15+M15)/2)*0.125,1),"N/A") -> 0 | AL15: =IFERROR(IF(AK15="N/A","N/A",ROUND(0.7*AK15+0.3*AI15,1)),"N/A") -> 0
... A177: 20612331821 | B177: ASOCIACIÓN DE MUJERES LAS FLORES DE LUYA | C177: AMAZONAS | D177: 0 | E177: 0 | F177: =IFERROR(SCORECARDS!H176,"") -> 0 | G177: =IFERROR(MATRIZ_174!U176,0) -> 0 | H177: 0 | I177: =IFERROR(SCORECARDS!I176,"") -> 0 | J177: =IFERROR(SCORECARDS!J176,"") -> 0 | K177: 0 | L177: 0 | M177: 0 | N177: 0 | O177: 0 | P177: =IFERROR(F177,0) -> 0 | Q177: =IFERROR(SQRT(G177*H177),0) -> 0 | R177: =IFERROR((I177+J177+L177)/3,0) -> 0 | S177: =IFERROR((J177+F177)/2,0) -> 0 | T177: =IFERROR((K177+M177+MATRIZ_174!O176)/3,0) -> 0 | U177: =IFERROR(MATRIZ_174!AP176*50,0) -> 0 | V177: =IFERROR(IF(E177=0,50,E177),0) -> 50 | W177: =IF(MATRIZ_174!R176>0,65,35) -> 35 | X177: =IF(MATRIZ_174!O176=0,70,30) -> 70 | Y177: =IF(OR(MATRIZ_174!P176="ASOCIACION",MATRIZ_174!P176="PENDIENTE"),65,40) -> 65 | Z177: =IFERROR(ROUND(AVERAGE(P177,Q177,R177,S177,T177),1),0) -> 0 | AA177: =IFERROR(ROUND(AVERAGE(U177,V177,W177,X177,Y177),1),0) -> 44 | AB177: =IFERROR(ROUND(AA177*(1-Z177/100),1),0) -> 44 | AC177: =IF(AND(Z177>=50,AA177<50),"🟢 Resilientes",IF(AND(Z177>=50,AA177>=50),"🟠 Expuestas Adaptables",IF(AND(Z177<50,AA177<50),"⬜ Riesgo Latente","🔴 Riesgo Crítico"))) -> ⬜ Riesgo Latente | AD177: =IF(G177=0,"🚫 Inh. vigente OSCE","") -> 🚫 Inh. vigente OSCE | AE177: =IFERROR(MATRIZ_174!W176,0) -> 0 | AF177: =IFERROR(MATRIZ_174!X176,0) -> 0 | AG177: =IFERROR(MATRIZ_174!Y176,0) -> 0 | AH177: =IFERROR(MATRIZ_174!Z176,0) -> 0 | AI177: =IFERROR(MATRIZ_174!AP176,"N/A") -> 0 | AJ177: =IFERROR(MATRIZ_174!AO176,"N/A") -> 0 | AK177: =IFERROR(ROUND(POWER((E177*F177*G177*H177*I177*J177*K177),1/7)*0.875+((L177+M177)/2)*0.125,1),"N/A") -> 0 | AL177: =IFERROR(IF(AK177="N/A","N/A",ROUND(0.7*AK177+0.3*AI177,1)),"N/A") -> 0
A178: PROMEDIO MUESTRAL | Z178: =IFERROR(AVERAGE(Z4:Z176),"—") -> 0.0011560694 | AA178: =IFERROR(AVERAGE(AA4:AA176),"—") -> 45.008671 | AB178: =IFERROR(AVERAGE(AB4:AB176),"—") -> 45.008671 | AC178: n = 174 organizaciones | AL178: =IFERROR(AVERAGE(AL4:AL176),"—") -> 0
A180: METODOLOGÍA ISCAM | ISA-EUDR = 0.875×(D1×D2×...×D7)^(1/7) + 0.125×(D8+D9)/2 | ISA-PV = Promedio(D12:D15) | ISA-Completo = 0.70×ISA-EUDR + 0.30×ISA-PV | IP = Promedio(IP1..IP5): IP1=D2, IP2=√(D3×D4), IP3=(D5+D6+D8)/3, IP4=(D6+D2)/2, IP5=(D7+D9+Cert)/3 | IV = Promedio(IV1..IV5): IV1=ISA-PV×50, IV2=D1(base=50), IV3=ha>0?→65:35, IV4=cert=0?→70:30, IV5=tipo Asoc?→65:40 | RE = IV×(1−IP/100) | Corte 2×2: 50 | █ GRIS=pendiente Inst.2 █ AZUL=Datos llenos █ NARANJA=IV █ ROJO=RE █ VERDE=Ambiental █ OSCURO=ISA

Sheet PONDERADORES
A1: BLOQUE DE SUPUESTOS — PONDERACIONES DEL ÍNDICE PVE
A2: LEYENDA DE COLORES
A3: 🔵 Azul | B3: Input hardcoded — valor primario, editable
A4: ⚫ Negro | B4: Fórmula calculada — no editar manualmente
A5: 🟡 Amarillo | B5: Input editable — cambiar ponderación aquí
A6: 🟢 Verde | B6: Resultado positivo (cumple)
A7: 🔴 Rojo | B7: Resultado negativo (no cumple)
A8: ⬜ Gris | B8: Dato pendiente de capturar
A10: PONDERACIONES — MODIFICAR SOLO LAS CELDAS AMARILLAS
A11: Componente | B11: Dimensión EUDR | C11: Variable | D11: Ponderación (%)
A12: EXP_UE | B12: D7 / Exposición UE | C12: % FOB exportado a UE sobre FOB total | D12: 25
A13: TRAZA | B13: D2 / Trazabilidad | C13: ¿Existe vínculo lote → parcela con coords? | D13: 20
A14: DILIG | B14: D5 / Debida diligencia | C14: ¿Existe proceso de evaluación de riesgo? | D14: 15
A15: CAPAC | B15: D6 / Capacidad digital | C15: ¿Tiene personal dedicado a datos? | D15: 10
A16: PRESION | B16: D7 / Presión comprador | C16: ¿Comprador UE exige EUDR? | D16: 15
A17: CERTIF | B17: D8 / Certificaciones | C17: Score de certificaciones vigentes (Org + Ftrade) | D17: 10
A18: PPWR | B18: D14 / Envases | C18: ¿Usa sacos reutilizables o certificados? | D18: 5
A19: TOTAL | D19: =SUM(D12:D18) -> 100
A21: ⚠ El TOTAL debe sumar 100. Si lo ajustas, el Índice PVE en SCORECARDS se recalcula automáticamente.
A23: VERSION ISCAM (2026-10-12) — Pesos mostrados para transparencia (fijos, no editables)
A24: ISA-EUDR e ISA-PV usan pesos FIJOS (87.5%/12.5% y 70%/30%). IP/IV pesan 20% cada sub-dim.
A25: SUBDIM | B25: FÓRMULA | C25: PESO
A26: ISA-EUDR | C26: 100%
A28: ISA-PactoVerde | B28: =PROMEDIO(D12:D15) -> #NAME? | C28: 100%
A30: ISA-Completo | B30: =0.7*ISA-EUDR + 0.3*ISA-PV -> #NAME? | C30: 100%
A32: IP1 | B32: =D2 -> 0 | C32: 20%
A33: IP2 | B33: =√(D3 * D4) -> #NAME? | C33: 20%
A34: IP3 | B34: =(D5 + D6 + D8) / 3 -> 0 | C34: 20%
A35: IP4 | B35: =(D6 + D2) / 2 -> 0 | C35: 20%
A36: IP5 | B36: =(D7 + D9 + Cert) / 3 -> #NAME? | C36: 20%
A37: IP (total) | B37: =PROMEDIO(IP1:IP5) -> #NAME? | C37: 100%
A39: IV1 | C39: 20%
A40: IV2 | C40: 20%
A41: IV3 | C41: 20%
A42: IV4 | C42: 20%
A43: IV5 | C43: 20%
A44: IV (total) | B44: =PROMEDIO(IV1:IV5) -> #NAME? | C44: 100%
A46: RE | C46: —
A47: Cuadrante 2×2 | B47: IP≥50 vs <50 × IV≥50 vs <50 | C47: Corte=50

Sheet MATRIZ_174
A1: MATRIZ 174 — Datos existentes de organizaciones | W1: D12 | X1: D13 | Y1: D14 | Z1: D15 | AA1: P1 | AB1: P2 | AC1: P3 | AD1: P4 | AE1: P5 | AF1: P6 | AG1: P7 | AH1: P8 | AI1: P9 | AJ1: P10 | AK1: P11 | AL1: P12 | AM1: P13 | AN1: P14 | AO1: Bloque P Score (0-1) | AP1: ISA-PactoVerde (0-1)
A2: RUC | B2: Razón Social (SUNAT) | C2: Depto | D2: Producto | E2: FOB Total USD | F2: N° DUAs | G2: Exporta | H2: Cert. Orgánica | I2: Cert. Fairtrade | J2: Estado SUNAT | K2: Avance EUDR | L2: FOB UE USD | M2: % UE/FOB | N2: HS Code principal | O2: Score Cert (0-1) | P2: Tipo org. | Q2: N° aprox. socios | R2: Hectáreas aprox. | S2: PVE Score (0-100) | T2: Clasificación | U2: D3 Score (OSCE) | V2: D3 Observación | W2: D12 — Huella Carbono 0=Sin medición 1=En curso (ha conocidas) 2=Certificado ───────────────────── NOTA: Valor actual = proxy FAO/IPCC (ha × factor IPCC/FAO por cultivo). Reemplazar tras Instrumento 2 Q40-Q44. | X2: Reporte Sostenibilidad (D13) 0=No, 1=En curso, 2=Publicado | Y2: Economía Circular (D14) 0=No, 1=En transición, 2=Avanzado | Z2: Fitosanitario/LMR (D15) 0=No verificado, 1=En monitoreo, 2=Cumple UE | AA2: P1 — Productividad (USD/ha/año) | AB2: P2 — Ingreso neto (USD/ha) | AC2: P3 — % socios con acceso crédito | AD2: P4 — Gender score (% muj. en org.) | AE2: P5 — Formalización laboral (%) | AF2: P6 — Capacitación/año/persona | AG2: P7 — Tasa retención socios (%) | AH2: P8 — Diversificación ingresos (%) | AI2: P9 — Acceso mercados premium (%) | AJ2: P10 — Inversión EUDR (USD/año) | AK2: P11 — Score trazabilidad (%) | AL2: P12 — Quejas resueltas (%) | AM2: P13 — Energía renovable (%) | AN2: P14 — Residuos gestionados (%) | AO2: P_Global — Promedio P1:P14 (0=None, 1=满分) | AP2: ISA-PactoVerde = AVG(D12:D15)/2 0=Nada, 2=Certificado
A3: 20118578415 | B3: CENT.DE COOP.AGR. CAF.VALLES SANDIA LTDA | C3: PUNO | D3: CAFÉ | E3: 5107246.6 | F3: 38 | G3: SI | H3: nan | I3: nan | J3: ACTIVO | K3: nan | L3: 2553623.3 | M3: =IF(E3>0,ROUND(L3/E3*100,1),0) -> 50 | N3: PENDIENTE | O3: =IF(H3="SI",1,0)*0.6+IF(I3="SI",1,0)*0.4 -> 0 | P3: PENDIENTE | S3: =IFERROR(SCORECARDS!C1,"—") -> 0 | T3: =IF(ISTEXT(S3),S3,IF(S3<34,"🔴 Crítico",IF(S3<67,"🟡 Vulnerable","🟢 Preparado"))) -> 🔴 Crítico | U3: 1 | V3: Sin hallazgos OSCE / OEFA | W3: 1 | X3: 0 | Y3: 0 | Z3: 0 | AA3: 0 | AB3: 0 | AC3: 0 | AD3: 0 | AE3: 0 | AF3: 0 | AG3: 0 | AH3: 0 | AI3: 0 | AJ3: 0 | AK3: 0 | AL3: 0 | AM3: 0 | AN3: 0 | AO3: =IFERROR(AVERAGE(AA3,AB3,AC3,AD3,AE3,AF3,AG3,AH3,AI3,AJ3,AK3,AL3,AM3,AN3),"N/A") -> 0 | AP3: =IFERROR(AVERAGE(W3,X3,Y3,Z3)/2,"N/A") -> 0.125
A4: 20129156083 | B4: COOP AGRARIA CAFET VALLE RIO APURIMAC | C4: AYACUCHO | D4: CACAO | E4: 0 | G4: NO | H4: nan | I4: nan | J4: ACTIVO | K4: nan | L4: 0 | M4: =IF(E4>0,ROUND(L4/E4*100,1),0) -> 0 | N4: PENDIENTE | O4: =IF(H4="SI",1,0)*0.6+IF(I4="SI",1,0)*0.4 -> 0 | P4: PENDIENTE | S4: =IFERROR(SCORECARDS!C2,"—") -> ISA-Completo (0-100) | T4: =IF(ISTEXT(S4),S4,IF(S4<34,"🔴 Crítico",IF(S4<67,"🟡 Vulnerable","🟢 Preparado"))) -> ISA-Completo (0-100) | W4: 0 | X4: 0 | Y4: 0 | Z4: 0 | AA4: 0 | AB4: 0 | AC4: 0 | AD4: 0 | AE4: 0 | AF4: 0 | AG4: 0 | AH4: 0 | AI4: 0 | AJ4: 0 | AK4: 0 | AL4: 0 | AM4: 0 | AN4: 0 | AO4: =IFERROR(AVERAGE(AA4,AB4,AC4,AD4,AE4,AF4,AG4,AH4,AI4,AJ4,AK4,AL4,AM4,AN4),"N/A") -> 0 | AP4: =IFERROR(AVERAGE(W4,X4,Y4,Z4)/2,"N/A") -> 0
A5: 20129529530 | B5: COOP AGRARIA CAFETALERA SATIPO LTDA | C5: JUNIN | D5: nan | E5: 9603968.1 | F5: 41 | G5: SI | H5: nan | I5: nan | J5: ACTIVO | K5: nan | L5: 4801984.1 | M5: =IF(E5>0,ROUND(L5/E5*100,1),0) -> 50 | N5: PENDIENTE | O5: =IF(H5="SI",1,0)*0.6+IF(I5="SI",1,0)*0.4 -> 0 | P5: PENDIENTE | S5: =IFERROR(SCORECARDS!C3,"—") -> 0 | T5: =IF(ISTEXT(S5),S5,IF(S5<34,"🔴 Crítico",IF(S5<67,"🟡 Vulnerable","🟢 Preparado"))) -> 🔴 Crítico | U5: 1 | V5: Sin hallazgos OSCE / OEFA | W5: 1 | X5: 0 | Y5: 0 | Z5: 0 | AA5: 0 | AB5: 0 | AC5: 0 | AD5: 0 | AE5: 0 | AF5: 0 | AG5: 0 | AH5: 0 | AI5: 0 | AJ5: 0 | AK5: 0 | AL5: 0 | AM5: 0 | AN5: 0 | AO5: =IFERROR(AVERAGE(AA5,AB5,AC5,AD5,AE5,AF5,AG5,AH5,AI5,AJ5,AK5,AL5,AM5,AN5),"N/A") -> 0 | AP5: =IFERROR(AVERAGE(W5,X5,Y5,Z5)/2,"N/A") -> 0.125
A6: 20132489824 | B6: COOPERATIVA AGRARIA CAFETALERA CHANCAMAYO LTDA. N° 008-B-VII | C6: CUSCO | D6: nan | G6: NO | H6: Cer | I6: Vig | J6: ACTIVO | K6: nan | L6: 0 | M6: =IF(E6>0,ROUND(L6/E6*100,1),0) -> 0 | N6: PENDIENTE | O6: =IF(H6="SI",1,0)*0.6+IF(I6="SI",1,0)*0.4 -> 0 | P6: PENDIENTE | Q6: 44 | R6: 44 | S6: =IFERROR(SCORECARDS!C4,"—") -> 0 | T6: =IF(ISTEXT(S6),S6,IF(S6<34,"🔴 Crítico",IF(S6<67,"🟡 Vulnerable","🟢 Preparado"))) -> 🔴 Crítico | W6: 1 | X6: 0 | Y6: 0 | Z6: 0 | AA6: 0 | AB6: 0 | AC6: 0 | AD6: 0 | AE6: 0 | AF6: 0 | AG6: 0 | AH6: 0 | AI6: 0 | AJ6: 0 | AK6: 0 | AL6: 0 | AM6: 0 | AN6: 0 | AO6: =IFERROR(AVERAGE(AA6,AB6,AC6,AD6,AE6,AF6,AG6,AH6,AI6,AJ6,AK6,AL6,AM6,AN6),"N/A") -> 0 | AP6: =IFERROR(AVERAGE(W6,X6,Y6,Z6)/2,"N/A") -> 0.125
A7: 20132505455 | B7: COOPERATIVA AGRARIA CAFETALERA AGUILAYOC LTDA. 084 | C7: CUSCO | D7: CAFÉ | G7: NO | H7: Cer | I7: nan | J7: ACTIVO | K7: 0.75 | L7: 0 | M7: =IF(E7>0,ROUND(L7/E7*100,1),0) -> 0 | N7: PENDIENTE | O7: =IF(H7="SI",1,0)*0.6+IF(I7="SI",1,0)*0.4 -> 0 | P7: PENDIENTE | Q7: 100 | R7: 218 | S7: =IFERROR(SCORECARDS!C5,"—") -> 0 | T7: =IF(ISTEXT(S7),S7,IF(S7<34,"🔴 Crítico",IF(S7<67,"🟡 Vulnerable","🟢 Preparado"))) -> 🔴 Crítico | W7: 1 | X7: 0 | Y7: 0 | Z7: 0 | AA7: 0 | AB7: 0 | AC7: 0 | AD7: 0 | AE7: 0 | AF7: 0 | AG7: 0 | AH7: 0 | AI7: 0 | AJ7: 0 | AK7: 0 | AL7: 0 | AM7: 0 | AN7: 0 | AO7: =IFERROR(AVERAGE(AA7,AB7,AC7,AD7,AE7,AF7,AG7,AH7,AI7,AJ7,AK7,AL7,AM7,AN7),"N/A") -> 0 | AP7: =IFERROR(AVERAGE(W7,X7,Y7,Z7)/2,"N/A") -> 0.125
A8: 20132509795 | B8: COOPERATIVA AGRARIA CAFETALERA JOSE OLAYA LTDA N° 252 | C8: CUSCO | D8: CAFÉ | E8: 2477083.5 | F8: 14 | G8: SI | H8: nan | I8: nan | J8: ACTIVO | K8: nan | L8: 1238541.8 | M8: =IF(E8>0,ROUND(L8/E8*100,1),0) -> 50 | N8: PENDIENTE | O8: =IF(H8="SI",1,0)*0.6+IF(I8="SI",1,0)*0.4 -> 0 | P8: PENDIENTE | S8: =IFERROR(SCORECARDS!C6,"—") -> 0 | T8: =IF(ISTEXT(S8),S8,IF(S8<34,"🔴 Crítico",IF(S8<67,"🟡 Vulnerable","🟢 Preparado"))) -> 🔴 Crítico | U8: 1 | V8: Sin hallazgos OSCE / OEFA | W8: 1 | X8: 0 | Y8: 0 | Z8: 0 | AA8: 0 | AB8: 0 | AC8: 0 | AD8: 0 | AE8: 0 | AF8: 0 | AG8: 0 | AH8: 0 | AI8: 0 | AJ8: 0 | AK8: 0 | AL8: 0 | AM8: 0 | AN8: 0 | AO8: =IFERROR(AVERAGE(AA8,AB8,AC8,AD8,AE8,AF8,AG8,AH8,AI8,AJ8,AK8,AL8,AM8,AN8),"N/A") -> 0 | AP8: =IFERROR(AVERAGE(W8,X8,Y8,Z8)/2,"N/A") -> 0.125
A9: 20132509876 | B9: COOPERATIVA AGRARIA CAFETALERA MARANURA LTDA. 129 | C9: CUSCO | D9: CAFÉ | E9: 1689820.3 | F9: 5 | G9: SI | H9: nan | I9: nan | J9: ACTIVO | K9: nan | L9: 0 | M9: =IF(E9>0,ROUND(L9/E9*100,1),0) -> 0 | N9: PENDIENTE | O9: =IF(H9="SI",1,0)*0.6+IF(I9="SI",1,0)*0.4 -> 0 | P9: PENDIENTE | S9: =IFERROR(SCORECARDS!C7,"—") -> 0 | T9: =IF(ISTEXT(S9),S9,IF(S9<34,"🔴 Crítico",IF(S9<67,"🟡 Vulnerable","🟢 Preparado"))) -> 🔴 Crítico | W9: 0 | X9: 0 | Y9: 0 | Z9: 0 | AA9: 0 | AB9: 0 | AC9: 0 | AD9: 0 | AE9: 0 | AF9: 0 | AG9: 0 | AH9: 0 | AI9: 0 | AJ9: 0 | AK9: 0 | AL9: 0 | AM9: 0 | AN9: 0 | AO9: =IFERROR(AVERAGE(AA9,AB9,AC9,AD9,AE9,AF9,AG9,AH9,AI9,AJ9,AK9,AL9,AM9,AN9),"N/A") -> 0 | AP9: =IFERROR(AVERAGE(W9,X9,Y9,Z9)/2,"N/A") -> 0
A10: 20132517119 | B10: COOPERATIVA AGRARIA CAFETALERA MATEO PUMACAHUA LTDA N° 185 | C10: CUSCO | D10: CAFÉ | E10: 0 | G10: NO | H10: Cer | I10: Fai | J10: ACTIVO | K10: 0.75 | L10: 0 | M10: =IF(E10>0,ROUND(L10/E10*100,1),0) -> 0 | N10: PENDIENTE | O10: =IF(H10="SI",1,0)*0.6+IF(I10="SI",1,0)*0.4 -> 0 | P10: PENDIENTE | Q10: 177 | R10: 469 | S10: =IFERROR(SCORECARDS!C8,"—") -> 0 | T10: =IF(ISTEXT(S10),S10,IF(S10<34,"🔴 Crítico",IF(S10<67,"🟡 Vulnerable","🟢 Preparado"))) -> 🔴 Crítico | W10: 1 | X10: 0 | Y10: 0 | Z10: 0 | AA10: 0 | AB10: 0 | AC10: 0 | AD10: 0 | AE10: 0 | AF10: 0 | AG10: 0 | AH10: 0 | AI10: 0 | AJ10: 0 | AK10: 0 | AL10: 0 | AM10: 0 | AN10: 0 | AO10: =IFERROR(AVERAGE(AA10,AB10,AC10,AD10,AE10,AF10,AG10,AH10,AI10,AJ10,AK10,AL10,AM10,AN10),"N/A") -> 0 | AP10: =IFERROR(AVERAGE(W10,X10,Y10,Z10)/2,"N/A") -> 0.125
A11: 20136201132 | B11: COOPERATIVA AGRARIA CAFETALERA ALTO URUBAMBA LTDA N° 239 | C11: CUSCO | D11: CAFÉ | E11: 681394.36 | F11: 6 | G11: SI | H11: nan | I11: nan | J11: ACTIVO | K11: nan | L11: 0 | M11: =IF(E11>0,ROUND(L11/E11*100,1),0) -> 0 | N11: PENDIENTE | O11: =IF(H11="SI",1,0)*0.6+IF(I11="SI",1,0)*0.4 -> 0 | P11: PENDIENTE | S11: =IFERROR(SCORECARDS!C9,"—") -> 0 | T11: =IF(ISTEXT(S11),S11,IF(S11<34,"🔴 Crítico",IF(S11<67,"🟡 Vulnerable","🟢 Preparado"))) -> 🔴 Crítico | W11: 0 | X11: 0 | Y11: 0 | Z11: 0 | AA11: 0 | AB11: 0 | AC11: 0 | AD11: 0 | AE11: 0 | AF11: 0 | AG11: 0 | AH11: 0 | AI11: 0 | AJ11: 0 | AK11: 0 | AL11: 0 | AM11: 0 | AN11: 0 | AO11: =IFERROR(AVERAGE(AA11,AB11,AC11,AD11,AE11,AF11,AG11,AH11,AI11,AJ11,AK11,AL11,AM11,AN11),"N/A") -> 0 | AP11: =IFERROR(AVERAGE(W11,X11,Y11,Z11)/2,"N/A") -> 0
A12: 20136201213 | B12: CENTRAL DE COOPERATIVAS AGRARIAS CAFETALERAS COCLA LTDA. N° | C12: CUSCO | D12: CAFÉ | E12: 4445611.6 | F12: 33 | G12: SI | H12: Cer | I12: Fai | J12: ACTIVO | K12: 0.75 | L12: 894391.27 | M12: =IF(E12>0,ROUND(L12/E12*100,1),0) -> 20.1 | N12: PENDIENTE | O12: =IF(H12="SI",1,0)*0.6+IF(I12="SI",1,0)*0.4 -> 0 | P12: PENDIENTE | Q12: 660 | R12: 1670 | S12: =IFERROR(SCORECARDS!C10,"—") -> 0 | T12: =IF(ISTEXT(S12),S12,IF(S12<34,"🔴 Crítico",IF(S12<67,"🟡 Vulnerable","🟢 Preparado"))) -> 🔴 Crítico | U12: 0.75 | V12: ⚠ 1 infracc. ambiental (OEFA) | W12: 1 | X12: 0 | Y12: 0 | Z12: 0 | AA12: 0 | AB12: 0 | AC12: 0 | AD12: 0 | AE12: 0 | AF12: 0 | AG12: 0 | AH12: 0 | AI12: 0 | AJ12: 0 | AK12: 0 | AL12: 0 | AM12: 0 | AN12: 0 | AO12: =IFERROR(AVERAGE(AA12,AB12,AC12,AD12,AE12,AF12,AG12,AH12,AI12,AJ12,AK12,AL12,AM12,AN12),"N/A") -> 0 | AP12: =IFERROR(AVERAGE(W12,X12,Y12,Z12)/2,"N/A") -> 0.125
A13: 20140292657 | B13: COOPERATIVA AGRARIA CAFETALERA CCOCHAPAMPA LTDA. | C13: CUSCO | D13: CAFÉ | E13: 0 | G13: NO | H13: Cer | I13: Fa | J13: ACTIVO | K13: 0.75 | L13: 0 | M13: =IF(E13>0,ROUND(L13/E13*100,1),0) -> 0 | N13: PENDIENTE | O13: =IF(H13="SI",1,0)*0.6+IF(I13="SI",1,0)*0.4 -> 0 | P13: PENDIENTE | Q13: 49 | R13: 136.9 | S13: =IFERROR(SCORECARDS!C11,"—") -> 0 | T13: =IF(ISTEXT(S13),S13,IF(S13<34,"🔴 Crítico",IF(S13<67,"🟡 Vulnerable","🟢 Preparado"))) -> 🔴 Crítico | W13: 1 | X13: 0 | Y13: 0 | Z13: 0 | AA13: 0 | AB13: 0 | AC13: 0 | AD13: 0 | AE13: 0 | AF13: 0 | AG13: 0 | AH13: 0 | AI13: 0 | AJ13: 0 | AK13: 0 | AL13: 0 | AM13: 0 | AN13: 0 | AO13: =IFERROR(AVERAGE(AA13,AB13,AC13,AD13,AE13,AF13,AG13,AH13,AI13,AJ13,AK13,AL13,AM13,AN13),"N/A") -> 0 | AP13: =IFERROR(AVERAGE(W13,X13,Y13,Z13)/2,"N/A") -> 0.125
A14: 20143692010 | B14: COOPERATIVA AGRARIA EL QUINACHO LTDA. N° 078 | C14: AYACUCHO | D14: CACAO | E14: 4030694.7 | F14: 14 | G14: SI | H14: nan | I14: nan | J14: ACTIVO | K14: nan | L14: 2015347.3 | M14: =IF(E14>0,ROUND(L14/E14*100,1),0) -> 50 | N14: PENDIENTE | O14: =IF(H14="SI",1,0)*0.6+IF(I14="SI",1,0)*0.4 -> 0 | P14: PENDIENTE | S14: =IFERROR(SCORECARDS!C12,"—") -> 0 | T14: =IF(ISTEXT(S14),S14,IF(S14<34,"🔴 Crítico",IF(S14<67,"🟡 Vulnerable","🟢 Preparado"))) -> 🔴 Crítico | U14: 1 | V14: Sin hallazgos OSCE / OEFA | W14: 1 | X14: 0 | Y14: 0 | Z14: 0 | AA14: 0 | AB14: 0 | AC14: 0 | AD14: 0 | AE14: 0 | AF14: 0 | AG14: 0 | AH14: 0 | AI14: 0 | AJ14: 0 | AK14: 0 | AL14: 0 | AM14: 0 | AN14: 0 | AO14: =IFERROR(AVERAGE(AA14,AB14,AC14,AD14,AE14,AF14,AG14,AH14,AI14,AJ14,AK14,AL14,AM14,AN14),"N/A") -> 0 | AP14: =IFERROR(AVERAGE(W14,X14,Y14,Z14)/2,"N/A") -> 0.125
A15: 20145484597 | B15: COOPERATIVA AGRARIA CAFETALERA SAN IGNACIO LTDA. | C15: PUNO | D15: CAFÉ | G15: NO | H15: nan | I15: nan | J15: ACTIVO | K15: nan | L15: 0 | M15: =IF(E15>0,ROUND(L15/E15*100,1),0) -> 0 | N15: PENDIENTE | O15: =IF(H15="SI",1,0)*0.6+IF(I15="SI",1,0)*0.4 -> 0 | P15: PENDIENTE | S15: =IFERROR(SCORECARDS!C13,"—") -> 0 | T15: =IF(ISTEXT(S15),S15,IF(S15<34,"🔴 Crítico",IF(S15<67,"🟡 Vulnerable","🟢 Preparado"))) -> 🔴 Crítico | W15: 0 | X15: 0 | Y15: 0 | Z15: 0 | AA15: 0 | AB15: 0 | AC15: 0 | AD15: 0 | AE15: 0 | AF15: 0 | AG15: 0 | AH15: 0 | AI15: 0 | AJ15: 0 | AK15: 0 | AL15: 0 | AM15: 0 | AN15: 0 | AO15: =IFERROR(AVERAGE(AA15,AB15,AC15,AD15,AE15,AF15,AG15,AH15,AI15,AJ15,AK15,AL15,AM15,AN15),"N/A") -> 0 | AP15: =IFERROR(AVERAGE(W15,X15,Y15,Z15)/2,"N/A") -> 0
A16: 20146696041 | B16: COOP AGRARIA CAFET JOSE GABRIEL CONDORCA | C16: PIURA | D16: CAFÉ | G16: NO | H16: nan | I16: nan | J16: ACTIVO | K16: nan | L16: 0 | M16: =IF(E16>0,ROUND(L16/E16*100,1),0) -> 0 | N16: PENDIENTE | O16: =IF(H16="SI",1,0)*0.6+IF(I16="SI",1,0)*0.4 -> 0 | P16: PENDIENTE | S16: =IFERROR(SCORECARDS!C14,"—") -> 0 | T16: =IF(ISTEXT(S16),S16,IF(S16<34,"🔴 Crítico",IF(S16<67,"🟡 Vulnerable","🟢 Preparado"))) -> 🔴 Crítico | W16: 0 | X16: 0 | Y16: 0 | Z16: 0 | AA16: 0 | AB16: 0 | AC16: 0 | AD16: 0 | AE16: 0 | AF16: 0 | AG16: 0 | AH16: 0 | AI16: 0 | AJ16: 0 | AK16: 0 | AL16: 0 | AM16: 0 | AN16: 0 | AO16: =IFERROR(AVERAGE(AA16,AB16,AC16,AD16,AE16,AF16,AG16,AH16,AI16,AJ16,AK16,AL16,AM16,AN16),"N/A") -> 0 | AP16: =IFERROR(AVERAGE(W16,X16,Y16,Z16)/2,"N/A") -> 0
A17: 20147443120 | B17: COOPERATIVA AGRARIA CAFETALERA TIRIJUAY PAVAYOC LTDA 013-B-V | C17: CUSCO | D17: nan | G17: NO | H17: Cer | I17: Vig | J17: SUSPENSION TEMPORAL | K17: nan | L17: 0 | M17: =IF(E17>0,ROUND(L17/E17*100,1),0) -> 0 | N17: PENDIENTE | O17: =IF(H17="SI",1,0)*0.6+IF(I17="SI",1,0)*0.4 -> 0 | P17: PENDIENTE | Q17: 74 | R17: 150 | S17: =IFERROR(SCORECARDS!C15,"—") -> 0 | T17: =IF(ISTEXT(S17),S17,IF(S17<34,"🔴 Crítico",IF(S17<67,"🟡 Vulnerable","🟢 Preparado"))) -> 🔴 Crítico | W17: 1 | X17: 0 | Y17: 0 | Z17: 0 | AA17: 0 | AB17: 0 | AC17: 0 | AD17: 0 | AE17: 0 | AF17: 0 | AG17: 0 | AH17: 0 | AI17: 0 | AJ17: 0 | AK17: 0 | AL17: 0 | AM17: 0 | AN17: 0 | AO17: =IFERROR(AVERAGE(AA17,AB17,AC17,AD17,AE17,AF17,AG17,AH17,AI17,AJ17,AK17,AL17,AM17,AN17),"N/A") -> 0 | AP17: =IFERROR(AVERAGE(W17,X17,Y17,Z17)/2,"N/A") -> 0.125
A18: 20166786861 | B18: COMITE CENTRAL DE PRODUCTORES AGROPECUARIOS DE SAN ALEJANDRO | C18: UCAYALI | D18: CACAO | G18: NO | H18: nan | I18: nan | J18: ACTIVO | K18: nan | L18: 0 | M18: =IF(E18>0,ROUND(L18/E18*100,1),0) -> 0 | N18: PENDIENTE | O18: =IF(H18="SI",1,0)*0.6+IF(I18="SI",1,0)*0.4 -> 0 | P18: PENDIENTE | S18: =IFERROR(SCORECARDS!C16,"—") -> 0 | T18: =IF(ISTEXT(S18),S18,IF(S18<34,"🔴 Crítico",IF(S18<67,"🟡 Vulnerable","🟢 Preparado"))) -> 🔴 Crítico | W18: 0 | X18: 0 | Y18: 0 | Z18: 0 | AA18: 0 | AB18: 0 | AC18: 0 | AD18: 0 | AE18: 0 | AF18: 0 | AG18: 0 | AH18: 0 | AI18: 0 | AJ18: 0 | AK18: 0 | AL18: 0 | AM18: 0 | AN18: 0 | AO18: =IFERROR(AVERAGE(AA18,AB18,AC18,AD18,AE18,AF18,AG18,AH18,AI18,AJ18,AK18,AL18,AM18,AN18),"N/A") -> 0 | AP18: =IFERROR(AVERAGE(W18,X18,Y18,Z18)/2,"N/A") -> 0
A19: 20170142773 | B19: COOPERATIVA AGRARIA CAFETALERA BAGUA GRANDE LIMITADA | C19: AMAZONAS | D19: CAFÉ | E19: 9070756.9 | F19: 41 | G19: SI | H19: nan | I19: nan | J19: ACTIVO | K19: nan | L19: 4535378.4 | M19: =IF(E19>0,ROUND(L19/E19*100,1),0) -> 50 | N19: PENDIENTE | O19: =IF(H19="SI",1,0)*0.6+IF(I19="SI",1,0)*0.4 -> 0 | P19: PENDIENTE | S19: =IFERROR(SCORECARDS!C17,"—") -> 0 | T19: =IF(ISTEXT(S19),S19,IF(S19<34,"🔴 Crítico",IF(S19<67,"🟡 Vulnerable","🟢 Preparado"))) -> 🔴 Crítico | U19: 1 | V19: Sin hallazgos OSCE / OEFA | W19: 1 | X19: 0 | Y19: 0 | Z19: 0 | AA19: 0 | AB19: 0 | AC19: 0 | AD19: 0 | AE19: 0 | AF19: 0 | AG19: 0 | AH19: 0 | AI19: 0 | AJ19: 0 | AK19: 0 | AL19: 0 | AM19: 0 | AN19: 0 | AO19: =IFERROR(AVERAGE(AA19,AB19,AC19,AD19,AE19,AF19,AG19,AH19,AI19,AJ19,AK19,AL19,AM19,AN19),"N/A") -> 0 | AP19: =IFERROR(AVERAGE(W19,X19,Y19,Z19)/2,"N/A") -> 0.125
A20: 20200880448 | B20: COOPERATIVA AGRARIA CAFETALERA JORGE CHAVEZ LTDA | C20: CUSCO | D20: nan | G20: NO | H20: Cer | I20: Vig | J20: ACTIVO | K20: nan | L20: 0 | M20: =IF(E20>0,ROUND(L20/E20*100,1),0) -> 0 | N20: PENDIENTE | O20: =IF(H20="SI",1,0)*0.6+IF(I20="SI",1,0)*0.4 -> 0 | P20: PENDIENTE | Q20: 36 | R20: 38 | S20: =IFERROR(SCORECARDS!C18,"—") -> 0 | T20: =IF(ISTEXT(S20),S20,IF(S20<34,"🔴 Crítico",IF(S20<67,"🟡 Vulnerable","🟢 Preparado"))) -> 🔴 Crítico | W20: 1 | X20: 0 | Y20: 0 | Z20: 0 | AA20: 0 | AB20: 0 | AC20: 0 | AD20: 0 | AE20: 0 | AF20: 0 | AG20: 0 | AH20: 0 | AI20: 0 | AJ20: 0 | AK20: 0 | AL20: 0 | AM20: 0 | AN20: 0 | AO20: =IFERROR(AVERAGE(AA20,AB20,AC20,AD20,AE20,AF20,AG20,AH20,AI20,AJ20,AK20,AL20,AM20,AN20),"N/A") -> 0 | AP20: =IFERROR(AVERAGE(W20,X20,Y20,Z20)/2,"N/A") -> 0.125
A21: 20352417018 | B21: COOPERATIVA AGRARIA DE CACAOTEROS TECNIFICADOS DE PADRE ABAD | C21: UCAYALI | D21: CACAO | E21: 0 | G21: NO | H21: nan | I21: nan | J21: SUSPENSION TEMPORAL | K21: nan | L21: 0 | M21: =IF(E21>0,ROUND(L21/E21*100,1),0) -> 0 | N21: PENDIENTE | O21: =IF(H21="SI",1,0)*0.6+IF(I21="SI",1,0)*0.4 -> 0 | P21: PENDIENTE | S21: =IFERROR(SCORECARDS!C19,"—") -> 0 | T21: =IF(ISTEXT(S21),S21,IF(S21<34,"🔴 Crítico",IF(S21<67,"🟡 Vulnerable","🟢 Preparado"))) -> 🔴 Crítico | W21: 0 | X21: 0 | Y21: 0 | Z21: 0 | AA21: 0 | AB21: 0 | AC21: 0 | AD21: 0 | AE21: 0 | AF21: 0 | AG21: 0 | AH21: 0 | AI21: 0 | AJ21: 0 | AK21: 0 | AL21: 0 | AM21: 0 | AN21: 0 | AO21: =IFERROR(AVERAGE(AA21,AB21,AC21,AD21,AE21,AF21,AG21,AH21,AI21,AJ21,AK21,AL21,AM21,AN21),"N/A") -> 0 | AP21: =IFERROR(AVERAGE(W21,X21,Y21,Z21)/2,"N/A") -> 0
A22: 20352423921 | B22: COOPERATIVA AGRARIA CAFETALERA DIVISORIA LTDA | C22: HUANUCO | D22: CAFÉ | E22: 0 | G22: NO | H22: nan | I22: nan | J22: ACTIVO | K22: nan | L22: 0 | M22: =IF(E22>0,ROUND(L22/E22*100,1),0) -> 0 | N22: PENDIENTE | O22: =IF(H22="SI",1,0)*0.6+IF(I22="SI",1,0)*0.4 -> 0 | P22: PENDIENTE | S22: =IFERROR(SCORECARDS!C20,"—") -> 0 | T22: =IF(ISTEXT(S22),S22,IF(S22<34,"🔴 Crítico",IF(S22<67,"🟡 Vulnerable","🟢 Preparado"))) -> 🔴 Crítico | W22: 0 | X22: 0 | Y22: 0 | Z22: 0 | AA22: 0 | AB22: 0 | AC22: 0 | AD22: 0 | AE22: 0 | AF22: 0 | AG22: 0 | AH22: 0 | AI22: 0 | AJ22: 0 | AK22: 0 | AL22: 0 | AM22: 0 | AN22: 0 | AO22: =IFERROR(AVERAGE(AA22,AB22,AC22,AD22,AE22,AF22,AG22,AH22,AI22,AJ22,AK22,AL22,AM22,AN22),"N/A") -> 0 | AP22: =IFERROR(AVERAGE(W22,X22,Y22,Z22)/2,"N/A") -> 0
A23: 20393152207 | B23: COOPERATIVA AGRO INDUSTRIAL APCTVASH | C23: UCAYALI | D23: CACAO | G23: NO | H23: nan | I23: nan | J23: ACTIVO | K23: nan | L23: 0 | M23: =IF(E23>0,ROUND(L23/E23*100,1),0) -> 0 | N23: PENDIENTE | O23: =IF(H23="SI",1,0)*0.6+IF(I23="SI",1,0)*0.4 -> 0 | P23: PENDIENTE | S23: =IFERROR(SCORECARDS!C21,"—") -> 0 | T23: =IF(ISTEXT(S23),S23,IF(S23<34,"🔴 Crítico",IF(S23<67,"🟡 Vulnerable","🟢 Preparado"))) -> 🔴 Crítico | W23: 0 | X23: 0 | Y23: 0 | Z23: 0 | AA23: 0 | AB23: 0 | AC23: 0 | AD23: 0 | AE23: 0 | AF23: 0 | AG23: 0 | AH23: 0 | AI23: 0 | AJ23: 0 | AK23: 0 | AL23: 0 | AM23: 0 | AN23: 0 | AO23: =IFERROR(AVERAGE(AA23,AB23,AC23,AD23,AE23,AF23,AG23,AH23,AI23,AJ23,AK23,AL23,AM23,AN23),"N/A") -> 0 | AP23: =IFERROR(AVERAGE(W23,X23,Y23,Z23)/2,"N/A") -> 0
A24: 20393593670 | B24: COMITE CENTRAL CON DESARROLLO AL FUTURO DE CURIMANA | C24: UCAYALI | D24: CACAO | E24: 0 | G24: NO | H24: nan | I24: nan | J24: BAJA DE OFICIO | K24: nan | L24: 0 | M24: =IF(E24>0,ROUND(L24/E24*100,1),0) -> 0 | N24: PENDIENTE | O24: =IF(H24="SI",1,0)*0.6+IF(I24="SI",1,0)*0.4 -> 0 | P24: PENDIENTE | S24: =IFERROR(SCORECARDS!C22,"—") -> 0 | T24: =IF(ISTEXT(S24),S24,IF(S24<34,"🔴 Crítico",IF(S24<67,"🟡 Vulnerable","🟢 Preparado"))) -> 🔴 Crítico | W24: 0 | X24: 0 | Y24: 0 | Z24: 0 | AA24: 0 | AB24: 0 | AC24: 0 | AD24: 0 | AE24: 0 | AF24: 0 | AG24: 0 | AH24: 0 | AI24: 0 | AJ24: 0 | AK24: 0 | AL24: 0 | AM24: 0 | AN24: 0 | AO24: =IFERROR(AVERAGE(AA24,AB24,AC24,AD24,AE24,AF24,AG24,AH24,AI24,AJ24,AK24,AL24,AM24,AN24),"N/A") -> 0 | AP24: =IFERROR(AVERAGE(W24,X24,Y24,Z24)/2,"N/A") -> 0
A25: 20393692228 | B25: COOPERATIVA AGRARIA CACAOTERA SAN ALEJANDRO LTDA | C25: UCAYALI | D25: CACAO | E25: 0 | G25: NO | H25: nan | I25: nan | J25: ACTIVO | K25: nan | L25: 0 | M25: =IF(E25>0,ROUND(L25/E25*100,1),0) -> 0 | N25: PENDIENTE | O25: =IF(H25="SI",1,0)*0.6+IF(I25="SI",1,0)*0.4 -> 0 | P25: PENDIENTE | S25: =IFERROR(SCORECARDS!C23,"—") -> 0 | T25: =IF(ISTEXT(S25),S25,IF(S25<34,"🔴 Crítico",IF(S25<67,"🟡 Vulnerable","🟢 Preparado"))) -> 🔴 Crítico | W25: 0 | X25: 0 | Y25: 0 | Z25: 0 | AA25: 0 | AB25: 0 | AC25: 0 | AD25: 0 | AE25: 0 | AF25: 0 | AG25: 0 | AH25: 0 | AI25: 0 | AJ25: 0 | AK25: 0 | AL25: 0 | AM25: 0 | AN25: 0 | AO25: =IFERROR(AVERAGE(AA25,AB25,AC25,AD25,AE25,AF25,AG25,AH25,AI25,AJ25,AK25,AL25,AM25,AN25),"N/A") -> 0 | AP25: =IFERROR(AVERAGE(W25,X25,Y25,Z25)/2,"N/A") -> 0
A26: 20393786044 | B26: COOPERATIVA AGRARIA CAFETALERA COORDILLERA AZUL DE UCAYALI L | C26: UCAYALI | D26: CAFÉ | G26: NO | H26: nan | I26: nan | J26: ACTIVO | K26: nan | L26: 0 | M26: =IF(E26>0,ROUND(L26/E26*100,1),0) -> 0 | N26: PENDIENTE | O26: =IF(H26="SI",1,0)*0.6+IF(I26="SI",1,0)*0.4 -> 0 | P26: PENDIENTE | S26: =IFERROR(SCORECARDS!C24,"—") -> 0 | T26: =IF(ISTEXT(S26),S26,IF(S26<34,"🔴 Crítico",IF(S26<67,"🟡 Vulnerable","🟢 Preparado"))) -> 🔴 Crítico | W26: 0 | X26: 0 | Y26: 0 | Z26: 0 | AA26: 0 | AB26: 0 | AC26: 0 | AD26: 0 | AE26: 0 | AF26: 0 | AG26: 0 | AH26: 0 | AI26: 0 | AJ26: 0 | AK26: 0 | AL26: 0 | AM26: 0 | AN26: 0 | AO26: =IFERROR(AVERAGE(AA26,AB26,AC26,AD26,AE26,AF26,AG26,AH26,AI26,AJ26,AK26,AL26,AM26,AN26),"N/A") -> 0 | AP26: =IFERROR(AVERAGE(W26,X26,Y26,Z26)/2,"N/A") -> 0
A27: 20393816211 | B27: COOPERATIVA AGRARIA SAN JUAN BAUTISTA | C27: UCAYALI | D27: CACAO | E27: 0 | G27: NO | H27: nan | I27: nan | J27: ACTIVO | K27: nan | L27: 0 | M27: =IF(E27>0,ROUND(L27/E27*100,1),0) -> 0 | N27: PENDIENTE | O27: =IF(H27="SI",1,0)*0.6+IF(I27="SI",1,0)*0.4 -> 0 | P27: PENDIENTE | S27: =IFERROR(SCORECARDS!C25,"—") -> 0 | T27: =IF(ISTEXT(S27),S27,IF(S27<34,"🔴 Crítico",IF(S27<67,"🟡 Vulnerable","🟢 Preparado"))) -> 🔴 Crítico | W27: 0 | X27: 0 | Y27: 0 | Z27: 0 | AA27: 0 | AB27: 0 | AC27: 0 | AD27: 0 | AE27: 0 | AF27: 0 | AG27: 0 | AH27: 0 | AI27: 0 | AJ27: 0 | AK27: 0 | AL27: 0 | AM27: 0 | AN27: 0 | AO27: =IFERROR(AVERAGE(AA27,AB27,AC27,AD27,AE27,AF27,AG27,AH27,AI27,AJ27,AK27,AL27,AM27,AN27),"N/A") -> 0 | AP27: =IFERROR(AVERAGE(W27,X27,Y27,Z27)/2,"N/A") -> 0
A28: 20393882868 | B28: COOPERATIVA AGRARIA ASCAH | C28: UCAYALI | D28: CACAO | G28: NO | H28: nan | I28: nan | J28: ACTIVO | K28: nan | L28: 0 | M28: =IF(E28>0,ROUND(L28/E28*100,1),0) -> 0 | N28: PENDIENTE | O28: =IF(H28="SI",1,0)*0.6+IF(I28="SI",1,0)*0.4 -> 0 | P28: PENDIENTE | S28: =IFERROR(SCORECARDS!C26,"—") -> 0 | T28: =IF(ISTEXT(S28),S28,IF(S28<34,"🔴 Crítico",IF(S28<67,"🟡 Vulnerable","🟢 Preparado"))) -> 🔴 Crítico | W28: 0 | X28: 0 | Y28: 0 | Z28: 0 | AA28: 0 | AB28: 0 | AC28: 0 | AD28: 0 | AE28: 0 | AF28: 0 | AG28: 0 | AH28: 0 | AI28: 0 | AJ28: 0 | AK28: 0 | AL28: 0 | AM28: 0 | AN28: 0 | AO28: =IFERROR(AVERAGE(AA28,AB28,AC28,AD28,AE28,AF28,AG28,AH28,AI28,AJ28,AK28,AL28,AM28,AN28),"N/A") -> 0 | AP28: =IFERROR(AVERAGE(W28,X28,Y28,Z28)/2,"N/A") -> 0
A29: 20393972000 | B29: ASOCIACION DE MUJERES EMPRENDEDORAS FLOR DE BOQUERON | C29: UCAYALI | D29: CACAO | G29: NO | H29: nan | I29: nan | J29: ACTIVO | K29: nan | L29: 0 | M29: =IF(E29>0,ROUND(L29/E29*100,1),0) -> 0 | N29: PENDIENTE | O29: =IF(H29="SI",1,0)*0.6+IF(I29="SI",1,0)*0.4 -> 0 | P29: PENDIENTE | S29: =IFERROR(SCORECARDS!C27,"—") -> 0 | T29: =IF(ISTEXT(S29),S29,IF(S29<34,"🔴 Crítico",IF(S29<67,"🟡 Vulnerable","🟢 Preparado"))) -> 🔴 Crítico | W29: 0 | X29: 0 | Y29: 0 | Z29: 0 | AA29: 0 | AB29: 0 | AC29: 0 | AD29: 0 | AE29: 0 | AF29: 0 | AG29: 0 | AH29: 0 | AI29: 0 | AJ29: 0 | AK29: 0 | AL29: 0 | AM29: 0 | AN29: 0 | AO29: =IFERROR(AVERAGE(AA29,AB29,AC29,AD29,AE29,AF29,AG29,AH29,AI29,AJ29,AK29,AL29,AM29,AN29),"N/A") -> 0 | AP29: =IFERROR(AVERAGE(W29,X29,Y29,Z29)/2,"N/A") -> 0
A30: 20447888701 | B30: COOPERATIVA AGRARIA INDUSTRIAL SAN GABAN LTDA. | C30: PUNO | D30: CACAO | G30: NO | H30: nan | I30: nan | J30: ACTIVO | K30: nan | L30: 0 | M30: =IF(E30>0,ROUND(L30/E30*100,1),0) -> 0 | N30: PENDIENTE | O30: =IF(H30="SI",1,0)*0.6+IF(I30="SI",1,0)*0.4 -> 0 | P30: PENDIENTE | S30: =IFERROR(SCORECARDS!C28,"—") -> 0 | T30: =IF(ISTEXT(S30),S30,IF(S30<34,"🔴 Crítico",IF(S30<67,"🟡 Vulnerable","🟢 Preparado"))) -> 🔴 Crítico | W30: 0 | X30: 0 | Y30: 0 | Z30: 0 | AA30: 0 | AB30: 0 | AC30: 0 | AD30: 0 | AE30: 0 | AF30: 0 | AG30: 0 | AH30: 0 | AI30: 0 | AJ30: 0 | AK30: 0 | AL30: 0 | AM30: 0 | AN30: 0 | AO30: =IFERROR(AVERAGE(AA30,AB30,AC30,AD30,AE30,AF30,AG30,AH30,AI30,AJ30,AK30,AL30,AM30,AN30),"N/A") -> 0 | AP30: =IFERROR(AVERAGE(W30,X30,Y30,Z30)/2,"N/A") -> 0
A31: 20450189201 | B31: COOPERATIVA DE SERVICIOS MULTIPLES FRUTOS DE SELVA | C31: SAN MARTIN | D31: CAFÉ | E31: 0 | G31: NO | H31: nan | I31: nan | J31: ACTIVO | K31: nan | L31: 0 | M31: =IF(E31>0,ROUND(L31/E31*100,1),0) -> 0 | N31: PENDIENTE | O31: =IF(H31="SI",1,0)*0.6+IF(I31="SI",1,0)*0.4 -> 0 | P31: PENDIENTE | S31: =IFERROR(SCORECARDS!C29,"—") -> 0 | T31: =IF(ISTEXT(S31),S31,IF(S31<34,"🔴 Crítico",IF(S31<67,"🟡 Vulnerable","🟢 Preparado"))) -> 🔴 Crítico | W31: 0 | X31: 0 | Y31: 0 | Z31: 0 | AA31: 0 | AB31: 0 | AC31: 0 | AD31: 0 | AE31: 0 | AF31: 0 | AG31: 0 | AH31: 0 | AI31: 0 | AJ31: 0 | AK31: 0 | AL31: 0 | AM31: 0 | AN31: 0 | AO31: =IFERROR(AVERAGE(AA31,AB31,AC31,AD31,AE31,AF31,AG31,AH31,AI31,AJ31,AK31,AL31,AM31,AN31),"N/A") -> 0 | AP31: =IFERROR(AVERAGE(W31,X31,Y31,Z31)/2,"N/A") -> 0
A32: 20450207544 | B32: COOPERATIVA AGRARIA UCHIZA LTDA | C32: SAN MARTIN | D32: CACAO | E32: 0 | G32: NO | H32: nan | I32: nan | J32: ACTIVO | K32: nan | L32: 0 | M32: =IF(E32>0,ROUND(L32/E32*100,1),0) -> 0 | N32: PENDIENTE | O32: =IF(H32="SI",1,0)*0.6+IF(I32="SI",1,0)*0.4 -> 0 | P32: PENDIENTE | S32: =IFERROR(SCORECARDS!C30,"—") -> 0 | T32: =IF(ISTEXT(S32),S32,IF(S32<34,"🔴 Crítico",IF(S32<67,"🟡 Vulnerable","🟢 Preparado"))) -> 🔴 Crítico | W32: 0 | X32: 0 | Y32: 0 | Z32: 0 | AA32: 0 | AB32: 0 | AC32: 0 | AD32: 0 | AE32: 0 | AF32: 0 | AG32: 0 | AH32: 0 | AI32: 0 | AJ32: 0 | AK32: 0 | AL32: 0 | AM32: 0 | AN32: 0 | AO32: =IFERROR(AVERAGE(AA32,AB32,AC32,AD32,AE32,AF32,AG32,AH32,AI32,AJ32,AK32,AL32,AM32,AN32),"N/A") -> 0 | AP32: =IFERROR(AVERAGE(W32,X32,Y32,Z32)/2,"N/A") -> 0
A33: 20450242021 | B33: COOPERATIVA DE SERVICIOS MULTIPLES CAPEMA | C33: SAN MARTIN | D33: CAFÉ | E33: 0 | G33: NO | H33: nan | I33: nan | J33: ACTIVO | K33: nan | L33: 0 | M33: =IF(E33>0,ROUND(L33/E33*100,1),0) -> 0 | N33: PENDIENTE | O33: =IF(H33="SI",1,0)*0.6+IF(I33="SI",1,0)*0.4 -> 0 | P33: PENDIENTE | S33: =IFERROR(SCORECARDS!C31,"—") -> 0 | T33: =IF(ISTEXT(S33),S33,IF(S33<34,"🔴 Crítico",IF(S33<67,"🟡 Vulnerable","🟢 Preparado"))) -> 🔴 Crítico | W33: 0 | X33: 0 | Y33: 0 | Z33: 0 | AA33: 0 | AB33: 0 | AC33: 0 | AD33: 0 | AE33: 0 | AF33: 0 | AG33: 0 | AH33: 0 | AI33: 0 | AJ33: 0 | AK33: 0 | AL33: 0 | AM33: 0 | AN33: 0 | AO33: =IFERROR(AVERAGE(AA33,AB33,AC33,AD33,AE33,AF33,AG33,AH33,AI33,AJ33,AK33,AL33,AM33,AN33),"N/A") -> 0 | AP33: =IFERROR(AVERAGE(W33,X33,Y33,Z33)/2,"N/A") -> 0
A34: 20450319423 | B34: COOPERATIVA AGRARIA DE SERVICIOS MULTIPLES CAFE DONCEL | C34: SAN MARTIN | D34: CAFÉ | G34: NO | H34: nan | I34: nan | J34: ACTIVO | K34: nan | L34: 0 | M34: =IF(E34>0,ROUND(L34/E34*100,1),0) -> 0 | N34: PENDIENTE | O34: =IF(H34="SI",1,0)*0.6+IF(I34="SI",1,0)*0.4 -> 0 | P34: PENDIENTE | S34: =IFERROR(SCORECARDS!C32,"—") -> 0 | T34: =IF(ISTEXT(S34),S34,IF(S34<34,"🔴 Crítico",IF(S34<67,"🟡 Vulnerable","🟢 Preparado"))) -> 🔴 Crítico | W34: 0 | X34: 0 | Y34: 0 | Z34: 0 | AA34: 0 | AB34: 0 | AC34: 0 | AD34: 0 | AE34: 0 | AF34: 0 | AG34: 0 | AH34: 0 | AI34: 0 | AJ34: 0 | AK34: 0 | AL34: 0 | AM34: 0 | AN34: 0 | AO34: =IFERROR(AVERAGE(AA34,AB34,AC34,AD34,AE34,AF34,AG34,AH34,AI34,AJ34,AK34,AL34,AM34,AN34),"N/A") -> 0 | AP34: =IFERROR(AVERAGE(W34,X34,Y34,Z34)/2,"N/A") -> 0
A35: 20452774705 | B35: COOPERATIVA AGRARIA CACAO VRAE | C35: CUSCO | D35: CACAO | E35: 1931452.7 | F35: 7 | G35: SI | H35: nan | I35: nan | J35: ACTIVO | K35: nan | L35: 965726.35 | M35: =IF(E35>0,ROUND(L35/E35*100,1),0) -> 50 | N35: PENDIENTE | O35: =IF(H35="SI",1,0)*0.6+IF(I35="SI",1,0)*0.4 -> 0 | P35: PENDIENTE | S35: =IFERROR(SCORECARDS!C33,"—") -> 0 | T35: =IF(ISTEXT(S35),S35,IF(S35<34,"🔴 Crítico",IF(S35<67,"🟡 Vulnerable","🟢 Preparado"))) -> 🔴 Crítico | U35: 1 | V35: Sin hallazgos OSCE / OEFA | W35: 1 | X35: 0 | Y35: 0 | Z35: 0 | AA35: 0 | AB35: 0 | AC35: 0 | AD35: 0 | AE35: 0 | AF35: 0 | AG35: 0 | AH35: 0 | AI35: 0 | AJ35: 0 | AK35: 0 | AL35: 0 | AM35: 0 | AN35: 0 | AO35: =IFERROR(AVERAGE(AA35,AB35,AC35,AD35,AE35,AF35,AG35,AH35,AI35,AJ35,AK35,AL35,AM35,AN35),"N/A") -> 0 | AP35: =IFERROR(AVERAGE(W35,X35,Y35,Z35)/2,"N/A") -> 0.125
A36: 20479595276 | B36: COOPERATIVA AGRARIA CAFETALERA CASIL LTDA. | C36: CAJAMARCA | D36: CAFÉ | E36: 4538578.9 | F36: 24 | G36: SI | H36: SI | I36: SI | J36: ACTIVO | K36: nan | L36: 965167.45 | M36: =IF(E36>0,ROUND(L36/E36*100,1),0) -> 21.3 | N36: PENDIENTE | O36: =IF(H36="SI",1,0)*0.6+IF(I36="SI",1,0)*0.4 -> 1 | P36: PENDIENTE | Q36: 178 | R36: 437 | S36: =IFERROR(SCORECARDS!C34,"—") -> 0 | T36: =IF(ISTEXT(S36),S36,IF(S36<34,"🔴 Crítico",IF(S36<67,"🟡 Vulnerable","🟢 Preparado"))) -> 🔴 Crítico | U36: 1 | V36: Sin hallazgos OSCE / OEFA | W36: 1 | X36: 0 | Y36: 0 | Z36: 0 | AA36: 0 | AB36: 0 | AC36: 0 | AD36: 0 | AE36: 0 | AF36: 0 | AG36: 0 | AH36: 0 | AI36: 0 | AJ36: 0 | AK36: 0 | AL36: 0 | AM36: 0 | AN36: 0 | AO36: =IFERROR(AVERAGE(AA36,AB36,AC36,AD36,AE36,AF36,AG36,AH36,AI36,AJ36,AK36,AL36,AM36,AN36),"N/A") -> 0 | AP36: =IFERROR(AVERAGE(W36,X36,Y36,Z36)/2,"N/A") -> 0.125
A37: 20479622699 | B37: COOPERATIVA AGRARIA JUAN MARCO EL PALTO | C37: AMAZONAS | D37: CAFÉ | E37: 0 | G37: NO | H37: nan | I37: nan | J37: ACTIVO | K37: nan | L37: 0 | M37: =IF(E37>0,ROUND(L37/E37*100,1),0) -> 0 | N37: PENDIENTE | O37: =IF(H37="SI",1,0)*0.6+IF(I37="SI",1,0)*0.4 -> 0 | P37: PENDIENTE | S37: =IFERROR(SCORECARDS!C35,"—") -> 0 | T37: =IF(ISTEXT(S37),S37,IF(S37<34,"🔴 Crítico",IF(S37<67,"🟡 Vulnerable","🟢 Preparado"))) -> 🔴 Crítico | W37: 0 | X37: 0 | Y37: 0 | Z37: 0 | AA37: 0 | AB37: 0 | AC37: 0 | AD37: 0 | AE37: 0 | AF37: 0 | AG37: 0 | AH37: 0 | AI37: 0 | AJ37: 0 | AK37: 0 | AL37: 0 | AM37: 0 | AN37: 0 | AO37: =IFERROR(AVERAGE(AA37,AB37,AC37,AD37,AE37,AF37,AG37,AH37,AI37,AJ37,AK37,AL37,AM37,AN37),"N/A") -> 0 | AP37: =IFERROR(AVERAGE(W37,X37,Y37,Z37)/2,"N/A") -> 0
A38: 20479856258 | B38: ASOCIACION DE PRODUCTORES AGROPECUARIOS LUIS SOLIBARRIA | C38: AMAZONAS | D38: nan | G38: NO | H38: nan | I38: nan | J38: BAJA DE OFICIO | K38: nan | L38: 0 | M38: =IF(E38>0,ROUND(L38/E38*100,1),0) -> 0 | N38: PENDIENTE | O38: =IF(H38="SI",1,0)*0.6+IF(I38="SI",1,0)*0.4 -> 0 | P38: PENDIENTE | S38: =IFERROR(SCORECARDS!C36,"—") -> 0 | T38: =IF(ISTEXT(S38),S38,IF(S38<34,"🔴 Crítico",IF(S38<67,"🟡 Vulnerable","🟢 Preparado"))) -> 🔴 Crítico | W38: 0 | X38: 0 | Y38: 0 | Z38: 0 | AA38: 0 | AB38: 0 | AC38: 0 | AD38: 0 | AE38: 0 | AF38: 0 | AG38: 0 | AH38: 0 | AI38: 0 | AJ38: 0 | AK38: 0 | AL38: 0 | AM38: 0 | AN38: 0 | AO38: =IFERROR(AVERAGE(AA38,AB38,AC38,AD38,AE38,AF38,AG38,AH38,AI38,AJ38,AK38,AL38,AM38,AN38),"N/A") -> 0 | AP38: =IFERROR(AVERAGE(W38,X38,Y38,Z38)/2,"N/A") -> 0
A39: 20479917141 | B39: COOPERATIVA AGRARIA CENTRAL DE PRODUCTORES DE AMAZONAS | C39: AMAZONAS | D39: CACAO | E39: 1175215.3 | F39: 7 | G39: SI | H39: nan | I39: nan | J39: ACTIVO | K39: nan | L39: 587607.64 | M39: =IF(E39>0,ROUND(L39/E39*100,1),0) -> 50 | N39: PENDIENTE | O39: =IF(H39="SI",1,0)*0.6+IF(I39="SI",1,0)*0.4 -> 0 | P39: PENDIENTE | S39: =IFERROR(SCORECARDS!C37,"—") -> 0 | T39: =IF(ISTEXT(S39),S39,IF(S39<34,"🔴 Crítico",IF(S39<67,"🟡 Vulnerable","🟢 Preparado"))) -> 🔴 Crítico | U39: 1 | V39: Sin hallazgos OSCE / OEFA | W39: 1 | X39: 0 | Y39: 0 | Z39: 0 | AA39: 0 | AB39: 0 | AC39: 0 | AD39: 0 | AE39: 0 | AF39: 0 | AG39: 0 | AH39: 0 | AI39: 0 | AJ39: 0 | AK39: 0 | AL39: 0 | AM39: 0 | AN39: 0 | AO39: =IFERROR(AVERAGE(AA39,AB39,AC39,AD39,AE39,AF39,AG39,AH39,AI39,AJ39,AK39,AL39,AM39,AN39),"N/A") -> 0 | AP39: =IFERROR(AVERAGE(W39,X39,Y39,Z39)/2,"N/A") -> 0.125
A40: 20480458550 | B40: COOPERATIVA AGRARIA APROCAM | C40: AMAZONAS | D40: CACAO | E40: 1684430 | F40: 14 | G40: SI | H40: nan | I40: nan | J40: ACTIVO | K40: nan | L40: 842214.99 | M40: =IF(E40>0,ROUND(L40/E40*100,1),0) -> 50 | N40: PENDIENTE | O40: =IF(H40="SI",1,0)*0.6+IF(I40="SI",1,0)*0.4 -> 0 | P40: PENDIENTE | S40: =IFERROR(SCORECARDS!C38,"—") -> 0 | T40: =IF(ISTEXT(S40),S40,IF(S40<34,"🔴 Crítico",IF(S40<67,"🟡 Vulnerable","🟢 Preparado"))) -> 🔴 Crítico | U40: 1 | V40: Sin hallazgos OSCE / OEFA | W40: 1 | X40: 0 | Y40: 0 | Z40: 0 | AA40: 0 | AB40: 0 | AC40: 0 | AD40: 0 | AE40: 0 | AF40: 0 | AG40: 0 | AH40: 0 | AI40: 0 | AJ40: 0 | AK40: 0 | AL40: 0 | AM40: 0 | AN40: 0 | AO40: =IFERROR(AVERAGE(AA40,AB40,AC40,AD40,AE40,AF40,AG40,AH40,AI40,AJ40,AK40,AL40,AM40,AN40),"N/A") -> 0 | AP40: =IFERROR(AVERAGE(W40,X40,Y40,Z40)/2,"N/A") -> 0.125
A41: 20480762895 | B41: ASOCIACION DE PRODUCTORES AGROPECUARIOS LA FLOR DE CAFE | C41: AMAZONAS | D41: CAFÉ | E41: 0 | G41: NO | H41: nan | I41: nan | J41: BAJA DE OFICIO | K41: nan | L41: 0 | M41: =IF(E41>0,ROUND(L41/E41*100,1),0) -> 0 | N41: PENDIENTE | O41: =IF(H41="SI",1,0)*0.6+IF(I41="SI",1,0)*0.4 -> 0 | P41: PENDIENTE | S41: =IFERROR(SCORECARDS!C39,"—") -> 0 | T41: =IF(ISTEXT(S41),S41,IF(S41<34,"🔴 Crítico",IF(S41<67,"🟡 Vulnerable","🟢 Preparado"))) -> 🔴 Crítico | W41: 0 | X41: 0 | Y41: 0 | Z41: 0 | AA41: 0 | AB41: 0 | AC41: 0 | AD41: 0 | AE41: 0 | AF41: 0 | AG41: 0 | AH41: 0 | AI41: 0 | AJ41: 0 | AK41: 0 | AL41: 0 | AM41: 0 | AN41: 0 | AO41: =IFERROR(AVERAGE(AA41,AB41,AC41,AD41,AE41,AF41,AG41,AH41,AI41,AJ41,AK41,AL41,AM41,AN41),"N/A") -> 0 | AP41: =IFERROR(AVERAGE(W41,X41,Y41,Z41)/2,"N/A") -> 0
A42: 20484163902 | B42: COOPERATIVA AGRARIA APPROCAP LTDA | C42: PIURA | D42: CACAO | E42: 817000 | F42: 6 | G42: SI | H42: nan | I42: nan | J42: ACTIVO | K42: nan | L42: 408500 | M42: =IF(E42>0,ROUND(L42/E42*100,1),0) -> 50 | N42: PENDIENTE | O42: =IF(H42="SI",1,0)*0.6+IF(I42="SI",1,0)*0.4 -> 0 | P42: PENDIENTE | S42: =IFERROR(SCORECARDS!C40,"—") -> 0 | T42: =IF(ISTEXT(S42),S42,IF(S42<34,"🔴 Crítico",IF(S42<67,"🟡 Vulnerable","🟢 Preparado"))) -> 🔴 Crítico | U42: 1 | V42: Sin hallazgos OSCE / OEFA | W42: 0 | X42: 0 | Y42: 0 | Z42: 0 | AA42: 0 | AB42: 0 | AC42: 0 | AD42: 0 | AE42: 0 | AF42: 0 | AG42: 0 | AH42: 0 | AI42: 0 | AJ42: 0 | AK42: 0 | AL42: 0 | AM42: 0 | AN42: 0 | AO42: =IFERROR(AVERAGE(AA42,AB42,AC42,AD42,AE42,AF42,AG42,AH42,AI42,AJ42,AK42,AL42,AM42,AN42),"N/A") -> 0 | AP42: =IFERROR(AVERAGE(W42,X42,Y42,Z42)/2,"N/A") -> 0
A43: 20485945815 | B43: COOPERATIVA AGRARIA CAFETALERA ECOLOGICO ALTO PALOMAR | C43: JUNIN | D43: CAFÉ | E43: 0 | G43: NO | H43: nan | I43: nan | J43: SUSPENSION TEMPORAL | K43: nan | L43: 0 | M43: =IF(E43>0,ROUND(L43/E43*100,1),0) -> 0 | N43: PENDIENTE | O43: =IF(H43="SI",1,0)*0.6+IF(I43="SI",1,0)*0.4 -> 0 | P43: PENDIENTE | S43: =IFERROR(SCORECARDS!C41,"—") -> 0 | T43: =IF(ISTEXT(S43),S43,IF(S43<34,"🔴 Crítico",IF(S43<67,"🟡 Vulnerable","🟢 Preparado"))) -> 🔴 Crítico | W43: 0 | X43: 0 | Y43: 0 | Z43: 0 | AA43: 0 | AB43: 0 | AC43: 0 | AD43: 0 | AE43: 0 | AF43: 0 | AG43: 0 | AH43: 0 | AI43: 0 | AJ43: 0 | AK43: 0 | AL43: 0 | AM43: 0 | AN43: 0 | AO43: =IFERROR(AVERAGE(AA43,AB43,AC43,AD43,AE43,AF43,AG43,AH43,AI43,AJ43,AK43,AL43,AM43,AN43),"N/A") -> 0 | AP43: =IFERROR(AVERAGE(W43,X43,Y43,Z43)/2,"N/A") -> 0
A44: 20486094657 | B44: ASOCIACION DE PRODUCTORES DE CAFES ESPECIALES MOUNTAIN COFFE | C44: JUNIN | D44: CAFÉ | E44: 0 | G44: NO | H44: nan | I44: nan | J44: ACTIVO | K44: nan | L44: 0 | M44: =IF(E44>0,ROUND(L44/E44*100,1),0) -> 0 | N44: PENDIENTE | O44: =IF(H44="SI",1,0)*0.6+IF(I44="SI",1,0)*0.4 -> 0 | P44: PENDIENTE | S44: =IFERROR(SCORECARDS!C42,"—") -> 0 | T44: =IF(ISTEXT(S44),S44,IF(S44<34,"🔴 Crítico",IF(S44<67,"🟡 Vulnerable","🟢 Preparado"))) -> 🔴 Crítico | W44: 0 | X44: 0 | Y44: 0 | Z44: 0 | AA44: 0 | AB44: 0 | AC44: 0 | AD44: 0 | AE44: 0 | AF44: 0 | AG44: 0 | AH44: 0 | AI44: 0 | AJ44: 0 | AK44: 0 | AL44: 0 | AM44: 0 | AN44: 0 | AO44: =IFERROR(AVERAGE(AA44,AB44,AC44,AD44,AE44,AF44,AG44,AH44,AI44,AJ44,AK44,AL44,AM44,AN44),"N/A") -> 0 | AP44: =IFERROR(AVERAGE(W44,X44,Y44,Z44)/2,"N/A") -> 0
A45: 20486255090 | B45: COOPERATIVA AGRARIA SANGARENI | C45: JUNIN | D45: CAFÉ | E45: 13207692 | F45: 41 | G45: SI | H45: nan | I45: nan | J45: ACTIVO | K45: nan | L45: 6603846 | M45: =IF(E45>0,ROUND(L45/E45*100,1),0) -> 50 | N45: PENDIENTE | O45: =IF(H45="SI",1,0)*0.6+IF(I45="SI",1,0)*0.4 -> 0 | P45: PENDIENTE | S45: =IFERROR(SCORECARDS!C43,"—") -> 0 | T45: =IF(ISTEXT(S45),S45,IF(S45<34,"🔴 Crítico",IF(S45<67,"🟡 Vulnerable","🟢 Preparado"))) -> 🔴 Crítico | U45: 1 | V45: Sin hallazgos OSCE / OEFA | W45: 1 | X45: 0 | Y45: 0 | Z45: 0 | AA45: 0 | AB45: 0 | AC45: 0 | AD45: 0 | AE45: 0 | AF45: 0 | AG45: 0 | AH45: 0 | AI45: 0 | AJ45: 0 | AK45: 0 | AL45: 0 | AM45: 0 | AN45: 0 | AO45: =IFERROR(AVERAGE(AA45,AB45,AC45,AD45,AE45,AF45,AG45,AH45,AI45,AJ45,AK45,AL45,AM45,AN45),"N/A") -> 0 | AP45: =IFERROR(AVERAGE(W45,X45,Y45,Z45)/2,"N/A") -> 0.125
A46: 20486668335 | B46: COOPERATIVA AGROINDUSTRIAL SONOMORO LTDA | C46: JUNIN | D46: nan | E46: 0 | G46: NO | H46: nan | I46: nan | J46: SUSPENSION TEMPORAL | K46: nan | L46: 0 | M46: =IF(E46>0,ROUND(L46/E46*100,1),0) -> 0 | N46: PENDIENTE | O46: =IF(H46="SI",1,0)*0.6+IF(I46="SI",1,0)*0.4 -> 0 | P46: PENDIENTE | S46: =IFERROR(SCORECARDS!C44,"—") -> 0 | T46: =IF(ISTEXT(S46),S46,IF(S46<34,"🔴 Crítico",IF(S46<67,"🟡 Vulnerable","🟢 Preparado"))) -> 🔴 Crítico | W46: 0 | X46: 0 | Y46: 0 | Z46: 0 | AA46: 0 | AB46: 0 | AC46: 0 | AD46: 0 | AE46: 0 | AF46: 0 | AG46: 0 | AH46: 0 | AI46: 0 | AJ46: 0 | AK46: 0 | AL46: 0 | AM46: 0 | AN46: 0 | AO46: =IFERROR(AVERAGE(AA46,AB46,AC46,AD46,AE46,AF46,AG46,AH46,AI46,AJ46,AK46,AL46,AM46,AN46),"N/A") -> 0 | AP46: =IFERROR(AVERAGE(W46,X46,Y46,Z46)/2,"N/A") -> 0
A47: 20486876019 | B47: COOPERATIVA AGROECOLOGICO INDUSTRIAL MAZAMARI LTDA | C47: JUNIN | D47: CACAO | G47: NO | H47: nan | I47: nan | J47: ACTIVO | K47: nan | L47: 0 | M47: =IF(E47>0,ROUND(L47/E47*100,1),0) -> 0 | N47: PENDIENTE | O47: =IF(H47="SI",1,0)*0.6+IF(I47="SI",1,0)*0.4 -> 0 | P47: PENDIENTE | S47: =IFERROR(SCORECARDS!C45,"—") -> 0 | T47: =IF(ISTEXT(S47),S47,IF(S47<34,"🔴 Crítico",IF(S47<67,"🟡 Vulnerable","🟢 Preparado"))) -> 🔴 Crítico | W47: 0 | X47: 0 | Y47: 0 | Z47: 0 | AA47: 0 | AB47: 0 | AC47: 0 | AD47: 0 | AE47: 0 | AF47: 0 | AG47: 0 | AH47: 0 | AI47: 0 | AJ47: 0 | AK47: 0 | AL47: 0 | AM47: 0 | AN47: 0 | AO47: =IFERROR(AVERAGE(AA47,AB47,AC47,AD47,AE47,AF47,AG47,AH47,AI47,AJ47,AK47,AL47,AM47,AN47),"N/A") -> 0 | AP47: =IFERROR(AVERAGE(W47,X47,Y47,Z47)/2,"N/A") -> 0
A48: 20486973219 | B48: COOPERATIVA AGRARIA SONOMORO DEL VRAEM LTDA | C48: JUNIN | D48: CACAO | E48: 30342293 | F48: 108 | G48: SI | H48: nan | I48: nan | J48: ACTIVO | K48: nan | L48: 15171147 | M48: =IF(E48>0,ROUND(L48/E48*100,1),0) -> 50 | N48: PENDIENTE | O48: =IF(H48="SI",1,0)*0.6+IF(I48="SI",1,0)*0.4 -> 0 | P48: PENDIENTE | S48: =IFERROR(SCORECARDS!C46,"—") -> 0 | T48: =IF(ISTEXT(S48),S48,IF(S48<34,"🔴 Crítico",IF(S48<67,"🟡 Vulnerable","🟢 Preparado"))) -> 🔴 Crítico | U48: 1 | V48: Sin hallazgos OSCE / OEFA | W48: 1 | X48: 0 | Y48: 0 | Z48: 0 | AA48: 0 | AB48: 0 | AC48: 0 | AD48: 0 | AE48: 0 | AF48: 0 | AG48: 0 | AH48: 0 | AI48: 0 | AJ48: 0 | AK48: 0 | AL48: 0 | AM48: 0 | AN48: 0 | AO48: =IFERROR(AVERAGE(AA48,AB48,AC48,AD48,AE48,AF48,AG48,AH48,AI48,AJ48,AK48,AL48,AM48,AN48),"N/A") -> 0 | AP48: =IFERROR(AVERAGE(W48,X48,Y48,Z48)/2,"N/A") -> 0.125
A49: 20487242994 | B49: COOPERATIVA AGRARIA ECOLOGICA CACAOTERA VALLE RIO ENE - COOP | C49: JUNIN | D49: CACAO | E49: 2290978.7 | F49: 10 | G49: SI | H49: nan | I49: nan | J49: ACTIVO | K49: nan | L49: 1145489.4 | M49: =IF(E49>0,ROUND(L49/E49*100,1),0) -> 50 | N49: PENDIENTE | O49: =IF(H49="SI",1,0)*0.6+IF(I49="SI",1,0)*0.4 -> 0 | P49: PENDIENTE | S49: =IFERROR(SCORECARDS!C47,"—") -> 0 | T49: =IF(ISTEXT(S49),S49,IF(S49<34,"🔴 Crítico",IF(S49<67,"🟡 Vulnerable","🟢 Preparado"))) -> 🔴 Crítico | U49: 1 | V49: Sin hallazgos OSCE / OEFA | W49: 1 | X49: 0 | Y49: 0 | Z49: 0 | AA49: 0 | AB49: 0 | AC49: 0 | AD49: 0 | AE49: 0 | AF49: 0 | AG49: 0 | AH49: 0 | AI49: 0 | AJ49: 0 | AK49: 0 | AL49: 0 | AM49: 0 | AN49: 0 | AO49: =IFERROR(AVERAGE(AA49,AB49,AC49,AD49,AE49,AF49,AG49,AH49,AI49,AJ49,AK49,AL49,AM49,AN49),"N/A") -> 0 | AP49: =IFERROR(AVERAGE(W49,X49,Y49,Z49)/2,"N/A") -> 0.125
A50: 20487351343 | B50: ASOCIACION DE PRODUCTORES AGROPECUARIOS TUPAC AMARU DE CHIÑA | C50: LAMBAYEQUE | D50: CAFÉ | G50: NO | H50: nan | I50: nan | J50: BAJA DE OFICIO | K50: nan | L50: 0 | M50: =IF(E50>0,ROUND(L50/E50*100,1),0) -> 0 | N50: PENDIENTE | O50: =IF(H50="SI",1,0)*0.6+IF(I50="SI",1,0)*0.4 -> 0 | P50: PENDIENTE | S50: =IFERROR(SCORECARDS!C48,"—") -> 0 | T50: =IF(ISTEXT(S50),S50,IF(S50<34,"🔴 Crítico",IF(S50<67,"🟡 Vulnerable","🟢 Preparado"))) -> 🔴 Crítico | W50: 0 | X50: 0 | Y50: 0 | Z50: 0 | AA50: 0 | AB50: 0 | AC50: 0 | AD50: 0 | AE50: 0 | AF50: 0 | AG50: 0 | AH50: 0 | AI50: 0 | AJ50: 0 | AK50: 0 | AL50: 0 | AM50: 0 | AN50: 0 | AO50: =IFERROR(AVERAGE(AA50,AB50,AC50,AD50,AE50,AF50,AG50,AH50,AI50,AJ50,AK50,AL50,AM50,AN50),"N/A") -> 0 | AP50: =IFERROR(AVERAGE(W50,X50,Y50,Z50)/2,"N/A") -> 0
A51: 20487661539 | B51: ASOCIACION DE PRODUCTORES CACAOTEROS DEL DISTRITO DE HUARANG | C51: CAJAMARCA | D51: CACAO | G51: NO | H51: nan | I51: nan | J51: ACTIVO | K51: nan | L51: 0 | M51: =IF(E51>0,ROUND(L51/E51*100,1),0) -> 0 | N51: PENDIENTE | O51: =IF(H51="SI",1,0)*0.6+IF(I51="SI",1,0)*0.4 -> 0 | P51: PENDIENTE | S51: =IFERROR(SCORECARDS!C49,"—") -> 0 | T51: =IF(ISTEXT(S51),S51,IF(S51<34,"🔴 Crítico",IF(S51<67,"🟡 Vulnerable","🟢 Preparado"))) -> 🔴 Crítico | W51: 0 | X51: 0 | Y51: 0 | Z51: 0 | AA51: 0 | AB51: 0 | AC51: 0 | AD51: 0 | AE51: 0 | AF51: 0 | AG51: 0 | AH51: 0 | AI51: 0 | AJ51: 0 | AK51: 0 | AL51: 0 | AM51: 0 | AN51: 0 | AO51: =IFERROR(AVERAGE(AA51,AB51,AC51,AD51,AE51,AF51,AG51,AH51,AI51,AJ51,AK51,AL51,AM51,AN51),"N/A") -> 0 | AP51: =IFERROR(AVERAGE(W51,X51,Y51,Z51)/2,"N/A") -> 0
A52: 20490726196 | B52: ASOCIACIÓN DE PRODUCTORES AGROPECUARIOS VALLESITO - CHAHUARE | C52: CUSCO | D52: CACAO | G52: NO | H52: nan | I52: nan | J52: ACTIVO | K52: nan | L52: 0 | M52: =IF(E52>0,ROUND(L52/E52*100,1),0) -> 0 | N52: PENDIENTE | O52: =IF(H52="SI",1,0)*0.6+IF(I52="SI",1,0)*0.4 -> 0 | P52: PENDIENTE | S52: =IFERROR(SCORECARDS!C50,"—") -> 0 | T52: =IF(ISTEXT(S52),S52,IF(S52<34,"🔴 Crítico",IF(S52<67,"🟡 Vulnerable","🟢 Preparado"))) -> 🔴 Crítico | W52: 0 | X52: 0 | Y52: 0 | Z52: 0 | AA52: 0 | AB52: 0 | AC52: 0 | AD52: 0 | AE52: 0 | AF52: 0 | AG52: 0 | AH52: 0 | AI52: 0 | AJ52: 0 | AK52: 0 | AL52: 0 | AM52: 0 | AN52: 0 | AO52: =IFERROR(AVERAGE(AA52,AB52,AC52,AD52,AE52,AF52,AG52,AH52,AI52,AJ52,AK52,AL52,AM52,AN52),"N/A") -> 0 | AP52: =IFERROR(AVERAGE(W52,X52,Y52,Z52)/2,"N/A") -> 0
A53: 20493934822 | B53: COOPERATIVA AGRARIA NUEVO AMANECER LTDA. | C53: SAN MARTIN | D53: CACAO | E53: 0 | G53: NO | H53: nan | I53: nan | J53: ACTIVO | K53: nan | L53: 0 | M53: =IF(E53>0,ROUND(L53/E53*100,1),0) -> 0 | N53: PENDIENTE | O53: =IF(H53="SI",1,0)*0.6+IF(I53="SI",1,0)*0.4 -> 0 | P53: PENDIENTE | S53: =IFERROR(SCORECARDS!C51,"—") -> 0 | T53: =IF(ISTEXT(S53),S53,IF(S53<34,"🔴 Crítico",IF(S53<67,"🟡 Vulnerable","🟢 Preparado"))) -> 🔴 Crítico | W53: 0 | X53: 0 | Y53: 0 | Z53: 0 | AA53: 0 | AB53: 0 | AC53: 0 | AD53: 0 | AE53: 0 | AF53: 0 | AG53: 0 | AH53: 0 | AI53: 0 | AJ53: 0 | AK53: 0 | AL53: 0 | AM53: 0 | AN53: 0 | AO53: =IFERROR(AVERAGE(AA53,AB53,AC53,AD53,AE53,AF53,AG53,AH53,AI53,AJ53,AK53,AL53,AM53,AN53),"N/A") -> 0 | AP53: =IFERROR(AVERAGE(W53,X53,Y53,Z53)/2,"N/A") -> 0
A54: 20493959574 | B54: COOPERATIVA AGRARIA DE SERVICIOS MUJERES TECNOLOGAS CACAOTER | C54: SAN MARTIN | D54: CACAO | G54: NO | H54: nan | I54: nan | J54: SUSPENSION TEMPORAL | K54: nan | L54: 0 | M54: =IF(E54>0,ROUND(L54/E54*100,1),0) -> 0 | N54: PENDIENTE | O54: =IF(H54="SI",1,0)*0.6+IF(I54="SI",1,0)*0.4 -> 0 | P54: PENDIENTE | S54: =IFERROR(SCORECARDS!C52,"—") -> 0 | T54: =IF(ISTEXT(S54),S54,IF(S54<34,"🔴 Crítico",IF(S54<67,"🟡 Vulnerable","🟢 Preparado"))) -> 🔴 Crítico | W54: 0 | X54: 0 | Y54: 0 | Z54: 0 | AA54: 0 | AB54: 0 | AC54: 0 | AD54: 0 | AE54: 0 | AF54: 0 | AG54: 0 | AH54: 0 | AI54: 0 | AJ54: 0 | AK54: 0 | AL54: 0 | AM54: 0 | AN54: 0 | AO54: =IFERROR(AVERAGE(AA54,AB54,AC54,AD54,AE54,AF54,AG54,AH54,AI54,AJ54,AK54,AL54,AM54,AN54),"N/A") -> 0 | AP54: =IFERROR(AVERAGE(W54,X54,Y54,Z54)/2,"N/A") -> 0
A55: 20494126819 | B55: ASOCIACION DE PRODUCTORES AGROPECUARIOS RIO MAYO SHANAO | C55: SAN MARTIN | D55: CACAO | G55: NO | H55: nan | I55: nan | J55: ACTIVO | K55: nan | L55: 0 | M55: =IF(E55>0,ROUND(L55/E55*100,1),0) -> 0 | N55: PENDIENTE | O55: =IF(H55="SI",1,0)*0.6+IF(I55="SI",1,0)*0.4 -> 0 | P55: PENDIENTE | S55: =IFERROR(SCORECARDS!C53,"—") -> 0 | T55: =IF(ISTEXT(S55),S55,IF(S55<34,"🔴 Crítico",IF(S55<67,"🟡 Vulnerable","🟢 Preparado"))) -> 🔴 Crítico | W55: 0 | X55: 0 | Y55: 0 | Z55: 0 | AA55: 0 | AB55: 0 | AC55: 0 | AD55: 0 | AE55: 0 | AF55: 0 | AG55: 0 | AH55: 0 | AI55: 0 | AJ55: 0 | AK55: 0 | AL55: 0 | AM55: 0 | AN55: 0 | AO55: =IFERROR(AVERAGE(AA55,AB55,AC55,AD55,AE55,AF55,AG55,AH55,AI55,AJ55,AK55,AL55,AM55,AN55),"N/A") -> 0 | AP55: =IFERROR(AVERAGE(W55,X55,Y55,Z55)/2,"N/A") -> 0
A56: 20494145791 | B56: ASOCIACION ECOLOGICA Y DE PRODUCTORES AGROPECUARIOS SAN JOSE | C56: LORETO | D56: CACAO | G56: NO | H56: nan | I56: nan | J56: ACTIVO | K56: nan | L56: 0 | M56: =IF(E56>0,ROUND(L56/E56*100,1),0) -> 0 | N56: PENDIENTE | O56: =IF(H56="SI",1,0)*0.6+IF(I56="SI",1,0)*0.4 -> 0 | P56: PENDIENTE | S56: =IFERROR(SCORECARDS!C54,"—") -> 0 | T56: =IF(ISTEXT(S56),S56,IF(S56<34,"🔴 Crítico",IF(S56<67,"🟡 Vulnerable","🟢 Preparado"))) -> 🔴 Crítico | W56: 0 | X56: 0 | Y56: 0 | Z56: 0 | AA56: 0 | AB56: 0 | AC56: 0 | AD56: 0 | AE56: 0 | AF56: 0 | AG56: 0 | AH56: 0 | AI56: 0 | AJ56: 0 | AK56: 0 | AL56: 0 | AM56: 0 | AN56: 0 | AO56: =IFERROR(AVERAGE(AA56,AB56,AC56,AD56,AE56,AF56,AG56,AH56,AI56,AJ56,AK56,AL56,AM56,AN56),"N/A") -> 0 | AP56: =IFERROR(AVERAGE(W56,X56,Y56,Z56)/2,"N/A") -> 0
A57: 20494699690 | B57: ASOCIACION DE PRODUCTORES DE CACAO ECOLOGICO DE KIMBIRI - AP | C57: CUSCO | D57: CACAO | G57: NO | H57: nan | I57: nan | J57: ACTIVO | K57: nan | L57: 0 | M57: =IF(E57>0,ROUND(L57/E57*100,1),0) -> 0 | N57: PENDIENTE | O57: =IF(H57="SI",1,0)*0.6+IF(I57="SI",1,0)*0.4 -> 0 | P57: PENDIENTE | S57: =IFERROR(SCORECARDS!C55,"—") -> 0 | T57: =IF(ISTEXT(S57),S57,IF(S57<34,"🔴 Crítico",IF(S57<67,"🟡 Vulnerable","🟢 Preparado"))) -> 🔴 Crítico | W57: 0 | X57: 0 | Y57: 0 | Z57: 0 | AA57: 0 | AB57: 0 | AC57: 0 | AD57: 0 | AE57: 0 | AF57: 0 | AG57: 0 | AH57: 0 | AI57: 0 | AJ57: 0 | AK57: 0 | AL57: 0 | AM57: 0 | AN57: 0 | AO57: =IFERROR(AVERAGE(AA57,AB57,AC57,AD57,AE57,AF57,AG57,AH57,AI57,AJ57,AK57,AL57,AM57,AN57),"N/A") -> 0 | AP57: =IFERROR(AVERAGE(W57,X57,Y57,Z57)/2,"N/A") -> 0
A58: 20525969551 | B58: COOPERATIVA AGRARIA DE PRODUCTORES DE BANANO, CACAO ORGANICO | C58: PIURA | D58: CACAO | E58: 105840 | F58: 7 | G58: SI | H58: nan | I58: nan | J58: ACTIVO | K58: nan | L58: 52920 | M58: =IF(E58>0,ROUND(L58/E58*100,1),0) -> 50 | N58: PENDIENTE | O58: =IF(H58="SI",1,0)*0.6+IF(I58="SI",1,0)*0.4 -> 0 | P58: PENDIENTE | S58: =IFERROR(SCORECARDS!C56,"—") -> 0 | T58: =IF(ISTEXT(S58),S58,IF(S58<34,"🔴 Crítico",IF(S58<67,"🟡 Vulnerable","🟢 Preparado"))) -> 🔴 Crítico | U58: 1 | V58: Sin hallazgos OSCE / OEFA | W58: 0 | X58: 0 | Y58: 0 | Z58: 0 | AA58: 0 | AB58: 0 | AC58: 0 | AD58: 0 | AE58: 0 | AF58: 0 | AG58: 0 | AH58: 0 | AI58: 0 | AJ58: 0 | AK58: 0 | AL58: 0 | AM58: 0 | AN58: 0 | AO58: =IFERROR(AVERAGE(AA58,AB58,AC58,AD58,AE58,AF58,AG58,AH58,AI58,AJ58,AK58,AL58,AM58,AN58),"N/A") -> 0 | AP58: =IFERROR(AVERAGE(W58,X58,Y58,Z58)/2,"N/A") -> 0
A59: 20526514689 | B59: ASOCIACION DE PRODUCTORES AGROPECUARIOS ARTESANALES E INDUST | C59: PIURA | D59: CACAO | G59: NO | H59: nan | I59: nan | J59: BAJA DE OFICIO | K59: nan | L59: 0 | M59: =IF(E59>0,ROUND(L59/E59*100,1),0) -> 0 | N59: PENDIENTE | O59: =IF(H59="SI",1,0)*0.6+IF(I59="SI",1,0)*0.4 -> 0 | P59: PENDIENTE | S59: =IFERROR(SCORECARDS!C57,"—") -> 0 | T59: =IF(ISTEXT(S59),S59,IF(S59<34,"🔴 Crítico",IF(S59<67,"🟡 Vulnerable","🟢 Preparado"))) -> 🔴 Crítico | W59: 0 | X59: 0 | Y59: 0 | Z59: 0 | AA59: 0 | AB59: 0 | AC59: 0 | AD59: 0 | AE59: 0 | AF59: 0 | AG59: 0 | AH59: 0 | AI59: 0 | AJ59: 0 | AK59: 0 | AL59: 0 | AM59: 0 | AN59: 0 | AO59: =IFERROR(AVERAGE(AA59,AB59,AC59,AD59,AE59,AF59,AG59,AH59,AI59,AJ59,AK59,AL59,AM59,AN59),"N/A") -> 0 | AP59: =IFERROR(AVERAGE(W59,X59,Y59,Z59)/2,"N/A") -> 0
A60: 20527565376 | B60: COOPERATIVA AGRARIA CAFETALERA VALLE DE INCAHUASI | C60: APURIMAC | D60: CAFÉ | E60: 10746931 | F60: 59 | G60: SI | H60: nan | I60: nan | J60: ACTIVO | K60: nan | L60: 5373465.5 | M60: =IF(E60>0,ROUND(L60/E60*100,1),0) -> 50 | N60: PENDIENTE | O60: =IF(H60="SI",1,0)*0.6+IF(I60="SI",1,0)*0.4 -> 0 | P60: PENDIENTE | S60: =IFERROR(SCORECARDS!C58,"—") -> 0 | T60: =IF(ISTEXT(S60),S60,IF(S60<34,"🔴 Crítico",IF(S60<67,"🟡 Vulnerable","🟢 Preparado"))) -> 🔴 Crítico | U60: 1 | V60: Sin hallazgos OSCE / OEFA | W60: 1 | X60: 0 | Y60: 0 | Z60: 0 | AA60: 0 | AB60: 0 | AC60: 0 | AD60: 0 | AE60: 0 | AF60: 0 | AG60: 0 | AH60: 0 | AI60: 0 | AJ60: 0 | AK60: 0 | AL60: 0 | AM60: 0 | AN60: 0 | AO60: =IFERROR(AVERAGE(AA60,AB60,AC60,AD60,AE60,AF60,AG60,AH60,AI60,AJ60,AK60,AL60,AM60,AN60),"N/A") -> 0 | AP60: =IFERROR(AVERAGE(W60,X60,Y60,Z60)/2,"N/A") -> 0.125
A61: 20528996214 | B61: COOPERATIVA AGRARIA CAFETALERA MILAGROS - MONZON | C61: HUANUCO | D61: CAFÉ | G61: NO | H61: nan | I61: nan | J61: ACTIVO | K61: nan | L61: 0 | M61: =IF(E61>0,ROUND(L61/E61*100,1),0) -> 0 | N61: PENDIENTE | O61: =IF(H61="SI",1,0)*0.6+IF(I61="SI",1,0)*0.4 -> 0 | P61: PENDIENTE | S61: =IFERROR(SCORECARDS!C59,"—") -> 0 | T61: =IF(ISTEXT(S61),S61,IF(S61<34,"🔴 Crítico",IF(S61<67,"🟡 Vulnerable","🟢 Preparado"))) -> 🔴 Crítico | W61: 0 | X61: 0 | Y61: 0 | Z61: 0 | AA61: 0 | AB61: 0 | AC61: 0 | AD61: 0 | AE61: 0 | AF61: 0 | AG61: 0 | AH61: 0 | AI61: 0 | AJ61: 0 | AK61: 0 | AL61: 0 | AM61: 0 | AN61: 0 | AO61: =IFERROR(AVERAGE(AA61,AB61,AC61,AD61,AE61,AF61,AG61,AH61,AI61,AJ61,AK61,AL61,AM61,AN61),"N/A") -> 0 | AP61: =IFERROR(AVERAGE(W61,X61,Y61,Z61)/2,"N/A") -> 0
A62: 20529801433 | B62: OPA MARAY-ULLMA SAN LORENZO | C62: PIURA | D62: CAFÉ | G62: NO | H62: nan | I62: nan | J62: BAJA DE OFICIO | K62: nan | L62: 0 | M62: =IF(E62>0,ROUND(L62/E62*100,1),0) -> 0 | N62: PENDIENTE | O62: =IF(H62="SI",1,0)*0.6+IF(I62="SI",1,0)*0.4 -> 0 | P62: PENDIENTE | S62: =IFERROR(SCORECARDS!C60,"—") -> 0 | T62: =IF(ISTEXT(S62),S62,IF(S62<34,"🔴 Crítico",IF(S62<67,"🟡 Vulnerable","🟢 Preparado"))) -> 🔴 Crítico | W62: 0 | X62: 0 | Y62: 0 | Z62: 0 | AA62: 0 | AB62: 0 | AC62: 0 | AD62: 0 | AE62: 0 | AF62: 0 | AG62: 0 | AH62: 0 | AI62: 0 | AJ62: 0 | AK62: 0 | AL62: 0 | AM62: 0 | AN62: 0 | AO62: =IFERROR(AVERAGE(AA62,AB62,AC62,AD62,AE62,AF62,AG62,AH62,AI62,AJ62,AK62,AL62,AM62,AN62),"N/A") -> 0 | AP62: =IFERROR(AVERAGE(W62,X62,Y62,Z62)/2,"N/A") -> 0
A63: 20529822350 | B63: OPA PAPAYO - LA LAGUNA | C63: PIURA | D63: CAFÉ | G63: NO | H63: nan | I63: nan | J63: BAJA DE OFICIO | K63: nan | L63: 0 | M63: =IF(E63>0,ROUND(L63/E63*100,1),0) -> 0 | N63: PENDIENTE | O63: =IF(H63="SI",1,0)*0.6+IF(I63="SI",1,0)*0.4 -> 0 | P63: PENDIENTE | S63: =IFERROR(SCORECARDS!C61,"—") -> 0 | T63: =IF(ISTEXT(S63),S63,IF(S63<34,"🔴 Crítico",IF(S63<67,"🟡 Vulnerable","🟢 Preparado"))) -> 🔴 Crítico | W63: 0 | X63: 0 | Y63: 0 | Z63: 0 | AA63: 0 | AB63: 0 | AC63: 0 | AD63: 0 | AE63: 0 | AF63: 0 | AG63: 0 | AH63: 0 | AI63: 0 | AJ63: 0 | AK63: 0 | AL63: 0 | AM63: 0 | AN63: 0 | AO63: =IFERROR(AVERAGE(AA63,AB63,AC63,AD63,AE63,AF63,AG63,AH63,AI63,AJ63,AK63,AL63,AM63,AN63),"N/A") -> 0 | AP63: =IFERROR(AVERAGE(W63,X63,Y63,Z63)/2,"N/A") -> 0
A64: 20531405723 | B64: COOPERATIVA DE SERVICIOS MULTIPLES ADISA NARANJOS | C64: SAN MARTIN | D64: CAFÉ | E64: 0 | G64: NO | H64: nan | I64: nan | J64: ACTIVO | K64: nan | L64: 0 | M64: =IF(E64>0,ROUND(L64/E64*100,1),0) -> 0 | N64: PENDIENTE | O64: =IF(H64="SI",1,0)*0.6+IF(I64="SI",1,0)*0.4 -> 0 | P64: PENDIENTE | S64: =IFERROR(SCORECARDS!C62,"—") -> 0 | T64: =IF(ISTEXT(S64),S64,IF(S64<34,"🔴 Crítico",IF(S64<67,"🟡 Vulnerable","🟢 Preparado"))) -> 🔴 Crítico | W64: 0 | X64: 0 | Y64: 0 | Z64: 0 | AA64: 0 | AB64: 0 | AC64: 0 | AD64: 0 | AE64: 0 | AF64: 0 | AG64: 0 | AH64: 0 | AI64: 0 | AJ64: 0 | AK64: 0 | AL64: 0 | AM64: 0 | AN64: 0 | AO64: =IFERROR(AVERAGE(AA64,AB64,AC64,AD64,AE64,AF64,AG64,AH64,AI64,AJ64,AK64,AL64,AM64,AN64),"N/A") -> 0 | AP64: =IFERROR(AVERAGE(W64,X64,Y64,Z64)/2,"N/A") -> 0
A65: 20531441797 | B65: COOPERATIVA AGRARIA ALLIMA CACAO LTDA. | C65: SAN MARTIN | D65: CACAO | E65: 1984.05 | F65: 1 | G65: SI | H65: nan | I65: nan | J65: ACTIVO | K65: nan | L65: 0 | M65: =IF(E65>0,ROUND(L65/E65*100,1),0) -> 0 | N65: PENDIENTE | O65: =IF(H65="SI",1,0)*0.6+IF(I65="SI",1,0)*0.4 -> 0 | P65: PENDIENTE | S65: =IFERROR(SCORECARDS!C63,"—") -> 0 | T65: =IF(ISTEXT(S65),S65,IF(S65<34,"🔴 Crítico",IF(S65<67,"🟡 Vulnerable","🟢 Preparado"))) -> 🔴 Crítico | W65: 0 | X65: 0 | Y65: 0 | Z65: 0 | AA65: 0 | AB65: 0 | AC65: 0 | AD65: 0 | AE65: 0 | AF65: 0 | AG65: 0 | AH65: 0 | AI65: 0 | AJ65: 0 | AK65: 0 | AL65: 0 | AM65: 0 | AN65: 0 | AO65: =IFERROR(AVERAGE(AA65,AB65,AC65,AD65,AE65,AF65,AG65,AH65,AI65,AJ65,AK65,AL65,AM65,AN65),"N/A") -> 0 | AP65: =IFERROR(AVERAGE(W65,X65,Y65,Z65)/2,"N/A") -> 0
A66: 20534524774 | B66: COOPERATIVA AGRARIA TROPICAL ECOLOGICA DE KIMBIRI | C66: CUSCO | D66: CAFÉ | G66: NO | H66: nan | I66: nan | J66: ACTIVO | K66: nan | L66: 0 | M66: =IF(E66>0,ROUND(L66/E66*100,1),0) -> 0 | N66: PENDIENTE | O66: =IF(H66="SI",1,0)*0.6+IF(I66="SI",1,0)*0.4 -> 0 | P66: PENDIENTE | S66: =IFERROR(SCORECARDS!C64,"—") -> 0 | T66: =IF(ISTEXT(S66),S66,IF(S66<34,"🔴 Crítico",IF(S66<67,"🟡 Vulnerable","🟢 Preparado"))) -> 🔴 Crítico | W66: 0 | X66: 0 | Y66: 0 | Z66: 0 | AA66: 0 | AB66: 0 | AC66: 0 | AD66: 0 | AE66: 0 | AF66: 0 | AG66: 0 | AH66: 0 | AI66: 0 | AJ66: 0 | AK66: 0 | AL66: 0 | AM66: 0 | AN66: 0 | AO66: =IFERROR(AVERAGE(AA66,AB66,AC66,AD66,AE66,AF66,AG66,AH66,AI66,AJ66,AK66,AL66,AM66,AN66),"N/A") -> 0 | AP66: =IFERROR(AVERAGE(W66,X66,Y66,Z66)/2,"N/A") -> 0
A67: 20539205600 | B67: ASOCIACION DE PRODUCTORES Y EXPORTADORES DE CAFE RODRIGUEZ D | C67: AMAZONAS | D67: CAFÉ | G67: NO | H67: nan | I67: nan | J67: ACTIVO | K67: nan | L67: 0 | M67: =IF(E67>0,ROUND(L67/E67*100,1),0) -> 0 | N67: PENDIENTE | O67: =IF(H67="SI",1,0)*0.6+IF(I67="SI",1,0)*0.4 -> 0 | P67: PENDIENTE | S67: =IFERROR(SCORECARDS!C65,"—") -> 0 | T67: =IF(ISTEXT(S67),S67,IF(S67<34,"🔴 Crítico",IF(S67<67,"🟡 Vulnerable","🟢 Preparado"))) -> 🔴 Crítico | W67: 0 | X67: 0 | Y67: 0 | Z67: 0 | AA67: 0 | AB67: 0 | AC67: 0 | AD67: 0 | AE67: 0 | AF67: 0 | AG67: 0 | AH67: 0 | AI67: 0 | AJ67: 0 | AK67: 0 | AL67: 0 | AM67: 0 | AN67: 0 | AO67: =IFERROR(AVERAGE(AA67,AB67,AC67,AD67,AE67,AF67,AG67,AH67,AI67,AJ67,AK67,AL67,AM67,AN67),"N/A") -> 0 | AP67: =IFERROR(AVERAGE(W67,X67,Y67,Z67)/2,"N/A") -> 0
A68: 20539241665 | B68: ASOCIACION DE PRODUCTORES DE CAFES ORGANICOS Y CAFES ESPECIA | C68: AMAZONAS | D68: CAFÉ | G68: NO | H68: nan | I68: nan | J68: ACTIVO | K68: nan | L68: 0 | M68: =IF(E68>0,ROUND(L68/E68*100,1),0) -> 0 | N68: PENDIENTE | O68: =IF(H68="SI",1,0)*0.6+IF(I68="SI",1,0)*0.4 -> 0 | P68: PENDIENTE | S68: =IFERROR(SCORECARDS!C66,"—") -> 0 | T68: =IF(ISTEXT(S68),S68,IF(S68<34,"🔴 Crítico",IF(S68<67,"🟡 Vulnerable","🟢 Preparado"))) -> 🔴 Crítico | W68: 0 | X68: 0 | Y68: 0 | Z68: 0 | AA68: 0 | AB68: 0 | AC68: 0 | AD68: 0 | AE68: 0 | AF68: 0 | AG68: 0 | AH68: 0 | AI68: 0 | AJ68: 0 | AK68: 0 | AL68: 0 | AM68: 0 | AN68: 0 | AO68: =IFERROR(AVERAGE(AA68,AB68,AC68,AD68,AE68,AF68,AG68,AH68,AI68,AJ68,AK68,AL68,AM68,AN68),"N/A") -> 0 | AP68: =IFERROR(AVERAGE(W68,X68,Y68,Z68)/2,"N/A") -> 0
A69: 20539280644 | B69: ASOCIACION DE PEQUEÑOS AGRICULTORES PARA LA PRODUCCION ECOLO | C69: LAMBAYEQUE | D69: CAFÉ | G69: NO | H69: nan | I69: nan | J69: BAJA DE OFICIO | K69: nan | L69: 0 | M69: =IF(E69>0,ROUND(L69/E69*100,1),0) -> 0 | N69: PENDIENTE | O69: =IF(H69="SI",1,0)*0.6+IF(I69="SI",1,0)*0.4 -> 0 | P69: PENDIENTE | S69: =IFERROR(SCORECARDS!C67,"—") -> 0 | T69: =IF(ISTEXT(S69),S69,IF(S69<34,"🔴 Crítico",IF(S69<67,"🟡 Vulnerable","🟢 Preparado"))) -> 🔴 Crítico | W69: 0 | X69: 0 | Y69: 0 | Z69: 0 | AA69: 0 | AB69: 0 | AC69: 0 | AD69: 0 | AE69: 0 | AF69: 0 | AG69: 0 | AH69: 0 | AI69: 0 | AJ69: 0 | AK69: 0 | AL69: 0 | AM69: 0 | AN69: 0 | AO69: =IFERROR(AVERAGE(AA69,AB69,AC69,AD69,AE69,AF69,AG69,AH69,AI69,AJ69,AK69,AL69,AM69,AN69),"N/A") -> 0 | AP69: =IFERROR(AVERAGE(W69,X69,Y69,Z69)/2,"N/A") -> 0
A70: 20542209951 | B70: COOPERATIVA AGRARIA VALLE GRANDE | C70: SAN MARTIN | D70: CAFÉ | E70: 13246409 | F70: 46 | G70: SI | H70: Si | I70: Si | J70: ACTIVO | K70: 1 | L70: 7878141.7 | M70: =IF(E70>0,ROUND(L70/E70*100,1),0) -> 59.5 | N70: PENDIENTE | O70: =IF(H70="SI",1,0)*0.6+IF(I70="SI",1,0)*0.4 -> 0 | P70: PENDIENTE | Q70: 622 | R70: 4031 | S70: =IFERROR(SCORECARDS!C68,"—") -> 0 | T70: =IF(ISTEXT(S70),S70,IF(S70<34,"🔴 Crítico",IF(S70<67,"🟡 Vulnerable","🟢 Preparado"))) -> 🔴 Crítico | U70: 1 | V70: Sin hallazgos OSCE / OEFA | W70: 1 | X70: 0 | Y70: 0 | Z70: 0 | AA70: 0 | AB70: 0 | AC70: 0 | AD70: 0 | AE70: 0 | AF70: 0 | AG70: 0 | AH70: 0 | AI70: 0 | AJ70: 0 | AK70: 0 | AL70: 0 | AM70: 0 | AN70: 0 | AO70: =IFERROR(AVERAGE(AA70,AB70,AC70,AD70,AE70,AF70,AG70,AH70,AI70,AJ70,AK70,AL70,AM70,AN70),"N/A") -> 0 | AP70: =IFERROR(AVERAGE(W70,X70,Y70,Z70)/2,"N/A") -> 0.125
A71: 20542251990 | B71: ASOCIACION DE MUJERES EMPRENDEDORAS DE NUEVO PROGRESO | C71: SAN MARTIN | D71: CACAO | G71: NO | H71: nan | I71: nan | J71: ACTIVO | K71: nan | L71: 0 | M71: =IF(E71>0,ROUND(L71/E71*100,1),0) -> 0 | N71: PENDIENTE | O71: =IF(H71="SI",1,0)*0.6+IF(I71="SI",1,0)*0.4 -> 0 | P71: PENDIENTE | S71: =IFERROR(SCORECARDS!C69,"—") -> 0 | T71: =IF(ISTEXT(S71),S71,IF(S71<34,"🔴 Crítico",IF(S71<67,"🟡 Vulnerable","🟢 Preparado"))) -> 🔴 Crítico | W71: 0 | X71: 0 | Y71: 0 | Z71: 0 | AA71: 0 | AB71: 0 | AC71: 0 | AD71: 0 | AE71: 0 | AF71: 0 | AG71: 0 | AH71: 0 | AI71: 0 | AJ71: 0 | AK71: 0 | AL71: 0 | AM71: 0 | AN71: 0 | AO71: =IFERROR(AVERAGE(AA71,AB71,AC71,AD71,AE71,AF71,AG71,AH71,AI71,AJ71,AK71,AL71,AM71,AN71),"N/A") -> 0 | AP71: =IFERROR(AVERAGE(W71,X71,Y71,Z71)/2,"N/A") -> 0
A72: 20542257416 | B72: EMPRESA INDUSTRIAL ORO VERDE SOCIEDAD ANONIMA CERRADA | C72: SAN MARTIN | D72: CACAO | E72: 2826075 | F72: 12 | G72: SI | H72: nan | I72: nan | J72: ACTIVO | K72: nan | L72: 1413037.5 | M72: =IF(E72>0,ROUND(L72/E72*100,1),0) -> 50 | N72: PENDIENTE | O72: =IF(H72="SI",1,0)*0.6+IF(I72="SI",1,0)*0.4 -> 0 | P72: PENDIENTE | S72: =IFERROR(SCORECARDS!C70,"—") -> 0 | T72: =IF(ISTEXT(S72),S72,IF(S72<34,"🔴 Crítico",IF(S72<67,"🟡 Vulnerable","🟢 Preparado"))) -> 🔴 Crítico | U72: 1 | V72: Sin hallazgos OSCE / OEFA | W72: 1 | X72: 0 | Y72: 0 | Z72: 0 | AA72: 0 | AB72: 0 | AC72: 0 | AD72: 0 | AE72: 0 | AF72: 0 | AG72: 0 | AH72: 0 | AI72: 0 | AJ72: 0 | AK72: 0 | AL72: 0 | AM72: 0 | AN72: 0 | AO72: =IFERROR(AVERAGE(AA72,AB72,AC72,AD72,AE72,AF72,AG72,AH72,AI72,AJ72,AK72,AL72,AM72,AN72),"N/A") -> 0 | AP72: =IFERROR(AVERAGE(W72,X72,Y72,Z72)/2,"N/A") -> 0.125
A73: 20542264544 | B73: COOPERATIVA AGRARIA VALLE DEL BIAVO LTDA | C73: SAN MARTIN | D73: CAFÉ | E73: 1187600.5 | F73: 6 | G73: SI | H73: PE- | I73: FLO | J73: ACTIVO | K73: 1 | L73: 1187600.5 | M73: =IF(E73>0,ROUND(L73/E73*100,1),0) -> 100 | N73: PENDIENTE | O73: =IF(H73="SI",1,0)*0.6+IF(I73="SI",1,0)*0.4 -> 0 | P73: PENDIENTE | Q73: 416 | R73: 1248 | S73: =IFERROR(SCORECARDS!C71,"—") -> 0 | T73: =IF(ISTEXT(S73),S73,IF(S73<34,"🔴 Crítico",IF(S73<67,"🟡 Vulnerable","🟢 Preparado"))) -> 🔴 Crítico | U73: 1 | V73: Sin hallazgos OSCE / OEFA | W73: 1 | X73: 0 | Y73: 0 | Z73: 0 | AA73: 0 | AB73: 0 | AC73: 0 | AD73: 0 | AE73: 0 | AF73: 0 | AG73: 0 | AH73: 0 | AI73: 0 | AJ73: 0 | AK73: 0 | AL73: 0 | AM73: 0 | AN73: 0 | AO73: =IFERROR(AVERAGE(AA73,AB73,AC73,AD73,AE73,AF73,AG73,AH73,AI73,AJ73,AK73,AL73,AM73,AN73),"N/A") -> 0 | AP73: =IFERROR(AVERAGE(W73,X73,Y73,Z73)/2,"N/A") -> 0.125
A74: 20542289024 | B74: CUENCAS DEL HUALLAGA ASOCIACION DE PRODUCTORES AGROPECUARIOS | C74: SAN MARTIN | D74: CACAO | E74: 24285432 | F74: 111 | G74: SI | H74: nan | I74: nan | J74: ACTIVO | K74: nan | L74: 12142716 | M74: =IF(E74>0,ROUND(L74/E74*100,1),0) -> 50 | N74: PENDIENTE | O74: =IF(H74="SI",1,0)*0.6+IF(I74="SI",1,0)*0.4 -> 0 | P74: PENDIENTE | S74: =IFERROR(SCORECARDS!C72,"—") -> 0 | T74: =IF(ISTEXT(S74),S74,IF(S74<34,"🔴 Crítico",IF(S74<67,"🟡 Vulnerable","🟢 Preparado"))) -> 🔴 Crítico | U74: 1 | V74: Sin hallazgos OSCE / OEFA | W74: 1 | X74: 0 | Y74: 0 | Z74: 0 | AA74: 0 | AB74: 0 | AC74: 0 | AD74: 0 | AE74: 0 | AF74: 0 | AG74: 0 | AH74: 0 | AI74: 0 | AJ74: 0 | AK74: 0 | AL74: 0 | AM74: 0 | AN74: 0 | AO74: =IFERROR(AVERAGE(AA74,AB74,AC74,AD74,AE74,AF74,AG74,AH74,AI74,AJ74,AK74,AL74,AM74,AN74),"N/A") -> 0 | AP74: =IFERROR(AVERAGE(W74,X74,Y74,Z74)/2,"N/A") -> 0.125
A75: 20542299330 | B75: ASOCIACION DE PRODUCTORES AGROPECUARIOS DE SHUCUSHYACU FLOR | C75: LORETO | D75: CACAO | G75: NO | H75: nan | I75: nan | J75: ACTIVO | K75: nan | L75: 0 | M75: =IF(E75>0,ROUND(L75/E75*100,1),0) -> 0 | N75: PENDIENTE | O75: =IF(H75="SI",1,0)*0.6+IF(I75="SI",1,0)*0.4 -> 0 | P75: PENDIENTE | S75: =IFERROR(SCORECARDS!C73,"—") -> 0 | T75: =IF(ISTEXT(S75),S75,IF(S75<34,"🔴 Crítico",IF(S75<67,"🟡 Vulnerable","🟢 Preparado"))) -> 🔴 Crítico | W75: 0 | X75: 0 | Y75: 0 | Z75: 0 | AA75: 0 | AB75: 0 | AC75: 0 | AD75: 0 | AE75: 0 | AF75: 0 | AG75: 0 | AH75: 0 | AI75: 0 | AJ75: 0 | AK75: 0 | AL75: 0 | AM75: 0 | AN75: 0 | AO75: =IFERROR(AVERAGE(AA75,AB75,AC75,AD75,AE75,AF75,AG75,AH75,AI75,AJ75,AK75,AL75,AM75,AN75),"N/A") -> 0 | AP75: =IFERROR(AVERAGE(W75,X75,Y75,Z75)/2,"N/A") -> 0
A76: 20542311569 | B76: COOPERATIVA AGRARIA ACHUAR SHAKAIM LTDA | C76: LORETO | D76: CACAO | G76: NO | H76: nan | I76: nan | J76: ACTIVO | K76: nan | L76: 0 | M76: =IF(E76>0,ROUND(L76/E76*100,1),0) -> 0 | N76: PENDIENTE | O76: =IF(H76="SI",1,0)*0.6+IF(I76="SI",1,0)*0.4 -> 0 | P76: PENDIENTE | S76: =IFERROR(SCORECARDS!C74,"—") -> 0 | T76: =IF(ISTEXT(S76),S76,IF(S76<34,"🔴 Crítico",IF(S76<67,"🟡 Vulnerable","🟢 Preparado"))) -> 🔴 Crítico | W76: 0 | X76: 0 | Y76: 0 | Z76: 0 | AA76: 0 | AB76: 0 | AC76: 0 | AD76: 0 | AE76: 0 | AF76: 0 | AG76: 0 | AH76: 0 | AI76: 0 | AJ76: 0 | AK76: 0 | AL76: 0 | AM76: 0 | AN76: 0 | AO76: =IFERROR(AVERAGE(AA76,AB76,AC76,AD76,AE76,AF76,AG76,AH76,AI76,AJ76,AK76,AL76,AM76,AN76),"N/A") -> 0 | AP76: =IFERROR(AVERAGE(W76,X76,Y76,Z76)/2,"N/A") -> 0
A77: 20542380455 | B77: COOPERATIVA AGRARIA ECOFOREST | C77: CAJAMARCA | D77: CAFÉ | E77: 16891006 | F77: 81 | G77: SI | H77: nan | I77: nan | J77: ACTIVO | K77: nan | L77: 8445503.2 | M77: =IF(E77>0,ROUND(L77/E77*100,1),0) -> 50 | N77: PENDIENTE | O77: =IF(H77="SI",1,0)*0.6+IF(I77="SI",1,0)*0.4 -> 0 | P77: PENDIENTE | S77: =IFERROR(SCORECARDS!C75,"—") -> 0 | T77: =IF(ISTEXT(S77),S77,IF(S77<34,"🔴 Crítico",IF(S77<67,"🟡 Vulnerable","🟢 Preparado"))) -> 🔴 Crítico | U77: 1 | V77: Sin hallazgos OSCE / OEFA | W77: 1 | X77: 0 | Y77: 0 | Z77: 0 | AA77: 0 | AB77: 0 | AC77: 0 | AD77: 0 | AE77: 0 | AF77: 0 | AG77: 0 | AH77: 0 | AI77: 0 | AJ77: 0 | AK77: 0 | AL77: 0 | AM77: 0 | AN77: 0 | AO77: =IFERROR(AVERAGE(AA77,AB77,AC77,AD77,AE77,AF77,AG77,AH77,AI77,AJ77,AK77,AL77,AM77,AN77),"N/A") -> 0 | AP77: =IFERROR(AVERAGE(W77,X77,Y77,Z77)/2,"N/A") -> 0.125
A78: 20542482886 | B78: COOPERATIVA AGROINDUSTRIAL APCCA | C78: HUANUCO | D78: CACAO | G78: NO | H78: nan | I78: nan | J78: SUSPENSION TEMPORAL | K78: nan | L78: 0 | M78: =IF(E78>0,ROUND(L78/E78*100,1),0) -> 0 | N78: PENDIENTE | O78: =IF(H78="SI",1,0)*0.6+IF(I78="SI",1,0)*0.4 -> 0 | P78: PENDIENTE | S78: =IFERROR(SCORECARDS!C76,"—") -> 0 | T78: =IF(ISTEXT(S78),S78,IF(S78<34,"🔴 Crítico",IF(S78<67,"🟡 Vulnerable","🟢 Preparado"))) -> 🔴 Crítico | W78: 0 | X78: 0 | Y78: 0 | Z78: 0 | AA78: 0 | AB78: 0 | AC78: 0 | AD78: 0 | AE78: 0 | AF78: 0 | AG78: 0 | AH78: 0 | AI78: 0 | AJ78: 0 | AK78: 0 | AL78: 0 | AM78: 0 | AN78: 0 | AO78: =IFERROR(AVERAGE(AA78,AB78,AC78,AD78,AE78,AF78,AG78,AH78,AI78,AJ78,AK78,AL78,AM78,AN78),"N/A") -> 0 | AP78: =IFERROR(AVERAGE(W78,X78,Y78,Z78)/2,"N/A") -> 0
A79: 20542825163 | B79: COOPERATIVA AGRARIA CACAO FINO AGROBOSQUE | C79: MADRE DE DIOS | D79: CACAO | E79: 0 | G79: NO | H79: nan | I79: nan | J79: ACTIVO | K79: nan | L79: 0 | M79: =IF(E79>0,ROUND(L79/E79*100,1),0) -> 0 | N79: PENDIENTE | O79: =IF(H79="SI",1,0)*0.6+IF(I79="SI",1,0)*0.4 -> 0 | P79: PENDIENTE | S79: =IFERROR(SCORECARDS!C77,"—") -> 0 | T79: =IF(ISTEXT(S79),S79,IF(S79<34,"🔴 Crítico",IF(S79<67,"🟡 Vulnerable","🟢 Preparado"))) -> 🔴 Crítico | W79: 0 | X79: 0 | Y79: 0 | Z79: 0 | AA79: 0 | AB79: 0 | AC79: 0 | AD79: 0 | AE79: 0 | AF79: 0 | AG79: 0 | AH79: 0 | AI79: 0 | AJ79: 0 | AK79: 0 | AL79: 0 | AM79: 0 | AN79: 0 | AO79: =IFERROR(AVERAGE(AA79,AB79,AC79,AD79,AE79,AF79,AG79,AH79,AI79,AJ79,AK79,AL79,AM79,AN79),"N/A") -> 0 | AP79: =IFERROR(AVERAGE(W79,X79,Y79,Z79)/2,"N/A") -> 0
A80: 20561140091 | B80: COOPERATIVA AGRARIA ECOLOGICA CAFETALERA DE LONYA GRANDE | C80: AMAZONAS | D80: CAFÉ | E80: 0 | G80: NO | H80: SI( | I80: NO | J80: SUSPENSION TEMPORAL | K80: 0.5 | L80: 0 | M80: =IF(E80>0,ROUND(L80/E80*100,1),0) -> 0 | N80: PENDIENTE | O80: =IF(H80="SI",1,0)*0.6+IF(I80="SI",1,0)*0.4 -> 0 | P80: PENDIENTE | Q80: 351 | R80: 1045.6 | S80: =IFERROR(SCORECARDS!C78,"—") -> 0 | T80: =IF(ISTEXT(S80),S80,IF(S80<34,"🔴 Crítico",IF(S80<67,"🟡 Vulnerable","🟢 Preparado"))) -> 🔴 Crítico | W80: 1 | X80: 0 | Y80: 0 | Z80: 0 | AA80: 0 | AB80: 0 | AC80: 0 | AD80: 0 | AE80: 0 | AF80: 0 | AG80: 0 | AH80: 0 | AI80: 0 | AJ80: 0 | AK80: 0 | AL80: 0 | AM80: 0 | AN80: 0 | AO80: =IFERROR(AVERAGE(AA80,AB80,AC80,AD80,AE80,AF80,AG80,AH80,AI80,AJ80,AK80,AL80,AM80,AN80),"N/A") -> 0 | AP80: =IFERROR(AVERAGE(W80,X80,Y80,Z80)/2,"N/A") -> 0.125
A81: 20564032485 | B81: ASOCIACION DE PRODUCTORES ECOLOGICOS DE CACAO MEDIO URUBAMBA | C81: CUSCO | D81: CACAO | E81: 0 | G81: NO | H81: nan | I81: nan | J81: ACTIVO | K81: nan | L81: 0 | M81: =IF(E81>0,ROUND(L81/E81*100,1),0) -> 0 | N81: PENDIENTE | O81: =IF(H81="SI",1,0)*0.6+IF(I81="SI",1,0)*0.4 -> 0 | P81: PENDIENTE | S81: =IFERROR(SCORECARDS!C79,"—") -> 0 | T81: =IF(ISTEXT(S81),S81,IF(S81<34,"🔴 Crítico",IF(S81<67,"🟡 Vulnerable","🟢 Preparado"))) -> 🔴 Crítico | W81: 0 | X81: 0 | Y81: 0 | Z81: 0 | AA81: 0 | AB81: 0 | AC81: 0 | AD81: 0 | AE81: 0 | AF81: 0 | AG81: 0 | AH81: 0 | AI81: 0 | AJ81: 0 | AK81: 0 | AL81: 0 | AM81: 0 | AN81: 0 | AO81: =IFERROR(AVERAGE(AA81,AB81,AC81,AD81,AE81,AF81,AG81,AH81,AI81,AJ81,AK81,AL81,AM81,AN81),"N/A") -> 0 | AP81: =IFERROR(AVERAGE(W81,X81,Y81,Z81)/2,"N/A") -> 0
A82: 20568071281 | B82: COOPERATIVA AGRARIA CAFETALERA CEPRO YANESHA | C82: PASCO | D82: CAFÉ | E82: 1435723.7 | F82: 10 | G82: SI | H82: nan | I82: nan | J82: ACTIVO | K82: nan | L82: 717861.85 | M82: =IF(E82>0,ROUND(L82/E82*100,1),0) -> 50 | N82: PENDIENTE | O82: =IF(H82="SI",1,0)*0.6+IF(I82="SI",1,0)*0.4 -> 0 | P82: PENDIENTE | S82: =IFERROR(SCORECARDS!C80,"—") -> 0 | T82: =IF(ISTEXT(S82),S82,IF(S82<34,"🔴 Crítico",IF(S82<67,"🟡 Vulnerable","🟢 Preparado"))) -> 🔴 Crítico | U82: 1 | V82: Sin hallazgos OSCE / OEFA | W82: 1 | X82: 0 | Y82: 0 | Z82: 0 | AA82: 0 | AB82: 0 | AC82: 0 | AD82: 0 | AE82: 0 | AF82: 0 | AG82: 0 | AH82: 0 | AI82: 0 | AJ82: 0 | AK82: 0 | AL82: 0 | AM82: 0 | AN82: 0 | AO82: =IFERROR(AVERAGE(AA82,AB82,AC82,AD82,AE82,AF82,AG82,AH82,AI82,AJ82,AK82,AL82,AM82,AN82),"N/A") -> 0 | AP82: =IFERROR(AVERAGE(W82,X82,Y82,Z82)/2,"N/A") -> 0.125
A83: 20568080948 | B83: CONSEJO REGULADOR DE LA DENOMINACION DE ORIGEN CAFE VILLA RI | C83: PASCO | D83: CAFÉ | G83: NO | H83: nan | I83: nan | J83: ACTIVO | K83: nan | L83: 0 | M83: =IF(E83>0,ROUND(L83/E83*100,1),0) -> 0 | N83: PENDIENTE | O83: =IF(H83="SI",1,0)*0.6+IF(I83="SI",1,0)*0.4 -> 0 | P83: PENDIENTE | S83: =IFERROR(SCORECARDS!C81,"—") -> 0 | T83: =IF(ISTEXT(S83),S83,IF(S83<34,"🔴 Crítico",IF(S83<67,"🟡 Vulnerable","🟢 Preparado"))) -> 🔴 Crítico | W83: 0 | X83: 0 | Y83: 0 | Z83: 0 | AA83: 0 | AB83: 0 | AC83: 0 | AD83: 0 | AE83: 0 | AF83: 0 | AG83: 0 | AH83: 0 | AI83: 0 | AJ83: 0 | AK83: 0 | AL83: 0 | AM83: 0 | AN83: 0 | AO83: =IFERROR(AVERAGE(AA83,AB83,AC83,AD83,AE83,AF83,AG83,AH83,AI83,AJ83,AK83,AL83,AM83,AN83),"N/A") -> 0 | AP83: =IFERROR(AVERAGE(W83,X83,Y83,Z83)/2,"N/A") -> 0
A84: 20568190450 | B84: COOPERATIVA AGRARIA KEMITO ENE LTDA. - KEMITO ENE | C84: JUNIN | D84: CACAO | E84: 113466.98 | F84: 10 | G84: SI | H84: nan | I84: nan | J84: ACTIVO | K84: nan | L84: 0 | M84: =IF(E84>0,ROUND(L84/E84*100,1),0) -> 0 | N84: PENDIENTE | O84: =IF(H84="SI",1,0)*0.6+IF(I84="SI",1,0)*0.4 -> 0 | P84: PENDIENTE | S84: =IFERROR(SCORECARDS!C82,"—") -> 0 | T84: =IF(ISTEXT(S84),S84,IF(S84<34,"🔴 Crítico",IF(S84<67,"🟡 Vulnerable","🟢 Preparado"))) -> 🔴 Crítico | W84: 0 | X84: 0 | Y84: 0 | Z84: 0 | AA84: 0 | AB84: 0 | AC84: 0 | AD84: 0 | AE84: 0 | AF84: 0 | AG84: 0 | AH84: 0 | AI84: 0 | AJ84: 0 | AK84: 0 | AL84: 0 | AM84: 0 | AN84: 0 | AO84: =IFERROR(AVERAGE(AA84,AB84,AC84,AD84,AE84,AF84,AG84,AH84,AI84,AJ84,AK84,AL84,AM84,AN84),"N/A") -> 0 | AP84: =IFERROR(AVERAGE(W84,X84,Y84,Z84)/2,"N/A") -> 0
A85: 20568194951 | B85: ASOCIACION DE PRODUCTORES AGROSOSTENIBLES VILLA ECOLOGICA PE | C85: JUNIN | D85: CAFÉ | E85: 5355025.2 | F85: 27 | G85: SI | H85: nan | I85: nan | J85: ACTIVO | K85: nan | L85: 2677512.6 | M85: =IF(E85>0,ROUND(L85/E85*100,1),0) -> 50 | N85: PENDIENTE | O85: =IF(H85="SI",1,0)*0.6+IF(I85="SI",1,0)*0.4 -> 0 | P85: PENDIENTE | S85: =IFERROR(SCORECARDS!C83,"—") -> 0 | T85: =IF(ISTEXT(S85),S85,IF(S85<34,"🔴 Crítico",IF(S85<67,"🟡 Vulnerable","🟢 Preparado"))) -> 🔴 Crítico | U85: 1 | V85: Sin hallazgos OSCE / OEFA | W85: 1 | X85: 0 | Y85: 0 | Z85: 0 | AA85: 0 | AB85: 0 | AC85: 0 | AD85: 0 | AE85: 0 | AF85: 0 | AG85: 0 | AH85: 0 | AI85: 0 | AJ85: 0 | AK85: 0 | AL85: 0 | AM85: 0 | AN85: 0 | AO85: =IFERROR(AVERAGE(AA85,AB85,AC85,AD85,AE85,AF85,AG85,AH85,AI85,AJ85,AK85,AL85,AM85,AN85),"N/A") -> 0 | AP85: =IFERROR(AVERAGE(W85,X85,Y85,Z85)/2,"N/A") -> 0.125
A86: 20568428375 | B86: COOPERATIVA AGRARIA ASHANINKA DEL VALLE PICHIS | C86: PASCO | D86: CACAO | G86: NO | H86: nan | I86: nan | J86: ACTIVO | K86: nan | L86: 0 | M86: =IF(E86>0,ROUND(L86/E86*100,1),0) -> 0 | N86: PENDIENTE | O86: =IF(H86="SI",1,0)*0.6+IF(I86="SI",1,0)*0.4 -> 0 | P86: PENDIENTE | S86: =IFERROR(SCORECARDS!C84,"—") -> 0 | T86: =IF(ISTEXT(S86),S86,IF(S86<34,"🔴 Crítico",IF(S86<67,"🟡 Vulnerable","🟢 Preparado"))) -> 🔴 Crítico | W86: 0 | X86: 0 | Y86: 0 | Z86: 0 | AA86: 0 | AB86: 0 | AC86: 0 | AD86: 0 | AE86: 0 | AF86: 0 | AG86: 0 | AH86: 0 | AI86: 0 | AJ86: 0 | AK86: 0 | AL86: 0 | AM86: 0 | AN86: 0 | AO86: =IFERROR(AVERAGE(AA86,AB86,AC86,AD86,AE86,AF86,AG86,AH86,AI86,AJ86,AK86,AL86,AM86,AN86),"N/A") -> 0 | AP86: =IFERROR(AVERAGE(W86,X86,Y86,Z86)/2,"N/A") -> 0
A87: 20568549083 | B87: COOPERATIVA AGRARIA INDUSTRIAL APASC SANCORE-PALCAZU LTDA | C87: PASCO | D87: CACAO | G87: NO | H87: nan | I87: nan | J87: ACTIVO | K87: nan | L87: 0 | M87: =IF(E87>0,ROUND(L87/E87*100,1),0) -> 0 | N87: PENDIENTE | O87: =IF(H87="SI",1,0)*0.6+IF(I87="SI",1,0)*0.4 -> 0 | P87: PENDIENTE | S87: =IFERROR(SCORECARDS!C85,"—") -> 0 | T87: =IF(ISTEXT(S87),S87,IF(S87<34,"🔴 Crítico",IF(S87<67,"🟡 Vulnerable","🟢 Preparado"))) -> 🔴 Crítico | W87: 0 | X87: 0 | Y87: 0 | Z87: 0 | AA87: 0 | AB87: 0 | AC87: 0 | AD87: 0 | AE87: 0 | AF87: 0 | AG87: 0 | AH87: 0 | AI87: 0 | AJ87: 0 | AK87: 0 | AL87: 0 | AM87: 0 | AN87: 0 | AO87: =IFERROR(AVERAGE(AA87,AB87,AC87,AD87,AE87,AF87,AG87,AH87,AI87,AJ87,AK87,AL87,AM87,AN87),"N/A") -> 0 | AP87: =IFERROR(AVERAGE(W87,X87,Y87,Z87)/2,"N/A") -> 0
A88: 20568560133 | B88: COOPERATIVA AGRARIA ECOLOGICO ALTO PALCAZU LAGUNA RAYA | C88: PASCO | D88: CACAO | G88: NO | H88: nan | I88: nan | J88: ACTIVO | K88: nan | L88: 0 | M88: =IF(E88>0,ROUND(L88/E88*100,1),0) -> 0 | N88: PENDIENTE | O88: =IF(H88="SI",1,0)*0.6+IF(I88="SI",1,0)*0.4 -> 0 | P88: PENDIENTE | S88: =IFERROR(SCORECARDS!C86,"—") -> 0 | T88: =IF(ISTEXT(S88),S88,IF(S88<34,"🔴 Crítico",IF(S88<67,"🟡 Vulnerable","🟢 Preparado"))) -> 🔴 Crítico | W88: 0 | X88: 0 | Y88: 0 | Z88: 0 | AA88: 0 | AB88: 0 | AC88: 0 | AD88: 0 | AE88: 0 | AF88: 0 | AG88: 0 | AH88: 0 | AI88: 0 | AJ88: 0 | AK88: 0 | AL88: 0 | AM88: 0 | AN88: 0 | AO88: =IFERROR(AVERAGE(AA88,AB88,AC88,AD88,AE88,AF88,AG88,AH88,AI88,AJ88,AK88,AL88,AM88,AN88),"N/A") -> 0 | AP88: =IFERROR(AVERAGE(W88,X88,Y88,Z88)/2,"N/A") -> 0
A89: 20568567731 | B89: COOPERATIVA AGRARIA VILLA RICA GOLDEN COFFEE LTDA. | C89: PASCO | D89: CAFÉ | E89: 0 | G89: NO | H89: nan | I89: nan | J89: ACTIVO | K89: nan | L89: 0 | M89: =IF(E89>0,ROUND(L89/E89*100,1),0) -> 0 | N89: PENDIENTE | O89: =IF(H89="SI",1,0)*0.6+IF(I89="SI",1,0)*0.4 -> 0 | P89: PENDIENTE | S89: =IFERROR(SCORECARDS!C87,"—") -> 0 | T89: =IF(ISTEXT(S89),S89,IF(S89<34,"🔴 Crítico",IF(S89<67,"🟡 Vulnerable","🟢 Preparado"))) -> 🔴 Crítico | W89: 0 | X89: 0 | Y89: 0 | Z89: 0 | AA89: 0 | AB89: 0 | AC89: 0 | AD89: 0 | AE89: 0 | AF89: 0 | AG89: 0 | AH89: 0 | AI89: 0 | AJ89: 0 | AK89: 0 | AL89: 0 | AM89: 0 | AN89: 0 | AO89: =IFERROR(AVERAGE(AA89,AB89,AC89,AD89,AE89,AF89,AG89,AH89,AI89,AJ89,AK89,AL89,AM89,AN89),"N/A") -> 0 | AP89: =IFERROR(AVERAGE(W89,X89,Y89,Z89)/2,"N/A") -> 0
A90: 20568609833 | B90: ASOCIACION DE MUJERES PRODUCTORAS ARTESANAS CACAO JENTARI - | C90: JUNIN | D90: CACAO | G90: NO | H90: nan | I90: nan | J90: BAJA DE OFICIO | K90: nan | L90: 0 | M90: =IF(E90>0,ROUND(L90/E90*100,1),0) -> 0 | N90: PENDIENTE | O90: =IF(H90="SI",1,0)*0.6+IF(I90="SI",1,0)*0.4 -> 0 | P90: PENDIENTE | S90: =IFERROR(SCORECARDS!C88,"—") -> 0 | T90: =IF(ISTEXT(S90),S90,IF(S90<34,"🔴 Crítico",IF(S90<67,"🟡 Vulnerable","🟢 Preparado"))) -> 🔴 Crítico | W90: 0 | X90: 0 | Y90: 0 | Z90: 0 | AA90: 0 | AB90: 0 | AC90: 0 | AD90: 0 | AE90: 0 | AF90: 0 | AG90: 0 | AH90: 0 | AI90: 0 | AJ90: 0 | AK90: 0 | AL90: 0 | AM90: 0 | AN90: 0 | AO90: =IFERROR(AVERAGE(AA90,AB90,AC90,AD90,AE90,AF90,AG90,AH90,AI90,AJ90,AK90,AL90,AM90,AN90),"N/A") -> 0 | AP90: =IFERROR(AVERAGE(W90,X90,Y90,Z90)/2,"N/A") -> 0
A91: 20568962282 | B91: ASOCIACIÓN DE PRODUCTORES CENTRO COFFEE | C91: JUNIN | D91: CAFÉ | E91: 0 | G91: NO | H91: nan | I91: nan | J91: SUSPENSION TEMPORAL | K91: nan | L91: 0 | M91: =IF(E91>0,ROUND(L91/E91*100,1),0) -> 0 | N91: PENDIENTE | O91: =IF(H91="SI",1,0)*0.6+IF(I91="SI",1,0)*0.4 -> 0 | P91: PENDIENTE | S91: =IFERROR(SCORECARDS!C89,"—") -> 0 | T91: =IF(ISTEXT(S91),S91,IF(S91<34,"🔴 Crítico",IF(S91<67,"🟡 Vulnerable","🟢 Preparado"))) -> 🔴 Crítico | W91: 0 | X91: 0 | Y91: 0 | Z91: 0 | AA91: 0 | AB91: 0 | AC91: 0 | AD91: 0 | AE91: 0 | AF91: 0 | AG91: 0 | AH91: 0 | AI91: 0 | AJ91: 0 | AK91: 0 | AL91: 0 | AM91: 0 | AN91: 0 | AO91: =IFERROR(AVERAGE(AA91,AB91,AC91,AD91,AE91,AF91,AG91,AH91,AI91,AJ91,AK91,AL91,AM91,AN91),"N/A") -> 0 | AP91: =IFERROR(AVERAGE(W91,X91,Y91,Z91)/2,"N/A") -> 0
A92: 20570706927 | B92: COOPERATIVA AGRARIA RUTAS DEL INCA | C92: CAJAMARCA | D92: CAFÉ | E92: 9585341.8 | F92: 58 | G92: SI | H92: nan | I92: nan | J92: ACTIVO | K92: nan | L92: 4792670.9 | M92: =IF(E92>0,ROUND(L92/E92*100,1),0) -> 50 | N92: PENDIENTE | O92: =IF(H92="SI",1,0)*0.6+IF(I92="SI",1,0)*0.4 -> 0 | P92: PENDIENTE | S92: =IFERROR(SCORECARDS!C90,"—") -> 0 | T92: =IF(ISTEXT(S92),S92,IF(S92<34,"🔴 Crítico",IF(S92<67,"🟡 Vulnerable","🟢 Preparado"))) -> 🔴 Crítico | U92: 1 | V92: Sin hallazgos OSCE / OEFA | W92: 1 | X92: 0 | Y92: 0 | Z92: 0 | AA92: 0 | AB92: 0 | AC92: 0 | AD92: 0 | AE92: 0 | AF92: 0 | AG92: 0 | AH92: 0 | AI92: 0 | AJ92: 0 | AK92: 0 | AL92: 0 | AM92: 0 | AN92: 0 | AO92: =IFERROR(AVERAGE(AA92,AB92,AC92,AD92,AE92,AF92,AG92,AH92,AI92,AJ92,AK92,AL92,AM92,AN92),"N/A") -> 0 | AP92: =IFERROR(AVERAGE(W92,X92,Y92,Z92)/2,"N/A") -> 0.125
A93: 20572111131 | B93: ASOCIACION DE MUJERES ORGANIZADAS CHOCO WARMIS | C93: SAN MARTIN | D93: nan | G93: NO | H93: nan | I93: nan | J93: ACTIVO | K93: nan | L93: 0 | M93: =IF(E93>0,ROUND(L93/E93*100,1),0) -> 0 | N93: PENDIENTE | O93: =IF(H93="SI",1,0)*0.6+IF(I93="SI",1,0)*0.4 -> 0 | P93: PENDIENTE | S93: =IFERROR(SCORECARDS!C91,"—") -> 0 | T93: =IF(ISTEXT(S93),S93,IF(S93<34,"🔴 Crítico",IF(S93<67,"🟡 Vulnerable","🟢 Preparado"))) -> 🔴 Crítico | W93: 0 | X93: 0 | Y93: 0 | Z93: 0 | AA93: 0 | AB93: 0 | AC93: 0 | AD93: 0 | AE93: 0 | AF93: 0 | AG93: 0 | AH93: 0 | AI93: 0 | AJ93: 0 | AK93: 0 | AL93: 0 | AM93: 0 | AN93: 0 | AO93: =IFERROR(AVERAGE(AA93,AB93,AC93,AD93,AE93,AF93,AG93,AH93,AI93,AJ93,AK93,AL93,AM93,AN93),"N/A") -> 0 | AP93: =IFERROR(AVERAGE(W93,X93,Y93,Z93)/2,"N/A") -> 0
A94: 20572190251 | B94: CENTRAL DE COOPERATIVAS AGRARIAS CACAO AROMA DE TOCACHE LTDA | C94: SAN MARTIN | D94: nan | E94: 3777944.8 | F94: 14 | G94: SI | H94: nan | I94: nan | J94: ACTIVO | K94: nan | L94: 1888972.4 | M94: =IF(E94>0,ROUND(L94/E94*100,1),0) -> 50 | N94: PENDIENTE | O94: =IF(H94="SI",1,0)*0.6+IF(I94="SI",1,0)*0.4 -> 0 | P94: PENDIENTE | S94: =IFERROR(SCORECARDS!C92,"—") -> 0 | T94: =IF(ISTEXT(S94),S94,IF(S94<34,"🔴 Crítico",IF(S94<67,"🟡 Vulnerable","🟢 Preparado"))) -> 🔴 Crítico | U94: 1 | V94: Sin hallazgos OSCE / OEFA | W94: 1 | X94: 0 | Y94: 0 | Z94: 0 | AA94: 0 | AB94: 0 | AC94: 0 | AD94: 0 | AE94: 0 | AF94: 0 | AG94: 0 | AH94: 0 | AI94: 0 | AJ94: 0 | AK94: 0 | AL94: 0 | AM94: 0 | AN94: 0 | AO94: =IFERROR(AVERAGE(AA94,AB94,AC94,AD94,AE94,AF94,AG94,AH94,AI94,AJ94,AK94,AL94,AM94,AN94),"N/A") -> 0 | AP94: =IFERROR(AVERAGE(W94,X94,Y94,Z94)/2,"N/A") -> 0.125
A95: 20573049102 | B95: COOPERATIVA AGRARIA CACAOTERA PUERTO INCA | C95: HUANUCO | D95: CACAO | G95: NO | H95: nan | I95: nan | J95: ACTIVO | K95: nan | L95: 0 | M95: =IF(E95>0,ROUND(L95/E95*100,1),0) -> 0 | N95: PENDIENTE | O95: =IF(H95="SI",1,0)*0.6+IF(I95="SI",1,0)*0.4 -> 0 | P95: PENDIENTE | S95: =IFERROR(SCORECARDS!C93,"—") -> 0 | T95: =IF(ISTEXT(S95),S95,IF(S95<34,"🔴 Crítico",IF(S95<67,"🟡 Vulnerable","🟢 Preparado"))) -> 🔴 Crítico | W95: 0 | X95: 0 | Y95: 0 | Z95: 0 | AA95: 0 | AB95: 0 | AC95: 0 | AD95: 0 | AE95: 0 | AF95: 0 | AG95: 0 | AH95: 0 | AI95: 0 | AJ95: 0 | AK95: 0 | AL95: 0 | AM95: 0 | AN95: 0 | AO95: =IFERROR(AVERAGE(AA95,AB95,AC95,AD95,AE95,AF95,AG95,AH95,AI95,AJ95,AK95,AL95,AM95,AN95),"N/A") -> 0 | AP95: =IFERROR(AVERAGE(W95,X95,Y95,Z95)/2,"N/A") -> 0
A96: 20573057385 | B96: COOPERATIVA AGRARIA PARAISO | C96: HUANUCO | D96: CACAO | E96: 0 | G96: NO | H96: nan | I96: nan | J96: ACTIVO | K96: nan | L96: 0 | M96: =IF(E96>0,ROUND(L96/E96*100,1),0) -> 0 | N96: PENDIENTE | O96: =IF(H96="SI",1,0)*0.6+IF(I96="SI",1,0)*0.4 -> 0 | P96: PENDIENTE | S96: =IFERROR(SCORECARDS!C94,"—") -> 0 | T96: =IF(ISTEXT(S96),S96,IF(S96<34,"🔴 Crítico",IF(S96<67,"🟡 Vulnerable","🟢 Preparado"))) -> 🔴 Crítico | W96: 0 | X96: 0 | Y96: 0 | Z96: 0 | AA96: 0 | AB96: 0 | AC96: 0 | AD96: 0 | AE96: 0 | AF96: 0 | AG96: 0 | AH96: 0 | AI96: 0 | AJ96: 0 | AK96: 0 | AL96: 0 | AM96: 0 | AN96: 0 | AO96: =IFERROR(AVERAGE(AA96,AB96,AC96,AD96,AE96,AF96,AG96,AH96,AI96,AJ96,AK96,AL96,AM96,AN96),"N/A") -> 0 | AP96: =IFERROR(AVERAGE(W96,X96,Y96,Z96)/2,"N/A") -> 0
A97: 20573138202 | B97: ASOCIACION DE PRODUCTORES AGROPECUARIOS Y FORESTALES EL ALVA | C97: HUANUCO | D97: CACAO | G97: NO | H97: nan | I97: nan | J97: BAJA DE OFICIO | K97: nan | L97: 0 | M97: =IF(E97>0,ROUND(L97/E97*100,1),0) -> 0 | N97: PENDIENTE | O97: =IF(H97="SI",1,0)*0.6+IF(I97="SI",1,0)*0.4 -> 0 | P97: PENDIENTE | S97: =IFERROR(SCORECARDS!C95,"—") -> 0 | T97: =IF(ISTEXT(S97),S97,IF(S97<34,"🔴 Crítico",IF(S97<67,"🟡 Vulnerable","🟢 Preparado"))) -> 🔴 Crítico | W97: 0 | X97: 0 | Y97: 0 | Z97: 0 | AA97: 0 | AB97: 0 | AC97: 0 | AD97: 0 | AE97: 0 | AF97: 0 | AG97: 0 | AH97: 0 | AI97: 0 | AJ97: 0 | AK97: 0 | AL97: 0 | AM97: 0 | AN97: 0 | AO97: =IFERROR(AVERAGE(AA97,AB97,AC97,AD97,AE97,AF97,AG97,AH97,AI97,AJ97,AK97,AL97,AM97,AN97),"N/A") -> 0 | AP97: =IFERROR(AVERAGE(W97,X97,Y97,Z97)/2,"N/A") -> 0
A98: 20573260008 | B98: COOPERATIVA AGRARIA AUCAYACU | C98: HUANUCO | D98: CACAO | G98: NO | H98: nan | I98: nan | J98: ACTIVO | K98: nan | L98: 0 | M98: =IF(E98>0,ROUND(L98/E98*100,1),0) -> 0 | N98: PENDIENTE | O98: =IF(H98="SI",1,0)*0.6+IF(I98="SI",1,0)*0.4 -> 0 | P98: PENDIENTE | S98: =IFERROR(SCORECARDS!C96,"—") -> 0 | T98: =IF(ISTEXT(S98),S98,IF(S98<34,"🔴 Crítico",IF(S98<67,"🟡 Vulnerable","🟢 Preparado"))) -> 🔴 Crítico | W98: 0 | X98: 0 | Y98: 0 | Z98: 0 | AA98: 0 | AB98: 0 | AC98: 0 | AD98: 0 | AE98: 0 | AF98: 0 | AG98: 0 | AH98: 0 | AI98: 0 | AJ98: 0 | AK98: 0 | AL98: 0 | AM98: 0 | AN98: 0 | AO98: =IFERROR(AVERAGE(AA98,AB98,AC98,AD98,AE98,AF98,AG98,AH98,AI98,AJ98,AK98,AL98,AM98,AN98),"N/A") -> 0 | AP98: =IFERROR(AVERAGE(W98,X98,Y98,Z98)/2,"N/A") -> 0
A99: 20573344791 | B99: ASOCIACION AGROECOLOGICO HUANGANAPAMPA | C99: HUANUCO | D99: PLÁTANO | G99: NO | H99: nan | I99: nan | J99: BAJA DE OFICIO | K99: nan | L99: 0 | M99: =IF(E99>0,ROUND(L99/E99*100,1),0) -> 0 | N99: PENDIENTE | O99: =IF(H99="SI",1,0)*0.6+IF(I99="SI",1,0)*0.4 -> 0 | P99: PENDIENTE | S99: =IFERROR(SCORECARDS!C97,"—") -> 0 | T99: =IF(ISTEXT(S99),S99,IF(S99<34,"🔴 Crítico",IF(S99<67,"🟡 Vulnerable","🟢 Preparado"))) -> 🔴 Crítico | W99: 0 | X99: 0 | Y99: 0 | Z99: 0 | AA99: 0 | AB99: 0 | AC99: 0 | AD99: 0 | AE99: 0 | AF99: 0 | AG99: 0 | AH99: 0 | AI99: 0 | AJ99: 0 | AK99: 0 | AL99: 0 | AM99: 0 | AN99: 0 | AO99: =IFERROR(AVERAGE(AA99,AB99,AC99,AD99,AE99,AF99,AG99,AH99,AI99,AJ99,AK99,AL99,AM99,AN99),"N/A") -> 0 | AP99: =IFERROR(AVERAGE(W99,X99,Y99,Z99)/2,"N/A") -> 0
A100: 20574797013 | B100: ASOCIACION DE PRODUCTORES AGROPECUARIOS DE PARAISO CENTRAL | C100: CUSCO | D100: CACAO | G100: NO | H100: nan | I100: nan | J100: ACTIVO | K100: nan | L100: 0 | M100: =IF(E100>0,ROUND(L100/E100*100,1),0) -> 0 | N100: PENDIENTE | O100: =IF(H100="SI",1,0)*0.6+IF(I100="SI",1,0)*0.4 -> 0 | P100: PENDIENTE | S100: =IFERROR(SCORECARDS!C98,"—") -> 0 | T100: =IF(ISTEXT(S100),S100,IF(S100<34,"🔴 Crítico",IF(S100<67,"🟡 Vulnerable","🟢 Preparado"))) -> 🔴 Crítico | W100: 0 | X100: 0 | Y100: 0 | Z100: 0 | AA100: 0 | AB100: 0 | AC100: 0 | AD100: 0 | AE100: 0 | AF100: 0 | AG100: 0 | AH100: 0 | AI100: 0 | AJ100: 0 | AK100: 0 | AL100: 0 | AM100: 0 | AN100: 0 | AO100: =IFERROR(AVERAGE(AA100,AB100,AC100,AD100,AE100,AF100,AG100,AH100,AI100,AJ100,AK100,AL100,AM100,AN100),"N/A") -> 0 | AP100: =IFERROR(AVERAGE(W100,X100,Y100,Z100)/2,"N/A") -> 0
...

Sheet PREGUNTAS_PROXY
A1: PREGUNTAS PROXY — Verificación rápida por dimensión EUDR
A2: Dim. | B2: # | C2: Pregunta | D2: Respuesta | E2: Score (0-1) | F2: Variable | G2: Fuente | H2: Obs.
A3: DIMENSIÓN D1 — Clasificación regulatoria
A4: D1 | B4: 1 | C4: ¿Cuál es el rol principal de la organización? | F4: tipo_rol | G4: Entrevista directiva / SUNAT
A5: D1 | B5: 2 | C5: ¿La organización está inscrita en el RNCA (Registro Nacional de Cooperativas Agrarias)? | F5: rnca | G5: SUNAT / MIDAGRI RNCA
A6: D1 | B6: 3 | C6: ¿Exporta directamente bajo su propio RUC (no a través de un agente)? | F6: exporta_directo | G6: ADUANET / DUAs
A7: DIMENSIÓN D2 — Trazabilidad y geolocalización
A8: D2 | B8: 1 | C8: ¿Existe al menos un registro donde cada lote exportado esté vinculado a la parcela de origen? | F8: lote_parcela | G8: Entrevista + revisión documentos
A9: D2 | B9: 2 | C9: ¿Se registran las coordenadas geográficas de las parcelas de los socios? | F9: coords | G9: Entrevista + evidencia
A10: D2 | B10: 3 | C10: ¿Con qué frecuencia se actualizan las coordenadas de parcelas? | F10: frec_coords | G10: Entrevista
A11: D2 | B11: 4 | C11: ¿Se usa balance de masas (mezcla de lotes sin segregación física)? | F11: bal_masas | G11: Entrevista — ROJO si dice Sí | H11: ⚠ Bal. de masas prohibido bajo EUDR
A12: D2 | B12: 5 | C12: ¿Los proveedores externos (no socios) representan volumen significativo? | F12: pct_ext | G12: Entrevista
A13: D2 | B13: 6 | C13: ¿Se registra la trazabilidad de proveedores externos (nombre, cantidad, origen)? | F13: traza_ext | G13: Entrevista
A14: DIMENSIÓN D3 — Legalidad de la producción
A15: D3 | B15: 1 | C15: ¿Qué porcentaje aproximado de los socios tiene título de propiedad o constancia de posesión inscrita en SUNARP? | F15: pct_titulo | G15: Entrevista / MIDAGRI
A16: D3 | B16: 2 | C16: ¿La zona de producción está en un área natural protegida o zona de amortiguamiento? | F16: anp | G16: GEOSERFOR / SINIA
A17: D3 | B17: 3 | C17: ¿La organización cuenta con autorizaciones ambientales vigentes (EIA, DIA, certificación forestal)? | F17: aut_ambiental | G17: Entrevista / OEFA
A18: D3 | B18: 4 | C18: ¿Hay algún proceso sancionador vigente de OEFA o SINEFA contra la organización? | F18: sancion_oea | G18: OEFA / SINEFA
A19: DIMENSIÓN D4 — Riesgo de deforestación
A20: D4 | B20: 1 | C20: ¿La organización ha realizado cruces de sus parcelas contra mapas de deforestación (GEOSERFOR / PNCB)? | F20: cruce_deforest | G20: Entrevista / verificación web
A21: D4 | B21: 2 | C21: ¿Se han detectado alertas de deforestación en parcelas de la organización? | F21: alerta_deforest | G21: GEOSERFOR / GFW
A22: DIMENSIÓN D5 — Sistema de debida diligencia
A23: D5 | B23: 1 | C23: ¿Existe un proceso documentado para evaluar riesgo de deforestación antes de exportar? | F23: proc_dd | G23: Entrevista + revisión docs
A24: D5 | B24: 2 | C24: ¿Se registran las alertas o rechazos de compradores europeos en los últimos 2 años? | F24: reg_rechazos | G24: Entrevista
A25: D5 | B25: 3 | C25: ¿La organización elabora un reporte periódico de debida diligencia? | F25: reporte_dd | G25: Entrevista
A26: DIMENSIÓN D6 — Capacidad organizacional y digital
A27: D6 | B27: 1 | C27: ¿Hay personal dedicado (tiempo completo o parcial) a tareas de gestión de datos o sistemas? | F27: personal_datos | G27: Entrevista
A28: D6 | B28: 2 | C28: ¿La organización tiene acceso a internet estable en su sede? | F28: internet | G28: Entrevista
A29: D6 | B29: 3 | C29: ¿Usa algún software o herramienta digital para gestionar trazabilidad? | F29: sw_trazabilidad | G29: Entrevista
A30: D6 | B30: 4 | C30: ¿El presupuesto anual incluye una partida para tecnología o datos? | F30: presupuesto_tech | G30: Entrevista directiva
A31: DIMENSIÓN D7 — Posición en la cadena de valor
A32: D7 | B32: 1 | C32: ¿Cuál es el destino principal de las exportaciones? | F32: destino_principal | G32: DUAs / Entrevista
A33: D7 | B33: 2 | C33: ¿El comprador principal (primera mano) es una empresa europea o está sujeta a CS3D? | F33: comprador_ue | G33: Entrevista / web
A34: D7 | B34: 3 | C34: ¿El comprador ha solicitado evidencia de trazabilidad o geolocalización? | F34: exige_evidencia | G34: Entrevista
A35: D7 | B35: 4 | C35: ¿Hay contrato escrito con cláusula EUDR o debida diligencia? | F35: contrato_eudr | G35: Entrevista / docs legales
A36: DIMENSIÓN D8 — Gobernanza y participación de socios
A37: D8 | B37: 1 | C37: ¿Los socios conocen los requisitos EUDR y sus implicancias? | F37: socios_conocen | G37: Entrevista + observación
A38: D8 | B38: 2 | C38: ¿Existe un mecanismo formal para que los socios entreguen datos de parcelas? | F38: mec_entrega | G38: Entrevista
A39: DIMENSIÓN D9 — Sostenibilidad económica del cumplimiento
A40: D9 | B40: 1 | C40: ¿La organización ha estimado el costo de adecuación al EUDR? | F40: costo_estimado | G40: Entrevista directiva
A41: D9 | B41: 2 | C41: ¿Existe una fuente de financiamiento identificada para la adecuación? | F41: financiamiento | G41: Entrevista
A42: DIMENSIÓN D10 — Confusión certificación / EUDR
A43: D10 | B43: 1 | C43: ¿La organización cree que sus certificaciones (Orgánica, Fairtrade, Rainforest) cubren los requisitos EUDR? | F43: cree_cubierta | G43: Entrevista — ROJO si dice Sí sin entender EUDR
A44: D10 | B44: 2 | C44: ¿Ha recibido asesoría específica sobre EUDR (no solo genérica de sostenibilidad)? | F44: asesoria_eudr | G44: Entrevista
A45: DIMENSIÓN D11 — Ecosistema de apoyo externo
A46: D11 | B46: 1 | C46: ¿Conoce programas de MIDAGRI, GIZ, EFI, PROMPERÚ o cooperación para apoyo EUDR? | F46: prog_apoyo | G46: Entrevista
A47: D11 | B47: 2 | C47: ¿Está inscrita en la plataforma de trazabilidad de APPCACAO o JNC? | F47: plataforma_traz | G47: Verificación web + entrevista
A48: DIMENSIÓN PPWR — Envases y Packaging (PPWR)
A49: PPWR | B49: P1 | C49: ¿Qué tipo de sacos de exportación usa principalmente? | F49: tipo_saco | G49: Entrevista
A50: PPWR | B50: P2 | C50: ¿Los sacos tienen certificación FSC o equivalente? | F50: fsc | G50: Entrevista / proveedor
A52: RESUMEN DE SCORES POR DIMENSIÓN
A53: Dimensión | B53: Score promedio | C53: N° preguntas | D53: Nivel
A54: D1 — Clasificación regulatoria | B54: =IFERROR(AVERAGEIF(E3:E6,">0"),0) -> 0 | C54: =COUNTIF(E3:E6,">0") -> 0 | D54: =IF(B54>=0.67,"🟢 Verde",IF(B54>=0.34,"🟡 Amarillo","🔴 Rojo")) -> 🔴 Rojo
A55: D2 — Trazabilidad y geolocalización | B55: =IFERROR(AVERAGEIF(E7:E13,">0"),0) -> 0 | C55: =COUNTIF(E7:E13,">0") -> 0 | D55: =IF(B55>=0.67,"🟢 Verde",IF(B55>=0.34,"🟡 Amarillo","🔴 Rojo")) -> 🔴 Rojo
A56: D3 — Legalidad de la producción | B56: =IFERROR(AVERAGEIF(E14:E18,">0"),0) -> 0 | C56: =COUNTIF(E14:E18,">0") -> 0 | D56: =IF(B56>=0.67,"🟢 Verde",IF(B56>=0.34,"🟡 Amarillo","🔴 Rojo")) -> 🔴 Rojo
A57: D4 — Riesgo de deforestación | B57: =IFERROR(AVERAGEIF(E19:E21,">0"),0) -> 0 | C57: =COUNTIF(E19:E21,">0") -> 0 | D57: =IF(B57>=0.67,"🟢 Verde",IF(B57>=0.34,"🟡 Amarillo","🔴 Rojo")) -> 🔴 Rojo
A58: D5 — Sistema de debida diligencia | B58: =IFERROR(AVERAGEIF(E22:E25,">0"),0) -> 0 | C58: =COUNTIF(E22:E25,">0") -> 0 | D58: =IF(B58>=0.67,"🟢 Verde",IF(B58>=0.34,"🟡 Amarillo","🔴 Rojo")) -> 🔴 Rojo
A59: D6 — Capacidad organizacional y digital | B59: =IFERROR(AVERAGEIF(E26:E30,">0"),0) -> 0 | C59: =COUNTIF(E26:E30,">0") -> 0 | D59: =IF(B59>=0.67,"🟢 Verde",IF(B59>=0.34,"🟡 Amarillo","🔴 Rojo")) -> 🔴 Rojo
A60: D7 — Posición en la cadena de valor | B60: =IFERROR(AVERAGEIF(E31:E35,">0"),0) -> 0 | C60: =COUNTIF(E31:E35,">0") -> 0 | D60: =IF(B60>=0.67,"🟢 Verde",IF(B60>=0.34,"🟡 Amarillo","🔴 Rojo")) -> 🔴 Rojo
A61: D8 — Gobernanza y participación de socios | B61: =IFERROR(AVERAGEIF(E36:E38,">0"),0) -> 0 | C61: =COUNTIF(E36:E38,">0") -> 0 | D61: =IF(B61>=0.67,"🟢 Verde",IF(B61>=0.34,"🟡 Amarillo","🔴 Rojo")) -> 🔴 Rojo
A62: D9 — Sostenibilidad económica del cumplimiento | B62: =IFERROR(AVERAGEIF(E39:E41,">0"),0) -> 0 | C62: =COUNTIF(E39:E41,">0") -> 0 | D62: =IF(B62>=0.67,"🟢 Verde",IF(B62>=0.34,"🟡 Amarillo","🔴 Rojo")) -> 🔴 Rojo
A63: D10 — Confusión certificación / EUDR | B63: =IFERROR(AVERAGEIF(E42:E44,">0"),0) -> 0 | C63: =COUNTIF(E42:E44,">0") -> 0 | D63: =IF(B63>=0.67,"🟢 Verde",IF(B63>=0.34,"🟡 Amarillo","🔴 Rojo")) -> 🔴 Rojo
A64: D11 — Ecosistema de apoyo externo | B64: =IFERROR(AVERAGEIF(E45:E47,">0"),0) -> 0 | C64: =COUNTIF(E45:E47,">0") -> 0 | D64: =IF(B64>=0.67,"🟢 Verde",IF(B64>=0.34,"🟡 Amarillo","🔴 Rojo")) -> 🔴 Rojo
A65: PPWR — Envases y Packaging (PPWR) | B65: =IFERROR(AVERAGEIF(E48:E50,">0"),0) -> 0 | C65: =COUNTIF(E48:E50,">0") -> 0 | D65: =IF(B65>=0.67,"🟢 Verde",IF(B65>=0.34,"🟡 Amarillo","🔴 Rojo")) -> 🔴 Rojo

Sheet SCORECARDS
A1: SCORECARDS — ISA-Completo · IP · IV · RE · Café y Cacao Perú
A2: RUC | B2: Razón Social | C2: ISA-Completo (0-100) | D2: Semáforo | E2: Ranking | F2: FOB UE USD | G2: % UE/FOB | H2: Trazab. (D2) | I2: Dilig. (D5) | J2: Capacidad (D6) | K2: Legalidad D3 (OSCE) | L2: Cert (0-1) | M2: PPWR | N2: Tipología ISCAM | O2: Segmento
A3: 20118578415 | B3: CENT.DE COOP.AGR. CAF.VALLES SANDIA LTDA | C3: =IFERROR(ISCAM_Score!AL4,"—") -> 0 | D3: =IF(C3="—","— Sin Inst.2",IF(C3<34,"🔴 Crítico",IF(C3<67,"🟡 En desarrollo","🟢 Alineado"))) -> 🔴 Crítico | E3: =IFERROR(RANK(C3,C:C,-1),"") -> 1 | F3: 2553623.3 | G3: =IFERROR(MATRIZ_174!M3,0) -> 50 | H3: 0 | I3: 0 | J3: 0 | K3: =IFERROR(INDEX(MATRIZ_174!$U:$U,MATCH(A3,MATRIZ_174!$A:$A,0)),"") -> 1 | L3: =IFERROR(MATRIZ_174!O3,0) -> 0 | M3: 0 | N3: =IFERROR(ISCAM_Score!AC4,"") -> ⬜ Riesgo Latente | O3: PUNO
A4: 20129156083 | B4: COOP AGRARIA CAFET VALLE RIO APURIMAC | C4: =IFERROR(ISCAM_Score!AL5,"—") -> 0 | D4: =IF(C4="—","— Sin Inst.2",IF(C4<34,"🔴 Crítico",IF(C4<67,"🟡 En desarrollo","🟢 Alineado"))) -> 🔴 Crítico | E4: =IFERROR(RANK(C4,C:C,-1),"") -> 1 | F4: 0 | G4: =IFERROR(MATRIZ_174!M4,0) -> 0 | H4: 0 | I4: 0 | J4: 0 | K4: =IFERROR(INDEX(MATRIZ_174!$U:$U,MATCH(A4,MATRIZ_174!$A:$A,0)),"") -> 0 | L4: =IFERROR(MATRIZ_174!O4,0) -> 0 | M4: 0 | N4: =IFERROR(ISCAM_Score!AC5,"") -> ⬜ Riesgo Latente | O4: AYACUCHO
A5: 20129529530 | B5: COOP AGRARIA CAFETALERA SATIPO LTDA | C5: =IFERROR(ISCAM_Score!AL6,"—") -> 0 | D5: =IF(C5="—","— Sin Inst.2",IF(C5<34,"🔴 Crítico",IF(C5<67,"🟡 En desarrollo","🟢 Alineado"))) -> 🔴 Crítico | E5: =IFERROR(RANK(C5,C:C,-1),"") -> 1 | F5: 4801984.1 | G5: =IFERROR(MATRIZ_174!M5,0) -> 50 | H5: 0 | I5: 0 | J5: 0 | K5: =IFERROR(INDEX(MATRIZ_174!$U:$U,MATCH(A5,MATRIZ_174!$A:$A,0)),"") -> 1 | L5: =IFERROR(MATRIZ_174!O5,0) -> 0 | M5: 0 | N5: =IFERROR(ISCAM_Score!AC6,"") -> ⬜ Riesgo Latente | O5: JUNIN
A6: 20132489824 | B6: COOPERATIVA AGRARIA CAFETALERA CHANCAMAYO LTDA. N° 008-B-VII | C6: =IFERROR(ISCAM_Score!AL7,"—") -> 0 | D6: =IF(C6="—","— Sin Inst.2",IF(C6<34,"🔴 Crítico",IF(C6<67,"🟡 En desarrollo","🟢 Alineado"))) -> 🔴 Crítico | E6: =IFERROR(RANK(C6,C:C,-1),"") -> 1 | F6: =IFERROR(MATRIZ_174!L6,0) -> 0 | G6: =IFERROR(MATRIZ_174!M6,0) -> 0 | H6: 0 | I6: 0 | J6: 0 | K6: =IFERROR(INDEX(MATRIZ_174!$U:$U,MATCH(A6,MATRIZ_174!$A:$A,0)),"") -> 0 | L6: =IFERROR(MATRIZ_174!O6,0) -> 0 | M6: 0 | N6: =IFERROR(ISCAM_Score!AC7,"") -> 🔴 Riesgo Crítico | O6: CUSCO
A7: 20132505455 | B7: COOPERATIVA AGRARIA CAFETALERA AGUILAYOC LTDA. 084 | C7: =IFERROR(ISCAM_Score!AL8,"—") -> 0 | D7: =IF(C7="—","— Sin Inst.2",IF(C7<34,"🔴 Crítico",IF(C7<67,"🟡 En desarrollo","🟢 Alineado"))) -> 🔴 Crítico | E7: =IFERROR(RANK(C7,C:C,-1),"") -> 1 | F7: =IFERROR(MATRIZ_174!L7,0) -> 0 | G7: =IFERROR(MATRIZ_174!M7,0) -> 0 | H7: 0 | I7: 0 | J7: 0 | K7: =IFERROR(INDEX(MATRIZ_174!$U:$U,MATCH(A7,MATRIZ_174!$A:$A,0)),"") -> 0 | L7: =IFERROR(MATRIZ_174!O7,0) -> 0 | M7: 0 | N7: =IFERROR(ISCAM_Score!AC8,"") -> 🔴 Riesgo Crítico | O7: CUSCO
A8: 20132509795 | B8: COOPERATIVA AGRARIA CAFETALERA JOSE OLAYA LTDA N° 252 | C8: =IFERROR(ISCAM_Score!AL9,"—") -> 0 | D8: =IF(C8="—","— Sin Inst.2",IF(C8<34,"🔴 Crítico",IF(C8<67,"🟡 En desarrollo","🟢 Alineado"))) -> 🔴 Crítico | E8: =IFERROR(RANK(C8,C:C,-1),"") -> 1 | F8: 1238541.8 | G8: =IFERROR(MATRIZ_174!M8,0) -> 50 | H8: 0 | I8: 0 | J8: 0 | K8: =IFERROR(INDEX(MATRIZ_174!$U:$U,MATCH(A8,MATRIZ_174!$A:$A,0)),"") -> 1 | L8: =IFERROR(MATRIZ_174!O8,0) -> 0 | M8: 0 | N8: =IFERROR(ISCAM_Score!AC9,"") -> ⬜ Riesgo Latente | O8: CUSCO
A9: 20132509876 | B9: COOPERATIVA AGRARIA CAFETALERA MARANURA LTDA. 129 | C9: =IFERROR(ISCAM_Score!AL10,"—") -> 0 | D9: =IF(C9="—","— Sin Inst.2",IF(C9<34,"🔴 Crítico",IF(C9<67,"🟡 En desarrollo","🟢 Alineado"))) -> 🔴 Crítico | E9: =IFERROR(RANK(C9,C:C,-1),"") -> 1 | F9: 0 | G9: =IFERROR(MATRIZ_174!M9,0) -> 0 | H9: 0 | I9: 0 | J9: 0 | K9: =IFERROR(INDEX(MATRIZ_174!$U:$U,MATCH(A9,MATRIZ_174!$A:$A,0)),"") -> 0 | L9: =IFERROR(MATRIZ_174!O9,0) -> 0 | M9: 0 | N9: =IFERROR(ISCAM_Score!AC10,"") -> ⬜ Riesgo Latente | O9: CUSCO
A10: 20132517119 | B10: COOPERATIVA AGRARIA CAFETALERA MATEO PUMACAHUA LTDA N° 185 | C10: =IFERROR(ISCAM_Score!AL11,"—") -> 0 | D10: =IF(C10="—","— Sin Inst.2",IF(C10<34,"🔴 Crítico",IF(C10<67,"🟡 En desarrollo","🟢 Alineado"))) -> 🔴 Crítico | E10: =IFERROR(RANK(C10,C:C,-1),"") -> 1 | F10: 0 | G10: =IFERROR(MATRIZ_174!M10,0) -> 0 | H10: 0 | I10: 0 | J10: 0 | K10: =IFERROR(INDEX(MATRIZ_174!$U:$U,MATCH(A10,MATRIZ_174!$A:$A,0)),"") -> 0 | L10: =IFERROR(MATRIZ_174!O10,0) -> 0 | M10: 0 | N10: =IFERROR(ISCAM_Score!AC11,"") -> 🔴 Riesgo Crítico | O10: CUSCO
A11: 20136201132 | B11: COOPERATIVA AGRARIA CAFETALERA ALTO URUBAMBA LTDA N° 239 | C11: =IFERROR(ISCAM_Score!AL12,"—") -> 0 | D11: =IF(C11="—","— Sin Inst.2",IF(C11<34,"🔴 Crítico",IF(C11<67,"🟡 En desarrollo","🟢 Alineado"))) -> 🔴 Crítico | E11: =IFERROR(RANK(C11,C:C,-1),"") -> 1 | F11: =IFERROR(MATRIZ_174!L11,0) -> 0 | G11: =IFERROR(MATRIZ_174!M11,0) -> 0 | H11: 0 | I11: 0 | J11: 0 | K11: =IFERROR(INDEX(MATRIZ_174!$U:$U,MATCH(A11,MATRIZ_174!$A:$A,0)),"") -> 0 | L11: =IFERROR(MATRIZ_174!O11,0) -> 0 | M11: 0 | N11: =IFERROR(ISCAM_Score!AC12,"") -> ⬜ Riesgo Latente | O11: CUSCO
A12: 20136201213 | B12: CENTRAL DE COOPERATIVAS AGRARIAS CAFETALERAS COCLA LTDA. N° | C12: =IFERROR(ISCAM_Score!AL13,"—") -> 0 | D12: =IF(C12="—","— Sin Inst.2",IF(C12<34,"🔴 Crítico",IF(C12<67,"🟡 En desarrollo","🟢 Alineado"))) -> 🔴 Crítico | E12: =IFERROR(RANK(C12,C:C,-1),"") -> 1 | F12: 894391.27 | G12: =IFERROR(MATRIZ_174!M12,0) -> 20.1 | H12: 0 | I12: 0 | J12: 0 | K12: =IFERROR(INDEX(MATRIZ_174!$U:$U,MATCH(A12,MATRIZ_174!$A:$A,0)),"") -> 0.75 | L12: =IFERROR(MATRIZ_174!O12,0) -> 0 | M12: 0 | N12: =IFERROR(ISCAM_Score!AC13,"") -> 🔴 Riesgo Crítico | O12: CUSCO
A13: 20140292657 | B13: COOPERATIVA AGRARIA CAFETALERA CCOCHAPAMPA LTDA. | C13: =IFERROR(ISCAM_Score!AL14,"—") -> 0 | D13: =IF(C13="—","— Sin Inst.2",IF(C13<34,"🔴 Crítico",IF(C13<67,"🟡 En desarrollo","🟢 Alineado"))) -> 🔴 Crítico | E13: =IFERROR(RANK(C13,C:C,-1),"") -> 1 | F13: 0 | G13: =IFERROR(MATRIZ_174!M13,0) -> 0 | H13: 0 | I13: 0 | J13: 0 | K13: =IFERROR(INDEX(MATRIZ_174!$U:$U,MATCH(A13,MATRIZ_174!$A:$A,0)),"") -> 0 | L13: =IFERROR(MATRIZ_174!O13,0) -> 0 | M13: 0 | N13: =IFERROR(ISCAM_Score!AC14,"") -> 🔴 Riesgo Crítico | O13: CUSCO
A14: 20143692010 | B14: COOPERATIVA AGRARIA EL QUINACHO LTDA. N° 078 | C14: =IFERROR(ISCAM_Score!AL15,"—") -> 0 | D14: =IF(C14="—","— Sin Inst.2",IF(C14<34,"🔴 Crítico",IF(C14<67,"🟡 En desarrollo","🟢 Alineado"))) -> 🔴 Crítico | E14: =IFERROR(RANK(C14,C:C,-1),"") -> 1 | F14: 2015347.3 | G14: =IFERROR(MATRIZ_174!M14,0) -> 50 | H14: 0 | I14: 0 | J14: 0 | K14: =IFERROR(INDEX(MATRIZ_174!$U:$U,MATCH(A14,MATRIZ_174!$A:$A,0)),"") -> 1 | L14: =IFERROR(MATRIZ_174!O14,0) -> 0 | M14: 0 | N14: =IFERROR(ISCAM_Score!AC15,"") -> ⬜ Riesgo Latente | O14: AYACUCHO
A15: 20145484597 | B15: COOPERATIVA AGRARIA CAFETALERA SAN IGNACIO LTDA. | C15: =IFERROR(ISCAM_Score!AL16,"—") -> 0 | D15: =IF(C15="—","— Sin Inst.2",IF(C15<34,"🔴 Crítico",IF(C15<67,"🟡 En desarrollo","🟢 Alineado"))) -> 🔴 Crítico | E15: =IFERROR(RANK(C15,C:C,-1),"") -> 1 | F15: =IFERROR(MATRIZ_174!L15,0) -> 0 | G15: =IFERROR(MATRIZ_174!M15,0) -> 0 | H15: 0 | I15: 0 | J15: 0 | K15: =IFERROR(INDEX(MATRIZ_174!$U:$U,MATCH(A15,MATRIZ_174!$A:$A,0)),"") -> 0 | L15: =IFERROR(MATRIZ_174!O15,0) -> 0 | M15: 0 | N15: =IFERROR(ISCAM_Score!AC16,"") -> ⬜ Riesgo Latente | O15: PUNO
A16: 20146696041 | B16: COOP AGRARIA CAFET JOSE GABRIEL CONDORCA | C16: =IFERROR(ISCAM_Score!AL17,"—") -> 0 | D16: =IF(C16="—","— Sin Inst.2",IF(C16<34,"🔴 Crítico",IF(C16<67,"🟡 En desarrollo","🟢 Alineado"))) -> 🔴 Crítico | E16: =IFERROR(RANK(C16,C:C,-1),"") -> 1 | F16: =IFERROR(MATRIZ_174!L16,0) -> 0 | G16: =IFERROR(MATRIZ_174!M16,0) -> 0 | H16: 0 | I16: 0 | J16: 0 | K16: =IFERROR(INDEX(MATRIZ_174!$U:$U,MATCH(A16,MATRIZ_174!$A:$A,0)),"") -> 0 | L16: =IFERROR(MATRIZ_174!O16,0) -> 0 | M16: 0 | N16: =IFERROR(ISCAM_Score!AC17,"") -> ⬜ Riesgo Latente | O16: PIURA
A17: 20147443120 | B17: COOPERATIVA AGRARIA CAFETALERA TIRIJUAY PAVAYOC LTDA 013-B-V | C17: =IFERROR(ISCAM_Score!AL18,"—") -> 0 | D17: =IF(C17="—","— Sin Inst.2",IF(C17<34,"🔴 Crítico",IF(C17<67,"🟡 En desarrollo","🟢 Alineado"))) -> 🔴 Crítico | E17: =IFERROR(RANK(C17,C:C,-1),"") -> 1 | F17: =IFERROR(MATRIZ_174!L17,0) -> 0 | G17: =IFERROR(MATRIZ_174!M17,0) -> 0 | H17: 0 | I17: 0 | J17: 0 | K17: =IFERROR(INDEX(MATRIZ_174!$U:$U,MATCH(A17,MATRIZ_174!$A:$A,0)),"") -> 0 | L17: =IFERROR(MATRIZ_174!O17,0) -> 0 | M17: 0 | N17: =IFERROR(ISCAM_Score!AC18,"") -> 🔴 Riesgo Crítico | O17: CUSCO
A18: 20166786861 | B18: COMITE CENTRAL DE PRODUCTORES AGROPECUARIOS DE SAN ALEJANDRO | C18: =IFERROR(ISCAM_Score!AL19,"—") -> 0 | D18: =IF(C18="—","— Sin Inst.2",IF(C18<34,"🔴 Crítico",IF(C18<67,"🟡 En desarrollo","🟢 Alineado"))) -> 🔴 Crítico | E18: =IFERROR(RANK(C18,C:C,-1),"") -> 1 | F18: =IFERROR(MATRIZ_174!L18,0) -> 0 | G18: =IFERROR(MATRIZ_174!M18,0) -> 0 | H18: 0 | I18: 0 | J18: 0 | K18: =IFERROR(INDEX(MATRIZ_174!$U:$U,MATCH(A18,MATRIZ_174!$A:$A,0)),"") -> 0 | L18: =IFERROR(MATRIZ_174!O18,0) -> 0 | M18: 0 | N18: =IFERROR(ISCAM_Score!AC19,"") -> ⬜ Riesgo Latente | O18: UCAYALI
A19: 20170142773 | B19: COOPERATIVA AGRARIA CAFETALERA BAGUA GRANDE LIMITADA | C19: =IFERROR(ISCAM_Score!AL20,"—") -> 0 | D19: =IF(C19="—","— Sin Inst.2",IF(C19<34,"🔴 Crítico",IF(C19<67,"🟡 En desarrollo","🟢 Alineado"))) -> 🔴 Crítico | E19: =IFERROR(RANK(C19,C:C,-1),"") -> 1 | F19: 4535378.4 | G19: =IFERROR(MATRIZ_174!M19,0) -> 50 | H19: 0 | I19: 0 | J19: 0 | K19: =IFERROR(INDEX(MATRIZ_174!$U:$U,MATCH(A19,MATRIZ_174!$A:$A,0)),"") -> 1 | L19: =IFERROR(MATRIZ_174!O19,0) -> 0 | M19: 0 | N19: =IFERROR(ISCAM_Score!AC20,"") -> ⬜ Riesgo Latente | O19: AMAZONAS
A20: 20200880448 | B20: COOPERATIVA AGRARIA CAFETALERA JORGE CHAVEZ LTDA | C20: =IFERROR(ISCAM_Score!AL21,"—") -> 0 | D20: =IF(C20="—","— Sin Inst.2",IF(C20<34,"🔴 Crítico",IF(C20<67,"🟡 En desarrollo","🟢 Alineado"))) -> 🔴 Crítico | E20: =IFERROR(RANK(C20,C:C,-1),"") -> 1 | F20: =IFERROR(MATRIZ_174!L20,0) -> 0 | G20: =IFERROR(MATRIZ_174!M20,0) -> 0 | H20: 0 | I20: 0 | J20: 0 | K20: =IFERROR(INDEX(MATRIZ_174!$U:$U,MATCH(A20,MATRIZ_174!$A:$A,0)),"") -> 0 | L20: =IFERROR(MATRIZ_174!O20,0) -> 0 | M20: 0 | N20: =IFERROR(ISCAM_Score!AC21,"") -> 🔴 Riesgo Crítico | O20: CUSCO
A21: 20352417018 | B21: COOPERATIVA AGRARIA DE CACAOTEROS TECNIFICADOS DE PADRE ABAD | C21: =IFERROR(ISCAM_Score!AL22,"—") -> 0 | D21: =IF(C21="—","— Sin Inst.2",IF(C21<34,"🔴 Crítico",IF(C21<67,"🟡 En desarrollo","🟢 Alineado"))) -> 🔴 Crítico | E21: =IFERROR(RANK(C21,C:C,-1),"") -> 1 | F21: 0 | G21: =IFERROR(MATRIZ_174!M21,0) -> 0 | H21: 0 | I21: 0 | J21: 0 | K21: =IFERROR(INDEX(MATRIZ_174!$U:$U,MATCH(A21,MATRIZ_174!$A:$A,0)),"") -> 0 | L21: =IFERROR(MATRIZ_174!O21,0) -> 0 | M21: 0 | N21: =IFERROR(ISCAM_Score!AC22,"") -> ⬜ Riesgo Latente | O21: UCAYALI
A22: 20352423921 | B22: COOPERATIVA AGRARIA CAFETALERA DIVISORIA LTDA | C22: =IFERROR(ISCAM_Score!AL23,"—") -> 0 | D22: =IF(C22="—","— Sin Inst.2",IF(C22<34,"🔴 Crítico",IF(C22<67,"🟡 En desarrollo","🟢 Alineado"))) -> 🔴 Crítico | E22: =IFERROR(RANK(C22,C:C,-1),"") -> 1 | F22: 0 | G22: =IFERROR(MATRIZ_174!M22,0) -> 0 | H22: 0 | I22: 0 | J22: 0 | K22: =IFERROR(INDEX(MATRIZ_174!$U:$U,MATCH(A22,MATRIZ_174!$A:$A,0)),"") -> 0 | L22: =IFERROR(MATRIZ_174!O22,0) -> 0 | M22: 0 | N22: =IFERROR(ISCAM_Score!AC23,"") -> ⬜ Riesgo Latente | O22: HUANUCO
A23: 20393152207 | B23: COOPERATIVA AGRO INDUSTRIAL APCTVASH | C23: =IFERROR(ISCAM_Score!AL24,"—") -> 0 | D23: =IF(C23="—","— Sin Inst.2",IF(C23<34,"🔴 Crítico",IF(C23<67,"🟡 En desarrollo","🟢 Alineado"))) -> 🔴 Crítico | E23: =IFERROR(RANK(C23,C:C,-1),"") -> 1 | F23: =IFERROR(MATRIZ_174!L23,0) -> 0 | G23: =IFERROR(MATRIZ_174!M23,0) -> 0 | H23: 0 | I23: 0 | J23: 0 | K23: =IFERROR(INDEX(MATRIZ_174!$U:$U,MATCH(A23,MATRIZ_174!$A:$A,0)),"") -> 0 | L23: =IFERROR(MATRIZ_174!O23,0) -> 0 | M23: 0 | N23: =IFERROR(ISCAM_Score!AC24,"") -> ⬜ Riesgo Latente | O23: UCAYALI
A24: 20393593670 | B24: COMITE CENTRAL CON DESARROLLO AL FUTURO DE CURIMANA | C24: =IFERROR(ISCAM_Score!AL25,"—") -> 0 | D24: =IF(C24="—","— Sin Inst.2",IF(C24<34,"🔴 Crítico",IF(C24<67,"🟡 En desarrollo","🟢 Alineado"))) -> 🔴 Crítico | E24: =IFERROR(RANK(C24,C:C,-1),"") -> 1 | F24: 0 | G24: =IFERROR(MATRIZ_174!M24,0) -> 0 | H24: 0 | I24: 0 | J24: 0 | K24: =IFERROR(INDEX(MATRIZ_174!$U:$U,MATCH(A24,MATRIZ_174!$A:$A,0)),"") -> 0 | L24: =IFERROR(MATRIZ_174!O24,0) -> 0 | M24: 0 | N24: =IFERROR(ISCAM_Score!AC25,"") -> ⬜ Riesgo Latente | O24: UCAYALI
A25: 20393692228 | B25: COOPERATIVA AGRARIA CACAOTERA SAN ALEJANDRO LTDA | C25: =IFERROR(ISCAM_Score!AL26,"—") -> 0 | D25: =IF(C25="—","— Sin Inst.2",IF(C25<34,"🔴 Crítico",IF(C25<67,"🟡 En desarrollo","🟢 Alineado"))) -> 🔴 Crítico | E25: =IFERROR(RANK(C25,C:C,-1),"") -> 1 | F25: 0 | G25: =IFERROR(MATRIZ_174!M25,0) -> 0 | H25: 0 | I25: 0 | J25: 0 | K25: =IFERROR(INDEX(MATRIZ_174!$U:$U,MATCH(A25,MATRIZ_174!$A:$A,0)),"") -> 0 | L25: =IFERROR(MATRIZ_174!O25,0) -> 0 | M25: 0 | N25: =IFERROR(ISCAM_Score!AC26,"") -> ⬜ Riesgo Latente | O25: UCAYALI
A26: 20393786044 | B26: COOPERATIVA AGRARIA CAFETALERA COORDILLERA AZUL DE UCAYALI L | C26: =IFERROR(ISCAM_Score!AL27,"—") -> 0 | D26: =IF(C26="—","— Sin Inst.2",IF(C26<34,"🔴 Crítico",IF(C26<67,"🟡 En desarrollo","🟢 Alineado"))) -> 🔴 Crítico | E26: =IFERROR(RANK(C26,C:C,-1),"") -> 1 | F26: =IFERROR(MATRIZ_174!L26,0) -> 0 | G26: =IFERROR(MATRIZ_174!M26,0) -> 0 | H26: 0 | I26: 0 | J26: 0 | K26: =IFERROR(INDEX(MATRIZ_174!$U:$U,MATCH(A26,MATRIZ_174!$A:$A,0)),"") -> 0 | L26: =IFERROR(MATRIZ_174!O26,0) -> 0 | M26: 0 | N26: =IFERROR(ISCAM_Score!AC27,"") -> ⬜ Riesgo Latente | O26: UCAYALI
A27: 20393816211 | B27: COOPERATIVA AGRARIA SAN JUAN BAUTISTA | C27: =IFERROR(ISCAM_Score!AL28,"—") -> 0 | D27: =IF(C27="—","— Sin Inst.2",IF(C27<34,"🔴 Crítico",IF(C27<67,"🟡 En desarrollo","🟢 Alineado"))) -> 🔴 Crítico | E27: =IFERROR(RANK(C27,C:C,-1),"") -> 1 | F27: 0 | G27: =IFERROR(MATRIZ_174!M27,0) -> 0 | H27: 0 | I27: 0 | J27: 0 | K27: =IFERROR(INDEX(MATRIZ_174!$U:$U,MATCH(A27,MATRIZ_174!$A:$A,0)),"") -> 0 | L27: =IFERROR(MATRIZ_174!O27,0) -> 0 | M27: 0 | N27: =IFERROR(ISCAM_Score!AC28,"") -> ⬜ Riesgo Latente | O27: UCAYALI
A28: 20393882868 | B28: COOPERATIVA AGRARIA ASCAH | C28: =IFERROR(ISCAM_Score!AL29,"—") -> 0 | D28: =IF(C28="—","— Sin Inst.2",IF(C28<34,"🔴 Crítico",IF(C28<67,"🟡 En desarrollo","🟢 Alineado"))) -> 🔴 Crítico | E28: =IFERROR(RANK(C28,C:C,-1),"") -> 1 | F28: =IFERROR(MATRIZ_174!L28,0) -> 0 | G28: =IFERROR(MATRIZ_174!M28,0) -> 0 | H28: 0 | I28: 0 | J28: 0 | K28: =IFERROR(INDEX(MATRIZ_174!$U:$U,MATCH(A28,MATRIZ_174!$A:$A,0)),"") -> 0 | L28: =IFERROR(MATRIZ_174!O28,0) -> 0 | M28: 0 | N28: =IFERROR(ISCAM_Score!AC29,"") -> ⬜ Riesgo Latente | O28: UCAYALI
A29: 20393972000 | B29: ASOCIACION DE MUJERES EMPRENDEDORAS FLOR DE BOQUERON | C29: =IFERROR(ISCAM_Score!AL30,"—") -> 0 | D29: =IF(C29="—","— Sin Inst.2",IF(C29<34,"🔴 Crítico",IF(C29<67,"🟡 En desarrollo","🟢 Alineado"))) -> 🔴 Crítico | E29: =IFERROR(RANK(C29,C:C,-1),"") -> 1 | F29: =IFERROR(MATRIZ_174!L29,0) -> 0 | G29: =IFERROR(MATRIZ_174!M29,0) -> 0 | H29: 0 | I29: 0 | J29: 0 | K29: =IFERROR(INDEX(MATRIZ_174!$U:$U,MATCH(A29,MATRIZ_174!$A:$A,0)),"") -> 0 | L29: =IFERROR(MATRIZ_174!O29,0) -> 0 | M29: 0 | N29: =IFERROR(ISCAM_Score!AC30,"") -> ⬜ Riesgo Latente | O29: UCAYALI
A30: 20447888701 | B30: COOPERATIVA AGRARIA INDUSTRIAL SAN GABAN LTDA. | C30: =IFERROR(ISCAM_Score!AL31,"—") -> 0 | D30: =IF(C30="—","— Sin Inst.2",IF(C30<34,"🔴 Crítico",IF(C30<67,"🟡 En desarrollo","🟢 Alineado"))) -> 🔴 Crítico | E30: =IFERROR(RANK(C30,C:C,-1),"") -> 1 | F30: =IFERROR(MATRIZ_174!L30,0) -> 0 | G30: =IFERROR(MATRIZ_174!M30,0) -> 0 | H30: 0 | I30: 0 | J30: 0 | K30: =IFERROR(INDEX(MATRIZ_174!$U:$U,MATCH(A30,MATRIZ_174!$A:$A,0)),"") -> 0 | L30: =IFERROR(MATRIZ_174!O30,0) -> 0 | M30: 0 | N30: =IFERROR(ISCAM_Score!AC31,"") -> ⬜ Riesgo Latente | O30: PUNO
A31: 20450189201 | B31: COOPERATIVA DE SERVICIOS MULTIPLES FRUTOS DE SELVA | C31: =IFERROR(ISCAM_Score!AL32,"—") -> 0 | D31: =IF(C31="—","— Sin Inst.2",IF(C31<34,"🔴 Crítico",IF(C31<67,"🟡 En desarrollo","🟢 Alineado"))) -> 🔴 Crítico | E31: =IFERROR(RANK(C31,C:C,-1),"") -> 1 | F31: 0 | G31: =IFERROR(MATRIZ_174!M31,0) -> 0 | H31: 0 | I31: 0 | J31: 0 | K31: =IFERROR(INDEX(MATRIZ_174!$U:$U,MATCH(A31,MATRIZ_174!$A:$A,0)),"") -> 0 | L31: =IFERROR(MATRIZ_174!O31,0) -> 0 | M31: 0 | N31: =IFERROR(ISCAM_Score!AC32,"") -> ⬜ Riesgo Latente | O31: SAN MARTIN
A32: 20450207544 | B32: COOPERATIVA AGRARIA UCHIZA LTDA | C32: =IFERROR(ISCAM_Score!AL33,"—") -> 0 | D32: =IF(C32="—","— Sin Inst.2",IF(C32<34,"🔴 Crítico",IF(C32<67,"🟡 En desarrollo","🟢 Alineado"))) -> 🔴 Crítico | E32: =IFERROR(RANK(C32,C:C,-1),"") -> 1 | F32: 0 | G32: =IFERROR(MATRIZ_174!M32,0) -> 0 | H32: 0 | I32: 0 | J32: 0 | K32: =IFERROR(INDEX(MATRIZ_174!$U:$U,MATCH(A32,MATRIZ_174!$A:$A,0)),"") -> 0 | L32: =IFERROR(MATRIZ_174!O32,0) -> 0 | M32: 0 | N32: =IFERROR(ISCAM_Score!AC33,"") -> ⬜ Riesgo Latente | O32: SAN MARTIN
A33: 20450242021 | B33: COOPERATIVA DE SERVICIOS MULTIPLES CAPEMA | C33: =IFERROR(ISCAM_Score!AL34,"—") -> 0 | D33: =IF(C33="—","— Sin Inst.2",IF(C33<34,"🔴 Crítico",IF(C33<67,"🟡 En desarrollo","🟢 Alineado"))) -> 🔴 Crítico | E33: =IFERROR(RANK(C33,C:C,-1),"") -> 1 | F33: 0 | G33: =IFERROR(MATRIZ_174!M33,0) -> 0 | H33: 0 | I33: 0 | J33: 0 | K33: =IFERROR(INDEX(MATRIZ_174!$U:$U,MATCH(A33,MATRIZ_174!$A:$A,0)),"") -> 0 | L33: =IFERROR(MATRIZ_174!O33,0) -> 0 | M33: 0 | N33: =IFERROR(ISCAM_Score!AC34,"") -> ⬜ Riesgo Latente | O33: SAN MARTIN
A34: 20450319423 | B34: COOPERATIVA AGRARIA DE SERVICIOS MULTIPLES CAFE DONCEL | C34: =IFERROR(ISCAM_Score!AL35,"—") -> 0 | D34: =IF(C34="—","— Sin Inst.2",IF(C34<34,"🔴 Crítico",IF(C34<67,"🟡 En desarrollo","🟢 Alineado"))) -> 🔴 Crítico | E34: =IFERROR(RANK(C34,C:C,-1),"") -> 1 | F34: =IFERROR(MATRIZ_174!L34,0) -> 0 | G34: =IFERROR(MATRIZ_174!M34,0) -> 0 | H34: 0 | I34: 0 | J34: 0 | K34: =IFERROR(INDEX(MATRIZ_174!$U:$U,MATCH(A34,MATRIZ_174!$A:$A,0)),"") -> 0 | L34: =IFERROR(MATRIZ_174!O34,0) -> 0 | M34: 0 | N34: =IFERROR(ISCAM_Score!AC35,"") -> ⬜ Riesgo Latente | O34: SAN MARTIN
A35: 20452774705 | B35: COOPERATIVA AGRARIA CACAO VRAE | C35: =IFERROR(ISCAM_Score!AL36,"—") -> 0 | D35: =IF(C35="—","— Sin Inst.2",IF(C35<34,"🔴 Crítico",IF(C35<67,"🟡 En desarrollo","🟢 Alineado"))) -> 🔴 Crítico | E35: =IFERROR(RANK(C35,C:C,-1),"") -> 1 | F35: 965726.35 | G35: =IFERROR(MATRIZ_174!M35,0) -> 50 | H35: 0 | I35: 0 | J35: 0 | K35: =IFERROR(INDEX(MATRIZ_174!$U:$U,MATCH(A35,MATRIZ_174!$A:$A,0)),"") -> 1 | L35: =IFERROR(MATRIZ_174!O35,0) -> 0 | M35: 0 | N35: =IFERROR(ISCAM_Score!AC36,"") -> ⬜ Riesgo Latente | O35: CUSCO
A36: 20479595276 | B36: COOPERATIVA AGRARIA CAFETALERA CASIL LTDA. | C36: =IFERROR(ISCAM_Score!AL37,"—") -> 0 | D36: =IF(C36="—","— Sin Inst.2",IF(C36<34,"🔴 Crítico",IF(C36<67,"🟡 En desarrollo","🟢 Alineado"))) -> 🔴 Crítico | E36: =IFERROR(RANK(C36,C:C,-1),"") -> 1 | F36: 965167.45 | G36: =IFERROR(MATRIZ_174!M36,0) -> 21.3 | H36: 0 | I36: 0 | J36: 0 | K36: =IFERROR(INDEX(MATRIZ_174!$U:$U,MATCH(A36,MATRIZ_174!$A:$A,0)),"") -> 1 | L36: =IFERROR(MATRIZ_174!O36,0) -> 1 | M36: 0 | N36: =IFERROR(ISCAM_Score!AC37,"") -> ⬜ Riesgo Latente | O36: CAJAMARCA
A37: 20479622699 | B37: COOPERATIVA AGRARIA JUAN MARCO EL PALTO | C37: =IFERROR(ISCAM_Score!AL38,"—") -> 0 | D37: =IF(C37="—","— Sin Inst.2",IF(C37<34,"🔴 Crítico",IF(C37<67,"🟡 En desarrollo","🟢 Alineado"))) -> 🔴 Crítico | E37: =IFERROR(RANK(C37,C:C,-1),"") -> 1 | F37: 0 | G37: =IFERROR(MATRIZ_174!M37,0) -> 0 | H37: 0 | I37: 0 | J37: 0 | K37: =IFERROR(INDEX(MATRIZ_174!$U:$U,MATCH(A37,MATRIZ_174!$A:$A,0)),"") -> 0 | L37: =IFERROR(MATRIZ_174!O37,0) -> 0 | M37: 0 | N37: =IFERROR(ISCAM_Score!AC38,"") -> ⬜ Riesgo Latente | O37: AMAZONAS
A38: 20479856258 | B38: ASOCIACION DE PRODUCTORES AGROPECUARIOS LUIS SOLIBARRIA | C38: =IFERROR(ISCAM_Score!AL39,"—") -> 0 | D38: =IF(C38="—","— Sin Inst.2",IF(C38<34,"🔴 Crítico",IF(C38<67,"🟡 En desarrollo","🟢 Alineado"))) -> 🔴 Crítico | E38: =IFERROR(RANK(C38,C:C,-1),"") -> 1 | F38: =IFERROR(MATRIZ_174!L38,0) -> 0 | G38: =IFERROR(MATRIZ_174!M38,0) -> 0 | H38: 0 | I38: 0 | J38: 0 | K38: =IFERROR(INDEX(MATRIZ_174!$U:$U,MATCH(A38,MATRIZ_174!$A:$A,0)),"") -> 0 | L38: =IFERROR(MATRIZ_174!O38,0) -> 0 | M38: 0 | N38: =IFERROR(ISCAM_Score!AC39,"") -> ⬜ Riesgo Latente | O38: AMAZONAS
A39: 20479917141 | B39: COOPERATIVA AGRARIA CENTRAL DE PRODUCTORES DE AMAZONAS | C39: =IFERROR(ISCAM_Score!AL40,"—") -> 0 | D39: =IF(C39="—","— Sin Inst.2",IF(C39<34,"🔴 Crítico",IF(C39<67,"🟡 En desarrollo","🟢 Alineado"))) -> 🔴 Crítico | E39: =IFERROR(RANK(C39,C:C,-1),"") -> 1 | F39: 587607.64 | G39: =IFERROR(MATRIZ_174!M39,0) -> 50 | H39: 0 | I39: 0 | J39: 0 | K39: =IFERROR(INDEX(MATRIZ_174!$U:$U,MATCH(A39,MATRIZ_174!$A:$A,0)),"") -> 1 | L39: =IFERROR(MATRIZ_174!O39,0) -> 0 | M39: 0 | N39: =IFERROR(ISCAM_Score!AC40,"") -> ⬜ Riesgo Latente | O39: AMAZONAS
A40: 20480458550 | B40: COOPERATIVA AGRARIA APROCAM | C40: =IFERROR(ISCAM_Score!AL41,"—") -> 0 | D40: =IF(C40="—","— Sin Inst.2",IF(C40<34,"🔴 Crítico",IF(C40<67,"🟡 En desarrollo","🟢 Alineado"))) -> 🔴 Crítico | E40: =IFERROR(RANK(C40,C:C,-1),"") -> 1 | F40: 842214.99 | G40: =IFERROR(MATRIZ_174!M40,0) -> 50 | H40: 0 | I40: 0 | J40: 0 | K40: =IFERROR(INDEX(MATRIZ_174!$U:$U,MATCH(A40,MATRIZ_174!$A:$A,0)),"") -> 1 | L40: =IFERROR(MATRIZ_174!O40,0) -> 0 | M40: 0 | N40: =IFERROR(ISCAM_Score!AC41,"") -> ⬜ Riesgo Latente | O40: AMAZONAS
A41: 20480762895 | B41: ASOCIACION DE PRODUCTORES AGROPECUARIOS LA FLOR DE CAFE | C41: =IFERROR(ISCAM_Score!AL42,"—") -> 0 | D41: =IF(C41="—","— Sin Inst.2",IF(C41<34,"🔴 Crítico",IF(C41<67,"🟡 En desarrollo","🟢 Alineado"))) -> 🔴 Crítico | E41: =IFERROR(RANK(C41,C:C,-1),"") -> 1 | F41: 0 | G41: =IFERROR(MATRIZ_174!M41,0) -> 0 | H41: 0 | I41: 0 | J41: 0 | K41: =IFERROR(INDEX(MATRIZ_174!$U:$U,MATCH(A41,MATRIZ_174!$A:$A,0)),"") -> 0 | L41: =IFERROR(MATRIZ_174!O41,0) -> 0 | M41: 0 | N41: =IFERROR(ISCAM_Score!AC42,"") -> ⬜ Riesgo Latente | O41: AMAZONAS
A42: 20484163902 | B42: COOPERATIVA AGRARIA APPROCAP LTDA | C42: =IFERROR(ISCAM_Score!AL43,"—") -> 0 | D42: =IF(C42="—","— Sin Inst.2",IF(C42<34,"🔴 Crítico",IF(C42<67,"🟡 En desarrollo","🟢 Alineado"))) -> 🔴 Crítico | E42: =IFERROR(RANK(C42,C:C,-1),"") -> 1 | F42: 408500 | G42: =IFERROR(MATRIZ_174!M42,0) -> 50 | H42: 0 | I42: 0 | J42: 0 | K42: =IFERROR(INDEX(MATRIZ_174!$U:$U,MATCH(A42,MATRIZ_174!$A:$A,0)),"") -> 1 | L42: =IFERROR(MATRIZ_174!O42,0) -> 0 | M42: 0 | N42: =IFERROR(ISCAM_Score!AC43,"") -> ⬜ Riesgo Latente | O42: PIURA
A43: 20485945815 | B43: COOPERATIVA AGRARIA CAFETALERA ECOLOGICO ALTO PALOMAR | C43: =IFERROR(ISCAM_Score!AL44,"—") -> 0 | D43: =IF(C43="—","— Sin Inst.2",IF(C43<34,"🔴 Crítico",IF(C43<67,"🟡 En desarrollo","🟢 Alineado"))) -> 🔴 Crítico | E43: =IFERROR(RANK(C43,C:C,-1),"") -> 1 | F43: 0 | G43: =IFERROR(MATRIZ_174!M43,0) -> 0 | H43: 0 | I43: 0 | J43: 0 | K43: =IFERROR(INDEX(MATRIZ_174!$U:$U,MATCH(A43,MATRIZ_174!$A:$A,0)),"") -> 0 | L43: =IFERROR(MATRIZ_174!O43,0) -> 0 | M43: 0 | N43: =IFERROR(ISCAM_Score!AC44,"") -> ⬜ Riesgo Latente | O43: JUNIN
A44: 20486094657 | B44: ASOCIACION DE PRODUCTORES DE CAFES ESPECIALES MOUNTAIN COFFE | C44: =IFERROR(ISCAM_Score!AL45,"—") -> 0 | D44: =IF(C44="—","— Sin Inst.2",IF(C44<34,"🔴 Crítico",IF(C44<67,"🟡 En desarrollo","🟢 Alineado"))) -> 🔴 Crítico | E44: =IFERROR(RANK(C44,C:C,-1),"") -> 1 | F44: 0 | G44: =IFERROR(MATRIZ_174!M44,0) -> 0 | H44: 0 | I44: 0 | J44: 0 | K44: =IFERROR(INDEX(MATRIZ_174!$U:$U,MATCH(A44,MATRIZ_174!$A:$A,0)),"") -> 0 | L44: =IFERROR(MATRIZ_174!O44,0) -> 0 | M44: 0 | N44: =IFERROR(ISCAM_Score!AC45,"") -> ⬜ Riesgo Latente | O44: JUNIN
A45: 20486255090 | B45: COOPERATIVA AGRARIA SANGARENI | C45: =IFERROR(ISCAM_Score!AL46,"—") -> 0 | D45: =IF(C45="—","— Sin Inst.2",IF(C45<34,"🔴 Crítico",IF(C45<67,"🟡 En desarrollo","🟢 Alineado"))) -> 🔴 Crítico | E45: =IFERROR(RANK(C45,C:C,-1),"") -> 1 | F45: 6603846 | G45: =IFERROR(MATRIZ_174!M45,0) -> 50 | H45: 0 | I45: 0 | J45: 0 | K45: =IFERROR(INDEX(MATRIZ_174!$U:$U,MATCH(A45,MATRIZ_174!$A:$A,0)),"") -> 1 | L45: =IFERROR(MATRIZ_174!O45,0) -> 0 | M45: 0 | N45: =IFERROR(ISCAM_Score!AC46,"") -> ⬜ Riesgo Latente | O45: JUNIN
A46: 20486668335 | B46: COOPERATIVA AGROINDUSTRIAL SONOMORO LTDA | C46: =IFERROR(ISCAM_Score!AL47,"—") -> 0 | D46: =IF(C46="—","— Sin Inst.2",IF(C46<34,"🔴 Crítico",IF(C46<67,"🟡 En desarrollo","🟢 Alineado"))) -> 🔴 Crítico | E46: =IFERROR(RANK(C46,C:C,-1),"") -> 1 | F46: 0 | G46: =IFERROR(MATRIZ_174!M46,0) -> 0 | H46: 0 | I46: 0 | J46: 0 | K46: =IFERROR(INDEX(MATRIZ_174!$U:$U,MATCH(A46,MATRIZ_174!$A:$A,0)),"") -> 0 | L46: =IFERROR(MATRIZ_174!O46,0) -> 0 | M46: 0 | N46: =IFERROR(ISCAM_Score!AC47,"") -> ⬜ Riesgo Latente | O46: JUNIN
A47: 20486876019 | B47: COOPERATIVA AGROECOLOGICO INDUSTRIAL MAZAMARI LTDA | C47: =IFERROR(ISCAM_Score!AL48,"—") -> 0 | D47: =IF(C47="—","— Sin Inst.2",IF(C47<34,"🔴 Crítico",IF(C47<67,"🟡 En desarrollo","🟢 Alineado"))) -> 🔴 Crítico | E47: =IFERROR(RANK(C47,C:C,-1),"") -> 1 | F47: =IFERROR(MATRIZ_174!L47,0) -> 0 | G47: =IFERROR(MATRIZ_174!M47,0) -> 0 | H47: 0 | I47: 0 | J47: 0 | K47: =IFERROR(INDEX(MATRIZ_174!$U:$U,MATCH(A47,MATRIZ_174!$A:$A,0)),"") -> 0 | L47: =IFERROR(MATRIZ_174!O47,0) -> 0 | M47: 0 | N47: =IFERROR(ISCAM_Score!AC48,"") -> ⬜ Riesgo Latente | O47: JUNIN
A48: 20486973219 | B48: COOPERATIVA AGRARIA SONOMORO DEL VRAEM LTDA | C48: =IFERROR(ISCAM_Score!AL49,"—") -> 0 | D48: =IF(C48="—","— Sin Inst.2",IF(C48<34,"🔴 Crítico",IF(C48<67,"🟡 En desarrollo","🟢 Alineado"))) -> 🔴 Crítico | E48: =IFERROR(RANK(C48,C:C,-1),"") -> 1 | F48: 15171147 | G48: =IFERROR(MATRIZ_174!M48,0) -> 50 | H48: 0 | I48: 0 | J48: 0 | K48: =IFERROR(INDEX(MATRIZ_174!$U:$U,MATCH(A48,MATRIZ_174!$A:$A,0)),"") -> 1 | L48: =IFERROR(MATRIZ_174!O48,0) -> 0 | M48: 0 | N48: =IFERROR(ISCAM_Score!AC49,"") -> ⬜ Riesgo Latente | O48: JUNIN
A49: 20487242994 | B49: COOPERATIVA AGRARIA ECOLOGICA CACAOTERA VALLE RIO ENE - COOP | C49: =IFERROR(ISCAM_Score!AL50,"—") -> 0 | D49: =IF(C49="—","— Sin Inst.2",IF(C49<34,"🔴 Crítico",IF(C49<67,"🟡 En desarrollo","🟢 Alineado"))) -> 🔴 Crítico | E49: =IFERROR(RANK(C49,C:C,-1),"") -> 1 | F49: 1145489.4 | G49: =IFERROR(MATRIZ_174!M49,0) -> 50 | H49: 0 | I49: 0 | J49: 0 | K49: =IFERROR(INDEX(MATRIZ_174!$U:$U,MATCH(A49,MATRIZ_174!$A:$A,0)),"") -> 1 | L49: =IFERROR(MATRIZ_174!O49,0) -> 0 | M49: 0 | N49: =IFERROR(ISCAM_Score!AC50,"") -> ⬜ Riesgo Latente | O49: JUNIN
A50: 20487351343 | B50: ASOCIACION DE PRODUCTORES AGROPECUARIOS TUPAC AMARU DE CHIÑA | C50: =IFERROR(ISCAM_Score!AL51,"—") -> 0 | D50: =IF(C50="—","— Sin Inst.2",IF(C50<34,"🔴 Crítico",IF(C50<67,"🟡 En desarrollo","🟢 Alineado"))) -> 🔴 Crítico | E50: =IFERROR(RANK(C50,C:C,-1),"") -> 1 | F50: =IFERROR(MATRIZ_174!L50,0) -> 0 | G50: =IFERROR(MATRIZ_174!M50,0) -> 0 | H50: 0 | I50: 0 | J50: 0 | K50: =IFERROR(INDEX(MATRIZ_174!$U:$U,MATCH(A50,MATRIZ_174!$A:$A,0)),"") -> 0 | L50: =IFERROR(MATRIZ_174!O50,0) -> 0 | M50: 0 | N50: =IFERROR(ISCAM_Score!AC51,"") -> ⬜ Riesgo Latente | O50: LAMBAYEQUE
A51: 20487661539 | B51: ASOCIACION DE PRODUCTORES CACAOTEROS DEL DISTRITO DE HUARANG | C51: =IFERROR(ISCAM_Score!AL52,"—") -> 0 | D51: =IF(C51="—","— Sin Inst.2",IF(C51<34,"🔴 Crítico",IF(C51<67,"🟡 En desarrollo","🟢 Alineado"))) -> 🔴 Crítico | E51: =IFERROR(RANK(C51,C:C,-1),"") -> 1 | F51: =IFERROR(MATRIZ_174!L51,0) -> 0 | G51: =IFERROR(MATRIZ_174!M51,0) -> 0 | H51: 0 | I51: 0 | J51: 0 | K51: =IFERROR(INDEX(MATRIZ_174!$U:$U,MATCH(A51,MATRIZ_174!$A:$A,0)),"") -> 0 | L51: =IFERROR(MATRIZ_174!O51,0) -> 0 | M51: 0 | N51: =IFERROR(ISCAM_Score!AC52,"") -> ⬜ Riesgo Latente | O51: CAJAMARCA
A52: 20490726196 | B52: ASOCIACIÓN DE PRODUCTORES AGROPECUARIOS VALLESITO - CHAHUARE | C52: =IFERROR(ISCAM_Score!AL53,"—") -> 0 | D52: =IF(C52="—","— Sin Inst.2",IF(C52<34,"🔴 Crítico",IF(C52<67,"🟡 En desarrollo","🟢 Alineado"))) -> 🔴 Crítico | E52: =IFERROR(RANK(C52,C:C,-1),"") -> 1 | F52: =IFERROR(MATRIZ_174!L52,0) -> 0 | G52: =IFERROR(MATRIZ_174!M52,0) -> 0 | H52: 0 | I52: 0 | J52: 0 | K52: =IFERROR(INDEX(MATRIZ_174!$U:$U,MATCH(A52,MATRIZ_174!$A:$A,0)),"") -> 0 | L52: =IFERROR(MATRIZ_174!O52,0) -> 0 | M52: 0 | N52: =IFERROR(ISCAM_Score!AC53,"") -> ⬜ Riesgo Latente | O52: CUSCO
A53: 20493934822 | B53: COOPERATIVA AGRARIA NUEVO AMANECER LTDA. | C53: =IFERROR(ISCAM_Score!AL54,"—") -> 0 | D53: =IF(C53="—","— Sin Inst.2",IF(C53<34,"🔴 Crítico",IF(C53<67,"🟡 En desarrollo","🟢 Alineado"))) -> 🔴 Crítico | E53: =IFERROR(RANK(C53,C:C,-1),"") -> 1 | F53: 0 | G53: =IFERROR(MATRIZ_174!M53,0) -> 0 | H53: 0 | I53: 0 | J53: 0 | K53: =IFERROR(INDEX(MATRIZ_174!$U:$U,MATCH(A53,MATRIZ_174!$A:$A,0)),"") -> 0 | L53: =IFERROR(MATRIZ_174!O53,0) -> 0 | M53: 0 | N53: =IFERROR(ISCAM_Score!AC54,"") -> ⬜ Riesgo Latente | O53: SAN MARTIN
A54: 20493959574 | B54: COOPERATIVA AGRARIA DE SERVICIOS MUJERES TECNOLOGAS CACAOTER | C54: =IFERROR(ISCAM_Score!AL55,"—") -> 0 | D54: =IF(C54="—","— Sin Inst.2",IF(C54<34,"🔴 Crítico",IF(C54<67,"🟡 En desarrollo","🟢 Alineado"))) -> 🔴 Crítico | E54: =IFERROR(RANK(C54,C:C,-1),"") -> 1 | F54: =IFERROR(MATRIZ_174!L54,0) -> 0 | G54: =IFERROR(MATRIZ_174!M54,0) -> 0 | H54: 0 | I54: 0 | J54: 0 | K54: =IFERROR(INDEX(MATRIZ_174!$U:$U,MATCH(A54,MATRIZ_174!$A:$A,0)),"") -> 0 | L54: =IFERROR(MATRIZ_174!O54,0) -> 0 | M54: 0 | N54: =IFERROR(ISCAM_Score!AC55,"") -> ⬜ Riesgo Latente | O54: SAN MARTIN
A55: 20494126819 | B55: ASOCIACION DE PRODUCTORES AGROPECUARIOS RIO MAYO SHANAO | C55: =IFERROR(ISCAM_Score!AL56,"—") -> 0 | D55: =IF(C55="—","— Sin Inst.2",IF(C55<34,"🔴 Crítico",IF(C55<67,"🟡 En desarrollo","🟢 Alineado"))) -> 🔴 Crítico | E55: =IFERROR(RANK(C55,C:C,-1),"") -> 1 | F55: =IFERROR(MATRIZ_174!L55,0) -> 0 | G55: =IFERROR(MATRIZ_174!M55,0) -> 0 | H55: 0 | I55: 0 | J55: 0 | K55: =IFERROR(INDEX(MATRIZ_174!$U:$U,MATCH(A55,MATRIZ_174!$A:$A,0)),"") -> 0 | L55: =IFERROR(MATRIZ_174!O55,0) -> 0 | M55: 0 | N55: =IFERROR(ISCAM_Score!AC56,"") -> ⬜ Riesgo Latente | O55: SAN MARTIN
A56: 20494145791 | B56: ASOCIACION ECOLOGICA Y DE PRODUCTORES AGROPECUARIOS SAN JOSE | C56: =IFERROR(ISCAM_Score!AL57,"—") -> 0 | D56: =IF(C56="—","— Sin Inst.2",IF(C56<34,"🔴 Crítico",IF(C56<67,"🟡 En desarrollo","🟢 Alineado"))) -> 🔴 Crítico | E56: =IFERROR(RANK(C56,C:C,-1),"") -> 1 | F56: =IFERROR(MATRIZ_174!L56,0) -> 0 | G56: =IFERROR(MATRIZ_174!M56,0) -> 0 | H56: 0 | I56: 0 | J56: 0 | K56: =IFERROR(INDEX(MATRIZ_174!$U:$U,MATCH(A56,MATRIZ_174!$A:$A,0)),"") -> 0 | L56: =IFERROR(MATRIZ_174!O56,0) -> 0 | M56: 0 | N56: =IFERROR(ISCAM_Score!AC57,"") -> ⬜ Riesgo Latente | O56: LORETO
A57: 20494699690 | B57: ASOCIACION DE PRODUCTORES DE CACAO ECOLOGICO DE KIMBIRI - AP | C57: =IFERROR(ISCAM_Score!AL58,"—") -> 0 | D57: =IF(C57="—","— Sin Inst.2",IF(C57<34,"🔴 Crítico",IF(C57<67,"🟡 En desarrollo","🟢 Alineado"))) -> 🔴 Crítico | E57: =IFERROR(RANK(C57,C:C,-1),"") -> 1 | F57: =IFERROR(MATRIZ_174!L57,0) -> 0 | G57: =IFERROR(MATRIZ_174!M57,0) -> 0 | H57: 0 | I57: 0 | J57: 0 | K57: =IFERROR(INDEX(MATRIZ_174!$U:$U,MATCH(A57,MATRIZ_174!$A:$A,0)),"") -> 0 | L57: =IFERROR(MATRIZ_174!O57,0) -> 0 | M57: 0 | N57: =IFERROR(ISCAM_Score!AC58,"") -> ⬜ Riesgo Latente | O57: CUSCO
A58: 20525969551 | B58: COOPERATIVA AGRARIA DE PRODUCTORES DE BANANO, CACAO ORGANICO | C58: =IFERROR(ISCAM_Score!AL59,"—") -> 0 | D58: =IF(C58="—","— Sin Inst.2",IF(C58<34,"🔴 Crítico",IF(C58<67,"🟡 En desarrollo","🟢 Alineado"))) -> 🔴 Crítico | E58: =IFERROR(RANK(C58,C:C,-1),"") -> 1 | F58: 52920 | G58: =IFERROR(MATRIZ_174!M58,0) -> 50 | H58: 0 | I58: 0 | J58: 0 | K58: =IFERROR(INDEX(MATRIZ_174!$U:$U,MATCH(A58,MATRIZ_174!$A:$A,0)),"") -> 1 | L58: =IFERROR(MATRIZ_174!O58,0) -> 0 | M58: 0 | N58: =IFERROR(ISCAM_Score!AC59,"") -> ⬜ Riesgo Latente | O58: PIURA
A59: 20526514689 | B59: ASOCIACION DE PRODUCTORES AGROPECUARIOS ARTESANALES E INDUST | C59: =IFERROR(ISCAM_Score!AL60,"—") -> 0 | D59: =IF(C59="—","— Sin Inst.2",IF(C59<34,"🔴 Crítico",IF(C59<67,"🟡 En desarrollo","🟢 Alineado"))) -> 🔴 Crítico | E59: =IFERROR(RANK(C59,C:C,-1),"") -> 1 | F59: =IFERROR(MATRIZ_174!L59,0) -> 0 | G59: =IFERROR(MATRIZ_174!M59,0) -> 0 | H59: 0 | I59: 0 | J59: 0 | K59: =IFERROR(INDEX(MATRIZ_174!$U:$U,MATCH(A59,MATRIZ_174!$A:$A,0)),"") -> 0 | L59: =IFERROR(MATRIZ_174!O59,0) -> 0 | M59: 0 | N59: =IFERROR(ISCAM_Score!AC60,"") -> ⬜ Riesgo Latente | O59: PIURA
A60: 20527565376 | B60: COOPERATIVA AGRARIA CAFETALERA VALLE DE INCAHUASI | C60: =IFERROR(ISCAM_Score!AL61,"—") -> 0 | D60: =IF(C60="—","— Sin Inst.2",IF(C60<34,"🔴 Crítico",IF(C60<67,"🟡 En desarrollo","🟢 Alineado"))) -> 🔴 Crítico | E60: =IFERROR(RANK(C60,C:C,-1),"") -> 1 | F60: 5373465.5 | G60: =IFERROR(MATRIZ_174!M60,0) -> 50 | H60: 0 | I60: 0 | J60: 0 | K60: =IFERROR(INDEX(MATRIZ_174!$U:$U,MATCH(A60,MATRIZ_174!$A:$A,0)),"") -> 1 | L60: =IFERROR(MATRIZ_174!O60,0) -> 0 | M60: 0 | N60: =IFERROR(ISCAM_Score!AC61,"") -> ⬜ Riesgo Latente | O60: APURIMAC
A61: 20528996214 | B61: COOPERATIVA AGRARIA CAFETALERA MILAGROS - MONZON | C61: =IFERROR(ISCAM_Score!AL62,"—") -> 0 | D61: =IF(C61="—","— Sin Inst.2",IF(C61<34,"🔴 Crítico",IF(C61<67,"🟡 En desarrollo","🟢 Alineado"))) -> 🔴 Crítico | E61: =IFERROR(RANK(C61,C:C,-1),"") -> 1 | F61: =IFERROR(MATRIZ_174!L61,0) -> 0 | G61: =IFERROR(MATRIZ_174!M61,0) -> 0 | H61: 0 | I61: 0 | J61: 0 | K61: =IFERROR(INDEX(MATRIZ_174!$U:$U,MATCH(A61,MATRIZ_174!$A:$A,0)),"") -> 0 | L61: =IFERROR(MATRIZ_174!O61,0) -> 0 | M61: 0 | N61: =IFERROR(ISCAM_Score!AC62,"") -> ⬜ Riesgo Latente | O61: HUANUCO
A62: 20529801433 | B62: OPA MARAY-ULLMA SAN LORENZO | C62: =IFERROR(ISCAM_Score!AL63,"—") -> 0 | D62: =IF(C62="—","— Sin Inst.2",IF(C62<34,"🔴 Crítico",IF(C62<67,"🟡 En desarrollo","🟢 Alineado"))) -> 🔴 Crítico | E62: =IFERROR(RANK(C62,C:C,-1),"") -> 1 | F62: =IFERROR(MATRIZ_174!L62,0) -> 0 | G62: =IFERROR(MATRIZ_174!M62,0) -> 0 | H62: 0 | I62: 0 | J62: 0 | K62: =IFERROR(INDEX(MATRIZ_174!$U:$U,MATCH(A62,MATRIZ_174!$A:$A,0)),"") -> 0 | L62: =IFERROR(MATRIZ_174!O62,0) -> 0 | M62: 0 | N62: =IFERROR(ISCAM_Score!AC63,"") -> ⬜ Riesgo Latente | O62: PIURA
A63: 20529822350 | B63: OPA PAPAYO - LA LAGUNA | C63: =IFERROR(ISCAM_Score!AL64,"—") -> 0 | D63: =IF(C63="—","— Sin Inst.2",IF(C63<34,"🔴 Crítico",IF(C63<67,"🟡 En desarrollo","🟢 Alineado"))) -> 🔴 Crítico | E63: =IFERROR(RANK(C63,C:C,-1),"") -> 1 | F63: =IFERROR(MATRIZ_174!L63,0) -> 0 | G63: =IFERROR(MATRIZ_174!M63,0) -> 0 | H63: 0 | I63: 0 | J63: 0 | K63: =IFERROR(INDEX(MATRIZ_174!$U:$U,MATCH(A63,MATRIZ_174!$A:$A,0)),"") -> 0 | L63: =IFERROR(MATRIZ_174!O63,0) -> 0 | M63: 0 | N63: =IFERROR(ISCAM_Score!AC64,"") -> ⬜ Riesgo Latente | O63: PIURA
A64: 20531405723 | B64: COOPERATIVA DE SERVICIOS MULTIPLES ADISA NARANJOS | C64: =IFERROR(ISCAM_Score!AL65,"—") -> 0 | D64: =IF(C64="—","— Sin Inst.2",IF(C64<34,"🔴 Crítico",IF(C64<67,"🟡 En desarrollo","🟢 Alineado"))) -> 🔴 Crítico | E64: =IFERROR(RANK(C64,C:C,-1),"") -> 1 | F64: 0 | G64: =IFERROR(MATRIZ_174!M64,0) -> 0 | H64: 0 | I64: 0 | J64: 0 | K64: =IFERROR(INDEX(MATRIZ_174!$U:$U,MATCH(A64,MATRIZ_174!$A:$A,0)),"") -> 0 | L64: =IFERROR(MATRIZ_174!O64,0) -> 0 | M64: 0 | N64: =IFERROR(ISCAM_Score!AC65,"") -> ⬜ Riesgo Latente | O64: SAN MARTIN
A65: 20531441797 | B65: COOPERATIVA AGRARIA ALLIMA CACAO LTDA. | C65: =IFERROR(ISCAM_Score!AL66,"—") -> 0 | D65: =IF(C65="—","— Sin Inst.2",IF(C65<34,"🔴 Crítico",IF(C65<67,"🟡 En desarrollo","🟢 Alineado"))) -> 🔴 Crítico | E65: =IFERROR(RANK(C65,C:C,-1),"") -> 1 | F65: 0 | G65: =IFERROR(MATRIZ_174!M65,0) -> 0 | H65: 0 | I65: 0 | J65: 0 | K65: =IFERROR(INDEX(MATRIZ_174!$U:$U,MATCH(A65,MATRIZ_174!$A:$A,0)),"") -> 0 | L65: =IFERROR(MATRIZ_174!O65,0) -> 0 | M65: 0 | N65: =IFERROR(ISCAM_Score!AC66,"") -> ⬜ Riesgo Latente | O65: SAN MARTIN
A66: 20534524774 | B66: COOPERATIVA AGRARIA TROPICAL ECOLOGICA DE KIMBIRI | C66: =IFERROR(ISCAM_Score!AL67,"—") -> 0 | D66: =IF(C66="—","— Sin Inst.2",IF(C66<34,"🔴 Crítico",IF(C66<67,"🟡 En desarrollo","🟢 Alineado"))) -> 🔴 Crítico | E66: =IFERROR(RANK(C66,C:C,-1),"") -> 1 | F66: =IFERROR(MATRIZ_174!L66,0) -> 0 | G66: =IFERROR(MATRIZ_174!M66,0) -> 0 | H66: 0 | I66: 0 | J66: 0 | K66: =IFERROR(INDEX(MATRIZ_174!$U:$U,MATCH(A66,MATRIZ_174!$A:$A,0)),"") -> 0 | L66: =IFERROR(MATRIZ_174!O66,0) -> 0 | M66: 0 | N66: =IFERROR(ISCAM_Score!AC67,"") -> ⬜ Riesgo Latente | O66: CUSCO
A67: 20539205600 | B67: ASOCIACION DE PRODUCTORES Y EXPORTADORES DE CAFE RODRIGUEZ D | C67: =IFERROR(ISCAM_Score!AL68,"—") -> 0 | D67: =IF(C67="—","— Sin Inst.2",IF(C67<34,"🔴 Crítico",IF(C67<67,"🟡 En desarrollo","🟢 Alineado"))) -> 🔴 Crítico | E67: =IFERROR(RANK(C67,C:C,-1),"") -> 1 | F67: =IFERROR(MATRIZ_174!L67,0) -> 0 | G67: =IFERROR(MATRIZ_174!M67,0) -> 0 | H67: 0 | I67: 0 | J67: 0 | K67: =IFERROR(INDEX(MATRIZ_174!$U:$U,MATCH(A67,MATRIZ_174!$A:$A,0)),"") -> 0 | L67: =IFERROR(MATRIZ_174!O67,0) -> 0 | M67: 0 | N67: =IFERROR(ISCAM_Score!AC68,"") -> ⬜ Riesgo Latente | O67: AMAZONAS
A68: 20539241665 | B68: ASOCIACION DE PRODUCTORES DE CAFES ORGANICOS Y CAFES ESPECIA | C68: =IFERROR(ISCAM_Score!AL69,"—") -> 0 | D68: =IF(C68="—","— Sin Inst.2",IF(C68<34,"🔴 Crítico",IF(C68<67,"🟡 En desarrollo","🟢 Alineado"))) -> 🔴 Crítico | E68: =IFERROR(RANK(C68,C:C,-1),"") -> 1 | F68: =IFERROR(MATRIZ_174!L68,0) -> 0 | G68: =IFERROR(MATRIZ_174!M68,0) -> 0 | H68: 0 | I68: 0 | J68: 0 | K68: =IFERROR(INDEX(MATRIZ_174!$U:$U,MATCH(A68,MATRIZ_174!$A:$A,0)),"") -> 0 | L68: =IFERROR(MATRIZ_174!O68,0) -> 0 | M68: 0 | N68: =IFERROR(ISCAM_Score!AC69,"") -> ⬜ Riesgo Latente | O68: AMAZONAS
A69: 20539280644 | B69: ASOCIACION DE PEQUEÑOS AGRICULTORES PARA LA PRODUCCION ECOLO | C69: =IFERROR(ISCAM_Score!AL70,"—") -> 0 | D69: =IF(C69="—","— Sin Inst.2",IF(C69<34,"🔴 Crítico",IF(C69<67,"🟡 En desarrollo","🟢 Alineado"))) -> 🔴 Crítico | E69: =IFERROR(RANK(C69,C:C,-1),"") -> 1 | F69: =IFERROR(MATRIZ_174!L69,0) -> 0 | G69: =IFERROR(MATRIZ_174!M69,0) -> 0 | H69: 0 | I69: 0 | J69: 0 | K69: =IFERROR(INDEX(MATRIZ_174!$U:$U,MATCH(A69,MATRIZ_174!$A:$A,0)),"") -> 0 | L69: =IFERROR(MATRIZ_174!O69,0) -> 0 | M69: 0 | N69: =IFERROR(ISCAM_Score!AC70,"") -> ⬜ Riesgo Latente | O69: LAMBAYEQUE
A70: 20542209951 | B70: COOPERATIVA AGRARIA VALLE GRANDE | C70: =IFERROR(ISCAM_Score!AL71,"—") -> 0 | D70: =IF(C70="—","— Sin Inst.2",IF(C70<34,"🔴 Crítico",IF(C70<67,"🟡 En desarrollo","🟢 Alineado"))) -> 🔴 Crítico | E70: =IFERROR(RANK(C70,C:C,-1),"") -> 1 | F70: 7878141.7 | G70: =IFERROR(MATRIZ_174!M70,0) -> 59.5 | H70: 0 | I70: 0 | J70: 0 | K70: =IFERROR(INDEX(MATRIZ_174!$U:$U,MATCH(A70,MATRIZ_174!$A:$A,0)),"") -> 1 | L70: =IFERROR(MATRIZ_174!O70,0) -> 0 | M70: 0 | N70: =IFERROR(ISCAM_Score!AC71,"") -> 🔴 Riesgo Crítico | O70: SAN MARTIN
A71: 20542251990 | B71: ASOCIACION DE MUJERES EMPRENDEDORAS DE NUEVO PROGRESO | C71: =IFERROR(ISCAM_Score!AL72,"—") -> 0 | D71: =IF(C71="—","— Sin Inst.2",IF(C71<34,"🔴 Crítico",IF(C71<67,"🟡 En desarrollo","🟢 Alineado"))) -> 🔴 Crítico | E71: =IFERROR(RANK(C71,C:C,-1),"") -> 1 | F71: =IFERROR(MATRIZ_174!L71,0) -> 0 | G71: =IFERROR(MATRIZ_174!M71,0) -> 0 | H71: 0 | I71: 0 | J71: 0 | K71: =IFERROR(INDEX(MATRIZ_174!$U:$U,MATCH(A71,MATRIZ_174!$A:$A,0)),"") -> 0 | L71: =IFERROR(MATRIZ_174!O71,0) -> 0 | M71: 0 | N71: =IFERROR(ISCAM_Score!AC72,"") -> ⬜ Riesgo Latente | O71: SAN MARTIN
A72: 20542257416 | B72: EMPRESA INDUSTRIAL ORO VERDE SOCIEDAD ANONIMA CERRADA | C72: =IFERROR(ISCAM_Score!AL73,"—") -> 0 | D72: =IF(C72="—","— Sin Inst.2",IF(C72<34,"🔴 Crítico",IF(C72<67,"🟡 En desarrollo","🟢 Alineado"))) -> 🔴 Crítico | E72: =IFERROR(RANK(C72,C:C,-1),"") -> 1 | F72: 1413037.5 | G72: =IFERROR(MATRIZ_174!M72,0) -> 50 | H72: 0 | I72: 0 | J72: 0 | K72: =IFERROR(INDEX(MATRIZ_174!$U:$U,MATCH(A72,MATRIZ_174!$A:$A,0)),"") -> 1 | L72: =IFERROR(MATRIZ_174!O72,0) -> 0 | M72: 0 | N72: =IFERROR(ISCAM_Score!AC73,"") -> ⬜ Riesgo Latente | O72: SAN MARTIN
A73: 20542264544 | B73: COOPERATIVA AGRARIA VALLE DEL BIAVO LTDA | C73: =IFERROR(ISCAM_Score!AL74,"—") -> 0 | D73: =IF(C73="—","— Sin Inst.2",IF(C73<34,"🔴 Crítico",IF(C73<67,"🟡 En desarrollo","🟢 Alineado"))) -> 🔴 Crítico | E73: =IFERROR(RANK(C73,C:C,-1),"") -> 1 | F73: 1187600.5 | G73: =IFERROR(MATRIZ_174!M73,0) -> 100 | H73: 0 | I73: 0 | J73: 0 | K73: =IFERROR(INDEX(MATRIZ_174!$U:$U,MATCH(A73,MATRIZ_174!$A:$A,0)),"") -> 1 | L73: =IFERROR(MATRIZ_174!O73,0) -> 0 | M73: 0 | N73: =IFERROR(ISCAM_Score!AC74,"") -> 🔴 Riesgo Crítico | O73: SAN MARTIN
A74: 20542289024 | B74: CUENCAS DEL HUALLAGA ASOCIACION DE PRODUCTORES AGROPECUARIOS | C74: =IFERROR(ISCAM_Score!AL75,"—") -> 0 | D74: =IF(C74="—","— Sin Inst.2",IF(C74<34,"🔴 Crítico",IF(C74<67,"🟡 En desarrollo","🟢 Alineado"))) -> 🔴 Crítico | E74: =IFERROR(RANK(C74,C:C,-1),"") -> 1 | F74: 12142716 | G74: =IFERROR(MATRIZ_174!M74,0) -> 50 | H74: 0 | I74: 0 | J74: 0 | K74: =IFERROR(INDEX(MATRIZ_174!$U:$U,MATCH(A74,MATRIZ_174!$A:$A,0)),"") -> 1 | L74: =IFERROR(MATRIZ_174!O74,0) -> 0 | M74: 0 | N74: =IFERROR(ISCAM_Score!AC75,"") -> ⬜ Riesgo Latente | O74: SAN MARTIN
A75: 20542299330 | B75: ASOCIACION DE PRODUCTORES AGROPECUARIOS DE SHUCUSHYACU FLOR | C75: =IFERROR(ISCAM_Score!AL76,"—") -> 0 | D75: =IF(C75="—","— Sin Inst.2",IF(C75<34,"🔴 Crítico",IF(C75<67,"🟡 En desarrollo","🟢 Alineado"))) -> 🔴 Crítico | E75: =IFERROR(RANK(C75,C:C,-1),"") -> 1 | F75: =IFERROR(MATRIZ_174!L75,0) -> 0 | G75: =IFERROR(MATRIZ_174!M75,0) -> 0 | H75: 0 | I75: 0 | J75: 0 | K75: =IFERROR(INDEX(MATRIZ_174!$U:$U,MATCH(A75,MATRIZ_174!$A:$A,0)),"") -> 0 | L75: =IFERROR(MATRIZ_174!O75,0) -> 0 | M75: 0 | N75: =IFERROR(ISCAM_Score!AC76,"") -> ⬜ Riesgo Latente | O75: LORETO
A76: 20542311569 | B76: COOPERATIVA AGRARIA ACHUAR SHAKAIM LTDA | C76: =IFERROR(ISCAM_Score!AL77,"—") -> 0 | D76: =IF(C76="—","— Sin Inst.2",IF(C76<34,"🔴 Crítico",IF(C76<67,"🟡 En desarrollo","🟢 Alineado"))) -> 🔴 Crítico | E76: =IFERROR(RANK(C76,C:C,-1),"") -> 1 | F76: =IFERROR(MATRIZ_174!L76,0) -> 0 | G76: =IFERROR(MATRIZ_174!M76,0) -> 0 | H76: 0 | I76: 0 | J76: 0 | K76: =IFERROR(INDEX(MATRIZ_174!$U:$U,MATCH(A76,MATRIZ_174!$A:$A,0)),"") -> 0 | L76: =IFERROR(MATRIZ_174!O76,0) -> 0 | M76: 0 | N76: =IFERROR(ISCAM_Score!AC77,"") -> ⬜ Riesgo Latente | O76: LORETO
A77: 20542380455 | B77: COOPERATIVA AGRARIA ECOFOREST | C77: =IFERROR(ISCAM_Score!AL78,"—") -> 0 | D77: =IF(C77="—","— Sin Inst.2",IF(C77<34,"🔴 Crítico",IF(C77<67,"🟡 En desarrollo","🟢 Alineado"))) -> 🔴 Crítico | E77: =IFERROR(RANK(C77,C:C,-1),"") -> 1 | F77: 8445503.2 | G77: =IFERROR(MATRIZ_174!M77,0) -> 50 | H77: 0 | I77: 0 | J77: 0 | K77: =IFERROR(INDEX(MATRIZ_174!$U:$U,MATCH(A77,MATRIZ_174!$A:$A,0)),"") -> 1 | L77: =IFERROR(MATRIZ_174!O77,0) -> 0 | M77: 0 | N77: =IFERROR(ISCAM_Score!AC78,"") -> ⬜ Riesgo Latente | O77: CAJAMARCA
A78: 20542482886 | B78: COOPERATIVA AGROINDUSTRIAL APCCA | C78: =IFERROR(ISCAM_Score!AL79,"—") -> 0 | D78: =IF(C78="—","— Sin Inst.2",IF(C78<34,"🔴 Crítico",IF(C78<67,"🟡 En desarrollo","🟢 Alineado"))) -> 🔴 Crítico | E78: =IFERROR(RANK(C78,C:C,-1),"") -> 1 | F78: =IFERROR(MATRIZ_174!L78,0) -> 0 | G78: =IFERROR(MATRIZ_174!M78,0) -> 0 | H78: 0 | I78: 0 | J78: 0 | K78: =IFERROR(INDEX(MATRIZ_174!$U:$U,MATCH(A78,MATRIZ_174!$A:$A,0)),"") -> 0 | L78: =IFERROR(MATRIZ_174!O78,0) -> 0 | M78: 0 | N78: =IFERROR(ISCAM_Score!AC79,"") -> ⬜ Riesgo Latente | O78: HUANUCO
A79: 20542825163 | B79: COOPERATIVA AGRARIA CACAO FINO AGROBOSQUE | C79: =IFERROR(ISCAM_Score!AL80,"—") -> 0 | D79: =IF(C79="—","— Sin Inst.2",IF(C79<34,"🔴 Crítico",IF(C79<67,"🟡 En desarrollo","🟢 Alineado"))) -> 🔴 Crítico | E79: =IFERROR(RANK(C79,C:C,-1),"") -> 1 | F79: 0 | G79: =IFERROR(MATRIZ_174!M79,0) -> 0 | H79: 0 | I79: 0 | J79: 0 | K79: =IFERROR(INDEX(MATRIZ_174!$U:$U,MATCH(A79,MATRIZ_174!$A:$A,0)),"") -> 0 | L79: =IFERROR(MATRIZ_174!O79,0) -> 0 | M79: 0 | N79: =IFERROR(ISCAM_Score!AC80,"") -> ⬜ Riesgo Latente | O79: MADRE DE DIOS
A80: 20561140091 | B80: COOPERATIVA AGRARIA ECOLOGICA CAFETALERA DE LONYA GRANDE | C80: =IFERROR(ISCAM_Score!AL81,"—") -> 0 | D80: =IF(C80="—","— Sin Inst.2",IF(C80<34,"🔴 Crítico",IF(C80<67,"🟡 En desarrollo","🟢 Alineado"))) -> 🔴 Crítico | E80: =IFERROR(RANK(C80,C:C,-1),"") -> 1 | F80: 0 | G80: =IFERROR(MATRIZ_174!M80,0) -> 0 | H80: 0 | I80: 0 | J80: 0 | K80: =IFERROR(INDEX(MATRIZ_174!$U:$U,MATCH(A80,MATRIZ_174!$A:$A,0)),"") -> 0 | L80: =IFERROR(MATRIZ_174!O80,0) -> 0 | M80: 0 | N80: =IFERROR(ISCAM_Score!AC81,"") -> 🔴 Riesgo Crítico | O80: AMAZONAS
A81: 20564032485 | B81: ASOCIACION DE PRODUCTORES ECOLOGICOS DE CACAO MEDIO URUBAMBA | C81: =IFERROR(ISCAM_Score!AL82,"—") -> 0 | D81: =IF(C81="—","— Sin Inst.2",IF(C81<34,"🔴 Crítico",IF(C81<67,"🟡 En desarrollo","🟢 Alineado"))) -> 🔴 Crítico | E81: =IFERROR(RANK(C81,C:C,-1),"") -> 1 | F81: 0 | G81: =IFERROR(MATRIZ_174!M81,0) -> 0 | H81: 0 | I81: 0 | J81: 0 | K81: =IFERROR(INDEX(MATRIZ_174!$U:$U,MATCH(A81,MATRIZ_174!$A:$A,0)),"") -> 0 | L81: =IFERROR(MATRIZ_174!O81,0) -> 0 | M81: 0 | N81: =IFERROR(ISCAM_Score!AC82,"") -> ⬜ Riesgo Latente | O81: CUSCO
A82: 20568071281 | B82: COOPERATIVA AGRARIA CAFETALERA CEPRO YANESHA | C82: =IFERROR(ISCAM_Score!AL83,"—") -> 0 | D82: =IF(C82="—","— Sin Inst.2",IF(C82<34,"🔴 Crítico",IF(C82<67,"🟡 En desarrollo","🟢 Alineado"))) -> 🔴 Crítico | E82: =IFERROR(RANK(C82,C:C,-1),"") -> 1 | F82: 717861.85 | G82: =IFERROR(MATRIZ_174!M82,0) -> 50 | H82: 0 | I82: 0 | J82: 0 | K82: =IFERROR(INDEX(MATRIZ_174!$U:$U,MATCH(A82,MATRIZ_174!$A:$A,0)),"") -> 1 | L82: =IFERROR(MATRIZ_174!O82,0) -> 0 | M82: 0 | N82: =IFERROR(ISCAM_Score!AC83,"") -> ⬜ Riesgo Latente | O82: PASCO
A83: 20568080948 | B83: CONSEJO REGULADOR DE LA DENOMINACION DE ORIGEN CAFE VILLA RI | C83: =IFERROR(ISCAM_Score!AL84,"—") -> 0 | D83: =IF(C83="—","— Sin Inst.2",IF(C83<34,"🔴 Crítico",IF(C83<67,"🟡 En desarrollo","🟢 Alineado"))) -> 🔴 Crítico | E83: =IFERROR(RANK(C83,C:C,-1),"") -> 1 | F83: =IFERROR(MATRIZ_174!L83,0) -> 0 | G83: =IFERROR(MATRIZ_174!M83,0) -> 0 | H83: 0 | I83: 0 | J83: 0 | K83: =IFERROR(INDEX(MATRIZ_174!$U:$U,MATCH(A83,MATRIZ_174!$A:$A,0)),"") -> 0 | L83: =IFERROR(MATRIZ_174!O83,0) -> 0 | M83: 0 | N83: =IFERROR(ISCAM_Score!AC84,"") -> ⬜ Riesgo Latente | O83: PASCO
A84: 20568190450 | B84: COOPERATIVA AGRARIA KEMITO ENE LTDA. - KEMITO ENE | C84: =IFERROR(ISCAM_Score!AL85,"—") -> 0 | D84: =IF(C84="—","— Sin Inst.2",IF(C84<34,"🔴 Crítico",IF(C84<67,"🟡 En desarrollo","🟢 Alineado"))) -> 🔴 Crítico | E84: =IFERROR(RANK(C84,C:C,-1),"") -> 1 | F84: =IFERROR(MATRIZ_174!L84,0) -> 0 | G84: =IFERROR(MATRIZ_174!M84,0) -> 0 | H84: 0 | I84: 0 | J84: 0 | K84: =IFERROR(INDEX(MATRIZ_174!$U:$U,MATCH(A84,MATRIZ_174!$A:$A,0)),"") -> 0 | L84: =IFERROR(MATRIZ_174!O84,0) -> 0 | M84: 0 | N84: =IFERROR(ISCAM_Score!AC85,"") -> ⬜ Riesgo Latente | O84: JUNIN
A85: 20568194951 | B85: ASOCIACION DE PRODUCTORES AGROSOSTENIBLES VILLA ECOLOGICA PE | C85: =IFERROR(ISCAM_Score!AL86,"—") -> 0 | D85: =IF(C85="—","— Sin Inst.2",IF(C85<34,"🔴 Crítico",IF(C85<67,"🟡 En desarrollo","🟢 Alineado"))) -> 🔴 Crítico | E85: =IFERROR(RANK(C85,C:C,-1),"") -> 1 | F85: 2677512.6 | G85: =IFERROR(MATRIZ_174!M85,0) -> 50 | H85: 0 | I85: 0 | J85: 0 | K85: =IFERROR(INDEX(MATRIZ_174!$U:$U,MATCH(A85,MATRIZ_174!$A:$A,0)),"") -> 1 | L85: =IFERROR(MATRIZ_174!O85,0) -> 0 | M85: 0 | N85: =IFERROR(ISCAM_Score!AC86,"") -> ⬜ Riesgo Latente | O85: JUNIN
A86: 20568428375 | B86: COOPERATIVA AGRARIA ASHANINKA DEL VALLE PICHIS | C86: =IFERROR(ISCAM_Score!AL87,"—") -> 0 | D86: =IF(C86="—","— Sin Inst.2",IF(C86<34,"🔴 Crítico",IF(C86<67,"🟡 En desarrollo","🟢 Alineado"))) -> 🔴 Crítico | E86: =IFERROR(RANK(C86,C:C,-1),"") -> 1 | F86: =IFERROR(MATRIZ_174!L86,0) -> 0 | G86: =IFERROR(MATRIZ_174!M86,0) -> 0 | H86: 0 | I86: 0 | J86: 0 | K86: =IFERROR(INDEX(MATRIZ_174!$U:$U,MATCH(A86,MATRIZ_174!$A:$A,0)),"") -> 0 | L86: =IFERROR(MATRIZ_174!O86,0) -> 0 | M86: 0 | N86: =IFERROR(ISCAM_Score!AC87,"") -> ⬜ Riesgo Latente | O86: PASCO
A87: 20568549083 | B87: COOPERATIVA AGRARIA INDUSTRIAL APASC SANCORE-PALCAZU LTDA | C87: =IFERROR(ISCAM_Score!AL88,"—") -> 0 | D87: =IF(C87="—","— Sin Inst.2",IF(C87<34,"🔴 Crítico",IF(C87<67,"🟡 En desarrollo","🟢 Alineado"))) -> 🔴 Crítico | E87: =IFERROR(RANK(C87,C:C,-1),"") -> 1 | F87: =IFERROR(MATRIZ_174!L87,0) -> 0 | G87: =IFERROR(MATRIZ_174!M87,0) -> 0 | H87: 0 | I87: 0 | J87: 0 | K87: =IFERROR(INDEX(MATRIZ_174!$U:$U,MATCH(A87,MATRIZ_174!$A:$A,0)),"") -> 0 | L87: =IFERROR(MATRIZ_174!O87,0) -> 0 | M87: 0 | N87: =IFERROR(ISCAM_Score!AC88,"") -> ⬜ Riesgo Latente | O87: PASCO
A88: 20568560133 | B88: COOPERATIVA AGRARIA ECOLOGICO ALTO PALCAZU LAGUNA RAYA | C88: =IFERROR(ISCAM_Score!AL89,"—") -> 0 | D88: =IF(C88="—","— Sin Inst.2",IF(C88<34,"🔴 Crítico",IF(C88<67,"🟡 En desarrollo","🟢 Alineado"))) -> 🔴 Crítico | E88: =IFERROR(RANK(C88,C:C,-1),"") -> 1 | F88: =IFERROR(MATRIZ_174!L88,0) -> 0 | G88: =IFERROR(MATRIZ_174!M88,0) -> 0 | H88: 0 | I88: 0 | J88: 0 | K88: =IFERROR(INDEX(MATRIZ_174!$U:$U,MATCH(A88,MATRIZ_174!$A:$A,0)),"") -> 0 | L88: =IFERROR(MATRIZ_174!O88,0) -> 0 | M88: 0 | N88: =IFERROR(ISCAM_Score!AC89,"") -> ⬜ Riesgo Latente | O88: PASCO
A89: 20568567731 | B89: COOPERATIVA AGRARIA VILLA RICA GOLDEN COFFEE LTDA. | C89: =IFERROR(ISCAM_Score!AL90,"—") -> 0 | D89: =IF(C89="—","— Sin Inst.2",IF(C89<34,"🔴 Crítico",IF(C89<67,"🟡 En desarrollo","🟢 Alineado"))) -> 🔴 Crítico | E89: =IFERROR(RANK(C89,C:C,-1),"") -> 1 | F89: 0 | G89: =IFERROR(MATRIZ_174!M89,0) -> 0 | H89: 0 | I89: 0 | J89: 0 | K89: =IFERROR(INDEX(MATRIZ_174!$U:$U,MATCH(A89,MATRIZ_174!$A:$A,0)),"") -> 0 | L89: =IFERROR(MATRIZ_174!O89,0) -> 0 | M89: 0 | N89: =IFERROR(ISCAM_Score!AC90,"") -> ⬜ Riesgo Latente | O89: PASCO
A90: 20568609833 | B90: ASOCIACION DE MUJERES PRODUCTORAS ARTESANAS CACAO JENTARI - | C90: =IFERROR(ISCAM_Score!AL91,"—") -> 0 | D90: =IF(C90="—","— Sin Inst.2",IF(C90<34,"🔴 Crítico",IF(C90<67,"🟡 En desarrollo","🟢 Alineado"))) -> 🔴 Crítico | E90: =IFERROR(RANK(C90,C:C,-1),"") -> 1 | F90: =IFERROR(MATRIZ_174!L90,0) -> 0 | G90: =IFERROR(MATRIZ_174!M90,0) -> 0 | H90: 0 | I90: 0 | J90: 0 | K90: =IFERROR(INDEX(MATRIZ_174!$U:$U,MATCH(A90,MATRIZ_174!$A:$A,0)),"") -> 0 | L90: =IFERROR(MATRIZ_174!O90,0) -> 0 | M90: 0 | N90: =IFERROR(ISCAM_Score!AC91,"") -> ⬜ Riesgo Latente | O90: JUNIN
A91: 20568962282 | B91: ASOCIACIÓN DE PRODUCTORES CENTRO COFFEE | C91: =IFERROR(ISCAM_Score!AL92,"—") -> 0 | D91: =IF(C91="—","— Sin Inst.2",IF(C91<34,"🔴 Crítico",IF(C91<67,"🟡 En desarrollo","🟢 Alineado"))) -> 🔴 Crítico | E91: =IFERROR(RANK(C91,C:C,-1),"") -> 1 | F91: 0 | G91: =IFERROR(MATRIZ_174!M91,0) -> 0 | H91: 0 | I91: 0 | J91: 0 | K91: =IFERROR(INDEX(MATRIZ_174!$U:$U,MATCH(A91,MATRIZ_174!$A:$A,0)),"") -> 0 | L91: =IFERROR(MATRIZ_174!O91,0) -> 0 | M91: 0 | N91: =IFERROR(ISCAM_Score!AC92,"") -> ⬜ Riesgo Latente | O91: JUNIN
A92: 20570706927 | B92: COOPERATIVA AGRARIA RUTAS DEL INCA | C92: =IFERROR(ISCAM_Score!AL93,"—") -> 0 | D92: =IF(C92="—","— Sin Inst.2",IF(C92<34,"🔴 Crítico",IF(C92<67,"🟡 En desarrollo","🟢 Alineado"))) -> 🔴 Crítico | E92: =IFERROR(RANK(C92,C:C,-1),"") -> 1 | F92: 4792670.9 | G92: =IFERROR(MATRIZ_174!M92,0) -> 50 | H92: 0 | I92: 0 | J92: 0 | K92: =IFERROR(INDEX(MATRIZ_174!$U:$U,MATCH(A92,MATRIZ_174!$A:$A,0)),"") -> 1 | L92: =IFERROR(MATRIZ_174!O92,0) -> 0 | M92: 0 | N92: =IFERROR(ISCAM_Score!AC93,"") -> ⬜ Riesgo Latente | O92: CAJAMARCA
A93: 20572111131 | B93: ASOCIACION DE MUJERES ORGANIZADAS CHOCO WARMIS | C93: =IFERROR(ISCAM_Score!AL94,"—") -> 0 | D93: =IF(C93="—","— Sin Inst.2",IF(C93<34,"🔴 Crítico",IF(C93<67,"🟡 En desarrollo","🟢 Alineado"))) -> 🔴 Crítico | E93: =IFERROR(RANK(C93,C:C,-1),"") -> 1 | F93: =IFERROR(MATRIZ_174!L93,0) -> 0 | G93: =IFERROR(MATRIZ_174!M93,0) -> 0 | H93: 0 | I93: 0 | J93: 0 | K93: =IFERROR(INDEX(MATRIZ_174!$U:$U,MATCH(A93,MATRIZ_174!$A:$A,0)),"") -> 0 | L93: =IFERROR(MATRIZ_174!O93,0) -> 0 | M93: 0 | N93: =IFERROR(ISCAM_Score!AC94,"") -> ⬜ Riesgo Latente | O93: SAN MARTIN
A94: 20572190251 | B94: CENTRAL DE COOPERATIVAS AGRARIAS CACAO AROMA DE TOCACHE LTDA | C94: =IFERROR(ISCAM_Score!AL95,"—") -> 0 | D94: =IF(C94="—","— Sin Inst.2",IF(C94<34,"🔴 Crítico",IF(C94<67,"🟡 En desarrollo","🟢 Alineado"))) -> 🔴 Crítico | E94: =IFERROR(RANK(C94,C:C,-1),"") -> 1 | F94: 1888972.4 | G94: =IFERROR(MATRIZ_174!M94,0) -> 50 | H94: 0 | I94: 0 | J94: 0 | K94: =IFERROR(INDEX(MATRIZ_174!$U:$U,MATCH(A94,MATRIZ_174!$A:$A,0)),"") -> 1 | L94: =IFERROR(MATRIZ_174!O94,0) -> 0 | M94: 0 | N94: =IFERROR(ISCAM_Score!AC95,"") -> ⬜ Riesgo Latente | O94: SAN MARTIN
A95: 20573049102 | B95: COOPERATIVA AGRARIA CACAOTERA PUERTO INCA | C95: =IFERROR(ISCAM_Score!AL96,"—") -> 0 | D95: =IF(C95="—","— Sin Inst.2",IF(C95<34,"🔴 Crítico",IF(C95<67,"🟡 En desarrollo","🟢 Alineado"))) -> 🔴 Crítico | E95: =IFERROR(RANK(C95,C:C,-1),"") -> 1 | F95: =IFERROR(MATRIZ_174!L95,0) -> 0 | G95: =IFERROR(MATRIZ_174!M95,0) -> 0 | H95: 0 | I95: 0 | J95: 0 | K95: =IFERROR(INDEX(MATRIZ_174!$U:$U,MATCH(A95,MATRIZ_174!$A:$A,0)),"") -> 0 | L95: =IFERROR(MATRIZ_174!O95,0) -> 0 | M95: 0 | N95: =IFERROR(ISCAM_Score!AC96,"") -> ⬜ Riesgo Latente | O95: HUANUCO
A96: 20573057385 | B96: COOPERATIVA AGRARIA PARAISO | C96: =IFERROR(ISCAM_Score!AL97,"—") -> 0 | D96: =IF(C96="—","— Sin Inst.2",IF(C96<34,"🔴 Crítico",IF(C96<67,"🟡 En desarrollo","🟢 Alineado"))) -> 🔴 Crítico | E96: =IFERROR(RANK(C96,C:C,-1),"") -> 1 | F96: 0 | G96: =IFERROR(MATRIZ_174!M96,0) -> 0 | H96: 0 | I96: 0 | J96: 0 | K96: =IFERROR(INDEX(MATRIZ_174!$U:$U,MATCH(A96,MATRIZ_174!$A:$A,0)),"") -> 0 | L96: =IFERROR(MATRIZ_174!O96,0) -> 0 | M96: 0 | N96: =IFERROR(ISCAM_Score!AC97,"") -> ⬜ Riesgo Latente | O96: HUANUCO
A97: 20573138202 | B97: ASOCIACION DE PRODUCTORES AGROPECUARIOS Y FORESTALES EL ALVA | C97: =IFERROR(ISCAM_Score!AL98,"—") -> 0 | D97: =IF(C97="—","— Sin Inst.2",IF(C97<34,"🔴 Crítico",IF(C97<67,"🟡 En desarrollo","🟢 Alineado"))) -> 🔴 Crítico | E97: =IFERROR(RANK(C97,C:C,-1),"") -> 1 | F97: =IFERROR(MATRIZ_174!L97,0) -> 0 | G97: =IFERROR(MATRIZ_174!M97,0) -> 0 | H97: 0 | I97: 0 | J97: 0 | K97: =IFERROR(INDEX(MATRIZ_174!$U:$U,MATCH(A97,MATRIZ_174!$A:$A,0)),"") -> 0 | L97: =IFERROR(MATRIZ_174!O97,0) -> 0 | M97: 0 | N97: =IFERROR(ISCAM_Score!AC98,"") -> ⬜ Riesgo Latente | O97: HUANUCO
A98: 20573260008 | B98: COOPERATIVA AGRARIA AUCAYACU | C98: =IFERROR(ISCAM_Score!AL99,"—") -> 0 | D98: =IF(C98="—","— Sin Inst.2",IF(C98<34,"🔴 Crítico",IF(C98<67,"🟡 En desarrollo","🟢 Alineado"))) -> 🔴 Crítico | E98: =IFERROR(RANK(C98,C:C,-1),"") -> 1 | F98: =IFERROR(MATRIZ_174!L98,0) -> 0 | G98: =IFERROR(MATRIZ_174!M98,0) -> 0 | H98: 0 | I98: 0 | J98: 0 | K98: =IFERROR(INDEX(MATRIZ_174!$U:$U,MATCH(A98,MATRIZ_174!$A:$A,0)),"") -> 0 | L98: =IFERROR(MATRIZ_174!O98,0) -> 0 | M98: 0 | N98: =IFERROR(ISCAM_Score!AC99,"") -> ⬜ Riesgo Latente | O98: HUANUCO
A99: 20573344791 | B99: ASOCIACION AGROECOLOGICO HUANGANAPAMPA | C99: =IFERROR(ISCAM_Score!AL100,"—") -> 0 | D99: =IF(C99="—","— Sin Inst.2",IF(C99<34,"🔴 Crítico",IF(C99<67,"🟡 En desarrollo","🟢 Alineado"))) -> 🔴 Crítico | E99: =IFERROR(RANK(C99,C:C,-1),"") -> 1 | F99: =IFERROR(MATRIZ_174!L99,0) -> 0 | G99: =IFERROR(MATRIZ_174!M99,0) -> 0 | H99: 0 | I99: 0 | J99: 0 | K99: =IFERROR(INDEX(MATRIZ_174!$U:$U,MATCH(A99,MATRIZ_174!$A:$A,0)),"") -> 0 | L99: =IFERROR(MATRIZ_174!O99,0) -> 0 | M99: 0 | N99: =IFERROR(ISCAM_Score!AC100,"") -> ⬜ Riesgo Latente | O99: HUANUCO
A100: 20574797013 | B100: ASOCIACION DE PRODUCTORES AGROPECUARIOS DE PARAISO CENTRAL | C100: =IFERROR(ISCAM_Score!AL101,"—") -> 0 | D100: =IF(C100="—","— Sin Inst.2",IF(C100<34,"🔴 Crítico",IF(C100<67,"🟡 En desarrollo","🟢 Alineado"))) -> 🔴 Crítico | E100: =IFERROR(RANK(C100,C:C,-1),"") -> 1 | F100: =IFERROR(MATRIZ_174!L100,0) -> 0 | G100: =IFERROR(MATRIZ_174!M100,0) -> 0 | H100: 0 | I100: 0 | J100: 0 | K100: =IFERROR(INDEX(MATRIZ_174!$U:$U,MATCH(A100,MATRIZ_174!$A:$A,0)),"") -> 0 | L100: =IFERROR(MATRIZ_174!O100,0) -> 0 | M100: 0 | N100: =IFERROR(ISCAM_Score!AC101,"") -> ⬜ Riesgo Latente | O100: CUSCO
...

Sheet RADAR_BRECHAS
A1: RADAR DE BRECHAS — Score promedio por departamento y dimensión
A2: Departamento / Dimensión | B2: D1 | C2: D2 | D2: D3 | E2: D4 | F2: D5 | G2: D6 | H2: D7 | I2: D8 | J2: D9 | K2: D10 | L2: D11 | M2: PVE Promedio
A3: SAN MARTIN | B3: =0 -> 0 | C3: =IFERROR(AVERAGEIF(MATRIZ_174!C:C,A3,SCORECARDS!H:H),0) -> 0 | D3: =IFERROR(AVERAGEIF(MATRIZ_174!$C:$C,A3,ISCAM_Score!$G:$G),0) -> 0.16666667 | E3: =0 -> 0 | F3: =IFERROR(AVERAGEIF(MATRIZ_174!C:C,A3,SCORECARDS!I:I),0) -> 0 | G3: =IFERROR(AVERAGEIF(MATRIZ_174!C:C,A3,SCORECARDS!J:J),0) -> 0 | H3: =IFERROR(AVERAGEIF(MATRIZ_174!C:C,A3,SCORECARDS!K:K),0) -> 0.375 | I3: =0 -> 0 | J3: =0 -> 0 | K3: =0 -> 0 | L3: =0 -> 0 | M3: =IFERROR(AVERAGE(B3:L3),0) -> 0.049242424
A4: JUNIN | B4: =0 -> 0 | C4: =IFERROR(AVERAGEIF(MATRIZ_174!C:C,A4,SCORECARDS!H:H),0) -> 0 | D4: =IFERROR(AVERAGEIF(MATRIZ_174!$C:$C,A4,ISCAM_Score!$G:$G),0) -> 0.2173913 | E4: =0 -> 0 | F4: =IFERROR(AVERAGEIF(MATRIZ_174!C:C,A4,SCORECARDS!I:I),0) -> 0 | G4: =IFERROR(AVERAGEIF(MATRIZ_174!C:C,A4,SCORECARDS!J:J),0) -> 0 | H4: =IFERROR(AVERAGEIF(MATRIZ_174!C:C,A4,SCORECARDS!K:K),0) -> 0.26086957 | I4: =0 -> 0 | J4: =0 -> 0 | K4: =0 -> 0 | L4: =0 -> 0 | M4: =IFERROR(AVERAGE(B4:L4),0) -> 0.043478261
A5: AMAZONAS | B5: =0 -> 0 | C5: =IFERROR(AVERAGEIF(MATRIZ_174!C:C,A5,SCORECARDS!H:H),0) -> 0 | D5: =IFERROR(AVERAGEIF(MATRIZ_174!$C:$C,A5,ISCAM_Score!$G:$G),0) -> 0.26315789 | E5: =0 -> 0 | F5: =IFERROR(AVERAGEIF(MATRIZ_174!C:C,A5,SCORECARDS!I:I),0) -> 0 | G5: =IFERROR(AVERAGEIF(MATRIZ_174!C:C,A5,SCORECARDS!J:J),0) -> 0 | H5: =IFERROR(AVERAGEIF(MATRIZ_174!C:C,A5,SCORECARDS!K:K),0) -> 0.26315789 | I5: =0 -> 0 | J5: =0 -> 0 | K5: =0 -> 0 | L5: =0 -> 0 | M5: =IFERROR(AVERAGE(B5:L5),0) -> 0.04784689
A6: CAJAMARCA | B6: =0 -> 0 | C6: =IFERROR(AVERAGEIF(MATRIZ_174!C:C,A6,SCORECARDS!H:H),0) -> 0 | D6: =IFERROR(AVERAGEIF(MATRIZ_174!$C:$C,A6,ISCAM_Score!$G:$G),0) -> 0.11111111 | E6: =0 -> 0 | F6: =IFERROR(AVERAGEIF(MATRIZ_174!C:C,A6,SCORECARDS!I:I),0) -> 0 | G6: =IFERROR(AVERAGEIF(MATRIZ_174!C:C,A6,SCORECARDS!J:J),0) -> 0 | H6: =IFERROR(AVERAGEIF(MATRIZ_174!C:C,A6,SCORECARDS!K:K),0) -> 0.44444444 | I6: =0 -> 0 | J6: =0 -> 0 | K6: =0 -> 0 | L6: =0 -> 0 | M6: =IFERROR(AVERAGE(B6:L6),0) -> 0.050505051
A7: CUSCO | B7: =0 -> 0 | C7: =IFERROR(AVERAGEIF(MATRIZ_174!C:C,A7,SCORECARDS!H:H),0) -> 0 | D7: =IFERROR(AVERAGEIF(MATRIZ_174!$C:$C,A7,ISCAM_Score!$G:$G),0) -> 0.23958333 | E7: =0 -> 0 | F7: =IFERROR(AVERAGEIF(MATRIZ_174!C:C,A7,SCORECARDS!I:I),0) -> 0 | G7: =IFERROR(AVERAGEIF(MATRIZ_174!C:C,A7,SCORECARDS!J:J),0) -> 0 | H7: =IFERROR(AVERAGEIF(MATRIZ_174!C:C,A7,SCORECARDS!K:K),0) -> 0.11458333 | I7: =0 -> 0 | J7: =0 -> 0 | K7: =0 -> 0 | L7: =0 -> 0 | M7: =IFERROR(AVERAGE(B7:L7),0) -> 0.03219697
A8: UCAYALI | B8: =0 -> 0 | C8: =IFERROR(AVERAGEIF(MATRIZ_174!C:C,A8,SCORECARDS!H:H),0) -> 0 | D8: =IFERROR(AVERAGEIF(MATRIZ_174!$C:$C,A8,ISCAM_Score!$G:$G),0) -> 0.11111111 | E8: =0 -> 0 | F8: =IFERROR(AVERAGEIF(MATRIZ_174!C:C,A8,SCORECARDS!I:I),0) -> 0 | G8: =IFERROR(AVERAGEIF(MATRIZ_174!C:C,A8,SCORECARDS!J:J),0) -> 0 | H8: =IFERROR(AVERAGEIF(MATRIZ_174!C:C,A8,SCORECARDS!K:K),0) -> 0.11111111 | I8: =0 -> 0 | J8: =0 -> 0 | K8: =0 -> 0 | L8: =0 -> 0 | M8: =IFERROR(AVERAGE(B8:L8),0) -> 0.02020202
A9: PASCO | B9: =0 -> 0 | C9: =IFERROR(AVERAGEIF(MATRIZ_174!C:C,A9,SCORECARDS!H:H),0) -> 0 | D9: =IFERROR(AVERAGEIF(MATRIZ_174!$C:$C,A9,ISCAM_Score!$G:$G),0) -> 0.25 | E9: =0 -> 0 | F9: =IFERROR(AVERAGEIF(MATRIZ_174!C:C,A9,SCORECARDS!I:I),0) -> 0 | G9: =IFERROR(AVERAGEIF(MATRIZ_174!C:C,A9,SCORECARDS!J:J),0) -> 0 | H9: =IFERROR(AVERAGEIF(MATRIZ_174!C:C,A9,SCORECARDS!K:K),0) -> 0.125 | I9: =0 -> 0 | J9: =0 -> 0 | K9: =0 -> 0 | L9: =0 -> 0 | M9: =IFERROR(AVERAGE(B9:L9),0) -> 0.034090909
A10: PIURA | B10: =0 -> 0 | C10: =IFERROR(AVERAGEIF(MATRIZ_174!C:C,A10,SCORECARDS!H:H),0) -> 0 | D10: =IFERROR(AVERAGEIF(MATRIZ_174!$C:$C,A10,ISCAM_Score!$G:$G),0) -> 0.1 | E10: =0 -> 0 | F10: =IFERROR(AVERAGEIF(MATRIZ_174!C:C,A10,SCORECARDS!I:I),0) -> 0 | G10: =IFERROR(AVERAGEIF(MATRIZ_174!C:C,A10,SCORECARDS!J:J),0) -> 0 | H10: =IFERROR(AVERAGEIF(MATRIZ_174!C:C,A10,SCORECARDS!K:K),0) -> 0.2 | I10: =0 -> 0 | J10: =0 -> 0 | K10: =0 -> 0 | L10: =0 -> 0 | M10: =IFERROR(AVERAGE(B10:L10),0) -> 0.027272727
A11: AYACUCHO | B11: =0 -> 0 | C11: =IFERROR(AVERAGEIF(MATRIZ_174!C:C,A11,SCORECARDS!H:H),0) -> 0 | D11: =IFERROR(AVERAGEIF(MATRIZ_174!$C:$C,A11,ISCAM_Score!$G:$G),0) -> 0.66666667 | E11: =0 -> 0 | F11: =IFERROR(AVERAGEIF(MATRIZ_174!C:C,A11,SCORECARDS!I:I),0) -> 0 | G11: =IFERROR(AVERAGEIF(MATRIZ_174!C:C,A11,SCORECARDS!J:J),0) -> 0 | H11: =IFERROR(AVERAGEIF(MATRIZ_174!C:C,A11,SCORECARDS!K:K),0) -> 0.33333333 | I11: =0 -> 0 | J11: =0 -> 0 | K11: =0 -> 0 | L11: =0 -> 0 | M11: =IFERROR(AVERAGE(B11:L11),0) -> 0.090909091
A12: PUNO | B12: =0 -> 0 | C12: =IFERROR(AVERAGEIF(MATRIZ_174!C:C,A12,SCORECARDS!H:H),0) -> 0 | D12: =IFERROR(AVERAGEIF(MATRIZ_174!$C:$C,A12,ISCAM_Score!$G:$G),0) -> 0.5 | E12: =0 -> 0 | F12: =IFERROR(AVERAGEIF(MATRIZ_174!C:C,A12,SCORECARDS!I:I),0) -> 0 | G12: =IFERROR(AVERAGEIF(MATRIZ_174!C:C,A12,SCORECARDS!J:J),0) -> 0 | H12: =IFERROR(AVERAGEIF(MATRIZ_174!C:C,A12,SCORECARDS!K:K),0) -> 0.33333333 | I12: =0 -> 0 | J12: =0 -> 0 | K12: =0 -> 0 | L12: =0 -> 0 | M12: =IFERROR(AVERAGE(B12:L12),0) -> 0.075757576
A13: APURIMAC | B13: =0 -> 0 | C13: =IFERROR(AVERAGEIF(MATRIZ_174!C:C,A13,SCORECARDS!H:H),0) -> 0 | D13: =IFERROR(AVERAGEIF(MATRIZ_174!$C:$C,A13,ISCAM_Score!$G:$G),0) -> 0 | E13: =0 -> 0 | F13: =IFERROR(AVERAGEIF(MATRIZ_174!C:C,A13,SCORECARDS!I:I),0) -> 0 | G13: =IFERROR(AVERAGEIF(MATRIZ_174!C:C,A13,SCORECARDS!J:J),0) -> 0 | H13: =IFERROR(AVERAGEIF(MATRIZ_174!C:C,A13,SCORECARDS!K:K),0) -> 1 | I13: =0 -> 0 | J13: =0 -> 0 | K13: =0 -> 0 | L13: =0 -> 0 | M13: =IFERROR(AVERAGE(B13:L13),0) -> 0.090909091
A14: MADRE DE DIOS | B14: =0 -> 0 | C14: =IFERROR(AVERAGEIF(MATRIZ_174!C:C,A14,SCORECARDS!H:H),0) -> 0 | D14: =IFERROR(AVERAGEIF(MATRIZ_174!$C:$C,A14,ISCAM_Score!$G:$G),0) -> 0.16666667 | E14: =0 -> 0 | F14: =IFERROR(AVERAGEIF(MATRIZ_174!C:C,A14,SCORECARDS!I:I),0) -> 0 | G14: =IFERROR(AVERAGEIF(MATRIZ_174!C:C,A14,SCORECARDS!J:J),0) -> 0 | H14: =IFERROR(AVERAGEIF(MATRIZ_174!C:C,A14,SCORECARDS!K:K),0) -> 0.16666667 | I14: =0 -> 0 | J14: =0 -> 0 | K14: =0 -> 0 | L14: =0 -> 0 | M14: =IFERROR(AVERAGE(B14:L14),0) -> 0.03030303
... A17: OTROS | B17: =0 -> 0 | C17: =IFERROR(AVERAGEIF(MATRIZ_174!C:C,A17,SCORECARDS!H:H),0) -> 0 | D17: =IFERROR(AVERAGEIF(MATRIZ_174!$C:$C,A17,ISCAM_Score!$G:$G),0) -> 0 | E17: =0 -> 0 | F17: =IFERROR(AVERAGEIF(MATRIZ_174!C:C,A17,SCORECARDS!I:I),0) -> 0 | G17: =IFERROR(AVERAGEIF(MATRIZ_174!C:C,A17,SCORECARDS!J:J),0) -> 0 | H17: =IFERROR(AVERAGEIF(MATRIZ_174!C:C,A17,SCORECARDS!K:K),0) -> 0 | I17: =0 -> 0 | J17: =0 -> 0 | K17: =0 -> 0 | L17: =0 -> 0 | M17: =IFERROR(AVERAGE(B17:L17),0) -> 0
D18: =IFERROR(AVERAGEIF(MATRIZ_174!$C:$C,A18,ISCAM_Score!$G:$G),0) -> 0
D19: =IFERROR(AVERAGEIF(MATRIZ_174!$C:$C,A19,ISCAM_Score!$G:$G),0) -> 0
A20: LEYENDA — NIVELES DE CUMPLIMIENTO
A21: 🟢 Verde (0.67–1.00) — Cumplimiento adecuado
A22: 🟡 Amarillo (0.34–0.66) — Brecha moderada
A23: 🔴 Rojo (0.00–0.33) — Brecha crítica
A24: ⬜ Gris (0.00) — Sin dato capturado
D25: =IFERROR(AVERAGEIF(MATRIZ_174!$C:$C,A25,ISCAM_Score!$G:$G),0) -> 0
A26: NOTA: Los scores en D2, D5, D6, D7 corresponden a los valores ingresados manualmente en SCORECARDS. Completar la hoja PREGUNTAS_PROXY y transferir los scores a SCORECARDS para actualizar este radar.
