Workbook

Sheet INSTRUCCIONES
A1: PLANTILLA ÍNDICE PVE — PACTO VERDE EUROPEO
A2: Clasificación de preparación y vulnerabilidad de cooperativas café y cacao ante el EUDR / Pacto Verde Europeo
A4: PROPÓSITO
A7: CÓMO FUNCIONA
A10: FLUJO DE USO
A11: Paso 1 | B11: Revisar PONDERADORES — los pesos son editables en celdas amarillas
A12: Paso 2 | B12: Ir a MATRIZ_174 — verificar/actualizar FOB, país destino, certificaciones
A13: Paso 3 | B13: Para cada organización con FOB UE > 0, completar PREGUNTAS_PROXY usando llamada telefónica o visita de 30 min
A14: Paso 4 | B14: Revisar SCORECARDS — el semáforo se actualiza automáticamente
A15: Paso 5 | B15: Usar RADAR_BRECHAS para comparación por departamento
A17: SEMÁFORO
A18: 🔴 Crítico (0–33) | B18: La cooperativa no puede generar la declaración EUDR. Riesgo de rechazo en frontera UE desde dic 2026.
A19: 🟡 Vulnerable (34–66) | B19: Tiene infraestructura parcial pero incompleta. Necesita inversión en geolocalización y proceso.
A20: 🟢 Preparado (67–100) | B20: Cumple los requisitos mínimos. Requiere monitoreo de actualización.
A22: NOTAS IMPORTANTES

Sheet INSTRUMENTO_2_PREGUNTAS
A1: INSTRUMENTO 2 (v0.4, 119 preguntas) — Correspondencia pregunta → destino en esta plantilla
A2: Sección | B2: ID | C2: Bloque / Dimensión | D2: Pregunta | E2: Tipo de campo | F2: Opciones | G2: Destino en esta plantilla | H2: Nota
A3: Sección 0 — Metadata de campo | B3: M1 | C3: Bloque 0 — Ficha de identificación | D3: Fecha | E3: — | F3: — | G3: Google Sheet de respuestas, col. D (`fecha_aplicacion`)
A4: Sección 0 — Metadata de campo | B4: M2 | C4: Bloque 0 — Ficha de identificación | D4: Respuesta corta | E4: — | F4: — | G4: Google Sheet de respuestas, col. E (`encuestador`)
A5: Sección 0 — Metadata de campo | B5: M3 | C5: Bloque 0 — Ficha de identificación | D5: Lista desplegable | E5: Google Form directo / Piggyback GIZ / Piggyback SAFE / Piggyback MIDAGRI / Evento gremial / Otro | F5: — | G5: Google Sheet de respuestas, col. F (`canal_aplicacion`)
A6: Sección 1 — Bloque 0: Ficha de identificación | B6: B0.1 | C6: Bloque 0 — Ficha de identificación | D6: Nombre de la cooperativa / razón social | E6: Respuesta corta | F6: — | G6: `MATRIZ_174!B` (Razón Social)
A7: Sección 1 — Bloque 0: Ficha de identificación | B7: B0.2 | C7: Bloque 0 — Ficha de identificación | D7: RUC | E7: Respuesta corta (validación: regex 11 dígitos si el Form lo permite) | F7: — | G7: `MATRIZ_174!A` · `ISCAM_Score!A` · `SCORECARDS!A` — clave de join
A8: Sección 1 — Bloque 0: Ficha de identificación | B8: B0.3 | C8: Bloque 0 — Ficha de identificación | D8: Producto(s) exportado(s) (café, cacao, madera, otro — indique código SA si lo conoce) | E8: Párrafo | F8: — | G8: `MATRIZ_174!D` (Producto)
A9: Sección 1 — Bloque 0: Ficha de identificación | B9: B0.4 | C9: Bloque 0 — Ficha de identificación | D9: N.º de socios productores y hectáreas totales asociadas (indique ambos: "N.º socios: ___ / Hectáreas: ___") | E9: Párrafo | F9: — | G9: `MATRIZ_174!Q` (N.° socios) + `R` (Ha)
A10: Sección 1 — Bloque 0: Ficha de identificación | B10: B0.5 | C10: Bloque 0 — Ficha de identificación | D10: ¿Exporta directamente a la Unión Europea o a través de un tercero? | E10: Opción múltiple | F10: Directamente / A través de un tercero | G10: `MATRIZ_174!G` (Exporta SI/NO)
A11: Sección 1 — Bloque 0: Ficha de identificación | B11: B0.6 | C11: Bloque 0 — Ficha de identificación | D11: Si respondió "a través de un tercero": ¿quién es el comprador que sí exporta a la UE? (deje en blanco si no aplica) | E11: Respuesta corta (opcional) | F11: — | G11: Sin destino en la plantilla — registro de auditoría
A12: Sección 1 — Bloque 0: Ficha de identificación | B12: B0.7 | C12: Bloque 0 — Ficha de identificación | D12: Volumen anual aproximado destinado a la UE, como % del total exportado | E12: Respuesta corta (validación numérica 0-100) | F12: — | G12: `MATRIZ_174!M` (% UE/FOB) — validación cruzada
A13: Sección 1 — Bloque 0: Ficha de identificación | B13: B0.8 | C13: Bloque 0 — Ficha de identificación | D13: Destino(s) de sus exportaciones, marcando primero el principal — incluya destinos fuera de la UE | E13: Casillas de verificación | F13: Alemania / Bélgica / Países Bajos / Francia / Italia / España / Suecia / Dinamarca / Estados Unidos / Japón / China / Otro (especificar) | G13: Proxy `destino_principal` (D7); validación vs. DUAs | H13: v0.4 — modificada
A14: Sección 1 — Bloque 0: Ficha de identificación | B14: B0.9 | C14: Bloque 0 — Ficha de identificación | D14: Certificaciones voluntarias vigentes | E14: Casillas de verificación | F14: Rainforest Alliance / Fairtrade / Orgánico / UTZ / Otra / Ninguna | G14: `MATRIZ_174!H`/`I` → `O` (Score Cert)
A15: Sección 1 — Bloque 0: Ficha de identificación | B15: B0.10 | C15: Bloque 0 — Ficha de identificación | D15: ¿Las parcelas de los socios están concentradas en un solo distrito, repartidas en varios distritos de una misma provincia, o dispersas en varias provincias/regiones? | E15: Opción múltiple | F15: Un solo distrito / Varios distritos, misma provincia / Varias provincias o regiones | G15: Insumo IV3 — `ISCAM_Score!W`
A16: Sección 1 — Bloque 0: Ficha de identificación | B16: B0.11 | C16: Bloque 0 — Ficha de identificación | D16: Distancia aproximada entre las parcelas más alejadas de los socios y el centro de acopio o planta de procesamiento más cercano | E16: Opción múltiple | F16: Menos de 5 km / Entre 5 y 20 km / Entre 20 y 50 km / Más de 50 km / No se ha medido | G16: Insumo IV3 — `ISCAM_Score!W`
A17: Sección 1 — Bloque 0: Ficha de identificación | B17: B0.12 | C17: Bloque 0 — Ficha de identificación | D17: % de mujeres en la directiva/consejo directivo | E17: Respuesta corta (validación numérica 0-100) | F17: — | G17: Insumo IV5 — `ISCAM_Score!Y`
A18: Sección 1 — Bloque 0: Ficha de identificación | B18: B0.13 | C18: Bloque 0 — Ficha de identificación | D18: ¿Qué porcentaje aproximado de los socios productores opera en zonas clasificadas como de riesgo alto o muy alto de deforestación según el Mapa de Deforestación del MINAM o Global Forest Watch? | E18: Opción múltiple | F18: Menos del 10% / Entre 10% y 30% / Entre 30% y 60% / Más del 60% / No se ha evaluado | G18: Insumo IV3/IP3 — `ISCAM_Score!W`/`R`
A19: Sección 1 — Bloque 0: Ficha de identificación | B19: B0.14 | C19: Bloque 0 — Ficha de identificación | D19: ¿La cooperativa tiene capacidad técnica de verificación directa en campo —personal o prestataire con formación agronómica— para supervisar las prácticas de los socios en sus parcelas de forma periódica? | E19: Opción múltiple | F19: No tiene capacidad de verificación / Parcial, cubre menos de la mitad de los socios / Parcial, cubre más de la mitad / Sí, capacidad suficiente para visitas periódicas a todos los socios | G19: Insumo IV3/IP3 — `ISCAM_Score!W`/`R`
A20: Sección 1 — Bloque 0: Ficha de identificación | B20: B0.15 | C20: Bloque 0 — Ficha de identificación | D20: Tipo de organización | E20: Opción múltiple | F20: Asociación / Cooperativa agraria / Cooperativa de servicios / Central o federación de cooperativas / Empresa / Otro (especificar) | G20: `MATRIZ_174!P` (Tipo org.) | H20: v0.4 — nueva
A21: Sección 1 — Bloque 0: Ficha de identificación | B21: B0.16 | C21: Bloque 0 — Ficha de identificación | D21: Departamento (y provincia) donde está registrada la sede de la organización | E21: Respuesta corta | F21: — | G21: `MATRIZ_174!C` (Depto) — validación SUNAT | H21: v0.4 — nueva
A22: Sección 1 — Bloque 0: Ficha de identificación | B22: B0.17 | C22: Bloque 0 — Ficha de identificación | D22: ¿La organización está inscrita en el RNCA (Registro Nacional de Cooperativas Agrarias)? | E22: Opción múltiple | F22: Sí / En trámite / No / No aplica (no es cooperativa agraria) | G22: Insumo IV2 — `ISCAM_Score!V`; proxy `rnca` | H22: v0.4 — nueva
A23: Sección 2 — Bloque P: Variables de Performance | B23: P1 | C23: Bloque P — Performance comercial | D23: Volumen exportado a la Unión Europea en el último año (especifique unidad —kg o toneladas— y producto si exporta ambos) | E23: Párrafo | F23: — | G23: Insumo IV1 — `ISCAM_Score!U`
A24: Sección 2 — Bloque P: Variables de Performance | B24: P1b | C24: Bloque P — Performance comercial | D24: Volumen TOTAL exportado a todos los destinos (UE y no UE) en el último año, mismo producto y misma unidad que la pregunta anterior | E24: Párrafo | F24: — | G24: Insumo IV1 — `ISCAM_Score!U`
A25: Sección 2 — Bloque P: Variables de Performance | B25: P2 | C25: Bloque P — Performance comercial | D25: Volumen exportado a la Unión Europea hace 3 años, mismo producto (kg o toneladas) | E25: Párrafo | F25: — | G25: No puntúa (retrospectivo)
A26: Sección 2 — Bloque P: Variables de Performance | B26: P3 | C26: Bloque P — Performance comercial | D26: Ingreso total generado por ventas de exportación a la UE en el último año (especifique moneda: S/ o USD) | E26: Párrafo | F26: — | G26: Insumo IV1 — `ISCAM_Score!U`; deriva PVE P2
A27: Sección 2 — Bloque P: Variables de Performance | B27: P4 | C27: Bloque P — Performance comercial | D27: N.º de compradores/clientes europeos activos actualmente | E27: Respuesta corta (numérica) | F27: — | G27: Insumo IV1 — `ISCAM_Score!U`
A28: Sección 2 — Bloque P: Variables de Performance | B28: P5 | C28: Bloque P — Performance comercial | D28: N.º de compradores/clientes europeos activos hace 3 años | E28: Respuesta corta (numérica) | F28: — | G28: No puntúa (retrospectivo)
A29: Sección 2 — Bloque P: Variables de Performance | B29: P6 | C29: Bloque P — Performance comercial | D29: Precio promedio pagado al socio productor por kg/quintal en el último año (especifique S/ o USD) | E29: Respuesta corta | F29: — | G29: Derivada `var_precio_socio`
A30: Sección 2 — Bloque P: Variables de Performance | B30: P7 | C30: Bloque P — Performance comercial | D30: Precio promedio pagado al socio productor por kg/quintal hace 3 años | E30: Respuesta corta | F30: — | G30: Derivada `var_precio_socio`
A31: Sección 2 — Bloque P: Variables de Performance | B31: P8 | C31: Bloque P — Performance comercial | D31: ¿Ha tenido algún lote rechazado u observado por un comprador europeo por motivos de trazabilidad/deforestación en los últimos 2 años? | E31: Opción múltiple | F31: Sí / No / No sabe | G31: Proxy `reg_rechazos` (D5)
A32: Sección 2 — Bloque P: Variables de Performance | B32: P9 | C32: Bloque P — Performance comercial | D32: Si la respuesta anterior fue "Sí": N.º aproximado de lotes rechazados u observados (deje en blanco si no aplica) | E32: Respuesta corta (opcional) | F32: — | G32: Detalle de P8 — no puntúa
A33: Sección 2 — Bloque P: Variables de Performance | B33: P10 | C33: Bloque P — Performance comercial | D33: ¿Ha perdido algún contrato o comprador europeo en los últimos 2 años por motivos de cumplimiento (EUDR u otro requisito de sostenibilidad del comprador)? | E33: Opción múltiple | F33: Sí / No / No sabe | G33: Proxy presión PV del comprador (D7)
A34: Sección 2 — Bloque P: Variables de Performance | B34: P11 | C34: Bloque P — Performance comercial | D34: % del volumen total exportado en el último año que cuenta con trazabilidad completa verificada hasta la parcela de origen (0-100%) | E34: Respuesta corta (validación numérica 0-100) | F34: — | G34: `MATRIZ_174!AK` (P11 — Score trazabilidad)
... A41: Sección 3 — D1: Clasificación regulatoria | B41: D1.4 | C41: D1 — Clasificación regulatoria | D41: ¿Cumple los umbrales de microempresa/pequeña empresa (Directiva 2013/34/UE)? | E41: Opción múltiple | F41: Sí / No / No sabe | G41: `ISCAM_Score!E` (D1)
A42: Sección 3 — D1: Clasificación regulatoria | B42: D1.3a | C42: D1 — Clasificación regulatoria | D42: *(Rama: solo si D1.3 = "Sí con certeza" o "Idea aproximada")* ¿Cuál es el rol que le corresponde a la organización? | E42: Opción múltiple | F42: Operador / Operador posterior / Comerciante / Micro o pequeño operador primario / No sabe | G42: `ISCAM_Score!E` (D1) | H42: v0.4 — nueva
A43: Sección 4 — D2: Trazabilidad y geolocalización | B43: D2.5 | C43: D2 — Trazabilidad y geolocalización | D43: ¿Existe registro de geolocalización (GPS/polígono) por parcela de socio? | E43: Escala lineal 0-4 | F43: 0 = No existe/No sabe … 4 = Implementado y verificado/auditado | G43: `ISCAM_Score!F` vía `SCORECARDS!H` (D2)
A44: Sección 4 — D2: Trazabilidad y geolocalización | B44: D2.6 | C44: D2 — Trazabilidad y geolocalización | D44: % de socios con parcela geolocalizada | E44: Respuesta corta (validación numérica 0-100) | F44: — | G44: `ISCAM_Score!F` vía `SCORECARDS!H` (D2)
A45: Sección 4 — D2: Trazabilidad y geolocalización | B45: D2.7 | C45: D2 — Trazabilidad y geolocalización | D45: ¿El sistema vincula un lote exportado con la(s) parcela(s) específica(s)? | E45: Escala lineal 0-4 | F45: Misma leyenda que D2.5 | G45: `ISCAM_Score!F` vía `SCORECARDS!H` (D2)
A46: Sección 4 — D2: Trazabilidad y geolocalización | B46: D2.8 | C46: D2 — Trazabilidad y geolocalización | D46: ¿Quién levantó la información de geolocalización? | E46: Opción múltiple | F46: Técnico propio / Consultor / Proyecto de cooperación / Socio por su cuenta / No se ha levantado | G46: `ISCAM_Score!F` vía `SCORECARDS!H` (D2)
A47: Sección 4 — D2: Trazabilidad y geolocalización | B47: D2.9 | C47: D2 — Trazabilidad y geolocalización | D47: Frecuencia de actualización de la geolocalización | E47: Opción múltiple | F47: Nunca / Al ingreso del socio / Anual / Por cosecha | G47: `ISCAM_Score!F` vía `SCORECARDS!H` (D2)
A48: Sección 4 — D2: Trazabilidad y geolocalización | B48: D2.10 | C48: D2 — Trazabilidad y geolocalización | D48: ¿Existe algún punto en el proceso de acopio o beneficio donde se mezclan físicamente lotes de distinto origen sin registro de qué parcelas los componen? | E48: Opción múltiple | F48: Sí, se mezclan sin control / Se mezclan pero con registro de origen / No, se mantiene segregación física completa | G48: `ISCAM_Score!F` (D2) + bandera `SCORECARDS!AD`
A49: Sección 4 — D2: Trazabilidad y geolocalización | B49: D2.5a | C49: D2 — Trazabilidad y geolocalización | D49: ¿Qué porcentaje aproximado del volumen exportado proviene de proveedores externos (productores que no son socios de la cooperativa)? | E49: Opción múltiple | F49: 0%, todo proviene de socios / Menos del 10% / Entre 10% y 30% / Más del 30% / No se ha cuantificado | G49: `ISCAM_Score!F` vía `SCORECARDS!H` (D2) | H49: v0.4 — nueva
A50: Sección 4 — D2: Trazabilidad y geolocalización | B50: D2.5b | C50: D2 — Trazabilidad y geolocalización | D50: *(Rama: solo si D2.5a ≠ "0%, todo proviene de socios" y ≠ "No se ha cuantificado")* Si compra a proveedores externos: ¿se registra el nombre, la cantidad y el origen (parcela o zona) de cada proveedor externo? | E50: Opción múltiple | F50: Sí, verificado con georreferencia / Sí, pero sin georreferencia / Solo nombre y cantidad / No se registra / No aplica | G50: `ISCAM_Score!F` (D2) + bandera | H50: v0.4 — nueva
A51: Sección 5 — D3: Legalidad de la producción | B51: D3.11 | C51: D3 — Legalidad de la producción | D51: % de socios con título de propiedad o posesión reconocida legalmente | E51: Respuesta corta (validación numérica 0-100) | F51: — | G51: `ISCAM_Score!G` (D3)
A52: Sección 5 — D3: Legalidad de la producción | B52: D3.12 | C52: D3 — Legalidad de la producción | D52: ¿Hay parcelas superpuestas a áreas naturales protegidas o su zona de amortiguamiento, reservas comunales o territorios indígenas sin sanear? | E52: Opción múltiple | F52: Sí, extensa / Sí, puntual / Sí, en área natural protegida o zona de amortiguamiento / No verificado / No, ninguna | G52: `ISCAM_Score!G` (D3) | H52: v0.4 — modificada
A53: Sección 5 — D3: Legalidad de la producción | B53: D3.13 | C53: D3 — Legalidad de la producción | D53: ¿Se verifica cumplimiento laboral (no trabajo infantil, seguridad social) a nivel de finca? | E53: Escala lineal 0-4 | F53: Misma leyenda que D2.5 | G53: `ISCAM_Score!G` (D3)
A54: Sección 5 — D3: Legalidad de la producción | B54: D3.14 | C54: D3 — Legalidad de la producción | D54: ¿Alguna parcela de socios se ubica en una zona de desarrollo alternativo (ex-cultivo de coca) o con antecedentes de conflicto social/territorial? | E54: Opción múltiple | F54: Sí / No / No verificado | G54: `ISCAM_Score!G` (D3)
A55: Sección 5 — D3: Legalidad de la producción | B55: D3.14a | C55: D3 — Legalidad de la producción | D55: ¿Los socios cuentan con autorización de uso de agua para su actividad productiva, cuando corresponde? | E55: Opción múltiple | F55: Sí, todas las fuentes verificadas / Parcialmente / No / No aplica | G55: `ISCAM_Score!G` (D3)
A56: Sección 5 — D3: Legalidad de la producción | B56: D3.14b | C56: D3 — Legalidad de la producción | D56: ¿El tratamiento de aguas residuales del beneficio/procesamiento cumple con lo exigido por la autoridad ambiental? | E56: Opción múltiple | F56: Siempre / A veces / No / No aplica | G56: `ISCAM_Score!G` (D3)
A57: Sección 5 — D3: Legalidad de la producción | B57: D3.14c | C57: D3 — Legalidad de la producción | D57: ¿Alguna parcela de socios se encuentra dentro de la faja marginal de un río, quebrada, lago o laguna? | E57: Opción múltiple | F57: Sí / No / No sabe | G57: `ISCAM_Score!G` (D3)
A58: Sección 5 — D3: Legalidad de la producción | B58: D3.14d | C58: D3 — Legalidad de la producción | D58: En las parcelas de los socios y en el inmueble donde opera la cooperativa, ¿existe algún derecho de terceros (carga, embargo, servidumbre, usufructo, arrendamiento o derecho de uso consuetudinario) que condicione o restrinja el uso de la tierra para cultivar café o cacao, o el derecho de la cooperativa a operar en esa finca? | E58: Opción múltiple | F58: No existe ningún derecho de terceros / Existe, pero está registrado y no restringe el uso / Existe un acuerdo documentado con el titular o con la autoridad que legitima el uso, aunque la cooperativa o el socio no tenga título formal / Existe usufructo, arrendamiento o carga sin acuerdo que lo resuelva / Se han invocado derechos de uso tradicional o consuetudinarios por una comunidad o pueblo indígena sin proceso de acuerdo / No verificado | G58: `ISCAM_Score!G` (D3)
A59: Sección 5 — D3: Legalidad de la producción | B59: D3.14e | C59: D3 — Legalidad de la producción | D59: ¿La cooperativa y sus socios están al día en sus obligaciones tributarias, aduaneras y comerciales vinculadas a la actividad exportadora? | E59: Opción múltiple | F59: Sí, verificado / Parcialmente / No verificado / No sabe | G59: `ISCAM_Score!G` (D3)
A60: Sección 5 — D3: Legalidad de la producción | B60: D3.14f | C60: D3 — Legalidad de la producción | D60: ¿Existen políticas o mecanismos internos contra la corrupción (código de conducta, canal de denuncias) aplicables a la cadena de abastecimiento? | E60: Opción múltiple | F60: Sí, formalizado / Informal / No existe | G60: `ISCAM_Score!G` (D3)
A61: Sección 5 — D3: Legalidad de la producción | B61: D3.14g | C61: D3 — Legalidad de la producción | D61: Cuando corresponde (parcelas de socios en territorio de comunidades indígenas, nativas o campesinas), ¿se ha realizado un proceso de Consentimiento Libre, Previo e Informado (CLPI)? | E61: Opción múltiple | F61: Sí, proceso documentado / Aplica pero no se ha realizado / No aplica, no hay territorios de este tipo / No sabe | G61: `ISCAM_Score!G` (D3)
A62: Sección 5 — D3: Legalidad de la producción | B62: D3.14h | C62: D3 — Legalidad de la producción | D62: ¿La organización cuenta con autorizaciones ambientales vigentes para su planta y actividad (EIA, DIA, certificación forestal o certificado de habilitación, según corresponda)? | E62: Opción múltiple | F62: Sí, vigentes y verificadas / Parcial, alguna falta o está vencida / No / No aplica (sin actividad que la requiera) | G62: `ISCAM_Score!G` (D3) | H62: v0.4 — nueva
A63: Sección 5 — D3: Legalidad de la producción | B63: D3.14i | C63: D3 — Legalidad de la producción | D63: ¿Existe algún proceso sancionador vigente de OEFA, SINEFA u otra autoridad ambiental contra la organización o sus socios? | E63: Opción múltiple | F63: Sí, vigente y sin resolver / Sí, en proceso de resolución / No / No sabe | G63: `MATRIZ_174!U` (D3) + bandera `ISCAM_Score!AD` + IV4 (`X`) | H63: v0.4 — nueva
A64: Sección 6 — D4: Riesgo de deforestación | B64: D4.15 | C64: D4 — Riesgo de deforestación | D64: ¿Se verificó cambio de uso de suelo posterior al 31 de diciembre de 2020 mediante cruce de las parcelas con mapas de deforestación (GEOSERFOR/PNCB o Global Forest Watch)? | E64: Opción múltiple | F64: No verificado / Verificación parcial / Verificado sin hallazgos / Casos detectados sin resolver / Verificado sistemáticamente y documentado | G64: `ISCAM_Score!H` (D4) | H64: v0.4 — modificada
A65: Sección 6 — D4: Riesgo de deforestación | B65: D4.16 | C65: D4 — Riesgo de deforestación | D65: ¿Usa herramientas de monitoreo satelital (Global Forest Watch, plataformas nacionales)? | E65: Escala lineal 0-4 | F65: Misma leyenda que D2.5 | G65: `ISCAM_Score!H` (D4)
A66: Sección 6 — D4: Riesgo de deforestación | B66: D4.17 | C66: D4 — Riesgo de deforestación | D66: ¿Conoce la clasificación de riesgo (bajo/estándar/alto) de su zona? | E66: Opción múltiple | F66: Sí documentado / Idea aproximada / No sabe | G66: `ISCAM_Score!H` (D4)
A67: Sección 6 — D4: Riesgo de deforestación | B67: D4.15a | C67: D4 — Riesgo de deforestación | D67: ¿Se han detectado alertas activas de deforestación en parcelas de socios de la organización (GEOSERFOR, PNCB o Global Forest Watch)? | E67: Opción múltiple | F67: Sí, detectadas y sin resolver / Sí, detectadas y mitigadas o aclaradas / No se han detectado / No se monitorea | G67: `ISCAM_Score!H` (D4) + IP2 (`Q`) + bandera | H67: v0.4 — nueva
A68: Sección 7 — D5: Sistema interno de diligencia debida | B68: D5.18 | C68: D5 — Diligencia debida | D68: ¿Existe procedimiento escrito de diligencia debida? | E68: Escala lineal 0-4 | F68: Misma leyenda que D2.5 | G68: `ISCAM_Score!I` vía `SCORECARDS!I` (D5)
A69: Sección 7 — D5: Sistema interno de diligencia debida | B69: D5.18a | C69: D5 — Diligencia debida | D69: ¿Existe una política de deforestación formal y escrita (distinta del procedimiento operativo), con objetivos, metas medibles y plazos (ej. compromiso de "cero deforestación" a una fecha determinada)? | E69: Escala lineal 0-4 | F69: Misma leyenda que D2.5 | G69: `ISCAM_Score!I` vía `SCORECARDS!I` (D5)
A70: Sección 7 — D5: Sistema interno de diligencia debida | B70: D5.18b | C70: D5 — Diligencia debida | D70: ¿La cooperativa prioriza sus riesgos de deforestación con algún criterio de probabilidad e impacto (aunque sea informal), o los atiende sin un orden definido? | E70: Opción múltiple | F70: No se prioriza, se atiende lo que surge / Priorización informal, sin criterio escrito / Priorización estructurada con matriz probabilidad×impacto o similar | G70: `ISCAM_Score!I` vía `SCORECARDS!I` (D5)
A71: Sección 7 — D5: Sistema interno de diligencia debida | B71: D5.19 | C71: D5 — Diligencia debida | D71: ¿Ha elaborado o participado en una declaración de diligencia debida / simplificada? | E71: Opción múltiple | F71: No sabe qué es / No pero lo entiende / En proceso / Presentada y aceptada | G71: `ISCAM_Score!I` vía `SCORECARDS!I` (D5)
A72: Sección 7 — D5: Sistema interno de diligencia debida | B72: D5.19a | C72: D5 — Diligencia debida | D72: Del plan de gestión de riesgos de la cooperativa (si existe), marque los componentes que incluye explícitamente | E72: Casillas de verificación | F72: Plazos definidos / Recursos (humanos o financieros) asignados / Responsables designados / Procedimientos de consulta con socios y comunidades / Sistema de seguimiento y monitoreo / Protocolo ante incumplimiento de un socio / Atención diferenciada a productoras mujeres | G72: `ISCAM_Score!I` vía `SCORECARDS!I` (D5)
A73: Sección 7 — D5: Sistema interno de diligencia debida | B73: D5.20 | C73: D5 — Diligencia debida | D73: ¿Existe responsable designado para el cumplimiento EUDR? | E73: Opción múltiple | F73: No / Función adicional / Dedicado | G73: `ISCAM_Score!I` vía `SCORECARDS!I` (D5)
A74: Sección 7 — D5: Sistema interno de diligencia debida | B74: D5.21 | C74: D5 — Diligencia debida | D74: ¿Capacitación formal en los últimos 12 meses? | E74: Opción múltiple | F74: No / Hace más de 12 meses / Sí, reciente | G74: `ISCAM_Score!I` vía `SCORECARDS!I` (D5)
A75: Sección 7 — D5: Sistema interno de diligencia debida | B75: D5.21a | C75: D5 — Diligencia debida | D75: ¿El plan de gestión de riesgos se revisa con una frecuencia definida (ej. anual, por campaña)? | E75: Opción múltiple | F75: No hay revisión definida / Revisión reactiva, sin frecuencia fija / Revisión periódica definida | G75: `ISCAM_Score!I` vía `SCORECARDS!I` (D5)
A76: Sección 7 — D5: Sistema interno de diligencia debida | B76: D5.21b | C76: D5 — Diligencia debida | D76: ¿La cooperativa elabora y comunica un reporte de debida diligencia con indicadores (ej. % de producto trazado hasta finca, N.º de alertas tempranas detectadas, N.º de productores capacitados)? | E76: Opción múltiple | F76: No / Sí, uso interno solamente / Sí, interno y compartido con compradores u otras partes interesadas | G76: `ISCAM_Score!I` vía `SCORECARDS!I` (D5)
A77: Sección 8 — D6: Capacidad organizacional y digital | B77: D6.22 | C77: D6 — Capacidad organizacional y digital | D77: Presupuesto asignado al cumplimiento EUDR | E77: Opción múltiple | F77: No / Parcial, solo actividades de cumplimiento / Parcial, incluye tecnología y datos / Sí, con partida explícita para tecnología y datos | G77: `ISCAM_Score!J` vía `SCORECARDS!J` (D6) | H77: v0.4 — modificada
A78: Sección 8 — D6: Capacidad organizacional y digital | B78: D6.22a | C78: D6 — Capacidad organizacional y digital | D78: ¿La cooperativa cuenta con una base de datos o sistema centralizado (digital o no) que permite vincular a cada socio proveedor con sus parcelas geolocalizadas, los lotes que ha entregado y su volumen? | E78: Opción múltiple | F78: No existe / Existe en papel desorganizado / Existe digital pero sin vínculos entre tablas / Existe digital con vínculos actualizados entre socio-parcela-lote | G78: `ISCAM_Score!J` vía `SCORECARDS!J` (D6)
A79: Sección 8 — D6: Capacidad organizacional y digital | B79: D6.22b | C79: D6 — Capacidad organizacional y digital | D79: *(Rama: solo si D6.22a ≠ "No existe" y ≠ "Existe en papel desorganizado")* ¿Qué tipo de sistema digital utiliza? | E79: Opción múltiple | F79: Excel o Access básico / Software especializado de trazabilidad (ChainPoint, Teia, BQuant, otro) / Sistema web propio o de tercero / Base de datos personalizada con soporte técnico regular | G79: `ISCAM_Score!J` vía `SCORECARDS!J` (D6)
A80: Sección 8 — D6: Capacidad organizacional y digital | B80: D6.23 | C80: D6 — Capacidad organizacional y digital | D80: Digitalización de registros | E80: Opción múltiple | F80: Papel / Mixto / Digital | G80: `ISCAM_Score!J` vía `SCORECARDS!J` (D6)
A81: Sección 8 — D6: Capacidad organizacional y digital | B81: D6.24 | C81: D6 — Capacidad organizacional y digital | D81: Conectividad a internet | E81: Opción múltiple | F81: No hay / Limitada / Confiable | G81: `ISCAM_Score!J` vía `SCORECARDS!J` (D6)
A82: Sección 8 — D6: Capacidad organizacional y digital | B82: D6.25 | C82: D6 — Capacidad organizacional y digital | D82: ¿Ha gestionado apoyo externo para adecuarse? | E82: Opción múltiple | F82: No y lo necesita / No lo cree necesario / Sí en el pasado / Sí activo | G82: `ISCAM_Score!J` vía `SCORECARDS!J` (D6)
A83: Sección 8 — D6: Capacidad organizacional y digital | B83: D6.25a | C83: D6 — Capacidad organizacional y digital | D83: ¿Los registros documentales de la cooperativa (actas, contratos con socios, guías de transporte, certificados, reportes de trazabilidad) se almacenan de forma segura —digital con respaldo o física en archivo— con capacidad de ser recuperados en menos de 48 horas si se pierden los originales? | E83: Opción múltiple | F83: No existe política de respaldo / Parcial, solo los más críticos / Sí, con respaldo definido pero no probado / Sí, con protocolo probado periódicamente | G83: `ISCAM_Score!J` vía `SCORECARDS!J` (D6)
A84: Sección 8 — D6: Capacidad organizacional y digital | B84: D6.25b | C84: D6 — Capacidad organizacional y digital | D84: *(Rama: solo si D6.25a = "Sí, con respaldo definido pero no probado" o "Sí, con protocolo probado")* ¿El protocolo fue diseñado internamente o con apoyo externo? ¿Cuándo se probó por última vez? | E84: Opción múltiple | F84: Diseñado internamente / Con apoyo de ONG o programa / Con apoyo de consultoría o proveedor IT / Nunca se ha probado / Probado hace más de 12 meses / Probado en los últimos 12 meses | G84: `ISCAM_Score!J` vía `SCORECARDS!J` (D6)
A85: Sección 8 — D6: Capacidad organizacional y digital | B85: D6.22c | C85: D6 — Capacidad organizacional y digital | D85: ¿Hay personal asignado a la gestión de datos y trazabilidad (aunque sea a medio tiempo)? | E85: Opción múltiple | F85: Sí, personal dedicado / Parcial, como función adicional / No / No sabe | G85: `ISCAM_Score!J` vía `SCORECARDS!J` (D6) | H85: v0.4 — nueva
A86: Sección 9 — D7: Cadena de valor | B86: D7.26 | C86: D7 — Cadena de valor / presión comprador | D86: ¿El comprador ha exigido formalmente geolocalización/diligencia debida? | E86: Opción múltiple | F86: Aún no / Informalmente / Formalmente por escrito | G86: `ISCAM_Score!K` (D7)
A87: Sección 9 — D7: Cadena de valor | B87: D7.27 | C87: D7 — Cadena de valor / presión comprador | D87: ¿El comprador ofrece financiamiento/asistencia técnica condicionada al cumplimiento? | E87: Opción múltiple | F87: Sí / No | G87: `ISCAM_Score!K` (D7)
A88: Sección 9 — D7: Cadena de valor | B88: D7.28 | C88: D7 — Cadena de valor / presión comprador | D88: Riesgo percibido de perder el contrato si no cumple a tiempo | E88: Opción múltiple | F88: No sabe / Bajo / Medio / Alto | G88: `ISCAM_Score!K` (D7)
A89: Sección 9 — D7: Cadena de valor | B89: D7.28b | C89: D7 — Cadena de valor / presión comprador | D89: ¿El comprador europeo ha comunicado que sus propias obligaciones (EUDR, CSRD, CSDDD u otra) implican requisitos adicionales sobre la cadena de suministro más allá de la geolocalización? | E89: Opción múltiple | F89: No ha mencionado nada / Lo ha mencionado verbalmente sin requisito formal / Sí, ha enviado documentación o cuestionario de proveedores / Sí, lo ha formalizado como cláusula contractual | G89: `ISCAM_Score!K` (D7)
A90: Sección 9 — D7: Cadena de valor | B90: D7.28c | C90: D7 — Cadena de valor / presión comprador | D90: *(Rama: solo si D7.28b = "Sí, ha enviado documentación" o "Sí, lo ha formalizado como cláusula")* ¿Qué tipo de documentación ha enviado o solicitado el comprador? ¿Cubre solo a la cooperativa o también a sus proveedores? | E90: Opción múltiple | F90: Cuestionario de autoevaluación / Guía de diligencia debida propia del comprador / Plantilla de trazabilidad (lotes, volúmenes, GPS) / Evaluación de riesgo de deforestación / Requisito de certificación de terceros (Fairtrade, Rainforest, orgánica) / Solo cubre a la cooperativa / Cubre también a los proveedores directos / Cubre hasta proveedores de segundo nivel | G90: `ISCAM_Score!K` (D7)
A91: Sección 9 — D7: Cadena de valor | B91: D7.26a | C91: D7 — Cadena de valor / presión comprador | D91: ¿El comprador principal (primera mano) es una empresa de la Unión Europea o está sujeto a la Directiva de diligencia debida empresarial (CSDDD)? | E91: Opción múltiple | F91: Sí, empresa de la UE / No es de la UE pero está sujeto a CSDDD / No / No sabe | G91: `ISCAM_Score!K` (D7) + IV1 (`U`) | H91: v0.4 — nueva
A92: Sección 9 — D7: Cadena de valor | B92: D7.26b | C92: D7 — Cadena de valor / presión comprador | D92: ¿Existe contrato o acuerdo escrito con el comprador principal que incluya cláusula de debida diligencia, geolocalización o trazabilidad? | E92: Opción múltiple | F92: Sí, con cláusula explícita EUDR o equivalente / Sí, pero sin cláusula específica / No hay contrato escrito / No sabe | G92: `ISCAM_Score!K` (D7) + PRESION (`PONDERADORES!A16`) | H92: v0.4 — nueva
A93: Sección 10 — D8: Gobernanza y participación de socios | B93: D8.29 | C93: D8 — Gobernanza y participación | D93: ¿Se han realizado asambleas o reuniones informativas sobre el EUDR dirigidas a los socios (no solo a la directiva)? | E93: Escala lineal 0-4 | F93: Misma leyenda que D2.5 | G93: `ISCAM_Score!L` (D8)
A94: Sección 10 — D8: Gobernanza y participación de socios | B94: D8.30 | C94: D8 — Gobernanza y participación | D94: % estimado de socios que entienden, al menos en términos generales, por qué se les pide geolocalización/documentación | E94: Respuesta corta (validación numérica 0-100) | F94: — | G94: `ISCAM_Score!L` (D8)
A95: Sección 10 — D8: Gobernanza y participación de socios | B95: D8.31 | C95: D8 — Gobernanza y participación | D95: ¿Existe algún mecanismo interno (incentivo o condición) para que los socios entreguen su información de parcela? | E95: Opción múltiple | F95: No existe / Se pide informalmente / Es requisito formal para vender a la cooperativa | G95: `ISCAM_Score!L` (D8)
A96: Sección 10 — D8: Gobernanza y participación de socios | B96: D8.32 | C96: D8 — Gobernanza y participación | D96: Rotación de la directiva en los últimos 2 años | E96: Opción múltiple | F96: Alta / Moderada / Baja/estable | G96: `ISCAM_Score!L` (D8)
A97: Sección 11 — D9: Sostenibilidad económica del cumplimiento | B97: D9.33 | C97: D9 — Sostenibilidad económica | D97: Estimación del costo total de adecuación (geolocalización, saneamiento, sistemas, capacitación) frente al presupuesto anual de la cooperativa | E97: Opción múltiple | F97: Costo mayor al 10% del presupuesto anual / Entre 3-10% / Menor al 3% / No se ha estimado | G97: `ISCAM_Score!M` (D9)
A98: Sección 11 — D9: Sostenibilidad económica del cumplimiento | B98: D9.34 | C98: D9 — Sostenibilidad económica | D98: ¿Cómo ha financiado (o financiaría) la organización la adecuación al EUDR? | E98: Opción múltiple | F98: Con crédito o endeudamiento / Con recursos propios / Existe fuente de financiamiento identificada (verde, cooperación o programa público), aún no ejecutada / No ha sido necesario / No sabe | G98: `ISCAM_Score!M` (D9) | H98: v0.4 — modificada
A99: Sección 11 — D9: Sostenibilidad económica del cumplimiento | B99: D9.35 | C99: D9 — Sostenibilidad económica | D99: ¿Existe riesgo de que el costo de adecuación se traslade a un menor precio pagado al socio productor? | E99: Opción múltiple | F99: Sí, ya ha ocurrido / Es un riesgo latente / No aplica / No se ha evaluado | G99: `ISCAM_Score!M` (D9)
A100: Sección 12 — D10: Confusión entre certificación voluntaria y cumplimiento EUDR | B100: D10.36 | C100: D10 — Confusión certificación/EUDR | D100: ¿La cooperativa cree que su certificación vigente (Rainforest Alliance, Fairtrade, Orgánico, etc.) ya cubre las obligaciones del EUDR? | E100: Opción múltiple | F100: Sí, totalmente / Sí, en parte / No, sabe que son cosas distintas / No tiene certificación | G100: `ISCAM_Score!N` (D10) — bandera, no promedia
A101: Sección 12 — D10: Confusión entre certificación voluntaria y cumplimiento EUDR | B101: D10.37 | C101: D10 — Confusión certificación/EUDR | D101: ¿Algún proveedor o consultor le ha ofrecido una "certificación EUDR" como producto? | E101: Opción múltiple | F101: Sí / No | G101: `ISCAM_Score!N` (D10) — bandera, no promedia
A102: Sección 12 — D10: Confusión entre certificación voluntaria y cumplimiento EUDR | B102: D10.36a | C102: D10 — Confusión certificación/EUDR | D102: ¿La organización ha recibido asesoría específica sobre el EUDR (a diferencia de asesoría genérica de sostenibilidad)? | E102: Opción múltiple | F102: Sí, asesoría especializada en EUDR / Solo asesoría genérica de sostenibilidad / No ha recibido asesoría / No sabe | G102: `ISCAM_Score!N` (D10) — bandera, no promedia | H102: v0.4 — nueva
A103: Sección 13 — D11: Ecosistema de apoyo externo | B103: D11.38 | C103: D11 — Ecosistema de apoyo externo | D103: Marque los actores con los que la cooperativa ya tiene contacto o apoyo activo | E103: Casillas de verificación | F103: SERFOR (legalidad forestal) / PNCB-MINAM (monitoreo satelital) / MIDAGRI o programa regional de café-cacao / Gobierno regional (catastro/saneamiento) / Cooperación internacional (GIZ, USAID, UE, ONG) / Junta Nacional del Café, APPCACAO u otro gremio / Ninguno | G103: `ISCAM_Score!O` (D11) — mapeo
A104: Sección 13 — D11: Ecosistema de apoyo externo | B104: D11.39 | C104: D11 — Ecosistema de apoyo externo | D104: De los actores no marcados en la pregunta anterior, ¿cuáles conoce pero no ha contactado, y por qué? | E104: Párrafo | F104: — | G104: `ISCAM_Score!O` (D11) — mapeo
A105: Sección 13 — D11: Ecosistema de apoyo externo | B105: D11.39a | C105: D11 — Ecosistema de apoyo externo | D105: ¿La organización está inscrita en una plataforma de trazabilidad del sector (APPCACAO, Junta Nacional del Café u otra equivalente)? | E105: Opción múltiple | F105: Sí / En proceso de inscripción / No / No conoce la plataforma | G105: `ISCAM_Score!O` (D11) — mapeo | H105: v0.4 — nueva
A106: Sección 14 — D12–D15: Pacto Verde europeo (alimentan ISA-PV, 30% de ISA-Completo) | B106: D12.42 | C106: D12 — Huella de carbono (Pacto Verde) | D106: ¿La organización mide o ha calculado la huella de carbono de su actividad productiva y de procesamiento (alcance 1 y 2)? | E106: Opción múltiple | F106: No mide (0) / Registra insumos o mide parcialmente, en curso (1) / Calculada y verificada por tercero (2) | G106: `MATRIZ_174!W` → `ISCAM_Score!AE` → `AI` (ISA-PV) → 30% de `AL` | H106: v0.4 — nueva
...

Sheet ISCAM_Score
A1: ISCAM — ISA-Completo = 0.70×ISA-EUDR + 0.30×ISA-PV | IP × IV → RE | Café y Cacao Perú — 174 organizaciones
A2: ISA-Completo = 0.70×ISA-EUDR + 0.30×ISA-PV | ISA-EUDR = 0.875×Núcleo(D1–D7, geom.) + 0.125×Extendido(D8–D9, arit.) | ISA-PV = Promedio(D12:D15) | IP = Promedio(IP1..IP5) | IV = Promedio(IV1..IV5) | RE = IV×(1−IP/100) | Corte 2×2: 50
A3: RUC | B3: Razón Social | C3: Depto | D3: FOB UE USD | E3: D1 — Clasific. Regulatoria | F3: D2 — Trazabilidad (SCORECARDS H) | G3: D3 — Legalidad (OSCE/Neon) | H3: D4 — Deforestación Cero | I3: D5 — Diligencia Debida | J3: D6 — Capacidad Digital | K3: D7 — Presión Comprador | L3: D8 — Gobernanza | M3: D9 — Riesgo Financiero | N3: D10 — Certificac. | O3: D11 — Ecosistema (inventario, no promedia) | P3: IP1 Trazabilidad D2 | Q3: IP2 √(D3×D4) | R3: IP3 (D5+D6+D8)/3 | S3: IP4 (D6+D2)/2 | T3: IP5 (D7+D9+Cert)/3 | U3: IV1 Exposición UE (% FOB UE) | V3: IV2 D1 (base=50) | W3: IV3 Parcela ha/socio (sin dato→65) | X3: IV4 Cert=0? → 70:30 | Y3: IV5 Tipo Asoc → 65:40 | Z3: IP Preparación | AA3: IV Vulnerabilidad | AB3: RE Exclusión | AC3: Tipología 2×2 ISCAM | AD3: Banderas Duras | AE3: D12 Huella Carbono | AF3: D13 Reporte Sostenib. | AG3: D14 Economía Circular | AH3: D15 Fitosanitario | AI3: ISA-PV Promedio D12:D15 | AJ3: P_Global Promedio P1:P14 | AK3: ISA-EUDR Geom.D1–D7 + Arit.D8–D9 | AL3: ISA-Completo 0.70×EUDR +0.30×PV
A4: 20118578415 | B4: CENT.DE COOP.AGR. CAF.VALLES SANDIA LTDA | C4: PUNO | D4: 2553623.3 | E4: 0 | F4: =IFERROR(SCORECARDS!H3,"") | G4: =IFERROR(MATRIZ_174!U3,0) | H4: 0 | I4: =IFERROR(SCORECARDS!I3,"") | J4: =IFERROR(SCORECARDS!J3,"") | K4: 0 | L4: 0 | M4: 0 | N4: 0 | O4: 0 | P4: =IFERROR(F4,0) | Q4: =IFERROR(SQRT(G4*H4),0) | R4: =IFERROR((I4+J4+L4)/3,0) | S4: =IFERROR((J4+F4)/2,0) | T4: =IFERROR((K4+M4+MATRIZ_174!O3)/3,0) | U4: =IFERROR(MIN(100,ROUND(MATRIZ_174!M3,1)),0) | V4: =IFERROR(IF(E4=0,50,E4),0) | W4: =IFERROR(IF(MATRIZ_174!R3=0,65,IF(MATRIZ_174!R3/MATRIZ_174!Q3>=2,35,IF(MATRIZ_174!R3/MATRIZ_174!Q3>=0.5,50,65))),65) | X4: =IF(MATRIZ_174!O3=0,70,30) | Y4: =IF(OR(MATRIZ_174!P3="ASOCIACION",MATRIZ_174!P3="PENDIENTE"),65,40) | Z4: =IFERROR(ROUND(AVERAGE(P4,Q4,R4,S4,T4),1),0) | AA4: =IFERROR(ROUND(AVERAGE(U4,V4,W4,X4,Y4),1),0) | AB4: =IFERROR(ROUND(AA4*(1-Z4/100),1),0) | AC4: =IF(AND(Z4>=50,AA4<50),"🟢 Resilientes",IF(AND(Z4>=50,AA4>=50),"🟠 Expuestas Adaptables",IF(AND(Z4<50,AA4<50),"⬜ Riesgo Latente","🔴 Riesgo Crítico"))) | AD4: =IF(G4=0,"🚫 Inh. vigente OSCE","") | AE4: =IFERROR(MATRIZ_174!W3,0) | AF4: =IFERROR(MATRIZ_174!X3,0) | AG4: =IFERROR(MATRIZ_174!Y3,0) | AH4: =IFERROR(MATRIZ_174!Z3,0) | AI4: =IFERROR(MATRIZ_174!AP3,"N/A") | AJ4: =IFERROR(MATRIZ_174!AO3,"N/A") | AK4: =IFERROR(ROUND(POWER((E4*F4*G4*H4*I4*J4*K4),1/7)*0.875+((L4+M4)/2)*0.125,1),"N/A") | AL4: =IFERROR(IF(OR(AK4="N/A",AI4="N/A"),"N/A",ROUND(0.7*AK4+0.3*AI4*100,1)),"N/A")
A5: 20129156083 | B5: COOP AGRARIA CAFET VALLE RIO APURIMAC | C5: AYACUCHO | D5: 0 | E5: 0 | F5: =IFERROR(SCORECARDS!H4,"") | G5: =IFERROR(MATRIZ_174!U4,0) | H5: 0 | I5: =IFERROR(SCORECARDS!I4,"") | J5: =IFERROR(SCORECARDS!J4,"") | K5: 0 | L5: 0 | M5: 0 | N5: 0 | O5: 0 | P5: =IFERROR(F5,0) | Q5: =IFERROR(SQRT(G5*H5),0) | R5: =IFERROR((I5+J5+L5)/3,0) | S5: =IFERROR((J5+F5)/2,0) | T5: =IFERROR((K5+M5+MATRIZ_174!O4)/3,0) | U5: =IFERROR(MIN(100,ROUND(MATRIZ_174!M4,1)),0) | V5: =IFERROR(IF(E5=0,50,E5),0) | W5: =IFERROR(IF(MATRIZ_174!R4=0,65,IF(MATRIZ_174!R4/MATRIZ_174!Q4>=2,35,IF(MATRIZ_174!R4/MATRIZ_174!Q4>=0.5,50,65))),65) | X5: =IF(MATRIZ_174!O4=0,70,30) | Y5: =IF(OR(MATRIZ_174!P4="ASOCIACION",MATRIZ_174!P4="PENDIENTE"),65,40) | Z5: =IFERROR(ROUND(AVERAGE(P5,Q5,R5,S5,T5),1),0) | AA5: =IFERROR(ROUND(AVERAGE(U5,V5,W5,X5,Y5),1),0) | AB5: =IFERROR(ROUND(AA5*(1-Z5/100),1),0) | AC5: =IF(AND(Z5>=50,AA5<50),"🟢 Resilientes",IF(AND(Z5>=50,AA5>=50),"🟠 Expuestas Adaptables",IF(AND(Z5<50,AA5<50),"⬜ Riesgo Latente","🔴 Riesgo Crítico"))) | AD5: =IF(G5=0,"🚫 Inh. vigente OSCE","") | AE5: =IFERROR(MATRIZ_174!W4,0) | AF5: =IFERROR(MATRIZ_174!X4,0) | AG5: =IFERROR(MATRIZ_174!Y4,0) | AH5: =IFERROR(MATRIZ_174!Z4,0) | AI5: =IFERROR(MATRIZ_174!AP4,"N/A") | AJ5: =IFERROR(MATRIZ_174!AO4,"N/A") | AK5: =IFERROR(ROUND(POWER((E5*F5*G5*H5*I5*J5*K5),1/7)*0.875+((L5+M5)/2)*0.125,1),"N/A") | AL5: =IFERROR(IF(OR(AK5="N/A",AI5="N/A"),"N/A",ROUND(0.7*AK5+0.3*AI5*100,1)),"N/A")
A6: 20129529530 | B6: COOP AGRARIA CAFETALERA SATIPO LTDA | C6: JUNIN | D6: 4801984.1 | E6: 0 | F6: =IFERROR(SCORECARDS!H5,"") | G6: =IFERROR(MATRIZ_174!U5,0) | H6: 0 | I6: =IFERROR(SCORECARDS!I5,"") | J6: =IFERROR(SCORECARDS!J5,"") | K6: 0 | L6: 0 | M6: 0 | N6: 0 | O6: 0 | P6: =IFERROR(F6,0) | Q6: =IFERROR(SQRT(G6*H6),0) | R6: =IFERROR((I6+J6+L6)/3,0) | S6: =IFERROR((J6+F6)/2,0) | T6: =IFERROR((K6+M6+MATRIZ_174!O5)/3,0) | U6: =IFERROR(MIN(100,ROUND(MATRIZ_174!M5,1)),0) | V6: =IFERROR(IF(E6=0,50,E6),0) | W6: =IFERROR(IF(MATRIZ_174!R5=0,65,IF(MATRIZ_174!R5/MATRIZ_174!Q5>=2,35,IF(MATRIZ_174!R5/MATRIZ_174!Q5>=0.5,50,65))),65) | X6: =IF(MATRIZ_174!O5=0,70,30) | Y6: =IF(OR(MATRIZ_174!P5="ASOCIACION",MATRIZ_174!P5="PENDIENTE"),65,40) | Z6: =IFERROR(ROUND(AVERAGE(P6,Q6,R6,S6,T6),1),0) | AA6: =IFERROR(ROUND(AVERAGE(U6,V6,W6,X6,Y6),1),0) | AB6: =IFERROR(ROUND(AA6*(1-Z6/100),1),0) | AC6: =IF(AND(Z6>=50,AA6<50),"🟢 Resilientes",IF(AND(Z6>=50,AA6>=50),"🟠 Expuestas Adaptables",IF(AND(Z6<50,AA6<50),"⬜ Riesgo Latente","🔴 Riesgo Crítico"))) | AD6: =IF(G6=0,"🚫 Inh. vigente OSCE","") | AE6: =IFERROR(MATRIZ_174!W5,0) | AF6: =IFERROR(MATRIZ_174!X5,0) | AG6: =IFERROR(MATRIZ_174!Y5,0) | AH6: =IFERROR(MATRIZ_174!Z5,0) | AI6: =IFERROR(MATRIZ_174!AP5,"N/A") | AJ6: =IFERROR(MATRIZ_174!AO5,"N/A") | AK6: =IFERROR(ROUND(POWER((E6*F6*G6*H6*I6*J6*K6),1/7)*0.875+((L6+M6)/2)*0.125,1),"N/A") | AL6: =IFERROR(IF(OR(AK6="N/A",AI6="N/A"),"N/A",ROUND(0.7*AK6+0.3*AI6*100,1)),"N/A")
A7: 20132489824 | B7: COOPERATIVA AGRARIA CAFETALERA CHANCAMAYO LTDA. N° 008-B-VII | C7: CUSCO | D7: 0 | E7: 0 | F7: =IFERROR(SCORECARDS!H6,"") | G7: =IFERROR(MATRIZ_174!U6,0) | H7: 0 | I7: =IFERROR(SCORECARDS!I6,"") | J7: =IFERROR(SCORECARDS!J6,"") | K7: 0 | L7: 0 | M7: 0 | N7: 0 | O7: 0 | P7: =IFERROR(F7,0) | Q7: =IFERROR(SQRT(G7*H7),0) | R7: =IFERROR((I7+J7+L7)/3,0) | S7: =IFERROR((J7+F7)/2,0) | T7: =IFERROR((K7+M7+MATRIZ_174!O6)/3,0) | U7: =IFERROR(MIN(100,ROUND(MATRIZ_174!M6,1)),0) | V7: =IFERROR(IF(E7=0,50,E7),0) | W7: =IFERROR(IF(MATRIZ_174!R6=0,65,IF(MATRIZ_174!R6/MATRIZ_174!Q6>=2,35,IF(MATRIZ_174!R6/MATRIZ_174!Q6>=0.5,50,65))),65) | X7: =IF(MATRIZ_174!O6=0,70,30) | Y7: =IF(OR(MATRIZ_174!P6="ASOCIACION",MATRIZ_174!P6="PENDIENTE"),65,40) | Z7: =IFERROR(ROUND(AVERAGE(P7,Q7,R7,S7,T7),1),0) | AA7: =IFERROR(ROUND(AVERAGE(U7,V7,W7,X7,Y7),1),0) | AB7: =IFERROR(ROUND(AA7*(1-Z7/100),1),0) | AC7: =IF(AND(Z7>=50,AA7<50),"🟢 Resilientes",IF(AND(Z7>=50,AA7>=50),"🟠 Expuestas Adaptables",IF(AND(Z7<50,AA7<50),"⬜ Riesgo Latente","🔴 Riesgo Crítico"))) | AD7: =IF(G7=0,"🚫 Inh. vigente OSCE","") | AE7: =IFERROR(MATRIZ_174!W6,0) | AF7: =IFERROR(MATRIZ_174!X6,0) | AG7: =IFERROR(MATRIZ_174!Y6,0) | AH7: =IFERROR(MATRIZ_174!Z6,0) | AI7: =IFERROR(MATRIZ_174!AP6,"N/A") | AJ7: =IFERROR(MATRIZ_174!AO6,"N/A") | AK7: =IFERROR(ROUND(POWER((E7*F7*G7*H7*I7*J7*K7),1/7)*0.875+((L7+M7)/2)*0.125,1),"N/A") | AL7: =IFERROR(IF(OR(AK7="N/A",AI7="N/A"),"N/A",ROUND(0.7*AK7+0.3*AI7*100,1)),"N/A")
A8: 20132505455 | B8: COOPERATIVA AGRARIA CAFETALERA AGUILAYOC LTDA. 084 | C8: CUSCO | D8: 0 | E8: 0 | F8: =IFERROR(SCORECARDS!H7,"") | G8: =IFERROR(MATRIZ_174!U7,0) | H8: 0 | I8: =IFERROR(SCORECARDS!I7,"") | J8: =IFERROR(SCORECARDS!J7,"") | K8: 0 | L8: 0 | M8: 0 | N8: 0 | O8: 0 | P8: =IFERROR(F8,0) | Q8: =IFERROR(SQRT(G8*H8),0) | R8: =IFERROR((I8+J8+L8)/3,0) | S8: =IFERROR((J8+F8)/2,0) | T8: =IFERROR((K8+M8+MATRIZ_174!O7)/3,0) | U8: =IFERROR(MIN(100,ROUND(MATRIZ_174!M7,1)),0) | V8: =IFERROR(IF(E8=0,50,E8),0) | W8: =IFERROR(IF(MATRIZ_174!R7=0,65,IF(MATRIZ_174!R7/MATRIZ_174!Q7>=2,35,IF(MATRIZ_174!R7/MATRIZ_174!Q7>=0.5,50,65))),65) | X8: =IF(MATRIZ_174!O7=0,70,30) | Y8: =IF(OR(MATRIZ_174!P7="ASOCIACION",MATRIZ_174!P7="PENDIENTE"),65,40) | Z8: =IFERROR(ROUND(AVERAGE(P8,Q8,R8,S8,T8),1),0) | AA8: =IFERROR(ROUND(AVERAGE(U8,V8,W8,X8,Y8),1),0) | AB8: =IFERROR(ROUND(AA8*(1-Z8/100),1),0) | AC8: =IF(AND(Z8>=50,AA8<50),"🟢 Resilientes",IF(AND(Z8>=50,AA8>=50),"🟠 Expuestas Adaptables",IF(AND(Z8<50,AA8<50),"⬜ Riesgo Latente","🔴 Riesgo Crítico"))) | AD8: =IF(G8=0,"🚫 Inh. vigente OSCE","") | AE8: =IFERROR(MATRIZ_174!W7,0) | AF8: =IFERROR(MATRIZ_174!X7,0) | AG8: =IFERROR(MATRIZ_174!Y7,0) | AH8: =IFERROR(MATRIZ_174!Z7,0) | AI8: =IFERROR(MATRIZ_174!AP7,"N/A") | AJ8: =IFERROR(MATRIZ_174!AO7,"N/A") | AK8: =IFERROR(ROUND(POWER((E8*F8*G8*H8*I8*J8*K8),1/7)*0.875+((L8+M8)/2)*0.125,1),"N/A") | AL8: =IFERROR(IF(OR(AK8="N/A",AI8="N/A"),"N/A",ROUND(0.7*AK8+0.3*AI8*100,1)),"N/A")
A9: 20132509795 | B9: COOPERATIVA AGRARIA CAFETALERA JOSE OLAYA LTDA N° 252 | C9: CUSCO | D9: 1238541.8 | E9: 0 | F9: =IFERROR(SCORECARDS!H8,"") | G9: =IFERROR(MATRIZ_174!U8,0) | H9: 0 | I9: =IFERROR(SCORECARDS!I8,"") | J9: =IFERROR(SCORECARDS!J8,"") | K9: 0 | L9: 0 | M9: 0 | N9: 0 | O9: 0 | P9: =IFERROR(F9,0) | Q9: =IFERROR(SQRT(G9*H9),0) | R9: =IFERROR((I9+J9+L9)/3,0) | S9: =IFERROR((J9+F9)/2,0) | T9: =IFERROR((K9+M9+MATRIZ_174!O8)/3,0) | U9: =IFERROR(MIN(100,ROUND(MATRIZ_174!M8,1)),0) | V9: =IFERROR(IF(E9=0,50,E9),0) | W9: =IFERROR(IF(MATRIZ_174!R8=0,65,IF(MATRIZ_174!R8/MATRIZ_174!Q8>=2,35,IF(MATRIZ_174!R8/MATRIZ_174!Q8>=0.5,50,65))),65) | X9: =IF(MATRIZ_174!O8=0,70,30) | Y9: =IF(OR(MATRIZ_174!P8="ASOCIACION",MATRIZ_174!P8="PENDIENTE"),65,40) | Z9: =IFERROR(ROUND(AVERAGE(P9,Q9,R9,S9,T9),1),0) | AA9: =IFERROR(ROUND(AVERAGE(U9,V9,W9,X9,Y9),1),0) | AB9: =IFERROR(ROUND(AA9*(1-Z9/100),1),0) | AC9: =IF(AND(Z9>=50,AA9<50),"🟢 Resilientes",IF(AND(Z9>=50,AA9>=50),"🟠 Expuestas Adaptables",IF(AND(Z9<50,AA9<50),"⬜ Riesgo Latente","🔴 Riesgo Crítico"))) | AD9: =IF(G9=0,"🚫 Inh. vigente OSCE","") | AE9: =IFERROR(MATRIZ_174!W8,0) | AF9: =IFERROR(MATRIZ_174!X8,0) | AG9: =IFERROR(MATRIZ_174!Y8,0) | AH9: =IFERROR(MATRIZ_174!Z8,0) | AI9: =IFERROR(MATRIZ_174!AP8,"N/A") | AJ9: =IFERROR(MATRIZ_174!AO8,"N/A") | AK9: =IFERROR(ROUND(POWER((E9*F9*G9*H9*I9*J9*K9),1/7)*0.875+((L9+M9)/2)*0.125,1),"N/A") | AL9: =IFERROR(IF(OR(AK9="N/A",AI9="N/A"),"N/A",ROUND(0.7*AK9+0.3*AI9*100,1)),"N/A")
A10: 20132509876 | B10: COOPERATIVA AGRARIA CAFETALERA MARANURA LTDA. 129 | C10: CUSCO | D10: 0 | E10: 0 | F10: =IFERROR(SCORECARDS!H9,"") | G10: =IFERROR(MATRIZ_174!U9,0) | H10: 0 | I10: =IFERROR(SCORECARDS!I9,"") | J10: =IFERROR(SCORECARDS!J9,"") | K10: 0 | L10: 0 | M10: 0 | N10: 0 | O10: 0 | P10: =IFERROR(F10,0) | Q10: =IFERROR(SQRT(G10*H10),0) | R10: =IFERROR((I10+J10+L10)/3,0) | S10: =IFERROR((J10+F10)/2,0) | T10: =IFERROR((K10+M10+MATRIZ_174!O9)/3,0) | U10: =IFERROR(MIN(100,ROUND(MATRIZ_174!M9,1)),0) | V10: =IFERROR(IF(E10=0,50,E10),0) | W10: =IFERROR(IF(MATRIZ_174!R9=0,65,IF(MATRIZ_174!R9/MATRIZ_174!Q9>=2,35,IF(MATRIZ_174!R9/MATRIZ_174!Q9>=0.5,50,65))),65) | X10: =IF(MATRIZ_174!O9=0,70,30) | Y10: =IF(OR(MATRIZ_174!P9="ASOCIACION",MATRIZ_174!P9="PENDIENTE"),65,40) | Z10: =IFERROR(ROUND(AVERAGE(P10,Q10,R10,S10,T10),1),0) | AA10: =IFERROR(ROUND(AVERAGE(U10,V10,W10,X10,Y10),1),0) | AB10: =IFERROR(ROUND(AA10*(1-Z10/100),1),0) | AC10: =IF(AND(Z10>=50,AA10<50),"🟢 Resilientes",IF(AND(Z10>=50,AA10>=50),"🟠 Expuestas Adaptables",IF(AND(Z10<50,AA10<50),"⬜ Riesgo Latente","🔴 Riesgo Crítico"))) | AD10: =IF(G10=0,"🚫 Inh. vigente OSCE","") | AE10: =IFERROR(MATRIZ_174!W9,0) | AF10: =IFERROR(MATRIZ_174!X9,0) | AG10: =IFERROR(MATRIZ_174!Y9,0) | AH10: =IFERROR(MATRIZ_174!Z9,0) | AI10: =IFERROR(MATRIZ_174!AP9,"N/A") | AJ10: =IFERROR(MATRIZ_174!AO9,"N/A") | AK10: =IFERROR(ROUND(POWER((E10*F10*G10*H10*I10*J10*K10),1/7)*0.875+((L10+M10)/2)*0.125,1),"N/A") | AL10: =IFERROR(IF(OR(AK10="N/A",AI10="N/A"),"N/A",ROUND(0.7*AK10+0.3*AI10*100,1)),"N/A")
A11: 20132517119 | B11: COOPERATIVA AGRARIA CAFETALERA MATEO PUMACAHUA LTDA N° 185 | C11: CUSCO | D11: 0 | E11: 0 | F11: =IFERROR(SCORECARDS!H10,"") | G11: =IFERROR(MATRIZ_174!U10,0) | H11: 0 | I11: =IFERROR(SCORECARDS!I10,"") | J11: =IFERROR(SCORECARDS!J10,"") | K11: 0 | L11: 0 | M11: 0 | N11: 0 | O11: 0 | P11: =IFERROR(F11,0) | Q11: =IFERROR(SQRT(G11*H11),0) | R11: =IFERROR((I11+J11+L11)/3,0) | S11: =IFERROR((J11+F11)/2,0) | T11: =IFERROR((K11+M11+MATRIZ_174!O10)/3,0) | U11: =IFERROR(MIN(100,ROUND(MATRIZ_174!M10,1)),0) | V11: =IFERROR(IF(E11=0,50,E11),0) | W11: =IFERROR(IF(MATRIZ_174!R10=0,65,IF(MATRIZ_174!R10/MATRIZ_174!Q10>=2,35,IF(MATRIZ_174!R10/MATRIZ_174!Q10>=0.5,50,65))),65) | X11: =IF(MATRIZ_174!O10=0,70,30) | Y11: =IF(OR(MATRIZ_174!P10="ASOCIACION",MATRIZ_174!P10="PENDIENTE"),65,40) | Z11: =IFERROR(ROUND(AVERAGE(P11,Q11,R11,S11,T11),1),0) | AA11: =IFERROR(ROUND(AVERAGE(U11,V11,W11,X11,Y11),1),0) | AB11: =IFERROR(ROUND(AA11*(1-Z11/100),1),0) | AC11: =IF(AND(Z11>=50,AA11<50),"🟢 Resilientes",IF(AND(Z11>=50,AA11>=50),"🟠 Expuestas Adaptables",IF(AND(Z11<50,AA11<50),"⬜ Riesgo Latente","🔴 Riesgo Crítico"))) | AD11: =IF(G11=0,"🚫 Inh. vigente OSCE","") | AE11: =IFERROR(MATRIZ_174!W10,0) | AF11: =IFERROR(MATRIZ_174!X10,0) | AG11: =IFERROR(MATRIZ_174!Y10,0) | AH11: =IFERROR(MATRIZ_174!Z10,0) | AI11: =IFERROR(MATRIZ_174!AP10,"N/A") | AJ11: =IFERROR(MATRIZ_174!AO10,"N/A") | AK11: =IFERROR(ROUND(POWER((E11*F11*G11*H11*I11*J11*K11),1/7)*0.875+((L11+M11)/2)*0.125,1),"N/A") | AL11: =IFERROR(IF(OR(AK11="N/A",AI11="N/A"),"N/A",ROUND(0.7*AK11+0.3*AI11*100,1)),"N/A")
A12: 20136201132 | B12: COOPERATIVA AGRARIA CAFETALERA ALTO URUBAMBA LTDA N° 239 | C12: CUSCO | D12: 0 | E12: 0 | F12: =IFERROR(SCORECARDS!H11,"") | G12: =IFERROR(MATRIZ_174!U11,0) | H12: 0 | I12: =IFERROR(SCORECARDS!I11,"") | J12: =IFERROR(SCORECARDS!J11,"") | K12: 0 | L12: 0 | M12: 0 | N12: 0 | O12: 0 | P12: =IFERROR(F12,0) | Q12: =IFERROR(SQRT(G12*H12),0) | R12: =IFERROR((I12+J12+L12)/3,0) | S12: =IFERROR((J12+F12)/2,0) | T12: =IFERROR((K12+M12+MATRIZ_174!O11)/3,0) | U12: =IFERROR(MIN(100,ROUND(MATRIZ_174!M11,1)),0) | V12: =IFERROR(IF(E12=0,50,E12),0) | W12: =IFERROR(IF(MATRIZ_174!R11=0,65,IF(MATRIZ_174!R11/MATRIZ_174!Q11>=2,35,IF(MATRIZ_174!R11/MATRIZ_174!Q11>=0.5,50,65))),65) | X12: =IF(MATRIZ_174!O11=0,70,30) | Y12: =IF(OR(MATRIZ_174!P11="ASOCIACION",MATRIZ_174!P11="PENDIENTE"),65,40) | Z12: =IFERROR(ROUND(AVERAGE(P12,Q12,R12,S12,T12),1),0) | AA12: =IFERROR(ROUND(AVERAGE(U12,V12,W12,X12,Y12),1),0) | AB12: =IFERROR(ROUND(AA12*(1-Z12/100),1),0) | AC12: =IF(AND(Z12>=50,AA12<50),"🟢 Resilientes",IF(AND(Z12>=50,AA12>=50),"🟠 Expuestas Adaptables",IF(AND(Z12<50,AA12<50),"⬜ Riesgo Latente","🔴 Riesgo Crítico"))) | AD12: =IF(G12=0,"🚫 Inh. vigente OSCE","") | AE12: =IFERROR(MATRIZ_174!W11,0) | AF12: =IFERROR(MATRIZ_174!X11,0) | AG12: =IFERROR(MATRIZ_174!Y11,0) | AH12: =IFERROR(MATRIZ_174!Z11,0) | AI12: =IFERROR(MATRIZ_174!AP11,"N/A") | AJ12: =IFERROR(MATRIZ_174!AO11,"N/A") | AK12: =IFERROR(ROUND(POWER((E12*F12*G12*H12*I12*J12*K12),1/7)*0.875+((L12+M12)/2)*0.125,1),"N/A") | AL12: =IFERROR(IF(OR(AK12="N/A",AI12="N/A"),"N/A",ROUND(0.7*AK12+0.3*AI12*100,1)),"N/A")
A13: 20136201213 | B13: CENTRAL DE COOPERATIVAS AGRARIAS CAFETALERAS COCLA LTDA. N° | C13: CUSCO | D13: 894391.27 | E13: 0 | F13: =IFERROR(SCORECARDS!H12,"") | G13: =IFERROR(MATRIZ_174!U12,0) | H13: 0 | I13: =IFERROR(SCORECARDS!I12,"") | J13: =IFERROR(SCORECARDS!J12,"") | K13: 0 | L13: 0 | M13: 0 | N13: 0 | O13: 0 | P13: =IFERROR(F13,0) | Q13: =IFERROR(SQRT(G13*H13),0) | R13: =IFERROR((I13+J13+L13)/3,0) | S13: =IFERROR((J13+F13)/2,0) | T13: =IFERROR((K13+M13+MATRIZ_174!O12)/3,0) | U13: =IFERROR(MIN(100,ROUND(MATRIZ_174!M12,1)),0) | V13: =IFERROR(IF(E13=0,50,E13),0) | W13: =IFERROR(IF(MATRIZ_174!R12=0,65,IF(MATRIZ_174!R12/MATRIZ_174!Q12>=2,35,IF(MATRIZ_174!R12/MATRIZ_174!Q12>=0.5,50,65))),65) | X13: =IF(MATRIZ_174!O12=0,70,30) | Y13: =IF(OR(MATRIZ_174!P12="ASOCIACION",MATRIZ_174!P12="PENDIENTE"),65,40) | Z13: =IFERROR(ROUND(AVERAGE(P13,Q13,R13,S13,T13),1),0) | AA13: =IFERROR(ROUND(AVERAGE(U13,V13,W13,X13,Y13),1),0) | AB13: =IFERROR(ROUND(AA13*(1-Z13/100),1),0) | AC13: =IF(AND(Z13>=50,AA13<50),"🟢 Resilientes",IF(AND(Z13>=50,AA13>=50),"🟠 Expuestas Adaptables",IF(AND(Z13<50,AA13<50),"⬜ Riesgo Latente","🔴 Riesgo Crítico"))) | AD13: =IF(G13=0,"🚫 Inh. vigente OSCE","") | AE13: =IFERROR(MATRIZ_174!W12,0) | AF13: =IFERROR(MATRIZ_174!X12,0) | AG13: =IFERROR(MATRIZ_174!Y12,0) | AH13: =IFERROR(MATRIZ_174!Z12,0) | AI13: =IFERROR(MATRIZ_174!AP12,"N/A") | AJ13: =IFERROR(MATRIZ_174!AO12,"N/A") | AK13: =IFERROR(ROUND(POWER((E13*F13*G13*H13*I13*J13*K13),1/7)*0.875+((L13+M13)/2)*0.125,1),"N/A") | AL13: =IFERROR(IF(OR(AK13="N/A",AI13="N/A"),"N/A",ROUND(0.7*AK13+0.3*AI13*100,1)),"N/A")
A14: 20140292657 | B14: COOPERATIVA AGRARIA CAFETALERA CCOCHAPAMPA LTDA. | C14: CUSCO | D14: 0 | E14: 0 | F14: =IFERROR(SCORECARDS!H13,"") | G14: =IFERROR(MATRIZ_174!U13,0) | H14: 0 | I14: =IFERROR(SCORECARDS!I13,"") | J14: =IFERROR(SCORECARDS!J13,"") | K14: 0 | L14: 0 | M14: 0 | N14: 0 | O14: 0 | P14: =IFERROR(F14,0) | Q14: =IFERROR(SQRT(G14*H14),0) | R14: =IFERROR((I14+J14+L14)/3,0) | S14: =IFERROR((J14+F14)/2,0) | T14: =IFERROR((K14+M14+MATRIZ_174!O13)/3,0) | U14: =IFERROR(MIN(100,ROUND(MATRIZ_174!M13,1)),0) | V14: =IFERROR(IF(E14=0,50,E14),0) | W14: =IFERROR(IF(MATRIZ_174!R13=0,65,IF(MATRIZ_174!R13/MATRIZ_174!Q13>=2,35,IF(MATRIZ_174!R13/MATRIZ_174!Q13>=0.5,50,65))),65) | X14: =IF(MATRIZ_174!O13=0,70,30) | Y14: =IF(OR(MATRIZ_174!P13="ASOCIACION",MATRIZ_174!P13="PENDIENTE"),65,40) | Z14: =IFERROR(ROUND(AVERAGE(P14,Q14,R14,S14,T14),1),0) | AA14: =IFERROR(ROUND(AVERAGE(U14,V14,W14,X14,Y14),1),0) | AB14: =IFERROR(ROUND(AA14*(1-Z14/100),1),0) | AC14: =IF(AND(Z14>=50,AA14<50),"🟢 Resilientes",IF(AND(Z14>=50,AA14>=50),"🟠 Expuestas Adaptables",IF(AND(Z14<50,AA14<50),"⬜ Riesgo Latente","🔴 Riesgo Crítico"))) | AD14: =IF(G14=0,"🚫 Inh. vigente OSCE","") | AE14: =IFERROR(MATRIZ_174!W13,0) | AF14: =IFERROR(MATRIZ_174!X13,0) | AG14: =IFERROR(MATRIZ_174!Y13,0) | AH14: =IFERROR(MATRIZ_174!Z13,0) | AI14: =IFERROR(MATRIZ_174!AP13,"N/A") | AJ14: =IFERROR(MATRIZ_174!AO13,"N/A") | AK14: =IFERROR(ROUND(POWER((E14*F14*G14*H14*I14*J14*K14),1/7)*0.875+((L14+M14)/2)*0.125,1),"N/A") | AL14: =IFERROR(IF(OR(AK14="N/A",AI14="N/A"),"N/A",ROUND(0.7*AK14+0.3*AI14*100,1)),"N/A")
A15: 20143692010 | B15: COOPERATIVA AGRARIA EL QUINACHO LTDA. N° 078 | C15: AYACUCHO | D15: 2015347.3 | E15: 0 | F15: =IFERROR(SCORECARDS!H14,"") | G15: =IFERROR(MATRIZ_174!U14,0) | H15: 0 | I15: =IFERROR(SCORECARDS!I14,"") | J15: =IFERROR(SCORECARDS!J14,"") | K15: 0 | L15: 0 | M15: 0 | N15: 0 | O15: 0 | P15: =IFERROR(F15,0) | Q15: =IFERROR(SQRT(G15*H15),0) | R15: =IFERROR((I15+J15+L15)/3,0) | S15: =IFERROR((J15+F15)/2,0) | T15: =IFERROR((K15+M15+MATRIZ_174!O14)/3,0) | U15: =IFERROR(MIN(100,ROUND(MATRIZ_174!M14,1)),0) | V15: =IFERROR(IF(E15=0,50,E15),0) | W15: =IFERROR(IF(MATRIZ_174!R14=0,65,IF(MATRIZ_174!R14/MATRIZ_174!Q14>=2,35,IF(MATRIZ_174!R14/MATRIZ_174!Q14>=0.5,50,65))),65) | X15: =IF(MATRIZ_174!O14=0,70,30) | Y15: =IF(OR(MATRIZ_174!P14="ASOCIACION",MATRIZ_174!P14="PENDIENTE"),65,40) | Z15: =IFERROR(ROUND(AVERAGE(P15,Q15,R15,S15,T15),1),0) | AA15: =IFERROR(ROUND(AVERAGE(U15,V15,W15,X15,Y15),1),0) | AB15: =IFERROR(ROUND(AA15*(1-Z15/100),1),0) | AC15: =IF(AND(Z15>=50,AA15<50),"🟢 Resilientes",IF(AND(Z15>=50,AA15>=50),"🟠 Expuestas Adaptables",IF(AND(Z15<50,AA15<50),"⬜ Riesgo Latente","🔴 Riesgo Crítico"))) | AD15: =IF(G15=0,"🚫 Inh. vigente OSCE","") | AE15: =IFERROR(MATRIZ_174!W14,0) | AF15: =IFERROR(MATRIZ_174!X14,0) | AG15: =IFERROR(MATRIZ_174!Y14,0) | AH15: =IFERROR(MATRIZ_174!Z14,0) | AI15: =IFERROR(MATRIZ_174!AP14,"N/A") | AJ15: =IFERROR(MATRIZ_174!AO14,"N/A") | AK15: =IFERROR(ROUND(POWER((E15*F15*G15*H15*I15*J15*K15),1/7)*0.875+((L15+M15)/2)*0.125,1),"N/A") | AL15: =IFERROR(IF(OR(AK15="N/A",AI15="N/A"),"N/A",ROUND(0.7*AK15+0.3*AI15*100,1)),"N/A")
... A177: 20612331821 | B177: ASOCIACIÓN DE MUJERES LAS FLORES DE LUYA | C177: AMAZONAS | D177: 0 | E177: 0 | F177: =IFERROR(SCORECARDS!H176,"") | G177: =IFERROR(MATRIZ_174!U176,0) | H177: 0 | I177: =IFERROR(SCORECARDS!I176,"") | J177: =IFERROR(SCORECARDS!J176,"") | K177: 0 | L177: 0 | M177: 0 | N177: 0 | O177: 0 | P177: =IFERROR(F177,0) | Q177: =IFERROR(SQRT(G177*H177),0) | R177: =IFERROR((I177+J177+L177)/3,0) | S177: =IFERROR((J177+F177)/2,0) | T177: =IFERROR((K177+M177+MATRIZ_174!O176)/3,0) | U177: =IFERROR(MIN(100,ROUND(MATRIZ_174!M176,1)),0) | V177: =IFERROR(IF(E177=0,50,E177),0) | W177: =IFERROR(IF(MATRIZ_174!R176=0,65,IF(MATRIZ_174!R176/MATRIZ_174!Q176>=2,35,IF(MATRIZ_174!R176/MATRIZ_174!Q176>=0.5,50,65))),65) | X177: =IF(MATRIZ_174!O176=0,70,30) | Y177: =IF(OR(MATRIZ_174!P176="ASOCIACION",MATRIZ_174!P176="PENDIENTE"),65,40) | Z177: =IFERROR(ROUND(AVERAGE(P177,Q177,R177,S177,T177),1),0) | AA177: =IFERROR(ROUND(AVERAGE(U177,V177,W177,X177,Y177),1),0) | AB177: =IFERROR(ROUND(AA177*(1-Z177/100),1),0) | AC177: =IF(AND(Z177>=50,AA177<50),"🟢 Resilientes",IF(AND(Z177>=50,AA177>=50),"🟠 Expuestas Adaptables",IF(AND(Z177<50,AA177<50),"⬜ Riesgo Latente","🔴 Riesgo Crítico"))) | AD177: =IF(G177=0,"🚫 Inh. vigente OSCE","") | AE177: =IFERROR(MATRIZ_174!W176,0) | AF177: =IFERROR(MATRIZ_174!X176,0) | AG177: =IFERROR(MATRIZ_174!Y176,0) | AH177: =IFERROR(MATRIZ_174!Z176,0) | AI177: =IFERROR(MATRIZ_174!AP176,"N/A") | AJ177: =IFERROR(MATRIZ_174!AO176,"N/A") | AK177: =IFERROR(ROUND(POWER((E177*F177*G177*H177*I177*J177*K177),1/7)*0.875+((L177+M177)/2)*0.125,1),"N/A") | AL177: =IFERROR(IF(OR(AK177="N/A",AI177="N/A"),"N/A",ROUND(0.7*AK177+0.3*AI177*100,1)),"N/A")
A178: PROMEDIO MUESTRAL | Z178: =IFERROR(AVERAGE(Z4:Z177),"—") | AA178: =IFERROR(AVERAGE(AA4:AA177),"—") | AB178: =IFERROR(AVERAGE(AB4:AB177),"—") | AC178: n = 174 organizaciones | AL178: =IFERROR(AVERAGE(AL4:AL177),"—")
A180: METODOLOGÍA ISCAM | ISA-EUDR = 0.875×(D1×D2×...×D7)^(1/7) + 0.125×(D8+D9)/2 | ISA-PV = Promedio(D12:D15) | ISA-Completo = 0.70×ISA-EUDR + 0.30×ISA-PV | IP = Promedio(IP1..IP5): IP1=D2, IP2=√(D3×D4), IP3=(D5+D6+D8)/3, IP4=(D6+D2)/2, IP5=(D7+D9+Cert)/3 | IV = Promedio(IV1..IV5): IV1=ISA-PV×50, IV2=D1(base=50), IV3=ha>0?→65:35, IV4=cert=0?→70:30, IV5=tipo Asoc?→65:40 | RE = IV×(1−IP/100) | Corte 2×2: 50 | █ GRIS=pendiente Inst.2 █ AZUL=Datos llenos █ NARANJA=IV █ ROJO=RE █ VERDE=Ambiental █ OSCURO=ISA

Sheet PONDERADORES
A1: BLOQUE DE SUPUESTOS — PONDERACIONES DEL ÍNDICE PVE
A2: LEYENDA DE COLORES
A3: 🔵 Azul | B3: Input hardcoded — valor primario, editable
A4: ⚫ Negro | B4: Fórmula calculada — no editar manualmente
A5: 🟡 Amarillo | B5: Input editable — cambiar ponderación aquí
A6: 🟢 Verde | B6: Resultado positivo (cumple)
A7: 🔴 Rojo | B7: Resultado negativo (no cumple)
A8: ⬜ Gris | B8: Dato pendiente de capturar
A10: PONDERACIONES — MODIFICAR SOLO LAS CELDAS AMARILLAS
A11: Componente | B11: Dimensión EUDR | C11: Variable | D11: Ponderación (%)
A12: EXP_UE | B12: D7 / Exposición UE | C12: % FOB exportado a UE sobre FOB total | D12: 25
A13: TRAZA | B13: D2 / Trazabilidad | C13: ¿Existe vínculo lote → parcela con coords? | D13: 20
A14: DILIG | B14: D5 / Debida diligencia | C14: ¿Existe proceso de evaluación de riesgo? | D14: 15
A15: CAPAC | B15: D6 / Capacidad digital | C15: ¿Tiene personal dedicado a datos? | D15: 10
A16: PRESION | B16: D7 / Presión comprador | C16: ¿Comprador UE exige EUDR? | D16: 15
A17: CERTIF | B17: D8 / Certificaciones (variable Cert — NO confundir con D8 Gobernanza de ISCAM_Score) | C17: Score de certificaciones vigentes (Org + Ftrade) | D17: 10
A18: PPWR | B18: D14 / Envases PPWR — NO confundir con D14 Economía Circular de ISCAM_Score | C18: ¿Usa sacos reutilizables o certificados? | D18: 5
A19: TOTAL | D19: =SUM(D12:D18)
A21: ⚠ El TOTAL debe sumar 100. Si lo ajustas, el Índice PVE en SCORECARDS se recalcula automáticamente.
A23: VERSION ISCAM (2026-10-12) — Pesos mostrados para transparencia (fijos, no editables)
A24: ISA-EUDR e ISA-PV usan pesos FIJOS (87.5%/12.5% y 70%/30%). IP/IV pesan 20% cada sub-dim.
A25: SUBDIM | B25: FÓRMULA | C25: PESO
A26: ISA-EUDR | B26: Geom(D1:D7)^(1/7)×0.875 + ((D8+D9)/2)×0.125 — ver ISCAM_Score!AK | C26: 100%
A28: ISA-PactoVerde | B28: AVG(D12:D15) — ver ISCAM_Score!AI y MATRIZ_174!AP | C28: 100%
A30: ISA-Completo | B30: 0.70×ISA-EUDR + 0.30×ISA-PV — ver ISCAM_Score!AL | C30: 100%
A32: IP1 | B32: =D2 — ver ISCAM_Score!P | C32: 20%
A33: IP2 | B33: SQRT(D3 × D4) — ver ISCAM_Score!Q | C33: 20%
A34: IP3 | B34: (D5 + D6 + D8) / 3 — ver ISCAM_Score!R | C34: 20%
A35: IP4 | B35: (D6 + D2) / 2 — ver ISCAM_Score!S | C35: 20%
A36: IP5 | B36: (D7 + D9 + Cert) / 3 — ver ISCAM_Score!T | C36: 20%
A37: IP (total) | B37: AVG(IP1:IP5) — ver ISCAM_Score!Z | C37: 100%
A39: IV1 | B39: Exposición UE = % FOB UE (MATRIZ_174!M) — ver ISCAM_Score!U | C39: 20%
A40: IV2 | B40: D1 (base 50 si D1=0) — ver ISCAM_Score!V | C40: 20%
A41: IV3 | B41: Tamaño de parcela ha/socio (Q/R); sin dato → 65 — ver ISCAM_Score!W | C41: 20%
A42: IV4 | B42: Certificación: Cert=0 → 70 / Cert>0 → 30 — ver ISCAM_Score!X | C42: 20%
A43: IV5 | B43: Tipo de organización (PENDIENTE/Asociación → 65) — ver ISCAM_Score!Y | C43: 20%
A44: IV (total) | B44: AVG(IV1:IV5) — ver ISCAM_Score!AA | C44: 100%
A46: RE | C46: —
A47: Cuadrante 2×2 | B47: IP≥50 vs <50 × IV≥50 vs <50 | C47: Corte=50
A48: NOTAS 2026-10-14: | B48: IV1–IV5 son proxies documentados mientras se ingesta el Instrumento 2; sus definiciones de diseño usan B0.7/P1/P1b/P4/D7.26a (IV1), B0.4/B0.10/B0.11/B0.13/B0.14 (IV3) y B0.12 + D3.14i (IV4/IV5).
A49: P_Global | B49: DECIDIDO 2026-10-14: P_Global NO entra en ISA-Completo. El índice es el regresor/predictor del objetivo (f); la performance es la variable dependiente. ISCAM (Fase 4, paso 12) usa los indicadores de performance como validación externa del índice (certificaciones, % volumen trazable, continuidad exportadora, acceso a mercado UE): P_Global es esa variable de validación, no un insumo del índice. Fuente: Metodologia - Indice de Alineamiento (ISA) §5, Comparativa §3.3, Propuesta ISCAM IP-IV-RE.
A50: Escalas | B50: ISA-EUDR e ISA-Completo en 0–100; ISA-PV en 0–1 (MATRIZ_174!AP); el 0.30 de ISA-Completo multiplica ISA-PV ×100 (corregido 2026-10-14).

Sheet MATRIZ_174
A1: MATRIZ 174 — Datos existentes de organizaciones | W1: D12 | X1: D13 | Y1: D14 | Z1: D15 | AA1: P1 | AB1: P2 | AC1: P3 | AD1: P4 | AE1: P5 | AF1: P6 | AG1: P7 | AH1: P8 | AI1: P9 | AJ1: P10 | AK1: P11 | AL1: P12 | AM1: P13 | AN1: P14 | AO1: Bloque P Score (0-1) | AP1: ISA-PactoVerde (0-1)
A2: RUC | B2: Razón Social (SUNAT) | C2: Depto | D2: Producto | E2: FOB Total USD | F2: N° DUAs | G2: Exporta | H2: Cert. Orgánica | I2: Cert. Fairtrade | J2: Estado SUNAT | K2: Avance EUDR | L2: FOB UE USD | M2: % UE/FOB | N2: HS Code principal | O2: Score Cert (0-1) | P2: Tipo org. | Q2: N° aprox. socios | R2: Hectáreas aprox. | S2: PVE Score (0-100) | T2: Clasificación | U2: D3 Score (OSCE) | V2: D3 Observación | W2: D12 — Huella Carbono 0=Sin medición 1=En curso (ha conocidas) 2=Certificado ───────────────────── NOTA: Valor actual = proxy FAO/IPCC (ha × factor IPCC/FAO por cultivo). Reemplazar tras Instrumento 2 Q40-Q44. | X2: Reporte Sostenibilidad (D13) 0=No, 1=En curso, 2=Publicado | Y2: Economía Circular (D14) 0=No, 1=En transición, 2=Avanzado | Z2: Fitosanitario/LMR (D15) 0=No verificado, 1=En monitoreo, 2=Cumple UE | AA2: P1 — Productividad (USD/ha/año) | AB2: P2 — Ingreso neto (USD/ha) | AC2: P3 — % socios con acceso crédito | AD2: P4 — Gender score (% muj. en org.) | AE2: P5 — Formalización laboral (%) | AF2: P6 — Capacitación/año/persona | AG2: P7 — Tasa retención socios (%) | AH2: P8 — Diversificación ingresos (%) | AI2: P9 — Acceso mercados premium (%) | AJ2: P10 — Inversión EUDR (USD/año) | AK2: P11 — Score trazabilidad (%) | AL2: P12 — Quejas resueltas (%) | AM2: P13 — Energía renovable (%) | AN2: P14 — Residuos gestionados (%) | AO2: P_Global — Promedio P1:P14 (0=None, 1=满分) | AP2: ISA-PactoVerde = AVG(D12:D15)/2 0=Nada, 2=Certificado
A3: 20118578415 | B3: CENT.DE COOP.AGR. CAF.VALLES SANDIA LTDA | C3: PUNO | D3: CAFÉ | E3: 5107246.6 | F3: 38 | G3: SI | H3: nan | I3: nan | J3: ACTIVO | K3: nan | L3: 2553623.3 | M3: =IF(E3>0,ROUND(L3/E3*100,1),0) | N3: PENDIENTE | O3: =IF(H3="SI",1,0)*0.6+IF(I3="SI",1,0)*0.4 | P3: PENDIENTE | S3: =IFERROR(SCORECARDS!C3,"") | T3: =IF(NOT(ISNUMBER(S3)),"—",IF(S3<34,"🔴 Crítico",IF(S3<67,"🟡 Vulnerable","🟢 Preparado"))) | U3: 1 | V3: Sin hallazgos OSCE / OEFA | W3: 1 | X3: 0 | Y3: 0 | Z3: 0 | AA3: 0 | AB3: 0 | AC3: 0 | AD3: 0 | AE3: 0 | AF3: 0 | AG3: 0 | AH3: 0 | AI3: 0 | AJ3: 0 | AK3: 0 | AL3: 0 | AM3: 0 | AN3: 0 | AO3: =IFERROR(AVERAGE(AA3,AB3,AC3,AD3,AE3,AF3,AG3,AH3,AI3,AJ3,AK3,AL3,AM3,AN3),"N/A") | AP3: =IFERROR(AVERAGE(W3,X3,Y3,Z3)/2,"N/A")
A4: 20129156083 | B4: COOP AGRARIA CAFET VALLE RIO APURIMAC | C4: AYACUCHO | D4: CACAO | E4: 0 | G4: NO | H4: nan | I4: nan | J4: ACTIVO | K4: nan | L4: 0 | M4: =IF(E4>0,ROUND(L4/E4*100,1),0) | N4: PENDIENTE | O4: =IF(H4="SI",1,0)*0.6+IF(I4="SI",1,0)*0.4 | P4: PENDIENTE | S4: =IFERROR(SCORECARDS!C4,"") | T4: =IF(NOT(ISNUMBER(S4)),"—",IF(S4<34,"🔴 Crítico",IF(S4<67,"🟡 Vulnerable","🟢 Preparado"))) | W4: 0 | X4: 0 | Y4: 0 | Z4: 0 | AA4: 0 | AB4: 0 | AC4: 0 | AD4: 0 | AE4: 0 | AF4: 0 | AG4: 0 | AH4: 0 | AI4: 0 | AJ4: 0 | AK4: 0 | AL4: 0 | AM4: 0 | AN4: 0 | AO4: =IFERROR(AVERAGE(AA4,AB4,AC4,AD4,AE4,AF4,AG4,AH4,AI4,AJ4,AK4,AL4,AM4,AN4),"N/A") | AP4: =IFERROR(AVERAGE(W4,X4,Y4,Z4)/2,"N/A")
A5: 20129529530 | B5: COOP AGRARIA CAFETALERA SATIPO LTDA | C5: JUNIN | E5: 9603968.1 | F5: 41 | G5: SI | H5: nan | I5: nan | J5: ACTIVO | K5: nan | L5: 4801984.1 | M5: =IF(E5>0,ROUND(L5/E5*100,1),0) | N5: PENDIENTE | O5: =IF(H5="SI",1,0)*0.6+IF(I5="SI",1,0)*0.4 | P5: PENDIENTE | S5: =IFERROR(SCORECARDS!C5,"") | T5: =IF(NOT(ISNUMBER(S5)),"—",IF(S5<34,"🔴 Crítico",IF(S5<67,"🟡 Vulnerable","🟢 Preparado"))) | U5: 1 | V5: Sin hallazgos OSCE / OEFA | W5: 1 | X5: 0 | Y5: 0 | Z5: 0 | AA5: 0 | AB5: 0 | AC5: 0 | AD5: 0 | AE5: 0 | AF5: 0 | AG5: 0 | AH5: 0 | AI5: 0 | AJ5: 0 | AK5: 0 | AL5: 0 | AM5: 0 | AN5: 0 | AO5: =IFERROR(AVERAGE(AA5,AB5,AC5,AD5,AE5,AF5,AG5,AH5,AI5,AJ5,AK5,AL5,AM5,AN5),"N/A") | AP5: =IFERROR(AVERAGE(W5,X5,Y5,Z5)/2,"N/A")
A6: 20132489824 | B6: COOPERATIVA AGRARIA CAFETALERA CHANCAMAYO LTDA. N° 008-B-VII | C6: CUSCO | G6: NO | H6: Cer | I6: Vig | J6: ACTIVO | K6: nan | L6: 0 | M6: =IF(E6>0,ROUND(L6/E6*100,1),0) | N6: PENDIENTE | O6: =IF(H6="SI",1,0)*0.6+IF(I6="SI",1,0)*0.4 | P6: PENDIENTE | Q6: 44 | R6: 44 | S6: =IFERROR(SCORECARDS!C6,"") | T6: =IF(NOT(ISNUMBER(S6)),"—",IF(S6<34,"🔴 Crítico",IF(S6<67,"🟡 Vulnerable","🟢 Preparado"))) | W6: 1 | X6: 0 | Y6: 0 | Z6: 0 | AA6: 0 | AB6: 0 | AC6: 0 | AD6: 0 | AE6: 0 | AF6: 0 | AG6: 0 | AH6: 0 | AI6: 0 | AJ6: 0 | AK6: 0 | AL6: 0 | AM6: 0 | AN6: 0 | AO6: =IFERROR(AVERAGE(AA6,AB6,AC6,AD6,AE6,AF6,AG6,AH6,AI6,AJ6,AK6,AL6,AM6,AN6),"N/A") | AP6: =IFERROR(AVERAGE(W6,X6,Y6,Z6)/2,"N/A")
A7: 20132505455 | B7: COOPERATIVA AGRARIA CAFETALERA AGUILAYOC LTDA. 084 | C7: CUSCO | D7: CAFÉ | G7: NO | H7: Cer | I7: nan | J7: ACTIVO | K7: 0.75 | L7: 0 | M7: =IF(E7>0,ROUND(L7/E7*100,1),0) | N7: PENDIENTE | O7: =IF(H7="SI",1,0)*0.6+IF(I7="SI",1,0)*0.4 | P7: PENDIENTE | Q7: 100 | R7: 218 | S7: =IFERROR(SCORECARDS!C7,"") | T7: =IF(NOT(ISNUMBER(S7)),"—",IF(S7<34,"🔴 Crítico",IF(S7<67,"🟡 Vulnerable","🟢 Preparado"))) | W7: 1 | X7: 0 | Y7: 0 | Z7: 0 | AA7: 0 | AB7: 0 | AC7: 0 | AD7: 0 | AE7: 0 | AF7: 0 | AG7: 0 | AH7: 0 | AI7: 0 | AJ7: 0 | AK7: 0 | AL7: 0 | AM7: 0 | AN7: 0 | AO7: =IFERROR(AVERAGE(AA7,AB7,AC7,AD7,AE7,AF7,AG7,AH7,AI7,AJ7,AK7,AL7,AM7,AN7),"N/A") | AP7: =IFERROR(AVERAGE(W7,X7,Y7,Z7)/2,"N/A")
A8: 20132509795 | B8: COOPERATIVA AGRARIA CAFETALERA JOSE OLAYA LTDA N° 252 | C8: CUSCO | D8: CAFÉ | E8: 2477083.5 | F8: 14 | G8: SI | H8: nan | I8: nan | J8: ACTIVO | K8: nan | L8: 1238541.8 | M8: =IF(E8>0,ROUND(L8/E8*100,1),0) | N8: PENDIENTE | O8: =IF(H8="SI",1,0)*0.6+IF(I8="SI",1,0)*0.4 | P8: PENDIENTE | S8: =IFERROR(SCORECARDS!C8,"") | T8: =IF(NOT(ISNUMBER(S8)),"—",IF(S8<34,"🔴 Crítico",IF(S8<67,"🟡 Vulnerable","🟢 Preparado"))) | U8: 1 | V8: Sin hallazgos OSCE / OEFA | W8: 1 | X8: 0 | Y8: 0 | Z8: 0 | AA8: 0 | AB8: 0 | AC8: 0 | AD8: 0 | AE8: 0 | AF8: 0 | AG8: 0 | AH8: 0 | AI8: 0 | AJ8: 0 | AK8: 0 | AL8: 0 | AM8: 0 | AN8: 0 | AO8: =IFERROR(AVERAGE(AA8,AB8,AC8,AD8,AE8,AF8,AG8,AH8,AI8,AJ8,AK8,AL8,AM8,AN8),"N/A") | AP8: =IFERROR(AVERAGE(W8,X8,Y8,Z8)/2,"N/A")
A9: 20132509876 | B9: COOPERATIVA AGRARIA CAFETALERA MARANURA LTDA. 129 | C9: CUSCO | D9: CAFÉ | E9: 1689820.3 | F9: 5 | G9: SI | H9: nan | I9: nan | J9: ACTIVO | K9: nan | L9: 0 | M9: =IF(E9>0,ROUND(L9/E9*100,1),0) | N9: PENDIENTE | O9: =IF(H9="SI",1,0)*0.6+IF(I9="SI",1,0)*0.4 | P9: PENDIENTE | S9: =IFERROR(SCORECARDS!C9,"") | T9: =IF(NOT(ISNUMBER(S9)),"—",IF(S9<34,"🔴 Crítico",IF(S9<67,"🟡 Vulnerable","🟢 Preparado"))) | W9: 0 | X9: 0 | Y9: 0 | Z9: 0 | AA9: 0 | AB9: 0 | AC9: 0 | AD9: 0 | AE9: 0 | AF9: 0 | AG9: 0 | AH9: 0 | AI9: 0 | AJ9: 0 | AK9: 0 | AL9: 0 | AM9: 0 | AN9: 0 | AO9: =IFERROR(AVERAGE(AA9,AB9,AC9,AD9,AE9,AF9,AG9,AH9,AI9,AJ9,AK9,AL9,AM9,AN9),"N/A") | AP9: =IFERROR(AVERAGE(W9,X9,Y9,Z9)/2,"N/A")
A10: 20132517119 | B10: COOPERATIVA AGRARIA CAFETALERA MATEO PUMACAHUA LTDA N° 185 | C10: CUSCO | D10: CAFÉ | E10: 0 | G10: NO | H10: Cer | I10: Fai | J10: ACTIVO | K10: 0.75 | L10: 0 | M10: =IF(E10>0,ROUND(L10/E10*100,1),0) | N10: PENDIENTE | O10: =IF(H10="SI",1,0)*0.6+IF(I10="SI",1,0)*0.4 | P10: PENDIENTE | Q10: 177 | R10: 469 | S10: =IFERROR(SCORECARDS!C10,"") | T10: =IF(NOT(ISNUMBER(S10)),"—",IF(S10<34,"🔴 Crítico",IF(S10<67,"🟡 Vulnerable","🟢 Preparado"))) | W10: 1 | X10: 0 | Y10: 0 | Z10: 0 | AA10: 0 | AB10: 0 | AC10: 0 | AD10: 0 | AE10: 0 | AF10: 0 | AG10: 0 | AH10: 0 | AI10: 0 | AJ10: 0 | AK10: 0 | AL10: 0 | AM10: 0 | AN10: 0 | AO10: =IFERROR(AVERAGE(AA10,AB10,AC10,AD10,AE10,AF10,AG10,AH10,AI10,AJ10,AK10,AL10,AM10,AN10),"N/A") | AP10: =IFERROR(AVERAGE(W10,X10,Y10,Z10)/2,"N/A")
A11: 20136201132 | B11: COOPERATIVA AGRARIA CAFETALERA ALTO URUBAMBA LTDA N° 239 | C11: CUSCO | D11: CAFÉ | E11: 681394.36 | F11: 6 | G11: SI | H11: nan | I11: nan | J11: ACTIVO | K11: nan | L11: 0 | M11: =IF(E11>0,ROUND(L11/E11*100,1),0) | N11: PENDIENTE | O11: =IF(H11="SI",1,0)*0.6+IF(I11="SI",1,0)*0.4 | P11: PENDIENTE | S11: =IFERROR(SCORECARDS!C11,"") | T11: =IF(NOT(ISNUMBER(S11)),"—",IF(S11<34,"🔴 Crítico",IF(S11<67,"🟡 Vulnerable","🟢 Preparado"))) | W11: 0 | X11: 0 | Y11: 0 | Z11: 0 | AA11: 0 | AB11: 0 | AC11: 0 | AD11: 0 | AE11: 0 | AF11: 0 | AG11: 0 | AH11: 0 | AI11: 0 | AJ11: 0 | AK11: 0 | AL11: 0 | AM11: 0 | AN11: 0 | AO11: =IFERROR(AVERAGE(AA11,AB11,AC11,AD11,AE11,AF11,AG11,AH11,AI11,AJ11,AK11,AL11,AM11,AN11),"N/A") | AP11: =IFERROR(AVERAGE(W11,X11,Y11,Z11)/2,"N/A")
A12: 20136201213 | B12: CENTRAL DE COOPERATIVAS AGRARIAS CAFETALERAS COCLA LTDA. N° | C12: CUSCO | D12: CAFÉ | E12: 4445611.6 | F12: 33 | G12: SI | H12: Cer | I12: Fai | J12: ACTIVO | K12: 0.75 | L12: 894391.27 | M12: =IF(E12>0,ROUND(L12/E12*100,1),0) | N12: PENDIENTE | O12: =IF(H12="SI",1,0)*0.6+IF(I12="SI",1,0)*0.4 | P12: PENDIENTE | Q12: 660 | R12: 1670 | S12: =IFERROR(SCORECARDS!C12,"") | T12: =IF(NOT(ISNUMBER(S12)),"—",IF(S12<34,"🔴 Crítico",IF(S12<67,"🟡 Vulnerable","🟢 Preparado"))) | U12: 0.75 | V12: ⚠ 1 infracc. ambiental (OEFA) | W12: 1 | X12: 0 | Y12: 0 | Z12: 0 | AA12: 0 | AB12: 0 | AC12: 0 | AD12: 0 | AE12: 0 | AF12: 0 | AG12: 0 | AH12: 0 | AI12: 0 | AJ12: 0 | AK12: 0 | AL12: 0 | AM12: 0 | AN12: 0 | AO12: =IFERROR(AVERAGE(AA12,AB12,AC12,AD12,AE12,AF12,AG12,AH12,AI12,AJ12,AK12,AL12,AM12,AN12),"N/A") | AP12: =IFERROR(AVERAGE(W12,X12,Y12,Z12)/2,"N/A")
A13: 20140292657 | B13: COOPERATIVA AGRARIA CAFETALERA CCOCHAPAMPA LTDA. | C13: CUSCO | D13: CAFÉ | E13: 0 | G13: NO | H13: Cer | I13: Fa | J13: ACTIVO | K13: 0.75 | L13: 0 | M13: =IF(E13>0,ROUND(L13/E13*100,1),0) | N13: PENDIENTE | O13: =IF(H13="SI",1,0)*0.6+IF(I13="SI",1,0)*0.4 | P13: PENDIENTE | Q13: 49 | R13: 136.9 | S13: =IFERROR(SCORECARDS!C13,"") | T13: =IF(NOT(ISNUMBER(S13)),"—",IF(S13<34,"🔴 Crítico",IF(S13<67,"🟡 Vulnerable","🟢 Preparado"))) | W13: 1 | X13: 0 | Y13: 0 | Z13: 0 | AA13: 0 | AB13: 0 | AC13: 0 | AD13: 0 | AE13: 0 | AF13: 0 | AG13: 0 | AH13: 0 | AI13: 0 | AJ13: 0 | AK13: 0 | AL13: 0 | AM13: 0 | AN13: 0 | AO13: =IFERROR(AVERAGE(AA13,AB13,AC13,AD13,AE13,AF13,AG13,AH13,AI13,AJ13,AK13,AL13,AM13,AN13),"N/A") | AP13: =IFERROR(AVERAGE(W13,X13,Y13,Z13)/2,"N/A")
A14: 20143692010 | B14: COOPERATIVA AGRARIA EL QUINACHO LTDA. N° 078 | C14: AYACUCHO | D14: CACAO | E14: 4030694.7 | F14: 14 | G14: SI | H14: nan | I14: nan | J14: ACTIVO | K14: nan | L14: 2015347.3 | M14: =IF(E14>0,ROUND(L14/E14*100,1),0) | N14: PENDIENTE | O14: =IF(H14="SI",1,0)*0.6+IF(I14="SI",1,0)*0.4 | P14: PENDIENTE | S14: =IFERROR(SCORECARDS!C14,"") | T14: =IF(NOT(ISNUMBER(S14)),"—",IF(S14<34,"🔴 Crítico",IF(S14<67,"🟡 Vulnerable","🟢 Preparado"))) | U14: 1 | V14: Sin hallazgos OSCE / OEFA | W14: 1 | X14: 0 | Y14: 0 | Z14: 0 | AA14: 0 | AB14: 0 | AC14: 0 | AD14: 0 | AE14: 0 | AF14: 0 | AG14: 0 | AH14: 0 | AI14: 0 | AJ14: 0 | AK14: 0 | AL14: 0 | AM14: 0 | AN14: 0 | AO14: =IFERROR(AVERAGE(AA14,AB14,AC14,AD14,AE14,AF14,AG14,AH14,AI14,AJ14,AK14,AL14,AM14,AN14),"N/A") | AP14: =IFERROR(AVERAGE(W14,X14,Y14,Z14)/2,"N/A")
A15: 20145484597 | B15: COOPERATIVA AGRARIA CAFETALERA SAN IGNACIO LTDA. | C15: PUNO | D15: CAFÉ | G15: NO | H15: nan | I15: nan | J15: ACTIVO | K15: nan | L15: 0 | M15: =IF(E15>0,ROUND(L15/E15*100,1),0) | N15: PENDIENTE | O15: =IF(H15="SI",1,0)*0.6+IF(I15="SI",1,0)*0.4 | P15: PENDIENTE | S15: =IFERROR(SCORECARDS!C15,"") | T15: =IF(NOT(ISNUMBER(S15)),"—",IF(S15<34,"🔴 Crítico",IF(S15<67,"🟡 Vulnerable","🟢 Preparado"))) | W15: 0 | X15: 0 | Y15: 0 | Z15: 0 | AA15: 0 | AB15: 0 | AC15: 0 | AD15: 0 | AE15: 0 | AF15: 0 | AG15: 0 | AH15: 0 | AI15: 0 | AJ15: 0 | AK15: 0 | AL15: 0 | AM15: 0 | AN15: 0 | AO15: =IFERROR(AVERAGE(AA15,AB15,AC15,AD15,AE15,AF15,AG15,AH15,AI15,AJ15,AK15,AL15,AM15,AN15),"N/A") | AP15: =IFERROR(AVERAGE(W15,X15,Y15,Z15)/2,"N/A")
A16: 20146696041 | B16: COOP AGRARIA CAFET JOSE GABRIEL CONDORCA | C16: PIURA | D16: CAFÉ | G16: NO | H16: nan | I16: nan | J16: ACTIVO | K16: nan | L16: 0 | M16: =IF(E16>0,ROUND(L16/E16*100,1),0) | N16: PENDIENTE | O16: =IF(H16="SI",1,0)*0.6+IF(I16="SI",1,0)*0.4 | P16: PENDIENTE | S16: =IFERROR(SCORECARDS!C16,"") | T16: =IF(NOT(ISNUMBER(S16)),"—",IF(S16<34,"🔴 Crítico",IF(S16<67,"🟡 Vulnerable","🟢 Preparado"))) | W16: 0 | X16: 0 | Y16: 0 | Z16: 0 | AA16: 0 | AB16: 0 | AC16: 0 | AD16: 0 | AE16: 0 | AF16: 0 | AG16: 0 | AH16: 0 | AI16: 0 | AJ16: 0 | AK16: 0 | AL16: 0 | AM16: 0 | AN16: 0 | AO16: =IFERROR(AVERAGE(AA16,AB16,AC16,AD16,AE16,AF16,AG16,AH16,AI16,AJ16,AK16,AL16,AM16,AN16),"N/A") | AP16: =IFERROR(AVERAGE(W16,X16,Y16,Z16)/2,"N/A")
A17: 20147443120 | B17: COOPERATIVA AGRARIA CAFETALERA TIRIJUAY PAVAYOC LTDA 013-B-V | C17: CUSCO | G17: NO | H17: Cer | I17: Vig | J17: SUSPENSION TEMPORAL | K17: nan | L17: 0 | M17: =IF(E17>0,ROUND(L17/E17*100,1),0) | N17: PENDIENTE | O17: =IF(H17="SI",1,0)*0.6+IF(I17="SI",1,0)*0.4 | P17: PENDIENTE | Q17: 74 | R17: 150 | S17: =IFERROR(SCORECARDS!C17,"") | T17: =IF(NOT(ISNUMBER(S17)),"—",IF(S17<34,"🔴 Crítico",IF(S17<67,"🟡 Vulnerable","🟢 Preparado"))) | W17: 1 | X17: 0 | Y17: 0 | Z17: 0 | AA17: 0 | AB17: 0 | AC17: 0 | AD17: 0 | AE17: 0 | AF17: 0 | AG17: 0 | AH17: 0 | AI17: 0 | AJ17: 0 | AK17: 0 | AL17: 0 | AM17: 0 | AN17: 0 | AO17: =IFERROR(AVERAGE(AA17,AB17,AC17,AD17,AE17,AF17,AG17,AH17,AI17,AJ17,AK17,AL17,AM17,AN17),"N/A") | AP17: =IFERROR(AVERAGE(W17,X17,Y17,Z17)/2,"N/A")
A18: 20166786861 | B18: COMITE CENTRAL DE PRODUCTORES AGROPECUARIOS DE SAN ALEJANDRO | C18: UCAYALI | D18: CACAO | G18: NO | H18: nan | I18: nan | J18: ACTIVO | K18: nan | L18: 0 | M18: =IF(E18>0,ROUND(L18/E18*100,1),0) | N18: PENDIENTE | O18: =IF(H18="SI",1,0)*0.6+IF(I18="SI",1,0)*0.4 | P18: PENDIENTE | S18: =IFERROR(SCORECARDS!C18,"") | T18: =IF(NOT(ISNUMBER(S18)),"—",IF(S18<34,"🔴 Crítico",IF(S18<67,"🟡 Vulnerable","🟢 Preparado"))) | W18: 0 | X18: 0 | Y18: 0 | Z18: 0 | AA18: 0 | AB18: 0 | AC18: 0 | AD18: 0 | AE18: 0 | AF18: 0 | AG18: 0 | AH18: 0 | AI18: 0 | AJ18: 0 | AK18: 0 | AL18: 0 | AM18: 0 | AN18: 0 | AO18: =IFERROR(AVERAGE(AA18,AB18,AC18,AD18,AE18,AF18,AG18,AH18,AI18,AJ18,AK18,AL18,AM18,AN18),"N/A") | AP18: =IFERROR(AVERAGE(W18,X18,Y18,Z18)/2,"N/A")
A19: 20170142773 | B19: COOPERATIVA AGRARIA CAFETALERA BAGUA GRANDE LIMITADA | C19: AMAZONAS | D19: CAFÉ | E19: 9070756.9 | F19: 41 | G19: SI | H19: nan | I19: nan | J19: ACTIVO | K19: nan | L19: 4535378.4 | M19: =IF(E19>0,ROUND(L19/E19*100,1),0) | N19: PENDIENTE | O19: =IF(H19="SI",1,0)*0.6+IF(I19="SI",1,0)*0.4 | P19: PENDIENTE | S19: =IFERROR(SCORECARDS!C19,"") | T19: =IF(NOT(ISNUMBER(S19)),"—",IF(S19<34,"🔴 Crítico",IF(S19<67,"🟡 Vulnerable","🟢 Preparado"))) | U19: 1 | V19: Sin hallazgos OSCE / OEFA | W19: 1 | X19: 0 | Y19: 0 | Z19: 0 | AA19: 0 | AB19: 0 | AC19: 0 | AD19: 0 | AE19: 0 | AF19: 0 | AG19: 0 | AH19: 0 | AI19: 0 | AJ19: 0 | AK19: 0 | AL19: 0 | AM19: 0 | AN19: 0 | AO19: =IFERROR(AVERAGE(AA19,AB19,AC19,AD19,AE19,AF19,AG19,AH19,AI19,AJ19,AK19,AL19,AM19,AN19),"N/A") | AP19: =IFERROR(AVERAGE(W19,X19,Y19,Z19)/2,"N/A")
A20: 20200880448 | B20: COOPERATIVA AGRARIA CAFETALERA JORGE CHAVEZ LTDA | C20: CUSCO | G20: NO | H20: Cer | I20: Vig | J20: ACTIVO | K20: nan | L20: 0 | M20: =IF(E20>0,ROUND(L20/E20*100,1),0) | N20: PENDIENTE | O20: =IF(H20="SI",1,0)*0.6+IF(I20="SI",1,0)*0.4 | P20: PENDIENTE | Q20: 36 | R20: 38 | S20: =IFERROR(SCORECARDS!C20,"") | T20: =IF(NOT(ISNUMBER(S20)),"—",IF(S20<34,"🔴 Crítico",IF(S20<67,"🟡 Vulnerable","🟢 Preparado"))) | W20: 1 | X20: 0 | Y20: 0 | Z20: 0 | AA20: 0 | AB20: 0 | AC20: 0 | AD20: 0 | AE20: 0 | AF20: 0 | AG20: 0 | AH20: 0 | AI20: 0 | AJ20: 0 | AK20: 0 | AL20: 0 | AM20: 0 | AN20: 0 | AO20: =IFERROR(AVERAGE(AA20,AB20,AC20,AD20,AE20,AF20,AG20,AH20,AI20,AJ20,AK20,AL20,AM20,AN20),"N/A") | AP20: =IFERROR(AVERAGE(W20,X20,Y20,Z20)/2,"N/A")
A21: 20352417018 | B21: COOPERATIVA AGRARIA DE CACAOTEROS TECNIFICADOS DE PADRE ABAD | C21: UCAYALI | D21: CACAO | E21: 0 | G21: NO | H21: nan | I21: nan | J21: SUSPENSION TEMPORAL | K21: nan | L21: 0 | M21: =IF(E21>0,ROUND(L21/E21*100,1),0) | N21: PENDIENTE | O21: =IF(H21="SI",1,0)*0.6+IF(I21="SI",1,0)*0.4 | P21: PENDIENTE | S21: =IFERROR(SCORECARDS!C21,"") | T21: =IF(NOT(ISNUMBER(S21)),"—",IF(S21<34,"🔴 Crítico",IF(S21<67,"🟡 Vulnerable","🟢 Preparado"))) | W21: 0 | X21: 0 | Y21: 0 | Z21: 0 | AA21: 0 | AB21: 0 | AC21: 0 | AD21: 0 | AE21: 0 | AF21: 0 | AG21: 0 | AH21: 0 | AI21: 0 | AJ21: 0 | AK21: 0 | AL21: 0 | AM21: 0 | AN21: 0 | AO21: =IFERROR(AVERAGE(AA21,AB21,AC21,AD21,AE21,AF21,AG21,AH21,AI21,AJ21,AK21,AL21,AM21,AN21),"N/A") | AP21: =IFERROR(AVERAGE(W21,X21,Y21,Z21)/2,"N/A")
A22: 20352423921 | B22: COOPERATIVA AGRARIA CAFETALERA DIVISORIA LTDA | C22: HUANUCO | D22: CAFÉ | E22: 0 | G22: NO | H22: nan | I22: nan | J22: ACTIVO | K22: nan | L22: 0 | M22: =IF(E22>0,ROUND(L22/E22*100,1),0) | N22: PENDIENTE | O22: =IF(H22="SI",1,0)*0.6+IF(I22="SI",1,0)*0.4 | P22: PENDIENTE | S22: =IFERROR(SCORECARDS!C22,"") | T22: =IF(NOT(ISNUMBER(S22)),"—",IF(S22<34,"🔴 Crítico",IF(S22<67,"🟡 Vulnerable","🟢 Preparado"))) | W22: 0 | X22: 0 | Y22: 0 | Z22: 0 | AA22: 0 | AB22: 0 | AC22: 0 | AD22: 0 | AE22: 0 | AF22: 0 | AG22: 0 | AH22: 0 | AI22: 0 | AJ22: 0 | AK22: 0 | AL22: 0 | AM22: 0 | AN22: 0 | AO22: =IFERROR(AVERAGE(AA22,AB22,AC22,AD22,AE22,AF22,AG22,AH22,AI22,AJ22,AK22,AL22,AM22,AN22),"N/A") | AP22: =IFERROR(AVERAGE(W22,X22,Y22,Z22)/2,"N/A")
A23: 20393152207 | B23: COOPERATIVA AGRO INDUSTRIAL APCTVASH | C23: UCAYALI | D23: CACAO | G23: NO | H23: nan | I23: nan | J23: ACTIVO | K23: nan | L23: 0 | M23: =IF(E23>0,ROUND(L23/E23*100,1),0) | N23: PENDIENTE | O23: =IF(H23="SI",1,0)*0.6+IF(I23="SI",1,0)*0.4 | P23: PENDIENTE | S23: =IFERROR(SCORECARDS!C23,"") | T23: =IF(NOT(ISNUMBER(S23)),"—",IF(S23<34,"🔴 Crítico",IF(S23<67,"🟡 Vulnerable","🟢 Preparado"))) | W23: 0 | X23: 0 | Y23: 0 | Z23: 0 | AA23: 0 | AB23: 0 | AC23: 0 | AD23: 0 | AE23: 0 | AF23: 0 | AG23: 0 | AH23: 0 | AI23: 0 | AJ23: 0 | AK23: 0 | AL23: 0 | AM23: 0 | AN23: 0 | AO23: =IFERROR(AVERAGE(AA23,AB23,AC23,AD23,AE23,AF23,AG23,AH23,AI23,AJ23,AK23,AL23,AM23,AN23),"N/A") | AP23: =IFERROR(AVERAGE(W23,X23,Y23,Z23)/2,"N/A")
A24: 20393593670 | B24: COMITE CENTRAL CON DESARROLLO AL FUTURO DE CURIMANA | C24: UCAYALI | D24: CACAO | E24: 0 | G24: NO | H24: nan | I24: nan | J24: BAJA DE OFICIO | K24: nan | L24: 0 | M24: =IF(E24>0,ROUND(L24/E24*100,1),0) | N24: PENDIENTE | O24: =IF(H24="SI",1,0)*0.6+IF(I24="SI",1,0)*0.4 | P24: PENDIENTE | S24: =IFERROR(SCORECARDS!C24,"") | T24: =IF(NOT(ISNUMBER(S24)),"—",IF(S24<34,"🔴 Crítico",IF(S24<67,"🟡 Vulnerable","🟢 Preparado"))) | W24: 0 | X24: 0 | Y24: 0 | Z24: 0 | AA24: 0 | AB24: 0 | AC24: 0 | AD24: 0 | AE24: 0 | AF24: 0 | AG24: 0 | AH24: 0 | AI24: 0 | AJ24: 0 | AK24: 0 | AL24: 0 | AM24: 0 | AN24: 0 | AO24: =IFERROR(AVERAGE(AA24,AB24,AC24,AD24,AE24,AF24,AG24,AH24,AI24,AJ24,AK24,AL24,AM24,AN24),"N/A") | AP24: =IFERROR(AVERAGE(W24,X24,Y24,Z24)/2,"N/A")
A25: 20393692228 | B25: COOPERATIVA AGRARIA CACAOTERA SAN ALEJANDRO LTDA | C25: UCAYALI | D25: CACAO | E25: 0 | G25: NO | H25: nan | I25: nan | J25: ACTIVO | K25: nan | L25: 0 | M25: =IF(E25>0,ROUND(L25/E25*100,1),0) | N25: PENDIENTE | O25: =IF(H25="SI",1,0)*0.6+IF(I25="SI",1,0)*0.4 | P25: PENDIENTE | S25: =IFERROR(SCORECARDS!C25,"") | T25: =IF(NOT(ISNUMBER(S25)),"—",IF(S25<34,"🔴 Crítico",IF(S25<67,"🟡 Vulnerable","🟢 Preparado"))) | W25: 0 | X25: 0 | Y25: 0 | Z25: 0 | AA25: 0 | AB25: 0 | AC25: 0 | AD25: 0 | AE25: 0 | AF25: 0 | AG25: 0 | AH25: 0 | AI25: 0 | AJ25: 0 | AK25: 0 | AL25: 0 | AM25: 0 | AN25: 0 | AO25: =IFERROR(AVERAGE(AA25,AB25,AC25,AD25,AE25,AF25,AG25,AH25,AI25,AJ25,AK25,AL25,AM25,AN25),"N/A") | AP25: =IFERROR(AVERAGE(W25,X25,Y25,Z25)/2,"N/A")
A26: 20393786044 | B26: COOPERATIVA AGRARIA CAFETALERA COORDILLERA AZUL DE UCAYALI L | C26: UCAYALI | D26: CAFÉ | G26: NO | H26: nan | I26: nan | J26: ACTIVO | K26: nan | L26: 0 | M26: =IF(E26>0,ROUND(L26/E26*100,1),0) | N26: PENDIENTE | O26: =IF(H26="SI",1,0)*0.6+IF(I26="SI",1,0)*0.4 | P26: PENDIENTE | S26: =IFERROR(SCORECARDS!C26,"") | T26: =IF(NOT(ISNUMBER(S26)),"—",IF(S26<34,"🔴 Crítico",IF(S26<67,"🟡 Vulnerable","🟢 Preparado"))) | W26: 0 | X26: 0 | Y26: 0 | Z26: 0 | AA26: 0 | AB26: 0 | AC26: 0 | AD26: 0 | AE26: 0 | AF26: 0 | AG26: 0 | AH26: 0 | AI26: 0 | AJ26: 0 | AK26: 0 | AL26: 0 | AM26: 0 | AN26: 0 | AO26: =IFERROR(AVERAGE(AA26,AB26,AC26,AD26,AE26,AF26,AG26,AH26,AI26,AJ26,AK26,AL26,AM26,AN26),"N/A") | AP26: =IFERROR(AVERAGE(W26,X26,Y26,Z26)/2,"N/A")
A27: 20393816211 | B27: COOPERATIVA AGRARIA SAN JUAN BAUTISTA | C27: UCAYALI | D27: CACAO | E27: 0 | G27: NO | H27: nan | I27: nan | J27: ACTIVO | K27: nan | L27: 0 | M27: =IF(E27>0,ROUND(L27/E27*100,1),0) | N27: PENDIENTE | O27: =IF(H27="SI",1,0)*0.6+IF(I27="SI",1,0)*0.4 | P27: PENDIENTE | S27: =IFERROR(SCORECARDS!C27,"") | T27: =IF(NOT(ISNUMBER(S27)),"—",IF(S27<34,"🔴 Crítico",IF(S27<67,"🟡 Vulnerable","🟢 Preparado"))) | W27: 0 | X27: 0 | Y27: 0 | Z27: 0 | AA27: 0 | AB27: 0 | AC27: 0 | AD27: 0 | AE27: 0 | AF27: 0 | AG27: 0 | AH27: 0 | AI27: 0 | AJ27: 0 | AK27: 0 | AL27: 0 | AM27: 0 | AN27: 0 | AO27: =IFERROR(AVERAGE(AA27,AB27,AC27,AD27,AE27,AF27,AG27,AH27,AI27,AJ27,AK27,AL27,AM27,AN27),"N/A") | AP27: =IFERROR(AVERAGE(W27,X27,Y27,Z27)/2,"N/A")
A28: 20393882868 | B28: COOPERATIVA AGRARIA ASCAH | C28: UCAYALI | D28: CACAO | G28: NO | H28: nan | I28: nan | J28: ACTIVO | K28: nan | L28: 0 | M28: =IF(E28>0,ROUND(L28/E28*100,1),0) | N28: PENDIENTE | O28: =IF(H28="SI",1,0)*0.6+IF(I28="SI",1,0)*0.4 | P28: PENDIENTE | S28: =IFERROR(SCORECARDS!C28,"") | T28: =IF(NOT(ISNUMBER(S28)),"—",IF(S28<34,"🔴 Crítico",IF(S28<67,"🟡 Vulnerable","🟢 Preparado"))) | W28: 0 | X28: 0 | Y28: 0 | Z28: 0 | AA28: 0 | AB28: 0 | AC28: 0 | AD28: 0 | AE28: 0 | AF28: 0 | AG28: 0 | AH28: 0 | AI28: 0 | AJ28: 0 | AK28: 0 | AL28: 0 | AM28: 0 | AN28: 0 | AO28: =IFERROR(AVERAGE(AA28,AB28,AC28,AD28,AE28,AF28,AG28,AH28,AI28,AJ28,AK28,AL28,AM28,AN28),"N/A") | AP28: =IFERROR(AVERAGE(W28,X28,Y28,Z28)/2,"N/A")
A29: 20393972000 | B29: ASOCIACION DE MUJERES EMPRENDEDORAS FLOR DE BOQUERON | C29: UCAYALI | D29: CACAO | G29: NO | H29: nan | I29: nan | J29: ACTIVO | K29: nan | L29: 0 | M29: =IF(E29>0,ROUND(L29/E29*100,1),0) | N29: PENDIENTE | O29: =IF(H29="SI",1,0)*0.6+IF(I29="SI",1,0)*0.4 | P29: PENDIENTE | S29: =IFERROR(SCORECARDS!C29,"") | T29: =IF(NOT(ISNUMBER(S29)),"—",IF(S29<34,"🔴 Crítico",IF(S29<67,"🟡 Vulnerable","🟢 Preparado"))) | W29: 0 | X29: 0 | Y29: 0 | Z29: 0 | AA29: 0 | AB29: 0 | AC29: 0 | AD29: 0 | AE29: 0 | AF29: 0 | AG29: 0 | AH29: 0 | AI29: 0 | AJ29: 0 | AK29: 0 | AL29: 0 | AM29: 0 | AN29: 0 | AO29: =IFERROR(AVERAGE(AA29,AB29,AC29,AD29,AE29,AF29,AG29,AH29,AI29,AJ29,AK29,AL29,AM29,AN29),"N/A") | AP29: =IFERROR(AVERAGE(W29,X29,Y29,Z29)/2,"N/A")
A30: 20447888701 | B30: COOPERATIVA AGRARIA INDUSTRIAL SAN GABAN LTDA. | C30: PUNO | D30: CACAO | G30: NO | H30: nan | I30: nan | J30: ACTIVO | K30: nan | L30: 0 | M30: =IF(E30>0,ROUND(L30/E30*100,1),0) | N30: PENDIENTE | O30: =IF(H30="SI",1,0)*0.6+IF(I30="SI",1,0)*0.4 | P30: PENDIENTE | S30: =IFERROR(SCORECARDS!C30,"") | T30: =IF(NOT(ISNUMBER(S30)),"—",IF(S30<34,"🔴 Crítico",IF(S30<67,"🟡 Vulnerable","🟢 Preparado"))) | W30: 0 | X30: 0 | Y30: 0 | Z30: 0 | AA30: 0 | AB30: 0 | AC30: 0 | AD30: 0 | AE30: 0 | AF30: 0 | AG30: 0 | AH30: 0 | AI30: 0 | AJ30: 0 | AK30: 0 | AL30: 0 | AM30: 0 | AN30: 0 | AO30: =IFERROR(AVERAGE(AA30,AB30,AC30,AD30,AE30,AF30,AG30,AH30,AI30,AJ30,AK30,AL30,AM30,AN30),"N/A") | AP30: =IFERROR(AVERAGE(W30,X30,Y30,Z30)/2,"N/A")
A31: 20450189201 | B31: COOPERATIVA DE SERVICIOS MULTIPLES FRUTOS DE SELVA | C31: SAN MARTIN | D31: CAFÉ | E31: 0 | G31: NO | H31: nan | I31: nan | J31: ACTIVO | K31: nan | L31: 0 | M31: =IF(E31>0,ROUND(L31/E31*100,1),0) | N31: PENDIENTE | O31: =IF(H31="SI",1,0)*0.6+IF(I31="SI",1,0)*0.4 | P31: PENDIENTE | S31: =IFERROR(SCORECARDS!C31,"") | T31: =IF(NOT(ISNUMBER(S31)),"—",IF(S31<34,"🔴 Crítico",IF(S31<67,"🟡 Vulnerable","🟢 Preparado"))) | W31: 0 | X31: 0 | Y31: 0 | Z31: 0 | AA31: 0 | AB31: 0 | AC31: 0 | AD31: 0 | AE31: 0 | AF31: 0 | AG31: 0 | AH31: 0 | AI31: 0 | AJ31: 0 | AK31: 0 | AL31: 0 | AM31: 0 | AN31: 0 | AO31: =IFERROR(AVERAGE(AA31,AB31,AC31,AD31,AE31,AF31,AG31,AH31,AI31,AJ31,AK31,AL31,AM31,AN31),"N/A") | AP31: =IFERROR(AVERAGE(W31,X31,Y31,Z31)/2,"N/A")
A32: 20450207544 | B32: COOPERATIVA AGRARIA UCHIZA LTDA | C32: SAN MARTIN | D32: CACAO | E32: 0 | G32: NO | H32: nan | I32: nan | J32: ACTIVO | K32: nan | L32: 0 | M32: =IF(E32>0,ROUND(L32/E32*100,1),0) | N32: PENDIENTE | O32: =IF(H32="SI",1,0)*0.6+IF(I32="SI",1,0)*0.4 | P32: PENDIENTE | S32: =IFERROR(SCORECARDS!C32,"") | T32: =IF(NOT(ISNUMBER(S32)),"—",IF(S32<34,"🔴 Crítico",IF(S32<67,"🟡 Vulnerable","🟢 Preparado"))) | W32: 0 | X32: 0 | Y32: 0 | Z32: 0 | AA32: 0 | AB32: 0 | AC32: 0 | AD32: 0 | AE32: 0 | AF32: 0 | AG32: 0 | AH32: 0 | AI32: 0 | AJ32: 0 | AK32: 0 | AL32: 0 | AM32: 0 | AN32: 0 | AO32: =IFERROR(AVERAGE(AA32,AB32,AC32,AD32,AE32,AF32,AG32,AH32,AI32,AJ32,AK32,AL32,AM32,AN32),"N/A") | AP32: =IFERROR(AVERAGE(W32,X32,Y32,Z32)/2,"N/A")
A33: 20450242021 | B33: COOPERATIVA DE SERVICIOS MULTIPLES CAPEMA | C33: SAN MARTIN | D33: CAFÉ | E33: 0 | G33: NO | H33: nan | I33: nan | J33: ACTIVO | K33: nan | L33: 0 | M33: =IF(E33>0,ROUND(L33/E33*100,1),0) | N33: PENDIENTE | O33: =IF(H33="SI",1,0)*0.6+IF(I33="SI",1,0)*0.4 | P33: PENDIENTE | S33: =IFERROR(SCORECARDS!C33,"") | T33: =IF(NOT(ISNUMBER(S33)),"—",IF(S33<34,"🔴 Crítico",IF(S33<67,"🟡 Vulnerable","🟢 Preparado"))) | W33: 0 | X33: 0 | Y33: 0 | Z33: 0 | AA33: 0 | AB33: 0 | AC33: 0 | AD33: 0 | AE33: 0 | AF33: 0 | AG33: 0 | AH33: 0 | AI33: 0 | AJ33: 0 | AK33: 0 | AL33: 0 | AM33: 0 | AN33: 0 | AO33: =IFERROR(AVERAGE(AA33,AB33,AC33,AD33,AE33,AF33,AG33,AH33,AI33,AJ33,AK33,AL33,AM33,AN33),"N/A") | AP33: =IFERROR(AVERAGE(W33,X33,Y33,Z33)/2,"N/A")
A34: 20450319423 | B34: COOPERATIVA AGRARIA DE SERVICIOS MULTIPLES CAFE DONCEL | C34: SAN MARTIN | D34: CAFÉ | G34: NO | H34: nan | I34: nan | J34: ACTIVO | K34: nan | L34: 0 | M34: =IF(E34>0,ROUND(L34/E34*100,1),0) | N34: PENDIENTE | O34: =IF(H34="SI",1,0)*0.6+IF(I34="SI",1,0)*0.4 | P34: PENDIENTE | S34: =IFERROR(SCORECARDS!C34,"") | T34: =IF(NOT(ISNUMBER(S34)),"—",IF(S34<34,"🔴 Crítico",IF(S34<67,"🟡 Vulnerable","🟢 Preparado"))) | W34: 0 | X34: 0 | Y34: 0 | Z34: 0 | AA34: 0 | AB34: 0 | AC34: 0 | AD34: 0 | AE34: 0 | AF34: 0 | AG34: 0 | AH34: 0 | AI34: 0 | AJ34: 0 | AK34: 0 | AL34: 0 | AM34: 0 | AN34: 0 | AO34: =IFERROR(AVERAGE(AA34,AB34,AC34,AD34,AE34,AF34,AG34,AH34,AI34,AJ34,AK34,AL34,AM34,AN34),"N/A") | AP34: =IFERROR(AVERAGE(W34,X34,Y34,Z34)/2,"N/A")
A35: 20452774705 | B35: COOPERATIVA AGRARIA CACAO VRAE | C35: CUSCO | D35: CACAO | E35: 1931452.7 | F35: 7 | G35: SI | H35: nan | I35: nan | J35: ACTIVO | K35: nan | L35: 965726.35 | M35: =IF(E35>0,ROUND(L35/E35*100,1),0) | N35: PENDIENTE | O35: =IF(H35="SI",1,0)*0.6+IF(I35="SI",1,0)*0.4 | P35: PENDIENTE | S35: =IFERROR(SCORECARDS!C35,"") | T35: =IF(NOT(ISNUMBER(S35)),"—",IF(S35<34,"🔴 Crítico",IF(S35<67,"🟡 Vulnerable","🟢 Preparado"))) | U35: 1 | V35: Sin hallazgos OSCE / OEFA | W35: 1 | X35: 0 | Y35: 0 | Z35: 0 | AA35: 0 | AB35: 0 | AC35: 0 | AD35: 0 | AE35: 0 | AF35: 0 | AG35: 0 | AH35: 0 | AI35: 0 | AJ35: 0 | AK35: 0 | AL35: 0 | AM35: 0 | AN35: 0 | AO35: =IFERROR(AVERAGE(AA35,AB35,AC35,AD35,AE35,AF35,AG35,AH35,AI35,AJ35,AK35,AL35,AM35,AN35),"N/A") | AP35: =IFERROR(AVERAGE(W35,X35,Y35,Z35)/2,"N/A")
A36: 20479595276 | B36: COOPERATIVA AGRARIA CAFETALERA CASIL LTDA. | C36: CAJAMARCA | D36: CAFÉ | E36: 4538578.9 | F36: 24 | G36: SI | H36: SI | I36: SI | J36: ACTIVO | K36: nan | L36: 965167.45 | M36: =IF(E36>0,ROUND(L36/E36*100,1),0) | N36: PENDIENTE | O36: =IF(H36="SI",1,0)*0.6+IF(I36="SI",1,0)*0.4 | P36: PENDIENTE | Q36: 178 | R36: 437 | S36: =IFERROR(SCORECARDS!C36,"") | T36: =IF(NOT(ISNUMBER(S36)),"—",IF(S36<34,"🔴 Crítico",IF(S36<67,"🟡 Vulnerable","🟢 Preparado"))) | U36: 1 | V36: Sin hallazgos OSCE / OEFA | W36: 1 | X36: 0 | Y36: 0 | Z36: 0 | AA36: 0 | AB36: 0 | AC36: 0 | AD36: 0 | AE36: 0 | AF36: 0 | AG36: 0 | AH36: 0 | AI36: 0 | AJ36: 0 | AK36: 0 | AL36: 0 | AM36: 0 | AN36: 0 | AO36: =IFERROR(AVERAGE(AA36,AB36,AC36,AD36,AE36,AF36,AG36,AH36,AI36,AJ36,AK36,AL36,AM36,AN36),"N/A") | AP36: =IFERROR(AVERAGE(W36,X36,Y36,Z36)/2,"N/A")
A37: 20479622699 | B37: COOPERATIVA AGRARIA JUAN MARCO EL PALTO | C37: AMAZONAS | D37: CAFÉ | E37: 0 | G37: NO | H37: nan | I37: nan | J37: ACTIVO | K37: nan | L37: 0 | M37: =IF(E37>0,ROUND(L37/E37*100,1),0) | N37: PENDIENTE | O37: =IF(H37="SI",1,0)*0.6+IF(I37="SI",1,0)*0.4 | P37: PENDIENTE | S37: =IFERROR(SCORECARDS!C37,"") | T37: =IF(NOT(ISNUMBER(S37)),"—",IF(S37<34,"🔴 Crítico",IF(S37<67,"🟡 Vulnerable","🟢 Preparado"))) | W37: 0 | X37: 0 | Y37: 0 | Z37: 0 | AA37: 0 | AB37: 0 | AC37: 0 | AD37: 0 | AE37: 0 | AF37: 0 | AG37: 0 | AH37: 0 | AI37: 0 | AJ37: 0 | AK37: 0 | AL37: 0 | AM37: 0 | AN37: 0 | AO37: =IFERROR(AVERAGE(AA37,AB37,AC37,AD37,AE37,AF37,AG37,AH37,AI37,AJ37,AK37,AL37,AM37,AN37),"N/A") | AP37: =IFERROR(AVERAGE(W37,X37,Y37,Z37)/2,"N/A")
A38: 20479856258 | B38: ASOCIACION DE PRODUCTORES AGROPECUARIOS LUIS SOLIBARRIA | C38: AMAZONAS | G38: NO | H38: nan | I38: nan | J38: BAJA DE OFICIO | K38: nan | L38: 0 | M38: =IF(E38>0,ROUND(L38/E38*100,1),0) | N38: PENDIENTE | O38: =IF(H38="SI",1,0)*0.6+IF(I38="SI",1,0)*0.4 | P38: PENDIENTE | S38: =IFERROR(SCORECARDS!C38,"") | T38: =IF(NOT(ISNUMBER(S38)),"—",IF(S38<34,"🔴 Crítico",IF(S38<67,"🟡 Vulnerable","🟢 Preparado"))) | W38: 0 | X38: 0 | Y38: 0 | Z38: 0 | AA38: 0 | AB38: 0 | AC38: 0 | AD38: 0 | AE38: 0 | AF38: 0 | AG38: 0 | AH38: 0 | AI38: 0 | AJ38: 0 | AK38: 0 | AL38: 0 | AM38: 0 | AN38: 0 | AO38: =IFERROR(AVERAGE(AA38,AB38,AC38,AD38,AE38,AF38,AG38,AH38,AI38,AJ38,AK38,AL38,AM38,AN38),"N/A") | AP38: =IFERROR(AVERAGE(W38,X38,Y38,Z38)/2,"N/A")
A39: 20479917141 | B39: COOPERATIVA AGRARIA CENTRAL DE PRODUCTORES DE AMAZONAS | C39: AMAZONAS | D39: CACAO | E39: 1175215.3 | F39: 7 | G39: SI | H39: nan | I39: nan | J39: ACTIVO | K39: nan | L39: 587607.64 | M39: =IF(E39>0,ROUND(L39/E39*100,1),0) | N39: PENDIENTE | O39: =IF(H39="SI",1,0)*0.6+IF(I39="SI",1,0)*0.4 | P39: PENDIENTE | S39: =IFERROR(SCORECARDS!C39,"") | T39: =IF(NOT(ISNUMBER(S39)),"—",IF(S39<34,"🔴 Crítico",IF(S39<67,"🟡 Vulnerable","🟢 Preparado"))) | U39: 1 | V39: Sin hallazgos OSCE / OEFA | W39: 1 | X39: 0 | Y39: 0 | Z39: 0 | AA39: 0 | AB39: 0 | AC39: 0 | AD39: 0 | AE39: 0 | AF39: 0 | AG39: 0 | AH39: 0 | AI39: 0 | AJ39: 0 | AK39: 0 | AL39: 0 | AM39: 0 | AN39: 0 | AO39: =IFERROR(AVERAGE(AA39,AB39,AC39,AD39,AE39,AF39,AG39,AH39,AI39,AJ39,AK39,AL39,AM39,AN39),"N/A") | AP39: =IFERROR(AVERAGE(W39,X39,Y39,Z39)/2,"N/A")
A40: 20480458550 | B40: COOPERATIVA AGRARIA APROCAM | C40: AMAZONAS | D40: CACAO | E40: 1684430 | F40: 14 | G40: SI | H40: nan | I40: nan | J40: ACTIVO | K40: nan | L40: 842214.99 | M40: =IF(E40>0,ROUND(L40/E40*100,1),0) | N40: PENDIENTE | O40: =IF(H40="SI",1,0)*0.6+IF(I40="SI",1,0)*0.4 | P40: PENDIENTE | S40: =IFERROR(SCORECARDS!C40,"") | T40: =IF(NOT(ISNUMBER(S40)),"—",IF(S40<34,"🔴 Crítico",IF(S40<67,"🟡 Vulnerable","🟢 Preparado"))) | U40: 1 | V40: Sin hallazgos OSCE / OEFA | W40: 1 | X40: 0 | Y40: 0 | Z40: 0 | AA40: 0 | AB40: 0 | AC40: 0 | AD40: 0 | AE40: 0 | AF40: 0 | AG40: 0 | AH40: 0 | AI40: 0 | AJ40: 0 | AK40: 0 | AL40: 0 | AM40: 0 | AN40: 0 | AO40: =IFERROR(AVERAGE(AA40,AB40,AC40,AD40,AE40,AF40,AG40,AH40,AI40,AJ40,AK40,AL40,AM40,AN40),"N/A") | AP40: =IFERROR(AVERAGE(W40,X40,Y40,Z40)/2,"N/A")
A41: 20480762895 | B41: ASOCIACION DE PRODUCTORES AGROPECUARIOS LA FLOR DE CAFE | C41: AMAZONAS | D41: CAFÉ | E41: 0 | G41: NO | H41: nan | I41: nan | J41: BAJA DE OFICIO | K41: nan | L41: 0 | M41: =IF(E41>0,ROUND(L41/E41*100,1),0) | N41: PENDIENTE | O41: =IF(H41="SI",1,0)*0.6+IF(I41="SI",1,0)*0.4 | P41: PENDIENTE | S41: =IFERROR(SCORECARDS!C41,"") | T41: =IF(NOT(ISNUMBER(S41)),"—",IF(S41<34,"🔴 Crítico",IF(S41<67,"🟡 Vulnerable","🟢 Preparado"))) | W41: 0 | X41: 0 | Y41: 0 | Z41: 0 | AA41: 0 | AB41: 0 | AC41: 0 | AD41: 0 | AE41: 0 | AF41: 0 | AG41: 0 | AH41: 0 | AI41: 0 | AJ41: 0 | AK41: 0 | AL41: 0 | AM41: 0 | AN41: 0 | AO41: =IFERROR(AVERAGE(AA41,AB41,AC41,AD41,AE41,AF41,AG41,AH41,AI41,AJ41,AK41,AL41,AM41,AN41),"N/A") | AP41: =IFERROR(AVERAGE(W41,X41,Y41,Z41)/2,"N/A")
A42: 20484163902 | B42: COOPERATIVA AGRARIA APPROCAP LTDA | C42: PIURA | D42: CACAO | E42: 817000 | F42: 6 | G42: SI | H42: nan | I42: nan | J42: ACTIVO | K42: nan | L42: 408500 | M42: =IF(E42>0,ROUND(L42/E42*100,1),0) | N42: PENDIENTE | O42: =IF(H42="SI",1,0)*0.6+IF(I42="SI",1,0)*0.4 | P42: PENDIENTE | S42: =IFERROR(SCORECARDS!C42,"") | T42: =IF(NOT(ISNUMBER(S42)),"—",IF(S42<34,"🔴 Crítico",IF(S42<67,"🟡 Vulnerable","🟢 Preparado"))) | U42: 1 | V42: Sin hallazgos OSCE / OEFA | W42: 0 | X42: 0 | Y42: 0 | Z42: 0 | AA42: 0 | AB42: 0 | AC42: 0 | AD42: 0 | AE42: 0 | AF42: 0 | AG42: 0 | AH42: 0 | AI42: 0 | AJ42: 0 | AK42: 0 | AL42: 0 | AM42: 0 | AN42: 0 | AO42: =IFERROR(AVERAGE(AA42,AB42,AC42,AD42,AE42,AF42,AG42,AH42,AI42,AJ42,AK42,AL42,AM42,AN42),"N/A") | AP42: =IFERROR(AVERAGE(W42,X42,Y42,Z42)/2,"N/A")
A43: 20485945815 | B43: COOPERATIVA AGRARIA CAFETALERA ECOLOGICO ALTO PALOMAR | C43: JUNIN | D43: CAFÉ | E43: 0 | G43: NO | H43: nan | I43: nan | J43: SUSPENSION TEMPORAL | K43: nan | L43: 0 | M43: =IF(E43>0,ROUND(L43/E43*100,1),0) | N43: PENDIENTE | O43: =IF(H43="SI",1,0)*0.6+IF(I43="SI",1,0)*0.4 | P43: PENDIENTE | S43: =IFERROR(SCORECARDS!C43,"") | T43: =IF(NOT(ISNUMBER(S43)),"—",IF(S43<34,"🔴 Crítico",IF(S43<67,"🟡 Vulnerable","🟢 Preparado"))) | W43: 0 | X43: 0 | Y43: 0 | Z43: 0 | AA43: 0 | AB43: 0 | AC43: 0 | AD43: 0 | AE43: 0 | AF43: 0 | AG43: 0 | AH43: 0 | AI43: 0 | AJ43: 0 | AK43: 0 | AL43: 0 | AM43: 0 | AN43: 0 | AO43: =IFERROR(AVERAGE(AA43,AB43,AC43,AD43,AE43,AF43,AG43,AH43,AI43,AJ43,AK43,AL43,AM43,AN43),"N/A") | AP43: =IFERROR(AVERAGE(W43,X43,Y43,Z43)/2,"N/A")
A44: 20486094657 | B44: ASOCIACION DE PRODUCTORES DE CAFES ESPECIALES MOUNTAIN COFFE | C44: JUNIN | D44: CAFÉ | E44: 0 | G44: NO | H44: nan | I44: nan | J44: ACTIVO | K44: nan | L44: 0 | M44: =IF(E44>0,ROUND(L44/E44*100,1),0) | N44: PENDIENTE | O44: =IF(H44="SI",1,0)*0.6+IF(I44="SI",1,0)*0.4 | P44: PENDIENTE | S44: =IFERROR(SCORECARDS!C44,"") | T44: =IF(NOT(ISNUMBER(S44)),"—",IF(S44<34,"🔴 Crítico",IF(S44<67,"🟡 Vulnerable","🟢 Preparado"))) | W44: 0 | X44: 0 | Y44: 0 | Z44: 0 | AA44: 0 | AB44: 0 | AC44: 0 | AD44: 0 | AE44: 0 | AF44: 0 | AG44: 0 | AH44: 0 | AI44: 0 | AJ44: 0 | AK44: 0 | AL44: 0 | AM44: 0 | AN44: 0 | AO44: =IFERROR(AVERAGE(AA44,AB44,AC44,AD44,AE44,AF44,AG44,AH44,AI44,AJ44,AK44,AL44,AM44,AN44),"N/A") | AP44: =IFERROR(AVERAGE(W44,X44,Y44,Z44)/2,"N/A")
A45: 20486255090 | B45: COOPERATIVA AGRARIA SANGARENI | C45: JUNIN | D45: CAFÉ | E45: 13207692 | F45: 41 | G45: SI | H45: nan | I45: nan | J45: ACTIVO | K45: nan | L45: 6603846 | M45: =IF(E45>0,ROUND(L45/E45*100,1),0) | N45: PENDIENTE | O45: =IF(H45="SI",1,0)*0.6+IF(I45="SI",1,0)*0.4 | P45: PENDIENTE | S45: =IFERROR(SCORECARDS!C45,"") | T45: =IF(NOT(ISNUMBER(S45)),"—",IF(S45<34,"🔴 Crítico",IF(S45<67,"🟡 Vulnerable","🟢 Preparado"))) | U45: 1 | V45: Sin hallazgos OSCE / OEFA | W45: 1 | X45: 0 | Y45: 0 | Z45: 0 | AA45: 0 | AB45: 0 | AC45: 0 | AD45: 0 | AE45: 0 | AF45: 0 | AG45: 0 | AH45: 0 | AI45: 0 | AJ45: 0 | AK45: 0 | AL45: 0 | AM45: 0 | AN45: 0 | AO45: =IFERROR(AVERAGE(AA45,AB45,AC45,AD45,AE45,AF45,AG45,AH45,AI45,AJ45,AK45,AL45,AM45,AN45),"N/A") | AP45: =IFERROR(AVERAGE(W45,X45,Y45,Z45)/2,"N/A")
A46: 20486668335 | B46: COOPERATIVA AGROINDUSTRIAL SONOMORO LTDA | C46: JUNIN | E46: 0 | G46: NO | H46: nan | I46: nan | J46: SUSPENSION TEMPORAL | K46: nan | L46: 0 | M46: =IF(E46>0,ROUND(L46/E46*100,1),0) | N46: PENDIENTE | O46: =IF(H46="SI",1,0)*0.6+IF(I46="SI",1,0)*0.4 | P46: PENDIENTE | S46: =IFERROR(SCORECARDS!C46,"") | T46: =IF(NOT(ISNUMBER(S46)),"—",IF(S46<34,"🔴 Crítico",IF(S46<67,"🟡 Vulnerable","🟢 Preparado"))) | W46: 0 | X46: 0 | Y46: 0 | Z46: 0 | AA46: 0 | AB46: 0 | AC46: 0 | AD46: 0 | AE46: 0 | AF46: 0 | AG46: 0 | AH46: 0 | AI46: 0 | AJ46: 0 | AK46: 0 | AL46: 0 | AM46: 0 | AN46: 0 | AO46: =IFERROR(AVERAGE(AA46,AB46,AC46,AD46,AE46,AF46,AG46,AH46,AI46,AJ46,AK46,AL46,AM46,AN46),"N/A") | AP46: =IFERROR(AVERAGE(W46,X46,Y46,Z46)/2,"N/A")
A47: 20486876019 | B47: COOPERATIVA AGROECOLOGICO INDUSTRIAL MAZAMARI LTDA | C47: JUNIN | D47: CACAO | G47: NO | H47: nan | I47: nan | J47: ACTIVO | K47: nan | L47: 0 | M47: =IF(E47>0,ROUND(L47/E47*100,1),0) | N47: PENDIENTE | O47: =IF(H47="SI",1,0)*0.6+IF(I47="SI",1,0)*0.4 | P47: PENDIENTE | S47: =IFERROR(SCORECARDS!C47,"") | T47: =IF(NOT(ISNUMBER(S47)),"—",IF(S47<34,"🔴 Crítico",IF(S47<67,"🟡 Vulnerable","🟢 Preparado"))) | W47: 0 | X47: 0 | Y47: 0 | Z47: 0 | AA47: 0 | AB47: 0 | AC47: 0 | AD47: 0 | AE47: 0 | AF47: 0 | AG47: 0 | AH47: 0 | AI47: 0 | AJ47: 0 | AK47: 0 | AL47: 0 | AM47: 0 | AN47: 0 | AO47: =IFERROR(AVERAGE(AA47,AB47,AC47,AD47,AE47,AF47,AG47,AH47,AI47,AJ47,AK47,AL47,AM47,AN47),"N/A") | AP47: =IFERROR(AVERAGE(W47,X47,Y47,Z47)/2,"N/A")
A48: 20486973219 | B48: COOPERATIVA AGRARIA SONOMORO DEL VRAEM LTDA | C48: JUNIN | D48: CACAO | E48: 30342293 | F48: 108 | G48: SI | H48: nan | I48: nan | J48: ACTIVO | K48: nan | L48: 15171147 | M48: =IF(E48>0,ROUND(L48/E48*100,1),0) | N48: PENDIENTE | O48: =IF(H48="SI",1,0)*0.6+IF(I48="SI",1,0)*0.4 | P48: PENDIENTE | S48: =IFERROR(SCORECARDS!C48,"") | T48: =IF(NOT(ISNUMBER(S48)),"—",IF(S48<34,"🔴 Crítico",IF(S48<67,"🟡 Vulnerable","🟢 Preparado"))) | U48: 1 | V48: Sin hallazgos OSCE / OEFA | W48: 1 | X48: 0 | Y48: 0 | Z48: 0 | AA48: 0 | AB48: 0 | AC48: 0 | AD48: 0 | AE48: 0 | AF48: 0 | AG48: 0 | AH48: 0 | AI48: 0 | AJ48: 0 | AK48: 0 | AL48: 0 | AM48: 0 | AN48: 0 | AO48: =IFERROR(AVERAGE(AA48,AB48,AC48,AD48,AE48,AF48,AG48,AH48,AI48,AJ48,AK48,AL48,AM48,AN48),"N/A") | AP48: =IFERROR(AVERAGE(W48,X48,Y48,Z48)/2,"N/A")
A49: 20487242994 | B49: COOPERATIVA AGRARIA ECOLOGICA CACAOTERA VALLE RIO ENE - COOP | C49: JUNIN | D49: CACAO | E49: 2290978.7 | F49: 10 | G49: SI | H49: nan | I49: nan | J49: ACTIVO | K49: nan | L49: 1145489.4 | M49: =IF(E49>0,ROUND(L49/E49*100,1),0) | N49: PENDIENTE | O49: =IF(H49="SI",1,0)*0.6+IF(I49="SI",1,0)*0.4 | P49: PENDIENTE | S49: =IFERROR(SCORECARDS!C49,"") | T49: =IF(NOT(ISNUMBER(S49)),"—",IF(S49<34,"🔴 Crítico",IF(S49<67,"🟡 Vulnerable","🟢 Preparado"))) | U49: 1 | V49: Sin hallazgos OSCE / OEFA | W49: 1 | X49: 0 | Y49: 0 | Z49: 0 | AA49: 0 | AB49: 0 | AC49: 0 | AD49: 0 | AE49: 0 | AF49: 0 | AG49: 0 | AH49: 0 | AI49: 0 | AJ49: 0 | AK49: 0 | AL49: 0 | AM49: 0 | AN49: 0 | AO49: =IFERROR(AVERAGE(AA49,AB49,AC49,AD49,AE49,AF49,AG49,AH49,AI49,AJ49,AK49,AL49,AM49,AN49),"N/A") | AP49: =IFERROR(AVERAGE(W49,X49,Y49,Z49)/2,"N/A")
A50: 20487351343 | B50: ASOCIACION DE PRODUCTORES AGROPECUARIOS TUPAC AMARU DE CHIÑA | C50: LAMBAYEQUE | D50: CAFÉ | G50: NO | H50: nan | I50: nan | J50: BAJA DE OFICIO | K50: nan | L50: 0 | M50: =IF(E50>0,ROUND(L50/E50*100,1),0) | N50: PENDIENTE | O50: =IF(H50="SI",1,0)*0.6+IF(I50="SI",1,0)*0.4 | P50: PENDIENTE | S50: =IFERROR(SCORECARDS!C50,"") | T50: =IF(NOT(ISNUMBER(S50)),"—",IF(S50<34,"🔴 Crítico",IF(S50<67,"🟡 Vulnerable","🟢 Preparado"))) | W50: 0 | X50: 0 | Y50: 0 | Z50: 0 | AA50: 0 | AB50: 0 | AC50: 0 | AD50: 0 | AE50: 0 | AF50: 0 | AG50: 0 | AH50: 0 | AI50: 0 | AJ50: 0 | AK50: 0 | AL50: 0 | AM50: 0 | AN50: 0 | AO50: =IFERROR(AVERAGE(AA50,AB50,AC50,AD50,AE50,AF50,AG50,AH50,AI50,AJ50,AK50,AL50,AM50,AN50),"N/A") | AP50: =IFERROR(AVERAGE(W50,X50,Y50,Z50)/2,"N/A")
A51: 20487661539 | B51: ASOCIACION DE PRODUCTORES CACAOTEROS DEL DISTRITO DE HUARANG | C51: CAJAMARCA | D51: CACAO | G51: NO | H51: nan | I51: nan | J51: ACTIVO | K51: nan | L51: 0 | M51: =IF(E51>0,ROUND(L51/E51*100,1),0) | N51: PENDIENTE | O51: =IF(H51="SI",1,0)*0.6+IF(I51="SI",1,0)*0.4 | P51: PENDIENTE | S51: =IFERROR(SCORECARDS!C51,"") | T51: =IF(NOT(ISNUMBER(S51)),"—",IF(S51<34,"🔴 Crítico",IF(S51<67,"🟡 Vulnerable","🟢 Preparado"))) | W51: 0 | X51: 0 | Y51: 0 | Z51: 0 | AA51: 0 | AB51: 0 | AC51: 0 | AD51: 0 | AE51: 0 | AF51: 0 | AG51: 0 | AH51: 0 | AI51: 0 | AJ51: 0 | AK51: 0 | AL51: 0 | AM51: 0 | AN51: 0 | AO51: =IFERROR(AVERAGE(AA51,AB51,AC51,AD51,AE51,AF51,AG51,AH51,AI51,AJ51,AK51,AL51,AM51,AN51),"N/A") | AP51: =IFERROR(AVERAGE(W51,X51,Y51,Z51)/2,"N/A")
A52: 20490726196 | B52: ASOCIACIÓN DE PRODUCTORES AGROPECUARIOS VALLESITO - CHAHUARE | C52: CUSCO | D52: CACAO | G52: NO | H52: nan | I52: nan | J52: ACTIVO | K52: nan | L52: 0 | M52: =IF(E52>0,ROUND(L52/E52*100,1),0) | N52: PENDIENTE | O52: =IF(H52="SI",1,0)*0.6+IF(I52="SI",1,0)*0.4 | P52: PENDIENTE | S52: =IFERROR(SCORECARDS!C52,"") | T52: =IF(NOT(ISNUMBER(S52)),"—",IF(S52<34,"🔴 Crítico",IF(S52<67,"🟡 Vulnerable","🟢 Preparado"))) | W52: 0 | X52: 0 | Y52: 0 | Z52: 0 | AA52: 0 | AB52: 0 | AC52: 0 | AD52: 0 | AE52: 0 | AF52: 0 | AG52: 0 | AH52: 0 | AI52: 0 | AJ52: 0 | AK52: 0 | AL52: 0 | AM52: 0 | AN52: 0 | AO52: =IFERROR(AVERAGE(AA52,AB52,AC52,AD52,AE52,AF52,AG52,AH52,AI52,AJ52,AK52,AL52,AM52,AN52),"N/A") | AP52: =IFERROR(AVERAGE(W52,X52,Y52,Z52)/2,"N/A")
A53: 20493934822 | B53: COOPERATIVA AGRARIA NUEVO AMANECER LTDA. | C53: SAN MARTIN | D53: CACAO | E53: 0 | G53: NO | H53: nan | I53: nan | J53: ACTIVO | K53: nan | L53: 0 | M53: =IF(E53>0,ROUND(L53/E53*100,1),0) | N53: PENDIENTE | O53: =IF(H53="SI",1,0)*0.6+IF(I53="SI",1,0)*0.4 | P53: PENDIENTE | S53: =IFERROR(SCORECARDS!C53,"") | T53: =IF(NOT(ISNUMBER(S53)),"—",IF(S53<34,"🔴 Crítico",IF(S53<67,"🟡 Vulnerable","🟢 Preparado"))) | W53: 0 | X53: 0 | Y53: 0 | Z53: 0 | AA53: 0 | AB53: 0 | AC53: 0 | AD53: 0 | AE53: 0 | AF53: 0 | AG53: 0 | AH53: 0 | AI53: 0 | AJ53: 0 | AK53: 0 | AL53: 0 | AM53: 0 | AN53: 0 | AO53: =IFERROR(AVERAGE(AA53,AB53,AC53,AD53,AE53,AF53,AG53,AH53,AI53,AJ53,AK53,AL53,AM53,AN53),"N/A") | AP53: =IFERROR(AVERAGE(W53,X53,Y53,Z53)/2,"N/A")
A54: 20493959574 | B54: COOPERATIVA AGRARIA DE SERVICIOS MUJERES TECNOLOGAS CACAOTER | C54: SAN MARTIN | D54: CACAO | G54: NO | H54: nan | I54: nan | J54: SUSPENSION TEMPORAL | K54: nan | L54: 0 | M54: =IF(E54>0,ROUND(L54/E54*100,1),0) | N54: PENDIENTE | O54: =IF(H54="SI",1,0)*0.6+IF(I54="SI",1,0)*0.4 | P54: PENDIENTE | S54: =IFERROR(SCORECARDS!C54,"") | T54: =IF(NOT(ISNUMBER(S54)),"—",IF(S54<34,"🔴 Crítico",IF(S54<67,"🟡 Vulnerable","🟢 Preparado"))) | W54: 0 | X54: 0 | Y54: 0 | Z54: 0 | AA54: 0 | AB54: 0 | AC54: 0 | AD54: 0 | AE54: 0 | AF54: 0 | AG54: 0 | AH54: 0 | AI54: 0 | AJ54: 0 | AK54: 0 | AL54: 0 | AM54: 0 | AN54: 0 | AO54: =IFERROR(AVERAGE(AA54,AB54,AC54,AD54,AE54,AF54,AG54,AH54,AI54,AJ54,AK54,AL54,AM54,AN54),"N/A") | AP54: =IFERROR(AVERAGE(W54,X54,Y54,Z54)/2,"N/A")
A55: 20494126819 | B55: ASOCIACION DE PRODUCTORES AGROPECUARIOS RIO MAYO SHANAO | C55: SAN MARTIN | D55: CACAO | G55: NO | H55: nan | I55: nan | J55: ACTIVO | K55: nan | L55: 0 | M55: =IF(E55>0,ROUND(L55/E55*100,1),0) | N55: PENDIENTE | O55: =IF(H55="SI",1,0)*0.6+IF(I55="SI",1,0)*0.4 | P55: PENDIENTE | S55: =IFERROR(SCORECARDS!C55,"") | T55: =IF(NOT(ISNUMBER(S55)),"—",IF(S55<34,"🔴 Crítico",IF(S55<67,"🟡 Vulnerable","🟢 Preparado"))) | W55: 0 | X55: 0 | Y55: 0 | Z55: 0 | AA55: 0 | AB55: 0 | AC55: 0 | AD55: 0 | AE55: 0 | AF55: 0 | AG55: 0 | AH55: 0 | AI55: 0 | AJ55: 0 | AK55: 0 | AL55: 0 | AM55: 0 | AN55: 0 | AO55: =IFERROR(AVERAGE(AA55,AB55,AC55,AD55,AE55,AF55,AG55,AH55,AI55,AJ55,AK55,AL55,AM55,AN55),"N/A") | AP55: =IFERROR(AVERAGE(W55,X55,Y55,Z55)/2,"N/A")
A56: 20494145791 | B56: ASOCIACION ECOLOGICA Y DE PRODUCTORES AGROPECUARIOS SAN JOSE | C56: LORETO | D56: CACAO | G56: NO | H56: nan | I56: nan | J56: ACTIVO | K56: nan | L56: 0 | M56: =IF(E56>0,ROUND(L56/E56*100,1),0) | N56: PENDIENTE | O56: =IF(H56="SI",1,0)*0.6+IF(I56="SI",1,0)*0.4 | P56: PENDIENTE | S56: =IFERROR(SCORECARDS!C56,"") | T56: =IF(NOT(ISNUMBER(S56)),"—",IF(S56<34,"🔴 Crítico",IF(S56<67,"🟡 Vulnerable","🟢 Preparado"))) | W56: 0 | X56: 0 | Y56: 0 | Z56: 0 | AA56: 0 | AB56: 0 | AC56: 0 | AD56: 0 | AE56: 0 | AF56: 0 | AG56: 0 | AH56: 0 | AI56: 0 | AJ56: 0 | AK56: 0 | AL56: 0 | AM56: 0 | AN56: 0 | AO56: =IFERROR(AVERAGE(AA56,AB56,AC56,AD56,AE56,AF56,AG56,AH56,AI56,AJ56,AK56,AL56,AM56,AN56),"N/A") | AP56: =IFERROR(AVERAGE(W56,X56,Y56,Z56)/2,"N/A")
A57: 20494699690 | B57: ASOCIACION DE PRODUCTORES DE CACAO ECOLOGICO DE KIMBIRI - AP | C57: CUSCO | D57: CACAO | G57: NO | H57: nan | I57: nan | J57: ACTIVO | K57: nan | L57: 0 | M57: =IF(E57>0,ROUND(L57/E57*100,1),0) | N57: PENDIENTE | O57: =IF(H57="SI",1,0)*0.6+IF(I57="SI",1,0)*0.4 | P57: PENDIENTE | S57: =IFERROR(SCORECARDS!C57,"") | T57: =IF(NOT(ISNUMBER(S57)),"—",IF(S57<34,"🔴 Crítico",IF(S57<67,"🟡 Vulnerable","🟢 Preparado"))) | W57: 0 | X57: 0 | Y57: 0 | Z57: 0 | AA57: 0 | AB57: 0 | AC57: 0 | AD57: 0 | AE57: 0 | AF57: 0 | AG57: 0 | AH57: 0 | AI57: 0 | AJ57: 0 | AK57: 0 | AL57: 0 | AM57: 0 | AN57: 0 | AO57: =IFERROR(AVERAGE(AA57,AB57,AC57,AD57,AE57,AF57,AG57,AH57,AI57,AJ57,AK57,AL57,AM57,AN57),"N/A") | AP57: =IFERROR(AVERAGE(W57,X57,Y57,Z57)/2,"N/A")
A58: 20525969551 | B58: COOPERATIVA AGRARIA DE PRODUCTORES DE BANANO, CACAO ORGANICO | C58: PIURA | D58: CACAO | E58: 105840 | F58: 7 | G58: SI | H58: nan | I58: nan | J58: ACTIVO | K58: nan | L58: 52920 | M58: =IF(E58>0,ROUND(L58/E58*100,1),0) | N58: PENDIENTE | O58: =IF(H58="SI",1,0)*0.6+IF(I58="SI",1,0)*0.4 | P58: PENDIENTE | S58: =IFERROR(SCORECARDS!C58,"") | T58: =IF(NOT(ISNUMBER(S58)),"—",IF(S58<34,"🔴 Crítico",IF(S58<67,"🟡 Vulnerable","🟢 Preparado"))) | U58: 1 | V58: Sin hallazgos OSCE / OEFA | W58: 0 | X58: 0 | Y58: 0 | Z58: 0 | AA58: 0 | AB58: 0 | AC58: 0 | AD58: 0 | AE58: 0 | AF58: 0 | AG58: 0 | AH58: 0 | AI58: 0 | AJ58: 0 | AK58: 0 | AL58: 0 | AM58: 0 | AN58: 0 | AO58: =IFERROR(AVERAGE(AA58,AB58,AC58,AD58,AE58,AF58,AG58,AH58,AI58,AJ58,AK58,AL58,AM58,AN58),"N/A") | AP58: =IFERROR(AVERAGE(W58,X58,Y58,Z58)/2,"N/A")
A59: 20526514689 | B59: ASOCIACION DE PRODUCTORES AGROPECUARIOS ARTESANALES E INDUST | C59: PIURA | D59: CACAO | G59: NO | H59: nan | I59: nan | J59: BAJA DE OFICIO | K59: nan | L59: 0 | M59: =IF(E59>0,ROUND(L59/E59*100,1),0) | N59: PENDIENTE | O59: =IF(H59="SI",1,0)*0.6+IF(I59="SI",1,0)*0.4 | P59: PENDIENTE | S59: =IFERROR(SCORECARDS!C59,"") | T59: =IF(NOT(ISNUMBER(S59)),"—",IF(S59<34,"🔴 Crítico",IF(S59<67,"🟡 Vulnerable","🟢 Preparado"))) | W59: 0 | X59: 0 | Y59: 0 | Z59: 0 | AA59: 0 | AB59: 0 | AC59: 0 | AD59: 0 | AE59: 0 | AF59: 0 | AG59: 0 | AH59: 0 | AI59: 0 | AJ59: 0 | AK59: 0 | AL59: 0 | AM59: 0 | AN59: 0 | AO59: =IFERROR(AVERAGE(AA59,AB59,AC59,AD59,AE59,AF59,AG59,AH59,AI59,AJ59,AK59,AL59,AM59,AN59),"N/A") | AP59: =IFERROR(AVERAGE(W59,X59,Y59,Z59)/2,"N/A")
A60: 20527565376 | B60: COOPERATIVA AGRARIA CAFETALERA VALLE DE INCAHUASI | C60: APURIMAC | D60: CAFÉ | E60: 10746931 | F60: 59 | G60: SI | H60: nan | I60: nan | J60: ACTIVO | K60: nan | L60: 5373465.5 | M60: =IF(E60>0,ROUND(L60/E60*100,1),0) | N60: PENDIENTE | O60: =IF(H60="SI",1,0)*0.6+IF(I60="SI",1,0)*0.4 | P60: PENDIENTE | S60: =IFERROR(SCORECARDS!C60,"") | T60: =IF(NOT(ISNUMBER(S60)),"—",IF(S60<34,"🔴 Crítico",IF(S60<67,"🟡 Vulnerable","🟢 Preparado"))) | U60: 1 | V60: Sin hallazgos OSCE / OEFA | W60: 1 | X60: 0 | Y60: 0 | Z60: 0 | AA60: 0 | AB60: 0 | AC60: 0 | AD60: 0 | AE60: 0 | AF60: 0 | AG60: 0 | AH60: 0 | AI60: 0 | AJ60: 0 | AK60: 0 | AL60: 0 | AM60: 0 | AN60: 0 | AO60: =IFERROR(AVERAGE(AA60,AB60,AC60,AD60,AE60,AF60,AG60,AH60,AI60,AJ60,AK60,AL60,AM60,AN60),"N/A") | AP60: =IFERROR(AVERAGE(W60,X60,Y60,Z60)/2,"N/A")
A61: 20528996214 | B61: COOPERATIVA AGRARIA CAFETALERA MILAGROS - MONZON | C61: HUANUCO | D61: CAFÉ | G61: NO | H61: nan | I61: nan | J61: ACTIVO | K61: nan | L61: 0 | M61: =IF(E61>0,ROUND(L61/E61*100,1),0) | N61: PENDIENTE | O61: =IF(H61="SI",1,0)*0.6+IF(I61="SI",1,0)*0.4 | P61: PENDIENTE | S61: =IFERROR(SCORECARDS!C61,"") | T61: =IF(NOT(ISNUMBER(S61)),"—",IF(S61<34,"🔴 Crítico",IF(S61<67,"🟡 Vulnerable","🟢 Preparado"))) | W61: 0 | X61: 0 | Y61: 0 | Z61: 0 | AA61: 0 | AB61: 0 | AC61: 0 | AD61: 0 | AE61: 0 | AF61: 0 | AG61: 0 | AH61: 0 | AI61: 0 | AJ61: 0 | AK61: 0 | AL61: 0 | AM61: 0 | AN61: 0 | AO61: =IFERROR(AVERAGE(AA61,AB61,AC61,AD61,AE61,AF61,AG61,AH61,AI61,AJ61,AK61,AL61,AM61,AN61),"N/A") | AP61: =IFERROR(AVERAGE(W61,X61,Y61,Z61)/2,"N/A")
A62: 20529801433 | B62: OPA MARAY-ULLMA SAN LORENZO | C62: PIURA | D62: CAFÉ | G62: NO | H62: nan | I62: nan | J62: BAJA DE OFICIO | K62: nan | L62: 0 | M62: =IF(E62>0,ROUND(L62/E62*100,1),0) | N62: PENDIENTE | O62: =IF(H62="SI",1,0)*0.6+IF(I62="SI",1,0)*0.4 | P62: PENDIENTE | S62: =IFERROR(SCORECARDS!C62,"") | T62: =IF(NOT(ISNUMBER(S62)),"—",IF(S62<34,"🔴 Crítico",IF(S62<67,"🟡 Vulnerable","🟢 Preparado"))) | W62: 0 | X62: 0 | Y62: 0 | Z62: 0 | AA62: 0 | AB62: 0 | AC62: 0 | AD62: 0 | AE62: 0 | AF62: 0 | AG62: 0 | AH62: 0 | AI62: 0 | AJ62: 0 | AK62: 0 | AL62: 0 | AM62: 0 | AN62: 0 | AO62: =IFERROR(AVERAGE(AA62,AB62,AC62,AD62,AE62,AF62,AG62,AH62,AI62,AJ62,AK62,AL62,AM62,AN62),"N/A") | AP62: =IFERROR(AVERAGE(W62,X62,Y62,Z62)/2,"N/A")
A63: 20529822350 | B63: OPA PAPAYO - LA LAGUNA | C63: PIURA | D63: CAFÉ | G63: NO | H63: nan | I63: nan | J63: BAJA DE OFICIO | K63: nan | L63: 0 | M63: =IF(E63>0,ROUND(L63/E63*100,1),0) | N63: PENDIENTE | O63: =IF(H63="SI",1,0)*0.6+IF(I63="SI",1,0)*0.4 | P63: PENDIENTE | S63: =IFERROR(SCORECARDS!C63,"") | T63: =IF(NOT(ISNUMBER(S63)),"—",IF(S63<34,"🔴 Crítico",IF(S63<67,"🟡 Vulnerable","🟢 Preparado"))) | W63: 0 | X63: 0 | Y63: 0 | Z63: 0 | AA63: 0 | AB63: 0 | AC63: 0 | AD63: 0 | AE63: 0 | AF63: 0 | AG63: 0 | AH63: 0 | AI63: 0 | AJ63: 0 | AK63: 0 | AL63: 0 | AM63: 0 | AN63: 0 | AO63: =IFERROR(AVERAGE(AA63,AB63,AC63,AD63,AE63,AF63,AG63,AH63,AI63,AJ63,AK63,AL63,AM63,AN63),"N/A") | AP63: =IFERROR(AVERAGE(W63,X63,Y63,Z63)/2,"N/A")
A64: 20531405723 | B64: COOPERATIVA DE SERVICIOS MULTIPLES ADISA NARANJOS | C64: SAN MARTIN | D64: CAFÉ | E64: 0 | G64: NO | H64: nan | I64: nan | J64: ACTIVO | K64: nan | L64: 0 | M64: =IF(E64>0,ROUND(L64/E64*100,1),0) | N64: PENDIENTE | O64: =IF(H64="SI",1,0)*0.6+IF(I64="SI",1,0)*0.4 | P64: PENDIENTE | S64: =IFERROR(SCORECARDS!C64,"") | T64: =IF(NOT(ISNUMBER(S64)),"—",IF(S64<34,"🔴 Crítico",IF(S64<67,"🟡 Vulnerable","🟢 Preparado"))) | W64: 0 | X64: 0 | Y64: 0 | Z64: 0 | AA64: 0 | AB64: 0 | AC64: 0 | AD64: 0 | AE64: 0 | AF64: 0 | AG64: 0 | AH64: 0 | AI64: 0 | AJ64: 0 | AK64: 0 | AL64: 0 | AM64: 0 | AN64: 0 | AO64: =IFERROR(AVERAGE(AA64,AB64,AC64,AD64,AE64,AF64,AG64,AH64,AI64,AJ64,AK64,AL64,AM64,AN64),"N/A") | AP64: =IFERROR(AVERAGE(W64,X64,Y64,Z64)/2,"N/A")
A65: 20531441797 | B65: COOPERATIVA AGRARIA ALLIMA CACAO LTDA. | C65: SAN MARTIN | D65: CACAO | E65: 1984.05 | F65: 1 | G65: SI | H65: nan | I65: nan | J65: ACTIVO | K65: nan | L65: 0 | M65: =IF(E65>0,ROUND(L65/E65*100,1),0) | N65: PENDIENTE | O65: =IF(H65="SI",1,0)*0.6+IF(I65="SI",1,0)*0.4 | P65: PENDIENTE | S65: =IFERROR(SCORECARDS!C65,"") | T65: =IF(NOT(ISNUMBER(S65)),"—",IF(S65<34,"🔴 Crítico",IF(S65<67,"🟡 Vulnerable","🟢 Preparado"))) | W65: 0 | X65: 0 | Y65: 0 | Z65: 0 | AA65: 0 | AB65: 0 | AC65: 0 | AD65: 0 | AE65: 0 | AF65: 0 | AG65: 0 | AH65: 0 | AI65: 0 | AJ65: 0 | AK65: 0 | AL65: 0 | AM65: 0 | AN65: 0 | AO65: =IFERROR(AVERAGE(AA65,AB65,AC65,AD65,AE65,AF65,AG65,AH65,AI65,AJ65,AK65,AL65,AM65,AN65),"N/A") | AP65: =IFERROR(AVERAGE(W65,X65,Y65,Z65)/2,"N/A")
A66: 20534524774 | B66: COOPERATIVA AGRARIA TROPICAL ECOLOGICA DE KIMBIRI | C66: CUSCO | D66: CAFÉ | G66: NO | H66: nan | I66: nan | J66: ACTIVO | K66: nan | L66: 0 | M66: =IF(E66>0,ROUND(L66/E66*100,1),0) | N66: PENDIENTE | O66: =IF(H66="SI",1,0)*0.6+IF(I66="SI",1,0)*0.4 | P66: PENDIENTE | S66: =IFERROR(SCORECARDS!C66,"") | T66: =IF(NOT(ISNUMBER(S66)),"—",IF(S66<34,"🔴 Crítico",IF(S66<67,"🟡 Vulnerable","🟢 Preparado"))) | W66: 0 | X66: 0 | Y66: 0 | Z66: 0 | AA66: 0 | AB66: 0 | AC66: 0 | AD66: 0 | AE66: 0 | AF66: 0 | AG66: 0 | AH66: 0 | AI66: 0 | AJ66: 0 | AK66: 0 | AL66: 0 | AM66: 0 | AN66: 0 | AO66: =IFERROR(AVERAGE(AA66,AB66,AC66,AD66,AE66,AF66,AG66,AH66,AI66,AJ66,AK66,AL66,AM66,AN66),"N/A") | AP66: =IFERROR(AVERAGE(W66,X66,Y66,Z66)/2,"N/A")
A67: 20539205600 | B67: ASOCIACION DE PRODUCTORES Y EXPORTADORES DE CAFE RODRIGUEZ D | C67: AMAZONAS | D67: CAFÉ | G67: NO | H67: nan | I67: nan | J67: ACTIVO | K67: nan | L67: 0 | M67: =IF(E67>0,ROUND(L67/E67*100,1),0) | N67: PENDIENTE | O67: =IF(H67="SI",1,0)*0.6+IF(I67="SI",1,0)*0.4 | P67: PENDIENTE | S67: =IFERROR(SCORECARDS!C67,"") | T67: =IF(NOT(ISNUMBER(S67)),"—",IF(S67<34,"🔴 Crítico",IF(S67<67,"🟡 Vulnerable","🟢 Preparado"))) | W67: 0 | X67: 0 | Y67: 0 | Z67: 0 | AA67: 0 | AB67: 0 | AC67: 0 | AD67: 0 | AE67: 0 | AF67: 0 | AG67: 0 | AH67: 0 | AI67: 0 | AJ67: 0 | AK67: 0 | AL67: 0 | AM67: 0 | AN67: 0 | AO67: =IFERROR(AVERAGE(AA67,AB67,AC67,AD67,AE67,AF67,AG67,AH67,AI67,AJ67,AK67,AL67,AM67,AN67),"N/A") | AP67: =IFERROR(AVERAGE(W67,X67,Y67,Z67)/2,"N/A")
A68: 20539241665 | B68: ASOCIACION DE PRODUCTORES DE CAFES ORGANICOS Y CAFES ESPECIA | C68: AMAZONAS | D68: CAFÉ | G68: NO | H68: nan | I68: nan | J68: ACTIVO | K68: nan | L68: 0 | M68: =IF(E68>0,ROUND(L68/E68*100,1),0) | N68: PENDIENTE | O68: =IF(H68="SI",1,0)*0.6+IF(I68="SI",1,0)*0.4 | P68: PENDIENTE | S68: =IFERROR(SCORECARDS!C68,"") | T68: =IF(NOT(ISNUMBER(S68)),"—",IF(S68<34,"🔴 Crítico",IF(S68<67,"🟡 Vulnerable","🟢 Preparado"))) | W68: 0 | X68: 0 | Y68: 0 | Z68: 0 | AA68: 0 | AB68: 0 | AC68: 0 | AD68: 0 | AE68: 0 | AF68: 0 | AG68: 0 | AH68: 0 | AI68: 0 | AJ68: 0 | AK68: 0 | AL68: 0 | AM68: 0 | AN68: 0 | AO68: =IFERROR(AVERAGE(AA68,AB68,AC68,AD68,AE68,AF68,AG68,AH68,AI68,AJ68,AK68,AL68,AM68,AN68),"N/A") | AP68: =IFERROR(AVERAGE(W68,X68,Y68,Z68)/2,"N/A")
A69: 20539280644 | B69: ASOCIACION DE PEQUEÑOS AGRICULTORES PARA LA PRODUCCION ECOLO | C69: LAMBAYEQUE | D69: CAFÉ | G69: NO | H69: nan | I69: nan | J69: BAJA DE OFICIO | K69: nan | L69: 0 | M69: =IF(E69>0,ROUND(L69/E69*100,1),0) | N69: PENDIENTE | O69: =IF(H69="SI",1,0)*0.6+IF(I69="SI",1,0)*0.4 | P69: PENDIENTE | S69: =IFERROR(SCORECARDS!C69,"") | T69: =IF(NOT(ISNUMBER(S69)),"—",IF(S69<34,"🔴 Crítico",IF(S69<67,"🟡 Vulnerable","🟢 Preparado"))) | W69: 0 | X69: 0 | Y69: 0 | Z69: 0 | AA69: 0 | AB69: 0 | AC69: 0 | AD69: 0 | AE69: 0 | AF69: 0 | AG69: 0 | AH69: 0 | AI69: 0 | AJ69: 0 | AK69: 0 | AL69: 0 | AM69: 0 | AN69: 0 | AO69: =IFERROR(AVERAGE(AA69,AB69,AC69,AD69,AE69,AF69,AG69,AH69,AI69,AJ69,AK69,AL69,AM69,AN69),"N/A") | AP69: =IFERROR(AVERAGE(W69,X69,Y69,Z69)/2,"N/A")
A70: 20542209951 | B70: COOPERATIVA AGRARIA VALLE GRANDE | C70: SAN MARTIN | D70: CAFÉ | E70: 13246409 | F70: 46 | G70: SI | H70: Si | I70: Si | J70: ACTIVO | K70: 1 | L70: 7878141.7 | M70: =IF(E70>0,ROUND(L70/E70*100,1),0) | N70: PENDIENTE | O70: =IF(H70="SI",1,0)*0.6+IF(I70="SI",1,0)*0.4 | P70: PENDIENTE | Q70: 622 | R70: 4031 | S70: =IFERROR(SCORECARDS!C70,"") | T70: =IF(NOT(ISNUMBER(S70)),"—",IF(S70<34,"🔴 Crítico",IF(S70<67,"🟡 Vulnerable","🟢 Preparado"))) | U70: 1 | V70: Sin hallazgos OSCE / OEFA | W70: 1 | X70: 0 | Y70: 0 | Z70: 0 | AA70: 0 | AB70: 0 | AC70: 0 | AD70: 0 | AE70: 0 | AF70: 0 | AG70: 0 | AH70: 0 | AI70: 0 | AJ70: 0 | AK70: 0 | AL70: 0 | AM70: 0 | AN70: 0 | AO70: =IFERROR(AVERAGE(AA70,AB70,AC70,AD70,AE70,AF70,AG70,AH70,AI70,AJ70,AK70,AL70,AM70,AN70),"N/A") | AP70: =IFERROR(AVERAGE(W70,X70,Y70,Z70)/2,"N/A")
A71: 20542251990 | B71: ASOCIACION DE MUJERES EMPRENDEDORAS DE NUEVO PROGRESO | C71: SAN MARTIN | D71: CACAO | G71: NO | H71: nan | I71: nan | J71: ACTIVO | K71: nan | L71: 0 | M71: =IF(E71>0,ROUND(L71/E71*100,1),0) | N71: PENDIENTE | O71: =IF(H71="SI",1,0)*0.6+IF(I71="SI",1,0)*0.4 | P71: PENDIENTE | S71: =IFERROR(SCORECARDS!C71,"") | T71: =IF(NOT(ISNUMBER(S71)),"—",IF(S71<34,"🔴 Crítico",IF(S71<67,"🟡 Vulnerable","🟢 Preparado"))) | W71: 0 | X71: 0 | Y71: 0 | Z71: 0 | AA71: 0 | AB71: 0 | AC71: 0 | AD71: 0 | AE71: 0 | AF71: 0 | AG71: 0 | AH71: 0 | AI71: 0 | AJ71: 0 | AK71: 0 | AL71: 0 | AM71: 0 | AN71: 0 | AO71: =IFERROR(AVERAGE(AA71,AB71,AC71,AD71,AE71,AF71,AG71,AH71,AI71,AJ71,AK71,AL71,AM71,AN71),"N/A") | AP71: =IFERROR(AVERAGE(W71,X71,Y71,Z71)/2,"N/A")
A72: 20542257416 | B72: EMPRESA INDUSTRIAL ORO VERDE SOCIEDAD ANONIMA CERRADA | C72: SAN MARTIN | D72: CACAO | E72: 2826075 | F72: 12 | G72: SI | H72: nan | I72: nan | J72: ACTIVO | K72: nan | L72: 1413037.5 | M72: =IF(E72>0,ROUND(L72/E72*100,1),0) | N72: PENDIENTE | O72: =IF(H72="SI",1,0)*0.6+IF(I72="SI",1,0)*0.4 | P72: PENDIENTE | S72: =IFERROR(SCORECARDS!C72,"") | T72: =IF(NOT(ISNUMBER(S72)),"—",IF(S72<34,"🔴 Crítico",IF(S72<67,"🟡 Vulnerable","🟢 Preparado"))) | U72: 1 | V72: Sin hallazgos OSCE / OEFA | W72: 1 | X72: 0 | Y72: 0 | Z72: 0 | AA72: 0 | AB72: 0 | AC72: 0 | AD72: 0 | AE72: 0 | AF72: 0 | AG72: 0 | AH72: 0 | AI72: 0 | AJ72: 0 | AK72: 0 | AL72: 0 | AM72: 0 | AN72: 0 | AO72: =IFERROR(AVERAGE(AA72,AB72,AC72,AD72,AE72,AF72,AG72,AH72,AI72,AJ72,AK72,AL72,AM72,AN72),"N/A") | AP72: =IFERROR(AVERAGE(W72,X72,Y72,Z72)/2,"N/A")
A73: 20542264544 | B73: COOPERATIVA AGRARIA VALLE DEL BIAVO LTDA | C73: SAN MARTIN | D73: CAFÉ | E73: 1187600.5 | F73: 6 | G73: SI | H73: PE- | I73: FLO | J73: ACTIVO | K73: 1 | L73: 1187600.5 | M73: =IF(E73>0,ROUND(L73/E73*100,1),0) | N73: PENDIENTE | O73: =IF(H73="SI",1,0)*0.6+IF(I73="SI",1,0)*0.4 | P73: PENDIENTE | Q73: 416 | R73: 1248 | S73: =IFERROR(SCORECARDS!C73,"") | T73: =IF(NOT(ISNUMBER(S73)),"—",IF(S73<34,"🔴 Crítico",IF(S73<67,"🟡 Vulnerable","🟢 Preparado"))) | U73: 1 | V73: Sin hallazgos OSCE / OEFA | W73: 1 | X73: 0 | Y73: 0 | Z73: 0 | AA73: 0 | AB73: 0 | AC73: 0 | AD73: 0 | AE73: 0 | AF73: 0 | AG73: 0 | AH73: 0 | AI73: 0 | AJ73: 0 | AK73: 0 | AL73: 0 | AM73: 0 | AN73: 0 | AO73: =IFERROR(AVERAGE(AA73,AB73,AC73,AD73,AE73,AF73,AG73,AH73,AI73,AJ73,AK73,AL73,AM73,AN73),"N/A") | AP73: =IFERROR(AVERAGE(W73,X73,Y73,Z73)/2,"N/A")
A74: 20542289024 | B74: CUENCAS DEL HUALLAGA ASOCIACION DE PRODUCTORES AGROPECUARIOS | C74: SAN MARTIN | D74: CACAO | E74: 24285432 | F74: 111 | G74: SI | H74: nan | I74: nan | J74: ACTIVO | K74: nan | L74: 12142716 | M74: =IF(E74>0,ROUND(L74/E74*100,1),0) | N74: PENDIENTE | O74: =IF(H74="SI",1,0)*0.6+IF(I74="SI",1,0)*0.4 | P74: PENDIENTE | S74: =IFERROR(SCORECARDS!C74,"") | T74: =IF(NOT(ISNUMBER(S74)),"—",IF(S74<34,"🔴 Crítico",IF(S74<67,"🟡 Vulnerable","🟢 Preparado"))) | U74: 1 | V74: Sin hallazgos OSCE / OEFA | W74: 1 | X74: 0 | Y74: 0 | Z74: 0 | AA74: 0 | AB74: 0 | AC74: 0 | AD74: 0 | AE74: 0 | AF74: 0 | AG74: 0 | AH74: 0 | AI74: 0 | AJ74: 0 | AK74: 0 | AL74: 0 | AM74: 0 | AN74: 0 | AO74: =IFERROR(AVERAGE(AA74,AB74,AC74,AD74,AE74,AF74,AG74,AH74,AI74,AJ74,AK74,AL74,AM74,AN74),"N/A") | AP74: =IFERROR(AVERAGE(W74,X74,Y74,Z74)/2,"N/A")
A75: 20542299330 | B75: ASOCIACION DE PRODUCTORES AGROPECUARIOS DE SHUCUSHYACU FLOR | C75: LORETO | D75: CACAO | G75: NO | H75: nan | I75: nan | J75: ACTIVO | K75: nan | L75: 0 | M75: =IF(E75>0,ROUND(L75/E75*100,1),0) | N75: PENDIENTE | O75: =IF(H75="SI",1,0)*0.6+IF(I75="SI",1,0)*0.4 | P75: PENDIENTE | S75: =IFERROR(SCORECARDS!C75,"") | T75: =IF(NOT(ISNUMBER(S75)),"—",IF(S75<34,"🔴 Crítico",IF(S75<67,"🟡 Vulnerable","🟢 Preparado"))) | W75: 0 | X75: 0 | Y75: 0 | Z75: 0 | AA75: 0 | AB75: 0 | AC75: 0 | AD75: 0 | AE75: 0 | AF75: 0 | AG75: 0 | AH75: 0 | AI75: 0 | AJ75: 0 | AK75: 0 | AL75: 0 | AM75: 0 | AN75: 0 | AO75: =IFERROR(AVERAGE(AA75,AB75,AC75,AD75,AE75,AF75,AG75,AH75,AI75,AJ75,AK75,AL75,AM75,AN75),"N/A") | AP75: =IFERROR(AVERAGE(W75,X75,Y75,Z75)/2,"N/A")
A76: 20542311569 | B76: COOPERATIVA AGRARIA ACHUAR SHAKAIM LTDA | C76: LORETO | D76: CACAO | G76: NO | H76: nan | I76: nan | J76: ACTIVO | K76: nan | L76: 0 | M76: =IF(E76>0,ROUND(L76/E76*100,1),0) | N76: PENDIENTE | O76: =IF(H76="SI",1,0)*0.6+IF(I76="SI",1,0)*0.4 | P76: PENDIENTE | S76: =IFERROR(SCORECARDS!C76,"") | T76: =IF(NOT(ISNUMBER(S76)),"—",IF(S76<34,"🔴 Crítico",IF(S76<67,"🟡 Vulnerable","🟢 Preparado"))) | W76: 0 | X76: 0 | Y76: 0 | Z76: 0 | AA76: 0 | AB76: 0 | AC76: 0 | AD76: 0 | AE76: 0 | AF76: 0 | AG76: 0 | AH76: 0 | AI76: 0 | AJ76: 0 | AK76: 0 | AL76: 0 | AM76: 0 | AN76: 0 | AO76: =IFERROR(AVERAGE(AA76,AB76,AC76,AD76,AE76,AF76,AG76,AH76,AI76,AJ76,AK76,AL76,AM76,AN76),"N/A") | AP76: =IFERROR(AVERAGE(W76,X76,Y76,Z76)/2,"N/A")
A77: 20542380455 | B77: COOPERATIVA AGRARIA ECOFOREST | C77: CAJAMARCA | D77: CAFÉ | E77: 16891006 | F77: 81 | G77: SI | H77: nan | I77: nan | J77: ACTIVO | K77: nan | L77: 8445503.2 | M77: =IF(E77>0,ROUND(L77/E77*100,1),0) | N77: PENDIENTE | O77: =IF(H77="SI",1,0)*0.6+IF(I77="SI",1,0)*0.4 | P77: PENDIENTE | S77: =IFERROR(SCORECARDS!C77,"") | T77: =IF(NOT(ISNUMBER(S77)),"—",IF(S77<34,"🔴 Crítico",IF(S77<67,"🟡 Vulnerable","🟢 Preparado"))) | U77: 1 | V77: Sin hallazgos OSCE / OEFA | W77: 1 | X77: 0 | Y77: 0 | Z77: 0 | AA77: 0 | AB77: 0 | AC77: 0 | AD77: 0 | AE77: 0 | AF77: 0 | AG77: 0 | AH77: 0 | AI77: 0 | AJ77: 0 | AK77: 0 | AL77: 0 | AM77: 0 | AN77: 0 | AO77: =IFERROR(AVERAGE(AA77,AB77,AC77,AD77,AE77,AF77,AG77,AH77,AI77,AJ77,AK77,AL77,AM77,AN77),"N/A") | AP77: =IFERROR(AVERAGE(W77,X77,Y77,Z77)/2,"N/A")
A78: 20542482886 | B78: COOPERATIVA AGROINDUSTRIAL APCCA | C78: HUANUCO | D78: CACAO | G78: NO | H78: nan | I78: nan | J78: SUSPENSION TEMPORAL | K78: nan | L78: 0 | M78: =IF(E78>0,ROUND(L78/E78*100,1),0) | N78: PENDIENTE | O78: =IF(H78="SI",1,0)*0.6+IF(I78="SI",1,0)*0.4 | P78: PENDIENTE | S78: =IFERROR(SCORECARDS!C78,"") | T78: =IF(NOT(ISNUMBER(S78)),"—",IF(S78<34,"🔴 Crítico",IF(S78<67,"🟡 Vulnerable","🟢 Preparado"))) | W78: 0 | X78: 0 | Y78: 0 | Z78: 0 | AA78: 0 | AB78: 0 | AC78: 0 | AD78: 0 | AE78: 0 | AF78: 0 | AG78: 0 | AH78: 0 | AI78: 0 | AJ78: 0 | AK78: 0 | AL78: 0 | AM78: 0 | AN78: 0 | AO78: =IFERROR(AVERAGE(AA78,AB78,AC78,AD78,AE78,AF78,AG78,AH78,AI78,AJ78,AK78,AL78,AM78,AN78),"N/A") | AP78: =IFERROR(AVERAGE(W78,X78,Y78,Z78)/2,"N/A")
A79: 20542825163 | B79: COOPERATIVA AGRARIA CACAO FINO AGROBOSQUE | C79: MADRE DE DIOS | D79: CACAO | E79: 0 | G79: NO | H79: nan | I79: nan | J79: ACTIVO | K79: nan | L79: 0 | M79: =IF(E79>0,ROUND(L79/E79*100,1),0) | N79: PENDIENTE | O79: =IF(H79="SI",1,0)*0.6+IF(I79="SI",1,0)*0.4 | P79: PENDIENTE | S79: =IFERROR(SCORECARDS!C79,"") | T79: =IF(NOT(ISNUMBER(S79)),"—",IF(S79<34,"🔴 Crítico",IF(S79<67,"🟡 Vulnerable","🟢 Preparado"))) | W79: 0 | X79: 0 | Y79: 0 | Z79: 0 | AA79: 0 | AB79: 0 | AC79: 0 | AD79: 0 | AE79: 0 | AF79: 0 | AG79: 0 | AH79: 0 | AI79: 0 | AJ79: 0 | AK79: 0 | AL79: 0 | AM79: 0 | AN79: 0 | AO79: =IFERROR(AVERAGE(AA79,AB79,AC79,AD79,AE79,AF79,AG79,AH79,AI79,AJ79,AK79,AL79,AM79,AN79),"N/A") | AP79: =IFERROR(AVERAGE(W79,X79,Y79,Z79)/2,"N/A")
A80: 20561140091 | B80: COOPERATIVA AGRARIA ECOLOGICA CAFETALERA DE LONYA GRANDE | C80: AMAZONAS | D80: CAFÉ | E80: 0 | G80: NO | H80: SI( | I80: NO | J80: SUSPENSION TEMPORAL | K80: 0.5 | L80: 0 | M80: =IF(E80>0,ROUND(L80/E80*100,1),0) | N80: PENDIENTE | O80: =IF(H80="SI",1,0)*0.6+IF(I80="SI",1,0)*0.4 | P80: PENDIENTE | Q80: 351 | R80: 1045.6 | S80: =IFERROR(SCORECARDS!C80,"") | T80: =IF(NOT(ISNUMBER(S80)),"—",IF(S80<34,"🔴 Crítico",IF(S80<67,"🟡 Vulnerable","🟢 Preparado"))) | W80: 1 | X80: 0 | Y80: 0 | Z80: 0 | AA80: 0 | AB80: 0 | AC80: 0 | AD80: 0 | AE80: 0 | AF80: 0 | AG80: 0 | AH80: 0 | AI80: 0 | AJ80: 0 | AK80: 0 | AL80: 0 | AM80: 0 | AN80: 0 | AO80: =IFERROR(AVERAGE(AA80,AB80,AC80,AD80,AE80,AF80,AG80,AH80,AI80,AJ80,AK80,AL80,AM80,AN80),"N/A") | AP80: =IFERROR(AVERAGE(W80,X80,Y80,Z80)/2,"N/A")
A81: 20564032485 | B81: ASOCIACION DE PRODUCTORES ECOLOGICOS DE CACAO MEDIO URUBAMBA | C81: CUSCO | D81: CACAO | E81: 0 | G81: NO | H81: nan | I81: nan | J81: ACTIVO | K81: nan | L81: 0 | M81: =IF(E81>0,ROUND(L81/E81*100,1),0) | N81: PENDIENTE | O81: =IF(H81="SI",1,0)*0.6+IF(I81="SI",1,0)*0.4 | P81: PENDIENTE | S81: =IFERROR(SCORECARDS!C81,"") | T81: =IF(NOT(ISNUMBER(S81)),"—",IF(S81<34,"🔴 Crítico",IF(S81<67,"🟡 Vulnerable","🟢 Preparado"))) | W81: 0 | X81: 0 | Y81: 0 | Z81: 0 | AA81: 0 | AB81: 0 | AC81: 0 | AD81: 0 | AE81: 0 | AF81: 0 | AG81: 0 | AH81: 0 | AI81: 0 | AJ81: 0 | AK81: 0 | AL81: 0 | AM81: 0 | AN81: 0 | AO81: =IFERROR(AVERAGE(AA81,AB81,AC81,AD81,AE81,AF81,AG81,AH81,AI81,AJ81,AK81,AL81,AM81,AN81),"N/A") | AP81: =IFERROR(AVERAGE(W81,X81,Y81,Z81)/2,"N/A")
A82: 20568071281 | B82: COOPERATIVA AGRARIA CAFETALERA CEPRO YANESHA | C82: PASCO | D82: CAFÉ | E82: 1435723.7 | F82: 10 | G82: SI | H82: nan | I82: nan | J82: ACTIVO | K82: nan | L82: 717861.85 | M82: =IF(E82>0,ROUND(L82/E82*100,1),0) | N82: PENDIENTE | O82: =IF(H82="SI",1,0)*0.6+IF(I82="SI",1,0)*0.4 | P82: PENDIENTE | S82: =IFERROR(SCORECARDS!C82,"") | T82: =IF(NOT(ISNUMBER(S82)),"—",IF(S82<34,"🔴 Crítico",IF(S82<67,"🟡 Vulnerable","🟢 Preparado"))) | U82: 1 | V82: Sin hallazgos OSCE / OEFA | W82: 1 | X82: 0 | Y82: 0 | Z82: 0 | AA82: 0 | AB82: 0 | AC82: 0 | AD82: 0 | AE82: 0 | AF82: 0 | AG82: 0 | AH82: 0 | AI82: 0 | AJ82: 0 | AK82: 0 | AL82: 0 | AM82: 0 | AN82: 0 | AO82: =IFERROR(AVERAGE(AA82,AB82,AC82,AD82,AE82,AF82,AG82,AH82,AI82,AJ82,AK82,AL82,AM82,AN82),"N/A") | AP82: =IFERROR(AVERAGE(W82,X82,Y82,Z82)/2,"N/A")
A83: 20568080948 | B83: CONSEJO REGULADOR DE LA DENOMINACION DE ORIGEN CAFE VILLA RI | C83: PASCO | D83: CAFÉ | G83: NO | H83: nan | I83: nan | J83: ACTIVO | K83: nan | L83: 0 | M83: =IF(E83>0,ROUND(L83/E83*100,1),0) | N83: PENDIENTE | O83: =IF(H83="SI",1,0)*0.6+IF(I83="SI",1,0)*0.4 | P83: PENDIENTE | S83: =IFERROR(SCORECARDS!C83,"") | T83: =IF(NOT(ISNUMBER(S83)),"—",IF(S83<34,"🔴 Crítico",IF(S83<67,"🟡 Vulnerable","🟢 Preparado"))) | W83: 0 | X83: 0 | Y83: 0 | Z83: 0 | AA83: 0 | AB83: 0 | AC83: 0 | AD83: 0 | AE83: 0 | AF83: 0 | AG83: 0 | AH83: 0 | AI83: 0 | AJ83: 0 | AK83: 0 | AL83: 0 | AM83: 0 | AN83: 0 | AO83: =IFERROR(AVERAGE(AA83,AB83,AC83,AD83,AE83,AF83,AG83,AH83,AI83,AJ83,AK83,AL83,AM83,AN83),"N/A") | AP83: =IFERROR(AVERAGE(W83,X83,Y83,Z83)/2,"N/A")
A84: 20568190450 | B84: COOPERATIVA AGRARIA KEMITO ENE LTDA. - KEMITO ENE | C84: JUNIN | D84: CACAO | E84: 113466.98 | F84: 10 | G84: SI | H84: nan | I84: nan | J84: ACTIVO | K84: nan | L84: 0 | M84: =IF(E84>0,ROUND(L84/E84*100,1),0) | N84: PENDIENTE | O84: =IF(H84="SI",1,0)*0.6+IF(I84="SI",1,0)*0.4 | P84: PENDIENTE | S84: =IFERROR(SCORECARDS!C84,"") | T84: =IF(NOT(ISNUMBER(S84)),"—",IF(S84<34,"🔴 Crítico",IF(S84<67,"🟡 Vulnerable","🟢 Preparado"))) | W84: 0 | X84: 0 | Y84: 0 | Z84: 0 | AA84: 0 | AB84: 0 | AC84: 0 | AD84: 0 | AE84: 0 | AF84: 0 | AG84: 0 | AH84: 0 | AI84: 0 | AJ84: 0 | AK84: 0 | AL84: 0 | AM84: 0 | AN84: 0 | AO84: =IFERROR(AVERAGE(AA84,AB84,AC84,AD84,AE84,AF84,AG84,AH84,AI84,AJ84,AK84,AL84,AM84,AN84),"N/A") | AP84: =IFERROR(AVERAGE(W84,X84,Y84,Z84)/2,"N/A")
A85: 20568194951 | B85: ASOCIACION DE PRODUCTORES AGROSOSTENIBLES VILLA ECOLOGICA PE | C85: JUNIN | D85: CAFÉ | E85: 5355025.2 | F85: 27 | G85: SI | H85: nan | I85: nan | J85: ACTIVO | K85: nan | L85: 2677512.6 | M85: =IF(E85>0,ROUND(L85/E85*100,1),0) | N85: PENDIENTE | O85: =IF(H85="SI",1,0)*0.6+IF(I85="SI",1,0)*0.4 | P85: PENDIENTE | S85: =IFERROR(SCORECARDS!C85,"") | T85: =IF(NOT(ISNUMBER(S85)),"—",IF(S85<34,"🔴 Crítico",IF(S85<67,"🟡 Vulnerable","🟢 Preparado"))) | U85: 1 | V85: Sin hallazgos OSCE / OEFA | W85: 1 | X85: 0 | Y85: 0 | Z85: 0 | AA85: 0 | AB85: 0 | AC85: 0 | AD85: 0 | AE85: 0 | AF85: 0 | AG85: 0 | AH85: 0 | AI85: 0 | AJ85: 0 | AK85: 0 | AL85: 0 | AM85: 0 | AN85: 0 | AO85: =IFERROR(AVERAGE(AA85,AB85,AC85,AD85,AE85,AF85,AG85,AH85,AI85,AJ85,AK85,AL85,AM85,AN85),"N/A") | AP85: =IFERROR(AVERAGE(W85,X85,Y85,Z85)/2,"N/A")
A86: 20568428375 | B86: COOPERATIVA AGRARIA ASHANINKA DEL VALLE PICHIS | C86: PASCO | D86: CACAO | G86: NO | H86: nan | I86: nan | J86: ACTIVO | K86: nan | L86: 0 | M86: =IF(E86>0,ROUND(L86/E86*100,1),0) | N86: PENDIENTE | O86: =IF(H86="SI",1,0)*0.6+IF(I86="SI",1,0)*0.4 | P86: PENDIENTE | S86: =IFERROR(SCORECARDS!C86,"") | T86: =IF(NOT(ISNUMBER(S86)),"—",IF(S86<34,"🔴 Crítico",IF(S86<67,"🟡 Vulnerable","🟢 Preparado"))) | W86: 0 | X86: 0 | Y86: 0 | Z86: 0 | AA86: 0 | AB86: 0 | AC86: 0 | AD86: 0 | AE86: 0 | AF86: 0 | AG86: 0 | AH86: 0 | AI86: 0 | AJ86: 0 | AK86: 0 | AL86: 0 | AM86: 0 | AN86: 0 | AO86: =IFERROR(AVERAGE(AA86,AB86,AC86,AD86,AE86,AF86,AG86,AH86,AI86,AJ86,AK86,AL86,AM86,AN86),"N/A") | AP86: =IFERROR(AVERAGE(W86,X86,Y86,Z86)/2,"N/A")
A87: 20568549083 | B87: COOPERATIVA AGRARIA INDUSTRIAL APASC SANCORE-PALCAZU LTDA | C87: PASCO | D87: CACAO | G87: NO | H87: nan | I87: nan | J87: ACTIVO | K87: nan | L87: 0 | M87: =IF(E87>0,ROUND(L87/E87*100,1),0) | N87: PENDIENTE | O87: =IF(H87="SI",1,0)*0.6+IF(I87="SI",1,0)*0.4 | P87: PENDIENTE | S87: =IFERROR(SCORECARDS!C87,"") | T87: =IF(NOT(ISNUMBER(S87)),"—",IF(S87<34,"🔴 Crítico",IF(S87<67,"🟡 Vulnerable","🟢 Preparado"))) | W87: 0 | X87: 0 | Y87: 0 | Z87: 0 | AA87: 0 | AB87: 0 | AC87: 0 | AD87: 0 | AE87: 0 | AF87: 0 | AG87: 0 | AH87: 0 | AI87: 0 | AJ87: 0 | AK87: 0 | AL87: 0 | AM87: 0 | AN87: 0 | AO87: =IFERROR(AVERAGE(AA87,AB87,AC87,AD87,AE87,AF87,AG87,AH87,AI87,AJ87,AK87,AL87,AM87,AN87),"N/A") | AP87: =IFERROR(AVERAGE(W87,X87,Y87,Z87)/2,"N/A")
A88: 20568560133 | B88: COOPERATIVA AGRARIA ECOLOGICO ALTO PALCAZU LAGUNA RAYA | C88: PASCO | D88: CACAO | G88: NO | H88: nan | I88: nan | J88: ACTIVO | K88: nan | L88: 0 | M88: =IF(E88>0,ROUND(L88/E88*100,1),0) | N88: PENDIENTE | O88: =IF(H88="SI",1,0)*0.6+IF(I88="SI",1,0)*0.4 | P88: PENDIENTE | S88: =IFERROR(SCORECARDS!C88,"") | T88: =IF(NOT(ISNUMBER(S88)),"—",IF(S88<34,"🔴 Crítico",IF(S88<67,"🟡 Vulnerable","🟢 Preparado"))) | W88: 0 | X88: 0 | Y88: 0 | Z88: 0 | AA88: 0 | AB88: 0 | AC88: 0 | AD88: 0 | AE88: 0 | AF88: 0 | AG88: 0 | AH88: 0 | AI88: 0 | AJ88: 0 | AK88: 0 | AL88: 0 | AM88: 0 | AN88: 0 | AO88: =IFERROR(AVERAGE(AA88,AB88,AC88,AD88,AE88,AF88,AG88,AH88,AI88,AJ88,AK88,AL88,AM88,AN88),"N/A") | AP88: =IFERROR(AVERAGE(W88,X88,Y88,Z88)/2,"N/A")
A89: 20568567731 | B89: COOPERATIVA AGRARIA VILLA RICA GOLDEN COFFEE LTDA. | C89: PASCO | D89: CAFÉ | E89: 0 | G89: NO | H89: nan | I89: nan | J89: ACTIVO | K89: nan | L89: 0 | M89: =IF(E89>0,ROUND(L89/E89*100,1),0) | N89: PENDIENTE | O89: =IF(H89="SI",1,0)*0.6+IF(I89="SI",1,0)*0.4 | P89: PENDIENTE | S89: =IFERROR(SCORECARDS!C89,"") | T89: =IF(NOT(ISNUMBER(S89)),"—",IF(S89<34,"🔴 Crítico",IF(S89<67,"🟡 Vulnerable","🟢 Preparado"))) | W89: 0 | X89: 0 | Y89: 0 | Z89: 0 | AA89: 0 | AB89: 0 | AC89: 0 | AD89: 0 | AE89: 0 | AF89: 0 | AG89: 0 | AH89: 0 | AI89: 0 | AJ89: 0 | AK89: 0 | AL89: 0 | AM89: 0 | AN89: 0 | AO89: =IFERROR(AVERAGE(AA89,AB89,AC89,AD89,AE89,AF89,AG89,AH89,AI89,AJ89,AK89,AL89,AM89,AN89),"N/A") | AP89: =IFERROR(AVERAGE(W89,X89,Y89,Z89)/2,"N/A")
A90: 20568609833 | B90: ASOCIACION DE MUJERES PRODUCTORAS ARTESANAS CACAO JENTARI - | C90: JUNIN | D90: CACAO | G90: NO | H90: nan | I90: nan | J90: BAJA DE OFICIO | K90: nan | L90: 0 | M90: =IF(E90>0,ROUND(L90/E90*100,1),0) | N90: PENDIENTE | O90: =IF(H90="SI",1,0)*0.6+IF(I90="SI",1,0)*0.4 | P90: PENDIENTE | S90: =IFERROR(SCORECARDS!C90,"") | T90: =IF(NOT(ISNUMBER(S90)),"—",IF(S90<34,"🔴 Crítico",IF(S90<67,"🟡 Vulnerable","🟢 Preparado"))) | W90: 0 | X90: 0 | Y90: 0 | Z90: 0 | AA90: 0 | AB90: 0 | AC90: 0 | AD90: 0 | AE90: 0 | AF90: 0 | AG90: 0 | AH90: 0 | AI90: 0 | AJ90: 0 | AK90: 0 | AL90: 0 | AM90: 0 | AN90: 0 | AO90: =IFERROR(AVERAGE(AA90,AB90,AC90,AD90,AE90,AF90,AG90,AH90,AI90,AJ90,AK90,AL90,AM90,AN90),"N/A") | AP90: =IFERROR(AVERAGE(W90,X90,Y90,Z90)/2,"N/A")
A91: 20568962282 | B91: ASOCIACIÓN DE PRODUCTORES CENTRO COFFEE | C91: JUNIN | D91: CAFÉ | E91: 0 | G91: NO | H91: nan | I91: nan | J91: SUSPENSION TEMPORAL | K91: nan | L91: 0 | M91: =IF(E91>0,ROUND(L91/E91*100,1),0) | N91: PENDIENTE | O91: =IF(H91="SI",1,0)*0.6+IF(I91="SI",1,0)*0.4 | P91: PENDIENTE | S91: =IFERROR(SCORECARDS!C91,"") | T91: =IF(NOT(ISNUMBER(S91)),"—",IF(S91<34,"🔴 Crítico",IF(S91<67,"🟡 Vulnerable","🟢 Preparado"))) | W91: 0 | X91: 0 | Y91: 0 | Z91: 0 | AA91: 0 | AB91: 0 | AC91: 0 | AD91: 0 | AE91: 0 | AF91: 0 | AG91: 0 | AH91: 0 | AI91: 0 | AJ91: 0 | AK91: 0 | AL91: 0 | AM91: 0 | AN91: 0 | AO91: =IFERROR(AVERAGE(AA91,AB91,AC91,AD91,AE91,AF91,AG91,AH91,AI91,AJ91,AK91,AL91,AM91,AN91),"N/A") | AP91: =IFERROR(AVERAGE(W91,X91,Y91,Z91)/2,"N/A")
A92: 20570706927 | B92: COOPERATIVA AGRARIA RUTAS DEL INCA | C92: CAJAMARCA | D92: CAFÉ | E92: 9585341.8 | F92: 58 | G92: SI | H92: nan | I92: nan | J92: ACTIVO | K92: nan | L92: 4792670.9 | M92: =IF(E92>0,ROUND(L92/E92*100,1),0) | N92: PENDIENTE | O92: =IF(H92="SI",1,0)*0.6+IF(I92="SI",1,0)*0.4 | P92: PENDIENTE | S92: =IFERROR(SCORECARDS!C92,"") | T92: =IF(NOT(ISNUMBER(S92)),"—",IF(S92<34,"🔴 Crítico",IF(S92<67,"🟡 Vulnerable","🟢 Preparado"))) | U92: 1 | V92: Sin hallazgos OSCE / OEFA | W92: 1 | X92: 0 | Y92: 0 | Z92: 0 | AA92: 0 | AB92: 0 | AC92: 0 | AD92: 0 | AE92: 0 | AF92: 0 | AG92: 0 | AH92: 0 | AI92: 0 | AJ92: 0 | AK92: 0 | AL92: 0 | AM92: 0 | AN92: 0 | AO92: =IFERROR(AVERAGE(AA92,AB92,AC92,AD92,AE92,AF92,AG92,AH92,AI92,AJ92,AK92,AL92,AM92,AN92),"N/A") | AP92: =IFERROR(AVERAGE(W92,X92,Y92,Z92)/2,"N/A")
A93: 20572111131 | B93: ASOCIACION DE MUJERES ORGANIZADAS CHOCO WARMIS | C93: SAN MARTIN | G93: NO | H93: nan | I93: nan | J93: ACTIVO | K93: nan | L93: 0 | M93: =IF(E93>0,ROUND(L93/E93*100,1),0) | N93: PENDIENTE | O93: =IF(H93="SI",1,0)*0.6+IF(I93="SI",1,0)*0.4 | P93: PENDIENTE | S93: =IFERROR(SCORECARDS!C93,"") | T93: =IF(NOT(ISNUMBER(S93)),"—",IF(S93<34,"🔴 Crítico",IF(S93<67,"🟡 Vulnerable","🟢 Preparado"))) | W93: 0 | X93: 0 | Y93: 0 | Z93: 0 | AA93: 0 | AB93: 0 | AC93: 0 | AD93: 0 | AE93: 0 | AF93: 0 | AG93: 0 | AH93: 0 | AI93: 0 | AJ93: 0 | AK93: 0 | AL93: 0 | AM93: 0 | AN93: 0 | AO93: =IFERROR(AVERAGE(AA93,AB93,AC93,AD93,AE93,AF93,AG93,AH93,AI93,AJ93,AK93,AL93,AM93,AN93),"N/A") | AP93: =IFERROR(AVERAGE(W93,X93,Y93,Z93)/2,"N/A")
A94: 20572190251 | B94: CENTRAL DE COOPERATIVAS AGRARIAS CACAO AROMA DE TOCACHE LTDA | C94: SAN MARTIN | E94: 3777944.8 | F94: 14 | G94: SI | H94: nan | I94: nan | J94: ACTIVO | K94: nan | L94: 1888972.4 | M94: =IF(E94>0,ROUND(L94/E94*100,1),0) | N94: PENDIENTE | O94: =IF(H94="SI",1,0)*0.6+IF(I94="SI",1,0)*0.4 | P94: PENDIENTE | S94: =IFERROR(SCORECARDS!C94,"") | T94: =IF(NOT(ISNUMBER(S94)),"—",IF(S94<34,"🔴 Crítico",IF(S94<67,"🟡 Vulnerable","🟢 Preparado"))) | U94: 1 | V94: Sin hallazgos OSCE / OEFA | W94: 1 | X94: 0 | Y94: 0 | Z94: 0 | AA94: 0 | AB94: 0 | AC94: 0 | AD94: 0 | AE94: 0 | AF94: 0 | AG94: 0 | AH94: 0 | AI94: 0 | AJ94: 0 | AK94: 0 | AL94: 0 | AM94: 0 | AN94: 0 | AO94: =IFERROR(AVERAGE(AA94,AB94,AC94,AD94,AE94,AF94,AG94,AH94,AI94,AJ94,AK94,AL94,AM94,AN94),"N/A") | AP94: =IFERROR(AVERAGE(W94,X94,Y94,Z94)/2,"N/A")
A95: 20573049102 | B95: COOPERATIVA AGRARIA CACAOTERA PUERTO INCA | C95: HUANUCO | D95: CACAO | G95: NO | H95: nan | I95: nan | J95: ACTIVO | K95: nan | L95: 0 | M95: =IF(E95>0,ROUND(L95/E95*100,1),0) | N95: PENDIENTE | O95: =IF(H95="SI",1,0)*0.6+IF(I95="SI",1,0)*0.4 | P95: PENDIENTE | S95: =IFERROR(SCORECARDS!C95,"") | T95: =IF(NOT(ISNUMBER(S95)),"—",IF(S95<34,"🔴 Crítico",IF(S95<67,"🟡 Vulnerable","🟢 Preparado"))) | W95: 0 | X95: 0 | Y95: 0 | Z95: 0 | AA95: 0 | AB95: 0 | AC95: 0 | AD95: 0 | AE95: 0 | AF95: 0 | AG95: 0 | AH95: 0 | AI95: 0 | AJ95: 0 | AK95: 0 | AL95: 0 | AM95: 0 | AN95: 0 | AO95: =IFERROR(AVERAGE(AA95,AB95,AC95,AD95,AE95,AF95,AG95,AH95,AI95,AJ95,AK95,AL95,AM95,AN95),"N/A") | AP95: =IFERROR(AVERAGE(W95,X95,Y95,Z95)/2,"N/A")
A96: 20573057385 | B96: COOPERATIVA AGRARIA PARAISO | C96: HUANUCO | D96: CACAO | E96: 0 | G96: NO | H96: nan | I96: nan | J96: ACTIVO | K96: nan | L96: 0 | M96: =IF(E96>0,ROUND(L96/E96*100,1),0) | N96: PENDIENTE | O96: =IF(H96="SI",1,0)*0.6+IF(I96="SI",1,0)*0.4 | P96: PENDIENTE | S96: =IFERROR(SCORECARDS!C96,"") | T96: =IF(NOT(ISNUMBER(S96)),"—",IF(S96<34,"🔴 Crítico",IF(S96<67,"🟡 Vulnerable","🟢 Preparado"))) | W96: 0 | X96: 0 | Y96: 0 | Z96: 0 | AA96: 0 | AB96: 0 | AC96: 0 | AD96: 0 | AE96: 0 | AF96: 0 | AG96: 0 | AH96: 0 | AI96: 0 | AJ96: 0 | AK96: 0 | AL96: 0 | AM96: 0 | AN96: 0 | AO96: =IFERROR(AVERAGE(AA96,AB96,AC96,AD96,AE96,AF96,AG96,AH96,AI96,AJ96,AK96,AL96,AM96,AN96),"N/A") | AP96: =IFERROR(AVERAGE(W96,X96,Y96,Z96)/2,"N/A")
A97: 20573138202 | B97: ASOCIACION DE PRODUCTORES AGROPECUARIOS Y FORESTALES EL ALVA | C97: HUANUCO | D97: CACAO | G97: NO | H97: nan | I97: nan | J97: BAJA DE OFICIO | K97: nan | L97: 0 | M97: =IF(E97>0,ROUND(L97/E97*100,1),0) | N97: PENDIENTE | O97: =IF(H97="SI",1,0)*0.6+IF(I97="SI",1,0)*0.4 | P97: PENDIENTE | S97: =IFERROR(SCORECARDS!C97,"") | T97: =IF(NOT(ISNUMBER(S97)),"—",IF(S97<34,"🔴 Crítico",IF(S97<67,"🟡 Vulnerable","🟢 Preparado"))) | W97: 0 | X97: 0 | Y97: 0 | Z97: 0 | AA97: 0 | AB97: 0 | AC97: 0 | AD97: 0 | AE97: 0 | AF97: 0 | AG97: 0 | AH97: 0 | AI97: 0 | AJ97: 0 | AK97: 0 | AL97: 0 | AM97: 0 | AN97: 0 | AO97: =IFERROR(AVERAGE(AA97,AB97,AC97,AD97,AE97,AF97,AG97,AH97,AI97,AJ97,AK97,AL97,AM97,AN97),"N/A") | AP97: =IFERROR(AVERAGE(W97,X97,Y97,Z97)/2,"N/A")
A98: 20573260008 | B98: COOPERATIVA AGRARIA AUCAYACU | C98: HUANUCO | D98: CACAO | G98: NO | H98: nan | I98: nan | J98: ACTIVO | K98: nan | L98: 0 | M98: =IF(E98>0,ROUND(L98/E98*100,1),0) | N98: PENDIENTE | O98: =IF(H98="SI",1,0)*0.6+IF(I98="SI",1,0)*0.4 | P98: PENDIENTE | S98: =IFERROR(SCORECARDS!C98,"") | T98: =IF(NOT(ISNUMBER(S98)),"—",IF(S98<34,"🔴 Crítico",IF(S98<67,"🟡 Vulnerable","🟢 Preparado"))) | W98: 0 | X98: 0 | Y98: 0 | Z98: 0 | AA98: 0 | AB98: 0 | AC98: 0 | AD98: 0 | AE98: 0 | AF98: 0 | AG98: 0 | AH98: 0 | AI98: 0 | AJ98: 0 | AK98: 0 | AL98: 0 | AM98: 0 | AN98: 0 | AO98: =IFERROR(AVERAGE(AA98,AB98,AC98,AD98,AE98,AF98,AG98,AH98,AI98,AJ98,AK98,AL98,AM98,AN98),"N/A") | AP98: =IFERROR(AVERAGE(W98,X98,Y98,Z98)/2,"N/A")
A99: 20573344791 | B99: ASOCIACION AGROECOLOGICO HUANGANAPAMPA | C99: HUANUCO | D99: PLÁTANO | G99: NO | H99: nan | I99: nan | J99: BAJA DE OFICIO | K99: nan | L99: 0 | M99: =IF(E99>0,ROUND(L99/E99*100,1),0) | N99: PENDIENTE | O99: =IF(H99="SI",1,0)*0.6+IF(I99="SI",1,0)*0.4 | P99: PENDIENTE | S99: =IFERROR(SCORECARDS!C99,"") | T99: =IF(NOT(ISNUMBER(S99)),"—",IF(S99<34,"🔴 Crítico",IF(S99<67,"🟡 Vulnerable","🟢 Preparado"))) | W99: 0 | X99: 0 | Y99: 0 | Z99: 0 | AA99: 0 | AB99: 0 | AC99: 0 | AD99: 0 | AE99: 0 | AF99: 0 | AG99: 0 | AH99: 0 | AI99: 0 | AJ99: 0 | AK99: 0 | AL99: 0 | AM99: 0 | AN99: 0 | AO99: =IFERROR(AVERAGE(AA99,AB99,AC99,AD99,AE99,AF99,AG99,AH99,AI99,AJ99,AK99,AL99,AM99,AN99),"N/A") | AP99: =IFERROR(AVERAGE(W99,X99,Y99,Z99)/2,"N/A")
A100: 20574797013 | B100: ASOCIACION DE PRODUCTORES AGROPECUARIOS DE PARAISO CENTRAL | C100: CUSCO | D100: CACAO | G100: NO | H100: nan | I100: nan | J100: ACTIVO | K100: nan | L100: 0 | M100: =IF(E100>0,ROUND(L100/E100*100,1),0) | N100: PENDIENTE | O100: =IF(H100="SI",1,0)*0.6+IF(I100="SI",1,0)*0.4 | P100: PENDIENTE | S100: =IFERROR(SCORECARDS!C100,"") | T100: =IF(NOT(ISNUMBER(S100)),"—",IF(S100<34,"🔴 Crítico",IF(S100<67,"🟡 Vulnerable","🟢 Preparado"))) | W100: 0 | X100: 0 | Y100: 0 | Z100: 0 | AA100: 0 | AB100: 0 | AC100: 0 | AD100: 0 | AE100: 0 | AF100: 0 | AG100: 0 | AH100: 0 | AI100: 0 | AJ100: 0 | AK100: 0 | AL100: 0 | AM100: 0 | AN100: 0 | AO100: =IFERROR(AVERAGE(AA100,AB100,AC100,AD100,AE100,AF100,AG100,AH100,AI100,AJ100,AK100,AL100,AM100,AN100),"N/A") | AP100: =IFERROR(AVERAGE(W100,X100,Y100,Z100)/2,"N/A")
...

Sheet PREGUNTAS_PROXY
A1: PREGUNTAS PROXY — Verificación rápida por dimensión EUDR
A2: Dim. | B2: # | C2: Pregunta | D2: Respuesta | E2: Score (0-1) | F2: Variable | G2: Fuente | H2: Obs.
A3: DIMENSIÓN D1 — Clasificación regulatoria
A4: D1 | B4: 1 | C4: ¿Cuál es el rol principal de la organización? | F4: tipo_rol | G4: Entrevista directiva / SUNAT
A5: D1 | B5: 2 | C5: ¿La organización está inscrita en el RNCA (Registro Nacional de Cooperativas Agrarias)? | F5: rnca | G5: SUNAT / MIDAGRI RNCA
A6: D1 | B6: 3 | C6: ¿Exporta directamente bajo su propio RUC (no a través de un agente)? | F6: exporta_directo | G6: ADUANET / DUAs
A7: DIMENSIÓN D2 — Trazabilidad y geolocalización
A8: D2 | B8: 1 | C8: ¿Existe al menos un registro donde cada lote exportado esté vinculado a la parcela de origen? | F8: lote_parcela | G8: Entrevista + revisión documentos
A9: D2 | B9: 2 | C9: ¿Se registran las coordenadas geográficas de las parcelas de los socios? | F9: coords | G9: Entrevista + evidencia
A10: D2 | B10: 3 | C10: ¿Con qué frecuencia se actualizan las coordenadas de parcelas? | F10: frec_coords | G10: Entrevista
A11: D2 | B11: 4 | C11: ¿Se usa balance de masas (mezcla de lotes sin segregación física)? | F11: bal_masas | G11: Entrevista — ROJO si dice Sí | H11: ⚠ Bal. de masas prohibido bajo EUDR
A12: D2 | B12: 5 | C12: ¿Los proveedores externos (no socios) representan volumen significativo? | F12: pct_ext | G12: Entrevista
A13: D2 | B13: 6 | C13: ¿Se registra la trazabilidad de proveedores externos (nombre, cantidad, origen)? | F13: traza_ext | G13: Entrevista
A14: DIMENSIÓN D3 — Legalidad de la producción
A15: D3 | B15: 1 | C15: ¿Qué porcentaje aproximado de los socios tiene título de propiedad o constancia de posesión inscrita en SUNARP? | F15: pct_titulo | G15: Entrevista / MIDAGRI
A16: D3 | B16: 2 | C16: ¿La zona de producción está en un área natural protegida o zona de amortiguamiento? | F16: anp | G16: GEOSERFOR / SINIA
A17: D3 | B17: 3 | C17: ¿La organización cuenta con autorizaciones ambientales vigentes (EIA, DIA, certificación forestal)? | F17: aut_ambiental | G17: Entrevista / OEFA
A18: D3 | B18: 4 | C18: ¿Hay algún proceso sancionador vigente de OEFA o SINEFA contra la organización? | F18: sancion_oea | G18: OEFA / SINEFA
A19: DIMENSIÓN D4 — Riesgo de deforestación
A20: D4 | B20: 1 | C20: ¿La organización ha realizado cruces de sus parcelas contra mapas de deforestación (GEOSERFOR / PNCB)? | F20: cruce_deforest | G20: Entrevista / verificación web
A21: D4 | B21: 2 | C21: ¿Se han detectado alertas de deforestación en parcelas de la organización? | F21: alerta_deforest | G21: GEOSERFOR / GFW
A22: DIMENSIÓN D5 — Sistema de debida diligencia
A23: D5 | B23: 1 | C23: ¿Existe un proceso documentado para evaluar riesgo de deforestación antes de exportar? | F23: proc_dd | G23: Entrevista + revisión docs
A24: D5 | B24: 2 | C24: ¿Se registran las alertas o rechazos de compradores europeos en los últimos 2 años? | F24: reg_rechazos | G24: Entrevista
A25: D5 | B25: 3 | C25: ¿La organización elabora un reporte periódico de debida diligencia? | F25: reporte_dd | G25: Entrevista
A26: DIMENSIÓN D6 — Capacidad organizacional y digital
A27: D6 | B27: 1 | C27: ¿Hay personal dedicado (tiempo completo o parcial) a tareas de gestión de datos o sistemas? | F27: personal_datos | G27: Entrevista
A28: D6 | B28: 2 | C28: ¿La organización tiene acceso a internet estable en su sede? | F28: internet | G28: Entrevista
A29: D6 | B29: 3 | C29: ¿Usa algún software o herramienta digital para gestionar trazabilidad? | F29: sw_trazabilidad | G29: Entrevista
A30: D6 | B30: 4 | C30: ¿El presupuesto anual incluye una partida para tecnología o datos? | F30: presupuesto_tech | G30: Entrevista directiva
A31: DIMENSIÓN D7 — Posición en la cadena de valor
A32: D7 | B32: 1 | C32: ¿Cuál es el destino principal de las exportaciones? | F32: destino_principal | G32: DUAs / Entrevista
A33: D7 | B33: 2 | C33: ¿El comprador principal (primera mano) es una empresa europea o está sujeta a CS3D? | F33: comprador_ue | G33: Entrevista / web
A34: D7 | B34: 3 | C34: ¿El comprador ha solicitado evidencia de trazabilidad o geolocalización? | F34: exige_evidencia | G34: Entrevista
A35: D7 | B35: 4 | C35: ¿Hay contrato escrito con cláusula EUDR o debida diligencia? | F35: contrato_eudr | G35: Entrevista / docs legales
A36: DIMENSIÓN D8 — Gobernanza y participación de socios
A37: D8 | B37: 1 | C37: ¿Los socios conocen los requisitos EUDR y sus implicancias? | F37: socios_conocen | G37: Entrevista + observación
A38: D8 | B38: 2 | C38: ¿Existe un mecanismo formal para que los socios entreguen datos de parcelas? | F38: mec_entrega | G38: Entrevista
A39: DIMENSIÓN D9 — Sostenibilidad económica del cumplimiento
A40: D9 | B40: 1 | C40: ¿La organización ha estimado el costo de adecuación al EUDR? | F40: costo_estimado | G40: Entrevista directiva
A41: D9 | B41: 2 | C41: ¿Existe una fuente de financiamiento identificada para la adecuación? | F41: financiamiento | G41: Entrevista
A42: DIMENSIÓN D10 — Confusión certificación / EUDR
A43: D10 | B43: 1 | C43: ¿La organización cree que sus certificaciones (Orgánica, Fairtrade, Rainforest) cubren los requisitos EUDR? | F43: cree_cubierta | G43: Entrevista — ROJO si dice Sí sin entender EUDR
A44: D10 | B44: 2 | C44: ¿Ha recibido asesoría específica sobre EUDR (no solo genérica de sostenibilidad)? | F44: asesoria_eudr | G44: Entrevista
A45: DIMENSIÓN D11 — Ecosistema de apoyo externo
A46: D11 | B46: 1 | C46: ¿Conoce programas de MIDAGRI, GIZ, EFI, PROMPERÚ o cooperación para apoyo EUDR? | F46: prog_apoyo | G46: Entrevista
A47: D11 | B47: 2 | C47: ¿Está inscrita en la plataforma de trazabilidad de APPCACAO o JNC? | F47: plataforma_traz | G47: Verificación web + entrevista
A48: DIMENSIÓN PPWR — Envases y Packaging (PPWR)
A49: PPWR | B49: P1 | C49: ¿Qué tipo de sacos de exportación usa principalmente? | F49: tipo_saco | G49: Entrevista
A50: PPWR | B50: P2 | C50: ¿Los sacos tienen certificación FSC o equivalente? | F50: fsc | G50: Entrevista / proveedor
A52: RESUMEN DE SCORES POR DIMENSIÓN
A53: Dimensión | B53: Score promedio | C53: N° preguntas | D53: Nivel
A54: D1 — Clasificación regulatoria | B54: =IFERROR(AVERAGEIF(E3:E6,">0"),0) | C54: =COUNTIF(E3:E6,">0") | D54: =IF(B54>=0.67,"🟢 Verde",IF(B54>=0.34,"🟡 Amarillo","🔴 Rojo"))
A55: D2 — Trazabilidad y geolocalización | B55: =IFERROR(AVERAGEIF(E7:E13,">0"),0) | C55: =COUNTIF(E7:E13,">0") | D55: =IF(B55>=0.67,"🟢 Verde",IF(B55>=0.34,"🟡 Amarillo","🔴 Rojo"))
A56: D3 — Legalidad de la producción | B56: =IFERROR(AVERAGEIF(E14:E18,">0"),0) | C56: =COUNTIF(E14:E18,">0") | D56: =IF(B56>=0.67,"🟢 Verde",IF(B56>=0.34,"🟡 Amarillo","🔴 Rojo"))
A57: D4 — Riesgo de deforestación | B57: =IFERROR(AVERAGEIF(E19:E21,">0"),0) | C57: =COUNTIF(E19:E21,">0") | D57: =IF(B57>=0.67,"🟢 Verde",IF(B57>=0.34,"🟡 Amarillo","🔴 Rojo"))
A58: D5 — Sistema de debida diligencia | B58: =IFERROR(AVERAGEIF(E22:E25,">0"),0) | C58: =COUNTIF(E22:E25,">0") | D58: =IF(B58>=0.67,"🟢 Verde",IF(B58>=0.34,"🟡 Amarillo","🔴 Rojo"))
A59: D6 — Capacidad organizacional y digital | B59: =IFERROR(AVERAGEIF(E26:E30,">0"),0) | C59: =COUNTIF(E26:E30,">0") | D59: =IF(B59>=0.67,"🟢 Verde",IF(B59>=0.34,"🟡 Amarillo","🔴 Rojo"))
A60: D7 — Posición en la cadena de valor | B60: =IFERROR(AVERAGEIF(E31:E35,">0"),0) | C60: =COUNTIF(E31:E35,">0") | D60: =IF(B60>=0.67,"🟢 Verde",IF(B60>=0.34,"🟡 Amarillo","🔴 Rojo"))
A61: D8 — Gobernanza y participación de socios | B61: =IFERROR(AVERAGEIF(E36:E38,">0"),0) | C61: =COUNTIF(E36:E38,">0") | D61: =IF(B61>=0.67,"🟢 Verde",IF(B61>=0.34,"🟡 Amarillo","🔴 Rojo"))
A62: D9 — Sostenibilidad económica del cumplimiento | B62: =IFERROR(AVERAGEIF(E39:E41,">0"),0) | C62: =COUNTIF(E39:E41,">0") | D62: =IF(B62>=0.67,"🟢 Verde",IF(B62>=0.34,"🟡 Amarillo","🔴 Rojo"))
A63: D10 — Confusión certificación / EUDR | B63: =IFERROR(AVERAGEIF(E42:E44,">0"),0) | C63: =COUNTIF(E42:E44,">0") | D63: =IF(B63>=0.67,"🟢 Verde",IF(B63>=0.34,"🟡 Amarillo","🔴 Rojo"))
A64: D11 — Ecosistema de apoyo externo | B64: =IFERROR(AVERAGEIF(E45:E47,">0"),0) | C64: =COUNTIF(E45:E47,">0") | D64: =IF(B64>=0.67,"🟢 Verde",IF(B64>=0.34,"🟡 Amarillo","🔴 Rojo"))
A65: PPWR — Envases y Packaging (PPWR) | B65: =IFERROR(AVERAGEIF(E48:E50,">0"),0) | C65: =COUNTIF(E48:E50,">0") | D65: =IF(B65>=0.67,"🟢 Verde",IF(B65>=0.34,"🟡 Amarillo","🔴 Rojo"))

Sheet SCORECARDS
A1: SCORECARDS — ISA-Completo · IP · IV · RE · Café y Cacao Perú
A2: RUC | B2: Razón Social | C2: ISA-Completo (0-100) | D2: Semáforo | E2: Ranking | F2: FOB UE USD | G2: % UE/FOB | H2: Trazab. (D2) | I2: Dilig. (D5) | J2: Capacidad (D6) | K2: Legalidad D3 (OSCE) | L2: Cert (0-1) | M2: PPWR | N2: Tipología ISCAM | O2: Segmento
A3: 20118578415 | B3: CENT.DE COOP.AGR. CAF.VALLES SANDIA LTDA | C3: =IFERROR(ISCAM_Score!AL4,"—") | D3: =IF(C3="—","— Sin Inst.2",IF(C3<34,"🔴 Crítico",IF(C3<67,"🟡 Vulnerable","🟢 Preparado"))) | E3: =IFERROR(RANK(C3,C:C,-1),"") | F3: =IFERROR(MATRIZ_174!L3,0) | G3: =IFERROR(MATRIZ_174!M3,0) | H3: 0 | I3: 0 | J3: 0 | K3: =IFERROR(INDEX(MATRIZ_174!$U:$U,MATCH(A3,MATRIZ_174!$A:$A,0)),"") | L3: =IFERROR(MATRIZ_174!O3,0) | M3: 0 | N3: =IFERROR(ISCAM_Score!AC4,"") | O3: PUNO
A4: 20129156083 | B4: COOP AGRARIA CAFET VALLE RIO APURIMAC | C4: =IFERROR(ISCAM_Score!AL5,"—") | D4: =IF(C4="—","— Sin Inst.2",IF(C4<34,"🔴 Crítico",IF(C4<67,"🟡 Vulnerable","🟢 Preparado"))) | E4: =IFERROR(RANK(C4,C:C,-1),"") | F4: =IFERROR(MATRIZ_174!L4,0) | G4: =IFERROR(MATRIZ_174!M4,0) | H4: 0 | I4: 0 | J4: 0 | K4: =IFERROR(INDEX(MATRIZ_174!$U:$U,MATCH(A4,MATRIZ_174!$A:$A,0)),"") | L4: =IFERROR(MATRIZ_174!O4,0) | M4: 0 | N4: =IFERROR(ISCAM_Score!AC5,"") | O4: AYACUCHO
A5: 20129529530 | B5: COOP AGRARIA CAFETALERA SATIPO LTDA | C5: =IFERROR(ISCAM_Score!AL6,"—") | D5: =IF(C5="—","— Sin Inst.2",IF(C5<34,"🔴 Crítico",IF(C5<67,"🟡 Vulnerable","🟢 Preparado"))) | E5: =IFERROR(RANK(C5,C:C,-1),"") | F5: =IFERROR(MATRIZ_174!L5,0) | G5: =IFERROR(MATRIZ_174!M5,0) | H5: 0 | I5: 0 | J5: 0 | K5: =IFERROR(INDEX(MATRIZ_174!$U:$U,MATCH(A5,MATRIZ_174!$A:$A,0)),"") | L5: =IFERROR(MATRIZ_174!O5,0) | M5: 0 | N5: =IFERROR(ISCAM_Score!AC6,"") | O5: JUNIN
A6: 20132489824 | B6: COOPERATIVA AGRARIA CAFETALERA CHANCAMAYO LTDA. N° 008-B-VII | C6: =IFERROR(ISCAM_Score!AL7,"—") | D6: =IF(C6="—","— Sin Inst.2",IF(C6<34,"🔴 Crítico",IF(C6<67,"🟡 Vulnerable","🟢 Preparado"))) | E6: =IFERROR(RANK(C6,C:C,-1),"") | F6: =IFERROR(MATRIZ_174!L6,0) | G6: =IFERROR(MATRIZ_174!M6,0) | H6: 0 | I6: 0 | J6: 0 | K6: =IFERROR(INDEX(MATRIZ_174!$U:$U,MATCH(A6,MATRIZ_174!$A:$A,0)),"") | L6: =IFERROR(MATRIZ_174!O6,0) | M6: 0 | N6: =IFERROR(ISCAM_Score!AC7,"") | O6: CUSCO
A7: 20132505455 | B7: COOPERATIVA AGRARIA CAFETALERA AGUILAYOC LTDA. 084 | C7: =IFERROR(ISCAM_Score!AL8,"—") | D7: =IF(C7="—","— Sin Inst.2",IF(C7<34,"🔴 Crítico",IF(C7<67,"🟡 Vulnerable","🟢 Preparado"))) | E7: =IFERROR(RANK(C7,C:C,-1),"") | F7: =IFERROR(MATRIZ_174!L7,0) | G7: =IFERROR(MATRIZ_174!M7,0) | H7: 0 | I7: 0 | J7: 0 | K7: =IFERROR(INDEX(MATRIZ_174!$U:$U,MATCH(A7,MATRIZ_174!$A:$A,0)),"") | L7: =IFERROR(MATRIZ_174!O7,0) | M7: 0 | N7: =IFERROR(ISCAM_Score!AC8,"") | O7: CUSCO
A8: 20132509795 | B8: COOPERATIVA AGRARIA CAFETALERA JOSE OLAYA LTDA N° 252 | C8: =IFERROR(ISCAM_Score!AL9,"—") | D8: =IF(C8="—","— Sin Inst.2",IF(C8<34,"🔴 Crítico",IF(C8<67,"🟡 Vulnerable","🟢 Preparado"))) | E8: =IFERROR(RANK(C8,C:C,-1),"") | F8: =IFERROR(MATRIZ_174!L8,0) | G8: =IFERROR(MATRIZ_174!M8,0) | H8: 0 | I8: 0 | J8: 0 | K8: =IFERROR(INDEX(MATRIZ_174!$U:$U,MATCH(A8,MATRIZ_174!$A:$A,0)),"") | L8: =IFERROR(MATRIZ_174!O8,0) | M8: 0 | N8: =IFERROR(ISCAM_Score!AC9,"") | O8: CUSCO
A9: 20132509876 | B9: COOPERATIVA AGRARIA CAFETALERA MARANURA LTDA. 129 | C9: =IFERROR(ISCAM_Score!AL10,"—") | D9: =IF(C9="—","— Sin Inst.2",IF(C9<34,"🔴 Crítico",IF(C9<67,"🟡 Vulnerable","🟢 Preparado"))) | E9: =IFERROR(RANK(C9,C:C,-1),"") | F9: =IFERROR(MATRIZ_174!L9,0) | G9: =IFERROR(MATRIZ_174!M9,0) | H9: 0 | I9: 0 | J9: 0 | K9: =IFERROR(INDEX(MATRIZ_174!$U:$U,MATCH(A9,MATRIZ_174!$A:$A,0)),"") | L9: =IFERROR(MATRIZ_174!O9,0) | M9: 0 | N9: =IFERROR(ISCAM_Score!AC10,"") | O9: CUSCO
A10: 20132517119 | B10: COOPERATIVA AGRARIA CAFETALERA MATEO PUMACAHUA LTDA N° 185 | C10: =IFERROR(ISCAM_Score!AL11,"—") | D10: =IF(C10="—","— Sin Inst.2",IF(C10<34,"🔴 Crítico",IF(C10<67,"🟡 Vulnerable","🟢 Preparado"))) | E10: =IFERROR(RANK(C10,C:C,-1),"") | F10: =IFERROR(MATRIZ_174!L10,0) | G10: =IFERROR(MATRIZ_174!M10,0) | H10: 0 | I10: 0 | J10: 0 | K10: =IFERROR(INDEX(MATRIZ_174!$U:$U,MATCH(A10,MATRIZ_174!$A:$A,0)),"") | L10: =IFERROR(MATRIZ_174!O10,0) | M10: 0 | N10: =IFERROR(ISCAM_Score!AC11,"") | O10: CUSCO
A11: 20136201132 | B11: COOPERATIVA AGRARIA CAFETALERA ALTO URUBAMBA LTDA N° 239 | C11: =IFERROR(ISCAM_Score!AL12,"—") | D11: =IF(C11="—","— Sin Inst.2",IF(C11<34,"🔴 Crítico",IF(C11<67,"🟡 Vulnerable","🟢 Preparado"))) | E11: =IFERROR(RANK(C11,C:C,-1),"") | F11: =IFERROR(MATRIZ_174!L11,0) | G11: =IFERROR(MATRIZ_174!M11,0) | H11: 0 | I11: 0 | J11: 0 | K11: =IFERROR(INDEX(MATRIZ_174!$U:$U,MATCH(A11,MATRIZ_174!$A:$A,0)),"") | L11: =IFERROR(MATRIZ_174!O11,0) | M11: 0 | N11: =IFERROR(ISCAM_Score!AC12,"") | O11: CUSCO
A12: 20136201213 | B12: CENTRAL DE COOPERATIVAS AGRARIAS CAFETALERAS COCLA LTDA. N° | C12: =IFERROR(ISCAM_Score!AL13,"—") | D12: =IF(C12="—","— Sin Inst.2",IF(C12<34,"🔴 Crítico",IF(C12<67,"🟡 Vulnerable","🟢 Preparado"))) | E12: =IFERROR(RANK(C12,C:C,-1),"") | F12: =IFERROR(MATRIZ_174!L12,0) | G12: =IFERROR(MATRIZ_174!M12,0) | H12: 0 | I12: 0 | J12: 0 | K12: =IFERROR(INDEX(MATRIZ_174!$U:$U,MATCH(A12,MATRIZ_174!$A:$A,0)),"") | L12: =IFERROR(MATRIZ_174!O12,0) | M12: 0 | N12: =IFERROR(ISCAM_Score!AC13,"") | O12: CUSCO
A13: 20140292657 | B13: COOPERATIVA AGRARIA CAFETALERA CCOCHAPAMPA LTDA. | C13: =IFERROR(ISCAM_Score!AL14,"—") | D13: =IF(C13="—","— Sin Inst.2",IF(C13<34,"🔴 Crítico",IF(C13<67,"🟡 Vulnerable","🟢 Preparado"))) | E13: =IFERROR(RANK(C13,C:C,-1),"") | F13: =IFERROR(MATRIZ_174!L13,0) | G13: =IFERROR(MATRIZ_174!M13,0) | H13: 0 | I13: 0 | J13: 0 | K13: =IFERROR(INDEX(MATRIZ_174!$U:$U,MATCH(A13,MATRIZ_174!$A:$A,0)),"") | L13: =IFERROR(MATRIZ_174!O13,0) | M13: 0 | N13: =IFERROR(ISCAM_Score!AC14,"") | O13: CUSCO
A14: 20143692010 | B14: COOPERATIVA AGRARIA EL QUINACHO LTDA. N° 078 | C14: =IFERROR(ISCAM_Score!AL15,"—") | D14: =IF(C14="—","— Sin Inst.2",IF(C14<34,"🔴 Crítico",IF(C14<67,"🟡 Vulnerable","🟢 Preparado"))) | E14: =IFERROR(RANK(C14,C:C,-1),"") | F14: =IFERROR(MATRIZ_174!L14,0) | G14: =IFERROR(MATRIZ_174!M14,0) | H14: 0 | I14: 0 | J14: 0 | K14: =IFERROR(INDEX(MATRIZ_174!$U:$U,MATCH(A14,MATRIZ_174!$A:$A,0)),"") | L14: =IFERROR(MATRIZ_174!O14,0) | M14: 0 | N14: =IFERROR(ISCAM_Score!AC15,"") | O14: AYACUCHO
... A176: 20612331821 | B176: ASOCIACIÓN DE MUJERES LAS FLORES DE LUYA | C176: =IFERROR(ISCAM_Score!AL177,"—") | D176: =IF(C176="—","— Sin Inst.2",IF(C176<34,"🔴 Crítico",IF(C176<67,"🟡 Vulnerable","🟢 Preparado"))) | E176: =IFERROR(RANK(C176,C:C,-1),"") | F176: =IFERROR(MATRIZ_174!L176,0) | G176: =IFERROR(MATRIZ_174!M176,0) | H176: 0 | I176: 0 | J176: 0 | K176: =IFERROR(INDEX(MATRIZ_174!$U:$U,MATCH(A176,MATRIZ_174!$A:$A,0)),"") | L176: =IFERROR(MATRIZ_174!O176,0) | M176: 0 | N176: =IFERROR(ISCAM_Score!AC177,"") | O176: AMAZONAS
K177: =IFERROR(INDEX(MATRIZ_174!$U:$U,MATCH(A177,MATRIZ_174!$A:$A,0)),"")
K178: =IFERROR(INDEX(MATRIZ_174!$U:$U,MATCH(A178,MATRIZ_174!$A:$A,0)),"")
A179: RESUMEN EJECUTIVO | K179: =IFERROR(INDEX(MATRIZ_174!$U:$U,MATCH(A179,MATRIZ_174!$A:$A,0)),"")
A180: Total organizaciones | B180: =COUNTA(A3:A176) | K180: =IFERROR(INDEX(MATRIZ_174!$U:$U,MATCH(A180,MATRIZ_174!$A:$A,0)),"")
A181: Con exposición UE (FOB UE > 0) | B181: =COUNTIF(F3:F176,">0") | K181: =IFERROR(INDEX(MATRIZ_174!$U:$U,MATCH(A181,MATRIZ_174!$A:$A,0)),"")
A182: 🔴 Críticos (0-33) | B182: =COUNTIF(C3:C176,"<34")-COUNTIF(C3:C176,0) | K182: =IFERROR(INDEX(MATRIZ_174!$U:$U,MATCH(A182,MATRIZ_174!$A:$A,0)),"")
A183: 🟡 Vulnerables (34-66) | B183: =COUNTIFS(C3:C176,">=34",C3:C176,"<67") | K183: =IFERROR(INDEX(MATRIZ_174!$U:$U,MATCH(A183,MATRIZ_174!$A:$A,0)),"")
A184: 🟢 Preparados (67-100) | B184: =COUNTIF(C3:C176,">=67") | K184: =IFERROR(INDEX(MATRIZ_174!$U:$U,MATCH(A184,MATRIZ_174!$A:$A,0)),"")
A185: Sin dato (score = 0) | B185: =COUNTIF(C3:C176,0) | K185: =IFERROR(INDEX(MATRIZ_174!$U:$U,MATCH(A185,MATRIZ_174!$A:$A,0)),"")
A186: PVE promedio (con dato) | B186: =IFERROR(AVERAGEIF(C3:C176,">0"),"N/A") | K186: =IFERROR(INDEX(MATRIZ_174!$U:$U,MATCH(A186,MATRIZ_174!$A:$A,0)),"")
A187: FOB total expuesto a UE (USD) | B187: =SUMIF(F3:F176,">0",F3:F176) | K187: =IFERROR(INDEX(MATRIZ_174!$U:$U,MATCH(A187,MATRIZ_174!$A:$A,0)),"")

Sheet RADAR_BRECHAS
A1: RADAR DE BRECHAS — Score promedio por departamento y dimensión
A2: Departamento / Dimensión | B2: D1 | C2: D2 | D2: D3 | E2: D4 | F2: D5 | G2: D6 | H2: D7 | I2: D8 | J2: D9 | K2: D10 | L2: D11 | M2: PVE Promedio
A3: SAN MARTIN | B3: =IFERROR(AVERAGEIF(ISCAM_Score!$C$4:$C$177,A3,ISCAM_Score!$E$4:$E$177),0) | C3: =IFERROR(AVERAGEIF(MATRIZ_174!$C$3:$C$176,A3,SCORECARDS!$H$3:$H$176),0) | D3: =IFERROR(AVERAGEIF(ISCAM_Score!$C$4:$C$177,A3,ISCAM_Score!$G$4:$G$177),0) | E3: =IFERROR(AVERAGEIF(ISCAM_Score!$C$4:$C$177,A3,ISCAM_Score!$H$4:$H$177),0) | F3: =IFERROR(AVERAGEIF(MATRIZ_174!$C$3:$C$176,A3,SCORECARDS!$I$3:$I$176),0) | G3: =IFERROR(AVERAGEIF(MATRIZ_174!$C$3:$C$176,A3,SCORECARDS!$J$3:$J$176),0) | H3: =IFERROR(AVERAGEIF(ISCAM_Score!$C$4:$C$177,A3,ISCAM_Score!$K$4:$K$177),0) | I3: =IFERROR(AVERAGEIF(ISCAM_Score!$C$4:$C$177,A3,ISCAM_Score!$L$4:$L$177),0) | J3: =IFERROR(AVERAGEIF(ISCAM_Score!$C$4:$C$177,A3,ISCAM_Score!$M$4:$M$177),0) | K3: =IFERROR(AVERAGEIF(ISCAM_Score!$C$4:$C$177,A3,ISCAM_Score!$N$4:$N$177),0) | L3: =IFERROR(AVERAGEIF(ISCAM_Score!$C$4:$C$177,A3,ISCAM_Score!$O$4:$O$177),0) | M3: =IFERROR(AVERAGE(B3:L3),0)
A4: JUNIN | B4: =IFERROR(AVERAGEIF(ISCAM_Score!$C$4:$C$177,A4,ISCAM_Score!$E$4:$E$177),0) | C4: =IFERROR(AVERAGEIF(MATRIZ_174!$C$3:$C$176,A4,SCORECARDS!$H$3:$H$176),0) | D4: =IFERROR(AVERAGEIF(ISCAM_Score!$C$4:$C$177,A4,ISCAM_Score!$G$4:$G$177),0) | E4: =IFERROR(AVERAGEIF(ISCAM_Score!$C$4:$C$177,A4,ISCAM_Score!$H$4:$H$177),0) | F4: =IFERROR(AVERAGEIF(MATRIZ_174!$C$3:$C$176,A4,SCORECARDS!$I$3:$I$176),0) | G4: =IFERROR(AVERAGEIF(MATRIZ_174!$C$3:$C$176,A4,SCORECARDS!$J$3:$J$176),0) | H4: =IFERROR(AVERAGEIF(ISCAM_Score!$C$4:$C$177,A4,ISCAM_Score!$K$4:$K$177),0) | I4: =IFERROR(AVERAGEIF(ISCAM_Score!$C$4:$C$177,A4,ISCAM_Score!$L$4:$L$177),0) | J4: =IFERROR(AVERAGEIF(ISCAM_Score!$C$4:$C$177,A4,ISCAM_Score!$M$4:$M$177),0) | K4: =IFERROR(AVERAGEIF(ISCAM_Score!$C$4:$C$177,A4,ISCAM_Score!$N$4:$N$177),0) | L4: =IFERROR(AVERAGEIF(ISCAM_Score!$C$4:$C$177,A4,ISCAM_Score!$O$4:$O$177),0) | M4: =IFERROR(AVERAGE(B4:L4),0)
A5: AMAZONAS | B5: =IFERROR(AVERAGEIF(ISCAM_Score!$C$4:$C$177,A5,ISCAM_Score!$E$4:$E$177),0) | C5: =IFERROR(AVERAGEIF(MATRIZ_174!$C$3:$C$176,A5,SCORECARDS!$H$3:$H$176),0) | D5: =IFERROR(AVERAGEIF(ISCAM_Score!$C$4:$C$177,A5,ISCAM_Score!$G$4:$G$177),0) | E5: =IFERROR(AVERAGEIF(ISCAM_Score!$C$4:$C$177,A5,ISCAM_Score!$H$4:$H$177),0) | F5: =IFERROR(AVERAGEIF(MATRIZ_174!$C$3:$C$176,A5,SCORECARDS!$I$3:$I$176),0) | G5: =IFERROR(AVERAGEIF(MATRIZ_174!$C$3:$C$176,A5,SCORECARDS!$J$3:$J$176),0) | H5: =IFERROR(AVERAGEIF(ISCAM_Score!$C$4:$C$177,A5,ISCAM_Score!$K$4:$K$177),0) | I5: =IFERROR(AVERAGEIF(ISCAM_Score!$C$4:$C$177,A5,ISCAM_Score!$L$4:$L$177),0) | J5: =IFERROR(AVERAGEIF(ISCAM_Score!$C$4:$C$177,A5,ISCAM_Score!$M$4:$M$177),0) | K5: =IFERROR(AVERAGEIF(ISCAM_Score!$C$4:$C$177,A5,ISCAM_Score!$N$4:$N$177),0) | L5: =IFERROR(AVERAGEIF(ISCAM_Score!$C$4:$C$177,A5,ISCAM_Score!$O$4:$O$177),0) | M5: =IFERROR(AVERAGE(B5:L5),0)
A6: CAJAMARCA | B6: =IFERROR(AVERAGEIF(ISCAM_Score!$C$4:$C$177,A6,ISCAM_Score!$E$4:$E$177),0) | C6: =IFERROR(AVERAGEIF(MATRIZ_174!$C$3:$C$176,A6,SCORECARDS!$H$3:$H$176),0) | D6: =IFERROR(AVERAGEIF(ISCAM_Score!$C$4:$C$177,A6,ISCAM_Score!$G$4:$G$177),0) | E6: =IFERROR(AVERAGEIF(ISCAM_Score!$C$4:$C$177,A6,ISCAM_Score!$H$4:$H$177),0) | F6: =IFERROR(AVERAGEIF(MATRIZ_174!$C$3:$C$176,A6,SCORECARDS!$I$3:$I$176),0) | G6: =IFERROR(AVERAGEIF(MATRIZ_174!$C$3:$C$176,A6,SCORECARDS!$J$3:$J$176),0) | H6: =IFERROR(AVERAGEIF(ISCAM_Score!$C$4:$C$177,A6,ISCAM_Score!$K$4:$K$177),0) | I6: =IFERROR(AVERAGEIF(ISCAM_Score!$C$4:$C$177,A6,ISCAM_Score!$L$4:$L$177),0) | J6: =IFERROR(AVERAGEIF(ISCAM_Score!$C$4:$C$177,A6,ISCAM_Score!$M$4:$M$177),0) | K6: =IFERROR(AVERAGEIF(ISCAM_Score!$C$4:$C$177,A6,ISCAM_Score!$N$4:$N$177),0) | L6: =IFERROR(AVERAGEIF(ISCAM_Score!$C$4:$C$177,A6,ISCAM_Score!$O$4:$O$177),0) | M6: =IFERROR(AVERAGE(B6:L6),0)
A7: CUSCO | B7: =IFERROR(AVERAGEIF(ISCAM_Score!$C$4:$C$177,A7,ISCAM_Score!$E$4:$E$177),0) | C7: =IFERROR(AVERAGEIF(MATRIZ_174!$C$3:$C$176,A7,SCORECARDS!$H$3:$H$176),0) | D7: =IFERROR(AVERAGEIF(ISCAM_Score!$C$4:$C$177,A7,ISCAM_Score!$G$4:$G$177),0) | E7: =IFERROR(AVERAGEIF(ISCAM_Score!$C$4:$C$177,A7,ISCAM_Score!$H$4:$H$177),0) | F7: =IFERROR(AVERAGEIF(MATRIZ_174!$C$3:$C$176,A7,SCORECARDS!$I$3:$I$176),0) | G7: =IFERROR(AVERAGEIF(MATRIZ_174!$C$3:$C$176,A7,SCORECARDS!$J$3:$J$176),0) | H7: =IFERROR(AVERAGEIF(ISCAM_Score!$C$4:$C$177,A7,ISCAM_Score!$K$4:$K$177),0) | I7: =IFERROR(AVERAGEIF(ISCAM_Score!$C$4:$C$177,A7,ISCAM_Score!$L$4:$L$177),0) | J7: =IFERROR(AVERAGEIF(ISCAM_Score!$C$4:$C$177,A7,ISCAM_Score!$M$4:$M$177),0) | K7: =IFERROR(AVERAGEIF(ISCAM_Score!$C$4:$C$177,A7,ISCAM_Score!$N$4:$N$177),0) | L7: =IFERROR(AVERAGEIF(ISCAM_Score!$C$4:$C$177,A7,ISCAM_Score!$O$4:$O$177),0) | M7: =IFERROR(AVERAGE(B7:L7),0)
A8: UCAYALI | B8: =IFERROR(AVERAGEIF(ISCAM_Score!$C$4:$C$177,A8,ISCAM_Score!$E$4:$E$177),0) | C8: =IFERROR(AVERAGEIF(MATRIZ_174!$C$3:$C$176,A8,SCORECARDS!$H$3:$H$176),0) | D8: =IFERROR(AVERAGEIF(ISCAM_Score!$C$4:$C$177,A8,ISCAM_Score!$G$4:$G$177),0) | E8: =IFERROR(AVERAGEIF(ISCAM_Score!$C$4:$C$177,A8,ISCAM_Score!$H$4:$H$177),0) | F8: =IFERROR(AVERAGEIF(MATRIZ_174!$C$3:$C$176,A8,SCORECARDS!$I$3:$I$176),0) | G8: =IFERROR(AVERAGEIF(MATRIZ_174!$C$3:$C$176,A8,SCORECARDS!$J$3:$J$176),0) | H8: =IFERROR(AVERAGEIF(ISCAM_Score!$C$4:$C$177,A8,ISCAM_Score!$K$4:$K$177),0) | I8: =IFERROR(AVERAGEIF(ISCAM_Score!$C$4:$C$177,A8,ISCAM_Score!$L$4:$L$177),0) | J8: =IFERROR(AVERAGEIF(ISCAM_Score!$C$4:$C$177,A8,ISCAM_Score!$M$4:$M$177),0) | K8: =IFERROR(AVERAGEIF(ISCAM_Score!$C$4:$C$177,A8,ISCAM_Score!$N$4:$N$177),0) | L8: =IFERROR(AVERAGEIF(ISCAM_Score!$C$4:$C$177,A8,ISCAM_Score!$O$4:$O$177),0) | M8: =IFERROR(AVERAGE(B8:L8),0)
A9: PASCO | B9: =IFERROR(AVERAGEIF(ISCAM_Score!$C$4:$C$177,A9,ISCAM_Score!$E$4:$E$177),0) | C9: =IFERROR(AVERAGEIF(MATRIZ_174!$C$3:$C$176,A9,SCORECARDS!$H$3:$H$176),0) | D9: =IFERROR(AVERAGEIF(ISCAM_Score!$C$4:$C$177,A9,ISCAM_Score!$G$4:$G$177),0) | E9: =IFERROR(AVERAGEIF(ISCAM_Score!$C$4:$C$177,A9,ISCAM_Score!$H$4:$H$177),0) | F9: =IFERROR(AVERAGEIF(MATRIZ_174!$C$3:$C$176,A9,SCORECARDS!$I$3:$I$176),0) | G9: =IFERROR(AVERAGEIF(MATRIZ_174!$C$3:$C$176,A9,SCORECARDS!$J$3:$J$176),0) | H9: =IFERROR(AVERAGEIF(ISCAM_Score!$C$4:$C$177,A9,ISCAM_Score!$K$4:$K$177),0) | I9: =IFERROR(AVERAGEIF(ISCAM_Score!$C$4:$C$177,A9,ISCAM_Score!$L$4:$L$177),0) | J9: =IFERROR(AVERAGEIF(ISCAM_Score!$C$4:$C$177,A9,ISCAM_Score!$M$4:$M$177),0) | K9: =IFERROR(AVERAGEIF(ISCAM_Score!$C$4:$C$177,A9,ISCAM_Score!$N$4:$N$177),0) | L9: =IFERROR(AVERAGEIF(ISCAM_Score!$C$4:$C$177,A9,ISCAM_Score!$O$4:$O$177),0) | M9: =IFERROR(AVERAGE(B9:L9),0)
A10: PIURA | B10: =IFERROR(AVERAGEIF(ISCAM_Score!$C$4:$C$177,A10,ISCAM_Score!$E$4:$E$177),0) | C10: =IFERROR(AVERAGEIF(MATRIZ_174!$C$3:$C$176,A10,SCORECARDS!$H$3:$H$176),0) | D10: =IFERROR(AVERAGEIF(ISCAM_Score!$C$4:$C$177,A10,ISCAM_Score!$G$4:$G$177),0) | E10: =IFERROR(AVERAGEIF(ISCAM_Score!$C$4:$C$177,A10,ISCAM_Score!$H$4:$H$177),0) | F10: =IFERROR(AVERAGEIF(MATRIZ_174!$C$3:$C$176,A10,SCORECARDS!$I$3:$I$176),0) | G10: =IFERROR(AVERAGEIF(MATRIZ_174!$C$3:$C$176,A10,SCORECARDS!$J$3:$J$176),0) | H10: =IFERROR(AVERAGEIF(ISCAM_Score!$C$4:$C$177,A10,ISCAM_Score!$K$4:$K$177),0) | I10: =IFERROR(AVERAGEIF(ISCAM_Score!$C$4:$C$177,A10,ISCAM_Score!$L$4:$L$177),0) | J10: =IFERROR(AVERAGEIF(ISCAM_Score!$C$4:$C$177,A10,ISCAM_Score!$M$4:$M$177),0) | K10: =IFERROR(AVERAGEIF(ISCAM_Score!$C$4:$C$177,A10,ISCAM_Score!$N$4:$N$177),0) | L10: =IFERROR(AVERAGEIF(ISCAM_Score!$C$4:$C$177,A10,ISCAM_Score!$O$4:$O$177),0) | M10: =IFERROR(AVERAGE(B10:L10),0)
A11: AYACUCHO | B11: =IFERROR(AVERAGEIF(ISCAM_Score!$C$4:$C$177,A11,ISCAM_Score!$E$4:$E$177),0) | C11: =IFERROR(AVERAGEIF(MATRIZ_174!$C$3:$C$176,A11,SCORECARDS!$H$3:$H$176),0) | D11: =IFERROR(AVERAGEIF(ISCAM_Score!$C$4:$C$177,A11,ISCAM_Score!$G$4:$G$177),0) | E11: =IFERROR(AVERAGEIF(ISCAM_Score!$C$4:$C$177,A11,ISCAM_Score!$H$4:$H$177),0) | F11: =IFERROR(AVERAGEIF(MATRIZ_174!$C$3:$C$176,A11,SCORECARDS!$I$3:$I$176),0) | G11: =IFERROR(AVERAGEIF(MATRIZ_174!$C$3:$C$176,A11,SCORECARDS!$J$3:$J$176),0) | H11: =IFERROR(AVERAGEIF(ISCAM_Score!$C$4:$C$177,A11,ISCAM_Score!$K$4:$K$177),0) | I11: =IFERROR(AVERAGEIF(ISCAM_Score!$C$4:$C$177,A11,ISCAM_Score!$L$4:$L$177),0) | J11: =IFERROR(AVERAGEIF(ISCAM_Score!$C$4:$C$177,A11,ISCAM_Score!$M$4:$M$177),0) | K11: =IFERROR(AVERAGEIF(ISCAM_Score!$C$4:$C$177,A11,ISCAM_Score!$N$4:$N$177),0) | L11: =IFERROR(AVERAGEIF(ISCAM_Score!$C$4:$C$177,A11,ISCAM_Score!$O$4:$O$177),0) | M11: =IFERROR(AVERAGE(B11:L11),0)
A12: PUNO | B12: =IFERROR(AVERAGEIF(ISCAM_Score!$C$4:$C$177,A12,ISCAM_Score!$E$4:$E$177),0) | C12: =IFERROR(AVERAGEIF(MATRIZ_174!$C$3:$C$176,A12,SCORECARDS!$H$3:$H$176),0) | D12: =IFERROR(AVERAGEIF(ISCAM_Score!$C$4:$C$177,A12,ISCAM_Score!$G$4:$G$177),0) | E12: =IFERROR(AVERAGEIF(ISCAM_Score!$C$4:$C$177,A12,ISCAM_Score!$H$4:$H$177),0) | F12: =IFERROR(AVERAGEIF(MATRIZ_174!$C$3:$C$176,A12,SCORECARDS!$I$3:$I$176),0) | G12: =IFERROR(AVERAGEIF(MATRIZ_174!$C$3:$C$176,A12,SCORECARDS!$J$3:$J$176),0) | H12: =IFERROR(AVERAGEIF(ISCAM_Score!$C$4:$C$177,A12,ISCAM_Score!$K$4:$K$177),0) | I12: =IFERROR(AVERAGEIF(ISCAM_Score!$C$4:$C$177,A12,ISCAM_Score!$L$4:$L$177),0) | J12: =IFERROR(AVERAGEIF(ISCAM_Score!$C$4:$C$177,A12,ISCAM_Score!$M$4:$M$177),0) | K12: =IFERROR(AVERAGEIF(ISCAM_Score!$C$4:$C$177,A12,ISCAM_Score!$N$4:$N$177),0) | L12: =IFERROR(AVERAGEIF(ISCAM_Score!$C$4:$C$177,A12,ISCAM_Score!$O$4:$O$177),0) | M12: =IFERROR(AVERAGE(B12:L12),0)
A13: APURIMAC | B13: =IFERROR(AVERAGEIF(ISCAM_Score!$C$4:$C$177,A13,ISCAM_Score!$E$4:$E$177),0) | C13: =IFERROR(AVERAGEIF(MATRIZ_174!$C$3:$C$176,A13,SCORECARDS!$H$3:$H$176),0) | D13: =IFERROR(AVERAGEIF(ISCAM_Score!$C$4:$C$177,A13,ISCAM_Score!$G$4:$G$177),0) | E13: =IFERROR(AVERAGEIF(ISCAM_Score!$C$4:$C$177,A13,ISCAM_Score!$H$4:$H$177),0) | F13: =IFERROR(AVERAGEIF(MATRIZ_174!$C$3:$C$176,A13,SCORECARDS!$I$3:$I$176),0) | G13: =IFERROR(AVERAGEIF(MATRIZ_174!$C$3:$C$176,A13,SCORECARDS!$J$3:$J$176),0) | H13: =IFERROR(AVERAGEIF(ISCAM_Score!$C$4:$C$177,A13,ISCAM_Score!$K$4:$K$177),0) | I13: =IFERROR(AVERAGEIF(ISCAM_Score!$C$4:$C$177,A13,ISCAM_Score!$L$4:$L$177),0) | J13: =IFERROR(AVERAGEIF(ISCAM_Score!$C$4:$C$177,A13,ISCAM_Score!$M$4:$M$177),0) | K13: =IFERROR(AVERAGEIF(ISCAM_Score!$C$4:$C$177,A13,ISCAM_Score!$N$4:$N$177),0) | L13: =IFERROR(AVERAGEIF(ISCAM_Score!$C$4:$C$177,A13,ISCAM_Score!$O$4:$O$177),0) | M13: =IFERROR(AVERAGE(B13:L13),0)
A14: MADRE DE DIOS | B14: =IFERROR(AVERAGEIF(ISCAM_Score!$C$4:$C$177,A14,ISCAM_Score!$E$4:$E$177),0) | C14: =IFERROR(AVERAGEIF(MATRIZ_174!$C$3:$C$176,A14,SCORECARDS!$H$3:$H$176),0) | D14: =IFERROR(AVERAGEIF(ISCAM_Score!$C$4:$C$177,A14,ISCAM_Score!$G$4:$G$177),0) | E14: =IFERROR(AVERAGEIF(ISCAM_Score!$C$4:$C$177,A14,ISCAM_Score!$H$4:$H$177),0) | F14: =IFERROR(AVERAGEIF(MATRIZ_174!$C$3:$C$176,A14,SCORECARDS!$I$3:$I$176),0) | G14: =IFERROR(AVERAGEIF(MATRIZ_174!$C$3:$C$176,A14,SCORECARDS!$J$3:$J$176),0) | H14: =IFERROR(AVERAGEIF(ISCAM_Score!$C$4:$C$177,A14,ISCAM_Score!$K$4:$K$177),0) | I14: =IFERROR(AVERAGEIF(ISCAM_Score!$C$4:$C$177,A14,ISCAM_Score!$L$4:$L$177),0) | J14: =IFERROR(AVERAGEIF(ISCAM_Score!$C$4:$C$177,A14,ISCAM_Score!$M$4:$M$177),0) | K14: =IFERROR(AVERAGEIF(ISCAM_Score!$C$4:$C$177,A14,ISCAM_Score!$N$4:$N$177),0) | L14: =IFERROR(AVERAGEIF(ISCAM_Score!$C$4:$C$177,A14,ISCAM_Score!$O$4:$O$177),0) | M14: =IFERROR(AVERAGE(B14:L14),0)
... A17: OTROS | B17: =IFERROR(AVERAGEIF(ISCAM_Score!$C$4:$C$177,A17,ISCAM_Score!$E$4:$E$177),0) | C17: =IFERROR(AVERAGEIF(MATRIZ_174!$C$3:$C$176,A17,SCORECARDS!$H$3:$H$176),0) | D17: =IFERROR(AVERAGEIF(ISCAM_Score!$C$4:$C$177,A17,ISCAM_Score!$G$4:$G$177),0) | E17: =IFERROR(AVERAGEIF(ISCAM_Score!$C$4:$C$177,A17,ISCAM_Score!$H$4:$H$177),0) | F17: =IFERROR(AVERAGEIF(MATRIZ_174!$C$3:$C$176,A17,SCORECARDS!$I$3:$I$176),0) | G17: =IFERROR(AVERAGEIF(MATRIZ_174!$C$3:$C$176,A17,SCORECARDS!$J$3:$J$176),0) | H17: =IFERROR(AVERAGEIF(ISCAM_Score!$C$4:$C$177,A17,ISCAM_Score!$K$4:$K$177),0) | I17: =IFERROR(AVERAGEIF(ISCAM_Score!$C$4:$C$177,A17,ISCAM_Score!$L$4:$L$177),0) | J17: =IFERROR(AVERAGEIF(ISCAM_Score!$C$4:$C$177,A17,ISCAM_Score!$M$4:$M$177),0) | K17: =IFERROR(AVERAGEIF(ISCAM_Score!$C$4:$C$177,A17,ISCAM_Score!$N$4:$N$177),0) | L17: =IFERROR(AVERAGEIF(ISCAM_Score!$C$4:$C$177,A17,ISCAM_Score!$O$4:$O$177),0) | M17: =IFERROR(AVERAGE(B17:L17),0)
A20: LEYENDA — NIVELES DE CUMPLIMIENTO
A21: 🟢 Verde (0.67–1.00) — Cumplimiento adecuado
A22: 🟡 Amarillo (0.34–0.66) — Brecha moderada
A23: 🔴 Rojo (0.00–0.33) — Brecha crítica
A24: ⬜ Gris (0.00) — Sin dato capturado
A26: NOTA: D2/D5/D6 provienen de SCORECARDS (carga del Instrumento 2); D1, D3, D4 y D7–D11 de ISCAM_Score. Sin dato = 0 = ⬜ gris (la ausencia de dato no implica cumplimiento). Corregido 2026-10-14.
A28: CORTE POR PRODUCTO — paridad café/cacao (sin sesgo)
A29: Producto | B29: N.° orgs | C29: ISA-EUDR | D29: ISA-PV | E29: ISA-Completo | F29: IP | G29: IV | H29: RE
A30: CAFÉ | B30: =COUNTIF(MATRIZ_174!$D$3:$D$176,A30) | C30: =IFERROR(AVERAGEIF(MATRIZ_174!$D$3:$D$176,A30,ISCAM_Score!$AK$4:$AK$177),0) | D30: =IFERROR(AVERAGEIF(MATRIZ_174!$D$3:$D$176,A30,ISCAM_Score!$AI$4:$AI$177),0) | E30: =IFERROR(AVERAGEIF(MATRIZ_174!$D$3:$D$176,A30,ISCAM_Score!$AL$4:$AL$177),0) | F30: =IFERROR(AVERAGEIF(MATRIZ_174!$D$3:$D$176,A30,ISCAM_Score!$Z$4:$Z$177),0) | G30: =IFERROR(AVERAGEIF(MATRIZ_174!$D$3:$D$176,A30,ISCAM_Score!$AA$4:$AA$177),0) | H30: =IFERROR(AVERAGEIF(MATRIZ_174!$D$3:$D$176,A30,ISCAM_Score!$AB$4:$AB$177),0)
A31: CACAO | B31: =COUNTIF(MATRIZ_174!$D$3:$D$176,A31) | C31: =IFERROR(AVERAGEIF(MATRIZ_174!$D$3:$D$176,A31,ISCAM_Score!$AK$4:$AK$177),0) | D31: =IFERROR(AVERAGEIF(MATRIZ_174!$D$3:$D$176,A31,ISCAM_Score!$AI$4:$AI$177),0) | E31: =IFERROR(AVERAGEIF(MATRIZ_174!$D$3:$D$176,A31,ISCAM_Score!$AL$4:$AL$177),0) | F31: =IFERROR(AVERAGEIF(MATRIZ_174!$D$3:$D$176,A31,ISCAM_Score!$Z$4:$Z$177),0) | G31: =IFERROR(AVERAGEIF(MATRIZ_174!$D$3:$D$176,A31,ISCAM_Score!$AA$4:$AA$177),0) | H31: =IFERROR(AVERAGEIF(MATRIZ_174!$D$3:$D$176,A31,ISCAM_Score!$AB$4:$AB$177),0)
A32: SIN PRODUCTO REGISTRADO | B32: =COUNTBLANK(MATRIZ_174!$D$3:$D$176) | C32: =IFERROR(AVERAGEIF(MATRIZ_174!$D$3:$D$176,"",ISCAM_Score!$AK$4:$AK$177),0) | D32: =IFERROR(AVERAGEIF(MATRIZ_174!$D$3:$D$176,"",ISCAM_Score!$AI$4:$AI$177),0) | E32: =IFERROR(AVERAGEIF(MATRIZ_174!$D$3:$D$176,"",ISCAM_Score!$AL$4:$AL$177),0) | F32: =IFERROR(AVERAGEIF(MATRIZ_174!$D$3:$D$176,"",ISCAM_Score!$Z$4:$Z$177),0) | G32: =IFERROR(AVERAGEIF(MATRIZ_174!$D$3:$D$176,"",ISCAM_Score!$AA$4:$AA$177),0) | H32: =IFERROR(AVERAGEIF(MATRIZ_174!$D$3:$D$176,"",ISCAM_Score!$AB$4:$AB$177),0)
A34: Chequeo de paridad | B34: =IF(OR(NOT(ISNUMBER(E30)),NOT(ISNUMBER(E31))),"⏳ Sin datos suficientes para evaluar paridad",IF(ABS(E30-E31)<=5,"✔ Sin brecha café/cacao (≤5 pts en ISA-Completo)","⚠ Brecha café/cacao >5 pts en ISA-Completo — revisar sesgo antes de publicar"))
A35: Regla: brecha máxima aceptable de 5 puntos de ISA-Completo entre café y cacao. Si se supera, revisar sesgo de redacción del instrumento o de muestreo antes de publicar resultados.
