Workbook

Sheet README
B1: README — Base de organizaciones agrarias por RUC (SUNAT · OECE/RNP · MIDAGRI-PPA · Exportaciones FOB)
B2: 1. CONTENIDO DEL LIBRO Y DE CADA PESTAÑA
B3: Pestaña | C3: Contenido | D3: Archivo / fuente de origen | E3: Filas de datos | F3: RUCs únicos | G3: Rango
B4: README | C4: Esta hoja: documentación del libro, metodología, tratamiento y diccionario de atributos. | D4: — | G4: —
B5: b1 | C5: Hoja preexistente del libro (no modificada). 6 organizaciones con datos de intervención 2025: producto, sede/ubigeo, certificados, beneficiarios, ventas 2018-2025 y comprobantes 2025. | D5: Fuente interna del libro (no documentada en fuentes_urls.md) | E5: =COUNTA('b1'!A2:A7) | F5: {=ROWS(_xlfn.UNIQUE(TRIM('b1'!AD2:AD7&"")))} | G5: b1!A1:AE7
B6: b2 | C6: Hoja preexistente del libro (no modificada). Histórico por organización 2018-2025: intervención, beneficiarios por sexo, asistencia técnica/talleres, ventas nacionales y de exportación, comprobantes. Fila 1 = numeración de columnas; encabezados en fila 2. | D6: Fuente interna del libro (no documentada en fuentes_urls.md) | E6: =COUNTA('b2'!A3:A680) | F6: {=ROWS(_xlfn.UNIQUE(_xlfn._xlws.FILTER(TRIM('b2'!DI3:DI680&""),TRIM('b2'!DI3:DI680&"")<>"")))} | G6: b2!A1:DK680
B7: b3 | C7: Hoja preexistente del libro (no modificada). Ficha de 25 organizaciones cafetaleras con PAC: socios, hectáreas, producción y cosecha 2026, altitud, variedades, certificaciones, calidad, avance EUDR y contactos. | D7: Fuente interna del libro (no documentada en fuentes_urls.md) | E7: =COUNTA('b3'!E2:E26) | F7: {=ROWS(_xlfn.UNIQUE(TRIM('b3'!E2:E26&"")))} | G7: b3!A1:AW26
B8: RUC_ID | C8: Lista maestra RUC + razón social, generada por fórmula (VSTACK) desde b1+b2+b3 (registro interno del programa). 596 RUCs. No incluye 20404057805 (ACOPAGRO), que sí está en rucs.txt/RUC_CONSULTAMASIVA (universo externo de consulta) pero no aparece en b1/b2/b3. | D8: Hoja preexistente del libro / rucs.txt (universo de consulta) | E8: =COUNTA(RUC_ID!A2:A597) | F8: =ROWS(_xlfn.UNIQUE(RUC_ID!A2:A597)) | G8: RUC_ID!A1:B597
B9: RUC_CONSULTAMASIVA | C9: Ficha SUNAT completa por RUC (24 campos): contribuyente, estado/condición, fechas, ubicación, dirección, comercio exterior, CIIU, regímenes. | D9: 9 archivos RM20260919*.txt — Consulta RUC múltiple SUNAT (19/09/2026) | E9: =COUNTA(RUC_CONSULTAMASIVA!A2:A598) | F9: =ROWS(_xlfn.UNIQUE(RUC_CONSULTAMASIVA!A2:A598)) | G9: RUC_CONSULTAMASIVA!A1:X598
B10: RUC_OECE | C10: Ficha de proveedor OECE por RUC: datos SUNAT resumidos + teléfono, email y código de registro RNP. | D10: ruc-oece-ficha.txt (consulta 20/09/2026) | E10: =COUNTA(RUC_OECE!A2:A598) | F10: =ROWS(_xlfn.UNIQUE(RUC_OECE!A2:A598)) | G10: RUC_OECE!A1:L598
B11: RUC_OECE_PERSONAS | C11: Órganos de administración, representantes legales y socios por RUC (DNI, nombre, cargo, fecha de ingreso). Contiene datos personales. | D11: ruc-oece-personas.txt (consulta 20/09/2026) | E11: =COUNTA(RUC_OECE_PERSONAS!A2:A816) | F11: =ROWS(_xlfn.UNIQUE(RUC_OECE_PERSONAS!A2:A816)) | G11: RUC_OECE_PERSONAS!A1:I816
B12: RNP | C12: Subconjunto de RUC_OECE: solo proveedores inscritos en el Registro Nacional de Proveedores (con código de registro). | D12: ruc-oece-ficha-inscritos-rnp.txt (consulta 20/09/2026) | E12: =COUNTA(RNP!A2:A156) | F12: =ROWS(_xlfn.UNIQUE(RNP!A2:A156)) | G12: RNP!A1:L156
B13: RUC_PPA | C13: Inscripción en el Padrón de Productores Agrarios (MIDAGRI) y nombre registrado. | D13: ruc-padron-ppa.txt (consulta 20/09/2026) | E13: =COUNTA(RUC_PPA!A2:A598) | F13: =ROWS(_xlfn.UNIQUE(RUC_PPA!A2:A598)) | G13: RUC_PPA!A1:D598
B14: RUC_FOB | C14: Detalle de exportaciones: una fila por RUC-anio-mes-aduana-agente-pais con valor FOB (USD). Ene-2025 a may-2026 (fuente original, 597 RUC) mas 2024 completo para 33 RUC que ya exportaban en 2025-2026 (fuente historica 2010-2025, ver CTL_FUENTE_CONSULTA fila 8). El resto del universo no tiene 2024. Numero de DUA y canal de control (verde/rojo/naranja) por operacion en RUC_FOB_DUA (pestana nueva, ver CTL_FUENTE_CONSULTA fila 9) -- NO es la partida arancelaria, esa sigue bloqueada por captcha. | D14: ruc-exportaciones-fob.txt (consulta 19/09/2026) mas SUNAT exportaciones 2010-2025.xlsx (archivo aportado por el usuario, cargado 17/09/2026, agregado el 23/09/2026) | E14: =COUNTA(RUC_FOB!A2:A5000) | F14: {=ROWS(_xlfn.UNIQUE(_xlfn._xlws.FILTER(RUC_FOB!A2:A5000,RUC_FOB!A2:A5000<>"")))} | G14: RUC_FOB!A1:K959
B15: RUC_FOB (2) | C15: Resumen de RUC_FOB agrupado por RUC (una fila por RUC), calculado con formulas; fila 69 = totales y fila 70 = control contra el detalle (fila 68 queda en blanco a proposito). Estas dos filas NO son RUCs: estan resaltadas en amarillo con nota en A69; cualquier suma de columna (p.ej. fob_total_usd) debe acotarse a filas 2:67, nunca a la columna completa ni a un rango que incluya 68:70, o se duplica el total. | D15: Derivada de RUC_FOB | E15: =COUNTA('RUC_FOB (2)'!A2:A67) | F15: {=ROWS(_xlfn.UNIQUE('RUC_FOB (2)'!A2:A67))} | G15: RUC_FOB (2)'!A1:M70
B18: 2. METODOLOGÍA DE ACCESO A LOS DATASETS
B19: Universo: rucs.txt (597 RUCs únicos; fuentes_urls.md indica 598). Cada fuente se consultó RUC por RUC sobre ese universo y el resultado se exportó a .txt (campo fecha_consulta en cada fila). Las URLs son las documentadas en fuentes_urls.md como fuentes oficiales para reconstruir o ampliar cada dato.
B20: Dataset (pestaña) | C20: Institución / sistema | D20: Forma de acceso | E20: Fecha de consulta | F20: Fuentes oficiales / endpoints para reconstruir o ampliar | G20: Limitaciones
B21: rucs.txt (RUC_ID) | C21: Input interno | D21: Lista entregada: define el universo de cooperativas y asociaciones agrarias a cruzar | E21: — | F21: No es un dataset público; es la base de partida | G21: Solo contiene el número de RUC
B22: RM20260919*.txt (RUC_CONSULTAMASIVA) | C22: SUNAT — Consulta RUC | D22: Consulta múltiple de RUC en SUNAT, en lotes de hasta 100 RUCs; descarga en .txt separado por '|' (9 archivos) | E22: 19/09/2026 | F22: https://e.sunat.gob.pe/ (formulario web) · APIs de terceros: https://openruc.com/api/ruc/{ruc}, https://docs.apisunat.pe/consulta/sunat-ruc, https://docs.apiperu.dev/referencia/consultar-ruc/ | G22: Formulario con CAPTCHA; no hay API oficial de descarga masiva
B23: ruc-oece-ficha.txt (RUC_OECE) | C23: OECE — ficha de proveedor | D23: GET https://eap.oece.gob.pe/ficha-proveedor-cns/1.0/ficha/{ruc}/resumen (JSON, sin captcha ni sesión — accesible por fetch directo, confirmado en vivo 20/09/2026) más GET https://eap.oece.gob.pe/perfilprov-bus/1.0/ficha/{ruc} para teléfono/email. La misma respuesta trae también la conformación societaria completa (representantes, órganos de administración, socios) con DNI — alimenta a la vez RUC_OECE_PERSONAS y RNP. Ver identidad-fiscal/api/src/ingest/oece-ficha-connector.ts (repo Rastro/appsperu). | E23: 20/09/2026 | F23: https://eap.oece.gob.pe/ficha-proveedor-cns/1.0/ficha (endpoint real usado, no documentado oficialmente por OECE) · https://www.gob.pe/oece · https://contratacionesabiertas.oece.gob.pe · APIs RUC de terceros no usadas: openruc.com, apisunat, apiperu, json.pe | G23: No es una API pública documentada por OECE; depende de que no cambien la ruta ni agreguen autenticación. Teléfono/email solo cuando el RUC figura como proveedor.
B24: ruc-oece-personas.txt (RUC_OECE_PERSONAS) | C24: OECE / RNP — directivos y representantes | D24: Misma consulta que RUC_OECE (GET .../ficha-proveedor-cns/1.0/ficha/{ruc}/resumen): la respuesta JSON trae órganos de administración, representantes y socios con DNI en el mismo payload, sin llamada aparte. | E24: 20/09/2026 | F24: https://eap.oece.gob.pe/ficha-proveedor-cns/1.0/ficha (mismo endpoint que RUC_OECE) · https://contratacionesabiertas.oece.gob.pe (OCDS, no cubre esta estructura) · https://www.gob.pe/institucion/oece/tema/transparencia-y-datos-abiertos · APIs de terceros no usadas: Croma, Apify | G24: No es una API pública documentada por OECE. Contiene datos personales (DNI): uso interno.
B25: ruc-oece-ficha-inscritos-rnp.txt (RNP) | C25: RNP — Registro Nacional de Proveedores | D25: Derivado del mismo payload de RUC_OECE (GET .../ficha-proveedor-cns/1.0/ficha/{ruc}/resumen): se filtra a los RUC cuyo codigo_registro viene no vacío. No requiere consulta aparte ni CAPTCHA — la nota anterior de CAPTCHA correspondía al portal web público del RNP, no al endpoint realmente usado. | E25: 20/09/2026 | F25: https://eap.oece.gob.pe/ficha-proveedor-cns/1.0/ficha (mismo endpoint que RUC_OECE) · portal web con CAPTCHA no usado: https://www.rnp.gob.pe/Constancia/RNP_Constancia/ConsultaRuc.asp · https://www.rnp.gob.pe/Constancia/RNP_Constancia/ConsultaRucEyC.asp | G25: No es una API pública documentada por OECE (comparte limitación con RUC_OECE).
B26: ruc-padron-ppa.txt (RUC_PPA) | C26: MIDAGRI — Padrón de Productores Agrarios | D26: GET https://gateway.midagri.gob.pe/sisppa/api/services/app/Consulta/GetNombreConsulta?codDocumento=6&Documento={ruc} (JSON, API interna ABP Framework, sin captcha ni sesión — accesible por fetch directo, confirmado en vivo 20/09/2026). codDocumento=6 = RUC, confirmado en vivo probando valores. Ver identidad-fiscal/api/src/ingest/padron-ppa-connector.ts (repo Rastro/appsperu). | E26: 20/09/2026 | F26: https://gateway.midagri.gob.pe/sisppa/api/services/app/Consulta/GetNombreConsulta (endpoint real usado, no documentado oficialmente por MIDAGRI) · https://ppa.midagri.gob.pe · ficha técnica PDF · trámite gob.pe | G26: No es una API pública documentada por MIDAGRI; depende de que no cambien la ruta del gateway ABP ni agreguen autenticación.
B27: ruc-exportaciones-fob.txt (RUC_FOB) | C27: SUNAT — Aduanas (exportaciones) | D27: GET por RUC y año contra el endpoint HTML "Consulta por Importador/Exportador" de Aduanet (no es una API pública documentada, pero no está bloqueado para fetch directo — confirmado en vivo el 19/09/2026). Filtra régimen=40 (exportación definitiva). El parámetro de año no es el año real: hay que mandar año-1992 (offset descubierto empíricamente probando valores contra resultados conocidos). Sin resultado en JSON: se parsea el HTML de respuesta. Sin bulk: una consulta por RUC-año, con pausa de ~400ms entre pedidos. Ver identidad-fiscal/api/src/ingest/exportaciones-fob-connector.ts en el repo Rastro (appsperu) para la implementación de referencia. | E27: 19/09/2026 | F27: http://www.aduanet.gob.pe/cl-ad-itconsultadwh/ieITS01Alias (endpoint real usado, no documentado oficialmente por SUNAT/Aduanas) · https://www.sunat.gob.pe/estadisticasestudios/exportaciones.html · https://www.sunat.gob.pe/estad-comExt/modelo_web/informes/anuarios/2024/cdro_33.xlsx · https://ww3.sunat.gob.pe/servlet/HRGDecExp?opcion=aduanaexp&codr=50 · http://www.aduanet.gob.pe/cl-ad-itestadispartida/resumenPPaisS01Alias · https://datosabiertos.gob.pe | G27: No es una API pública documentada — es un endpoint HTML interno de Aduanet que resultó no estar bloqueado para fetch directo (a diferencia de *.sunat.gob.pe). Depende de que Aduanet no cambie esa ruta ni bloquee el acceso; el offset de año (-1992) y el código de régimen (40) tampoco están documentados por SUNAT. Los anuarios/cuadros oficiales (URLs alternativas de arriba) solo dan totales por aduana/país, no por RUC.
B28: ruc-contratacion-estatal.txt (RUC_CONTRATACION) | C28: OECE / Open Contracting Partnership (mirror OCDS) | D28: Descarga bulk anual de OCDS republicada por Open Contracting Partnership; filtrada por los 597 RUC del universo (script oece_contrataciones_por_ruc.py) | E28: 23/09/2026 | F28: https://data.open-contracting.org/en/publication/135 (bulk anual) · https://contratacionesabiertas.oece.gob.pe (endpoint search?supplier= no filtra por proveedor) | G28: Solo 10 de 597 RUC tienen procesos/contratos; el endpoint de búsqueda de OECE no filtra por proveedor, se usó el bulk anual como vía verificada
B31: 2.1 Endpoints públicos directos e indirectos
B32: Directo = portal, servicio o archivo oficial de la entidad que produce el dato (SUNAT, OECE, RNP, MIDAGRI, PNDA). Indirecto = servicio de terceros que replica, indexa o consulta la fuente oficial (OpenRUC, APISUNAT, APIperu, json.pe, Croma, Apify). Fuente: fuentes_urls.md.
B33: Dataset (pestañas) | C33: Tipo | D33: Recurso | E33: Endpoint / URL | F33: Método y acceso | G33: Formato / notas
B34: RUC_CONSULTAMASIVA · RUC_OECE · RNP (ficha RUC) | C34: Directo | D34: SUNAT — Consulta RUC (web oficial) | E34: https://e.sunat.gob.pe/ | F34: Web · formulario con CAPTCHA · consulta individual y múltiple | G34: HTML / descarga .txt (consulta múltiple)
B35: RUC_CONSULTAMASIVA · RUC_OECE · RNP (ficha RUC) | C35: Indirecto | D35: OpenRUC — API RUC SUNAT (Latinfo) | E35: GET https://openruc.com/api/ruc/{ruc} | F35: API REST GET · sin API key · gratis | G35: JSON: razón social, estado, condición, dirección
B36: RUC_CONSULTAMASIVA · RUC_OECE · RNP (ficha RUC) | C36: Indirecto | D36: APISUNAT — Consulta RUC | E36: GET https://dev.apisunat.pe/api/v1/business/ruc/{RUC} (doc: https://docs.apisunat.pe/consulta/sunat-ruc) | F36: API REST GET · requiere API key | G36: JSON
B37: RUC_CONSULTAMASIVA · RUC_OECE · RNP (ficha RUC) | C37: Indirecto | D37: APIperu — Consultar RUC | E37: POST https://api.apiperu.dev/ruc (doc: https://docs.apiperu.dev/referencia/consultar-ruc/) | F37: API REST POST · token · plan gratuito | G37: JSON (ficha RUC completa)
B38: RUC_CONSULTAMASIVA · RUC_OECE · RNP (ficha RUC) | C38: Indirecto | D38: json.pe — Consulta RUC | E38: POST https://api.json.pe/api/ruc (doc: https://docs.json.pe/api-consulta/endpoint/ruc) | F38: API REST POST · requiere token | G38: JSON
B39: RUC_OECE · RUC_OECE_PERSONAS | C39: Directo | D39: OECE — Portal de Contrataciones Abiertas (OCDS) | E39: https://contratacionesabiertas.oece.gob.pe | F39: Descarga masiva (bulk) · sin autenticación · actualización diaria | G39: JSON / CSV / Excel (OCDS), procesos 2003–presente
B40: RUC_OECE · RUC_OECE_PERSONAS | C40: Directo | D40: OECE — Transparencia y datos abiertos | E40: https://www.gob.pe/institucion/oece/tema/transparencia-y-datos-abiertos | F40: Web · enlaces a estadísticas, BI y observatorio de precios | G40: HTML / descargas
B41: RUC_OECE · RUC_OECE_PERSONAS · RNP | C41: Directo | D41: OECE — SEACE / Registro de proveedores | E41: https://www.gob.pe/oece | F41: Web · consulta por RUC (ficha de proveedor con directivos) | G41: HTML · sin bulk
B42: RUC_OECE · RUC_OECE_PERSONAS | C42: Indirecto | D42: Croma API — OECE Contrataciones | E42: POST https://api.croma.run/pe/oece/processes-search/v1 | F42: API REST POST · búsqueda por RUC proveedor, entidad, texto, categoría, fechas | G42: JSON (dataset indexado)
B43: RUC_OECE · RUC_OECE_PERSONAS | C43: Indirecto | D43: Apify — Peru OECE Tender Scraper | E43: https://apify.com/publicmoney/peru-oece-scraper | F43: Actor/scraper sobre contratacionesabiertas.oece.gob.pe · cuenta Apify | G43: JSON / CSV / Excel
B44: RNP | C44: Directo | D44: RNP — Consulta RUC | E44: https://www.rnp.gob.pe/Constancia/RNP_Constancia/ConsultaRuc.asp | F44: Web · formulario con CAPTCHA · uno por uno | G44: HTML (verificación de inscripción)
... B58: HECHO_CONTRATACION_ESTATAL | C58: Directo (bulk, republicado por Open Contracting Partnership) | D58: OCDS bulk anual (mirror OCP de OECE Contrataciones Abiertas) | E58: https://data.open-contracting.org/en/publication/135/download?name={año}.jsonl.gz | F58: Descarga directa por año (jsonl.gz) · sin autenticación · filtrado por RUC en script propio | G58: JSONL comprimido · OCDS; el endpoint search?supplier= de OECE no filtra por proveedor (2.75M+ resultados)
B60: 3. TRATAMIENTO DE LOS DATOS
B61: Paso | C61: Pestaña(s) | D61: Tratamiento aplicado
B62: 1 | C62: RUC_ID / rucs.txt | D62: Validación del universo: rucs.txt/RUC_CONSULTAMASIVA (universo externo, usado para consultar SUNAT/OECE/RNP/PPA/FOB) tiene 597 RUCs únicos de 11 dígitos, sin duplicados. RUC_ID es un universo DISTINTO por diseño: se genera con fórmula (VSTACK) desde b1+b2+b3 (registro interno del programa) y tiene 596 — no incluye 20404057805 (COOPERATIVA AGRARIA ACOPAGRO LTDA) porque esa organización no figura en b1/b2/b3, aunque sí fue consultada en SUNAT/OECE/etc. No es un error de carga: son dos universos que casi coinciden pero no son el mismo.
B63: 2 | C63: RUC_CONSULTAMASIVA | D63: Unión de los 9 archivos SUNAT (698 registros). Se eliminaron 101 duplicados idénticos entre archivos → 597 RUCs. Se normalizó la codificación (UTF-8 / Latin-1), se quitaron comillas externas y espacios sobrantes. Orden = el de los archivos.
B64: 3 | C64: RUC_OECE | D64: Carga de 597 RUCs ordenados por número. Contraste con SUNAT: 6 diferencias (5 razones sociales que en SUNAT vienen con comillas truncadas y 1 distrito truncado en OECE); se conservó el valor del archivo OECE. Campos sin dato (teléfono, email, código) quedan en blanco.
B65: 4 | C65: RNP | D65: Se verificó que el archivo de inscritos RNP es idéntico, fila por fila, a los 155 RUCs de RUC_OECE con código de registro.
B66: 5 | C66: RUC_OECE_PERSONAS | D66: Carga de 815 filas (139 RUCs) sin deduplicar: una misma persona puede figurar con varios roles o cargos. Se conservan DNI con ceros a la izquierda. Contiene datos personales: uso interno.
B67: 6 | C67: RUC_PPA | D67: Carga de 597 RUCs; los 597 figuran como registrados (true) y nombre_ppa coincide con la razón social de RUC_OECE.
B68: 7 | C68: RUC_FOB | D68: Carga de 958 operaciones (66 RUCs): 680 operaciones (64 RUCs) de la fuente original (ene-2025 a may-2026) mas 278 operaciones de 2024 para 33 RUC, agregadas el 23/09/2026 desde un archivo historico aportado por el usuario (ver CTL_FUENTE_CONSULTA fila 8; de esos 33, 2 RUC no tenian ninguna fila previa en RUC_FOB). mes y fob_usd como numeros (fob_usd con formato #,##0.00); RUC, anio y codigos de aduana/agente/pais como texto para conservar ceros a la izquierda.
B69: 8 | C69: RUC_FOB (2) | D69: Agrupacion por RUC con formulas sobre RUC_FOB (UNIQUE, SUMIFS, COUNTIFS, FILTER, TEXTJOIN, rango ampliado a 5000 desde el 23/09/2026): n de operaciones, FOB total y por anio, primer/ultimo periodo, paises, aduanas y agentes. Control (fila 70) = 0 contra el detalle.
B70: 9 | C70: Todas las cargadas | D70: Controles de calidad: suma de verificación de cada bloque contra el archivo original, conteo de filas y RUCs únicos, revisión de celdas vacías. RUC guardado como texto (11 dígitos). Formato común: encabezado en negrita con fondo azul claro, fila 1 inmovilizada y comentario de fuente en A1.
B71: 10 | C71: b1, b2, b3 | D71: Hojas preexistentes del libro: no fueron modificadas; solo se documentan aquí.
B72: 11 | C72: RUC_CONTRATACION | D72: Carga del archivo subido ruc-contratacion-estatal.txt (53 filas, 10 RUC de los 597). RUC y entidad_ruc guardados como texto. Se construyó HECHO_CONTRATACION_ESTATAL con fórmulas FILTER sobre esta pestaña y se agregó la fila 8 en CTL_FUENTE_CONSULTA.
B74: 4. ATRIBUTOS ADICIONALES AL RUC POR PESTAÑA
B75: Pestaña | C75: N° | D75: Atributo (columna) | E75: Descripción | F75: Tipo
B76: RUC_ID | C76: 1 | D76: RAZON SOCIAL | E76: Razón social de la organización | F76: Texto
B77: RUC_CONSULTAMASIVA | C77: 1 | D77: Nombre ó RazonSocial | E77: Razón social registrada en SUNAT | F77: Texto
B78: RUC_CONSULTAMASIVA | C78: 2 | D78: Tipo de Contribuyente | E78: Tipo (asociación, cooperativa, comunidad, S.A.C., etc.) | F78: Texto
B79: RUC_CONSULTAMASIVA | C79: 3 | D79: Profesion u Oficio | E79: Profesión u oficio (aplica a personas naturales) | F79: Texto
B80: RUC_CONSULTAMASIVA | C80: 4 | D80: Nombre Comercial | E80: Nombre comercial declarado | F80: Texto
B81: RUC_CONSULTAMASIVA | C81: 5 | D81: Condicion del Contribuyente | E81: HABIDO / NO HABIDO | F81: Texto
B82: RUC_CONSULTAMASIVA | C82: 6 | D82: Estado del Contribuyente | E82: ACTIVO, BAJA DE OFICIO, SUSPENSIÓN TEMPORAL, etc. | F82: Texto
B83: RUC_CONSULTAMASIVA | C83: 7 | D83: Fecha de Inscripcion | E83: Fecha de inscripción en el RUC (dd/mm/aaaa) | F83: Fecha (texto)
B84: RUC_CONSULTAMASIVA | C84: 8 | D84: Fecha de Inicio de Actividades | E84: Fecha de inicio de actividades (dd/mm/aaaa) | F84: Fecha (texto)
B85: RUC_CONSULTAMASIVA | C85: 9 | D85: Departamento | E85: Departamento del domicilio fiscal | F85: Texto
B86: RUC_CONSULTAMASIVA | C86: 10 | D86: Provincia | E86: Provincia del domicilio fiscal | F86: Texto
... B149: RUC_CONTRATACION | C149: — | D149: ocid, nivel_registro, entidad_ruc, entidad_nombre, objeto, monto, moneda, fecha, estado, metodo_contratacion, rol_en_proceso, fuente, fecha_consulta | E149: Identificador OCDS del proceso/contrato; nivel (proceso o contrato); entidad contratante; objeto y monto (PEN); fecha; estado; método de contratación; rol de la organización (tenderer/supplier) | F149: Mixto
B151: 5. ESTRUCTURA DE DATOS PROPUESTA POR RUC (máximo de atributos, priorizando lo más vigente y directo)
B152: Modelo con el RUC (11 dígitos, texto) como llave única: una tabla maestra con una fila por RUC (el 'golden record') y tablas satélite para los datos que tienen varias filas por RUC. Cada valor guarda su fuente y fecha, y se elige con reglas de prioridad explícitas.
B154: 5.1 Reglas de prioridad para elegir el valor vigente
B155: N° | C155: Regla | D155: Aplicación
B156: 1 | C156: Fuente directa antes que indirecta | D156: Un valor de SUNAT, OECE, RNP o MIDAGRI prevalece sobre OpenRUC, APISUNAT, APIperu, json.pe, Croma o Apify. Las indirectas solo rellenan vacíos y quedan marcadas como tales.
B157: 2 | C157: Entidad dueña del dato | D157: Datos tributarios y de ubicación: SUNAT. Proveedor del Estado, contacto y directivos: OECE/RNP. Productor agrario: MIDAGRI-PPA. Exportaciones: SUNAT-Aduanas. Datos del programa (socios, hectáreas, ventas, beneficiarios): registros internos b1/b2/b3.
B158: 3 | C158: Lo más reciente gana | D158: Entre fuentes del mismo nivel se toma la de fecha_consulta o fecha de corte más reciente. Si la fecha es la misma, se aplica la regla 2.
B159: 4 | C159: Valor informado antes que vacío | D159: Un valor vacío, '-' o '0' no reemplaza a uno informado. Se registra como 'sin dato' con su fuente.
B160: 5 | C160: Trazabilidad por atributo | D160: Cada atributo lleva {atributo}_fuente, {atributo}_tipo_fuente (directa/indirecta) y {atributo}_fecha. El histórico de valores reemplazados se guarda en HIST_ATRIBUTO.
B161: 6 | C161: Vigencia de relaciones | D161: En personas y cargos se marca vigente = SI para el último período por RUC, rol y cargo; los anteriores quedan con fecha_fin.
B162: 7 | C162: Caducidad y refresco | D162: Estado y condición SUNAT: mensual. RNP y OECE: trimestral o antes de un proceso. PPA: anual. Exportaciones: mensual. Datos del programa: por campaña o año. Se marca desactualizado si se supera el plazo.
B163: 8 | C163: Normalización de llaves | D163: RUC como texto de 11 dígitos sin espacios; DNI de 8 dígitos con ceros a la izquierda; ubigeo INEI de 6 dígitos; códigos de aduana, agente, país (ISO-2) y CIIU como texto.
B165: 5.2 Tablas del modelo
B166: Tabla | C166: Grano (1 fila por…) | D166: Llave | E166: Contenido principal | F166: Fuente directa prioritaria (alternativa) | G166: Pestañas actuales que la alimentan | H166: Pestaña construida
B167: DIM_ORGANIZACION (maestra) | C167: RUC | D167: ruc (PK) | E167: Identidad, estado/condición tributaria, ubicación, actividad, contacto, registros (RNP, PPA), ventas totales 2024-2025, indicadores resumidos de exportación, directivos y programa | F167: SUNAT Consulta RUC (OECE / APIs RUC) | G167: RUC_ID, RUC_CONSULTAMASIVA, RUC_OECE, RNP, RUC_PPA, RUC_FOB (2), b1, b2, b3 | H167: =IF(COUNTA(DIM_ORGANIZACION!A1)>0,"Sí — DIM_ORGANIZACION","No")
B168: REG_RNP | C168: RUC + código de registro | D168: ruc + codigo_registro | E168: Inscripción de proveedor, capítulo (bienes/servicios), vigencia, constancia | F168: RNP (OECE-SEACE) | G168: RNP, RUC_OECE | H168: =IF(COUNTA(REG_RNP!A1)>0,"Sí — REG_RNP","No")
B169: REG_PPA | C169: RUC + registro PPA | D169: ruc | E169: Condición de productor agrario, nombre registrado, fecha de empadronamiento | F169: MIDAGRI-PPA | G169: RUC_PPA | H169: =IF(COUNTA(REG_PPA!A1)>0,"Sí — REG_PPA","No")
B170: REL_PERSONA_CARGO | C170: RUC + DNI + rol + cargo + fecha_ingreso | D170: ruc + dni + rol + cargo + fecha_ingreso | E170: Directivos, representantes y socios, con tipo de órgano, fechas y bandera 'vigente' | F170: OECE/RNP (SUNAT representantes legales) | G170: RUC_OECE_PERSONAS | H170: =IF(COUNTA(REL_PERSONA_CARGO!A1)>0,"Sí — REL_PERSONA_CARGO","No")
B171: DIM_PERSONA | C171: DNI (o documento) | D171: dni (PK) | E171: Nombre normalizado de la persona (dato personal: acceso restringido) | F171: OECE/RNP (RENIEC si se autoriza) | G171: RUC_OECE_PERSONAS | H171: =IF(COUNTA(DIM_PERSONA!A1)>0,"Sí — DIM_PERSONA","No")
B172: HECHO_EXPORTACION | C172: RUC + año + mes + aduana + agente + país | D172: ruc + anio + mes + aduana_codigo + agente_codigo + pais_codigo | E172: Valor FOB (USD); ampliable con subpartida, producto y peso neto | F172: SUNAT-Aduanas (Aduanet) | G172: RUC_FOB | H172: =IF(COUNTA(HECHO_EXPORTACION!A1)>0,"Sí — HECHO_EXPORTACION","No")
B173: HECHO_CONTRATACION_ESTATAL | C173: RUC + proceso OCDS | D173: ruc + ocid | E173: Procesos y contratos con el Estado: entidad, objeto, monto, fecha, estado | F173: OECE Contrataciones Abiertas OCDS (Croma / Apify) | G173: RUC_CONTRATACION | H173: Sí — HECHO_CONTRATACION_ESTATAL
B174: HECHO_PROGRAMA_ANUAL | C174: RUC + año | D174: ruc + anio | E174: Servicio o intervención, beneficiarios por sexo, asistencia técnica, talleres, ventas nacionales y de exportación, comprobantes | F174: Registros internos del programa | G174: b1, b2 | H174: =IF(COUNTA(HECHO_PROGRAMA_ANUAL!A1)>0,"Sí — HECHO_PROGRAMA_ANUAL","No")
B175: HECHO_CAMPANIA_PRODUCTIVA | C175: RUC + campaña | D175: ruc + campania | E175: Socios por sexo, hectáreas, producción estimada, meses de cosecha y embarque, altitud, variedades, calidad, EUDR | F175: Registros internos del programa (declarado por la organización) | G175: b3 | H175: =IF(COUNTA(HECHO_CAMPANIA_PRODUCTIVA!A1)>0,"Sí — HECHO_CAMPANIA_PRODUCTIVA","No")
B176: REL_CERTIFICACION | C176: RUC + tipo + número de certificado | D176: ruc + tipo_cert + nro_cert | E176: Orgánica, Comercio Justo y otras, con fecha de vigencia | F176: Organismo certificador / registro interno | G176: b1, b3 | H176: =IF(COUNTA(REL_CERTIFICACION!A1)>0,"Sí — REL_CERTIFICACION","No")
B177: REL_CONTACTO | C177: RUC + tipo + valor | D177: ruc + tipo_contacto + valor | E177: Teléfonos, correos, web y redes, con fuente y fecha (varios por RUC) | F177: OECE (SUNAT, registro interno) | G177: RUC_OECE, RNP, b3 | H177: =IF(COUNTA(REL_CONTACTO!A1)>0,"Sí — REL_CONTACTO","No")
B178: CTL_FUENTE_CONSULTA | C178: Fuente + lote de consulta | D178: id_consulta | E178: Bitácora: fuente, endpoint, tipo directo/indirecto, fecha_consulta, RUCs consultados y devueltos, archivo | F178: — | G178: README sección 2, fecha_consulta de cada pestaña | H178: =IF(COUNTA(CTL_FUENTE_CONSULTA!A1)>0,"Sí — CTL_FUENTE_CONSULTA","No")
B179: HIST_ATRIBUTO | C179: RUC + atributo + fecha | D179: ruc + atributo + fecha_valor | E179: Histórico de valores reemplazados, para auditar cambios de estado, dirección, contacto, etc. | F179: — | G179: — | H179: =IF(COUNTA(HIST_ATRIBUTO!A2:A5000)>0,"Sí — HIST_ATRIBUTO ("&COUNTA(HIST_ATRIBUTO!A2:A5000)&" filas)","Sí (plantilla vacía) — HIST_ATRIBUTO")
B181: 5.3 Diccionario de la tabla maestra DIM_ORGANIZACION (una fila por RUC)
B182: Atributo | C182: Tipo | D182: Fuente 1: directa y vigente | E182: Fuente 2: respaldo | F182: Dónde está hoy (pestaña!columna) | G182: Cobertura actual (registros con dato)
B183: ruc | C183: Texto(11) | D183: rucs.txt / RUC_ID (universo) | E183: SUNAT Consulta RUC | F183: RUC_CONSULTAMASIVA!A | G183: {=SUMPRODUCT((LEN(RUC_CONSULTAMASIVA!$A$2:$A$598)>0)*(RUC_CONSULTAMASIVA!$A$2:$A$598<>"-"))}
B184: razon_social | C184: Texto | D184: SUNAT Consulta RUC | E184: OECE ficha; MIDAGRI-PPA | F184: RUC_CONSULTAMASIVA!B · RUC_OECE!B | G184: {=SUMPRODUCT((LEN(RUC_CONSULTAMASIVA!$B$2:$B$598)>0)*(RUC_CONSULTAMASIVA!$B$2:$B$598<>"-"))}
B185: nombre_comercial | C185: Texto | D185: SUNAT Consulta RUC | E185: b2/b3 (sigla declarada) | F185: RUC_CONSULTAMASIVA!E | G185: {=SUMPRODUCT((LEN(RUC_CONSULTAMASIVA!$E$2:$E$598)>0)*(RUC_CONSULTAMASIVA!$E$2:$E$598<>"-"))}
...

Sheet DIM_ORGANIZACION
A1: ruc | B1: razon_social | C1: nombre_comercial | D1: tipo_contribuyente | E1: tipo_organizacion_programa | F1: estado_contribuyente | G1: condicion_contribuyente | H1: fecha_inscripcion_ruc | I1: fecha_inicio_actividades | J1: ubigeo | K1: departamento | L1: provincia | M1: distrito | N1: direccion_fiscal | O1: actividad_comercio_exterior | P1: ciiu_principal | Q1: ciiu_secundario_1 | R1: ciiu_secundario_2 | S1: buen_contribuyente | T1: agente_retencion | U1: telefono_principal | V1: email_principal | W1: inscrito_rnp | X1: codigo_rnp | Y1: inscrito_ppa | Z1: nombre_ppa | AA1: ventas_totales_2024 | AB1: ventas_totales_2025 | AC1: exporta | AD1: fob_total_usd | AE1: ultimo_periodo_exportacion | AF1: fob_ultimo_anio_usd | AG1: n_paises_destino | AH1: presidente_vigente | AI1: representante_legal_vigente | AJ1: gerente_general | AK1: n_directivos_vigentes | AL1: producto_dominante | AM1: anios_intervencion | AN1: servicio_programa | AO1: n_socios_varones | AP1: n_socias_mujeres | AQ1: hectareas_totales | AR1: certificacion_organica | AS1: certificacion_comercio_justo | AT1: avance_eudr | AU1: fecha_ultima_actualizacion | AV1: score_completitud | AW1: n_duas | AX1: n_duas_canal_no_verde
A2: {=_xlfn._xlws.SORT(_xlfn.UNIQUE(_xlfn._xlws.FILTER(RUC_CONSULTAMASIVA!$A$2:$A$5000,RUC_CONSULTAMASIVA!$A$2:$A$5000<>"")))} | B2: {=_xlfn.LET(_xlpm.s,_xlfn.LET(_xlpm.v,TRIM(_xlfn.XLOOKUP(_xlfn.ANCHORARRAY($A$2),RUC_CONSULTAMASIVA!$A$2:$A$5000,RUC_CONSULTAMASIVA!$B$2:$B$5000,"")&""),IF((_xlpm.v="-")+(_xlpm.v="0"),"",_xlpm.v)),_xlpm.o,_xlfn.LET(_xlpm.v,TRIM(_xlfn.XLOOKUP(_xlfn.ANCHORARRAY($A$2),RUC_OECE!$A$2:$A$5000,RUC_OECE!$B$2:$B$5000,"")&""),IF((_xlpm.v="-")+(_xlpm.v="0"),"",_xlpm.v)),IF(_xlpm.s="",_xlpm.o,_xlpm.s))} | C2: {=_xlfn.LET(_xlpm.v,TRIM(_xlfn.XLOOKUP(_xlfn.ANCHORARRAY($A$2),RUC_CONSULTAMASIVA!$A$2:$A$5000,RUC_CONSULTAMASIVA!$E$2:$E$5000,"")&""),IF((_xlpm.v="-")+(_xlpm.v="0"),"",_xlpm.v))} | D2: {=_xlfn.LET(_xlpm.s,_xlfn.LET(_xlpm.v,TRIM(_xlfn.XLOOKUP(_xlfn.ANCHORARRAY($A$2),RUC_CONSULTAMASIVA!$A$2:$A$5000,RUC_CONSULTAMASIVA!$C$2:$C$5000,"")&""),IF((_xlpm.v="-")+(_xlpm.v="0"),"",_xlpm.v)),_xlpm.o,_xlfn.LET(_xlpm.v,TRIM(_xlfn.XLOOKUP(_xlfn.ANCHORARRAY($A$2),RUC_OECE!$A$2:$A$5000,RUC_OECE!$C$2:$C$5000,"")&""),IF((_xlpm.v="-")+(_xlpm.v="0"),"",_xlpm.v)),IF(_xlpm.s="",_xlpm.o,_xlpm.s))} | E2: {=_xlfn.LET(_xlpm.v,TRIM(_xlfn.XLOOKUP(_xlfn.ANCHORARRAY($A$2),TRIM('b2'!$DI$3:$DI$2000&""),'b2'!$DK$3:$DK$2000,"")&""),IF((_xlpm.v="-")+(_xlpm.v="0"),"",_xlpm.v))} | F2: {=_xlfn.LET(_xlpm.s,_xlfn.LET(_xlpm.v,TRIM(_xlfn.XLOOKUP(_xlfn.ANCHORARRAY($A$2),RUC_CONSULTAMASIVA!$A$2:$A$5000,RUC_CONSULTAMASIVA!$G$2:$G$5000,"")&""),IF((_xlpm.v="-")+(_xlpm.v="0"),"",_xlpm.v)),_xlpm.o,_xlfn.LET(_xlpm.v,TRIM(_xlfn.XLOOKUP(_xlfn.ANCHORARRAY($A$2),RUC_OECE!$A$2:$A$5000,RUC_OECE!$D$2:$D$5000,"")&""),IF((_xlpm.v="-")+(_xlpm.v="0"),"",_xlpm.v)),IF(_xlpm.s="",_xlpm.o,_xlpm.s))} | G2: {=_xlfn.LET(_xlpm.s,_xlfn.LET(_xlpm.v,TRIM(_xlfn.XLOOKUP(_xlfn.ANCHORARRAY($A$2),RUC_CONSULTAMASIVA!$A$2:$A$5000,RUC_CONSULTAMASIVA!$F$2:$F$5000,"")&""),IF((_xlpm.v="-")+(_xlpm.v="0"),"",_xlpm.v)),_xlpm.o,_xlfn.LET(_xlpm.v,TRIM(_xlfn.XLOOKUP(_xlfn.ANCHORARRAY($A$2),RUC_OECE!$A$2:$A$5000,RUC_OECE!$E$2:$E$5000,"")&""),IF((_xlpm.v="-")+(_xlpm.v="0"),"",_xlpm.v)),IF(_xlpm.s="",_xlpm.o,_xlpm.s))} | H2: {=_xlfn.LET(_xlpm.t,_xlfn.LET(_xlpm.v,TRIM(_xlfn.XLOOKUP(_xlfn.ANCHORARRAY($A$2),RUC_CONSULTAMASIVA!$A$2:$A$5000,RUC_CONSULTAMASIVA!$H$2:$H$5000,"")&""),IF((_xlpm.v="-")+(_xlpm.v="0"),"",_xlpm.v)),IFERROR(DATE(RIGHT(_xlpm.t,4),MID(_xlpm.t,4,2),LEFT(_xlpm.t,2)),""))} | I2: {=_xlfn.LET(_xlpm.t,_xlfn.LET(_xlpm.v,TRIM(_xlfn.XLOOKUP(_xlfn.ANCHORARRAY($A$2),RUC_CONSULTAMASIVA!$A$2:$A$5000,RUC_CONSULTAMASIVA!$I$2:$I$5000,"")&""),IF((_xlpm.v="-")+(_xlpm.v="0"),"",_xlpm.v)),IFERROR(DATE(RIGHT(_xlpm.t,4),MID(_xlpm.t,4,2),LEFT(_xlpm.t,2)),""))} | J2: {=_xlfn.LET(_xlpm.v,TRIM(_xlfn.XLOOKUP(_xlfn.ANCHORARRAY($A$2),TRIM('b2'!$DI$3:$DI$2000&""),'b2'!$E$3:$E$2000,"")&""),IF((_xlpm.v="-")+(_xlpm.v="0"),"",_xlpm.v))} | K2: {=_xlfn.LET(_xlpm.s,_xlfn.LET(_xlpm.v,TRIM(_xlfn.XLOOKUP(_xlfn.ANCHORARRAY($A$2),RUC_CONSULTAMASIVA!$A$2:$A$5000,RUC_CONSULTAMASIVA!$J$2:$J$5000,"")&""),IF((_xlpm.v="-")+(_xlpm.v="0"),"",_xlpm.v)),_xlpm.o,_xlfn.LET(_xlpm.v,TRIM(_xlfn.XLOOKUP(_xlfn.ANCHORARRAY($A$2),RUC_OECE!$A$2:$A$5000,RUC_OECE!$F$2:$F$5000,"")&""),IF((_xlpm.v="-")+(_xlpm.v="0"),"",_xlpm.v)),IF(_xlpm.s="",_xlpm.o,_xlpm.s))} | L2: {=_xlfn.LET(_xlpm.s,_xlfn.LET(_xlpm.v,TRIM(_xlfn.XLOOKUP(_xlfn.ANCHORARRAY($A$2),RUC_CONSULTAMASIVA!$A$2:$A$5000,RUC_CONSULTAMASIVA!$K$2:$K$5000,"")&""),IF((_xlpm.v="-")+(_xlpm.v="0"),"",_xlpm.v)),_xlpm.o,_xlfn.LET(_xlpm.v,TRIM(_xlfn.XLOOKUP(_xlfn.ANCHORARRAY($A$2),RUC_OECE!$A$2:$A$5000,RUC_OECE!$G$2:$G$5000,"")&""),IF((_xlpm.v="-")+(_xlpm.v="0"),"",_xlpm.v)),IF(_xlpm.s="",_xlpm.o,_xlpm.s))} | M2: {=_xlfn.LET(_xlpm.s,_xlfn.LET(_xlpm.v,TRIM(_xlfn.XLOOKUP(_xlfn.ANCHORARRAY($A$2),RUC_CONSULTAMASIVA!$A$2:$A$5000,RUC_CONSULTAMASIVA!$L$2:$L$5000,"")&""),IF((_xlpm.v="-")+(_xlpm.v="0"),"",_xlpm.v)),_xlpm.o,_xlfn.LET(_xlpm.v,TRIM(_xlfn.XLOOKUP(_xlfn.ANCHORARRAY($A$2),RUC_OECE!$A$2:$A$5000,RUC_OECE!$H$2:$H$5000,"")&""),IF((_xlpm.v="-")+(_xlpm.v="0"),"",_xlpm.v)),IF(_xlpm.s="",_xlpm.o,_xlpm.s))} | N2: {=_xlfn.LET(_xlpm.s,_xlfn.LET(_xlpm.v,TRIM(_xlfn.XLOOKUP(_xlfn.ANCHORARRAY($A$2),RUC_CONSULTAMASIVA!$A$2:$A$5000,RUC_CONSULTAMASIVA!$M$2:$M$5000,"")&""),IF((_xlpm.v="-")+(_xlpm.v="0"),"",_xlpm.v)),_xlpm.o,_xlfn.LET(_xlpm.v,TRIM(_xlfn.XLOOKUP(_xlfn.ANCHORARRAY($A$2),TRIM('b3'!$E$2:$E$200&""),'b3'!$Z$2:$Z$200,"")&""),IF((_xlpm.v="-")+(_xlpm.v="0"),"",_xlpm.v)),IF(_xlpm.s="",_xlpm.o,_xlpm.s))} | O2: {=_xlfn.LET(_xlpm.v,TRIM(_xlfn.XLOOKUP(_xlfn.ANCHORARRAY($A$2),RUC_CONSULTAMASIVA!$A$2:$A$5000,RUC_CONSULTAMASIVA!$P$2:$P$5000,"")&""),IF((_xlpm.v="-")+(_xlpm.v="0"),"",_xlpm.v))} | P2: {=_xlfn.LET(_xlpm.v,TRIM(_xlfn.XLOOKUP(_xlfn.ANCHORARRAY($A$2),RUC_CONSULTAMASIVA!$A$2:$A$5000,RUC_CONSULTAMASIVA!$Q$2:$Q$5000,"")&""),IF((_xlpm.v="-")+(_xlpm.v="0"),"",_xlpm.v))} | Q2: {=_xlfn.LET(_xlpm.v,TRIM(_xlfn.XLOOKUP(_xlfn.ANCHORARRAY($A$2),RUC_CONSULTAMASIVA!$A$2:$A$5000,RUC_CONSULTAMASIVA!$R$2:$R$5000,"")&""),IF((_xlpm.v="-")+(_xlpm.v="0"),"",_xlpm.v))} | R2: {=_xlfn.LET(_xlpm.v,TRIM(_xlfn.XLOOKUP(_xlfn.ANCHORARRAY($A$2),RUC_CONSULTAMASIVA!$A$2:$A$5000,RUC_CONSULTAMASIVA!$S$2:$S$5000,"")&""),IF((_xlpm.v="-")+(_xlpm.v="0"),"",_xlpm.v))} | S2: {=_xlfn.LET(_xlpm.v,TRIM(_xlfn.XLOOKUP(_xlfn.ANCHORARRAY($A$2),RUC_CONSULTAMASIVA!$A$2:$A$5000,RUC_CONSULTAMASIVA!$U$2:$U$5000,"")&""),IF((_xlpm.v="-")+(_xlpm.v="0"),"",_xlpm.v))} | T2: {=_xlfn.LET(_xlpm.v,TRIM(_xlfn.XLOOKUP(_xlfn.ANCHORARRAY($A$2),RUC_CONSULTAMASIVA!$A$2:$A$5000,RUC_CONSULTAMASIVA!$V$2:$V$5000,"")&""),IF((_xlpm.v="-")+(_xlpm.v="0"),"",_xlpm.v))} | U2: {=_xlfn.LET(_xlpm.s,_xlfn.LET(_xlpm.v,TRIM(_xlfn.XLOOKUP(_xlfn.ANCHORARRAY($A$2),RUC_OECE!$A$2:$A$5000,RUC_OECE!$I$2:$I$5000,"")&""),IF((_xlpm.v="-")+(_xlpm.v="0"),"",_xlpm.v)),_xlpm.o,_xlfn.LET(_xlpm.v,TRIM(_xlfn.XLOOKUP(_xlfn.ANCHORARRAY($A$2),TRIM('b3'!$E$2:$E$200&""),'b3'!$AB$2:$AB$200,"")&""),IF((_xlpm.v="-")+(_xlpm.v="0"),"",_xlpm.v)),IF(_xlpm.s="",_xlpm.o,_xlpm.s))} | V2: {=_xlfn.LET(_xlpm.s,_xlfn.LET(_xlpm.v,TRIM(_xlfn.XLOOKUP(_xlfn.ANCHORARRAY($A$2),RUC_OECE!$A$2:$A$5000,RUC_OECE!$J$2:$J$5000,"")&""),IF((_xlpm.v="-")+(_xlpm.v="0"),"",_xlpm.v)),_xlpm.o,_xlfn.LET(_xlpm.v,TRIM(_xlfn.XLOOKUP(_xlfn.ANCHORARRAY($A$2),TRIM('b3'!$E$2:$E$200&""),'b3'!$AA$2:$AA$200,"")&""),IF((_xlpm.v="-")+(_xlpm.v="0"),"",_xlpm.v)),IF(_xlpm.s="",_xlpm.o,_xlpm.s))} | W2: {=IF(COUNTIF(_xlfn.ANCHORARRAY(REG_RNP!A2),_xlfn.ANCHORARRAY($A$2))>0,"SI","NO")} | X2: {=_xlfn.XLOOKUP(_xlfn.ANCHORARRAY($A$2),_xlfn.ANCHORARRAY(REG_RNP!A2),_xlfn.ANCHORARRAY(REG_RNP!B2),"")} | Y2: {=_xlfn.XLOOKUP(_xlfn.ANCHORARRAY($A$2),_xlfn.ANCHORARRAY(REG_PPA!A2),_xlfn.ANCHORARRAY(REG_PPA!B2),"")} | Z2: {=_xlfn.XLOOKUP(_xlfn.ANCHORARRAY($A$2),_xlfn.ANCHORARRAY(REG_PPA!A2),_xlfn.ANCHORARRAY(REG_PPA!C2),"")} | AA2: {=SUMIFS(HECHO_PROGRAMA_ANUAL!$N$2:$N$5000,HECHO_PROGRAMA_ANUAL!$B$2:$B$5000,_xlfn.ANCHORARRAY($A$2),HECHO_PROGRAMA_ANUAL!$D$2:$D$5000,VALUE(RIGHT($AA$1,4)))} | AB2: {=SUMIFS(HECHO_PROGRAMA_ANUAL!$N$2:$N$5000,HECHO_PROGRAMA_ANUAL!$B$2:$B$5000,_xlfn.ANCHORARRAY($A$2),HECHO_PROGRAMA_ANUAL!$D$2:$D$5000,VALUE(RIGHT($AB$1,4)))} | AC2: {=IF(COUNTIF(_xlfn.ANCHORARRAY(HECHO_EXPORTACION!A2),_xlfn.ANCHORARRAY($A$2))>0,"SI","NO")} | AD2: {=IF(_xlfn.ANCHORARRAY(AC2)="SI",SUMIFS(_xlfn.ANCHORARRAY(HECHO_EXPORTACION!K2),_xlfn.ANCHORARRAY(HECHO_EXPORTACION!A2),_xlfn.ANCHORARRAY($A$2)),"")} | AE2: {=_xlfn.MAP(_xlfn.ANCHORARRAY($A$2),_xlfn.LAMBDA(_xlpm.r,_xlfn.LET(_xlpm.x,_xlfn._xlws.FILTER(_xlfn.ANCHORARRAY(HECHO_EXPORTACION!D2),_xlfn.ANCHORARRAY(HECHO_EXPORTACION!A2)=_xlpm.r,""),_xlpm.m,MAX(IFERROR(--_xlpm.x,0)),IF(_xlpm.m=0,"",LEFT(_xlpm.m,4)&"-"&RIGHT(_xlpm.m,2)))))} | AF2: {=IF(_xlfn.ANCHORARRAY(AE2)="","",SUMIFS(_xlfn.ANCHORARRAY(HECHO_EXPORTACION!K2),_xlfn.ANCHORARRAY(HECHO_EXPORTACION!A2),_xlfn.ANCHORARRAY($A$2),_xlfn.ANCHORARRAY(HECHO_EXPORTACION!B2),LEFT(_xlfn.ANCHORARRAY(AE2),4)))} | AG2: {=_xlfn.MAP(_xlfn.ANCHORARRAY($A$2),_xlfn.LAMBDA(_xlpm.r,IF(COUNTIF(_xlfn.ANCHORARRAY(HECHO_EXPORTACION!A2),_xlpm.r)=0,"",ROWS(_xlfn.UNIQUE(_xlfn._xlws.FILTER(_xlfn.ANCHORARRAY(HECHO_EXPORTACION!J2),_xlfn.ANCHORARRAY(HECHO_EXPORTACION!A2)=_xlpm.r))))))} | AH2: {=_xlfn.XLOOKUP(_xlfn.ANCHORARRAY($A$2)&"|PRESIDENTE|SI",_xlfn.ANCHORARRAY(REL_PERSONA_CARGO!A2)&"|"&UPPER(TRIM(_xlfn.ANCHORARRAY(REL_PERSONA_CARGO!F2)))&"|"&_xlfn.ANCHORARRAY(REL_PERSONA_CARGO!I2),_xlfn.ANCHORARRAY(REL_PERSONA_CARGO!C2),"")} | AI2: {=_xlfn.LET(_xlpm.s,_xlfn.XLOOKUP(_xlfn.ANCHORARRAY($A$2)&"|REPRESENTANTE|SI",_xlfn.ANCHORARRAY(REL_PERSONA_CARGO!A2)&"|"&_xlfn.ANCHORARRAY(REL_PERSONA_CARGO!D2)&"|"&_xlfn.ANCHORARRAY(REL_PERSONA_CARGO!I2),_xlfn.ANCHORARRAY(REL_PERSONA_CARGO!C2),""),_xlpm.o,_xlfn.LET(_xlpm.v,TRIM(_xlfn.XLOOKUP(_xlfn.ANCHORARRAY($A$2),TRIM('b3'!$E$2:$E$200&""),'b3'!$AH$2:$AH$200,"")&""),IF((_xlpm.v="-")+(_xlpm.v="0"),"",_xlpm.v)),IF(_xlpm.s="",_xlpm.o,_xlpm.s))} | AJ2: {=_xlfn.LET(_xlpm.s,_xlfn.XLOOKUP(_xlfn.ANCHORARRAY($A$2)&"|GERENTE GENERAL|SI",_xlfn.ANCHORARRAY(REL_PERSONA_CARGO!A2)&"|"&UPPER(TRIM(_xlfn.ANCHORARRAY(REL_PERSONA_CARGO!F2)))&"|"&_xlfn.ANCHORARRAY(REL_PERSONA_CARGO!I2),_xlfn.ANCHORARRAY(REL_PERSONA_CARGO!C2),""),_xlpm.o,_xlfn.LET(_xlpm.v,TRIM(_xlfn.XLOOKUP(_xlfn.ANCHORARRAY($A$2),TRIM('b3'!$E$2:$E$200&""),'b3'!$AE$2:$AE$200,"")&""),IF((_xlpm.v="-")+(_xlpm.v="0"),"",_xlpm.v)),IF(_xlpm.s="",_xlpm.o,_xlpm.s))} | AK2: {=_xlfn.LET(_xlpm.n,COUNTIFS(_xlfn.ANCHORARRAY(REL_PERSONA_CARGO!A2),_xlfn.ANCHORARRAY($A$2),_xlfn.ANCHORARRAY(REL_PERSONA_CARGO!D2),"ORGANO_ADMINISTRACION",_xlfn.ANCHORARRAY(REL_PERSONA_CARGO!I2),"SI"),IF(_xlpm.n=0,"",_xlpm.n))} | AL2: {=_xlfn.LET(_xlpm.v,TRIM(_xlfn.XLOOKUP(_xlfn.ANCHORARRAY($A$2),TRIM('b2'!$DI$3:$DI$2000&""),'b2'!$B$3:$B$2000,"")&""),IF((_xlpm.v="-")+(_xlpm.v="0"),"",_xlpm.v))} | AM2: {=_xlfn.LET(_xlpm.v,TRIM(_xlfn.XLOOKUP(_xlfn.ANCHORARRAY($A$2),TRIM('b2'!$DI$3:$DI$2000&""),'b2'!$R$3:$R$2000,"")&""),IF((_xlpm.v="-")+(_xlpm.v="0"),"",_xlpm.v))} | AN2: {=_xlfn.LET(_xlpm.v,TRIM(_xlfn.XLOOKUP(_xlfn.ANCHORARRAY($A$2),TRIM('b2'!$DI$3:$DI$2000&""),'b2'!$Q$3:$Q$2000,"")&""),IF((_xlpm.v="-")+(_xlpm.v="0"),"",_xlpm.v))} | AO2: {=_xlfn.LET(_xlpm.v,_xlfn.XLOOKUP(_xlfn.ANCHORARRAY($A$2),TRIM('b3'!$E$2:$E$200&""),'b3'!$M$2:$M$200,""),IF(_xlpm.v="","",_xlpm.v))} | AP2: {=_xlfn.LET(_xlpm.v,_xlfn.XLOOKUP(_xlfn.ANCHORARRAY($A$2),TRIM('b3'!$E$2:$E$200&""),'b3'!$N$2:$N$200,""),IF(_xlpm.v="","",_xlpm.v))} | AQ2: {=_xlfn.LET(_xlpm.v,_xlfn.XLOOKUP(_xlfn.ANCHORARRAY($A$2),TRIM('b3'!$E$2:$E$200&""),'b3'!$O$2:$O$200,""),IF(_xlpm.v="","",_xlpm.v))} | AR2: {=_xlfn.LET(_xlpm.v,TRIM(_xlfn.XLOOKUP(_xlfn.ANCHORARRAY($A$2),TRIM('b3'!$E$2:$E$200&""),'b3'!$U$2:$U$200,"")&""),IF((_xlpm.v="-")+(_xlpm.v="0"),"",_xlpm.v))} | AS2: {=_xlfn.LET(_xlpm.v,TRIM(_xlfn.XLOOKUP(_xlfn.ANCHORARRAY($A$2),TRIM('b3'!$E$2:$E$200&""),'b3'!$V$2:$V$200,"")&""),IF((_xlpm.v="-")+(_xlpm.v="0"),"",_xlpm.v))} | AT2: {=_xlfn.LET(_xlpm.v,TRIM(_xlfn.XLOOKUP(_xlfn.ANCHORARRAY($A$2),TRIM('b3'!$E$2:$E$200&""),'b3'!$Y$2:$Y$200,"")&""),IF((_xlpm.v="-")+(_xlpm.v="0"),"",_xlpm.v))} | AU2: {=_xlfn.LET(_xlpm.cv,_xlfn.LAMBDA(_xlpm.t,IFERROR(DATE(LEFT(_xlpm.t,4),MID(_xlpm.t,6,2),MID(_xlpm.t,9,2))+TIME(MID(_xlpm.t,12,2),MID(_xlpm.t,15,2),MID(_xlpm.t,18,2)),0)),_xlpm.o,_xlpm.cv(_xlfn.XLOOKUP(_xlfn.ANCHORARRAY($A$2),RUC_OECE!$A$2:$A$5000,RUC_OECE!$L$2:$L$5000,"")),_xlpm.p,_xlpm.cv(_xlfn.XLOOKUP(_xlfn.ANCHORARRAY($A$2),_xlfn.ANCHORARRAY(REG_PPA!A2),_xlfn.ANCHORARRAY(REG_PPA!F2),"")),_xlpm.e,_xlpm.cv(_xlfn.XLOOKUP(_xlfn.ANCHORARRAY($A$2),_xlfn.ANCHORARRAY(HECHO_EXPORTACION!A2),_xlfn.ANCHORARRAY(HECHO_EXPORTACION!P2),"")),_xlpm.m,IF(_xlpm.o>_xlpm.p,_xlpm.o,_xlpm.p),_xlpm.x,IF(_xlpm.m>_xlpm.e,_xlpm.m,_xlpm.e),IF(_xlpm.x=0,"",_xlpm.x))} | AV2: {=_xlfn.LET(_xlpm.n,ROWS(_xlfn.ANCHORARRAY($A$2)),_xlpm.b,_xlfn.TAKE(_xlfn.HSTACK($B$2:$AT$5000,$AW$2:$AX$5000),_xlpm.n),_xlfn.BYROW(_xlpm.b,_xlfn.LAMBDA(_xlpm.r,SUM(--(_xlpm.r<>""))/COLUMNS(_xlpm.r))))} | AW2: {=_xlfn.LET(_xlpm.n,COUNTIFS(RUC_FOB_DUA!$A$2:$A$5000,_xlfn.ANCHORARRAY($A$2)),IF(_xlpm.n=0,"",_xlpm.n))} | AX2: {=_xlfn.LET(_xlpm.n,COUNTIFS(RUC_FOB_DUA!$A$2:$A$5000,_xlfn.ANCHORARRAY($A$2),RUC_FOB_DUA!$I$2:$I$5000,"<>VERDE"),IF(_xlpm.n=0,"",_xlpm.n))}
A3: 20118588135 | B3: CENTRAL DE COOPERATIVAS DE SERVICIOS ESPECIALES ALPAQUERAS DE PUNO LTDA. - CECOALP | C3: CECOALP | D3: COOPERATIVAS, SAIS, CAPS | E3: 07 Otros | F3: ACTIVO | G3: HABIDO | H3: 34084 | I3: 33239 | J3: 211101 | K3: PUNO | L3: SAN ROMAN | M3: JULIACA | N3: JR. MIRAFLORES NRO. 1496 URB. SAN FRANCISCO (A UNA ACUADRA MERDO.PEDRO VILCA A.) | O3: IMPORTADOR/EXPORTADOR | P3: VTA. MAY. DE MATERIAS PRIMAS AGROPEC. | U3: 051328851 | V3: nilvaflors@gmail.com | W3: SI | X3: S0148048 | Y3: SI | Z3: CENTRAL DE COOPERATIVAS DE SERVICIOS ESPECIALES ALPAQUERAS DE PUNO LTDA. - CECOALP | AA3: 0 | AB3: 0 | AC3: NO | AH3: MAMANI OJEDA PEDRO LAUREANO | AI3: LOPEZ MULLISACA CESAR | AK3: 3 | AL3: FIBRA DE ALPACA | AM3: 2018-2019-2020-2021-2023 | AN3: PAC | AU3: 46285.072 | AV3: 0.66666667
A4: 20119208026 | B4: FONGAL TACNA | C4: FONGAL TACNA | D4: ASOCIACION | E4: 01 Asociación | F4: ACTIVO | G4: HABIDO | H4: 34088 | I4: 29468 | J4: 230101 | K4: TACNA | L4: TACNA | M4: CRL. GREG. ALBARRACIN LANCHIPA | N4: OVL. CUSCO NRO. S/N FND. LA AGRONOMICA | O4: SIN ACTIVIDAD | P4: ELAB DE OTROS PROD. ALIMENTICIOS. | Q4: SERVICIOS AGRICOLAS, GANADERAS. | U4: 052-401722 | V4: john_sarmiento_4321@hotmail.es | W4: SI | X4: B0048031 | Y4: SI | Z4: FONGAL TACNA | AA4: 0 | AB4: 0 | AC4: NO | AH4: MAMANI MAMANI VICTOR | AI4: MAMANI MAMANI VICTOR | AK4: 6 | AL4: DERIVADOS LACTEOS | AM4: 2018 | AN4: PAC | AU4: 46285.072 | AV4: 0.68888889
A5: 20129156083 | B5: COOP AGRARIA CAFET VALLE RIO APURIMAC | C5: CAC VALLE RIO APURIMAC | D5: COOPERATIVAS, SAIS, CAPS | E5: 02 Cooperativa | F5: ACTIVO | G5: HABIDO | H5: 34093 | I5: 25551 | J5: 050503 | K5: AYACUCHO | L5: LA MAR | M5: AYNA | N5: AV. 28 DE JULIO NRO. 4 (PUERTO SAN FRANCISCO) | O5: EXPORTADOR | P5: VTA. MAY. ALIMENTOS, BEBIDAS Y TABACO. | Q5: ELAB. CACAO, CHOCOLATE Y CONFIT. | U5: 066-325179 | V5: cacvra@yahoo.es | W5: SI | X5: S0128686 | Y5: SI | Z5: COOP AGRARIA CAFET VALLE RIO APURIMAC | AA5: 0 | AB5: 0 | AC5: NO | AH5: HUAMAN SANTA CRUZ BENJAMIN | AI5: ZAMALLOA BRAVO HERNAN | AK5: 7 | AL5: CACAO | AM5: 2018-2019-2020-2021-2023 | AN5: PAC | AU5: 46285.072 | AV5: 0.68888889
A6: 20129529530 | B6: COOP AGRARIA CAFETALERA SATIPO LTDA | C6: C.A.C. SATIPO LTDA. | D6: COOPERATIVAS, SAIS, CAPS | F6: ACTIVO | G6: HABIDO | H6: 34093 | I6: 34039 | K6: JUNIN | L6: SATIPO | M6: SATIPO | N6: JR. MANUEL PRADO NRO. 433 | O6: EXPORTADOR | P6: CULTIVO DE FRUTAS. | R6: ACTIVIDADES INMOBILIARIAS | T6: SI, incorporado al Régimen de Agentes de Retención de IGV (R.S.229-2024) a partir del 01/01/2025 | U6: 545030 | V6: edisondario@hotmail.com | W6: SI | X6: S0836027 | Y6: SI | Z6: COOP AGRARIA CAFETALERA SATIPO LTDA | AA6: 0 | AB6: 0 | AC6: SI | AD6: 9603968.1 | AE6: 2026-04 | AF6: 261159.86 | AG6: 4 | AH6: HUARCAYA HUINCHO AGAPITO | AI6: AYALA LOMBARDI JOSEPH OSCAR JOHNNATAN | AK6: 7 | AU6: 46285.072 | AV6: 0.68888889
A7: 20129772043 | B7: COOPERATIVA COMUNAL VICCO LTDA | C7: COOPERATIVA COMUNAL VICCO LTDA | D7: COOPERATIVAS, SAIS, CAPS | F7: ACTIVO | G7: HABIDO | H7: 34093 | I7: 26547 | K7: PASCO | L7: PASCO | M7: VICCO | N7: AV. CERRO DE PASCO NRO. 990 CERCADO (COST. CAPILLA 3 DE MAYO) | O7: SIN ACTIVIDAD | P7: CRIA DE GANADO. | Q7: TRANSPORTE DE CARGA POR CARRETERA. | W7: NO | Y7: SI | Z7: COOPERATIVA COMUNAL VICCO LTDA | AA7: 0 | AB7: 0 | AC7: NO | AU7: 46285.072 | AV7: 0.44444444
A8: 20129830426 | B8: COOPERATIVA COMUNAL HUAYLLAY LTDA 16 | D8: COOPERATIVAS, SAIS, CAPS | E8: 02 Cooperativa | F8: ACTIVO | G8: HABIDO | H8: 34093 | I8: 26342 | J8: 190104 | K8: PASCO | L8: PASCO | M8: HUAYLLAY | N8: PZA. RAMON CASTILLA NRO. 121 HUAYLLAY | O8: SIN ACTIVIDAD | P8: CRIA DE GANADO. | Q8: ELAB DE PRODUCTOS LACTEOS. | W8: SI | X8: S1069969 | Y8: SI | Z8: COOPERATIVA COMUNAL HUAYLLAY LTDA 16 | AA8: 0 | AB8: 0 | AC8: NO | AL8: FIBRA DE ALPACA | AM8: 2021-2022-2024 - 2025 | AN8: PAC | AU8: 46285.072 | AV8: 0.55555556
A9: 20129842351 | B9: COOPERATIVA COMUNAL SAN ANTONIO DE RANCAS LTDA. 289 | C9: RANCAS | D9: COOPERATIVAS, SAIS, CAPS | E9: 02 Cooperativa | F9: ACTIVO | G9: HABIDO | H9: 34093 | I9: 21124 | J9: 190109 | K9: PASCO | L9: PASCO | M9: SIMON BOLIVAR | N9: CAL. SAN MARTIN NRO. 121 SN ANTONIO RANCAS (PLAZA PRINCIPAL) | O9: SIN ACTIVIDAD | P9: CRIA DE GANADO. | Q9: TRANSPORTE DE CARGA POR CARRETERA. | R9: OTROS TIPOS DE VENTA AL POR MENOR. | W9: NO | Y9: SI | Z9: COOPERATIVA COMUNAL SAN ANTONIO DE RANCAS LTDA. 289 | AA9: 0 | AB9: 0 | AC9: NO | AL9: FIBRA DE ALPACA | AM9: 2019-2020-2021-2022 | AN9: PAC | AU9: 46285.072 | AV9: 0.57777778
A10: 20131453427 | B10: COOPERATIVA COMUNAL SAN PEDRO DE RACCO | D10: COOPERATIVAS, SAIS, CAPS | E10: 02 Cooperativa | F10: ACTIVO | G10: HABIDO | H10: 34093 | I10: 25469 | J10: 190109 | K10: PASCO | L10: PASCO | M10: SIMON BOLIVAR | N10: AV. FEDERICO ROJAS HERRERA NRO. S/N ANX. SAN PEDRO DE RACCO | O10: SIN ACTIVIDAD | P10: CRIA DE GANADO. | Q10: ALQUILER OTROS TIPOS MAQ.Y EQUI. NCP. | R10: CRIA DE ANIMALES DOMESTICOS. | S10: SI, incorporado al Régimen de Buenos Contribuyentes (Resolución N° 1930050007770) a partir del 01/02/2022 | W10: SI | X10: S2342817 | Y10: SI | Z10: COOPERATIVA COMUNAL SAN PEDRO DE RACCO | AA10: 0 | AB10: 0 | AC10: NO | AL10: FIBRA DE ALPACA | AM10: 2021-2022-2024 - 2025 | AN10: PAC | AU10: 46285.072 | AV10: 0.6
A11: 20132489824 | B11: COOPERATIVA AGRARIA CAFETALERA CHANCAMAYO LTDA. N° 008-B-VII | D11: COOPERATIVAS, SAIS, CAPS | F11: ACTIVO | G11: HABIDO | H11: 34095 | I11: 27075 | K11: CUSCO | L11: LA CONVENCION | M11: SANTA ANA | N11: AV. EDGAR DE LA TORRE NRO. 1353 (CENTRAL COCLA) | O11: SIN ACTIVIDAD | P11: TRANSPORTE DE CARGA POR CARRETERA. | Q11: SERVICIOS AGRICOLAS, GANADERAS. | R11: ACTIVIDADES INMOBILIARIAS | U11: 976 065194 | V11: walticomt@hotmail.com | W11: SI | X11: S0438053 | Y11: SI | Z11: COOPERATIVA AGRARIA CAFETALERA CHANCAMAYO LTDA. N° 008-B-VII | AA11: 0 | AB11: 0 | AC11: NO | AI11: Fredy Castillo Herrera | AJ11: Fredy Castillo Herrera | AO11: 30 | AP11: 14 | AQ11: 44 | AR11: Certificacion Organica, vigencia hasta 14/08/2026 | AS11: Vigencia organica hasta 26/03/2027 | AU11: 46285.072 | AV11: 0.66666667
A12: 20132505455 | B12: COOPERATIVA AGRARIA CAFETALERA AGUILAYOC LTDA. 084 | D12: COOPERATIVAS, SAIS, CAPS | E12: 02 Cooperativa | F12: ACTIVO | G12: HABIDO | H12: 34095 | I12: 29317 | J12: 080901 | K12: CUSCO | L12: LA CONVENCION | M12: SANTA ANA | N12: JR. OLLANTA NRO. 130 URB. SANTA ANA | O12: SIN ACTIVIDAD | P12: EXPLOTACION MIXTA. | Q12: ACTIVIDADES INMOBILIARIAS | S12: SI, incorporado al Régimen de Buenos Contribuyentes (Resolución N° 0930050010724) a partir del 01/04/2018 | U12: 084282566 | V12: cacaguilayoc@gmail.com | W12: SI | X12: S1293176 | Y12: SI | Z12: COOPERATIVA AGRARIA CAFETALERA AGUILAYOC LTDA. 084 | AA12: 168351.56 | AB12: 615259.83 | AC12: NO | AH12: mora candia walter | AI12: GIBAJA CRUZ YOLANDA | AJ12: Fernando Saldivar Perez | AK12: 5 | AL12: CAFÉ | AM12: 2024 - 2025 | AN12: PAC | AO12: 73 | AP12: 27 | AQ12: 218 | AR12: Certificacion Organica, 26 de noviembre del 2026 | AT12: 0.75 | AU12: 46285.072 | AV12: 0.82222222
A13: 20132509795 | B13: COOPERATIVA AGRARIA CAFETALERA JOSE OLAYA LTDA N° 252 | C13: CAC JOSE OLAYA LTDA 252 | D13: COOPERATIVAS, SAIS, CAPS | E13: 02 Cooperativa | F13: ACTIVO | G13: HABIDO | H13: 34095 | I13: 26401 | J13: 080901 | K13: CUSCO | L13: LA CONVENCION | M13: SANTA ANA | N13: AV. EDGAR DE LA TORRE NRO. 232 COO. QUILLABAMBA | O13: IMPORTADOR/EXPORTADOR | P13: CULTIVO DE FRUTAS. | Q13: ACTIVIDADES INMOBILIARIAS | U13: 282638 | V13: 252cacjoseolaya@gmail.com | W13: SI | X13: S0882298 | Y13: SI | Z13: COOPERATIVA AGRARIA CAFETALERA JOSE OLAYA LTDA N° 252 | AA13: 0 | AB13: 0 | AC13: SI | AD13: 2477083.5 | AE13: 2025-12 | AF13: 1039099.4 | AG13: 5 | AH13: PEZO TTUPA PERCY | AI13: HERRERA PAULLO LEONID | AK13: 7 | AL13: CAFÉ | AM13: 2018-2019-2020-2021-2022-2023 | AN13: PAC | AU13: 46285.072 | AV13: 0.77777778
A14: 20132509876 | B14: COOPERATIVA AGRARIA CAFETALERA MARANURA LTDA. 129 | D14: COOPERATIVAS, SAIS, CAPS | E14: 02 Cooperativa | F14: ACTIVO | G14: HABIDO | H14: 34095 | I14: 23713 | J14: 080904 | K14: CUSCO | L14: LA CONVENCION | M14: MARANURA | N14: NRO. SN SEC. PAMPA MARANURA (CARRTERA QBBA CUSCO KM10 EX FUNDOMARANUR) | O14: IMPORTADOR/EXPORTADOR | P14: TRANSPORTE DE CARGA POR CARRETERA. | Q14: ELAB. CACAO, CHOCOLATE Y CONFIT. | U14: 984403611 | V14: CACMARANURA@HOTMAIL.COM | W14: SI | X14: S1112758 | Y14: SI | Z14: COOPERATIVA AGRARIA CAFETALERA MARANURA LTDA. 129 | AA14: 0 | AB14: 0 | AC14: SI | AD14: 1689820.3 | AE14: 2026-01 | AF14: 610049.62 | AG14: 1 | AH14: huaman delgado silvestre | AI14: PIMENTEL CONDORI LUDGARDO | AK14: 5 | AL14: CAFÉ | AM14: 2019-2020-2021-2022-2023 | AN14: PAC | AU14: 46285.072 | AV14: 0.75555556
A15: 20132517119 | B15: COOPERATIVA AGRARIA CAFETALERA MATEO PUMACAHUA LTDA N° 185 | C15: COOP. AGRARIA CAFETALERA | D15: COOPERATIVAS, SAIS, CAPS | E15: 02 Cooperativa | F15: ACTIVO | G15: HABIDO | H15: 34095 | I15: 24066 | J15: 080901 | K15: CUSCO | L15: LA CONVENCION | M15: SANTA ANA | N15: JR. LIBERTAD NRO. 631 | O15: IMPORTADOR/EXPORTADOR | P15: ELAB. CACAO, CHOCOLATE Y CONFIT. | Q15: ACTIVIDADES INMOBILIARIAS | U15: 084281110 | V15: CAMARALACONVENCION_@hotmail.com | W15: SI | X15: S1142161 | Y15: SI | Z15: COOPERATIVA AGRARIA CAFETALERA MATEO PUMACAHUA LTDA N° 185 | AA15: 80172.952 | AB15: 274646.15 | AC15: NO | AH15: VALDEZ VALENCIA REMIGIO | AI15: JOHN ERIC MOLINA HERRERA | AJ15: Remigio Valdez Valencia | AK15: 5 | AL15: CAFÉ | AM15: 2024 - 2025 | AN15: PAC | AO15: 133 | AP15: 44 | AQ15: 469 | AR15: Certificación Orgánica, Vigencia hasta agosto 2026 | AS15: Fairtrade hasta junio 2026 | AT15: 0.75 | AU15: 46285.072 | AV15: 0.84444444
A16: 20136201132 | B16: COOPERATIVA AGRARIA CAFETALERA ALTO URUBAMBA LTDA N° 239 | C16: C.A.C. ALTO URUBAMBA | D16: COOPERATIVAS, SAIS, CAPS | E16: 02 Cooperativa | F16: ACTIVO | G16: HABIDO | H16: 34102 | I16: 24744 | J16: 080901 | K16: CUSCO | L16: LA CONVENCION | M16: SANTA ANA | N16: AV. FRANCISCA ZUBIAGA NRO. 427 QUILLABAMBA (COSTADO DE ELECTRO SUR S.A.) | O16: SIN ACTIVIDAD | P16: VTA. MAY. DE MATERIAS PRIMAS AGROPEC. | Q16: RESTAURANTES, BARES Y CANTINAS. | U16: 944257022 | V16: c.a.c.altourubamba@gmail.com | W16: SI | X16: S0143918 | Y16: SI | Z16: COOPERATIVA AGRARIA CAFETALERA ALTO URUBAMBA LTDA N° 239 | AA16: 0 | AB16: 0 | AC16: SI | AD16: 681394.36 | AE16: 2025-11 | AF16: 561223.8 | AG16: 4 | AH16: CIRILO QUISPE ILLA | AI16: FLOREZ PALOMINO JOSE | AK16: 5 | AL16: CAFÉ | AM16: 2018-2019-2020-2021-2022-2023 | AN16: PAC | AU16: 46285.072 | AV16: 0.77777778
A17: 20136201213 | B17: CENTRAL DE COOPERATIVAS AGRARIAS CAFETALERAS COCLA LTDA. N° 281 | C17: CENTRAL COCLA LTDA. 281 | D17: COOPERATIVAS, SAIS, CAPS | E17: 02 Cooperativa | F17: ACTIVO | G17: HABIDO | H17: 34102 | I17: 24314 | J17: 080901 | K17: CUSCO | L17: LA CONVENCION | M17: SANTA ANA | N17: AV. EDGAR DE LA TORRE NRO. 1353 QUILLABAMBA (LOCAL DE COCLA) | O17: EXPORTADOR | P17: VTA. MAY. DE OTROS PRODUCTOS. | Q17: ELAB DE OTROS PROD. ALIMENTICIOS. | R17: ACTIVIDADES INMOBILIARIAS | T17: NO, Excluido del Régimen de Agentes de Retención de IGV a partir del 01/02/2015 | U17: 084-281377 | V17: gerencia@cocla.pe | W17: SI | X17: S0552459 | Y17: SI | Z17: CENTRAL DE COOPERATIVAS AGRARIAS CAFETALERAS COCLA LTDA. N° 281 | AA17: 6987135.7 | AB17: 9915753.4 | AC17: SI | AD17: 4445611.6 | AE17: 2026-03 | AF17: 166105.86 | AG17: 5 | AH17: aguilar lozano guillermo | AI17: CURI LEON TANY | AJ17: Vivanco Delgado Vladimir | AK17: 5 | AL17: CAFÉ | AM17: 2024 - 2025 | AN17: PAC | AO17: 472 | AP17: 188 | AQ17: 1670 | AR17: Certificación Orgánica, vigencia hasta agosto 2026 | AS17: Fair trade hasta junio 2027 | AT17: 0.75 | AU17: 46285.072 | AV17: 0.97777778
A18: 20140181405 | B18: COOPERATIVA AGRARIA CAFETALERA LA FLORIDA | C18: COOPERATIVA LA FLORIDA | D18: COOPERATIVAS, SAIS, CAPS | F18: ACTIVO | G18: HABIDO | H18: 34129 | I18: 25849 | K18: JUNIN | L18: CHANCHAMAYO | M18: PERENE | N18: AV. CHANCHAMAYO MZA. O LOTE. 24 C.P. PUERTO YURINAKI (A UNA CDRA PARQUE PTO YURINAKI S75098560) | O18: EXPORTADOR | P18: CULTIVO DE FRUTAS. | Q18: RESTAURANTES, BARES Y CANTINAS. | T18: NO, Excluido del Régimen de Agentes de Retención de IGV a partir del 01/01/2025 | U18: 064-531190 | V18: admlaflorida@spide.com | W18: SI | X18: S0599278 | Y18: SI | Z18: COOPERATIVA AGRARIA CAFETALERA LA FLORIDA | AA18: 0 | AB18: 0 | AC18: SI | AD18: 4202982.9 | AE18: 2026-04 | AF18: 67334.78 | AG18: 7 | AI18: RIVAS PEÑA CESAR | AJ18: Edwin Villacorta Reategui | AO18: 339 | AP18: 111 | AQ18: 1605.8 | AR18: 1780867353, VIGENCIA HASTA 06 FEB 2028 | AS18: FLO ID 796, VIGENCIA HASTA 24 DIC 2028 | AT18: 0.75 | AU18: 46285.072 | AV18: 0.8
A19: 20140292657 | B19: COOPERATIVA AGRARIA CAFETALERA CCOCHAPAMPA LTDA. | C19: COOP AGRARIA CAFETALERA | D19: COOPERATIVAS, SAIS, CAPS | E19: 02 Cooperativa | F19: ACTIVO | G19: HABIDO | H19: 34129 | I19: 33909 | J19: 080901 | K19: CUSCO | L19: LA CONVENCION | M19: SANTA ANA | N19: AV. EDGAR DE LA TORRE NRO. 350 (FT I.E TUPAC AMAR LOCAL COOP. 2P CELESTE) | O19: EXPORTADOR | P19: CULTIVO DE FRUTAS. | Q19: VTA. MAY. DE OTROS PRODUCTOS. | U19: 958301167 | V19: CONTABILIDADAGREGADOSCUSCO@HOTMAIL.COM | W19: SI | X19: S1370809 | Y19: SI | Z19: COOPERATIVA AGRARIA CAFETALERA CCOCHAPAMPA LTDA. | AA19: 477922.31 | AB19: 1773460 | AC19: NO | AH19: aguilar masias gabriel | AI19: PIMENTEL CONDORI LUDGARDO | AJ19: Augusto Tirado Bejar | AK19: 7 | AL19: CAFÉ | AM19: 2024 - 2025 | AN19: PAC | AO19: 38 | AP19: 11 | AQ19: 136.9 | AR19: Certificacion Organica, , vigencia hasta agosto 2026. | AS19: FairTrade (en proceso) | AT19: 0.75 | AU19: 46285.072 | AV19: 0.84444444
A20: 20143224857 | B20: COOPERATIVA AGRARIA DE USUARIOS AMAYBAMBA PISTIPATA LTDA. N°34 | C20: COOPERATIVA AGRARIA | D20: COOPERATIVAS, SAIS, CAPS | E20: 02 Cooperativa | F20: ACTIVO | G20: HABIDO | H20: 34144 | I20: 25934 | J20: 080903 | K20: CUSCO | L20: LA CONVENCION | M20: HUAYOPATA | N20: CAR. QUILLABAMBA CUSCO NRO. KM35 | O20: SIN ACTIVIDAD | P20: CULTIVO DE FRUTAS. | W20: NO | Y20: SI | Z20: COOPERATIVA AGRARIA DE USUARIOS AMAYBAMBA PISTIPATA LTDA. N°34 | AA20: 45825.402 | AB20: 167029 | AC20: NO | AL20: TE | AM20: 2021-2022-2023-2024 - 2025 | AN20: PAC | AU20: 46285.072 | AV20: 0.53333333
A21: 20143692010 | B21: COOPERATIVA AGRARIA EL QUINACHO LTDA. N° 078 | C21: CAC. EL QUINACHO | D21: COOPERATIVAS, SAIS, CAPS | E21: 02 Cooperativa | F21: ACTIVO | G21: HABIDO | H21: 34144 | I21: 25942 | J21: 050407 | K21: AYACUCHO | L21: HUANTA | M21: SIVIA | N21: AV. QUINACHO MZA. V LOTE. 1 (COSTADO DE LA PLAZA PRINCIPAL) | O21: IMPORTADOR/EXPORTADOR | P21: ELAB. CACAO, CHOCOLATE Y CONFIT. | U21: 980444176 | V21: astogozmemarisol@gmail.com | W21: SI | X21: S0758757 | Y21: SI | Z21: COOPERATIVA AGRARIA EL QUINACHO LTDA. N° 078 | AA21: 0 | AB21: 3073770.7 | AC21: SI | AD21: 4030694.7 | AE21: 2026-05 | AF21: 109193.16 | AG21: 3 | AH21: LAPA ÑAHUINCCOPA EFRAIN | AI21: SANTIVAÑEZ SANCHEZ NENE LUIS | AK21: 3 | AL21: CACAO | AM21: 2020-2021-2022-2023 - 2025 | AN21: CALIDAD | AU21: 46285.072 | AV21: 0.75555556
A22: 20145484597 | B22: COOPERATIVA AGRARIA CAFETALERA SAN IGNACIO LTDA. | D22: COOPERATIVAS, SAIS, CAPS | E22: 02 Cooperativa | F22: ACTIVO | G22: HABIDO | H22: 34150 | I22: 33990 | J22: 211201 | K22: PUNO | L22: SANDIA | M22: SAN PEDRO DE PUTINA PUNCO | N22: JR. PROGRESO MZA. L LOTE. 15 BAR. BELLAVISTA (AL FRENTE DEL CENTRO DE SALUD) | O22: SIN ACTIVIDAD | P22: VTA. MAY. DE MATERIAS PRIMAS AGROPEC. | Q22: TRANSPORTE DE CARGA POR CARRETERA. | U22: 951401272 | W22: SI | X22: S0369016 | Y22: SI | Z22: COOPERATIVA AGRARIA CAFETALERA SAN IGNACIO LTDA. | AA22: 0 | AB22: 0 | AC22: NO | AI22: BLANCO CHIARA ADOLFO | AL22: CAFÉ | AM22: 2018-2019-2020 | AN22: PAC | AU22: 46285.072 | AV22: 0.6
A23: 20146696041 | B23: COOP AGRARIA CAFET JOSE GABRIEL CONDORCA | C23: COOP AGRA CAF JOSE GAB COND | D23: COOPERATIVAS, SAIS, CAPS | E23: 02 Cooperativa | F23: ACTIVO | G23: HABIDO | H23: 34151 | I23: 25517 | J23: 200302 | K23: PIURA | L23: HUANCABAMBA | M23: CANCHAQUE | N23: NRO. S/N INT. S/N C.P.M COYONA (A 500M DEL PUESTO DE SALUD DE COYONA) | O23: SIN ACTIVIDAD | P23: VTA. MAY. ALIMENTOS, BEBIDAS Y TABACO. | S23: SI, incorporado al Régimen de Buenos Contribuyentes (Resolución N° 0830050012681) a partir del 01/02/2022 | W23: NO | Y23: SI | Z23: COOP AGRARIA CAFET JOSE GABRIEL CONDORCA | AA23: 0 | AB23: 0 | AC23: NO | AL23: CAFÉ | AM23: 2021-2023 | AN23: PAC | AU23: 46285.072 | AV23: 0.55555556
A24: 20147443120 | B24: COOPERATIVA AGRARIA CAFETALERA TIRIJUAY PAVAYOC LTDA 013-B-VII | D24: COOPERATIVAS, SAIS, CAPS | F24: SUSPENSION TEMPORAL | G24: NO HABIDO | H24: 34151 | I24: 27668 | K24: CUSCO | L24: LA CONVENCION | M24: OCOBAMBA | N24: NRO. SN C.P. DE VERSALLES (CALLE PRINCIPAL FRENT A ESCUELA C2P AZUL) | O24: SIN ACTIVIDAD | P24: VTA. MAY. MATERIALES DE CONSTRUCCION. | Q24: SERVICIOS AGRICOLAS, GANADERAS. | U24: 974 776 817 | V24: cactirijuaypavayoc@gmail.com | W24: NO | Y24: SI | Z24: COOPERATIVA AGRARIA CAFETALERA TIRIJUAY PAVAYOC LTDA 013-B-VII | AA24: 0 | AB24: 0 | AC24: NO | AI24: Carlos Velasquez Champi | AJ24: Carlos Velasquez Champi | AO24: 44 | AP24: 30 | AQ24: 150 | AR24: Certificacion Organica, vigencia hasta 14/08/2026 | AS24: Vigencia organica hasta 26/03/2027 | AU24: 46285.072 | AV24: 0.62222222
A25: 20166786861 | B25: COMITE CENTRAL DE PRODUCTORES AGROPECUARIOS DE SAN ALEJANDRO | D25: ASOCIACION | E25: 01 Asociación | F25: ACTIVO | G25: HABIDO | H25: 34194 | I25: 33295 | J25: 250302 | K25: UCAYALI | L25: PADRE ABAD | M25: IRAZOLA | N25: JR. JR. JHON F. KENNEDY MZA. 0 LOTE. 01 C.V. JJ.VV. MIGUEL GRAU (CERCA AL PUERTO GRAU) | O25: SIN ACTIVIDAD | P25: EXPLOTACION MIXTA. | Q25: ELAB. CACAO, CHOCOLATE Y CONFIT. | W25: NO | Y25: SI | Z25: COMITE CENTRAL DE PRODUCTORES AGROPECUARIOS DE SAN ALEJANDRO | AA25: 0 | AB25: 23891.548 | AC25: NO | AL25: CACAO | AM25: 2025 | AN25: PAC | AU25: 46285.072 | AV25: 0.53333333
A26: 20170142773 | B26: COOPERATIVA AGRARIA CAFETALERA BAGUA GRANDE LIMITADA | C26: CAC.BAGUA GRANDE LTDA | D26: COOPERATIVAS, SAIS, CAPS | E26: 02 Cooperativa | F26: ACTIVO | G26: HABIDO | H26: 34202 | I26: 28840 | J26: 010701 | K26: AMAZONAS | L26: UTCUBAMBA | M26: BAGUA GRANDE | N26: JR. ISIDRO MAMANI NRO. 120 SECTOR SAN LUIS (FRENTE A LA PLAZA DE GANADO) | O26: IMPORTADOR/EXPORTADOR | P26: CULTIVO DE FRUTAS. | Q26: OTRAS ACTIVID.DE TIPO SERVICIO NCP | W26: SI | X26: S1645249 | Y26: SI | Z26: COOPERATIVA AGRARIA CAFETALERA BAGUA GRANDE LIMITADA | AA26: 9154082 | AB26: 0 | AC26: SI | AD26: 9070756.9 | AE26: 2026-05 | AF26: 402384.75 | AG26: 7 | AH26: saavedra gonzales clodomiro | AI26: TALLEDO TORRES RAUL MANUEL | AK26: 3 | AL26: CAFÉ | AM26: 2018-2019-2020-2023-2024 | AN26: PAC | AU26: 46285.072 | AV26: 0.73333333
A27: 20175089111 | B27: COOP. AG. SOCIEDAD AGRICOLA DE INTERES SOCIAL JOSE CARLOS MARIATEGUI LTDA.N°16 SUNCHUBAMBA Y ANEXOS | D27: COOPERATIVAS, SAIS, CAPS | E27: 02 Cooperativa | F27: ACTIVO | G27: HABIDO | H27: 34229 | I27: 26594 | J27: 060104 | K27: CAJAMARCA | L27: CAJAMARCA | M27: COSPAN | N27: CAL. CENTRO POBLADO SUNCHUBAMB NRO. S/N C.P. SUNCHUBAMBA | O27: EXPORTADOR | P27: EXPLOTACION MIXTA. | Q27: TRANSPORTE DE CARGA POR CARRETERA. | U27: 076607101 | V27: JCMRODRIGUEZ@GMAIL.COM | W27: SI | X27: S0170876 | Y27: SI | Z27: COOP. AG. SOCIEDAD AGRICOLA DE INTERES SOCIAL JOSE CARLOS MARIATEGUI LTDA.N°16 SUNCHUBAMBA Y ANEXOS | AA27: 17323 | AB27: 15800 | AC27: NO | AH27: sanchez gaitan esteban | AI27: ALCALDE INFANTE JORGE LUIS | AK27: 6 | AL27: DERIVADOS LACTEOS | AM27: 2023-2024 - 2025 | AN27: PAC | AU27: 46285.072 | AV27: 0.66666667
A28: 20183732031 | B28: ASOCIACION DE PRODUCTORES DE ROCOTO Y PRODUCTOS AGRICOLAS DE OXAPAMPA | D28: ASOCIACION | E28: 01 Asociación | F28: BAJA DE OFICIO | G28: HABIDO | H28: 45056 | I28: 45056 | J28: 190301 | K28: PASCO | L28: OXAPAMPA | M28: OXAPAMPA | N28: JR. MULLER NRO. S/N LA ESPERANZA (CDRA. 8 - PLANTA ROCOTERA) | O28: SIN ACTIVIDAD | P28: CULTIVO DE HORTALIZAS Y LEGUMBRES. | W28: NO | Y28: SI | Z28: ASOCIACION DE PRODUCTORES DE ROCOTO Y PRODUCTOS AGRICOLAS DE OXAPAMPA | AA28: 0 | AB28: 0 | AC28: NO | AL28: CAPSICUMS | AM28: 2019 | AN28: PAC | AU28: 46285.072 | AV28: 0.51111111
A29: 20200880448 | B29: COOPERATIVA AGRARIA CAFETALERA JORGE CHAVEZ LTDA | D29: COOPERATIVAS, SAIS, CAPS | F29: ACTIVO | G29: HABIDO | H29: 34321 | I29: 30231 | K29: CUSCO | L29: CALCA | M29: YANATILE | N29: NRO. S/N INT. S/N C.C.CUQUIPATA (CARRETERA KM.117) | O29: SIN ACTIVIDAD | P29: VTA. MAY. DE OTROS PRODUCTOS. | U29: 954 004 223 | V29: josecarloshanccotorres144@gmail.com | W29: NO | Y29: SI | Z29: COOPERATIVA AGRARIA CAFETALERA JORGE CHAVEZ LTDA | AA29: 0 | AB29: 0 | AC29: NO | AI29: Raul Castro Farfan | AO29: 29 | AP29: 7 | AQ29: 38 | AR29: Certificacion Organica, vigencia hasta 14/08/2026 | AS29: Vigencia organica hasta 26/03/2027 | AU29: 46285.072 | AV29: 0.57777778
A30: 20204028061 | B30: COOPERATIVA COMUNAL SAN PEDRO DE CAJAS | C30: COOP COMUNAL SN PEDRO DE CAJAS | D30: COOPERATIVAS, SAIS, CAPS | E30: 02 Cooperativa | F30: ACTIVO | G30: HABIDO | H30: 34341 | I30: 28351 | J30: 120708 | K30: JUNIN | L30: TARMA | M30: SAN PEDRO DE CAJAS | N30: JR. AREQUIPA Y GRAU NRO. SN (CERCA PLAZA PRINCIPAL) | O30: SIN ACTIVIDAD | P30: CRIA DE ANIMALES DOMESTICOS. | Q30: CRIA DE GANADO. | W30: NO | Y30: SI | Z30: COOPERATIVA COMUNAL SAN PEDRO DE CAJAS | AA30: 0 | AB30: 0 | AC30: NO | AL30: FIBRA DE ALPACA | AM30: 2019-2020 | AN30: PAC | AU30: 46285.072 | AV30: 0.55555556
A31: 20287980672 | B31: COMUNIDAD NATIVA TRES ISLAS | C31: CN. TRES ISCAS | D31: COMUNIDAD CAMPESINA, NATIVA | E31: 05 Comunidades Campesinas | F31: ACTIVO | G31: HABIDO | H31: 34906 | I31: 34881 | J31: 170101 | K31: MADRE DE DIOS | L31: TAMBOPATA | M31: TAMBOPATA | N31: CAR. TRES ISLAS KM. 18 COMUNIDAD TRES ISLAS (MISMO SALON COMUNAL TRES ISLAS) | O31: SIN ACTIVIDAD | P31: SILVICULTURA Y EXT. DE MADERA. | Q31: EXT. DE PIEDRA, ARENA Y ARCILLA. | W31: NO | Y31: SI | Z31: COMUNIDAD NATIVA TRES ISLAS | AA31: 74396 | AB31: 101505 | AC31: NO | AL31: AGUAJE | AM31: 2019 | AN31: PAC | AU31: 46285.072 | AV31: 0.55555556
A32: 20323699365 | B32: INVERSIONES PERUALP S.A. | C32: FLORALP | D32: SOCIEDAD ANONIMA | E32: 07 Otros | F32: ACTIVO | G32: HABIDO | H32: 35719 | I32: 35718 | J32: 190301 | K32: PASCO | L32: OXAPAMPA | M32: CHONTABAMBA | N32: CAR. PRINCIPAL KM. 2 BAR. BARRIO NUEVA FLORIDA (MARGEN DERECHA CARRETERA A CHONTABAMBA) | O32: IMPORTADOR/EXPORTADOR | P32: ELAB DE PRODUCTOS LACTEOS. | Q32: TRANSPORTE DE CARGA POR CARRETERA. | U32: 063462465 | V32: jduarte@floralpperu.com | W32: SI | X32: B0014648 | Y32: SI | Z32: INVERSIONES PERUALP S.A. | AA32: 0 | AB32: 0 | AC32: NO | AH32: MARIN FREY, HELGA SARA | AI32: MARIN FREY, JAIME ALFREDO | AJ32: JAIME ALBERTO MARIN FREY | AK32: 6 | AL32: DERIVADOS LACTEOS | AM32: 2018 | AN32: PAC | AU32: 46285.072 | AV32: 0.71111111
A33: 20326767400 | B33: ASOC.C.DE ACOPIO D.LECHE SR.D.L.MILAGROS | D33: ASOCIACION | E33: 01 Asociación | F33: ACTIVO | G33: HABIDO | H33: 35257 | I33: 35257 | J33: 040520 | K33: AREQUIPA | L33: CAYLLOMA | M33: LLUTA | N33: PARCELAMIENTO NRO. B (FRENTE A PARCELA B2-80 IRRIG. MAJES) | O33: SIN ACTIVIDAD | P33: ACTIVIDADES OTRAS ASOCIACIONES NCP. | Q33: ELAB DE PRODUCTOS LACTEOS. | R33: TRANSPORTE DE CARGA POR CARRETERA. | U33: 958996698 | V33: calmilagroscontabilidad@hotmail.com | W33: SI | X33: S2943858 | Y33: SI | Z33: ASOC.C.DE ACOPIO D.LECHE SR.D.L.MILAGROS | AA33: 394769.86 | AB33: 338125.16 | AC33: NO | AH33: OBANDO DE GUZMAN LILIA MARIA | AI33: OBANDO DE GUZMAN LILIA MARIA | AK33: 7 | AL33: DERIVADOS LACTEOS | AM33: 2022-2023-2024 - 2025 | AN33: PAC | AU33: 46285.072 | AV33: 0.68888889
A34: 20327993705 | B34: CENTRO DE ACOPIO DE LECHE LUIS PASTEUR | D34: ASOCIACION | E34: 01 Asociación | F34: ACTIVO | G34: HABIDO | H34: 35465 | I34: 35465 | J34: 040520 | K34: AREQUIPA | L34: CAYLLOMA | M34: MAJES | N34: SECCION NRO. D INT. 1 IRRIGACION MAJES (1ER. RAMAL ALTURA 908, PANAMERICANA SUR) | O34: SIN ACTIVIDAD | P34: ELAB DE PRODUCTOS LACTEOS. | Q34: TRANSPORTE DE CARGA POR CARRETERA. | W34: NO | Y34: SI | Z34: CENTRO DE ACOPIO DE LECHE LUIS PASTEUR | AA34: 0 | AB34: 246100 | AC34: NO | AL34: DERIVADOS LACTEOS | AM34: 2025 | AN34: PAC | AU34: 46285.072 | AV34: 0.53333333
A35: 20352266052 | B35: ASOCIACION DE PRODUCTORES DE PALMITO DE AGUAYTIA | D35: ASOCIACION | E35: 01 Asociación | F35: BAJA DE OFICIO | G35: NO HABIDO | H35: 40346 | I35: 40346 | J35: 250301 | K35: UCAYALI | L35: PADRE ABAD | M35: PADRE ABAD | N35: JR. GENARO PAREDES MZA. 167 LOTE. 2 JJ.VV. PAMPA YURAC | O35: SIN ACTIVIDAD | P35: CULTIVOS DE CEREALES. | W35: NO | Y35: SI | Z35: ASOCIACION DE PRODUCTORES DE PALMITO DE AGUAYTIA | AA35: 0 | AB35: 0 | AC35: NO | AL35: PALMITO | AM35: 2018-2019 | AN35: PAC | AU35: 46285.072 | AV35: 0.51111111
A36: 20352417018 | B36: COOPERATIVA AGRARIA DE CACAOTEROS TECNIFICADOS DE PADRE ABAD | C36: ACATPA | D36: COOPERATIVAS, SAIS, CAPS | E36: 02 Cooperativa | F36: SUSPENSION TEMPORAL | G36: HABIDO | H36: 39538 | I36: 39539 | J36: 250302 | K36: UCAYALI | L36: PADRE ABAD | M36: IRAZOLA | N36: MZA. Ñ LOTE. 10 SAN ALEJANDRO (JUNTA VECINAL MIGUEL GRAU) | O36: IMPORTADOR/EXPORTADOR | P36: CULTIVO DE FRUTAS. | Q36: OTROS TIPOS TRANSPORTE REG. VIA TER. | U36: 576387 | W36: SI | X36: S0374689 | Y36: SI | Z36: COOPERATIVA AGRARIA DE CACAOTEROS TECNIFICADOS DE PADRE ABAD | AA36: 0 | AB36: 0 | AC36: NO | AI36: ESPIRITU PRUDENCIO JACINTO GUILLERMO | AL36: CACAO | AM36: 2018 | AN36: PAC | AU36: 46285.072 | AV36: 0.62222222
A37: 20352423921 | B37: COOPERATIVA AGRARIA CAFETALERA DIVISORIA LTDA | D37: COOPERATIVAS, SAIS, CAPS | E37: 02 Cooperativa | F37: ACTIVO | G37: HABIDO | H37: 36964 | I37: 36964 | J37: 100605 | K37: HUANUCO | L37: LEONCIO PRADO | M37: LUYANDO | N37: CAL. CARRETERA TINGO MARIA-PU MZA. A LOTE. 23 ZONA HABILITACION URBANA (BALANZA MAPRESA) | O37: IMPORTADOR/EXPORTADOR | P37: VTA. MAY. DE MATERIAS PRIMAS AGROPEC. | Q37: ELAB DE OTROS PROD. ALIMENTICIOS. | U37: 947595969 | V37: gerencia@cacdivisoria.com | W37: SI | X37: S0596909 | Y37: SI | Z37: COOPERATIVA AGRARIA CAFETALERA DIVISORIA LTDA | AA37: 0 | AB37: 0 | AC37: NO | AH37: PARRA CABALLERO MARIO AQUILES | AI37: RODRIGUEZ CIRIACO EUGENIO MARIO | AK37: 5 | AL37: CAFÉ | AM37: 2018 | AN37: PAC | AU37: 46285.072 | AV37: 0.66666667
A38: 20365575674 | B38: COMUNIDAD CAMPESINA SAN ANTONIO DE RANCAS | D38: COMUNIDAD CAMPESINA, NATIVA | E38: 05 Comunidades Campesinas | F38: ACTIVO | G38: HABIDO | H38: 36118 | I38: 36100 | J38: 190109 | K38: PASCO | L38: PASCO | M38: SIMON BOLIVAR | N38: CAL. SUCRE NRO. 127 RANCAS (SEGUNDO PISO FRENTE A LA BODEGA CHAVEZ) | O38: SIN ACTIVIDAD | P38: EXPLOTACION MIXTA. | Q38: FAB. DE CALZADO. | W38: SI | X38: S2209855 | Y38: SI | Z38: COMUNIDAD CAMPESINA SAN ANTONIO DE RANCAS | AA38: 156032 | AB38: 291119.08 | AC38: NO | AH38: ROBLES CHAVEZ PERCY GODOFREDO | AI38: 04045388 | AK38: 2 | AL38: DERIVADOS LACTEOS | AM38: 2024 - 2025 | AN38: PAC | AU38: 46285.072 | AV38: 0.62222222
A39: 20393152207 | B39: COOPERATIVA AGRO INDUSTRIAL APCTVASH | D39: COOPERATIVAS, SAIS, CAPS | E39: 02 Cooperativa | F39: ACTIVO | G39: HABIDO | H39: 44069 | I39: 44075 | J39: 250301 | K39: UCAYALI | L39: PADRE ABAD | M39: PADRE ABAD | N39: KM. 6 P.J. CASERIO SHAMBILLO | O39: SIN ACTIVIDAD | P39: VTA. MAY. DE MATERIAS PRIMAS AGROPEC. | Q39: ELAB. CACAO, CHOCOLATE Y CONFIT. | R39: OTROS TIPOS DE VENTA POR MENOR. | U39: 061-794794 | W39: SI | X39: S0490351 | Y39: SI | Z39: COOPERATIVA AGRO INDUSTRIAL APCTVASH | AA39: 34611.17 | AB39: 0 | AC39: NO | AI39: GARCIA GUTIERREZ GERMAN | AL39: CACAO | AM39: 2024 | AN39: PAC | AU39: 46285.072 | AV39: 0.62222222
A40: 20393335620 | B40: ASOCIACIÓN DE PRODUCTORES ECOLÓGICOS DEL CASERÍO SAN CRISTÓBAL DE AGUA BLANCA | D40: ASOCIACION | E40: 01 Asociación | F40: BAJA DE OFICIO | G40: HABIDO | H40: 41066 | I40: 41066 | J40: 250102 | K40: UCAYALI | L40: CORONEL PORTILLO | M40: CAMPOVERDE | N40: JR. SAN MARTIN MZA. 57 LOTE. 5 (ENTRANDO POR EL MERCADO 250 METROS) | O40: SIN ACTIVIDAD | P40: CULTIVOS DE CEREALES. | W40: NO | Y40: SI | Z40: ASOCIACIÓN DE PRODUCTORES ECOLÓGICOS DEL CASERÍO SAN CRISTÓBAL DE AGUA BLANCA | AA40: 0 | AB40: 0 | AC40: NO | AL40: PANELA | AM40: 2018 | AN40: PAC | AU40: 46285.072 | AV40: 0.51111111
A41: 20393415062 | B41: ASOCIACION AGROINDUSTRIAS PROGRESO | D41: ASOCIACION | E41: 01 Asociación | F41: ACTIVO | G41: HABIDO | H41: 41150 | I41: 41150 | J41: 250301 | K41: UCAYALI | L41: PADRE ABAD | M41: PADRE ABAD | N41: AV. LAS INDUSTRIAS MZA. A LOTE. 1 CAS. MARIELA (AGUAYTIA) | O41: SIN ACTIVIDAD | P41: TRANSPORTE DE CARGA POR CARRETERA. | Q41: ELAB DE OTROS PROD. ALIMENTICIOS. | R41: OTROS TIPOS DE VENTA AL POR MENOR. | U41: 981676442 | V41: FVARASCOMITIVOS@MAIL.COM | W41: SI | X41: B0788802 | Y41: SI | Z41: ASOCIACION AGROINDUSTRIAS PROGRESO | AA41: 32204.112 | AB41: 0 | AC41: NO | AH41: vargas cometivos francisco | AI41: FRANCISCO VARAS COMETIVOS | AK41: 6 | AL41: PLÁTANO | AM41: 2022-2023-2024 | AN41: PAC | AU41: 46285.072 | AV41: 0.68888889
A42: 20393449471 | B42: CENTRO UNICO DE AGRICULTORES PLATANEROS DE LA PROVINCIA DE PADRE ABAD | C42: CUAPPPA | D42: ASOCIACION | E42: 01 Asociación | F42: BAJA DE OFICIO | G42: HABIDO | H42: 39652 | I42: 39661 | J42: 250301 | K42: UCAYALI | L42: PADRE ABAD | M42: PADRE ABAD | N42: CAR. FEDERICO BASADRE MZA. 155 LOTE. 4A JUNTA VECINAL PAMPAYURAC | O42: SIN ACTIVIDAD | P42: ACTIVIDADES OTRAS ASOCIACIONES NCP. | U42: 061-961956251 | W42: SI | X42: S0433032 | Y42: SI | Z42: CENTRO UNICO DE AGRICULTORES PLATANEROS DE LA PROVINCIA DE PADRE ABAD | AA42: 0 | AB42: 0 | AC42: NO | AI42: ESPINOZA GONZALES VICTOR | AL42: PLÁTANO | AM42: 2019 | AN42: PAC | AU42: 46285.072 | AV42: 0.6
A43: 20393576660 | B43: ASOCIACION DE PRODUCTORES ECOLOGICOS EL PIMENTAL | D43: ASOCIACION | E43: 01 Asociación | F43: ACTIVO | G43: HABIDO | H43: 40932 | I43: 40932 | J43: 250102 | K43: UCAYALI | L43: CORONEL PORTILLO | M43: CAMPOVERDE | N43: JR. ISAO SASAGAWA MZA. 1 LOTE. 01A CAS. PIMENTAL (CARRETERA TOURNAVISTA 5KM) | O43: SIN ACTIVIDAD | P43: ACTIVIDADES OTRAS ASOCIACIONES NCP. | W43: NO | Y43: SI | Z43: ASOCIACION DE PRODUCTORES ECOLOGICOS EL PIMENTAL | AA43: 0 | AB43: 0 | AC43: NO | AL43: CAPSICUMS | AM43: 2018-2019-2021 | AN43: PAC | AU43: 46285.072 | AV43: 0.51111111
A44: 20393593670 | B44: COMITE CENTRAL CON DESARROLLO AL FUTURO DE CURIMANA | D44: ASOCIACION | E44: 01 Asociación | F44: BAJA DE OFICIO | G44: NO HABIDO | H44: 40310 | I44: 40330 | J44: 250303 | K44: UCAYALI | L44: PADRE ABAD | M44: CURIMANA | N44: JR. GARIBALDI BARDALES MZA. 54 LOTE. 6 (AL COSTADO DE LA PNP CURIMANA) | O44: IMPORTADOR/EXPORTADOR | P44: VTA. MAY. DE MATERIAS PRIMAS AGROPEC. | Q44: OTROS TIPOS DE VENTA AL POR MENOR. | W44: NO | Y44: SI | Z44: COMITE CENTRAL CON DESARROLLO AL FUTURO DE CURIMANA | AA44: 0 | AB44: 0 | AC44: NO | AL44: CACAO | AM44: 2019 | AN44: PAC | AU44: 46285.072 | AV44: 0.53333333
A45: 20393692228 | B45: COOPERATIVA AGRARIA CACAOTERA SAN ALEJANDRO LTDA | C45: CACSA | D45: COOPERATIVAS, SAIS, CAPS | E45: 02 Cooperativa | F45: ACTIVO | G45: HABIDO | H45: 40679 | I45: 40679 | J45: 250302 | K45: UCAYALI | L45: PADRE ABAD | M45: IRAZOLA | N45: CAL. LAS FLORES NRO. S/N SAN ALEJANDRO (A 1 KM. DEL BANCO DE LA NACION) | O45: EXPORTADOR | P45: CULTIVO DE FRUTAS. | Q45: VTA. MAY. DE MATERIAS PRIMAS AGROPEC. | W45: NO | Y45: SI | Z45: COOPERATIVA AGRARIA CACAOTERA SAN ALEJANDRO LTDA | AA45: 0 | AB45: 55074.5 | AC45: NO | AL45: CACAO | AM45: 2025 | AN45: PAC | AU45: 46285.072 | AV45: 0.55555556
A46: 20393757290 | B46: ASOCIACION DE AGRICULTORES DEL CENTRO POBLADO SAN JOSE DE YARINACOCHA | D46: ASOCIACION | E46: 01 Asociación | F46: BAJA DE OFICIO | G46: HABIDO | H46: 45435 | I46: 45435 | J46: 250105 | K46: UCAYALI | L46: CORONEL PORTILLO | M46: YARINACOCHA | N46: JR. TUPAC AMARU MZA. 12 LOTE. 06 C.P. SAN JOSE | O46: SIN ACTIVIDAD | P46: CULTIVO DE HORTALIZAS Y LEGUMBRES. | Q46: CULTIVO DE FRUTAS. | W46: NO | Y46: SI | Z46: ASOCIACION DE AGRICULTORES DEL CENTRO POBLADO SAN JOSE DE YARINACOCHA | AA46: 0 | AB46: 0 | AC46: NO | AL46: CAMU CAMU | AM46: 2021-2022-2023 | AN46: PAC | AU46: 46285.072 | AV46: 0.53333333
A47: 20393786044 | B47: COOPERATIVA AGRARIA CAFETALERA COORDILLERA AZUL DE UCAYALI LTDA | D47: COOPERATIVAS, SAIS, CAPS | E47: 02 Cooperativa | F47: ACTIVO | G47: HABIDO | H47: 41003 | I47: 41155 | J47: 250301 | K47: UCAYALI | L47: PADRE ABAD | M47: PADRE ABAD | N47: CAR. FEDERICO BASADRE MZA. 8 LOTE. 11 (POR LA MUNICIPALDAD CP DIVISORIA) | O47: SIN ACTIVIDAD | P47: CULTIVO DE FRUTAS. | W47: NO | Y47: SI | Z47: COOPERATIVA AGRARIA CAFETALERA COORDILLERA AZUL DE UCAYALI LTDA | AA47: 0 | AB47: 0 | AC47: NO | AL47: CAFÉ | AM47: 2018-2019 | AN47: PAC | AU47: 46285.072 | AV47: 0.51111111
A48: 20393816211 | B48: COOPERATIVA AGRARIA SAN JUAN BAUTISTA | D48: COOPERATIVAS, SAIS, CAPS | E48: 02 Cooperativa | F48: ACTIVO | G48: HABIDO | H48: 42299 | I48: 42299 | J48: 250302 | K48: UCAYALI | L48: PADRE ABAD | M48: IRAZOLA | N48: CAR. FEDERICO BASADRE KM. 130 C.P. SAN JUAN BAUTISTA (FRENTE AL CONSEJO MUNICIPAL) | O48: IMPORTADOR/EXPORTADOR | P48: EXPLOTACION MIXTA. | Q48: CULTIVOS DE CEREALES. | W48: NO | Y48: SI | Z48: COOPERATIVA AGRARIA SAN JUAN BAUTISTA | AA48: 73430.4 | AB48: 160363.5 | AC48: NO | AL48: CACAO | AM48: 2024 - 2025 | AN48: PAC | AU48: 46285.072 | AV48: 0.53333333
A49: 20393882868 | B49: COOPERATIVA AGRARIA ASCAH | D49: COOPERATIVAS, SAIS, CAPS | E49: 02 Cooperativa | F49: ACTIVO | G49: HABIDO | H49: 42227 | I49: 42227 | J49: 250301 | K49: UCAYALI | L49: PADRE ABAD | M49: PADRE ABAD | N49: JR. ANCASH ULTIMA CDRA NRO. S/N C.P. HUIPOCA (AL COSTADO DEL I.E. ELIAS AGUIRRE) | O49: SIN ACTIVIDAD | P49: ELAB. CACAO, CHOCOLATE Y CONFIT. | Q49: CULTIVO DE FRUTAS. | W49: NO | Y49: SI | Z49: COOPERATIVA AGRARIA ASCAH | AA49: 0 | AB49: 0 | AC49: NO | AL49: CACAO | AM49: 2019-2020 | AN49: PAC | AU49: 46285.072 | AV49: 0.53333333
A50: 20393972000 | B50: ASOCIACION DE MUJERES EMPRENDEDORAS FLOR DE BOQUERON | D50: ASOCIACION | E50: 01 Asociación | F50: ACTIVO | G50: HABIDO | H50: 41619 | I50: 41619 | J50: 250303 | K50: UCAYALI | L50: PADRE ABAD | M50: BOQUERON | N50: CAL. 23 DE SETIEMBRE MZA. I LOTE. 17 | O50: SIN ACTIVIDAD | P50: ELAB. CACAO, CHOCOLATE Y CONFIT. | Q50: ELAB. PROD. DE PANADERIA. | R50: RESTAURANTES, BARES Y CANTINAS. | U50: 937440761 | V50: godoyyanac@gmail.com | W50: SI | X50: S1555602 | Y50: SI | Z50: ASOCIACION DE MUJERES EMPRENDEDORAS FLOR DE BOQUERON | AA50: 0 | AB50: 0 | AC50: NO | AH50: GODOY YANAC NILDA | AI50: GODOY YANAC NILDA | AK50: 6 | AL50: CACAO | AM50: 2021 | AN50: PAC | AU50: 46285.072 | AV50: 0.68888889
A51: 20393981173 | B51: ASOCIACION DE PRODUCTORES AGRARIOS SANTA ELENA | D51: ASOCIACION | E51: 01 Asociación | F51: ACTIVO | G51: HABIDO | H51: 41653 | I51: 41653 | J51: 250104 | K51: UCAYALI | L51: CORONEL PORTILLO | M51: CALLERIA | N51: JR. NICOLAS DE PIEROLA NRO. 398 (POR MAESTRO) | O51: SIN ACTIVIDAD | P51: ACTIVIDADES OTRAS ASOCIACIONES NCP. | W51: SI | X51: S0846945 | Y51: SI | Z51: ASOCIACION DE PRODUCTORES AGRARIOS SANTA ELENA | AA51: 0 | AB51: 0 | AC51: NO | AH51: LOPEZ HARO, RICARLOS NILSON | AI51: LOPEZ HARO, RICARLOS NILSON | AK51: 1 | AL51: PLÁTANO | AM51: 2019-2020-2021-2022 | AN51: PAC | AU51: 46285.072 | AV51: 0.6
A52: 20402648504 | B52: COOPERATIVA AGRARIA KIVINAKI | C52: AGRO CAFÉ | D52: COOPERATIVAS, SAIS, CAPS | E52: 02 Cooperativa | F52: ACTIVO | G52: HABIDO | H52: 36307 | I52: 36312 | J52: 120301 | K52: JUNIN | L52: CHANCHAMAYO | M52: PERENE | N52: AV. MARGINAL MZA. A LOTE. 1 C.P. SAN FERNANDO DE KIVINAKI (A 2 CUADRAS DEL CENTRO DE SALUD) | O52: EXPORTADOR | P52: ELAB. FRUTAS, LEG. Y HORTALIZAS. | Q52: CULTIVOS DE CEREALES. | R52: CULTIVO DE FRUTAS. | W52: SI | X52: S0750480 | Y52: SI | Z52: COOPERATIVA AGRARIA KIVINAKI | AA52: 15042.92 | AB52: 530 | AC52: SI | AD52: 1244035.8 | AE52: 2025-09 | AF52: 1244035.8 | AG52: 2 | AL52: NARANJA | AM52: 2023-2024 - 2025 | AN52: PAC | AU52: 46285.072 | AV52: 0.68888889
A53: 20404057805 | B53: COOPERATIVA AGRARIA ACOPAGRO LTDA | D53: COOPERATIVAS, SAIS, CAPS | F53: ACTIVO | G53: HABIDO | H53: 35634 | I53: 35634 | K53: SAN MARTIN | L53: MARISCAL CACERES | M53: JUANJUI | N53: JR. ARICA NRO. 284 | O53: IMPORTADOR/EXPORTADOR | P53: CULTIVOS DE CEREALES. | Q53: TRANSPORTE DE CARGA POR CARRETERA. | U53: 042545190 | V53: contabilidad@acopagro.com.pe | W53: SI | X53: S0631562 | Y53: SI | Z53: COOPERATIVA AGRARIA ACOPAGRO LTDA | AA53: 0 | AB53: 0 | AC53: SI | AD53: 19542085 | AE53: 2026-02 | AF53: 925766.4 | AG53: 4 | AH53: LANARES SALAS MARTHA | AI53: RIOS NUÑEZ SEGUNDO GONZALO | AK53: 6 | AU53: 46285.072 | AV53: 0.64444444
A54: 20406542671 | B54: SOCIEDAD PERUANA DE CRIADORES DE ALPACAS Y LLAMAS DE MACUSANI | C54: SPAR MACUSANI | D54: ASOCIACION | E54: 01 Asociación | F54: ACTIVO | G54: HABIDO | H54: 41976 | I54: 41976 | J54: 210301 | K54: PUNO | L54: CARABAYA | M54: MACUSANI | N54: AV. CENTENARIO NRO. 118 CERCADO (A MEDIA CUADRA DE LA PLAZA DE ARMAS) | O54: SIN ACTIVIDAD | P54: CRIA DE ANIMALES DOMESTICOS. | W54: SI | X54: S1746405 | Y54: SI | Z54: SOCIEDAD PERUANA DE CRIADORES DE ALPACAS Y LLAMAS DE MACUSANI | AA54: 0 | AB54: 0 | AC54: NO | AI54: ROSELLO VILCA WALDIR FREDY | AK54: 1 | AL54: FIBRA DE ALPACA | AM54: 2019-2020-2021-2022-2023 | AN54: PAC | AU54: 46285.072 | AV54: 0.6
A55: 20407808666 | B55: COOPERATIVA AGRARIA PURIFOR - COOP PURIFOR | C55: COOP PURIFOR | D55: COOPERATIVAS, SAIS, CAPS | E55: 02 Cooperativa | F55: ACTIVO | G55: HABIDO | H55: 39772 | I55: 39783 | J55: 020507 | K55: ANCASH | L55: BOLOGNESI | M55: COLQUIOC | N55: JR. SAN JUAN NRO. SN C.P. CHASQUITAMBO | O55: SIN ACTIVIDAD | P55: SERVICIOS AGRICOLAS, GANADERAS. | Q55: VTA. MIN. EN PUESTOS DE VENTA. | U55: 985747811 | V55: COOPPURIFOR@GMAIL.COM | W55: SI | X55: S2073812 | Y55: SI | Z55: COOPERATIVA AGRARIA PURIFOR - COOP PURIFOR | AA55: 362155.2 | AB55: 488080 | AC55: NO | AH55: HUERTA REYNALTE RAFAEL DINO | AI55: GUILLEN INOCENTE FERNANDO | AK55: 5 | AL55: PALTA | AM55: 2022-2023-2024 - 2025 | AN55: PAC | AU55: 46285.072 | AV55: 0.68888889
A56: 20447686407 | B56: ASOCIACION DE PRODUCTORES DE PIÑA DEL VALLE DE SAN GABAN | D56: ASOCIACION | E56: 01 Asociación | F56: ACTIVO | G56: HABIDO | H56: 44120 | I56: 44120 | J56: 210309 | K56: PUNO | L56: CARABAYA | M56: SAN GABAN | N56: NRO. SN URB. ORINETAL (A 1 CDRA DE LA PLAZA DE ARMAS) | O56: SIN ACTIVIDAD | P56: OTRAS ACTIVID.DE TIPO SERVICIO NCP | Q56: VTA. MIN. ALIMENTOS, BEBIDAS, TABACO. | R56: EXPLOTACION MIXTA. | W56: NO | Y56: SI | Z56: ASOCIACION DE PRODUCTORES DE PIÑA DEL VALLE DE SAN GABAN | AA56: 0 | AB56: 0 | AC56: NO | AL56: PIÑA | AM56: 2019 | AN56: PAC | AU56: 46285.072 | AV56: 0.55555556
A57: 20447688281 | B57: SOCIEDAD PERUANA DE CRIADORES DE ALPACAS Y LLAMAS DE PARATIA | D57: ASOCIACION | E57: 01 Asociación | F57: ACTIVO | G57: HABIDO | H57: 46273 | I57: 46273 | J57: 210602 | K57: PUNO | L57: LAMPA | M57: PARATIA | N57: NRO. ___ C.C. LLANCA (AL FRENTE DE LA ESCUELA) | O57: SIN ACTIVIDAD | P57: CRIA DE ANIMALES DOMESTICOS. | U57: 332522 | V57: CONTABLECIA@OUTLOOK.COM | W57: SI | X57: S0737671 | Y57: SI | Z57: SOCIEDAD PERUANA DE CRIADORES DE ALPACAS Y LLAMAS DE PARATIA | AA57: 0 | AB57: 228581.3 | AC57: NO | AH57: CAJIA CUTIPA JACINTO VALERIO | AI57: CAJIA CUTIPA JACINTO VALERIO | AK57: 6 | AL57: FIBRA DE ALPACA | AM57: 2025 | AN57: PAC | AU57: 46285.072 | AV57: 0.64444444
A58: 20447888701 | B58: COOPERATIVA AGRARIA INDUSTRIAL SAN GABAN LTDA. | D58: COOPERATIVAS, SAIS, CAPS | E58: 02 Cooperativa | F58: ACTIVO | G58: HABIDO | H58: 39577 | I58: 40299 | J58: 210309 | K58: PUNO | L58: CARABAYA | M58: SAN GABAN | N58: JR. LA CULTURA NRO. SN URB. NUEVO MIRAFLORES | O58: SIN ACTIVIDAD | P58: SERVICIOS AGRICOLAS, GANADERAS. | Q58: ELAB. CACAO, CHOCOLATE Y CONFIT. | R58: EXPLOTACION MIXTA. | U58: 051331522 | V58: anibal_bk3@hotmail.com | W58: SI | X58: S0657969 | Y58: SI | Z58: COOPERATIVA AGRARIA INDUSTRIAL SAN GABAN LTDA. | AA58: 0 | AB58: 49800.512 | AC58: NO | AH58: miguel gabriel bustinza montesinos | AI58: MACHACA PARI ALI NEAL | AK58: 5 | AL58: CACAO | AM58: 2025 | AN58: PAC | AU58: 46285.072 | AV58: 0.68888889
A59: 20448031358 | B59: ASOCIACION DE PRODUCTORES DE PAPAYA ANDINA ORGÁNICA DE LA PROVINCIA DE SANDIA | D59: ASOCIACION | E59: 01 Asociación | F59: BAJA DE OFICIO | G59: NO HABIDO | H59: 40868 | I59: 40868 | J59: 211201 | K59: PUNO | L59: SANDIA | M59: SANDIA | N59: JR. LIMA NRO. 322 | O59: SIN ACTIVIDAD | P59: CULTIVO DE FRUTAS. | Q59: ELAB DE OTROS PROD. ALIMENTICIOS. | W59: SI | X59: S2194874 | Y59: SI | Z59: ASOCIACION DE PRODUCTORES DE PAPAYA ANDINA ORGÁNICA DE LA PROVINCIA DE SANDIA | AA59: 0 | AB59: 0 | AC59: NO | AH59: SANCA QUISPE ROLANDO | AI59: SANCA QUISPE ROLANDO | AK59: 1 | AL59: PAPAYITA ANDINA | AM59: 2018-2019-2020-2021-2022-2023 | AN59: PAC | AU59: 46285.072 | AV59: 0.62222222
A60: 20448277781 | B60: COOPERATIVA AGRARIA INDUSTRIALIZADA CABANA LTDA | C60: COOPAIN CABANA | D60: COOPERATIVAS, SAIS, CAPS | E60: 02 Cooperativa | F60: ACTIVO | G60: HABIDO | H60: 40590 | I60: 40603 | J60: 211102 | K60: PUNO | L60: SAN ROMAN | M60: CABANA | N60: JR. LIMA NRO. SN (INGRESO DEL DISTRITO DE CABANA) | O60: IMPORTADOR/EXPORTADOR | P60: EXPLOTACION MIXTA. | Q60: ELAB. DE PRODUCTOS DE MOLINERIA. | R60: ELAB. PROD. DE PANADERIA. | U60: 980278888 | V60: coopain.tesoreria@gmail.com | W60: SI | X60: S1070803 | Y60: SI | Z60: COOPERATIVA AGRARIA INDUSTRIALIZADA CABANA LTDA | AA60: 2235307.9 | AB60: 1143706.3 | AC60: SI | AD60: 542368.16 | AE60: 2026-01 | AF60: 63080 | AG60: 1 | AH60: MIRANDA ALEJO RUFO | AI60: COILA PARICAHUA ABELARDO | AK60: 3 | AL60: QUINUA Y OTROS GRANOS | AM60: 2019-2020-2021-2022-2023 | AN60: PAC | AU60: 46285.072 | AV60: 0.8
A61: 20448748902 | B61: INDUSTRIAS AGROALIMENTOS EL ESTABLO SOCIEDAD COMERCIAL DE RESPONSABILIDAD LIMITADA | D61: SOC.COM.RESPONS. LTDA | E61: 07 Otros | F61: ACTIVO | G61: HABIDO | H61: 41432 | I61: 41522 | J61: 210701 | K61: PUNO | L61: LAMPA | M61: LAMPA | N61: DOBLE CANCHA TIKA ESKINA KM. 24 C.C. DE CATACHA (CARRETERA JULIACA LAMPA KM 24) | O61: SIN ACTIVIDAD | P61: ELAB DE OTROS PROD. ALIMENTICIOS. | S61: SI, incorporado al Régimen de Buenos Contribuyentes (Resolución N° 2130050004348) a partir del 01/02/2017 | W61: NO | Y61: SI | Z61: INDUSTRIAS AGROALIMENTOS EL ESTABLO SOCIEDAD COMERCIAL DE RESPONSABILIDAD LIMITADA | AA61: 0 | AB61: 0 | AC61: NO | AL61: DERIVADOS LACTEOS | AM61: 2018 | AN61: PAC | AU61: 46285.072 | AV61: 0.53333333
A62: 20448766471 | B62: COOPERATIVA DE SERVICIOS SAN SANTIAGO - ACORA | D62: COOPERATIVAS, SAIS, CAPS | E62: 02 Cooperativa | F62: ACTIVO | G62: HABIDO | H62: 41463 | I62: 41718 | J62: 210101 | K62: PUNO | L62: PUNO | M62: ACORA | N62: CAR. PUNO-DESAGUADERO KM. 1397 SEC. WISCALLPUTI CARITAMAYA (EN LA MISMA MUNICIPALIDAD DE CARITAMAYA) | O62: SIN ACTIVIDAD | P62: ELAB DE PRODUCTOS LACTEOS. | Q62: SERVICIOS AGRICOLAS, GANADERAS. | R62: EXPLOTACION MIXTA. | W62: NO | Y62: SI | Z62: COOPERATIVA DE SERVICIOS SAN SANTIAGO - ACORA | AA62: 530220 | AB62: 867958 | AC62: NO | AL62: DERIVADOS LACTEOS | AM62: 2023-2024 - 2025 | AN62: PAC | AU62: 46285.072 | AV62: 0.55555556
A63: 20448791310 | B63: COOPERATIVA AGROINDUSTRIAL DE PRODUCTORES AGROPECUARIOS CABANA LIMITADA | D63: COOPERATIVAS, SAIS, CAPS | E63: 02 Cooperativa | F63: ACTIVO | G63: HABIDO | H63: 41508 | I63: 41508 | J63: 211102 | K63: PUNO | L63: SAN ROMAN | M63: CABANA | N63: AV. SANTA ASUNCION NRO. SN CABANA (AL COSTADO DE I.E.PRIMARIA 70556) | O63: SIN ACTIVIDAD | P63: ELAB DE PRODUCTOS LACTEOS. | Q63: OTRAS ACTIVIDADES EMPRESARIALES NCP. | W63: NO | Y63: SI | Z63: COOPERATIVA AGROINDUSTRIAL DE PRODUCTORES AGROPECUARIOS CABANA LIMITADA | AA63: 0 | AB63: 664790 | AC63: NO | AL63: DERIVADOS LACTEOS | AM63: 2025 | AN63: PAC | AU63: 46285.072 | AV63: 0.53333333
A64: 20448807500 | B64: CONSORCIO ALPAQUERO PERU EXPORT | D64: CONTRATOS COLABORACION EMPRESARIAL | E64: 07 Otros | F64: SUSPENSION TEMPORAL | G64: HABIDO | H64: 41537 | I64: 41537 | J64: 211101 | K64: PUNO | L64: SAN ROMAN | M64: JULIACA | N64: JR. AZANGARO NRO. 338 BARRIO ZARUMILLA (CERCA AL COLEGIO DE ABOGADOS) | O64: EXPORTADOR | P64: CRIA DE GANADO. | W64: NO | Y64: SI | Z64: CONSORCIO ALPAQUERO PERU EXPORT | AA64: 0 | AB64: 0 | AC64: NO | AL64: FIBRA DE ALPACA | AM64: 2018-2019-2020-2021-2022-2023 | AN64: PAC | AU64: 46285.072 | AV64: 0.51111111
A65: 20448843051 | B65: ASOCIACION DE PRODUCTORES AGROPECUARIOS PIEDRA BLANCA DE CHALLAPAMPA | D65: ASOCIACION | E65: 01 Asociación | F65: ACTIVO | G65: HABIDO | H65: 44158 | I65: 44166 | J65: 211303 | K65: PUNO | L65: YUNGUYO | M65: COPANI | N65: YUNGUYO - COPANI SAM 38 NRO. -- (SECTOR MARCACHANI) | O65: SIN ACTIVIDAD | P65: CRIA DE GANADO. | Q65: EXPLOTACION MIXTA. | W65: NO | Y65: SI | Z65: ASOCIACION DE PRODUCTORES AGROPECUARIOS PIEDRA BLANCA DE CHALLAPAMPA | AA65: 0 | AB65: 0 | AC65: NO | AL65: HABA | AM65: 2024 | AN65: PAC | AU65: 46285.072 | AV65: 0.53333333
A66: 20449558902 | B66: ASOCIACION CIVIL DE MANTENIMIENTO VIAL Y DESARROLLO AGROPECUARIO CALVARIO | D66: ASOCIACION | E66: 01 Asociación | F66: ACTIVO | G66: HABIDO | H66: 36473 | I66: 36479 | J66: 050501 | K66: AYACUCHO | L66: LA MAR | M66: SAN MIGUEL | N66: NRO. S/N CONCEJO MENOR PATIBAMBA (CENTRO POBLADO DE PATIBAMBA) | O66: SIN ACTIVIDAD | P66: CONSTRUCCION EDIFICIOS COMPLETOS. | Q66: EXPLOTACION MIXTA. | U66: 966630480 | V66: gpg1956@hotmail.com | W66: SI | X66: S0125910 | Y66: SI | Z66: ASOCIACION CIVIL DE MANTENIMIENTO VIAL Y DESARROLLO AGROPECUARIO CALVARIO | AA66: 0 | AB66: 0 | AC66: NO | AH66: NAVARRO CANALES CIPRIANO | AI66: NAVARRO CANALES CIPRIANO | AK66: 5 | AL66: PALTA | AM66: 2019-2020-2021-2022 | AN66: PAC | AU66: 46285.072 | AV66: 0.66666667
A67: 20450105113 | B67: COOPERATIVA AGRARIA DEL PALMITO APROPAL | D67: COOPERATIVAS, SAIS, CAPS | E67: 02 Cooperativa | F67: ACTIVO | G67: HABIDO | H67: 39231 | I67: 39234 | J67: 220504 | K67: SAN MARTIN | L67: LAMAS | M67: CAYNARACHI | N67: AV. LA MARGINAL NRO. 177 BAR. SAN MARTIN -CPM.ALIANZA (C.P.M. ALIANZA / CERCA A PAMPA HERMOSA) | O67: IMPORTADOR/EXPORTADOR | P67: ELAB. FRUTAS, LEG. Y HORTALIZAS. | Q67: OTROS TIPOS DE VENTA AL POR MENOR. | R67: CULTIVO DE HORTALIZAS Y LEGUMBRES. | S67: SI, incorporado al Régimen de Buenos Contribuyentes (Resolución N° 1830050014304) a partir del 01/02/2022 | W67: NO | Y67: SI | Z67: COOPERATIVA AGRARIA DEL PALMITO APROPAL | AA67: 0 | AB67: 0 | AC67: SI | AD67: 826091.89 | AE67: 2026-03 | AF67: 116039.69 | AG67: 4 | AL67: PALMITO | AM67: 2019-2020-2021-2022-2023 | AN67: PAC | AU67: 46285.072 | AV67: 0.66666667
A68: 20450189201 | B68: COOPERATIVA DE SERVICIOS MULTIPLES FRUTOS DE SELVA | C68: FRUTOS DE SELVA | D68: COOPERATIVAS, SAIS, CAPS | E68: 02 Cooperativa | F68: ACTIVO | G68: HABIDO | H68: 39056 | I68: 39056 | J68: 220101 | K68: SAN MARTIN | L68: MOYOBAMBA | M68: MOYOBAMBA | N68: CAR. FERNANDO BELAUNDE TERRY KM. 491 SEC. PERLA DE INDAÑE | O68: IMPORTADOR/EXPORTADOR | P68: SERVICIOS AGRICOLAS, GANADERAS. | Q68: TRANSPORTE DE CARGA POR CARRETERA. | W68: NO | Y68: SI | Z68: COOPERATIVA DE SERVICIOS MULTIPLES FRUTOS DE SELVA | AA68: 0 | AB68: 0 | AC68: NO | AL68: CAFÉ | AM68: 2021-2022-2023-2024 | AN68: PAC | AU68: 46285.072 | AV68: 0.55555556
A69: 20450207544 | B69: COOPERATIVA AGRARIA UCHIZA LTDA | C69: CAU LTDA | D69: COOPERATIVAS, SAIS, CAPS | E69: 02 Cooperativa | F69: ACTIVO | G69: HABIDO | H69: 39127 | I69: 39173 | J69: 221005 | K69: SAN MARTIN | L69: TOCACHE | M69: UCHIZA | N69: AV. RICARDO PALMA NRO. C-16 (COSTADO DEL INSTITUTO TECNOLOGICO FVC) | O69: IMPORTADOR/EXPORTADOR | P69: CULTIVOS DE CEREALES. | Q69: PESCA, EXPLOT. CRIADEROS DE PECES. | W69: NO | Y69: SI | Z69: COOPERATIVA AGRARIA UCHIZA LTDA | AA69: 0 | AB69: 0 | AC69: NO | AL69: CACAO | AM69: 2019-2020 | AN69: PAC | AU69: 46285.072 | AV69: 0.55555556
A70: 20450242021 | B70: COOPERATIVA DE SERVICIOS MULTIPLES CAPEMA | C70: CAPEMA | D70: COOPERATIVAS, SAIS, CAPS | E70: 02 Cooperativa | F70: ACTIVO | G70: HABIDO | H70: 39265 | I70: 39265 | J70: 220804 | K70: SAN MARTIN | L70: RIOJA | M70: NUEVA CAJAMARCA | N70: AV. CAJAMARCA SUR NRO. 1135 | O70: EXPORTADOR | P70: ACTIVIDADES OTRAS ASOCIACIONES NCP. | Q70: VTA. MAY. DE MATERIAS PRIMAS AGROPEC. | W70: NO | Y70: SI | Z70: COOPERATIVA DE SERVICIOS MULTIPLES CAPEMA | AA70: 0 | AB70: 0 | AC70: NO | AL70: CAFÉ | AM70: 2019 | AN70: PAC | AU70: 46285.072 | AV70: 0.55555556
A71: 20450319423 | B71: COOPERATIVA AGRARIA DE SERVICIOS MULTIPLES CAFE DONCEL | D71: COOPERATIVAS, SAIS, CAPS | E71: 02 Cooperativa | F71: ACTIVO | G71: HABIDO | H71: 39555 | I71: 39558 | J71: 220105 | K71: SAN MARTIN | L71: MOYOBAMBA | M71: SORITOR | N71: AV. CAJAMARCA NRO. S/N (C-1 BARRIO TANGUMI SALIDA A SAN MARCOS) | O71: SIN ACTIVIDAD | P71: CULTIVOS DE CEREALES. | Q71: TRANSPORTE DE CARGA POR CARRETERA. | W71: NO | Y71: SI | Z71: COOPERATIVA AGRARIA DE SERVICIOS MULTIPLES CAFE DONCEL | AA71: 0 | AB71: 0 | AC71: NO | AL71: CAFÉ | AM71: 2018-2019 | AN71: PAC | AU71: 46285.072 | AV71: 0.53333333
A72: 20450638791 | B72: ASOCIACION DE CASTAÑEROS DE LA RESERVA DE TAMBOPATA LOS PIONEROS - ASCART | D72: ASOCIACION | E72: 01 Asociación | F72: ACTIVO | G72: HABIDO | H72: 39709 | I72: 39709 | J72: 170101 | K72: MADRE DE DIOS | L72: TAMBOPATA | M72: LAS PIEDRAS | N72: JR. CESAR VALLEJO NRO. SN (A ESPALDAS DE COLEGIO MIGUEL GRAU) | O72: IMPORTADOR/EXPORTADOR | P72: CULTIVO DE HORTALIZAS Y LEGUMBRES. | Q72: ELAB. FRUTAS, LEG. Y HORTALIZAS. | W72: NO | Y72: SI | Z72: ASOCIACION DE CASTAÑEROS DE LA RESERVA DE TAMBOPATA LOS PIONEROS - ASCART | AA72: 0 | AB72: 0 | AC72: NO | AL72: CASTAÑA | AM72: 2018-2019-2020-2021-2022-2023 | AN72: PAC | AU72: 46285.072 | AV72: 0.53333333
A73: 20452774705 | B73: COOPERATIVA AGRARIA CACAO VRAE | D73: COOPERATIVAS, SAIS, CAPS | E73: 01 Asociación | F73: ACTIVO | G73: HABIDO | H73: 38840 | I73: 38840 | J73: 080907 | K73: CUSCO | L73: LA CONVENCION | M73: KIMBIRI | N73: NRO. 549 BQ. CIRCUNVALACION (A UNA CUADRA DE LOS BOMBEROS) | O73: EXPORTADOR | P73: ELAB. CACAO, CHOCOLATE Y CONFIT. | Q73: OTROS TIPOS DE VENTA POR MENOR. | U73: 921060381 | V73: COOPERATIVACACAOVRAE@GMAIL.COM | W73: SI | X73: S0645093 | Y73: SI | Z73: COOPERATIVA AGRARIA CACAO VRAE | AA73: 0 | AB73: 0 | AC73: SI | AD73: 1931452.7 | AE73: 2026-04 | AF73: 829301.48 | AG73: 5 | AH73: EPIFANIO TITO SULCA | AI73: RIVERA OCHOA MARCO ANTONIO | AK73: 6 | AL73: CACAO | AM73: 2018-2019-2020-2021-2022-2023 | AN73: PAC | AU73: 46285.072 | AV73: 0.75555556
A74: 20454319169 | B74: ASOCIACION LA JOYA AGRO EXPORT | D74: ASOCIACION | E74: 01 Asociación | F74: ACTIVO | G74: HABIDO | H74: 45824 | I74: 45824 | J74: 040108 | K74: AREQUIPA | L74: AREQUIPA | M74: JACOBO HUNTER | N74: NRO. -- C.P. LA JOYA LATERAL 5 (A 8 KM DE LA ESTACION DE LECHE GLORIA) | O74: SIN ACTIVIDAD | P74: ACTIVIDADES OTRAS ASOCIACIONES NCP. | W74: NO | Y74: SI | Z74: ASOCIACION LA JOYA AGRO EXPORT | AA74: 1132800 | AB74: 811600 | AC74: NO | AL74: PALTA | AM74: 2023-2024 - 2025 | AN74: PAC | AU74: 46285.072 | AV74: 0.51111111
A75: 20454864604 | B75: ASOCIACION DE PRODUCTORES AGROINDUSTRIALES SIGUAS MAJES - PRASIMEX | D75: ASOCIACION | E75: 01 Asociación | F75: ACTIVO | G75: HABIDO | H75: 40581 | I75: 40581 | J75: 040520 | K75: AREQUIPA | L75: CAYLLOMA | M75: MAJES | N75: MZA. K LOTE. 3 EL PEDREGAL (AV. ISLAY AL FRENTE DE MERCADO OVALO) | O75: SIN ACTIVIDAD | P75: EXPLOTACION MIXTA. | Q75: ACTIVIDADES OTRAS ASOCIACIONES NCP. | W75: NO | Y75: SI | Z75: ASOCIACION DE PRODUCTORES AGROINDUSTRIALES SIGUAS MAJES - PRASIMEX | AA75: 0 | AB75: 0 | AC75: NO | AL75: PALTA | AM75: 2019-2020-2021-2022 | AN75: PAC | AU75: 46285.072 | AV75: 0.53333333
A76: 20455129321 | B76: ASOCIACIÓN DE CRIADORES DE ALPACAS DEL DISTRITO DE SIBAYO ASCADIS | D76: ASOCIACION | E76: 01 Asociación | F76: BAJA PROV. POR OFICIO | G76: NO HABIDO | H76: 41180 | I76: 41183 | J76: 040515 | K76: AREQUIPA | L76: CAYLLOMA | M76: SIBAYO | N76: PLAZA PRINCIPAL S/N NRO. --- (DENTRO MUNICIPALIDAD DISTRITAL DE SIBAYO) | O76: SIN ACTIVIDAD | P76: PRODUC. CARNE Y PROD. CARNICOS. | Q76: PREP Y TEJ DE FIBRAS TEXTILES. | W76: SI | X76: S1663828 | Y76: SI | Z76: ASOCIACIÓN DE CRIADORES DE ALPACAS DEL DISTRITO DE SIBAYO ASCADIS | AA76: 0 | AB76: 0 | AC76: NO | AL76: FIBRA DE ALPACA | AM76: 2019-2020-2021 | AN76: PAC | AU76: 46285.072 | AV76: 0.55555556
A77: 20455429120 | B77: ASOCIACION DE PRODUCTORES AGROPECUARIOS DE AGROEXPORTACION E-4 IRRIGACION MAJES-AREQUIPA | D77: ASOCIACION | E77: 01 Asociación | F77: BAJA PROV. POR OFICIO | G77: HABIDO | H77: 40154 | I77: 40154 | J77: 040520 | K77: AREQUIPA | L77: CAYLLOMA | M77: MAJES | N77: ASENTAMIENTO 8 PARCELA NRO. 39 SECCION E (A LA ALTURA DE LA UNSA) | O77: EXPORTADOR | P77: ACTIVIDADES OTRAS ASOCIACIONES NCP. | Q77: SERVICIOS AGRICOLAS, GANADERAS. | W77: NO | Y77: SI | Z77: ASOCIACION DE PRODUCTORES AGROPECUARIOS DE AGROEXPORTACION E-4 IRRIGACION MAJES-AREQUIPA | AA77: 0 | AB77: 0 | AC77: NO | AL77: PALTA | AM77: 2019-2020-2021-2022 | AN77: PAC | AU77: 46285.072 | AV77: 0.53333333
A78: 20479595276 | B78: COOPERATIVA AGRARIA CAFETALERA CASIL LTDA. | D78: COOPERATIVAS, SAIS, CAPS | E78: 02 Cooperativa | F78: ACTIVO | G78: HABIDO | H78: 37694 | I78: 37681 | J78: 060901 | K78: CAJAMARCA | L78: SAN IGNACIO | M78: SAN IGNACIO | N78: AV. SAN IGNACIO NRO. 625 (COSTADO CEMENTERIO) | O78: EXPORTADOR | P78: CULTIVOS DE CEREALES. | R78: EXPLOTACION MIXTA. | T78: SI, incorporado al Régimen de Agentes de Retención de IGV (R.S.229-2024) a partir del 01/01/2025 | U78: 956300479 | V78: gerencia@coopcasil.pe | W78: NO | Y78: SI | Z78: COOPERATIVA AGRARIA CAFETALERA CASIL LTDA. | AA78: 0 | AB78: 2396608.6 | AC78: SI | AD78: 4538578.9 | AE78: 2025-11 | AF78: 3256065.8 | AG78: 8 | AI78: ANDRES NUÑEZ RAMIREZ | AJ78: ANDRES NUÑEZ RAMIREZ | AL78: CAFÉ | AM78: 2025 | AN78: PAC | AO78: 136 | AP78: 42 | AQ78: 437 | AR78: SI | AS78: SI | AU78: 46285.072 | AV78: 0.84444444
A79: 20479622699 | B79: COOPERATIVA AGRARIA JUAN MARCO EL PALTO | D79: COOPERATIVAS, SAIS, CAPS | E79: 02 Cooperativa | F79: ACTIVO | G79: HABIDO | H79: 37777 | I79: 37773 | J79: 010706 | K79: AMAZONAS | L79: UTCUBAMBA | M79: LONYA GRANDE | N79: CAL. PRIMERO DE OCTUBRE NRO. REF SEC. NUEVA DELLI (A 1 CDRA DEL PARQUE INFANTIL) | O79: EXPORTADOR | P79: CULTIVO DE FRUTAS. | R79: OTROS TIPOS DE VENTA AL POR MENOR. | W79: NO | Y79: SI | Z79: COOPERATIVA AGRARIA JUAN MARCO EL PALTO | AA79: 0 | AB79: 0 | AC79: NO | AL79: CAFÉ | AM79: 2021-2022-2023 | AN79: PAC | AU79: 46285.072 | AV79: 0.53333333
A80: 20479728501 | B80: ASOCIACION AGROPECUARIA DE MOLINOPAMPA | D80: ASOCIACION | E80: 01 Asociación | F80: ACTIVO | G80: HABIDO | H80: 38082 | I80: 38308 | J80: 010114 | K80: AMAZONAS | L80: CHACHAPOYAS | M80: MOLINOPAMPA | N80: JR. EL MOLINO NRO. S/N (COSTADO A LA FISCALIA) | O80: SIN ACTIVIDAD | P80: ELAB DE PRODUCTOS LACTEOS. | Q80: FAB. OTROS PRODUCTOS DE MADERA. | R80: TRANSPORTE DE CARGA POR CARRETERA. | U80: 041-478026 | V80: JULY_1@HOTMAIL.COM | W80: SI | X80: S0003285 | Y80: SI | Z80: ASOCIACION AGROPECUARIA DE MOLINOPAMPA | AA80: 0 | AB80: 0 | AC80: NO | AH80: CABAÑAS CALAMPA EMIGNO TEODORO | AI80: CABAÑAS CALAMPA EMIGNO TEODORO | AK80: 6 | AL80: DERIVADOS LACTEOS | AM80: 2025 | AN80: PAC | AU80: 46285.072 | AV80: 0.68888889
A81: 20479856258 | B81: ASOCIACION DE PRODUCTORES AGROPECUARIOS LUIS SOLIBARRIA | D81: ASOCIACION | F81: BAJA DE OFICIO | G81: HABIDO | H81: 38471 | I81: 38473 | K81: AMAZONAS | L81: UTCUBAMBA | M81: BAGUA GRANDE | N81: AV. CHACHAPOYAS NRO. 3125 | O81: SIN ACTIVIDAD | P81: ELAB. CACAO, CHOCOLATE Y CONFIT. | Q81: VTA. MAY. DE MATERIAS PRIMAS AGROPEC. | U81: 941922277 | V81: vmcampos_2@hotmail.com | W81: SI | X81: B0003863 | Y81: SI | Z81: ASOCIACION DE PRODUCTORES AGROPECUARIOS LUIS SOLIBARRIA | AA81: 0 | AB81: 0 | AC81: NO | AH81: FLORES SALVADOR ADALBERTO | AI81: FLORES SALVADOR ADALBERTO | AK81: 4 | AU81: 46285.072 | AV81: 0.55555556
A82: 20479917141 | B82: COOPERATIVA AGRARIA CENTRAL DE PRODUCTORES DE AMAZONAS | C82: CEPROAA | D82: COOPERATIVAS, SAIS, CAPS | E82: 02 Cooperativa | F82: ACTIVO | G82: HABIDO | H82: 38625 | I82: 38625 | J82: 010702 | K82: AMAZONAS | L82: UTCUBAMBA | M82: CAJARURO | N82: JR. ATAHUALPA NRO. 150 (AL COSTADO DE LA POSTA MEDICA) | O82: IMPORTADOR/EXPORTADOR | P82: VTA. MAY. DE MATERIAS PRIMAS AGROPEC. | W82: NO | Y82: SI | Z82: COOPERATIVA AGRARIA CENTRAL DE PRODUCTORES DE AMAZONAS | AA82: 0 | AB82: 0 | AC82: SI | AD82: 1175215.3 | AE82: 2025-12 | AF82: 377881.98 | AG82: 2 | AL82: CACAO | AM82: 2018-2019-2020-2021-2022-2023 | AN82: PAC | AU82: 46285.072 | AV82: 0.62222222
A83: 20480118295 | B83: ASOCIACION DE PRODUCTORES AGROPECUARIOS SANTO TOMAS | C83: BELLA TOMASINA | D83: ASOCIACION | E83: 01 Asociación | F83: ACTIVO | G83: HABIDO | H83: 39118 | I83: 39114 | J83: 010521 | K83: AMAZONAS | L83: LUYA | M83: SANTO TOMAS | N83: PRO. JUNIN NRO. 100 (FRENTE AL MIRADOR PERLAS) | O83: SIN ACTIVIDAD | P83: ELAB DE PRODUCTOS LACTEOS. | U83: 945205853 | V83: marbelith_yo@hotmail.com | W83: SI | X83: S1580111 | Y83: SI | Z83: ASOCIACION DE PRODUCTORES AGROPECUARIOS SANTO TOMAS | AA83: 0 | AB83: 56541.927 | AC83: NO | AH83: TAUCHA CHAUCA FELIPE | AI83: TAUCA CHAUCA FELIPE | AK83: 7 | AL83: DERIVADOS LACTEOS | AM83: 2025 | AN83: PAC | AU83: 46285.072 | AV83: 0.66666667
A84: 20480458550 | B84: COOPERATIVA AGRARIA APROCAM | D84: COOPERATIVAS, SAIS, CAPS | E84: 02 Cooperativa | F84: ACTIVO | G84: HABIDO | H84: 39700 | I84: 39692 | J84: 010201 | K84: AMAZONAS | L84: BAGUA | M84: BAGUA | N84: OTR. CARRETERA BAGUA COPALLIN KM. 4 C.P. CERCADO (KILOMETRO 4.5 C.P. TOMAQUE) | O84: EXPORTADOR | P84: VTA. MAY. DE MATERIAS PRIMAS AGROPEC. | Q84: ELAB. CACAO, CHOCOLATE Y CONFIT. | U84: 943 813 290 | V84: CERTIFICACIONES.APROCAM@GMAIL.COM | W84: SI | X84: S1846386 | Y84: SI | Z84: COOPERATIVA AGRARIA APROCAM | AA84: 0 | AB84: 0 | AC84: SI | AD84: 1684430 | AE84: 2026-04 | AF84: 133793.84 | AG84: 2 | AH84: SANTOS CRUZ FLORES | AI84: MENDOZA REAP FREDDY | AK84: 7 | AL84: CACAO | AM84: 2018-2019-2020-2021-2022-2023 | AN84: PAC | AU84: 46285.072 | AV84: 0.75555556
A85: 20480762895 | B85: ASOCIACION DE PRODUCTORES AGROPECUARIOS LA FLOR DE CAFE | D85: ASOCIACION | E85: 01 Asociación | F85: BAJA DE OFICIO | G85: HABIDO | H85: 40169 | I85: 40148 | J85: 010601 | K85: AMAZONAS | L85: RODRIGUEZ DE MENDOZA | M85: SAN NICOLAS | N85: JR. ALONSO DE ALVARADO NRO. S/ N BARRIO DE ONCHE (FRENTE A FISCALIA. COLOR BLANCA) | O85: EXPORTADOR | P85: ACTIVIDADES OTRAS ASOCIACIONES NCP. | Q85: SERVICIOS AGRICOLAS, GANADERAS. | R85: TRANSPORTE DE CARGA POR CARRETERA. | W85: NO | Y85: SI | Z85: ASOCIACION DE PRODUCTORES AGROPECUARIOS LA FLOR DE CAFE | AA85: 0 | AB85: 0 | AC85: NO | AL85: CAFÉ | AM85: 2019-2020-2021-2022-2023 | AN85: PAC | AU85: 46285.072 | AV85: 0.55555556
A86: 20481402540 | B86: ASOCIACION DE APICULTORES NECTAR DE VIDA DEL VALLE CHICAMA | D86: ASOCIACION | E86: 01 Asociación | F86: BAJA DE OFICIO | G86: HABIDO | H86: 45463 | I86: 45463 | J86: 130205 | K86: LA LIBERTAD | L86: ASCOPE | M86: PAIJAN | N86: CAL. CASA GRANDE NRO. 198 SEC. LICAPA | O86: SIN ACTIVIDAD | P86: CRIA DE ANIMALES DOMESTICOS. | Q86: OTROS TIPOS DE VENTA POR MENOR. | W86: NO | Y86: SI | Z86: ASOCIACION DE APICULTORES NECTAR DE VIDA DEL VALLE CHICAMA | AA86: 0 | AB86: 57207 | AC86: NO | AL86: MIEL DE ABEJA Y DERIVADOS | AM86: 2025 | AN86: PAC | AU86: 46285.072 | AV86: 0.53333333
A87: 20481929122 | B87: ASOCIACION DE PEQUEÑOS PRODUCTORES AGROPECUARIOS PERLA DEL PARAISO | D87: ASOCIACION | E87: 01 Asociación | F87: ACTIVO | G87: HABIDO | H87: 42684 | I87: 42684 | J87: 130602 | K87: LA LIBERTAD | L87: OTUZCO | M87: AGALLPAMPA | N87: NRO. 25 CAS. EL PARAISO | O87: SIN ACTIVIDAD | P87: CRIA DE GANADO. | Q87: ELAB DE PRODUCTOS LACTEOS. | U87: 987771691 | V87: ab-luis@hotmail.com | W87: SI | X87: S0867961 | Y87: SI | Z87: ASOCIACION DE PEQUEÑOS PRODUCTORES AGROPECUARIOS PERLA DEL PARAISO | AA87: 246770 | AB87: 0 | AC87: NO | AH87: luis cueva jose wilder | AI87: LUIS CUEVA JOSE WILDER | AK87: 5 | AL87: DERIVADOS LACTEOS | AM87: 2021-2022-2023-2024 | AN87: PAC | AU87: 46285.072 | AV87: 0.66666667
A88: 20482423320 | B88: ASOCIACION DE PRODUCTORES AGROINDUSTRIALES SANTA ROSA | D88: ASOCIACION | E88: 01 Asociación | F88: BAJA DE OFICIO | G88: HABIDO | H88: 42438 | I88: 42438 | J88: 130601 | K88: LA LIBERTAD | L88: OTUZCO | M88: OTUZCO | N88: LOS ROSALES NRO. SN BAR. RAMON CASTILLA | O88: SIN ACTIVIDAD | P88: OTROS TIPOS DE VENTA POR MENOR. | U88: 949704968 | V88: apasanta_rosacaupar@yahoo.com | W88: SI | X88: S0863797 | Y88: SI | Z88: ASOCIACION DE PRODUCTORES AGROINDUSTRIALES SANTA ROSA | AA88: 0 | AB88: 0 | AC88: NO | AH88: HURTADO VALDIVIEZO ORFELINDA | AI88: HURTADO VALDIVIEZO ORFELINDA | AK88: 3 | AL88: DERIVADOS LACTEOS | AM88: 2023 | AN88: PAC | AU88: 46285.072 | AV88: 0.64444444
A89: 20482572163 | B89: COOPERATIVA AGRARIA DE PRODUCTORES LA VICTORIA CACHICADAN - COAPROLAVIC | D89: COOPERATIVAS, SAIS, CAPS | E89: 02 Cooperativa | F89: ACTIVO | G89: HABIDO | H89: 44174 | I89: 44172 | J89: 131003 | K89: LA LIBERTAD | L89: SANTIAGO DE CHUCO | M89: CACHICADAN | N89: CASERIO SANTA ROSA NRO. S/N CAS. SANTA ROSA | O89: SIN ACTIVIDAD | P89: CRIA DE GANADO. | Q89: ELAB DE PRODUCTOS LACTEOS. | W89: NO | Y89: SI | Z89: COOPERATIVA AGRARIA DE PRODUCTORES LA VICTORIA CACHICADAN - COAPROLAVIC | AA89: 184840 | AB89: 216380 | AC89: NO | AL89: DERIVADOS LACTEOS | AM89: 2024 - 2025 | AN89: PAC | AU89: 46285.072 | AV89: 0.53333333
A90: 20484163902 | B90: COOPERATIVA AGRARIA APPROCAP LTDA | C90: APPROCAP | D90: COOPERATIVAS, SAIS, CAPS | E90: 02 Cooperativa | F90: ACTIVO | G90: HABIDO | H90: 38054 | I90: 38100 | J90: 200407 | K90: PIURA | L90: MORROPON | M90: SAN JUAN DE BIGOTE | N90: CAL. JOSE CARLOS MARIATEGUI NRO. S/N (COLISEO MUNICIPAL DEL DISTRITO) | O90: IMPORTADOR/EXPORTADOR | P90: ELAB. FRUTAS, LEG. Y HORTALIZAS. | Q90: ACTIVIDADES OTRAS ASOCIACIONES NCP. | R90: SERVICIOS AGRICOLAS, GANADERAS. | W90: NO | Y90: SI | Z90: COOPERATIVA AGRARIA APPROCAP LTDA | AA90: 0 | AB90: 1289165.6 | AC90: SI | AD90: 817000 | AE90: 2026-04 | AF90: 137000 | AG90: 1 | AL90: CACAO | AM90: 2025 | AN90: PAC | AU90: 46285.072 | AV90: 0.66666667
A91: 20485945815 | B91: COOPERATIVA AGRARIA CAFETALERA ECOLOGICO ALTO PALOMAR | D91: COOPERATIVAS, SAIS, CAPS | E91: 02 Cooperativa | F91: SUSPENSION TEMPORAL | G91: HABIDO | H91: 37316 | I91: 37316 | J91: 120304 | K91: JUNIN | L91: CHANCHAMAYO | M91: SAN LUIS DE SHUARO | N91: CAR. SANCHIRIO SANTA HERMINIA KM. 6 C.P. ALTO PALOMAR (COSTADO COOP. COPCHEVI) | O91: IMPORTADOR/EXPORTADOR | P91: CULTIVO DE FRUTAS. | W91: NO | Y91: SI | Z91: COOPERATIVA AGRARIA CAFETALERA ECOLOGICO ALTO PALOMAR | AA91: 0 | AB91: 0 | AC91: NO | AL91: CAFÉ | AM91: 2019-2020 | AN91: PAC | AU91: 46285.072 | AV91: 0.51111111
A92: 20486049198 | B92: COOPERATIVA AGROPECUARIA DE SERVICIOS VALLE DEL CUNAS LIMITADA (CAS VALLE DEL CUNAS LTDA) | D92: COOPERATIVAS, SAIS, CAPS | E92: 02 Cooperativa | F92: SUSPENSION TEMPORAL | G92: HABIDO | H92: 37700 | I92: 37712 | J92: 120214 | K92: JUNIN | L92: CONCEPCION | M92: SAN JOSE DE QUERO | N92: JR. PARRA DEL RIEGO NRO. SN (S76294270-COSTADO DE LA PLAZA PRINCIPAL) | O92: EXPORTADOR | P92: SERVICIOS AGRICOLAS, GANADERAS. | Q92: ELAB DE OTROS PROD. ALIMENTICIOS. | R92: CULTIVO DE HORTALIZAS Y LEGUMBRES. | W92: NO | Y92: SI | Z92: COOPERATIVA AGROPECUARIA DE SERVICIOS VALLE DEL CUNAS LIMITADA (CAS VALLE DEL CUNAS LTDA) | AA92: 0 | AB92: 0 | AC92: NO | AL92: MACA | AM92: 2019 | AN92: PAC | AU92: 46285.072 | AV92: 0.55555556
A93: 20486073145 | B93: ASOCIACION AGRO GANADERO ECOLOGICO DEL ALTO CACAZU - VILLA RICA | D93: ASOCIACION | E93: 01 Asociación | F93: BAJA DE OFICIO | G93: HABIDO | H93: 45092 | I93: 45092 | J93: 190307 | K93: PASCO | L93: OXAPAMPA | M93: VILLA RICA | N93: CAR. MARGINAL NRO. SN C.P. LA CUMBRE SECT. SAN PABLO (S78997430 A 100 MTS DE CATARATA CACAZU) | O93: SIN ACTIVIDAD | P93: VTA. MAY. DE MATERIAS PRIMAS AGROPEC. | W93: NO | Y93: SI | Z93: ASOCIACION AGRO GANADERO ECOLOGICO DEL ALTO CACAZU - VILLA RICA | AA93: 0 | AB93: 0 | AC93: NO | AL93: DERIVADOS LACTEOS | AM93: 2019-2020 | AN93: PAC | AU93: 46285.072 | AV93: 0.51111111
A94: 20486094657 | B94: ASOCIACION DE PRODUCTORES DE CAFES ESPECIALES MOUNTAIN COFFE | D94: ASOCIACION | E94: 01 Asociación | F94: ACTIVO | G94: NO HABIDO | H94: 37834 | I94: 37834 | J94: 120606 | K94: JUNIN | L94: CHANCHAMAYO | M94: PICHANAQUI | N94: JR. ANDRES A CACERES NRO. 875 | O94: EXPORTADOR | P94: CULTIVOS DE CEREALES. | Q94: TRANSPORTE DE CARGA POR CARRETERA. | W94: NO | Y94: SI | Z94: ASOCIACION DE PRODUCTORES DE CAFES ESPECIALES MOUNTAIN COFFE | AA94: 0 | AB94: 0 | AC94: NO | AL94: CAFÉ | AM94: 2018 | AN94: PAC | AU94: 46285.072 | AV94: 0.53333333
A95: 20486217830 | B95: COMUNIDAD CAMPESINA DE SANTA BARBARA | D95: COMUNIDAD CAMPESINA, NATIVA | E95: 05 Comunidades Campesinas | F95: ACTIVO | G95: HABIDO | H95: 38209 | I95: 38209 | J95: 090101 | K95: HUANCAVELICA | L95: HUANCAVELICA | M95: HUANCAVELICA | N95: JR. MERCURIO NRO. 105 BARRIO SANTA BARABARA (LOCAL COMUNAL) | O95: SIN ACTIVIDAD | P95: ALQUILER OTROS TIPOS MAQ.Y EQUI. NCP. | Q95: TRANSPORTE DE CARGA POR CARRETERA. | U95: 954474824 | V95: chahuayo_d@hotmail.com | W95: SI | X95: S0831285 | Y95: SI | Z95: COMUNIDAD CAMPESINA DE SANTA BARBARA | AA95: 0 | AB95: 0 | AC95: NO | AH95: DE LA CRUZ CASTILLO JAIME ROSE | AI95: DE LA CRUZ CASTILLO JAIME ROSE | AK95: 9 | AL95: FIBRA DE ALPACA | AM95: 2019-2021 | AN95: PAC | AU95: 46285.072 | AV95: 0.66666667
A96: 20486255090 | B96: COOPERATIVA AGRARIA SANGARENI | D96: COOPERATIVAS, SAIS, CAPS | E96: 02 Cooperativa | F96: ACTIVO | G96: HABIDO | H96: 38338 | I96: 38338 | J96: 120606 | K96: JUNIN | L96: SATIPO | M96: PANGOA | N96: AV. SONOMORO NRO. 199 (UNA CUADRA ANTES DEL PUENTE SAN RAMON) | O96: EXPORTADOR | P96: CULTIVOS DE CEREALES. | Q96: SERVICIOS AGRICOLAS, GANADERAS. | W96: NO | Y96: SI | Z96: COOPERATIVA AGRARIA SANGARENI | AA96: 8202629.2 | AB96: 9860568.5 | AC96: SI | AD96: 13207692 | AE96: 2025-12 | AF96: 7990596.3 | AG96: 4 | AL96: CAFÉ | AM96: 2024 - 2025 | AN96: PAC | AU96: 46285.072 | AV96: 0.62222222
A97: 20486668335 | B97: COOPERATIVA AGROINDUSTRIAL SONOMORO LTDA | C97: CAI SONOMORO LTDA | D97: COOPERATIVAS, SAIS, CAPS | F97: SUSPENSION TEMPORAL | G97: HABIDO | H97: 39288 | I97: 39295 | K97: JUNIN | L97: SATIPO | M97: PANGOA | N97: CAL. 3 DE NOVIEMBRE NRO. S/N (ESQ. AV SONOMORO Y 3 DE NOVIEMBRE) | O97: IMPORTADOR/EXPORTADOR | P97: CULTIVOS DE CEREALES. | Q97: PESCA, EXPLOT. CRIADEROS DE PECES. | U97: 964557158 | V97: CAISONOMORO1@HOTMail.com | W97: SI | X97: S1522292 | Y97: SI | Z97: COOPERATIVA AGROINDUSTRIAL SONOMORO LTDA | AA97: 0 | AB97: 0 | AC97: NO | AH97: CAMPOS MONTES JHONY | AI97: SOLIS PALOMINO LUIS ALBERTO | AK97: 6 | AU97: 46285.072 | AV97: 0.57777778
A98: 20486876019 | B98: COOPERATIVA AGROECOLOGICO INDUSTRIAL MAZAMARI LTDA | C98: CAI MAZAMARI LTDA | D98: COOPERATIVAS, SAIS, CAPS | E98: 02 Cooperativa | F98: ACTIVO | G98: HABIDO | H98: 39645 | I98: 39645 | J98: 120604 | K98: JUNIN | L98: SATIPO | M98: MAZAMARI | N98: AV. BOTTO BERNALES NRO. 1082 (ALTURA GRASA SINTÉTICO LA PICHANGA) | O98: SIN ACTIVIDAD | P98: EXPLOTACION MIXTA. | W98: NO | Y98: SI | Z98: COOPERATIVA AGROECOLOGICO INDUSTRIAL MAZAMARI LTDA | AA98: 0 | AB98: 0 | AC98: NO | AL98: CACAO | AM98: 2019 | AN98: PAC | AU98: 46285.072 | AV98: 0.53333333
A99: 20486973219 | B99: COOPERATIVA AGRARIA SONOMORO DEL VRAEM LTDA | C99: COAS LTDA | D99: COOPERATIVAS, SAIS, CAPS | E99: 02 Cooperativa | F99: ACTIVO | G99: HABIDO | H99: 40470 | I99: 40544 | J99: 120606 | K99: JUNIN | L99: SATIPO | M99: PANGOA | N99: JR. LAS PALMERAS NRO. SN CP NAYLAMP DE SONOMORO (A 1 CDRA DE CE 30671 NAYLAMP DE SONOMOR) | O99: IMPORTADOR/EXPORTADOR | P99: ELAB. CACAO, CHOCOLATE Y CONFIT. | Q99: SERVICIOS AGRICOLAS, GANADERAS. | W99: SI | X99: S3021823 | Y99: SI | Z99: COOPERATIVA AGRARIA SONOMORO DEL VRAEM LTDA | AA99: 0 | AB99: 28217690 | AC99: SI | AD99: 30342293 | AE99: 2026-04 | AF99: 1405371.9 | AG99: 4 | AL99: CACAO | AM99: 2025 | AN99: PAC | AU99: 46285.072 | AV99: 0.66666667
A100: 20487226875 | B100: ORGANIZACION CENTRAL DE PRODUCTORES DE GRANADILLAS ESPECIALES DE LA PROVINCIA DE OXAPAMPA-PASCO | D100: ASOCIACION | E100: 01 Asociación | F100: ACTIVO | G100: HABIDO | H100: 40177 | I100: 40179 | J100: 190301 | K100: PASCO | L100: OXAPAMPA | M100: OXAPAMPA | N100: PJ. RICHLE NRO. 182 INT. 2 URB. OXAPAMPA (S72827129 DETRAS DE HOSPITAL GENERAL) | O100: IMPORTADOR/EXPORTADOR | P100: TRANSPORTE DE CARGA POR CARRETERA. | Q100: CULTIVO DE FRUTAS. | U100: 462339 | V100: dapaucar@hotmail.com | W100: SI | X100: S0776139 | Y100: SI | Z100: ORGANIZACION CENTRAL DE PRODUCTORES DE GRANADILLAS ESPECIALES DE LA PROVINCIA DE OXAPAMPA-PASCO | AA100: 0 | AB100: 0 | AC100: NO | AH100: vasquez guadalupe leoncio juan | AI100: VASQUEZ GUADALUPE LEONCIO JUAN | AK100: 3 | AL100: GRANADILLA | AM100: 2019-2020 | AN100: PAC | AU100: 46285.072 | AV100: 0.66666667
...

Sheet b1
A1: Nombre de la Organización | B1: PRODUCTO DOM | C1: PRODUCTO 1 | D1: SEDE | E1: Ubigeo | F1: DEPARTAMENTO | G1: Provincia | H1: Distrito | I1: TIPO DE CERTIFICADO | J1: 2025 | K1: SERVICIO | L1: AÑOS DE INTERVENCION | M1: AÑOS DE INTERVENCIÓN DESDE 2018 AL 2024 | N1: INTERVENCIÓN 2019 al 2025 | O1: BENF MASC 2025 | P1: BENF FEM 2025 | Q1: TOTAL BENF 2025 | R1: TOTAL VENTAS 2018 AL 2025 | S1: V. EJEC NACIONALES 2025 | T1: V. EJEC EXPORTACION 2025 | U1: VENTAS TOTALES 2025 | V1: INCREMENTOS VENTAS EN 2025 | W1: DIFERENCIA VENTAS 2025-2024 | X1: Boleta de Venta 2025 | Y1: Declaración Jurada 2025 | Z1: Factura 2025 | AA1: Guía de Remisión 2025 | AB1: Liquidación de Compra 2025 | AC1: Total general 2025 | AD1: RUC | AE1: Tipo de Organización* (Asociación/Cooperativa/CCNN, Comunidad Campesina y otros.)
A2: COOPERATIVA AGRARIA DE USUARIOS DE PEQUEÑOS PRODUCTORES DEL PERU | B2: MANGO | C2: MANGO | D2: ANCASH | E2: 020801 | F2: ANCASH | G2: CASMA | H2: CASMA | I2: FAIR TRADE | J2: 1 | K2: PAC | L2: 2025 | M2: 1 | N2: SI | O2: 15 | P2: 9 | Q2: 24 | X2: 0 | Y2: 399056.4 | Z2: 866144.87 | AA2: 0 | AB2: 0 | AC2: 1265201.3 | AD2: 20601575184 | AE2: Cooperativa
A3: COOPERATIVA AGRARIA AGROFRUTOS ORGANICOS | B3: MANGO | C3: MANGO | D3: LAMBAYEQUE | E3: 140307 | F3: LAMBAYEQUE | G3: LAMBAYEQUE | H3: MOTUPE | I3: ORGANICO | J3: 1 | K3: PAC | L3: 2025 | M3: 1 | N3: =IF(OR([1]!Tabla16[[#This Row],[2019]]=1,[1]!Tabla16[[#This Row],[2020]]=1,[1]!Tabla16[[#This Row],[2021]]=1,[1]!Tabla16[[#This Row],[2022]]=1,[1]!Tabla16[[#This Row],[2023]]=1,[1]!Tabla16[[#This Row],[2024]]=1,[1]!Tabla16[[#This Row],[2025]]=1),"SI","NO") | O3: 62 | P3: 10 | Q3: 72 | R3: #REF! | S3: 22435.002 | T3: 0 | U3: 22435.002 | V3: #REF! | W3: ='[2]DATA CONSOLIDADA 2018-2025 '!$CM5-[1]!Tabla16[[#This Row],[VENTAS TOTALES 20224]] | X3: 0 | Y3: 0 | Z3: 22435.002 | AA3: 0 | AB3: 0 | AC3: 22435.002 | AD3: 20613899287 | AE3: Cooperativa
A4: COOPERATIVA AGRARIA DE USUARIOS ASPRAOSRA LTDA | B4: BANANO | C4: BANANO | D4: PIURA | F4: PIURA | G4: MORROPON | H4: BUENOS AIRES | I4: ORGANICO/GLOBAL GAP | J4: 1 | K4: PAC | L4: 2025 | M4: 1 | N4: =IF(OR([1]!Tabla16[[#This Row],[2019]]=1,[1]!Tabla16[[#This Row],[2020]]=1,[1]!Tabla16[[#This Row],[2021]]=1,[1]!Tabla16[[#This Row],[2022]]=1,[1]!Tabla16[[#This Row],[2023]]=1,[1]!Tabla16[[#This Row],[2024]]=1,[1]!Tabla16[[#This Row],[2025]]=1),"SI","NO") | O4: 22 | P4: 14 | Q4: 36 | R4: #REF! | S4: 0 | T4: 781855.2 | U4: 781855.2 | V4: #REF! | W4: ='[2]DATA CONSOLIDADA 2018-2025 '!$CM6-[1]!Tabla16[[#This Row],[VENTAS TOTALES 20224]] | X4: 0 | Y4: 0 | Z4: 781855.2 | AA4: 0 | AB4: 0 | AC4: 781855.2 | AD4: 20526179367 | AE4: Cooperativa
A5: ASOCIACION DE AGRICULTORES INNOVADORES DE ANCASH, EDIFLOR | B5: PALTA | C5: PALTA | D5: ANCASH | F5: ANCASH | G5: SANTA | H5: CHIMBOTE | I5: GLOBAL GAP | J5: 1 | K5: PAC | L5: 2025 | M5: =SUM([1]!Tabla16[[#This Row],[2018]:[2025]]) | N5: =IF(OR([1]!Tabla16[[#This Row],[2019]]=1,[1]!Tabla16[[#This Row],[2020]]=1,[1]!Tabla16[[#This Row],[2021]]=1,[1]!Tabla16[[#This Row],[2022]]=1,[1]!Tabla16[[#This Row],[2023]]=1,[1]!Tabla16[[#This Row],[2024]]=1,[1]!Tabla16[[#This Row],[2025]]=1),"SI","NO") | O5: 4 | P5: 7 | Q5: 11 | R5: #REF! | S5: 120000 | T5: 0 | U5: 120000 | V5: #REF! | W5: ='[2]DATA CONSOLIDADA 2018-2025 '!$CM10-[1]!Tabla16[[#This Row],[VENTAS TOTALES 20224]] | X5: 0 | Y5: 120000 | Z5: 0 | AA5: 0 | AB5: 0 | AC5: 120000 | AD5: 20611531088 | AE5: Asociacion
A6: ASOCIACIÓN DE PRODUCTORES AGROPECUARIOS CHASKAS DE HUANCALLAMA-APACHAHUA | B6: PALTA | C6: PALTA | D6: HUANCAVELICA | E6: 090409 | F6: HUANCAVELICA | G6: CASTROVIRREYNA | H6: MOLLEPAMPA | I6: GLOBAL GAP | J6: 1 | K6: PAC | L6: 2025 | M6: 1 | N6: =IF(OR([1]!Tabla16[[#This Row],[2019]]=1,[1]!Tabla16[[#This Row],[2020]]=1,[1]!Tabla16[[#This Row],[2021]]=1,[1]!Tabla16[[#This Row],[2022]]=1,[1]!Tabla16[[#This Row],[2023]]=1,[1]!Tabla16[[#This Row],[2024]]=1,[1]!Tabla16[[#This Row],[2025]]=1),"SI","NO") | O6: 20 | P6: 4 | Q6: 24 | R6: #REF! | S6: 0 | T6: 0 | U6: 0 | V6: #REF! | W6: ='[2]DATA CONSOLIDADA 2018-2025 '!$CM11-[1]!Tabla16[[#This Row],[VENTAS TOTALES 20224]] | X6: 0 | Y6: 0 | Z6: 0 | AA6: 0 | AB6: 0 | AC6: 0 | AD6: 20607063576 | AE6: Asociación
A7: ASOCIACION DE AGRICULTORES DE PALTOS EN HUAMAMPALI - ALTO LARAN | B7: PALTA | C7: PALTA | D7: ICA | F7: ICA | G7: CHINCHA | H7: HUAMANPALI | I7: GLOBAL GAP | J7: 1 | K7: PAC | L7: 2025 | M7: 1 | N7: =IF(OR([1]!Tabla16[[#This Row],[2019]]=1,[1]!Tabla16[[#This Row],[2020]]=1,[1]!Tabla16[[#This Row],[2021]]=1,[1]!Tabla16[[#This Row],[2022]]=1,[1]!Tabla16[[#This Row],[2023]]=1,[1]!Tabla16[[#This Row],[2024]]=1,[1]!Tabla16[[#This Row],[2025]]=1),"SI","NO") | O7: 19 | P7: 2 | Q7: 21 | R7: 0 | S7: 0 | T7: 0 | U7: 0 | V7: 0 | W7: 0 | X7: 0 | Y7: 0 | Z7: 0 | AA7: 0 | AB7: 0 | AC7: 0 | AD7: 20605371869 | AE7: Asociación

Sheet b2
A1: 2 | B1: 3 | C1: 4 | D1: 7 | E1: 8 | F1: 9 | G1: 10 | H1: 11 | I1: 12 | J1: 13 | K1: 14 | L1: 15 | M1: 16 | N1: 17 | O1: 18 | P1: 19 | R1: 20 | S1: 21 | T1: 22 | V1: 23 | W1: 24 | X1: 25 | Y1: 26 | Z1: 27 | AA1: 28 | AB1: 29 | AC1: 30 | AD1: 31 | AE1: 32 | AF1: 33 | AG1: 34 | AH1: 35 | AI1: 36 | AJ1: 37 | AK1: 38 | AL1: 39 | AM1: 40 | AN1: 41 | AO1: 42 | AP1: 43 | AQ1: 44 | AR1: 45 | AS1: 46 | AT1: 47 | AU1: 48 | AV1: 49 | AW1: 50 | AX1: 51 | AY1: 52 | AZ1: 53 | BA1: 54 | BB1: 55 | BC1: 56 | BD1: 57 | BE1: 58 | BF1: 59 | BG1: 60 | BH1: 61 | BI1: 62 | BJ1: 63 | BK1: 64 | BL1: 65 | BM1: 66 | BN1: 67 | BO1: 68 | BP1: 69 | BQ1: 70 | BR1: 71 | BS1: 72 | BT1: 73 | BU1: 74 | BV1: 75 | BW1: 76 | BX1: 77 | BY1: 78 | BZ1: 79 | CA1: 80 | CB1: 81 | CC1: 82 | CD1: 83 | CE1: 84 | CF1: 85 | CG1: 86 | CH1: 87 | CI1: 88 | CJ1: 89 | CK1: 90 | CL1: 91 | CM1: 92 | CN1: 93 | CO1: 94 | CP1: 95 | CQ1: 96 | CR1: 97 | CS1: 98 | CT1: 99 | CU1: 100 | CV1: 101 | CW1: 102 | CX1: 103 | CY1: 104 | CZ1: 105 | DA1: 106 | DB1: 107 | DI1: 122 | DJ1: 123 | DK1: 124
A2: Nombre de la Organización | B2: PRODUCTO DOM | C2: PRODUCTO 1 | D2: SEDE | E2: Ubigeo | F2: DEPARTAMENTO | G2: Provincia | H2: Distrito | I2: 2018 | J2: 2019 | K2: 2020 | L2: 2021 | M2: 2022 | N2: 2023 | O2: 2024 | P2: 2025 | Q2: SERVICIO | R2: AÑOS DE INTERVENCION | S2: AÑOS DE INTERVENCIÓN DESDE 2018 AL 2024 | T2: INTERVENCIÓN 2019 al 2025 | U2: INTERVENCIÓN 2020 al 2026 | V2: TOTAL BENF 2018 | W2: BENF MASC 2019 | X2: BENF FEM 2019 | Y2: TOTAL BENF 2019 | Z2: BENF MASC 2020 | AA2: BENF FEM 2020 | AB2: TOTAL BENF 2020 | AC2: BENF MASC 2021 | AD2: BENF FEM 2021 | AE2: TOTAL BENF 2021 | AF2: BENF MASC 2022 | AG2: BENF FEM 2022 | AH2: TOTAL BENF 2022 | AI2: BENF MASC 2023 | AJ2: BENF FEM 2023 | AK2: TOTAL BENF 2023 | AL2: BENF MASC 2024 | AM2: BENF FEM 2024 | AN2: TOTAL BENF 2024 | AO2: BENF MASC 2025 | AP2: BENF FEM 2025 | AQ2: TOTAL BENF 2025 | AR2: BENEFICIADOS ULTIMO AÑO | AS2: ASISTENCIA TÉCNICA 2020 | AT2: TALLERES 2020 | AU2: ASISTENCIA TÉCNICA 2021 | AV2: TALLERES 2021 | AW2: ASISTENCIA TÉCNICA 2022 | AX2: TALLERES 2022 | AY2: ASISTENCIA TÉCNICA 2023 | AZ2: TALLERES 2023 | BA2: ASISTENCIA TÉCNICA 2024 | BB2: TALLERES 2024 | BC2: ASISTENCIA TÉCNICA 2025 | BD2: TALLERES 2025 | BE2: VENTAS TOTALES 2018 | BF2: VENTAS NACIONALES 2019 | BG2: VENTAS INTERNACIONALES 2019 | BH2: VENTAS TOTALES 2019 | BI2: INCREMENTOS VENTAS EN 2019 | BJ2: INCREMENTOS VENTAS EN 20192 | BK2: VENTAS NACIONALES 2020 | BL2: VENTAS INTERNACIONALES 2020 | BM2: VENTAS TOTALES 2020 | BN2: INCREMENTOS VENTAS EN 2020 | BO2: DIFERENCIA VENTA 2020-2019 | BP2: VENTAS NACIONALES 2021 | BQ2: VENTAS INTERNACIONALES 2021 | BR2: VENTAS TOTALES 2021 | BS2: INCREMENTOS VENTAS EN 20201 | BT2: DIFERENCIA VENTA 2021-2020 | BU2: V. EJEC NACIONALES 2022 | BV2: V. EJEC EXPORTACION 2022 | BW2: VENTAS TOTALES 2022 | BX2: INCREMENTOS VENTAS EN 22022 | BY2: DIFERENCIA VENTAS 2022-2021 | BZ2: V. EJEC NACIONALES 2023 | CA2: V. EJEC EXPORTACION 2023 | CB2: VENTAS TOTALES 2023 | CC2: INCREMENTOS VENTAS EN 2023 | CD2: DIFERENCIA VENTAS 2023-2022 | CE2: V. EJEC NACIONALES 2024 | CF2: V. EJEC EXPORTACION 2024 | CG2: VENTAS TOTALES 20224 | CH2: INCREMENTOS VENTAS EN 2024 | CI2: DIFERENCIA VENTAS 2024-2023 | CJ2: TOTAL VENTAS 2018 AL 2025 | CK2: V. EJEC NACIONALES 2025 | CL2: V. EJEC EXPORTACION 2025 | CM2: VENTAS TOTALES 2025 | CN2: INCREMENTOS VENTAS EN 2025 | CO2: DIFERENCIA VENTAS 2025-2024 | CP2: Boleta de Venta 2023 | CQ2: Declaracion Jurada 2023 | CR2: Documento de Entrega Cooperativo (DEC) 2023 | CS2: Factura 2023 | CT2: Guia de Remision 2023 | CU2: Liquidacion de Compra 2023 | CV2: Total Ventas 2023 (De comprobantes) (*) | CW2: Boleta de Venta 2024 | CX2: Declaración Jurada 2024 | CY2: Factura 2024 | CZ2: Guía de Remisión 2024 | DA2: Liquidación de Compra 2024 | DB2: Total general 2024 | DC2: Boleta de Venta 2025 | DD2: Declaración Jurada 2025 | DE2: Factura 2025 | DF2: Guía de Remisión 2025 | DG2: Liquidación de Compra 2025 | DH2: Total general 2025 | DI2: RUC | DJ2: NOMBRE SUNAT | DK2: Tipo de Organización* (Asociación/Cooperativa/CCNN, Comunidad Campesina y otros.)
A3: COOPERATIVA AGRARIA CAFETALERA MONTAÑA AZUL LTDA. - COOPACMA | B3: CAFÉ | C3: CAFÉ | D3: AMAZONAS | E3: 010706 | F3: AMAZONAS | G3: UTCUBAMBA | H3: LONYA GRANDE | I3: 1 | J3: 1 | K3: 1 | Q3: PAC | R3: =IF(I3=1,I$2,"")&IF(J3=1,IF(I3=1,"-","")&J$2,"")&IF(K3=1,IF(OR(J3=1,I3=1),"-","")&K$2,"")&IF(L3=1,IF(OR(K3=1,J3=1,I3=1),"-","")&L$2,"")&IF(M3=1,IF(OR(L3=1,K3=1,J3=1,I3=1),"-","")&M$2,"")&IF(N3=1,IF(OR(M3=1,L3=1,K3=1,J3=1,I3=1),"-","")&N$2,"")&IF(O3=1,IF(OR(N3=1,M3=1,L3=1,K3=1,J3=1,I3=1),"-","")&O$2,"")&IF(P3=1,IF(I3=1," - ",IF(J3=1," - ",IF(K3=1," - ",IF(L3=1," - ",IF(M3=1," - ",IF(N3=1," - ",IF(O3=1," - ","")))))))&P$2,"") | S3: =SUM('b2'!$I3:$P3) | T3: =IF(OR('b2'!$J3=1,'b2'!$K3=1,'b2'!$L3=1,'b2'!$M3=1,'b2'!$N3=1,'b2'!$O3=1,'b2'!$P3=1),"SI","NO") | U3: =IF(OR('b2'!$K3=1,'b2'!$L3=1,'b2'!$M3=1,'b2'!$N3=1,'b2'!$O3=1,'b2'!$P3=1),"SI","NO") | V3: 106 | W3: 72 | X3: 34 | Y3: 106 | Z3: 68 | AA3: 31 | AB3: 99 | AC3: 0 | AD3: 0 | AE3: 0 | AF3: 0 | AG3: 0 | AH3: 0 | AI3: 0 | AJ3: 0 | AK3: 0 | AL3: 0 | AM3: 0 | AN3: 0 | AO3: 0 | AP3: 0 | AQ3: 0 | AR3: =IF('b2'!$AQ3>0,'b2'!$AQ3,IF('b2'!$AN3>0,'b2'!$AN3,IF('b2'!$AK3>0,'b2'!$AK3,IF('b2'!$AH3>0,'b2'!$AH3,IF('b2'!$AE3>0,'b2'!$AE3,IF('b2'!$AB3>0,'b2'!$AB3,IF('b2'!$Y3>0,'b2'!$Y3,IF('b2'!$V3>0,'b2'!$V3," ---")))))))) | AS3: 0 | AT3: 9 | AU3: 0 | AV3: 0 | AW3: 0 | AX3: 0 | AY3: 0 | AZ3: 0 | BA3: 0 | BB3: 0 | BC3: 0 | BD3: 0 | BE3: 0 | BF3: 0 | BG3: 83583.84 | BH3: 83583.84 | BI3: #REF! | BJ3: #REF! | BK3: 3460.24 | BL3: 0 | BM3: 3460.24 | BN3: #REF! | BO3: #REF! | BP3: 0 | BQ3: 0 | BR3: 0 | BS3: #REF! | BT3: ='[2]DATA CONSOLIDADA 2018-2025 '!$BR5-'b2'!$BO3 | BU3: 0 | BV3: 0 | BW3: 0 | BX3: #REF! | BY3: #REF! | BZ3: 0 | CA3: 0 | CB3: 0 | CC3: #REF! | CD3: ='[2]DATA CONSOLIDADA 2018-2025 '!$CB5-'b2'!$BW3 | CE3: 0 | CF3: 0 | CG3: 0 | CH3: #REF! | CI3: ='[2]DATA CONSOLIDADA 2018-2025 '!$CG5-'b2'!$CB3 | CJ3: #REF! | CK3: 0 | CL3: 0 | CM3: 0 | CN3: #REF! | CO3: ='[2]DATA CONSOLIDADA 2018-2025 '!$CM5-'b2'!$CG3 | CP3: 0 | CQ3: 0 | CR3: 0 | CS3: 0 | CT3: 0 | CU3: 0 | CV3: 0 | CW3: 0 | CX3: 0 | CY3: 0 | CZ3: 0 | DA3: 0 | DB3: 0 | DC3: 0 | DD3: 0 | DE3: 0 | DF3: 0 | DG3: 0 | DH3: 0 | DI3: 20600200756 | DJ3: COOPERATIVA AGRARIA CAFETALERA MONTAÑA AZUL LTDA. - COOPACMA | DK3: 02 Cooperativa
A4: ASOCIACIÓN DE PRODUCTORES DE CAFÉ ORGANICO Y CAFES ESPECIALES -APROCOYCE AMAZONAS | B4: CAFÉ | C4: CAFÉ | D4: AMAZONAS | E4: 010601 | F4: AMAZONAS | G4: RODRIGUEZ DE MENDOZA | H4: SAN NICOLAS | J4: 1 | K4: 1 | L4: 1 | M4: 1 | N4: 1 | Q4: PAC | R4: =IF(I4=1,I$2,"")&IF(J4=1,IF(I4=1,"-","")&J$2,"")&IF(K4=1,IF(OR(J4=1,I4=1),"-","")&K$2,"")&IF(L4=1,IF(OR(K4=1,J4=1,I4=1),"-","")&L$2,"")&IF(M4=1,IF(OR(L4=1,K4=1,J4=1,I4=1),"-","")&M$2,"")&IF(N4=1,IF(OR(M4=1,L4=1,K4=1,J4=1,I4=1),"-","")&N$2,"")&IF(O4=1,IF(OR(N4=1,M4=1,L4=1,K4=1,J4=1,I4=1),"-","")&O$2,"")&IF(P4=1,IF(I4=1," - ",IF(J4=1," - ",IF(K4=1," - ",IF(L4=1," - ",IF(M4=1," - ",IF(N4=1," - ",IF(O4=1," - ","")))))))&P$2,"") | S4: =SUM('b2'!$I4:$P4) | T4: =IF(OR('b2'!$J4=1,'b2'!$K4=1,'b2'!$L4=1,'b2'!$M4=1,'b2'!$N4=1,'b2'!$O4=1,'b2'!$P4=1),"SI","NO") | U4: =IF(OR('b2'!$K4=1,'b2'!$L4=1,'b2'!$M4=1,'b2'!$N4=1,'b2'!$O4=1,'b2'!$P4=1),"SI","NO") | V4: 0 | W4: 50 | X4: 33 | Y4: 83 | Z4: 222 | AA4: 135 | AB4: 357 | AC4: 208 | AD4: 150 | AE4: 358 | AF4: 208 | AG4: 150 | AH4: 358 | AI4: 208 | AJ4: 150 | AK4: 358 | AL4: 0 | AM4: 0 | AN4: 0 | AO4: 0 | AP4: 0 | AQ4: 0 | AR4: =IF('b2'!$AQ4>0,'b2'!$AQ4,IF('b2'!$AN4>0,'b2'!$AN4,IF('b2'!$AK4>0,'b2'!$AK4,IF('b2'!$AH4>0,'b2'!$AH4,IF('b2'!$AE4>0,'b2'!$AE4,IF('b2'!$AB4>0,'b2'!$AB4,IF('b2'!$Y4>0,'b2'!$Y4,IF('b2'!$V4>0,'b2'!$V4," ---")))))))) | AS4: 0 | AT4: 0 | AU4: 27 | AV4: 8 | AW4: 41 | AX4: 7 | AY4: 32 | AZ4: 6 | BA4: 0 | BB4: 0 | BC4: 0 | BD4: 0 | BE4: 0 | BF4: 4171009.2 | BG4: 0 | BH4: 4171009.2 | BI4: #REF! | BJ4: #REF! | BK4: 741888.91 | BL4: 0 | BM4: 741888.91 | BN4: #REF! | BO4: #REF! | BP4: 4099294.7 | BQ4: 0 | BR4: 4099294.7 | BS4: #REF! | BT4: ='[2]DATA CONSOLIDADA 2018-2025 '!$BR6-'b2'!$BO4 | BU4: 1820885 | BV4: 0 | BW4: 1820885 | BX4: #REF! | BY4: #REF! | BZ4: 4179472.3 | CA4: 0 | CB4: 4179472.3 | CC4: #REF! | CD4: ='[2]DATA CONSOLIDADA 2018-2025 '!$CB6-'b2'!$BW4 | CE4: 0 | CF4: 0 | CG4: 0 | CH4: #REF! | CI4: ='[2]DATA CONSOLIDADA 2018-2025 '!$CG6-'b2'!$CB4 | CJ4: #REF! | CK4: 0 | CL4: 0 | CM4: 0 | CN4: #REF! | CO4: ='[2]DATA CONSOLIDADA 2018-2025 '!$CM6-'b2'!$CG4 | CP4: 0 | CQ4: 0 | CR4: 0 | CS4: 4179472.3 | CT4: 0 | CU4: 0 | CV4: 4179472.3 | CW4: 0 | CX4: 0 | CY4: 0 | CZ4: 0 | DA4: 0 | DB4: 0 | DC4: 0 | DD4: 0 | DE4: 0 | DF4: 0 | DG4: 0 | DH4: 0 | DI4: 20539241665 | DJ4: ASOCIACION DE PRODUCTORES DE CAFES ORGANICOS Y CAFES ESPECIALES DE AMAZONAS | DK4: 01 Asociación
A5: ASOCIACIÓN DE PRODUCTORES Y EXPORTADORES DE CAFÉ RODRIGUEZ DE MENDOZA-APROEXPORT | B5: CAFÉ | C5: CAFÉ | D5: AMAZONAS | E5: 010601 | F5: AMAZONAS | G5: RODRIGUEZ DE MENDOZA | H5: SAN NICOLAS | J5: 1 | Q5: PAC | R5: =IF(I5=1,I$2,"")&IF(J5=1,IF(I5=1,"-","")&J$2,"")&IF(K5=1,IF(OR(J5=1,I5=1),"-","")&K$2,"")&IF(L5=1,IF(OR(K5=1,J5=1,I5=1),"-","")&L$2,"")&IF(M5=1,IF(OR(L5=1,K5=1,J5=1,I5=1),"-","")&M$2,"")&IF(N5=1,IF(OR(M5=1,L5=1,K5=1,J5=1,I5=1),"-","")&N$2,"")&IF(O5=1,IF(OR(N5=1,M5=1,L5=1,K5=1,J5=1,I5=1),"-","")&O$2,"")&IF(P5=1,IF(I5=1," - ",IF(J5=1," - ",IF(K5=1," - ",IF(L5=1," - ",IF(M5=1," - ",IF(N5=1," - ",IF(O5=1," - ","")))))))&P$2,"") | S5: =SUM('b2'!$I5:$P5) | T5: =IF(OR('b2'!$J5=1,'b2'!$K5=1,'b2'!$L5=1,'b2'!$M5=1,'b2'!$N5=1,'b2'!$O5=1,'b2'!$P5=1),"SI","NO") | U5: =IF(OR('b2'!$K5=1,'b2'!$L5=1,'b2'!$M5=1,'b2'!$N5=1,'b2'!$O5=1,'b2'!$P5=1),"SI","NO") | V5: 0 | W5: 231 | X5: 149 | Y5: 380 | Z5: 0 | AA5: 0 | AB5: 0 | AC5: 0 | AD5: 0 | AE5: 0 | AF5: 0 | AG5: 0 | AH5: 0 | AI5: 0 | AJ5: 0 | AK5: 0 | AL5: 0 | AM5: 0 | AN5: 0 | AO5: 0 | AP5: 0 | AQ5: 0 | AR5: =IF('b2'!$AQ5>0,'b2'!$AQ5,IF('b2'!$AN5>0,'b2'!$AN5,IF('b2'!$AK5>0,'b2'!$AK5,IF('b2'!$AH5>0,'b2'!$AH5,IF('b2'!$AE5>0,'b2'!$AE5,IF('b2'!$AB5>0,'b2'!$AB5,IF('b2'!$Y5>0,'b2'!$Y5,IF('b2'!$V5>0,'b2'!$V5," ---")))))))) | AS5: 0 | AT5: 0 | AU5: 0 | AV5: 0 | AW5: 0 | AX5: 0 | AY5: 0 | AZ5: 0 | BA5: 0 | BB5: 0 | BC5: 0 | BD5: 0 | BE5: 0 | BF5: 0 | BG5: 0 | BH5: 0 | BI5: #REF! | BJ5: #REF! | BK5: 0 | BL5: 0 | BM5: 0 | BN5: #REF! | BO5: #REF! | BP5: 0 | BQ5: 0 | BR5: 0 | BS5: #REF! | BT5: ='[2]DATA CONSOLIDADA 2018-2025 '!$BR7-'b2'!$BO5 | BU5: 0 | BV5: 0 | BW5: 0 | BX5: #REF! | BY5: #REF! | BZ5: 0 | CA5: 0 | CB5: 0 | CC5: #REF! | CD5: ='[2]DATA CONSOLIDADA 2018-2025 '!$CB7-'b2'!$BW5 | CE5: 0 | CF5: 0 | CG5: 0 | CH5: #REF! | CI5: ='[2]DATA CONSOLIDADA 2018-2025 '!$CG7-'b2'!$CB5 | CJ5: #REF! | CK5: 0 | CL5: 0 | CM5: 0 | CN5: #REF! | CO5: ='[2]DATA CONSOLIDADA 2018-2025 '!$CM7-'b2'!$CG5 | CP5: 0 | CQ5: 0 | CR5: 0 | CS5: 0 | CT5: 0 | CU5: 0 | CV5: 0 | CW5: 0 | CX5: 0 | CY5: 0 | CZ5: 0 | DA5: 0 | DB5: 0 | DC5: 0 | DD5: 0 | DE5: 0 | DF5: 0 | DG5: 0 | DH5: 0 | DI5: 20539205600 | DJ5: ASOCIACION DE PRODUCTORES Y EXPORTADORES DE CAFE RODRIGUEZ DE MENDOZA | DK5: 01 Asociación
A6: COOPERATIVA AGRARIA CAFETALERA ALTA MONTAÑA | B6: CAFÉ | C6: CAFÉ | D6: AMAZONAS | E6: 010604 | F6: AMAZONAS | G6: RODRIGUEZ DE MENDOZA | H6: HUAMBO | I6: 1 | J6: 1 | K6: 1 | L6: 1 | M6: 1 | N6: 1 | Q6: PAC | R6: =IF(I6=1,I$2,"")&IF(J6=1,IF(I6=1,"-","")&J$2,"")&IF(K6=1,IF(OR(J6=1,I6=1),"-","")&K$2,"")&IF(L6=1,IF(OR(K6=1,J6=1,I6=1),"-","")&L$2,"")&IF(M6=1,IF(OR(L6=1,K6=1,J6=1,I6=1),"-","")&M$2,"")&IF(N6=1,IF(OR(M6=1,L6=1,K6=1,J6=1,I6=1),"-","")&N$2,"")&IF(O6=1,IF(OR(N6=1,M6=1,L6=1,K6=1,J6=1,I6=1),"-","")&O$2,"")&IF(P6=1,IF(I6=1," - ",IF(J6=1," - ",IF(K6=1," - ",IF(L6=1," - ",IF(M6=1," - ",IF(N6=1," - ",IF(O6=1," - ","")))))))&P$2,"") | S6: =SUM('b2'!$I6:$P6) | T6: =IF(OR('b2'!$J6=1,'b2'!$K6=1,'b2'!$L6=1,'b2'!$M6=1,'b2'!$N6=1,'b2'!$O6=1,'b2'!$P6=1),"SI","NO") | U6: =IF(OR('b2'!$K6=1,'b2'!$L6=1,'b2'!$M6=1,'b2'!$N6=1,'b2'!$O6=1,'b2'!$P6=1),"SI","NO") | V6: 150 | W6: 0 | X6: 0 | Y6: 0 | Z6: 108 | AA6: 42 | AB6: 150 | AC6: 205 | AD6: 119 | AE6: 324 | AF6: 205 | AG6: 119 | AH6: 324 | AI6: 205 | AJ6: 119 | AK6: 324 | AL6: 0 | AM6: 0 | AN6: 0 | AO6: 0 | AP6: 0 | AQ6: 0 | AR6: =IF('b2'!$AQ6>0,'b2'!$AQ6,IF('b2'!$AN6>0,'b2'!$AN6,IF('b2'!$AK6>0,'b2'!$AK6,IF('b2'!$AH6>0,'b2'!$AH6,IF('b2'!$AE6>0,'b2'!$AE6,IF('b2'!$AB6>0,'b2'!$AB6,IF('b2'!$Y6>0,'b2'!$Y6,IF('b2'!$V6>0,'b2'!$V6," ---")))))))) | AS6: 0 | AT6: 0 | AU6: 25 | AV6: 9 | AW6: 41 | AX6: 7 | AY6: 32 | AZ6: 6 | BA6: 0 | BB6: 0 | BC6: 0 | BD6: 0 | BE6: 0 | BF6: 409100 | BG6: 0 | BH6: 409100 | BI6: #REF! | BJ6: #REF! | BK6: 325000 | BL6: 0 | BM6: 325000 | BN6: #REF! | BO6: #REF! | BP6: 1224192.5 | BQ6: 398235.92 | BR6: 1622428.4 | BS6: #REF! | BT6: ='[2]DATA CONSOLIDADA 2018-2025 '!$BR8-'b2'!$BO6 | BU6: 820950 | BV6: 0 | BW6: 820950 | BX6: #REF! | BY6: #REF! | BZ6: 165821.2 | CA6: 0 | CB6: 165821.2 | CC6: #REF! | CD6: ='[2]DATA CONSOLIDADA 2018-2025 '!$CB8-'b2'!$BW6 | CE6: 0 | CF6: 0 | CG6: 0 | CH6: #REF! | CI6: ='[2]DATA CONSOLIDADA 2018-2025 '!$CG8-'b2'!$CB6 | CJ6: #REF! | CK6: 0 | CL6: 0 | CM6: 0 | CN6: #REF! | CO6: ='[2]DATA CONSOLIDADA 2018-2025 '!$CM8-'b2'!$CG6 | CP6: 9793.4 | CQ6: 0 | CR6: 0 | CS6: 156027.8 | CT6: 0 | CU6: 0 | CV6: 165821.2 | CW6: 0 | CX6: 0 | CY6: 0 | CZ6: 0 | DA6: 0 | DB6: 0 | DC6: 0 | DD6: 0 | DE6: 0 | DF6: 0 | DG6: 0 | DH6: 0 | DI6: 20603320621 | DJ6: COOPERATIVA AGRARIA CAFETALERA ALTA MONTAÑA | DK6: 02 Cooperativa
A7: ASOCIACION DE PRODUCTORES AGROPECUARIOS LA FLOR DE CAFÉ | B7: CAFÉ | C7: CAFÉ | D7: AMAZONAS | E7: 010601 | F7: AMAZONAS | G7: RODRIGUEZ DE MENDOZA | H7: SAN NICOLAS | J7: 1 | K7: 1 | L7: 1 | M7: 1 | N7: 1 | Q7: PAC | R7: =IF(I7=1,I$2,"")&IF(J7=1,IF(I7=1,"-","")&J$2,"")&IF(K7=1,IF(OR(J7=1,I7=1),"-","")&K$2,"")&IF(L7=1,IF(OR(K7=1,J7=1,I7=1),"-","")&L$2,"")&IF(M7=1,IF(OR(L7=1,K7=1,J7=1,I7=1),"-","")&M$2,"")&IF(N7=1,IF(OR(M7=1,L7=1,K7=1,J7=1,I7=1),"-","")&N$2,"")&IF(O7=1,IF(OR(N7=1,M7=1,L7=1,K7=1,J7=1,I7=1),"-","")&O$2,"")&IF(P7=1,IF(I7=1," - ",IF(J7=1," - ",IF(K7=1," - ",IF(L7=1," - ",IF(M7=1," - ",IF(N7=1," - ",IF(O7=1," - ","")))))))&P$2,"") | S7: =SUM('b2'!$I7:$P7) | T7: =IF(OR('b2'!$J7=1,'b2'!$K7=1,'b2'!$L7=1,'b2'!$M7=1,'b2'!$N7=1,'b2'!$O7=1,'b2'!$P7=1),"SI","NO") | U7: =IF(OR('b2'!$K7=1,'b2'!$L7=1,'b2'!$M7=1,'b2'!$N7=1,'b2'!$O7=1,'b2'!$P7=1),"SI","NO") | V7: 0 | W7: 210 | X7: 113 | Y7: 323 | Z7: 210 | AA7: 113 | AB7: 323 | AC7: 274 | AD7: 137 | AE7: 411 | AF7: 274 | AG7: 137 | AH7: 411 | AI7: 274 | AJ7: 137 | AK7: 411 | AL7: 0 | AM7: 0 | AN7: 0 | AO7: 0 | AP7: 0 | AQ7: 0 | AR7: =IF('b2'!$AQ7>0,'b2'!$AQ7,IF('b2'!$AN7>0,'b2'!$AN7,IF('b2'!$AK7>0,'b2'!$AK7,IF('b2'!$AH7>0,'b2'!$AH7,IF('b2'!$AE7>0,'b2'!$AE7,IF('b2'!$AB7>0,'b2'!$AB7,IF('b2'!$Y7>0,'b2'!$Y7,IF('b2'!$V7>0,'b2'!$V7," ---")))))))) | AS7: 0 | AT7: 0 | AU7: 26 | AV7: 8 | AW7: 43 | AX7: 7 | AY7: 32 | AZ7: 6 | BA7: 0 | BB7: 0 | BC7: 0 | BD7: 0 | BE7: 0 | BF7: 6041471.5 | BG7: 0 | BH7: 6041471.5 | BI7: #REF! | BJ7: #REF! | BK7: 523737.39 | BL7: 0 | BM7: 523737.39 | BN7: #REF! | BO7: #REF! | BP7: 3394807.7 | BQ7: 0 | BR7: 3394807.7 | BS7: #REF! | BT7: ='[2]DATA CONSOLIDADA 2018-2025 '!$BR9-'b2'!$BO7 | BU7: 4076542 | BV7: 446118 | BW7: 4522660 | BX7: #REF! | BY7: #REF! | BZ7: 5733612.8 | CA7: 984023.42 | CB7: 6717636.2 | CC7: #REF! | CD7: ='[2]DATA CONSOLIDADA 2018-2025 '!$CB9-'b2'!$BW7 | CE7: 0 | CF7: 0 | CG7: 0 | CH7: #REF! | CI7: ='[2]DATA CONSOLIDADA 2018-2025 '!$CG9-'b2'!$CB7 | CJ7: #REF! | CK7: 0 | CL7: 0 | CM7: 0 | CN7: #REF! | CO7: ='[2]DATA CONSOLIDADA 2018-2025 '!$CM9-'b2'!$CG7 | CP7: 0 | CQ7: 0 | CR7: 0 | CS7: 6717636.2 | CT7: 0 | CU7: 0 | CV7: 6717636.2 | CW7: 0 | CX7: 0 | CY7: 0 | CZ7: 0 | DA7: 0 | DB7: 0 | DC7: 0 | DD7: 0 | DE7: 0 | DF7: 0 | DG7: 0 | DH7: 0 | DI7: 20480762895 | DJ7: ASOCIACION DE PRODUCTORES AGROPECUARIOS LA FLOR DE CAFÉ | DK7: 01 Asociación
A8: COOPERATIVA DE SERVICIOS MULTIPLES - APROCAM | B8: CACAO | C8: CACAO | D8: AMAZONAS | E8: 010201 | F8: AMAZONAS | G8: BAGUA | H8: BAGUA | I8: 1 | J8: 1 | K8: 1 | L8: 1 | M8: 1 | N8: 1 | Q8: PAC | R8: =IF(I8=1,I$2,"")&IF(J8=1,IF(I8=1,"-","")&J$2,"")&IF(K8=1,IF(OR(J8=1,I8=1),"-","")&K$2,"")&IF(L8=1,IF(OR(K8=1,J8=1,I8=1),"-","")&L$2,"")&IF(M8=1,IF(OR(L8=1,K8=1,J8=1,I8=1),"-","")&M$2,"")&IF(N8=1,IF(OR(M8=1,L8=1,K8=1,J8=1,I8=1),"-","")&N$2,"")&IF(O8=1,IF(OR(N8=1,M8=1,L8=1,K8=1,J8=1,I8=1),"-","")&O$2,"")&IF(P8=1,IF(I8=1," - ",IF(J8=1," - ",IF(K8=1," - ",IF(L8=1," - ",IF(M8=1," - ",IF(N8=1," - ",IF(O8=1," - ","")))))))&P$2,"") | S8: =SUM('b2'!$I8:$P8) | T8: =IF(OR('b2'!$J8=1,'b2'!$K8=1,'b2'!$L8=1,'b2'!$M8=1,'b2'!$N8=1,'b2'!$O8=1,'b2'!$P8=1),"SI","NO") | U8: =IF(OR('b2'!$K8=1,'b2'!$L8=1,'b2'!$M8=1,'b2'!$N8=1,'b2'!$O8=1,'b2'!$P8=1),"SI","NO") | V8: 418 | W8: 353 | X8: 65 | Y8: 418 | Z8: 357 | AA8: 66 | AB8: 423 | AC8: 201 | AD8: 43 | AE8: 244 | AF8: 201 | AG8: 43 | AH8: 244 | AI8: 201 | AJ8: 43 | AK8: 244 | AL8: 0 | AM8: 0 | AN8: 0 | AO8: 0 | AP8: 0 | AQ8: 0 | AR8: =IF('b2'!$AQ8>0,'b2'!$AQ8,IF('b2'!$AN8>0,'b2'!$AN8,IF('b2'!$AK8>0,'b2'!$AK8,IF('b2'!$AH8>0,'b2'!$AH8,IF('b2'!$AE8>0,'b2'!$AE8,IF('b2'!$AB8>0,'b2'!$AB8,IF('b2'!$Y8>0,'b2'!$Y8,IF('b2'!$V8>0,'b2'!$V8," ---")))))))) | AS8: 0 | AT8: 0 | AU8: 35 | AV8: 7 | AW8: 32 | AX8: 5 | AY8: 39 | AZ8: 7 | BA8: 0 | BB8: 0 | BC8: 0 | BD8: 0 | BE8: 279033.24 | BF8: 0 | BG8: 1026216.8 | BH8: 1026216.8 | BI8: #REF! | BJ8: #REF! | BK8: 101917.7 | BL8: 284025.07 | BM8: 385942.77 | BN8: #REF! | BO8: #REF! | BP8: 78859.15 | BQ8: 2033180.4 | BR8: 2112039.5 | BS8: #REF! | BT8: ='[2]DATA CONSOLIDADA 2018-2025 '!$BR10-'b2'!$BO8 | BU8: 65644.73 | BV8: 1189543.9 | BW8: 1255188.6 | BX8: #REF! | BY8: #REF! | BZ8: 114467.98 | CA8: 1092156.7 | CB8: 1206624.7 | CC8: #REF! | CD8: ='[2]DATA CONSOLIDADA 2018-2025 '!$CB10-'b2'!$BW8 | CE8: 0 | CF8: 0 | CG8: 0 | CH8: #REF! | CI8: ='[2]DATA CONSOLIDADA 2018-2025 '!$CG10-'b2'!$CB8 | CJ8: #REF! | CK8: 0 | CL8: 0 | CM8: 0 | CN8: #REF! | CO8: ='[2]DATA CONSOLIDADA 2018-2025 '!$CM10-'b2'!$CG8 | CP8: 34067.084 | CQ8: 0 | CR8: 0 | CS8: 1172557.6 | CT8: 0 | CU8: 0 | CV8: 1206624.7 | CW8: 0 | CX8: 0 | CY8: 0 | CZ8: 0 | DA8: 0 | DB8: 0 | DC8: 0 | DD8: 0 | DE8: 0 | DF8: 0 | DG8: 0 | DH8: 0 | DI8: 20480458550 | DJ8: COOPERATIVA AGRARIA APROCAM | DK8: 02 Cooperativa
A9: COOPERATIVA CENTRAL DE PRODUCTORES AGROPECUARIOS DE AMAZONAS - CEPROAA | B9: CACAO | C9: CACAO | D9: AMAZONAS | E9: 010702 | F9: AMAZONAS | G9: UTCUBAMBA | H9: CAJARURO | I9: 1 | J9: 1 | K9: 1 | L9: 1 | M9: 1 | N9: 1 | Q9: PAC | R9: =IF(I9=1,I$2,"")&IF(J9=1,IF(I9=1,"-","")&J$2,"")&IF(K9=1,IF(OR(J9=1,I9=1),"-","")&K$2,"")&IF(L9=1,IF(OR(K9=1,J9=1,I9=1),"-","")&L$2,"")&IF(M9=1,IF(OR(L9=1,K9=1,J9=1,I9=1),"-","")&M$2,"")&IF(N9=1,IF(OR(M9=1,L9=1,K9=1,J9=1,I9=1),"-","")&N$2,"")&IF(O9=1,IF(OR(N9=1,M9=1,L9=1,K9=1,J9=1,I9=1),"-","")&O$2,"")&IF(P9=1,IF(I9=1," - ",IF(J9=1," - ",IF(K9=1," - ",IF(L9=1," - ",IF(M9=1," - ",IF(N9=1," - ",IF(O9=1," - ","")))))))&P$2,"") | S9: =SUM('b2'!$I9:$P9) | T9: =IF(OR('b2'!$J9=1,'b2'!$K9=1,'b2'!$L9=1,'b2'!$M9=1,'b2'!$N9=1,'b2'!$O9=1,'b2'!$P9=1),"SI","NO") | U9: =IF(OR('b2'!$K9=1,'b2'!$L9=1,'b2'!$M9=1,'b2'!$N9=1,'b2'!$O9=1,'b2'!$P9=1),"SI","NO") | V9: 344 | W9: 272 | X9: 71 | Y9: 343 | Z9: 266 | AA9: 71 | AB9: 337 | AC9: 271 | AD9: 71 | AE9: 342 | AF9: 271 | AG9: 71 | AH9: 342 | AI9: 271 | AJ9: 71 | AK9: 342 | AL9: 0 | AM9: 0 | AN9: 0 | AO9: 0 | AP9: 0 | AQ9: 0 | AR9: =IF('b2'!$AQ9>0,'b2'!$AQ9,IF('b2'!$AN9>0,'b2'!$AN9,IF('b2'!$AK9>0,'b2'!$AK9,IF('b2'!$AH9>0,'b2'!$AH9,IF('b2'!$AE9>0,'b2'!$AE9,IF('b2'!$AB9>0,'b2'!$AB9,IF('b2'!$Y9>0,'b2'!$Y9,IF('b2'!$V9>0,'b2'!$V9," ---")))))))) | AS9: 0 | AT9: 0 | AU9: 24 | AV9: 7 | AW9: 28 | AX9: 7 | AY9: 39 | AZ9: 6 | BA9: 0 | BB9: 0 | BC9: 0 | BD9: 0 | BE9: 0 | BF9: 0 | BG9: 1072102.3 | BH9: 1072102.3 | BI9: #REF! | BJ9: #REF! | BK9: 454472.63 | BL9: 0 | BM9: 454472.63 | BN9: #REF! | BO9: #REF! | BP9: 1609560.4 | BQ9: 0 | BR9: 1609560.4 | BS9: #REF! | BT9: ='[2]DATA CONSOLIDADA 2018-2025 '!$BR11-'b2'!$BO9 | BU9: 1731876.8 | BV9: 0 | BW9: 1731876.8 | BX9: #REF! | BY9: #REF! | BZ9: 1545263.1 | CA9: 0 | CB9: 1545263.1 | CC9: #REF! | CD9: ='[2]DATA CONSOLIDADA 2018-2025 '!$CB11-'b2'!$BW9 | CE9: 0 | CF9: 0 | CG9: 0 | CH9: #REF! | CI9: ='[2]DATA CONSOLIDADA 2018-2025 '!$CG11-'b2'!$CB9 | CJ9: #REF! | CK9: 0 | CL9: 0 | CM9: 0 | CN9: #REF! | CO9: ='[2]DATA CONSOLIDADA 2018-2025 '!$CM11-'b2'!$CG9 | CP9: 9912.9964 | CQ9: 0 | CR9: 820166.58 | CS9: 715183.52 | CT9: 0 | CU9: 0 | CV9: 1545263.1 | CW9: 0 | CX9: 0 | CY9: 0 | CZ9: 0 | DA9: 0 | DB9: 0 | DC9: 0 | DD9: 0 | DE9: 0 | DF9: 0 | DG9: 0 | DH9: 0 | DI9: 20479917141 | DJ9: COOPERATIVA AGRARIA CENTRAL DE PRODUCTORES DE AMAZONAS | DK9: 02 Cooperativa
A10: ASOCIACION DE PRODUCTORES AGROPECUARIOS LUIS SOLIBARRIA | B10: CACAO | C10: CACAO | D10: AMAZONAS | E10: 010701 | F10: AMAZONAS | G10: UTCUBAMBA | H10: BAGUA GRANDE | I10: 1 | J10: 1 | Q10: PAC | R10: =IF(I10=1,I$2,"")&IF(J10=1,IF(I10=1,"-","")&J$2,"")&IF(K10=1,IF(OR(J10=1,I10=1),"-","")&K$2,"")&IF(L10=1,IF(OR(K10=1,J10=1,I10=1),"-","")&L$2,"")&IF(M10=1,IF(OR(L10=1,K10=1,J10=1,I10=1),"-","")&M$2,"")&IF(N10=1,IF(OR(M10=1,L10=1,K10=1,J10=1,I10=1),"-","")&N$2,"")&IF(O10=1,IF(OR(N10=1,M10=1,L10=1,K10=1,J10=1,I10=1),"-","")&O$2,"")&IF(P10=1,IF(I10=1," - ",IF(J10=1," - ",IF(K10=1," - ",IF(L10=1," - ",IF(M10=1," - ",IF(N10=1," - ",IF(O10=1," - ","")))))))&P$2,"") | S10: =SUM('b2'!$I10:$P10) | T10: =IF(OR('b2'!$J10=1,'b2'!$K10=1,'b2'!$L10=1,'b2'!$M10=1,'b2'!$N10=1,'b2'!$O10=1,'b2'!$P10=1),"SI","NO") | U10: =IF(OR('b2'!$K10=1,'b2'!$L10=1,'b2'!$M10=1,'b2'!$N10=1,'b2'!$O10=1,'b2'!$P10=1),"SI","NO") | V10: 147 | W10: 120 | X10: 25 | Y10: 145 | Z10: 0 | AA10: 0 | AB10: 0 | AC10: 0 | AD10: 0 | AE10: 0 | AF10: 0 | AG10: 0 | AH10: 0 | AI10: 0 | AJ10: 0 | AK10: 0 | AL10: 0 | AM10: 0 | AN10: 0 | AO10: 0 | AP10: 0 | AQ10: 0 | AR10: =IF('b2'!$AQ10>0,'b2'!$AQ10,IF('b2'!$AN10>0,'b2'!$AN10,IF('b2'!$AK10>0,'b2'!$AK10,IF('b2'!$AH10>0,'b2'!$AH10,IF('b2'!$AE10>0,'b2'!$AE10,IF('b2'!$AB10>0,'b2'!$AB10,IF('b2'!$Y10>0,'b2'!$Y10,IF('b2'!$V10>0,'b2'!$V10," ---")))))))) | AS10: 0 | AT10: 0 | AU10: 0 | AV10: 0 | AW10: 0 | AX10: 0 | AY10: 0 | AZ10: 0 | BA10: 0 | BB10: 0 | BC10: 0 | BD10: 0 | BE10: 0 | BF10: 0 | BG10: 0 | BH10: 0 | BI10: #REF! | BJ10: #REF! | BK10: 0 | BL10: 0 | BM10: 0 | BN10: #REF! | BO10: #REF! | BP10: 0 | BQ10: 0 | BR10: 0 | BS10: #REF! | BT10: ='[2]DATA CONSOLIDADA 2018-2025 '!$BR12-'b2'!$BO10 | BU10: 0 | BV10: 0 | BW10: 0 | BX10: #REF! | BY10: #REF! | BZ10: 0 | CA10: 0 | CB10: 0 | CC10: #REF! | CD10: ='[2]DATA CONSOLIDADA 2018-2025 '!$CB12-'b2'!$BW10 | CE10: 0 | CF10: 0 | CG10: 0 | CH10: #REF! | CI10: ='[2]DATA CONSOLIDADA 2018-2025 '!$CG12-'b2'!$CB10 | CJ10: #REF! | CK10: 0 | CL10: 0 | CM10: 0 | CN10: #REF! | CO10: ='[2]DATA CONSOLIDADA 2018-2025 '!$CM12-'b2'!$CG10 | CP10: 0 | CQ10: 0 | CR10: 0 | CS10: 0 | CT10: 0 | CU10: 0 | CV10: 0 | CW10: 0 | CX10: 0 | CY10: 0 | CZ10: 0 | DA10: 0 | DB10: 0 | DC10: 0 | DD10: 0 | DE10: 0 | DF10: 0 | DG10: 0 | DH10: 0 | DI10: 20479856258 | DJ10: ASOCIACION DE PRODUCTORES AGROPECUARIOS LUIS SOLIBARRIA | DK10: 01 Asociación
A11: COOPERATIVA AGRARIA CAFETALERA BAGUA GRANDE LTDA | B11: CAFÉ | C11: CAFÉ | D11: AMAZONAS | E11: 010701 | F11: AMAZONAS | G11: UTCUBAMBA | H11: BAGUA GRANDE | I11: 1 | J11: 1 | K11: 1 | N11: 1 | O11: 1 | Q11: PAC | R11: =IF(I11=1,I$2,"")&IF(J11=1,IF(I11=1,"-","")&J$2,"")&IF(K11=1,IF(OR(J11=1,I11=1),"-","")&K$2,"")&IF(L11=1,IF(OR(K11=1,J11=1,I11=1),"-","")&L$2,"")&IF(M11=1,IF(OR(L11=1,K11=1,J11=1,I11=1),"-","")&M$2,"")&IF(N11=1,IF(OR(M11=1,L11=1,K11=1,J11=1,I11=1),"-","")&N$2,"")&IF(O11=1,IF(OR(N11=1,M11=1,L11=1,K11=1,J11=1,I11=1),"-","")&O$2,"")&IF(P11=1,IF(I11=1," - ",IF(J11=1," - ",IF(K11=1," - ",IF(L11=1," - ",IF(M11=1," - ",IF(N11=1," - ",IF(O11=1," - ","")))))))&P$2,"") | S11: =SUM('b2'!$I11:$P11) | T11: =IF(OR('b2'!$J11=1,'b2'!$K11=1,'b2'!$L11=1,'b2'!$M11=1,'b2'!$N11=1,'b2'!$O11=1,'b2'!$P11=1),"SI","NO") | U11: =IF(OR('b2'!$K11=1,'b2'!$L11=1,'b2'!$M11=1,'b2'!$N11=1,'b2'!$O11=1,'b2'!$P11=1),"SI","NO") | V11: 592 | W11: 498 | X11: 91 | Y11: 589 | Z11: 296 | AA11: 58 | AB11: 354 | AC11: 0 | AD11: 0 | AE11: 0 | AF11: 0 | AG11: 0 | AH11: 0 | AI11: 596 | AJ11: 94 | AK11: 690 | AL11: 263 | AM11: 46 | AN11: 309 | AO11: 0 | AP11: 0 | AQ11: 0 | AR11: =IF('b2'!$AQ11>0,'b2'!$AQ11,IF('b2'!$AN11>0,'b2'!$AN11,IF('b2'!$AK11>0,'b2'!$AK11,IF('b2'!$AH11>0,'b2'!$AH11,IF('b2'!$AE11>0,'b2'!$AE11,IF('b2'!$AB11>0,'b2'!$AB11,IF('b2'!$Y11>0,'b2'!$Y11,IF('b2'!$V11>0,'b2'!$V11," ---")))))))) | AS11: 0 | AT11: 9 | AU11: 0 | AV11: 0 | AW11: 0 | AX11: 0 | AY11: 45 | AZ11: 6 | BA11: 30 | BB11: 5 | BC11: 0 | BD11: 0 | BE11: 448800 | BF11: 0 | BG11: 1768356.9 | BH11: 1768356.9 | BI11: #REF! | BJ11: #REF! | BK11: 443003.7 | BL11: 1384395.9 | BM11: 1827399.6 | BN11: #REF! | BO11: #REF! | BP11: 0 | BQ11: 0 | BR11: 0 | BS11: #REF! | BT11: ='[2]DATA CONSOLIDADA 2018-2025 '!$BR13-'b2'!$BO11 | BU11: 0 | BV11: 0 | BW11: 0 | BX11: #REF! | BY11: #REF! | BZ11: 0 | CA11: 5910875.3 | CB11: 5910875.3 | CC11: #REF! | CD11: ='[2]DATA CONSOLIDADA 2018-2025 '!$CB13-'b2'!$BW11 | CE11: 264948.69 | CF11: 8889133.3 | CG11: 9154082 | CH11: #REF! | CI11: ='[2]DATA CONSOLIDADA 2018-2025 '!$CG13-'b2'!$CB11 | CJ11: #REF! | CK11: 0 | CL11: 0 | CM11: 0 | CN11: #REF! | CO11: ='[2]DATA CONSOLIDADA 2018-2025 '!$CM13-'b2'!$CG11 | CP11: 0 | CQ11: 0 | CR11: 0 | CS11: 5910875.3 | CT11: 0 | CU11: 0 | CV11: 5910875.3 | CW11: 0 | CX11: 0 | CY11: 9154082 | CZ11: 0 | DA11: 0 | DB11: 9154082 | DC11: 0 | DD11: 0 | DE11: 0 | DF11: 0 | DG11: 0 | DH11: 0 | DI11: 20170142773 | DJ11: COOPERATIVA AGRARIA CAFETALERA BAGUA GRANDE LIMITADA | DK11: 02 Cooperativa
A12: ASOCIACION DE PRODUCTORES AGROPECUARIOS VALLE VERDE DE RODRIGUEZ DE MENDOZA | B12: CAFÉ | C12: CAFÉ | D12: AMAZONAS | E12: 010601 | F12: AMAZONAS | G12: RODRIGUEZ DE MENDOZA | H12: SAN NICOLAS | I12: 1 | J12: 1 | Q12: PAC | R12: =IF(I12=1,I$2,"")&IF(J12=1,IF(I12=1,"-","")&J$2,"")&IF(K12=1,IF(OR(J12=1,I12=1),"-","")&K$2,"")&IF(L12=1,IF(OR(K12=1,J12=1,I12=1),"-","")&L$2,"")&IF(M12=1,IF(OR(L12=1,K12=1,J12=1,I12=1),"-","")&M$2,"")&IF(N12=1,IF(OR(M12=1,L12=1,K12=1,J12=1,I12=1),"-","")&N$2,"")&IF(O12=1,IF(OR(N12=1,M12=1,L12=1,K12=1,J12=1,I12=1),"-","")&O$2,"")&IF(P12=1,IF(I12=1," - ",IF(J12=1," - ",IF(K12=1," - ",IF(L12=1," - ",IF(M12=1," - ",IF(N12=1," - ",IF(O12=1," - ","")))))))&P$2,"") | S12: =SUM('b2'!$I12:$P12) | T12: =IF(OR('b2'!$J12=1,'b2'!$K12=1,'b2'!$L12=1,'b2'!$M12=1,'b2'!$N12=1,'b2'!$O12=1,'b2'!$P12=1),"SI","NO") | U12: =IF(OR('b2'!$K12=1,'b2'!$L12=1,'b2'!$M12=1,'b2'!$N12=1,'b2'!$O12=1,'b2'!$P12=1),"SI","NO") | V12: 427 | W12: 0 | X12: 0 | Y12: 0 | Z12: 0 | AA12: 0 | AB12: 0 | AC12: 0 | AD12: 0 | AE12: 0 | AF12: 0 | AG12: 0 | AH12: 0 | AI12: 0 | AJ12: 0 | AK12: 0 | AL12: 0 | AM12: 0 | AN12: 0 | AO12: 0 | AP12: 0 | AQ12: 0 | AR12: =IF('b2'!$AQ12>0,'b2'!$AQ12,IF('b2'!$AN12>0,'b2'!$AN12,IF('b2'!$AK12>0,'b2'!$AK12,IF('b2'!$AH12>0,'b2'!$AH12,IF('b2'!$AE12>0,'b2'!$AE12,IF('b2'!$AB12>0,'b2'!$AB12,IF('b2'!$Y12>0,'b2'!$Y12,IF('b2'!$V12>0,'b2'!$V12," ---")))))))) | AS12: 0 | AT12: 0 | AU12: 0 | AV12: 0 | AW12: 0 | AX12: 0 | AY12: 0 | AZ12: 0 | BA12: 0 | BB12: 0 | BC12: 0 | BD12: 0 | BE12: 0 | BF12: 0 | BG12: 0 | BH12: 0 | BI12: #REF! | BJ12: #REF! | BK12: 0 | BL12: 0 | BM12: 0 | BN12: #REF! | BO12: #REF! | BP12: 0 | BQ12: 0 | BR12: 0 | BS12: #REF! | BT12: ='[2]DATA CONSOLIDADA 2018-2025 '!$BR14-'b2'!$BO12 | BU12: 0 | BV12: 0 | BW12: 0 | BX12: #REF! | BY12: #REF! | BZ12: 0 | CA12: 0 | CB12: 0 | CC12: #REF! | CD12: ='[2]DATA CONSOLIDADA 2018-2025 '!$CB14-'b2'!$BW12 | CE12: 0 | CF12: 0 | CG12: 0 | CH12: #REF! | CI12: ='[2]DATA CONSOLIDADA 2018-2025 '!$CG14-'b2'!$CB12 | CJ12: #REF! | CK12: 0 | CL12: 0 | CM12: 0 | CN12: #REF! | CO12: ='[2]DATA CONSOLIDADA 2018-2025 '!$CM14-'b2'!$CG12 | CP12: 0 | CQ12: 0 | CR12: 0 | CS12: 0 | CT12: 0 | CU12: 0 | CV12: 0 | CW12: 0 | CX12: 0 | CY12: 0 | CZ12: 0 | DA12: 0 | DB12: 0 | DC12: 0 | DD12: 0 | DE12: 0 | DF12: 0 | DG12: 0 | DH12: 0 | DI12: 20600682386 | DJ12: ASOCIACION DE PRODUCTORES AGROPECUARIOS VALLE VERDE DE RODRIGUEZ DE MENDOZA | DK12: 01 Asociación
A13: ASOCIACION DE PRODUCTORES AGROPECUARIOS LUIS SOLIBARRIA | B13: CACAO | C13: CACAO | D13: AMAZONAS | E13: 010701 | F13: AMAZONAS | G13: UTCUBAMBA | H13: BAGUA GRANDE | L13: 1 | M13: 1 | Q13: PAC | R13: =IF(I13=1,I$2,"")&IF(J13=1,IF(I13=1,"-","")&J$2,"")&IF(K13=1,IF(OR(J13=1,I13=1),"-","")&K$2,"")&IF(L13=1,IF(OR(K13=1,J13=1,I13=1),"-","")&L$2,"")&IF(M13=1,IF(OR(L13=1,K13=1,J13=1,I13=1),"-","")&M$2,"")&IF(N13=1,IF(OR(M13=1,L13=1,K13=1,J13=1,I13=1),"-","")&N$2,"")&IF(O13=1,IF(OR(N13=1,M13=1,L13=1,K13=1,J13=1,I13=1),"-","")&O$2,"")&IF(P13=1,IF(I13=1," - ",IF(J13=1," - ",IF(K13=1," - ",IF(L13=1," - ",IF(M13=1," - ",IF(N13=1," - ",IF(O13=1," - ","")))))))&P$2,"") | S13: =SUM('b2'!$I13:$P13) | T13: =IF(OR('b2'!$J13=1,'b2'!$K13=1,'b2'!$L13=1,'b2'!$M13=1,'b2'!$N13=1,'b2'!$O13=1,'b2'!$P13=1),"SI","NO") | U13: =IF(OR('b2'!$K13=1,'b2'!$L13=1,'b2'!$M13=1,'b2'!$N13=1,'b2'!$O13=1,'b2'!$P13=1),"SI","NO") | V13: 0 | W13: 0 | X13: 0 | Y13: 0 | Z13: 0 | AA13: 0 | AB13: 0 | AC13: 121 | AD13: 25 | AE13: 146 | AF13: 121 | AG13: 25 | AH13: 146 | AI13: 0 | AJ13: 0 | AK13: 0 | AL13: 0 | AM13: 0 | AN13: 0 | AO13: 0 | AP13: 0 | AQ13: 0 | AR13: =IF('b2'!$AQ13>0,'b2'!$AQ13,IF('b2'!$AN13>0,'b2'!$AN13,IF('b2'!$AK13>0,'b2'!$AK13,IF('b2'!$AH13>0,'b2'!$AH13,IF('b2'!$AE13>0,'b2'!$AE13,IF('b2'!$AB13>0,'b2'!$AB13,IF('b2'!$Y13>0,'b2'!$Y13,IF('b2'!$V13>0,'b2'!$V13," ---")))))))) | AS13: 0 | AT13: 0 | AU13: 16 | AV13: 2 | AW13: 23 | AX13: 6 | AY13: 0 | AZ13: 0 | BA13: 0 | BB13: 0 | BC13: 0 | BD13: 0 | BE13: 0 | BF13: 0 | BG13: 0 | BH13: 0 | BI13: #REF! | BJ13: #REF! | BK13: 0 | BL13: 0 | BM13: 0 | BN13: #REF! | BO13: #REF! | BP13: 0 | BQ13: 0 | BR13: 0 | BS13: #REF! | BT13: ='[2]DATA CONSOLIDADA 2018-2025 '!$BR15-'b2'!$BO13 | BU13: 0 | BV13: 0 | BW13: 0 | BX13: #REF! | BY13: #REF! | BZ13: 0 | CA13: 0 | CB13: 0 | CC13: #REF! | CD13: ='[2]DATA CONSOLIDADA 2018-2025 '!$CB15-'b2'!$BW13 | CE13: 0 | CF13: 0 | CG13: 0 | CH13: #REF! | CI13: ='[2]DATA CONSOLIDADA 2018-2025 '!$CG15-'b2'!$CB13 | CJ13: #REF! | CK13: 0 | CL13: 0 | CM13: 0 | CN13: #REF! | CO13: ='[2]DATA CONSOLIDADA 2018-2025 '!$CM15-'b2'!$CG13 | CP13: 0 | CQ13: 0 | CR13: 0 | CS13: 0 | CT13: 0 | CU13: 0 | CV13: 0 | CW13: 0 | CX13: 0 | CY13: 0 | CZ13: 0 | DA13: 0 | DB13: 0 | DC13: 0 | DD13: 0 | DE13: 0 | DF13: 0 | DG13: 0 | DH13: 0 | DI13: 20479856258 | DJ13: ASOCIACION DE PRODUCTORES AGROPECUARIOS LUIS SOLIBARRIA | DK13: 01 Asociación
A14: COOPERATIVA AGRARIA CAFETALERA PRODUCTORA COMERCIAL EXPORTADORA CAFE ANDES AMAZONICOS LTDA | B14: CAFÉ | C14: CAFÉ | D14: AMAZONAS | E14: 010706 | F14: AMAZONAS | G14: UTCUBAMBA | H14: LONYA GRANDE | L14: 1 | M14: 1 | Q14: PAC | R14: =IF(I14=1,I$2,"")&IF(J14=1,IF(I14=1,"-","")&J$2,"")&IF(K14=1,IF(OR(J14=1,I14=1),"-","")&K$2,"")&IF(L14=1,IF(OR(K14=1,J14=1,I14=1),"-","")&L$2,"")&IF(M14=1,IF(OR(L14=1,K14=1,J14=1,I14=1),"-","")&M$2,"")&IF(N14=1,IF(OR(M14=1,L14=1,K14=1,J14=1,I14=1),"-","")&N$2,"")&IF(O14=1,IF(OR(N14=1,M14=1,L14=1,K14=1,J14=1,I14=1),"-","")&O$2,"")&IF(P14=1,IF(I14=1," - ",IF(J14=1," - ",IF(K14=1," - ",IF(L14=1," - ",IF(M14=1," - ",IF(N14=1," - ",IF(O14=1," - ","")))))))&P$2,"") | S14: =SUM('b2'!$I14:$P14) | T14: =IF(OR('b2'!$J14=1,'b2'!$K14=1,'b2'!$L14=1,'b2'!$M14=1,'b2'!$N14=1,'b2'!$O14=1,'b2'!$P14=1),"SI","NO") | U14: =IF(OR('b2'!$K14=1,'b2'!$L14=1,'b2'!$M14=1,'b2'!$N14=1,'b2'!$O14=1,'b2'!$P14=1),"SI","NO") | V14: 0 | W14: 0 | X14: 0 | Y14: 0 | Z14: 0 | AA14: 0 | AB14: 0 | AC14: 179 | AD14: 45 | AE14: 224 | AF14: 179 | AG14: 45 | AH14: 224 | AI14: 0 | AJ14: 0 | AK14: 0 | AL14: 0 | AM14: 0 | AN14: 0 | AO14: 0 | AP14: 0 | AQ14: 0 | AR14: =IF('b2'!$AQ14>0,'b2'!$AQ14,IF('b2'!$AN14>0,'b2'!$AN14,IF('b2'!$AK14>0,'b2'!$AK14,IF('b2'!$AH14>0,'b2'!$AH14,IF('b2'!$AE14>0,'b2'!$AE14,IF('b2'!$AB14>0,'b2'!$AB14,IF('b2'!$Y14>0,'b2'!$Y14,IF('b2'!$V14>0,'b2'!$V14," ---")))))))) | AS14: 0 | AT14: 0 | AU14: 12 | AV14: 8 | AW14: 54 | AX14: 8 | AY14: 0 | AZ14: 0 | BA14: 0 | BB14: 0 | BC14: 0 | BD14: 0 | BE14: 0 | BF14: 0 | BG14: 0 | BH14: 0 | BI14: #REF! | BJ14: #REF! | BK14: 0 | BL14: 0 | BM14: 0 | BN14: #REF! | BO14: #REF! | BP14: 250823.36 | BQ14: 0 | BR14: 250823.36 | BS14: #REF! | BT14: ='[2]DATA CONSOLIDADA 2018-2025 '!$BR16-'b2'!$BO14 | BU14: 0 | BV14: 0 | BW14: 0 | BX14: #REF! | BY14: #REF! | BZ14: 0 | CA14: 0 | CB14: 0 | CC14: #REF! | CD14: ='[2]DATA CONSOLIDADA 2018-2025 '!$CB16-'b2'!$BW14 | CE14: 0 | CF14: 0 | CG14: 0 | CH14: #REF! | CI14: ='[2]DATA CONSOLIDADA 2018-2025 '!$CG16-'b2'!$CB14 | CJ14: #REF! | CK14: 0 | CL14: 0 | CM14: 0 | CN14: #REF! | CO14: ='[2]DATA CONSOLIDADA 2018-2025 '!$CM16-'b2'!$CG14 | CP14: 0 | CQ14: 0 | CR14: 0 | CS14: 0 | CT14: 0 | CU14: 0 | CV14: 0 | CW14: 0 | CX14: 0 | CY14: 0 | CZ14: 0 | DA14: 0 | DB14: 0 | DC14: 0 | DD14: 0 | DE14: 0 | DF14: 0 | DG14: 0 | DH14: 0 | DI14: 20600001109 | DJ14: COOPERATIVA AGRARIA CAFETALERA PRODUCTORA COMERCIAL EXPORTADORA CAFE ANDES AMAZONICOS LTDA | DK14: 02 Cooperativa
A15: COOPERATIVA DE SERVICIOS MULTIPLES JUAN MARCO EL PALTO | B15: CAFÉ | C15: CAFÉ | D15: AMAZONAS | E15: 010706 | F15: AMAZONAS | G15: UTCUBAMBA | H15: LONYA GRANDE | L15: 1 | M15: 1 | N15: 1 | Q15: PAC | R15: =IF(I15=1,I$2,"")&IF(J15=1,IF(I15=1,"-","")&J$2,"")&IF(K15=1,IF(OR(J15=1,I15=1),"-","")&K$2,"")&IF(L15=1,IF(OR(K15=1,J15=1,I15=1),"-","")&L$2,"")&IF(M15=1,IF(OR(L15=1,K15=1,J15=1,I15=1),"-","")&M$2,"")&IF(N15=1,IF(OR(M15=1,L15=1,K15=1,J15=1,I15=1),"-","")&N$2,"")&IF(O15=1,IF(OR(N15=1,M15=1,L15=1,K15=1,J15=1,I15=1),"-","")&O$2,"")&IF(P15=1,IF(I15=1," - ",IF(J15=1," - ",IF(K15=1," - ",IF(L15=1," - ",IF(M15=1," - ",IF(N15=1," - ",IF(O15=1," - ","")))))))&P$2,"") | S15: =SUM('b2'!$I15:$P15) | T15: =IF(OR('b2'!$J15=1,'b2'!$K15=1,'b2'!$L15=1,'b2'!$M15=1,'b2'!$N15=1,'b2'!$O15=1,'b2'!$P15=1),"SI","NO") | U15: =IF(OR('b2'!$K15=1,'b2'!$L15=1,'b2'!$M15=1,'b2'!$N15=1,'b2'!$O15=1,'b2'!$P15=1),"SI","NO") | V15: 0 | W15: 0 | X15: 0 | Y15: 0 | Z15: 0 | AA15: 0 | AB15: 0 | AC15: 224 | AD15: 68 | AE15: 292 | AF15: 224 | AG15: 68 | AH15: 292 | AI15: 224 | AJ15: 68 | AK15: 292 | AL15: 0 | AM15: 0 | AN15: 0 | AO15: 0 | AP15: 0 | AQ15: 0 | AR15: =IF('b2'!$AQ15>0,'b2'!$AQ15,IF('b2'!$AN15>0,'b2'!$AN15,IF('b2'!$AK15>0,'b2'!$AK15,IF('b2'!$AH15>0,'b2'!$AH15,IF('b2'!$AE15>0,'b2'!$AE15,IF('b2'!$AB15>0,'b2'!$AB15,IF('b2'!$Y15>0,'b2'!$Y15,IF('b2'!$V15>0,'b2'!$V15," ---")))))))) | AS15: 0 | AT15: 0 | AU15: 10 | AV15: 8 | AW15: 60 | AX15: 8 | AY15: 44 | AZ15: 6 | BA15: 0 | BB15: 0 | BC15: 0 | BD15: 0 | BE15: 0 | BF15: 0 | BG15: 0 | BH15: 0 | BI15: #REF! | BJ15: #REF! | BK15: 0 | BL15: 0 | BM15: 0 | BN15: #REF! | BO15: #REF! | BP15: 0 | BQ15: 1177220.5 | BR15: 1177220.5 | BS15: #REF! | BT15: ='[2]DATA CONSOLIDADA 2018-2025 '!$BR17-'b2'!$BO15 | BU15: 117797.43 | BV15: 3107691.5 | BW15: 3225488.9 | BX15: #REF! | BY15: #REF! | BZ15: 45403.05 | CA15: 3044784.1 | CB15: 3090187.2 | CC15: #REF! | CD15: ='[2]DATA CONSOLIDADA 2018-2025 '!$CB17-'b2'!$BW15 | CE15: 0 | CF15: 0 | CG15: 0 | CH15: #REF! | CI15: ='[2]DATA CONSOLIDADA 2018-2025 '!$CG17-'b2'!$CB15 | CJ15: #REF! | CK15: 0 | CL15: 0 | CM15: 0 | CN15: #REF! | CO15: ='[2]DATA CONSOLIDADA 2018-2025 '!$CM17-'b2'!$CG15 | CP15: 0 | CQ15: 0 | CR15: 0 | CS15: 3090187.2 | CT15: 0 | CU15: 0 | CV15: 3090187.2 | CW15: 0 | CX15: 0 | CY15: 0 | CZ15: 0 | DA15: 0 | DB15: 0 | DC15: 0 | DD15: 0 | DE15: 0 | DF15: 0 | DG15: 0 | DH15: 0 | DI15: 20479622699 | DJ15: COOPERATIVA AGRARIA JUAN MARCO EL PALTO | DK15: 02 Cooperativa
A16: SEDIR-SERVICIO PARA EL DESARROLLO INTEGRAL RURAL | B16: PALTA | C16: PALTA | D16: ANCASH | E16: 021805 | F16: ANCASH | G16: SANTA | H16: MORO | I16: 1 | Q16: PAC | R16: =IF(I16=1,I$2,"")&IF(J16=1,IF(I16=1,"-","")&J$2,"")&IF(K16=1,IF(OR(J16=1,I16=1),"-","")&K$2,"")&IF(L16=1,IF(OR(K16=1,J16=1,I16=1),"-","")&L$2,"")&IF(M16=1,IF(OR(L16=1,K16=1,J16=1,I16=1),"-","")&M$2,"")&IF(N16=1,IF(OR(M16=1,L16=1,K16=1,J16=1,I16=1),"-","")&N$2,"")&IF(O16=1,IF(OR(N16=1,M16=1,L16=1,K16=1,J16=1,I16=1),"-","")&O$2,"")&IF(P16=1,IF(I16=1," - ",IF(J16=1," - ",IF(K16=1," - ",IF(L16=1," - ",IF(M16=1," - ",IF(N16=1," - ",IF(O16=1," - ","")))))))&P$2,"") | S16: =SUM('b2'!$I16:$P16) | T16: =IF(OR('b2'!$J16=1,'b2'!$K16=1,'b2'!$L16=1,'b2'!$M16=1,'b2'!$N16=1,'b2'!$O16=1,'b2'!$P16=1),"SI","NO") | U16: =IF(OR('b2'!$K16=1,'b2'!$L16=1,'b2'!$M16=1,'b2'!$N16=1,'b2'!$O16=1,'b2'!$P16=1),"SI","NO") | V16: 34 | W16: 0 | X16: 0 | Y16: 0 | Z16: 0 | AA16: 0 | AB16: 0 | AC16: 0 | AD16: 0 | AE16: 0 | AF16: 0 | AG16: 0 | AH16: 0 | AI16: 0 | AJ16: 0 | AK16: 0 | AL16: 0 | AM16: 0 | AN16: 0 | AO16: 0 | AP16: 0 | AQ16: 0 | AR16: =IF('b2'!$AQ16>0,'b2'!$AQ16,IF('b2'!$AN16>0,'b2'!$AN16,IF('b2'!$AK16>0,'b2'!$AK16,IF('b2'!$AH16>0,'b2'!$AH16,IF('b2'!$AE16>0,'b2'!$AE16,IF('b2'!$AB16>0,'b2'!$AB16,IF('b2'!$Y16>0,'b2'!$Y16,IF('b2'!$V16>0,'b2'!$V16," ---")))))))) | AS16: 0 | AT16: 0 | AU16: 0 | AV16: 0 | AW16: 0 | AX16: 0 | AY16: 0 | AZ16: 0 | BA16: 0 | BB16: 0 | BC16: 0 | BD16: 0 | BE16: 0 | BF16: 0 | BG16: 0 | BH16: 0 | BI16: #REF! | BJ16: #REF! | BK16: 0 | BL16: 0 | BM16: 0 | BN16: #REF! | BO16: #REF! | BP16: 0 | BQ16: 0 | BR16: 0 | BS16: #REF! | BT16: ='[2]DATA CONSOLIDADA 2018-2025 '!$BR18-'b2'!$BO16 | BU16: 0 | BV16: 0 | BW16: 0 | BX16: #REF! | BY16: #REF! | BZ16: 0 | CA16: 0 | CB16: 0 | CC16: #REF! | CD16: ='[2]DATA CONSOLIDADA 2018-2025 '!$CB18-'b2'!$BW16 | CE16: 0 | CF16: 0 | CG16: 0 | CH16: #REF! | CI16: ='[2]DATA CONSOLIDADA 2018-2025 '!$CG18-'b2'!$CB16 | CJ16: #REF! | CK16: 0 | CL16: 0 | CM16: 0 | CN16: #REF! | CO16: ='[2]DATA CONSOLIDADA 2018-2025 '!$CM18-'b2'!$CG16 | CP16: 0 | CQ16: 0 | CR16: 0 | CS16: 0 | CT16: 0 | CU16: 0 | CV16: 0 | CW16: 0 | CX16: 0 | CY16: 0 | CZ16: 0 | DA16: 0 | DB16: 0 | DC16: 0 | DD16: 0 | DE16: 0 | DF16: 0 | DG16: 0 | DH16: 0 | DI16: 20541732706 | DJ16: SERVICIO PARA EL DESARROLLO INTEGRAL RURAL | DK16: 01 Asociación
A17: ASOCIACION DE PRODUCTORES DE MANZANO ORGANICO DE PARIACOTO | B17: MANZANA | C17: MANZANA | D17: ANCASH | E17: 020110 | F17: ANCASH | G17: HUARAZ | H17: PARIACOTO | I17: 1 | Q17: PAC | R17: =IF(I17=1,I$2,"")&IF(J17=1,IF(I17=1,"-","")&J$2,"")&IF(K17=1,IF(OR(J17=1,I17=1),"-","")&K$2,"")&IF(L17=1,IF(OR(K17=1,J17=1,I17=1),"-","")&L$2,"")&IF(M17=1,IF(OR(L17=1,K17=1,J17=1,I17=1),"-","")&M$2,"")&IF(N17=1,IF(OR(M17=1,L17=1,K17=1,J17=1,I17=1),"-","")&N$2,"")&IF(O17=1,IF(OR(N17=1,M17=1,L17=1,K17=1,J17=1,I17=1),"-","")&O$2,"")&IF(P17=1,IF(I17=1," - ",IF(J17=1," - ",IF(K17=1," - ",IF(L17=1," - ",IF(M17=1," - ",IF(N17=1," - ",IF(O17=1," - ","")))))))&P$2,"") | S17: =SUM('b2'!$I17:$P17) | T17: =IF(OR('b2'!$J17=1,'b2'!$K17=1,'b2'!$L17=1,'b2'!$M17=1,'b2'!$N17=1,'b2'!$O17=1,'b2'!$P17=1),"SI","NO") | U17: =IF(OR('b2'!$K17=1,'b2'!$L17=1,'b2'!$M17=1,'b2'!$N17=1,'b2'!$O17=1,'b2'!$P17=1),"SI","NO") | V17: 15 | W17: 0 | X17: 0 | Y17: 0 | Z17: 0 | AA17: 0 | AB17: 0 | AC17: 0 | AD17: 0 | AE17: 0 | AF17: 0 | AG17: 0 | AH17: 0 | AI17: 0 | AJ17: 0 | AK17: 0 | AL17: 0 | AM17: 0 | AN17: 0 | AO17: 0 | AP17: 0 | AQ17: 0 | AR17: =IF('b2'!$AQ17>0,'b2'!$AQ17,IF('b2'!$AN17>0,'b2'!$AN17,IF('b2'!$AK17>0,'b2'!$AK17,IF('b2'!$AH17>0,'b2'!$AH17,IF('b2'!$AE17>0,'b2'!$AE17,IF('b2'!$AB17>0,'b2'!$AB17,IF('b2'!$Y17>0,'b2'!$Y17,IF('b2'!$V17>0,'b2'!$V17," ---")))))))) | AS17: 0 | AT17: 0 | AU17: 0 | AV17: 0 | AW17: 0 | AX17: 0 | AY17: 0 | AZ17: 0 | BA17: 0 | BB17: 0 | BC17: 0 | BD17: 0 | BE17: 0 | BF17: 0 | BG17: 0 | BH17: 0 | BI17: #REF! | BJ17: #REF! | BK17: 0 | BL17: 0 | BM17: 0 | BN17: #REF! | BO17: #REF! | BP17: 0 | BQ17: 0 | BR17: 0 | BS17: #REF! | BT17: ='[2]DATA CONSOLIDADA 2018-2025 '!$BR19-'b2'!$BO17 | BU17: 0 | BV17: 0 | BW17: 0 | BX17: #REF! | BY17: #REF! | BZ17: 0 | CA17: 0 | CB17: 0 | CC17: #REF! | CD17: ='[2]DATA CONSOLIDADA 2018-2025 '!$CB19-'b2'!$BW17 | CE17: 0 | CF17: 0 | CG17: 0 | CH17: #REF! | CI17: ='[2]DATA CONSOLIDADA 2018-2025 '!$CG19-'b2'!$CB17 | CJ17: #REF! | CK17: 0 | CL17: 0 | CM17: 0 | CN17: #REF! | CO17: ='[2]DATA CONSOLIDADA 2018-2025 '!$CM19-'b2'!$CG17 | CP17: 0 | CQ17: 0 | CR17: 0 | CS17: 0 | CT17: 0 | CU17: 0 | CV17: 0 | CW17: 0 | CX17: 0 | CY17: 0 | CZ17: 0 | DA17: 0 | DB17: 0 | DC17: 0 | DD17: 0 | DE17: 0 | DF17: 0 | DG17: 0 | DH17: 0 | DI17: 20600862074 | DJ17: ASOCIACIÓN DE PRODUCTORES DE MANZANO ORGANICO DEL DISTRITO DE PARIACOTO | DK17: 01 Asociación
A18: ASOCIACION DE PRODUCTORES ECOLOGICOS AGRARIOS DEL DISTRITO DE QUICHES | B18: ROMERO | C18: ROMERO | D18: ANCASH | E18: 021901 | F18: ANCASH | G18: SIHUAS | H18: SIHUAS | I18: 1 | Q18: PAC | R18: =IF(I18=1,I$2,"")&IF(J18=1,IF(I18=1,"-","")&J$2,"")&IF(K18=1,IF(OR(J18=1,I18=1),"-","")&K$2,"")&IF(L18=1,IF(OR(K18=1,J18=1,I18=1),"-","")&L$2,"")&IF(M18=1,IF(OR(L18=1,K18=1,J18=1,I18=1),"-","")&M$2,"")&IF(N18=1,IF(OR(M18=1,L18=1,K18=1,J18=1,I18=1),"-","")&N$2,"")&IF(O18=1,IF(OR(N18=1,M18=1,L18=1,K18=1,J18=1,I18=1),"-","")&O$2,"")&IF(P18=1,IF(I18=1," - ",IF(J18=1," - ",IF(K18=1," - ",IF(L18=1," - ",IF(M18=1," - ",IF(N18=1," - ",IF(O18=1," - ","")))))))&P$2,"") | S18: =SUM('b2'!$I18:$P18) | T18: =IF(OR('b2'!$J18=1,'b2'!$K18=1,'b2'!$L18=1,'b2'!$M18=1,'b2'!$N18=1,'b2'!$O18=1,'b2'!$P18=1),"SI","NO") | U18: =IF(OR('b2'!$K18=1,'b2'!$L18=1,'b2'!$M18=1,'b2'!$N18=1,'b2'!$O18=1,'b2'!$P18=1),"SI","NO") | V18: 82 | W18: 0 | X18: 0 | Y18: 0 | Z18: 0 | AA18: 0 | AB18: 0 | AC18: 0 | AD18: 0 | AE18: 0 | AF18: 0 | AG18: 0 | AH18: 0 | AI18: 0 | AJ18: 0 | AK18: 0 | AL18: 0 | AM18: 0 | AN18: 0 | AO18: 0 | AP18: 0 | AQ18: 0 | AR18: =IF('b2'!$AQ18>0,'b2'!$AQ18,IF('b2'!$AN18>0,'b2'!$AN18,IF('b2'!$AK18>0,'b2'!$AK18,IF('b2'!$AH18>0,'b2'!$AH18,IF('b2'!$AE18>0,'b2'!$AE18,IF('b2'!$AB18>0,'b2'!$AB18,IF('b2'!$Y18>0,'b2'!$Y18,IF('b2'!$V18>0,'b2'!$V18," ---")))))))) | AS18: 0 | AT18: 0 | AU18: 0 | AV18: 0 | AW18: 0 | AX18: 0 | AY18: 0 | AZ18: 0 | BA18: 0 | BB18: 0 | BC18: 0 | BD18: 0 | BE18: 0 | BF18: 0 | BG18: 0 | BH18: 0 | BI18: #REF! | BJ18: #REF! | BK18: 0 | BL18: 0 | BM18: 0 | BN18: #REF! | BO18: #REF! | BP18: 0 | BQ18: 0 | BR18: 0 | BS18: #REF! | BT18: ='[2]DATA CONSOLIDADA 2018-2025 '!$BR20-'b2'!$BO18 | BU18: 0 | BV18: 0 | BW18: 0 | BX18: #REF! | BY18: #REF! | BZ18: 0 | CA18: 0 | CB18: 0 | CC18: #REF! | CD18: ='[2]DATA CONSOLIDADA 2018-2025 '!$CB20-'b2'!$BW18 | CE18: 0 | CF18: 0 | CG18: 0 | CH18: #REF! | CI18: ='[2]DATA CONSOLIDADA 2018-2025 '!$CG20-'b2'!$CB18 | CJ18: #REF! | CK18: 0 | CL18: 0 | CM18: 0 | CN18: #REF! | CO18: ='[2]DATA CONSOLIDADA 2018-2025 '!$CM20-'b2'!$CG18 | CP18: 0 | CQ18: 0 | CR18: 0 | CS18: 0 | CT18: 0 | CU18: 0 | CV18: 0 | CW18: 0 | CX18: 0 | CY18: 0 | CZ18: 0 | DA18: 0 | DB18: 0 | DC18: 0 | DD18: 0 | DE18: 0 | DF18: 0 | DG18: 0 | DH18: 0 | DI18: 20602544495 | DJ18: ASOCIACION DE PRODUCTORES ECOLOGICOS AGRARIOS DEL DISTRITO DE QUICHES PROVINCIA DE SIHUAS-ANCASH | DK18: 01 Asociación
A19: ASOCIACION DE PRODUCTORES Y COMERCIANTES DE TARA DE PUCHKA | B19: TARA | C19: TARA | D19: ANCASH | E19: 021016 | F19: ANCASH | G19: HUARI | H19: UCO | I19: 1 | Q19: PAC | R19: =IF(I19=1,I$2,"")&IF(J19=1,IF(I19=1,"-","")&J$2,"")&IF(K19=1,IF(OR(J19=1,I19=1),"-","")&K$2,"")&IF(L19=1,IF(OR(K19=1,J19=1,I19=1),"-","")&L$2,"")&IF(M19=1,IF(OR(L19=1,K19=1,J19=1,I19=1),"-","")&M$2,"")&IF(N19=1,IF(OR(M19=1,L19=1,K19=1,J19=1,I19=1),"-","")&N$2,"")&IF(O19=1,IF(OR(N19=1,M19=1,L19=1,K19=1,J19=1,I19=1),"-","")&O$2,"")&IF(P19=1,IF(I19=1," - ",IF(J19=1," - ",IF(K19=1," - ",IF(L19=1," - ",IF(M19=1," - ",IF(N19=1," - ",IF(O19=1," - ","")))))))&P$2,"") | S19: =SUM('b2'!$I19:$P19) | T19: =IF(OR('b2'!$J19=1,'b2'!$K19=1,'b2'!$L19=1,'b2'!$M19=1,'b2'!$N19=1,'b2'!$O19=1,'b2'!$P19=1),"SI","NO") | U19: =IF(OR('b2'!$K19=1,'b2'!$L19=1,'b2'!$M19=1,'b2'!$N19=1,'b2'!$O19=1,'b2'!$P19=1),"SI","NO") | V19: 39 | W19: 0 | X19: 0 | Y19: 0 | Z19: 0 | AA19: 0 | AB19: 0 | AC19: 0 | AD19: 0 | AE19: 0 | AF19: 0 | AG19: 0 | AH19: 0 | AI19: 0 | AJ19: 0 | AK19: 0 | AL19: 0 | AM19: 0 | AN19: 0 | AO19: 0 | AP19: 0 | AQ19: 0 | AR19: =IF('b2'!$AQ19>0,'b2'!$AQ19,IF('b2'!$AN19>0,'b2'!$AN19,IF('b2'!$AK19>0,'b2'!$AK19,IF('b2'!$AH19>0,'b2'!$AH19,IF('b2'!$AE19>0,'b2'!$AE19,IF('b2'!$AB19>0,'b2'!$AB19,IF('b2'!$Y19>0,'b2'!$Y19,IF('b2'!$V19>0,'b2'!$V19," ---")))))))) | AS19: 0 | AT19: 0 | AU19: 0 | AV19: 0 | AW19: 0 | AX19: 0 | AY19: 0 | AZ19: 0 | BA19: 0 | BB19: 0 | BC19: 0 | BD19: 0 | BE19: 0 | BF19: 0 | BG19: 0 | BH19: 0 | BI19: #REF! | BJ19: #REF! | BK19: 0 | BL19: 0 | BM19: 0 | BN19: #REF! | BO19: #REF! | BP19: 0 | BQ19: 0 | BR19: 0 | BS19: #REF! | BT19: ='[2]DATA CONSOLIDADA 2018-2025 '!$BR21-'b2'!$BO19 | BU19: 0 | BV19: 0 | BW19: 0 | BX19: #REF! | BY19: #REF! | BZ19: 0 | CA19: 0 | CB19: 0 | CC19: #REF! | CD19: ='[2]DATA CONSOLIDADA 2018-2025 '!$CB21-'b2'!$BW19 | CE19: 0 | CF19: 0 | CG19: 0 | CH19: #REF! | CI19: ='[2]DATA CONSOLIDADA 2018-2025 '!$CG21-'b2'!$CB19 | CJ19: #REF! | CK19: 0 | CL19: 0 | CM19: 0 | CN19: #REF! | CO19: ='[2]DATA CONSOLIDADA 2018-2025 '!$CM21-'b2'!$CG19 | CP19: 0 | CQ19: 0 | CR19: 0 | CS19: 0 | CT19: 0 | CU19: 0 | CV19: 0 | CW19: 0 | CX19: 0 | CY19: 0 | CZ19: 0 | DA19: 0 | DB19: 0 | DC19: 0 | DD19: 0 | DE19: 0 | DF19: 0 | DG19: 0 | DH19: 0 | DI19: 20534142146 | DJ19: ASOCIACION DE PRODUCTORES Y COMERCIANTES DE TARA DE PUCHKA | DK19: 01 Asociación
A20: GRUPO ASOCIADO PRODUCTORES DE CARAZ | B20: FLORES | C20: FLORES | D20: ANCASH | E20: 021201 | F20: ANCASH | G20: HUAYLAS | H20: CARAZ | I20: 1 | Q20: PAC | R20: =IF(I20=1,I$2,"")&IF(J20=1,IF(I20=1,"-","")&J$2,"")&IF(K20=1,IF(OR(J20=1,I20=1),"-","")&K$2,"")&IF(L20=1,IF(OR(K20=1,J20=1,I20=1),"-","")&L$2,"")&IF(M20=1,IF(OR(L20=1,K20=1,J20=1,I20=1),"-","")&M$2,"")&IF(N20=1,IF(OR(M20=1,L20=1,K20=1,J20=1,I20=1),"-","")&N$2,"")&IF(O20=1,IF(OR(N20=1,M20=1,L20=1,K20=1,J20=1,I20=1),"-","")&O$2,"")&IF(P20=1,IF(I20=1," - ",IF(J20=1," - ",IF(K20=1," - ",IF(L20=1," - ",IF(M20=1," - ",IF(N20=1," - ",IF(O20=1," - ","")))))))&P$2,"") | S20: =SUM('b2'!$I20:$P20) | T20: =IF(OR('b2'!$J20=1,'b2'!$K20=1,'b2'!$L20=1,'b2'!$M20=1,'b2'!$N20=1,'b2'!$O20=1,'b2'!$P20=1),"SI","NO") | U20: =IF(OR('b2'!$K20=1,'b2'!$L20=1,'b2'!$M20=1,'b2'!$N20=1,'b2'!$O20=1,'b2'!$P20=1),"SI","NO") | V20: 4 | W20: 0 | X20: 0 | Y20: 0 | Z20: 0 | AA20: 0 | AB20: 0 | AC20: 0 | AD20: 0 | AE20: 0 | AF20: 0 | AG20: 0 | AH20: 0 | AI20: 0 | AJ20: 0 | AK20: 0 | AL20: 0 | AM20: 0 | AN20: 0 | AO20: 0 | AP20: 0 | AQ20: 0 | AR20: =IF('b2'!$AQ20>0,'b2'!$AQ20,IF('b2'!$AN20>0,'b2'!$AN20,IF('b2'!$AK20>0,'b2'!$AK20,IF('b2'!$AH20>0,'b2'!$AH20,IF('b2'!$AE20>0,'b2'!$AE20,IF('b2'!$AB20>0,'b2'!$AB20,IF('b2'!$Y20>0,'b2'!$Y20,IF('b2'!$V20>0,'b2'!$V20," ---")))))))) | AS20: 0 | AT20: 0 | AU20: 0 | AV20: 0 | AW20: 0 | AX20: 0 | AY20: 0 | AZ20: 0 | BA20: 0 | BB20: 0 | BC20: 0 | BD20: 0 | BE20: 0 | BF20: 0 | BG20: 0 | BH20: 0 | BI20: #REF! | BJ20: #REF! | BK20: 0 | BL20: 0 | BM20: 0 | BN20: #REF! | BO20: #REF! | BP20: 0 | BQ20: 0 | BR20: 0 | BS20: #REF! | BT20: ='[2]DATA CONSOLIDADA 2018-2025 '!$BR22-'b2'!$BO20 | BU20: 0 | BV20: 0 | BW20: 0 | BX20: #REF! | BY20: #REF! | BZ20: 0 | CA20: 0 | CB20: 0 | CC20: #REF! | CD20: ='[2]DATA CONSOLIDADA 2018-2025 '!$CB22-'b2'!$BW20 | CE20: 0 | CF20: 0 | CG20: 0 | CH20: #REF! | CI20: ='[2]DATA CONSOLIDADA 2018-2025 '!$CG22-'b2'!$CB20 | CJ20: #REF! | CK20: 0 | CL20: 0 | CM20: 0 | CN20: #REF! | CO20: ='[2]DATA CONSOLIDADA 2018-2025 '!$CM22-'b2'!$CG20 | CP20: 0 | CQ20: 0 | CR20: 0 | CS20: 0 | CT20: 0 | CU20: 0 | CV20: 0 | CW20: 0 | CX20: 0 | CY20: 0 | CZ20: 0 | DA20: 0 | DB20: 0 | DC20: 0 | DD20: 0 | DE20: 0 | DF20: 0 | DG20: 0 | DH20: 0 | DI20: SIN RUC | DJ20: ND | DK20: 01 Asociación
A21: COOPERATIVA DE PRODUCTORES AGROECOLOGICOS LA PERLA DE LOS ANDES-CALLEJON DE HUAYLAS ANCASH | B21: TARWI | C21: TARWI | D21: ANCASH | E21: 021201 | F21: ANCASH | G21: HUAYLAS | H21: CARAZ | I21: 1 | J21: 1 | K21: 1 | L21: 1 | M21: 1 | N21: 1 | Q21: PAC | R21: =IF(I21=1,I$2,"")&IF(J21=1,IF(I21=1,"-","")&J$2,"")&IF(K21=1,IF(OR(J21=1,I21=1),"-","")&K$2,"")&IF(L21=1,IF(OR(K21=1,J21=1,I21=1),"-","")&L$2,"")&IF(M21=1,IF(OR(L21=1,K21=1,J21=1,I21=1),"-","")&M$2,"")&IF(N21=1,IF(OR(M21=1,L21=1,K21=1,J21=1,I21=1),"-","")&N$2,"")&IF(O21=1,IF(OR(N21=1,M21=1,L21=1,K21=1,J21=1,I21=1),"-","")&O$2,"")&IF(P21=1,IF(I21=1," - ",IF(J21=1," - ",IF(K21=1," - ",IF(L21=1," - ",IF(M21=1," - ",IF(N21=1," - ",IF(O21=1," - ","")))))))&P$2,"") | S21: =SUM('b2'!$I21:$P21) | T21: =IF(OR('b2'!$J21=1,'b2'!$K21=1,'b2'!$L21=1,'b2'!$M21=1,'b2'!$N21=1,'b2'!$O21=1,'b2'!$P21=1),"SI","NO") | U21: =IF(OR('b2'!$K21=1,'b2'!$L21=1,'b2'!$M21=1,'b2'!$N21=1,'b2'!$O21=1,'b2'!$P21=1),"SI","NO") | V21: 521 | W21: 79 | X21: 17 | Y21: 96 | Z21: 213 | AA21: 60 | AB21: 273 | AC21: 215 | AD21: 58 | AE21: 273 | AF21: 59 | AG21: 18 | AH21: 77 | AI21: 59 | AJ21: 18 | AK21: 77 | AL21: 0 | AM21: 0 | AN21: 0 | AO21: 0 | AP21: 0 | AQ21: 0 | AR21: =IF('b2'!$AQ21>0,'b2'!$AQ21,IF('b2'!$AN21>0,'b2'!$AN21,IF('b2'!$AK21>0,'b2'!$AK21,IF('b2'!$AH21>0,'b2'!$AH21,IF('b2'!$AE21>0,'b2'!$AE21,IF('b2'!$AB21>0,'b2'!$AB21,IF('b2'!$Y21>0,'b2'!$Y21,IF('b2'!$V21>0,'b2'!$V21," ---")))))))) | AS21: 18 | AT21: 6 | AU21: 36 | AV21: 7 | AW21: 25 | AX21: 6 | AY21: 36 | AZ21: 2 | BA21: 0 | BB21: 0 | BC21: 0 | BD21: 0 | BE21: 0 | BF21: 11802.35 | BG21: 0 | BH21: 11802.35 | BI21: #REF! | BJ21: #REF! | BK21: 109219.27 | BL21: 0 | BM21: 109219.27 | BN21: #REF! | BO21: #REF! | BP21: 131381.75 | BQ21: 0 | BR21: 131381.75 | BS21: #REF! | BT21: ='[2]DATA CONSOLIDADA 2018-2025 '!$BR23-'b2'!$BO21 | BU21: 129764.41 | BV21: 0 | BW21: 129764.41 | BX21: #REF! | BY21: #REF! | BZ21: 141145.57 | CA21: 0 | CB21: 141145.57 | CC21: #REF! | CD21: ='[2]DATA CONSOLIDADA 2018-2025 '!$CB23-'b2'!$BW21 | CE21: 0 | CF21: 0 | CG21: 0 | CH21: #REF! | CI21: ='[2]DATA CONSOLIDADA 2018-2025 '!$CG23-'b2'!$CB21 | CJ21: #REF! | CK21: 0 | CL21: 0 | CM21: 0 | CN21: #REF! | CO21: ='[2]DATA CONSOLIDADA 2018-2025 '!$CM23-'b2'!$CG21 | CP21: 0 | CQ21: 0 | CR21: 0 | CS21: 141147 | CT21: 0 | CU21: 0 | CV21: 141147 | CW21: 0 | CX21: 0 | CY21: 0 | CZ21: 0 | DA21: 0 | DB21: 0 | DC21: 0 | DD21: 0 | DE21: 0 | DF21: 0 | DG21: 0 | DH21: 0 | DI21: 20603223421 | DJ21: COOPERATIVA DE PRODUCTORES AGROECOLOGICOS LA PERLA DE LOS ANDES-CALLEJON DE HUAYLAS ANCASH | DK21: 02 Cooperativa
A22: ASOCIACIÓN DE SEMILLARISTAS DE MAIZ CHOCLO VIRGEN DE LAS MERCEDES DEL DISTRITO DE CHINGAS | B22: MAÍZ | C22: MAÍZ BLANCO GIGANTE | D22: ANCASH | E22: 020304 | F22: ANCASH | G22: ANTONIO RAYMONDI | H22: CHINGAS | I22: 1 | J22: 1 | K22: 1 | L22: 1 | M22: 1 | N22: 1 | Q22: PAC | R22: =IF(I22=1,I$2,"")&IF(J22=1,IF(I22=1,"-","")&J$2,"")&IF(K22=1,IF(OR(J22=1,I22=1),"-","")&K$2,"")&IF(L22=1,IF(OR(K22=1,J22=1,I22=1),"-","")&L$2,"")&IF(M22=1,IF(OR(L22=1,K22=1,J22=1,I22=1),"-","")&M$2,"")&IF(N22=1,IF(OR(M22=1,L22=1,K22=1,J22=1,I22=1),"-","")&N$2,"")&IF(O22=1,IF(OR(N22=1,M22=1,L22=1,K22=1,J22=1,I22=1),"-","")&O$2,"")&IF(P22=1,IF(I22=1," - ",IF(J22=1," - ",IF(K22=1," - ",IF(L22=1," - ",IF(M22=1," - ",IF(N22=1," - ",IF(O22=1," - ","")))))))&P$2,"") | S22: =SUM('b2'!$I22:$P22) | T22: =IF(OR('b2'!$J22=1,'b2'!$K22=1,'b2'!$L22=1,'b2'!$M22=1,'b2'!$N22=1,'b2'!$O22=1,'b2'!$P22=1),"SI","NO") | U22: =IF(OR('b2'!$K22=1,'b2'!$L22=1,'b2'!$M22=1,'b2'!$N22=1,'b2'!$O22=1,'b2'!$P22=1),"SI","NO") | V22: 28 | W22: 23 | X22: 3 | Y22: 26 | Z22: 23 | AA22: 3 | AB22: 26 | AC22: 20 | AD22: 3 | AE22: 23 | AF22: 20 | AG22: 3 | AH22: 23 | AI22: 20 | AJ22: 3 | AK22: 23 | AL22: 0 | AM22: 0 | AN22: 0 | AO22: 0 | AP22: 0 | AQ22: 0 | AR22: =IF('b2'!$AQ22>0,'b2'!$AQ22,IF('b2'!$AN22>0,'b2'!$AN22,IF('b2'!$AK22>0,'b2'!$AK22,IF('b2'!$AH22>0,'b2'!$AH22,IF('b2'!$AE22>0,'b2'!$AE22,IF('b2'!$AB22>0,'b2'!$AB22,IF('b2'!$Y22>0,'b2'!$Y22,IF('b2'!$V22>0,'b2'!$V22," ---")))))))) | AS22: 3 | AT22: 0 | AU22: 44 | AV22: 8 | AW22: 25 | AX22: 5 | AY22: 34 | AZ22: 4 | BA22: 0 | BB22: 0 | BC22: 0 | BD22: 0 | BE22: 0 | BF22: 0 | BG22: 0 | BH22: 0 | BI22: #REF! | BJ22: #REF! | BK22: 13830 | BL22: 0 | BM22: 13830 | BN22: #REF! | BO22: #REF! | BP22: 378700 | BQ22: 0 | BR22: 378700 | BS22: #REF! | BT22: ='[2]DATA CONSOLIDADA 2018-2025 '!$BR24-'b2'!$BO22 | BU22: 452800 | BV22: 0 | BW22: 452800 | BX22: #REF! | BY22: #REF! | BZ22: 564965 | CA22: 0 | CB22: 564965 | CC22: #REF! | CD22: ='[2]DATA CONSOLIDADA 2018-2025 '!$CB24-'b2'!$BW22 | CE22: 0 | CF22: 0 | CG22: 0 | CH22: #REF! | CI22: ='[2]DATA CONSOLIDADA 2018-2025 '!$CG24-'b2'!$CB22 | CJ22: #REF! | CK22: 0 | CL22: 0 | CM22: 0 | CN22: #REF! | CO22: ='[2]DATA CONSOLIDADA 2018-2025 '!$CM24-'b2'!$CG22 | CP22: 0 | CQ22: 564965 | CR22: 0 | CS22: 0 | CT22: 0 | CU22: 0 | CV22: 564965 | CW22: 0 | CX22: 0 | CY22: 0 | CZ22: 0 | DA22: 0 | DB22: 0 | DC22: 0 | DD22: 0 | DE22: 0 | DF22: 0 | DG22: 0 | DH22: 0 | DI22: 20601547458 | DJ22: ASOCIACION DE SEMILLARISTAS DE MAIZ CHOCLO VIRGEN DE LA MERCEDES DEL DISTRITO DE CHINGAS | DK22: 01 Asociación
A23: ASOCIACION DE PRODUCTORES DE PALTOS MORO | B23: PALTA | C23: PALTA | D23: ANCASH | E23: 021805 | F23: ANCASH | G23: SANTA | H23: MORO | J23: 1 | Q23: PAC | R23: =IF(I23=1,I$2,"")&IF(J23=1,IF(I23=1,"-","")&J$2,"")&IF(K23=1,IF(OR(J23=1,I23=1),"-","")&K$2,"")&IF(L23=1,IF(OR(K23=1,J23=1,I23=1),"-","")&L$2,"")&IF(M23=1,IF(OR(L23=1,K23=1,J23=1,I23=1),"-","")&M$2,"")&IF(N23=1,IF(OR(M23=1,L23=1,K23=1,J23=1,I23=1),"-","")&N$2,"")&IF(O23=1,IF(OR(N23=1,M23=1,L23=1,K23=1,J23=1,I23=1),"-","")&O$2,"")&IF(P23=1,IF(I23=1," - ",IF(J23=1," - ",IF(K23=1," - ",IF(L23=1," - ",IF(M23=1," - ",IF(N23=1," - ",IF(O23=1," - ","")))))))&P$2,"") | S23: =SUM('b2'!$I23:$P23) | T23: =IF(OR('b2'!$J23=1,'b2'!$K23=1,'b2'!$L23=1,'b2'!$M23=1,'b2'!$N23=1,'b2'!$O23=1,'b2'!$P23=1),"SI","NO") | U23: =IF(OR('b2'!$K23=1,'b2'!$L23=1,'b2'!$M23=1,'b2'!$N23=1,'b2'!$O23=1,'b2'!$P23=1),"SI","NO") | V23: 0 | W23: 33 | X23: 2 | Y23: 35 | Z23: 0 | AA23: 0 | AB23: 0 | AC23: 0 | AD23: 0 | AE23: 0 | AF23: 0 | AG23: 0 | AH23: 0 | AI23: 0 | AJ23: 0 | AK23: 0 | AL23: 0 | AM23: 0 | AN23: 0 | AO23: 0 | AP23: 0 | AQ23: 0 | AR23: =IF('b2'!$AQ23>0,'b2'!$AQ23,IF('b2'!$AN23>0,'b2'!$AN23,IF('b2'!$AK23>0,'b2'!$AK23,IF('b2'!$AH23>0,'b2'!$AH23,IF('b2'!$AE23>0,'b2'!$AE23,IF('b2'!$AB23>0,'b2'!$AB23,IF('b2'!$Y23>0,'b2'!$Y23,IF('b2'!$V23>0,'b2'!$V23," ---")))))))) | AS23: 0 | AT23: 0 | AU23: 0 | AV23: 0 | AW23: 0 | AX23: 0 | AY23: 0 | AZ23: 0 | BA23: 0 | BB23: 0 | BC23: 0 | BD23: 0 | BE23: 0 | BF23: 260411.15 | BG23: 0 | BH23: 260411.15 | BI23: #REF! | BJ23: #REF! | BK23: 0 | BL23: 0 | BM23: 0 | BN23: #REF! | BO23: #REF! | BP23: 0 | BQ23: 0 | BR23: 0 | BS23: #REF! | BT23: ='[2]DATA CONSOLIDADA 2018-2025 '!$BR25-'b2'!$BO23 | BU23: 0 | BV23: 0 | BW23: 0 | BX23: #REF! | BY23: #REF! | BZ23: 0 | CA23: 0 | CB23: 0 | CC23: #REF! | CD23: ='[2]DATA CONSOLIDADA 2018-2025 '!$CB25-'b2'!$BW23 | CE23: 0 | CF23: 0 | CG23: 0 | CH23: #REF! | CI23: ='[2]DATA CONSOLIDADA 2018-2025 '!$CG25-'b2'!$CB23 | CJ23: #REF! | CK23: 0 | CL23: 0 | CM23: 0 | CN23: #REF! | CO23: ='[2]DATA CONSOLIDADA 2018-2025 '!$CM25-'b2'!$CG23 | CP23: 0 | CQ23: 0 | CR23: 0 | CS23: 0 | CT23: 0 | CU23: 0 | CV23: 0 | CW23: 0 | CX23: 0 | CY23: 0 | CZ23: 0 | DA23: 0 | DB23: 0 | DC23: 0 | DD23: 0 | DE23: 0 | DF23: 0 | DG23: 0 | DH23: 0 | DI23: 20603736703 | DJ23: ASOCIACION DE PRODUCTORES DE PALTOS MORO - APROPALMO | DK23: 01 Asociación
A24: COOPERATIVA AGRARIA VALLE FORTALEZA-COAVAF | B24: DURAZNO | C24: DURAZNO | D24: ANCASH | E24: 020503 | F24: ANCASH | G24: BOLOGNESI | H24: ANTONIO RAYMONDI | L24: 1 | Q24: PAC | R24: =IF(I24=1,I$2,"")&IF(J24=1,IF(I24=1,"-","")&J$2,"")&IF(K24=1,IF(OR(J24=1,I24=1),"-","")&K$2,"")&IF(L24=1,IF(OR(K24=1,J24=1,I24=1),"-","")&L$2,"")&IF(M24=1,IF(OR(L24=1,K24=1,J24=1,I24=1),"-","")&M$2,"")&IF(N24=1,IF(OR(M24=1,L24=1,K24=1,J24=1,I24=1),"-","")&N$2,"")&IF(O24=1,IF(OR(N24=1,M24=1,L24=1,K24=1,J24=1,I24=1),"-","")&O$2,"")&IF(P24=1,IF(I24=1," - ",IF(J24=1," - ",IF(K24=1," - ",IF(L24=1," - ",IF(M24=1," - ",IF(N24=1," - ",IF(O24=1," - ","")))))))&P$2,"") | S24: =SUM('b2'!$I24:$P24) | T24: =IF(OR('b2'!$J24=1,'b2'!$K24=1,'b2'!$L24=1,'b2'!$M24=1,'b2'!$N24=1,'b2'!$O24=1,'b2'!$P24=1),"SI","NO") | U24: =IF(OR('b2'!$K24=1,'b2'!$L24=1,'b2'!$M24=1,'b2'!$N24=1,'b2'!$O24=1,'b2'!$P24=1),"SI","NO") | V24: 0 | W24: 0 | X24: 0 | Y24: 0 | Z24: 0 | AA24: 0 | AB24: 0 | AC24: 64 | AD24: 10 | AE24: 74 | AF24: 0 | AG24: 0 | AH24: 0 | AI24: 0 | AJ24: 0 | AK24: 0 | AL24: 0 | AM24: 0 | AN24: 0 | AO24: 0 | AP24: 0 | AQ24: 0 | AR24: =IF('b2'!$AQ24>0,'b2'!$AQ24,IF('b2'!$AN24>0,'b2'!$AN24,IF('b2'!$AK24>0,'b2'!$AK24,IF('b2'!$AH24>0,'b2'!$AH24,IF('b2'!$AE24>0,'b2'!$AE24,IF('b2'!$AB24>0,'b2'!$AB24,IF('b2'!$Y24>0,'b2'!$Y24,IF('b2'!$V24>0,'b2'!$V24," ---")))))))) | AS24: 0 | AT24: 0 | AU24: 52 | AV24: 8 | AW24: 0 | AX24: 0 | AY24: 0 | AZ24: 0 | BA24: 0 | BB24: 0 | BC24: 0 | BD24: 0 | BE24: 0 | BF24: 0 | BG24: 0 | BH24: 0 | BI24: #REF! | BJ24: #REF! | BK24: 0 | BL24: 0 | BM24: 0 | BN24: #REF! | BO24: #REF! | BP24: 183225 | BQ24: 0 | BR24: 183225 | BS24: #REF! | BT24: ='[2]DATA CONSOLIDADA 2018-2025 '!$BR26-'b2'!$BO24 | BU24: 0 | BV24: 0 | BW24: 0 | BX24: #REF! | BY24: #REF! | BZ24: 0 | CA24: 0 | CB24: 0 | CC24: #REF! | CD24: ='[2]DATA CONSOLIDADA 2018-2025 '!$CB26-'b2'!$BW24 | CE24: 0 | CF24: 0 | CG24: 0 | CH24: #REF! | CI24: ='[2]DATA CONSOLIDADA 2018-2025 '!$CG26-'b2'!$CB24 | CJ24: #REF! | CK24: 0 | CL24: 0 | CM24: 0 | CN24: #REF! | CO24: ='[2]DATA CONSOLIDADA 2018-2025 '!$CM26-'b2'!$CG24 | CP24: 0 | CQ24: 0 | CR24: 0 | CS24: 0 | CT24: 0 | CU24: 0 | CV24: 0 | CW24: 0 | CX24: 0 | CY24: 0 | CZ24: 0 | DA24: 0 | DB24: 0 | DC24: 0 | DD24: 0 | DE24: 0 | DF24: 0 | DG24: 0 | DH24: 0 | DI24: 20600276221 | DJ24: COOPERATIVA AGRARIA VALLE FORTALEZA - COAVAFF | DK24: 02 Cooperativa
A25: ASOCIACION DE PRODUCTORES AGROECOLOGICOS DE PARIACOTO PROMOVIENDO VIDA SALUDABLE - APAPROVIS | B25: PALTA | C25: PALTA | D25: ANCASH | E25: 020110 | F25: ANCASH | G25: HUARAZ | H25: PARIACOTO | L25: 1 | M25: 1 | N25: 1 | O25: 1 | Q25: PAC | R25: =IF(I25=1,I$2,"")&IF(J25=1,IF(I25=1,"-","")&J$2,"")&IF(K25=1,IF(OR(J25=1,I25=1),"-","")&K$2,"")&IF(L25=1,IF(OR(K25=1,J25=1,I25=1),"-","")&L$2,"")&IF(M25=1,IF(OR(L25=1,K25=1,J25=1,I25=1),"-","")&M$2,"")&IF(N25=1,IF(OR(M25=1,L25=1,K25=1,J25=1,I25=1),"-","")&N$2,"")&IF(O25=1,IF(OR(N25=1,M25=1,L25=1,K25=1,J25=1,I25=1),"-","")&O$2,"")&IF(P25=1,IF(I25=1," - ",IF(J25=1," - ",IF(K25=1," - ",IF(L25=1," - ",IF(M25=1," - ",IF(N25=1," - ",IF(O25=1," - ","")))))))&P$2,"") | S25: =SUM('b2'!$I25:$P25) | T25: =IF(OR('b2'!$J25=1,'b2'!$K25=1,'b2'!$L25=1,'b2'!$M25=1,'b2'!$N25=1,'b2'!$O25=1,'b2'!$P25=1),"SI","NO") | U25: =IF(OR('b2'!$K25=1,'b2'!$L25=1,'b2'!$M25=1,'b2'!$N25=1,'b2'!$O25=1,'b2'!$P25=1),"SI","NO") | V25: 0 | W25: 0 | X25: 0 | Y25: 0 | Z25: 0 | AA25: 0 | AB25: 0 | AC25: 20 | AD25: 6 | AE25: 26 | AF25: 20 | AG25: 6 | AH25: 26 | AI25: 20 | AJ25: 6 | AK25: 26 | AL25: 20 | AM25: 6 | AN25: 26 | AO25: 0 | AP25: 0 | AQ25: 0 | AR25: =IF('b2'!$AQ25>0,'b2'!$AQ25,IF('b2'!$AN25>0,'b2'!$AN25,IF('b2'!$AK25>0,'b2'!$AK25,IF('b2'!$AH25>0,'b2'!$AH25,IF('b2'!$AE25>0,'b2'!$AE25,IF('b2'!$AB25>0,'b2'!$AB25,IF('b2'!$Y25>0,'b2'!$Y25,IF('b2'!$V25>0,'b2'!$V25," ---")))))))) | AS25: 0 | AT25: 0 | AU25: 67 | AV25: 10 | AW25: 16 | AX25: 5 | AY25: 38 | AZ25: 1 | BA25: 30 | BB25: 0 | BC25: 0 | BD25: 0 | BE25: 0 | BF25: 0 | BG25: 0 | BH25: 0 | BI25: #REF! | BJ25: #REF! | BK25: 0 | BL25: 0 | BM25: 0 | BN25: #REF! | BO25: #REF! | BP25: 211492.7 | BQ25: 0 | BR25: 211492.7 | BS25: #REF! | BT25: ='[2]DATA CONSOLIDADA 2018-2025 '!$BR27-'b2'!$BO25 | BU25: 52556.7 | BV25: 0 | BW25: 52556.7 | BX25: #REF! | BY25: #REF! | BZ25: 77420.7 | CA25: 0 | CB25: 77420.7 | CC25: #REF! | CD25: ='[2]DATA CONSOLIDADA 2018-2025 '!$CB27-'b2'!$BW25 | CE25: 48724 | CF25: 0 | CG25: 48724 | CH25: #REF! | CI25: ='[2]DATA CONSOLIDADA 2018-2025 '!$CG27-'b2'!$CB25 | CJ25: #REF! | CK25: 0 | CL25: 0 | CM25: 0 | CN25: #REF! | CO25: ='[2]DATA CONSOLIDADA 2018-2025 '!$CM27-'b2'!$CG25 | CP25: 0 | CQ25: 77420.7 | CR25: 0 | CS25: 0 | CT25: 0 | CU25: 0 | CV25: 77420.7 | CW25: 0 | CX25: 48724 | CY25: 0 | CZ25: 0 | DA25: 0 | DB25: 48724 | DC25: 0 | DD25: 0 | DE25: 0 | DF25: 0 | DG25: 0 | DH25: 0 | DI25: 20605197583 | DJ25: ASOCIACION DE PRODUCTORES AGROECOLOGICOS DE PARIACOTO PROMOVIENDO VIDA SALUDABLE - APAPROVIS | DK25: 01 Asociación
A26: COOPERATIVA AGRARIA PURIFOR | B26: PALTA | C26: PALTA | D26: ANCASH | E26: 020507 | F26: ANCASH | G26: BOLOGNESI | H26: COLQUIOC | M26: 1 | N26: 1 | O26: 1 | P26: 1 | Q26: PAC | R26: =IF(I26=1,I$2,"")&IF(J26=1,IF(I26=1,"-","")&J$2,"")&IF(K26=1,IF(OR(J26=1,I26=1),"-","")&K$2,"")&IF(L26=1,IF(OR(K26=1,J26=1,I26=1),"-","")&L$2,"")&IF(M26=1,IF(OR(L26=1,K26=1,J26=1,I26=1),"-","")&M$2,"")&IF(N26=1,IF(OR(M26=1,L26=1,K26=1,J26=1,I26=1),"-","")&N$2,"")&IF(O26=1,IF(OR(N26=1,M26=1,L26=1,K26=1,J26=1,I26=1),"-","")&O$2,"")&IF(P26=1,IF(I26=1," - ",IF(J26=1," - ",IF(K26=1," - ",IF(L26=1," - ",IF(M26=1," - ",IF(N26=1," - ",IF(O26=1," - ","")))))))&P$2,"") | S26: =SUM('b2'!$I26:$P26) | T26: =IF(OR('b2'!$J26=1,'b2'!$K26=1,'b2'!$L26=1,'b2'!$M26=1,'b2'!$N26=1,'b2'!$O26=1,'b2'!$P26=1),"SI","NO") | U26: =IF(OR('b2'!$K26=1,'b2'!$L26=1,'b2'!$M26=1,'b2'!$N26=1,'b2'!$O26=1,'b2'!$P26=1),"SI","NO") | V26: 0 | W26: 0 | X26: 0 | Y26: 0 | Z26: 0 | AA26: 0 | AB26: 0 | AC26: 0 | AD26: 0 | AE26: 0 | AF26: 57 | AG26: 29 | AH26: 86 | AI26: 57 | AJ26: 29 | AK26: 86 | AL26: 61 | AM26: 25 | AN26: 86 | AO26: 59 | AP26: 25 | AQ26: 84 | AR26: =IF('b2'!$AQ26>0,'b2'!$AQ26,IF('b2'!$AN26>0,'b2'!$AN26,IF('b2'!$AK26>0,'b2'!$AK26,IF('b2'!$AH26>0,'b2'!$AH26,IF('b2'!$AE26>0,'b2'!$AE26,IF('b2'!$AB26>0,'b2'!$AB26,IF('b2'!$Y26>0,'b2'!$Y26,IF('b2'!$V26>0,'b2'!$V26," ---")))))))) | AS26: 0 | AT26: 0 | AU26: 0 | AV26: 0 | AW26: 19 | AX26: 5 | AY26: 38 | AZ26: 0 | BA26: 31 | BB26: 3 | BC26: 12 | BD26: 0 | BE26: 0 | BF26: 0 | BG26: 0 | BH26: 0 | BI26: #REF! | BJ26: #REF! | BK26: 0 | BL26: 0 | BM26: 0 | BN26: #REF! | BO26: #REF! | BP26: 0 | BQ26: 0 | BR26: 0 | BS26: #REF! | BT26: ='[2]DATA CONSOLIDADA 2018-2025 '!$BR28-'b2'!$BO26 | BU26: 351529.15 | BV26: 0 | BW26: 351529.15 | BX26: #REF! | BY26: #REF! | BZ26: 100445.5 | CA26: 0 | CB26: 100445.5 | CC26: #REF! | CD26: ='[2]DATA CONSOLIDADA 2018-2025 '!$CB28-'b2'!$BW26 | CE26: 362155.2 | CF26: 0 | CG26: 362155.2 | CH26: #REF! | CI26: ='[2]DATA CONSOLIDADA 2018-2025 '!$CG28-'b2'!$CB26 | CJ26: #REF! | CK26: 488080 | CL26: 0 | CM26: 488080 | CN26: #REF! | CO26: ='[2]DATA CONSOLIDADA 2018-2025 '!$CM28-'b2'!$CG26 | CP26: 0 | CQ26: 100445.5 | CR26: 0 | CS26: 0 | CT26: 0 | CU26: 0 | CV26: 100445.5 | CW26: 0 | CX26: 362155.2 | CY26: 0 | CZ26: 0 | DA26: 0 | DB26: 362155.2 | DC26: 0 | DD26: 470180 | DE26: 0 | DF26: 17900 | DG26: 0 | DH26: 488080 | DI26: 20407808666 | DJ26: COOPERATIVA AGRARIA PURIFOR - COOP PURIFOR | DK26: 02 Cooperativa
A27: COOPERATIVA AGRARIA ANDINA DE SANTA CRUZ LTDA. | B27: KIWICHA | C27: KIWICHA | D27: ANCASH | E27: 021208 | F27: ANCASH | G27: HUAYLAS | H27: SANTA CRUZ | M27: 1 | O27: 1 | P27: 1 | Q27: PAC | R27: =IF(I27=1,I$2,"")&IF(J27=1,IF(I27=1,"-","")&J$2,"")&IF(K27=1,IF(OR(J27=1,I27=1),"-","")&K$2,"")&IF(L27=1,IF(OR(K27=1,J27=1,I27=1),"-","")&L$2,"")&IF(M27=1,IF(OR(L27=1,K27=1,J27=1,I27=1),"-","")&M$2,"")&IF(N27=1,IF(OR(M27=1,L27=1,K27=1,J27=1,I27=1),"-","")&N$2,"")&IF(O27=1,IF(OR(N27=1,M27=1,L27=1,K27=1,J27=1,I27=1),"-","")&O$2,"")&IF(P27=1,IF(I27=1," - ",IF(J27=1," - ",IF(K27=1," - ",IF(L27=1," - ",IF(M27=1," - ",IF(N27=1," - ",IF(O27=1," - ","")))))))&P$2,"") | S27: =SUM('b2'!$I27:$P27) | T27: =IF(OR('b2'!$J27=1,'b2'!$K27=1,'b2'!$L27=1,'b2'!$M27=1,'b2'!$N27=1,'b2'!$O27=1,'b2'!$P27=1),"SI","NO") | U27: =IF(OR('b2'!$K27=1,'b2'!$L27=1,'b2'!$M27=1,'b2'!$N27=1,'b2'!$O27=1,'b2'!$P27=1),"SI","NO") | V27: 0 | W27: 0 | X27: 0 | Y27: 0 | Z27: 0 | AA27: 0 | AB27: 0 | AC27: 0 | AD27: 0 | AE27: 0 | AF27: 9 | AG27: 10 | AH27: 19 | AI27: 0 | AJ27: 0 | AK27: 0 | AL27: 8 | AM27: 10 | AN27: 18 | AO27: 10 | AP27: 17 | AQ27: 27 | AR27: =IF('b2'!$AQ27>0,'b2'!$AQ27,IF('b2'!$AN27>0,'b2'!$AN27,IF('b2'!$AK27>0,'b2'!$AK27,IF('b2'!$AH27>0,'b2'!$AH27,IF('b2'!$AE27>0,'b2'!$AE27,IF('b2'!$AB27>0,'b2'!$AB27,IF('b2'!$Y27>0,'b2'!$Y27,IF('b2'!$V27>0,'b2'!$V27," ---")))))))) | AS27: 0 | AT27: 0 | AU27: 0 | AV27: 0 | AW27: 22 | AX27: 6 | AY27: 0 | AZ27: 0 | BA27: 28 | BB27: 0 | BC27: 31 | BD27: 0 | BE27: 0 | BF27: 0 | BG27: 0 | BH27: 0 | BI27: #REF! | BJ27: #REF! | BK27: 0 | BL27: 0 | BM27: 0 | BN27: #REF! | BO27: #REF! | BP27: 0 | BQ27: 0 | BR27: 0 | BS27: #REF! | BT27: ='[2]DATA CONSOLIDADA 2018-2025 '!$BR29-'b2'!$BO27 | BU27: 29700 | BV27: 0 | BW27: 29700 | BX27: #REF! | BY27: #REF! | BZ27: 0 | CA27: 0 | CB27: 0 | CC27: #REF! | CD27: ='[2]DATA CONSOLIDADA 2018-2025 '!$CB29-'b2'!$BW27 | CE27: 65663.1 | CF27: 0 | CG27: 65663.1 | CH27: #REF! | CI27: ='[2]DATA CONSOLIDADA 2018-2025 '!$CG29-'b2'!$CB27 | CJ27: #REF! | CK27: 28801.99 | CL27: 0 | CM27: 28801.99 | CN27: #REF! | CO27: ='[2]DATA CONSOLIDADA 2018-2025 '!$CM29-'b2'!$CG27 | CP27: 0 | CQ27: 0 | CR27: 0 | CS27: 0 | CT27: 0 | CU27: 0 | CV27: 0 | CW27: 0 | CX27: 65663.1 | CY27: 0 | CZ27: 0 | DA27: 0 | DB27: 65663.1 | DC27: 1143.9897 | DD27: 27658 | DE27: 0 | DF27: 0 | DG27: 0 | DH27: 28801.99 | DI27: 20604755230 | DJ27: COOPERATIVA AGRARIA ANDINA DE SANTA CRUZ LTDA. | DK27: 02 Cooperativa
A28: COOPERATIVA AGRARIA KIWICHA WAYI LTDA | B28: KIWICHA | C28: KIWICHA | D28: ANCASH | E28: 021201 | F28: ANCASH | G28: HUAYLAS | H28: CARAZ | M28: 1 | N28: 1 | O28: 1 | P28: 1 | Q28: PAC | R28: =IF(I28=1,I$2,"")&IF(J28=1,IF(I28=1,"-","")&J$2,"")&IF(K28=1,IF(OR(J28=1,I28=1),"-","")&K$2,"")&IF(L28=1,IF(OR(K28=1,J28=1,I28=1),"-","")&L$2,"")&IF(M28=1,IF(OR(L28=1,K28=1,J28=1,I28=1),"-","")&M$2,"")&IF(N28=1,IF(OR(M28=1,L28=1,K28=1,J28=1,I28=1),"-","")&N$2,"")&IF(O28=1,IF(OR(N28=1,M28=1,L28=1,K28=1,J28=1,I28=1),"-","")&O$2,"")&IF(P28=1,IF(I28=1," - ",IF(J28=1," - ",IF(K28=1," - ",IF(L28=1," - ",IF(M28=1," - ",IF(N28=1," - ",IF(O28=1," - ","")))))))&P$2,"") | S28: =SUM('b2'!$I28:$P28) | T28: =IF(OR('b2'!$J28=1,'b2'!$K28=1,'b2'!$L28=1,'b2'!$M28=1,'b2'!$N28=1,'b2'!$O28=1,'b2'!$P28=1),"SI","NO") | U28: =IF(OR('b2'!$K28=1,'b2'!$L28=1,'b2'!$M28=1,'b2'!$N28=1,'b2'!$O28=1,'b2'!$P28=1),"SI","NO") | V28: 0 | W28: 0 | X28: 0 | Y28: 0 | Z28: 0 | AA28: 0 | AB28: 0 | AC28: 0 | AD28: 0 | AE28: 0 | AF28: 12 | AG28: 14 | AH28: 26 | AI28: 12 | AJ28: 14 | AK28: 26 | AL28: 11 | AM28: 14 | AN28: 25 | AO28: 11 | AP28: 14 | AQ28: 25 | AR28: =IF('b2'!$AQ28>0,'b2'!$AQ28,IF('b2'!$AN28>0,'b2'!$AN28,IF('b2'!$AK28>0,'b2'!$AK28,IF('b2'!$AH28>0,'b2'!$AH28,IF('b2'!$AE28>0,'b2'!$AE28,IF('b2'!$AB28>0,'b2'!$AB28,IF('b2'!$Y28>0,'b2'!$Y28,IF('b2'!$V28>0,'b2'!$V28," ---")))))))) | AS28: 0 | AT28: 0 | AU28: 0 | AV28: 0 | AW28: 23 | AX28: 6 | AY28: 37 | AZ28: 3 | BA28: 25 | BB28: 3 | BC28: 29 | BD28: 2 | BE28: 0 | BF28: 0 | BG28: 0 | BH28: 0 | BI28: #REF! | BJ28: #REF! | BK28: 0 | BL28: 0 | BM28: 0 | BN28: #REF! | BO28: #REF! | BP28: 0 | BQ28: 0 | BR28: 0 | BS28: #REF! | BT28: ='[2]DATA CONSOLIDADA 2018-2025 '!$BR30-'b2'!$BO28 | BU28: 88340 | BV28: 0 | BW28: 88340 | BX28: #REF! | BY28: #REF! | BZ28: 132750.28 | CA28: 0 | CB28: 132750.28 | CC28: #REF! | CD28: ='[2]DATA CONSOLIDADA 2018-2025 '!$CB30-'b2'!$BW28 | CE28: 197902 | CF28: 0 | CG28: 197902 | CH28: #REF! | CI28: ='[2]DATA CONSOLIDADA 2018-2025 '!$CG30-'b2'!$CB28 | CJ28: #REF! | CK28: 102372.15 | CL28: 0 | CM28: 102372.15 | CN28: #REF! | CO28: ='[2]DATA CONSOLIDADA 2018-2025 '!$CM30-'b2'!$CG28 | CP28: 0 | CQ28: 59729 | CR28: 0 | CS28: 73021.284 | CT28: 0 | CU28: 0 | CV28: 132750.28 | CW28: 0 | CX28: 197902 | CY28: 0 | CZ28: 0 | DA28: 0 | DB28: 197902 | DC28: 0 | DD28: 77932.1 | DE28: 24440.055 | DF28: 0 | DG28: 0 | DH28: 102372.15 | DI28: 20600558715 | DJ28: COOPERATIVA AGRARIA KIWICHA WAYI LTDA | DK28: 02 Cooperativa
A29: ASOCIACION PRODUCTORES AGROPECUARIOS SANTA ROSA DE KIMAN AYLLU | B29: PALTA | C29: PALTA | D29: ANCASH | E29: 021210 | F29: ANCASH | G29: HUAYLAS | H29: YURACMARCA | M29: 1 | N29: 1 | O29: 1 | P29: 1 | Q29: PAC | R29: =IF(I29=1,I$2,"")&IF(J29=1,IF(I29=1,"-","")&J$2,"")&IF(K29=1,IF(OR(J29=1,I29=1),"-","")&K$2,"")&IF(L29=1,IF(OR(K29=1,J29=1,I29=1),"-","")&L$2,"")&IF(M29=1,IF(OR(L29=1,K29=1,J29=1,I29=1),"-","")&M$2,"")&IF(N29=1,IF(OR(M29=1,L29=1,K29=1,J29=1,I29=1),"-","")&N$2,"")&IF(O29=1,IF(OR(N29=1,M29=1,L29=1,K29=1,J29=1,I29=1),"-","")&O$2,"")&IF(P29=1,IF(I29=1," - ",IF(J29=1," - ",IF(K29=1," - ",IF(L29=1," - ",IF(M29=1," - ",IF(N29=1," - ",IF(O29=1," - ","")))))))&P$2,"") | S29: =SUM('b2'!$I29:$P29) | T29: =IF(OR('b2'!$J29=1,'b2'!$K29=1,'b2'!$L29=1,'b2'!$M29=1,'b2'!$N29=1,'b2'!$O29=1,'b2'!$P29=1),"SI","NO") | U29: =IF(OR('b2'!$K29=1,'b2'!$L29=1,'b2'!$M29=1,'b2'!$N29=1,'b2'!$O29=1,'b2'!$P29=1),"SI","NO") | V29: 0 | W29: 0 | X29: 0 | Y29: 0 | Z29: 0 | AA29: 0 | AB29: 0 | AC29: 0 | AD29: 0 | AE29: 0 | AF29: 13 | AG29: 7 | AH29: 20 | AI29: 13 | AJ29: 7 | AK29: 20 | AL29: 11 | AM29: 7 | AN29: 18 | AO29: 11 | AP29: 5 | AQ29: 16 | AR29: =IF('b2'!$AQ29>0,'b2'!$AQ29,IF('b2'!$AN29>0,'b2'!$AN29,IF('b2'!$AK29>0,'b2'!$AK29,IF('b2'!$AH29>0,'b2'!$AH29,IF('b2'!$AE29>0,'b2'!$AE29,IF('b2'!$AB29>0,'b2'!$AB29,IF('b2'!$Y29>0,'b2'!$Y29,IF('b2'!$V29>0,'b2'!$V29," ---")))))))) | AS29: 0 | AT29: 0 | AU29: 0 | AV29: 0 | AW29: 19 | AX29: 5 | AY29: 44 | AZ29: 3 | BA29: 32 | BB29: 4 | BC29: 35 | BD29: 0 | BE29: 0 | BF29: 0 | BG29: 0 | BH29: 0 | BI29: #REF! | BJ29: #REF! | BK29: 0 | BL29: 0 | BM29: 0 | BN29: #REF! | BO29: #REF! | BP29: 0 | BQ29: 0 | BR29: 0 | BS29: #REF! | BT29: ='[2]DATA CONSOLIDADA 2018-2025 '!$BR31-'b2'!$BO29 | BU29: 180390 | BV29: 0 | BW29: 180390 | BX29: #REF! | BY29: #REF! | BZ29: 208400 | CA29: 0 | CB29: 208400 | CC29: #REF! | CD29: ='[2]DATA CONSOLIDADA 2018-2025 '!$CB31-'b2'!$BW29 | CE29: 241803.66 | CF29: 0 | CG29: 241803.66 | CH29: #REF! | CI29: ='[2]DATA CONSOLIDADA 2018-2025 '!$CG31-'b2'!$CB29 | CJ29: #REF! | CK29: 189229.51 | CL29: 0 | CM29: 189229.51 | CN29: #REF! | CO29: ='[2]DATA CONSOLIDADA 2018-2025 '!$CM31-'b2'!$CG29 | CP29: 0 | CQ29: 208400 | CR29: 0 | CS29: 0 | CT29: 0 | CU29: 0 | CV29: 208400 | CW29: 0 | CX29: 241803.66 | CY29: 0 | CZ29: 0 | DA29: 0 | DB29: 241803.66 | DC29: 0 | DD29: 152584.41 | DE29: 0 | DF29: 0 | DG29: 36645.095 | DH29: 189229.51 | DI29: 20533718176 | DJ29: ASOCIACION PRODUCTORES AGROPECUARIOS SANTA ROSA DE KIMAN AYLLU | DK29: 01 Asociación
A30: COOPERATIVA AGRARIA COYAPAPI | B30: PALTA | C30: PALTA | D30: ANCASH | E30: 020110 | F30: ANCASH | G30: HUARAZ | H30: PARIACOTO | M30: 1 | N30: 1 | O30: 1 | Q30: PAC | R30: =IF(I30=1,I$2,"")&IF(J30=1,IF(I30=1,"-","")&J$2,"")&IF(K30=1,IF(OR(J30=1,I30=1),"-","")&K$2,"")&IF(L30=1,IF(OR(K30=1,J30=1,I30=1),"-","")&L$2,"")&IF(M30=1,IF(OR(L30=1,K30=1,J30=1,I30=1),"-","")&M$2,"")&IF(N30=1,IF(OR(M30=1,L30=1,K30=1,J30=1,I30=1),"-","")&N$2,"")&IF(O30=1,IF(OR(N30=1,M30=1,L30=1,K30=1,J30=1,I30=1),"-","")&O$2,"")&IF(P30=1,IF(I30=1," - ",IF(J30=1," - ",IF(K30=1," - ",IF(L30=1," - ",IF(M30=1," - ",IF(N30=1," - ",IF(O30=1," - ","")))))))&P$2,"") | S30: =SUM('b2'!$I30:$P30) | T30: =IF(OR('b2'!$J30=1,'b2'!$K30=1,'b2'!$L30=1,'b2'!$M30=1,'b2'!$N30=1,'b2'!$O30=1,'b2'!$P30=1),"SI","NO") | U30: =IF(OR('b2'!$K30=1,'b2'!$L30=1,'b2'!$M30=1,'b2'!$N30=1,'b2'!$O30=1,'b2'!$P30=1),"SI","NO") | V30: 0 | W30: 0 | X30: 0 | Y30: 0 | Z30: 0 | AA30: 0 | AB30: 0 | AC30: 0 | AD30: 0 | AE30: 0 | AF30: 132 | AG30: 19 | AH30: 151 | AI30: 132 | AJ30: 19 | AK30: 151 | AL30: 135 | AM30: 14 | AN30: 149 | AO30: 0 | AP30: 0 | AQ30: 0 | AR30: =IF('b2'!$AQ30>0,'b2'!$AQ30,IF('b2'!$AN30>0,'b2'!$AN30,IF('b2'!$AK30>0,'b2'!$AK30,IF('b2'!$AH30>0,'b2'!$AH30,IF('b2'!$AE30>0,'b2'!$AE30,IF('b2'!$AB30>0,'b2'!$AB30,IF('b2'!$Y30>0,'b2'!$Y30,IF('b2'!$V30>0,'b2'!$V30," ---")))))))) | AS30: 0 | AT30: 0 | AU30: 0 | AV30: 0 | AW30: 17 | AX30: 5 | AY30: 37 | AZ30: 1 | BA30: 27 | BB30: 3 | BC30: 0 | BD30: 0 | BE30: 0 | BF30: 0 | BG30: 0 | BH30: 0 | BI30: #REF! | BJ30: #REF! | BK30: 0 | BL30: 0 | BM30: 0 | BN30: #REF! | BO30: #REF! | BP30: 0 | BQ30: 0 | BR30: 0 | BS30: #REF! | BT30: ='[2]DATA CONSOLIDADA 2018-2025 '!$BR32-'b2'!$BO30 | BU30: 363932.5 | BV30: 0 | BW30: 363932.5 | BX30: #REF! | BY30: #REF! | BZ30: 664665.6 | CA30: 0 | CB30: 664665.6 | CC30: #REF! | CD30: ='[2]DATA CONSOLIDADA 2018-2025 '!$CB32-'b2'!$BW30 | CE30: 1376040 | CF30: 0 | CG30: 1376040 | CH30: #REF! | CI30: ='[2]DATA CONSOLIDADA 2018-2025 '!$CG32-'b2'!$CB30 | CJ30: #REF! | CK30: 0 | CL30: 0 | CM30: 0 | CN30: #REF! | CO30: ='[2]DATA CONSOLIDADA 2018-2025 '!$CM32-'b2'!$CG30 | CP30: 0 | CQ30: 664665.6 | CR30: 0 | CS30: 0 | CT30: 0 | CU30: 0 | CV30: 664665.6 | CW30: 0 | CX30: 1376040 | CY30: 0 | CZ30: 0 | DA30: 0 | DB30: 1376040 | DC30: 0 | DD30: 0 | DE30: 0 | DF30: 0 | DG30: 0 | DH30: 0 | DI30: 20604218358 | DJ30: COOPERATIVA AGRARIA COYAPAPI | DK30: 02 Cooperativa
A31: ASOCIACIÓN DE FRUTICULTORES DEL VALLE PAMPAS- AFRUVAP | B31: PALTA | C31: PALTA | D31: APURIMAC | E31: 030601 | F31: APURIMAC | G31: CHINCHEROS | H31: CHINCHEROS | J31: 1 | K31: 1 | Q31: PAC | R31: =IF(I31=1,I$2,"")&IF(J31=1,IF(I31=1,"-","")&J$2,"")&IF(K31=1,IF(OR(J31=1,I31=1),"-","")&K$2,"")&IF(L31=1,IF(OR(K31=1,J31=1,I31=1),"-","")&L$2,"")&IF(M31=1,IF(OR(L31=1,K31=1,J31=1,I31=1),"-","")&M$2,"")&IF(N31=1,IF(OR(M31=1,L31=1,K31=1,J31=1,I31=1),"-","")&N$2,"")&IF(O31=1,IF(OR(N31=1,M31=1,L31=1,K31=1,J31=1,I31=1),"-","")&O$2,"")&IF(P31=1,IF(I31=1," - ",IF(J31=1," - ",IF(K31=1," - ",IF(L31=1," - ",IF(M31=1," - ",IF(N31=1," - ",IF(O31=1," - ","")))))))&P$2,"") | S31: =SUM('b2'!$I31:$P31) | T31: =IF(OR('b2'!$J31=1,'b2'!$K31=1,'b2'!$L31=1,'b2'!$M31=1,'b2'!$N31=1,'b2'!$O31=1,'b2'!$P31=1),"SI","NO") | U31: =IF(OR('b2'!$K31=1,'b2'!$L31=1,'b2'!$M31=1,'b2'!$N31=1,'b2'!$O31=1,'b2'!$P31=1),"SI","NO") | V31: 0 | W31: 15 | X31: 12 | Y31: 27 | Z31: 20 | AA31: 4 | AB31: 24 | AC31: 0 | AD31: 0 | AE31: 0 | AF31: 0 | AG31: 0 | AH31: 0 | AI31: 0 | AJ31: 0 | AK31: 0 | AL31: 0 | AM31: 0 | AN31: 0 | AO31: 0 | AP31: 0 | AQ31: 0 | AR31: =IF('b2'!$AQ31>0,'b2'!$AQ31,IF('b2'!$AN31>0,'b2'!$AN31,IF('b2'!$AK31>0,'b2'!$AK31,IF('b2'!$AH31>0,'b2'!$AH31,IF('b2'!$AE31>0,'b2'!$AE31,IF('b2'!$AB31>0,'b2'!$AB31,IF('b2'!$Y31>0,'b2'!$Y31,IF('b2'!$V31>0,'b2'!$V31," ---")))))))) | AS31: 0 | AT31: 2 | AU31: 0 | AV31: 0 | AW31: 0 | AX31: 0 | AY31: 0 | AZ31: 0 | BA31: 0 | BB31: 0 | BC31: 0 | BD31: 0 | BE31: 0 | BF31: 0 | BG31: 0 | BH31: 0 | BI31: #REF! | BJ31: #REF! | BK31: 324995 | BL31: 0 | BM31: 324995 | BN31: #REF! | BO31: #REF! | BP31: 0 | BQ31: 0 | BR31: 0 | BS31: #REF! | BT31: ='[2]DATA CONSOLIDADA 2018-2025 '!$BR33-'b2'!$BO31 | BU31: 0 | BV31: 0 | BW31: 0 | BX31: #REF! | BY31: #REF! | BZ31: 0 | CA31: 0 | CB31: 0 | CC31: #REF! | CD31: ='[2]DATA CONSOLIDADA 2018-2025 '!$CB33-'b2'!$BW31 | CE31: 0 | CF31: 0 | CG31: 0 | CH31: #REF! | CI31: ='[2]DATA CONSOLIDADA 2018-2025 '!$CG33-'b2'!$CB31 | CJ31: #REF! | CK31: 0 | CL31: 0 | CM31: 0 | CN31: #REF! | CO31: ='[2]DATA CONSOLIDADA 2018-2025 '!$CM33-'b2'!$CG31 | CP31: 0 | CQ31: 0 | CR31: 0 | CS31: 0 | CT31: 0 | CU31: 0 | CV31: 0 | CW31: 0 | CX31: 0 | CY31: 0 | CZ31: 0 | DA31: 0 | DB31: 0 | DC31: 0 | DD31: 0 | DE31: 0 | DF31: 0 | DG31: 0 | DH31: 0 | DI31: 20527890285 | DJ31: ASOCIACION DE FRUTICULTORES DEL VALLE PAMPAS- AFRUVAP | DK31: 01 Asociación
A32: ASOCIACIÓN DE PRODUCTORES AGROPECUARIOS ORGANICOS VALLE PAMPAS - APAOVAP | B32: PALTA | C32: PALTA | D32: APURIMAC | E32: 030604 | F32: APURIMAC | G32: CHINCHEROS | H32: HUACCANA | I32: 1 | J32: 1 | K32: 1 | Q32: PAC | R32: =IF(I32=1,I$2,"")&IF(J32=1,IF(I32=1,"-","")&J$2,"")&IF(K32=1,IF(OR(J32=1,I32=1),"-","")&K$2,"")&IF(L32=1,IF(OR(K32=1,J32=1,I32=1),"-","")&L$2,"")&IF(M32=1,IF(OR(L32=1,K32=1,J32=1,I32=1),"-","")&M$2,"")&IF(N32=1,IF(OR(M32=1,L32=1,K32=1,J32=1,I32=1),"-","")&N$2,"")&IF(O32=1,IF(OR(N32=1,M32=1,L32=1,K32=1,J32=1,I32=1),"-","")&O$2,"")&IF(P32=1,IF(I32=1," - ",IF(J32=1," - ",IF(K32=1," - ",IF(L32=1," - ",IF(M32=1," - ",IF(N32=1," - ",IF(O32=1," - ","")))))))&P$2,"") | S32: =SUM('b2'!$I32:$P32) | T32: =IF(OR('b2'!$J32=1,'b2'!$K32=1,'b2'!$L32=1,'b2'!$M32=1,'b2'!$N32=1,'b2'!$O32=1,'b2'!$P32=1),"SI","NO") | U32: =IF(OR('b2'!$K32=1,'b2'!$L32=1,'b2'!$M32=1,'b2'!$N32=1,'b2'!$O32=1,'b2'!$P32=1),"SI","NO") | V32: 37 | W32: 13 | X32: 15 | Y32: 28 | Z32: 11 | AA32: 8 | AB32: 19 | AC32: 0 | AD32: 0 | AE32: 0 | AF32: 0 | AG32: 0 | AH32: 0 | AI32: 0 | AJ32: 0 | AK32: 0 | AL32: 0 | AM32: 0 | AN32: 0 | AO32: 0 | AP32: 0 | AQ32: 0 | AR32: =IF('b2'!$AQ32>0,'b2'!$AQ32,IF('b2'!$AN32>0,'b2'!$AN32,IF('b2'!$AK32>0,'b2'!$AK32,IF('b2'!$AH32>0,'b2'!$AH32,IF('b2'!$AE32>0,'b2'!$AE32,IF('b2'!$AB32>0,'b2'!$AB32,IF('b2'!$Y32>0,'b2'!$Y32,IF('b2'!$V32>0,'b2'!$V32," ---")))))))) | AS32: 0 | AT32: 2 | AU32: 0 | AV32: 0 | AW32: 0 | AX32: 0 | AY32: 0 | AZ32: 0 | BA32: 0 | BB32: 0 | BC32: 0 | BD32: 0 | BE32: 0 | BF32: 1974706.2 | BG32: 0 | BH32: 1974706.2 | BI32: #REF! | BJ32: #REF! | BK32: 58325 | BL32: 0 | BM32: 58325 | BN32: #REF! | BO32: #REF! | BP32: 0 | BQ32: 0 | BR32: 0 | BS32: #REF! | BT32: ='[2]DATA CONSOLIDADA 2018-2025 '!$BR34-'b2'!$BO32 | BU32: 0 | BV32: 0 | BW32: 0 | BX32: #REF! | BY32: #REF! | BZ32: 0 | CA32: 0 | CB32: 0 | CC32: #REF! | CD32: ='[2]DATA CONSOLIDADA 2018-2025 '!$CB34-'b2'!$BW32 | CE32: 0 | CF32: 0 | CG32: 0 | CH32: #REF! | CI32: ='[2]DATA CONSOLIDADA 2018-2025 '!$CG34-'b2'!$CB32 | CJ32: #REF! | CK32: 0 | CL32: 0 | CM32: 0 | CN32: #REF! | CO32: ='[2]DATA CONSOLIDADA 2018-2025 '!$CM34-'b2'!$CG32 | CP32: 0 | CQ32: 0 | CR32: 0 | CS32: 0 | CT32: 0 | CU32: 0 | CV32: 0 | CW32: 0 | CX32: 0 | CY32: 0 | CZ32: 0 | DA32: 0 | DB32: 0 | DC32: 0 | DD32: 0 | DE32: 0 | DF32: 0 | DG32: 0 | DH32: 0 | DI32: 20490594265 | DJ32: ASOCIACION DE PRODUCTORES AGROPECUARIOS ORGANICOS VALLE PAMPAS - APAOVAP | DK32: 01 Asociación
A33: COOPERATIVA AGROINDUSTRIAL MACHUPICCHU LTDA | B33: QUINUA Y OTROS GRANOS | C33: QUINUA | D33: APURIMAC | E33: 030213 | F33: APURIMAC | G33: ANDAHUAYLAS | H33: SAN JERONIMO | I33: 1 | J33: 1 | K33: 1 | L33: 1 | N33: 1 | P33: 1 | Q33: PAC | R33: =IF(I33=1,I$2,"")&IF(J33=1,IF(I33=1,"-","")&J$2,"")&IF(K33=1,IF(OR(J33=1,I33=1),"-","")&K$2,"")&IF(L33=1,IF(OR(K33=1,J33=1,I33=1),"-","")&L$2,"")&IF(M33=1,IF(OR(L33=1,K33=1,J33=1,I33=1),"-","")&M$2,"")&IF(N33=1,IF(OR(M33=1,L33=1,K33=1,J33=1,I33=1),"-","")&N$2,"")&IF(O33=1,IF(OR(N33=1,M33=1,L33=1,K33=1,J33=1,I33=1),"-","")&O$2,"")&IF(P33=1,IF(I33=1," - ",IF(J33=1," - ",IF(K33=1," - ",IF(L33=1," - ",IF(M33=1," - ",IF(N33=1," - ",IF(O33=1," - ","")))))))&P$2,"") | S33: =SUM('b2'!$I33:$P33) | T33: =IF(OR('b2'!$J33=1,'b2'!$K33=1,'b2'!$L33=1,'b2'!$M33=1,'b2'!$N33=1,'b2'!$O33=1,'b2'!$P33=1),"SI","NO") | U33: =IF(OR('b2'!$K33=1,'b2'!$L33=1,'b2'!$M33=1,'b2'!$N33=1,'b2'!$O33=1,'b2'!$P33=1),"SI","NO") | V33: 463 | W33: 217 | X33: 44 | Y33: 261 | Z33: 210 | AA33: 43 | AB33: 253 | AC33: 190 | AD33: 50 | AE33: 240 | AF33: 0 | AG33: 0 | AH33: 0 | AI33: 120 | AJ33: 80 | AK33: 200 | AL33: 0 | AM33: 0 | AN33: 0 | AO33: 92 | AP33: 15 | AQ33: 107 | AR33: =IF('b2'!$AQ33>0,'b2'!$AQ33,IF('b2'!$AN33>0,'b2'!$AN33,IF('b2'!$AK33>0,'b2'!$AK33,IF('b2'!$AH33>0,'b2'!$AH33,IF('b2'!$AE33>0,'b2'!$AE33,IF('b2'!$AB33>0,'b2'!$AB33,IF('b2'!$Y33>0,'b2'!$Y33,IF('b2'!$V33>0,'b2'!$V33," ---")))))))) | AS33: 0 | AT33: 7 | AU33: 22 | AV33: 4 | AW33: 0 | AX33: 0 | AY33: 25 | AZ33: 7 | BA33: 0 | BB33: 0 | BC33: 24 | BD33: 0 | BE33: 2120163.2 | BF33: 2632717.2 | BG33: 0 | BH33: 2632717.2 | BI33: #REF! | BJ33: #REF! | BK33: 1413126.6 | BL33: 951293.2 | BM33: 2364419.8 | BN33: #REF! | BO33: #REF! | BP33: 671996.57 | BQ33: 364049.58 | BR33: 1036046.2 | BS33: #REF! | BT33: ='[2]DATA CONSOLIDADA 2018-2025 '!$BR35-'b2'!$BO33 | BU33: 0 | BV33: 0 | BW33: 0 | BX33: #REF! | BY33: #REF! | BZ33: 2082623.3 | CA33: 0 | CB33: 2082623.3 | CC33: #REF! | CD33: ='[2]DATA CONSOLIDADA 2018-2025 '!$CB35-'b2'!$BW33 | CE33: 0 | CF33: 0 | CG33: 0 | CH33: #REF! | CI33: ='[2]DATA CONSOLIDADA 2018-2025 '!$CG35-'b2'!$CB33 | CJ33: #REF! | CK33: 108583.6 | CL33: 0 | CM33: 108583.6 | CN33: #REF! | CO33: ='[2]DATA CONSOLIDADA 2018-2025 '!$CM35-'b2'!$CG33 | CP33: 0 | CQ33: 0 | CR33: 0 | CS33: 2082623.3 | CT33: 0 | CU33: 0 | CV33: 2082623.3 | CW33: 0 | CX33: 0 | CY33: 0 | CZ33: 0 | DA33: 0 | DB33: 0 | DC33: 0 | DD33: 0 | DE33: 108583.6 | DF33: 0 | DG33: 0 | DH33: 108583.6 | DI33: 20490810146 | DJ33: COOPERATIVA AGRARIA MACHUPICCHU LTDA - CAGMA LTDA | DK33: 02 Cooperativa
A34: COOPERATIVA AGROINDUSTRIAL TIERRA ANDINA LTDA | B34: QUINUA Y OTROS GRANOS | C34: QUINUA | D34: APURIMAC | E34: 030201 | F34: APURIMAC | G34: ANDAHUAYLAS | H34: ANDAHUAYLAS | I34: 1 | J34: 1 | K34: 1 | L34: 1 | M34: 1 | N34: 1 | Q34: PAC | R34: =IF(I34=1,I$2,"")&IF(J34=1,IF(I34=1,"-","")&J$2,"")&IF(K34=1,IF(OR(J34=1,I34=1),"-","")&K$2,"")&IF(L34=1,IF(OR(K34=1,J34=1,I34=1),"-","")&L$2,"")&IF(M34=1,IF(OR(L34=1,K34=1,J34=1,I34=1),"-","")&M$2,"")&IF(N34=1,IF(OR(M34=1,L34=1,K34=1,J34=1,I34=1),"-","")&N$2,"")&IF(O34=1,IF(OR(N34=1,M34=1,L34=1,K34=1,J34=1,I34=1),"-","")&O$2,"")&IF(P34=1,IF(I34=1," - ",IF(J34=1," - ",IF(K34=1," - ",IF(L34=1," - ",IF(M34=1," - ",IF(N34=1," - ",IF(O34=1," - ","")))))))&P$2,"") | S34: =SUM('b2'!$I34:$P34) | T34: =IF(OR('b2'!$J34=1,'b2'!$K34=1,'b2'!$L34=1,'b2'!$M34=1,'b2'!$N34=1,'b2'!$O34=1,'b2'!$P34=1),"SI","NO") | U34: =IF(OR('b2'!$K34=1,'b2'!$L34=1,'b2'!$M34=1,'b2'!$N34=1,'b2'!$O34=1,'b2'!$P34=1),"SI","NO") | V34: 168 | W34: 93 | X34: 42 | Y34: 135 | Z34: 82 | AA34: 41 | AB34: 123 | AC34: 103 | AD34: 47 | AE34: 150 | AF34: 103 | AG34: 47 | AH34: 150 | AI34: 103 | AJ34: 47 | AK34: 150 | AL34: 0 | AM34: 0 | AN34: 0 | AO34: 0 | AP34: 0 | AQ34: 0 | AR34: =IF('b2'!$AQ34>0,'b2'!$AQ34,IF('b2'!$AN34>0,'b2'!$AN34,IF('b2'!$AK34>0,'b2'!$AK34,IF('b2'!$AH34>0,'b2'!$AH34,IF('b2'!$AE34>0,'b2'!$AE34,IF('b2'!$AB34>0,'b2'!$AB34,IF('b2'!$Y34>0,'b2'!$Y34,IF('b2'!$V34>0,'b2'!$V34," ---")))))))) | AS34: 0 | AT34: 6 | AU34: 59 | AV34: 4 | AW34: 24 | AX34: 3 | AY34: 5 | AZ34: 0 | BA34: 0 | BB34: 0 | BC34: 0 | BD34: 0 | BE34: 0 | BF34: 471229 | BG34: 0 | BH34: 471229 | BI34: #REF! | BJ34: #REF! | BK34: 1076214.4 | BL34: 0 | BM34: 1076214.4 | BN34: #REF! | BO34: #REF! | BP34: 748371.58 | BQ34: 0 | BR34: 748371.58 | BS34: #REF! | BT34: ='[2]DATA CONSOLIDADA 2018-2025 '!$BR36-'b2'!$BO34 | BU34: 0 | BV34: 0 | BW34: 0 | BX34: #REF! | BY34: #REF! | BZ34: 200004 | CA34: 0 | CB34: 200004 | CC34: #REF! | CD34: ='[2]DATA CONSOLIDADA 2018-2025 '!$CB36-'b2'!$BW34 | CE34: 0 | CF34: 0 | CG34: 0 | CH34: #REF! | CI34: ='[2]DATA CONSOLIDADA 2018-2025 '!$CG36-'b2'!$CB34 | CJ34: #REF! | CK34: 0 | CL34: 0 | CM34: 0 | CN34: #REF! | CO34: ='[2]DATA CONSOLIDADA 2018-2025 '!$CM36-'b2'!$CG34 | CP34: 0 | CQ34: 200004 | CR34: 0 | CS34: 0 | CT34: 0 | CU34: 0 | CV34: 200004 | CW34: 0 | CX34: 0 | CY34: 0 | CZ34: 0 | DA34: 0 | DB34: 0 | DC34: 0 | DD34: 0 | DE34: 0 | DF34: 0 | DG34: 0 | DH34: 0 | DI34: 20600998847 | DJ34: COOPERATIVA AGROINDUSTRIAL TIERRA ANDINA APURIMAC LTDA - CATAA LTDA | DK34: 02 Cooperativa
A35: ASOCIACIÓN DE MUJERES PRODUCTORAS DE TALLARINES DE CASA SANTO DOMINGO | B35: QUINUA Y OTROS GRANOS | C35: QUINUA | D35: APURIMAC | E35: 030101 | F35: APURIMAC | G35: ABANCAY | H35: ABANCAY | J35: 1 | K35: 1 | L35: 1 | Q35: PAC | R35: =IF(I35=1,I$2,"")&IF(J35=1,IF(I35=1,"-","")&J$2,"")&IF(K35=1,IF(OR(J35=1,I35=1),"-","")&K$2,"")&IF(L35=1,IF(OR(K35=1,J35=1,I35=1),"-","")&L$2,"")&IF(M35=1,IF(OR(L35=1,K35=1,J35=1,I35=1),"-","")&M$2,"")&IF(N35=1,IF(OR(M35=1,L35=1,K35=1,J35=1,I35=1),"-","")&N$2,"")&IF(O35=1,IF(OR(N35=1,M35=1,L35=1,K35=1,J35=1,I35=1),"-","")&O$2,"")&IF(P35=1,IF(I35=1," - ",IF(J35=1," - ",IF(K35=1," - ",IF(L35=1," - ",IF(M35=1," - ",IF(N35=1," - ",IF(O35=1," - ","")))))))&P$2,"") | S35: =SUM('b2'!$I35:$P35) | T35: =IF(OR('b2'!$J35=1,'b2'!$K35=1,'b2'!$L35=1,'b2'!$M35=1,'b2'!$N35=1,'b2'!$O35=1,'b2'!$P35=1),"SI","NO") | U35: =IF(OR('b2'!$K35=1,'b2'!$L35=1,'b2'!$M35=1,'b2'!$N35=1,'b2'!$O35=1,'b2'!$P35=1),"SI","NO") | V35: 0 | W35: 4 | X35: 6 | Y35: 10 | Z35: 8 | AA35: 17 | AB35: 25 | AC35: 8 | AD35: 17 | AE35: 25 | AF35: 0 | AG35: 0 | AH35: 0 | AI35: 0 | AJ35: 0 | AK35: 0 | AL35: 0 | AM35: 0 | AN35: 0 | AO35: 0 | AP35: 0 | AQ35: 0 | AR35: =IF('b2'!$AQ35>0,'b2'!$AQ35,IF('b2'!$AN35>0,'b2'!$AN35,IF('b2'!$AK35>0,'b2'!$AK35,IF('b2'!$AH35>0,'b2'!$AH35,IF('b2'!$AE35>0,'b2'!$AE35,IF('b2'!$AB35>0,'b2'!$AB35,IF('b2'!$Y35>0,'b2'!$Y35,IF('b2'!$V35>0,'b2'!$V35," ---")))))))) | AS35: 0 | AT35: 0 | AU35: 3 | AV35: 0 | AW35: 0 | AX35: 0 | AY35: 0 | AZ35: 0 | BA35: 0 | BB35: 0 | BC35: 0 | BD35: 0 | BE35: 0 | BF35: 48276 | BG35: 0 | BH35: 48276 | BI35: #REF! | BJ35: #REF! | BK35: 37127 | BL35: 0 | BM35: 37127 | BN35: #REF! | BO35: #REF! | BP35: 50168 | BQ35: 0 | BR35: 50168 | BS35: #REF! | BT35: ='[2]DATA CONSOLIDADA 2018-2025 '!$BR37-'b2'!$BO35 | BU35: 0 | BV35: 0 | BW35: 0 | BX35: #REF! | BY35: #REF! | BZ35: 0 | CA35: 0 | CB35: 0 | CC35: #REF! | CD35: ='[2]DATA CONSOLIDADA 2018-2025 '!$CB37-'b2'!$BW35 | CE35: 0 | CF35: 0 | CG35: 0 | CH35: #REF! | CI35: ='[2]DATA CONSOLIDADA 2018-2025 '!$CG37-'b2'!$CB35 | CJ35: #REF! | CK35: 0 | CL35: 0 | CM35: 0 | CN35: #REF! | CO35: ='[2]DATA CONSOLIDADA 2018-2025 '!$CM37-'b2'!$CG35 | CP35: 0 | CQ35: 0 | CR35: 0 | CS35: 0 | CT35: 0 | CU35: 0 | CV35: 0 | CW35: 0 | CX35: 0 | CY35: 0 | CZ35: 0 | DA35: 0 | DB35: 0 | DC35: 0 | DD35: 0 | DE35: 0 | DF35: 0 | DG35: 0 | DH35: 0 | DI35: 20490195301 | DJ35: ASOCIACION DE MUJERES PRODUCTORAS SANTO DOMINGO TALLARIN DE CASA | DK35: 01 Asociación
