Workbook

Sheet Hoja1
A1: 2 | B1: 3 | C1: 4 | D1: 7 | E1: 8 | F1: 9 | G1: 10 | H1: 11 | I1: 12 | J1: 13 | K1: 14 | L1: 15 | M1: 16 | N1: 17 | O1: 18 | P1: 19 | R1: 20 | S1: 21 | T1: 22 | V1: 23 | W1: 24 | X1: 25 | Y1: 26 | Z1: 27 | AA1: 28 | AB1: 29 | AC1: 30 | AD1: 31 | AE1: 32 | AF1: 33 | AG1: 34 | AH1: 35 | AI1: 36 | AJ1: 37 | AK1: 38 | AL1: 39 | AM1: 40 | AN1: 41 | AO1: 42 | AP1: 43 | AQ1: 44 | AR1: 45 | AS1: 46 | AT1: 47 | AU1: 48 | AV1: 49 | AW1: 50 | AX1: 51 | AY1: 52 | AZ1: 53 | BA1: 54 | BB1: 55 | BC1: 56 | BD1: 57 | BE1: 58 | BF1: 59 | BG1: 60 | BH1: 61 | BI1: 62 | BJ1: 63 | BK1: 64 | BL1: 65 | BM1: 66 | BN1: 67 | BO1: 68 | BP1: 69 | BQ1: 70 | BR1: 71 | BS1: 72 | BT1: 73 | BU1: 74 | BV1: 75 | BW1: 76 | BX1: 77 | BY1: 78 | BZ1: 79 | CA1: 80 | CB1: 81 | CC1: 82 | CD1: 83 | CE1: 84 | CF1: 85 | CG1: 86 | CH1: 87 | CI1: 88 | CJ1: 89 | CK1: 90 | CL1: 91 | CM1: 92 | CN1: 93 | CO1: 94 | CP1: 95 | CQ1: 96 | CR1: 97 | CS1: 98 | CT1: 99 | CU1: 100 | CV1: 101 | CW1: 102 | CX1: 103 | CY1: 104 | CZ1: 105 | DA1: 106 | DB1: 107 | DI1: 122 | DJ1: 123 | DK1: 124
I2: AÑOS INTERVENCIÓN | V2: BENEFICIARIOS | BE2: VENTAS HISTORIAL | CP2: VENTAS PORTIPO DE COMPROMABNTE (OBTENIDO SISPAC 2023 DEL REPORTE MATRIZ GENERAL DE VENTAS) | CW2: VENTAS POR TIPO DE COMPROMABNTE año 2024 | DC2: VENTAS POR TIPO DE COMPROMABNTE año 2025 -12.01.26)
V3: 2018 | W3: 2019 | Z3: 2020 | AC3: 2021 | AF3: 2022 | AI3: 2023 | AL3: 2024 | AO3: 2025 (Ciierre de Agosto 2025) | AS3: 2020 | AU3: 2021 | AW3: 2022 | AY3: 2023 | BA3: 2024 | BC3: 2025 (cierre agosto 2025) | BE3: 2018 | BF3: 2019 | BK3: 2020 | BP3: 2021 | BU3: 2022 | BZ3: 2023 | CE3: 2024 | CK3: 2025 (Cierre de 12.01.26) | CP3: 2023 detallado por tipo comprobante
A4: Nombre de la Organización | B4: PRODUCTO DOM | C4: PRODUCTO 1 | D4: SEDE | E4: Ubigeo | F4: DEPARTAMENTO | G4: Provincia | H4: Distrito | I4: 2018 | J4: 2019 | K4: 2020 | L4: 2021 | M4: 2022 | N4: 2023 | O4: 2024 | P4: 2025 | Q4: SERVICIO | R4: AÑOS DE INTERVENCION | S4: AÑOS DE INTERVENCIÓN DESDE 2018 AL 2024 | T4: INTERVENCIÓN 2019 al 2025 | U4: INTERVENCIÓN 2020 al 2026 | V4: TOTAL BENF 2018 | W4: BENF MASC 2019 | X4: BENF FEM 2019 | Y4: TOTAL BENF 2019 | Z4: BENF MASC 2020 | AA4: BENF FEM 2020 | AB4: TOTAL BENF 2020 | AC4: BENF MASC 2021 | AD4: BENF FEM 2021 | AE4: TOTAL BENF 2021 | AF4: BENF MASC 2022 | AG4: BENF FEM 2022 | AH4: TOTAL BENF 2022 | AI4: BENF MASC 2023 | AJ4: BENF FEM 2023 | AK4: TOTAL BENF 2023 | AL4: BENF MASC 2024 | AM4: BENF FEM 2024 | AN4: TOTAL BENF 2024 | AO4: BENF MASC 2025 | AP4: BENF FEM 2025 | AQ4: TOTAL BENF 2025 | AR4: BENEFICIADOS ULTIMO AÑO | AS4: ASISTENCIA TÉCNICA 2020 | AT4: TALLERES 2020 | AU4: ASISTENCIA TÉCNICA 2021 | AV4: TALLERES 2021 | AW4: ASISTENCIA TÉCNICA 2022 | AX4: TALLERES 2022 | AY4: ASISTENCIA TÉCNICA 2023 | AZ4: TALLERES 2023 | BA4: ASISTENCIA TÉCNICA 2024 | BB4: TALLERES 2024 | BC4: ASISTENCIA TÉCNICA 2025 | BD4: TALLERES 2025 | BE4: VENTAS TOTALES 2018 | BF4: VENTAS NACIONALES 2019 | BG4: VENTAS INTERNACIONALES 2019 | BH4: VENTAS TOTALES 2019 | BI4: INCREMENTOS VENTAS EN 2019 | BJ4: INCREMENTOS VENTAS EN 20192 | BK4: VENTAS NACIONALES 2020 | BL4: VENTAS INTERNACIONALES 2020 | BM4: VENTAS TOTALES 2020 | BN4: INCREMENTOS VENTAS EN 2020 | BO4: DIFERENCIA VENTA 2020-2019 | BP4: VENTAS NACIONALES 2021 | BQ4: VENTAS INTERNACIONALES 2021 | BR4: VENTAS TOTALES 2021 | BS4: INCREMENTOS VENTAS EN 20201 | BT4: DIFERENCIA VENTA 2021-2020 | BU4: V. EJEC NACIONALES 2022 | BV4: V. EJEC EXPORTACION 2022 | BW4: VENTAS TOTALES 2022 | BX4: INCREMENTOS VENTAS EN 22022 | BY4: DIFERENCIA VENTAS 2022-2021 | BZ4: V. EJEC NACIONALES 2023 | CA4: V. EJEC EXPORTACION 2023 | CB4: VENTAS TOTALES 2023 | CC4: INCREMENTOS VENTAS EN 2023 | CD4: DIFERENCIA VENTAS 2023-2022 | CE4: V. EJEC NACIONALES 2024 | CF4: V. EJEC EXPORTACION 2024 | CG4: VENTAS TOTALES 20224 | CH4: INCREMENTOS VENTAS EN 2024 | CI4: DIFERENCIA VENTAS 2024-2023 | CJ4: TOTAL VENTAS 2018 AL 2025 | CK4: V. EJEC NACIONALES 2025 | CL4: V. EJEC EXPORTACION 2025 | CM4: VENTAS TOTALES 2025 | CN4: INCREMENTOS VENTAS EN 2025 | CO4: DIFERENCIA VENTAS 2025-2024 | CP4: Boleta de Venta 2023 | CQ4: Declaracion Jurada 2023 | CR4: Documento de Entrega Cooperativo (DEC) 2023 | CS4: Factura 2023 | CT4: Guia de Remision 2023 | CU4: Liquidacion de Compra 2023 | CV4: Total Ventas 2023 (De comprobantes) (*) | CW4: Boleta de Venta 2024 | CX4: Declaración Jurada 2024 | CY4: Factura 2024 | CZ4: Guía de Remisión 2024 | DA4: Liquidación de Compra 2024 | DB4: Total general 2024 | DC4: Boleta de Venta 2025 | DD4: Declaración Jurada 2025 | DE4: Factura 2025 | DF4: Guía de Remisión 2025 | DG4: Liquidación de Compra 2025 | DH4: Total general 2025 | DI4: RUC | DJ4: NOMBRE SUNAT | DK4: Tipo de Organización* (Asociación/Cooperativa/CCNN, Comunidad Campesina y otros.)
A5: COOPERATIVA AGRARIA CAFETALERA MONTAÑA AZUL LTDA. - COOPACMA | B5: CAFÉ | C5: CAFÉ | D5: AMAZONAS | E5: 010706 | F5: AMAZONAS | G5: UTCUBAMBA | H5: LONYA GRANDE | I5: 1 | J5: 1 | K5: 1 | Q5: PAC | R5: =IF(I5=1, I$4, "") & IF(J5=1, IF(I5=1, "-", "") & J$4, "") & IF(K5=1, IF(OR(J5=1, I5=1), "-", "") & K$4, "") & IF(L5=1, IF(OR(K5=1, J5=1, I5=1), "-", "") & L$4, "") & IF(M5=1, IF(OR(L5=1, K5=1, J5=1, I5=1), "-", "") & M$4, "") & IF(N5=1, IF(OR(M5=1, L5=1, K5=1, J5=1, I5=1), "-", "") & N$4, "") & IF(O5=1, IF(OR(N5=1, M5=1, L5=1, K5=1, J5=1, I5=1), "-", "") & O$4, "") & IF(P5=1, IF(I5=1, " - ", IF(J5=1, " - ", IF(K5=1, " - ", IF(L5=1, " - ", IF(M5=1, " - ", IF(N5=1, " - ", IF(O5=1, " - ", ""))))))) & P$4, "") -> 2018-2019-2020 | S5: =SUM(Hoja1!$I5:$P5) -> 3 | T5: =IF(OR(Hoja1!$J5=1,Hoja1!$K5=1,Hoja1!$L5=1,Hoja1!$M5=1,Hoja1!$N5=1,Hoja1!$O5=1,Hoja1!$P5=1),"SI","NO") -> SI | U5: =IF(OR(Hoja1!$K5=1,Hoja1!$L5=1,Hoja1!$M5=1,Hoja1!$N5=1,Hoja1!$O5=1,Hoja1!$P5=1),"SI","NO") -> SI | V5: 106 | W5: 72 | X5: 34 | Y5: 106 | Z5: 68 | AA5: 31 | AB5: 99 | AC5: 0 | AD5: 0 | AE5: 0 | AF5: 0 | AG5: 0 | AH5: 0 | AI5: 0 | AJ5: 0 | AK5: 0 | AL5: 0 | AM5: 0 | AN5: 0 | AO5: 0 | AP5: 0 | AQ5: 0 | AR5: =IF(Hoja1!$AQ5>0,Hoja1!$AQ5,IF(Hoja1!$AN5>0,Hoja1!$AN5,IF(Hoja1!$AK5>0,Hoja1!$AK5,IF(Hoja1!$AH5>0,Hoja1!$AH5,IF(Hoja1!$AE5>0,Hoja1!$AE5,IF(Hoja1!$AB5>0,Hoja1!$AB5,IF(Hoja1!$Y5>0,Hoja1!$Y5,IF(Hoja1!$V5>0,Hoja1!$V5," ---")))))))) -> 99 | AS5: 0 | AT5: 9 | AU5: 0 | AV5: 0 | AW5: 0 | AX5: 0 | AY5: 0 | AZ5: 0 | BA5: 0 | BB5: 0 | BC5: 0 | BD5: 0 | BE5: 0 | BF5: 0 | BG5: 83583.84 | BH5: 83583.84 | BI5: =IF('[1]DATA CONSOLIDADA 2018-2025 '!$BH5>'[1]DATA CONSOLIDADA 2018-2025 '!$AN5,"Incremento",IF('[1]DATA CONSOLIDADA 2018-2025 '!$AN5='[1]DATA CONSOLIDADA 2018-2025 '!$BH5,"Sin incremento",IF('[1]DATA CONSOLIDADA 2018-2025 '!$BH5<'[1]DATA CONSOLIDADA 2018-2025 '!$AN5,"Disminución"," ---"))) -> #REF! | BJ5: ='[1]DATA CONSOLIDADA 2018-2025 '!$BH5-'[1]DATA CONSOLIDADA 2018-2025 '!$BE5 -> #REF! | BK5: 3460.24 | BL5: 0 | BM5: 3460.24 | BN5: =IF('[1]DATA CONSOLIDADA 2018-2025 '!$BM5>'[1]DATA CONSOLIDADA 2018-2025 '!$BH5,"Incremento",IF('[1]DATA CONSOLIDADA 2018-2025 '!$BH5='[1]DATA CONSOLIDADA 2018-2025 '!$BM5,"Sin incremento",IF('[1]DATA CONSOLIDADA 2018-2025 '!$BM5<'[1]DATA CONSOLIDADA 2018-2025 '!$BH5,"Disminución"," ---"))) -> #REF! | BO5: ='[1]DATA CONSOLIDADA 2018-2025 '!$BM5-'[1]DATA CONSOLIDADA 2018-2025 '!$BH5 -> #REF! | BP5: 0 | BQ5: 0 | BR5: 0 | BS5: =IF('[1]DATA CONSOLIDADA 2018-2025 '!$BR5>'[1]DATA CONSOLIDADA 2018-2025 '!$BM5,"Incremento",IF('[1]DATA CONSOLIDADA 2018-2025 '!$BM5='[1]DATA CONSOLIDADA 2018-2025 '!$BR5,"Sin incremento",IF('[1]DATA CONSOLIDADA 2018-2025 '!$BR5<'[1]DATA CONSOLIDADA 2018-2025 '!$BM5,"Disminución"," ---"))) -> #REF! | BT5: ='[1]DATA CONSOLIDADA 2018-2025 '!$BR5-Hoja1!$BO5 -> #REF! | BU5: 0 | BV5: 0 | BW5: 0 | BX5: =IF('[1]DATA CONSOLIDADA 2018-2025 '!$BW5>'[1]DATA CONSOLIDADA 2018-2025 '!$BR5,"Incremento",IF('[1]DATA CONSOLIDADA 2018-2025 '!$BR5='[1]DATA CONSOLIDADA 2018-2025 '!$BW5,"Sin incremento",IF('[1]DATA CONSOLIDADA 2018-2025 '!$BW5<'[1]DATA CONSOLIDADA 2018-2025 '!$BR5,"Disminución"," ---"))) -> #REF! | BY5: ='[1]DATA CONSOLIDADA 2018-2025 '!$BW5-'[1]DATA CONSOLIDADA 2018-2025 '!$BR5 -> #REF! | BZ5: 0 | CA5: 0 | CB5: 0 | CC5: =IF('[1]DATA CONSOLIDADA 2018-2025 '!$CB5>'[1]DATA CONSOLIDADA 2018-2025 '!$BW5,"Incremento",IF('[1]DATA CONSOLIDADA 2018-2025 '!$BW5='[1]DATA CONSOLIDADA 2018-2025 '!$CB5,"Sin incremento",IF('[1]DATA CONSOLIDADA 2018-2025 '!$CB5<'[1]DATA CONSOLIDADA 2018-2025 '!$BW5,"Disminución"," ---"))) -> #REF! | CD5: ='[1]DATA CONSOLIDADA 2018-2025 '!$CB5-Hoja1!$BW5 -> #REF! | CE5: 0 | CF5: 0 | CG5: 0 | CH5: =IF('[1]DATA CONSOLIDADA 2018-2025 '!$CG5>'[1]DATA CONSOLIDADA 2018-2025 '!$CB5,"Incremento",IF('[1]DATA CONSOLIDADA 2018-2025 '!$CB5='[1]DATA CONSOLIDADA 2018-2025 '!$CG5,"Sin incremento",IF('[1]DATA CONSOLIDADA 2018-2025 '!$CG5<'[1]DATA CONSOLIDADA 2018-2025 '!$CB5,"Disminución"," ---"))) -> #REF! | CI5: ='[1]DATA CONSOLIDADA 2018-2025 '!$CG5-Hoja1!$CB5 -> #REF! | CJ5: ='[1]DATA CONSOLIDADA 2018-2025 '!$BE5+'[1]DATA CONSOLIDADA 2018-2025 '!$BH5+'[1]DATA CONSOLIDADA 2018-2025 '!$BM5+'[1]DATA CONSOLIDADA 2018-2025 '!$BR5+'[1]DATA CONSOLIDADA 2018-2025 '!$BW5+'[1]DATA CONSOLIDADA 2018-2025 '!$CB5+'[1]DATA CONSOLIDADA 2018-2025 '!$CG5 -> #REF! | CK5: 0 | CL5: 0 | CM5: 0 | CN5: =IF('[1]DATA CONSOLIDADA 2018-2025 '!$CM5>'[1]DATA CONSOLIDADA 2018-2025 '!$CG5,"Incremento",IF('[1]DATA CONSOLIDADA 2018-2025 '!$CG5='[1]DATA CONSOLIDADA 2018-2025 '!$CM5,"Sin incremento",IF('[1]DATA CONSOLIDADA 2018-2025 '!$CM5<'[1]DATA CONSOLIDADA 2018-2025 '!$CG5,"Disminución"," ---"))) -> #REF! | CO5: ='[1]DATA CONSOLIDADA 2018-2025 '!$CM5-Hoja1!$CG5 -> #REF! | CP5: 0 | CQ5: 0 | CR5: 0 | CS5: 0 | CT5: 0 | CU5: 0 | CV5: 0 | CW5: 0 | CX5: 0 | CY5: 0 | CZ5: 0 | DA5: 0 | DB5: 0 | DC5: 0 | DD5: 0 | DE5: 0 | DF5: 0 | DG5: 0 | DH5: 0 | DI5: 20600200756 | DJ5: COOPERATIVA AGRARIA CAFETALERA MONTAÑA AZUL LTDA. - COOPACMA | DK5: 02 Cooperativa
A6: ASOCIACIÓN DE PRODUCTORES DE CAFÉ ORGANICO Y CAFES ESPECIALES -APROCOYCE AMAZONAS | B6: CAFÉ | C6: CAFÉ | D6: AMAZONAS | E6: 010601 | F6: AMAZONAS | G6: RODRIGUEZ DE MENDOZA | H6: SAN NICOLAS | J6: 1 | K6: 1 | L6: 1 | M6: 1 | N6: 1 | Q6: PAC | R6: =IF(I6=1, I$4, "") & IF(J6=1, IF(I6=1, "-", "") & J$4, "") & IF(K6=1, IF(OR(J6=1, I6=1), "-", "") & K$4, "") & IF(L6=1, IF(OR(K6=1, J6=1, I6=1), "-", "") & L$4, "") & IF(M6=1, IF(OR(L6=1, K6=1, J6=1, I6=1), "-", "") & M$4, "") & IF(N6=1, IF(OR(M6=1, L6=1, K6=1, J6=1, I6=1), "-", "") & N$4, "") & IF(O6=1, IF(OR(N6=1, M6=1, L6=1, K6=1, J6=1, I6=1), "-", "") & O$4, "") & IF(P6=1, IF(I6=1, " - ", IF(J6=1, " - ", IF(K6=1, " - ", IF(L6=1, " - ", IF(M6=1, " - ", IF(N6=1, " - ", IF(O6=1, " - ", ""))))))) & P$4, "") -> 2019-2020-2021-2022-2023 | S6: =SUM(Hoja1!$I6:$P6) -> 5 | T6: =IF(OR(Hoja1!$J6=1,Hoja1!$K6=1,Hoja1!$L6=1,Hoja1!$M6=1,Hoja1!$N6=1,Hoja1!$O6=1,Hoja1!$P6=1),"SI","NO") -> SI | U6: =IF(OR(Hoja1!$K6=1,Hoja1!$L6=1,Hoja1!$M6=1,Hoja1!$N6=1,Hoja1!$O6=1,Hoja1!$P6=1),"SI","NO") -> SI | V6: 0 | W6: 50 | X6: 33 | Y6: 83 | Z6: 222 | AA6: 135 | AB6: 357 | AC6: 208 | AD6: 150 | AE6: 358 | AF6: 208 | AG6: 150 | AH6: 358 | AI6: 208 | AJ6: 150 | AK6: 358 | AL6: 0 | AM6: 0 | AN6: 0 | AO6: 0 | AP6: 0 | AQ6: 0 | AR6: =IF(Hoja1!$AQ6>0,Hoja1!$AQ6,IF(Hoja1!$AN6>0,Hoja1!$AN6,IF(Hoja1!$AK6>0,Hoja1!$AK6,IF(Hoja1!$AH6>0,Hoja1!$AH6,IF(Hoja1!$AE6>0,Hoja1!$AE6,IF(Hoja1!$AB6>0,Hoja1!$AB6,IF(Hoja1!$Y6>0,Hoja1!$Y6,IF(Hoja1!$V6>0,Hoja1!$V6," ---")))))))) -> 358 | AS6: 0 | AT6: 0 | AU6: 27 | AV6: 8 | AW6: 41 | AX6: 7 | AY6: 32 | AZ6: 6 | BA6: 0 | BB6: 0 | BC6: 0 | BD6: 0 | BE6: 0 | BF6: 4171009.2 | BG6: 0 | BH6: 4171009.2 | BI6: =IF('[1]DATA CONSOLIDADA 2018-2025 '!$BH6>'[1]DATA CONSOLIDADA 2018-2025 '!$AN6,"Incremento",IF('[1]DATA CONSOLIDADA 2018-2025 '!$AN6='[1]DATA CONSOLIDADA 2018-2025 '!$BH6,"Sin incremento",IF('[1]DATA CONSOLIDADA 2018-2025 '!$BH6<'[1]DATA CONSOLIDADA 2018-2025 '!$AN6,"Disminución"," ---"))) -> #REF! | BJ6: ='[1]DATA CONSOLIDADA 2018-2025 '!$BH6-'[1]DATA CONSOLIDADA 2018-2025 '!$BE6 -> #REF! | BK6: 741888.91 | BL6: 0 | BM6: 741888.91 | BN6: =IF('[1]DATA CONSOLIDADA 2018-2025 '!$BM6>'[1]DATA CONSOLIDADA 2018-2025 '!$BH6,"Incremento",IF('[1]DATA CONSOLIDADA 2018-2025 '!$BH6='[1]DATA CONSOLIDADA 2018-2025 '!$BM6,"Sin incremento",IF('[1]DATA CONSOLIDADA 2018-2025 '!$BM6<'[1]DATA CONSOLIDADA 2018-2025 '!$BH6,"Disminución"," ---"))) -> #REF! | BO6: ='[1]DATA CONSOLIDADA 2018-2025 '!$BM6-'[1]DATA CONSOLIDADA 2018-2025 '!$BH6 -> #REF! | BP6: 4099294.7 | BQ6: 0 | BR6: 4099294.7 | BS6: =IF('[1]DATA CONSOLIDADA 2018-2025 '!$BR6>'[1]DATA CONSOLIDADA 2018-2025 '!$BM6,"Incremento",IF('[1]DATA CONSOLIDADA 2018-2025 '!$BM6='[1]DATA CONSOLIDADA 2018-2025 '!$BR6,"Sin incremento",IF('[1]DATA CONSOLIDADA 2018-2025 '!$BR6<'[1]DATA CONSOLIDADA 2018-2025 '!$BM6,"Disminución"," ---"))) -> #REF! | BT6: ='[1]DATA CONSOLIDADA 2018-2025 '!$BR6-Hoja1!$BO6 -> #REF! | BU6: 1820885 | BV6: 0 | BW6: 1820885 | BX6: =IF('[1]DATA CONSOLIDADA 2018-2025 '!$BW6>'[1]DATA CONSOLIDADA 2018-2025 '!$BR6,"Incremento",IF('[1]DATA CONSOLIDADA 2018-2025 '!$BR6='[1]DATA CONSOLIDADA 2018-2025 '!$BW6,"Sin incremento",IF('[1]DATA CONSOLIDADA 2018-2025 '!$BW6<'[1]DATA CONSOLIDADA 2018-2025 '!$BR6,"Disminución"," ---"))) -> #REF! | BY6: ='[1]DATA CONSOLIDADA 2018-2025 '!$BW6-'[1]DATA CONSOLIDADA 2018-2025 '!$BR6 -> #REF! | BZ6: 4179472.3 | CA6: 0 | CB6: 4179472.3 | CC6: =IF('[1]DATA CONSOLIDADA 2018-2025 '!$CB6>'[1]DATA CONSOLIDADA 2018-2025 '!$BW6,"Incremento",IF('[1]DATA CONSOLIDADA 2018-2025 '!$BW6='[1]DATA CONSOLIDADA 2018-2025 '!$CB6,"Sin incremento",IF('[1]DATA CONSOLIDADA 2018-2025 '!$CB6<'[1]DATA CONSOLIDADA 2018-2025 '!$BW6,"Disminución"," ---"))) -> #REF! | CD6: ='[1]DATA CONSOLIDADA 2018-2025 '!$CB6-Hoja1!$BW6 -> #REF! | CE6: 0 | CF6: 0 | CG6: 0 | CH6: =IF('[1]DATA CONSOLIDADA 2018-2025 '!$CG6>'[1]DATA CONSOLIDADA 2018-2025 '!$CB6,"Incremento",IF('[1]DATA CONSOLIDADA 2018-2025 '!$CB6='[1]DATA CONSOLIDADA 2018-2025 '!$CG6,"Sin incremento",IF('[1]DATA CONSOLIDADA 2018-2025 '!$CG6<'[1]DATA CONSOLIDADA 2018-2025 '!$CB6,"Disminución"," ---"))) -> #REF! | CI6: ='[1]DATA CONSOLIDADA 2018-2025 '!$CG6-Hoja1!$CB6 -> #REF! | CJ6: ='[1]DATA CONSOLIDADA 2018-2025 '!$BE6+'[1]DATA CONSOLIDADA 2018-2025 '!$BH6+'[1]DATA CONSOLIDADA 2018-2025 '!$BM6+'[1]DATA CONSOLIDADA 2018-2025 '!$BR6+'[1]DATA CONSOLIDADA 2018-2025 '!$BW6+'[1]DATA CONSOLIDADA 2018-2025 '!$CB6+'[1]DATA CONSOLIDADA 2018-2025 '!$CG6 -> #REF! | CK6: 0 | CL6: 0 | CM6: 0 | CN6: =IF('[1]DATA CONSOLIDADA 2018-2025 '!$CM6>'[1]DATA CONSOLIDADA 2018-2025 '!$CG6,"Incremento",IF('[1]DATA CONSOLIDADA 2018-2025 '!$CG6='[1]DATA CONSOLIDADA 2018-2025 '!$CM6,"Sin incremento",IF('[1]DATA CONSOLIDADA 2018-2025 '!$CM6<'[1]DATA CONSOLIDADA 2018-2025 '!$CG6,"Disminución"," ---"))) -> #REF! | CO6: ='[1]DATA CONSOLIDADA 2018-2025 '!$CM6-Hoja1!$CG6 -> #REF! | CP6: 0 | CQ6: 0 | CR6: 0 | CS6: 4179472.3 | CT6: 0 | CU6: 0 | CV6: 4179472.3 | CW6: 0 | CX6: 0 | CY6: 0 | CZ6: 0 | DA6: 0 | DB6: 0 | DC6: 0 | DD6: 0 | DE6: 0 | DF6: 0 | DG6: 0 | DH6: 0 | DI6: 20539241665 | DJ6: ASOCIACION DE PRODUCTORES DE CAFES ORGANICOS Y CAFES ESPECIALES DE AMAZONAS | DK6: 01 Asociación
A7: ASOCIACIÓN DE PRODUCTORES Y EXPORTADORES DE CAFÉ RODRIGUEZ DE MENDOZA-APROEXPORT | B7: CAFÉ | C7: CAFÉ | D7: AMAZONAS | E7: 010601 | F7: AMAZONAS | G7: RODRIGUEZ DE MENDOZA | H7: SAN NICOLAS | J7: 1 | Q7: PAC | R7: =IF(I7=1, I$4, "") & IF(J7=1, IF(I7=1, "-", "") & J$4, "") & IF(K7=1, IF(OR(J7=1, I7=1), "-", "") & K$4, "") & IF(L7=1, IF(OR(K7=1, J7=1, I7=1), "-", "") & L$4, "") & IF(M7=1, IF(OR(L7=1, K7=1, J7=1, I7=1), "-", "") & M$4, "") & IF(N7=1, IF(OR(M7=1, L7=1, K7=1, J7=1, I7=1), "-", "") & N$4, "") & IF(O7=1, IF(OR(N7=1, M7=1, L7=1, K7=1, J7=1, I7=1), "-", "") & O$4, "") & IF(P7=1, IF(I7=1, " - ", IF(J7=1, " - ", IF(K7=1, " - ", IF(L7=1, " - ", IF(M7=1, " - ", IF(N7=1, " - ", IF(O7=1, " - ", ""))))))) & P$4, "") -> 2019 | S7: =SUM(Hoja1!$I7:$P7) -> 1 | T7: =IF(OR(Hoja1!$J7=1,Hoja1!$K7=1,Hoja1!$L7=1,Hoja1!$M7=1,Hoja1!$N7=1,Hoja1!$O7=1,Hoja1!$P7=1),"SI","NO") -> SI | U7: =IF(OR(Hoja1!$K7=1,Hoja1!$L7=1,Hoja1!$M7=1,Hoja1!$N7=1,Hoja1!$O7=1,Hoja1!$P7=1),"SI","NO") -> NO | V7: 0 | W7: 231 | X7: 149 | Y7: 380 | Z7: 0 | AA7: 0 | AB7: 0 | AC7: 0 | AD7: 0 | AE7: 0 | AF7: 0 | AG7: 0 | AH7: 0 | AI7: 0 | AJ7: 0 | AK7: 0 | AL7: 0 | AM7: 0 | AN7: 0 | AO7: 0 | AP7: 0 | AQ7: 0 | AR7: =IF(Hoja1!$AQ7>0,Hoja1!$AQ7,IF(Hoja1!$AN7>0,Hoja1!$AN7,IF(Hoja1!$AK7>0,Hoja1!$AK7,IF(Hoja1!$AH7>0,Hoja1!$AH7,IF(Hoja1!$AE7>0,Hoja1!$AE7,IF(Hoja1!$AB7>0,Hoja1!$AB7,IF(Hoja1!$Y7>0,Hoja1!$Y7,IF(Hoja1!$V7>0,Hoja1!$V7," ---")))))))) -> 380 | AS7: 0 | AT7: 0 | AU7: 0 | AV7: 0 | AW7: 0 | AX7: 0 | AY7: 0 | AZ7: 0 | BA7: 0 | BB7: 0 | BC7: 0 | BD7: 0 | BE7: 0 | BF7: 0 | BG7: 0 | BH7: 0 | BI7: =IF('[1]DATA CONSOLIDADA 2018-2025 '!$BH7>'[1]DATA CONSOLIDADA 2018-2025 '!$AN7,"Incremento",IF('[1]DATA CONSOLIDADA 2018-2025 '!$AN7='[1]DATA CONSOLIDADA 2018-2025 '!$BH7,"Sin incremento",IF('[1]DATA CONSOLIDADA 2018-2025 '!$BH7<'[1]DATA CONSOLIDADA 2018-2025 '!$AN7,"Disminución"," ---"))) -> #REF! | BJ7: ='[1]DATA CONSOLIDADA 2018-2025 '!$BH7-'[1]DATA CONSOLIDADA 2018-2025 '!$BE7 -> #REF! | BK7: 0 | BL7: 0 | BM7: 0 | BN7: =IF('[1]DATA CONSOLIDADA 2018-2025 '!$BM7>'[1]DATA CONSOLIDADA 2018-2025 '!$BH7,"Incremento",IF('[1]DATA CONSOLIDADA 2018-2025 '!$BH7='[1]DATA CONSOLIDADA 2018-2025 '!$BM7,"Sin incremento",IF('[1]DATA CONSOLIDADA 2018-2025 '!$BM7<'[1]DATA CONSOLIDADA 2018-2025 '!$BH7,"Disminución"," ---"))) -> #REF! | BO7: ='[1]DATA CONSOLIDADA 2018-2025 '!$BM7-'[1]DATA CONSOLIDADA 2018-2025 '!$BH7 -> #REF! | BP7: 0 | BQ7: 0 | BR7: 0 | BS7: =IF('[1]DATA CONSOLIDADA 2018-2025 '!$BR7>'[1]DATA CONSOLIDADA 2018-2025 '!$BM7,"Incremento",IF('[1]DATA CONSOLIDADA 2018-2025 '!$BM7='[1]DATA CONSOLIDADA 2018-2025 '!$BR7,"Sin incremento",IF('[1]DATA CONSOLIDADA 2018-2025 '!$BR7<'[1]DATA CONSOLIDADA 2018-2025 '!$BM7,"Disminución"," ---"))) -> #REF! | BT7: ='[1]DATA CONSOLIDADA 2018-2025 '!$BR7-Hoja1!$BO7 -> #REF! | BU7: 0 | BV7: 0 | BW7: 0 | BX7: =IF('[1]DATA CONSOLIDADA 2018-2025 '!$BW7>'[1]DATA CONSOLIDADA 2018-2025 '!$BR7,"Incremento",IF('[1]DATA CONSOLIDADA 2018-2025 '!$BR7='[1]DATA CONSOLIDADA 2018-2025 '!$BW7,"Sin incremento",IF('[1]DATA CONSOLIDADA 2018-2025 '!$BW7<'[1]DATA CONSOLIDADA 2018-2025 '!$BR7,"Disminución"," ---"))) -> #REF! | BY7: ='[1]DATA CONSOLIDADA 2018-2025 '!$BW7-'[1]DATA CONSOLIDADA 2018-2025 '!$BR7 -> #REF! | BZ7: 0 | CA7: 0 | CB7: 0 | CC7: =IF('[1]DATA CONSOLIDADA 2018-2025 '!$CB7>'[1]DATA CONSOLIDADA 2018-2025 '!$BW7,"Incremento",IF('[1]DATA CONSOLIDADA 2018-2025 '!$BW7='[1]DATA CONSOLIDADA 2018-2025 '!$CB7,"Sin incremento",IF('[1]DATA CONSOLIDADA 2018-2025 '!$CB7<'[1]DATA CONSOLIDADA 2018-2025 '!$BW7,"Disminución"," ---"))) -> #REF! | CD7: ='[1]DATA CONSOLIDADA 2018-2025 '!$CB7-Hoja1!$BW7 -> #REF! | CE7: 0 | CF7: 0 | CG7: 0 | CH7: =IF('[1]DATA CONSOLIDADA 2018-2025 '!$CG7>'[1]DATA CONSOLIDADA 2018-2025 '!$CB7,"Incremento",IF('[1]DATA CONSOLIDADA 2018-2025 '!$CB7='[1]DATA CONSOLIDADA 2018-2025 '!$CG7,"Sin incremento",IF('[1]DATA CONSOLIDADA 2018-2025 '!$CG7<'[1]DATA CONSOLIDADA 2018-2025 '!$CB7,"Disminución"," ---"))) -> #REF! | CI7: ='[1]DATA CONSOLIDADA 2018-2025 '!$CG7-Hoja1!$CB7 -> #REF! | CJ7: ='[1]DATA CONSOLIDADA 2018-2025 '!$BE7+'[1]DATA CONSOLIDADA 2018-2025 '!$BH7+'[1]DATA CONSOLIDADA 2018-2025 '!$BM7+'[1]DATA CONSOLIDADA 2018-2025 '!$BR7+'[1]DATA CONSOLIDADA 2018-2025 '!$BW7+'[1]DATA CONSOLIDADA 2018-2025 '!$CB7+'[1]DATA CONSOLIDADA 2018-2025 '!$CG7 -> #REF! | CK7: 0 | CL7: 0 | CM7: 0 | CN7: =IF('[1]DATA CONSOLIDADA 2018-2025 '!$CM7>'[1]DATA CONSOLIDADA 2018-2025 '!$CG7,"Incremento",IF('[1]DATA CONSOLIDADA 2018-2025 '!$CG7='[1]DATA CONSOLIDADA 2018-2025 '!$CM7,"Sin incremento",IF('[1]DATA CONSOLIDADA 2018-2025 '!$CM7<'[1]DATA CONSOLIDADA 2018-2025 '!$CG7,"Disminución"," ---"))) -> #REF! | CO7: ='[1]DATA CONSOLIDADA 2018-2025 '!$CM7-Hoja1!$CG7 -> #REF! | CP7: 0 | CQ7: 0 | CR7: 0 | CS7: 0 | CT7: 0 | CU7: 0 | CV7: 0 | CW7: 0 | CX7: 0 | CY7: 0 | CZ7: 0 | DA7: 0 | DB7: 0 | DC7: 0 | DD7: 0 | DE7: 0 | DF7: 0 | DG7: 0 | DH7: 0 | DI7: 20539205600 | DJ7: ASOCIACION DE PRODUCTORES Y EXPORTADORES DE CAFE RODRIGUEZ DE MENDOZA | DK7: 01 Asociación
A8: COOPERATIVA AGRARIA CAFETALERA ALTA MONTAÑA | B8: CAFÉ | C8: CAFÉ | D8: AMAZONAS | E8: 010604 | F8: AMAZONAS | G8: RODRIGUEZ DE MENDOZA | H8: HUAMBO | I8: 1 | J8: 1 | K8: 1 | L8: 1 | M8: 1 | N8: 1 | Q8: PAC | R8: =IF(I8=1, I$4, "") & IF(J8=1, IF(I8=1, "-", "") & J$4, "") & IF(K8=1, IF(OR(J8=1, I8=1), "-", "") & K$4, "") & IF(L8=1, IF(OR(K8=1, J8=1, I8=1), "-", "") & L$4, "") & IF(M8=1, IF(OR(L8=1, K8=1, J8=1, I8=1), "-", "") & M$4, "") & IF(N8=1, IF(OR(M8=1, L8=1, K8=1, J8=1, I8=1), "-", "") & N$4, "") & IF(O8=1, IF(OR(N8=1, M8=1, L8=1, K8=1, J8=1, I8=1), "-", "") & O$4, "") & IF(P8=1, IF(I8=1, " - ", IF(J8=1, " - ", IF(K8=1, " - ", IF(L8=1, " - ", IF(M8=1, " - ", IF(N8=1, " - ", IF(O8=1, " - ", ""))))))) & P$4, "") -> 2018-2019-2020-2021-2022-2023 | S8: =SUM(Hoja1!$I8:$P8) -> 6 | T8: =IF(OR(Hoja1!$J8=1,Hoja1!$K8=1,Hoja1!$L8=1,Hoja1!$M8=1,Hoja1!$N8=1,Hoja1!$O8=1,Hoja1!$P8=1),"SI","NO") -> SI | U8: =IF(OR(Hoja1!$K8=1,Hoja1!$L8=1,Hoja1!$M8=1,Hoja1!$N8=1,Hoja1!$O8=1,Hoja1!$P8=1),"SI","NO") -> SI | V8: 150 | W8: 0 | X8: 0 | Y8: 0 | Z8: 108 | AA8: 42 | AB8: 150 | AC8: 205 | AD8: 119 | AE8: 324 | AF8: 205 | AG8: 119 | AH8: 324 | AI8: 205 | AJ8: 119 | AK8: 324 | AL8: 0 | AM8: 0 | AN8: 0 | AO8: 0 | AP8: 0 | AQ8: 0 | AR8: =IF(Hoja1!$AQ8>0,Hoja1!$AQ8,IF(Hoja1!$AN8>0,Hoja1!$AN8,IF(Hoja1!$AK8>0,Hoja1!$AK8,IF(Hoja1!$AH8>0,Hoja1!$AH8,IF(Hoja1!$AE8>0,Hoja1!$AE8,IF(Hoja1!$AB8>0,Hoja1!$AB8,IF(Hoja1!$Y8>0,Hoja1!$Y8,IF(Hoja1!$V8>0,Hoja1!$V8," ---")))))))) -> 324 | AS8: 0 | AT8: 0 | AU8: 25 | AV8: 9 | AW8: 41 | AX8: 7 | AY8: 32 | AZ8: 6 | BA8: 0 | BB8: 0 | BC8: 0 | BD8: 0 | BE8: 0 | BF8: 409100 | BG8: 0 | BH8: 409100 | BI8: =IF('[1]DATA CONSOLIDADA 2018-2025 '!$BH8>'[1]DATA CONSOLIDADA 2018-2025 '!$AN8,"Incremento",IF('[1]DATA CONSOLIDADA 2018-2025 '!$AN8='[1]DATA CONSOLIDADA 2018-2025 '!$BH8,"Sin incremento",IF('[1]DATA CONSOLIDADA 2018-2025 '!$BH8<'[1]DATA CONSOLIDADA 2018-2025 '!$AN8,"Disminución"," ---"))) -> #REF! | BJ8: ='[1]DATA CONSOLIDADA 2018-2025 '!$BH8-'[1]DATA CONSOLIDADA 2018-2025 '!$BE8 -> #REF! | BK8: 325000 | BL8: 0 | BM8: 325000 | BN8: =IF('[1]DATA CONSOLIDADA 2018-2025 '!$BM8>'[1]DATA CONSOLIDADA 2018-2025 '!$BH8,"Incremento",IF('[1]DATA CONSOLIDADA 2018-2025 '!$BH8='[1]DATA CONSOLIDADA 2018-2025 '!$BM8,"Sin incremento",IF('[1]DATA CONSOLIDADA 2018-2025 '!$BM8<'[1]DATA CONSOLIDADA 2018-2025 '!$BH8,"Disminución"," ---"))) -> #REF! | BO8: ='[1]DATA CONSOLIDADA 2018-2025 '!$BM8-'[1]DATA CONSOLIDADA 2018-2025 '!$BH8 -> #REF! | BP8: 1224192.5 | BQ8: 398235.92 | BR8: 1622428.4 | BS8: =IF('[1]DATA CONSOLIDADA 2018-2025 '!$BR8>'[1]DATA CONSOLIDADA 2018-2025 '!$BM8,"Incremento",IF('[1]DATA CONSOLIDADA 2018-2025 '!$BM8='[1]DATA CONSOLIDADA 2018-2025 '!$BR8,"Sin incremento",IF('[1]DATA CONSOLIDADA 2018-2025 '!$BR8<'[1]DATA CONSOLIDADA 2018-2025 '!$BM8,"Disminución"," ---"))) -> #REF! | BT8: ='[1]DATA CONSOLIDADA 2018-2025 '!$BR8-Hoja1!$BO8 -> #REF! | BU8: 820950 | BV8: 0 | BW8: 820950 | BX8: =IF('[1]DATA CONSOLIDADA 2018-2025 '!$BW8>'[1]DATA CONSOLIDADA 2018-2025 '!$BR8,"Incremento",IF('[1]DATA CONSOLIDADA 2018-2025 '!$BR8='[1]DATA CONSOLIDADA 2018-2025 '!$BW8,"Sin incremento",IF('[1]DATA CONSOLIDADA 2018-2025 '!$BW8<'[1]DATA CONSOLIDADA 2018-2025 '!$BR8,"Disminución"," ---"))) -> #REF! | BY8: ='[1]DATA CONSOLIDADA 2018-2025 '!$BW8-'[1]DATA CONSOLIDADA 2018-2025 '!$BR8 -> #REF! | BZ8: 165821.2 | CA8: 0 | CB8: 165821.2 | CC8: =IF('[1]DATA CONSOLIDADA 2018-2025 '!$CB8>'[1]DATA CONSOLIDADA 2018-2025 '!$BW8,"Incremento",IF('[1]DATA CONSOLIDADA 2018-2025 '!$BW8='[1]DATA CONSOLIDADA 2018-2025 '!$CB8,"Sin incremento",IF('[1]DATA CONSOLIDADA 2018-2025 '!$CB8<'[1]DATA CONSOLIDADA 2018-2025 '!$BW8,"Disminución"," ---"))) -> #REF! | CD8: ='[1]DATA CONSOLIDADA 2018-2025 '!$CB8-Hoja1!$BW8 -> #REF! | CE8: 0 | CF8: 0 | CG8: 0 | CH8: =IF('[1]DATA CONSOLIDADA 2018-2025 '!$CG8>'[1]DATA CONSOLIDADA 2018-2025 '!$CB8,"Incremento",IF('[1]DATA CONSOLIDADA 2018-2025 '!$CB8='[1]DATA CONSOLIDADA 2018-2025 '!$CG8,"Sin incremento",IF('[1]DATA CONSOLIDADA 2018-2025 '!$CG8<'[1]DATA CONSOLIDADA 2018-2025 '!$CB8,"Disminución"," ---"))) -> #REF! | CI8: ='[1]DATA CONSOLIDADA 2018-2025 '!$CG8-Hoja1!$CB8 -> #REF! | CJ8: ='[1]DATA CONSOLIDADA 2018-2025 '!$BE8+'[1]DATA CONSOLIDADA 2018-2025 '!$BH8+'[1]DATA CONSOLIDADA 2018-2025 '!$BM8+'[1]DATA CONSOLIDADA 2018-2025 '!$BR8+'[1]DATA CONSOLIDADA 2018-2025 '!$BW8+'[1]DATA CONSOLIDADA 2018-2025 '!$CB8+'[1]DATA CONSOLIDADA 2018-2025 '!$CG8 -> #REF! | CK8: 0 | CL8: 0 | CM8: 0 | CN8: =IF('[1]DATA CONSOLIDADA 2018-2025 '!$CM8>'[1]DATA CONSOLIDADA 2018-2025 '!$CG8,"Incremento",IF('[1]DATA CONSOLIDADA 2018-2025 '!$CG8='[1]DATA CONSOLIDADA 2018-2025 '!$CM8,"Sin incremento",IF('[1]DATA CONSOLIDADA 2018-2025 '!$CM8<'[1]DATA CONSOLIDADA 2018-2025 '!$CG8,"Disminución"," ---"))) -> #REF! | CO8: ='[1]DATA CONSOLIDADA 2018-2025 '!$CM8-Hoja1!$CG8 -> #REF! | CP8: 9793.4 | CQ8: 0 | CR8: 0 | CS8: 156027.8 | CT8: 0 | CU8: 0 | CV8: 165821.2 | CW8: 0 | CX8: 0 | CY8: 0 | CZ8: 0 | DA8: 0 | DB8: 0 | DC8: 0 | DD8: 0 | DE8: 0 | DF8: 0 | DG8: 0 | DH8: 0 | DI8: 20603320621 | DJ8: COOPERATIVA AGRARIA CAFETALERA ALTA MONTAÑA | DK8: 02 Cooperativa
A9: ASOCIACION DE PRODUCTORES AGROPECUARIOS LA FLOR DE CAFÉ | B9: CAFÉ | C9: CAFÉ | D9: AMAZONAS | E9: 010601 | F9: AMAZONAS | G9: RODRIGUEZ DE MENDOZA | H9: SAN NICOLAS | J9: 1 | K9: 1 | L9: 1 | M9: 1 | N9: 1 | Q9: PAC | R9: =IF(I9=1, I$4, "") & IF(J9=1, IF(I9=1, "-", "") & J$4, "") & IF(K9=1, IF(OR(J9=1, I9=1), "-", "") & K$4, "") & IF(L9=1, IF(OR(K9=1, J9=1, I9=1), "-", "") & L$4, "") & IF(M9=1, IF(OR(L9=1, K9=1, J9=1, I9=1), "-", "") & M$4, "") & IF(N9=1, IF(OR(M9=1, L9=1, K9=1, J9=1, I9=1), "-", "") & N$4, "") & IF(O9=1, IF(OR(N9=1, M9=1, L9=1, K9=1, J9=1, I9=1), "-", "") & O$4, "") & IF(P9=1, IF(I9=1, " - ", IF(J9=1, " - ", IF(K9=1, " - ", IF(L9=1, " - ", IF(M9=1, " - ", IF(N9=1, " - ", IF(O9=1, " - ", ""))))))) & P$4, "") -> 2019-2020-2021-2022-2023 | S9: =SUM(Hoja1!$I9:$P9) -> 5 | T9: =IF(OR(Hoja1!$J9=1,Hoja1!$K9=1,Hoja1!$L9=1,Hoja1!$M9=1,Hoja1!$N9=1,Hoja1!$O9=1,Hoja1!$P9=1),"SI","NO") -> SI | U9: =IF(OR(Hoja1!$K9=1,Hoja1!$L9=1,Hoja1!$M9=1,Hoja1!$N9=1,Hoja1!$O9=1,Hoja1!$P9=1),"SI","NO") -> SI | V9: 0 | W9: 210 | X9: 113 | Y9: 323 | Z9: 210 | AA9: 113 | AB9: 323 | AC9: 274 | AD9: 137 | AE9: 411 | AF9: 274 | AG9: 137 | AH9: 411 | AI9: 274 | AJ9: 137 | AK9: 411 | AL9: 0 | AM9: 0 | AN9: 0 | AO9: 0 | AP9: 0 | AQ9: 0 | AR9: =IF(Hoja1!$AQ9>0,Hoja1!$AQ9,IF(Hoja1!$AN9>0,Hoja1!$AN9,IF(Hoja1!$AK9>0,Hoja1!$AK9,IF(Hoja1!$AH9>0,Hoja1!$AH9,IF(Hoja1!$AE9>0,Hoja1!$AE9,IF(Hoja1!$AB9>0,Hoja1!$AB9,IF(Hoja1!$Y9>0,Hoja1!$Y9,IF(Hoja1!$V9>0,Hoja1!$V9," ---")))))))) -> 411 | AS9: 0 | AT9: 0 | AU9: 26 | AV9: 8 | AW9: 43 | AX9: 7 | AY9: 32 | AZ9: 6 | BA9: 0 | BB9: 0 | BC9: 0 | BD9: 0 | BE9: 0 | BF9: 6041471.5 | BG9: 0 | BH9: 6041471.5 | BI9: =IF('[1]DATA CONSOLIDADA 2018-2025 '!$BH9>'[1]DATA CONSOLIDADA 2018-2025 '!$AN9,"Incremento",IF('[1]DATA CONSOLIDADA 2018-2025 '!$AN9='[1]DATA CONSOLIDADA 2018-2025 '!$BH9,"Sin incremento",IF('[1]DATA CONSOLIDADA 2018-2025 '!$BH9<'[1]DATA CONSOLIDADA 2018-2025 '!$AN9,"Disminución"," ---"))) -> #REF! | BJ9: ='[1]DATA CONSOLIDADA 2018-2025 '!$BH9-'[1]DATA CONSOLIDADA 2018-2025 '!$BE9 -> #REF! | BK9: 523737.39 | BL9: 0 | BM9: 523737.39 | BN9: =IF('[1]DATA CONSOLIDADA 2018-2025 '!$BM9>'[1]DATA CONSOLIDADA 2018-2025 '!$BH9,"Incremento",IF('[1]DATA CONSOLIDADA 2018-2025 '!$BH9='[1]DATA CONSOLIDADA 2018-2025 '!$BM9,"Sin incremento",IF('[1]DATA CONSOLIDADA 2018-2025 '!$BM9<'[1]DATA CONSOLIDADA 2018-2025 '!$BH9,"Disminución"," ---"))) -> #REF! | BO9: ='[1]DATA CONSOLIDADA 2018-2025 '!$BM9-'[1]DATA CONSOLIDADA 2018-2025 '!$BH9 -> #REF! | BP9: 3394807.7 | BQ9: 0 | BR9: 3394807.7 | BS9: =IF('[1]DATA CONSOLIDADA 2018-2025 '!$BR9>'[1]DATA CONSOLIDADA 2018-2025 '!$BM9,"Incremento",IF('[1]DATA CONSOLIDADA 2018-2025 '!$BM9='[1]DATA CONSOLIDADA 2018-2025 '!$BR9,"Sin incremento",IF('[1]DATA CONSOLIDADA 2018-2025 '!$BR9<'[1]DATA CONSOLIDADA 2018-2025 '!$BM9,"Disminución"," ---"))) -> #REF! | BT9: ='[1]DATA CONSOLIDADA 2018-2025 '!$BR9-Hoja1!$BO9 -> #REF! | BU9: 4076542 | BV9: 446118 | BW9: 4522660 | BX9: =IF('[1]DATA CONSOLIDADA 2018-2025 '!$BW9>'[1]DATA CONSOLIDADA 2018-2025 '!$BR9,"Incremento",IF('[1]DATA CONSOLIDADA 2018-2025 '!$BR9='[1]DATA CONSOLIDADA 2018-2025 '!$BW9,"Sin incremento",IF('[1]DATA CONSOLIDADA 2018-2025 '!$BW9<'[1]DATA CONSOLIDADA 2018-2025 '!$BR9,"Disminución"," ---"))) -> #REF! | BY9: ='[1]DATA CONSOLIDADA 2018-2025 '!$BW9-'[1]DATA CONSOLIDADA 2018-2025 '!$BR9 -> #REF! | BZ9: 5733612.8 | CA9: 984023.42 | CB9: 6717636.2 | CC9: =IF('[1]DATA CONSOLIDADA 2018-2025 '!$CB9>'[1]DATA CONSOLIDADA 2018-2025 '!$BW9,"Incremento",IF('[1]DATA CONSOLIDADA 2018-2025 '!$BW9='[1]DATA CONSOLIDADA 2018-2025 '!$CB9,"Sin incremento",IF('[1]DATA CONSOLIDADA 2018-2025 '!$CB9<'[1]DATA CONSOLIDADA 2018-2025 '!$BW9,"Disminución"," ---"))) -> #REF! | CD9: ='[1]DATA CONSOLIDADA 2018-2025 '!$CB9-Hoja1!$BW9 -> #REF! | CE9: 0 | CF9: 0 | CG9: 0 | CH9: =IF('[1]DATA CONSOLIDADA 2018-2025 '!$CG9>'[1]DATA CONSOLIDADA 2018-2025 '!$CB9,"Incremento",IF('[1]DATA CONSOLIDADA 2018-2025 '!$CB9='[1]DATA CONSOLIDADA 2018-2025 '!$CG9,"Sin incremento",IF('[1]DATA CONSOLIDADA 2018-2025 '!$CG9<'[1]DATA CONSOLIDADA 2018-2025 '!$CB9,"Disminución"," ---"))) -> #REF! | CI9: ='[1]DATA CONSOLIDADA 2018-2025 '!$CG9-Hoja1!$CB9 -> #REF! | CJ9: ='[1]DATA CONSOLIDADA 2018-2025 '!$BE9+'[1]DATA CONSOLIDADA 2018-2025 '!$BH9+'[1]DATA CONSOLIDADA 2018-2025 '!$BM9+'[1]DATA CONSOLIDADA 2018-2025 '!$BR9+'[1]DATA CONSOLIDADA 2018-2025 '!$BW9+'[1]DATA CONSOLIDADA 2018-2025 '!$CB9+'[1]DATA CONSOLIDADA 2018-2025 '!$CG9 -> #REF! | CK9: 0 | CL9: 0 | CM9: 0 | CN9: =IF('[1]DATA CONSOLIDADA 2018-2025 '!$CM9>'[1]DATA CONSOLIDADA 2018-2025 '!$CG9,"Incremento",IF('[1]DATA CONSOLIDADA 2018-2025 '!$CG9='[1]DATA CONSOLIDADA 2018-2025 '!$CM9,"Sin incremento",IF('[1]DATA CONSOLIDADA 2018-2025 '!$CM9<'[1]DATA CONSOLIDADA 2018-2025 '!$CG9,"Disminución"," ---"))) -> #REF! | CO9: ='[1]DATA CONSOLIDADA 2018-2025 '!$CM9-Hoja1!$CG9 -> #REF! | CP9: 0 | CQ9: 0 | CR9: 0 | CS9: 6717636.2 | CT9: 0 | CU9: 0 | CV9: 6717636.2 | CW9: 0 | CX9: 0 | CY9: 0 | CZ9: 0 | DA9: 0 | DB9: 0 | DC9: 0 | DD9: 0 | DE9: 0 | DF9: 0 | DG9: 0 | DH9: 0 | DI9: 20480762895 | DJ9: ASOCIACION DE PRODUCTORES AGROPECUARIOS LA FLOR DE CAFÉ | DK9: 01 Asociación
A10: COOPERATIVA DE SERVICIOS MULTIPLES - APROCAM | B10: CACAO | C10: CACAO | D10: AMAZONAS | E10: 010201 | F10: AMAZONAS | G10: BAGUA | H10: BAGUA | I10: 1 | J10: 1 | K10: 1 | L10: 1 | M10: 1 | N10: 1 | Q10: PAC | R10: =IF(I10=1, I$4, "") & IF(J10=1, IF(I10=1, "-", "") & J$4, "") & IF(K10=1, IF(OR(J10=1, I10=1), "-", "") & K$4, "") & IF(L10=1, IF(OR(K10=1, J10=1, I10=1), "-", "") & L$4, "") & IF(M10=1, IF(OR(L10=1, K10=1, J10=1, I10=1), "-", "") & M$4, "") & IF(N10=1, IF(OR(M10=1, L10=1, K10=1, J10=1, I10=1), "-", "") & N$4, "") & IF(O10=1, IF(OR(N10=1, M10=1, L10=1, K10=1, J10=1, I10=1), "-", "") & O$4, "") & IF(P10=1, IF(I10=1, " - ", IF(J10=1, " - ", IF(K10=1, " - ", IF(L10=1, " - ", IF(M10=1, " - ", IF(N10=1, " - ", IF(O10=1, " - ", ""))))))) & P$4, "") -> 2018-2019-2020-2021-2022-2023 | S10: =SUM(Hoja1!$I10:$P10) -> 6 | T10: =IF(OR(Hoja1!$J10=1,Hoja1!$K10=1,Hoja1!$L10=1,Hoja1!$M10=1,Hoja1!$N10=1,Hoja1!$O10=1,Hoja1!$P10=1),"SI","NO") -> SI | U10: =IF(OR(Hoja1!$K10=1,Hoja1!$L10=1,Hoja1!$M10=1,Hoja1!$N10=1,Hoja1!$O10=1,Hoja1!$P10=1),"SI","NO") -> SI | V10: 418 | W10: 353 | X10: 65 | Y10: 418 | Z10: 357 | AA10: 66 | AB10: 423 | AC10: 201 | AD10: 43 | AE10: 244 | AF10: 201 | AG10: 43 | AH10: 244 | AI10: 201 | AJ10: 43 | AK10: 244 | AL10: 0 | AM10: 0 | AN10: 0 | AO10: 0 | AP10: 0 | AQ10: 0 | AR10: =IF(Hoja1!$AQ10>0,Hoja1!$AQ10,IF(Hoja1!$AN10>0,Hoja1!$AN10,IF(Hoja1!$AK10>0,Hoja1!$AK10,IF(Hoja1!$AH10>0,Hoja1!$AH10,IF(Hoja1!$AE10>0,Hoja1!$AE10,IF(Hoja1!$AB10>0,Hoja1!$AB10,IF(Hoja1!$Y10>0,Hoja1!$Y10,IF(Hoja1!$V10>0,Hoja1!$V10," ---")))))))) -> 244 | AS10: 0 | AT10: 0 | AU10: 35 | AV10: 7 | AW10: 32 | AX10: 5 | AY10: 39 | AZ10: 7 | BA10: 0 | BB10: 0 | BC10: 0 | BD10: 0 | BE10: 279033.24 | BF10: 0 | BG10: 1026216.8 | BH10: 1026216.8 | BI10: =IF('[1]DATA CONSOLIDADA 2018-2025 '!$BH10>'[1]DATA CONSOLIDADA 2018-2025 '!$AN10,"Incremento",IF('[1]DATA CONSOLIDADA 2018-2025 '!$AN10='[1]DATA CONSOLIDADA 2018-2025 '!$BH10,"Sin incremento",IF('[1]DATA CONSOLIDADA 2018-2025 '!$BH10<'[1]DATA CONSOLIDADA 2018-2025 '!$AN10,"Disminución"," ---"))) -> #REF! | BJ10: ='[1]DATA CONSOLIDADA 2018-2025 '!$BH10-'[1]DATA CONSOLIDADA 2018-2025 '!$BE10 -> #REF! | BK10: 101917.7 | BL10: 284025.07 | BM10: 385942.77 | BN10: =IF('[1]DATA CONSOLIDADA 2018-2025 '!$BM10>'[1]DATA CONSOLIDADA 2018-2025 '!$BH10,"Incremento",IF('[1]DATA CONSOLIDADA 2018-2025 '!$BH10='[1]DATA CONSOLIDADA 2018-2025 '!$BM10,"Sin incremento",IF('[1]DATA CONSOLIDADA 2018-2025 '!$BM10<'[1]DATA CONSOLIDADA 2018-2025 '!$BH10,"Disminución"," ---"))) -> #REF! | BO10: ='[1]DATA CONSOLIDADA 2018-2025 '!$BM10-'[1]DATA CONSOLIDADA 2018-2025 '!$BH10 -> #REF! | BP10: 78859.15 | BQ10: 2033180.4 | BR10: 2112039.5 | BS10: =IF('[1]DATA CONSOLIDADA 2018-2025 '!$BR10>'[1]DATA CONSOLIDADA 2018-2025 '!$BM10,"Incremento",IF('[1]DATA CONSOLIDADA 2018-2025 '!$BM10='[1]DATA CONSOLIDADA 2018-2025 '!$BR10,"Sin incremento",IF('[1]DATA CONSOLIDADA 2018-2025 '!$BR10<'[1]DATA CONSOLIDADA 2018-2025 '!$BM10,"Disminución"," ---"))) -> #REF! | BT10: ='[1]DATA CONSOLIDADA 2018-2025 '!$BR10-Hoja1!$BO10 -> #REF! | BU10: 65644.73 | BV10: 1189543.9 | BW10: 1255188.6 | BX10: =IF('[1]DATA CONSOLIDADA 2018-2025 '!$BW10>'[1]DATA CONSOLIDADA 2018-2025 '!$BR10,"Incremento",IF('[1]DATA CONSOLIDADA 2018-2025 '!$BR10='[1]DATA CONSOLIDADA 2018-2025 '!$BW10,"Sin incremento",IF('[1]DATA CONSOLIDADA 2018-2025 '!$BW10<'[1]DATA CONSOLIDADA 2018-2025 '!$BR10,"Disminución"," ---"))) -> #REF! | BY10: ='[1]DATA CONSOLIDADA 2018-2025 '!$BW10-'[1]DATA CONSOLIDADA 2018-2025 '!$BR10 -> #REF! | BZ10: 114467.98 | CA10: 1092156.7 | CB10: 1206624.7 | CC10: =IF('[1]DATA CONSOLIDADA 2018-2025 '!$CB10>'[1]DATA CONSOLIDADA 2018-2025 '!$BW10,"Incremento",IF('[1]DATA CONSOLIDADA 2018-2025 '!$BW10='[1]DATA CONSOLIDADA 2018-2025 '!$CB10,"Sin incremento",IF('[1]DATA CONSOLIDADA 2018-2025 '!$CB10<'[1]DATA CONSOLIDADA 2018-2025 '!$BW10,"Disminución"," ---"))) -> #REF! | CD10: ='[1]DATA CONSOLIDADA 2018-2025 '!$CB10-Hoja1!$BW10 -> #REF! | CE10: 0 | CF10: 0 | CG10: 0 | CH10: =IF('[1]DATA CONSOLIDADA 2018-2025 '!$CG10>'[1]DATA CONSOLIDADA 2018-2025 '!$CB10,"Incremento",IF('[1]DATA CONSOLIDADA 2018-2025 '!$CB10='[1]DATA CONSOLIDADA 2018-2025 '!$CG10,"Sin incremento",IF('[1]DATA CONSOLIDADA 2018-2025 '!$CG10<'[1]DATA CONSOLIDADA 2018-2025 '!$CB10,"Disminución"," ---"))) -> #REF! | CI10: ='[1]DATA CONSOLIDADA 2018-2025 '!$CG10-Hoja1!$CB10 -> #REF! | CJ10: ='[1]DATA CONSOLIDADA 2018-2025 '!$BE10+'[1]DATA CONSOLIDADA 2018-2025 '!$BH10+'[1]DATA CONSOLIDADA 2018-2025 '!$BM10+'[1]DATA CONSOLIDADA 2018-2025 '!$BR10+'[1]DATA CONSOLIDADA 2018-2025 '!$BW10+'[1]DATA CONSOLIDADA 2018-2025 '!$CB10+'[1]DATA CONSOLIDADA 2018-2025 '!$CG10 -> #REF! | CK10: 0 | CL10: 0 | CM10: 0 | CN10: =IF('[1]DATA CONSOLIDADA 2018-2025 '!$CM10>'[1]DATA CONSOLIDADA 2018-2025 '!$CG10,"Incremento",IF('[1]DATA CONSOLIDADA 2018-2025 '!$CG10='[1]DATA CONSOLIDADA 2018-2025 '!$CM10,"Sin incremento",IF('[1]DATA CONSOLIDADA 2018-2025 '!$CM10<'[1]DATA CONSOLIDADA 2018-2025 '!$CG10,"Disminución"," ---"))) -> #REF! | CO10: ='[1]DATA CONSOLIDADA 2018-2025 '!$CM10-Hoja1!$CG10 -> #REF! | CP10: 34067.084 | CQ10: 0 | CR10: 0 | CS10: 1172557.6 | CT10: 0 | CU10: 0 | CV10: 1206624.7 | CW10: 0 | CX10: 0 | CY10: 0 | CZ10: 0 | DA10: 0 | DB10: 0 | DC10: 0 | DD10: 0 | DE10: 0 | DF10: 0 | DG10: 0 | DH10: 0 | DI10: 20480458550 | DJ10: COOPERATIVA AGRARIA APROCAM | DK10: 02 Cooperativa
A11: COOPERATIVA CENTRAL DE PRODUCTORES AGROPECUARIOS DE AMAZONAS - CEPROAA | B11: CACAO | C11: CACAO | D11: AMAZONAS | E11: 010702 | F11: AMAZONAS | G11: UTCUBAMBA | H11: CAJARURO | I11: 1 | J11: 1 | K11: 1 | L11: 1 | M11: 1 | N11: 1 | Q11: PAC | R11: =IF(I11=1, I$4, "") & IF(J11=1, IF(I11=1, "-", "") & J$4, "") & IF(K11=1, IF(OR(J11=1, I11=1), "-", "") & K$4, "") & IF(L11=1, IF(OR(K11=1, J11=1, I11=1), "-", "") & L$4, "") & IF(M11=1, IF(OR(L11=1, K11=1, J11=1, I11=1), "-", "") & M$4, "") & IF(N11=1, IF(OR(M11=1, L11=1, K11=1, J11=1, I11=1), "-", "") & N$4, "") & IF(O11=1, IF(OR(N11=1, M11=1, L11=1, K11=1, J11=1, I11=1), "-", "") & O$4, "") & IF(P11=1, IF(I11=1, " - ", IF(J11=1, " - ", IF(K11=1, " - ", IF(L11=1, " - ", IF(M11=1, " - ", IF(N11=1, " - ", IF(O11=1, " - ", ""))))))) & P$4, "") -> 2018-2019-2020-2021-2022-2023 | S11: =SUM(Hoja1!$I11:$P11) -> 6 | T11: =IF(OR(Hoja1!$J11=1,Hoja1!$K11=1,Hoja1!$L11=1,Hoja1!$M11=1,Hoja1!$N11=1,Hoja1!$O11=1,Hoja1!$P11=1),"SI","NO") -> SI | U11: =IF(OR(Hoja1!$K11=1,Hoja1!$L11=1,Hoja1!$M11=1,Hoja1!$N11=1,Hoja1!$O11=1,Hoja1!$P11=1),"SI","NO") -> SI | V11: 344 | W11: 272 | X11: 71 | Y11: 343 | Z11: 266 | AA11: 71 | AB11: 337 | AC11: 271 | AD11: 71 | AE11: 342 | AF11: 271 | AG11: 71 | AH11: 342 | AI11: 271 | AJ11: 71 | AK11: 342 | AL11: 0 | AM11: 0 | AN11: 0 | AO11: 0 | AP11: 0 | AQ11: 0 | AR11: =IF(Hoja1!$AQ11>0,Hoja1!$AQ11,IF(Hoja1!$AN11>0,Hoja1!$AN11,IF(Hoja1!$AK11>0,Hoja1!$AK11,IF(Hoja1!$AH11>0,Hoja1!$AH11,IF(Hoja1!$AE11>0,Hoja1!$AE11,IF(Hoja1!$AB11>0,Hoja1!$AB11,IF(Hoja1!$Y11>0,Hoja1!$Y11,IF(Hoja1!$V11>0,Hoja1!$V11," ---")))))))) -> 342 | AS11: 0 | AT11: 0 | AU11: 24 | AV11: 7 | AW11: 28 | AX11: 7 | AY11: 39 | AZ11: 6 | BA11: 0 | BB11: 0 | BC11: 0 | BD11: 0 | BE11: 0 | BF11: 0 | BG11: 1072102.3 | BH11: 1072102.3 | BI11: =IF('[1]DATA CONSOLIDADA 2018-2025 '!$BH11>'[1]DATA CONSOLIDADA 2018-2025 '!$AN11,"Incremento",IF('[1]DATA CONSOLIDADA 2018-2025 '!$AN11='[1]DATA CONSOLIDADA 2018-2025 '!$BH11,"Sin incremento",IF('[1]DATA CONSOLIDADA 2018-2025 '!$BH11<'[1]DATA CONSOLIDADA 2018-2025 '!$AN11,"Disminución"," ---"))) -> #REF! | BJ11: ='[1]DATA CONSOLIDADA 2018-2025 '!$BH11-'[1]DATA CONSOLIDADA 2018-2025 '!$BE11 -> #REF! | BK11: 454472.63 | BL11: 0 | BM11: 454472.63 | BN11: =IF('[1]DATA CONSOLIDADA 2018-2025 '!$BM11>'[1]DATA CONSOLIDADA 2018-2025 '!$BH11,"Incremento",IF('[1]DATA CONSOLIDADA 2018-2025 '!$BH11='[1]DATA CONSOLIDADA 2018-2025 '!$BM11,"Sin incremento",IF('[1]DATA CONSOLIDADA 2018-2025 '!$BM11<'[1]DATA CONSOLIDADA 2018-2025 '!$BH11,"Disminución"," ---"))) -> #REF! | BO11: ='[1]DATA CONSOLIDADA 2018-2025 '!$BM11-'[1]DATA CONSOLIDADA 2018-2025 '!$BH11 -> #REF! | BP11: 1609560.4 | BQ11: 0 | BR11: 1609560.4 | BS11: =IF('[1]DATA CONSOLIDADA 2018-2025 '!$BR11>'[1]DATA CONSOLIDADA 2018-2025 '!$BM11,"Incremento",IF('[1]DATA CONSOLIDADA 2018-2025 '!$BM11='[1]DATA CONSOLIDADA 2018-2025 '!$BR11,"Sin incremento",IF('[1]DATA CONSOLIDADA 2018-2025 '!$BR11<'[1]DATA CONSOLIDADA 2018-2025 '!$BM11,"Disminución"," ---"))) -> #REF! | BT11: ='[1]DATA CONSOLIDADA 2018-2025 '!$BR11-Hoja1!$BO11 -> #REF! | BU11: 1731876.8 | BV11: 0 | BW11: 1731876.8 | BX11: =IF('[1]DATA CONSOLIDADA 2018-2025 '!$BW11>'[1]DATA CONSOLIDADA 2018-2025 '!$BR11,"Incremento",IF('[1]DATA CONSOLIDADA 2018-2025 '!$BR11='[1]DATA CONSOLIDADA 2018-2025 '!$BW11,"Sin incremento",IF('[1]DATA CONSOLIDADA 2018-2025 '!$BW11<'[1]DATA CONSOLIDADA 2018-2025 '!$BR11,"Disminución"," ---"))) -> #REF! | BY11: ='[1]DATA CONSOLIDADA 2018-2025 '!$BW11-'[1]DATA CONSOLIDADA 2018-2025 '!$BR11 -> #REF! | BZ11: 1545263.1 | CA11: 0 | CB11: 1545263.1 | CC11: =IF('[1]DATA CONSOLIDADA 2018-2025 '!$CB11>'[1]DATA CONSOLIDADA 2018-2025 '!$BW11,"Incremento",IF('[1]DATA CONSOLIDADA 2018-2025 '!$BW11='[1]DATA CONSOLIDADA 2018-2025 '!$CB11,"Sin incremento",IF('[1]DATA CONSOLIDADA 2018-2025 '!$CB11<'[1]DATA CONSOLIDADA 2018-2025 '!$BW11,"Disminución"," ---"))) -> #REF! | CD11: ='[1]DATA CONSOLIDADA 2018-2025 '!$CB11-Hoja1!$BW11 -> #REF! | CE11: 0 | CF11: 0 | CG11: 0 | CH11: =IF('[1]DATA CONSOLIDADA 2018-2025 '!$CG11>'[1]DATA CONSOLIDADA 2018-2025 '!$CB11,"Incremento",IF('[1]DATA CONSOLIDADA 2018-2025 '!$CB11='[1]DATA CONSOLIDADA 2018-2025 '!$CG11,"Sin incremento",IF('[1]DATA CONSOLIDADA 2018-2025 '!$CG11<'[1]DATA CONSOLIDADA 2018-2025 '!$CB11,"Disminución"," ---"))) -> #REF! | CI11: ='[1]DATA CONSOLIDADA 2018-2025 '!$CG11-Hoja1!$CB11 -> #REF! | CJ11: ='[1]DATA CONSOLIDADA 2018-2025 '!$BE11+'[1]DATA CONSOLIDADA 2018-2025 '!$BH11+'[1]DATA CONSOLIDADA 2018-2025 '!$BM11+'[1]DATA CONSOLIDADA 2018-2025 '!$BR11+'[1]DATA CONSOLIDADA 2018-2025 '!$BW11+'[1]DATA CONSOLIDADA 2018-2025 '!$CB11+'[1]DATA CONSOLIDADA 2018-2025 '!$CG11 -> #REF! | CK11: 0 | CL11: 0 | CM11: 0 | CN11: =IF('[1]DATA CONSOLIDADA 2018-2025 '!$CM11>'[1]DATA CONSOLIDADA 2018-2025 '!$CG11,"Incremento",IF('[1]DATA CONSOLIDADA 2018-2025 '!$CG11='[1]DATA CONSOLIDADA 2018-2025 '!$CM11,"Sin incremento",IF('[1]DATA CONSOLIDADA 2018-2025 '!$CM11<'[1]DATA CONSOLIDADA 2018-2025 '!$CG11,"Disminución"," ---"))) -> #REF! | CO11: ='[1]DATA CONSOLIDADA 2018-2025 '!$CM11-Hoja1!$CG11 -> #REF! | CP11: 9912.9964 | CQ11: 0 | CR11: 820166.58 | CS11: 715183.52 | CT11: 0 | CU11: 0 | CV11: 1545263.1 | CW11: 0 | CX11: 0 | CY11: 0 | CZ11: 0 | DA11: 0 | DB11: 0 | DC11: 0 | DD11: 0 | DE11: 0 | DF11: 0 | DG11: 0 | DH11: 0 | DI11: 20479917141 | DJ11: COOPERATIVA AGRARIA CENTRAL DE PRODUCTORES DE AMAZONAS | DK11: 02 Cooperativa
A12: ASOCIACION DE PRODUCTORES AGROPECUARIOS LUIS SOLIBARRIA | B12: CACAO | C12: CACAO | D12: AMAZONAS | E12: 010701 | F12: AMAZONAS | G12: UTCUBAMBA | H12: BAGUA GRANDE | I12: 1 | J12: 1 | Q12: PAC | R12: =IF(I12=1, I$4, "") & IF(J12=1, IF(I12=1, "-", "") & J$4, "") & IF(K12=1, IF(OR(J12=1, I12=1), "-", "") & K$4, "") & IF(L12=1, IF(OR(K12=1, J12=1, I12=1), "-", "") & L$4, "") & IF(M12=1, IF(OR(L12=1, K12=1, J12=1, I12=1), "-", "") & M$4, "") & IF(N12=1, IF(OR(M12=1, L12=1, K12=1, J12=1, I12=1), "-", "") & N$4, "") & IF(O12=1, IF(OR(N12=1, M12=1, L12=1, K12=1, J12=1, I12=1), "-", "") & O$4, "") & IF(P12=1, IF(I12=1, " - ", IF(J12=1, " - ", IF(K12=1, " - ", IF(L12=1, " - ", IF(M12=1, " - ", IF(N12=1, " - ", IF(O12=1, " - ", ""))))))) & P$4, "") -> 2018-2019 | S12: =SUM(Hoja1!$I12:$P12) -> 2 | T12: =IF(OR(Hoja1!$J12=1,Hoja1!$K12=1,Hoja1!$L12=1,Hoja1!$M12=1,Hoja1!$N12=1,Hoja1!$O12=1,Hoja1!$P12=1),"SI","NO") -> SI | U12: =IF(OR(Hoja1!$K12=1,Hoja1!$L12=1,Hoja1!$M12=1,Hoja1!$N12=1,Hoja1!$O12=1,Hoja1!$P12=1),"SI","NO") -> NO | V12: 147 | W12: 120 | X12: 25 | Y12: 145 | Z12: 0 | AA12: 0 | AB12: 0 | AC12: 0 | AD12: 0 | AE12: 0 | AF12: 0 | AG12: 0 | AH12: 0 | AI12: 0 | AJ12: 0 | AK12: 0 | AL12: 0 | AM12: 0 | AN12: 0 | AO12: 0 | AP12: 0 | AQ12: 0 | AR12: =IF(Hoja1!$AQ12>0,Hoja1!$AQ12,IF(Hoja1!$AN12>0,Hoja1!$AN12,IF(Hoja1!$AK12>0,Hoja1!$AK12,IF(Hoja1!$AH12>0,Hoja1!$AH12,IF(Hoja1!$AE12>0,Hoja1!$AE12,IF(Hoja1!$AB12>0,Hoja1!$AB12,IF(Hoja1!$Y12>0,Hoja1!$Y12,IF(Hoja1!$V12>0,Hoja1!$V12," ---")))))))) -> 145 | AS12: 0 | AT12: 0 | AU12: 0 | AV12: 0 | AW12: 0 | AX12: 0 | AY12: 0 | AZ12: 0 | BA12: 0 | BB12: 0 | BC12: 0 | BD12: 0 | BE12: 0 | BF12: 0 | BG12: 0 | BH12: 0 | BI12: =IF('[1]DATA CONSOLIDADA 2018-2025 '!$BH12>'[1]DATA CONSOLIDADA 2018-2025 '!$AN12,"Incremento",IF('[1]DATA CONSOLIDADA 2018-2025 '!$AN12='[1]DATA CONSOLIDADA 2018-2025 '!$BH12,"Sin incremento",IF('[1]DATA CONSOLIDADA 2018-2025 '!$BH12<'[1]DATA CONSOLIDADA 2018-2025 '!$AN12,"Disminución"," ---"))) -> #REF! | BJ12: ='[1]DATA CONSOLIDADA 2018-2025 '!$BH12-'[1]DATA CONSOLIDADA 2018-2025 '!$BE12 -> #REF! | BK12: 0 | BL12: 0 | BM12: 0 | BN12: =IF('[1]DATA CONSOLIDADA 2018-2025 '!$BM12>'[1]DATA CONSOLIDADA 2018-2025 '!$BH12,"Incremento",IF('[1]DATA CONSOLIDADA 2018-2025 '!$BH12='[1]DATA CONSOLIDADA 2018-2025 '!$BM12,"Sin incremento",IF('[1]DATA CONSOLIDADA 2018-2025 '!$BM12<'[1]DATA CONSOLIDADA 2018-2025 '!$BH12,"Disminución"," ---"))) -> #REF! | BO12: ='[1]DATA CONSOLIDADA 2018-2025 '!$BM12-'[1]DATA CONSOLIDADA 2018-2025 '!$BH12 -> #REF! | BP12: 0 | BQ12: 0 | BR12: 0 | BS12: =IF('[1]DATA CONSOLIDADA 2018-2025 '!$BR12>'[1]DATA CONSOLIDADA 2018-2025 '!$BM12,"Incremento",IF('[1]DATA CONSOLIDADA 2018-2025 '!$BM12='[1]DATA CONSOLIDADA 2018-2025 '!$BR12,"Sin incremento",IF('[1]DATA CONSOLIDADA 2018-2025 '!$BR12<'[1]DATA CONSOLIDADA 2018-2025 '!$BM12,"Disminución"," ---"))) -> #REF! | BT12: ='[1]DATA CONSOLIDADA 2018-2025 '!$BR12-Hoja1!$BO12 -> #REF! | BU12: 0 | BV12: 0 | BW12: 0 | BX12: =IF('[1]DATA CONSOLIDADA 2018-2025 '!$BW12>'[1]DATA CONSOLIDADA 2018-2025 '!$BR12,"Incremento",IF('[1]DATA CONSOLIDADA 2018-2025 '!$BR12='[1]DATA CONSOLIDADA 2018-2025 '!$BW12,"Sin incremento",IF('[1]DATA CONSOLIDADA 2018-2025 '!$BW12<'[1]DATA CONSOLIDADA 2018-2025 '!$BR12,"Disminución"," ---"))) -> #REF! | BY12: ='[1]DATA CONSOLIDADA 2018-2025 '!$BW12-'[1]DATA CONSOLIDADA 2018-2025 '!$BR12 -> #REF! | BZ12: 0 | CA12: 0 | CB12: 0 | CC12: =IF('[1]DATA CONSOLIDADA 2018-2025 '!$CB12>'[1]DATA CONSOLIDADA 2018-2025 '!$BW12,"Incremento",IF('[1]DATA CONSOLIDADA 2018-2025 '!$BW12='[1]DATA CONSOLIDADA 2018-2025 '!$CB12,"Sin incremento",IF('[1]DATA CONSOLIDADA 2018-2025 '!$CB12<'[1]DATA CONSOLIDADA 2018-2025 '!$BW12,"Disminución"," ---"))) -> #REF! | CD12: ='[1]DATA CONSOLIDADA 2018-2025 '!$CB12-Hoja1!$BW12 -> #REF! | CE12: 0 | CF12: 0 | CG12: 0 | CH12: =IF('[1]DATA CONSOLIDADA 2018-2025 '!$CG12>'[1]DATA CONSOLIDADA 2018-2025 '!$CB12,"Incremento",IF('[1]DATA CONSOLIDADA 2018-2025 '!$CB12='[1]DATA CONSOLIDADA 2018-2025 '!$CG12,"Sin incremento",IF('[1]DATA CONSOLIDADA 2018-2025 '!$CG12<'[1]DATA CONSOLIDADA 2018-2025 '!$CB12,"Disminución"," ---"))) -> #REF! | CI12: ='[1]DATA CONSOLIDADA 2018-2025 '!$CG12-Hoja1!$CB12 -> #REF! | CJ12: ='[1]DATA CONSOLIDADA 2018-2025 '!$BE12+'[1]DATA CONSOLIDADA 2018-2025 '!$BH12+'[1]DATA CONSOLIDADA 2018-2025 '!$BM12+'[1]DATA CONSOLIDADA 2018-2025 '!$BR12+'[1]DATA CONSOLIDADA 2018-2025 '!$BW12+'[1]DATA CONSOLIDADA 2018-2025 '!$CB12+'[1]DATA CONSOLIDADA 2018-2025 '!$CG12 -> #REF! | CK12: 0 | CL12: 0 | CM12: 0 | CN12: =IF('[1]DATA CONSOLIDADA 2018-2025 '!$CM12>'[1]DATA CONSOLIDADA 2018-2025 '!$CG12,"Incremento",IF('[1]DATA CONSOLIDADA 2018-2025 '!$CG12='[1]DATA CONSOLIDADA 2018-2025 '!$CM12,"Sin incremento",IF('[1]DATA CONSOLIDADA 2018-2025 '!$CM12<'[1]DATA CONSOLIDADA 2018-2025 '!$CG12,"Disminución"," ---"))) -> #REF! | CO12: ='[1]DATA CONSOLIDADA 2018-2025 '!$CM12-Hoja1!$CG12 -> #REF! | CP12: 0 | CQ12: 0 | CR12: 0 | CS12: 0 | CT12: 0 | CU12: 0 | CV12: 0 | CW12: 0 | CX12: 0 | CY12: 0 | CZ12: 0 | DA12: 0 | DB12: 0 | DC12: 0 | DD12: 0 | DE12: 0 | DF12: 0 | DG12: 0 | DH12: 0 | DI12: 20479856258 | DJ12: ASOCIACION DE PRODUCTORES AGROPECUARIOS LUIS SOLIBARRIA | DK12: 01 Asociación
A13: COOPERATIVA AGRARIA CAFETALERA BAGUA GRANDE LTDA | B13: CAFÉ | C13: CAFÉ | D13: AMAZONAS | E13: 010701 | F13: AMAZONAS | G13: UTCUBAMBA | H13: BAGUA GRANDE | I13: 1 | J13: 1 | K13: 1 | N13: 1 | O13: 1 | Q13: PAC | R13: =IF(I13=1, I$4, "") & IF(J13=1, IF(I13=1, "-", "") & J$4, "") & IF(K13=1, IF(OR(J13=1, I13=1), "-", "") & K$4, "") & IF(L13=1, IF(OR(K13=1, J13=1, I13=1), "-", "") & L$4, "") & IF(M13=1, IF(OR(L13=1, K13=1, J13=1, I13=1), "-", "") & M$4, "") & IF(N13=1, IF(OR(M13=1, L13=1, K13=1, J13=1, I13=1), "-", "") & N$4, "") & IF(O13=1, IF(OR(N13=1, M13=1, L13=1, K13=1, J13=1, I13=1), "-", "") & O$4, "") & IF(P13=1, IF(I13=1, " - ", IF(J13=1, " - ", IF(K13=1, " - ", IF(L13=1, " - ", IF(M13=1, " - ", IF(N13=1, " - ", IF(O13=1, " - ", ""))))))) & P$4, "") -> 2018-2019-2020-2023-2024 | S13: =SUM(Hoja1!$I13:$P13) -> 5 | T13: =IF(OR(Hoja1!$J13=1,Hoja1!$K13=1,Hoja1!$L13=1,Hoja1!$M13=1,Hoja1!$N13=1,Hoja1!$O13=1,Hoja1!$P13=1),"SI","NO") -> SI | U13: =IF(OR(Hoja1!$K13=1,Hoja1!$L13=1,Hoja1!$M13=1,Hoja1!$N13=1,Hoja1!$O13=1,Hoja1!$P13=1),"SI","NO") -> SI | V13: 592 | W13: 498 | X13: 91 | Y13: 589 | Z13: 296 | AA13: 58 | AB13: 354 | AC13: 0 | AD13: 0 | AE13: 0 | AF13: 0 | AG13: 0 | AH13: 0 | AI13: 596 | AJ13: 94 | AK13: 690 | AL13: 263 | AM13: 46 | AN13: 309 | AO13: 0 | AP13: 0 | AQ13: 0 | AR13: =IF(Hoja1!$AQ13>0,Hoja1!$AQ13,IF(Hoja1!$AN13>0,Hoja1!$AN13,IF(Hoja1!$AK13>0,Hoja1!$AK13,IF(Hoja1!$AH13>0,Hoja1!$AH13,IF(Hoja1!$AE13>0,Hoja1!$AE13,IF(Hoja1!$AB13>0,Hoja1!$AB13,IF(Hoja1!$Y13>0,Hoja1!$Y13,IF(Hoja1!$V13>0,Hoja1!$V13," ---")))))))) -> 309 | AS13: 0 | AT13: 9 | AU13: 0 | AV13: 0 | AW13: 0 | AX13: 0 | AY13: 45 | AZ13: 6 | BA13: 30 | BB13: 5 | BC13: 0 | BD13: 0 | BE13: 448800 | BF13: 0 | BG13: 1768356.9 | BH13: 1768356.9 | BI13: =IF('[1]DATA CONSOLIDADA 2018-2025 '!$BH13>'[1]DATA CONSOLIDADA 2018-2025 '!$AN13,"Incremento",IF('[1]DATA CONSOLIDADA 2018-2025 '!$AN13='[1]DATA CONSOLIDADA 2018-2025 '!$BH13,"Sin incremento",IF('[1]DATA CONSOLIDADA 2018-2025 '!$BH13<'[1]DATA CONSOLIDADA 2018-2025 '!$AN13,"Disminución"," ---"))) -> #REF! | BJ13: ='[1]DATA CONSOLIDADA 2018-2025 '!$BH13-'[1]DATA CONSOLIDADA 2018-2025 '!$BE13 -> #REF! | BK13: 443003.7 | BL13: 1384395.9 | BM13: 1827399.6 | BN13: =IF('[1]DATA CONSOLIDADA 2018-2025 '!$BM13>'[1]DATA CONSOLIDADA 2018-2025 '!$BH13,"Incremento",IF('[1]DATA CONSOLIDADA 2018-2025 '!$BH13='[1]DATA CONSOLIDADA 2018-2025 '!$BM13,"Sin incremento",IF('[1]DATA CONSOLIDADA 2018-2025 '!$BM13<'[1]DATA CONSOLIDADA 2018-2025 '!$BH13,"Disminución"," ---"))) -> #REF! | BO13: ='[1]DATA CONSOLIDADA 2018-2025 '!$BM13-'[1]DATA CONSOLIDADA 2018-2025 '!$BH13 -> #REF! | BP13: 0 | BQ13: 0 | BR13: 0 | BS13: =IF('[1]DATA CONSOLIDADA 2018-2025 '!$BR13>'[1]DATA CONSOLIDADA 2018-2025 '!$BM13,"Incremento",IF('[1]DATA CONSOLIDADA 2018-2025 '!$BM13='[1]DATA CONSOLIDADA 2018-2025 '!$BR13,"Sin incremento",IF('[1]DATA CONSOLIDADA 2018-2025 '!$BR13<'[1]DATA CONSOLIDADA 2018-2025 '!$BM13,"Disminución"," ---"))) -> #REF! | BT13: ='[1]DATA CONSOLIDADA 2018-2025 '!$BR13-Hoja1!$BO13 -> #REF! | BU13: 0 | BV13: 0 | BW13: 0 | BX13: =IF('[1]DATA CONSOLIDADA 2018-2025 '!$BW13>'[1]DATA CONSOLIDADA 2018-2025 '!$BR13,"Incremento",IF('[1]DATA CONSOLIDADA 2018-2025 '!$BR13='[1]DATA CONSOLIDADA 2018-2025 '!$BW13,"Sin incremento",IF('[1]DATA CONSOLIDADA 2018-2025 '!$BW13<'[1]DATA CONSOLIDADA 2018-2025 '!$BR13,"Disminución"," ---"))) -> #REF! | BY13: ='[1]DATA CONSOLIDADA 2018-2025 '!$BW13-'[1]DATA CONSOLIDADA 2018-2025 '!$BR13 -> #REF! | BZ13: 0 | CA13: 5910875.3 | CB13: 5910875.3 | CC13: =IF('[1]DATA CONSOLIDADA 2018-2025 '!$CB13>'[1]DATA CONSOLIDADA 2018-2025 '!$BW13,"Incremento",IF('[1]DATA CONSOLIDADA 2018-2025 '!$BW13='[1]DATA CONSOLIDADA 2018-2025 '!$CB13,"Sin incremento",IF('[1]DATA CONSOLIDADA 2018-2025 '!$CB13<'[1]DATA CONSOLIDADA 2018-2025 '!$BW13,"Disminución"," ---"))) -> #REF! | CD13: ='[1]DATA CONSOLIDADA 2018-2025 '!$CB13-Hoja1!$BW13 -> #REF! | CE13: 264948.69 | CF13: 8889133.3 | CG13: 9154082 | CH13: =IF('[1]DATA CONSOLIDADA 2018-2025 '!$CG13>'[1]DATA CONSOLIDADA 2018-2025 '!$CB13,"Incremento",IF('[1]DATA CONSOLIDADA 2018-2025 '!$CB13='[1]DATA CONSOLIDADA 2018-2025 '!$CG13,"Sin incremento",IF('[1]DATA CONSOLIDADA 2018-2025 '!$CG13<'[1]DATA CONSOLIDADA 2018-2025 '!$CB13,"Disminución"," ---"))) -> #REF! | CI13: ='[1]DATA CONSOLIDADA 2018-2025 '!$CG13-Hoja1!$CB13 -> #REF! | CJ13: ='[1]DATA CONSOLIDADA 2018-2025 '!$BE13+'[1]DATA CONSOLIDADA 2018-2025 '!$BH13+'[1]DATA CONSOLIDADA 2018-2025 '!$BM13+'[1]DATA CONSOLIDADA 2018-2025 '!$BR13+'[1]DATA CONSOLIDADA 2018-2025 '!$BW13+'[1]DATA CONSOLIDADA 2018-2025 '!$CB13+'[1]DATA CONSOLIDADA 2018-2025 '!$CG13 -> #REF! | CK13: 0 | CL13: 0 | CM13: 0 | CN13: =IF('[1]DATA CONSOLIDADA 2018-2025 '!$CM13>'[1]DATA CONSOLIDADA 2018-2025 '!$CG13,"Incremento",IF('[1]DATA CONSOLIDADA 2018-2025 '!$CG13='[1]DATA CONSOLIDADA 2018-2025 '!$CM13,"Sin incremento",IF('[1]DATA CONSOLIDADA 2018-2025 '!$CM13<'[1]DATA CONSOLIDADA 2018-2025 '!$CG13,"Disminución"," ---"))) -> #REF! | CO13: ='[1]DATA CONSOLIDADA 2018-2025 '!$CM13-Hoja1!$CG13 -> #REF! | CP13: 0 | CQ13: 0 | CR13: 0 | CS13: 5910875.3 | CT13: 0 | CU13: 0 | CV13: 5910875.3 | CW13: 0 | CX13: 0 | CY13: 9154082 | CZ13: 0 | DA13: 0 | DB13: 9154082 | DC13: 0 | DD13: 0 | DE13: 0 | DF13: 0 | DG13: 0 | DH13: 0 | DI13: 20170142773 | DJ13: COOPERATIVA AGRARIA CAFETALERA BAGUA GRANDE LIMITADA | DK13: 02 Cooperativa
A14: ASOCIACION DE PRODUCTORES AGROPECUARIOS VALLE VERDE DE RODRIGUEZ DE MENDOZA | B14: CAFÉ | C14: CAFÉ | D14: AMAZONAS | E14: 010601 | F14: AMAZONAS | G14: RODRIGUEZ DE MENDOZA | H14: SAN NICOLAS | I14: 1 | J14: 1 | Q14: PAC | R14: =IF(I14=1, I$4, "") & IF(J14=1, IF(I14=1, "-", "") & J$4, "") & IF(K14=1, IF(OR(J14=1, I14=1), "-", "") & K$4, "") & IF(L14=1, IF(OR(K14=1, J14=1, I14=1), "-", "") & L$4, "") & IF(M14=1, IF(OR(L14=1, K14=1, J14=1, I14=1), "-", "") & M$4, "") & IF(N14=1, IF(OR(M14=1, L14=1, K14=1, J14=1, I14=1), "-", "") & N$4, "") & IF(O14=1, IF(OR(N14=1, M14=1, L14=1, K14=1, J14=1, I14=1), "-", "") & O$4, "") & IF(P14=1, IF(I14=1, " - ", IF(J14=1, " - ", IF(K14=1, " - ", IF(L14=1, " - ", IF(M14=1, " - ", IF(N14=1, " - ", IF(O14=1, " - ", ""))))))) & P$4, "") -> 2018-2019 | S14: =SUM(Hoja1!$I14:$P14) -> 2 | T14: =IF(OR(Hoja1!$J14=1,Hoja1!$K14=1,Hoja1!$L14=1,Hoja1!$M14=1,Hoja1!$N14=1,Hoja1!$O14=1,Hoja1!$P14=1),"SI","NO") -> SI | U14: =IF(OR(Hoja1!$K14=1,Hoja1!$L14=1,Hoja1!$M14=1,Hoja1!$N14=1,Hoja1!$O14=1,Hoja1!$P14=1),"SI","NO") -> NO | V14: 427 | W14: 0 | X14: 0 | Y14: 0 | Z14: 0 | AA14: 0 | AB14: 0 | AC14: 0 | AD14: 0 | AE14: 0 | AF14: 0 | AG14: 0 | AH14: 0 | AI14: 0 | AJ14: 0 | AK14: 0 | AL14: 0 | AM14: 0 | AN14: 0 | AO14: 0 | AP14: 0 | AQ14: 0 | AR14: =IF(Hoja1!$AQ14>0,Hoja1!$AQ14,IF(Hoja1!$AN14>0,Hoja1!$AN14,IF(Hoja1!$AK14>0,Hoja1!$AK14,IF(Hoja1!$AH14>0,Hoja1!$AH14,IF(Hoja1!$AE14>0,Hoja1!$AE14,IF(Hoja1!$AB14>0,Hoja1!$AB14,IF(Hoja1!$Y14>0,Hoja1!$Y14,IF(Hoja1!$V14>0,Hoja1!$V14," ---")))))))) -> 427 | AS14: 0 | AT14: 0 | AU14: 0 | AV14: 0 | AW14: 0 | AX14: 0 | AY14: 0 | AZ14: 0 | BA14: 0 | BB14: 0 | BC14: 0 | BD14: 0 | BE14: 0 | BF14: 0 | BG14: 0 | BH14: 0 | BI14: =IF('[1]DATA CONSOLIDADA 2018-2025 '!$BH14>'[1]DATA CONSOLIDADA 2018-2025 '!$AN14,"Incremento",IF('[1]DATA CONSOLIDADA 2018-2025 '!$AN14='[1]DATA CONSOLIDADA 2018-2025 '!$BH14,"Sin incremento",IF('[1]DATA CONSOLIDADA 2018-2025 '!$BH14<'[1]DATA CONSOLIDADA 2018-2025 '!$AN14,"Disminución"," ---"))) -> #REF! | BJ14: ='[1]DATA CONSOLIDADA 2018-2025 '!$BH14-'[1]DATA CONSOLIDADA 2018-2025 '!$BE14 -> #REF! | BK14: 0 | BL14: 0 | BM14: 0 | BN14: =IF('[1]DATA CONSOLIDADA 2018-2025 '!$BM14>'[1]DATA CONSOLIDADA 2018-2025 '!$BH14,"Incremento",IF('[1]DATA CONSOLIDADA 2018-2025 '!$BH14='[1]DATA CONSOLIDADA 2018-2025 '!$BM14,"Sin incremento",IF('[1]DATA CONSOLIDADA 2018-2025 '!$BM14<'[1]DATA CONSOLIDADA 2018-2025 '!$BH14,"Disminución"," ---"))) -> #REF! | BO14: ='[1]DATA CONSOLIDADA 2018-2025 '!$BM14-'[1]DATA CONSOLIDADA 2018-2025 '!$BH14 -> #REF! | BP14: 0 | BQ14: 0 | BR14: 0 | BS14: =IF('[1]DATA CONSOLIDADA 2018-2025 '!$BR14>'[1]DATA CONSOLIDADA 2018-2025 '!$BM14,"Incremento",IF('[1]DATA CONSOLIDADA 2018-2025 '!$BM14='[1]DATA CONSOLIDADA 2018-2025 '!$BR14,"Sin incremento",IF('[1]DATA CONSOLIDADA 2018-2025 '!$BR14<'[1]DATA CONSOLIDADA 2018-2025 '!$BM14,"Disminución"," ---"))) -> #REF! | BT14: ='[1]DATA CONSOLIDADA 2018-2025 '!$BR14-Hoja1!$BO14 -> #REF! | BU14: 0 | BV14: 0 | BW14: 0 | BX14: =IF('[1]DATA CONSOLIDADA 2018-2025 '!$BW14>'[1]DATA CONSOLIDADA 2018-2025 '!$BR14,"Incremento",IF('[1]DATA CONSOLIDADA 2018-2025 '!$BR14='[1]DATA CONSOLIDADA 2018-2025 '!$BW14,"Sin incremento",IF('[1]DATA CONSOLIDADA 2018-2025 '!$BW14<'[1]DATA CONSOLIDADA 2018-2025 '!$BR14,"Disminución"," ---"))) -> #REF! | BY14: ='[1]DATA CONSOLIDADA 2018-2025 '!$BW14-'[1]DATA CONSOLIDADA 2018-2025 '!$BR14 -> #REF! | BZ14: 0 | CA14: 0 | CB14: 0 | CC14: =IF('[1]DATA CONSOLIDADA 2018-2025 '!$CB14>'[1]DATA CONSOLIDADA 2018-2025 '!$BW14,"Incremento",IF('[1]DATA CONSOLIDADA 2018-2025 '!$BW14='[1]DATA CONSOLIDADA 2018-2025 '!$CB14,"Sin incremento",IF('[1]DATA CONSOLIDADA 2018-2025 '!$CB14<'[1]DATA CONSOLIDADA 2018-2025 '!$BW14,"Disminución"," ---"))) -> #REF! | CD14: ='[1]DATA CONSOLIDADA 2018-2025 '!$CB14-Hoja1!$BW14 -> #REF! | CE14: 0 | CF14: 0 | CG14: 0 | CH14: =IF('[1]DATA CONSOLIDADA 2018-2025 '!$CG14>'[1]DATA CONSOLIDADA 2018-2025 '!$CB14,"Incremento",IF('[1]DATA CONSOLIDADA 2018-2025 '!$CB14='[1]DATA CONSOLIDADA 2018-2025 '!$CG14,"Sin incremento",IF('[1]DATA CONSOLIDADA 2018-2025 '!$CG14<'[1]DATA CONSOLIDADA 2018-2025 '!$CB14,"Disminución"," ---"))) -> #REF! | CI14: ='[1]DATA CONSOLIDADA 2018-2025 '!$CG14-Hoja1!$CB14 -> #REF! | CJ14: ='[1]DATA CONSOLIDADA 2018-2025 '!$BE14+'[1]DATA CONSOLIDADA 2018-2025 '!$BH14+'[1]DATA CONSOLIDADA 2018-2025 '!$BM14+'[1]DATA CONSOLIDADA 2018-2025 '!$BR14+'[1]DATA CONSOLIDADA 2018-2025 '!$BW14+'[1]DATA CONSOLIDADA 2018-2025 '!$CB14+'[1]DATA CONSOLIDADA 2018-2025 '!$CG14 -> #REF! | CK14: 0 | CL14: 0 | CM14: 0 | CN14: =IF('[1]DATA CONSOLIDADA 2018-2025 '!$CM14>'[1]DATA CONSOLIDADA 2018-2025 '!$CG14,"Incremento",IF('[1]DATA CONSOLIDADA 2018-2025 '!$CG14='[1]DATA CONSOLIDADA 2018-2025 '!$CM14,"Sin incremento",IF('[1]DATA CONSOLIDADA 2018-2025 '!$CM14<'[1]DATA CONSOLIDADA 2018-2025 '!$CG14,"Disminución"," ---"))) -> #REF! | CO14: ='[1]DATA CONSOLIDADA 2018-2025 '!$CM14-Hoja1!$CG14 -> #REF! | CP14: 0 | CQ14: 0 | CR14: 0 | CS14: 0 | CT14: 0 | CU14: 0 | CV14: 0 | CW14: 0 | CX14: 0 | CY14: 0 | CZ14: 0 | DA14: 0 | DB14: 0 | DC14: 0 | DD14: 0 | DE14: 0 | DF14: 0 | DG14: 0 | DH14: 0 | DI14: 20600682386 | DJ14: ASOCIACION DE PRODUCTORES AGROPECUARIOS VALLE VERDE DE RODRIGUEZ DE MENDOZA | DK14: 01 Asociación
A15: ASOCIACION DE PRODUCTORES AGROPECUARIOS LUIS SOLIBARRIA | B15: CACAO | C15: CACAO | D15: AMAZONAS | E15: 010701 | F15: AMAZONAS | G15: UTCUBAMBA | H15: BAGUA GRANDE | L15: 1 | M15: 1 | Q15: PAC | R15: =IF(I15=1, I$4, "") & IF(J15=1, IF(I15=1, "-", "") & J$4, "") & IF(K15=1, IF(OR(J15=1, I15=1), "-", "") & K$4, "") & IF(L15=1, IF(OR(K15=1, J15=1, I15=1), "-", "") & L$4, "") & IF(M15=1, IF(OR(L15=1, K15=1, J15=1, I15=1), "-", "") & M$4, "") & IF(N15=1, IF(OR(M15=1, L15=1, K15=1, J15=1, I15=1), "-", "") & N$4, "") & IF(O15=1, IF(OR(N15=1, M15=1, L15=1, K15=1, J15=1, I15=1), "-", "") & O$4, "") & IF(P15=1, IF(I15=1, " - ", IF(J15=1, " - ", IF(K15=1, " - ", IF(L15=1, " - ", IF(M15=1, " - ", IF(N15=1, " - ", IF(O15=1, " - ", ""))))))) & P$4, "") -> 2021-2022 | S15: =SUM(Hoja1!$I15:$P15) -> 2 | T15: =IF(OR(Hoja1!$J15=1,Hoja1!$K15=1,Hoja1!$L15=1,Hoja1!$M15=1,Hoja1!$N15=1,Hoja1!$O15=1,Hoja1!$P15=1),"SI","NO") -> SI | U15: =IF(OR(Hoja1!$K15=1,Hoja1!$L15=1,Hoja1!$M15=1,Hoja1!$N15=1,Hoja1!$O15=1,Hoja1!$P15=1),"SI","NO") -> SI | V15: 0 | W15: 0 | X15: 0 | Y15: 0 | Z15: 0 | AA15: 0 | AB15: 0 | AC15: 121 | AD15: 25 | AE15: 146 | AF15: 121 | AG15: 25 | AH15: 146 | AI15: 0 | AJ15: 0 | AK15: 0 | AL15: 0 | AM15: 0 | AN15: 0 | AO15: 0 | AP15: 0 | AQ15: 0 | AR15: =IF(Hoja1!$AQ15>0,Hoja1!$AQ15,IF(Hoja1!$AN15>0,Hoja1!$AN15,IF(Hoja1!$AK15>0,Hoja1!$AK15,IF(Hoja1!$AH15>0,Hoja1!$AH15,IF(Hoja1!$AE15>0,Hoja1!$AE15,IF(Hoja1!$AB15>0,Hoja1!$AB15,IF(Hoja1!$Y15>0,Hoja1!$Y15,IF(Hoja1!$V15>0,Hoja1!$V15," ---")))))))) -> 146 | AS15: 0 | AT15: 0 | AU15: 16 | AV15: 2 | AW15: 23 | AX15: 6 | AY15: 0 | AZ15: 0 | BA15: 0 | BB15: 0 | BC15: 0 | BD15: 0 | BE15: 0 | BF15: 0 | BG15: 0 | BH15: 0 | BI15: =IF('[1]DATA CONSOLIDADA 2018-2025 '!$BH15>'[1]DATA CONSOLIDADA 2018-2025 '!$AN15,"Incremento",IF('[1]DATA CONSOLIDADA 2018-2025 '!$AN15='[1]DATA CONSOLIDADA 2018-2025 '!$BH15,"Sin incremento",IF('[1]DATA CONSOLIDADA 2018-2025 '!$BH15<'[1]DATA CONSOLIDADA 2018-2025 '!$AN15,"Disminución"," ---"))) -> #REF! | BJ15: ='[1]DATA CONSOLIDADA 2018-2025 '!$BH15-'[1]DATA CONSOLIDADA 2018-2025 '!$BE15 -> #REF! | BK15: 0 | BL15: 0 | BM15: 0 | BN15: =IF('[1]DATA CONSOLIDADA 2018-2025 '!$BM15>'[1]DATA CONSOLIDADA 2018-2025 '!$BH15,"Incremento",IF('[1]DATA CONSOLIDADA 2018-2025 '!$BH15='[1]DATA CONSOLIDADA 2018-2025 '!$BM15,"Sin incremento",IF('[1]DATA CONSOLIDADA 2018-2025 '!$BM15<'[1]DATA CONSOLIDADA 2018-2025 '!$BH15,"Disminución"," ---"))) -> #REF! | BO15: ='[1]DATA CONSOLIDADA 2018-2025 '!$BM15-'[1]DATA CONSOLIDADA 2018-2025 '!$BH15 -> #REF! | BP15: 0 | BQ15: 0 | BR15: 0 | BS15: =IF('[1]DATA CONSOLIDADA 2018-2025 '!$BR15>'[1]DATA CONSOLIDADA 2018-2025 '!$BM15,"Incremento",IF('[1]DATA CONSOLIDADA 2018-2025 '!$BM15='[1]DATA CONSOLIDADA 2018-2025 '!$BR15,"Sin incremento",IF('[1]DATA CONSOLIDADA 2018-2025 '!$BR15<'[1]DATA CONSOLIDADA 2018-2025 '!$BM15,"Disminución"," ---"))) -> #REF! | BT15: ='[1]DATA CONSOLIDADA 2018-2025 '!$BR15-Hoja1!$BO15 -> #REF! | BU15: 0 | BV15: 0 | BW15: 0 | BX15: =IF('[1]DATA CONSOLIDADA 2018-2025 '!$BW15>'[1]DATA CONSOLIDADA 2018-2025 '!$BR15,"Incremento",IF('[1]DATA CONSOLIDADA 2018-2025 '!$BR15='[1]DATA CONSOLIDADA 2018-2025 '!$BW15,"Sin incremento",IF('[1]DATA CONSOLIDADA 2018-2025 '!$BW15<'[1]DATA CONSOLIDADA 2018-2025 '!$BR15,"Disminución"," ---"))) -> #REF! | BY15: ='[1]DATA CONSOLIDADA 2018-2025 '!$BW15-'[1]DATA CONSOLIDADA 2018-2025 '!$BR15 -> #REF! | BZ15: 0 | CA15: 0 | CB15: 0 | CC15: =IF('[1]DATA CONSOLIDADA 2018-2025 '!$CB15>'[1]DATA CONSOLIDADA 2018-2025 '!$BW15,"Incremento",IF('[1]DATA CONSOLIDADA 2018-2025 '!$BW15='[1]DATA CONSOLIDADA 2018-2025 '!$CB15,"Sin incremento",IF('[1]DATA CONSOLIDADA 2018-2025 '!$CB15<'[1]DATA CONSOLIDADA 2018-2025 '!$BW15,"Disminución"," ---"))) -> #REF! | CD15: ='[1]DATA CONSOLIDADA 2018-2025 '!$CB15-Hoja1!$BW15 -> #REF! | CE15: 0 | CF15: 0 | CG15: 0 | CH15: =IF('[1]DATA CONSOLIDADA 2018-2025 '!$CG15>'[1]DATA CONSOLIDADA 2018-2025 '!$CB15,"Incremento",IF('[1]DATA CONSOLIDADA 2018-2025 '!$CB15='[1]DATA CONSOLIDADA 2018-2025 '!$CG15,"Sin incremento",IF('[1]DATA CONSOLIDADA 2018-2025 '!$CG15<'[1]DATA CONSOLIDADA 2018-2025 '!$CB15,"Disminución"," ---"))) -> #REF! | CI15: ='[1]DATA CONSOLIDADA 2018-2025 '!$CG15-Hoja1!$CB15 -> #REF! | CJ15: ='[1]DATA CONSOLIDADA 2018-2025 '!$BE15+'[1]DATA CONSOLIDADA 2018-2025 '!$BH15+'[1]DATA CONSOLIDADA 2018-2025 '!$BM15+'[1]DATA CONSOLIDADA 2018-2025 '!$BR15+'[1]DATA CONSOLIDADA 2018-2025 '!$BW15+'[1]DATA CONSOLIDADA 2018-2025 '!$CB15+'[1]DATA CONSOLIDADA 2018-2025 '!$CG15 -> #REF! | CK15: 0 | CL15: 0 | CM15: 0 | CN15: =IF('[1]DATA CONSOLIDADA 2018-2025 '!$CM15>'[1]DATA CONSOLIDADA 2018-2025 '!$CG15,"Incremento",IF('[1]DATA CONSOLIDADA 2018-2025 '!$CG15='[1]DATA CONSOLIDADA 2018-2025 '!$CM15,"Sin incremento",IF('[1]DATA CONSOLIDADA 2018-2025 '!$CM15<'[1]DATA CONSOLIDADA 2018-2025 '!$CG15,"Disminución"," ---"))) -> #REF! | CO15: ='[1]DATA CONSOLIDADA 2018-2025 '!$CM15-Hoja1!$CG15 -> #REF! | CP15: 0 | CQ15: 0 | CR15: 0 | CS15: 0 | CT15: 0 | CU15: 0 | CV15: 0 | CW15: 0 | CX15: 0 | CY15: 0 | CZ15: 0 | DA15: 0 | DB15: 0 | DC15: 0 | DD15: 0 | DE15: 0 | DF15: 0 | DG15: 0 | DH15: 0 | DI15: 20479856258 | DJ15: ASOCIACION DE PRODUCTORES AGROPECUARIOS LUIS SOLIBARRIA | DK15: 01 Asociación
A16: COOPERATIVA AGRARIA CAFETALERA PRODUCTORA COMERCIAL EXPORTADORA CAFE ANDES AMAZONICOS LTDA | B16: CAFÉ | C16: CAFÉ | D16: AMAZONAS | E16: 010706 | F16: AMAZONAS | G16: UTCUBAMBA | H16: LONYA GRANDE | L16: 1 | M16: 1 | Q16: PAC | R16: =IF(I16=1, I$4, "") & IF(J16=1, IF(I16=1, "-", "") & J$4, "") & IF(K16=1, IF(OR(J16=1, I16=1), "-", "") & K$4, "") & IF(L16=1, IF(OR(K16=1, J16=1, I16=1), "-", "") & L$4, "") & IF(M16=1, IF(OR(L16=1, K16=1, J16=1, I16=1), "-", "") & M$4, "") & IF(N16=1, IF(OR(M16=1, L16=1, K16=1, J16=1, I16=1), "-", "") & N$4, "") & IF(O16=1, IF(OR(N16=1, M16=1, L16=1, K16=1, J16=1, I16=1), "-", "") & O$4, "") & IF(P16=1, IF(I16=1, " - ", IF(J16=1, " - ", IF(K16=1, " - ", IF(L16=1, " - ", IF(M16=1, " - ", IF(N16=1, " - ", IF(O16=1, " - ", ""))))))) & P$4, "") -> 2021-2022 | S16: =SUM(Hoja1!$I16:$P16) -> 2 | T16: =IF(OR(Hoja1!$J16=1,Hoja1!$K16=1,Hoja1!$L16=1,Hoja1!$M16=1,Hoja1!$N16=1,Hoja1!$O16=1,Hoja1!$P16=1),"SI","NO") -> SI | U16: =IF(OR(Hoja1!$K16=1,Hoja1!$L16=1,Hoja1!$M16=1,Hoja1!$N16=1,Hoja1!$O16=1,Hoja1!$P16=1),"SI","NO") -> SI | V16: 0 | W16: 0 | X16: 0 | Y16: 0 | Z16: 0 | AA16: 0 | AB16: 0 | AC16: 179 | AD16: 45 | AE16: 224 | AF16: 179 | AG16: 45 | AH16: 224 | AI16: 0 | AJ16: 0 | AK16: 0 | AL16: 0 | AM16: 0 | AN16: 0 | AO16: 0 | AP16: 0 | AQ16: 0 | AR16: =IF(Hoja1!$AQ16>0,Hoja1!$AQ16,IF(Hoja1!$AN16>0,Hoja1!$AN16,IF(Hoja1!$AK16>0,Hoja1!$AK16,IF(Hoja1!$AH16>0,Hoja1!$AH16,IF(Hoja1!$AE16>0,Hoja1!$AE16,IF(Hoja1!$AB16>0,Hoja1!$AB16,IF(Hoja1!$Y16>0,Hoja1!$Y16,IF(Hoja1!$V16>0,Hoja1!$V16," ---")))))))) -> 224 | AS16: 0 | AT16: 0 | AU16: 12 | AV16: 8 | AW16: 54 | AX16: 8 | AY16: 0 | AZ16: 0 | BA16: 0 | BB16: 0 | BC16: 0 | BD16: 0 | BE16: 0 | BF16: 0 | BG16: 0 | BH16: 0 | BI16: =IF('[1]DATA CONSOLIDADA 2018-2025 '!$BH16>'[1]DATA CONSOLIDADA 2018-2025 '!$AN16,"Incremento",IF('[1]DATA CONSOLIDADA 2018-2025 '!$AN16='[1]DATA CONSOLIDADA 2018-2025 '!$BH16,"Sin incremento",IF('[1]DATA CONSOLIDADA 2018-2025 '!$BH16<'[1]DATA CONSOLIDADA 2018-2025 '!$AN16,"Disminución"," ---"))) -> #REF! | BJ16: ='[1]DATA CONSOLIDADA 2018-2025 '!$BH16-'[1]DATA CONSOLIDADA 2018-2025 '!$BE16 -> #REF! | BK16: 0 | BL16: 0 | BM16: 0 | BN16: =IF('[1]DATA CONSOLIDADA 2018-2025 '!$BM16>'[1]DATA CONSOLIDADA 2018-2025 '!$BH16,"Incremento",IF('[1]DATA CONSOLIDADA 2018-2025 '!$BH16='[1]DATA CONSOLIDADA 2018-2025 '!$BM16,"Sin incremento",IF('[1]DATA CONSOLIDADA 2018-2025 '!$BM16<'[1]DATA CONSOLIDADA 2018-2025 '!$BH16,"Disminución"," ---"))) -> #REF! | BO16: ='[1]DATA CONSOLIDADA 2018-2025 '!$BM16-'[1]DATA CONSOLIDADA 2018-2025 '!$BH16 -> #REF! | BP16: 250823.36 | BQ16: 0 | BR16: 250823.36 | BS16: =IF('[1]DATA CONSOLIDADA 2018-2025 '!$BR16>'[1]DATA CONSOLIDADA 2018-2025 '!$BM16,"Incremento",IF('[1]DATA CONSOLIDADA 2018-2025 '!$BM16='[1]DATA CONSOLIDADA 2018-2025 '!$BR16,"Sin incremento",IF('[1]DATA CONSOLIDADA 2018-2025 '!$BR16<'[1]DATA CONSOLIDADA 2018-2025 '!$BM16,"Disminución"," ---"))) -> #REF! | BT16: ='[1]DATA CONSOLIDADA 2018-2025 '!$BR16-Hoja1!$BO16 -> #REF! | BU16: 0 | BV16: 0 | BW16: 0 | BX16: =IF('[1]DATA CONSOLIDADA 2018-2025 '!$BW16>'[1]DATA CONSOLIDADA 2018-2025 '!$BR16,"Incremento",IF('[1]DATA CONSOLIDADA 2018-2025 '!$BR16='[1]DATA CONSOLIDADA 2018-2025 '!$BW16,"Sin incremento",IF('[1]DATA CONSOLIDADA 2018-2025 '!$BW16<'[1]DATA CONSOLIDADA 2018-2025 '!$BR16,"Disminución"," ---"))) -> #REF! | BY16: ='[1]DATA CONSOLIDADA 2018-2025 '!$BW16-'[1]DATA CONSOLIDADA 2018-2025 '!$BR16 -> #REF! | BZ16: 0 | CA16: 0 | CB16: 0 | CC16: =IF('[1]DATA CONSOLIDADA 2018-2025 '!$CB16>'[1]DATA CONSOLIDADA 2018-2025 '!$BW16,"Incremento",IF('[1]DATA CONSOLIDADA 2018-2025 '!$BW16='[1]DATA CONSOLIDADA 2018-2025 '!$CB16,"Sin incremento",IF('[1]DATA CONSOLIDADA 2018-2025 '!$CB16<'[1]DATA CONSOLIDADA 2018-2025 '!$BW16,"Disminución"," ---"))) -> #REF! | CD16: ='[1]DATA CONSOLIDADA 2018-2025 '!$CB16-Hoja1!$BW16 -> #REF! | CE16: 0 | CF16: 0 | CG16: 0 | CH16: =IF('[1]DATA CONSOLIDADA 2018-2025 '!$CG16>'[1]DATA CONSOLIDADA 2018-2025 '!$CB16,"Incremento",IF('[1]DATA CONSOLIDADA 2018-2025 '!$CB16='[1]DATA CONSOLIDADA 2018-2025 '!$CG16,"Sin incremento",IF('[1]DATA CONSOLIDADA 2018-2025 '!$CG16<'[1]DATA CONSOLIDADA 2018-2025 '!$CB16,"Disminución"," ---"))) -> #REF! | CI16: ='[1]DATA CONSOLIDADA 2018-2025 '!$CG16-Hoja1!$CB16 -> #REF! | CJ16: ='[1]DATA CONSOLIDADA 2018-2025 '!$BE16+'[1]DATA CONSOLIDADA 2018-2025 '!$BH16+'[1]DATA CONSOLIDADA 2018-2025 '!$BM16+'[1]DATA CONSOLIDADA 2018-2025 '!$BR16+'[1]DATA CONSOLIDADA 2018-2025 '!$BW16+'[1]DATA CONSOLIDADA 2018-2025 '!$CB16+'[1]DATA CONSOLIDADA 2018-2025 '!$CG16 -> #REF! | CK16: 0 | CL16: 0 | CM16: 0 | CN16: =IF('[1]DATA CONSOLIDADA 2018-2025 '!$CM16>'[1]DATA CONSOLIDADA 2018-2025 '!$CG16,"Incremento",IF('[1]DATA CONSOLIDADA 2018-2025 '!$CG16='[1]DATA CONSOLIDADA 2018-2025 '!$CM16,"Sin incremento",IF('[1]DATA CONSOLIDADA 2018-2025 '!$CM16<'[1]DATA CONSOLIDADA 2018-2025 '!$CG16,"Disminución"," ---"))) -> #REF! | CO16: ='[1]DATA CONSOLIDADA 2018-2025 '!$CM16-Hoja1!$CG16 -> #REF! | CP16: 0 | CQ16: 0 | CR16: 0 | CS16: 0 | CT16: 0 | CU16: 0 | CV16: 0 | CW16: 0 | CX16: 0 | CY16: 0 | CZ16: 0 | DA16: 0 | DB16: 0 | DC16: 0 | DD16: 0 | DE16: 0 | DF16: 0 | DG16: 0 | DH16: 0 | DI16: 20600001109 | DJ16: COOPERATIVA AGRARIA CAFETALERA PRODUCTORA COMERCIAL EXPORTADORA CAFE ANDES AMAZONICOS LTDA | DK16: 02 Cooperativa
A17: COOPERATIVA DE SERVICIOS MULTIPLES JUAN MARCO EL PALTO | B17: CAFÉ | C17: CAFÉ | D17: AMAZONAS | E17: 010706 | F17: AMAZONAS | G17: UTCUBAMBA | H17: LONYA GRANDE | L17: 1 | M17: 1 | N17: 1 | Q17: PAC | R17: =IF(I17=1, I$4, "") & IF(J17=1, IF(I17=1, "-", "") & J$4, "") & IF(K17=1, IF(OR(J17=1, I17=1), "-", "") & K$4, "") & IF(L17=1, IF(OR(K17=1, J17=1, I17=1), "-", "") & L$4, "") & IF(M17=1, IF(OR(L17=1, K17=1, J17=1, I17=1), "-", "") & M$4, "") & IF(N17=1, IF(OR(M17=1, L17=1, K17=1, J17=1, I17=1), "-", "") & N$4, "") & IF(O17=1, IF(OR(N17=1, M17=1, L17=1, K17=1, J17=1, I17=1), "-", "") & O$4, "") & IF(P17=1, IF(I17=1, " - ", IF(J17=1, " - ", IF(K17=1, " - ", IF(L17=1, " - ", IF(M17=1, " - ", IF(N17=1, " - ", IF(O17=1, " - ", ""))))))) & P$4, "") -> 2021-2022-2023 | S17: =SUM(Hoja1!$I17:$P17) -> 3 | T17: =IF(OR(Hoja1!$J17=1,Hoja1!$K17=1,Hoja1!$L17=1,Hoja1!$M17=1,Hoja1!$N17=1,Hoja1!$O17=1,Hoja1!$P17=1),"SI","NO") -> SI | U17: =IF(OR(Hoja1!$K17=1,Hoja1!$L17=1,Hoja1!$M17=1,Hoja1!$N17=1,Hoja1!$O17=1,Hoja1!$P17=1),"SI","NO") -> SI | V17: 0 | W17: 0 | X17: 0 | Y17: 0 | Z17: 0 | AA17: 0 | AB17: 0 | AC17: 224 | AD17: 68 | AE17: 292 | AF17: 224 | AG17: 68 | AH17: 292 | AI17: 224 | AJ17: 68 | AK17: 292 | AL17: 0 | AM17: 0 | AN17: 0 | AO17: 0 | AP17: 0 | AQ17: 0 | AR17: =IF(Hoja1!$AQ17>0,Hoja1!$AQ17,IF(Hoja1!$AN17>0,Hoja1!$AN17,IF(Hoja1!$AK17>0,Hoja1!$AK17,IF(Hoja1!$AH17>0,Hoja1!$AH17,IF(Hoja1!$AE17>0,Hoja1!$AE17,IF(Hoja1!$AB17>0,Hoja1!$AB17,IF(Hoja1!$Y17>0,Hoja1!$Y17,IF(Hoja1!$V17>0,Hoja1!$V17," ---")))))))) -> 292 | AS17: 0 | AT17: 0 | AU17: 10 | AV17: 8 | AW17: 60 | AX17: 8 | AY17: 44 | AZ17: 6 | BA17: 0 | BB17: 0 | BC17: 0 | BD17: 0 | BE17: 0 | BF17: 0 | BG17: 0 | BH17: 0 | BI17: =IF('[1]DATA CONSOLIDADA 2018-2025 '!$BH17>'[1]DATA CONSOLIDADA 2018-2025 '!$AN17,"Incremento",IF('[1]DATA CONSOLIDADA 2018-2025 '!$AN17='[1]DATA CONSOLIDADA 2018-2025 '!$BH17,"Sin incremento",IF('[1]DATA CONSOLIDADA 2018-2025 '!$BH17<'[1]DATA CONSOLIDADA 2018-2025 '!$AN17,"Disminución"," ---"))) -> #REF! | BJ17: ='[1]DATA CONSOLIDADA 2018-2025 '!$BH17-'[1]DATA CONSOLIDADA 2018-2025 '!$BE17 -> #REF! | BK17: 0 | BL17: 0 | BM17: 0 | BN17: =IF('[1]DATA CONSOLIDADA 2018-2025 '!$BM17>'[1]DATA CONSOLIDADA 2018-2025 '!$BH17,"Incremento",IF('[1]DATA CONSOLIDADA 2018-2025 '!$BH17='[1]DATA CONSOLIDADA 2018-2025 '!$BM17,"Sin incremento",IF('[1]DATA CONSOLIDADA 2018-2025 '!$BM17<'[1]DATA CONSOLIDADA 2018-2025 '!$BH17,"Disminución"," ---"))) -> #REF! | BO17: ='[1]DATA CONSOLIDADA 2018-2025 '!$BM17-'[1]DATA CONSOLIDADA 2018-2025 '!$BH17 -> #REF! | BP17: 0 | BQ17: 1177220.5 | BR17: 1177220.5 | BS17: =IF('[1]DATA CONSOLIDADA 2018-2025 '!$BR17>'[1]DATA CONSOLIDADA 2018-2025 '!$BM17,"Incremento",IF('[1]DATA CONSOLIDADA 2018-2025 '!$BM17='[1]DATA CONSOLIDADA 2018-2025 '!$BR17,"Sin incremento",IF('[1]DATA CONSOLIDADA 2018-2025 '!$BR17<'[1]DATA CONSOLIDADA 2018-2025 '!$BM17,"Disminución"," ---"))) -> #REF! | BT17: ='[1]DATA CONSOLIDADA 2018-2025 '!$BR17-Hoja1!$BO17 -> #REF! | BU17: 117797.43 | BV17: 3107691.5 | BW17: 3225488.9 | BX17: =IF('[1]DATA CONSOLIDADA 2018-2025 '!$BW17>'[1]DATA CONSOLIDADA 2018-2025 '!$BR17,"Incremento",IF('[1]DATA CONSOLIDADA 2018-2025 '!$BR17='[1]DATA CONSOLIDADA 2018-2025 '!$BW17,"Sin incremento",IF('[1]DATA CONSOLIDADA 2018-2025 '!$BW17<'[1]DATA CONSOLIDADA 2018-2025 '!$BR17,"Disminución"," ---"))) -> #REF! | BY17: ='[1]DATA CONSOLIDADA 2018-2025 '!$BW17-'[1]DATA CONSOLIDADA 2018-2025 '!$BR17 -> #REF! | BZ17: 45403.05 | CA17: 3044784.1 | CB17: 3090187.2 | CC17: =IF('[1]DATA CONSOLIDADA 2018-2025 '!$CB17>'[1]DATA CONSOLIDADA 2018-2025 '!$BW17,"Incremento",IF('[1]DATA CONSOLIDADA 2018-2025 '!$BW17='[1]DATA CONSOLIDADA 2018-2025 '!$CB17,"Sin incremento",IF('[1]DATA CONSOLIDADA 2018-2025 '!$CB17<'[1]DATA CONSOLIDADA 2018-2025 '!$BW17,"Disminución"," ---"))) -> #REF! | CD17: ='[1]DATA CONSOLIDADA 2018-2025 '!$CB17-Hoja1!$BW17 -> #REF! | CE17: 0 | CF17: 0 | CG17: 0 | CH17: =IF('[1]DATA CONSOLIDADA 2018-2025 '!$CG17>'[1]DATA CONSOLIDADA 2018-2025 '!$CB17,"Incremento",IF('[1]DATA CONSOLIDADA 2018-2025 '!$CB17='[1]DATA CONSOLIDADA 2018-2025 '!$CG17,"Sin incremento",IF('[1]DATA CONSOLIDADA 2018-2025 '!$CG17<'[1]DATA CONSOLIDADA 2018-2025 '!$CB17,"Disminución"," ---"))) -> #REF! | CI17: ='[1]DATA CONSOLIDADA 2018-2025 '!$CG17-Hoja1!$CB17 -> #REF! | CJ17: ='[1]DATA CONSOLIDADA 2018-2025 '!$BE17+'[1]DATA CONSOLIDADA 2018-2025 '!$BH17+'[1]DATA CONSOLIDADA 2018-2025 '!$BM17+'[1]DATA CONSOLIDADA 2018-2025 '!$BR17+'[1]DATA CONSOLIDADA 2018-2025 '!$BW17+'[1]DATA CONSOLIDADA 2018-2025 '!$CB17+'[1]DATA CONSOLIDADA 2018-2025 '!$CG17 -> #REF! | CK17: 0 | CL17: 0 | CM17: 0 | CN17: =IF('[1]DATA CONSOLIDADA 2018-2025 '!$CM17>'[1]DATA CONSOLIDADA 2018-2025 '!$CG17,"Incremento",IF('[1]DATA CONSOLIDADA 2018-2025 '!$CG17='[1]DATA CONSOLIDADA 2018-2025 '!$CM17,"Sin incremento",IF('[1]DATA CONSOLIDADA 2018-2025 '!$CM17<'[1]DATA CONSOLIDADA 2018-2025 '!$CG17,"Disminución"," ---"))) -> #REF! | CO17: ='[1]DATA CONSOLIDADA 2018-2025 '!$CM17-Hoja1!$CG17 -> #REF! | CP17: 0 | CQ17: 0 | CR17: 0 | CS17: 3090187.2 | CT17: 0 | CU17: 0 | CV17: 3090187.2 | CW17: 0 | CX17: 0 | CY17: 0 | CZ17: 0 | DA17: 0 | DB17: 0 | DC17: 0 | DD17: 0 | DE17: 0 | DF17: 0 | DG17: 0 | DH17: 0 | DI17: 20479622699 | DJ17: COOPERATIVA AGRARIA JUAN MARCO EL PALTO | DK17: 02 Cooperativa
A18: SEDIR-SERVICIO PARA EL DESARROLLO INTEGRAL RURAL | B18: PALTA | C18: PALTA | D18: ANCASH | E18: 021805 | F18: ANCASH | G18: SANTA | H18: MORO | I18: 1 | Q18: PAC | R18: =IF(I18=1, I$4, "") & IF(J18=1, IF(I18=1, "-", "") & J$4, "") & IF(K18=1, IF(OR(J18=1, I18=1), "-", "") & K$4, "") & IF(L18=1, IF(OR(K18=1, J18=1, I18=1), "-", "") & L$4, "") & IF(M18=1, IF(OR(L18=1, K18=1, J18=1, I18=1), "-", "") & M$4, "") & IF(N18=1, IF(OR(M18=1, L18=1, K18=1, J18=1, I18=1), "-", "") & N$4, "") & IF(O18=1, IF(OR(N18=1, M18=1, L18=1, K18=1, J18=1, I18=1), "-", "") & O$4, "") & IF(P18=1, IF(I18=1, " - ", IF(J18=1, " - ", IF(K18=1, " - ", IF(L18=1, " - ", IF(M18=1, " - ", IF(N18=1, " - ", IF(O18=1, " - ", ""))))))) & P$4, "") -> 2018 | S18: =SUM(Hoja1!$I18:$P18) -> 1 | T18: =IF(OR(Hoja1!$J18=1,Hoja1!$K18=1,Hoja1!$L18=1,Hoja1!$M18=1,Hoja1!$N18=1,Hoja1!$O18=1,Hoja1!$P18=1),"SI","NO") -> NO | U18: =IF(OR(Hoja1!$K18=1,Hoja1!$L18=1,Hoja1!$M18=1,Hoja1!$N18=1,Hoja1!$O18=1,Hoja1!$P18=1),"SI","NO") -> NO | V18: 34 | W18: 0 | X18: 0 | Y18: 0 | Z18: 0 | AA18: 0 | AB18: 0 | AC18: 0 | AD18: 0 | AE18: 0 | AF18: 0 | AG18: 0 | AH18: 0 | AI18: 0 | AJ18: 0 | AK18: 0 | AL18: 0 | AM18: 0 | AN18: 0 | AO18: 0 | AP18: 0 | AQ18: 0 | AR18: =IF(Hoja1!$AQ18>0,Hoja1!$AQ18,IF(Hoja1!$AN18>0,Hoja1!$AN18,IF(Hoja1!$AK18>0,Hoja1!$AK18,IF(Hoja1!$AH18>0,Hoja1!$AH18,IF(Hoja1!$AE18>0,Hoja1!$AE18,IF(Hoja1!$AB18>0,Hoja1!$AB18,IF(Hoja1!$Y18>0,Hoja1!$Y18,IF(Hoja1!$V18>0,Hoja1!$V18," ---")))))))) -> 34 | AS18: 0 | AT18: 0 | AU18: 0 | AV18: 0 | AW18: 0 | AX18: 0 | AY18: 0 | AZ18: 0 | BA18: 0 | BB18: 0 | BC18: 0 | BD18: 0 | BE18: 0 | BF18: 0 | BG18: 0 | BH18: 0 | BI18: =IF('[1]DATA CONSOLIDADA 2018-2025 '!$BH18>'[1]DATA CONSOLIDADA 2018-2025 '!$AN18,"Incremento",IF('[1]DATA CONSOLIDADA 2018-2025 '!$AN18='[1]DATA CONSOLIDADA 2018-2025 '!$BH18,"Sin incremento",IF('[1]DATA CONSOLIDADA 2018-2025 '!$BH18<'[1]DATA CONSOLIDADA 2018-2025 '!$AN18,"Disminución"," ---"))) -> #REF! | BJ18: ='[1]DATA CONSOLIDADA 2018-2025 '!$BH18-'[1]DATA CONSOLIDADA 2018-2025 '!$BE18 -> #REF! | BK18: 0 | BL18: 0 | BM18: 0 | BN18: =IF('[1]DATA CONSOLIDADA 2018-2025 '!$BM18>'[1]DATA CONSOLIDADA 2018-2025 '!$BH18,"Incremento",IF('[1]DATA CONSOLIDADA 2018-2025 '!$BH18='[1]DATA CONSOLIDADA 2018-2025 '!$BM18,"Sin incremento",IF('[1]DATA CONSOLIDADA 2018-2025 '!$BM18<'[1]DATA CONSOLIDADA 2018-2025 '!$BH18,"Disminución"," ---"))) -> #REF! | BO18: ='[1]DATA CONSOLIDADA 2018-2025 '!$BM18-'[1]DATA CONSOLIDADA 2018-2025 '!$BH18 -> #REF! | BP18: 0 | BQ18: 0 | BR18: 0 | BS18: =IF('[1]DATA CONSOLIDADA 2018-2025 '!$BR18>'[1]DATA CONSOLIDADA 2018-2025 '!$BM18,"Incremento",IF('[1]DATA CONSOLIDADA 2018-2025 '!$BM18='[1]DATA CONSOLIDADA 2018-2025 '!$BR18,"Sin incremento",IF('[1]DATA CONSOLIDADA 2018-2025 '!$BR18<'[1]DATA CONSOLIDADA 2018-2025 '!$BM18,"Disminución"," ---"))) -> #REF! | BT18: ='[1]DATA CONSOLIDADA 2018-2025 '!$BR18-Hoja1!$BO18 -> #REF! | BU18: 0 | BV18: 0 | BW18: 0 | BX18: =IF('[1]DATA CONSOLIDADA 2018-2025 '!$BW18>'[1]DATA CONSOLIDADA 2018-2025 '!$BR18,"Incremento",IF('[1]DATA CONSOLIDADA 2018-2025 '!$BR18='[1]DATA CONSOLIDADA 2018-2025 '!$BW18,"Sin incremento",IF('[1]DATA CONSOLIDADA 2018-2025 '!$BW18<'[1]DATA CONSOLIDADA 2018-2025 '!$BR18,"Disminución"," ---"))) -> #REF! | BY18: ='[1]DATA CONSOLIDADA 2018-2025 '!$BW18-'[1]DATA CONSOLIDADA 2018-2025 '!$BR18 -> #REF! | BZ18: 0 | CA18: 0 | CB18: 0 | CC18: =IF('[1]DATA CONSOLIDADA 2018-2025 '!$CB18>'[1]DATA CONSOLIDADA 2018-2025 '!$BW18,"Incremento",IF('[1]DATA CONSOLIDADA 2018-2025 '!$BW18='[1]DATA CONSOLIDADA 2018-2025 '!$CB18,"Sin incremento",IF('[1]DATA CONSOLIDADA 2018-2025 '!$CB18<'[1]DATA CONSOLIDADA 2018-2025 '!$BW18,"Disminución"," ---"))) -> #REF! | CD18: ='[1]DATA CONSOLIDADA 2018-2025 '!$CB18-Hoja1!$BW18 -> #REF! | CE18: 0 | CF18: 0 | CG18: 0 | CH18: =IF('[1]DATA CONSOLIDADA 2018-2025 '!$CG18>'[1]DATA CONSOLIDADA 2018-2025 '!$CB18,"Incremento",IF('[1]DATA CONSOLIDADA 2018-2025 '!$CB18='[1]DATA CONSOLIDADA 2018-2025 '!$CG18,"Sin incremento",IF('[1]DATA CONSOLIDADA 2018-2025 '!$CG18<'[1]DATA CONSOLIDADA 2018-2025 '!$CB18,"Disminución"," ---"))) -> #REF! | CI18: ='[1]DATA CONSOLIDADA 2018-2025 '!$CG18-Hoja1!$CB18 -> #REF! | CJ18: ='[1]DATA CONSOLIDADA 2018-2025 '!$BE18+'[1]DATA CONSOLIDADA 2018-2025 '!$BH18+'[1]DATA CONSOLIDADA 2018-2025 '!$BM18+'[1]DATA CONSOLIDADA 2018-2025 '!$BR18+'[1]DATA CONSOLIDADA 2018-2025 '!$BW18+'[1]DATA CONSOLIDADA 2018-2025 '!$CB18+'[1]DATA CONSOLIDADA 2018-2025 '!$CG18 -> #REF! | CK18: 0 | CL18: 0 | CM18: 0 | CN18: =IF('[1]DATA CONSOLIDADA 2018-2025 '!$CM18>'[1]DATA CONSOLIDADA 2018-2025 '!$CG18,"Incremento",IF('[1]DATA CONSOLIDADA 2018-2025 '!$CG18='[1]DATA CONSOLIDADA 2018-2025 '!$CM18,"Sin incremento",IF('[1]DATA CONSOLIDADA 2018-2025 '!$CM18<'[1]DATA CONSOLIDADA 2018-2025 '!$CG18,"Disminución"," ---"))) -> #REF! | CO18: ='[1]DATA CONSOLIDADA 2018-2025 '!$CM18-Hoja1!$CG18 -> #REF! | CP18: 0 | CQ18: 0 | CR18: 0 | CS18: 0 | CT18: 0 | CU18: 0 | CV18: 0 | CW18: 0 | CX18: 0 | CY18: 0 | CZ18: 0 | DA18: 0 | DB18: 0 | DC18: 0 | DD18: 0 | DE18: 0 | DF18: 0 | DG18: 0 | DH18: 0 | DI18: 20541732706 | DJ18: SERVICIO PARA EL DESARROLLO INTEGRAL RURAL | DK18: 01 Asociación
A19: ASOCIACION DE PRODUCTORES DE MANZANO ORGANICO DE PARIACOTO | B19: MANZANA | C19: MANZANA | D19: ANCASH | E19: 020110 | F19: ANCASH | G19: HUARAZ | H19: PARIACOTO | I19: 1 | Q19: PAC | R19: =IF(I19=1, I$4, "") & IF(J19=1, IF(I19=1, "-", "") & J$4, "") & IF(K19=1, IF(OR(J19=1, I19=1), "-", "") & K$4, "") & IF(L19=1, IF(OR(K19=1, J19=1, I19=1), "-", "") & L$4, "") & IF(M19=1, IF(OR(L19=1, K19=1, J19=1, I19=1), "-", "") & M$4, "") & IF(N19=1, IF(OR(M19=1, L19=1, K19=1, J19=1, I19=1), "-", "") & N$4, "") & IF(O19=1, IF(OR(N19=1, M19=1, L19=1, K19=1, J19=1, I19=1), "-", "") & O$4, "") & IF(P19=1, IF(I19=1, " - ", IF(J19=1, " - ", IF(K19=1, " - ", IF(L19=1, " - ", IF(M19=1, " - ", IF(N19=1, " - ", IF(O19=1, " - ", ""))))))) & P$4, "") -> 2018 | S19: =SUM(Hoja1!$I19:$P19) -> 1 | T19: =IF(OR(Hoja1!$J19=1,Hoja1!$K19=1,Hoja1!$L19=1,Hoja1!$M19=1,Hoja1!$N19=1,Hoja1!$O19=1,Hoja1!$P19=1),"SI","NO") -> NO | U19: =IF(OR(Hoja1!$K19=1,Hoja1!$L19=1,Hoja1!$M19=1,Hoja1!$N19=1,Hoja1!$O19=1,Hoja1!$P19=1),"SI","NO") -> NO | V19: 15 | W19: 0 | X19: 0 | Y19: 0 | Z19: 0 | AA19: 0 | AB19: 0 | AC19: 0 | AD19: 0 | AE19: 0 | AF19: 0 | AG19: 0 | AH19: 0 | AI19: 0 | AJ19: 0 | AK19: 0 | AL19: 0 | AM19: 0 | AN19: 0 | AO19: 0 | AP19: 0 | AQ19: 0 | AR19: =IF(Hoja1!$AQ19>0,Hoja1!$AQ19,IF(Hoja1!$AN19>0,Hoja1!$AN19,IF(Hoja1!$AK19>0,Hoja1!$AK19,IF(Hoja1!$AH19>0,Hoja1!$AH19,IF(Hoja1!$AE19>0,Hoja1!$AE19,IF(Hoja1!$AB19>0,Hoja1!$AB19,IF(Hoja1!$Y19>0,Hoja1!$Y19,IF(Hoja1!$V19>0,Hoja1!$V19," ---")))))))) -> 15 | AS19: 0 | AT19: 0 | AU19: 0 | AV19: 0 | AW19: 0 | AX19: 0 | AY19: 0 | AZ19: 0 | BA19: 0 | BB19: 0 | BC19: 0 | BD19: 0 | BE19: 0 | BF19: 0 | BG19: 0 | BH19: 0 | BI19: =IF('[1]DATA CONSOLIDADA 2018-2025 '!$BH19>'[1]DATA CONSOLIDADA 2018-2025 '!$AN19,"Incremento",IF('[1]DATA CONSOLIDADA 2018-2025 '!$AN19='[1]DATA CONSOLIDADA 2018-2025 '!$BH19,"Sin incremento",IF('[1]DATA CONSOLIDADA 2018-2025 '!$BH19<'[1]DATA CONSOLIDADA 2018-2025 '!$AN19,"Disminución"," ---"))) -> #REF! | BJ19: ='[1]DATA CONSOLIDADA 2018-2025 '!$BH19-'[1]DATA CONSOLIDADA 2018-2025 '!$BE19 -> #REF! | BK19: 0 | BL19: 0 | BM19: 0 | BN19: =IF('[1]DATA CONSOLIDADA 2018-2025 '!$BM19>'[1]DATA CONSOLIDADA 2018-2025 '!$BH19,"Incremento",IF('[1]DATA CONSOLIDADA 2018-2025 '!$BH19='[1]DATA CONSOLIDADA 2018-2025 '!$BM19,"Sin incremento",IF('[1]DATA CONSOLIDADA 2018-2025 '!$BM19<'[1]DATA CONSOLIDADA 2018-2025 '!$BH19,"Disminución"," ---"))) -> #REF! | BO19: ='[1]DATA CONSOLIDADA 2018-2025 '!$BM19-'[1]DATA CONSOLIDADA 2018-2025 '!$BH19 -> #REF! | BP19: 0 | BQ19: 0 | BR19: 0 | BS19: =IF('[1]DATA CONSOLIDADA 2018-2025 '!$BR19>'[1]DATA CONSOLIDADA 2018-2025 '!$BM19,"Incremento",IF('[1]DATA CONSOLIDADA 2018-2025 '!$BM19='[1]DATA CONSOLIDADA 2018-2025 '!$BR19,"Sin incremento",IF('[1]DATA CONSOLIDADA 2018-2025 '!$BR19<'[1]DATA CONSOLIDADA 2018-2025 '!$BM19,"Disminución"," ---"))) -> #REF! | BT19: ='[1]DATA CONSOLIDADA 2018-2025 '!$BR19-Hoja1!$BO19 -> #REF! | BU19: 0 | BV19: 0 | BW19: 0 | BX19: =IF('[1]DATA CONSOLIDADA 2018-2025 '!$BW19>'[1]DATA CONSOLIDADA 2018-2025 '!$BR19,"Incremento",IF('[1]DATA CONSOLIDADA 2018-2025 '!$BR19='[1]DATA CONSOLIDADA 2018-2025 '!$BW19,"Sin incremento",IF('[1]DATA CONSOLIDADA 2018-2025 '!$BW19<'[1]DATA CONSOLIDADA 2018-2025 '!$BR19,"Disminución"," ---"))) -> #REF! | BY19: ='[1]DATA CONSOLIDADA 2018-2025 '!$BW19-'[1]DATA CONSOLIDADA 2018-2025 '!$BR19 -> #REF! | BZ19: 0 | CA19: 0 | CB19: 0 | CC19: =IF('[1]DATA CONSOLIDADA 2018-2025 '!$CB19>'[1]DATA CONSOLIDADA 2018-2025 '!$BW19,"Incremento",IF('[1]DATA CONSOLIDADA 2018-2025 '!$BW19='[1]DATA CONSOLIDADA 2018-2025 '!$CB19,"Sin incremento",IF('[1]DATA CONSOLIDADA 2018-2025 '!$CB19<'[1]DATA CONSOLIDADA 2018-2025 '!$BW19,"Disminución"," ---"))) -> #REF! | CD19: ='[1]DATA CONSOLIDADA 2018-2025 '!$CB19-Hoja1!$BW19 -> #REF! | CE19: 0 | CF19: 0 | CG19: 0 | CH19: =IF('[1]DATA CONSOLIDADA 2018-2025 '!$CG19>'[1]DATA CONSOLIDADA 2018-2025 '!$CB19,"Incremento",IF('[1]DATA CONSOLIDADA 2018-2025 '!$CB19='[1]DATA CONSOLIDADA 2018-2025 '!$CG19,"Sin incremento",IF('[1]DATA CONSOLIDADA 2018-2025 '!$CG19<'[1]DATA CONSOLIDADA 2018-2025 '!$CB19,"Disminución"," ---"))) -> #REF! | CI19: ='[1]DATA CONSOLIDADA 2018-2025 '!$CG19-Hoja1!$CB19 -> #REF! | CJ19: ='[1]DATA CONSOLIDADA 2018-2025 '!$BE19+'[1]DATA CONSOLIDADA 2018-2025 '!$BH19+'[1]DATA CONSOLIDADA 2018-2025 '!$BM19+'[1]DATA CONSOLIDADA 2018-2025 '!$BR19+'[1]DATA CONSOLIDADA 2018-2025 '!$BW19+'[1]DATA CONSOLIDADA 2018-2025 '!$CB19+'[1]DATA CONSOLIDADA 2018-2025 '!$CG19 -> #REF! | CK19: 0 | CL19: 0 | CM19: 0 | CN19: =IF('[1]DATA CONSOLIDADA 2018-2025 '!$CM19>'[1]DATA CONSOLIDADA 2018-2025 '!$CG19,"Incremento",IF('[1]DATA CONSOLIDADA 2018-2025 '!$CG19='[1]DATA CONSOLIDADA 2018-2025 '!$CM19,"Sin incremento",IF('[1]DATA CONSOLIDADA 2018-2025 '!$CM19<'[1]DATA CONSOLIDADA 2018-2025 '!$CG19,"Disminución"," ---"))) -> #REF! | CO19: ='[1]DATA CONSOLIDADA 2018-2025 '!$CM19-Hoja1!$CG19 -> #REF! | CP19: 0 | CQ19: 0 | CR19: 0 | CS19: 0 | CT19: 0 | CU19: 0 | CV19: 0 | CW19: 0 | CX19: 0 | CY19: 0 | CZ19: 0 | DA19: 0 | DB19: 0 | DC19: 0 | DD19: 0 | DE19: 0 | DF19: 0 | DG19: 0 | DH19: 0 | DI19: 20600862074 | DJ19: ASOCIACIÓN DE PRODUCTORES DE MANZANO ORGANICO DEL DISTRITO DE PARIACOTO | DK19: 01 Asociación
A20: ASOCIACION DE PRODUCTORES ECOLOGICOS AGRARIOS DEL DISTRITO DE QUICHES | B20: ROMERO | C20: ROMERO | D20: ANCASH | E20: 021901 | F20: ANCASH | G20: SIHUAS | H20: SIHUAS | I20: 1 | Q20: PAC | R20: =IF(I20=1, I$4, "") & IF(J20=1, IF(I20=1, "-", "") & J$4, "") & IF(K20=1, IF(OR(J20=1, I20=1), "-", "") & K$4, "") & IF(L20=1, IF(OR(K20=1, J20=1, I20=1), "-", "") & L$4, "") & IF(M20=1, IF(OR(L20=1, K20=1, J20=1, I20=1), "-", "") & M$4, "") & IF(N20=1, IF(OR(M20=1, L20=1, K20=1, J20=1, I20=1), "-", "") & N$4, "") & IF(O20=1, IF(OR(N20=1, M20=1, L20=1, K20=1, J20=1, I20=1), "-", "") & O$4, "") & IF(P20=1, IF(I20=1, " - ", IF(J20=1, " - ", IF(K20=1, " - ", IF(L20=1, " - ", IF(M20=1, " - ", IF(N20=1, " - ", IF(O20=1, " - ", ""))))))) & P$4, "") -> 2018 | S20: =SUM(Hoja1!$I20:$P20) -> 1 | T20: =IF(OR(Hoja1!$J20=1,Hoja1!$K20=1,Hoja1!$L20=1,Hoja1!$M20=1,Hoja1!$N20=1,Hoja1!$O20=1,Hoja1!$P20=1),"SI","NO") -> NO | U20: =IF(OR(Hoja1!$K20=1,Hoja1!$L20=1,Hoja1!$M20=1,Hoja1!$N20=1,Hoja1!$O20=1,Hoja1!$P20=1),"SI","NO") -> NO | V20: 82 | W20: 0 | X20: 0 | Y20: 0 | Z20: 0 | AA20: 0 | AB20: 0 | AC20: 0 | AD20: 0 | AE20: 0 | AF20: 0 | AG20: 0 | AH20: 0 | AI20: 0 | AJ20: 0 | AK20: 0 | AL20: 0 | AM20: 0 | AN20: 0 | AO20: 0 | AP20: 0 | AQ20: 0 | AR20: =IF(Hoja1!$AQ20>0,Hoja1!$AQ20,IF(Hoja1!$AN20>0,Hoja1!$AN20,IF(Hoja1!$AK20>0,Hoja1!$AK20,IF(Hoja1!$AH20>0,Hoja1!$AH20,IF(Hoja1!$AE20>0,Hoja1!$AE20,IF(Hoja1!$AB20>0,Hoja1!$AB20,IF(Hoja1!$Y20>0,Hoja1!$Y20,IF(Hoja1!$V20>0,Hoja1!$V20," ---")))))))) -> 82 | AS20: 0 | AT20: 0 | AU20: 0 | AV20: 0 | AW20: 0 | AX20: 0 | AY20: 0 | AZ20: 0 | BA20: 0 | BB20: 0 | BC20: 0 | BD20: 0 | BE20: 0 | BF20: 0 | BG20: 0 | BH20: 0 | BI20: =IF('[1]DATA CONSOLIDADA 2018-2025 '!$BH20>'[1]DATA CONSOLIDADA 2018-2025 '!$AN20,"Incremento",IF('[1]DATA CONSOLIDADA 2018-2025 '!$AN20='[1]DATA CONSOLIDADA 2018-2025 '!$BH20,"Sin incremento",IF('[1]DATA CONSOLIDADA 2018-2025 '!$BH20<'[1]DATA CONSOLIDADA 2018-2025 '!$AN20,"Disminución"," ---"))) -> #REF! | BJ20: ='[1]DATA CONSOLIDADA 2018-2025 '!$BH20-'[1]DATA CONSOLIDADA 2018-2025 '!$BE20 -> #REF! | BK20: 0 | BL20: 0 | BM20: 0 | BN20: =IF('[1]DATA CONSOLIDADA 2018-2025 '!$BM20>'[1]DATA CONSOLIDADA 2018-2025 '!$BH20,"Incremento",IF('[1]DATA CONSOLIDADA 2018-2025 '!$BH20='[1]DATA CONSOLIDADA 2018-2025 '!$BM20,"Sin incremento",IF('[1]DATA CONSOLIDADA 2018-2025 '!$BM20<'[1]DATA CONSOLIDADA 2018-2025 '!$BH20,"Disminución"," ---"))) -> #REF! | BO20: ='[1]DATA CONSOLIDADA 2018-2025 '!$BM20-'[1]DATA CONSOLIDADA 2018-2025 '!$BH20 -> #REF! | BP20: 0 | BQ20: 0 | BR20: 0 | BS20: =IF('[1]DATA CONSOLIDADA 2018-2025 '!$BR20>'[1]DATA CONSOLIDADA 2018-2025 '!$BM20,"Incremento",IF('[1]DATA CONSOLIDADA 2018-2025 '!$BM20='[1]DATA CONSOLIDADA 2018-2025 '!$BR20,"Sin incremento",IF('[1]DATA CONSOLIDADA 2018-2025 '!$BR20<'[1]DATA CONSOLIDADA 2018-2025 '!$BM20,"Disminución"," ---"))) -> #REF! | BT20: ='[1]DATA CONSOLIDADA 2018-2025 '!$BR20-Hoja1!$BO20 -> #REF! | BU20: 0 | BV20: 0 | BW20: 0 | BX20: =IF('[1]DATA CONSOLIDADA 2018-2025 '!$BW20>'[1]DATA CONSOLIDADA 2018-2025 '!$BR20,"Incremento",IF('[1]DATA CONSOLIDADA 2018-2025 '!$BR20='[1]DATA CONSOLIDADA 2018-2025 '!$BW20,"Sin incremento",IF('[1]DATA CONSOLIDADA 2018-2025 '!$BW20<'[1]DATA CONSOLIDADA 2018-2025 '!$BR20,"Disminución"," ---"))) -> #REF! | BY20: ='[1]DATA CONSOLIDADA 2018-2025 '!$BW20-'[1]DATA CONSOLIDADA 2018-2025 '!$BR20 -> #REF! | BZ20: 0 | CA20: 0 | CB20: 0 | CC20: =IF('[1]DATA CONSOLIDADA 2018-2025 '!$CB20>'[1]DATA CONSOLIDADA 2018-2025 '!$BW20,"Incremento",IF('[1]DATA CONSOLIDADA 2018-2025 '!$BW20='[1]DATA CONSOLIDADA 2018-2025 '!$CB20,"Sin incremento",IF('[1]DATA CONSOLIDADA 2018-2025 '!$CB20<'[1]DATA CONSOLIDADA 2018-2025 '!$BW20,"Disminución"," ---"))) -> #REF! | CD20: ='[1]DATA CONSOLIDADA 2018-2025 '!$CB20-Hoja1!$BW20 -> #REF! | CE20: 0 | CF20: 0 | CG20: 0 | CH20: =IF('[1]DATA CONSOLIDADA 2018-2025 '!$CG20>'[1]DATA CONSOLIDADA 2018-2025 '!$CB20,"Incremento",IF('[1]DATA CONSOLIDADA 2018-2025 '!$CB20='[1]DATA CONSOLIDADA 2018-2025 '!$CG20,"Sin incremento",IF('[1]DATA CONSOLIDADA 2018-2025 '!$CG20<'[1]DATA CONSOLIDADA 2018-2025 '!$CB20,"Disminución"," ---"))) -> #REF! | CI20: ='[1]DATA CONSOLIDADA 2018-2025 '!$CG20-Hoja1!$CB20 -> #REF! | CJ20: ='[1]DATA CONSOLIDADA 2018-2025 '!$BE20+'[1]DATA CONSOLIDADA 2018-2025 '!$BH20+'[1]DATA CONSOLIDADA 2018-2025 '!$BM20+'[1]DATA CONSOLIDADA 2018-2025 '!$BR20+'[1]DATA CONSOLIDADA 2018-2025 '!$BW20+'[1]DATA CONSOLIDADA 2018-2025 '!$CB20+'[1]DATA CONSOLIDADA 2018-2025 '!$CG20 -> #REF! | CK20: 0 | CL20: 0 | CM20: 0 | CN20: =IF('[1]DATA CONSOLIDADA 2018-2025 '!$CM20>'[1]DATA CONSOLIDADA 2018-2025 '!$CG20,"Incremento",IF('[1]DATA CONSOLIDADA 2018-2025 '!$CG20='[1]DATA CONSOLIDADA 2018-2025 '!$CM20,"Sin incremento",IF('[1]DATA CONSOLIDADA 2018-2025 '!$CM20<'[1]DATA CONSOLIDADA 2018-2025 '!$CG20,"Disminución"," ---"))) -> #REF! | CO20: ='[1]DATA CONSOLIDADA 2018-2025 '!$CM20-Hoja1!$CG20 -> #REF! | CP20: 0 | CQ20: 0 | CR20: 0 | CS20: 0 | CT20: 0 | CU20: 0 | CV20: 0 | CW20: 0 | CX20: 0 | CY20: 0 | CZ20: 0 | DA20: 0 | DB20: 0 | DC20: 0 | DD20: 0 | DE20: 0 | DF20: 0 | DG20: 0 | DH20: 0 | DI20: 20602544495 | DJ20: ASOCIACION DE PRODUCTORES ECOLOGICOS AGRARIOS DEL DISTRITO DE QUICHES PROVINCIA DE SIHUAS-ANCASH | DK20: 01 Asociación
A21: ASOCIACION DE PRODUCTORES Y COMERCIANTES DE TARA DE PUCHKA | B21: TARA | C21: TARA | D21: ANCASH | E21: 021016 | F21: ANCASH | G21: HUARI | H21: UCO | I21: 1 | Q21: PAC | R21: =IF(I21=1, I$4, "") & IF(J21=1, IF(I21=1, "-", "") & J$4, "") & IF(K21=1, IF(OR(J21=1, I21=1), "-", "") & K$4, "") & IF(L21=1, IF(OR(K21=1, J21=1, I21=1), "-", "") & L$4, "") & IF(M21=1, IF(OR(L21=1, K21=1, J21=1, I21=1), "-", "") & M$4, "") & IF(N21=1, IF(OR(M21=1, L21=1, K21=1, J21=1, I21=1), "-", "") & N$4, "") & IF(O21=1, IF(OR(N21=1, M21=1, L21=1, K21=1, J21=1, I21=1), "-", "") & O$4, "") & IF(P21=1, IF(I21=1, " - ", IF(J21=1, " - ", IF(K21=1, " - ", IF(L21=1, " - ", IF(M21=1, " - ", IF(N21=1, " - ", IF(O21=1, " - ", ""))))))) & P$4, "") -> 2018 | S21: =SUM(Hoja1!$I21:$P21) -> 1 | T21: =IF(OR(Hoja1!$J21=1,Hoja1!$K21=1,Hoja1!$L21=1,Hoja1!$M21=1,Hoja1!$N21=1,Hoja1!$O21=1,Hoja1!$P21=1),"SI","NO") -> NO | U21: =IF(OR(Hoja1!$K21=1,Hoja1!$L21=1,Hoja1!$M21=1,Hoja1!$N21=1,Hoja1!$O21=1,Hoja1!$P21=1),"SI","NO") -> NO | V21: 39 | W21: 0 | X21: 0 | Y21: 0 | Z21: 0 | AA21: 0 | AB21: 0 | AC21: 0 | AD21: 0 | AE21: 0 | AF21: 0 | AG21: 0 | AH21: 0 | AI21: 0 | AJ21: 0 | AK21: 0 | AL21: 0 | AM21: 0 | AN21: 0 | AO21: 0 | AP21: 0 | AQ21: 0 | AR21: =IF(Hoja1!$AQ21>0,Hoja1!$AQ21,IF(Hoja1!$AN21>0,Hoja1!$AN21,IF(Hoja1!$AK21>0,Hoja1!$AK21,IF(Hoja1!$AH21>0,Hoja1!$AH21,IF(Hoja1!$AE21>0,Hoja1!$AE21,IF(Hoja1!$AB21>0,Hoja1!$AB21,IF(Hoja1!$Y21>0,Hoja1!$Y21,IF(Hoja1!$V21>0,Hoja1!$V21," ---")))))))) -> 39 | AS21: 0 | AT21: 0 | AU21: 0 | AV21: 0 | AW21: 0 | AX21: 0 | AY21: 0 | AZ21: 0 | BA21: 0 | BB21: 0 | BC21: 0 | BD21: 0 | BE21: 0 | BF21: 0 | BG21: 0 | BH21: 0 | BI21: =IF('[1]DATA CONSOLIDADA 2018-2025 '!$BH21>'[1]DATA CONSOLIDADA 2018-2025 '!$AN21,"Incremento",IF('[1]DATA CONSOLIDADA 2018-2025 '!$AN21='[1]DATA CONSOLIDADA 2018-2025 '!$BH21,"Sin incremento",IF('[1]DATA CONSOLIDADA 2018-2025 '!$BH21<'[1]DATA CONSOLIDADA 2018-2025 '!$AN21,"Disminución"," ---"))) -> #REF! | BJ21: ='[1]DATA CONSOLIDADA 2018-2025 '!$BH21-'[1]DATA CONSOLIDADA 2018-2025 '!$BE21 -> #REF! | BK21: 0 | BL21: 0 | BM21: 0 | BN21: =IF('[1]DATA CONSOLIDADA 2018-2025 '!$BM21>'[1]DATA CONSOLIDADA 2018-2025 '!$BH21,"Incremento",IF('[1]DATA CONSOLIDADA 2018-2025 '!$BH21='[1]DATA CONSOLIDADA 2018-2025 '!$BM21,"Sin incremento",IF('[1]DATA CONSOLIDADA 2018-2025 '!$BM21<'[1]DATA CONSOLIDADA 2018-2025 '!$BH21,"Disminución"," ---"))) -> #REF! | BO21: ='[1]DATA CONSOLIDADA 2018-2025 '!$BM21-'[1]DATA CONSOLIDADA 2018-2025 '!$BH21 -> #REF! | BP21: 0 | BQ21: 0 | BR21: 0 | BS21: =IF('[1]DATA CONSOLIDADA 2018-2025 '!$BR21>'[1]DATA CONSOLIDADA 2018-2025 '!$BM21,"Incremento",IF('[1]DATA CONSOLIDADA 2018-2025 '!$BM21='[1]DATA CONSOLIDADA 2018-2025 '!$BR21,"Sin incremento",IF('[1]DATA CONSOLIDADA 2018-2025 '!$BR21<'[1]DATA CONSOLIDADA 2018-2025 '!$BM21,"Disminución"," ---"))) -> #REF! | BT21: ='[1]DATA CONSOLIDADA 2018-2025 '!$BR21-Hoja1!$BO21 -> #REF! | BU21: 0 | BV21: 0 | BW21: 0 | BX21: =IF('[1]DATA CONSOLIDADA 2018-2025 '!$BW21>'[1]DATA CONSOLIDADA 2018-2025 '!$BR21,"Incremento",IF('[1]DATA CONSOLIDADA 2018-2025 '!$BR21='[1]DATA CONSOLIDADA 2018-2025 '!$BW21,"Sin incremento",IF('[1]DATA CONSOLIDADA 2018-2025 '!$BW21<'[1]DATA CONSOLIDADA 2018-2025 '!$BR21,"Disminución"," ---"))) -> #REF! | BY21: ='[1]DATA CONSOLIDADA 2018-2025 '!$BW21-'[1]DATA CONSOLIDADA 2018-2025 '!$BR21 -> #REF! | BZ21: 0 | CA21: 0 | CB21: 0 | CC21: =IF('[1]DATA CONSOLIDADA 2018-2025 '!$CB21>'[1]DATA CONSOLIDADA 2018-2025 '!$BW21,"Incremento",IF('[1]DATA CONSOLIDADA 2018-2025 '!$BW21='[1]DATA CONSOLIDADA 2018-2025 '!$CB21,"Sin incremento",IF('[1]DATA CONSOLIDADA 2018-2025 '!$CB21<'[1]DATA CONSOLIDADA 2018-2025 '!$BW21,"Disminución"," ---"))) -> #REF! | CD21: ='[1]DATA CONSOLIDADA 2018-2025 '!$CB21-Hoja1!$BW21 -> #REF! | CE21: 0 | CF21: 0 | CG21: 0 | CH21: =IF('[1]DATA CONSOLIDADA 2018-2025 '!$CG21>'[1]DATA CONSOLIDADA 2018-2025 '!$CB21,"Incremento",IF('[1]DATA CONSOLIDADA 2018-2025 '!$CB21='[1]DATA CONSOLIDADA 2018-2025 '!$CG21,"Sin incremento",IF('[1]DATA CONSOLIDADA 2018-2025 '!$CG21<'[1]DATA CONSOLIDADA 2018-2025 '!$CB21,"Disminución"," ---"))) -> #REF! | CI21: ='[1]DATA CONSOLIDADA 2018-2025 '!$CG21-Hoja1!$CB21 -> #REF! | CJ21: ='[1]DATA CONSOLIDADA 2018-2025 '!$BE21+'[1]DATA CONSOLIDADA 2018-2025 '!$BH21+'[1]DATA CONSOLIDADA 2018-2025 '!$BM21+'[1]DATA CONSOLIDADA 2018-2025 '!$BR21+'[1]DATA CONSOLIDADA 2018-2025 '!$BW21+'[1]DATA CONSOLIDADA 2018-2025 '!$CB21+'[1]DATA CONSOLIDADA 2018-2025 '!$CG21 -> #REF! | CK21: 0 | CL21: 0 | CM21: 0 | CN21: =IF('[1]DATA CONSOLIDADA 2018-2025 '!$CM21>'[1]DATA CONSOLIDADA 2018-2025 '!$CG21,"Incremento",IF('[1]DATA CONSOLIDADA 2018-2025 '!$CG21='[1]DATA CONSOLIDADA 2018-2025 '!$CM21,"Sin incremento",IF('[1]DATA CONSOLIDADA 2018-2025 '!$CM21<'[1]DATA CONSOLIDADA 2018-2025 '!$CG21,"Disminución"," ---"))) -> #REF! | CO21: ='[1]DATA CONSOLIDADA 2018-2025 '!$CM21-Hoja1!$CG21 -> #REF! | CP21: 0 | CQ21: 0 | CR21: 0 | CS21: 0 | CT21: 0 | CU21: 0 | CV21: 0 | CW21: 0 | CX21: 0 | CY21: 0 | CZ21: 0 | DA21: 0 | DB21: 0 | DC21: 0 | DD21: 0 | DE21: 0 | DF21: 0 | DG21: 0 | DH21: 0 | DI21: 20534142146 | DJ21: ASOCIACION DE PRODUCTORES Y COMERCIANTES DE TARA DE PUCHKA | DK21: 01 Asociación
A22: GRUPO ASOCIADO PRODUCTORES DE CARAZ | B22: FLORES | C22: FLORES | D22: ANCASH | E22: 021201 | F22: ANCASH | G22: HUAYLAS | H22: CARAZ | I22: 1 | Q22: PAC | R22: =IF(I22=1, I$4, "") & IF(J22=1, IF(I22=1, "-", "") & J$4, "") & IF(K22=1, IF(OR(J22=1, I22=1), "-", "") & K$4, "") & IF(L22=1, IF(OR(K22=1, J22=1, I22=1), "-", "") & L$4, "") & IF(M22=1, IF(OR(L22=1, K22=1, J22=1, I22=1), "-", "") & M$4, "") & IF(N22=1, IF(OR(M22=1, L22=1, K22=1, J22=1, I22=1), "-", "") & N$4, "") & IF(O22=1, IF(OR(N22=1, M22=1, L22=1, K22=1, J22=1, I22=1), "-", "") & O$4, "") & IF(P22=1, IF(I22=1, " - ", IF(J22=1, " - ", IF(K22=1, " - ", IF(L22=1, " - ", IF(M22=1, " - ", IF(N22=1, " - ", IF(O22=1, " - ", ""))))))) & P$4, "") -> 2018 | S22: =SUM(Hoja1!$I22:$P22) -> 1 | T22: =IF(OR(Hoja1!$J22=1,Hoja1!$K22=1,Hoja1!$L22=1,Hoja1!$M22=1,Hoja1!$N22=1,Hoja1!$O22=1,Hoja1!$P22=1),"SI","NO") -> NO | U22: =IF(OR(Hoja1!$K22=1,Hoja1!$L22=1,Hoja1!$M22=1,Hoja1!$N22=1,Hoja1!$O22=1,Hoja1!$P22=1),"SI","NO") -> NO | V22: 4 | W22: 0 | X22: 0 | Y22: 0 | Z22: 0 | AA22: 0 | AB22: 0 | AC22: 0 | AD22: 0 | AE22: 0 | AF22: 0 | AG22: 0 | AH22: 0 | AI22: 0 | AJ22: 0 | AK22: 0 | AL22: 0 | AM22: 0 | AN22: 0 | AO22: 0 | AP22: 0 | AQ22: 0 | AR22: =IF(Hoja1!$AQ22>0,Hoja1!$AQ22,IF(Hoja1!$AN22>0,Hoja1!$AN22,IF(Hoja1!$AK22>0,Hoja1!$AK22,IF(Hoja1!$AH22>0,Hoja1!$AH22,IF(Hoja1!$AE22>0,Hoja1!$AE22,IF(Hoja1!$AB22>0,Hoja1!$AB22,IF(Hoja1!$Y22>0,Hoja1!$Y22,IF(Hoja1!$V22>0,Hoja1!$V22," ---")))))))) -> 4 | AS22: 0 | AT22: 0 | AU22: 0 | AV22: 0 | AW22: 0 | AX22: 0 | AY22: 0 | AZ22: 0 | BA22: 0 | BB22: 0 | BC22: 0 | BD22: 0 | BE22: 0 | BF22: 0 | BG22: 0 | BH22: 0 | BI22: =IF('[1]DATA CONSOLIDADA 2018-2025 '!$BH22>'[1]DATA CONSOLIDADA 2018-2025 '!$AN22,"Incremento",IF('[1]DATA CONSOLIDADA 2018-2025 '!$AN22='[1]DATA CONSOLIDADA 2018-2025 '!$BH22,"Sin incremento",IF('[1]DATA CONSOLIDADA 2018-2025 '!$BH22<'[1]DATA CONSOLIDADA 2018-2025 '!$AN22,"Disminución"," ---"))) -> #REF! | BJ22: ='[1]DATA CONSOLIDADA 2018-2025 '!$BH22-'[1]DATA CONSOLIDADA 2018-2025 '!$BE22 -> #REF! | BK22: 0 | BL22: 0 | BM22: 0 | BN22: =IF('[1]DATA CONSOLIDADA 2018-2025 '!$BM22>'[1]DATA CONSOLIDADA 2018-2025 '!$BH22,"Incremento",IF('[1]DATA CONSOLIDADA 2018-2025 '!$BH22='[1]DATA CONSOLIDADA 2018-2025 '!$BM22,"Sin incremento",IF('[1]DATA CONSOLIDADA 2018-2025 '!$BM22<'[1]DATA CONSOLIDADA 2018-2025 '!$BH22,"Disminución"," ---"))) -> #REF! | BO22: ='[1]DATA CONSOLIDADA 2018-2025 '!$BM22-'[1]DATA CONSOLIDADA 2018-2025 '!$BH22 -> #REF! | BP22: 0 | BQ22: 0 | BR22: 0 | BS22: =IF('[1]DATA CONSOLIDADA 2018-2025 '!$BR22>'[1]DATA CONSOLIDADA 2018-2025 '!$BM22,"Incremento",IF('[1]DATA CONSOLIDADA 2018-2025 '!$BM22='[1]DATA CONSOLIDADA 2018-2025 '!$BR22,"Sin incremento",IF('[1]DATA CONSOLIDADA 2018-2025 '!$BR22<'[1]DATA CONSOLIDADA 2018-2025 '!$BM22,"Disminución"," ---"))) -> #REF! | BT22: ='[1]DATA CONSOLIDADA 2018-2025 '!$BR22-Hoja1!$BO22 -> #REF! | BU22: 0 | BV22: 0 | BW22: 0 | BX22: =IF('[1]DATA CONSOLIDADA 2018-2025 '!$BW22>'[1]DATA CONSOLIDADA 2018-2025 '!$BR22,"Incremento",IF('[1]DATA CONSOLIDADA 2018-2025 '!$BR22='[1]DATA CONSOLIDADA 2018-2025 '!$BW22,"Sin incremento",IF('[1]DATA CONSOLIDADA 2018-2025 '!$BW22<'[1]DATA CONSOLIDADA 2018-2025 '!$BR22,"Disminución"," ---"))) -> #REF! | BY22: ='[1]DATA CONSOLIDADA 2018-2025 '!$BW22-'[1]DATA CONSOLIDADA 2018-2025 '!$BR22 -> #REF! | BZ22: 0 | CA22: 0 | CB22: 0 | CC22: =IF('[1]DATA CONSOLIDADA 2018-2025 '!$CB22>'[1]DATA CONSOLIDADA 2018-2025 '!$BW22,"Incremento",IF('[1]DATA CONSOLIDADA 2018-2025 '!$BW22='[1]DATA CONSOLIDADA 2018-2025 '!$CB22,"Sin incremento",IF('[1]DATA CONSOLIDADA 2018-2025 '!$CB22<'[1]DATA CONSOLIDADA 2018-2025 '!$BW22,"Disminución"," ---"))) -> #REF! | CD22: ='[1]DATA CONSOLIDADA 2018-2025 '!$CB22-Hoja1!$BW22 -> #REF! | CE22: 0 | CF22: 0 | CG22: 0 | CH22: =IF('[1]DATA CONSOLIDADA 2018-2025 '!$CG22>'[1]DATA CONSOLIDADA 2018-2025 '!$CB22,"Incremento",IF('[1]DATA CONSOLIDADA 2018-2025 '!$CB22='[1]DATA CONSOLIDADA 2018-2025 '!$CG22,"Sin incremento",IF('[1]DATA CONSOLIDADA 2018-2025 '!$CG22<'[1]DATA CONSOLIDADA 2018-2025 '!$CB22,"Disminución"," ---"))) -> #REF! | CI22: ='[1]DATA CONSOLIDADA 2018-2025 '!$CG22-Hoja1!$CB22 -> #REF! | CJ22: ='[1]DATA CONSOLIDADA 2018-2025 '!$BE22+'[1]DATA CONSOLIDADA 2018-2025 '!$BH22+'[1]DATA CONSOLIDADA 2018-2025 '!$BM22+'[1]DATA CONSOLIDADA 2018-2025 '!$BR22+'[1]DATA CONSOLIDADA 2018-2025 '!$BW22+'[1]DATA CONSOLIDADA 2018-2025 '!$CB22+'[1]DATA CONSOLIDADA 2018-2025 '!$CG22 -> #REF! | CK22: 0 | CL22: 0 | CM22: 0 | CN22: =IF('[1]DATA CONSOLIDADA 2018-2025 '!$CM22>'[1]DATA CONSOLIDADA 2018-2025 '!$CG22,"Incremento",IF('[1]DATA CONSOLIDADA 2018-2025 '!$CG22='[1]DATA CONSOLIDADA 2018-2025 '!$CM22,"Sin incremento",IF('[1]DATA CONSOLIDADA 2018-2025 '!$CM22<'[1]DATA CONSOLIDADA 2018-2025 '!$CG22,"Disminución"," ---"))) -> #REF! | CO22: ='[1]DATA CONSOLIDADA 2018-2025 '!$CM22-Hoja1!$CG22 -> #REF! | CP22: 0 | CQ22: 0 | CR22: 0 | CS22: 0 | CT22: 0 | CU22: 0 | CV22: 0 | CW22: 0 | CX22: 0 | CY22: 0 | CZ22: 0 | DA22: 0 | DB22: 0 | DC22: 0 | DD22: 0 | DE22: 0 | DF22: 0 | DG22: 0 | DH22: 0 | DI22: SIN RUC | DJ22: ND | DK22: 01 Asociación
A23: COOPERATIVA DE PRODUCTORES AGROECOLOGICOS LA PERLA DE LOS ANDES-CALLEJON DE HUAYLAS ANCASH | B23: TARWI | C23: TARWI | D23: ANCASH | E23: 021201 | F23: ANCASH | G23: HUAYLAS | H23: CARAZ | I23: 1 | J23: 1 | K23: 1 | L23: 1 | M23: 1 | N23: 1 | Q23: PAC | R23: =IF(I23=1, I$4, "") & IF(J23=1, IF(I23=1, "-", "") & J$4, "") & IF(K23=1, IF(OR(J23=1, I23=1), "-", "") & K$4, "") & IF(L23=1, IF(OR(K23=1, J23=1, I23=1), "-", "") & L$4, "") & IF(M23=1, IF(OR(L23=1, K23=1, J23=1, I23=1), "-", "") & M$4, "") & IF(N23=1, IF(OR(M23=1, L23=1, K23=1, J23=1, I23=1), "-", "") & N$4, "") & IF(O23=1, IF(OR(N23=1, M23=1, L23=1, K23=1, J23=1, I23=1), "-", "") & O$4, "") & IF(P23=1, IF(I23=1, " - ", IF(J23=1, " - ", IF(K23=1, " - ", IF(L23=1, " - ", IF(M23=1, " - ", IF(N23=1, " - ", IF(O23=1, " - ", ""))))))) & P$4, "") -> 2018-2019-2020-2021-2022-2023 | S23: =SUM(Hoja1!$I23:$P23) -> 6 | T23: =IF(OR(Hoja1!$J23=1,Hoja1!$K23=1,Hoja1!$L23=1,Hoja1!$M23=1,Hoja1!$N23=1,Hoja1!$O23=1,Hoja1!$P23=1),"SI","NO") -> SI | U23: =IF(OR(Hoja1!$K23=1,Hoja1!$L23=1,Hoja1!$M23=1,Hoja1!$N23=1,Hoja1!$O23=1,Hoja1!$P23=1),"SI","NO") -> SI | V23: 521 | W23: 79 | X23: 17 | Y23: 96 | Z23: 213 | AA23: 60 | AB23: 273 | AC23: 215 | AD23: 58 | AE23: 273 | AF23: 59 | AG23: 18 | AH23: 77 | AI23: 59 | AJ23: 18 | AK23: 77 | AL23: 0 | AM23: 0 | AN23: 0 | AO23: 0 | AP23: 0 | AQ23: 0 | AR23: =IF(Hoja1!$AQ23>0,Hoja1!$AQ23,IF(Hoja1!$AN23>0,Hoja1!$AN23,IF(Hoja1!$AK23>0,Hoja1!$AK23,IF(Hoja1!$AH23>0,Hoja1!$AH23,IF(Hoja1!$AE23>0,Hoja1!$AE23,IF(Hoja1!$AB23>0,Hoja1!$AB23,IF(Hoja1!$Y23>0,Hoja1!$Y23,IF(Hoja1!$V23>0,Hoja1!$V23," ---")))))))) -> 77 | AS23: 18 | AT23: 6 | AU23: 36 | AV23: 7 | AW23: 25 | AX23: 6 | AY23: 36 | AZ23: 2 | BA23: 0 | BB23: 0 | BC23: 0 | BD23: 0 | BE23: 0 | BF23: 11802.35 | BG23: 0 | BH23: 11802.35 | BI23: =IF('[1]DATA CONSOLIDADA 2018-2025 '!$BH23>'[1]DATA CONSOLIDADA 2018-2025 '!$AN23,"Incremento",IF('[1]DATA CONSOLIDADA 2018-2025 '!$AN23='[1]DATA CONSOLIDADA 2018-2025 '!$BH23,"Sin incremento",IF('[1]DATA CONSOLIDADA 2018-2025 '!$BH23<'[1]DATA CONSOLIDADA 2018-2025 '!$AN23,"Disminución"," ---"))) -> #REF! | BJ23: ='[1]DATA CONSOLIDADA 2018-2025 '!$BH23-'[1]DATA CONSOLIDADA 2018-2025 '!$BE23 -> #REF! | BK23: 109219.27 | BL23: 0 | BM23: 109219.27 | BN23: =IF('[1]DATA CONSOLIDADA 2018-2025 '!$BM23>'[1]DATA CONSOLIDADA 2018-2025 '!$BH23,"Incremento",IF('[1]DATA CONSOLIDADA 2018-2025 '!$BH23='[1]DATA CONSOLIDADA 2018-2025 '!$BM23,"Sin incremento",IF('[1]DATA CONSOLIDADA 2018-2025 '!$BM23<'[1]DATA CONSOLIDADA 2018-2025 '!$BH23,"Disminución"," ---"))) -> #REF! | BO23: ='[1]DATA CONSOLIDADA 2018-2025 '!$BM23-'[1]DATA CONSOLIDADA 2018-2025 '!$BH23 -> #REF! | BP23: 131381.75 | BQ23: 0 | BR23: 131381.75 | BS23: =IF('[1]DATA CONSOLIDADA 2018-2025 '!$BR23>'[1]DATA CONSOLIDADA 2018-2025 '!$BM23,"Incremento",IF('[1]DATA CONSOLIDADA 2018-2025 '!$BM23='[1]DATA CONSOLIDADA 2018-2025 '!$BR23,"Sin incremento",IF('[1]DATA CONSOLIDADA 2018-2025 '!$BR23<'[1]DATA CONSOLIDADA 2018-2025 '!$BM23,"Disminución"," ---"))) -> #REF! | BT23: ='[1]DATA CONSOLIDADA 2018-2025 '!$BR23-Hoja1!$BO23 -> #REF! | BU23: 129764.41 | BV23: 0 | BW23: 129764.41 | BX23: =IF('[1]DATA CONSOLIDADA 2018-2025 '!$BW23>'[1]DATA CONSOLIDADA 2018-2025 '!$BR23,"Incremento",IF('[1]DATA CONSOLIDADA 2018-2025 '!$BR23='[1]DATA CONSOLIDADA 2018-2025 '!$BW23,"Sin incremento",IF('[1]DATA CONSOLIDADA 2018-2025 '!$BW23<'[1]DATA CONSOLIDADA 2018-2025 '!$BR23,"Disminución"," ---"))) -> #REF! | BY23: ='[1]DATA CONSOLIDADA 2018-2025 '!$BW23-'[1]DATA CONSOLIDADA 2018-2025 '!$BR23 -> #REF! | BZ23: 141145.57 | CA23: 0 | CB23: 141145.57 | CC23: =IF('[1]DATA CONSOLIDADA 2018-2025 '!$CB23>'[1]DATA CONSOLIDADA 2018-2025 '!$BW23,"Incremento",IF('[1]DATA CONSOLIDADA 2018-2025 '!$BW23='[1]DATA CONSOLIDADA 2018-2025 '!$CB23,"Sin incremento",IF('[1]DATA CONSOLIDADA 2018-2025 '!$CB23<'[1]DATA CONSOLIDADA 2018-2025 '!$BW23,"Disminución"," ---"))) -> #REF! | CD23: ='[1]DATA CONSOLIDADA 2018-2025 '!$CB23-Hoja1!$BW23 -> #REF! | CE23: 0 | CF23: 0 | CG23: 0 | CH23: =IF('[1]DATA CONSOLIDADA 2018-2025 '!$CG23>'[1]DATA CONSOLIDADA 2018-2025 '!$CB23,"Incremento",IF('[1]DATA CONSOLIDADA 2018-2025 '!$CB23='[1]DATA CONSOLIDADA 2018-2025 '!$CG23,"Sin incremento",IF('[1]DATA CONSOLIDADA 2018-2025 '!$CG23<'[1]DATA CONSOLIDADA 2018-2025 '!$CB23,"Disminución"," ---"))) -> #REF! | CI23: ='[1]DATA CONSOLIDADA 2018-2025 '!$CG23-Hoja1!$CB23 -> #REF! | CJ23: ='[1]DATA CONSOLIDADA 2018-2025 '!$BE23+'[1]DATA CONSOLIDADA 2018-2025 '!$BH23+'[1]DATA CONSOLIDADA 2018-2025 '!$BM23+'[1]DATA CONSOLIDADA 2018-2025 '!$BR23+'[1]DATA CONSOLIDADA 2018-2025 '!$BW23+'[1]DATA CONSOLIDADA 2018-2025 '!$CB23+'[1]DATA CONSOLIDADA 2018-2025 '!$CG23 -> #REF! | CK23: 0 | CL23: 0 | CM23: 0 | CN23: =IF('[1]DATA CONSOLIDADA 2018-2025 '!$CM23>'[1]DATA CONSOLIDADA 2018-2025 '!$CG23,"Incremento",IF('[1]DATA CONSOLIDADA 2018-2025 '!$CG23='[1]DATA CONSOLIDADA 2018-2025 '!$CM23,"Sin incremento",IF('[1]DATA CONSOLIDADA 2018-2025 '!$CM23<'[1]DATA CONSOLIDADA 2018-2025 '!$CG23,"Disminución"," ---"))) -> #REF! | CO23: ='[1]DATA CONSOLIDADA 2018-2025 '!$CM23-Hoja1!$CG23 -> #REF! | CP23: 0 | CQ23: 0 | CR23: 0 | CS23: 141147 | CT23: 0 | CU23: 0 | CV23: 141147 | CW23: 0 | CX23: 0 | CY23: 0 | CZ23: 0 | DA23: 0 | DB23: 0 | DC23: 0 | DD23: 0 | DE23: 0 | DF23: 0 | DG23: 0 | DH23: 0 | DI23: 20603223421 | DJ23: COOPERATIVA DE PRODUCTORES AGROECOLOGICOS LA PERLA DE LOS ANDES-CALLEJON DE HUAYLAS ANCASH | DK23: 02 Cooperativa
A24: ASOCIACIÓN DE SEMILLARISTAS DE MAIZ CHOCLO VIRGEN DE LAS MERCEDES DEL DISTRITO DE CHINGAS | B24: MAÍZ | C24: MAÍZ BLANCO GIGANTE | D24: ANCASH | E24: 020304 | F24: ANCASH | G24: ANTONIO RAYMONDI | H24: CHINGAS | I24: 1 | J24: 1 | K24: 1 | L24: 1 | M24: 1 | N24: 1 | Q24: PAC | R24: =IF(I24=1, I$4, "") & IF(J24=1, IF(I24=1, "-", "") & J$4, "") & IF(K24=1, IF(OR(J24=1, I24=1), "-", "") & K$4, "") & IF(L24=1, IF(OR(K24=1, J24=1, I24=1), "-", "") & L$4, "") & IF(M24=1, IF(OR(L24=1, K24=1, J24=1, I24=1), "-", "") & M$4, "") & IF(N24=1, IF(OR(M24=1, L24=1, K24=1, J24=1, I24=1), "-", "") & N$4, "") & IF(O24=1, IF(OR(N24=1, M24=1, L24=1, K24=1, J24=1, I24=1), "-", "") & O$4, "") & IF(P24=1, IF(I24=1, " - ", IF(J24=1, " - ", IF(K24=1, " - ", IF(L24=1, " - ", IF(M24=1, " - ", IF(N24=1, " - ", IF(O24=1, " - ", ""))))))) & P$4, "") -> 2018-2019-2020-2021-2022-2023 | S24: =SUM(Hoja1!$I24:$P24) -> 6 | T24: =IF(OR(Hoja1!$J24=1,Hoja1!$K24=1,Hoja1!$L24=1,Hoja1!$M24=1,Hoja1!$N24=1,Hoja1!$O24=1,Hoja1!$P24=1),"SI","NO") -> SI | U24: =IF(OR(Hoja1!$K24=1,Hoja1!$L24=1,Hoja1!$M24=1,Hoja1!$N24=1,Hoja1!$O24=1,Hoja1!$P24=1),"SI","NO") -> SI | V24: 28 | W24: 23 | X24: 3 | Y24: 26 | Z24: 23 | AA24: 3 | AB24: 26 | AC24: 20 | AD24: 3 | AE24: 23 | AF24: 20 | AG24: 3 | AH24: 23 | AI24: 20 | AJ24: 3 | AK24: 23 | AL24: 0 | AM24: 0 | AN24: 0 | AO24: 0 | AP24: 0 | AQ24: 0 | AR24: =IF(Hoja1!$AQ24>0,Hoja1!$AQ24,IF(Hoja1!$AN24>0,Hoja1!$AN24,IF(Hoja1!$AK24>0,Hoja1!$AK24,IF(Hoja1!$AH24>0,Hoja1!$AH24,IF(Hoja1!$AE24>0,Hoja1!$AE24,IF(Hoja1!$AB24>0,Hoja1!$AB24,IF(Hoja1!$Y24>0,Hoja1!$Y24,IF(Hoja1!$V24>0,Hoja1!$V24," ---")))))))) -> 23 | AS24: 3 | AT24: 0 | AU24: 44 | AV24: 8 | AW24: 25 | AX24: 5 | AY24: 34 | AZ24: 4 | BA24: 0 | BB24: 0 | BC24: 0 | BD24: 0 | BE24: 0 | BF24: 0 | BG24: 0 | BH24: 0 | BI24: =IF('[1]DATA CONSOLIDADA 2018-2025 '!$BH24>'[1]DATA CONSOLIDADA 2018-2025 '!$AN24,"Incremento",IF('[1]DATA CONSOLIDADA 2018-2025 '!$AN24='[1]DATA CONSOLIDADA 2018-2025 '!$BH24,"Sin incremento",IF('[1]DATA CONSOLIDADA 2018-2025 '!$BH24<'[1]DATA CONSOLIDADA 2018-2025 '!$AN24,"Disminución"," ---"))) -> #REF! | BJ24: ='[1]DATA CONSOLIDADA 2018-2025 '!$BH24-'[1]DATA CONSOLIDADA 2018-2025 '!$BE24 -> #REF! | BK24: 13830 | BL24: 0 | BM24: 13830 | BN24: =IF('[1]DATA CONSOLIDADA 2018-2025 '!$BM24>'[1]DATA CONSOLIDADA 2018-2025 '!$BH24,"Incremento",IF('[1]DATA CONSOLIDADA 2018-2025 '!$BH24='[1]DATA CONSOLIDADA 2018-2025 '!$BM24,"Sin incremento",IF('[1]DATA CONSOLIDADA 2018-2025 '!$BM24<'[1]DATA CONSOLIDADA 2018-2025 '!$BH24,"Disminución"," ---"))) -> #REF! | BO24: ='[1]DATA CONSOLIDADA 2018-2025 '!$BM24-'[1]DATA CONSOLIDADA 2018-2025 '!$BH24 -> #REF! | BP24: 378700 | BQ24: 0 | BR24: 378700 | BS24: =IF('[1]DATA CONSOLIDADA 2018-2025 '!$BR24>'[1]DATA CONSOLIDADA 2018-2025 '!$BM24,"Incremento",IF('[1]DATA CONSOLIDADA 2018-2025 '!$BM24='[1]DATA CONSOLIDADA 2018-2025 '!$BR24,"Sin incremento",IF('[1]DATA CONSOLIDADA 2018-2025 '!$BR24<'[1]DATA CONSOLIDADA 2018-2025 '!$BM24,"Disminución"," ---"))) -> #REF! | BT24: ='[1]DATA CONSOLIDADA 2018-2025 '!$BR24-Hoja1!$BO24 -> #REF! | BU24: 452800 | BV24: 0 | BW24: 452800 | BX24: =IF('[1]DATA CONSOLIDADA 2018-2025 '!$BW24>'[1]DATA CONSOLIDADA 2018-2025 '!$BR24,"Incremento",IF('[1]DATA CONSOLIDADA 2018-2025 '!$BR24='[1]DATA CONSOLIDADA 2018-2025 '!$BW24,"Sin incremento",IF('[1]DATA CONSOLIDADA 2018-2025 '!$BW24<'[1]DATA CONSOLIDADA 2018-2025 '!$BR24,"Disminución"," ---"))) -> #REF! | BY24: ='[1]DATA CONSOLIDADA 2018-2025 '!$BW24-'[1]DATA CONSOLIDADA 2018-2025 '!$BR24 -> #REF! | BZ24: 564965 | CA24: 0 | CB24: 564965 | CC24: =IF('[1]DATA CONSOLIDADA 2018-2025 '!$CB24>'[1]DATA CONSOLIDADA 2018-2025 '!$BW24,"Incremento",IF('[1]DATA CONSOLIDADA 2018-2025 '!$BW24='[1]DATA CONSOLIDADA 2018-2025 '!$CB24,"Sin incremento",IF('[1]DATA CONSOLIDADA 2018-2025 '!$CB24<'[1]DATA CONSOLIDADA 2018-2025 '!$BW24,"Disminución"," ---"))) -> #REF! | CD24: ='[1]DATA CONSOLIDADA 2018-2025 '!$CB24-Hoja1!$BW24 -> #REF! | CE24: 0 | CF24: 0 | CG24: 0 | CH24: =IF('[1]DATA CONSOLIDADA 2018-2025 '!$CG24>'[1]DATA CONSOLIDADA 2018-2025 '!$CB24,"Incremento",IF('[1]DATA CONSOLIDADA 2018-2025 '!$CB24='[1]DATA CONSOLIDADA 2018-2025 '!$CG24,"Sin incremento",IF('[1]DATA CONSOLIDADA 2018-2025 '!$CG24<'[1]DATA CONSOLIDADA 2018-2025 '!$CB24,"Disminución"," ---"))) -> #REF! | CI24: ='[1]DATA CONSOLIDADA 2018-2025 '!$CG24-Hoja1!$CB24 -> #REF! | CJ24: ='[1]DATA CONSOLIDADA 2018-2025 '!$BE24+'[1]DATA CONSOLIDADA 2018-2025 '!$BH24+'[1]DATA CONSOLIDADA 2018-2025 '!$BM24+'[1]DATA CONSOLIDADA 2018-2025 '!$BR24+'[1]DATA CONSOLIDADA 2018-2025 '!$BW24+'[1]DATA CONSOLIDADA 2018-2025 '!$CB24+'[1]DATA CONSOLIDADA 2018-2025 '!$CG24 -> #REF! | CK24: 0 | CL24: 0 | CM24: 0 | CN24: =IF('[1]DATA CONSOLIDADA 2018-2025 '!$CM24>'[1]DATA CONSOLIDADA 2018-2025 '!$CG24,"Incremento",IF('[1]DATA CONSOLIDADA 2018-2025 '!$CG24='[1]DATA CONSOLIDADA 2018-2025 '!$CM24,"Sin incremento",IF('[1]DATA CONSOLIDADA 2018-2025 '!$CM24<'[1]DATA CONSOLIDADA 2018-2025 '!$CG24,"Disminución"," ---"))) -> #REF! | CO24: ='[1]DATA CONSOLIDADA 2018-2025 '!$CM24-Hoja1!$CG24 -> #REF! | CP24: 0 | CQ24: 564965 | CR24: 0 | CS24: 0 | CT24: 0 | CU24: 0 | CV24: 564965 | CW24: 0 | CX24: 0 | CY24: 0 | CZ24: 0 | DA24: 0 | DB24: 0 | DC24: 0 | DD24: 0 | DE24: 0 | DF24: 0 | DG24: 0 | DH24: 0 | DI24: 20601547458 | DJ24: ASOCIACION DE SEMILLARISTAS DE MAIZ CHOCLO VIRGEN DE LA MERCEDES DEL DISTRITO DE CHINGAS | DK24: 01 Asociación
A25: ASOCIACION DE PRODUCTORES DE PALTOS MORO | B25: PALTA | C25: PALTA | D25: ANCASH | E25: 021805 | F25: ANCASH | G25: SANTA | H25: MORO | J25: 1 | Q25: PAC | R25: =IF(I25=1, I$4, "") & IF(J25=1, IF(I25=1, "-", "") & J$4, "") & IF(K25=1, IF(OR(J25=1, I25=1), "-", "") & K$4, "") & IF(L25=1, IF(OR(K25=1, J25=1, I25=1), "-", "") & L$4, "") & IF(M25=1, IF(OR(L25=1, K25=1, J25=1, I25=1), "-", "") & M$4, "") & IF(N25=1, IF(OR(M25=1, L25=1, K25=1, J25=1, I25=1), "-", "") & N$4, "") & IF(O25=1, IF(OR(N25=1, M25=1, L25=1, K25=1, J25=1, I25=1), "-", "") & O$4, "") & IF(P25=1, IF(I25=1, " - ", IF(J25=1, " - ", IF(K25=1, " - ", IF(L25=1, " - ", IF(M25=1, " - ", IF(N25=1, " - ", IF(O25=1, " - ", ""))))))) & P$4, "") -> 2019 | S25: =SUM(Hoja1!$I25:$P25) -> 1 | T25: =IF(OR(Hoja1!$J25=1,Hoja1!$K25=1,Hoja1!$L25=1,Hoja1!$M25=1,Hoja1!$N25=1,Hoja1!$O25=1,Hoja1!$P25=1),"SI","NO") -> SI | U25: =IF(OR(Hoja1!$K25=1,Hoja1!$L25=1,Hoja1!$M25=1,Hoja1!$N25=1,Hoja1!$O25=1,Hoja1!$P25=1),"SI","NO") -> NO | V25: 0 | W25: 33 | X25: 2 | Y25: 35 | Z25: 0 | AA25: 0 | AB25: 0 | AC25: 0 | AD25: 0 | AE25: 0 | AF25: 0 | AG25: 0 | AH25: 0 | AI25: 0 | AJ25: 0 | AK25: 0 | AL25: 0 | AM25: 0 | AN25: 0 | AO25: 0 | AP25: 0 | AQ25: 0 | AR25: =IF(Hoja1!$AQ25>0,Hoja1!$AQ25,IF(Hoja1!$AN25>0,Hoja1!$AN25,IF(Hoja1!$AK25>0,Hoja1!$AK25,IF(Hoja1!$AH25>0,Hoja1!$AH25,IF(Hoja1!$AE25>0,Hoja1!$AE25,IF(Hoja1!$AB25>0,Hoja1!$AB25,IF(Hoja1!$Y25>0,Hoja1!$Y25,IF(Hoja1!$V25>0,Hoja1!$V25," ---")))))))) -> 35 | AS25: 0 | AT25: 0 | AU25: 0 | AV25: 0 | AW25: 0 | AX25: 0 | AY25: 0 | AZ25: 0 | BA25: 0 | BB25: 0 | BC25: 0 | BD25: 0 | BE25: 0 | BF25: 260411.15 | BG25: 0 | BH25: 260411.15 | BI25: =IF('[1]DATA CONSOLIDADA 2018-2025 '!$BH25>'[1]DATA CONSOLIDADA 2018-2025 '!$AN25,"Incremento",IF('[1]DATA CONSOLIDADA 2018-2025 '!$AN25='[1]DATA CONSOLIDADA 2018-2025 '!$BH25,"Sin incremento",IF('[1]DATA CONSOLIDADA 2018-2025 '!$BH25<'[1]DATA CONSOLIDADA 2018-2025 '!$AN25,"Disminución"," ---"))) -> #REF! | BJ25: ='[1]DATA CONSOLIDADA 2018-2025 '!$BH25-'[1]DATA CONSOLIDADA 2018-2025 '!$BE25 -> #REF! | BK25: 0 | BL25: 0 | BM25: 0 | BN25: =IF('[1]DATA CONSOLIDADA 2018-2025 '!$BM25>'[1]DATA CONSOLIDADA 2018-2025 '!$BH25,"Incremento",IF('[1]DATA CONSOLIDADA 2018-2025 '!$BH25='[1]DATA CONSOLIDADA 2018-2025 '!$BM25,"Sin incremento",IF('[1]DATA CONSOLIDADA 2018-2025 '!$BM25<'[1]DATA CONSOLIDADA 2018-2025 '!$BH25,"Disminución"," ---"))) -> #REF! | BO25: ='[1]DATA CONSOLIDADA 2018-2025 '!$BM25-'[1]DATA CONSOLIDADA 2018-2025 '!$BH25 -> #REF! | BP25: 0 | BQ25: 0 | BR25: 0 | BS25: =IF('[1]DATA CONSOLIDADA 2018-2025 '!$BR25>'[1]DATA CONSOLIDADA 2018-2025 '!$BM25,"Incremento",IF('[1]DATA CONSOLIDADA 2018-2025 '!$BM25='[1]DATA CONSOLIDADA 2018-2025 '!$BR25,"Sin incremento",IF('[1]DATA CONSOLIDADA 2018-2025 '!$BR25<'[1]DATA CONSOLIDADA 2018-2025 '!$BM25,"Disminución"," ---"))) -> #REF! | BT25: ='[1]DATA CONSOLIDADA 2018-2025 '!$BR25-Hoja1!$BO25 -> #REF! | BU25: 0 | BV25: 0 | BW25: 0 | BX25: =IF('[1]DATA CONSOLIDADA 2018-2025 '!$BW25>'[1]DATA CONSOLIDADA 2018-2025 '!$BR25,"Incremento",IF('[1]DATA CONSOLIDADA 2018-2025 '!$BR25='[1]DATA CONSOLIDADA 2018-2025 '!$BW25,"Sin incremento",IF('[1]DATA CONSOLIDADA 2018-2025 '!$BW25<'[1]DATA CONSOLIDADA 2018-2025 '!$BR25,"Disminución"," ---"))) -> #REF! | BY25: ='[1]DATA CONSOLIDADA 2018-2025 '!$BW25-'[1]DATA CONSOLIDADA 2018-2025 '!$BR25 -> #REF! | BZ25: 0 | CA25: 0 | CB25: 0 | CC25: =IF('[1]DATA CONSOLIDADA 2018-2025 '!$CB25>'[1]DATA CONSOLIDADA 2018-2025 '!$BW25,"Incremento",IF('[1]DATA CONSOLIDADA 2018-2025 '!$BW25='[1]DATA CONSOLIDADA 2018-2025 '!$CB25,"Sin incremento",IF('[1]DATA CONSOLIDADA 2018-2025 '!$CB25<'[1]DATA CONSOLIDADA 2018-2025 '!$BW25,"Disminución"," ---"))) -> #REF! | CD25: ='[1]DATA CONSOLIDADA 2018-2025 '!$CB25-Hoja1!$BW25 -> #REF! | CE25: 0 | CF25: 0 | CG25: 0 | CH25: =IF('[1]DATA CONSOLIDADA 2018-2025 '!$CG25>'[1]DATA CONSOLIDADA 2018-2025 '!$CB25,"Incremento",IF('[1]DATA CONSOLIDADA 2018-2025 '!$CB25='[1]DATA CONSOLIDADA 2018-2025 '!$CG25,"Sin incremento",IF('[1]DATA CONSOLIDADA 2018-2025 '!$CG25<'[1]DATA CONSOLIDADA 2018-2025 '!$CB25,"Disminución"," ---"))) -> #REF! | CI25: ='[1]DATA CONSOLIDADA 2018-2025 '!$CG25-Hoja1!$CB25 -> #REF! | CJ25: ='[1]DATA CONSOLIDADA 2018-2025 '!$BE25+'[1]DATA CONSOLIDADA 2018-2025 '!$BH25+'[1]DATA CONSOLIDADA 2018-2025 '!$BM25+'[1]DATA CONSOLIDADA 2018-2025 '!$BR25+'[1]DATA CONSOLIDADA 2018-2025 '!$BW25+'[1]DATA CONSOLIDADA 2018-2025 '!$CB25+'[1]DATA CONSOLIDADA 2018-2025 '!$CG25 -> #REF! | CK25: 0 | CL25: 0 | CM25: 0 | CN25: =IF('[1]DATA CONSOLIDADA 2018-2025 '!$CM25>'[1]DATA CONSOLIDADA 2018-2025 '!$CG25,"Incremento",IF('[1]DATA CONSOLIDADA 2018-2025 '!$CG25='[1]DATA CONSOLIDADA 2018-2025 '!$CM25,"Sin incremento",IF('[1]DATA CONSOLIDADA 2018-2025 '!$CM25<'[1]DATA CONSOLIDADA 2018-2025 '!$CG25,"Disminución"," ---"))) -> #REF! | CO25: ='[1]DATA CONSOLIDADA 2018-2025 '!$CM25-Hoja1!$CG25 -> #REF! | CP25: 0 | CQ25: 0 | CR25: 0 | CS25: 0 | CT25: 0 | CU25: 0 | CV25: 0 | CW25: 0 | CX25: 0 | CY25: 0 | CZ25: 0 | DA25: 0 | DB25: 0 | DC25: 0 | DD25: 0 | DE25: 0 | DF25: 0 | DG25: 0 | DH25: 0 | DI25: 20603736703 | DJ25: ASOCIACION DE PRODUCTORES DE PALTOS MORO - APROPALMO | DK25: 01 Asociación
A26: COOPERATIVA AGRARIA VALLE FORTALEZA-COAVAF | B26: DURAZNO | C26: DURAZNO | D26: ANCASH | E26: 020503 | F26: ANCASH | G26: BOLOGNESI | H26: ANTONIO RAYMONDI | L26: 1 | Q26: PAC | R26: =IF(I26=1, I$4, "") & IF(J26=1, IF(I26=1, "-", "") & J$4, "") & IF(K26=1, IF(OR(J26=1, I26=1), "-", "") & K$4, "") & IF(L26=1, IF(OR(K26=1, J26=1, I26=1), "-", "") & L$4, "") & IF(M26=1, IF(OR(L26=1, K26=1, J26=1, I26=1), "-", "") & M$4, "") & IF(N26=1, IF(OR(M26=1, L26=1, K26=1, J26=1, I26=1), "-", "") & N$4, "") & IF(O26=1, IF(OR(N26=1, M26=1, L26=1, K26=1, J26=1, I26=1), "-", "") & O$4, "") & IF(P26=1, IF(I26=1, " - ", IF(J26=1, " - ", IF(K26=1, " - ", IF(L26=1, " - ", IF(M26=1, " - ", IF(N26=1, " - ", IF(O26=1, " - ", ""))))))) & P$4, "") -> 2021 | S26: =SUM(Hoja1!$I26:$P26) -> 1 | T26: =IF(OR(Hoja1!$J26=1,Hoja1!$K26=1,Hoja1!$L26=1,Hoja1!$M26=1,Hoja1!$N26=1,Hoja1!$O26=1,Hoja1!$P26=1),"SI","NO") -> SI | U26: =IF(OR(Hoja1!$K26=1,Hoja1!$L26=1,Hoja1!$M26=1,Hoja1!$N26=1,Hoja1!$O26=1,Hoja1!$P26=1),"SI","NO") -> SI | V26: 0 | W26: 0 | X26: 0 | Y26: 0 | Z26: 0 | AA26: 0 | AB26: 0 | AC26: 64 | AD26: 10 | AE26: 74 | AF26: 0 | AG26: 0 | AH26: 0 | AI26: 0 | AJ26: 0 | AK26: 0 | AL26: 0 | AM26: 0 | AN26: 0 | AO26: 0 | AP26: 0 | AQ26: 0 | AR26: =IF(Hoja1!$AQ26>0,Hoja1!$AQ26,IF(Hoja1!$AN26>0,Hoja1!$AN26,IF(Hoja1!$AK26>0,Hoja1!$AK26,IF(Hoja1!$AH26>0,Hoja1!$AH26,IF(Hoja1!$AE26>0,Hoja1!$AE26,IF(Hoja1!$AB26>0,Hoja1!$AB26,IF(Hoja1!$Y26>0,Hoja1!$Y26,IF(Hoja1!$V26>0,Hoja1!$V26," ---")))))))) -> 74 | AS26: 0 | AT26: 0 | AU26: 52 | AV26: 8 | AW26: 0 | AX26: 0 | AY26: 0 | AZ26: 0 | BA26: 0 | BB26: 0 | BC26: 0 | BD26: 0 | BE26: 0 | BF26: 0 | BG26: 0 | BH26: 0 | BI26: =IF('[1]DATA CONSOLIDADA 2018-2025 '!$BH26>'[1]DATA CONSOLIDADA 2018-2025 '!$AN26,"Incremento",IF('[1]DATA CONSOLIDADA 2018-2025 '!$AN26='[1]DATA CONSOLIDADA 2018-2025 '!$BH26,"Sin incremento",IF('[1]DATA CONSOLIDADA 2018-2025 '!$BH26<'[1]DATA CONSOLIDADA 2018-2025 '!$AN26,"Disminución"," ---"))) -> #REF! | BJ26: ='[1]DATA CONSOLIDADA 2018-2025 '!$BH26-'[1]DATA CONSOLIDADA 2018-2025 '!$BE26 -> #REF! | BK26: 0 | BL26: 0 | BM26: 0 | BN26: =IF('[1]DATA CONSOLIDADA 2018-2025 '!$BM26>'[1]DATA CONSOLIDADA 2018-2025 '!$BH26,"Incremento",IF('[1]DATA CONSOLIDADA 2018-2025 '!$BH26='[1]DATA CONSOLIDADA 2018-2025 '!$BM26,"Sin incremento",IF('[1]DATA CONSOLIDADA 2018-2025 '!$BM26<'[1]DATA CONSOLIDADA 2018-2025 '!$BH26,"Disminución"," ---"))) -> #REF! | BO26: ='[1]DATA CONSOLIDADA 2018-2025 '!$BM26-'[1]DATA CONSOLIDADA 2018-2025 '!$BH26 -> #REF! | BP26: 183225 | BQ26: 0 | BR26: 183225 | BS26: =IF('[1]DATA CONSOLIDADA 2018-2025 '!$BR26>'[1]DATA CONSOLIDADA 2018-2025 '!$BM26,"Incremento",IF('[1]DATA CONSOLIDADA 2018-2025 '!$BM26='[1]DATA CONSOLIDADA 2018-2025 '!$BR26,"Sin incremento",IF('[1]DATA CONSOLIDADA 2018-2025 '!$BR26<'[1]DATA CONSOLIDADA 2018-2025 '!$BM26,"Disminución"," ---"))) -> #REF! | BT26: ='[1]DATA CONSOLIDADA 2018-2025 '!$BR26-Hoja1!$BO26 -> #REF! | BU26: 0 | BV26: 0 | BW26: 0 | BX26: =IF('[1]DATA CONSOLIDADA 2018-2025 '!$BW26>'[1]DATA CONSOLIDADA 2018-2025 '!$BR26,"Incremento",IF('[1]DATA CONSOLIDADA 2018-2025 '!$BR26='[1]DATA CONSOLIDADA 2018-2025 '!$BW26,"Sin incremento",IF('[1]DATA CONSOLIDADA 2018-2025 '!$BW26<'[1]DATA CONSOLIDADA 2018-2025 '!$BR26,"Disminución"," ---"))) -> #REF! | BY26: ='[1]DATA CONSOLIDADA 2018-2025 '!$BW26-'[1]DATA CONSOLIDADA 2018-2025 '!$BR26 -> #REF! | BZ26: 0 | CA26: 0 | CB26: 0 | CC26: =IF('[1]DATA CONSOLIDADA 2018-2025 '!$CB26>'[1]DATA CONSOLIDADA 2018-2025 '!$BW26,"Incremento",IF('[1]DATA CONSOLIDADA 2018-2025 '!$BW26='[1]DATA CONSOLIDADA 2018-2025 '!$CB26,"Sin incremento",IF('[1]DATA CONSOLIDADA 2018-2025 '!$CB26<'[1]DATA CONSOLIDADA 2018-2025 '!$BW26,"Disminución"," ---"))) -> #REF! | CD26: ='[1]DATA CONSOLIDADA 2018-2025 '!$CB26-Hoja1!$BW26 -> #REF! | CE26: 0 | CF26: 0 | CG26: 0 | CH26: =IF('[1]DATA CONSOLIDADA 2018-2025 '!$CG26>'[1]DATA CONSOLIDADA 2018-2025 '!$CB26,"Incremento",IF('[1]DATA CONSOLIDADA 2018-2025 '!$CB26='[1]DATA CONSOLIDADA 2018-2025 '!$CG26,"Sin incremento",IF('[1]DATA CONSOLIDADA 2018-2025 '!$CG26<'[1]DATA CONSOLIDADA 2018-2025 '!$CB26,"Disminución"," ---"))) -> #REF! | CI26: ='[1]DATA CONSOLIDADA 2018-2025 '!$CG26-Hoja1!$CB26 -> #REF! | CJ26: ='[1]DATA CONSOLIDADA 2018-2025 '!$BE26+'[1]DATA CONSOLIDADA 2018-2025 '!$BH26+'[1]DATA CONSOLIDADA 2018-2025 '!$BM26+'[1]DATA CONSOLIDADA 2018-2025 '!$BR26+'[1]DATA CONSOLIDADA 2018-2025 '!$BW26+'[1]DATA CONSOLIDADA 2018-2025 '!$CB26+'[1]DATA CONSOLIDADA 2018-2025 '!$CG26 -> #REF! | CK26: 0 | CL26: 0 | CM26: 0 | CN26: =IF('[1]DATA CONSOLIDADA 2018-2025 '!$CM26>'[1]DATA CONSOLIDADA 2018-2025 '!$CG26,"Incremento",IF('[1]DATA CONSOLIDADA 2018-2025 '!$CG26='[1]DATA CONSOLIDADA 2018-2025 '!$CM26,"Sin incremento",IF('[1]DATA CONSOLIDADA 2018-2025 '!$CM26<'[1]DATA CONSOLIDADA 2018-2025 '!$CG26,"Disminución"," ---"))) -> #REF! | CO26: ='[1]DATA CONSOLIDADA 2018-2025 '!$CM26-Hoja1!$CG26 -> #REF! | CP26: 0 | CQ26: 0 | CR26: 0 | CS26: 0 | CT26: 0 | CU26: 0 | CV26: 0 | CW26: 0 | CX26: 0 | CY26: 0 | CZ26: 0 | DA26: 0 | DB26: 0 | DC26: 0 | DD26: 0 | DE26: 0 | DF26: 0 | DG26: 0 | DH26: 0 | DI26: 20600276221 | DJ26: COOPERATIVA AGRARIA VALLE FORTALEZA - COAVAFF | DK26: 02 Cooperativa
A27: ASOCIACION DE PRODUCTORES AGROECOLOGICOS DE PARIACOTO PROMOVIENDO VIDA SALUDABLE - APAPROVIS | B27: PALTA | C27: PALTA | D27: ANCASH | E27: 020110 | F27: ANCASH | G27: HUARAZ | H27: PARIACOTO | L27: 1 | M27: 1 | N27: 1 | O27: 1 | Q27: PAC | R27: =IF(I27=1, I$4, "") & IF(J27=1, IF(I27=1, "-", "") & J$4, "") & IF(K27=1, IF(OR(J27=1, I27=1), "-", "") & K$4, "") & IF(L27=1, IF(OR(K27=1, J27=1, I27=1), "-", "") & L$4, "") & IF(M27=1, IF(OR(L27=1, K27=1, J27=1, I27=1), "-", "") & M$4, "") & IF(N27=1, IF(OR(M27=1, L27=1, K27=1, J27=1, I27=1), "-", "") & N$4, "") & IF(O27=1, IF(OR(N27=1, M27=1, L27=1, K27=1, J27=1, I27=1), "-", "") & O$4, "") & IF(P27=1, IF(I27=1, " - ", IF(J27=1, " - ", IF(K27=1, " - ", IF(L27=1, " - ", IF(M27=1, " - ", IF(N27=1, " - ", IF(O27=1, " - ", ""))))))) & P$4, "") -> 2021-2022-2023-2024 | S27: =SUM(Hoja1!$I27:$P27) -> 4 | T27: =IF(OR(Hoja1!$J27=1,Hoja1!$K27=1,Hoja1!$L27=1,Hoja1!$M27=1,Hoja1!$N27=1,Hoja1!$O27=1,Hoja1!$P27=1),"SI","NO") -> SI | U27: =IF(OR(Hoja1!$K27=1,Hoja1!$L27=1,Hoja1!$M27=1,Hoja1!$N27=1,Hoja1!$O27=1,Hoja1!$P27=1),"SI","NO") -> SI | V27: 0 | W27: 0 | X27: 0 | Y27: 0 | Z27: 0 | AA27: 0 | AB27: 0 | AC27: 20 | AD27: 6 | AE27: 26 | AF27: 20 | AG27: 6 | AH27: 26 | AI27: 20 | AJ27: 6 | AK27: 26 | AL27: 20 | AM27: 6 | AN27: 26 | AO27: 0 | AP27: 0 | AQ27: 0 | AR27: =IF(Hoja1!$AQ27>0,Hoja1!$AQ27,IF(Hoja1!$AN27>0,Hoja1!$AN27,IF(Hoja1!$AK27>0,Hoja1!$AK27,IF(Hoja1!$AH27>0,Hoja1!$AH27,IF(Hoja1!$AE27>0,Hoja1!$AE27,IF(Hoja1!$AB27>0,Hoja1!$AB27,IF(Hoja1!$Y27>0,Hoja1!$Y27,IF(Hoja1!$V27>0,Hoja1!$V27," ---")))))))) -> 26 | AS27: 0 | AT27: 0 | AU27: 67 | AV27: 10 | AW27: 16 | AX27: 5 | AY27: 38 | AZ27: 1 | BA27: 30 | BB27: 0 | BC27: 0 | BD27: 0 | BE27: 0 | BF27: 0 | BG27: 0 | BH27: 0 | BI27: =IF('[1]DATA CONSOLIDADA 2018-2025 '!$BH27>'[1]DATA CONSOLIDADA 2018-2025 '!$AN27,"Incremento",IF('[1]DATA CONSOLIDADA 2018-2025 '!$AN27='[1]DATA CONSOLIDADA 2018-2025 '!$BH27,"Sin incremento",IF('[1]DATA CONSOLIDADA 2018-2025 '!$BH27<'[1]DATA CONSOLIDADA 2018-2025 '!$AN27,"Disminución"," ---"))) -> #REF! | BJ27: ='[1]DATA CONSOLIDADA 2018-2025 '!$BH27-'[1]DATA CONSOLIDADA 2018-2025 '!$BE27 -> #REF! | BK27: 0 | BL27: 0 | BM27: 0 | BN27: =IF('[1]DATA CONSOLIDADA 2018-2025 '!$BM27>'[1]DATA CONSOLIDADA 2018-2025 '!$BH27,"Incremento",IF('[1]DATA CONSOLIDADA 2018-2025 '!$BH27='[1]DATA CONSOLIDADA 2018-2025 '!$BM27,"Sin incremento",IF('[1]DATA CONSOLIDADA 2018-2025 '!$BM27<'[1]DATA CONSOLIDADA 2018-2025 '!$BH27,"Disminución"," ---"))) -> #REF! | BO27: ='[1]DATA CONSOLIDADA 2018-2025 '!$BM27-'[1]DATA CONSOLIDADA 2018-2025 '!$BH27 -> #REF! | BP27: 211492.7 | BQ27: 0 | BR27: 211492.7 | BS27: =IF('[1]DATA CONSOLIDADA 2018-2025 '!$BR27>'[1]DATA CONSOLIDADA 2018-2025 '!$BM27,"Incremento",IF('[1]DATA CONSOLIDADA 2018-2025 '!$BM27='[1]DATA CONSOLIDADA 2018-2025 '!$BR27,"Sin incremento",IF('[1]DATA CONSOLIDADA 2018-2025 '!$BR27<'[1]DATA CONSOLIDADA 2018-2025 '!$BM27,"Disminución"," ---"))) -> #REF! | BT27: ='[1]DATA CONSOLIDADA 2018-2025 '!$BR27-Hoja1!$BO27 -> #REF! | BU27: 52556.7 | BV27: 0 | BW27: 52556.7 | BX27: =IF('[1]DATA CONSOLIDADA 2018-2025 '!$BW27>'[1]DATA CONSOLIDADA 2018-2025 '!$BR27,"Incremento",IF('[1]DATA CONSOLIDADA 2018-2025 '!$BR27='[1]DATA CONSOLIDADA 2018-2025 '!$BW27,"Sin incremento",IF('[1]DATA CONSOLIDADA 2018-2025 '!$BW27<'[1]DATA CONSOLIDADA 2018-2025 '!$BR27,"Disminución"," ---"))) -> #REF! | BY27: ='[1]DATA CONSOLIDADA 2018-2025 '!$BW27-'[1]DATA CONSOLIDADA 2018-2025 '!$BR27 -> #REF! | BZ27: 77420.7 | CA27: 0 | CB27: 77420.7 | CC27: =IF('[1]DATA CONSOLIDADA 2018-2025 '!$CB27>'[1]DATA CONSOLIDADA 2018-2025 '!$BW27,"Incremento",IF('[1]DATA CONSOLIDADA 2018-2025 '!$BW27='[1]DATA CONSOLIDADA 2018-2025 '!$CB27,"Sin incremento",IF('[1]DATA CONSOLIDADA 2018-2025 '!$CB27<'[1]DATA CONSOLIDADA 2018-2025 '!$BW27,"Disminución"," ---"))) -> #REF! | CD27: ='[1]DATA CONSOLIDADA 2018-2025 '!$CB27-Hoja1!$BW27 -> #REF! | CE27: 48724 | CF27: 0 | CG27: 48724 | CH27: =IF('[1]DATA CONSOLIDADA 2018-2025 '!$CG27>'[1]DATA CONSOLIDADA 2018-2025 '!$CB27,"Incremento",IF('[1]DATA CONSOLIDADA 2018-2025 '!$CB27='[1]DATA CONSOLIDADA 2018-2025 '!$CG27,"Sin incremento",IF('[1]DATA CONSOLIDADA 2018-2025 '!$CG27<'[1]DATA CONSOLIDADA 2018-2025 '!$CB27,"Disminución"," ---"))) -> #REF! | CI27: ='[1]DATA CONSOLIDADA 2018-2025 '!$CG27-Hoja1!$CB27 -> #REF! | CJ27: ='[1]DATA CONSOLIDADA 2018-2025 '!$BE27+'[1]DATA CONSOLIDADA 2018-2025 '!$BH27+'[1]DATA CONSOLIDADA 2018-2025 '!$BM27+'[1]DATA CONSOLIDADA 2018-2025 '!$BR27+'[1]DATA CONSOLIDADA 2018-2025 '!$BW27+'[1]DATA CONSOLIDADA 2018-2025 '!$CB27+'[1]DATA CONSOLIDADA 2018-2025 '!$CG27 -> #REF! | CK27: 0 | CL27: 0 | CM27: 0 | CN27: =IF('[1]DATA CONSOLIDADA 2018-2025 '!$CM27>'[1]DATA CONSOLIDADA 2018-2025 '!$CG27,"Incremento",IF('[1]DATA CONSOLIDADA 2018-2025 '!$CG27='[1]DATA CONSOLIDADA 2018-2025 '!$CM27,"Sin incremento",IF('[1]DATA CONSOLIDADA 2018-2025 '!$CM27<'[1]DATA CONSOLIDADA 2018-2025 '!$CG27,"Disminución"," ---"))) -> #REF! | CO27: ='[1]DATA CONSOLIDADA 2018-2025 '!$CM27-Hoja1!$CG27 -> #REF! | CP27: 0 | CQ27: 77420.7 | CR27: 0 | CS27: 0 | CT27: 0 | CU27: 0 | CV27: 77420.7 | CW27: 0 | CX27: 48724 | CY27: 0 | CZ27: 0 | DA27: 0 | DB27: 48724 | DC27: 0 | DD27: 0 | DE27: 0 | DF27: 0 | DG27: 0 | DH27: 0 | DI27: 20605197583 | DJ27: ASOCIACION DE PRODUCTORES AGROECOLOGICOS DE PARIACOTO PROMOVIENDO VIDA SALUDABLE - APAPROVIS | DK27: 01 Asociación
A28: COOPERATIVA AGRARIA PURIFOR | B28: PALTA | C28: PALTA | D28: ANCASH | E28: 020507 | F28: ANCASH | G28: BOLOGNESI | H28: COLQUIOC | M28: 1 | N28: 1 | O28: 1 | P28: 1 | Q28: PAC | R28: =IF(I28=1, I$4, "") & IF(J28=1, IF(I28=1, "-", "") & J$4, "") & IF(K28=1, IF(OR(J28=1, I28=1), "-", "") & K$4, "") & IF(L28=1, IF(OR(K28=1, J28=1, I28=1), "-", "") & L$4, "") & IF(M28=1, IF(OR(L28=1, K28=1, J28=1, I28=1), "-", "") & M$4, "") & IF(N28=1, IF(OR(M28=1, L28=1, K28=1, J28=1, I28=1), "-", "") & N$4, "") & IF(O28=1, IF(OR(N28=1, M28=1, L28=1, K28=1, J28=1, I28=1), "-", "") & O$4, "") & IF(P28=1, IF(I28=1, " - ", IF(J28=1, " - ", IF(K28=1, " - ", IF(L28=1, " - ", IF(M28=1, " - ", IF(N28=1, " - ", IF(O28=1, " - ", ""))))))) & P$4, "") -> 2022-2023-2024 - 2025 | S28: =SUM(Hoja1!$I28:$P28) -> 4 | T28: =IF(OR(Hoja1!$J28=1,Hoja1!$K28=1,Hoja1!$L28=1,Hoja1!$M28=1,Hoja1!$N28=1,Hoja1!$O28=1,Hoja1!$P28=1),"SI","NO") -> SI | U28: =IF(OR(Hoja1!$K28=1,Hoja1!$L28=1,Hoja1!$M28=1,Hoja1!$N28=1,Hoja1!$O28=1,Hoja1!$P28=1),"SI","NO") -> SI | V28: 0 | W28: 0 | X28: 0 | Y28: 0 | Z28: 0 | AA28: 0 | AB28: 0 | AC28: 0 | AD28: 0 | AE28: 0 | AF28: 57 | AG28: 29 | AH28: 86 | AI28: 57 | AJ28: 29 | AK28: 86 | AL28: 61 | AM28: 25 | AN28: 86 | AO28: 59 | AP28: 25 | AQ28: 84 | AR28: =IF(Hoja1!$AQ28>0,Hoja1!$AQ28,IF(Hoja1!$AN28>0,Hoja1!$AN28,IF(Hoja1!$AK28>0,Hoja1!$AK28,IF(Hoja1!$AH28>0,Hoja1!$AH28,IF(Hoja1!$AE28>0,Hoja1!$AE28,IF(Hoja1!$AB28>0,Hoja1!$AB28,IF(Hoja1!$Y28>0,Hoja1!$Y28,IF(Hoja1!$V28>0,Hoja1!$V28," ---")))))))) -> 84 | AS28: 0 | AT28: 0 | AU28: 0 | AV28: 0 | AW28: 19 | AX28: 5 | AY28: 38 | AZ28: 0 | BA28: 31 | BB28: 3 | BC28: 12 | BD28: 0 | BE28: 0 | BF28: 0 | BG28: 0 | BH28: 0 | BI28: =IF('[1]DATA CONSOLIDADA 2018-2025 '!$BH28>'[1]DATA CONSOLIDADA 2018-2025 '!$AN28,"Incremento",IF('[1]DATA CONSOLIDADA 2018-2025 '!$AN28='[1]DATA CONSOLIDADA 2018-2025 '!$BH28,"Sin incremento",IF('[1]DATA CONSOLIDADA 2018-2025 '!$BH28<'[1]DATA CONSOLIDADA 2018-2025 '!$AN28,"Disminución"," ---"))) -> #REF! | BJ28: ='[1]DATA CONSOLIDADA 2018-2025 '!$BH28-'[1]DATA CONSOLIDADA 2018-2025 '!$BE28 -> #REF! | BK28: 0 | BL28: 0 | BM28: 0 | BN28: =IF('[1]DATA CONSOLIDADA 2018-2025 '!$BM28>'[1]DATA CONSOLIDADA 2018-2025 '!$BH28,"Incremento",IF('[1]DATA CONSOLIDADA 2018-2025 '!$BH28='[1]DATA CONSOLIDADA 2018-2025 '!$BM28,"Sin incremento",IF('[1]DATA CONSOLIDADA 2018-2025 '!$BM28<'[1]DATA CONSOLIDADA 2018-2025 '!$BH28,"Disminución"," ---"))) -> #REF! | BO28: ='[1]DATA CONSOLIDADA 2018-2025 '!$BM28-'[1]DATA CONSOLIDADA 2018-2025 '!$BH28 -> #REF! | BP28: 0 | BQ28: 0 | BR28: 0 | BS28: =IF('[1]DATA CONSOLIDADA 2018-2025 '!$BR28>'[1]DATA CONSOLIDADA 2018-2025 '!$BM28,"Incremento",IF('[1]DATA CONSOLIDADA 2018-2025 '!$BM28='[1]DATA CONSOLIDADA 2018-2025 '!$BR28,"Sin incremento",IF('[1]DATA CONSOLIDADA 2018-2025 '!$BR28<'[1]DATA CONSOLIDADA 2018-2025 '!$BM28,"Disminución"," ---"))) -> #REF! | BT28: ='[1]DATA CONSOLIDADA 2018-2025 '!$BR28-Hoja1!$BO28 -> #REF! | BU28: 351529.15 | BV28: 0 | BW28: 351529.15 | BX28: =IF('[1]DATA CONSOLIDADA 2018-2025 '!$BW28>'[1]DATA CONSOLIDADA 2018-2025 '!$BR28,"Incremento",IF('[1]DATA CONSOLIDADA 2018-2025 '!$BR28='[1]DATA CONSOLIDADA 2018-2025 '!$BW28,"Sin incremento",IF('[1]DATA CONSOLIDADA 2018-2025 '!$BW28<'[1]DATA CONSOLIDADA 2018-2025 '!$BR28,"Disminución"," ---"))) -> #REF! | BY28: ='[1]DATA CONSOLIDADA 2018-2025 '!$BW28-'[1]DATA CONSOLIDADA 2018-2025 '!$BR28 -> #REF! | BZ28: 100445.5 | CA28: 0 | CB28: 100445.5 | CC28: =IF('[1]DATA CONSOLIDADA 2018-2025 '!$CB28>'[1]DATA CONSOLIDADA 2018-2025 '!$BW28,"Incremento",IF('[1]DATA CONSOLIDADA 2018-2025 '!$BW28='[1]DATA CONSOLIDADA 2018-2025 '!$CB28,"Sin incremento",IF('[1]DATA CONSOLIDADA 2018-2025 '!$CB28<'[1]DATA CONSOLIDADA 2018-2025 '!$BW28,"Disminución"," ---"))) -> #REF! | CD28: ='[1]DATA CONSOLIDADA 2018-2025 '!$CB28-Hoja1!$BW28 -> #REF! | CE28: 362155.2 | CF28: 0 | CG28: 362155.2 | CH28: =IF('[1]DATA CONSOLIDADA 2018-2025 '!$CG28>'[1]DATA CONSOLIDADA 2018-2025 '!$CB28,"Incremento",IF('[1]DATA CONSOLIDADA 2018-2025 '!$CB28='[1]DATA CONSOLIDADA 2018-2025 '!$CG28,"Sin incremento",IF('[1]DATA CONSOLIDADA 2018-2025 '!$CG28<'[1]DATA CONSOLIDADA 2018-2025 '!$CB28,"Disminución"," ---"))) -> #REF! | CI28: ='[1]DATA CONSOLIDADA 2018-2025 '!$CG28-Hoja1!$CB28 -> #REF! | CJ28: ='[1]DATA CONSOLIDADA 2018-2025 '!$BE28+'[1]DATA CONSOLIDADA 2018-2025 '!$BH28+'[1]DATA CONSOLIDADA 2018-2025 '!$BM28+'[1]DATA CONSOLIDADA 2018-2025 '!$BR28+'[1]DATA CONSOLIDADA 2018-2025 '!$BW28+'[1]DATA CONSOLIDADA 2018-2025 '!$CB28+'[1]DATA CONSOLIDADA 2018-2025 '!$CG28 -> #REF! | CK28: 488080 | CL28: 0 | CM28: 488080 | CN28: =IF('[1]DATA CONSOLIDADA 2018-2025 '!$CM28>'[1]DATA CONSOLIDADA 2018-2025 '!$CG28,"Incremento",IF('[1]DATA CONSOLIDADA 2018-2025 '!$CG28='[1]DATA CONSOLIDADA 2018-2025 '!$CM28,"Sin incremento",IF('[1]DATA CONSOLIDADA 2018-2025 '!$CM28<'[1]DATA CONSOLIDADA 2018-2025 '!$CG28,"Disminución"," ---"))) -> #REF! | CO28: ='[1]DATA CONSOLIDADA 2018-2025 '!$CM28-Hoja1!$CG28 -> #REF! | CP28: 0 | CQ28: 100445.5 | CR28: 0 | CS28: 0 | CT28: 0 | CU28: 0 | CV28: 100445.5 | CW28: 0 | CX28: 362155.2 | CY28: 0 | CZ28: 0 | DA28: 0 | DB28: 362155.2 | DC28: 0 | DD28: 470180 | DE28: 0 | DF28: 17900 | DG28: 0 | DH28: 488080 | DI28: 20407808666 | DJ28: COOPERATIVA AGRARIA PURIFOR - COOP PURIFOR | DK28: 02 Cooperativa
A29: COOPERATIVA AGRARIA ANDINA DE SANTA CRUZ LTDA. | B29: KIWICHA | C29: KIWICHA | D29: ANCASH | E29: 021208 | F29: ANCASH | G29: HUAYLAS | H29: SANTA CRUZ | M29: 1 | O29: 1 | P29: 1 | Q29: PAC | R29: =IF(I29=1, I$4, "") & IF(J29=1, IF(I29=1, "-", "") & J$4, "") & IF(K29=1, IF(OR(J29=1, I29=1), "-", "") & K$4, "") & IF(L29=1, IF(OR(K29=1, J29=1, I29=1), "-", "") & L$4, "") & IF(M29=1, IF(OR(L29=1, K29=1, J29=1, I29=1), "-", "") & M$4, "") & IF(N29=1, IF(OR(M29=1, L29=1, K29=1, J29=1, I29=1), "-", "") & N$4, "") & IF(O29=1, IF(OR(N29=1, M29=1, L29=1, K29=1, J29=1, I29=1), "-", "") & O$4, "") & IF(P29=1, IF(I29=1, " - ", IF(J29=1, " - ", IF(K29=1, " - ", IF(L29=1, " - ", IF(M29=1, " - ", IF(N29=1, " - ", IF(O29=1, " - ", ""))))))) & P$4, "") -> 2022-2024 - 2025 | S29: =SUM(Hoja1!$I29:$P29) -> 3 | T29: =IF(OR(Hoja1!$J29=1,Hoja1!$K29=1,Hoja1!$L29=1,Hoja1!$M29=1,Hoja1!$N29=1,Hoja1!$O29=1,Hoja1!$P29=1),"SI","NO") -> SI | U29: =IF(OR(Hoja1!$K29=1,Hoja1!$L29=1,Hoja1!$M29=1,Hoja1!$N29=1,Hoja1!$O29=1,Hoja1!$P29=1),"SI","NO") -> SI | V29: 0 | W29: 0 | X29: 0 | Y29: 0 | Z29: 0 | AA29: 0 | AB29: 0 | AC29: 0 | AD29: 0 | AE29: 0 | AF29: 9 | AG29: 10 | AH29: 19 | AI29: 0 | AJ29: 0 | AK29: 0 | AL29: 8 | AM29: 10 | AN29: 18 | AO29: 10 | AP29: 17 | AQ29: 27 | AR29: =IF(Hoja1!$AQ29>0,Hoja1!$AQ29,IF(Hoja1!$AN29>0,Hoja1!$AN29,IF(Hoja1!$AK29>0,Hoja1!$AK29,IF(Hoja1!$AH29>0,Hoja1!$AH29,IF(Hoja1!$AE29>0,Hoja1!$AE29,IF(Hoja1!$AB29>0,Hoja1!$AB29,IF(Hoja1!$Y29>0,Hoja1!$Y29,IF(Hoja1!$V29>0,Hoja1!$V29," ---")))))))) -> 27 | AS29: 0 | AT29: 0 | AU29: 0 | AV29: 0 | AW29: 22 | AX29: 6 | AY29: 0 | AZ29: 0 | BA29: 28 | BB29: 0 | BC29: 31 | BD29: 0 | BE29: 0 | BF29: 0 | BG29: 0 | BH29: 0 | BI29: =IF('[1]DATA CONSOLIDADA 2018-2025 '!$BH29>'[1]DATA CONSOLIDADA 2018-2025 '!$AN29,"Incremento",IF('[1]DATA CONSOLIDADA 2018-2025 '!$AN29='[1]DATA CONSOLIDADA 2018-2025 '!$BH29,"Sin incremento",IF('[1]DATA CONSOLIDADA 2018-2025 '!$BH29<'[1]DATA CONSOLIDADA 2018-2025 '!$AN29,"Disminución"," ---"))) -> #REF! | BJ29: ='[1]DATA CONSOLIDADA 2018-2025 '!$BH29-'[1]DATA CONSOLIDADA 2018-2025 '!$BE29 -> #REF! | BK29: 0 | BL29: 0 | BM29: 0 | BN29: =IF('[1]DATA CONSOLIDADA 2018-2025 '!$BM29>'[1]DATA CONSOLIDADA 2018-2025 '!$BH29,"Incremento",IF('[1]DATA CONSOLIDADA 2018-2025 '!$BH29='[1]DATA CONSOLIDADA 2018-2025 '!$BM29,"Sin incremento",IF('[1]DATA CONSOLIDADA 2018-2025 '!$BM29<'[1]DATA CONSOLIDADA 2018-2025 '!$BH29,"Disminución"," ---"))) -> #REF! | BO29: ='[1]DATA CONSOLIDADA 2018-2025 '!$BM29-'[1]DATA CONSOLIDADA 2018-2025 '!$BH29 -> #REF! | BP29: 0 | BQ29: 0 | BR29: 0 | BS29: =IF('[1]DATA CONSOLIDADA 2018-2025 '!$BR29>'[1]DATA CONSOLIDADA 2018-2025 '!$BM29,"Incremento",IF('[1]DATA CONSOLIDADA 2018-2025 '!$BM29='[1]DATA CONSOLIDADA 2018-2025 '!$BR29,"Sin incremento",IF('[1]DATA CONSOLIDADA 2018-2025 '!$BR29<'[1]DATA CONSOLIDADA 2018-2025 '!$BM29,"Disminución"," ---"))) -> #REF! | BT29: ='[1]DATA CONSOLIDADA 2018-2025 '!$BR29-Hoja1!$BO29 -> #REF! | BU29: 29700 | BV29: 0 | BW29: 29700 | BX29: =IF('[1]DATA CONSOLIDADA 2018-2025 '!$BW29>'[1]DATA CONSOLIDADA 2018-2025 '!$BR29,"Incremento",IF('[1]DATA CONSOLIDADA 2018-2025 '!$BR29='[1]DATA CONSOLIDADA 2018-2025 '!$BW29,"Sin incremento",IF('[1]DATA CONSOLIDADA 2018-2025 '!$BW29<'[1]DATA CONSOLIDADA 2018-2025 '!$BR29,"Disminución"," ---"))) -> #REF! | BY29: ='[1]DATA CONSOLIDADA 2018-2025 '!$BW29-'[1]DATA CONSOLIDADA 2018-2025 '!$BR29 -> #REF! | BZ29: 0 | CA29: 0 | CB29: 0 | CC29: =IF('[1]DATA CONSOLIDADA 2018-2025 '!$CB29>'[1]DATA CONSOLIDADA 2018-2025 '!$BW29,"Incremento",IF('[1]DATA CONSOLIDADA 2018-2025 '!$BW29='[1]DATA CONSOLIDADA 2018-2025 '!$CB29,"Sin incremento",IF('[1]DATA CONSOLIDADA 2018-2025 '!$CB29<'[1]DATA CONSOLIDADA 2018-2025 '!$BW29,"Disminución"," ---"))) -> #REF! | CD29: ='[1]DATA CONSOLIDADA 2018-2025 '!$CB29-Hoja1!$BW29 -> #REF! | CE29: 65663.1 | CF29: 0 | CG29: 65663.1 | CH29: =IF('[1]DATA CONSOLIDADA 2018-2025 '!$CG29>'[1]DATA CONSOLIDADA 2018-2025 '!$CB29,"Incremento",IF('[1]DATA CONSOLIDADA 2018-2025 '!$CB29='[1]DATA CONSOLIDADA 2018-2025 '!$CG29,"Sin incremento",IF('[1]DATA CONSOLIDADA 2018-2025 '!$CG29<'[1]DATA CONSOLIDADA 2018-2025 '!$CB29,"Disminución"," ---"))) -> #REF! | CI29: ='[1]DATA CONSOLIDADA 2018-2025 '!$CG29-Hoja1!$CB29 -> #REF! | CJ29: ='[1]DATA CONSOLIDADA 2018-2025 '!$BE29+'[1]DATA CONSOLIDADA 2018-2025 '!$BH29+'[1]DATA CONSOLIDADA 2018-2025 '!$BM29+'[1]DATA CONSOLIDADA 2018-2025 '!$BR29+'[1]DATA CONSOLIDADA 2018-2025 '!$BW29+'[1]DATA CONSOLIDADA 2018-2025 '!$CB29+'[1]DATA CONSOLIDADA 2018-2025 '!$CG29 -> #REF! | CK29: 28801.99 | CL29: 0 | CM29: 28801.99 | CN29: =IF('[1]DATA CONSOLIDADA 2018-2025 '!$CM29>'[1]DATA CONSOLIDADA 2018-2025 '!$CG29,"Incremento",IF('[1]DATA CONSOLIDADA 2018-2025 '!$CG29='[1]DATA CONSOLIDADA 2018-2025 '!$CM29,"Sin incremento",IF('[1]DATA CONSOLIDADA 2018-2025 '!$CM29<'[1]DATA CONSOLIDADA 2018-2025 '!$CG29,"Disminución"," ---"))) -> #REF! | CO29: ='[1]DATA CONSOLIDADA 2018-2025 '!$CM29-Hoja1!$CG29 -> #REF! | CP29: 0 | CQ29: 0 | CR29: 0 | CS29: 0 | CT29: 0 | CU29: 0 | CV29: 0 | CW29: 0 | CX29: 65663.1 | CY29: 0 | CZ29: 0 | DA29: 0 | DB29: 65663.1 | DC29: 1143.9897 | DD29: 27658 | DE29: 0 | DF29: 0 | DG29: 0 | DH29: 28801.99 | DI29: 20604755230 | DJ29: COOPERATIVA AGRARIA ANDINA DE SANTA CRUZ LTDA. | DK29: 02 Cooperativa
A30: COOPERATIVA AGRARIA KIWICHA WAYI LTDA | B30: KIWICHA | C30: KIWICHA | D30: ANCASH | E30: 021201 | F30: ANCASH | G30: HUAYLAS | H30: CARAZ | M30: 1 | N30: 1 | O30: 1 | P30: 1 | Q30: PAC | R30: =IF(I30=1, I$4, "") & IF(J30=1, IF(I30=1, "-", "") & J$4, "") & IF(K30=1, IF(OR(J30=1, I30=1), "-", "") & K$4, "") & IF(L30=1, IF(OR(K30=1, J30=1, I30=1), "-", "") & L$4, "") & IF(M30=1, IF(OR(L30=1, K30=1, J30=1, I30=1), "-", "") & M$4, "") & IF(N30=1, IF(OR(M30=1, L30=1, K30=1, J30=1, I30=1), "-", "") & N$4, "") & IF(O30=1, IF(OR(N30=1, M30=1, L30=1, K30=1, J30=1, I30=1), "-", "") & O$4, "") & IF(P30=1, IF(I30=1, " - ", IF(J30=1, " - ", IF(K30=1, " - ", IF(L30=1, " - ", IF(M30=1, " - ", IF(N30=1, " - ", IF(O30=1, " - ", ""))))))) & P$4, "") -> 2022-2023-2024 - 2025 | S30: =SUM(Hoja1!$I30:$P30) -> 4 | T30: =IF(OR(Hoja1!$J30=1,Hoja1!$K30=1,Hoja1!$L30=1,Hoja1!$M30=1,Hoja1!$N30=1,Hoja1!$O30=1,Hoja1!$P30=1),"SI","NO") -> SI | U30: =IF(OR(Hoja1!$K30=1,Hoja1!$L30=1,Hoja1!$M30=1,Hoja1!$N30=1,Hoja1!$O30=1,Hoja1!$P30=1),"SI","NO") -> SI | V30: 0 | W30: 0 | X30: 0 | Y30: 0 | Z30: 0 | AA30: 0 | AB30: 0 | AC30: 0 | AD30: 0 | AE30: 0 | AF30: 12 | AG30: 14 | AH30: 26 | AI30: 12 | AJ30: 14 | AK30: 26 | AL30: 11 | AM30: 14 | AN30: 25 | AO30: 11 | AP30: 14 | AQ30: 25 | AR30: =IF(Hoja1!$AQ30>0,Hoja1!$AQ30,IF(Hoja1!$AN30>0,Hoja1!$AN30,IF(Hoja1!$AK30>0,Hoja1!$AK30,IF(Hoja1!$AH30>0,Hoja1!$AH30,IF(Hoja1!$AE30>0,Hoja1!$AE30,IF(Hoja1!$AB30>0,Hoja1!$AB30,IF(Hoja1!$Y30>0,Hoja1!$Y30,IF(Hoja1!$V30>0,Hoja1!$V30," ---")))))))) -> 25 | AS30: 0 | AT30: 0 | AU30: 0 | AV30: 0 | AW30: 23 | AX30: 6 | AY30: 37 | AZ30: 3 | BA30: 25 | BB30: 3 | BC30: 29 | BD30: 2 | BE30: 0 | BF30: 0 | BG30: 0 | BH30: 0 | BI30: =IF('[1]DATA CONSOLIDADA 2018-2025 '!$BH30>'[1]DATA CONSOLIDADA 2018-2025 '!$AN30,"Incremento",IF('[1]DATA CONSOLIDADA 2018-2025 '!$AN30='[1]DATA CONSOLIDADA 2018-2025 '!$BH30,"Sin incremento",IF('[1]DATA CONSOLIDADA 2018-2025 '!$BH30<'[1]DATA CONSOLIDADA 2018-2025 '!$AN30,"Disminución"," ---"))) -> #REF! | BJ30: ='[1]DATA CONSOLIDADA 2018-2025 '!$BH30-'[1]DATA CONSOLIDADA 2018-2025 '!$BE30 -> #REF! | BK30: 0 | BL30: 0 | BM30: 0 | BN30: =IF('[1]DATA CONSOLIDADA 2018-2025 '!$BM30>'[1]DATA CONSOLIDADA 2018-2025 '!$BH30,"Incremento",IF('[1]DATA CONSOLIDADA 2018-2025 '!$BH30='[1]DATA CONSOLIDADA 2018-2025 '!$BM30,"Sin incremento",IF('[1]DATA CONSOLIDADA 2018-2025 '!$BM30<'[1]DATA CONSOLIDADA 2018-2025 '!$BH30,"Disminución"," ---"))) -> #REF! | BO30: ='[1]DATA CONSOLIDADA 2018-2025 '!$BM30-'[1]DATA CONSOLIDADA 2018-2025 '!$BH30 -> #REF! | BP30: 0 | BQ30: 0 | BR30: 0 | BS30: =IF('[1]DATA CONSOLIDADA 2018-2025 '!$BR30>'[1]DATA CONSOLIDADA 2018-2025 '!$BM30,"Incremento",IF('[1]DATA CONSOLIDADA 2018-2025 '!$BM30='[1]DATA CONSOLIDADA 2018-2025 '!$BR30,"Sin incremento",IF('[1]DATA CONSOLIDADA 2018-2025 '!$BR30<'[1]DATA CONSOLIDADA 2018-2025 '!$BM30,"Disminución"," ---"))) -> #REF! | BT30: ='[1]DATA CONSOLIDADA 2018-2025 '!$BR30-Hoja1!$BO30 -> #REF! | BU30: 88340 | BV30: 0 | BW30: 88340 | BX30: =IF('[1]DATA CONSOLIDADA 2018-2025 '!$BW30>'[1]DATA CONSOLIDADA 2018-2025 '!$BR30,"Incremento",IF('[1]DATA CONSOLIDADA 2018-2025 '!$BR30='[1]DATA CONSOLIDADA 2018-2025 '!$BW30,"Sin incremento",IF('[1]DATA CONSOLIDADA 2018-2025 '!$BW30<'[1]DATA CONSOLIDADA 2018-2025 '!$BR30,"Disminución"," ---"))) -> #REF! | BY30: ='[1]DATA CONSOLIDADA 2018-2025 '!$BW30-'[1]DATA CONSOLIDADA 2018-2025 '!$BR30 -> #REF! | BZ30: 132750.28 | CA30: 0 | CB30: 132750.28 | CC30: =IF('[1]DATA CONSOLIDADA 2018-2025 '!$CB30>'[1]DATA CONSOLIDADA 2018-2025 '!$BW30,"Incremento",IF('[1]DATA CONSOLIDADA 2018-2025 '!$BW30='[1]DATA CONSOLIDADA 2018-2025 '!$CB30,"Sin incremento",IF('[1]DATA CONSOLIDADA 2018-2025 '!$CB30<'[1]DATA CONSOLIDADA 2018-2025 '!$BW30,"Disminución"," ---"))) -> #REF! | CD30: ='[1]DATA CONSOLIDADA 2018-2025 '!$CB30-Hoja1!$BW30 -> #REF! | CE30: 197902 | CF30: 0 | CG30: 197902 | CH30: =IF('[1]DATA CONSOLIDADA 2018-2025 '!$CG30>'[1]DATA CONSOLIDADA 2018-2025 '!$CB30,"Incremento",IF('[1]DATA CONSOLIDADA 2018-2025 '!$CB30='[1]DATA CONSOLIDADA 2018-2025 '!$CG30,"Sin incremento",IF('[1]DATA CONSOLIDADA 2018-2025 '!$CG30<'[1]DATA CONSOLIDADA 2018-2025 '!$CB30,"Disminución"," ---"))) -> #REF! | CI30: ='[1]DATA CONSOLIDADA 2018-2025 '!$CG30-Hoja1!$CB30 -> #REF! | CJ30: ='[1]DATA CONSOLIDADA 2018-2025 '!$BE30+'[1]DATA CONSOLIDADA 2018-2025 '!$BH30+'[1]DATA CONSOLIDADA 2018-2025 '!$BM30+'[1]DATA CONSOLIDADA 2018-2025 '!$BR30+'[1]DATA CONSOLIDADA 2018-2025 '!$BW30+'[1]DATA CONSOLIDADA 2018-2025 '!$CB30+'[1]DATA CONSOLIDADA 2018-2025 '!$CG30 -> #REF! | CK30: 102372.15 | CL30: 0 | CM30: 102372.15 | CN30: =IF('[1]DATA CONSOLIDADA 2018-2025 '!$CM30>'[1]DATA CONSOLIDADA 2018-2025 '!$CG30,"Incremento",IF('[1]DATA CONSOLIDADA 2018-2025 '!$CG30='[1]DATA CONSOLIDADA 2018-2025 '!$CM30,"Sin incremento",IF('[1]DATA CONSOLIDADA 2018-2025 '!$CM30<'[1]DATA CONSOLIDADA 2018-2025 '!$CG30,"Disminución"," ---"))) -> #REF! | CO30: ='[1]DATA CONSOLIDADA 2018-2025 '!$CM30-Hoja1!$CG30 -> #REF! | CP30: 0 | CQ30: 59729 | CR30: 0 | CS30: 73021.284 | CT30: 0 | CU30: 0 | CV30: 132750.28 | CW30: 0 | CX30: 197902 | CY30: 0 | CZ30: 0 | DA30: 0 | DB30: 197902 | DC30: 0 | DD30: 77932.1 | DE30: 24440.055 | DF30: 0 | DG30: 0 | DH30: 102372.15 | DI30: 20600558715 | DJ30: COOPERATIVA AGRARIA KIWICHA WAYI LTDA | DK30: 02 Cooperativa
A31: ASOCIACION PRODUCTORES AGROPECUARIOS SANTA ROSA DE KIMAN AYLLU | B31: PALTA | C31: PALTA | D31: ANCASH | E31: 021210 | F31: ANCASH | G31: HUAYLAS | H31: YURACMARCA | M31: 1 | N31: 1 | O31: 1 | P31: 1 | Q31: PAC | R31: =IF(I31=1, I$4, "") & IF(J31=1, IF(I31=1, "-", "") & J$4, "") & IF(K31=1, IF(OR(J31=1, I31=1), "-", "") & K$4, "") & IF(L31=1, IF(OR(K31=1, J31=1, I31=1), "-", "") & L$4, "") & IF(M31=1, IF(OR(L31=1, K31=1, J31=1, I31=1), "-", "") & M$4, "") & IF(N31=1, IF(OR(M31=1, L31=1, K31=1, J31=1, I31=1), "-", "") & N$4, "") & IF(O31=1, IF(OR(N31=1, M31=1, L31=1, K31=1, J31=1, I31=1), "-", "") & O$4, "") & IF(P31=1, IF(I31=1, " - ", IF(J31=1, " - ", IF(K31=1, " - ", IF(L31=1, " - ", IF(M31=1, " - ", IF(N31=1, " - ", IF(O31=1, " - ", ""))))))) & P$4, "") -> 2022-2023-2024 - 2025 | S31: =SUM(Hoja1!$I31:$P31) -> 4 | T31: =IF(OR(Hoja1!$J31=1,Hoja1!$K31=1,Hoja1!$L31=1,Hoja1!$M31=1,Hoja1!$N31=1,Hoja1!$O31=1,Hoja1!$P31=1),"SI","NO") -> SI | U31: =IF(OR(Hoja1!$K31=1,Hoja1!$L31=1,Hoja1!$M31=1,Hoja1!$N31=1,Hoja1!$O31=1,Hoja1!$P31=1),"SI","NO") -> SI | V31: 0 | W31: 0 | X31: 0 | Y31: 0 | Z31: 0 | AA31: 0 | AB31: 0 | AC31: 0 | AD31: 0 | AE31: 0 | AF31: 13 | AG31: 7 | AH31: 20 | AI31: 13 | AJ31: 7 | AK31: 20 | AL31: 11 | AM31: 7 | AN31: 18 | AO31: 11 | AP31: 5 | AQ31: 16 | AR31: =IF(Hoja1!$AQ31>0,Hoja1!$AQ31,IF(Hoja1!$AN31>0,Hoja1!$AN31,IF(Hoja1!$AK31>0,Hoja1!$AK31,IF(Hoja1!$AH31>0,Hoja1!$AH31,IF(Hoja1!$AE31>0,Hoja1!$AE31,IF(Hoja1!$AB31>0,Hoja1!$AB31,IF(Hoja1!$Y31>0,Hoja1!$Y31,IF(Hoja1!$V31>0,Hoja1!$V31," ---")))))))) -> 16 | AS31: 0 | AT31: 0 | AU31: 0 | AV31: 0 | AW31: 19 | AX31: 5 | AY31: 44 | AZ31: 3 | BA31: 32 | BB31: 4 | BC31: 35 | BD31: 0 | BE31: 0 | BF31: 0 | BG31: 0 | BH31: 0 | BI31: =IF('[1]DATA CONSOLIDADA 2018-2025 '!$BH31>'[1]DATA CONSOLIDADA 2018-2025 '!$AN31,"Incremento",IF('[1]DATA CONSOLIDADA 2018-2025 '!$AN31='[1]DATA CONSOLIDADA 2018-2025 '!$BH31,"Sin incremento",IF('[1]DATA CONSOLIDADA 2018-2025 '!$BH31<'[1]DATA CONSOLIDADA 2018-2025 '!$AN31,"Disminución"," ---"))) -> #REF! | BJ31: ='[1]DATA CONSOLIDADA 2018-2025 '!$BH31-'[1]DATA CONSOLIDADA 2018-2025 '!$BE31 -> #REF! | BK31: 0 | BL31: 0 | BM31: 0 | BN31: =IF('[1]DATA CONSOLIDADA 2018-2025 '!$BM31>'[1]DATA CONSOLIDADA 2018-2025 '!$BH31,"Incremento",IF('[1]DATA CONSOLIDADA 2018-2025 '!$BH31='[1]DATA CONSOLIDADA 2018-2025 '!$BM31,"Sin incremento",IF('[1]DATA CONSOLIDADA 2018-2025 '!$BM31<'[1]DATA CONSOLIDADA 2018-2025 '!$BH31,"Disminución"," ---"))) -> #REF! | BO31: ='[1]DATA CONSOLIDADA 2018-2025 '!$BM31-'[1]DATA CONSOLIDADA 2018-2025 '!$BH31 -> #REF! | BP31: 0 | BQ31: 0 | BR31: 0 | BS31: =IF('[1]DATA CONSOLIDADA 2018-2025 '!$BR31>'[1]DATA CONSOLIDADA 2018-2025 '!$BM31,"Incremento",IF('[1]DATA CONSOLIDADA 2018-2025 '!$BM31='[1]DATA CONSOLIDADA 2018-2025 '!$BR31,"Sin incremento",IF('[1]DATA CONSOLIDADA 2018-2025 '!$BR31<'[1]DATA CONSOLIDADA 2018-2025 '!$BM31,"Disminución"," ---"))) -> #REF! | BT31: ='[1]DATA CONSOLIDADA 2018-2025 '!$BR31-Hoja1!$BO31 -> #REF! | BU31: 180390 | BV31: 0 | BW31: 180390 | BX31: =IF('[1]DATA CONSOLIDADA 2018-2025 '!$BW31>'[1]DATA CONSOLIDADA 2018-2025 '!$BR31,"Incremento",IF('[1]DATA CONSOLIDADA 2018-2025 '!$BR31='[1]DATA CONSOLIDADA 2018-2025 '!$BW31,"Sin incremento",IF('[1]DATA CONSOLIDADA 2018-2025 '!$BW31<'[1]DATA CONSOLIDADA 2018-2025 '!$BR31,"Disminución"," ---"))) -> #REF! | BY31: ='[1]DATA CONSOLIDADA 2018-2025 '!$BW31-'[1]DATA CONSOLIDADA 2018-2025 '!$BR31 -> #REF! | BZ31: 208400 | CA31: 0 | CB31: 208400 | CC31: =IF('[1]DATA CONSOLIDADA 2018-2025 '!$CB31>'[1]DATA CONSOLIDADA 2018-2025 '!$BW31,"Incremento",IF('[1]DATA CONSOLIDADA 2018-2025 '!$BW31='[1]DATA CONSOLIDADA 2018-2025 '!$CB31,"Sin incremento",IF('[1]DATA CONSOLIDADA 2018-2025 '!$CB31<'[1]DATA CONSOLIDADA 2018-2025 '!$BW31,"Disminución"," ---"))) -> #REF! | CD31: ='[1]DATA CONSOLIDADA 2018-2025 '!$CB31-Hoja1!$BW31 -> #REF! | CE31: 241803.66 | CF31: 0 | CG31: 241803.66 | CH31: =IF('[1]DATA CONSOLIDADA 2018-2025 '!$CG31>'[1]DATA CONSOLIDADA 2018-2025 '!$CB31,"Incremento",IF('[1]DATA CONSOLIDADA 2018-2025 '!$CB31='[1]DATA CONSOLIDADA 2018-2025 '!$CG31,"Sin incremento",IF('[1]DATA CONSOLIDADA 2018-2025 '!$CG31<'[1]DATA CONSOLIDADA 2018-2025 '!$CB31,"Disminución"," ---"))) -> #REF! | CI31: ='[1]DATA CONSOLIDADA 2018-2025 '!$CG31-Hoja1!$CB31 -> #REF! | CJ31: ='[1]DATA CONSOLIDADA 2018-2025 '!$BE31+'[1]DATA CONSOLIDADA 2018-2025 '!$BH31+'[1]DATA CONSOLIDADA 2018-2025 '!$BM31+'[1]DATA CONSOLIDADA 2018-2025 '!$BR31+'[1]DATA CONSOLIDADA 2018-2025 '!$BW31+'[1]DATA CONSOLIDADA 2018-2025 '!$CB31+'[1]DATA CONSOLIDADA 2018-2025 '!$CG31 -> #REF! | CK31: 189229.51 | CL31: 0 | CM31: 189229.51 | CN31: =IF('[1]DATA CONSOLIDADA 2018-2025 '!$CM31>'[1]DATA CONSOLIDADA 2018-2025 '!$CG31,"Incremento",IF('[1]DATA CONSOLIDADA 2018-2025 '!$CG31='[1]DATA CONSOLIDADA 2018-2025 '!$CM31,"Sin incremento",IF('[1]DATA CONSOLIDADA 2018-2025 '!$CM31<'[1]DATA CONSOLIDADA 2018-2025 '!$CG31,"Disminución"," ---"))) -> #REF! | CO31: ='[1]DATA CONSOLIDADA 2018-2025 '!$CM31-Hoja1!$CG31 -> #REF! | CP31: 0 | CQ31: 208400 | CR31: 0 | CS31: 0 | CT31: 0 | CU31: 0 | CV31: 208400 | CW31: 0 | CX31: 241803.66 | CY31: 0 | CZ31: 0 | DA31: 0 | DB31: 241803.66 | DC31: 0 | DD31: 152584.41 | DE31: 0 | DF31: 0 | DG31: 36645.095 | DH31: 189229.51 | DI31: 20533718176 | DJ31: ASOCIACION PRODUCTORES AGROPECUARIOS SANTA ROSA DE KIMAN AYLLU | DK31: 01 Asociación
A32: COOPERATIVA AGRARIA COYAPAPI | B32: PALTA | C32: PALTA | D32: ANCASH | E32: 020110 | F32: ANCASH | G32: HUARAZ | H32: PARIACOTO | M32: 1 | N32: 1 | O32: 1 | Q32: PAC | R32: =IF(I32=1, I$4, "") & IF(J32=1, IF(I32=1, "-", "") & J$4, "") & IF(K32=1, IF(OR(J32=1, I32=1), "-", "") & K$4, "") & IF(L32=1, IF(OR(K32=1, J32=1, I32=1), "-", "") & L$4, "") & IF(M32=1, IF(OR(L32=1, K32=1, J32=1, I32=1), "-", "") & M$4, "") & IF(N32=1, IF(OR(M32=1, L32=1, K32=1, J32=1, I32=1), "-", "") & N$4, "") & IF(O32=1, IF(OR(N32=1, M32=1, L32=1, K32=1, J32=1, I32=1), "-", "") & O$4, "") & IF(P32=1, IF(I32=1, " - ", IF(J32=1, " - ", IF(K32=1, " - ", IF(L32=1, " - ", IF(M32=1, " - ", IF(N32=1, " - ", IF(O32=1, " - ", ""))))))) & P$4, "") -> 2022-2023-2024 | S32: =SUM(Hoja1!$I32:$P32) -> 3 | T32: =IF(OR(Hoja1!$J32=1,Hoja1!$K32=1,Hoja1!$L32=1,Hoja1!$M32=1,Hoja1!$N32=1,Hoja1!$O32=1,Hoja1!$P32=1),"SI","NO") -> SI | U32: =IF(OR(Hoja1!$K32=1,Hoja1!$L32=1,Hoja1!$M32=1,Hoja1!$N32=1,Hoja1!$O32=1,Hoja1!$P32=1),"SI","NO") -> SI | V32: 0 | W32: 0 | X32: 0 | Y32: 0 | Z32: 0 | AA32: 0 | AB32: 0 | AC32: 0 | AD32: 0 | AE32: 0 | AF32: 132 | AG32: 19 | AH32: 151 | AI32: 132 | AJ32: 19 | AK32: 151 | AL32: 135 | AM32: 14 | AN32: 149 | AO32: 0 | AP32: 0 | AQ32: 0 | AR32: =IF(Hoja1!$AQ32>0,Hoja1!$AQ32,IF(Hoja1!$AN32>0,Hoja1!$AN32,IF(Hoja1!$AK32>0,Hoja1!$AK32,IF(Hoja1!$AH32>0,Hoja1!$AH32,IF(Hoja1!$AE32>0,Hoja1!$AE32,IF(Hoja1!$AB32>0,Hoja1!$AB32,IF(Hoja1!$Y32>0,Hoja1!$Y32,IF(Hoja1!$V32>0,Hoja1!$V32," ---")))))))) -> 149 | AS32: 0 | AT32: 0 | AU32: 0 | AV32: 0 | AW32: 17 | AX32: 5 | AY32: 37 | AZ32: 1 | BA32: 27 | BB32: 3 | BC32: 0 | BD32: 0 | BE32: 0 | BF32: 0 | BG32: 0 | BH32: 0 | BI32: =IF('[1]DATA CONSOLIDADA 2018-2025 '!$BH32>'[1]DATA CONSOLIDADA 2018-2025 '!$AN32,"Incremento",IF('[1]DATA CONSOLIDADA 2018-2025 '!$AN32='[1]DATA CONSOLIDADA 2018-2025 '!$BH32,"Sin incremento",IF('[1]DATA CONSOLIDADA 2018-2025 '!$BH32<'[1]DATA CONSOLIDADA 2018-2025 '!$AN32,"Disminución"," ---"))) -> #REF! | BJ32: ='[1]DATA CONSOLIDADA 2018-2025 '!$BH32-'[1]DATA CONSOLIDADA 2018-2025 '!$BE32 -> #REF! | BK32: 0 | BL32: 0 | BM32: 0 | BN32: =IF('[1]DATA CONSOLIDADA 2018-2025 '!$BM32>'[1]DATA CONSOLIDADA 2018-2025 '!$BH32,"Incremento",IF('[1]DATA CONSOLIDADA 2018-2025 '!$BH32='[1]DATA CONSOLIDADA 2018-2025 '!$BM32,"Sin incremento",IF('[1]DATA CONSOLIDADA 2018-2025 '!$BM32<'[1]DATA CONSOLIDADA 2018-2025 '!$BH32,"Disminución"," ---"))) -> #REF! | BO32: ='[1]DATA CONSOLIDADA 2018-2025 '!$BM32-'[1]DATA CONSOLIDADA 2018-2025 '!$BH32 -> #REF! | BP32: 0 | BQ32: 0 | BR32: 0 | BS32: =IF('[1]DATA CONSOLIDADA 2018-2025 '!$BR32>'[1]DATA CONSOLIDADA 2018-2025 '!$BM32,"Incremento",IF('[1]DATA CONSOLIDADA 2018-2025 '!$BM32='[1]DATA CONSOLIDADA 2018-2025 '!$BR32,"Sin incremento",IF('[1]DATA CONSOLIDADA 2018-2025 '!$BR32<'[1]DATA CONSOLIDADA 2018-2025 '!$BM32,"Disminución"," ---"))) -> #REF! | BT32: ='[1]DATA CONSOLIDADA 2018-2025 '!$BR32-Hoja1!$BO32 -> #REF! | BU32: 363932.5 | BV32: 0 | BW32: 363932.5 | BX32: =IF('[1]DATA CONSOLIDADA 2018-2025 '!$BW32>'[1]DATA CONSOLIDADA 2018-2025 '!$BR32,"Incremento",IF('[1]DATA CONSOLIDADA 2018-2025 '!$BR32='[1]DATA CONSOLIDADA 2018-2025 '!$BW32,"Sin incremento",IF('[1]DATA CONSOLIDADA 2018-2025 '!$BW32<'[1]DATA CONSOLIDADA 2018-2025 '!$BR32,"Disminución"," ---"))) -> #REF! | BY32: ='[1]DATA CONSOLIDADA 2018-2025 '!$BW32-'[1]DATA CONSOLIDADA 2018-2025 '!$BR32 -> #REF! | BZ32: 664665.6 | CA32: 0 | CB32: 664665.6 | CC32: =IF('[1]DATA CONSOLIDADA 2018-2025 '!$CB32>'[1]DATA CONSOLIDADA 2018-2025 '!$BW32,"Incremento",IF('[1]DATA CONSOLIDADA 2018-2025 '!$BW32='[1]DATA CONSOLIDADA 2018-2025 '!$CB32,"Sin incremento",IF('[1]DATA CONSOLIDADA 2018-2025 '!$CB32<'[1]DATA CONSOLIDADA 2018-2025 '!$BW32,"Disminución"," ---"))) -> #REF! | CD32: ='[1]DATA CONSOLIDADA 2018-2025 '!$CB32-Hoja1!$BW32 -> #REF! | CE32: 1376040 | CF32: 0 | CG32: 1376040 | CH32: =IF('[1]DATA CONSOLIDADA 2018-2025 '!$CG32>'[1]DATA CONSOLIDADA 2018-2025 '!$CB32,"Incremento",IF('[1]DATA CONSOLIDADA 2018-2025 '!$CB32='[1]DATA CONSOLIDADA 2018-2025 '!$CG32,"Sin incremento",IF('[1]DATA CONSOLIDADA 2018-2025 '!$CG32<'[1]DATA CONSOLIDADA 2018-2025 '!$CB32,"Disminución"," ---"))) -> #REF! | CI32: ='[1]DATA CONSOLIDADA 2018-2025 '!$CG32-Hoja1!$CB32 -> #REF! | CJ32: ='[1]DATA CONSOLIDADA 2018-2025 '!$BE32+'[1]DATA CONSOLIDADA 2018-2025 '!$BH32+'[1]DATA CONSOLIDADA 2018-2025 '!$BM32+'[1]DATA CONSOLIDADA 2018-2025 '!$BR32+'[1]DATA CONSOLIDADA 2018-2025 '!$BW32+'[1]DATA CONSOLIDADA 2018-2025 '!$CB32+'[1]DATA CONSOLIDADA 2018-2025 '!$CG32 -> #REF! | CK32: 0 | CL32: 0 | CM32: 0 | CN32: =IF('[1]DATA CONSOLIDADA 2018-2025 '!$CM32>'[1]DATA CONSOLIDADA 2018-2025 '!$CG32,"Incremento",IF('[1]DATA CONSOLIDADA 2018-2025 '!$CG32='[1]DATA CONSOLIDADA 2018-2025 '!$CM32,"Sin incremento",IF('[1]DATA CONSOLIDADA 2018-2025 '!$CM32<'[1]DATA CONSOLIDADA 2018-2025 '!$CG32,"Disminución"," ---"))) -> #REF! | CO32: ='[1]DATA CONSOLIDADA 2018-2025 '!$CM32-Hoja1!$CG32 -> #REF! | CP32: 0 | CQ32: 664665.6 | CR32: 0 | CS32: 0 | CT32: 0 | CU32: 0 | CV32: 664665.6 | CW32: 0 | CX32: 1376040 | CY32: 0 | CZ32: 0 | DA32: 0 | DB32: 1376040 | DC32: 0 | DD32: 0 | DE32: 0 | DF32: 0 | DG32: 0 | DH32: 0 | DI32: 20604218358 | DJ32: COOPERATIVA AGRARIA COYAPAPI | DK32: 02 Cooperativa
A33: ASOCIACIÓN DE FRUTICULTORES DEL VALLE PAMPAS- AFRUVAP | B33: PALTA | C33: PALTA | D33: APURIMAC | E33: 030601 | F33: APURIMAC | G33: CHINCHEROS | H33: CHINCHEROS | J33: 1 | K33: 1 | Q33: PAC | R33: =IF(I33=1, I$4, "") & IF(J33=1, IF(I33=1, "-", "") & J$4, "") & IF(K33=1, IF(OR(J33=1, I33=1), "-", "") & K$4, "") & IF(L33=1, IF(OR(K33=1, J33=1, I33=1), "-", "") & L$4, "") & IF(M33=1, IF(OR(L33=1, K33=1, J33=1, I33=1), "-", "") & M$4, "") & IF(N33=1, IF(OR(M33=1, L33=1, K33=1, J33=1, I33=1), "-", "") & N$4, "") & IF(O33=1, IF(OR(N33=1, M33=1, L33=1, K33=1, J33=1, I33=1), "-", "") & O$4, "") & IF(P33=1, IF(I33=1, " - ", IF(J33=1, " - ", IF(K33=1, " - ", IF(L33=1, " - ", IF(M33=1, " - ", IF(N33=1, " - ", IF(O33=1, " - ", ""))))))) & P$4, "") -> 2019-2020 | S33: =SUM(Hoja1!$I33:$P33) -> 2 | T33: =IF(OR(Hoja1!$J33=1,Hoja1!$K33=1,Hoja1!$L33=1,Hoja1!$M33=1,Hoja1!$N33=1,Hoja1!$O33=1,Hoja1!$P33=1),"SI","NO") -> SI | U33: =IF(OR(Hoja1!$K33=1,Hoja1!$L33=1,Hoja1!$M33=1,Hoja1!$N33=1,Hoja1!$O33=1,Hoja1!$P33=1),"SI","NO") -> SI | V33: 0 | W33: 15 | X33: 12 | Y33: 27 | Z33: 20 | AA33: 4 | AB33: 24 | AC33: 0 | AD33: 0 | AE33: 0 | AF33: 0 | AG33: 0 | AH33: 0 | AI33: 0 | AJ33: 0 | AK33: 0 | AL33: 0 | AM33: 0 | AN33: 0 | AO33: 0 | AP33: 0 | AQ33: 0 | AR33: =IF(Hoja1!$AQ33>0,Hoja1!$AQ33,IF(Hoja1!$AN33>0,Hoja1!$AN33,IF(Hoja1!$AK33>0,Hoja1!$AK33,IF(Hoja1!$AH33>0,Hoja1!$AH33,IF(Hoja1!$AE33>0,Hoja1!$AE33,IF(Hoja1!$AB33>0,Hoja1!$AB33,IF(Hoja1!$Y33>0,Hoja1!$Y33,IF(Hoja1!$V33>0,Hoja1!$V33," ---")))))))) -> 24 | AS33: 0 | AT33: 2 | AU33: 0 | AV33: 0 | AW33: 0 | AX33: 0 | AY33: 0 | AZ33: 0 | BA33: 0 | BB33: 0 | BC33: 0 | BD33: 0 | BE33: 0 | BF33: 0 | BG33: 0 | BH33: 0 | BI33: =IF('[1]DATA CONSOLIDADA 2018-2025 '!$BH33>'[1]DATA CONSOLIDADA 2018-2025 '!$AN33,"Incremento",IF('[1]DATA CONSOLIDADA 2018-2025 '!$AN33='[1]DATA CONSOLIDADA 2018-2025 '!$BH33,"Sin incremento",IF('[1]DATA CONSOLIDADA 2018-2025 '!$BH33<'[1]DATA CONSOLIDADA 2018-2025 '!$AN33,"Disminución"," ---"))) -> #REF! | BJ33: ='[1]DATA CONSOLIDADA 2018-2025 '!$BH33-'[1]DATA CONSOLIDADA 2018-2025 '!$BE33 -> #REF! | BK33: 324995 | BL33: 0 | BM33: 324995 | BN33: =IF('[1]DATA CONSOLIDADA 2018-2025 '!$BM33>'[1]DATA CONSOLIDADA 2018-2025 '!$BH33,"Incremento",IF('[1]DATA CONSOLIDADA 2018-2025 '!$BH33='[1]DATA CONSOLIDADA 2018-2025 '!$BM33,"Sin incremento",IF('[1]DATA CONSOLIDADA 2018-2025 '!$BM33<'[1]DATA CONSOLIDADA 2018-2025 '!$BH33,"Disminución"," ---"))) -> #REF! | BO33: ='[1]DATA CONSOLIDADA 2018-2025 '!$BM33-'[1]DATA CONSOLIDADA 2018-2025 '!$BH33 -> #REF! | BP33: 0 | BQ33: 0 | BR33: 0 | BS33: =IF('[1]DATA CONSOLIDADA 2018-2025 '!$BR33>'[1]DATA CONSOLIDADA 2018-2025 '!$BM33,"Incremento",IF('[1]DATA CONSOLIDADA 2018-2025 '!$BM33='[1]DATA CONSOLIDADA 2018-2025 '!$BR33,"Sin incremento",IF('[1]DATA CONSOLIDADA 2018-2025 '!$BR33<'[1]DATA CONSOLIDADA 2018-2025 '!$BM33,"Disminución"," ---"))) -> #REF! | BT33: ='[1]DATA CONSOLIDADA 2018-2025 '!$BR33-Hoja1!$BO33 -> #REF! | BU33: 0 | BV33: 0 | BW33: 0 | BX33: =IF('[1]DATA CONSOLIDADA 2018-2025 '!$BW33>'[1]DATA CONSOLIDADA 2018-2025 '!$BR33,"Incremento",IF('[1]DATA CONSOLIDADA 2018-2025 '!$BR33='[1]DATA CONSOLIDADA 2018-2025 '!$BW33,"Sin incremento",IF('[1]DATA CONSOLIDADA 2018-2025 '!$BW33<'[1]DATA CONSOLIDADA 2018-2025 '!$BR33,"Disminución"," ---"))) -> #REF! | BY33: ='[1]DATA CONSOLIDADA 2018-2025 '!$BW33-'[1]DATA CONSOLIDADA 2018-2025 '!$BR33 -> #REF! | BZ33: 0 | CA33: 0 | CB33: 0 | CC33: =IF('[1]DATA CONSOLIDADA 2018-2025 '!$CB33>'[1]DATA CONSOLIDADA 2018-2025 '!$BW33,"Incremento",IF('[1]DATA CONSOLIDADA 2018-2025 '!$BW33='[1]DATA CONSOLIDADA 2018-2025 '!$CB33,"Sin incremento",IF('[1]DATA CONSOLIDADA 2018-2025 '!$CB33<'[1]DATA CONSOLIDADA 2018-2025 '!$BW33,"Disminución"," ---"))) -> #REF! | CD33: ='[1]DATA CONSOLIDADA 2018-2025 '!$CB33-Hoja1!$BW33 -> #REF! | CE33: 0 | CF33: 0 | CG33: 0 | CH33: =IF('[1]DATA CONSOLIDADA 2018-2025 '!$CG33>'[1]DATA CONSOLIDADA 2018-2025 '!$CB33,"Incremento",IF('[1]DATA CONSOLIDADA 2018-2025 '!$CB33='[1]DATA CONSOLIDADA 2018-2025 '!$CG33,"Sin incremento",IF('[1]DATA CONSOLIDADA 2018-2025 '!$CG33<'[1]DATA CONSOLIDADA 2018-2025 '!$CB33,"Disminución"," ---"))) -> #REF! | CI33: ='[1]DATA CONSOLIDADA 2018-2025 '!$CG33-Hoja1!$CB33 -> #REF! | CJ33: ='[1]DATA CONSOLIDADA 2018-2025 '!$BE33+'[1]DATA CONSOLIDADA 2018-2025 '!$BH33+'[1]DATA CONSOLIDADA 2018-2025 '!$BM33+'[1]DATA CONSOLIDADA 2018-2025 '!$BR33+'[1]DATA CONSOLIDADA 2018-2025 '!$BW33+'[1]DATA CONSOLIDADA 2018-2025 '!$CB33+'[1]DATA CONSOLIDADA 2018-2025 '!$CG33 -> #REF! | CK33: 0 | CL33: 0 | CM33: 0 | CN33: =IF('[1]DATA CONSOLIDADA 2018-2025 '!$CM33>'[1]DATA CONSOLIDADA 2018-2025 '!$CG33,"Incremento",IF('[1]DATA CONSOLIDADA 2018-2025 '!$CG33='[1]DATA CONSOLIDADA 2018-2025 '!$CM33,"Sin incremento",IF('[1]DATA CONSOLIDADA 2018-2025 '!$CM33<'[1]DATA CONSOLIDADA 2018-2025 '!$CG33,"Disminución"," ---"))) -> #REF! | CO33: ='[1]DATA CONSOLIDADA 2018-2025 '!$CM33-Hoja1!$CG33 -> #REF! | CP33: 0 | CQ33: 0 | CR33: 0 | CS33: 0 | CT33: 0 | CU33: 0 | CV33: 0 | CW33: 0 | CX33: 0 | CY33: 0 | CZ33: 0 | DA33: 0 | DB33: 0 | DC33: 0 | DD33: 0 | DE33: 0 | DF33: 0 | DG33: 0 | DH33: 0 | DI33: 20527890285 | DJ33: ASOCIACION DE FRUTICULTORES DEL VALLE PAMPAS- AFRUVAP | DK33: 01 Asociación
A34: ASOCIACIÓN DE PRODUCTORES AGROPECUARIOS ORGANICOS VALLE PAMPAS - APAOVAP | B34: PALTA | C34: PALTA | D34: APURIMAC | E34: 030604 | F34: APURIMAC | G34: CHINCHEROS | H34: HUACCANA | I34: 1 | J34: 1 | K34: 1 | Q34: PAC | R34: =IF(I34=1, I$4, "") & IF(J34=1, IF(I34=1, "-", "") & J$4, "") & IF(K34=1, IF(OR(J34=1, I34=1), "-", "") & K$4, "") & IF(L34=1, IF(OR(K34=1, J34=1, I34=1), "-", "") & L$4, "") & IF(M34=1, IF(OR(L34=1, K34=1, J34=1, I34=1), "-", "") & M$4, "") & IF(N34=1, IF(OR(M34=1, L34=1, K34=1, J34=1, I34=1), "-", "") & N$4, "") & IF(O34=1, IF(OR(N34=1, M34=1, L34=1, K34=1, J34=1, I34=1), "-", "") & O$4, "") & IF(P34=1, IF(I34=1, " - ", IF(J34=1, " - ", IF(K34=1, " - ", IF(L34=1, " - ", IF(M34=1, " - ", IF(N34=1, " - ", IF(O34=1, " - ", ""))))))) & P$4, "") -> 2018-2019-2020 | S34: =SUM(Hoja1!$I34:$P34) -> 3 | T34: =IF(OR(Hoja1!$J34=1,Hoja1!$K34=1,Hoja1!$L34=1,Hoja1!$M34=1,Hoja1!$N34=1,Hoja1!$O34=1,Hoja1!$P34=1),"SI","NO") -> SI | U34: =IF(OR(Hoja1!$K34=1,Hoja1!$L34=1,Hoja1!$M34=1,Hoja1!$N34=1,Hoja1!$O34=1,Hoja1!$P34=1),"SI","NO") -> SI | V34: 37 | W34: 13 | X34: 15 | Y34: 28 | Z34: 11 | AA34: 8 | AB34: 19 | AC34: 0 | AD34: 0 | AE34: 0 | AF34: 0 | AG34: 0 | AH34: 0 | AI34: 0 | AJ34: 0 | AK34: 0 | AL34: 0 | AM34: 0 | AN34: 0 | AO34: 0 | AP34: 0 | AQ34: 0 | AR34: =IF(Hoja1!$AQ34>0,Hoja1!$AQ34,IF(Hoja1!$AN34>0,Hoja1!$AN34,IF(Hoja1!$AK34>0,Hoja1!$AK34,IF(Hoja1!$AH34>0,Hoja1!$AH34,IF(Hoja1!$AE34>0,Hoja1!$AE34,IF(Hoja1!$AB34>0,Hoja1!$AB34,IF(Hoja1!$Y34>0,Hoja1!$Y34,IF(Hoja1!$V34>0,Hoja1!$V34," ---")))))))) -> 19 | AS34: 0 | AT34: 2 | AU34: 0 | AV34: 0 | AW34: 0 | AX34: 0 | AY34: 0 | AZ34: 0 | BA34: 0 | BB34: 0 | BC34: 0 | BD34: 0 | BE34: 0 | BF34: 1974706.2 | BG34: 0 | BH34: 1974706.2 | BI34: =IF('[1]DATA CONSOLIDADA 2018-2025 '!$BH34>'[1]DATA CONSOLIDADA 2018-2025 '!$AN34,"Incremento",IF('[1]DATA CONSOLIDADA 2018-2025 '!$AN34='[1]DATA CONSOLIDADA 2018-2025 '!$BH34,"Sin incremento",IF('[1]DATA CONSOLIDADA 2018-2025 '!$BH34<'[1]DATA CONSOLIDADA 2018-2025 '!$AN34,"Disminución"," ---"))) -> #REF! | BJ34: ='[1]DATA CONSOLIDADA 2018-2025 '!$BH34-'[1]DATA CONSOLIDADA 2018-2025 '!$BE34 -> #REF! | BK34: 58325 | BL34: 0 | BM34: 58325 | BN34: =IF('[1]DATA CONSOLIDADA 2018-2025 '!$BM34>'[1]DATA CONSOLIDADA 2018-2025 '!$BH34,"Incremento",IF('[1]DATA CONSOLIDADA 2018-2025 '!$BH34='[1]DATA CONSOLIDADA 2018-2025 '!$BM34,"Sin incremento",IF('[1]DATA CONSOLIDADA 2018-2025 '!$BM34<'[1]DATA CONSOLIDADA 2018-2025 '!$BH34,"Disminución"," ---"))) -> #REF! | BO34: ='[1]DATA CONSOLIDADA 2018-2025 '!$BM34-'[1]DATA CONSOLIDADA 2018-2025 '!$BH34 -> #REF! | BP34: 0 | BQ34: 0 | BR34: 0 | BS34: =IF('[1]DATA CONSOLIDADA 2018-2025 '!$BR34>'[1]DATA CONSOLIDADA 2018-2025 '!$BM34,"Incremento",IF('[1]DATA CONSOLIDADA 2018-2025 '!$BM34='[1]DATA CONSOLIDADA 2018-2025 '!$BR34,"Sin incremento",IF('[1]DATA CONSOLIDADA 2018-2025 '!$BR34<'[1]DATA CONSOLIDADA 2018-2025 '!$BM34,"Disminución"," ---"))) -> #REF! | BT34: ='[1]DATA CONSOLIDADA 2018-2025 '!$BR34-Hoja1!$BO34 -> #REF! | BU34: 0 | BV34: 0 | BW34: 0 | BX34: =IF('[1]DATA CONSOLIDADA 2018-2025 '!$BW34>'[1]DATA CONSOLIDADA 2018-2025 '!$BR34,"Incremento",IF('[1]DATA CONSOLIDADA 2018-2025 '!$BR34='[1]DATA CONSOLIDADA 2018-2025 '!$BW34,"Sin incremento",IF('[1]DATA CONSOLIDADA 2018-2025 '!$BW34<'[1]DATA CONSOLIDADA 2018-2025 '!$BR34,"Disminución"," ---"))) -> #REF! | BY34: ='[1]DATA CONSOLIDADA 2018-2025 '!$BW34-'[1]DATA CONSOLIDADA 2018-2025 '!$BR34 -> #REF! | BZ34: 0 | CA34: 0 | CB34: 0 | CC34: =IF('[1]DATA CONSOLIDADA 2018-2025 '!$CB34>'[1]DATA CONSOLIDADA 2018-2025 '!$BW34,"Incremento",IF('[1]DATA CONSOLIDADA 2018-2025 '!$BW34='[1]DATA CONSOLIDADA 2018-2025 '!$CB34,"Sin incremento",IF('[1]DATA CONSOLIDADA 2018-2025 '!$CB34<'[1]DATA CONSOLIDADA 2018-2025 '!$BW34,"Disminución"," ---"))) -> #REF! | CD34: ='[1]DATA CONSOLIDADA 2018-2025 '!$CB34-Hoja1!$BW34 -> #REF! | CE34: 0 | CF34: 0 | CG34: 0 | CH34: =IF('[1]DATA CONSOLIDADA 2018-2025 '!$CG34>'[1]DATA CONSOLIDADA 2018-2025 '!$CB34,"Incremento",IF('[1]DATA CONSOLIDADA 2018-2025 '!$CB34='[1]DATA CONSOLIDADA 2018-2025 '!$CG34,"Sin incremento",IF('[1]DATA CONSOLIDADA 2018-2025 '!$CG34<'[1]DATA CONSOLIDADA 2018-2025 '!$CB34,"Disminución"," ---"))) -> #REF! | CI34: ='[1]DATA CONSOLIDADA 2018-2025 '!$CG34-Hoja1!$CB34 -> #REF! | CJ34: ='[1]DATA CONSOLIDADA 2018-2025 '!$BE34+'[1]DATA CONSOLIDADA 2018-2025 '!$BH34+'[1]DATA CONSOLIDADA 2018-2025 '!$BM34+'[1]DATA CONSOLIDADA 2018-2025 '!$BR34+'[1]DATA CONSOLIDADA 2018-2025 '!$BW34+'[1]DATA CONSOLIDADA 2018-2025 '!$CB34+'[1]DATA CONSOLIDADA 2018-2025 '!$CG34 -> #REF! | CK34: 0 | CL34: 0 | CM34: 0 | CN34: =IF('[1]DATA CONSOLIDADA 2018-2025 '!$CM34>'[1]DATA CONSOLIDADA 2018-2025 '!$CG34,"Incremento",IF('[1]DATA CONSOLIDADA 2018-2025 '!$CG34='[1]DATA CONSOLIDADA 2018-2025 '!$CM34,"Sin incremento",IF('[1]DATA CONSOLIDADA 2018-2025 '!$CM34<'[1]DATA CONSOLIDADA 2018-2025 '!$CG34,"Disminución"," ---"))) -> #REF! | CO34: ='[1]DATA CONSOLIDADA 2018-2025 '!$CM34-Hoja1!$CG34 -> #REF! | CP34: 0 | CQ34: 0 | CR34: 0 | CS34: 0 | CT34: 0 | CU34: 0 | CV34: 0 | CW34: 0 | CX34: 0 | CY34: 0 | CZ34: 0 | DA34: 0 | DB34: 0 | DC34: 0 | DD34: 0 | DE34: 0 | DF34: 0 | DG34: 0 | DH34: 0 | DI34: 20490594265 | DJ34: ASOCIACION DE PRODUCTORES AGROPECUARIOS ORGANICOS VALLE PAMPAS - APAOVAP | DK34: 01 Asociación
A35: COOPERATIVA AGROINDUSTRIAL MACHUPICCHU LTDA | B35: QUINUA Y OTROS GRANOS | C35: QUINUA | D35: APURIMAC | E35: 030213 | F35: APURIMAC | G35: ANDAHUAYLAS | H35: SAN JERONIMO | I35: 1 | J35: 1 | K35: 1 | L35: 1 | N35: 1 | P35: 1 | Q35: PAC | R35: =IF(I35=1, I$4, "") & IF(J35=1, IF(I35=1, "-", "") & J$4, "") & IF(K35=1, IF(OR(J35=1, I35=1), "-", "") & K$4, "") & IF(L35=1, IF(OR(K35=1, J35=1, I35=1), "-", "") & L$4, "") & IF(M35=1, IF(OR(L35=1, K35=1, J35=1, I35=1), "-", "") & M$4, "") & IF(N35=1, IF(OR(M35=1, L35=1, K35=1, J35=1, I35=1), "-", "") & N$4, "") & IF(O35=1, IF(OR(N35=1, M35=1, L35=1, K35=1, J35=1, I35=1), "-", "") & O$4, "") & IF(P35=1, IF(I35=1, " - ", IF(J35=1, " - ", IF(K35=1, " - ", IF(L35=1, " - ", IF(M35=1, " - ", IF(N35=1, " - ", IF(O35=1, " - ", ""))))))) & P$4, "") -> 2018-2019-2020-2021-2023 - 2025 | S35: =SUM(Hoja1!$I35:$P35) -> 6 | T35: =IF(OR(Hoja1!$J35=1,Hoja1!$K35=1,Hoja1!$L35=1,Hoja1!$M35=1,Hoja1!$N35=1,Hoja1!$O35=1,Hoja1!$P35=1),"SI","NO") -> SI | U35: =IF(OR(Hoja1!$K35=1,Hoja1!$L35=1,Hoja1!$M35=1,Hoja1!$N35=1,Hoja1!$O35=1,Hoja1!$P35=1),"SI","NO") -> SI | V35: 463 | W35: 217 | X35: 44 | Y35: 261 | Z35: 210 | AA35: 43 | AB35: 253 | AC35: 190 | AD35: 50 | AE35: 240 | AF35: 0 | AG35: 0 | AH35: 0 | AI35: 120 | AJ35: 80 | AK35: 200 | AL35: 0 | AM35: 0 | AN35: 0 | AO35: 92 | AP35: 15 | AQ35: 107 | AR35: =IF(Hoja1!$AQ35>0,Hoja1!$AQ35,IF(Hoja1!$AN35>0,Hoja1!$AN35,IF(Hoja1!$AK35>0,Hoja1!$AK35,IF(Hoja1!$AH35>0,Hoja1!$AH35,IF(Hoja1!$AE35>0,Hoja1!$AE35,IF(Hoja1!$AB35>0,Hoja1!$AB35,IF(Hoja1!$Y35>0,Hoja1!$Y35,IF(Hoja1!$V35>0,Hoja1!$V35," ---")))))))) -> 107 | AS35: 0 | AT35: 7 | AU35: 22 | AV35: 4 | AW35: 0 | AX35: 0 | AY35: 25 | AZ35: 7 | BA35: 0 | BB35: 0 | BC35: 24 | BD35: 0 | BE35: 2120163.2 | BF35: 2632717.2 | BG35: 0 | BH35: 2632717.2 | BI35: =IF('[1]DATA CONSOLIDADA 2018-2025 '!$BH35>'[1]DATA CONSOLIDADA 2018-2025 '!$AN35,"Incremento",IF('[1]DATA CONSOLIDADA 2018-2025 '!$AN35='[1]DATA CONSOLIDADA 2018-2025 '!$BH35,"Sin incremento",IF('[1]DATA CONSOLIDADA 2018-2025 '!$BH35<'[1]DATA CONSOLIDADA 2018-2025 '!$AN35,"Disminución"," ---"))) -> #REF! | BJ35: ='[1]DATA CONSOLIDADA 2018-2025 '!$BH35-'[1]DATA CONSOLIDADA 2018-2025 '!$BE35 -> #REF! | BK35: 1413126.6 | BL35: 951293.2 | BM35: 2364419.8 | BN35: =IF('[1]DATA CONSOLIDADA 2018-2025 '!$BM35>'[1]DATA CONSOLIDADA 2018-2025 '!$BH35,"Incremento",IF('[1]DATA CONSOLIDADA 2018-2025 '!$BH35='[1]DATA CONSOLIDADA 2018-2025 '!$BM35,"Sin incremento",IF('[1]DATA CONSOLIDADA 2018-2025 '!$BM35<'[1]DATA CONSOLIDADA 2018-2025 '!$BH35,"Disminución"," ---"))) -> #REF! | BO35: ='[1]DATA CONSOLIDADA 2018-2025 '!$BM35-'[1]DATA CONSOLIDADA 2018-2025 '!$BH35 -> #REF! | BP35: 671996.57 | BQ35: 364049.58 | BR35: 1036046.2 | BS35: =IF('[1]DATA CONSOLIDADA 2018-2025 '!$BR35>'[1]DATA CONSOLIDADA 2018-2025 '!$BM35,"Incremento",IF('[1]DATA CONSOLIDADA 2018-2025 '!$BM35='[1]DATA CONSOLIDADA 2018-2025 '!$BR35,"Sin incremento",IF('[1]DATA CONSOLIDADA 2018-2025 '!$BR35<'[1]DATA CONSOLIDADA 2018-2025 '!$BM35,"Disminución"," ---"))) -> #REF! | BT35: ='[1]DATA CONSOLIDADA 2018-2025 '!$BR35-Hoja1!$BO35 -> #REF! | BU35: 0 | BV35: 0 | BW35: 0 | BX35: =IF('[1]DATA CONSOLIDADA 2018-2025 '!$BW35>'[1]DATA CONSOLIDADA 2018-2025 '!$BR35,"Incremento",IF('[1]DATA CONSOLIDADA 2018-2025 '!$BR35='[1]DATA CONSOLIDADA 2018-2025 '!$BW35,"Sin incremento",IF('[1]DATA CONSOLIDADA 2018-2025 '!$BW35<'[1]DATA CONSOLIDADA 2018-2025 '!$BR35,"Disminución"," ---"))) -> #REF! | BY35: ='[1]DATA CONSOLIDADA 2018-2025 '!$BW35-'[1]DATA CONSOLIDADA 2018-2025 '!$BR35 -> #REF! | BZ35: 2082623.3 | CA35: 0 | CB35: 2082623.3 | CC35: =IF('[1]DATA CONSOLIDADA 2018-2025 '!$CB35>'[1]DATA CONSOLIDADA 2018-2025 '!$BW35,"Incremento",IF('[1]DATA CONSOLIDADA 2018-2025 '!$BW35='[1]DATA CONSOLIDADA 2018-2025 '!$CB35,"Sin incremento",IF('[1]DATA CONSOLIDADA 2018-2025 '!$CB35<'[1]DATA CONSOLIDADA 2018-2025 '!$BW35,"Disminución"," ---"))) -> #REF! | CD35: ='[1]DATA CONSOLIDADA 2018-2025 '!$CB35-Hoja1!$BW35 -> #REF! | CE35: 0 | CF35: 0 | CG35: 0 | CH35: =IF('[1]DATA CONSOLIDADA 2018-2025 '!$CG35>'[1]DATA CONSOLIDADA 2018-2025 '!$CB35,"Incremento",IF('[1]DATA CONSOLIDADA 2018-2025 '!$CB35='[1]DATA CONSOLIDADA 2018-2025 '!$CG35,"Sin incremento",IF('[1]DATA CONSOLIDADA 2018-2025 '!$CG35<'[1]DATA CONSOLIDADA 2018-2025 '!$CB35,"Disminución"," ---"))) -> #REF! | CI35: ='[1]DATA CONSOLIDADA 2018-2025 '!$CG35-Hoja1!$CB35 -> #REF! | CJ35: ='[1]DATA CONSOLIDADA 2018-2025 '!$BE35+'[1]DATA CONSOLIDADA 2018-2025 '!$BH35+'[1]DATA CONSOLIDADA 2018-2025 '!$BM35+'[1]DATA CONSOLIDADA 2018-2025 '!$BR35+'[1]DATA CONSOLIDADA 2018-2025 '!$BW35+'[1]DATA CONSOLIDADA 2018-2025 '!$CB35+'[1]DATA CONSOLIDADA 2018-2025 '!$CG35 -> #REF! | CK35: 108583.6 | CL35: 0 | CM35: 108583.6 | CN35: =IF('[1]DATA CONSOLIDADA 2018-2025 '!$CM35>'[1]DATA CONSOLIDADA 2018-2025 '!$CG35,"Incremento",IF('[1]DATA CONSOLIDADA 2018-2025 '!$CG35='[1]DATA CONSOLIDADA 2018-2025 '!$CM35,"Sin incremento",IF('[1]DATA CONSOLIDADA 2018-2025 '!$CM35<'[1]DATA CONSOLIDADA 2018-2025 '!$CG35,"Disminución"," ---"))) -> #REF! | CO35: ='[1]DATA CONSOLIDADA 2018-2025 '!$CM35-Hoja1!$CG35 -> #REF! | CP35: 0 | CQ35: 0 | CR35: 0 | CS35: 2082623.3 | CT35: 0 | CU35: 0 | CV35: 2082623.3 | CW35: 0 | CX35: 0 | CY35: 0 | CZ35: 0 | DA35: 0 | DB35: 0 | DC35: 0 | DD35: 0 | DE35: 108583.6 | DF35: 0 | DG35: 0 | DH35: 108583.6 | DI35: 20490810146 | DJ35: COOPERATIVA AGRARIA MACHUPICCHU LTDA - CAGMA LTDA | DK35: 02 Cooperativa
A36: COOPERATIVA AGROINDUSTRIAL TIERRA ANDINA LTDA | B36: QUINUA Y OTROS GRANOS | C36: QUINUA | D36: APURIMAC | E36: 030201 | F36: APURIMAC | G36: ANDAHUAYLAS | H36: ANDAHUAYLAS | I36: 1 | J36: 1 | K36: 1 | L36: 1 | M36: 1 | N36: 1 | Q36: PAC | R36: =IF(I36=1, I$4, "") & IF(J36=1, IF(I36=1, "-", "") & J$4, "") & IF(K36=1, IF(OR(J36=1, I36=1), "-", "") & K$4, "") & IF(L36=1, IF(OR(K36=1, J36=1, I36=1), "-", "") & L$4, "") & IF(M36=1, IF(OR(L36=1, K36=1, J36=1, I36=1), "-", "") & M$4, "") & IF(N36=1, IF(OR(M36=1, L36=1, K36=1, J36=1, I36=1), "-", "") & N$4, "") & IF(O36=1, IF(OR(N36=1, M36=1, L36=1, K36=1, J36=1, I36=1), "-", "") & O$4, "") & IF(P36=1, IF(I36=1, " - ", IF(J36=1, " - ", IF(K36=1, " - ", IF(L36=1, " - ", IF(M36=1, " - ", IF(N36=1, " - ", IF(O36=1, " - ", ""))))))) & P$4, "") -> 2018-2019-2020-2021-2022-2023 | S36: =SUM(Hoja1!$I36:$P36) -> 6 | T36: =IF(OR(Hoja1!$J36=1,Hoja1!$K36=1,Hoja1!$L36=1,Hoja1!$M36=1,Hoja1!$N36=1,Hoja1!$O36=1,Hoja1!$P36=1),"SI","NO") -> SI | U36: =IF(OR(Hoja1!$K36=1,Hoja1!$L36=1,Hoja1!$M36=1,Hoja1!$N36=1,Hoja1!$O36=1,Hoja1!$P36=1),"SI","NO") -> SI | V36: 168 | W36: 93 | X36: 42 | Y36: 135 | Z36: 82 | AA36: 41 | AB36: 123 | AC36: 103 | AD36: 47 | AE36: 150 | AF36: 103 | AG36: 47 | AH36: 150 | AI36: 103 | AJ36: 47 | AK36: 150 | AL36: 0 | AM36: 0 | AN36: 0 | AO36: 0 | AP36: 0 | AQ36: 0 | AR36: =IF(Hoja1!$AQ36>0,Hoja1!$AQ36,IF(Hoja1!$AN36>0,Hoja1!$AN36,IF(Hoja1!$AK36>0,Hoja1!$AK36,IF(Hoja1!$AH36>0,Hoja1!$AH36,IF(Hoja1!$AE36>0,Hoja1!$AE36,IF(Hoja1!$AB36>0,Hoja1!$AB36,IF(Hoja1!$Y36>0,Hoja1!$Y36,IF(Hoja1!$V36>0,Hoja1!$V36," ---")))))))) -> 150 | AS36: 0 | AT36: 6 | AU36: 59 | AV36: 4 | AW36: 24 | AX36: 3 | AY36: 5 | AZ36: 0 | BA36: 0 | BB36: 0 | BC36: 0 | BD36: 0 | BE36: 0 | BF36: 471229 | BG36: 0 | BH36: 471229 | BI36: =IF('[1]DATA CONSOLIDADA 2018-2025 '!$BH36>'[1]DATA CONSOLIDADA 2018-2025 '!$AN36,"Incremento",IF('[1]DATA CONSOLIDADA 2018-2025 '!$AN36='[1]DATA CONSOLIDADA 2018-2025 '!$BH36,"Sin incremento",IF('[1]DATA CONSOLIDADA 2018-2025 '!$BH36<'[1]DATA CONSOLIDADA 2018-2025 '!$AN36,"Disminución"," ---"))) -> #REF! | BJ36: ='[1]DATA CONSOLIDADA 2018-2025 '!$BH36-'[1]DATA CONSOLIDADA 2018-2025 '!$BE36 -> #REF! | BK36: 1076214.4 | BL36: 0 | BM36: 1076214.4 | BN36: =IF('[1]DATA CONSOLIDADA 2018-2025 '!$BM36>'[1]DATA CONSOLIDADA 2018-2025 '!$BH36,"Incremento",IF('[1]DATA CONSOLIDADA 2018-2025 '!$BH36='[1]DATA CONSOLIDADA 2018-2025 '!$BM36,"Sin incremento",IF('[1]DATA CONSOLIDADA 2018-2025 '!$BM36<'[1]DATA CONSOLIDADA 2018-2025 '!$BH36,"Disminución"," ---"))) -> #REF! | BO36: ='[1]DATA CONSOLIDADA 2018-2025 '!$BM36-'[1]DATA CONSOLIDADA 2018-2025 '!$BH36 -> #REF! | BP36: 748371.58 | BQ36: 0 | BR36: 748371.58 | BS36: =IF('[1]DATA CONSOLIDADA 2018-2025 '!$BR36>'[1]DATA CONSOLIDADA 2018-2025 '!$BM36,"Incremento",IF('[1]DATA CONSOLIDADA 2018-2025 '!$BM36='[1]DATA CONSOLIDADA 2018-2025 '!$BR36,"Sin incremento",IF('[1]DATA CONSOLIDADA 2018-2025 '!$BR36<'[1]DATA CONSOLIDADA 2018-2025 '!$BM36,"Disminución"," ---"))) -> #REF! | BT36: ='[1]DATA CONSOLIDADA 2018-2025 '!$BR36-Hoja1!$BO36 -> #REF! | BU36: 0 | BV36: 0 | BW36: 0 | BX36: =IF('[1]DATA CONSOLIDADA 2018-2025 '!$BW36>'[1]DATA CONSOLIDADA 2018-2025 '!$BR36,"Incremento",IF('[1]DATA CONSOLIDADA 2018-2025 '!$BR36='[1]DATA CONSOLIDADA 2018-2025 '!$BW36,"Sin incremento",IF('[1]DATA CONSOLIDADA 2018-2025 '!$BW36<'[1]DATA CONSOLIDADA 2018-2025 '!$BR36,"Disminución"," ---"))) -> #REF! | BY36: ='[1]DATA CONSOLIDADA 2018-2025 '!$BW36-'[1]DATA CONSOLIDADA 2018-2025 '!$BR36 -> #REF! | BZ36: 200004 | CA36: 0 | CB36: 200004 | CC36: =IF('[1]DATA CONSOLIDADA 2018-2025 '!$CB36>'[1]DATA CONSOLIDADA 2018-2025 '!$BW36,"Incremento",IF('[1]DATA CONSOLIDADA 2018-2025 '!$BW36='[1]DATA CONSOLIDADA 2018-2025 '!$CB36,"Sin incremento",IF('[1]DATA CONSOLIDADA 2018-2025 '!$CB36<'[1]DATA CONSOLIDADA 2018-2025 '!$BW36,"Disminución"," ---"))) -> #REF! | CD36: ='[1]DATA CONSOLIDADA 2018-2025 '!$CB36-Hoja1!$BW36 -> #REF! | CE36: 0 | CF36: 0 | CG36: 0 | CH36: =IF('[1]DATA CONSOLIDADA 2018-2025 '!$CG36>'[1]DATA CONSOLIDADA 2018-2025 '!$CB36,"Incremento",IF('[1]DATA CONSOLIDADA 2018-2025 '!$CB36='[1]DATA CONSOLIDADA 2018-2025 '!$CG36,"Sin incremento",IF('[1]DATA CONSOLIDADA 2018-2025 '!$CG36<'[1]DATA CONSOLIDADA 2018-2025 '!$CB36,"Disminución"," ---"))) -> #REF! | CI36: ='[1]DATA CONSOLIDADA 2018-2025 '!$CG36-Hoja1!$CB36 -> #REF! | CJ36: ='[1]DATA CONSOLIDADA 2018-2025 '!$BE36+'[1]DATA CONSOLIDADA 2018-2025 '!$BH36+'[1]DATA CONSOLIDADA 2018-2025 '!$BM36+'[1]DATA CONSOLIDADA 2018-2025 '!$BR36+'[1]DATA CONSOLIDADA 2018-2025 '!$BW36+'[1]DATA CONSOLIDADA 2018-2025 '!$CB36+'[1]DATA CONSOLIDADA 2018-2025 '!$CG36 -> #REF! | CK36: 0 | CL36: 0 | CM36: 0 | CN36: =IF('[1]DATA CONSOLIDADA 2018-2025 '!$CM36>'[1]DATA CONSOLIDADA 2018-2025 '!$CG36,"Incremento",IF('[1]DATA CONSOLIDADA 2018-2025 '!$CG36='[1]DATA CONSOLIDADA 2018-2025 '!$CM36,"Sin incremento",IF('[1]DATA CONSOLIDADA 2018-2025 '!$CM36<'[1]DATA CONSOLIDADA 2018-2025 '!$CG36,"Disminución"," ---"))) -> #REF! | CO36: ='[1]DATA CONSOLIDADA 2018-2025 '!$CM36-Hoja1!$CG36 -> #REF! | CP36: 0 | CQ36: 200004 | CR36: 0 | CS36: 0 | CT36: 0 | CU36: 0 | CV36: 200004 | CW36: 0 | CX36: 0 | CY36: 0 | CZ36: 0 | DA36: 0 | DB36: 0 | DC36: 0 | DD36: 0 | DE36: 0 | DF36: 0 | DG36: 0 | DH36: 0 | DI36: 20600998847 | DJ36: COOPERATIVA AGROINDUSTRIAL TIERRA ANDINA APURIMAC LTDA - CATAA LTDA | DK36: 02 Cooperativa
A37: ASOCIACIÓN DE MUJERES PRODUCTORAS DE TALLARINES DE CASA SANTO DOMINGO | B37: QUINUA Y OTROS GRANOS | C37: QUINUA | D37: APURIMAC | E37: 030101 | F37: APURIMAC | G37: ABANCAY | H37: ABANCAY | J37: 1 | K37: 1 | L37: 1 | Q37: PAC | R37: =IF(I37=1, I$4, "") & IF(J37=1, IF(I37=1, "-", "") & J$4, "") & IF(K37=1, IF(OR(J37=1, I37=1), "-", "") & K$4, "") & IF(L37=1, IF(OR(K37=1, J37=1, I37=1), "-", "") & L$4, "") & IF(M37=1, IF(OR(L37=1, K37=1, J37=1, I37=1), "-", "") & M$4, "") & IF(N37=1, IF(OR(M37=1, L37=1, K37=1, J37=1, I37=1), "-", "") & N$4, "") & IF(O37=1, IF(OR(N37=1, M37=1, L37=1, K37=1, J37=1, I37=1), "-", "") & O$4, "") & IF(P37=1, IF(I37=1, " - ", IF(J37=1, " - ", IF(K37=1, " - ", IF(L37=1, " - ", IF(M37=1, " - ", IF(N37=1, " - ", IF(O37=1, " - ", ""))))))) & P$4, "") -> 2019-2020-2021 | S37: =SUM(Hoja1!$I37:$P37) -> 3 | T37: =IF(OR(Hoja1!$J37=1,Hoja1!$K37=1,Hoja1!$L37=1,Hoja1!$M37=1,Hoja1!$N37=1,Hoja1!$O37=1,Hoja1!$P37=1),"SI","NO") -> SI | U37: =IF(OR(Hoja1!$K37=1,Hoja1!$L37=1,Hoja1!$M37=1,Hoja1!$N37=1,Hoja1!$O37=1,Hoja1!$P37=1),"SI","NO") -> SI | V37: 0 | W37: 4 | X37: 6 | Y37: 10 | Z37: 8 | AA37: 17 | AB37: 25 | AC37: 8 | AD37: 17 | AE37: 25 | AF37: 0 | AG37: 0 | AH37: 0 | AI37: 0 | AJ37: 0 | AK37: 0 | AL37: 0 | AM37: 0 | AN37: 0 | AO37: 0 | AP37: 0 | AQ37: 0 | AR37: =IF(Hoja1!$AQ37>0,Hoja1!$AQ37,IF(Hoja1!$AN37>0,Hoja1!$AN37,IF(Hoja1!$AK37>0,Hoja1!$AK37,IF(Hoja1!$AH37>0,Hoja1!$AH37,IF(Hoja1!$AE37>0,Hoja1!$AE37,IF(Hoja1!$AB37>0,Hoja1!$AB37,IF(Hoja1!$Y37>0,Hoja1!$Y37,IF(Hoja1!$V37>0,Hoja1!$V37," ---")))))))) -> 25 | AS37: 0 | AT37: 0 | AU37: 3 | AV37: 0 | AW37: 0 | AX37: 0 | AY37: 0 | AZ37: 0 | BA37: 0 | BB37: 0 | BC37: 0 | BD37: 0 | BE37: 0 | BF37: 48276 | BG37: 0 | BH37: 48276 | BI37: =IF('[1]DATA CONSOLIDADA 2018-2025 '!$BH37>'[1]DATA CONSOLIDADA 2018-2025 '!$AN37,"Incremento",IF('[1]DATA CONSOLIDADA 2018-2025 '!$AN37='[1]DATA CONSOLIDADA 2018-2025 '!$BH37,"Sin incremento",IF('[1]DATA CONSOLIDADA 2018-2025 '!$BH37<'[1]DATA CONSOLIDADA 2018-2025 '!$AN37,"Disminución"," ---"))) -> #REF! | BJ37: ='[1]DATA CONSOLIDADA 2018-2025 '!$BH37-'[1]DATA CONSOLIDADA 2018-2025 '!$BE37 -> #REF! | BK37: 37127 | BL37: 0 | BM37: 37127 | BN37: =IF('[1]DATA CONSOLIDADA 2018-2025 '!$BM37>'[1]DATA CONSOLIDADA 2018-2025 '!$BH37,"Incremento",IF('[1]DATA CONSOLIDADA 2018-2025 '!$BH37='[1]DATA CONSOLIDADA 2018-2025 '!$BM37,"Sin incremento",IF('[1]DATA CONSOLIDADA 2018-2025 '!$BM37<'[1]DATA CONSOLIDADA 2018-2025 '!$BH37,"Disminución"," ---"))) -> #REF! | BO37: ='[1]DATA CONSOLIDADA 2018-2025 '!$BM37-'[1]DATA CONSOLIDADA 2018-2025 '!$BH37 -> #REF! | BP37: 50168 | BQ37: 0 | BR37: 50168 | BS37: =IF('[1]DATA CONSOLIDADA 2018-2025 '!$BR37>'[1]DATA CONSOLIDADA 2018-2025 '!$BM37,"Incremento",IF('[1]DATA CONSOLIDADA 2018-2025 '!$BM37='[1]DATA CONSOLIDADA 2018-2025 '!$BR37,"Sin incremento",IF('[1]DATA CONSOLIDADA 2018-2025 '!$BR37<'[1]DATA CONSOLIDADA 2018-2025 '!$BM37,"Disminución"," ---"))) -> #REF! | BT37: ='[1]DATA CONSOLIDADA 2018-2025 '!$BR37-Hoja1!$BO37 -> #REF! | BU37: 0 | BV37: 0 | BW37: 0 | BX37: =IF('[1]DATA CONSOLIDADA 2018-2025 '!$BW37>'[1]DATA CONSOLIDADA 2018-2025 '!$BR37,"Incremento",IF('[1]DATA CONSOLIDADA 2018-2025 '!$BR37='[1]DATA CONSOLIDADA 2018-2025 '!$BW37,"Sin incremento",IF('[1]DATA CONSOLIDADA 2018-2025 '!$BW37<'[1]DATA CONSOLIDADA 2018-2025 '!$BR37,"Disminución"," ---"))) -> #REF! | BY37: ='[1]DATA CONSOLIDADA 2018-2025 '!$BW37-'[1]DATA CONSOLIDADA 2018-2025 '!$BR37 -> #REF! | BZ37: 0 | CA37: 0 | CB37: 0 | CC37: =IF('[1]DATA CONSOLIDADA 2018-2025 '!$CB37>'[1]DATA CONSOLIDADA 2018-2025 '!$BW37,"Incremento",IF('[1]DATA CONSOLIDADA 2018-2025 '!$BW37='[1]DATA CONSOLIDADA 2018-2025 '!$CB37,"Sin incremento",IF('[1]DATA CONSOLIDADA 2018-2025 '!$CB37<'[1]DATA CONSOLIDADA 2018-2025 '!$BW37,"Disminución"," ---"))) -> #REF! | CD37: ='[1]DATA CONSOLIDADA 2018-2025 '!$CB37-Hoja1!$BW37 -> #REF! | CE37: 0 | CF37: 0 | CG37: 0 | CH37: =IF('[1]DATA CONSOLIDADA 2018-2025 '!$CG37>'[1]DATA CONSOLIDADA 2018-2025 '!$CB37,"Incremento",IF('[1]DATA CONSOLIDADA 2018-2025 '!$CB37='[1]DATA CONSOLIDADA 2018-2025 '!$CG37,"Sin incremento",IF('[1]DATA CONSOLIDADA 2018-2025 '!$CG37<'[1]DATA CONSOLIDADA 2018-2025 '!$CB37,"Disminución"," ---"))) -> #REF! | CI37: ='[1]DATA CONSOLIDADA 2018-2025 '!$CG37-Hoja1!$CB37 -> #REF! | CJ37: ='[1]DATA CONSOLIDADA 2018-2025 '!$BE37+'[1]DATA CONSOLIDADA 2018-2025 '!$BH37+'[1]DATA CONSOLIDADA 2018-2025 '!$BM37+'[1]DATA CONSOLIDADA 2018-2025 '!$BR37+'[1]DATA CONSOLIDADA 2018-2025 '!$BW37+'[1]DATA CONSOLIDADA 2018-2025 '!$CB37+'[1]DATA CONSOLIDADA 2018-2025 '!$CG37 -> #REF! | CK37: 0 | CL37: 0 | CM37: 0 | CN37: =IF('[1]DATA CONSOLIDADA 2018-2025 '!$CM37>'[1]DATA CONSOLIDADA 2018-2025 '!$CG37,"Incremento",IF('[1]DATA CONSOLIDADA 2018-2025 '!$CG37='[1]DATA CONSOLIDADA 2018-2025 '!$CM37,"Sin incremento",IF('[1]DATA CONSOLIDADA 2018-2025 '!$CM37<'[1]DATA CONSOLIDADA 2018-2025 '!$CG37,"Disminución"," ---"))) -> #REF! | CO37: ='[1]DATA CONSOLIDADA 2018-2025 '!$CM37-Hoja1!$CG37 -> #REF! | CP37: 0 | CQ37: 0 | CR37: 0 | CS37: 0 | CT37: 0 | CU37: 0 | CV37: 0 | CW37: 0 | CX37: 0 | CY37: 0 | CZ37: 0 | DA37: 0 | DB37: 0 | DC37: 0 | DD37: 0 | DE37: 0 | DF37: 0 | DG37: 0 | DH37: 0 | DI37: 20490195301 | DJ37: ASOCIACION DE MUJERES PRODUCTORAS SANTO DOMINGO TALLARIN DE CASA | DK37: 01 Asociación
A38: ASOCIACIÓN DE PRODUCTORES TAMBO INCA | B38: FIBRA DE ALPACA | C38: FIBRA DE ALPACA | D38: APURIMAC | E38: 030406 | F38: APURIMAC | G38: AYMARAES | H38: COTARUSE | I38: 1 | J38: 1 | Q38: PAC | R38: =IF(I38=1, I$4, "") & IF(J38=1, IF(I38=1, "-", "") & J$4, "") & IF(K38=1, IF(OR(J38=1, I38=1), "-", "") & K$4, "") & IF(L38=1, IF(OR(K38=1, J38=1, I38=1), "-", "") & L$4, "") & IF(M38=1, IF(OR(L38=1, K38=1, J38=1, I38=1), "-", "") & M$4, "") & IF(N38=1, IF(OR(M38=1, L38=1, K38=1, J38=1, I38=1), "-", "") & N$4, "") & IF(O38=1, IF(OR(N38=1, M38=1, L38=1, K38=1, J38=1, I38=1), "-", "") & O$4, "") & IF(P38=1, IF(I38=1, " - ", IF(J38=1, " - ", IF(K38=1, " - ", IF(L38=1, " - ", IF(M38=1, " - ", IF(N38=1, " - ", IF(O38=1, " - ", ""))))))) & P$4, "") -> 2018-2019 | S38: =SUM(Hoja1!$I38:$P38) -> 2 | T38: =IF(OR(Hoja1!$J38=1,Hoja1!$K38=1,Hoja1!$L38=1,Hoja1!$M38=1,Hoja1!$N38=1,Hoja1!$O38=1,Hoja1!$P38=1),"SI","NO") -> SI | U38: =IF(OR(Hoja1!$K38=1,Hoja1!$L38=1,Hoja1!$M38=1,Hoja1!$N38=1,Hoja1!$O38=1,Hoja1!$P38=1),"SI","NO") -> NO | V38: 46 | W38: 15 | X38: 2 | Y38: 17 | Z38: 0 | AA38: 0 | AB38: 0 | AC38: 0 | AD38: 0 | AE38: 0 | AF38: 0 | AG38: 0 | AH38: 0 | AI38: 0 | AJ38: 0 | AK38: 0 | AL38: 0 | AM38: 0 | AN38: 0 | AO38: 0 | AP38: 0 | AQ38: 0 | AR38: =IF(Hoja1!$AQ38>0,Hoja1!$AQ38,IF(Hoja1!$AN38>0,Hoja1!$AN38,IF(Hoja1!$AK38>0,Hoja1!$AK38,IF(Hoja1!$AH38>0,Hoja1!$AH38,IF(Hoja1!$AE38>0,Hoja1!$AE38,IF(Hoja1!$AB38>0,Hoja1!$AB38,IF(Hoja1!$Y38>0,Hoja1!$Y38,IF(Hoja1!$V38>0,Hoja1!$V38," ---")))))))) -> 17 | AS38: 0 | AT38: 0 | AU38: 0 | AV38: 0 | AW38: 0 | AX38: 0 | AY38: 0 | AZ38: 0 | BA38: 0 | BB38: 0 | BC38: 0 | BD38: 0 | BE38: 0 | BF38: 59829.9 | BG38: 0 | BH38: 59829.9 | BI38: =IF('[1]DATA CONSOLIDADA 2018-2025 '!$BH38>'[1]DATA CONSOLIDADA 2018-2025 '!$AN38,"Incremento",IF('[1]DATA CONSOLIDADA 2018-2025 '!$AN38='[1]DATA CONSOLIDADA 2018-2025 '!$BH38,"Sin incremento",IF('[1]DATA CONSOLIDADA 2018-2025 '!$BH38<'[1]DATA CONSOLIDADA 2018-2025 '!$AN38,"Disminución"," ---"))) -> #REF! | BJ38: ='[1]DATA CONSOLIDADA 2018-2025 '!$BH38-'[1]DATA CONSOLIDADA 2018-2025 '!$BE38 -> #REF! | BK38: 0 | BL38: 0 | BM38: 0 | BN38: =IF('[1]DATA CONSOLIDADA 2018-2025 '!$BM38>'[1]DATA CONSOLIDADA 2018-2025 '!$BH38,"Incremento",IF('[1]DATA CONSOLIDADA 2018-2025 '!$BH38='[1]DATA CONSOLIDADA 2018-2025 '!$BM38,"Sin incremento",IF('[1]DATA CONSOLIDADA 2018-2025 '!$BM38<'[1]DATA CONSOLIDADA 2018-2025 '!$BH38,"Disminución"," ---"))) -> #REF! | BO38: ='[1]DATA CONSOLIDADA 2018-2025 '!$BM38-'[1]DATA CONSOLIDADA 2018-2025 '!$BH38 -> #REF! | BP38: 0 | BQ38: 0 | BR38: 0 | BS38: =IF('[1]DATA CONSOLIDADA 2018-2025 '!$BR38>'[1]DATA CONSOLIDADA 2018-2025 '!$BM38,"Incremento",IF('[1]DATA CONSOLIDADA 2018-2025 '!$BM38='[1]DATA CONSOLIDADA 2018-2025 '!$BR38,"Sin incremento",IF('[1]DATA CONSOLIDADA 2018-2025 '!$BR38<'[1]DATA CONSOLIDADA 2018-2025 '!$BM38,"Disminución"," ---"))) -> #REF! | BT38: ='[1]DATA CONSOLIDADA 2018-2025 '!$BR38-Hoja1!$BO38 -> #REF! | BU38: 0 | BV38: 0 | BW38: 0 | BX38: =IF('[1]DATA CONSOLIDADA 2018-2025 '!$BW38>'[1]DATA CONSOLIDADA 2018-2025 '!$BR38,"Incremento",IF('[1]DATA CONSOLIDADA 2018-2025 '!$BR38='[1]DATA CONSOLIDADA 2018-2025 '!$BW38,"Sin incremento",IF('[1]DATA CONSOLIDADA 2018-2025 '!$BW38<'[1]DATA CONSOLIDADA 2018-2025 '!$BR38,"Disminución"," ---"))) -> #REF! | BY38: ='[1]DATA CONSOLIDADA 2018-2025 '!$BW38-'[1]DATA CONSOLIDADA 2018-2025 '!$BR38 -> #REF! | BZ38: 0 | CA38: 0 | CB38: 0 | CC38: =IF('[1]DATA CONSOLIDADA 2018-2025 '!$CB38>'[1]DATA CONSOLIDADA 2018-2025 '!$BW38,"Incremento",IF('[1]DATA CONSOLIDADA 2018-2025 '!$BW38='[1]DATA CONSOLIDADA 2018-2025 '!$CB38,"Sin incremento",IF('[1]DATA CONSOLIDADA 2018-2025 '!$CB38<'[1]DATA CONSOLIDADA 2018-2025 '!$BW38,"Disminución"," ---"))) -> #REF! | CD38: ='[1]DATA CONSOLIDADA 2018-2025 '!$CB38-Hoja1!$BW38 -> #REF! | CE38: 0 | CF38: 0 | CG38: 0 | CH38: =IF('[1]DATA CONSOLIDADA 2018-2025 '!$CG38>'[1]DATA CONSOLIDADA 2018-2025 '!$CB38,"Incremento",IF('[1]DATA CONSOLIDADA 2018-2025 '!$CB38='[1]DATA CONSOLIDADA 2018-2025 '!$CG38,"Sin incremento",IF('[1]DATA CONSOLIDADA 2018-2025 '!$CG38<'[1]DATA CONSOLIDADA 2018-2025 '!$CB38,"Disminución"," ---"))) -> #REF! | CI38: ='[1]DATA CONSOLIDADA 2018-2025 '!$CG38-Hoja1!$CB38 -> #REF! | CJ38: ='[1]DATA CONSOLIDADA 2018-2025 '!$BE38+'[1]DATA CONSOLIDADA 2018-2025 '!$BH38+'[1]DATA CONSOLIDADA 2018-2025 '!$BM38+'[1]DATA CONSOLIDADA 2018-2025 '!$BR38+'[1]DATA CONSOLIDADA 2018-2025 '!$BW38+'[1]DATA CONSOLIDADA 2018-2025 '!$CB38+'[1]DATA CONSOLIDADA 2018-2025 '!$CG38 -> #REF! | CK38: 0 | CL38: 0 | CM38: 0 | CN38: =IF('[1]DATA CONSOLIDADA 2018-2025 '!$CM38>'[1]DATA CONSOLIDADA 2018-2025 '!$CG38,"Incremento",IF('[1]DATA CONSOLIDADA 2018-2025 '!$CG38='[1]DATA CONSOLIDADA 2018-2025 '!$CM38,"Sin incremento",IF('[1]DATA CONSOLIDADA 2018-2025 '!$CM38<'[1]DATA CONSOLIDADA 2018-2025 '!$CG38,"Disminución"," ---"))) -> #REF! | CO38: ='[1]DATA CONSOLIDADA 2018-2025 '!$CM38-Hoja1!$CG38 -> #REF! | CP38: 0 | CQ38: 0 | CR38: 0 | CS38: 0 | CT38: 0 | CU38: 0 | CV38: 0 | CW38: 0 | CX38: 0 | CY38: 0 | CZ38: 0 | DA38: 0 | DB38: 0 | DC38: 0 | DD38: 0 | DE38: 0 | DF38: 0 | DG38: 0 | DH38: 0 | DI38: 20491172135 | DJ38: ASOCIACION DE PRODUCTORES DE ALPACAS TAMBOINCA | DK38: 01 Asociación
A39: COOPERATIVA AGRARIA DE SERVICIOS MÚLTIPLES TESORO CHANKA DE KISHUARA - COOPAGROS - KISHUARA | B39: PAPA | C39: PAPA | D39: APURIMAC | E39: 030207 | F39: APURIMAC | G39: ANDAHUAYLAS | H39: KISHUARA | I39: 1 | J39: 1 | K39: 1 | L39: 1 | Q39: PAC | R39: =IF(I39=1, I$4, "") & IF(J39=1, IF(I39=1, "-", "") & J$4, "") & IF(K39=1, IF(OR(J39=1, I39=1), "-", "") & K$4, "") & IF(L39=1, IF(OR(K39=1, J39=1, I39=1), "-", "") & L$4, "") & IF(M39=1, IF(OR(L39=1, K39=1, J39=1, I39=1), "-", "") & M$4, "") & IF(N39=1, IF(OR(M39=1, L39=1, K39=1, J39=1, I39=1), "-", "") & N$4, "") & IF(O39=1, IF(OR(N39=1, M39=1, L39=1, K39=1, J39=1, I39=1), "-", "") & O$4, "") & IF(P39=1, IF(I39=1, " - ", IF(J39=1, " - ", IF(K39=1, " - ", IF(L39=1, " - ", IF(M39=1, " - ", IF(N39=1, " - ", IF(O39=1, " - ", ""))))))) & P$4, "") -> 2018-2019-2020-2021 | S39: =SUM(Hoja1!$I39:$P39) -> 4 | T39: =IF(OR(Hoja1!$J39=1,Hoja1!$K39=1,Hoja1!$L39=1,Hoja1!$M39=1,Hoja1!$N39=1,Hoja1!$O39=1,Hoja1!$P39=1),"SI","NO") -> SI | U39: =IF(OR(Hoja1!$K39=1,Hoja1!$L39=1,Hoja1!$M39=1,Hoja1!$N39=1,Hoja1!$O39=1,Hoja1!$P39=1),"SI","NO") -> SI | V39: 40 | W39: 46 | X39: 6 | Y39: 52 | Z39: 24 | AA39: 5 | AB39: 29 | AC39: 24 | AD39: 5 | AE39: 29 | AF39: 0 | AG39: 0 | AH39: 0 | AI39: 0 | AJ39: 0 | AK39: 0 | AL39: 0 | AM39: 0 | AN39: 0 | AO39: 0 | AP39: 0 | AQ39: 0 | AR39: =IF(Hoja1!$AQ39>0,Hoja1!$AQ39,IF(Hoja1!$AN39>0,Hoja1!$AN39,IF(Hoja1!$AK39>0,Hoja1!$AK39,IF(Hoja1!$AH39>0,Hoja1!$AH39,IF(Hoja1!$AE39>0,Hoja1!$AE39,IF(Hoja1!$AB39>0,Hoja1!$AB39,IF(Hoja1!$Y39>0,Hoja1!$Y39,IF(Hoja1!$V39>0,Hoja1!$V39," ---")))))))) -> 29 | AS39: 0 | AT39: 2 | AU39: 45 | AV39: 6 | AW39: 0 | AX39: 0 | AY39: 0 | AZ39: 0 | BA39: 0 | BB39: 0 | BC39: 0 | BD39: 0 | BE39: 25160 | BF39: 540383.69 | BG39: 0 | BH39: 540383.69 | BI39: =IF('[1]DATA CONSOLIDADA 2018-2025 '!$BH39>'[1]DATA CONSOLIDADA 2018-2025 '!$AN39,"Incremento",IF('[1]DATA CONSOLIDADA 2018-2025 '!$AN39='[1]DATA CONSOLIDADA 2018-2025 '!$BH39,"Sin incremento",IF('[1]DATA CONSOLIDADA 2018-2025 '!$BH39<'[1]DATA CONSOLIDADA 2018-2025 '!$AN39,"Disminución"," ---"))) -> #REF! | BJ39: ='[1]DATA CONSOLIDADA 2018-2025 '!$BH39-'[1]DATA CONSOLIDADA 2018-2025 '!$BE39 -> #REF! | BK39: 236000 | BL39: 0 | BM39: 236000 | BN39: =IF('[1]DATA CONSOLIDADA 2018-2025 '!$BM39>'[1]DATA CONSOLIDADA 2018-2025 '!$BH39,"Incremento",IF('[1]DATA CONSOLIDADA 2018-2025 '!$BH39='[1]DATA CONSOLIDADA 2018-2025 '!$BM39,"Sin incremento",IF('[1]DATA CONSOLIDADA 2018-2025 '!$BM39<'[1]DATA CONSOLIDADA 2018-2025 '!$BH39,"Disminución"," ---"))) -> #REF! | BO39: ='[1]DATA CONSOLIDADA 2018-2025 '!$BM39-'[1]DATA CONSOLIDADA 2018-2025 '!$BH39 -> #REF! | BP39: 300149 | BQ39: 0 | BR39: 300149 | BS39: =IF('[1]DATA CONSOLIDADA 2018-2025 '!$BR39>'[1]DATA CONSOLIDADA 2018-2025 '!$BM39,"Incremento",IF('[1]DATA CONSOLIDADA 2018-2025 '!$BM39='[1]DATA CONSOLIDADA 2018-2025 '!$BR39,"Sin incremento",IF('[1]DATA CONSOLIDADA 2018-2025 '!$BR39<'[1]DATA CONSOLIDADA 2018-2025 '!$BM39,"Disminución"," ---"))) -> #REF! | BT39: ='[1]DATA CONSOLIDADA 2018-2025 '!$BR39-Hoja1!$BO39 -> #REF! | BU39: 0 | BV39: 0 | BW39: 0 | BX39: =IF('[1]DATA CONSOLIDADA 2018-2025 '!$BW39>'[1]DATA CONSOLIDADA 2018-2025 '!$BR39,"Incremento",IF('[1]DATA CONSOLIDADA 2018-2025 '!$BR39='[1]DATA CONSOLIDADA 2018-2025 '!$BW39,"Sin incremento",IF('[1]DATA CONSOLIDADA 2018-2025 '!$BW39<'[1]DATA CONSOLIDADA 2018-2025 '!$BR39,"Disminución"," ---"))) -> #REF! | BY39: ='[1]DATA CONSOLIDADA 2018-2025 '!$BW39-'[1]DATA CONSOLIDADA 2018-2025 '!$BR39 -> #REF! | BZ39: 0 | CA39: 0 | CB39: 0 | CC39: =IF('[1]DATA CONSOLIDADA 2018-2025 '!$CB39>'[1]DATA CONSOLIDADA 2018-2025 '!$BW39,"Incremento",IF('[1]DATA CONSOLIDADA 2018-2025 '!$BW39='[1]DATA CONSOLIDADA 2018-2025 '!$CB39,"Sin incremento",IF('[1]DATA CONSOLIDADA 2018-2025 '!$CB39<'[1]DATA CONSOLIDADA 2018-2025 '!$BW39,"Disminución"," ---"))) -> #REF! | CD39: ='[1]DATA CONSOLIDADA 2018-2025 '!$CB39-Hoja1!$BW39 -> #REF! | CE39: 0 | CF39: 0 | CG39: 0 | CH39: =IF('[1]DATA CONSOLIDADA 2018-2025 '!$CG39>'[1]DATA CONSOLIDADA 2018-2025 '!$CB39,"Incremento",IF('[1]DATA CONSOLIDADA 2018-2025 '!$CB39='[1]DATA CONSOLIDADA 2018-2025 '!$CG39,"Sin incremento",IF('[1]DATA CONSOLIDADA 2018-2025 '!$CG39<'[1]DATA CONSOLIDADA 2018-2025 '!$CB39,"Disminución"," ---"))) -> #REF! | CI39: ='[1]DATA CONSOLIDADA 2018-2025 '!$CG39-Hoja1!$CB39 -> #REF! | CJ39: ='[1]DATA CONSOLIDADA 2018-2025 '!$BE39+'[1]DATA CONSOLIDADA 2018-2025 '!$BH39+'[1]DATA CONSOLIDADA 2018-2025 '!$BM39+'[1]DATA CONSOLIDADA 2018-2025 '!$BR39+'[1]DATA CONSOLIDADA 2018-2025 '!$BW39+'[1]DATA CONSOLIDADA 2018-2025 '!$CB39+'[1]DATA CONSOLIDADA 2018-2025 '!$CG39 -> #REF! | CK39: 0 | CL39: 0 | CM39: 0 | CN39: =IF('[1]DATA CONSOLIDADA 2018-2025 '!$CM39>'[1]DATA CONSOLIDADA 2018-2025 '!$CG39,"Incremento",IF('[1]DATA CONSOLIDADA 2018-2025 '!$CG39='[1]DATA CONSOLIDADA 2018-2025 '!$CM39,"Sin incremento",IF('[1]DATA CONSOLIDADA 2018-2025 '!$CM39<'[1]DATA CONSOLIDADA 2018-2025 '!$CG39,"Disminución"," ---"))) -> #REF! | CO39: ='[1]DATA CONSOLIDADA 2018-2025 '!$CM39-Hoja1!$CG39 -> #REF! | CP39: 0 | CQ39: 0 | CR39: 0 | CS39: 0 | CT39: 0 | CU39: 0 | CV39: 0 | CW39: 0 | CX39: 0 | CY39: 0 | CZ39: 0 | DA39: 0 | DB39: 0 | DC39: 0 | DD39: 0 | DE39: 0 | DF39: 0 | DG39: 0 | DH39: 0 | DI39: 20491204436 | DJ39: COOPERATIVA AGRARIA DE SERVICIOS MULTIPLES TESORO CHANKA DE KISHUARA - COOPAGROS - KISHUARA | DK39: 02 Cooperativa
A40: COOPERATIVA AGRARIA CAFETALERA VALLE DE INCAHUASI | B40: CAFÉ | C40: CAFÉ | D40: APURIMAC | E40: 030201 | F40: APURIMAC | G40: ANDAHUAYLAS | H40: ANDAHUAYLAS | I40: 1 | J40: 1 | K40: 1 | L40: 1 | M40: 1 | N40: 1 | Q40: PAC | R40: =IF(I40=1, I$4, "") & IF(J40=1, IF(I40=1, "-", "") & J$4, "") & IF(K40=1, IF(OR(J40=1, I40=1), "-", "") & K$4, "") & IF(L40=1, IF(OR(K40=1, J40=1, I40=1), "-", "") & L$4, "") & IF(M40=1, IF(OR(L40=1, K40=1, J40=1, I40=1), "-", "") & M$4, "") & IF(N40=1, IF(OR(M40=1, L40=1, K40=1, J40=1, I40=1), "-", "") & N$4, "") & IF(O40=1, IF(OR(N40=1, M40=1, L40=1, K40=1, J40=1, I40=1), "-", "") & O$4, "") & IF(P40=1, IF(I40=1, " - ", IF(J40=1, " - ", IF(K40=1, " - ", IF(L40=1, " - ", IF(M40=1, " - ", IF(N40=1, " - ", IF(O40=1, " - ", ""))))))) & P$4, "") -> 2018-2019-2020-2021-2022-2023 | S40: =SUM(Hoja1!$I40:$P40) -> 6 | T40: =IF(OR(Hoja1!$J40=1,Hoja1!$K40=1,Hoja1!$L40=1,Hoja1!$M40=1,Hoja1!$N40=1,Hoja1!$O40=1,Hoja1!$P40=1),"SI","NO") -> SI | U40: =IF(OR(Hoja1!$K40=1,Hoja1!$L40=1,Hoja1!$M40=1,Hoja1!$N40=1,Hoja1!$O40=1,Hoja1!$P40=1),"SI","NO") -> SI | V40: 473 | W40: 374 | X40: 82 | Y40: 456 | Z40: 405 | AA40: 80 | AB40: 485 | AC40: 386 | AD40: 86 | AE40: 472 | AF40: 401 | AG40: 92 | AH40: 493 | AI40: 401 | AJ40: 92 | AK40: 493 | AL40: 0 | AM40: 0 | AN40: 0 | AO40: 0 | AP40: 0 | AQ40: 0 | AR40: =IF(Hoja1!$AQ40>0,Hoja1!$AQ40,IF(Hoja1!$AN40>0,Hoja1!$AN40,IF(Hoja1!$AK40>0,Hoja1!$AK40,IF(Hoja1!$AH40>0,Hoja1!$AH40,IF(Hoja1!$AE40>0,Hoja1!$AE40,IF(Hoja1!$AB40>0,Hoja1!$AB40,IF(Hoja1!$Y40>0,Hoja1!$Y40,IF(Hoja1!$V40>0,Hoja1!$V40," ---")))))))) -> 493 | AS40: 0 | AT40: 4 | AU40: 72 | AV40: 6 | AW40: 57 | AX40: 8 | AY40: 7 | AZ40: 18 | BA40: 0 | BB40: 0 | BC40: 0 | BD40: 0 | BE40: 0 | BF40: 22490.34 | BG40: 3082078.1 | BH40: 3104568.5 | BI40: =IF('[1]DATA CONSOLIDADA 2018-2025 '!$BH40>'[1]DATA CONSOLIDADA 2018-2025 '!$AN40,"Incremento",IF('[1]DATA CONSOLIDADA 2018-2025 '!$AN40='[1]DATA CONSOLIDADA 2018-2025 '!$BH40,"Sin incremento",IF('[1]DATA CONSOLIDADA 2018-2025 '!$BH40<'[1]DATA CONSOLIDADA 2018-2025 '!$AN40,"Disminución"," ---"))) -> #REF! | BJ40: ='[1]DATA CONSOLIDADA 2018-2025 '!$BH40-'[1]DATA CONSOLIDADA 2018-2025 '!$BE40 -> #REF! | BK40: 0 | BL40: 8063872.3 | BM40: 8063872.3 | BN40: =IF('[1]DATA CONSOLIDADA 2018-2025 '!$BM40>'[1]DATA CONSOLIDADA 2018-2025 '!$BH40,"Incremento",IF('[1]DATA CONSOLIDADA 2018-2025 '!$BH40='[1]DATA CONSOLIDADA 2018-2025 '!$BM40,"Sin incremento",IF('[1]DATA CONSOLIDADA 2018-2025 '!$BM40<'[1]DATA CONSOLIDADA 2018-2025 '!$BH40,"Disminución"," ---"))) -> #REF! | BO40: ='[1]DATA CONSOLIDADA 2018-2025 '!$BM40-'[1]DATA CONSOLIDADA 2018-2025 '!$BH40 -> #REF! | BP40: 0 | BQ40: 9080188.9 | BR40: 9080188.9 | BS40: =IF('[1]DATA CONSOLIDADA 2018-2025 '!$BR40>'[1]DATA CONSOLIDADA 2018-2025 '!$BM40,"Incremento",IF('[1]DATA CONSOLIDADA 2018-2025 '!$BM40='[1]DATA CONSOLIDADA 2018-2025 '!$BR40,"Sin incremento",IF('[1]DATA CONSOLIDADA 2018-2025 '!$BR40<'[1]DATA CONSOLIDADA 2018-2025 '!$BM40,"Disminución"," ---"))) -> #REF! | BT40: ='[1]DATA CONSOLIDADA 2018-2025 '!$BR40-Hoja1!$BO40 -> #REF! | BU40: 1723946.9 | BV40: 12670661 | BW40: 14394608 | BX40: =IF('[1]DATA CONSOLIDADA 2018-2025 '!$BW40>'[1]DATA CONSOLIDADA 2018-2025 '!$BR40,"Incremento",IF('[1]DATA CONSOLIDADA 2018-2025 '!$BR40='[1]DATA CONSOLIDADA 2018-2025 '!$BW40,"Sin incremento",IF('[1]DATA CONSOLIDADA 2018-2025 '!$BW40<'[1]DATA CONSOLIDADA 2018-2025 '!$BR40,"Disminución"," ---"))) -> #REF! | BY40: ='[1]DATA CONSOLIDADA 2018-2025 '!$BW40-'[1]DATA CONSOLIDADA 2018-2025 '!$BR40 -> #REF! | BZ40: 227111.23 | CA40: 7340280 | CB40: 7567391.3 | CC40: =IF('[1]DATA CONSOLIDADA 2018-2025 '!$CB40>'[1]DATA CONSOLIDADA 2018-2025 '!$BW40,"Incremento",IF('[1]DATA CONSOLIDADA 2018-2025 '!$BW40='[1]DATA CONSOLIDADA 2018-2025 '!$CB40,"Sin incremento",IF('[1]DATA CONSOLIDADA 2018-2025 '!$CB40<'[1]DATA CONSOLIDADA 2018-2025 '!$BW40,"Disminución"," ---"))) -> #REF! | CD40: ='[1]DATA CONSOLIDADA 2018-2025 '!$CB40-Hoja1!$BW40 -> #REF! | CE40: 0 | CF40: 0 | CG40: 0 | CH40: =IF('[1]DATA CONSOLIDADA 2018-2025 '!$CG40>'[1]DATA CONSOLIDADA 2018-2025 '!$CB40,"Incremento",IF('[1]DATA CONSOLIDADA 2018-2025 '!$CB40='[1]DATA CONSOLIDADA 2018-2025 '!$CG40,"Sin incremento",IF('[1]DATA CONSOLIDADA 2018-2025 '!$CG40<'[1]DATA CONSOLIDADA 2018-2025 '!$CB40,"Disminución"," ---"))) -> #REF! | CI40: ='[1]DATA CONSOLIDADA 2018-2025 '!$CG40-Hoja1!$CB40 -> #REF! | CJ40: ='[1]DATA CONSOLIDADA 2018-2025 '!$BE40+'[1]DATA CONSOLIDADA 2018-2025 '!$BH40+'[1]DATA CONSOLIDADA 2018-2025 '!$BM40+'[1]DATA CONSOLIDADA 2018-2025 '!$BR40+'[1]DATA CONSOLIDADA 2018-2025 '!$BW40+'[1]DATA CONSOLIDADA 2018-2025 '!$CB40+'[1]DATA CONSOLIDADA 2018-2025 '!$CG40 -> #REF! | CK40: 0 | CL40: 0 | CM40: 0 | CN40: =IF('[1]DATA CONSOLIDADA 2018-2025 '!$CM40>'[1]DATA CONSOLIDADA 2018-2025 '!$CG40,"Incremento",IF('[1]DATA CONSOLIDADA 2018-2025 '!$CG40='[1]DATA CONSOLIDADA 2018-2025 '!$CM40,"Sin incremento",IF('[1]DATA CONSOLIDADA 2018-2025 '!$CM40<'[1]DATA CONSOLIDADA 2018-2025 '!$CG40,"Disminución"," ---"))) -> #REF! | CO40: ='[1]DATA CONSOLIDADA 2018-2025 '!$CM40-Hoja1!$CG40 -> #REF! | CP40: 0 | CQ40: 0 | CR40: 0 | CS40: 7567391.3 | CT40: 0 | CU40: 0 | CV40: 7567391.3 | CW40: 0 | CX40: 0 | CY40: 0 | CZ40: 0 | DA40: 0 | DB40: 0 | DC40: 0 | DD40: 0 | DE40: 0 | DF40: 0 | DG40: 0 | DH40: 0 | DI40: 20527565376 | DJ40: COOPERATIVA AGRARIA CAFETALERA VALLE DE INCAHUASI | DK40: 02 Cooperativa
A41: ASOCIACION DE PRODUCTORES AGROPECUARIOS PAMPAS CALLEBAMBA | B41: PALTA | C41: PALTA | D41: APURIMAC | E41: 030601 | F41: APURIMAC | G41: CHINCHEROS | H41: CHINCHEROS | M41: 1 | N41: 1 | O41: 1 | Q41: PAC | R41: =IF(I41=1, I$4, "") & IF(J41=1, IF(I41=1, "-", "") & J$4, "") & IF(K41=1, IF(OR(J41=1, I41=1), "-", "") & K$4, "") & IF(L41=1, IF(OR(K41=1, J41=1, I41=1), "-", "") & L$4, "") & IF(M41=1, IF(OR(L41=1, K41=1, J41=1, I41=1), "-", "") & M$4, "") & IF(N41=1, IF(OR(M41=1, L41=1, K41=1, J41=1, I41=1), "-", "") & N$4, "") & IF(O41=1, IF(OR(N41=1, M41=1, L41=1, K41=1, J41=1, I41=1), "-", "") & O$4, "") & IF(P41=1, IF(I41=1, " - ", IF(J41=1, " - ", IF(K41=1, " - ", IF(L41=1, " - ", IF(M41=1, " - ", IF(N41=1, " - ", IF(O41=1, " - ", ""))))))) & P$4, "") -> 2022-2023-2024 | S41: =SUM(Hoja1!$I41:$P41) -> 3 | T41: =IF(OR(Hoja1!$J41=1,Hoja1!$K41=1,Hoja1!$L41=1,Hoja1!$M41=1,Hoja1!$N41=1,Hoja1!$O41=1,Hoja1!$P41=1),"SI","NO") -> SI | U41: =IF(OR(Hoja1!$K41=1,Hoja1!$L41=1,Hoja1!$M41=1,Hoja1!$N41=1,Hoja1!$O41=1,Hoja1!$P41=1),"SI","NO") -> SI | V41: 0 | W41: 0 | X41: 0 | Y41: 0 | Z41: 0 | AA41: 0 | AB41: 0 | AC41: 0 | AD41: 0 | AE41: 0 | AF41: 17 | AG41: 9 | AH41: 26 | AI41: 17 | AJ41: 9 | AK41: 26 | AL41: 15 | AM41: 10 | AN41: 25 | AO41: 0 | AP41: 0 | AQ41: 0 | AR41: =IF(Hoja1!$AQ41>0,Hoja1!$AQ41,IF(Hoja1!$AN41>0,Hoja1!$AN41,IF(Hoja1!$AK41>0,Hoja1!$AK41,IF(Hoja1!$AH41>0,Hoja1!$AH41,IF(Hoja1!$AE41>0,Hoja1!$AE41,IF(Hoja1!$AB41>0,Hoja1!$AB41,IF(Hoja1!$Y41>0,Hoja1!$Y41,IF(Hoja1!$V41>0,Hoja1!$V41," ---")))))))) -> 25 | AS41: 0 | AT41: 0 | AU41: 0 | AV41: 0 | AW41: 30 | AX41: 4 | AY41: 26 | AZ41: 2 | BA41: 22 | BB41: 7 | BC41: 0 | BD41: 0 | BE41: 0 | BF41: 0 | BG41: 0 | BH41: 0 | BI41: =IF('[1]DATA CONSOLIDADA 2018-2025 '!$BH41>'[1]DATA CONSOLIDADA 2018-2025 '!$AN41,"Incremento",IF('[1]DATA CONSOLIDADA 2018-2025 '!$AN41='[1]DATA CONSOLIDADA 2018-2025 '!$BH41,"Sin incremento",IF('[1]DATA CONSOLIDADA 2018-2025 '!$BH41<'[1]DATA CONSOLIDADA 2018-2025 '!$AN41,"Disminución"," ---"))) -> #REF! | BJ41: ='[1]DATA CONSOLIDADA 2018-2025 '!$BH41-'[1]DATA CONSOLIDADA 2018-2025 '!$BE41 -> #REF! | BK41: 0 | BL41: 0 | BM41: 0 | BN41: =IF('[1]DATA CONSOLIDADA 2018-2025 '!$BM41>'[1]DATA CONSOLIDADA 2018-2025 '!$BH41,"Incremento",IF('[1]DATA CONSOLIDADA 2018-2025 '!$BH41='[1]DATA CONSOLIDADA 2018-2025 '!$BM41,"Sin incremento",IF('[1]DATA CONSOLIDADA 2018-2025 '!$BM41<'[1]DATA CONSOLIDADA 2018-2025 '!$BH41,"Disminución"," ---"))) -> #REF! | BO41: ='[1]DATA CONSOLIDADA 2018-2025 '!$BM41-'[1]DATA CONSOLIDADA 2018-2025 '!$BH41 -> #REF! | BP41: 0 | BQ41: 0 | BR41: 0 | BS41: =IF('[1]DATA CONSOLIDADA 2018-2025 '!$BR41>'[1]DATA CONSOLIDADA 2018-2025 '!$BM41,"Incremento",IF('[1]DATA CONSOLIDADA 2018-2025 '!$BM41='[1]DATA CONSOLIDADA 2018-2025 '!$BR41,"Sin incremento",IF('[1]DATA CONSOLIDADA 2018-2025 '!$BR41<'[1]DATA CONSOLIDADA 2018-2025 '!$BM41,"Disminución"," ---"))) -> #REF! | BT41: ='[1]DATA CONSOLIDADA 2018-2025 '!$BR41-Hoja1!$BO41 -> #REF! | BU41: 525700 | BV41: 0 | BW41: 525700 | BX41: =IF('[1]DATA CONSOLIDADA 2018-2025 '!$BW41>'[1]DATA CONSOLIDADA 2018-2025 '!$BR41,"Incremento",IF('[1]DATA CONSOLIDADA 2018-2025 '!$BR41='[1]DATA CONSOLIDADA 2018-2025 '!$BW41,"Sin incremento",IF('[1]DATA CONSOLIDADA 2018-2025 '!$BW41<'[1]DATA CONSOLIDADA 2018-2025 '!$BR41,"Disminución"," ---"))) -> #REF! | BY41: ='[1]DATA CONSOLIDADA 2018-2025 '!$BW41-'[1]DATA CONSOLIDADA 2018-2025 '!$BR41 -> #REF! | BZ41: 320000 | CA41: 0 | CB41: 320000 | CC41: =IF('[1]DATA CONSOLIDADA 2018-2025 '!$CB41>'[1]DATA CONSOLIDADA 2018-2025 '!$BW41,"Incremento",IF('[1]DATA CONSOLIDADA 2018-2025 '!$BW41='[1]DATA CONSOLIDADA 2018-2025 '!$CB41,"Sin incremento",IF('[1]DATA CONSOLIDADA 2018-2025 '!$CB41<'[1]DATA CONSOLIDADA 2018-2025 '!$BW41,"Disminución"," ---"))) -> #REF! | CD41: ='[1]DATA CONSOLIDADA 2018-2025 '!$CB41-Hoja1!$BW41 -> #REF! | CE41: 0 | CF41: 0 | CG41: 0 | CH41: =IF('[1]DATA CONSOLIDADA 2018-2025 '!$CG41>'[1]DATA CONSOLIDADA 2018-2025 '!$CB41,"Incremento",IF('[1]DATA CONSOLIDADA 2018-2025 '!$CB41='[1]DATA CONSOLIDADA 2018-2025 '!$CG41,"Sin incremento",IF('[1]DATA CONSOLIDADA 2018-2025 '!$CG41<'[1]DATA CONSOLIDADA 2018-2025 '!$CB41,"Disminución"," ---"))) -> #REF! | CI41: ='[1]DATA CONSOLIDADA 2018-2025 '!$CG41-Hoja1!$CB41 -> #REF! | CJ41: ='[1]DATA CONSOLIDADA 2018-2025 '!$BE41+'[1]DATA CONSOLIDADA 2018-2025 '!$BH41+'[1]DATA CONSOLIDADA 2018-2025 '!$BM41+'[1]DATA CONSOLIDADA 2018-2025 '!$BR41+'[1]DATA CONSOLIDADA 2018-2025 '!$BW41+'[1]DATA CONSOLIDADA 2018-2025 '!$CB41+'[1]DATA CONSOLIDADA 2018-2025 '!$CG41 -> #REF! | CK41: 0 | CL41: 0 | CM41: 0 | CN41: =IF('[1]DATA CONSOLIDADA 2018-2025 '!$CM41>'[1]DATA CONSOLIDADA 2018-2025 '!$CG41,"Incremento",IF('[1]DATA CONSOLIDADA 2018-2025 '!$CG41='[1]DATA CONSOLIDADA 2018-2025 '!$CM41,"Sin incremento",IF('[1]DATA CONSOLIDADA 2018-2025 '!$CM41<'[1]DATA CONSOLIDADA 2018-2025 '!$CG41,"Disminución"," ---"))) -> #REF! | CO41: ='[1]DATA CONSOLIDADA 2018-2025 '!$CM41-Hoja1!$CG41 -> #REF! | CP41: 0 | CQ41: 320000 | CR41: 0 | CS41: 0 | CT41: 0 | CU41: 0 | CV41: 320000 | CW41: 0 | CX41: 0 | CY41: 0 | CZ41: 0 | DA41: 0 | DB41: 0 | DC41: 0 | DD41: 0 | DE41: 0 | DF41: 0 | DG41: 0 | DH41: 0 | DI41: 20605216812 | DJ41: ASOCIACION DE PRODUCTORES AGROPECUARIOS PAMPAS-CALLEBAMBA | DK41: 01 Asociación
